Workbook

Sheet Template
A1: =+'Annual Raw'!C4 -> #NAME? | B1: 36951 | C1: =EOMONTH(B1,12) -> 37346 | D1: =EOMONTH(C1,12) -> 37711 | E1: =EOMONTH(D1,12) -> 38077 | F1: =EOMONTH(E1,12) -> 38442 | G1: =EOMONTH(F1,12) -> 38807 | H1: =EOMONTH(G1,12) -> 39172 | I1: =EOMONTH(H1,12) -> 39538 | J1: =EOMONTH(I1,12) -> 39903 | ... AE1: =EOMONTH(AD1,12) -> 47573 | AH1: QTR | AI1: 41061 | AJ1: 41153 | AK1: 41244 | AL1: 41334 | AM1: 41426 | AN1: 41518 | AO1: 41609 | AP1: 41699 | AQ1: 41791 | AR1: 41883 | AS1: 41974 | AT1: 42064 | AU1: 42156 | AV1: 42248 | AW1: 42339 | AX1: 42430 | AY1: 42522 | AZ1: 42614 | BA1: 42705 | BB1: 42795 | BC1: 42887 | BD1: 42979 | BE1: 43070 | BF1: 43160 | BG1: 43252 | BH1: 43344 | BI1: 43435 | BJ1: 43525 | BK1: 43617 | BL1: 43709 | BM1: 43800 | BN1: 43891 | BO1: 43983 | BP1: 44075 | BQ1: =EOMONTH(BP1,3) -> 44196 | BR1: =EOMONTH(BQ1,3) -> 44286 | BS1: =EOMONTH(BR1,3) -> 44377 | BT1: =EOMONTH(BS1,3) -> 44469 | BU1: =EOMONTH(BT1,3) -> 44561 | BV1: =EOMONTH(BU1,3) -> 44651 | BW1: =EOMONTH(BV1,3) -> 44742 | BX1: =EOMONTH(BW1,3) -> 44834 | ... DB1: =EOMONTH(DA1,3) -> 47573 | DE1: HISTORICAL ESTIMATES | DF1: 46112
A2: Presentation Data (Start)
A4: Total Clients | AA4: 999186 | CJ4: 957265 | CK4: 992531 | CL4: 999186
A5: Rise in Active clients in Broking | Y5: 127792 | Z5: 147942 | AA5: 149404 | CG5: 90901 | CH5: 73670 | CJ5: 92326 | CK5: 96851 | CL5: 85640
CK6: =+CK5/CG5-1 -> 0.065455826 | CL6: =+CL5/CH5-1 -> 0.16248134
A7: Sales Break Up
A8: Broking Segment | Y8: 458 | Z8: 510 | AA8: 476 | CG8: 115 | CH8: 105 | CJ8: 116 | CK8: 129 | CL8: 120
A9: Non-Broking (Int on margin trading & distribution Income) | Y9: 132 | Z9: 193 | AA9: 265 | CG9: 48 | CH9: 55 | CJ9: 68 | CK9: 69 | CL9: 78
A10: Other income from Operations | Y10: 92 | Z10: 143 | AA10: 192 | CG10: 41 | CH10: 39.7 | CJ10: 43 | CK10: 50.6 | CL10: 57
A13: Assets under custody - crs | Y13: 53884 | Z13: 81369 | AA13: 94416 | CJ13: 101960 | CK13: 105772 | CL13: 94415
A14: Assets under distribution - crs | Z14: 6459 | AA14: 7788 | CG14: 6335 | CJ14: 7736 | CK14: 8368 | CL14: 7787
A15: MTF Books - crs | Z15: 686 | AA15: 1101 | CH15: 686 | CI15: 861 | CJ15: 1084 | CK15: 1231 | CL15: 1102
CH17: =+CH8/CH13 -> #DIV/0! | CI17: =+CI8/CI13 -> #DIV/0! | CJ17: =+CJ8/CJ13 -> 0.0011377011 | CK17: =+CK8/CK13 -> 0.0012196044 | CL17: =+CL8/CL13 -> 0.0012709845
CH18: =+CH9/CH14 -> #DIV/0! | CI18: =+CI9/CI14 -> #DIV/0! | CJ18: =+CJ9/CJ14 -> 0.0087900724 | CK18: =+CK9/CK14 -> 0.0082456979 | CL18: =+CL9/CL14 -> 0.010016694
CH19: =+CH10/CH15 -> 0.05787172 | CI19: =+CI10/CI15 -> 0 | CJ19: =+CJ10/CJ15 -> 0.039667897 | CK19: =+CK10/CK15 -> 0.041104793 | CL19: =+CL10/CL15 -> 0.051724138
A20: Presentation Data (End)
A21: Profit & Loss- Annual (Start)
A22: Gross Revenue | B22: ='Annual Raw'!C6 -> #NAME? | C22: ='Annual Raw'!D6 -> #NAME? | D22: ='Annual Raw'!E6 -> #NAME? | E22: ='Annual Raw'!F6 -> #NAME? | F22: ='Annual Raw'!G6 -> #NAME? | G22: ='Annual Raw'!H6 -> #NAME? | H22: ='Annual Raw'!I6 -> #NAME? | I22: ='Annual Raw'!J6 -> #NAME? | ... AA22: ='Annual Raw'!AB6 -> #NAME? | AB22: =+SUM(CM22:CP22) -> #NAME? | AC22: =+SUM(CQ22:CT22) -> #NAME? | AD22: =+SUM(CU22:CX22) -> #NAME? | AE22: =+SUM(CY22:DB22) -> #NAME? | AI22: ='QTR Raw'!C6+'QTR Raw'!C8 -> #NAME? | AJ22: ='QTR Raw'!D6+'QTR Raw'!D8 -> #NAME? | AK22: ='QTR Raw'!E6+'QTR Raw'!E8 -> #NAME? | AL22: ='QTR Raw'!F6+'QTR Raw'!F8 -> #NAME? | AM22: ='QTR Raw'!G6+'QTR Raw'!G8 -> #NAME? | AN22: ='QTR Raw'!H6+'QTR Raw'!H8 -> #NAME? | AO22: ='QTR Raw'!I6+'QTR Raw'!I8 -> #NAME? | AP22: ='QTR Raw'!J6+'QTR Raw'!J8 -> #NAME? | ... CG22: ='QTR Raw'!BA6+'QTR Raw'!BA8 -> #NAME? | CH22: 199.625 | CI22: ='QTR Raw'!BC6+'QTR Raw'!BC8 -> #NAME? | CJ22: ='QTR Raw'!BD6+'QTR Raw'!BD8 -> #NAME? | CK22: ='QTR Raw'!BE6+'QTR Raw'!BE8 -> #NAME? | CL22: ='QTR Raw'!BF6+'QTR Raw'!BF8 -> #NAME? | CM22: =+CI24+(CM25*CI24) -> #NAME? | CN22: =+CJ24+(CN25*CJ24) -> #NAME? | CO22: =+CK24+(CO25*CK24) -> #NAME? | CP22: =+CL24+(CP25*CL24) -> #NAME? | CQ22: =+CM24+(CQ25*CM24) -> #NAME? | CR22: =+CN24+(CR25*CN24) -> #NAME? | CS22: =+CO24+(CS25*CO24) -> #NAME? | CT22: =+CP24+(CT25*CP24) -> #NAME? | ... DB22: =+CX24+(DB25*CX24) -> #NAME? | DF22: 932.157
A23: Less: Exise Duty | B23: ='Annual Raw'!C7+'Annual Raw'!C8+'Annual Raw'!C9 -> #NAME? | C23: ='Annual Raw'!D7+'Annual Raw'!D8+'Annual Raw'!D9 -> #NAME? | D23: ='Annual Raw'!E7+'Annual Raw'!E8+'Annual Raw'!E9 -> #NAME? | E23: ='Annual Raw'!F7+'Annual Raw'!F8+'Annual Raw'!F9 -> #NAME? | F23: ='Annual Raw'!G7+'Annual Raw'!G8+'Annual Raw'!G9 -> #NAME? | G23: ='Annual Raw'!H7+'Annual Raw'!H8+'Annual Raw'!H9 -> #NAME? | H23: ='Annual Raw'!I7+'Annual Raw'!I8+'Annual Raw'!I9 -> #NAME? | I23: ='Annual Raw'!J7+'Annual Raw'!J8+'Annual Raw'!J9 -> #NAME? | ... AA23: ='Annual Raw'!AB7+'Annual Raw'!AB8+'Annual Raw'!AB9 -> #NAME? | AB23: =+SUM(CM23:CP23) -> 0 | AC23: =+SUM(CQ23:CT23) -> 0 | AD23: =+SUM(CU23:CX23) -> 0 | AE23: =+SUM(CY23:DB23) -> 0 | AI23: =+'QTR Raw'!C20+'QTR Raw'!C19+'QTR Raw'!C13+'QTR Raw'!C7 -> #NAME? | AJ23: =+'QTR Raw'!D20+'QTR Raw'!D19+'QTR Raw'!D13+'QTR Raw'!D7 -> #NAME? | AK23: =+'QTR Raw'!E20+'QTR Raw'!E19+'QTR Raw'!E13+'QTR Raw'!E7 -> #NAME? | AL23: =+'QTR Raw'!F20+'QTR Raw'!F19+'QTR Raw'!F13+'QTR Raw'!F7 -> #NAME? | AM23: =+'QTR Raw'!G20+'QTR Raw'!G19+'QTR Raw'!G13+'QTR Raw'!G7 -> #NAME? | AN23: =+'QTR Raw'!H20+'QTR Raw'!H19+'QTR Raw'!H13+'QTR Raw'!H7 -> #NAME? | AO23: =+'QTR Raw'!I20+'QTR Raw'!I19+'QTR Raw'!I13+'QTR Raw'!I7 -> #NAME? | AP23: =+'QTR Raw'!J20+'QTR Raw'!J19+'QTR Raw'!J13+'QTR Raw'!J7 -> #NAME? | ... CL23: =+'QTR Raw'!BF20+'QTR Raw'!BF19+'QTR Raw'!BF13+'QTR Raw'!BF7 -> #NAME? | DF23: 0
A24: Net Revenue | B24: =+B22-B23 -> #NAME? | C24: =+C22-C23 -> #NAME? | D24: =+D22-D23 -> #NAME? | E24: =+E22-E23 -> #NAME? | F24: =+F22-F23 -> #NAME? | G24: =+G22-G23 -> #NAME? | H24: =+H22-H23 -> #NAME? | I24: =+I22-I23 -> #NAME? | ... AE24: =+AE22-AE23 -> #NAME? | AI24: =+AI22-AI23 -> #NAME? | AJ24: =+AJ22-AJ23 -> #NAME? | AK24: =+AK22-AK23 -> #NAME? | AL24: =+AL22-AL23 -> #NAME? | AM24: =+AM22-AM23 -> #NAME? | AN24: =+AN22-AN23 -> #NAME? | AO24: =+AO22-AO23 -> #NAME? | AP24: =+AP22-AP23 -> #NAME? | ... DB24: =+DB22-DB23 -> #NAME? | DF24: 932.157
A25: Net Revenue YOY% | C25: =C24/B24-1 -> #NAME? | D25: =D24/C24-1 -> #NAME? | E25: =E24/D24-1 -> #NAME? | F25: =F24/E24-1 -> #NAME? | G25: =G24/F24-1 -> #NAME? | H25: =H24/G24-1 -> #NAME? | I25: =I24/H24-1 -> #NAME? | J25: =J24/I24-1 -> #NAME? | ... AE25: =AE24/AD24-1 -> #NAME? | AM25: =+IF(AI24<0,1-AM24/AI24,AM24/AI24-1) -> #NAME? | AN25: =+IF(AJ24<0,1-AN24/AJ24,AN24/AJ24-1) -> #NAME? | AO25: =+IF(AK24<0,1-AO24/AK24,AO24/AK24-1) -> #NAME? | AP25: =+IF(AL24<0,1-AP24/AL24,AP24/AL24-1) -> #NAME? | AQ25: =+IF(AM24<0,1-AQ24/AM24,AQ24/AM24-1) -> #NAME? | AR25: =+IF(AN24<0,1-AR24/AN24,AR24/AN24-1) -> #NAME? | AS25: =+IF(AO24<0,1-AS24/AO24,AS24/AO24-1) -> #NAME? | AT25: =+IF(AP24<0,1-AT24/AP24,AT24/AP24-1) -> #NAME? | ... CL25: =+IF(CH24<0,1-CL24/CH24,CL24/CH24-1) -> #NAME? | CM25: 0.25 | CN25: =+AVERAGE(CJ25:CM25) -> #NAME? | CO25: =+AVERAGE(CK25:CN25) -> #NAME? | CP25: =+AVERAGE(CL25:CO25) -> #NAME? | CQ25: =+AVERAGE(CM25:CP25) -> #NAME? | CR25: =+AVERAGE(CN25:CQ25) -> #NAME? | CS25: =+AVERAGE(CO25:CR25) -> #NAME? | CT25: =+AVERAGE(CP25:CS25) -> #NAME? | CU25: =+AVERAGE(CQ25:CT25) -> #NAME? | ... DB25: =+AVERAGE(CX25:DA25) -> #NAME? | DF25: 0.10223389
A26: Net Revenue QOQ% | AJ26: =+IF(AI24<0,1-AJ24/AI24,AJ24/AI24-1) -> #NAME? | AK26: =+IF(AJ24<0,1-AK24/AJ24,AK24/AJ24-1) -> #NAME? | AL26: =+IF(AK24<0,1-AL24/AK24,AL24/AK24-1) -> #NAME? | AM26: =+IF(AL24<0,1-AM24/AL24,AM24/AL24-1) -> #NAME? | AN26: =+IF(AM24<0,1-AN24/AM24,AN24/AM24-1) -> #NAME? | AO26: =+IF(AN24<0,1-AO24/AN24,AO24/AN24-1) -> #NAME? | AP26: =+IF(AO24<0,1-AP24/AO24,AP24/AO24-1) -> #NAME? | AQ26: =+IF(AP24<0,1-AQ24/AP24,AQ24/AP24-1) -> #NAME? | ... CL26: =+IF(CK24<0,1-CL24/CK24,CL24/CK24-1) -> #NAME? | CM26: =+CM24/CL24-1 -> #NAME? | CN26: =+CN24/CM24-1 -> #NAME? | CO26: =+CO24/CN24-1 -> #NAME? | CP26: =+CP24/CO24-1 -> #NAME? | CQ26: =+CQ24/CP24-1 -> #NAME? | CR26: =+CR24/CQ24-1 -> #NAME? | CS26: =+CS24/CR24-1 -> #NAME? | CT26: =+CT24/CS24-1 -> #NAME? | ... DB26: =+DB24/DA24-1 -> #NAME?
A27: Increase/Decrease in Stock | B27: ='Annual Raw'!C11 -> #NAME? | C27: ='Annual Raw'!D11 -> #NAME? | D27: ='Annual Raw'!E11 -> #NAME? | E27: ='Annual Raw'!F11 -> #NAME? | F27: ='Annual Raw'!G11 -> #NAME? | G27: ='Annual Raw'!H11 -> #NAME? | H27: ='Annual Raw'!I11 -> #NAME? | I27: ='Annual Raw'!J11 -> #NAME? | ... AA27: ='Annual Raw'!AB11 -> #NAME? | AB27: =+SUM(CM27:CP27) -> 0 | AC27: =+SUM(CQ27:CT27) -> 0 | AD27: =+SUM(CU27:CX27) -> 0 | AE27: =+SUM(CY27:DB27) -> 0 | AI27: ='QTR Raw'!C10 -> #NAME? | AJ27: ='QTR Raw'!D10 -> #NAME? | AK27: ='QTR Raw'!E10 -> #NAME? | AL27: ='QTR Raw'!F10 -> #NAME? | AM27: ='QTR Raw'!G10 -> #NAME? | AN27: ='QTR Raw'!H10 -> #NAME? | AO27: ='QTR Raw'!I10 -> #NAME? | AP27: ='QTR Raw'!J10 -> #NAME? | ... CL27: ='QTR Raw'!BF10 -> #NAME? | DF27: 0
A28: Purchase of Finished Goods | B28: 0 | C28: 0 | D28: 0 | E28: 0 | F28: 0 | G28: 0 | H28: 0 | I28: 0 | J28: 0 | K28: 0 | L28: 0 | M28: 0 | N28: 0 | O28: 0 | P28: 0 | Q28: 0 | R28: 0 | S28: 0 | T28: 0 | U28: 0 | V28: 0 | W28: 0 | X28: 0 | Y28: 0 | Z28: 0 | AA28: 0 | AB28: =+SUM(CM28:CP28) -> 0 | AC28: =+SUM(CQ28:CT28) -> 0 | AD28: =+SUM(CU28:CX28) -> 0 | AE28: =+SUM(CY28:DB28) -> 0 | AI28: ='QTR Raw'!C12 -> #NAME? | AJ28: ='QTR Raw'!D12 -> #NAME? | AK28: ='QTR Raw'!E12 -> #NAME? | AL28: ='QTR Raw'!F12 -> #NAME? | AM28: ='QTR Raw'!G12 -> #NAME? | AN28: ='QTR Raw'!H12 -> #NAME? | AO28: ='QTR Raw'!I12 -> #NAME? | AP28: ='QTR Raw'!J12 -> #NAME? | ... CL28: ='QTR Raw'!BF12 -> #NAME? | DF28: 0
A29: Raw Material Consumed | B29: ='Annual Raw'!C12 -> #NAME? | C29: ='Annual Raw'!D12 -> #NAME? | D29: ='Annual Raw'!E12 -> #NAME? | E29: ='Annual Raw'!F12 -> #NAME? | F29: ='Annual Raw'!G12 -> #NAME? | G29: ='Annual Raw'!H12 -> #NAME? | H29: ='Annual Raw'!I12 -> #NAME? | I29: ='Annual Raw'!J12 -> #NAME? | ... AA29: ='Annual Raw'!AB12 -> #NAME? | AB29: =+SUM(CM29:CP29) -> #NAME? | AC29: =+SUM(CQ29:CT29) -> #NAME? | AD29: =+SUM(CU29:CX29) -> #NAME? | AE29: =+SUM(CY29:DB29) -> #NAME? | AI29: ='QTR Raw'!C11 -> #NAME? | AJ29: ='QTR Raw'!D11 -> #NAME? | AK29: ='QTR Raw'!E11 -> #NAME? | AL29: ='QTR Raw'!F11 -> #NAME? | AM29: ='QTR Raw'!G11 -> #NAME? | AN29: ='QTR Raw'!H11 -> #NAME? | AO29: ='QTR Raw'!I11 -> #NAME? | AP29: ='QTR Raw'!J11 -> #NAME? | ... CL29: ='QTR Raw'!BF11 -> #NAME? | CM29: =+CM24-CM30 -> #NAME? | CN29: =+CN24-CN30 -> #NAME? | CO29: =+CO24-CO30 -> #NAME? | CP29: =+CP24-CP30 -> #NAME? | CQ29: =+CQ24-CQ30 -> #NAME? | CR29: =+CR24-CR30 -> #NAME? | CS29: =+CS24-CS30 -> #NAME? | CT29: =+CT24-CT30 -> #NAME? | ... DB29: =+DB24-DB30 -> #NAME? | DF29: 0
A30: Gross Profit | B30: =B24-B27-B29-B28 -> #NAME? | C30: =C24-C27-C29-C28 -> #NAME? | D30: =D24-D27-D29-D28 -> #NAME? | E30: =E24-E27-E29-E28 -> #NAME? | F30: =F24-F27-F29-F28 -> #NAME? | G30: =G24-G27-G29-G28 -> #NAME? | H30: =H24-H27-H29-H28 -> #NAME? | I30: =I24-I27-I29-I28 -> #NAME? | ... AE30: =AE24-AE27-AE29-AE28 -> #NAME? | AI30: =AI24-AI27-AI29-AI28 -> #NAME? | AJ30: =AJ24-AJ27-AJ29-AJ28 -> #NAME? | AK30: =AK24-AK27-AK29-AK28 -> #NAME? | AL30: =AL24-AL27-AL29-AL28 -> #NAME? | AM30: =AM24-AM27-AM29-AM28 -> #NAME? | AN30: =AN24-AN27-AN29-AN28 -> #NAME? | AO30: =AO24-AO27-AO29-AO28 -> #NAME? | AP30: =AP24-AP27-AP29-AP28 -> #NAME? | ... CL30: =CL24-CL27-CL29-CL28 -> #NAME? | CM30: =+CM31*CM24 -> #NAME? | CN30: =+CN31*CN24 -> #NAME? | CO30: =+CO31*CO24 -> #NAME? | CP30: =+CP31*CP24 -> #NAME? | CQ30: =+CQ31*CQ24 -> #NAME? | CR30: =+CR31*CR24 -> #NAME? | CS30: =+CS31*CS24 -> #NAME? | CT30: =+CT31*CT24 -> #NAME? | ... DB30: =+DB31*DB24 -> #NAME? | DF30: 932.157
A31: GP% | B31: =B30/B24 -> #NAME? | C31: =C30/C24 -> #NAME? | D31: =D30/D24 -> #NAME? | E31: =E30/E24 -> #NAME? | F31: =F30/F24 -> #NAME? | G31: =G30/G24 -> #NAME? | H31: =H30/H24 -> #NAME? | I31: =I30/I24 -> #NAME? | ... AE31: =AE30/AE24 -> #NAME? | AI31: =AI30/AI24 -> #NAME? | AJ31: =AJ30/AJ24 -> #NAME? | AK31: =AK30/AK24 -> #NAME? | AL31: =AL30/AL24 -> #NAME? | AM31: =AM30/AM24 -> #NAME? | AN31: =AN30/AN24 -> #NAME? | AO31: =AO30/AO24 -> #NAME? | AP31: =AP30/AP24 -> #NAME? | ... CL31: =CL30/CL24 -> #NAME? | CM31: =AVERAGE(CI31:CL31) -> #NAME? | CN31: =AVERAGE(CJ31:CM31) -> #NAME? | CO31: =AVERAGE(CK31:CN31) -> #NAME? | CP31: =AVERAGE(CL31:CO31) -> #NAME? | CQ31: =AVERAGE(CM31:CP31) -> #NAME? | CR31: =AVERAGE(CN31:CQ31) -> #NAME? | CS31: =AVERAGE(CO31:CR31) -> #NAME? | CT31: =AVERAGE(CP31:CS31) -> #NAME? | ... DB31: =AVERAGE(CX31:DA31) -> #NAME? | DF31: 1
A32: GP YOY% | C32: =+IF(B30<0,1-C30/B30,C30/B30-1) -> #NAME? | D32: =+IF(C30<0,1-D30/C30,D30/C30-1) -> #NAME? | E32: =+IF(D30<0,1-E30/D30,E30/D30-1) -> #NAME? | F32: =+IF(E30<0,1-F30/E30,F30/E30-1) -> #NAME? | G32: =+IF(F30<0,1-G30/F30,G30/F30-1) -> #NAME? | H32: =+IF(G30<0,1-H30/G30,H30/G30-1) -> #NAME? | I32: =+IF(H30<0,1-I30/H30,I30/H30-1) -> #NAME? | J32: =+IF(I30<0,1-J30/I30,J30/I30-1) -> #NAME? | ... AE32: =+IF(AD30<0,1-AE30/AD30,AE30/AD30-1) -> #NAME? | AM32: =+IF(AI30<0,1-AM30/AI30,AM30/AI30-1) -> #NAME? | AN32: =+IF(AJ30<0,1-AN30/AJ30,AN30/AJ30-1) -> #NAME? | AO32: =+IF(AK30<0,1-AO30/AK30,AO30/AK30-1) -> #NAME? | AP32: =+IF(AL30<0,1-AP30/AL30,AP30/AL30-1) -> #NAME? | AQ32: =+IF(AM30<0,1-AQ30/AM30,AQ30/AM30-1) -> #NAME? | AR32: =+IF(AN30<0,1-AR30/AN30,AR30/AN30-1) -> #NAME? | AS32: =+IF(AO30<0,1-AS30/AO30,AS30/AO30-1) -> #NAME? | AT32: =+IF(AP30<0,1-AT30/AP30,AT30/AP30-1) -> #NAME? | ... CL32: =+IF(CH30<0,1-CL30/CH30,CL30/CH30-1) -> #NAME? | CM32: =+CM30/CI30-1 -> #NAME? | CN32: =+CN30/CJ30-1 -> #NAME? | CO32: =+CO30/CK30-1 -> #NAME? | CP32: =+CP30/CL30-1 -> #NAME? | CQ32: =+CQ30/CM30-1 -> #NAME? | CR32: =+CR30/CN30-1 -> #NAME? | CS32: =+CS30/CO30-1 -> #NAME? | CT32: =+CT30/CP30-1 -> #NAME? | ... DB32: =+DB30/CX30-1 -> #NAME? | DF32: 0.10223389
A33: GP QOQ% | AJ33: =+IF(AI30<0,1-AJ30/AI30,AJ30/AI30-1) -> #NAME? | AK33: =+IF(AJ30<0,1-AK30/AJ30,AK30/AJ30-1) -> #NAME? | AL33: =+IF(AK30<0,1-AL30/AK30,AL30/AK30-1) -> #NAME? | AM33: =+IF(AL30<0,1-AM30/AL30,AM30/AL30-1) -> #NAME? | AN33: =+IF(AM30<0,1-AN30/AM30,AN30/AM30-1) -> #NAME? | AO33: =+IF(AN30<0,1-AO30/AN30,AO30/AN30-1) -> #NAME? | AP33: =+IF(AO30<0,1-AP30/AO30,AP30/AO30-1) -> #NAME? | AQ33: =+IF(AP30<0,1-AQ30/AP30,AQ30/AP30-1) -> #NAME? | ... CL33: =+IF(CK30<0,1-CL30/CK30,CL30/CK30-1) -> #NAME? | CM33: =+CM30/CL30-1 -> #NAME? | CN33: =+CN30/CM30-1 -> #NAME? | CO33: =+CO30/CN30-1 -> #NAME? | CP33: =+CP30/CO30-1 -> #NAME? | CQ33: =+CQ30/CP30-1 -> #NAME? | CR33: =+CR30/CQ30-1 -> #NAME? | CS33: =+CS30/CR30-1 -> #NAME? | CT33: =+CT30/CS30-1 -> #NAME? | ... DB33: =+DB30/DA30-1 -> #NAME?
A34: Employee Cost | B34: ='Annual Raw'!C14 -> #NAME? | C34: ='Annual Raw'!D14 -> #NAME? | D34: ='Annual Raw'!E14 -> #NAME? | E34: ='Annual Raw'!F14 -> #NAME? | F34: ='Annual Raw'!G14 -> #NAME? | G34: ='Annual Raw'!H14 -> #NAME? | H34: ='Annual Raw'!I14 -> #NAME? | I34: ='Annual Raw'!J14 -> #NAME? | ... AA34: ='Annual Raw'!AB14 -> #NAME? | AB34: =+SUM(CM34:CP34) -> #NAME? | AC34: =+SUM(CQ34:CT34) -> #NAME? | AD34: =+SUM(CU34:CX34) -> #NAME? | AE34: =+SUM(CY34:DB34) -> #NAME? | AI34: ='QTR Raw'!C16 -> #NAME? | AJ34: ='QTR Raw'!D16 -> #NAME? | AK34: ='QTR Raw'!E16 -> #NAME? | AL34: ='QTR Raw'!F16 -> #NAME? | AM34: ='QTR Raw'!G16 -> #NAME? | AN34: ='QTR Raw'!H16 -> #NAME? | AO34: ='QTR Raw'!I16 -> #NAME? | AP34: ='QTR Raw'!J16 -> #NAME? | ... CG34: ='QTR Raw'!BA16 -> #NAME? | CH34: 66.834 | CI34: ='QTR Raw'!BC16 -> #NAME? | CJ34: ='QTR Raw'!BD16 -> #NAME? | CK34: ='QTR Raw'!BE16 -> #NAME? | CL34: ='QTR Raw'!BF16 -> #NAME? | CM34: =CI34*107% -> #NAME? | CN34: =CJ34*107% -> #NAME? | CO34: =CK34*107% -> #NAME? | CP34: =CL34*107% -> #NAME? | CQ34: =CM34*107% -> #NAME? | CR34: =CN34*107% -> #NAME? | CS34: =CO34*107% -> #NAME? | CT34: =CP34*107% -> #NAME? | ... DB34: =CX34*107% -> #NAME? | DF34: 303.296
A35: General and Administration Expenses | B35: ='Annual Raw'!C17 -> #NAME? | C35: ='Annual Raw'!D17 -> #NAME? | D35: ='Annual Raw'!E17 -> #NAME? | E35: ='Annual Raw'!F17 -> #NAME? | F35: ='Annual Raw'!G17 -> #NAME? | G35: ='Annual Raw'!H17 -> #NAME? | H35: ='Annual Raw'!I17 -> #NAME? | I35: ='Annual Raw'!J17 -> #NAME? | ... AA35: ='Annual Raw'!AB17 -> #NAME? | AB35: =+SUM(CM35:CP35) -> 0 | AC35: =+SUM(CQ35:CT35) -> 0 | AD35: =+SUM(CU35:CX35) -> 0 | AE35: =+SUM(CY35:DB35) -> 0 | AI35: ='QTR Raw'!C17 -> #NAME? | AJ35: ='QTR Raw'!D17 -> #NAME? | AK35: ='QTR Raw'!E17 -> #NAME? | AL35: ='QTR Raw'!F17 -> #NAME? | AM35: ='QTR Raw'!G17 -> #NAME? | AN35: ='QTR Raw'!H17 -> #NAME? | AO35: ='QTR Raw'!I17 -> #NAME? | AP35: ='QTR Raw'!J17 -> #NAME? | ... CG35: ='QTR Raw'!BA17 -> #NAME? | CH35: 23.9 | CI35: ='QTR Raw'!BC17 -> #NAME? | CJ35: ='QTR Raw'!BD17 -> #NAME? | CK35: ='QTR Raw'!BE17 -> #NAME? | CL35: ='QTR Raw'!BF17 -> #NAME? | DF35: 98.548
A36: Miscellaneous Expenses | B36: ='Annual Raw'!C19-'Annual Raw'!C20 -> #NAME? | C36: ='Annual Raw'!D19-'Annual Raw'!D20 -> #NAME? | D36: ='Annual Raw'!E19-'Annual Raw'!E20 -> #NAME? | E36: ='Annual Raw'!F19-'Annual Raw'!F20 -> #NAME? | F36: ='Annual Raw'!G19-'Annual Raw'!G20 -> #NAME? | G36: ='Annual Raw'!H19-'Annual Raw'!H20 -> #NAME? | H36: ='Annual Raw'!I19-'Annual Raw'!I20 -> #NAME? | I36: ='Annual Raw'!J19-'Annual Raw'!J20 -> #NAME? | ... AA36: ='Annual Raw'!AB19-'Annual Raw'!AB20 -> #NAME? | AB36: =+SUM(CM36:CP36) -> 0 | AC36: =+SUM(CQ36:CT36) -> 0 | AD36: =+SUM(CU36:CX36) -> 0 | AE36: =+SUM(CY36:DB36) -> 0 | AI36: =+'QTR Raw'!C21 -> #NAME? | AJ36: =+'QTR Raw'!D21 -> #NAME? | AK36: =+'QTR Raw'!E21 -> #NAME? | AL36: =+'QTR Raw'!F21 -> #NAME? | AM36: =+'QTR Raw'!G21 -> #NAME? | AN36: =+'QTR Raw'!H21 -> #NAME? | AO36: =+'QTR Raw'!I21 -> #NAME? | AP36: =+'QTR Raw'!J21 -> #NAME? | ... CG36: =+'QTR Raw'!BA21 -> #NAME? | CH36: -0.29 | CI36: =+'QTR Raw'!BC21 -> #NAME? | CJ36: =+'QTR Raw'!BD21 -> #NAME? | CK36: =+'QTR Raw'!BE21 -> #NAME? | CL36: =+'QTR Raw'!BF21 -> #NAME? | DF36: 1.3
A37: Other Manufacturing Expenses | B37: ='Annual Raw'!C15+'Annual Raw'!C16 -> #NAME? | C37: ='Annual Raw'!D15+'Annual Raw'!D16 -> #NAME? | D37: ='Annual Raw'!E15+'Annual Raw'!E16 -> #NAME? | E37: ='Annual Raw'!F15+'Annual Raw'!F16 -> #NAME? | F37: ='Annual Raw'!G15+'Annual Raw'!G16 -> #NAME? | G37: ='Annual Raw'!H15+'Annual Raw'!H16 -> #NAME? | H37: ='Annual Raw'!I15+'Annual Raw'!I16 -> #NAME? | I37: ='Annual Raw'!J15+'Annual Raw'!J16 -> #NAME? | ... AA37: ='Annual Raw'!AB15+'Annual Raw'!AB16 -> #NAME? | AB37: =+SUM(CM37:CP37) -> #NAME? | AC37: =+SUM(CQ37:CT37) -> #NAME? | AD37: =+SUM(CU37:CX37) -> #NAME? | AE37: =+SUM(CY37:DB37) -> #NAME? | AI37: ='QTR Raw'!C14 -> #NAME? | AJ37: ='QTR Raw'!D14 -> #NAME? | AK37: ='QTR Raw'!E14 -> #NAME? | AL37: ='QTR Raw'!F14 -> #NAME? | AM37: ='QTR Raw'!G14 -> #NAME? | AN37: ='QTR Raw'!H14 -> #NAME? | AO37: ='QTR Raw'!I14 -> #NAME? | AP37: ='QTR Raw'!J14 -> #NAME? | ... CG37: ='QTR Raw'!BA14 -> #NAME? | CH37: 36.28 | CI37: ='QTR Raw'!BC14 -> #NAME? | CJ37: ='QTR Raw'!BD14 -> #NAME? | CK37: ='QTR Raw'!BE14 -> #NAME? | CL37: ='QTR Raw'!BF14 -> #NAME? | CM37: =CM40-CM34-CM35-CM36-CM38-CM39 -> #NAME? | CN37: =CN40-CN34-CN35-CN36-CN38-CN39 -> #NAME? | CO37: =CO40-CO34-CO35-CO36-CO38-CO39 -> #NAME? | CP37: =CP40-CP34-CP35-CP36-CP38-CP39 -> #NAME? | CQ37: =CQ40-CQ34-CQ35-CQ36-CQ38-CQ39 -> #NAME? | CR37: =CR40-CR34-CR35-CR36-CR38-CR39 -> #NAME? | CS37: =CS40-CS34-CS35-CS36-CS38-CS39 -> #NAME? | CT37: =CT40-CT34-CT35-CT36-CT38-CT39 -> #NAME? | ... DB37: =DB40-DB34-DB35-DB36-DB38-DB39 -> #NAME? | DF37: 150.144
A38: Power & Fuel Cost | B38: ='Annual Raw'!C13 -> #NAME? | C38: ='Annual Raw'!D13 -> #NAME? | D38: ='Annual Raw'!E13 -> #NAME? | E38: ='Annual Raw'!F13 -> #NAME? | F38: ='Annual Raw'!G13 -> #NAME? | G38: ='Annual Raw'!H13 -> #NAME? | H38: ='Annual Raw'!I13 -> #NAME? | I38: ='Annual Raw'!J13 -> #NAME? | ... AA38: ='Annual Raw'!AB13 -> #NAME? | AB38: =+SUM(CM38:CP38) -> 0 | AC38: =+SUM(CQ38:CT38) -> 0 | AD38: =+SUM(CU38:CX38) -> 0 | AE38: =+SUM(CY38:DB38) -> 0 | AI38: ='QTR Raw'!C15 -> #NAME? | AJ38: ='QTR Raw'!D15 -> #NAME? | AK38: ='QTR Raw'!E15 -> #NAME? | AL38: ='QTR Raw'!F15 -> #NAME? | AM38: ='QTR Raw'!G15 -> #NAME? | AN38: ='QTR Raw'!H15 -> #NAME? | AO38: ='QTR Raw'!I15 -> #NAME? | AP38: ='QTR Raw'!J15 -> #NAME? | ... CL38: ='QTR Raw'!BF15 -> #NAME? | DF38: 0
A39: Selling and Distribution Expenses | B39: ='Annual Raw'!C18 -> #NAME? | C39: ='Annual Raw'!D18 -> #NAME? | D39: ='Annual Raw'!E18 -> #NAME? | E39: ='Annual Raw'!F18 -> #NAME? | F39: ='Annual Raw'!G18 -> #NAME? | G39: ='Annual Raw'!H18 -> #NAME? | H39: ='Annual Raw'!I18 -> #NAME? | I39: ='Annual Raw'!J18 -> #NAME? | ... AA39: ='Annual Raw'!AB18 -> #NAME? | AB39: =+SUM(CM39:CP39) -> 0 | AC39: =+SUM(CQ39:CT39) -> 0 | AD39: =+SUM(CU39:CX39) -> 0 | AE39: =+SUM(CY39:DB39) -> 0 | AI39: ='QTR Raw'!C18 -> #NAME? | AJ39: ='QTR Raw'!D18 -> #NAME? | AK39: ='QTR Raw'!E18 -> #NAME? | AL39: ='QTR Raw'!F18 -> #NAME? | AM39: ='QTR Raw'!G18 -> #NAME? | AN39: ='QTR Raw'!H18 -> #NAME? | AO39: ='QTR Raw'!I18 -> #NAME? | AP39: ='QTR Raw'!J18 -> #NAME? | ... CL39: ='QTR Raw'!BF18 -> #NAME? | DF39: 0
A40: Total Cost | B40: =+SUM(B34:B39) -> #NAME? | C40: =+SUM(C34:C39) -> #NAME? | D40: =+SUM(D34:D39) -> #NAME? | E40: =+SUM(E34:E39) -> #NAME? | F40: =+SUM(F34:F39) -> #NAME? | G40: =+SUM(G34:G39) -> #NAME? | H40: =+SUM(H34:H39) -> #NAME? | I40: =+SUM(I34:I39) -> #NAME? | ... AE40: =+SUM(AE34:AE39) -> #NAME? | AI40: =+SUM(AI34:AI39) -> #NAME? | AJ40: =+SUM(AJ34:AJ39) -> #NAME? | AK40: =+SUM(AK34:AK39) -> #NAME? | AL40: =+SUM(AL34:AL39) -> #NAME? | AM40: =+SUM(AM34:AM39) -> #NAME? | AN40: =+SUM(AN34:AN39) -> #NAME? | AO40: =+SUM(AO34:AO39) -> #NAME? | AP40: =+SUM(AP34:AP39) -> #NAME? | ... CL40: =+SUM(CL34:CL39) -> #NAME? | CM40: =CM41*CM24 -> #NAME? | CN40: =CN41*CN24 -> #NAME? | CO40: =CO41*CO24 -> #NAME? | CP40: =CP41*CP24 -> #NAME? | CQ40: =CQ41*CQ24 -> #NAME? | CR40: =CR41*CR24 -> #NAME? | CS40: =CS41*CS24 -> #NAME? | CT40: =CT41*CT24 -> #NAME? | ... DB40: =DB41*DB24 -> #NAME? | DF40: 553.288
A41: Cost % | B41: =B40/B24 -> #NAME? | C41: =C40/C24 -> #NAME? | D41: =D40/D24 -> #NAME? | E41: =E40/E24 -> #NAME? | F41: =F40/F24 -> #NAME? | G41: =G40/G24 -> #NAME? | H41: =H40/H24 -> #NAME? | I41: =I40/I24 -> #NAME? | ... AE41: =AE40/AE24 -> #NAME? | AI41: =AI40/AI24 -> #NAME? | AJ41: =AJ40/AJ24 -> #NAME? | AK41: =AK40/AK24 -> #NAME? | AL41: =AL40/AL24 -> #NAME? | AM41: =AM40/AM24 -> #NAME? | AN41: =AN40/AN24 -> #NAME? | AO41: =AO40/AO24 -> #NAME? | AP41: =AP40/AP24 -> #NAME? | ... CL41: =CL40/CL24 -> #NAME? | CM41: =CL41 -> #NAME? | CN41: =AVERAGE(CJ41:CM41) -> #NAME? | CO41: =AVERAGE(CK41:CN41) -> #NAME? | CP41: =AVERAGE(CL41:CO41) -> #NAME? | CQ41: =AVERAGE(CM41:CP41) -> #NAME? | CR41: =AVERAGE(CN41:CQ41) -> #NAME? | CS41: =AVERAGE(CO41:CR41) -> #NAME? | CT41: =AVERAGE(CP41:CS41) -> #NAME? | CU41: =AVERAGE(CQ41:CT41) -> #NAME? | ... DB41: =AVERAGE(CX41:DA41) -> #NAME? | DF41: 0.59355666
A42: EBITDA | B42: =B30-B40 -> #NAME? | C42: =C30-C40 -> #NAME? | D42: =D30-D40 -> #NAME? | E42: =E30-E40 -> #NAME? | F42: =F30-F40 -> #NAME? | G42: =G30-G40 -> #NAME? | H42: =H30-H40 -> #NAME? | I42: =I30-I40 -> #NAME? | ... AE42: =AE30-AE40 -> #NAME? | AI42: =AI30-AI40 -> #NAME? | AJ42: =AJ30-AJ40 -> #NAME? | AK42: =AK30-AK40 -> #NAME? | AL42: =AL30-AL40 -> #NAME? | AM42: =AM30-AM40 -> #NAME? | AN42: =AN30-AN40 -> #NAME? | AO42: =AO30-AO40 -> #NAME? | AP42: =AP30-AP40 -> #NAME? | ... DB42: =DB30-DB40 -> #NAME? | DF42: 378.869
A43: EBITDA Margins | B43: =B42/B24 -> #NAME? | C43: =C42/C24 -> #NAME? | D43: =D42/D24 -> #NAME? | E43: =E42/E24 -> #NAME? | F43: =F42/F24 -> #NAME? | G43: =G42/G24 -> #NAME? | H43: =H42/H24 -> #NAME? | I43: =I42/I24 -> #NAME? | ... AE43: =AE42/AE24 -> #NAME? | AI43: =AI42/AI24 -> #NAME? | AJ43: =AJ42/AJ24 -> #NAME? | AK43: =AK42/AK24 -> #NAME? | AL43: =AL42/AL24 -> #NAME? | AM43: =AM42/AM24 -> #NAME? | AN43: =AN42/AN24 -> #NAME? | AO43: =AO42/AO24 -> #NAME? | AP43: =AP42/AP24 -> #NAME? | ... DB43: =DB42/DB24 -> #NAME? | DF43: 0.40644334
A44: EBITDA YOY% | C44: =+IF(B42<0,1-C42/B42,C42/B42-1) -> #NAME? | D44: =+IF(C42<0,1-D42/C42,D42/C42-1) -> #NAME? | E44: =+IF(D42<0,1-E42/D42,E42/D42-1) -> #NAME? | F44: =+IF(E42<0,1-F42/E42,F42/E42-1) -> #NAME? | G44: =+IF(F42<0,1-G42/F42,G42/F42-1) -> #NAME? | H44: =+IF(G42<0,1-H42/G42,H42/G42-1) -> #NAME? | I44: =+IF(H42<0,1-I42/H42,I42/H42-1) -> #NAME? | J44: =+IF(I42<0,1-J42/I42,J42/I42-1) -> #NAME? | ... AE44: =+IF(AD42<0,1-AE42/AD42,AE42/AD42-1) -> #NAME? | AM44: =+IF(AI42<0,1-AM42/AI42,AM42/AI42-1) -> #NAME? | AN44: =+IF(AJ42<0,1-AN42/AJ42,AN42/AJ42-1) -> #NAME? | AO44: =+IF(AK42<0,1-AO42/AK42,AO42/AK42-1) -> #NAME? | AP44: =+IF(AL42<0,1-AP42/AL42,AP42/AL42-1) -> #NAME? | AQ44: =+IF(AM42<0,1-AQ42/AM42,AQ42/AM42-1) -> #NAME? | AR44: =+IF(AN42<0,1-AR42/AN42,AR42/AN42-1) -> #NAME? | AS44: =+IF(AO42<0,1-AS42/AO42,AS42/AO42-1) -> #NAME? | AT44: =+IF(AP42<0,1-AT42/AP42,AT42/AP42-1) -> #NAME? | ... CL44: =+IF(CH42<0,1-CL42/CH42,CL42/CH42-1) -> #NAME? | CM44: =+CM42/CI42-1 -> #NAME? | CN44: =+CN42/CJ42-1 -> #NAME? | CO44: =+CO42/CK42-1 -> #NAME? | CP44: =+CP42/CL42-1 -> #NAME? | CQ44: =+CQ42/CM42-1 -> #NAME? | CR44: =+CR42/CN42-1 -> #NAME? | CS44: =+CS42/CO42-1 -> #NAME? | CT44: =+CT42/CP42-1 -> #NAME? | ... DB44: =+DB42/CX42-1 -> #NAME? | DF44: 0.21718332
A45: EBITDA QOQ% | AJ45: =+IF(AI42<0,1-AJ42/AI42,AJ42/AI42-1) -> #NAME? | AK45: =+IF(AJ42<0,1-AK42/AJ42,AK42/AJ42-1) -> #NAME? | AL45: =+IF(AK42<0,1-AL42/AK42,AL42/AK42-1) -> #NAME? | AM45: =+IF(AL42<0,1-AM42/AL42,AM42/AL42-1) -> #NAME? | AN45: =+IF(AM42<0,1-AN42/AM42,AN42/AM42-1) -> #NAME? | AO45: =+IF(AN42<0,1-AO42/AN42,AO42/AN42-1) -> #NAME? | AP45: =+IF(AO42<0,1-AP42/AO42,AP42/AO42-1) -> #NAME? | AQ45: =+IF(AP42<0,1-AQ42/AP42,AQ42/AP42-1) -> #NAME? | ... CI45: =+IF(CH42<0,1-CI42/CH42,CI42/CH42-1) -> #NAME? | CJ45: =+IF(CI42>1,CJ42/CI42-1,1-CJ42/CI42) -> #NAME? | CK45: =+IF(CJ42>1,CK42/CJ42-1,1-CK42/CJ42) -> #NAME? | CL45: =+IF(CK42>1,CL42/CK42-1,1-CL42/CK42) -> #NAME? | CM45: =+CM42/CL42-1 -> #NAME? | CN45: =+CN42/CM42-1 -> #NAME? | CO45: =+CO42/CN42-1 -> #NAME? | CP45: =+CP42/CO42-1 -> #NAME? | CQ45: =+CQ42/CP42-1 -> #NAME? | CR45: =+CR42/CQ42-1 -> #NAME? | CS45: =+CS42/CR42-1 -> #NAME? | CT45: =+CT42/CS42-1 -> #NAME? | ... DB45: =+DB42/DA42-1 -> #NAME?
A46: Depreciation | B46: ='Annual Raw'!C27 -> #NAME? | C46: ='Annual Raw'!D27 -> #NAME? | D46: ='Annual Raw'!E27 -> #NAME? | E46: ='Annual Raw'!F27 -> #NAME? | F46: ='Annual Raw'!G27 -> #NAME? | G46: ='Annual Raw'!H27 -> #NAME? | H46: ='Annual Raw'!I27 -> #NAME? | I46: ='Annual Raw'!J27 -> #NAME? | ... AA46: ='Annual Raw'!AB27 -> #NAME? | AB46: =+SUM(CM46:CP46) -> #NAME? | AC46: =+SUM(CQ46:CT46) -> #NAME? | AD46: =+SUM(CU46:CX46) -> #NAME? | AE46: =+SUM(CY46:DB46) -> #NAME? | AI46: ='QTR Raw'!C28 -> #NAME? | AJ46: ='QTR Raw'!D28 -> #NAME? | AK46: ='QTR Raw'!E28 -> #NAME? | AL46: ='QTR Raw'!F28 -> #NAME? | AM46: ='QTR Raw'!G28 -> #NAME? | AN46: ='QTR Raw'!H28 -> #NAME? | AO46: ='QTR Raw'!I28 -> #NAME? | AP46: ='QTR Raw'!J28 -> #NAME? | ... CG46: ='QTR Raw'!BA28 -> #NAME? | CH46: 8.5 | CI46: ='QTR Raw'!BC28 -> #NAME? | CJ46: ='QTR Raw'!BD28 -> #NAME? | CK46: ='QTR Raw'!BE28 -> #NAME? | CL46: ='QTR Raw'!BF28 -> #NAME? | CM46: =CM47*CL148 -> #NAME? | CN46: =CN47*CM148 -> #NAME? | CO46: =CO47*CN148 -> #NAME? | CP46: =CP47*CO148 -> #NAME? | CQ46: =CQ47*CP148 -> #NAME? | CR46: =CR47*CQ148 -> #NAME? | CS46: =CS47*CR148 -> #NAME? | CT46: =CT47*CS148 -> #NAME? | ... DB46: =DB47*DA148 -> #NAME? | DF46: 26.137
A47: Depreciation % of Net Block | B47: =+B46/B148 -> #NAME? | C47: =+C46/C148 -> #NAME? | D47: =+D46/D148 -> #NAME? | E47: =+E46/E148 -> #NAME? | F47: =+F46/F148 -> #NAME? | G47: =+G46/G148 -> #NAME? | H47: =+H46/H148 -> #NAME? | I47: =+I46/I148 -> #NAME? | ... AE47: =+AE46/AE148 -> #NAME? | AI47: =+AI46/AH148 -> #NAME? | AJ47: =+AJ46/AI148 -> #NAME? | AK47: =+AK46/AJ148 -> #NAME? | AL47: =+AL46/AK148 -> #NAME? | AM47: =+AM46/AL148 -> #NAME? | AN47: =+AN46/AM148 -> #NAME? | AO47: =+AO46/AN148 -> #NAME? | AP47: =+AP46/AO148 -> #NAME? | ... CL47: =+CL46/CK148 -> #NAME? | CM47: =CL47 -> #NAME? | CN47: =CM47 -> #NAME? | CO47: =CN47 -> #NAME? | CP47: =CO47 -> #NAME? | CQ47: =CP47 -> #NAME? | CR47: =CQ47 -> #NAME? | CS47: =CR47 -> #NAME? | CT47: =CS47 -> #NAME? | ... DB47: =DA47 -> #NAME? | DF47: 0.46837144
A48: EBIT | B48: =B42-B46 -> #NAME? | C48: =C42-C46 -> #NAME? | D48: =D42-D46 -> #NAME? | E48: =E42-E46 -> #NAME? | F48: =F42-F46 -> #NAME? | G48: =G42-G46 -> #NAME? | H48: =H42-H46 -> #NAME? | I48: =I42-I46 -> #NAME? | ... AE48: =AE42-AE46 -> #NAME? | AI48: =AI42-AI46 -> #NAME? | AJ48: =AJ42-AJ46 -> #NAME? | AK48: =AK42-AK46 -> #NAME? | AL48: =AL42-AL46 -> #NAME? | AM48: =AM42-AM46 -> #NAME? | AN48: =AN42-AN46 -> #NAME? | AO48: =AO42-AO46 -> #NAME? | AP48: =AP42-AP46 -> #NAME? | ... DB48: =DB42-DB46 -> #NAME? | DF48: 352.732
A49: Other Income | B49: ='Annual Raw'!C23 -> #NAME? | C49: ='Annual Raw'!D23 -> #NAME? | D49: ='Annual Raw'!E23 -> #NAME? | E49: ='Annual Raw'!F23 -> #NAME? | F49: ='Annual Raw'!G23 -> #NAME? | G49: ='Annual Raw'!H23 -> #NAME? | H49: ='Annual Raw'!I23 -> #NAME? | I49: ='Annual Raw'!J23 -> #NAME? | ... AA49: ='Annual Raw'!AB23 -> #NAME? | AB49: =+SUM(CM49:CP49) -> 0 | AC49: =+SUM(CQ49:CT49) -> 0 | AD49: =+SUM(CU49:CX49) -> 0 | AE49: =+SUM(CY49:DB49) -> 0 | AI49: ='QTR Raw'!C23 -> #NAME? | AJ49: ='QTR Raw'!D23 -> #NAME? | AK49: ='QTR Raw'!E23 -> #NAME? | AL49: ='QTR Raw'!F23 -> #NAME? | AM49: ='QTR Raw'!G23 -> #NAME? | AN49: ='QTR Raw'!H23 -> #NAME? | AO49: ='QTR Raw'!I23 -> #NAME? | AP49: ='QTR Raw'!J23 -> #NAME? | ... CG49: ='QTR Raw'!BA23 -> #NAME? | CH49: 0.393 | CI49: ='QTR Raw'!BC23 -> #NAME? | CJ49: ='QTR Raw'!BD23 -> #NAME? | CK49: ='QTR Raw'!BE23 -> #NAME? | CL49: ='QTR Raw'!BF23 -> #NAME? | DF49: 2.932
A50: Interest | B50: ='Annual Raw'!C25 -> #NAME? | C50: ='Annual Raw'!D25 -> #NAME? | D50: ='Annual Raw'!E25 -> #NAME? | E50: ='Annual Raw'!F25 -> #NAME? | F50: ='Annual Raw'!G25 -> #NAME? | G50: ='Annual Raw'!H25 -> #NAME? | H50: ='Annual Raw'!I25 -> #NAME? | I50: ='Annual Raw'!J25 -> #NAME? | ... AA50: ='Annual Raw'!AB25 -> #NAME? | AB50: =+SUM(CM50:CP50) -> #NAME? | AC50: =+SUM(CQ50:CT50) -> #NAME? | AD50: =+SUM(CU50:CX50) -> #NAME? | AE50: =+SUM(CY50:DB50) -> #NAME? | AI50: ='QTR Raw'!C25 -> #NAME? | AJ50: ='QTR Raw'!D25 -> #NAME? | AK50: ='QTR Raw'!E25 -> #NAME? | AL50: ='QTR Raw'!F25 -> #NAME? | AM50: ='QTR Raw'!G25 -> #NAME? | AN50: ='QTR Raw'!H25 -> #NAME? | AO50: ='QTR Raw'!I25 -> #NAME? | AP50: ='QTR Raw'!J25 -> #NAME? | ... CG50: ='QTR Raw'!BA25 -> #NAME? | CH50: 39.2 | CI50: ='QTR Raw'!BC25 -> #NAME? | CJ50: ='QTR Raw'!BD25 -> #NAME? | CK50: ='QTR Raw'!BE25 -> #NAME? | CL50: ='QTR Raw'!BF25 -> #NAME? | CM50: =CM51*CL182 -> #NAME? | CN50: =CN51*CM182 -> #NAME? | CO50: =CO51*CN182 -> #NAME? | CP50: =CP51*CO182 -> #NAME? | CQ50: =CQ51*CP182 -> #NAME? | CR50: =CR51*CQ182 -> #NAME? | CS50: =CS51*CR182 -> #NAME? | CT50: =CT51*CS182 -> #NAME? | ... DB50: =DB51*DA182 -> #NAME? | DF50: 184.091
A51: Interest % of Debt | B51: =+B50/B142 -> #NAME? | C51: =+C50/C142 -> #NAME? | D51: =+D50/D142 -> #NAME? | E51: =+E50/E142 -> #NAME? | F51: =+F50/F142 -> #NAME? | G51: =+G50/G142 -> #NAME? | H51: =+H50/H142 -> #NAME? | I51: =+I50/I142 -> #NAME? | ... AE51: =+AE50/AE142 -> #NAME? | AI51: =(AI50-AI49)/AH182 -> #NAME? | AJ51: =(AJ50-AJ49)/AI182 -> #NAME? | AK51: =(AK50-AK49)/AJ182 -> #NAME? | AL51: =(AL50-AL49)/AK182 -> #NAME? | AM51: =(AM50-AM49)/AL182 -> #NAME? | AN51: =(AN50-AN49)/AM182 -> #NAME? | AO51: =(AO50-AO49)/AN182 -> #NAME? | AP51: =(AP50-AP49)/AO182 -> #NAME? | ... CL51: =(CL50-CL49)/CK182 -> #NAME? | CM51: =+CL51 -> #NAME? | CN51: =+CM51 -> #NAME? | CO51: =+CN51 -> #NAME? | CP51: =+CO51 -> #NAME? | CQ51: =+CP51 -> #NAME? | CR51: =+CQ51 -> #NAME? | CS51: =+CR51 -> #NAME? | CT51: =+CS51 -> #NAME? | ... DB51: =+DA51 -> #NAME? | DF51: 0.22152815
A52: PBT | B52: =B48+B49-B50 -> #NAME? | C52: =C48+C49-C50 -> #NAME? | D52: =D48+D49-D50 -> #NAME? | E52: =E48+E49-E50 -> #NAME? | F52: =F48+F49-F50 -> #NAME? | G52: =G48+G49-G50 -> #NAME? | H52: =H48+H49-H50 -> #NAME? | I52: =I48+I49-I50 -> #NAME? | ... AE52: =AE48+AE49-AE50 -> #NAME? | AI52: =AI48+AI49-AI50 -> #NAME? | AJ52: =AJ48+AJ49-AJ50 -> #NAME? | AK52: =AK48+AK49-AK50 -> #NAME? | AL52: =AL48+AL49-AL50 -> #NAME? | AM52: =AM48+AM49-AM50 -> #NAME? | AN52: =AN48+AN49-AN50 -> #NAME? | AO52: =AO48+AO49-AO50 -> #NAME? | AP52: =AP48+AP49-AP50 -> #NAME? | ... DB52: =DB48+DB49-DB50 -> #NAME? | DF52: 171.573
A53: Tax | B53: ='Annual Raw'!C30 -> #NAME? | C53: ='Annual Raw'!D30 -> #NAME? | D53: ='Annual Raw'!E30 -> #NAME? | E53: ='Annual Raw'!F30 -> #NAME? | F53: ='Annual Raw'!G30 -> #NAME? | G53: ='Annual Raw'!H30 -> #NAME? | H53: ='Annual Raw'!I30 -> #NAME? | I53: ='Annual Raw'!J30 -> #NAME? | ... AA53: ='Annual Raw'!AB30 -> #NAME? | AB53: =+SUM(CM53:CP53) -> #NAME? | AC53: =+SUM(CQ53:CT53) -> #NAME? | AD53: =+SUM(CU53:CX53) -> #NAME? | AE53: =+SUM(CY53:DB53) -> #NAME? | AI53: ='QTR Raw'!C29 -> #NAME? | AJ53: ='QTR Raw'!D29 -> #NAME? | AK53: ='QTR Raw'!E29 -> #NAME? | AL53: ='QTR Raw'!F29 -> #NAME? | AM53: ='QTR Raw'!G29 -> #NAME? | AN53: ='QTR Raw'!H29 -> #NAME? | AO53: ='QTR Raw'!I29 -> #NAME? | AP53: ='QTR Raw'!J29 -> #NAME? | ... CG53: ='QTR Raw'!BA29 -> #NAME? | CH53: 7.2 | CI53: ='QTR Raw'!BC29 -> #NAME? | CJ53: ='QTR Raw'!BD29 -> #NAME? | CK53: ='QTR Raw'!BE29 -> #NAME? | CL53: ='QTR Raw'!BF29 -> #NAME? | CM53: =+CM52*CM54 -> #NAME? | CN53: =+CN52*CN54 -> #NAME? | CO53: =+CO52*CO54 -> #NAME? | CP53: =+CP52*CP54 -> #NAME? | CQ53: =+CQ52*CQ54 -> #NAME? | CR53: =+CR52*CR54 -> #NAME? | CS53: =+CS52*CS54 -> #NAME? | CT53: =+CT52*CT54 -> #NAME? | ... DB53: =+DB52*DB54 -> #NAME? | DF53: 42.299
A54: Tax Rate % | B54: =B53/B52 -> #NAME? | C54: =C53/C52 -> #NAME? | D54: =D53/D52 -> #NAME? | E54: =E53/E52 -> #NAME? | F54: =F53/F52 -> #NAME? | G54: =G53/G52 -> #NAME? | H54: =H53/H52 -> #NAME? | I54: =I53/I52 -> #NAME? | ... AE54: =AE53/AE52 -> #NAME? | AI54: =AI53/AI52 -> #NAME? | AJ54: =AJ53/AJ52 -> #NAME? | AK54: =AK53/AK52 -> #NAME? | AL54: =AL53/AL52 -> #NAME? | AM54: =AM53/AM52 -> #NAME? | AN54: =AN53/AN52 -> #NAME? | AO54: =AO53/AO52 -> #NAME? | AP54: =AP53/AP52 -> #NAME? | ... CL54: =CL53/CL52 -> #NAME? | CM54: =AVERAGE(CI54:CL54) -> #NAME? | CN54: =AVERAGE(CJ54:CM54) -> #NAME? | CO54: =AVERAGE(CK54:CN54) -> #NAME? | CP54: =AVERAGE(CL54:CO54) -> #NAME? | CQ54: =AVERAGE(CM54:CP54) -> #NAME? | CR54: =AVERAGE(CN54:CQ54) -> #NAME? | CS54: =AVERAGE(CO54:CR54) -> #NAME? | CT54: =AVERAGE(CP54:CS54) -> #NAME? | ... DB54: =AVERAGE(CX54:DA54) -> #NAME? | DF54: 0.24653646
A55: PAT | B55: =B52-B53 -> #NAME? | C55: =C52-C53 -> #NAME? | D55: =D52-D53 -> #NAME? | E55: =E52-E53 -> #NAME? | F55: =F52-F53 -> #NAME? | G55: =G52-G53 -> #NAME? | H55: =H52-H53 -> #NAME? | I55: =I52-I53 -> #NAME? | ... AE55: =AE52-AE53 -> #NAME? | AI55: =AI52-AI53 -> #NAME? | AJ55: =AJ52-AJ53 -> #NAME? | AK55: =AK52-AK53 -> #NAME? | AL55: =AL52-AL53 -> #NAME? | AM55: =AM52-AM53 -> #NAME? | AN55: =AN52-AN53 -> #NAME? | AO55: =AO52-AO53 -> #NAME? | AP55: =AP52-AP53 -> #NAME? | ... DB55: =DB52-DB53 -> #NAME? | DF55: 129.274
A56: PAT % | B56: =+B55/B24 -> #NAME? | C56: =+C55/C24 -> #NAME? | D56: =+D55/D24 -> #NAME? | E56: =+E55/E24 -> #NAME? | F56: =+F55/F24 -> #NAME? | G56: =+G55/G24 -> #NAME? | H56: =+H55/H24 -> #NAME? | I56: =+I55/I24 -> #NAME? | ... AE56: =+AE55/AE24 -> #NAME? | AI56: =+AI55/AI24 -> #NAME? | AJ56: =+AJ55/AJ24 -> #NAME? | AK56: =+AK55/AK24 -> #NAME? | AL56: =+AL55/AL24 -> #NAME? | AM56: =+AM55/AM24 -> #NAME? | AN56: =+AN55/AN24 -> #NAME? | AO56: =+AO55/AO24 -> #NAME? | AP56: =+AP55/AP24 -> #NAME? | ... DB56: =+DB55/DB24 -> #NAME? | DF56: 0.13868265
A57: PAT YOY% | C57: =+IF(B55<0,1-C55/B55,C55/B55-1) -> #NAME? | D57: =+IF(C55<0,1-D55/C55,D55/C55-1) -> #NAME? | E57: =+IF(D55<0,1-E55/D55,E55/D55-1) -> #NAME? | F57: =+IF(E55<0,1-F55/E55,F55/E55-1) -> #NAME? | G57: =+IF(F55<0,1-G55/F55,G55/F55-1) -> #NAME? | H57: =+IF(G55<0,1-H55/G55,H55/G55-1) -> #NAME? | I57: =+IF(H55<0,1-I55/H55,I55/H55-1) -> #NAME? | J57: =+IF(I55<0,1-J55/I55,J55/I55-1) -> #NAME? | ... AE57: =+IF(AD55<0,1-AE55/AD55,AE55/AD55-1) -> #NAME? | AM57: =+IF(AI55<0,1-AM55/AI55,AM55/AI55-1) -> #NAME? | AN57: =+IF(AJ55<0,1-AN55/AJ55,AN55/AJ55-1) -> #NAME? | AO57: =+IF(AK55<0,1-AO55/AK55,AO55/AK55-1) -> #NAME? | AP57: =+IF(AL55<0,1-AP55/AL55,AP55/AL55-1) -> #NAME? | AQ57: =+IF(AM55<0,1-AQ55/AM55,AQ55/AM55-1) -> #NAME? | AR57: =+IF(AN55<0,1-AR55/AN55,AR55/AN55-1) -> #NAME? | AS57: =+IF(AO55<0,1-AS55/AO55,AS55/AO55-1) -> #NAME? | AT57: =+IF(AP55<0,1-AT55/AP55,AT55/AP55-1) -> #NAME? | ... CL57: =+IF(CH55<0,1-CL55/CH55,CL55/CH55-1) -> #NAME? | CM57: =+CM55/CI55-1 -> #NAME? | CN57: =+CN55/CJ55-1 -> #NAME? | CO57: =+CO55/CK55-1 -> #NAME? | CP57: =+CP55/CL55-1 -> #NAME? | CQ57: =+CQ55/CM55-1 -> #NAME? | CR57: =+CR55/CN55-1 -> #NAME? | CS57: =+CS55/CO55-1 -> #NAME? | CT57: =+CT55/CP55-1 -> #NAME? | ... DB57: =+DB55/CX55-1 -> #NAME? | DF57: 0.24774627
A58: PAT QOQ% | AJ58: =+IF(AI55<0,1-AJ55/AI55,AJ55/AI55-1) -> #NAME? | AK58: =+IF(AJ55<0,1-AK55/AJ55,AK55/AJ55-1) -> #NAME? | AL58: =+IF(AK55<0,1-AL55/AK55,AL55/AK55-1) -> #NAME? | AM58: =+IF(AL55<0,1-AM55/AL55,AM55/AL55-1) -> #NAME? | AN58: =+IF(AM55<0,1-AN55/AM55,AN55/AM55-1) -> #NAME? | AO58: =+IF(AN55<0,1-AO55/AN55,AO55/AN55-1) -> #NAME? | AP58: =+IF(AO55<0,1-AP55/AO55,AP55/AO55-1) -> #NAME? | AQ58: =+IF(AP55<0,1-AQ55/AP55,AQ55/AP55-1) -> #NAME? | ... CL58: =+IF(CK55<0,1-CL55/CK55,CL55/CK55-1) -> #NAME? | CM58: =+CM55/CL55-1 -> #NAME? | CN58: =+CN55/CM55-1 -> #NAME? | CO58: =+CO55/CN55-1 -> #NAME? | CP58: =+CP55/CO55-1 -> #NAME? | CQ58: =+CQ55/CP55-1 -> #NAME? | CR58: =+CR55/CQ55-1 -> #NAME? | CS58: =+CS55/CR55-1 -> #NAME? | CT58: =+CT55/CS55-1 -> #NAME? | ... DB58: =+DB55/DA55-1 -> #NAME?
A59: Minority Interest | B59: ='Annual Raw'!C32 -> #NAME? | C59: ='Annual Raw'!D32 -> #NAME? | D59: ='Annual Raw'!E32 -> #NAME? | E59: ='Annual Raw'!F32 -> #NAME? | F59: ='Annual Raw'!G32 -> #NAME? | G59: ='Annual Raw'!H32 -> #NAME? | H59: ='Annual Raw'!I32 -> #NAME? | I59: ='Annual Raw'!J32 -> #NAME? | ... AA59: ='Annual Raw'!AB32 -> #NAME? | AB59: =+SUM(CM59:CP59) -> #NAME? | AC59: =+SUM(CQ59:CT59) -> #NAME? | AD59: =+SUM(CU59:CX59) -> #NAME? | AE59: =+SUM(CY59:DB59) -> #NAME? | AI59: ='QTR Raw'!C34 -> #NAME? | AJ59: ='QTR Raw'!D34 -> #NAME? | AK59: ='QTR Raw'!E34 -> #NAME? | AL59: ='QTR Raw'!F34 -> #NAME? | AM59: ='QTR Raw'!G34 -> #NAME? | AN59: ='QTR Raw'!H34 -> #NAME? | AO59: ='QTR Raw'!I34 -> #NAME? | AP59: ='QTR Raw'!J34 -> #NAME? | ... CL59: ='QTR Raw'!BF34 -> #NAME? | CM59: =+CL59 -> #NAME? | CN59: =+CM59 -> #NAME? | CO59: =+CN59 -> #NAME? | CP59: =+CO59 -> #NAME? | CQ59: =+CP59 -> #NAME? | CR59: =+CQ59 -> #NAME? | CS59: =+CR59 -> #NAME? | CT59: =+CS59 -> #NAME? | ... DB59: =+DA59 -> #NAME? | DF59: 0
A60: Share of Associate | B60: ='Annual Raw'!C33+'Annual Raw'!C28 -> #NAME? | C60: ='Annual Raw'!D33+'Annual Raw'!D28 -> #NAME? | D60: ='Annual Raw'!E33+'Annual Raw'!E28 -> #NAME? | E60: ='Annual Raw'!F33+'Annual Raw'!F28 -> #NAME? | F60: ='Annual Raw'!G33+'Annual Raw'!G28 -> #NAME? | G60: ='Annual Raw'!H33+'Annual Raw'!H28 -> #NAME? | H60: ='Annual Raw'!I33+'Annual Raw'!I28 -> #NAME? | I60: ='Annual Raw'!J33+'Annual Raw'!J28 -> #NAME? | ... AA60: ='Annual Raw'!AB33+'Annual Raw'!AB28 -> #NAME? | AB60: =+SUM(CM60:CP60) -> #NAME? | AC60: =+SUM(CQ60:CT60) -> #NAME? | AD60: =+SUM(CU60:CX60) -> #NAME? | AE60: =+SUM(CY60:DB60) -> #NAME? | AI60: ='QTR Raw'!C35 -> #NAME? | AJ60: ='QTR Raw'!D35 -> #NAME? | AK60: ='QTR Raw'!E35 -> #NAME? | AL60: ='QTR Raw'!F35 -> #NAME? | AM60: ='QTR Raw'!G35 -> #NAME? | AN60: ='QTR Raw'!H35 -> #NAME? | AO60: ='QTR Raw'!I35 -> #NAME? | AP60: ='QTR Raw'!J35 -> #NAME? | ... CL60: ='QTR Raw'!BF35 -> #NAME? | CM60: =+CL60 -> #NAME? | CN60: =+CM60 -> #NAME? | CO60: =+CN60 -> #NAME? | CP60: =+CO60 -> #NAME? | CQ60: =+CP60 -> #NAME? | CR60: =+CQ60 -> #NAME? | CS60: =+CR60 -> #NAME? | CT60: =+CS60 -> #NAME? | ... DB60: =+DA60 -> #NAME? | DF60: 0
A61: Exceptional Income / Expenses | B61: ='Annual Raw'!C29+'Annual Raw'!C31+'Annual Raw'!C34+'Annual Raw'!C36 -> #NAME? | C61: ='Annual Raw'!D29+'Annual Raw'!D31+'Annual Raw'!D34+'Annual Raw'!D36 -> #NAME? | D61: ='Annual Raw'!E29+'Annual Raw'!E31+'Annual Raw'!E34+'Annual Raw'!E36 -> #NAME? | E61: ='Annual Raw'!F29+'Annual Raw'!F31+'Annual Raw'!F34+'Annual Raw'!F36 -> #NAME? | F61: ='Annual Raw'!G29+'Annual Raw'!G31+'Annual Raw'!G34+'Annual Raw'!G36 -> #NAME? | G61: ='Annual Raw'!H29+'Annual Raw'!H31+'Annual Raw'!H34+'Annual Raw'!H36 -> #NAME? | H61: ='Annual Raw'!I29+'Annual Raw'!I31+'Annual Raw'!I34+'Annual Raw'!I36 -> #NAME? | I61: ='Annual Raw'!J29+'Annual Raw'!J31+'Annual Raw'!J34+'Annual Raw'!J36 -> #NAME? | ... AA61: ='Annual Raw'!AB29+'Annual Raw'!AB31+'Annual Raw'!AB34+'Annual Raw'!AB36 -> #NAME? | AB61: =+SUM(CM61:CP61) -> 0 | AC61: =+SUM(CQ61:CT61) -> 0 | AD61: =+SUM(CU61:CX61) -> 0 | AE61: =+SUM(CY61:DB61) -> 0 | AI61: ='QTR Raw'!C26+'QTR Raw'!C31+'QTR Raw'!C32+'QTR Raw'!C33+'QTR Raw'!C36+'QTR Raw'!C37+'QTR Raw'!C39 -> #NAME? | AJ61: ='QTR Raw'!D26+'QTR Raw'!D31+'QTR Raw'!D32+'QTR Raw'!D33+'QTR Raw'!D36+'QTR Raw'!D37+'QTR Raw'!D39 -> #NAME? | AK61: ='QTR Raw'!E26+'QTR Raw'!E31+'QTR Raw'!E32+'QTR Raw'!E33+'QTR Raw'!E36+'QTR Raw'!E37+'QTR Raw'!E39 -> #NAME? | AL61: ='QTR Raw'!F26+'QTR Raw'!F31+'QTR Raw'!F32+'QTR Raw'!F33+'QTR Raw'!F36+'QTR Raw'!F37+'QTR Raw'!F39 -> #NAME? | AM61: ='QTR Raw'!G26+'QTR Raw'!G31+'QTR Raw'!G32+'QTR Raw'!G33+'QTR Raw'!G36+'QTR Raw'!G37+'QTR Raw'!G39 -> #NAME? | AN61: ='QTR Raw'!H26+'QTR Raw'!H31+'QTR Raw'!H32+'QTR Raw'!H33+'QTR Raw'!H36+'QTR Raw'!H37+'QTR Raw'!H39 -> #NAME? | AO61: ='QTR Raw'!I26+'QTR Raw'!I31+'QTR Raw'!I32+'QTR Raw'!I33+'QTR Raw'!I36+'QTR Raw'!I37+'QTR Raw'!I39 -> #NAME? | AP61: ='QTR Raw'!J26+'QTR Raw'!J31+'QTR Raw'!J32+'QTR Raw'!J33+'QTR Raw'!J36+'QTR Raw'!J37+'QTR Raw'!J39 -> #NAME? | ... CL61: ='QTR Raw'!BF26+'QTR Raw'!BF31+'QTR Raw'!BF32+'QTR Raw'!BF33+'QTR Raw'!BF36+'QTR Raw'!BF37+'QTR Raw'!BF39 -> #NAME? | DF61: 0
A62: Consolidated Net Profit | B62: =B55+B59+B60+B61 -> #NAME? | C62: =C55+C59+C60+C61 -> #NAME? | D62: =D55+D59+D60+D61 -> #NAME? | E62: =E55+E59+E60+E61 -> #NAME? | F62: =F55+F59+F60+F61 -> #NAME? | G62: =G55+G59+G60+G61 -> #NAME? | H62: =H55+H59+H60+H61 -> #NAME? | I62: =I55+I59+I60+I61 -> #NAME? | ... AE62: =AE55+AE59+AE60+AE61 -> #NAME? | AI62: =AI55+AI59+AI60+AI61 -> #NAME? | AJ62: =AJ55+AJ59+AJ60+AJ61 -> #NAME? | AK62: =AK55+AK59+AK60+AK61 -> #NAME? | AL62: =AL55+AL59+AL60+AL61 -> #NAME? | AM62: =AM55+AM59+AM60+AM61 -> #NAME? | AN62: =AN55+AN59+AN60+AN61 -> #NAME? | AO62: =AO55+AO59+AO60+AO61 -> #NAME? | AP62: =AP55+AP59+AP60+AP61 -> #NAME? | ... DB62: =DB55+DB59+DB60+DB61 -> #NAME? | DF62: 129.274
A63: Profit & Loss- Annual (End)
A65: Ace - PAT | B65: ='Annual Raw'!C35 -> #NAME? | C65: ='Annual Raw'!D35 -> #NAME? | D65: ='Annual Raw'!E35 -> #NAME? | E65: ='Annual Raw'!F35 -> #NAME? | F65: ='Annual Raw'!G35 -> #NAME? | G65: ='Annual Raw'!H35 -> #NAME? | H65: ='Annual Raw'!I35 -> #NAME? | I65: ='Annual Raw'!J35 -> #NAME? | ... AA65: ='Annual Raw'!AB35 -> #NAME? | AB65: =+AB62 -> #NAME? | AC65: =+AC62 -> #NAME? | AD65: =+AD62 -> #NAME? | AE65: =+AE62 -> #NAME? | AI65: ='QTR Raw'!C42 -> #NAME? | AJ65: ='QTR Raw'!D42 -> #NAME? | AK65: ='QTR Raw'!E42 -> #NAME? | AL65: ='QTR Raw'!F42 -> #NAME? | AM65: ='QTR Raw'!G42 -> #NAME? | AN65: ='QTR Raw'!H42 -> #NAME? | AO65: ='QTR Raw'!I42 -> #NAME? | AP65: ='QTR Raw'!J42 -> #NAME? | ... CG65: ='QTR Raw'!BA42 -> #NAME? | CH65: 18.4 | CI65: ='QTR Raw'!BC42 -> #NAME? | CJ65: ='QTR Raw'!BD42 -> #NAME? | CK65: ='QTR Raw'!BE42 -> #NAME? | CL65: ='QTR Raw'!BF42 -> #NAME? | DF65: 129.274
A66: Checksum - PAT | B66: =B65-B62 -> #NAME? | C66: =C65-C62 -> #NAME? | D66: =D65-D62 -> #NAME? | E66: =E65-E62 -> #NAME? | F66: =F65-F62 -> #NAME? | G66: =G65-G62 -> #NAME? | H66: =H65-H62 -> #NAME? | I66: =I65-I62 -> #NAME? | ... AE66: =AE65-AE62 -> #NAME? | AI66: =AI65-AI62 -> #NAME? | AJ66: =AJ65-AJ62 -> #NAME? | AK66: =AK65-AK62 -> #NAME? | AL66: =AL65-AL62 -> #NAME? | AM66: =AM65-AM62 -> #NAME? | AN66: =AN65-AN62 -> #NAME? | AO66: =AO65-AO62 -> #NAME? | AP66: =AP65-AP62 -> #NAME? | ... CL66: =CL65-CL62 -> #NAME? | DF66: 0
A67: Ratios (Start)
A68: ROE (%) | B68: =(B62-B61)/B134 -> #NAME? | C68: =(C62-C61)/C134 -> #NAME? | D68: =(D62-D61)/D134 -> #NAME? | E68: =(E62-E61)/E134 -> #NAME? | F68: =(F62-F61)/F134 -> #NAME? | G68: =(G62-G61)/G134 -> #NAME? | H68: =(H62-H61)/H134 -> #NAME? | I68: =(I62-I61)/I134 -> #NAME? | ... AE68: =(AE62-AE61)/AE134 -> #NAME? | AL68: =(SUM(AI62:AL62)-SUM(AI61:AL61))/AL134 -> #NAME? | AM68: =(SUM(AJ62:AM62)-SUM(AJ61:AM61))/AM134 -> #NAME? | AN68: =(SUM(AK62:AN62)-SUM(AK61:AN61))/AN134 -> #NAME? | AO68: =(SUM(AL62:AO62)-SUM(AL61:AO61))/AO134 -> #NAME? | AP68: =(SUM(AM62:AP62)-SUM(AM61:AP61))/AP134 -> #NAME? | AQ68: =(SUM(AN62:AQ62)-SUM(AN61:AQ61))/AQ134 -> #NAME? | AR68: =(SUM(AO62:AR62)-SUM(AO61:AR61))/AR134 -> #NAME? | AS68: =(SUM(AP62:AS62)-SUM(AP61:AS61))/AS134 -> #NAME? | ... DB68: =(SUM(CY62:DB62)-SUM(CY61:DB61))/DB134 -> #NAME? | DF68: 0.095891417
A69: ROCE (%) | B69: =+B48/B143 -> #NAME? | C69: =+C48/C143 -> #NAME? | D69: =+D48/D143 -> #NAME? | E69: =+E48/E143 -> #NAME? | F69: =+F48/F143 -> #NAME? | G69: =+G48/G143 -> #NAME? | H69: =+H48/H143 -> #NAME? | I69: =+I48/I143 -> #NAME? | ... AE69: =+AE48/AE143 -> #NAME? | AL69: =+SUM(AI48:AL48)/AL143 -> #NAME? | AM69: =+SUM(AJ48:AM48)/AM143 -> #NAME? | AN69: =+SUM(AK48:AN48)/AN143 -> #NAME? | AO69: =+SUM(AL48:AO48)/AO143 -> #NAME? | AP69: =+SUM(AM48:AP48)/AP143 -> #NAME? | AQ69: =+SUM(AN48:AQ48)/AQ143 -> #NAME? | AR69: =+SUM(AO48:AR48)/AR143 -> #NAME? | AS69: =+SUM(AP48:AS48)/AS143 -> #NAME? | ... DB69: =+SUM(CY48:DB48)/DB143 -> #NAME? | DF69: 0.16186797
A70: Ratios (End)
A71: Checksum Of qtr to Annual
A72: Revenue - Checksum Of qtr to Annual | N72: =N24-SUM(AI24:AL24) -> #NAME? | O72: =O24-SUM(AM24:AP24) -> #NAME? | P72: =P24-SUM(AQ24:AT24) -> #NAME? | Q72: =Q24-SUM(AU24:AX24) -> #NAME? | R72: =R24-SUM(AY24:BB24) -> #NAME? | S72: =S24-SUM(BC24:BF24) -> #NAME? | T72: =T24-SUM(BG24:BJ24) -> #NAME? | U72: =U24-SUM(BK24:BN24) -> #NAME? | V72: =V24-SUM(BO24:BR24) -> #NAME? | W72: =W24-SUM(BS24:BV24) -> #NAME? | X72: =X24-SUM(BW24:BZ24) -> #NAME? | Y72: =Y24-SUM(CA24:CD24) -> #NAME? | Z72: =Z24-SUM(CE24:CH24) -> #NAME? | AA72: =AA24-SUM(CF24:CI24) -> #NAME? | AB72: =AB24-SUM(CM24:CP24) -> #NAME? | AC72: =AC24-SUM(CQ24:CT24) -> #NAME? | AD72: =AD24-SUM(CU24:CX24) -> #NAME? | AE72: =AE24-SUM(CY24:DB24) -> #NAME? | DF72: 0
A73: GP - Checksum Of qtr to Annual | N73: =N30-SUM(AI30:AL30) -> #NAME? | O73: =O30-SUM(AM30:AP30) -> #NAME? | P73: =P30-SUM(AQ30:AT30) -> #NAME? | Q73: =Q30-SUM(AU30:AX30) -> #NAME? | R73: =R30-SUM(AY30:BB30) -> #NAME? | S73: =S30-SUM(BC30:BF30) -> #NAME? | T73: =T30-SUM(BG30:BJ30) -> #NAME? | U73: =U30-SUM(BK30:BN30) -> #NAME? | V73: =V30-SUM(BO30:BR30) -> #NAME? | W73: =W30-SUM(BS30:BV30) -> #NAME? | X73: =X30-SUM(BW30:BZ30) -> #NAME? | Y73: =Y30-SUM(CA30:CD30) -> #NAME? | Z73: =Z30-SUM(CE30:CH30) -> #NAME? | AA73: =AA30-SUM(CF30:CI30) -> #NAME? | AB73: =AB30-SUM(CM30:CP30) -> #NAME? | AC73: =AC30-SUM(CQ30:CT30) -> #NAME? | AD73: =AD30-SUM(CU30:CX30) -> #NAME? | AE73: =AE30-SUM(CY30:DB30) -> #NAME? | DF73: 0
A74: EBITDA - Checksum Of qtr to Annual | N74: =N42-SUM(AI42:AL42) -> #NAME? | O74: =O42-SUM(AM42:AP42) -> #NAME? | P74: =P42-SUM(AQ42:AT42) -> #NAME? | Q74: =Q42-SUM(AU42:AX42) -> #NAME? | R74: =R42-SUM(AY42:BB42) -> #NAME? | S74: =S42-SUM(BC42:BF42) -> #NAME? | T74: =T42-SUM(BG42:BJ42) -> #NAME? | U74: =U42-SUM(BK42:BN42) -> #NAME? | V74: =V42-SUM(BO42:BR42) -> #NAME? | W74: =W42-SUM(BS42:BV42) -> #NAME? | X74: =X42-SUM(BW42:BZ42) -> #NAME? | Y74: =Y42-SUM(CA42:CD42) -> #NAME? | Z74: =Z42-SUM(CE42:CH42) -> #NAME? | AA74: =AA42-SUM(CF42:CI42) -> #NAME? | AB74: =AB42-SUM(CM42:CP42) -> #NAME? | AC74: =AC42-SUM(CQ42:CT42) -> #NAME? | AD74: =AD42-SUM(CU42:CX42) -> #NAME? | AE74: =AE42-SUM(CY42:DB42) -> #NAME? | DF74: 0
A75: PAT - Checksum Of qtr to Annual | N75: =N62-SUM(AI62:AL62) -> #NAME? | O75: =O62-SUM(AM62:AP62) -> #NAME? | P75: =P62-SUM(AQ62:AT62) -> #NAME? | Q75: =Q62-SUM(AU62:AX62) -> #NAME? | R75: =R62-SUM(AY62:BB62) -> #NAME? | S75: =S62-SUM(BC62:BF62) -> #NAME? | T75: =T62-SUM(BG62:BJ62) -> #NAME? | U75: =U62-SUM(BK62:BN62) -> #NAME? | V75: =V62-SUM(BO62:BR62) -> #NAME? | W75: =W55-SUM(BS55:BV55) -> #NAME? | X75: =X55-SUM(BW55:BZ55) -> #NAME? | Y75: =Y55-SUM(CA55:CD55) -> #NAME? | Z75: =Z55-SUM(CE55:CH55) -> #NAME? | AA75: =AA55-SUM(CF55:CI55) -> #NAME? | AB75: =AB55-SUM(CM55:CP55) -> #NAME? | AC75: =AC55-SUM(CQ55:CT55) -> #NAME? | AD75: =AD55-SUM(CU55:CX55) -> #NAME? | AE75: =AE55-SUM(CY55:DB55) -> #NAME? | DF75: 0
A76: Valuation (Start)
A77: Eq | B77: ='Annual Raw'!C104 -> #NAME? | C77: ='Annual Raw'!D104 -> #NAME? | D77: ='Annual Raw'!E104 -> #NAME? | E77: =+F77 -> 31.363 | F77: =+G77 -> 31.363 | G77: =+H77 -> 31.363 | H77: =+I77 -> 31.363 | I77: =+J77 -> 31.363 | J77: =+K77 -> 31.363 | K77: =+L77 -> 31.363 | L77: =+M77 -> 31.363 | ... AA77: =+AB77 -> 31.363 | AB77: =AA77 -> 31.363 | AC77: =AB77 -> 31.363 | AD77: =AC77 -> 31.363 | AE77: =AD77 -> 31.363 | AI77: =+AJ77 -> #NAME? | AJ77: =+AK77 -> #NAME? | AK77: =+AL77 -> #NAME? | AL77: =+AM77 -> #NAME? | AM77: =+AN77 -> #NAME? | AN77: =+AO77 -> #NAME? | AO77: =+AP77 -> #NAME? | AP77: =+AQ77 -> #NAME? | ... CI77: =+CJ77 -> #NAME? | CJ77: ='QTR Raw'!BD45 -> #NAME? | CK77: ='QTR Raw'!BE45 -> #NAME? | CL77: ='QTR Raw'!BF45 -> #NAME? | CM77: =+CL77 -> #NAME? | CN77: =+CM77 -> #NAME? | CO77: =+CN77 -> #NAME? | CP77: =+CO77 -> #NAME? | CQ77: =+CP77 -> #NAME? | CR77: =+CQ77 -> #NAME? | CS77: =+CR77 -> #NAME? | CT77: =+CS77 -> #NAME? | ... DB77: =+DA77 -> #NAME? | DF77: 31.363
A78: FV | B78: ='Annual Raw'!C105 -> #NAME? | C78: ='Annual Raw'!D105 -> #NAME? | D78: ='Annual Raw'!E105 -> #NAME? | E78: =+F78 -> 5 | F78: =+G78 -> 5 | G78: =+H78 -> 5 | H78: =+I78 -> 5 | I78: =+J78 -> 5 | J78: =+K78 -> 5 | K78: =+L78 -> 5 | L78: =+M78 -> 5 | ... AA78: =+AB78 -> 5 | AB78: =AA78 -> 5 | AC78: =AB78 -> 5 | AD78: =AC78 -> 5 | AE78: =AD78 -> 5 | AI78: =AJ78 -> #NAME? | AJ78: =AK78 -> #NAME? | AK78: =AL78 -> #NAME? | AL78: =AM78 -> #NAME? | AM78: =AN78 -> #NAME? | AN78: =AO78 -> #NAME? | AO78: =AP78 -> #NAME? | AP78: =AQ78 -> #NAME? | ... CI78: =CJ78 -> #NAME? | CJ78: ='QTR Raw'!BD46 -> #NAME? | CK78: ='QTR Raw'!BE46 -> #NAME? | CL78: ='QTR Raw'!BF46 -> #NAME? | CM78: =+CL78 -> #NAME? | CN78: =+CM78 -> #NAME? | CO78: =+CN78 -> #NAME? | CP78: =+CO78 -> #NAME? | CQ78: =+CP78 -> #NAME? | CR78: =+CQ78 -> #NAME? | CS78: =+CR78 -> #NAME? | CT78: =+CS78 -> #NAME? | ... DB78: =+DA78 -> #NAME? | DF78: 5
A79: No of share | B79: =B77/B78 -> #NAME? | C79: =C77/C78 -> #NAME? | D79: =D77/D78 -> #NAME? | E79: =E77/E78 -> 6.2726 | F79: =F77/F78 -> 6.2726 | G79: =G77/G78 -> 6.2726 | H79: =H77/H78 -> 6.2726 | I79: =I77/I78 -> 6.2726 | ... AE79: =AE77/AE78 -> 6.2726 | AI79: =AI77/AI78 -> #NAME? | AJ79: =AJ77/AJ78 -> #NAME? | AK79: =AK77/AK78 -> #NAME? | AL79: =AL77/AL78 -> #NAME? | AM79: =AM77/AM78 -> #NAME? | AN79: =AN77/AN78 -> #NAME? | AO79: =AO77/AO78 -> #NAME? | AP79: =AP77/AP78 -> #NAME? | ... DB79: =DB77/DB78 -> #NAME? | DF79: 6.2726
A80: EPS | B80: =(B62-B61)/B79 -> #NAME? | C80: =(C62-C61)/C79 -> #NAME? | D80: =(D62-D61)/D79 -> #NAME? | E80: =(E62-E61)/E79 -> 0 | F80: =(F62-F61)/F79 -> 0 | G80: =(G62-G61)/G79 -> 0 | H80: =(H62-H61)/H79 -> 0 | I80: =(I62-I61)/I79 -> 1.8913643 | ... AE80: =(AE62-AE61)/AE79 -> 58.491781 | AI80: =(AI62-AI61)/AI79 -> #NAME? | AJ80: =(AJ62-AJ61)/AJ79 -> #NAME? | AK80: =(AK62-AK61)/AK79 -> #NAME? | AL80: =(AL62-AL61)/AL79 -> #NAME? | AM80: =(AM62-AM61)/AM79 -> #NAME? | AN80: =(AN62-AN61)/AN79 -> #NAME? | AO80: =(AO62-AO61)/AO79 -> #NAME? | AP80: =(AP62-AP61)/AP79 -> #NAME? | ... DB80: =(DB62-DB61)/DB79 -> #NAME? | DF80: 20.609317
A81: DPS | B81: ='Annual Raw'!C110 -> #NAME? | C81: ='Annual Raw'!D110 -> #NAME? | D81: ='Annual Raw'!E110 -> #NAME? | E81: ='Annual Raw'!F110 -> #NAME? | F81: ='Annual Raw'!G110 -> #NAME? | G81: ='Annual Raw'!H110 -> #NAME? | H81: ='Annual Raw'!I110 -> #NAME? | I81: ='Annual Raw'!J110 -> #NAME? | ... AA81: ='Annual Raw'!AB110 -> #NAME?
A82: DPS % of EPS | B82: =B81/B80 -> #NAME? | C82: =C81/C80 -> #NAME? | D82: =D81/D80 -> #NAME? | E82: =E81/E80 -> #DIV/0! | F82: =F81/F80 -> #DIV/0! | G82: =G81/G80 -> #DIV/0! | H82: =H81/H80 -> #DIV/0! | I82: =I81/I80 -> 0 | ... AE82: =AE81/AE80 -> 0 | DF82: 0
A83: EPS TTM | B83: =+B80 -> #NAME? | C83: =+C80 -> #NAME? | D83: =+D80 -> #NAME? | E83: =+E80 -> 0 | F83: =+F80 -> 0 | G83: =+G80 -> 0 | H83: =+H80 -> 0 | I83: =+I80 -> 1.8913643 | ... AE83: =+AE80 -> 58.491781 | AL83: =SUM(AI80:AL80) -> #NAME? | AM83: =SUM(AJ80:AM80) -> #NAME? | AN83: =SUM(AK80:AN80) -> #NAME? | AO83: =SUM(AL80:AO80) -> #NAME? | AP83: =SUM(AM80:AP80) -> #NAME? | AQ83: =SUM(AN80:AQ80) -> #NAME? | AR83: =SUM(AO80:AR80) -> #NAME? | AS83: =SUM(AP80:AS80) -> #NAME? | ... DB83: =SUM(CY80:DB80) -> #NAME? | DF83: 20.609317
A84: EPS Growth YoY % | C84: =+C83/B83-1 -> #NAME? | D84: =+D83/C83-1 -> #NAME? | E84: =+E83/D83-1 -> #DIV/0! | F84: =+F83/E83-1 -> #DIV/0! | G84: =+G83/F83-1 -> #DIV/0! | H84: =+H83/G83-1 -> #DIV/0! | I84: =+I83/H83-1 -> #DIV/0! | J84: =+J83/I83-1 -> -2.4713716 | ... AE84: =+AE83/AD83-1 -> 0.25776529 | AP84: =+IF(AL83<0,1-AP83/AL83,AP83/AL83-1) -> #NAME? | AQ84: =+IF(AM83<0,1-AQ83/AM83,AQ83/AM83-1) -> #NAME? | AR84: =+IF(AN83<0,1-AR83/AN83,AR83/AN83-1) -> #NAME? | AS84: =+IF(AO83<0,1-AS83/AO83,AS83/AO83-1) -> #NAME? | AT84: =+IF(AP83<0,1-AT83/AP83,AT83/AP83-1) -> #NAME? | AU84: =+IF(AQ83<0,1-AU83/AQ83,AU83/AQ83-1) -> #NAME? | AV84: =+IF(AR83<0,1-AV83/AR83,AV83/AR83-1) -> #NAME? | AW84: =+IF(AS83<0,1-AW83/AS83,AW83/AS83-1) -> #NAME? | ... DB84: =+IF(CX83<0,1-DB83/CX83,DB83/CX83-1) -> #NAME? | DF84: 0.24774627
A85: Bloomberg Estimate
A86: Estimate deviation
A87: Promoter Share holding % | B87: ='Annual Raw'!C112 -> #NAME? | C87: ='Annual Raw'!D112 -> #NAME? | D87: ='Annual Raw'!E112 -> #NAME? | E87: ='Annual Raw'!F112 -> #NAME? | F87: ='Annual Raw'!G112 -> #NAME? | G87: ='Annual Raw'!H112 -> #NAME? | H87: ='Annual Raw'!I112 -> #NAME? | I87: ='Annual Raw'!J112 -> #NAME? | ... AA87: ='Annual Raw'!AB112 -> #NAME? | AI87: ='QTR Raw'!C49 -> #NAME? | AJ87: ='QTR Raw'!D49 -> #NAME? | AK87: ='QTR Raw'!E49 -> #NAME? | AL87: ='QTR Raw'!F49 -> #NAME? | AM87: ='QTR Raw'!G49 -> #NAME? | AN87: ='QTR Raw'!H49 -> #NAME? | AO87: ='QTR Raw'!I49 -> #NAME? | AP87: ='QTR Raw'!J49 -> #NAME? | ... CL87: ='QTR Raw'!BF49 -> #NAME?
A88: Pledge Share % | B88: ='Annual Raw'!C113 -> #NAME? | C88: ='Annual Raw'!D113 -> #NAME? | D88: ='Annual Raw'!E113 -> #NAME? | E88: ='Annual Raw'!F113 -> #NAME? | F88: ='Annual Raw'!G113 -> #NAME? | G88: ='Annual Raw'!H113 -> #NAME? | H88: ='Annual Raw'!I113 -> #NAME? | I88: ='Annual Raw'!J113 -> #NAME? | ... AA88: ='Annual Raw'!AB113 -> #NAME? | AI88: ='QTR Raw'!C50 -> #NAME? | AJ88: ='QTR Raw'!D50 -> #NAME? | AK88: ='QTR Raw'!E50 -> #NAME? | AL88: ='QTR Raw'!F50 -> #NAME? | AM88: ='QTR Raw'!G50 -> #NAME? | AN88: ='QTR Raw'!H50 -> #NAME? | AO88: ='QTR Raw'!I50 -> #NAME? | AP88: ='QTR Raw'!J50 -> #NAME? | ... CL88: ='QTR Raw'!BF50 -> #NAME?
A90: Share Price
A91: Share Price - Close | B91: ='Annual Raw'!C106 -> #NAME? | C91: ='Annual Raw'!D106 -> #NAME? | D91: ='Annual Raw'!E106 -> #NAME? | E91: ='Annual Raw'!F106 -> #NAME? | F91: ='Annual Raw'!G106 -> #NAME? | G91: ='Annual Raw'!H106 -> #NAME? | H91: ='Annual Raw'!I106 -> #NAME? | I91: ='Annual Raw'!J106 -> #NAME? | ... AA91: ='Annual Raw'!AB106 -> #NAME? | AB91: =+CP91 -> 575 | AC91: =+CT91 -> 575 | AD91: =+CX91 -> 575 | AE91: =+DB91 -> 575 | AJ91: ='QTR Share Price'!HP21 -> #NAME? | AK91: ='QTR Share Price'!HQ21 -> #NAME? | AL91: ='QTR Share Price'!HR21 -> #NAME? | AM91: ='QTR Share Price'!HS21 -> #NAME? | AN91: ='QTR Share Price'!HT21 -> #NAME? | AO91: ='QTR Share Price'!HU21 -> #NAME? | AP91: ='QTR Share Price'!HV21 -> #NAME? | AQ91: ='QTR Share Price'!HW21 -> #NAME? | ... CL91: ='QTR Share Price'!JR21 -> #NAME? | CM91: 575 | CN91: =+CM91 -> 575 | CO91: =+CN91 -> 575 | CP91: =+CO91 -> 575 | CQ91: =+CP91 -> 575 | CR91: =+CQ91 -> 575 | CS91: =+CR91 -> 575 | CT91: =+CS91 -> 575 | CU91: =+CT91 -> 575 | ... DB91: =+DA91 -> 575 | DF91: 417.7
A92: Share Price - High | B92: ='Annual Raw'!C107 -> #NAME? | C92: ='Annual Raw'!D107 -> #NAME? | D92: ='Annual Raw'!E107 -> #NAME? | E92: ='Annual Raw'!F107 -> #NAME? | F92: ='Annual Raw'!G107 -> #NAME? | G92: ='Annual Raw'!H107 -> #NAME? | H92: ='Annual Raw'!I107 -> #NAME? | I92: ='Annual Raw'!J107 -> #NAME? | ... AA92: ='Annual Raw'!AB107 -> #NAME? | AB92: =+MAX(CM92:CP92) -> #NAME? | AC92: =+MAX(CQ92:CT92) -> #NAME? | AD92: =+MAX(CU92:CX92) -> #NAME? | AE92: =+MAX(CY92:DB92) -> #NAME? | AJ92: ='QTR Share Price'!HP19 -> #NAME? | AK92: ='QTR Share Price'!HQ19 -> #NAME? | AL92: ='QTR Share Price'!HR19 -> #NAME? | AM92: ='QTR Share Price'!HS19 -> #NAME? | AN92: ='QTR Share Price'!HT19 -> #NAME? | AO92: ='QTR Share Price'!HU19 -> #NAME? | AP92: ='QTR Share Price'!HV19 -> #NAME? | AQ92: ='QTR Share Price'!HW19 -> #NAME? | ... CL92: ='QTR Share Price'!JR19 -> #NAME? | CM92: =+CM83*CM100 -> #NAME? | CN92: =+CN83*CN100 -> #NAME? | CO92: =+CO83*CO100 -> #NAME? | CP92: =+CP83*CP100 -> #NAME? | CQ92: =+CQ83*CQ100 -> #NAME? | CR92: =+CR83*CR100 -> #NAME? | CS92: =+CS83*CS100 -> #NAME? | CT92: =+CT83*CT100 -> #NAME? | ... DB92: =+DB83*DB100 -> #NAME? | DF92: 795.1
A93: Share Price - Low | B93: ='Annual Raw'!C108 -> #NAME? | C93: ='Annual Raw'!D108 -> #NAME? | D93: ='Annual Raw'!E108 -> #NAME? | E93: ='Annual Raw'!F108 -> #NAME? | F93: ='Annual Raw'!G108 -> #NAME? | G93: ='Annual Raw'!H108 -> #NAME? | H93: ='Annual Raw'!I108 -> #NAME? | I93: ='Annual Raw'!J108 -> #NAME? | ... AA93: ='Annual Raw'!AB108 -> #NAME? | AB93: =+MIN(CM93:CP93) -> #NAME? | AC93: =+MIN(CQ93:CT93) -> #NAME? | AD93: =+MIN(CU93:CX93) -> #NAME? | AE93: =+MIN(CY93:DB93) -> #NAME? | AJ93: =+'QTR Share Price'!HP20 -> #NAME? | AK93: =+'QTR Share Price'!HQ20 -> #NAME? | AL93: =+'QTR Share Price'!HR20 -> #NAME? | AM93: =+'QTR Share Price'!HS20 -> #NAME? | AN93: =+'QTR Share Price'!HT20 -> #NAME? | AO93: =+'QTR Share Price'!HU20 -> #NAME? | AP93: =+'QTR Share Price'!HV20 -> #NAME? | AQ93: =+'QTR Share Price'!HW20 -> #NAME? | ... CL93: =+'QTR Share Price'!JR20 -> #NAME? | CM93: =+CM101*CM83 -> #NAME? | CN93: =+CN101*CN83 -> #NAME? | CO93: =+CO101*CO83 -> #NAME? | CP93: =+CP101*CP83 -> #NAME? | CQ93: =+CQ101*CQ83 -> #NAME? | CR93: =+CR101*CR83 -> #NAME? | CS93: =+CS101*CS83 -> #NAME? | CT93: =+CT101*CT83 -> #NAME? | ... DB93: =+DB101*DB83 -> #NAME? | DF93: 0
A95: Upside (%) | AB95: =+AB92/AB91-1 -> #NAME? | AC95: =+AC92/AC91-1 -> #NAME? | AD95: =+AD92/AD91-1 -> #NAME? | AE95: =+AE92/AE91-1 -> #NAME? | CM95: =+CM92/CM91-1 -> #NAME? | CN95: =+CN92/CN91-1 -> #NAME? | CO95: =+CO92/CO91-1 -> #NAME? | CP95: =+CP92/CP91-1 -> #NAME? | CQ95: =+CQ92/CQ91-1 -> #NAME? | CR95: =+CR92/CR91-1 -> #NAME? | CS95: =+CS92/CS91-1 -> #NAME? | CT95: =+CT92/CT91-1 -> #NAME? | ... DB95: =+DB92/DB91-1 -> #NAME? | DF95: 0.90351927
A96: Downside (%) | AB96: =+AB93/AB91-1 -> #NAME? | AC96: =+AC93/AC91-1 -> #NAME? | AD96: =+AD93/AD91-1 -> #NAME? | AE96: =+AE93/AE91-1 -> #NAME? | CM96: =+CM93/CM91-1 -> #NAME? | CN96: =+CN93/CN91-1 -> #NAME? | CO96: =+CO93/CO91-1 -> #NAME? | CP96: =+CP93/CP91-1 -> #NAME? | CQ96: =+CQ93/CQ91-1 -> #NAME? | CR96: =+CR93/CR91-1 -> #NAME? | CS96: =+CS93/CS91-1 -> #NAME? | CT96: =+CT93/CT91-1 -> #NAME? | ... DB96: =+DB93/DB91-1 -> #NAME? | DF96: -1
A98: PE
A99: PE - Close | B99: =+B91/B83 -> #NAME? | C99: =+C91/C83 -> #NAME? | D99: =+D91/D83 -> #NAME? | E99: =+E91/E83 -> #DIV/0! | F99: =+F91/F83 -> #DIV/0! | G99: =+G91/G83 -> #DIV/0! | H99: =+H91/H83 -> #DIV/0! | I99: =+I91/I83 -> 0 | ... AE99: =+AE91/AE83 -> 9.8304409 | AL99: =+AL91/AL83 -> #NAME? | AM99: =+AM91/AM83 -> #NAME? | AN99: =+AN91/AN83 -> #NAME? | AO99: =+AO91/AO83 -> #NAME? | AP99: =+AP91/AP83 -> #NAME? | AQ99: =+AQ91/AQ83 -> #NAME? | AR99: =+AR91/AR83 -> #NAME? | AS99: =+AS91/AS83 -> #NAME? | ... DB99: =+DB91/DB83 -> #NAME? | DF99: 20.267533
A100: PE - High | B100: =+B92/B83 -> #NAME? | C100: =+C92/C83 -> #NAME? | D100: =+D92/D83 -> #NAME? | E100: =+E92/E83 -> #DIV/0! | F100: =+F92/F83 -> #DIV/0! | G100: =+G92/G83 -> #DIV/0! | H100: =+H92/H83 -> #DIV/0! | I100: =+I92/I83 -> 0 | ... AE100: =+AE92/AE83 -> 25 | AL100: =+AL92/AL83 -> #NAME? | AM100: =+AM92/AM83 -> #NAME? | AN100: =+AN92/AN83 -> #NAME? | AO100: =+AO92/AO83 -> #NAME? | AP100: =+AP92/AP83 -> #NAME? | AQ100: =+AQ92/AQ83 -> #NAME? | AR100: =+AR92/AR83 -> #NAME? | AS100: =+AS92/AS83 -> #NAME? | ... CL100: =+CL92/CL83 -> #NAME? | CM100: 25 | CN100: =+CM100 -> 25 | CO100: =+CN100 -> 25 | CP100: =+CO100 -> 25 | CQ100: =+CP100 -> 25 | CR100: =+CQ100 -> 25 | CS100: =+CR100 -> 25 | CT100: =+CS100 -> 25 | CU100: =+CT100 -> 25 | ... DB100: =+DA100 -> 25 | DF100: 38.579639
A101: PE - Low | B101: =+B93/B83 -> #NAME? | C101: =+C93/C83 -> #NAME? | D101: =+D93/D83 -> #NAME? | E101: =+E93/E83 -> #DIV/0! | F101: =+F93/F83 -> #DIV/0! | G101: =+G93/G83 -> #DIV/0! | H101: =+H93/H83 -> #DIV/0! | I101: =+I93/I83 -> 0 | ... AE101: =+AE93/AE83 -> 16.855301 | AL101: =+AL93/AL83 -> #NAME? | AM101: =+AM93/AM83 -> #NAME? | AN101: =+AN93/AN83 -> #NAME? | AO101: =+AO93/AO83 -> #NAME? | AP101: =+AP93/AP83 -> #NAME? | AQ101: =+AQ93/AQ83 -> #NAME? | AR101: =+AR93/AR83 -> #NAME? | AS101: =+AS93/AS83 -> #NAME? | ... CL101: =+CL93/CL83 -> #NAME? | CM101: =+CL101 -> #NAME? | CN101: =+CM101 -> #NAME? | CO101: =+CN101 -> #NAME? | CP101: =+CO101 -> #NAME? | CQ101: =+CP101 -> #NAME? | CR101: =+CQ101 -> #NAME? | CS101: =+CR101 -> #NAME? | CT101: =+CS101 -> #NAME? | ... DB101: =+DA101 -> #NAME? | DF101: 0
A103: PE - 1Yr Fwd | B103: =+B92/C83 -> #NAME? | C103: =+C92/D83 -> #NAME? | D103: =+D92/E83 -> #DIV/0! | E103: =+E92/F83 -> #DIV/0! | F103: =+F92/G83 -> #DIV/0! | G103: =+G92/H83 -> #DIV/0! | H103: =+H92/I83 -> 0 | I103: =+I92/J83 -> 0 | ... AD103: =+AD92/AE83 -> 19.876522 | AL103: =+AL92/AP83 -> #NAME? | AM103: =+AM92/AQ83 -> #NAME? | AN103: =+AN92/AR83 -> #NAME? | AO103: =+AO92/AS83 -> #NAME? | AP103: =+AP92/AT83 -> #NAME? | AQ103: =+AQ92/AU83 -> #NAME? | AR103: =+AR92/AV83 -> #NAME? | AS103: =+AS92/AW83 -> #NAME? | ... CL103: =+CL92/CP83 -> #NAME? | DF103: 29.24878
A104: Correlation | AO104: =+CORREL(AL83:AO83,AL100:AO100) -> #NAME? | AP104: =+CORREL(AM83:AP83,AM100:AP100) -> #NAME? | AQ104: =+CORREL(AN83:AQ83,AN100:AQ100) -> #NAME? | AR104: =+CORREL(AO83:AR83,AO100:AR100) -> #NAME? | AS104: =+CORREL(AP83:AS83,AP100:AS100) -> #NAME? | AT104: =+CORREL(AQ83:AT83,AQ100:AT100) -> #NAME? | AU104: =+CORREL(AR83:AU83,AR100:AU100) -> #NAME? | AV104: =+CORREL(AS83:AV83,AS100:AV100) -> #NAME? | ... CL104: =+CORREL(CI83:CL83,CI100:CL100) -> #NAME?
A106: BVPS | E106: =+E$134/E$79 -> 0 | F106: =+F$134/F$79 -> 0 | G106: =+G$134/G$79 -> 0 | H106: =+H$134/H$79 -> 0 | I106: =+I$134/I$79 -> 4.2722817 | J106: =+J$134/J$79 -> 10.54333 | K106: =+K$134/K$79 -> 11.416664 | L106: =+L$134/L$79 -> 12.547875 | ... AE106: =+AE$134/AE$79 -> 383.37383 | AL106: =+AL$134/AL$79 -> #NAME? | AM106: =+AM$134/AM$79 -> #NAME? | AN106: =+AN$134/AN$79 -> #NAME? | AO106: =+AO$134/AO$79 -> #NAME? | AP106: =+AP$134/AP$79 -> #NAME? | AQ106: =+AQ$134/AQ$79 -> #NAME? | AR106: =+AR$134/AR$79 -> #NAME? | AS106: =+AS$134/AS$79 -> #NAME? | ... DB106: =+DB$134/DB$79 -> #NAME? | DF106: 214.92348
A107: PB
A108: PB - Close | E108: =+E91/E$106 -> #DIV/0! | F108: =+F91/F$106 -> #DIV/0! | G108: =+G91/G$106 -> #DIV/0! | H108: =+H91/H$106 -> #DIV/0! | I108: =+I91/I$106 -> 0 | J108: =+J91/J$106 -> 0 | K108: =+K91/K$106 -> 0 | L108: =+L91/L$106 -> 0 | ... AE108: =+AE91/AE$106 -> 1.4998415 | AL108: =+AL91/AL$106 -> #NAME? | AM108: =+AM91/AM$106 -> #NAME? | AN108: =+AN91/AN$106 -> #NAME? | AO108: =+AO91/AO$106 -> #NAME? | AP108: =+AP91/AP$106 -> #NAME? | AQ108: =+AQ91/AQ$106 -> #NAME? | AR108: =+AR91/AR$106 -> #NAME? | AS108: =+AS91/AS$106 -> #NAME? | ... DB108: =+DB91/DB$106 -> #NAME? | DF108: 1.9434824
A109: PB - High | E109: =+E92/E$106 -> #DIV/0! | F109: =+F92/F$106 -> #DIV/0! | G109: =+G92/G$106 -> #DIV/0! | H109: =+H92/H$106 -> #DIV/0! | I109: =+I92/I$106 -> 0 | J109: =+J92/J$106 -> 0 | K109: =+K92/K$106 -> 0 | L109: =+L92/L$106 -> 0 | ... AE109: =+AE92/AE$106 -> 3.8142784 | AL109: =+AL92/AL$106 -> #NAME? | AM109: =+AM92/AM$106 -> #NAME? | AN109: =+AN92/AN$106 -> #NAME? | AO109: =+AO92/AO$106 -> #NAME? | AP109: =+AP92/AP$106 -> #NAME? | AQ109: =+AQ92/AQ$106 -> #NAME? | AR109: =+AR92/AR$106 -> #NAME? | AS109: =+AS92/AS$106 -> #NAME? | ... CL109: =+CL92/CL$106 -> #NAME? | CM109: =+CL109 -> #NAME? | CN109: =+CM109 -> #NAME? | CO109: =+CN109 -> #NAME? | CP109: =+CO109 -> #NAME? | CQ109: =+CP109 -> #NAME? | CR109: =+CQ109 -> #NAME? | CS109: =+CR109 -> #NAME? | CT109: =+CS109 -> #NAME? | ... DB109: =+DA109 -> #NAME? | DF109: 3.6994563
A110: PB - Low | E110: =+E93/E$106 -> #DIV/0! | F110: =+F93/F$106 -> #DIV/0! | G110: =+G93/G$106 -> #DIV/0! | H110: =+H93/H$106 -> #DIV/0! | I110: =+I93/I$106 -> 0 | J110: =+J93/J$106 -> 0 | K110: =+K93/K$106 -> 0 | L110: =+L93/L$106 -> 0 | ... AE110: =+AE93/AE$106 -> 2.5716324 | AL110: =+AL93/AL$106 -> #NAME? | AM110: =+AM93/AM$106 -> #NAME? | AN110: =+AN93/AN$106 -> #NAME? | AO110: =+AO93/AO$106 -> #NAME? | AP110: =+AP93/AP$106 -> #NAME? | AQ110: =+AQ93/AQ$106 -> #NAME? | AR110: =+AR93/AR$106 -> #NAME? | AS110: =+AS93/AS$106 -> #NAME? | ... CL110: =+CL93/CL$106 -> #NAME? | CM110: =+CL110 -> #NAME? | CN110: =+CM110 -> #NAME? | CO110: =+CN110 -> #NAME? | CP110: =+CO110 -> #NAME? | CQ110: =+CP110 -> #NAME? | CR110: =+CQ110 -> #NAME? | CS110: =+CR110 -> #NAME? | CT110: =+CS110 -> #NAME? | ... DB110: =+DA110 -> #NAME? | DF110: 0
...

Sheet QTR Raw
A1: ='Annual Raw'!A1 -> 226159 | B1: X | C1: 201206 | D1: 201209 | E1: 201212 | F1: 201303 | G1: 201306 | H1: 201309 | I1: 201312 | J1: 201403 | K1: 201406 | L1: 201409 | M1: 201412 | N1: 201503 | O1: 201506 | P1: 201509 | Q1: 201512 | R1: 201603 | S1: 201606 | T1: 201609 | U1: 201612 | V1: 201703 | W1: 201706 | X1: 201709 | Y1: 201712 | Z1: 201803 | AA1: 201806 | AB1: 201809 | AC1: 201812 | AD1: 201903 | AE1: 201906 | AF1: 201909 | AG1: 201912 | AH1: 202003 | AI1: 202006 | AJ1: 202009 | AK1: 202012 | AL1: 202103 | AM1: 202106 | AN1: 202109 | AO1: 202112 | AP1: 202203 | AQ1: 202206 | AR1: 202209 | AS1: 202212 | AT1: 202303 | AU1: 202306 | AV1: 202309 | AW1: 202312 | AX1: 202403 | AY1: 202406 | AZ1: 202409 | BA1: 202412 | BB1: 202503 | BC1: 202506 | BD1: 202509 | BE1: 202512 | BF1: 202603 | BG1: 202606 | BH1: 202609 | BI1: 202612 | BJ1: 202703 | BK1: 202706 | BL1: 202709 | BM1: 202712 | BN1: 202803 | BO1: 202806 | BP1: 202809 | BQ1: 202812 | BR1: 202903 | BS1: 202906 | BT1: 202909 | BU1: 202912 | BV1: 203003
A3: Field Description | B3: Field Name
A4: Company Name | B4: CD_COMPNAME | C4: =_xll.EQNXTDZ(A1,B4,C1) -> #NAME?
A5: Date End | B5: QTR_DATE_END | C5: =_xll.EQNXTDZ($A$1,$B5,C$1,$B$1) -> #NAME? | D5: =_xll.EQNXTDZ($A$1,$B5,D$1,$B$1) -> #NAME? | E5: =_xll.EQNXTDZ($A$1,$B5,E$1,$B$1) -> #NAME? | F5: =_xll.EQNXTDZ($A$1,$B5,F$1,$B$1) -> #NAME? | G5: =_xll.EQNXTDZ($A$1,$B5,G$1,$B$1) -> #NAME? | H5: =_xll.EQNXTDZ($A$1,$B5,H$1,$B$1) -> #NAME? | I5: =_xll.EQNXTDZ($A$1,$B5,I$1,$B$1) -> #NAME? | J5: =_xll.EQNXTDZ($A$1,$B5,J$1,$B$1) -> #NAME? | ... BV5: =_xll.EQNXTDZ($A$1,$B5,BV$1,$B$1) -> #NAME?
A6: Gross Sales | B6: QTR_GROSS_SALE | C6: =_xll.EQNXTDZ($A$1,$B6,C$1,$B$1) -> #NAME? | D6: =_xll.EQNXTDZ($A$1,$B6,D$1,$B$1) -> #NAME? | E6: =_xll.EQNXTDZ($A$1,$B6,E$1,$B$1) -> #NAME? | F6: =_xll.EQNXTDZ($A$1,$B6,F$1,$B$1) -> #NAME? | G6: =_xll.EQNXTDZ($A$1,$B6,G$1,$B$1) -> #NAME? | H6: =_xll.EQNXTDZ($A$1,$B6,H$1,$B$1) -> #NAME? | I6: =_xll.EQNXTDZ($A$1,$B6,I$1,$B$1) -> #NAME? | J6: =_xll.EQNXTDZ($A$1,$B6,J$1,$B$1) -> #NAME? | ... BV6: =_xll.EQNXTDZ($A$1,$B6,BV$1,$B$1) -> #NAME?
A7: Less: Excise Duty | B7: QTR_EXCISE_DUTY | C7: =_xll.EQNXTDZ($A$1,$B7,C$1,$B$1) -> #NAME? | D7: =_xll.EQNXTDZ($A$1,$B7,D$1,$B$1) -> #NAME? | E7: =_xll.EQNXTDZ($A$1,$B7,E$1,$B$1) -> #NAME? | F7: =_xll.EQNXTDZ($A$1,$B7,F$1,$B$1) -> #NAME? | G7: =_xll.EQNXTDZ($A$1,$B7,G$1,$B$1) -> #NAME? | H7: =_xll.EQNXTDZ($A$1,$B7,H$1,$B$1) -> #NAME? | I7: =_xll.EQNXTDZ($A$1,$B7,I$1,$B$1) -> #NAME? | J7: =_xll.EQNXTDZ($A$1,$B7,J$1,$B$1) -> #NAME? | ... BV7: =_xll.EQNXTDZ($A$1,$B7,BV$1,$B$1) -> #NAME?
A8: Other operating income | B8: QTR_JOB_WORKS | C8: =_xll.EQNXTDZ($A$1,$B8,C$1,$B$1) -> #NAME? | D8: =_xll.EQNXTDZ($A$1,$B8,D$1,$B$1) -> #NAME? | E8: =_xll.EQNXTDZ($A$1,$B8,E$1,$B$1) -> #NAME? | F8: =_xll.EQNXTDZ($A$1,$B8,F$1,$B$1) -> #NAME? | G8: =_xll.EQNXTDZ($A$1,$B8,G$1,$B$1) -> #NAME? | H8: =_xll.EQNXTDZ($A$1,$B8,H$1,$B$1) -> #NAME? | I8: =_xll.EQNXTDZ($A$1,$B8,I$1,$B$1) -> #NAME? | J8: =_xll.EQNXTDZ($A$1,$B8,J$1,$B$1) -> #NAME? | ... BV8: =_xll.EQNXTDZ($A$1,$B8,BV$1,$B$1) -> #NAME?
A9: Net Sales & Other Operating Income | B9: QTR_NET_SALES | C9: =_xll.EQNXTDZ($A$1,$B9,C$1,$B$1) -> #NAME? | D9: =_xll.EQNXTDZ($A$1,$B9,D$1,$B$1) -> #NAME? | E9: =_xll.EQNXTDZ($A$1,$B9,E$1,$B$1) -> #NAME? | F9: =_xll.EQNXTDZ($A$1,$B9,F$1,$B$1) -> #NAME? | G9: =_xll.EQNXTDZ($A$1,$B9,G$1,$B$1) -> #NAME? | H9: =_xll.EQNXTDZ($A$1,$B9,H$1,$B$1) -> #NAME? | I9: =_xll.EQNXTDZ($A$1,$B9,I$1,$B$1) -> #NAME? | J9: =_xll.EQNXTDZ($A$1,$B9,J$1,$B$1) -> #NAME? | ... BV9: =_xll.EQNXTDZ($A$1,$B9,BV$1,$B$1) -> #NAME?
A10: (Increase) / Decrease In Stocks | B10: QTR_INC_DEC_INVENTORY | C10: =_xll.EQNXTDZ($A$1,$B10,C$1,$B$1) -> #NAME? | D10: =_xll.EQNXTDZ($A$1,$B10,D$1,$B$1) -> #NAME? | E10: =_xll.EQNXTDZ($A$1,$B10,E$1,$B$1) -> #NAME? | F10: =_xll.EQNXTDZ($A$1,$B10,F$1,$B$1) -> #NAME? | G10: =_xll.EQNXTDZ($A$1,$B10,G$1,$B$1) -> #NAME? | H10: =_xll.EQNXTDZ($A$1,$B10,H$1,$B$1) -> #NAME? | I10: =_xll.EQNXTDZ($A$1,$B10,I$1,$B$1) -> #NAME? | J10: =_xll.EQNXTDZ($A$1,$B10,J$1,$B$1) -> #NAME? | ... BV10: =_xll.EQNXTDZ($A$1,$B10,BV$1,$B$1) -> #NAME?
A11: Cost of Services & Raw Materials | B11: QTR_RAW_MATERIAL_COST | C11: =_xll.EQNXTDZ($A$1,$B11,C$1,$B$1) -> #NAME? | D11: =_xll.EQNXTDZ($A$1,$B11,D$1,$B$1) -> #NAME? | E11: =_xll.EQNXTDZ($A$1,$B11,E$1,$B$1) -> #NAME? | F11: =_xll.EQNXTDZ($A$1,$B11,F$1,$B$1) -> #NAME? | G11: =_xll.EQNXTDZ($A$1,$B11,G$1,$B$1) -> #NAME? | H11: =_xll.EQNXTDZ($A$1,$B11,H$1,$B$1) -> #NAME? | I11: =_xll.EQNXTDZ($A$1,$B11,I$1,$B$1) -> #NAME? | J11: =_xll.EQNXTDZ($A$1,$B11,J$1,$B$1) -> #NAME? | ... BV11: =_xll.EQNXTDZ($A$1,$B11,BV$1,$B$1) -> #NAME?
A12: Purchase of Finished Goods | B12: QTR_PURCHASE_FIN_GOOD | C12: =_xll.EQNXTDZ($A$1,$B12,C$1,$B$1) -> #NAME? | D12: =_xll.EQNXTDZ($A$1,$B12,D$1,$B$1) -> #NAME? | E12: =_xll.EQNXTDZ($A$1,$B12,E$1,$B$1) -> #NAME? | F12: =_xll.EQNXTDZ($A$1,$B12,F$1,$B$1) -> #NAME? | G12: =_xll.EQNXTDZ($A$1,$B12,G$1,$B$1) -> #NAME? | H12: =_xll.EQNXTDZ($A$1,$B12,H$1,$B$1) -> #NAME? | I12: =_xll.EQNXTDZ($A$1,$B12,I$1,$B$1) -> #NAME? | J12: =_xll.EQNXTDZ($A$1,$B12,J$1,$B$1) -> #NAME? | ... BV12: =_xll.EQNXTDZ($A$1,$B12,BV$1,$B$1) -> #NAME?
A13: Excise Duty | B13: QTR_EXCISE | C13: =_xll.EQNXTDZ($A$1,$B13,C$1,$B$1) -> #NAME? | D13: =_xll.EQNXTDZ($A$1,$B13,D$1,$B$1) -> #NAME? | E13: =_xll.EQNXTDZ($A$1,$B13,E$1,$B$1) -> #NAME? | F13: =_xll.EQNXTDZ($A$1,$B13,F$1,$B$1) -> #NAME? | G13: =_xll.EQNXTDZ($A$1,$B13,G$1,$B$1) -> #NAME? | H13: =_xll.EQNXTDZ($A$1,$B13,H$1,$B$1) -> #NAME? | I13: =_xll.EQNXTDZ($A$1,$B13,I$1,$B$1) -> #NAME? | J13: =_xll.EQNXTDZ($A$1,$B13,J$1,$B$1) -> #NAME? | ... BV13: =_xll.EQNXTDZ($A$1,$B13,BV$1,$B$1) -> #NAME?
A14: Operating & Manufacturing Expenses | B14: QTR_MFG_EXPS | C14: =_xll.EQNXTDZ($A$1,$B14,C$1,$B$1) -> #NAME? | D14: =_xll.EQNXTDZ($A$1,$B14,D$1,$B$1) -> #NAME? | E14: =_xll.EQNXTDZ($A$1,$B14,E$1,$B$1) -> #NAME? | F14: =_xll.EQNXTDZ($A$1,$B14,F$1,$B$1) -> #NAME? | G14: =_xll.EQNXTDZ($A$1,$B14,G$1,$B$1) -> #NAME? | H14: =_xll.EQNXTDZ($A$1,$B14,H$1,$B$1) -> #NAME? | I14: =_xll.EQNXTDZ($A$1,$B14,I$1,$B$1) -> #NAME? | J14: =_xll.EQNXTDZ($A$1,$B14,J$1,$B$1) -> #NAME? | ... BV14: =_xll.EQNXTDZ($A$1,$B14,BV$1,$B$1) -> #NAME?
A15: Electricity Power & Fuel Cost | B15: QTR_ELECTRICITY_POWER_FUEL | C15: =_xll.EQNXTDZ($A$1,$B15,C$1,$B$1) -> #NAME? | D15: =_xll.EQNXTDZ($A$1,$B15,D$1,$B$1) -> #NAME? | E15: =_xll.EQNXTDZ($A$1,$B15,E$1,$B$1) -> #NAME? | F15: =_xll.EQNXTDZ($A$1,$B15,F$1,$B$1) -> #NAME? | G15: =_xll.EQNXTDZ($A$1,$B15,G$1,$B$1) -> #NAME? | H15: =_xll.EQNXTDZ($A$1,$B15,H$1,$B$1) -> #NAME? | I15: =_xll.EQNXTDZ($A$1,$B15,I$1,$B$1) -> #NAME? | J15: =_xll.EQNXTDZ($A$1,$B15,J$1,$B$1) -> #NAME? | ... BV15: =_xll.EQNXTDZ($A$1,$B15,BV$1,$B$1) -> #NAME?
A16: Employee Cost | B16: QTR_EXPLOYEE_COST | C16: =_xll.EQNXTDZ($A$1,$B16,C$1,$B$1) -> #NAME? | D16: =_xll.EQNXTDZ($A$1,$B16,D$1,$B$1) -> #NAME? | E16: =_xll.EQNXTDZ($A$1,$B16,E$1,$B$1) -> #NAME? | F16: =_xll.EQNXTDZ($A$1,$B16,F$1,$B$1) -> #NAME? | G16: =_xll.EQNXTDZ($A$1,$B16,G$1,$B$1) -> #NAME? | H16: =_xll.EQNXTDZ($A$1,$B16,H$1,$B$1) -> #NAME? | I16: =_xll.EQNXTDZ($A$1,$B16,I$1,$B$1) -> #NAME? | J16: =_xll.EQNXTDZ($A$1,$B16,J$1,$B$1) -> #NAME? | ... BV16: =_xll.EQNXTDZ($A$1,$B16,BV$1,$B$1) -> #NAME?
... A42: Consolidated PAT(after extra items) | B42: QTR_CONS_PAT_EXITM | C42: =_xll.EQNXTDZ($A$1,$B42,C$1,$B$1) -> #NAME? | D42: =_xll.EQNXTDZ($A$1,$B42,D$1,$B$1) -> #NAME? | E42: =_xll.EQNXTDZ($A$1,$B42,E$1,$B$1) -> #NAME? | F42: =_xll.EQNXTDZ($A$1,$B42,F$1,$B$1) -> #NAME? | G42: =_xll.EQNXTDZ($A$1,$B42,G$1,$B$1) -> #NAME? | H42: =_xll.EQNXTDZ($A$1,$B42,H$1,$B$1) -> #NAME? | I42: =_xll.EQNXTDZ($A$1,$B42,I$1,$B$1) -> #NAME? | J42: =_xll.EQNXTDZ($A$1,$B42,J$1,$B$1) -> #NAME? | ... BV42: =_xll.EQNXTDZ($A$1,$B42,BV$1,$B$1) -> #NAME?
A44: Field Description | B44: Field Name
A45: Equity Capital | B45: QTR_EQUITY_CAP | C45: =_xll.EQNXTDZ($A$1,$B45,C$1,$B$1) -> #NAME? | D45: =_xll.EQNXTDZ($A$1,$B45,D$1,$B$1) -> #NAME? | E45: =_xll.EQNXTDZ($A$1,$B45,E$1,$B$1) -> #NAME? | F45: =_xll.EQNXTDZ($A$1,$B45,F$1,$B$1) -> #NAME? | G45: =_xll.EQNXTDZ($A$1,$B45,G$1,$B$1) -> #NAME? | H45: =_xll.EQNXTDZ($A$1,$B45,H$1,$B$1) -> #NAME? | I45: =_xll.EQNXTDZ($A$1,$B45,I$1,$B$1) -> #NAME? | J45: =_xll.EQNXTDZ($A$1,$B45,J$1,$B$1) -> #NAME? | ... BV45: =_xll.EQNXTDZ($A$1,$B45,BV$1,$B$1) -> #NAME?
A46: Face Value | B46: QTR_FV | C46: =_xll.EQNXTDZ($A$1,$B46,C$1,$B$1) -> #NAME? | D46: =_xll.EQNXTDZ($A$1,$B46,D$1,$B$1) -> #NAME? | E46: =_xll.EQNXTDZ($A$1,$B46,E$1,$B$1) -> #NAME? | F46: =_xll.EQNXTDZ($A$1,$B46,F$1,$B$1) -> #NAME? | G46: =_xll.EQNXTDZ($A$1,$B46,G$1,$B$1) -> #NAME? | H46: =_xll.EQNXTDZ($A$1,$B46,H$1,$B$1) -> #NAME? | I46: =_xll.EQNXTDZ($A$1,$B46,I$1,$B$1) -> #NAME? | J46: =_xll.EQNXTDZ($A$1,$B46,J$1,$B$1) -> #NAME? | ... BV46: =_xll.EQNXTDZ($A$1,$B46,BV$1,$B$1) -> #NAME?
A47: Month End | B47: BMONTH_MONTHEND | C47: =_xll.EQNXTDZ($A$1,$B47,C$5) -> #NAME? | D47: =_xll.EQNXTDZ($A$1,$B47,D$5) -> #NAME? | E47: =_xll.EQNXTDZ($A$1,$B47,E$5) -> #NAME? | F47: =_xll.EQNXTDZ($A$1,$B47,F$5) -> #NAME? | G47: =_xll.EQNXTDZ($A$1,$B47,G$5) -> #NAME? | H47: =_xll.EQNXTDZ($A$1,$B47,H$5) -> #NAME? | I47: =_xll.EQNXTDZ($A$1,$B47,I$5) -> #NAME? | J47: =_xll.EQNXTDZ($A$1,$B47,J$5) -> #NAME? | ... BV47: =_xll.EQNXTDZ($A$1,$B47,BV$5) -> #NAME?
A48: Close | B48: BMONTH_CLOSE | C48: =_xll.EQNXTDZ($A$1,$B48,C$5) -> #NAME? | D48: =_xll.EQNXTDZ($A$1,$B48,D$5) -> #NAME? | E48: =_xll.EQNXTDZ($A$1,$B48,E$5) -> #NAME? | F48: =_xll.EQNXTDZ($A$1,$B48,F$5) -> #NAME? | G48: =_xll.EQNXTDZ($A$1,$B48,G$5) -> #NAME? | H48: =_xll.EQNXTDZ($A$1,$B48,H$5) -> #NAME? | I48: =_xll.EQNXTDZ($A$1,$B48,I$5) -> #NAME? | J48: =_xll.EQNXTDZ($A$1,$B48,J$5) -> #NAME? | ... BV48: =_xll.EQNXTDZ($A$1,$B48,BV$5) -> #NAME?
A49: Total of Promoter and Promoter Group | B49: SHP_TPFTOTALPROMOTER | C49: =_xll.EQNXTDZ($A$1,$B49,C$5) -> #NAME? | D49: =_xll.EQNXTDZ($A$1,$B49,D$5) -> #NAME? | E49: =_xll.EQNXTDZ($A$1,$B49,E$5) -> #NAME? | F49: =_xll.EQNXTDZ($A$1,$B49,F$5) -> #NAME? | G49: =_xll.EQNXTDZ($A$1,$B49,G$5) -> #NAME? | H49: =_xll.EQNXTDZ($A$1,$B49,H$5) -> #NAME? | I49: =_xll.EQNXTDZ($A$1,$B49,I$5) -> #NAME? | J49: =_xll.EQNXTDZ($A$1,$B49,J$5) -> #NAME? | ... BV49: =_xll.EQNXTDZ($A$1,$B49,BV$5) -> #NAME?
A50: Total of Promoter and Promoter Group Pledged | B50: SHP_PSHFTOTALPROMOTER | C50: =_xll.EQNXTDZ($A$1,$B50,C$5) -> #NAME? | D50: =_xll.EQNXTDZ($A$1,$B50,D$5) -> #NAME? | E50: =_xll.EQNXTDZ($A$1,$B50,E$5) -> #NAME? | F50: =_xll.EQNXTDZ($A$1,$B50,F$5) -> #NAME? | G50: =_xll.EQNXTDZ($A$1,$B50,G$5) -> #NAME? | H50: =_xll.EQNXTDZ($A$1,$B50,H$5) -> #NAME? | I50: =_xll.EQNXTDZ($A$1,$B50,I$5) -> #NAME? | J50: =_xll.EQNXTDZ($A$1,$B50,J$5) -> #NAME? | ... BV50: =_xll.EQNXTDZ($A$1,$B50,BV$5) -> #NAME?
A54: Field Description | B54: Field Name | C54: =_xll.EQNXTDZ($A$1,$B54,C$5) -> #NAME? | D54: =_xll.EQNXTDZ($A$1,$B54,D$5) -> #NAME? | E54: =_xll.EQNXTDZ($A$1,$B54,E$5) -> #NAME? | F54: =_xll.EQNXTDZ($A$1,$B54,F$5) -> #NAME? | G54: =_xll.EQNXTDZ($A$1,$B54,G$5) -> #NAME? | H54: =_xll.EQNXTDZ($A$1,$B54,H$5) -> #NAME? | I54: =_xll.EQNXTDZ($A$1,$B54,I$5) -> #NAME? | J54: =_xll.EQNXTDZ($A$1,$B54,J$5) -> #NAME? | ... BV54: =_xll.EQNXTDZ($A$1,$B54,BV$5) -> #NAME?
A55: Year End | B55: QTRB_DATE_END | C55: =_xll.EQNXTDZ($A$1,$B55,C$5,$B$1) -> #NAME? | D55: =_xll.EQNXTDZ($A$1,$B55,D$5,$B$1) -> #NAME? | E55: =_xll.EQNXTDZ($A$1,$B55,E$5,$B$1) -> #NAME? | F55: =_xll.EQNXTDZ($A$1,$B55,F$5,$B$1) -> #NAME? | G55: =_xll.EQNXTDZ($A$1,$B55,G$5,$B$1) -> #NAME? | H55: =_xll.EQNXTDZ($A$1,$B55,H$5,$B$1) -> #NAME? | I55: =_xll.EQNXTDZ($A$1,$B55,I$5,$B$1) -> #NAME? | J55: =_xll.EQNXTDZ($A$1,$B55,J$5,$B$1) -> #NAME? | ... BV55: =_xll.EQNXTDZ($A$1,$B55,BV$5,$B$1) -> #NAME?
A56: Share Capital | B56: QTRB_SHARE_CAPITAL | C56: =_xll.EQNXTDZ($A$1,$B56,C$5,$B$1) -> #NAME? | D56: =_xll.EQNXTDZ($A$1,$B56,D$5,$B$1) -> #NAME? | E56: =_xll.EQNXTDZ($A$1,$B56,E$5,$B$1) -> #NAME? | F56: =_xll.EQNXTDZ($A$1,$B56,F$5,$B$1) -> #NAME? | G56: =_xll.EQNXTDZ($A$1,$B56,G$5,$B$1) -> #NAME? | H56: =_xll.EQNXTDZ($A$1,$B56,H$5,$B$1) -> #NAME? | I56: =_xll.EQNXTDZ($A$1,$B56,I$5,$B$1) -> #NAME? | J56: =_xll.EQNXTDZ($A$1,$B56,J$5,$B$1) -> #NAME? | ... BV56: =_xll.EQNXTDZ($A$1,$B56,BV$5,$B$1) -> #NAME?
A57: Share Warrants & outstandings | B57: QTRB_SHAREWARNDOUT | C57: =_xll.EQNXTDZ($A$1,$B57,C$5,$B$1) -> #NAME? | D57: =_xll.EQNXTDZ($A$1,$B57,D$5,$B$1) -> #NAME? | E57: =_xll.EQNXTDZ($A$1,$B57,E$5,$B$1) -> #NAME? | F57: =_xll.EQNXTDZ($A$1,$B57,F$5,$B$1) -> #NAME? | G57: =_xll.EQNXTDZ($A$1,$B57,G$5,$B$1) -> #NAME? | H57: =_xll.EQNXTDZ($A$1,$B57,H$5,$B$1) -> #NAME? | I57: =_xll.EQNXTDZ($A$1,$B57,I$5,$B$1) -> #NAME? | J57: =_xll.EQNXTDZ($A$1,$B57,J$5,$B$1) -> #NAME? | ... BV57: =_xll.EQNXTDZ($A$1,$B57,BV$5,$B$1) -> #NAME?
A58: Reserves & Surplus | B58: QTRB_RESERVE | C58: =_xll.EQNXTDZ($A$1,$B58,C$5,$B$1) -> #NAME? | D58: =_xll.EQNXTDZ($A$1,$B58,D$5,$B$1) -> #NAME? | E58: =_xll.EQNXTDZ($A$1,$B58,E$5,$B$1) -> #NAME? | F58: =_xll.EQNXTDZ($A$1,$B58,F$5,$B$1) -> #NAME? | G58: =_xll.EQNXTDZ($A$1,$B58,G$5,$B$1) -> #NAME? | H58: =_xll.EQNXTDZ($A$1,$B58,H$5,$B$1) -> #NAME? | I58: =_xll.EQNXTDZ($A$1,$B58,I$5,$B$1) -> #NAME? | J58: =_xll.EQNXTDZ($A$1,$B58,J$5,$B$1) -> #NAME? | ... BV58: =_xll.EQNXTDZ($A$1,$B58,BV$5,$B$1) -> #NAME?
A59: Shareholder's Funds | B59: QTRB_SHAREHODERS_FUNDS | C59: =_xll.EQNXTDZ($A$1,$B59,C$5,$B$1) -> #NAME? | D59: =_xll.EQNXTDZ($A$1,$B59,D$5,$B$1) -> #NAME? | E59: =_xll.EQNXTDZ($A$1,$B59,E$5,$B$1) -> #NAME? | F59: =_xll.EQNXTDZ($A$1,$B59,F$5,$B$1) -> #NAME? | G59: =_xll.EQNXTDZ($A$1,$B59,G$5,$B$1) -> #NAME? | H59: =_xll.EQNXTDZ($A$1,$B59,H$5,$B$1) -> #NAME? | I59: =_xll.EQNXTDZ($A$1,$B59,I$5,$B$1) -> #NAME? | J59: =_xll.EQNXTDZ($A$1,$B59,J$5,$B$1) -> #NAME? | ... BV59: =_xll.EQNXTDZ($A$1,$B59,BV$5,$B$1) -> #NAME?
A60: Minority Interest | B60: QTRB_MINORITY_INTEREST_BS | C60: =_xll.EQNXTDZ($A$1,$B60,C$5,$B$1) -> #NAME? | D60: =_xll.EQNXTDZ($A$1,$B60,D$5,$B$1) -> #NAME? | E60: =_xll.EQNXTDZ($A$1,$B60,E$5,$B$1) -> #NAME? | F60: =_xll.EQNXTDZ($A$1,$B60,F$5,$B$1) -> #NAME? | G60: =_xll.EQNXTDZ($A$1,$B60,G$5,$B$1) -> #NAME? | H60: =_xll.EQNXTDZ($A$1,$B60,H$5,$B$1) -> #NAME? | I60: =_xll.EQNXTDZ($A$1,$B60,I$5,$B$1) -> #NAME? | J60: =_xll.EQNXTDZ($A$1,$B60,J$5,$B$1) -> #NAME? | ... BV60: =_xll.EQNXTDZ($A$1,$B60,BV$5,$B$1) -> #NAME?
A61: Long Term Borrowings | B61: QTRB_TOTAL_DEBTS | C61: =_xll.EQNXTDZ($A$1,$B61,C$5,$B$1) -> #NAME? | D61: =_xll.EQNXTDZ($A$1,$B61,D$5,$B$1) -> #NAME? | E61: =_xll.EQNXTDZ($A$1,$B61,E$5,$B$1) -> #NAME? | F61: =_xll.EQNXTDZ($A$1,$B61,F$5,$B$1) -> #NAME? | G61: =_xll.EQNXTDZ($A$1,$B61,G$5,$B$1) -> #NAME? | H61: =_xll.EQNXTDZ($A$1,$B61,H$5,$B$1) -> #NAME? | I61: =_xll.EQNXTDZ($A$1,$B61,I$5,$B$1) -> #NAME? | J61: =_xll.EQNXTDZ($A$1,$B61,J$5,$B$1) -> #NAME? | ... BV61: =_xll.EQNXTDZ($A$1,$B61,BV$5,$B$1) -> #NAME?
A62: Secured Loans | B62: QTRB_SECURED_LOANS | C62: =_xll.EQNXTDZ($A$1,$B62,C$5,$B$1) -> #NAME? | D62: =_xll.EQNXTDZ($A$1,$B62,D$5,$B$1) -> #NAME? | E62: =_xll.EQNXTDZ($A$1,$B62,E$5,$B$1) -> #NAME? | F62: =_xll.EQNXTDZ($A$1,$B62,F$5,$B$1) -> #NAME? | G62: =_xll.EQNXTDZ($A$1,$B62,G$5,$B$1) -> #NAME? | H62: =_xll.EQNXTDZ($A$1,$B62,H$5,$B$1) -> #NAME? | I62: =_xll.EQNXTDZ($A$1,$B62,I$5,$B$1) -> #NAME? | J62: =_xll.EQNXTDZ($A$1,$B62,J$5,$B$1) -> #NAME? | ... BV62: =_xll.EQNXTDZ($A$1,$B62,BV$5,$B$1) -> #NAME?
A63: Unsecured Loans | B63: QTRB_UNSECURED_LOANS_NF | C63: =_xll.EQNXTDZ($A$1,$B63,C$5,$B$1) -> #NAME? | D63: =_xll.EQNXTDZ($A$1,$B63,D$5,$B$1) -> #NAME? | E63: =_xll.EQNXTDZ($A$1,$B63,E$5,$B$1) -> #NAME? | F63: =_xll.EQNXTDZ($A$1,$B63,F$5,$B$1) -> #NAME? | G63: =_xll.EQNXTDZ($A$1,$B63,G$5,$B$1) -> #NAME? | H63: =_xll.EQNXTDZ($A$1,$B63,H$5,$B$1) -> #NAME? | I63: =_xll.EQNXTDZ($A$1,$B63,I$5,$B$1) -> #NAME? | J63: =_xll.EQNXTDZ($A$1,$B63,J$5,$B$1) -> #NAME? | ... BV63: =_xll.EQNXTDZ($A$1,$B63,BV$5,$B$1) -> #NAME?
A64: Other Long Term Liabilities | B64: QTRB_OTHER_LT_LIABILITIES | C64: =_xll.EQNXTDZ($A$1,$B64,C$5,$B$1) -> #NAME? | D64: =_xll.EQNXTDZ($A$1,$B64,D$5,$B$1) -> #NAME? | E64: =_xll.EQNXTDZ($A$1,$B64,E$5,$B$1) -> #NAME? | F64: =_xll.EQNXTDZ($A$1,$B64,F$5,$B$1) -> #NAME? | G64: =_xll.EQNXTDZ($A$1,$B64,G$5,$B$1) -> #NAME? | H64: =_xll.EQNXTDZ($A$1,$B64,H$5,$B$1) -> #NAME? | I64: =_xll.EQNXTDZ($A$1,$B64,I$5,$B$1) -> #NAME? | J64: =_xll.EQNXTDZ($A$1,$B64,J$5,$B$1) -> #NAME? | ... BV64: =_xll.EQNXTDZ($A$1,$B64,BV$5,$B$1) -> #NAME?
A65: Long Term Trade Payables | B65: QTRB_LT_TRADE_PAYABLE | C65: =_xll.EQNXTDZ($A$1,$B65,C$5,$B$1) -> #NAME? | D65: =_xll.EQNXTDZ($A$1,$B65,D$5,$B$1) -> #NAME? | E65: =_xll.EQNXTDZ($A$1,$B65,E$5,$B$1) -> #NAME? | F65: =_xll.EQNXTDZ($A$1,$B65,F$5,$B$1) -> #NAME? | G65: =_xll.EQNXTDZ($A$1,$B65,G$5,$B$1) -> #NAME? | H65: =_xll.EQNXTDZ($A$1,$B65,H$5,$B$1) -> #NAME? | I65: =_xll.EQNXTDZ($A$1,$B65,I$5,$B$1) -> #NAME? | J65: =_xll.EQNXTDZ($A$1,$B65,J$5,$B$1) -> #NAME? | ... BV65: =_xll.EQNXTDZ($A$1,$B65,BV$5,$B$1) -> #NAME?
A66: Lont Term Provisions | B66: QTRB_LT_PROVISIONS | C66: =_xll.EQNXTDZ($A$1,$B66,C$5,$B$1) -> #NAME? | D66: =_xll.EQNXTDZ($A$1,$B66,D$5,$B$1) -> #NAME? | E66: =_xll.EQNXTDZ($A$1,$B66,E$5,$B$1) -> #NAME? | F66: =_xll.EQNXTDZ($A$1,$B66,F$5,$B$1) -> #NAME? | G66: =_xll.EQNXTDZ($A$1,$B66,G$5,$B$1) -> #NAME? | H66: =_xll.EQNXTDZ($A$1,$B66,H$5,$B$1) -> #NAME? | I66: =_xll.EQNXTDZ($A$1,$B66,I$5,$B$1) -> #NAME? | J66: =_xll.EQNXTDZ($A$1,$B66,J$5,$B$1) -> #NAME? | ... BV66: =_xll.EQNXTDZ($A$1,$B66,BV$5,$B$1) -> #NAME?
... A97: Total Assets | B97: QTRB_TOTAL_APPLICATIONS | C97: =_xll.EQNXTDZ($A$1,$B97,C$5,$B$1) -> #NAME? | D97: =_xll.EQNXTDZ($A$1,$B97,D$5,$B$1) -> #NAME? | E97: =_xll.EQNXTDZ($A$1,$B97,E$5,$B$1) -> #NAME? | F97: =_xll.EQNXTDZ($A$1,$B97,F$5,$B$1) -> #NAME? | G97: =_xll.EQNXTDZ($A$1,$B97,G$5,$B$1) -> #NAME? | H97: =_xll.EQNXTDZ($A$1,$B97,H$5,$B$1) -> #NAME? | I97: =_xll.EQNXTDZ($A$1,$B97,I$5,$B$1) -> #NAME? | J97: =_xll.EQNXTDZ($A$1,$B97,J$5,$B$1) -> #NAME? | ... BV97: =_xll.EQNXTDZ($A$1,$B97,BV$5,$B$1) -> #NAME?

Sheet Annual Raw
A1: 226159 | B1: X | C1: 200103 | D1: 200203 | E1: 200303 | F1: 200403 | G1: 200503 | H1: 200603 | I1: 200703 | J1: 200803 | K1: 200903 | L1: 201003 | M1: 201103 | N1: 201203 | O1: 201303 | P1: 201403 | Q1: 201503 | R1: 201603 | S1: 201703 | T1: 201803 | U1: 201903 | V1: 202003 | W1: 202103 | X1: 202203 | Y1: 202303 | Z1: 202403 | AA1: 202503 | AB1: 202603 | AC1: 202703 | AD1: 202803 | AE1: 202903 | AF1: 203003
A3: Field Description | B3: Field Name
A4: Company Name | B4: CD_COMPNAME | C4: =_xll.EQNXTDZ(A1,B4,"L") -> #NAME?
A5: Year End | B5: PL_YEAR_END | C5: =_xll.EQNXTDZ($A$1,$B5,C$1,$B$1) -> #NAME? | D5: =_xll.EQNXTDZ($A$1,$B5,D$1,$B$1) -> #NAME? | E5: =_xll.EQNXTDZ($A$1,$B5,E$1,$B$1) -> #NAME? | F5: =_xll.EQNXTDZ($A$1,$B5,F$1,$B$1) -> #NAME? | G5: =_xll.EQNXTDZ($A$1,$B5,G$1,$B$1) -> #NAME? | H5: =_xll.EQNXTDZ($A$1,$B5,H$1,$B$1) -> #NAME? | I5: =_xll.EQNXTDZ($A$1,$B5,I$1,$B$1) -> #NAME? | J5: =_xll.EQNXTDZ($A$1,$B5,J$1,$B$1) -> #NAME? | ... AF5: =_xll.EQNXTDZ($A$1,$B5,AF$1,$B$1) -> #NAME?
A6: Sales Turnover | B6: PL_TOTAL_GROSS_SALES | C6: =_xll.EQNXTDZ($A$1,$B6,C$1,$B$1) -> #NAME? | D6: =_xll.EQNXTDZ($A$1,$B6,D$1,$B$1) -> #NAME? | E6: =_xll.EQNXTDZ($A$1,$B6,E$1,$B$1) -> #NAME? | F6: =_xll.EQNXTDZ($A$1,$B6,F$1,$B$1) -> #NAME? | G6: =_xll.EQNXTDZ($A$1,$B6,G$1,$B$1) -> #NAME? | H6: =_xll.EQNXTDZ($A$1,$B6,H$1,$B$1) -> #NAME? | I6: =_xll.EQNXTDZ($A$1,$B6,I$1,$B$1) -> #NAME? | J6: =_xll.EQNXTDZ($A$1,$B6,J$1,$B$1) -> #NAME? | ... AF6: =_xll.EQNXTDZ($A$1,$B6,AF$1,$B$1) -> #NAME?
A7: Less: Inter divisional transfers | B7: PL_INTER_DIV_TRF | C7: =_xll.EQNXTDZ($A$1,$B7,C$1,$B$1) -> #NAME? | D7: =_xll.EQNXTDZ($A$1,$B7,D$1,$B$1) -> #NAME? | E7: =_xll.EQNXTDZ($A$1,$B7,E$1,$B$1) -> #NAME? | F7: =_xll.EQNXTDZ($A$1,$B7,F$1,$B$1) -> #NAME? | G7: =_xll.EQNXTDZ($A$1,$B7,G$1,$B$1) -> #NAME? | H7: =_xll.EQNXTDZ($A$1,$B7,H$1,$B$1) -> #NAME? | I7: =_xll.EQNXTDZ($A$1,$B7,I$1,$B$1) -> #NAME? | J7: =_xll.EQNXTDZ($A$1,$B7,J$1,$B$1) -> #NAME? | ... AF7: =_xll.EQNXTDZ($A$1,$B7,AF$1,$B$1) -> #NAME?
A8: Less: Sales Returns | B8: PL_SALES_RETURN | C8: =_xll.EQNXTDZ($A$1,$B8,C$1,$B$1) -> #NAME? | D8: =_xll.EQNXTDZ($A$1,$B8,D$1,$B$1) -> #NAME? | E8: =_xll.EQNXTDZ($A$1,$B8,E$1,$B$1) -> #NAME? | F8: =_xll.EQNXTDZ($A$1,$B8,F$1,$B$1) -> #NAME? | G8: =_xll.EQNXTDZ($A$1,$B8,G$1,$B$1) -> #NAME? | H8: =_xll.EQNXTDZ($A$1,$B8,H$1,$B$1) -> #NAME? | I8: =_xll.EQNXTDZ($A$1,$B8,I$1,$B$1) -> #NAME? | J8: =_xll.EQNXTDZ($A$1,$B8,J$1,$B$1) -> #NAME? | ... AF8: =_xll.EQNXTDZ($A$1,$B8,AF$1,$B$1) -> #NAME?
A9: Less: Excise | B9: PL_EXCISE | C9: =_xll.EQNXTDZ($A$1,$B9,C$1,$B$1) -> #NAME? | D9: =_xll.EQNXTDZ($A$1,$B9,D$1,$B$1) -> #NAME? | E9: =_xll.EQNXTDZ($A$1,$B9,E$1,$B$1) -> #NAME? | F9: =_xll.EQNXTDZ($A$1,$B9,F$1,$B$1) -> #NAME? | G9: =_xll.EQNXTDZ($A$1,$B9,G$1,$B$1) -> #NAME? | H9: =_xll.EQNXTDZ($A$1,$B9,H$1,$B$1) -> #NAME? | I9: =_xll.EQNXTDZ($A$1,$B9,I$1,$B$1) -> #NAME? | J9: =_xll.EQNXTDZ($A$1,$B9,J$1,$B$1) -> #NAME? | ... AF9: =_xll.EQNXTDZ($A$1,$B9,AF$1,$B$1) -> #NAME?
A10: Net Sales | B10: PL_NET_SALES | C10: =_xll.EQNXTDZ($A$1,$B10,C$1,$B$1) -> #NAME? | D10: =_xll.EQNXTDZ($A$1,$B10,D$1,$B$1) -> #NAME? | E10: =_xll.EQNXTDZ($A$1,$B10,E$1,$B$1) -> #NAME? | F10: =_xll.EQNXTDZ($A$1,$B10,F$1,$B$1) -> #NAME? | G10: =_xll.EQNXTDZ($A$1,$B10,G$1,$B$1) -> #NAME? | H10: =_xll.EQNXTDZ($A$1,$B10,H$1,$B$1) -> #NAME? | I10: =_xll.EQNXTDZ($A$1,$B10,I$1,$B$1) -> #NAME? | J10: =_xll.EQNXTDZ($A$1,$B10,J$1,$B$1) -> #NAME? | ... AF10: =_xll.EQNXTDZ($A$1,$B10,AF$1,$B$1) -> #NAME?
A11: Increase/Decrease in Stock | B11: PL_INC_DEC_INVENTORY | C11: =_xll.EQNXTDZ($A$1,$B11,C$1,$B$1) -> #NAME? | D11: =_xll.EQNXTDZ($A$1,$B11,D$1,$B$1) -> #NAME? | E11: =_xll.EQNXTDZ($A$1,$B11,E$1,$B$1) -> #NAME? | F11: =_xll.EQNXTDZ($A$1,$B11,F$1,$B$1) -> #NAME? | G11: =_xll.EQNXTDZ($A$1,$B11,G$1,$B$1) -> #NAME? | H11: =_xll.EQNXTDZ($A$1,$B11,H$1,$B$1) -> #NAME? | I11: =_xll.EQNXTDZ($A$1,$B11,I$1,$B$1) -> #NAME? | J11: =_xll.EQNXTDZ($A$1,$B11,J$1,$B$1) -> #NAME? | ... AF11: =_xll.EQNXTDZ($A$1,$B11,AF$1,$B$1) -> #NAME?
A12: Raw Material Consumed | B12: PL_RAW_MATRS_CONSUMED | C12: =_xll.EQNXTDZ($A$1,$B12,C$1,$B$1) -> #NAME? | D12: =_xll.EQNXTDZ($A$1,$B12,D$1,$B$1) -> #NAME? | E12: =_xll.EQNXTDZ($A$1,$B12,E$1,$B$1) -> #NAME? | F12: =_xll.EQNXTDZ($A$1,$B12,F$1,$B$1) -> #NAME? | G12: =_xll.EQNXTDZ($A$1,$B12,G$1,$B$1) -> #NAME? | H12: =_xll.EQNXTDZ($A$1,$B12,H$1,$B$1) -> #NAME? | I12: =_xll.EQNXTDZ($A$1,$B12,I$1,$B$1) -> #NAME? | J12: =_xll.EQNXTDZ($A$1,$B12,J$1,$B$1) -> #NAME? | ... AF12: =_xll.EQNXTDZ($A$1,$B12,AF$1,$B$1) -> #NAME?
A13: Power & Fuel Cost | B13: PL_POWER_FUEL | C13: =_xll.EQNXTDZ($A$1,$B13,C$1,$B$1) -> #NAME? | D13: =_xll.EQNXTDZ($A$1,$B13,D$1,$B$1) -> #NAME? | E13: =_xll.EQNXTDZ($A$1,$B13,E$1,$B$1) -> #NAME? | F13: =_xll.EQNXTDZ($A$1,$B13,F$1,$B$1) -> #NAME? | G13: =_xll.EQNXTDZ($A$1,$B13,G$1,$B$1) -> #NAME? | H13: =_xll.EQNXTDZ($A$1,$B13,H$1,$B$1) -> #NAME? | I13: =_xll.EQNXTDZ($A$1,$B13,I$1,$B$1) -> #NAME? | J13: =_xll.EQNXTDZ($A$1,$B13,J$1,$B$1) -> #NAME? | ... AF13: =_xll.EQNXTDZ($A$1,$B13,AF$1,$B$1) -> #NAME?
A14: Employee Cost | B14: PL_EMPLOYEES | C14: =_xll.EQNXTDZ($A$1,$B14,C$1,$B$1) -> #NAME? | D14: =_xll.EQNXTDZ($A$1,$B14,D$1,$B$1) -> #NAME? | E14: =_xll.EQNXTDZ($A$1,$B14,E$1,$B$1) -> #NAME? | F14: =_xll.EQNXTDZ($A$1,$B14,F$1,$B$1) -> #NAME? | G14: =_xll.EQNXTDZ($A$1,$B14,G$1,$B$1) -> #NAME? | H14: =_xll.EQNXTDZ($A$1,$B14,H$1,$B$1) -> #NAME? | I14: =_xll.EQNXTDZ($A$1,$B14,I$1,$B$1) -> #NAME? | J14: =_xll.EQNXTDZ($A$1,$B14,J$1,$B$1) -> #NAME? | ... AF14: =_xll.EQNXTDZ($A$1,$B14,AF$1,$B$1) -> #NAME?
A15: Operating & Manufacturing Expenses | B15: PL_GEN_OTHER_MFG_EXPS | C15: =_xll.EQNXTDZ($A$1,$B15,C$1,$B$1) -> #NAME? | D15: =_xll.EQNXTDZ($A$1,$B15,D$1,$B$1) -> #NAME? | E15: =_xll.EQNXTDZ($A$1,$B15,E$1,$B$1) -> #NAME? | F15: =_xll.EQNXTDZ($A$1,$B15,F$1,$B$1) -> #NAME? | G15: =_xll.EQNXTDZ($A$1,$B15,G$1,$B$1) -> #NAME? | H15: =_xll.EQNXTDZ($A$1,$B15,H$1,$B$1) -> #NAME? | I15: =_xll.EQNXTDZ($A$1,$B15,I$1,$B$1) -> #NAME? | J15: =_xll.EQNXTDZ($A$1,$B15,J$1,$B$1) -> #NAME? | ... AF15: =_xll.EQNXTDZ($A$1,$B15,AF$1,$B$1) -> #NAME?
A16: Cost of Software development | B16: PL_COST_SW | C16: =_xll.EQNXTDZ($A$1,$B16,C$1,$B$1) -> #NAME? | D16: =_xll.EQNXTDZ($A$1,$B16,D$1,$B$1) -> #NAME? | E16: =_xll.EQNXTDZ($A$1,$B16,E$1,$B$1) -> #NAME? | F16: =_xll.EQNXTDZ($A$1,$B16,F$1,$B$1) -> #NAME? | G16: =_xll.EQNXTDZ($A$1,$B16,G$1,$B$1) -> #NAME? | H16: =_xll.EQNXTDZ($A$1,$B16,H$1,$B$1) -> #NAME? | I16: =_xll.EQNXTDZ($A$1,$B16,I$1,$B$1) -> #NAME? | J16: =_xll.EQNXTDZ($A$1,$B16,J$1,$B$1) -> #NAME? | ... AF16: =_xll.EQNXTDZ($A$1,$B16,AF$1,$B$1) -> #NAME?
... A36: Profit After Tax from Discontinued Operations | B36: PL_PAT_DIS_OP | C36: =_xll.EQNXTDZ($A$1,$B36,C$1,$B$1) -> #NAME? | D36: =_xll.EQNXTDZ($A$1,$B36,D$1,$B$1) -> #NAME? | E36: =_xll.EQNXTDZ($A$1,$B36,E$1,$B$1) -> #NAME? | F36: =_xll.EQNXTDZ($A$1,$B36,F$1,$B$1) -> #NAME? | G36: =_xll.EQNXTDZ($A$1,$B36,G$1,$B$1) -> #NAME? | H36: =_xll.EQNXTDZ($A$1,$B36,H$1,$B$1) -> #NAME? | I36: =_xll.EQNXTDZ($A$1,$B36,I$1,$B$1) -> #NAME? | J36: =_xll.EQNXTDZ($A$1,$B36,J$1,$B$1) -> #NAME? | ... AF36: =_xll.EQNXTDZ($A$1,$B36,AF$1,$B$1) -> #NAME?
A39: Field Description | B39: Field Name
A40: Year End | B40: BS_YEAR_END | C40: =_xll.EQNXTDZ($A$1,$B40,C$1,$B$1) -> #NAME? | D40: =_xll.EQNXTDZ($A$1,$B40,D$1,$B$1) -> #NAME? | E40: =_xll.EQNXTDZ($A$1,$B40,E$1,$B$1) -> #NAME? | F40: =_xll.EQNXTDZ($A$1,$B40,F$1,$B$1) -> #NAME? | G40: =_xll.EQNXTDZ($A$1,$B40,G$1,$B$1) -> #NAME? | H40: =_xll.EQNXTDZ($A$1,$B40,H$1,$B$1) -> #NAME? | I40: =_xll.EQNXTDZ($A$1,$B40,I$1,$B$1) -> #NAME? | J40: =_xll.EQNXTDZ($A$1,$B40,J$1,$B$1) -> #NAME? | ... AF40: =_xll.EQNXTDZ($A$1,$B40,AF$1,$B$1) -> #NAME?
A41: Share Capital | B41: BS_SHARE_CAPITAL | C41: =_xll.EQNXTDZ($A$1,$B41,C$1,$B$1) -> #NAME? | D41: =_xll.EQNXTDZ($A$1,$B41,D$1,$B$1) -> #NAME? | E41: =_xll.EQNXTDZ($A$1,$B41,E$1,$B$1) -> #NAME? | F41: =_xll.EQNXTDZ($A$1,$B41,F$1,$B$1) -> #NAME? | G41: =_xll.EQNXTDZ($A$1,$B41,G$1,$B$1) -> #NAME? | H41: =_xll.EQNXTDZ($A$1,$B41,H$1,$B$1) -> #NAME? | I41: =_xll.EQNXTDZ($A$1,$B41,I$1,$B$1) -> #NAME? | J41: =_xll.EQNXTDZ($A$1,$B41,J$1,$B$1) -> #NAME? | ... AF41: =_xll.EQNXTDZ($A$1,$B41,AF$1,$B$1) -> #NAME?
A42: Share Warrants & Outstandings | B42: BS_SHAREWROUTST | C42: =_xll.EQNXTDZ($A$1,$B42,C$1,$B$1) -> #NAME? | D42: =_xll.EQNXTDZ($A$1,$B42,D$1,$B$1) -> #NAME? | E42: =_xll.EQNXTDZ($A$1,$B42,E$1,$B$1) -> #NAME? | F42: =_xll.EQNXTDZ($A$1,$B42,F$1,$B$1) -> #NAME? | G42: =_xll.EQNXTDZ($A$1,$B42,G$1,$B$1) -> #NAME? | H42: =_xll.EQNXTDZ($A$1,$B42,H$1,$B$1) -> #NAME? | I42: =_xll.EQNXTDZ($A$1,$B42,I$1,$B$1) -> #NAME? | J42: =_xll.EQNXTDZ($A$1,$B42,J$1,$B$1) -> #NAME? | ... AF42: =_xll.EQNXTDZ($A$1,$B42,AF$1,$B$1) -> #NAME?
A43: Total Reserves | B43: BS_RESERVE | C43: =_xll.EQNXTDZ($A$1,$B43,C$1,$B$1) -> #NAME? | D43: =_xll.EQNXTDZ($A$1,$B43,D$1,$B$1) -> #NAME? | E43: =_xll.EQNXTDZ($A$1,$B43,E$1,$B$1) -> #NAME? | F43: =_xll.EQNXTDZ($A$1,$B43,F$1,$B$1) -> #NAME? | G43: =_xll.EQNXTDZ($A$1,$B43,G$1,$B$1) -> #NAME? | H43: =_xll.EQNXTDZ($A$1,$B43,H$1,$B$1) -> #NAME? | I43: =_xll.EQNXTDZ($A$1,$B43,I$1,$B$1) -> #NAME? | J43: =_xll.EQNXTDZ($A$1,$B43,J$1,$B$1) -> #NAME? | ... AF43: =_xll.EQNXTDZ($A$1,$B43,AF$1,$B$1) -> #NAME?
A44: Shareholder's Funds | B44: BS_SHAREHODERS_FUNDS | C44: =_xll.EQNXTDZ($A$1,$B44,C$1,$B$1) -> #NAME? | D44: =_xll.EQNXTDZ($A$1,$B44,D$1,$B$1) -> #NAME? | E44: =_xll.EQNXTDZ($A$1,$B44,E$1,$B$1) -> #NAME? | F44: =_xll.EQNXTDZ($A$1,$B44,F$1,$B$1) -> #NAME? | G44: =_xll.EQNXTDZ($A$1,$B44,G$1,$B$1) -> #NAME? | H44: =_xll.EQNXTDZ($A$1,$B44,H$1,$B$1) -> #NAME? | I44: =_xll.EQNXTDZ($A$1,$B44,I$1,$B$1) -> #NAME? | J44: =_xll.EQNXTDZ($A$1,$B44,J$1,$B$1) -> #NAME? | ... AF44: =_xll.EQNXTDZ($A$1,$B44,AF$1,$B$1) -> #NAME?
A45: Minority Interest | B45: BS_MINORITY_INTEREST | C45: =_xll.EQNXTDZ($A$1,$B45,C$1,$B$1) -> #NAME? | D45: =_xll.EQNXTDZ($A$1,$B45,D$1,$B$1) -> #NAME? | E45: =_xll.EQNXTDZ($A$1,$B45,E$1,$B$1) -> #NAME? | F45: =_xll.EQNXTDZ($A$1,$B45,F$1,$B$1) -> #NAME? | G45: =_xll.EQNXTDZ($A$1,$B45,G$1,$B$1) -> #NAME? | H45: =_xll.EQNXTDZ($A$1,$B45,H$1,$B$1) -> #NAME? | I45: =_xll.EQNXTDZ($A$1,$B45,I$1,$B$1) -> #NAME? | J45: =_xll.EQNXTDZ($A$1,$B45,J$1,$B$1) -> #NAME? | ... AF45: =_xll.EQNXTDZ($A$1,$B45,AF$1,$B$1) -> #NAME?
A46: Long-Term Borrowings | B46: BS_LTRM_BORROWING | C46: =_xll.EQNXTDZ($A$1,$B46,C$1,$B$1) -> #NAME? | D46: =_xll.EQNXTDZ($A$1,$B46,D$1,$B$1) -> #NAME? | E46: =_xll.EQNXTDZ($A$1,$B46,E$1,$B$1) -> #NAME? | F46: =_xll.EQNXTDZ($A$1,$B46,F$1,$B$1) -> #NAME? | G46: =_xll.EQNXTDZ($A$1,$B46,G$1,$B$1) -> #NAME? | H46: =_xll.EQNXTDZ($A$1,$B46,H$1,$B$1) -> #NAME? | I46: =_xll.EQNXTDZ($A$1,$B46,I$1,$B$1) -> #NAME? | J46: =_xll.EQNXTDZ($A$1,$B46,J$1,$B$1) -> #NAME? | ... AF46: =_xll.EQNXTDZ($A$1,$B46,AF$1,$B$1) -> #NAME?
A47: Secured Loans | B47: BS_SECURED_LOANS | C47: =_xll.EQNXTDZ($A$1,$B47,C$1,$B$1) -> #NAME? | D47: =_xll.EQNXTDZ($A$1,$B47,D$1,$B$1) -> #NAME? | E47: =_xll.EQNXTDZ($A$1,$B47,E$1,$B$1) -> #NAME? | F47: =_xll.EQNXTDZ($A$1,$B47,F$1,$B$1) -> #NAME? | G47: =_xll.EQNXTDZ($A$1,$B47,G$1,$B$1) -> #NAME? | H47: =_xll.EQNXTDZ($A$1,$B47,H$1,$B$1) -> #NAME? | I47: =_xll.EQNXTDZ($A$1,$B47,I$1,$B$1) -> #NAME? | J47: =_xll.EQNXTDZ($A$1,$B47,J$1,$B$1) -> #NAME? | ... AF47: =_xll.EQNXTDZ($A$1,$B47,AF$1,$B$1) -> #NAME?
A48: Unsecured Loans | B48: BS_UNSECURED_LOANS_NF | C48: =_xll.EQNXTDZ($A$1,$B48,C$1,$B$1) -> #NAME? | D48: =_xll.EQNXTDZ($A$1,$B48,D$1,$B$1) -> #NAME? | E48: =_xll.EQNXTDZ($A$1,$B48,E$1,$B$1) -> #NAME? | F48: =_xll.EQNXTDZ($A$1,$B48,F$1,$B$1) -> #NAME? | G48: =_xll.EQNXTDZ($A$1,$B48,G$1,$B$1) -> #NAME? | H48: =_xll.EQNXTDZ($A$1,$B48,H$1,$B$1) -> #NAME? | I48: =_xll.EQNXTDZ($A$1,$B48,I$1,$B$1) -> #NAME? | J48: =_xll.EQNXTDZ($A$1,$B48,J$1,$B$1) -> #NAME? | ... AF48: =_xll.EQNXTDZ($A$1,$B48,AF$1,$B$1) -> #NAME?
A49: Deferred Tax Assets / Liabilities | B49: BS_NET_DEF_TAX_NF | C49: =_xll.EQNXTDZ($A$1,$B49,C$1,$B$1) -> #NAME? | D49: =_xll.EQNXTDZ($A$1,$B49,D$1,$B$1) -> #NAME? | E49: =_xll.EQNXTDZ($A$1,$B49,E$1,$B$1) -> #NAME? | F49: =_xll.EQNXTDZ($A$1,$B49,F$1,$B$1) -> #NAME? | G49: =_xll.EQNXTDZ($A$1,$B49,G$1,$B$1) -> #NAME? | H49: =_xll.EQNXTDZ($A$1,$B49,H$1,$B$1) -> #NAME? | I49: =_xll.EQNXTDZ($A$1,$B49,I$1,$B$1) -> #NAME? | J49: =_xll.EQNXTDZ($A$1,$B49,J$1,$B$1) -> #NAME? | ... AF49: =_xll.EQNXTDZ($A$1,$B49,AF$1,$B$1) -> #NAME?
A50: Other Long Term Liabilities | B50: BS_OTH_LT_LIAB | C50: =_xll.EQNXTDZ($A$1,$B50,C$1,$B$1) -> #NAME? | D50: =_xll.EQNXTDZ($A$1,$B50,D$1,$B$1) -> #NAME? | E50: =_xll.EQNXTDZ($A$1,$B50,E$1,$B$1) -> #NAME? | F50: =_xll.EQNXTDZ($A$1,$B50,F$1,$B$1) -> #NAME? | G50: =_xll.EQNXTDZ($A$1,$B50,G$1,$B$1) -> #NAME? | H50: =_xll.EQNXTDZ($A$1,$B50,H$1,$B$1) -> #NAME? | I50: =_xll.EQNXTDZ($A$1,$B50,I$1,$B$1) -> #NAME? | J50: =_xll.EQNXTDZ($A$1,$B50,J$1,$B$1) -> #NAME? | ... AF50: =_xll.EQNXTDZ($A$1,$B50,AF$1,$B$1) -> #NAME?
A51: Long Term Trade Payables | B51: BS_LT_TRADE_PAYABLES | C51: =_xll.EQNXTDZ($A$1,$B51,C$1,$B$1) -> #NAME? | D51: =_xll.EQNXTDZ($A$1,$B51,D$1,$B$1) -> #NAME? | E51: =_xll.EQNXTDZ($A$1,$B51,E$1,$B$1) -> #NAME? | F51: =_xll.EQNXTDZ($A$1,$B51,F$1,$B$1) -> #NAME? | G51: =_xll.EQNXTDZ($A$1,$B51,G$1,$B$1) -> #NAME? | H51: =_xll.EQNXTDZ($A$1,$B51,H$1,$B$1) -> #NAME? | I51: =_xll.EQNXTDZ($A$1,$B51,I$1,$B$1) -> #NAME? | J51: =_xll.EQNXTDZ($A$1,$B51,J$1,$B$1) -> #NAME? | ... AF51: =_xll.EQNXTDZ($A$1,$B51,AF$1,$B$1) -> #NAME?
... A99: Estimated Capital Contracts Remaining | B99: BS_ESTIMATED_CAPITAL_CONTRACT | C99: =_xll.EQNXTDZ($A$1,$B99,C$1,$B$1) -> #NAME? | D99: =_xll.EQNXTDZ($A$1,$B99,D$1,$B$1) -> #NAME? | E99: =_xll.EQNXTDZ($A$1,$B99,E$1,$B$1) -> #NAME? | F99: =_xll.EQNXTDZ($A$1,$B99,F$1,$B$1) -> #NAME? | G99: =_xll.EQNXTDZ($A$1,$B99,G$1,$B$1) -> #NAME? | H99: =_xll.EQNXTDZ($A$1,$B99,H$1,$B$1) -> #NAME? | I99: =_xll.EQNXTDZ($A$1,$B99,I$1,$B$1) -> #NAME? | J99: =_xll.EQNXTDZ($A$1,$B99,J$1,$B$1) -> #NAME? | ... AF99: =_xll.EQNXTDZ($A$1,$B99,AF$1,$B$1) -> #NAME?
A103: Field Description | B103: Field Name
A104: Equity Paid Up | B104: BS_EQUITY_PAIDUP | C104: =_xll.EQNXTDZ($A$1,$B104,C$1,$B$1) -> #NAME? | D104: =_xll.EQNXTDZ($A$1,$B104,D$1,$B$1) -> #NAME? | E104: =_xll.EQNXTDZ($A$1,$B104,E$1,$B$1) -> #NAME? | F104: =_xll.EQNXTDZ($A$1,$B104,F$1,$B$1) -> #NAME? | G104: =_xll.EQNXTDZ($A$1,$B104,G$1,$B$1) -> #NAME? | H104: =_xll.EQNXTDZ($A$1,$B104,H$1,$B$1) -> #NAME? | I104: =_xll.EQNXTDZ($A$1,$B104,I$1,$B$1) -> #NAME? | J104: =_xll.EQNXTDZ($A$1,$B104,J$1,$B$1) -> #NAME? | ... AF104: =_xll.EQNXTDZ($A$1,$B104,AF$1,$B$1) -> #NAME?
A105: Face Value | B105: BS_FACE_VALUE | C105: =_xll.EQNXTDZ($A$1,$B105,C$1,$B$1) -> #NAME? | D105: =_xll.EQNXTDZ($A$1,$B105,D$1,$B$1) -> #NAME? | E105: =_xll.EQNXTDZ($A$1,$B105,E$1,$B$1) -> #NAME? | F105: =_xll.EQNXTDZ($A$1,$B105,F$1,$B$1) -> #NAME? | G105: =_xll.EQNXTDZ($A$1,$B105,G$1,$B$1) -> #NAME? | H105: =_xll.EQNXTDZ($A$1,$B105,H$1,$B$1) -> #NAME? | I105: =_xll.EQNXTDZ($A$1,$B105,I$1,$B$1) -> #NAME? | J105: =_xll.EQNXTDZ($A$1,$B105,J$1,$B$1) -> #NAME? | ... AF105: =_xll.EQNXTDZ($A$1,$B105,AF$1,$B$1) -> #NAME?
A106: Close Price (Unit Curr.) | B106: FH_YEAR_PRICE | C106: =_xll.EQNXTDZ($A$1,$B106,C$1,$B$1) -> #NAME? | D106: =_xll.EQNXTDZ($A$1,$B106,D$1,$B$1) -> #NAME? | E106: =_xll.EQNXTDZ($A$1,$B106,E$1,$B$1) -> #NAME? | F106: =_xll.EQNXTDZ($A$1,$B106,F$1,$B$1) -> #NAME? | G106: =_xll.EQNXTDZ($A$1,$B106,G$1,$B$1) -> #NAME? | H106: =_xll.EQNXTDZ($A$1,$B106,H$1,$B$1) -> #NAME? | I106: =_xll.EQNXTDZ($A$1,$B106,I$1,$B$1) -> #NAME? | J106: =_xll.EQNXTDZ($A$1,$B106,J$1,$B$1) -> #NAME? | ... AF106: =_xll.EQNXTDZ($A$1,$B106,AF$1,$B$1) -> #NAME?
A107: High Price (Unit Curr.) | B107: FH_HIGH | C107: =_xll.EQNXTDZ($A$1,$B107,C$1,$B$1) -> #NAME? | D107: =_xll.EQNXTDZ($A$1,$B107,D$1,$B$1) -> #NAME? | E107: =_xll.EQNXTDZ($A$1,$B107,E$1,$B$1) -> #NAME? | F107: =_xll.EQNXTDZ($A$1,$B107,F$1,$B$1) -> #NAME? | G107: =_xll.EQNXTDZ($A$1,$B107,G$1,$B$1) -> #NAME? | H107: =_xll.EQNXTDZ($A$1,$B107,H$1,$B$1) -> #NAME? | I107: =_xll.EQNXTDZ($A$1,$B107,I$1,$B$1) -> #NAME? | J107: =_xll.EQNXTDZ($A$1,$B107,J$1,$B$1) -> #NAME? | ... AF107: =_xll.EQNXTDZ($A$1,$B107,AF$1,$B$1) -> #NAME?
A108: Low Price (Unit Curr.) | B108: FH_LOW | C108: =_xll.EQNXTDZ($A$1,$B108,C$1,$B$1) -> #NAME? | D108: =_xll.EQNXTDZ($A$1,$B108,D$1,$B$1) -> #NAME? | E108: =_xll.EQNXTDZ($A$1,$B108,E$1,$B$1) -> #NAME? | F108: =_xll.EQNXTDZ($A$1,$B108,F$1,$B$1) -> #NAME? | G108: =_xll.EQNXTDZ($A$1,$B108,G$1,$B$1) -> #NAME? | H108: =_xll.EQNXTDZ($A$1,$B108,H$1,$B$1) -> #NAME? | I108: =_xll.EQNXTDZ($A$1,$B108,I$1,$B$1) -> #NAME? | J108: =_xll.EQNXTDZ($A$1,$B108,J$1,$B$1) -> #NAME? | ... AF108: =_xll.EQNXTDZ($A$1,$B108,AF$1,$B$1) -> #NAME?
A109: Market Capitalization | B109: FH_MCAP | C109: =_xll.EQNXTDZ($A$1,$B109,C$1,$B$1) -> #NAME? | D109: =_xll.EQNXTDZ($A$1,$B109,D$1,$B$1) -> #NAME? | E109: =_xll.EQNXTDZ($A$1,$B109,E$1,$B$1) -> #NAME? | F109: =_xll.EQNXTDZ($A$1,$B109,F$1,$B$1) -> #NAME? | G109: =_xll.EQNXTDZ($A$1,$B109,G$1,$B$1) -> #NAME? | H109: =_xll.EQNXTDZ($A$1,$B109,H$1,$B$1) -> #NAME? | I109: =_xll.EQNXTDZ($A$1,$B109,I$1,$B$1) -> #NAME? | J109: =_xll.EQNXTDZ($A$1,$B109,J$1,$B$1) -> #NAME? | ... AF109: =_xll.EQNXTDZ($A$1,$B109,AF$1,$B$1) -> #NAME?
A110: Adj DPS(Rs) | B110: FR_ADJ_DPS | C110: =_xll.EQNXTDZ($A$1,$B110,C$1,$B$1) -> #NAME? | D110: =_xll.EQNXTDZ($A$1,$B110,D$1,$B$1) -> #NAME? | E110: =_xll.EQNXTDZ($A$1,$B110,E$1,$B$1) -> #NAME? | F110: =_xll.EQNXTDZ($A$1,$B110,F$1,$B$1) -> #NAME? | G110: =_xll.EQNXTDZ($A$1,$B110,G$1,$B$1) -> #NAME? | H110: =_xll.EQNXTDZ($A$1,$B110,H$1,$B$1) -> #NAME? | I110: =_xll.EQNXTDZ($A$1,$B110,I$1,$B$1) -> #NAME? | J110: =_xll.EQNXTDZ($A$1,$B110,J$1,$B$1) -> #NAME? | ... AF110: =_xll.EQNXTDZ($A$1,$B110,AF$1,$B$1) -> #NAME?
A111: Date End | B111: SHP_DATE_END | C111: =_xll.EQNXTDZ($A$1,$B111,C$5) -> #NAME? | D111: =_xll.EQNXTDZ($A$1,$B111,D$5) -> #NAME? | E111: =_xll.EQNXTDZ($A$1,$B111,E$5) -> #NAME? | F111: =_xll.EQNXTDZ($A$1,$B111,F$5) -> #NAME? | G111: =_xll.EQNXTDZ($A$1,$B111,G$5) -> #NAME? | H111: =_xll.EQNXTDZ($A$1,$B111,H$5) -> #NAME? | I111: =_xll.EQNXTDZ($A$1,$B111,I$5) -> #NAME? | J111: =_xll.EQNXTDZ($A$1,$B111,J$5) -> #NAME? | ... AF111: =_xll.EQNXTDZ($A$1,$B111,AF$5) -> #NAME?
A112: Total of Promoter and Promoter Group | B112: SHP_TPFTOTALPROMOTER | C112: =_xll.EQNXTDZ($A$1,$B112,C$5) -> #NAME? | D112: =_xll.EQNXTDZ($A$1,$B112,D$5) -> #NAME? | E112: =_xll.EQNXTDZ($A$1,$B112,E$5) -> #NAME? | F112: =_xll.EQNXTDZ($A$1,$B112,F$5) -> #NAME? | G112: =_xll.EQNXTDZ($A$1,$B112,G$5) -> #NAME? | H112: =_xll.EQNXTDZ($A$1,$B112,H$5) -> #NAME? | I112: =_xll.EQNXTDZ($A$1,$B112,I$5) -> #NAME? | J112: =_xll.EQNXTDZ($A$1,$B112,J$5) -> #NAME? | ... AF112: =_xll.EQNXTDZ($A$1,$B112,AF$5) -> #NAME?
A113: Total of Promoter and Promoter Group Pledged | B113: SHP_PSHFTOTALPROMOTER | C113: =_xll.EQNXTDZ($A$1,$B113,C$5) -> #NAME? | D113: =_xll.EQNXTDZ($A$1,$B113,D$5) -> #NAME? | E113: =_xll.EQNXTDZ($A$1,$B113,E$5) -> #NAME? | F113: =_xll.EQNXTDZ($A$1,$B113,F$5) -> #NAME? | G113: =_xll.EQNXTDZ($A$1,$B113,G$5) -> #NAME? | H113: =_xll.EQNXTDZ($A$1,$B113,H$5) -> #NAME? | I113: =_xll.EQNXTDZ($A$1,$B113,I$5) -> #NAME? | J113: =_xll.EQNXTDZ($A$1,$B113,J$5) -> #NAME? | ... AF113: =_xll.EQNXTDZ($A$1,$B113,AF$5) -> #NAME?

Sheet QTR Share Price
A1: ='QTR Raw'!A1 -> 226159 | C1: 201206 | D1: 201207 | E1: 201208 | F1: 201209 | G1: 201210 | H1: 201211 | I1: 201212 | J1: 201301 | K1: 201302 | L1: 201303 | M1: 201304 | N1: 201305 | O1: 201306 | P1: 201307 | Q1: 201308 | R1: 201309 | S1: 201310 | T1: 201311 | U1: 201312 | V1: 201401 | W1: 201402 | X1: 201403 | Y1: 201404 | Z1: 201405 | AA1: 201406 | AB1: 201407 | AC1: 201408 | AD1: 201409 | AE1: 201410 | AF1: 201411 | AG1: 201412 | AH1: 201501 | AI1: 201502 | AJ1: 201503 | AK1: 201504 | AL1: 201505 | AM1: 201506 | AN1: 201507 | AO1: 201508 | AP1: 201509 | AQ1: 201510 | AR1: 201511 | AS1: 201512 | AT1: 201601 | AU1: 201602 | AV1: 201603 | AW1: 201604 | AX1: 201605 | AY1: 201606 | AZ1: 201607 | BA1: 201608 | BB1: 201609 | BC1: 201610 | BD1: 201611 | BE1: 201612 | BF1: 201701 | BG1: 201702 | BH1: 201703 | BI1: 201704 | BJ1: 201705 | BK1: 201706 | BL1: 201707 | BM1: 201708 | BN1: 201709 | BO1: 201710 | BP1: 201711 | BQ1: 201712 | BR1: 201801 | BS1: 201802 | BT1: 201803 | BU1: 201804 | BV1: 201805 | BW1: 201806 | BX1: 201807 | BY1: 201808 | BZ1: 201809 | CA1: 201810 | CB1: 201811 | CC1: 201812 | CD1: 201901 | CE1: 201902 | CF1: 201903 | CG1: 201904 | CH1: 201905 | CI1: 201906 | CJ1: 201907 | CK1: 201908 | CL1: 201909 | CM1: 201910 | CN1: 201911 | CO1: 201912 | CP1: 202001 | CQ1: 202002 | CR1: 202003 | CS1: 202004 | CT1: 202005 | CU1: 202006 | CV1: 202007 | CW1: 202008 | CX1: 202009 | CY1: 202010 | CZ1: 202011 | DA1: 202012 | DB1: 202101 | DC1: 202102 | DD1: 202103 | DE1: 202104 | DF1: 202105 | DG1: 202106 | DH1: 202107 | DI1: 202108 | DJ1: 202109 | DK1: 202110 | DL1: 202111 | DM1: 202112 | DN1: 202201 | DO1: 202202 | DP1: 202203 | DQ1: 202204 | DR1: 202205 | DS1: 202206 | DT1: 202207 | DU1: 202208 | DV1: 202209 | DW1: 202210 | DX1: 202211 | DY1: 202212 | DZ1: 202301 | EA1: 202302 | EB1: 202303 | EC1: 202304 | ED1: 202305 | EE1: 202306 | EF1: 202307 | EG1: 202308 | EH1: 202309 | EI1: 202310 | EJ1: 202311 | EK1: 202312 | EL1: 202401 | EM1: 202402 | EN1: 202403 | EO1: 202404 | EP1: 202405 | EQ1: 202406 | ER1: 202407 | ES1: 202408 | ET1: 202409 | EU1: 202410 | EV1: 202411 | EW1: 202412 | EX1: 202501 | EY1: 202502 | EZ1: 202503 | FA1: 202504 | FB1: 202505 | FC1: 202506 | FD1: 202507 | FE1: 202508 | FF1: 202509 | FG1: 202510 | FH1: 202511 | FI1: 202512 | FJ1: 202601 | FK1: 202602 | FL1: 202603 | FM1: 202604 | FN1: 202605 | FO1: 202606 | FP1: 202607 | FQ1: 202608 | FR1: 202609 | FS1: 202610 | FT1: 202611 | FU1: 202612 | FV1: 202701 | FW1: 202702 | FX1: 202703 | FY1: 202704 | FZ1: 202705 | GA1: 202706 | GB1: 202707 | GC1: 202708 | GD1: 202709 | GE1: 202710 | GF1: 202711 | GG1: 202712 | GH1: 202801 | GI1: 202802 | GJ1: 202803 | GK1: 202804 | GL1: 202805 | GM1: 202806 | GN1: 202807 | GO1: 202808 | GP1: 202809 | GQ1: 202810 | GR1: 202811 | GS1: 202812 | GT1: 202901 | GU1: 202902 | GV1: 202903 | GW1: 202904 | GX1: 202905 | GY1: 202906 | GZ1: 202907 | HA1: 202908 | HB1: 202909 | HC1: 202910 | HD1: 202911 | HE1: 202912 | HF1: 203001 | HG1: 203002 | HH1: 203003 | HM1: 201206 | HN1: 201207 | HO1: 201208 | HP1: 201209 | HQ1: 201212 | HR1: 201303 | HS1: 201306 | HT1: 201309 | HU1: 201312 | HV1: 201403 | HW1: 201406 | HX1: 201409 | HY1: 201412 | HZ1: 201503 | IA1: 201506 | IB1: 201509 | IC1: 201512 | ID1: 201603 | IE1: 201606 | IF1: 201609 | IG1: 201612 | IH1: 201703 | II1: 201706 | IJ1: 201709 | IK1: 201712 | IL1: 201803 | IM1: 201806 | IN1: 201809 | IO1: 201812 | IP1: 201903 | IQ1: 201906 | IR1: 201909 | IS1: 201912 | IT1: 202003 | IU1: 202006 | IV1: 202009 | IW1: 202012 | IX1: 202103 | IY1: 202106 | IZ1: 202109 | JA1: 202112 | JB1: 202203 | JC1: 202206 | JD1: 202209 | JE1: 202212 | JF1: 202303 | JG1: 202306 | JH1: 202309 | JI1: 202312 | JJ1: 202403 | JK1: 202406 | JL1: 202409 | JM1: 202412 | JN1: 202503 | JO1: 202506 | JP1: 202509 | JQ1: 202512 | JR1: 202603 | JS1: 202606 | JT1: 202609 | JU1: 202612 | JV1: 202703 | JW1: 202706 | JX1: 202709 | JY1: 202712 | JZ1: 202803 | KA1: 202806 | KB1: 202809 | KC1: 202812 | KD1: 202903 | KE1: 202906 | KF1: 202909 | KG1: 202912 | KH1: 203003
FF2: 45901 | FG2: =+EOMONTH(FF2,1) -> 45961 | FH2: =+EOMONTH(FG2,1) -> 45991 | FI2: =+EOMONTH(FH2,1) -> 46022 | FJ2: =+EOMONTH(FI2,1) -> 46053 | FK2: =+EOMONTH(FJ2,1) -> 46081 | FL2: =+EOMONTH(FK2,1) -> 46112 | FM2: =+EOMONTH(FL2,1) -> 46142 | FN2: =+EOMONTH(FM2,1) -> 46173 | ... HH2: =+EOMONTH(HG2,1) -> 47573
A4: Field Description | B4: Field Name
A5: MonthEnd | B5: NMONTH_MONTHEND | C5: {=_xll.EQNXTDZ($A$1,$B5,C$1)} -> #NAME? | D5: {=_xll.EQNXTDZ($A$1,$B5,D$1)} -> #NAME? | E5: {=_xll.EQNXTDZ($A$1,$B5,E$1)} -> #NAME? | F5: {=_xll.EQNXTDZ($A$1,$B5,F$1)} -> #NAME? | G5: {=_xll.EQNXTDZ($A$1,$B5,G$1)} -> #NAME? | H5: {=_xll.EQNXTDZ($A$1,$B5,H$1)} -> #NAME? | I5: {=_xll.EQNXTDZ($A$1,$B5,I$1)} -> #NAME? | J5: {=_xll.EQNXTDZ($A$1,$B5,J$1)} -> #NAME? | ... HH5: {=_xll.EQNXTDZ($A$1,$B5,HH$1)} -> #NAME?
A6: Open | B6: NMONTH_OPEN | C6: {=_xll.EQNXTDZ($A$1,$B6,C$1)} -> #NAME? | D6: {=_xll.EQNXTDZ($A$1,$B6,D$1)} -> #NAME? | E6: {=_xll.EQNXTDZ($A$1,$B6,E$1)} -> #NAME? | F6: {=_xll.EQNXTDZ($A$1,$B6,F$1)} -> #NAME? | G6: {=_xll.EQNXTDZ($A$1,$B6,G$1)} -> #NAME? | H6: {=_xll.EQNXTDZ($A$1,$B6,H$1)} -> #NAME? | I6: {=_xll.EQNXTDZ($A$1,$B6,I$1)} -> #NAME? | J6: {=_xll.EQNXTDZ($A$1,$B6,J$1)} -> #NAME? | ... HH6: {=_xll.EQNXTDZ($A$1,$B6,HH$1)} -> #NAME?
A7: High | B7: NMONTH_HIGH | C7: {=_xll.EQNXTDZ($A$1,$B7,C$1)} -> #NAME? | D7: {=_xll.EQNXTDZ($A$1,$B7,D$1)} -> #NAME? | E7: {=_xll.EQNXTDZ($A$1,$B7,E$1)} -> #NAME? | F7: {=_xll.EQNXTDZ($A$1,$B7,F$1)} -> #NAME? | G7: {=_xll.EQNXTDZ($A$1,$B7,G$1)} -> #NAME? | H7: {=_xll.EQNXTDZ($A$1,$B7,H$1)} -> #NAME? | I7: {=_xll.EQNXTDZ($A$1,$B7,I$1)} -> #NAME? | J7: {=_xll.EQNXTDZ($A$1,$B7,J$1)} -> #NAME? | ... HH7: {=_xll.EQNXTDZ($A$1,$B7,HH$1)} -> #NAME? | HP7: =+MAX(D7:F7) -> #NAME? | HQ7: =+MAX(G7:I7) -> #NAME? | HR7: =+MAX(J7:L7) -> #NAME? | HS7: =+MAX(M7:O7) -> #NAME? | HT7: =+MAX(P7:R7) -> #NAME? | HU7: =+MAX(S7:U7) -> #NAME? | HV7: =+MAX(V7:X7) -> #NAME? | HW7: =+MAX(Y7:AA7) -> #NAME? | HX7: =+MAX(AB7:AD7) -> #NAME? | HY7: =+MAX(AE7:AG7) -> #NAME? | HZ7: =+MAX(AH7:AJ7) -> #NAME? | IA7: =+MAX(AK7:AM7) -> #NAME? | IB7: =+MAX(AN7:AP7) -> #NAME? | IC7: =+MAX(AQ7:AS7) -> #NAME? | ID7: =+MAX(AT7:AV7) -> #NAME? | IE7: =+MAX(AW7:AY7) -> #NAME? | IF7: =+MAX(AZ7:BB7) -> #NAME? | IG7: =+MAX(BC7:BE7) -> #NAME? | IH7: =+MAX(BF7:BH7) -> #NAME? | II7: =+MAX(BI7:BK7) -> #NAME? | IJ7: =+MAX(BL7:BN7) -> #NAME? | IK7: =+MAX(BO7:BQ7) -> #NAME? | IL7: =+MAX(BR7:BT7) -> #NAME? | IM7: =+MAX(BU7:BW7) -> #NAME? | IN7: =+MAX(BX7:BZ7) -> #NAME? | IO7: =+MAX(CA7:CC7) -> #NAME? | IP7: =+MAX(CD7:CF7) -> #NAME? | IQ7: =+MAX(CG7:CI7) -> #NAME? | IR7: =+MAX(CJ7:CL7) -> #NAME? | IS7: =+MAX(CM7:CO7) -> #NAME? | IT7: =+MAX(CP7:CR7) -> #NAME? | IU7: =+MAX(CS7:CU7) -> #NAME? | IV7: =+MAX(CV7:CX7) -> #NAME? | IW7: =+MAX(CY7:DA7) -> #NAME? | IX7: =+MAX(DB7:DD7) -> #NAME? | IY7: =+MAX(DE7:DG7) -> #NAME? | IZ7: =+MAX(DH7:DJ7) -> #NAME? | JA7: =+MAX(DK7:DM7) -> #NAME? | JB7: =+MAX(DN7:DP7) -> #NAME? | JC7: =+MAX(DQ7:DS7) -> #NAME? | JD7: =+MAX(DT7:DV7) -> #NAME? | JE7: =+MAX(DW7:DY7) -> #NAME? | JF7: =+MAX(DZ7:EB7) -> #NAME? | JG7: =+MAX(EC7:EE7) -> #NAME? | JH7: =+MAX(EF7:EH7) -> #NAME? | JI7: =+MAX(EI7:EK7) -> #NAME? | JJ7: =+MAX(EL7:EN7) -> #NAME? | JK7: =MAX(EO7:EQ7) -> #NAME? | JL7: =MAX(ER7:ET7) -> #NAME? | JM7: =MAX(EU7:EW7) -> #NAME? | JN7: =MAX(EX7:EZ7) -> #NAME? | JO7: =MAX(FA7:FC7) -> #NAME? | JP7: =MAX(FD7:FF7) -> #NAME? | JQ7: =MAX(FG7:FI7) -> #NAME? | JR7: =MAX(FJ7:FL7) -> #NAME? | JS7: =MAX(FM7:FO7) -> #NAME? | JT7: =MAX(FP7:FR7) -> #NAME? | JU7: =MAX(FS7:FU7) -> #NAME? | JV7: =MAX(FV7:FX7) -> #NAME? | JW7: =MAX(FY7:GA7) -> #NAME? | JX7: =MAX(GB7:GD7) -> #NAME? | JY7: =MAX(GE7:GG7) -> #NAME? | JZ7: =MAX(GH7:GJ7) -> #NAME? | KA7: =MAX(GK7:GM7) -> #NAME? | KB7: =MAX(GN7:GP7) -> #NAME? | KC7: =MAX(GQ7:GS7) -> #NAME? | KD7: =MAX(GT7:GV7) -> #NAME? | KE7: =MAX(GW7:GY7) -> #NAME? | KF7: =MAX(GZ7:HB7) -> #NAME? | KG7: =MAX(HC7:HE7) -> #NAME? | KH7: =MAX(HF7:HH7) -> #NAME?
A8: Low | B8: NMONTH_LOW | C8: {=_xll.EQNXTDZ($A$1,$B8,C$1)} -> #NAME? | D8: {=_xll.EQNXTDZ($A$1,$B8,D$1)} -> #NAME? | E8: {=_xll.EQNXTDZ($A$1,$B8,E$1)} -> #NAME? | F8: {=_xll.EQNXTDZ($A$1,$B8,F$1)} -> #NAME? | G8: {=_xll.EQNXTDZ($A$1,$B8,G$1)} -> #NAME? | H8: {=_xll.EQNXTDZ($A$1,$B8,H$1)} -> #NAME? | I8: {=_xll.EQNXTDZ($A$1,$B8,I$1)} -> #NAME? | J8: {=_xll.EQNXTDZ($A$1,$B8,J$1)} -> #NAME? | ... HH8: {=_xll.EQNXTDZ($A$1,$B8,HH$1)} -> #NAME? | HP8: =+MIN(D8:F8) -> #NAME? | HQ8: =+MIN(G8:I8) -> #NAME? | HR8: =+MIN(J8:L8) -> #NAME? | HS8: =+MIN(M8:O8) -> #NAME? | HT8: =+MIN(P8:R8) -> #NAME? | HU8: =+MIN(S8:U8) -> #NAME? | HV8: =+MIN(V8:X8) -> #NAME? | HW8: =+MIN(Y8:AA8) -> #NAME? | HX8: =+MIN(AB8:AD8) -> #NAME? | HY8: =+MIN(AE8:AG8) -> #NAME? | HZ8: =+MIN(AH8:AJ8) -> #NAME? | IA8: =+MIN(AK8:AM8) -> #NAME? | IB8: =+MIN(AN8:AP8) -> #NAME? | IC8: =+MIN(AQ8:AS8) -> #NAME? | ID8: =+MIN(AT8:AV8) -> #NAME? | IE8: =+MIN(AW8:AY8) -> #NAME? | IF8: =+MIN(AZ8:BB8) -> #NAME? | IG8: =+MIN(BC8:BE8) -> #NAME? | IH8: =+MIN(BF8:BH8) -> #NAME? | II8: =+MIN(BI8:BK8) -> #NAME? | IJ8: =+MIN(BL8:BN8) -> #NAME? | IK8: =+MIN(BO8:BQ8) -> #NAME? | IL8: =+MIN(BR8:BT8) -> #NAME? | IM8: =+MIN(BU8:BW8) -> #NAME? | IN8: =+MIN(BX8:BZ8) -> #NAME? | IO8: =+MIN(CA8:CC8) -> #NAME? | IP8: =+MIN(CD8:CF8) -> #NAME? | IQ8: =+MIN(CG8:CI8) -> #NAME? | IR8: =+MIN(CJ8:CL8) -> #NAME? | IS8: =+MIN(CM8:CO8) -> #NAME? | IT8: =+MIN(CP8:CR8) -> #NAME? | IU8: =+MIN(CS8:CU8) -> #NAME? | IV8: =+MIN(CV8:CX8) -> #NAME? | IW8: =+MIN(CY8:DA8) -> #NAME? | IX8: =+MIN(DB8:DD8) -> #NAME? | IY8: =+MIN(DE8:DG8) -> #NAME? | IZ8: =+MIN(DH8:DJ8) -> #NAME? | JA8: =+MIN(DK8:DM8) -> #NAME? | JB8: =+MIN(DN8:DP8) -> #NAME? | JC8: =+MIN(DQ8:DS8) -> #NAME? | JD8: =+MIN(DT8:DV8) -> #NAME? | JE8: =+MIN(DW8:DY8) -> #NAME? | JF8: =+MIN(DZ8:EB8) -> #NAME? | JG8: =+MIN(EC8:EE8) -> #NAME? | JH8: =+MIN(EF8:EH8) -> #NAME? | JI8: =+MIN(EI8:EK8) -> #NAME? | JJ8: =+MIN(EL8:EN8) -> #NAME? | JK8: =MIN(EO8:EQ8) -> #NAME? | JL8: =MIN(ER8:ET8) -> #NAME? | JM8: =MIN(EU8:EW8) -> #NAME? | JN8: =MIN(EX8:EZ8) -> #NAME? | JO8: =MIN(FA8:FC8) -> #NAME? | JP8: =MIN(FD8:FF8) -> #NAME? | JQ8: =MIN(FG8:FI8) -> #NAME? | JR8: =MIN(FJ8:FL8) -> #NAME? | JS8: =MIN(FM8:FO8) -> #NAME? | JT8: =MIN(FP8:FR8) -> #NAME? | JU8: =MIN(FS8:FU8) -> #NAME? | JV8: =MIN(FV8:FX8) -> #NAME? | JW8: =MIN(FY8:GA8) -> #NAME? | JX8: =MIN(GB8:GD8) -> #NAME? | JY8: =MIN(GE8:GG8) -> #NAME? | JZ8: =MIN(GH8:GJ8) -> #NAME? | KA8: =MIN(GK8:GM8) -> #NAME? | KB8: =MIN(GN8:GP8) -> #NAME? | KC8: =MIN(GQ8:GS8) -> #NAME? | KD8: =MIN(GT8:GV8) -> #NAME? | KE8: =MIN(GW8:GY8) -> #NAME? | KF8: =MIN(GZ8:HB8) -> #NAME? | KG8: =MIN(HC8:HE8) -> #NAME? | KH8: =MIN(HF8:HH8) -> #NAME?
A9: Close | B9: NMONTH_CLOSE | C9: {=_xll.EQNXTDZ($A$1,$B9,C$1)} -> #NAME? | D9: {=_xll.EQNXTDZ($A$1,$B9,D$1)} -> #NAME? | E9: {=_xll.EQNXTDZ($A$1,$B9,E$1)} -> #NAME? | F9: {=_xll.EQNXTDZ($A$1,$B9,F$1)} -> #NAME? | G9: {=_xll.EQNXTDZ($A$1,$B9,G$1)} -> #NAME? | H9: {=_xll.EQNXTDZ($A$1,$B9,H$1)} -> #NAME? | I9: {=_xll.EQNXTDZ($A$1,$B9,I$1)} -> #NAME? | J9: {=_xll.EQNXTDZ($A$1,$B9,J$1)} -> #NAME? | ... HH9: {=_xll.EQNXTDZ($A$1,$B9,HH$1)} -> #NAME? | HP9: =+F9 -> #NAME? | HQ9: =+I9 -> #NAME? | HR9: =+L9 -> #NAME? | HS9: =+O9 -> #NAME? | HT9: =+R9 -> #NAME? | HU9: =+U9 -> #NAME? | HV9: =+X9 -> #NAME? | HW9: =+AA9 -> #NAME? | HX9: =+AD9 -> #NAME? | HY9: =+AG9 -> #NAME? | HZ9: =+AJ9 -> #NAME? | IA9: =+AM9 -> #NAME? | IB9: =+AP9 -> #NAME? | IC9: =+AS9 -> #NAME? | ID9: =+AV9 -> #NAME? | IE9: =+AY9 -> #NAME? | IF9: =+BB9 -> #NAME? | IG9: =+BE9 -> #NAME? | IH9: =+BH9 -> #NAME? | II9: =+BK9 -> #NAME? | IJ9: =+BN9 -> #NAME? | IK9: =+BQ9 -> #NAME? | IL9: =+BT9 -> #NAME? | IM9: =+BW9 -> #NAME? | IN9: =+BZ9 -> #NAME? | IO9: =+CC9 -> #NAME? | IP9: =+CF9 -> #NAME? | IQ9: =+CI9 -> #NAME? | IR9: =+CL9 -> #NAME? | IS9: =+CO9 -> #NAME? | IT9: =+CR9 -> #NAME? | IU9: =+CU9 -> #NAME? | IV9: =+CX9 -> #NAME? | IW9: =+DA9 -> #NAME? | IX9: =+DD9 -> #NAME? | IY9: =+DG9 -> #NAME? | IZ9: =+DJ9 -> #NAME? | JA9: =+DM9 -> #NAME? | JB9: =+DP9 -> #NAME? | JC9: =+DS9 -> #NAME? | JD9: =+DV9 -> #NAME? | JE9: =+DY9 -> #NAME? | JF9: =+EB9 -> #NAME? | JG9: =+EE9 -> #NAME? | JH9: =+EH9 -> #NAME? | JI9: =+EK9 -> #NAME? | JJ9: =+EN9 -> #NAME? | JK9: =EQ9 -> #NAME? | JL9: =ET9 -> #NAME? | JM9: =EW9 -> #NAME? | JN9: =EZ9 -> #NAME? | JO9: =FC9 -> #NAME? | JP9: =FF9 -> #NAME? | JQ9: =FI9 -> #NAME? | JR9: =FL9 -> #NAME? | JS9: =FO9 -> #NAME? | JT9: =FR9 -> #NAME? | JU9: =FU9 -> #NAME? | JV9: =FX9 -> #NAME? | JW9: =GA9 -> #NAME? | JX9: =GD9 -> #NAME? | JY9: =GG9 -> #NAME? | JZ9: =GJ9 -> #NAME? | KA9: =GM9 -> #NAME? | KB9: =GP9 -> #NAME? | KC9: =GS9 -> #NAME? | KD9: =GV9 -> #NAME? | KE9: =GY9 -> #NAME? | KF9: =HB9 -> #NAME? | KG9: =HE9 -> #NAME? | KH9: =HH9 -> #NAME?
A11: Field Description | B11: Field Name | C11: {=_xll.EQNXTDZ($A$1,$B11,C$1)} -> #NAME? | D11: {=_xll.EQNXTDZ($A$1,$B11,D$1)} -> #NAME? | E11: {=_xll.EQNXTDZ($A$1,$B11,E$1)} -> #NAME? | F11: {=_xll.EQNXTDZ($A$1,$B11,F$1)} -> #NAME? | G11: {=_xll.EQNXTDZ($A$1,$B11,G$1)} -> #NAME? | H11: {=_xll.EQNXTDZ($A$1,$B11,H$1)} -> #NAME? | I11: {=_xll.EQNXTDZ($A$1,$B11,I$1)} -> #NAME? | J11: {=_xll.EQNXTDZ($A$1,$B11,J$1)} -> #NAME? | ... HH11: {=_xll.EQNXTDZ($A$1,$B11,HH$1)} -> #NAME?
A12: Month End | B12: BMONTH_MONTHEND | C12: {=_xll.EQNXTDZ($A$1,$B12,C$1)} -> #NAME? | D12: {=_xll.EQNXTDZ($A$1,$B12,D$1)} -> #NAME? | E12: {=_xll.EQNXTDZ($A$1,$B12,E$1)} -> #NAME? | F12: {=_xll.EQNXTDZ($A$1,$B12,F$1)} -> #NAME? | G12: {=_xll.EQNXTDZ($A$1,$B12,G$1)} -> #NAME? | H12: {=_xll.EQNXTDZ($A$1,$B12,H$1)} -> #NAME? | I12: {=_xll.EQNXTDZ($A$1,$B12,I$1)} -> #NAME? | J12: {=_xll.EQNXTDZ($A$1,$B12,J$1)} -> #NAME? | ... HH12: {=_xll.EQNXTDZ($A$1,$B12,HH$1)} -> #NAME?
A13: Open | B13: BMONTH_OPEN | C13: {=_xll.EQNXTDZ($A$1,$B13,C$1)} -> #NAME? | D13: {=_xll.EQNXTDZ($A$1,$B13,D$1)} -> #NAME? | E13: {=_xll.EQNXTDZ($A$1,$B13,E$1)} -> #NAME? | F13: {=_xll.EQNXTDZ($A$1,$B13,F$1)} -> #NAME? | G13: {=_xll.EQNXTDZ($A$1,$B13,G$1)} -> #NAME? | H13: {=_xll.EQNXTDZ($A$1,$B13,H$1)} -> #NAME? | I13: {=_xll.EQNXTDZ($A$1,$B13,I$1)} -> #NAME? | J13: {=_xll.EQNXTDZ($A$1,$B13,J$1)} -> #NAME? | ... HH13: {=_xll.EQNXTDZ($A$1,$B13,HH$1)} -> #NAME?
A14: High | B14: BMONTH_HIGH | C14: {=_xll.EQNXTDZ($A$1,$B14,C$1)} -> #NAME? | D14: {=_xll.EQNXTDZ($A$1,$B14,D$1)} -> #NAME? | E14: {=_xll.EQNXTDZ($A$1,$B14,E$1)} -> #NAME? | F14: {=_xll.EQNXTDZ($A$1,$B14,F$1)} -> #NAME? | G14: {=_xll.EQNXTDZ($A$1,$B14,G$1)} -> #NAME? | H14: {=_xll.EQNXTDZ($A$1,$B14,H$1)} -> #NAME? | I14: {=_xll.EQNXTDZ($A$1,$B14,I$1)} -> #NAME? | J14: {=_xll.EQNXTDZ($A$1,$B14,J$1)} -> #NAME? | ... HH14: {=_xll.EQNXTDZ($A$1,$B14,HH$1)} -> #NAME? | HP14: =+MAX(D14:F14) -> #NAME? | HQ14: =+MAX(G14:I14) -> #NAME? | HR14: =+MAX(J14:L14) -> #NAME? | HS14: =+MAX(M14:O14) -> #NAME? | HT14: =+MAX(P14:R14) -> #NAME? | HU14: =+MAX(S14:U14) -> #NAME? | HV14: =+MAX(V14:X14) -> #NAME? | HW14: =+MAX(Y14:AA14) -> #NAME? | HX14: =+MAX(AB14:AD14) -> #NAME? | HY14: =+MAX(AE14:AG14) -> #NAME? | HZ14: =+MAX(AH14:AJ14) -> #NAME? | IA14: =+MAX(AK14:AM14) -> #NAME? | IB14: =+MAX(AN14:AP14) -> #NAME? | IC14: =+MAX(AQ14:AS14) -> #NAME? | ID14: =+MAX(AT14:AV14) -> #NAME? | IE14: =+MAX(AW14:AY14) -> #NAME? | IF14: =+MAX(AZ14:BB14) -> #NAME? | IG14: =+MAX(BC14:BE14) -> #NAME? | IH14: =+MAX(BF14:BH14) -> #NAME? | II14: =+MAX(BI14:BK14) -> #NAME? | IJ14: =+MAX(BL14:BN14) -> #NAME? | IK14: =+MAX(BO14:BQ14) -> #NAME? | IL14: =+MAX(BR14:BT14) -> #NAME? | IM14: =+MAX(BU14:BW14) -> #NAME? | IN14: =+MAX(BX14:BZ14) -> #NAME? | IO14: =+MAX(CA14:CC14) -> #NAME? | IP14: =+MAX(CD14:CF14) -> #NAME? | IQ14: =+MAX(CG14:CI14) -> #NAME? | IR14: =+MAX(CJ14:CL14) -> #NAME? | IS14: =+MAX(CM14:CO14) -> #NAME? | IT14: =+MAX(CP14:CR14) -> #NAME? | IU14: =+MAX(CS14:CU14) -> #NAME? | IV14: =+MAX(CV14:CX14) -> #NAME? | IW14: =+MAX(CY14:DA14) -> #NAME? | IX14: =+MAX(DB14:DD14) -> #NAME? | IY14: =+MAX(DE14:DG14) -> #NAME? | IZ14: =+MAX(DH14:DJ14) -> #NAME? | JA14: =+MAX(DK14:DM14) -> #NAME? | JB14: =+MAX(DN14:DP14) -> #NAME? | JC14: =+MAX(DQ14:DS14) -> #NAME? | JD14: =+MAX(DT14:DV14) -> #NAME? | JE14: =+MAX(DW14:DY14) -> #NAME? | JF14: =+MAX(DZ14:EB14) -> #NAME? | JG14: =+MAX(EC14:EE14) -> #NAME? | JH14: =+MAX(EF14:EH14) -> #NAME? | JI14: =+MAX(EI14:EK14) -> #NAME? | JJ14: =+MAX(EL14:EN14) -> #NAME? | JK14: =MAX(EO14:EQ14) -> #NAME? | JL14: =MAX(ER14:ET14) -> #NAME? | JM14: =MAX(EU14:EW14) -> #NAME? | JN14: =MAX(EX14:EZ14) -> #NAME? | JO14: =MAX(FA14:FC14) -> #NAME? | JP14: =MAX(FD14:FF14) -> #NAME? | JQ14: =MAX(FG14:FI14) -> #NAME? | JR14: =MAX(FJ14:FL14) -> #NAME? | JS14: =MAX(FM14:FO14) -> #NAME? | JT14: =MAX(FP14:FR14) -> #NAME? | JU14: =MAX(FS14:FU14) -> #NAME? | JV14: =MAX(FV14:FX14) -> #NAME? | JW14: =MAX(FY14:GA14) -> #NAME? | JX14: =MAX(GB14:GD14) -> #NAME? | JY14: =MAX(GE14:GG14) -> #NAME? | JZ14: =MAX(GH14:GJ14) -> #NAME? | KA14: =MAX(GK14:GM14) -> #NAME? | KB14: =MAX(GN14:GP14) -> #NAME? | KC14: =MAX(GQ14:GS14) -> #NAME? | KD14: =MAX(GT14:GV14) -> #NAME? | KE14: =MAX(GW14:GY14) -> #NAME? | KF14: =MAX(GZ14:HB14) -> #NAME? | KG14: =MAX(HC14:HE14) -> #NAME? | KH14: =MAX(HF14:HH14) -> #NAME?
A15: Low | B15: BMONTH_LOW | C15: {=_xll.EQNXTDZ($A$1,$B15,C$1)} -> #NAME? | D15: {=_xll.EQNXTDZ($A$1,$B15,D$1)} -> #NAME? | E15: {=_xll.EQNXTDZ($A$1,$B15,E$1)} -> #NAME? | F15: {=_xll.EQNXTDZ($A$1,$B15,F$1)} -> #NAME? | G15: {=_xll.EQNXTDZ($A$1,$B15,G$1)} -> #NAME? | H15: {=_xll.EQNXTDZ($A$1,$B15,H$1)} -> #NAME? | I15: {=_xll.EQNXTDZ($A$1,$B15,I$1)} -> #NAME? | J15: {=_xll.EQNXTDZ($A$1,$B15,J$1)} -> #NAME? | ... HH15: {=_xll.EQNXTDZ($A$1,$B15,HH$1)} -> #NAME? | HP15: =+MIN(D15:F15) -> #NAME? | HQ15: =+MIN(G15:I15) -> #NAME? | HR15: =+MIN(J15:L15) -> #NAME? | HS15: =+MIN(M15:O15) -> #NAME? | HT15: =+MIN(P15:R15) -> #NAME? | HU15: =+MIN(S15:U15) -> #NAME? | HV15: =+MIN(V15:X15) -> #NAME? | HW15: =+MIN(Y15:AA15) -> #NAME? | HX15: =+MIN(AB15:AD15) -> #NAME? | HY15: =+MIN(AE15:AG15) -> #NAME? | HZ15: =+MIN(AH15:AJ15) -> #NAME? | IA15: =+MIN(AK15:AM15) -> #NAME? | IB15: =+MIN(AN15:AP15) -> #NAME? | IC15: =+MIN(AQ15:AS15) -> #NAME? | ID15: =+MIN(AT15:AV15) -> #NAME? | IE15: =+MIN(AW15:AY15) -> #NAME? | IF15: =+MIN(AZ15:BB15) -> #NAME? | IG15: =+MIN(BC15:BE15) -> #NAME? | IH15: =+MIN(BF15:BH15) -> #NAME? | II15: =+MIN(BI15:BK15) -> #NAME? | IJ15: =+MIN(BL15:BN15) -> #NAME? | IK15: =+MIN(BO15:BQ15) -> #NAME? | IL15: =+MIN(BR15:BT15) -> #NAME? | IM15: =+MIN(BU15:BW15) -> #NAME? | IN15: =+MIN(BX15:BZ15) -> #NAME? | IO15: =+MIN(CA15:CC15) -> #NAME? | IP15: =+MIN(CD15:CF15) -> #NAME? | IQ15: =+MIN(CG15:CI15) -> #NAME? | IR15: =+MIN(CJ15:CL15) -> #NAME? | IS15: =+MIN(CM15:CO15) -> #NAME? | IT15: =+MIN(CP15:CR15) -> #NAME? | IU15: =+MIN(CS15:CU15) -> #NAME? | IV15: =+MIN(CV15:CX15) -> #NAME? | IW15: =+MIN(CY15:DA15) -> #NAME? | IX15: =+MIN(DB15:DD15) -> #NAME? | IY15: =+MIN(DE15:DG15) -> #NAME? | IZ15: =+MIN(DH15:DJ15) -> #NAME? | JA15: =+MIN(DK15:DM15) -> #NAME? | JB15: =+MIN(DN15:DP15) -> #NAME? | JC15: =+MIN(DQ15:DS15) -> #NAME? | JD15: =+MIN(DT15:DV15) -> #NAME? | JE15: =+MIN(DW15:DY15) -> #NAME? | JF15: =+MIN(DZ15:EB15) -> #NAME? | JG15: =+MIN(EC15:EE15) -> #NAME? | JH15: =+MIN(EF15:EH15) -> #NAME? | JI15: =+MIN(EI15:EK15) -> #NAME? | JJ15: =+MIN(EL15:EN15) -> #NAME? | JK15: =MIN(EO15:EQ15) -> #NAME? | JL15: =MIN(ER15:ET15) -> #NAME? | JM15: =MIN(EU15:EW15) -> #NAME? | JN15: =MIN(EX15:EZ15) -> #NAME? | JO15: =MIN(FA15:FC15) -> #NAME? | JP15: =MIN(FD15:FF15) -> #NAME? | JQ15: =MIN(FG15:FI15) -> #NAME? | JR15: =MIN(FJ15:FL15) -> #NAME? | JS15: =MIN(FM15:FO15) -> #NAME? | JT15: =MIN(FP15:FR15) -> #NAME? | JU15: =MIN(FS15:FU15) -> #NAME? | JV15: =MIN(FV15:FX15) -> #NAME? | JW15: =MIN(FY15:GA15) -> #NAME? | JX15: =MIN(GB15:GD15) -> #NAME? | JY15: =MIN(GE15:GG15) -> #NAME? | JZ15: =MIN(GH15:GJ15) -> #NAME? | KA15: =MIN(GK15:GM15) -> #NAME? | KB15: =MIN(GN15:GP15) -> #NAME? | KC15: =MIN(GQ15:GS15) -> #NAME? | KD15: =MIN(GT15:GV15) -> #NAME? | KE15: =MIN(GW15:GY15) -> #NAME? | KF15: =MIN(GZ15:HB15) -> #NAME? | KG15: =MIN(HC15:HE15) -> #NAME? | KH15: =MIN(HF15:HH15) -> #NAME?
A16: Close | B16: BMONTH_CLOSE | C16: {=_xll.EQNXTDZ($A$1,$B16,C$1)} -> #NAME? | D16: {=_xll.EQNXTDZ($A$1,$B16,D$1)} -> #NAME? | E16: {=_xll.EQNXTDZ($A$1,$B16,E$1)} -> #NAME? | F16: {=_xll.EQNXTDZ($A$1,$B16,F$1)} -> #NAME? | G16: {=_xll.EQNXTDZ($A$1,$B16,G$1)} -> #NAME? | H16: {=_xll.EQNXTDZ($A$1,$B16,H$1)} -> #NAME? | I16: {=_xll.EQNXTDZ($A$1,$B16,I$1)} -> #NAME? | J16: {=_xll.EQNXTDZ($A$1,$B16,J$1)} -> #NAME? | ... HH16: {=_xll.EQNXTDZ($A$1,$B16,HH$1)} -> #NAME? | HP16: =+F16 -> #NAME? | HQ16: =+I16 -> #NAME? | HR16: =+L16 -> #NAME? | HS16: =+O16 -> #NAME? | HT16: =+R16 -> #NAME? | HU16: =+U16 -> #NAME? | HV16: =+X16 -> #NAME? | HW16: =+AA16 -> #NAME? | HX16: =+AD16 -> #NAME? | HY16: =+AG16 -> #NAME? | HZ16: =+AJ16 -> #NAME? | IA16: =+AM16 -> #NAME? | IB16: =+AP16 -> #NAME? | IC16: =+AS16 -> #NAME? | ID16: =+AV16 -> #NAME? | IE16: =+AY16 -> #NAME? | IF16: =+BB16 -> #NAME? | IG16: =+BE16 -> #NAME? | IH16: =+BH16 -> #NAME? | II16: =+BK16 -> #NAME? | IJ16: =+BN16 -> #NAME? | IK16: =+BQ16 -> #NAME? | IL16: =+BT16 -> #NAME? | IM16: =+BW16 -> #NAME? | IN16: =+BZ16 -> #NAME? | IO16: =+CC16 -> #NAME? | IP16: =+CF16 -> #NAME? | IQ16: =+CI16 -> #NAME? | IR16: =+CL16 -> #NAME? | IS16: =+CO16 -> #NAME? | IT16: =+CR16 -> #NAME? | IU16: =+CU16 -> #NAME? | IV16: =+CX16 -> #NAME? | IW16: =+DA16 -> #NAME? | IX16: =+DD16 -> #NAME? | IY16: =+DG16 -> #NAME? | IZ16: =+DJ16 -> #NAME? | JA16: =+DM16 -> #NAME? | JB16: =+DP16 -> #NAME? | JC16: =+DS16 -> #NAME? | JD16: =+DV16 -> #NAME? | JE16: =+DY16 -> #NAME? | JF16: =+EB16 -> #NAME? | JG16: =+EE16 -> #NAME? | JH16: =+EH16 -> #NAME? | JI16: =+EK16 -> #NAME? | JJ16: =+EN16 -> #NAME? | JK16: =EQ16 -> #NAME? | JL16: =ET16 -> #NAME? | JM16: =EW16 -> #NAME? | JN16: =EZ16 -> #NAME? | JO16: =FC16 -> #NAME? | JP16: =FF16 -> #NAME? | JQ16: =FI16 -> #NAME? | JR16: =FL16 -> #NAME? | JS16: =FO16 -> #NAME? | JT16: =FR16 -> #NAME? | JU16: =FU16 -> #NAME? | JV16: =FX16 -> #NAME? | JW16: =GA16 -> #NAME? | JX16: =GD16 -> #NAME? | JY16: =GG16 -> #NAME? | JZ16: =GJ16 -> #NAME? | KA16: =GM16 -> #NAME? | KB16: =GP16 -> #NAME? | KC16: =GS16 -> #NAME? | KD16: =GV16 -> #NAME? | KE16: =GY16 -> #NAME? | KF16: =HB16 -> #NAME? | KG16: =HE16 -> #NAME? | KH16: =HH16 -> #NAME?
A19: High | HP19: =+IF(HP14=0,HP7,HP14) -> #NAME? | HQ19: =+IF(HQ14=0,HQ7,HQ14) -> #NAME? | HR19: =+IF(HR14=0,HR7,HR14) -> #NAME? | HS19: =+IF(HS14=0,HS7,HS14) -> #NAME? | HT19: =+IF(HT14=0,HT7,HT14) -> #NAME? | HU19: =+IF(HU14=0,HU7,HU14) -> #NAME? | HV19: =+IF(HV14=0,HV7,HV14) -> #NAME? | HW19: =+IF(HW14=0,HW7,HW14) -> #NAME? | ... KH19: =+IF(KH14=0,KH7,KH14) -> #NAME?
A20: Low | HP20: =+IF(HP15=0,HP8,HP15) -> #NAME? | HQ20: =+IF(HQ15=0,HQ8,HQ15) -> #NAME? | HR20: =+IF(HR15=0,HR8,HR15) -> #NAME? | HS20: =+IF(HS15=0,HS8,HS15) -> #NAME? | HT20: =+IF(HT15=0,HT8,HT15) -> #NAME? | HU20: =+IF(HU15=0,HU8,HU15) -> #NAME? | HV20: =+IF(HV15=0,HV8,HV15) -> #NAME? | HW20: =+IF(HW15=0,HW8,HW15) -> #NAME? | ... KH20: =+IF(KH15=0,KH8,KH15) -> #NAME?
A21: Close | HP21: =+IF(HP16=0,HP9,HP16) -> #NAME? | HQ21: =+IF(HQ16=0,HQ9,HQ16) -> #NAME? | HR21: =+IF(HR16=0,HR9,HR16) -> #NAME? | HS21: =+IF(HS16=0,HS9,HS16) -> #NAME? | HT21: =+IF(HT16=0,HT9,HT16) -> #NAME? | HU21: =+IF(HU16=0,HU9,HU16) -> #NAME? | HV21: =+IF(HV16=0,HV9,HV16) -> #NAME? | HW21: =+IF(HW16=0,HW9,HW16) -> #NAME? | ... KH21: =+IF(KH16=0,KH9,KH16) -> #NAME?

Sheet QTR No. of Shares
A1: ='QTR Raw'!A1 -> 226159 | C1: 201206 | D1: 201209 | E1: 201212 | F1: 201303 | G1: 201306 | H1: 201309 | I1: 201312 | J1: 201403 | K1: 201406 | L1: 201409 | M1: 201412 | N1: 201503 | O1: 201506 | P1: 201509 | Q1: 201512 | R1: 201603 | S1: 201606 | T1: 201609 | U1: 201612 | V1: 201703 | W1: 201706 | X1: 201709 | Y1: 201712 | Z1: 201803 | AA1: 201806 | AB1: 201809 | AC1: 201812 | AD1: 201903 | AE1: 201906 | AF1: 201909 | AG1: 201912 | AH1: 202003 | AI1: 202006 | AJ1: 202009 | AK1: 202012 | AL1: 202103 | AM1: 202106 | AN1: 202109 | AO1: 202112 | AP1: 202203 | AQ1: 202206 | AR1: 202209 | AS1: 202212 | AT1: 202303 | AU1: 202306 | AV1: 202309 | AW1: 202312 | AX1: 202403 | AY1: 202406
A4: Field Description | B4: Field Name
A5: Date End | B5: SHP_DATE_END | C5: {=_xll.EQNXTDZ($A$1,$B5,C$1)} -> #NAME? | D5: {=_xll.EQNXTDZ($A$1,$B5,D$1)} -> #NAME? | E5: {=_xll.EQNXTDZ($A$1,$B5,E$1)} -> #NAME? | F5: {=_xll.EQNXTDZ($A$1,$B5,F$1)} -> #NAME? | G5: {=_xll.EQNXTDZ($A$1,$B5,G$1)} -> #NAME? | H5: {=_xll.EQNXTDZ($A$1,$B5,H$1)} -> #NAME? | I5: {=_xll.EQNXTDZ($A$1,$B5,I$1)} -> #NAME? | J5: {=_xll.EQNXTDZ($A$1,$B5,J$1)} -> #NAME? | ... AY5: {=_xll.EQNXTDZ($A$1,$B5,AY$1)} -> #NAME?
A6: Grand Total | B6: SHP_NSGRANDTOTAL | C6: {=_xll.EQNXTDZ($A$1,$B6,C$1)} -> #NAME? | D6: {=_xll.EQNXTDZ($A$1,$B6,D$1)} -> #NAME? | E6: {=_xll.EQNXTDZ($A$1,$B6,E$1)} -> #NAME? | F6: {=_xll.EQNXTDZ($A$1,$B6,F$1)} -> #NAME? | G6: {=_xll.EQNXTDZ($A$1,$B6,G$1)} -> #NAME? | H6: {=_xll.EQNXTDZ($A$1,$B6,H$1)} -> #NAME? | I6: {=_xll.EQNXTDZ($A$1,$B6,I$1)} -> #NAME? | J6: {=_xll.EQNXTDZ($A$1,$B6,J$1)} -> #NAME? | ... AY6: {=_xll.EQNXTDZ($A$1,$B6,AY$1)} -> #NAME?
B7: In Crs. | C7: =+C6/10^7 -> #NAME? | D7: =+D6/10^7 -> #NAME? | E7: =+E6/10^7 -> #NAME? | F7: =+F6/10^7 -> #NAME? | G7: =+G6/10^7 -> #NAME? | H7: =+H6/10^7 -> #NAME? | I7: =+I6/10^7 -> #NAME? | J7: =+J6/10^7 -> #NAME? | ... AY7: =+AY6/10^7 -> #NAME?

Sheet Share price Daily
A1: =_xll.EQNXTH(B1,"[ADJC];[ADJH];[ADJL];[ADJO];[UCLS];[VOLUME]","2015-Jan-01","Y","All traded days","Asc") -> #NAME? | B1: =+'Annual Raw'!A1 -> 226159 | L1: =_xll.EQNXTH(B1,"[NADJC];[NADJH];[NADJLOW];[NADJOPEN];[NUCLOSE];[NVOLUME]","2015-Jan-01","Y","All traded days","Asc") -> #NAME?
A2: Anand Rathi Share & Stock Brokers Ltd. | L2: Anand Rathi Share & Stock Brokers Ltd.
A3: DATE | B3: ADJHIGH | C3: ADJCLOSE | D3: ADJLOW | E3: ADJOPEN | F3: CLOSE | G3: VOLUME | L3: DATE | M3: ADJCLOSE | N3: ADJHIGH | O3: ADJLOW | P3: ADJOPEN | Q3: CLOSE | R3: VOLUME
A4: 45930 | B4: 458.5 | C4: 445.65 | D4: 432 | E4: 432.1 | F4: 445.65 | G4: 1979965 | L4: 45930 | M4: 445.55 | N4: 458.7 | O4: 431 | P4: 432 | Q4: 445.55 | R4: 21291574
A5: 45931 | B5: 466.5 | C5: 451.5 | D5: 444.4 | E5: 444.4 | F5: 451.5 | G5: 619397 | L5: 45931 | M5: 451.75 | N5: 466.8 | O5: 445 | P5: 445 | Q5: 451.75 | R5: 5420031
A6: 45933 | B6: 471.85 | C6: 460.05 | D6: 447.2 | E6: 453.95 | F6: 460.05 | G6: 229647 | L6: 45933 | M6: 460 | N6: 471.65 | O6: 447.05 | P6: 454 | Q6: 460 | R6: 2806999
A7: 45936 | B7: 463.1 | C7: 450.75 | D7: 448.05 | E7: 460.25 | F7: 450.75 | G7: 162286 | L7: 45936 | M7: 450.7 | N7: 462.9 | O7: 448 | P7: 461.8 | Q7: 450.7 | R7: 1086849
A8: 45937 | B8: 455.9 | C8: 446.3 | D8: 441 | E8: 451 | F8: 446.3 | G8: 126162 | L8: 45937 | M8: 446.1 | N8: 455.65 | O8: 441 | P8: 450.85 | Q8: 446.1 | R8: 758856
A9: 45938 | B9: 449 | C9: 445.15 | D9: 442.8 | E9: 445.25 | F9: 445.15 | G9: 88118 | L9: 45938 | M9: 445.15 | N9: 449.75 | O9: 442.95 | P9: 445.7 | Q9: 445.15 | R9: 416377
A10: 45939 | B10: 454.65 | C10: 444.95 | D10: 441.65 | E10: 447.8 | F10: 444.95 | G10: 72131 | L10: 45939 | M10: 445.1 | N10: 454.95 | O10: 441.55 | P10: 444.75 | Q10: 445.1 | R10: 586027
A11: 45940 | B11: 464.25 | C11: 450.2 | D11: 445.35 | E11: 450.8 | F11: 450.2 | G11: 106655 | L11: 45940 | M11: 449.7 | N11: 464.8 | O11: 445.1 | P11: 445.25 | Q11: 449.7 | R11: 938593
A12: 45943 | B12: 458.15 | C12: 451.4 | D12: 448 | E12: 448.05 | F12: 451.4 | G12: 67427 | L12: 45943 | M12: 451.9 | N12: 458.6 | O12: 448.25 | P12: 449 | Q12: 451.9 | R12: 476710
A13: 45944 | B13: 477.55 | C13: 464.6 | D13: 453.7 | E13: 453.7 | F13: 464.6 | G13: 141797 | L13: 45944 | M13: 464.95 | N13: 478.1 | O13: 454.7 | P13: 455 | Q13: 464.95 | R13: 1870827
A14: 45945 | B14: 471.75 | C14: 464.1 | D14: 460.95 | E14: 466 | F14: 464.1 | G14: 80475 | L14: 45945 | M14: 465.65 | N14: 471.5 | O14: 460 | P14: 470.05 | Q14: 465.65 | R14: 674754
A15: 45946 | B15: 498.05 | C15: 487.55 | D15: 467 | E15: 470.5 | F15: 487.55 | G15: 238017 | L15: 45946 | M15: 487.45 | N15: 497.9 | O15: 467.25 | P15: 469.4 | Q15: 487.45 | R15: 2508533
... A2722: 46010 | B2722: 939 | C2722: 932.5 | D2722: 906.25 | E2722: 910.9 | F2722: 932.5 | G2722: 8862 | L2722: 46010 | M2722: 936.6 | N2722: 938.9 | O2722: 905 | P2722: 905 | Q2722: 936.6 | R2722: 296202

Sheet Sheet2
J19: 219.3 | K19: 186.25 | L19: 186.75
J20: 192.9 | K20: 135.5 | L20: 146.9 | N20: 219.3 | O20: 192.9 | P20: 186 | Q20: 178.7 | R20: 207 | S20: 255.15 | T20: 348.25 | U20: 374 | V20: 495.9 | W20: 659.9 | X20: 613.4 | Y20: 607.9 | Z20: 555.95 | AA20: 497.8 | AB20: 459.9 | AC20: 374 | AD20: 362 | AE20: 341.5 | AF20: 384.2 | AG20: 433.8 | AH20: 460 | AI20: 474.4 | AJ20: 414.4 | AK20: 318.7 | AL20: 303.25 | AM20: 332.7 | AN20: 295 | AO20: 247 | AP20: 214.4 | AQ20: 179.5 | AR20: 97.9 | AS20: 119.1 | AT20: 130.65 | AU20: 148.55 | AV20: 153.8 | AW20: 152.9 | AX20: 136 | AY20: 141.15 | AZ20: 128.1 | BA20: 142.5 | BB20: 143.55 | BC20: 124.5 | BD20: 241 | BE20: 450 | BF20: 503.35
J21: 186 | K21: 145.4 | L21: 169.1 | N21: 186.25 | O21: 135.5 | P21: 145.4 | Q21: 108.95 | R21: 137 | S21: 170 | T21: 243.15 | U21: 307.5 | V21: 325.1 | W21: 463 | X21: 467.05 | Y21: 436.5 | Z21: 467 | AA21: 348.2 | AB21: 325 | AC21: 313.1 | AD21: 285 | AE21: 277.85 | AF21: 327 | AG21: 317 | AH21: 370.7 | AI21: 360 | AJ21: 271.15 | AK21: 233.15 | AL21: 218.8 | AM21: 262 | AN21: 223.6 | AO21: 137.6 | AP21: 142 | AQ21: 59.3 | AR21: 58 | AS21: 72.8 | AT21: 80 | AU21: 107.25 | AV21: 106 | AW21: 125.1 | AX21: 112.25 | AY21: 81.45 | AZ21: 88 | BA21: 90.35 | BB21: 106.05 | BC21: 98.55 | BD21: 119.25 | BE21: 210 | BF21: 349
J22: 178.7 | K22: 108.95 | L22: 139.75 | N22: 186.75 | O22: 146.9 | P22: 169.1 | Q22: 139.75 | R22: 202.15 | S22: 249.05 | T22: 346.4 | U22: 349.2 | V22: 469.9 | W22: 584.8 | X22: 536.15 | Y22: 513.35 | Z22: 474 | AA22: 438.55 | AB22: 355.4 | AC22: 334.95 | AD22: 298.8 | AE22: 328.35 | AF22: 343 | AG22: 389.9 | AH22: 443.05 | AI22: 407.5 | AJ22: 290.1 | AK22: 235.75 | AL22: 292.65 | AM22: 276.1 | AN22: 237.05 | AO22: 190.1 | AP22: 147.2 | AQ22: 71.9 | AR22: 75.2 | AS22: 90.1 | AT22: 117.2 | AU22: 116.3 | AV22: 140.5 | AW22: 128.6 | AX22: 133.65 | AY22: 91.65 | AZ22: 97.65 | BA22: 125 | BB22: 115.35 | BC22: 119.25 | BD22: 219.3 | BE22: 442.65 | BF22: 503.35
J23: 207 | K23: 137 | L23: 202.15
J24: 255.15 | K24: 170 | L24: 249.05
J25: 348.25 | K25: 243.15 | L25: 346.4
J26: 374 | K26: 307.5 | L26: 349.2
J27: 495.9 | K27: 325.1 | L27: 469.9
J28: 659.9 | K28: 463 | L28: 584.8
J29: 613.4 | K29: 467.05 | L29: 536.15
J30: 607.9 | K30: 436.5 | L30: 513.35
J31: 555.95 | K31: 467 | L31: 474
J32: 497.8 | K32: 348.2 | L32: 438.55
J33: 459.9 | K33: 325 | L33: 355.4
J34: 374 | K34: 313.1 | L34: 334.95
... J63: 503.35 | K63: 349 | L63: 503.35
