Workbook

Sheet Template
A1: =+'Annual Raw'!C3 -> #NAME? | B1: =+EOMONTH(C1,-12) -> 36981 | C1: =+EOMONTH(D1,-12) -> 37346 | D1: =+EOMONTH(E1,-12) -> 37711 | E1: =+EOMONTH(F1,-12) -> 38077 | F1: =+EOMONTH(G1,-12) -> 38442 | G1: =+EOMONTH(H1,-12) -> 38807 | H1: =+EOMONTH(I1,-12) -> 39172 | I1: =+EOMONTH(J1,-12) -> 39538 | ... N1: =+EOMONTH(O1,-12) -> 41364 | O1: 41699 | P1: 42064 | Q1: 42430 | R1: 42795 | S1: 43160 | T1: 43525 | U1: 43891 | V1: 44256 | W1: 44621 | X1: 44986 | Y1: 45352 | Z1: 45717 | AA1: 46082 | AB1: 46447 | AC1: 46813 | AD1: 47178 | AE1: 47543 | AG1: Quarterly | AH1: 42185 | AI1: =+EOMONTH(AH1,3) -> 42277 | AJ1: =+EOMONTH(AI1,3) -> 42369 | AK1: =+EOMONTH(AJ1,3) -> 42460 | AL1: =+EOMONTH(AK1,3) -> 42551 | AM1: =+EOMONTH(AL1,3) -> 42643 | AN1: =+EOMONTH(AM1,3) -> 42735 | AO1: =+EOMONTH(AN1,3) -> 42825 | AP1: =+EOMONTH(AO1,3) -> 42916 | ... CO1: =+EOMONTH(CN1,3) -> 47573 | CR1: Historical Estimates | CS1: 46082
A2: Presentation Data (Start)
A4: Average eq | D4: =AVERAGE(C109:D109) -> #NAME? | E4: =AVERAGE(D109:E109) -> #NAME? | F4: =AVERAGE(E109:F109) -> #NAME? | G4: =AVERAGE(F109:G109) -> #NAME? | H4: =AVERAGE(G109:H109) -> #NAME? | I4: =AVERAGE(H109:I109) -> #NAME? | J4: =AVERAGE(I109:J109) -> #NAME? | K4: =AVERAGE(J109:K109) -> #NAME? | ... X4: =AVERAGE(W109:X109) -> #NAME? | Y4: =+AVERAGE(BN4:BQ4) -> #NAME? | Z4: =+AVERAGE(BR4:BU4) -> #NAME? | AA4: =+AVERAGE(BV4:BY4) -> #NAME? | AB4: =+AVERAGE(BZ4:CC4) -> #NAME? | AC4: =+AVERAGE(CD4:CG4) -> #NAME? | AD4: =+AVERAGE(CH4:CK4) -> #NAME? | AE4: =+AVERAGE(CL4:CO4) -> #NAME? | AH4: =AVERAGE(AG109:AH109) -> #NAME? | AI4: =AVERAGE(AH109:AI109) -> #NAME? | AJ4: =AVERAGE(AI109:AJ109) -> #NAME? | AK4: =AVERAGE(AJ109:AK109) -> #NAME? | AL4: =AVERAGE(AK109:AL109) -> #NAME? | AM4: =AVERAGE(AL109:AM109) -> #NAME? | AN4: =AVERAGE(AM109:AN109) -> #NAME? | AO4: =AVERAGE(AN109:AO109) -> #NAME? | ... CO4: =AVERAGE(CN109:CO109) -> #NAME? | CS4: 34079.696
A5: Average assets | D5: =AVERAGE(C116:D116) -> #NAME? | E5: =AVERAGE(D116:E116) -> #NAME? | F5: =AVERAGE(E116:F116) -> #NAME? | G5: =AVERAGE(F116:G116) -> #NAME? | H5: =AVERAGE(G116:H116) -> #NAME? | I5: =AVERAGE(H116:I116) -> #NAME? | J5: =AVERAGE(I116:J116) -> #NAME? | K5: =AVERAGE(J116:K116) -> #NAME? | ... X5: =AVERAGE(W116:X116) -> #NAME? | Y5: =+AVERAGE(BN5:BQ5) -> #NAME? | Z5: =+AVERAGE(BR5:BU5) -> #NAME? | AA5: =+AVERAGE(BV5:BY5) -> #NAME? | AB5: =+AVERAGE(BZ5:CC5) -> #NAME? | AC5: =+AVERAGE(CD5:CG5) -> #NAME? | AD5: =+AVERAGE(CH5:CK5) -> #NAME? | AE5: =+AVERAGE(CL5:CO5) -> #NAME? | AH5: =AVERAGE(AG116:AH116) -> #NAME? | AI5: =AVERAGE(AH116:AI116) -> #NAME? | AJ5: =AVERAGE(AI116:AJ116) -> #NAME? | AK5: =AVERAGE(AJ116:AK116) -> #NAME? | AL5: =AVERAGE(AK116:AL116) -> #NAME? | AM5: =AVERAGE(AL116:AM116) -> #NAME? | AN5: =AVERAGE(AM116:AN116) -> #NAME? | AO5: =AVERAGE(AN116:AO116) -> #NAME? | ... CO5: =AVERAGE(CN116:CO116) -> #NAME? | CS5: 402336.1
A7: Growth (%) | D7: =+D5/C5-1 -> #NAME? | E7: =+E5/D5-1 -> #NAME? | F7: =+F5/E5-1 -> #NAME? | G7: =+G5/F5-1 -> #NAME? | H7: =+H5/G5-1 -> #NAME? | I7: =+I5/H5-1 -> #NAME? | J7: =+J5/I5-1 -> #NAME? | K7: =+K5/J5-1 -> #NAME? | ... AE7: =+AE5/AD5-1 -> #NAME? | AM7: =AM5/AI5-1 -> #NAME? | AN7: =AN5/AJ5-1 -> #NAME? | AO7: =AO5/AK5-1 -> #NAME? | AP7: =AP5/AL5-1 -> #NAME? | AQ7: =AQ5/AM5-1 -> #NAME? | AR7: =AR5/AN5-1 -> #NAME? | AS7: =AS5/AO5-1 -> #NAME? | AT7: =AT5/AP5-1 -> #NAME? | ... CO7: =CO5/CK5-1 -> #NAME? | CS7: 0.18127355
A9: Leverage | D9: =D115/D109 -> #NAME? | E9: =E115/E109 -> #NAME? | F9: =F115/F109 -> #NAME? | G9: =G115/G109 -> #NAME? | H9: =H115/H109 -> #NAME? | I9: =I115/I109 -> #NAME? | J9: =J115/J109 -> #NAME? | K9: =K115/K109 -> #NAME? | ... AE9: =AE115/AE109 -> #NAME? | AH9: =AH115/AH109 -> #NAME? | AI9: =AI115/AI109 -> #NAME? | AJ9: =AJ115/AJ109 -> #NAME? | AK9: =AK115/AK109 -> #NAME? | AL9: =AL115/AL109 -> #NAME? | AM9: =AM115/AM109 -> #NAME? | AN9: =AN115/AN109 -> #NAME? | AO9: =AO115/AO109 -> #NAME? | ... CO9: =CO115/CO109 -> #NAME? | CS9: 11.032997
A12: Interest Income | D12: =D34/C5 -> #NAME? | E12: =E34/D5 -> #NAME? | F12: =F34/E5 -> #NAME? | G12: =G34/F5 -> #NAME? | H12: =H34/G5 -> #NAME? | I12: =I34/H5 -> #NAME? | J12: =J34/I5 -> #NAME? | K12: =K34/J5 -> #NAME? | ... AE12: =AE34/AD5 -> #NAME? | AH12: =AH34/AG5 -> #NAME? | AI12: =AI34/AH5 -> #NAME? | AJ12: =AJ34/AI5 -> #NAME? | AK12: =AK34/AJ5 -> #NAME? | AL12: =AL34/AK5 -> #NAME? | AM12: =AM34/AL5 -> #NAME? | AN12: =AN34/AM5 -> #NAME? | AO12: =AO34/AN5 -> #NAME? | ... BY12: =BY34/BX5 -> #NAME? | BZ12: =BY12 -> #NAME? | CA12: =BZ12 -> #NAME? | CB12: =CA12 -> #NAME? | CC12: =CB12 -> #NAME? | CD12: =CC12 -> #NAME? | CE12: =CD12 -> #NAME? | CF12: =CE12 -> #NAME? | CG12: =CF12 -> #NAME? | ... CO12: =CN12 -> #NAME? | CS12: 0.020251781
A13: Interest Expenses | D13: =D35/C5 -> #NAME? | E13: =E35/D5 -> #NAME? | F13: =F35/E5 -> #NAME? | G13: =G35/F5 -> #NAME? | H13: =H35/G5 -> #NAME? | I13: =I35/H5 -> #NAME? | J13: =J35/I5 -> #NAME? | K13: =K35/J5 -> #NAME? | ... AE13: =AE35/AD5 -> #NAME? | AH13: =AH35/AG5 -> #NAME? | AI13: =AI35/AH5 -> #NAME? | AJ13: =AJ35/AI5 -> #NAME? | AK13: =AK35/AJ5 -> #NAME? | AL13: =AL35/AK5 -> #NAME? | AM13: =AM35/AL5 -> #NAME? | AN13: =AN35/AM5 -> #NAME? | AO13: =AO35/AN5 -> #NAME? | ... BY13: =BY35/BX5 -> #NAME? | BZ13: =BY13 -> #NAME? | CA13: =BZ13 -> #NAME? | CB13: =CA13 -> #NAME? | CC13: =CB13 -> #NAME? | CD13: =CC13 -> #NAME? | CE13: =CD13 -> #NAME? | CF13: =CE13 -> #NAME? | CG13: =CF13 -> #NAME? | ... CO13: =CN13 -> #NAME? | CS13: 0.010814774
A14: NII | D14: =D12-D13 -> #NAME? | E14: =E12-E13 -> #NAME? | F14: =F12-F13 -> #NAME? | G14: =G12-G13 -> #NAME? | H14: =H12-H13 -> #NAME? | I14: =I12-I13 -> #NAME? | J14: =J12-J13 -> #NAME? | K14: =K12-K13 -> #NAME? | ... AE14: =AE12-AE13 -> #NAME? | AH14: =AH12-AH13 -> #NAME? | AI14: =AI12-AI13 -> #NAME? | AJ14: =AJ12-AJ13 -> #NAME? | AK14: =AK12-AK13 -> #NAME? | AL14: =AL12-AL13 -> #NAME? | AM14: =AM12-AM13 -> #NAME? | AN14: =AN12-AN13 -> #NAME? | AO14: =AO12-AO13 -> #NAME? | ... CO14: =CO12-CO13 -> #NAME? | CS14: 0.009437007
A15: Others income | D15: =D37/C5 -> #NAME? | E15: =E37/D5 -> #NAME? | F15: =F37/E5 -> #NAME? | G15: =G37/F5 -> #NAME? | H15: =H37/G5 -> #NAME? | I15: =I37/H5 -> #NAME? | J15: =J37/I5 -> #NAME? | K15: =K37/J5 -> #NAME? | ... AE15: =AE37/AD5 -> #NAME? | AH15: =AH37/AG5 -> #NAME? | AI15: =AI37/AH5 -> #NAME? | AJ15: =AJ37/AI5 -> #NAME? | AK15: =AK37/AJ5 -> #NAME? | AL15: =AL37/AK5 -> #NAME? | AM15: =AM37/AL5 -> #NAME? | AN15: =AN37/AM5 -> #NAME? | AO15: =AO37/AN5 -> #NAME? | ... BY15: =BY37/BX5 -> #NAME? | BZ15: =BY15 -> #NAME? | CA15: =BZ15 -> #NAME? | CB15: =CA15 -> #NAME? | CC15: =CB15 -> #NAME? | CD15: =CC15 -> #NAME? | CE15: =CD15 -> #NAME? | CF15: =CE15 -> #NAME? | CG15: =CF15 -> #NAME? | ... CO15: =CN15 -> #NAME? | CS15: 0.0025723805
A16: Other non-operating income
A17: Total income | D17: =D14+D15+D16 -> #NAME? | E17: =E14+E15+E16 -> #NAME? | F17: =F14+F15+F16 -> #NAME? | G17: =G14+G15+G16 -> #NAME? | H17: =H14+H15+H16 -> #NAME? | I17: =I14+I15+I16 -> #NAME? | J17: =J14+J15+J16 -> #NAME? | K17: =K14+K15+K16 -> #NAME? | ... AE17: =AE14+AE15+AE16 -> #NAME? | AH17: =AH14+AH15+AH16 -> #NAME? | AI17: =AI14+AI15+AI16 -> #NAME? | AJ17: =AJ14+AJ15+AJ16 -> #NAME? | AK17: =AK14+AK15+AK16 -> #NAME? | AL17: =AL14+AL15+AL16 -> #NAME? | AM17: =AM14+AM15+AM16 -> #NAME? | AN17: =AN14+AN15+AN16 -> #NAME? | AO17: =AO14+AO15+AO16 -> #NAME? | ... CO17: =CO14+CO15+CO16 -> #NAME? | CS17: 0.012009387
A18: TC | D18: =D46/C5 -> #NAME? | E18: =E46/D5 -> #NAME? | F18: =F46/E5 -> #NAME? | G18: =G46/F5 -> #NAME? | H18: =H46/G5 -> #NAME? | I18: =I46/H5 -> #NAME? | J18: =J46/I5 -> #NAME? | K18: =K46/J5 -> #NAME? | ... AE18: =AE46/AD5 -> #NAME? | AH18: =AH46/AG5 -> #NAME? | AI18: =AI46/AH5 -> #NAME? | AJ18: =AJ46/AI5 -> #NAME? | AK18: =AK46/AJ5 -> #NAME? | AL18: =AL46/AK5 -> #NAME? | AM18: =AM46/AL5 -> #NAME? | AN18: =AN46/AM5 -> #NAME? | AO18: =AO46/AN5 -> #NAME? | ... BY18: =BY46/BX5 -> #NAME? | BZ18: =BY18 -> #NAME? | CA18: =BZ18 -> #NAME? | CB18: =CA18 -> #NAME? | CC18: =CB18 -> #NAME? | CD18: =CC18 -> #NAME? | CE18: =CD18 -> #NAME? | CF18: =CE18 -> #NAME? | CG18: =CF18 -> #NAME? | ... CO18: =CN18 -> #NAME? | CS18: 0.0044659973
A19: PPP | D19: =D17-D18 -> #NAME? | E19: =E17-E18 -> #NAME? | F19: =F17-F18 -> #NAME? | G19: =G17-G18 -> #NAME? | H19: =H17-H18 -> #NAME? | I19: =I17-I18 -> #NAME? | J19: =J17-J18 -> #NAME? | K19: =K17-K18 -> #NAME? | ... AE19: =AE17-AE18 -> #NAME? | AH19: =AH17-AH18 -> #NAME? | AI19: =AI17-AI18 -> #NAME? | AJ19: =AJ17-AJ18 -> #NAME? | AK19: =AK17-AK18 -> #NAME? | AL19: =AL17-AL18 -> #NAME? | AM19: =AM17-AM18 -> #NAME? | AN19: =AN17-AN18 -> #NAME? | AO19: =AO17-AO18 -> #NAME? | ... CO19: =CO17-CO18 -> #NAME? | CS19: 0.0075433901
A20: Provision | D20: =D49/C5 -> #NAME? | E20: =E49/D5 -> #NAME? | F20: =F49/E5 -> #NAME? | G20: =G49/F5 -> #NAME? | H20: =H49/G5 -> #NAME? | I20: =I49/H5 -> #NAME? | J20: =J49/I5 -> #NAME? | K20: =K49/J5 -> #NAME? | ... AE20: =AE49/AD5 -> #NAME? | AH20: =AH49/AG5 -> #NAME? | AI20: =AI49/AH5 -> #NAME? | AJ20: =AJ49/AI5 -> #NAME? | AK20: =AK49/AJ5 -> #NAME? | AL20: =AL49/AK5 -> #NAME? | AM20: =AM49/AL5 -> #NAME? | AN20: =AN49/AM5 -> #NAME? | AO20: =AO49/AN5 -> #NAME? | ... BY20: =BY49/BX5 -> #NAME? | BZ20: =BY20 -> #NAME? | CA20: =BZ20 -> #NAME? | CB20: =CA20 -> #NAME? | CC20: =CB20 -> #NAME? | CD20: =CC20 -> #NAME? | CE20: =CD20 -> #NAME? | CF20: =CE20 -> #NAME? | CG20: =CF20 -> #NAME? | ... CO20: =CN20 -> #NAME? | CS20: 0.0020079988
A21: PBT | D21: =D19-D20 -> #NAME? | E21: =E19-E20 -> #NAME? | F21: =F19-F20 -> #NAME? | G21: =G19-G20 -> #NAME? | H21: =H19-H20 -> #NAME? | I21: =I19-I20 -> #NAME? | J21: =J19-J20 -> #NAME? | K21: =K19-K20 -> #NAME? | ... AE21: =AE19-AE20 -> #NAME? | AH21: =AH19-AH20 -> #NAME? | AI21: =AI19-AI20 -> #NAME? | AJ21: =AJ19-AJ20 -> #NAME? | AK21: =AK19-AK20 -> #NAME? | AL21: =AL19-AL20 -> #NAME? | AM21: =AM19-AM20 -> #NAME? | AN21: =AN19-AN20 -> #NAME? | AO21: =AO19-AO20 -> #NAME? | ... CO21: =CO19-CO20 -> #NAME? | CS21: 0.0055353913
A22: Tax | D22: =D51/C5 -> #NAME? | E22: =E51/D5 -> #NAME? | F22: =F51/E5 -> #NAME? | G22: =G51/F5 -> #NAME? | H22: =H51/G5 -> #NAME? | I22: =I51/H5 -> #NAME? | J22: =J51/I5 -> #NAME? | K22: =K51/J5 -> #NAME? | ... AE22: =AE51/AD5 -> #NAME? | AH22: =AH51/AG5 -> #NAME? | AI22: =AI51/AH5 -> #NAME? | AJ22: =AJ51/AI5 -> #NAME? | AK22: =AK51/AJ5 -> #NAME? | AL22: =AL51/AK5 -> #NAME? | AM22: =AM51/AL5 -> #NAME? | AN22: =AN51/AM5 -> #NAME? | AO22: =AO51/AN5 -> #NAME? | ... CO22: =CO51/CN5 -> #NAME? | CS22: 0.0014392017
A23: PAT | D23: =D21-D22 -> #NAME? | E23: =E21-E22 -> #NAME? | F23: =F21-F22 -> #NAME? | G23: =G21-G22 -> #NAME? | H23: =H21-H22 -> #NAME? | I23: =I21-I22 -> #NAME? | J23: =J21-J22 -> #NAME? | K23: =K21-K22 -> #NAME? | ... AE23: =AE21-AE22 -> #NAME? | AH23: =AH21-AH22 -> #NAME? | AI23: =AI21-AI22 -> #NAME? | AJ23: =AJ21-AJ22 -> #NAME? | AK23: =AK21-AK22 -> #NAME? | AL23: =AL21-AL22 -> #NAME? | AM23: =AM21-AM22 -> #NAME? | AN23: =AN21-AN22 -> #NAME? | AO23: =AO21-AO22 -> #NAME? | ... CO23: =CO21-CO22 -> #NAME? | CS23: 0.0040961896
BR24: =+BR23*4 -> #NAME? | BS24: =+BS23*4 -> #NAME? | BT24: =+BT23*4 -> #NAME? | BU24: =+BU23*4 -> #NAME? | BV24: =+BV23*4 -> #NAME? | BW24: =+BW23*4 -> #NAME? | BX24: =+BX23*4 -> #NAME? | BY24: =+BY23*4 -> #NAME?
A25: Preview
A26: Deposits | BH26: 186614 | BI26: 202294 | BJ26: 195909 | BK26: 195849 | BL26: 208436 | BM26: 234092 | BN26: 244364 | BO26: 239306 | BP26: 245738 | BQ26: 270727 | BR26: 267423 | BS26: 276289 | BT26: 279018 | BU26: 307152 | BV26: 305046 | BW26: 309800 | BX26: 321695 | BY26: 321695
A27: Advances | BH27: 129006 | BI27: 135240 | BJ27: 140561 | BK27: 148216 | BL27: 157139 | BM27: 175255 | BN27: 175603 | BO27: 183113 | BP27: 188796 | BQ27: 203677 | BR27: 209065 | BS27: 217504 | BT27: 228652 | BU27: 240007 | BV27: 241097 | BW27: 254187 | BX27: 273476 | BY27: 273476
BH28: =+BH119/BH27 -> #NAME? | BI28: =+BI119/BI27 -> #NAME? | BJ28: =+BJ119/BJ27 -> #NAME? | BK28: =+BK119/BK27 -> #NAME? | BL28: =+BL119/BL27 -> #NAME? | BM28: =+BM119/BM27 -> #NAME? | BN28: =+BN119/BN27 -> #NAME? | BO28: =+BO119/BO27 -> #NAME? | ... BY28: =+BY119/BY27 -> #NAME?
A30: CD Ratio | B30: =+B119/B113 -> #NAME? | C30: =+C119/C113 -> #NAME? | D30: =+D119/D113 -> #NAME? | E30: =+E119/E113 -> #NAME? | F30: =+F119/F113 -> #NAME? | G30: =+G119/G113 -> #NAME? | H30: =+H119/H113 -> #NAME? | I30: =+I119/I113 -> #NAME? | ... AE30: =+AE119/AE113 -> #NAME? | AI30: =+AI119/AI113 -> #NAME? | AJ30: =+AJ119/AJ113 -> #NAME? | AK30: =+AK119/AK113 -> #NAME? | AL30: =+AL119/AL113 -> #NAME? | AM30: =+AM119/AM113 -> #NAME? | AN30: =+AN119/AN113 -> #NAME? | AO30: =+AO119/AO113 -> #NAME? | AP30: =+AP119/AP113 -> #NAME? | ... CO30: =+CO119/CO113 -> #NAME? | CS30: 0.78664508
A32: Presentation Data (End)
A33: Profit & Loss- Annual (Start)
A34: Interest Income | B34: =+'Annual Raw'!C7 -> #NAME? | C34: =+'Annual Raw'!D7 -> #NAME? | D34: =+'Annual Raw'!E7 -> #NAME? | E34: =+'Annual Raw'!F7 -> #NAME? | F34: =+'Annual Raw'!G7 -> #NAME? | G34: =+'Annual Raw'!H7 -> #NAME? | H34: =+'Annual Raw'!I7 -> #NAME? | I34: =+'Annual Raw'!J7 -> #NAME? | ... AA34: =+'Annual Raw'!AB7 -> #NAME? | AB34: =SUM(BZ34:CC34) -> #NAME? | AC34: =SUM(CD34:CG34) -> #NAME? | AD34: =SUM(CH34:CK34) -> #NAME? | AE34: =SUM(CL34:CO34) -> #NAME? | AH34: =+'QTR Raw'!C6 -> #NAME? | AI34: =+'QTR Raw'!D6 -> #NAME? | AJ34: =+'QTR Raw'!E6 -> #NAME? | AK34: =+'QTR Raw'!F6 -> #NAME? | AL34: =+'QTR Raw'!G6 -> #NAME? | AM34: =+'QTR Raw'!H6 -> #NAME? | AN34: =+'QTR Raw'!I6 -> #NAME? | AO34: =+'QTR Raw'!J6 -> #NAME? | ... BY34: =+'QTR Raw'!AT6 -> #NAME? | BZ34: =BZ12*BY5 -> #NAME? | CA34: =CA12*BZ5 -> #NAME? | CB34: =CB12*CA5 -> #NAME? | CC34: =CC12*CB5 -> #NAME? | CD34: =CD12*CC5 -> #NAME? | CE34: =CE12*CD5 -> #NAME? | CF34: =CF12*CE5 -> #NAME? | CG34: =CG12*CF5 -> #NAME? | ... CO34: =CO12*CN5 -> #NAME? | CS34: 29281.64
A35: Interest exp | B35: =+'Annual Raw'!C10 -> #NAME? | C35: =+'Annual Raw'!D10 -> #NAME? | D35: =+'Annual Raw'!E10 -> #NAME? | E35: =+'Annual Raw'!F10 -> #NAME? | F35: =+'Annual Raw'!G10 -> #NAME? | G35: =+'Annual Raw'!H10 -> #NAME? | H35: =+'Annual Raw'!I10 -> #NAME? | I35: =+'Annual Raw'!J10 -> #NAME? | ... AA35: =+'Annual Raw'!AB10 -> #NAME? | AB35: =SUM(BZ35:CC35) -> #NAME? | AC35: =SUM(CD35:CG35) -> #NAME? | AD35: =SUM(CH35:CK35) -> #NAME? | AE35: =SUM(CL35:CO35) -> #NAME? | AH35: =+'QTR Raw'!C9 -> #NAME? | AI35: =+'QTR Raw'!D9 -> #NAME? | AJ35: =+'QTR Raw'!E9 -> #NAME? | AK35: =+'QTR Raw'!F9 -> #NAME? | AL35: =+'QTR Raw'!G9 -> #NAME? | AM35: =+'QTR Raw'!H9 -> #NAME? | AN35: =+'QTR Raw'!I9 -> #NAME? | AO35: =+'QTR Raw'!J9 -> #NAME? | ... BY35: =+'QTR Raw'!AT9 -> #NAME? | BZ35: =BZ13*BY5 -> #NAME? | CA35: =CA13*BZ5 -> #NAME? | CB35: =CB13*CA5 -> #NAME? | CC35: =CC13*CB5 -> #NAME? | CD35: =CD13*CC5 -> #NAME? | CE35: =CE13*CD5 -> #NAME? | CF35: =CF13*CE5 -> #NAME? | CG35: =CG13*CF5 -> #NAME? | ... CO35: =CO13*CN5 -> #NAME? | CS35: 15617.58
A36: NII | B36: =B34-B35 -> #NAME? | C36: =C34-C35 -> #NAME? | D36: =D34-D35 -> #NAME? | E36: =E34-E35 -> #NAME? | F36: =F34-F35 -> #NAME? | G36: =G34-G35 -> #NAME? | H36: =H34-H35 -> #NAME? | I36: =I34-I35 -> #NAME? | ... AE36: =AE34-AE35 -> #NAME? | AH36: =AH34-AH35 -> #NAME? | AI36: =AI34-AI35 -> #NAME? | AJ36: =AJ34-AJ35 -> #NAME? | AK36: =AK34-AK35 -> #NAME? | AL36: =AL34-AL35 -> #NAME? | AM36: =AM34-AM35 -> #NAME? | AN36: =AN34-AN35 -> #NAME? | AO36: =AO34-AO35 -> #NAME? | ... CO36: =CO34-CO35 -> #NAME? | CS36: 13664.06
A37: Other Income | B37: =+'Annual Raw'!C8 -> #NAME? | C37: =+'Annual Raw'!D8 -> #NAME? | D37: =+'Annual Raw'!E8 -> #NAME? | E37: =+'Annual Raw'!F8 -> #NAME? | F37: =+'Annual Raw'!G8 -> #NAME? | G37: =+'Annual Raw'!H8 -> #NAME? | H37: =+'Annual Raw'!I8 -> #NAME? | I37: =+'Annual Raw'!J8 -> #NAME? | ... AA37: =+'Annual Raw'!AB8 -> #NAME? | AB37: =SUM(BZ37:CC37) -> #NAME? | AC37: =SUM(CD37:CG37) -> #NAME? | AD37: =SUM(CH37:CK37) -> #NAME? | AE37: =SUM(CL37:CO37) -> #NAME? | AH37: =+'QTR Raw'!C7 -> #NAME? | AI37: =+'QTR Raw'!D7 -> #NAME? | AJ37: =+'QTR Raw'!E7 -> #NAME? | AK37: =+'QTR Raw'!F7 -> #NAME? | AL37: =+'QTR Raw'!G7 -> #NAME? | AM37: =+'QTR Raw'!H7 -> #NAME? | AN37: =+'QTR Raw'!I7 -> #NAME? | AO37: =+'QTR Raw'!J7 -> #NAME? | ... BY37: =+'QTR Raw'!AT7 -> #NAME? | BZ37: =BZ15*BY5 -> #NAME? | CA37: =CA15*BZ5 -> #NAME? | CB37: =CB15*CA5 -> #NAME? | CC37: =CC15*CB5 -> #NAME? | CD37: =CD15*CC5 -> #NAME? | CE37: =CE15*CD5 -> #NAME? | CF37: =CF15*CE5 -> #NAME? | CG37: =CG15*CF5 -> #NAME? | ... CO37: =CO15*CN5 -> #NAME? | CS37: 3540.89
A38: TI | B38: =B36+B37 -> #NAME? | C38: =C36+C37 -> #NAME? | D38: =D36+D37 -> #NAME? | E38: =E36+E37 -> #NAME? | F38: =F36+F37 -> #NAME? | G38: =G36+G37 -> #NAME? | H38: =H36+H37 -> #NAME? | I38: =I36+I37 -> #NAME? | ... AE38: =AE36+AE37 -> #NAME? | AH38: =AH36+AH37 -> #NAME? | AI38: =AI36+AI37 -> #NAME? | AJ38: =AJ36+AJ37 -> #NAME? | AK38: =AK36+AK37 -> #NAME? | AL38: =AL36+AL37 -> #NAME? | AM38: =AM36+AM37 -> #NAME? | AN38: =AN36+AN37 -> #NAME? | AO38: =AO36+AO37 -> #NAME? | ... CO38: =CO36+CO37 -> #NAME? | CS38: 17204.95
A39: YOY% | C39: =+IF(B38<0,1-C38/B38,C38/B38-1) -> #NAME? | D39: =+IF(C38<0,1-D38/C38,D38/C38-1) -> #NAME? | E39: =+IF(D38<0,1-E38/D38,E38/D38-1) -> #NAME? | F39: =+IF(E38<0,1-F38/E38,F38/E38-1) -> #NAME? | G39: =+IF(F38<0,1-G38/F38,G38/F38-1) -> #NAME? | H39: =+IF(G38<0,1-H38/G38,H38/G38-1) -> #NAME? | I39: =+IF(H38<0,1-I38/H38,I38/H38-1) -> #NAME? | J39: =+IF(I38<0,1-J38/I38,J38/I38-1) -> #NAME? | ... AB39: =+IF(AA38<0,1-AB38/AA38,AB38/AA38-1) -> #NAME? | AC39: =AC38/AB38-1 -> #NAME? | AD39: =AD38/AC38-1 -> #NAME? | AE39: =AE38/AD38-1 -> #NAME? | AL39: =+IF(AH38<0,1-AL38/AH38,AL38/AH38-1) -> #NAME? | AM39: =+IF(AI38<0,1-AM38/AI38,AM38/AI38-1) -> #NAME? | AN39: =+IF(AJ38<0,1-AN38/AJ38,AN38/AJ38-1) -> #NAME? | AO39: =+IF(AK38<0,1-AO38/AK38,AO38/AK38-1) -> #NAME? | AP39: =+IF(AL38<0,1-AP38/AL38,AP38/AL38-1) -> #NAME? | AQ39: =+IF(AM38<0,1-AQ38/AM38,AQ38/AM38-1) -> #NAME? | AR39: =+IF(AN38<0,1-AR38/AN38,AR38/AN38-1) -> #NAME? | AS39: =+IF(AO38<0,1-AS38/AO38,AS38/AO38-1) -> #NAME? | ... CO39: =+IF(CK38<0,1-CO38/CK38,CO38/CK38-1) -> #NAME? | CS39: 0.13791279
A40: Employee Cost | B40: =+'Annual Raw'!C12 -> #NAME? | C40: =+'Annual Raw'!D12 -> #NAME? | D40: =+'Annual Raw'!E12 -> #NAME? | E40: =+'Annual Raw'!F12 -> #NAME? | F40: =+'Annual Raw'!G12 -> #NAME? | G40: =+'Annual Raw'!H12 -> #NAME? | H40: =+'Annual Raw'!I12 -> #NAME? | I40: =+'Annual Raw'!J12 -> #NAME? | ... AA40: =+'Annual Raw'!AB12 -> #NAME? | AB40: =SUM(BZ40:CC40) -> #NAME? | AC40: =SUM(CD40:CG40) -> #NAME? | AD40: =SUM(CH40:CK40) -> #NAME? | AE40: =SUM(CL40:CO40) -> #NAME? | AH40: =+'QTR Raw'!C11 -> #NAME? | AI40: =+'QTR Raw'!D11 -> #NAME? | AJ40: =+'QTR Raw'!E11 -> #NAME? | AK40: =+'QTR Raw'!F11 -> #NAME? | AL40: =+'QTR Raw'!G11 -> #NAME? | AM40: =+'QTR Raw'!H11 -> #NAME? | AN40: =+'QTR Raw'!I11 -> #NAME? | AO40: =+'QTR Raw'!J11 -> #NAME? | ... BY40: =+'QTR Raw'!AT11 -> #NAME? | BZ40: =BZ18*BY5 -> #NAME? | CA40: =CA18*BZ5 -> #NAME? | CB40: =CB18*CA5 -> #NAME? | CC40: =CC18*CB5 -> #NAME? | CD40: =CD18*CC5 -> #NAME? | CE40: =CE18*CD5 -> #NAME? | CF40: =CF18*CE5 -> #NAME? | CG40: =CG18*CF5 -> #NAME? | ... CO40: =CO18*CN5 -> #NAME? | CS40: 3375.77
A41: Operating & Establishment Expenses | B41: =+'Annual Raw'!C11-'Annual Raw'!C12-'Annual Raw'!C13-'Annual Raw'!C14-'Annual Raw'!C15-'Annual Raw'!C16-'Annual Raw'!C17 -> #NAME? | C41: =+'Annual Raw'!D11-'Annual Raw'!D12-'Annual Raw'!D13-'Annual Raw'!D14-'Annual Raw'!D15-'Annual Raw'!D16-'Annual Raw'!D17 -> #NAME? | D41: =+'Annual Raw'!E11-'Annual Raw'!E12-'Annual Raw'!E13-'Annual Raw'!E14-'Annual Raw'!E15-'Annual Raw'!E16-'Annual Raw'!E17 -> #NAME? | E41: =+'Annual Raw'!F11-'Annual Raw'!F12-'Annual Raw'!F13-'Annual Raw'!F14-'Annual Raw'!F15-'Annual Raw'!F16-'Annual Raw'!F17 -> #NAME? | F41: =+'Annual Raw'!G11-'Annual Raw'!G12-'Annual Raw'!G13-'Annual Raw'!G14-'Annual Raw'!G15-'Annual Raw'!G16-'Annual Raw'!G17 -> #NAME? | G41: =+'Annual Raw'!H11-'Annual Raw'!H12-'Annual Raw'!H13-'Annual Raw'!H14-'Annual Raw'!H15-'Annual Raw'!H16-'Annual Raw'!H17 -> #NAME? | H41: =+'Annual Raw'!I11-'Annual Raw'!I12-'Annual Raw'!I13-'Annual Raw'!I14-'Annual Raw'!I15-'Annual Raw'!I16-'Annual Raw'!I17 -> #NAME? | I41: =+'Annual Raw'!J11-'Annual Raw'!J12-'Annual Raw'!J13-'Annual Raw'!J14-'Annual Raw'!J15-'Annual Raw'!J16-'Annual Raw'!J17 -> #NAME? | ... AA41: =+'Annual Raw'!AB11-'Annual Raw'!AB12-'Annual Raw'!AB13-'Annual Raw'!AB14-'Annual Raw'!AB15-'Annual Raw'!AB16-'Annual Raw'!AB17 -> #NAME? | AB41: =SUM(BZ41:CC41) -> 0 | AC41: =SUM(CD41:CG41) -> 0 | AD41: =SUM(CH41:CK41) -> 0 | AE41: =SUM(CL41:CO41) -> 0 | AH41: =+'QTR Raw'!C10-'QTR Raw'!C11-'QTR Raw'!C12 -> #NAME? | AI41: =+'QTR Raw'!D10-'QTR Raw'!D11-'QTR Raw'!D12 -> #NAME? | AJ41: =+'QTR Raw'!E10-'QTR Raw'!E11-'QTR Raw'!E12 -> #NAME? | AK41: =+'QTR Raw'!F10-'QTR Raw'!F11-'QTR Raw'!F12 -> #NAME? | AL41: =+'QTR Raw'!G10-'QTR Raw'!G11-'QTR Raw'!G12 -> #NAME? | AM41: =+'QTR Raw'!H10-'QTR Raw'!H11-'QTR Raw'!H12 -> #NAME? | AN41: =+'QTR Raw'!I10-'QTR Raw'!I11-'QTR Raw'!I12 -> #NAME? | AO41: =+'QTR Raw'!J10-'QTR Raw'!J11-'QTR Raw'!J12 -> #NAME? | ... BY41: =+'QTR Raw'!AT10-'QTR Raw'!AT11-'QTR Raw'!AT12 -> #NAME? | CS41: 3003.36
A42: Insurance | B42: =+'Annual Raw'!C17 -> #NAME? | C42: =+'Annual Raw'!D17 -> #NAME? | D42: =+'Annual Raw'!E17 -> #NAME? | E42: =+'Annual Raw'!F17 -> #NAME? | F42: =+'Annual Raw'!G17 -> #NAME? | G42: =+'Annual Raw'!H17 -> #NAME? | H42: =+'Annual Raw'!I17 -> #NAME? | I42: =+'Annual Raw'!J17 -> #NAME? | ... AA42: =+'Annual Raw'!AB17 -> #NAME?
A43: Rent, Rates & Taxes | B43: =+'Annual Raw'!C14 -> #NAME? | C43: =+'Annual Raw'!D14 -> #NAME? | D43: =+'Annual Raw'!E14 -> #NAME? | E43: =+'Annual Raw'!F14 -> #NAME? | F43: =+'Annual Raw'!G14 -> #NAME? | G43: =+'Annual Raw'!H14 -> #NAME? | H43: =+'Annual Raw'!I14 -> #NAME? | I43: =+'Annual Raw'!J14 -> #NAME? | ... AA43: =+'Annual Raw'!AB14 -> #NAME? | AB43: =SUM(BZ43:CC43) -> 0 | AC43: =SUM(CD43:CG43) -> 0 | AD43: =SUM(CH43:CK43) -> 0 | AE43: =SUM(CL43:CO43) -> 0 | CS43: 0
A44: Depreciation | B44: =+'Annual Raw'!C15+'Annual Raw'!C16 -> #NAME? | C44: =+'Annual Raw'!D15+'Annual Raw'!D16 -> #NAME? | D44: =+'Annual Raw'!E15+'Annual Raw'!E16 -> #NAME? | E44: =+'Annual Raw'!F15+'Annual Raw'!F16 -> #NAME? | F44: =+'Annual Raw'!G15+'Annual Raw'!G16 -> #NAME? | G44: =+'Annual Raw'!H15+'Annual Raw'!H16 -> #NAME? | H44: =+'Annual Raw'!I15+'Annual Raw'!I16 -> #NAME? | I44: =+'Annual Raw'!J15+'Annual Raw'!J16 -> #NAME? | ... AA44: =+'Annual Raw'!AB15+'Annual Raw'!AB16 -> #NAME? | AB44: =SUM(BZ44:CC44) -> 0 | AC44: =SUM(CD44:CG44) -> 0 | AD44: =SUM(CH44:CK44) -> 0 | AE44: =SUM(CL44:CO44) -> 0 | AH44: =+'QTR Raw'!C12 -> #NAME? | AI44: =+'QTR Raw'!D12 -> #NAME? | AJ44: =+'QTR Raw'!E12 -> #NAME? | AK44: =+'QTR Raw'!F12 -> #NAME? | AL44: =+'QTR Raw'!G12 -> #NAME? | AM44: =+'QTR Raw'!H12 -> #NAME? | AN44: =+'QTR Raw'!I12 -> #NAME? | AO44: =+'QTR Raw'!J12 -> #NAME? | ... BY44: =+'QTR Raw'!AT12 -> #NAME? | CS44: 0
A45: Advertisement & Sales Promotion | B45: =+'Annual Raw'!C13 -> #NAME? | C45: =+'Annual Raw'!D13 -> #NAME? | D45: =+'Annual Raw'!E13 -> #NAME? | E45: =+'Annual Raw'!F13 -> #NAME? | F45: =+'Annual Raw'!G13 -> #NAME? | G45: =+'Annual Raw'!H13 -> #NAME? | H45: =+'Annual Raw'!I13 -> #NAME? | I45: =+'Annual Raw'!J13 -> #NAME? | ... AA45: =+'Annual Raw'!AB13 -> #NAME? | AB45: =SUM(BZ45:CC45) -> 0 | AC45: =SUM(CD45:CG45) -> 0 | AD45: =SUM(CH45:CK45) -> 0 | AE45: =SUM(CL45:CO45) -> 0 | CS45: 0
A46: TC | B46: =SUM(B40:B45) -> #NAME? | C46: =SUM(C40:C45) -> #NAME? | D46: =SUM(D40:D45) -> #NAME? | E46: =SUM(E40:E45) -> #NAME? | F46: =SUM(F40:F45) -> #NAME? | G46: =SUM(G40:G45) -> #NAME? | H46: =SUM(H40:H45) -> #NAME? | I46: =SUM(I40:I45) -> #NAME? | ... AE46: =SUM(AE40:AE45) -> #NAME? | AH46: =SUM(AH40:AH44) -> #NAME? | AI46: =SUM(AI40:AI44) -> #NAME? | AJ46: =SUM(AJ40:AJ44) -> #NAME? | AK46: =SUM(AK40:AK44) -> #NAME? | AL46: =SUM(AL40:AL44) -> #NAME? | AM46: =SUM(AM40:AM44) -> #NAME? | AN46: =SUM(AN40:AN44) -> #NAME? | AO46: =SUM(AO40:AO44) -> #NAME? | ... AS46: =SUM(AS40:AS44) -> #NAME? | AT46: =SUM(AT40:AT45) -> #NAME? | AU46: =SUM(AU40:AU45) -> #NAME? | AV46: =SUM(AV40:AV45) -> #NAME? | AW46: =SUM(AW40:AW45) -> #NAME? | AX46: =SUM(AX40:AX45) -> #NAME? | AY46: =SUM(AY40:AY45) -> #NAME? | AZ46: =SUM(AZ40:AZ45) -> #NAME? | BA46: =SUM(BA40:BA45) -> #NAME? | ... CO46: =SUM(CO40:CO45) -> #NAME? | CS46: 6379.13
A47: PPP | B47: =+B38-B46 -> #NAME? | C47: =+C38-C46 -> #NAME? | D47: =+D38-D46 -> #NAME? | E47: =+E38-E46 -> #NAME? | F47: =+F38-F46 -> #NAME? | G47: =+G38-G46 -> #NAME? | H47: =+H38-H46 -> #NAME? | I47: =+I38-I46 -> #NAME? | ... AE47: =+AE38-AE46 -> #NAME? | AH47: =+AH38-AH46 -> #NAME? | AI47: =+AI38-AI46 -> #NAME? | AJ47: =+AJ38-AJ46 -> #NAME? | AK47: =+AK38-AK46 -> #NAME? | AL47: =+AL38-AL46 -> #NAME? | AM47: =+AM38-AM46 -> #NAME? | AN47: =+AN38-AN46 -> #NAME? | AO47: =+AO38-AO46 -> #NAME? | ... CO47: =+CO38-CO46 -> #NAME? | CS47: 10825.82
A48: YOY% | C48: =+IF(B47<0,1-C47/B47,C47/B47-1) -> #NAME? | D48: =+IF(C47<0,1-D47/C47,D47/C47-1) -> #NAME? | E48: =+IF(D47<0,1-E47/D47,E47/D47-1) -> #NAME? | F48: =+IF(E47<0,1-F47/E47,F47/E47-1) -> #NAME? | G48: =+IF(F47<0,1-G47/F47,G47/F47-1) -> #NAME? | H48: =+IF(G47<0,1-H47/G47,H47/G47-1) -> #NAME? | I48: =+IF(H47<0,1-I47/H47,I47/H47-1) -> #NAME? | J48: =+IF(I47<0,1-J47/I47,J47/I47-1) -> #NAME? | ... AB48: =+IF(AA47<0,1-AB47/AA47,AB47/AA47-1) -> #NAME? | AC48: =+AC47/AB47-1 -> #NAME? | AD48: =+AD47/AC47-1 -> #NAME? | AE48: =+AE47/AD47-1 -> #NAME? | AL48: =+IF(AH47<0,1-AL47/AH47,AL47/AH47-1) -> #NAME? | AM48: =+IF(AI47<0,1-AM47/AI47,AM47/AI47-1) -> #NAME? | AN48: =+IF(AJ47<0,1-AN47/AJ47,AN47/AJ47-1) -> #NAME? | AO48: =+IF(AK47<0,1-AO47/AK47,AO47/AK47-1) -> #NAME? | AP48: =+IF(AL47<0,1-AP47/AL47,AP47/AL47-1) -> #NAME? | AQ48: =+IF(AM47<0,1-AQ47/AM47,AQ47/AM47-1) -> #NAME? | AR48: =+IF(AN47<0,1-AR47/AN47,AR47/AN47-1) -> #NAME? | AS48: =+IF(AO47<0,1-AS47/AO47,AS47/AO47-1) -> #NAME? | ... CO48: =+IF(CK47<0,1-CO47/CK47,CO47/CK47-1) -> #NAME? | CS48: 0.1616897
A49: Provisions and Contingencies | B49: =+'Annual Raw'!C19 -> #NAME? | C49: =+'Annual Raw'!D19 -> #NAME? | D49: =+'Annual Raw'!E19 -> #NAME? | E49: =+'Annual Raw'!F19 -> #NAME? | F49: =+'Annual Raw'!G19 -> #NAME? | G49: =+'Annual Raw'!H19 -> #NAME? | H49: =+'Annual Raw'!I19 -> #NAME? | I49: =+'Annual Raw'!J19 -> #NAME? | ... AA49: =+'Annual Raw'!AB19 -> #NAME? | AB49: =SUM(BZ49:CC49) -> #NAME? | AC49: =SUM(CD49:CG49) -> #NAME? | AD49: =SUM(CH49:CK49) -> #NAME? | AE49: =SUM(CL49:CO49) -> #NAME? | AH49: =+'QTR Raw'!C18 -> #NAME? | AI49: =+'QTR Raw'!D18 -> #NAME? | AJ49: =+'QTR Raw'!E18 -> #NAME? | AK49: =+'QTR Raw'!F18 -> #NAME? | AL49: =+'QTR Raw'!G18 -> #NAME? | AM49: =+'QTR Raw'!H18 -> #NAME? | AN49: =+'QTR Raw'!I18 -> #NAME? | AO49: =+'QTR Raw'!J18 -> #NAME? | ... BY49: =+'QTR Raw'!AT18 -> #NAME? | BZ49: =BZ20*BY5 -> #NAME? | CA49: =CA20*BZ5 -> #NAME? | CB49: =CB20*CA5 -> #NAME? | CC49: =CC20*CB5 -> #NAME? | CD49: =CD20*CC5 -> #NAME? | CE49: =CE20*CD5 -> #NAME? | CF49: =CF20*CE5 -> #NAME? | CG49: =CG20*CF5 -> #NAME? | ... CO49: =CO20*CN5 -> #NAME? | CS49: 2968.45
A50: PBT | B50: =B47-B49 -> #NAME? | C50: =C47-C49 -> #NAME? | D50: =D47-D49 -> #NAME? | E50: =E47-E49 -> #NAME? | F50: =F47-F49 -> #NAME? | G50: =G47-G49 -> #NAME? | H50: =H47-H49 -> #NAME? | I50: =I47-I49 -> #NAME? | ... AE50: =AE47-AE49 -> #NAME? | AH50: =AH47-AH49 -> #NAME? | AI50: =AI47-AI49 -> #NAME? | AJ50: =AJ47-AJ49 -> #NAME? | AK50: =AK47-AK49 -> #NAME? | AL50: =AL47-AL49 -> #NAME? | AM50: =AM47-AM49 -> #NAME? | AN50: =AN47-AN49 -> #NAME? | AO50: =AO47-AO49 -> #NAME? | ... CO50: =CO47-CO49 -> #NAME? | CS50: 7857.37
A51: Tax | B51: =+'Annual Raw'!C18 -> #NAME? | C51: =+'Annual Raw'!D18 -> #NAME? | D51: =+'Annual Raw'!E18 -> #NAME? | E51: =+'Annual Raw'!F18 -> #NAME? | F51: =+'Annual Raw'!G18 -> #NAME? | G51: =+'Annual Raw'!H18 -> #NAME? | H51: =+'Annual Raw'!I18 -> #NAME? | I51: =+'Annual Raw'!J18 -> #NAME? | ... AA51: =+'Annual Raw'!AB18 -> #NAME? | AB51: =SUM(BZ51:CC51) -> #NAME? | AC51: =SUM(CD51:CG51) -> #NAME? | AD51: =SUM(CH51:CK51) -> #NAME? | AE51: =SUM(CL51:CO51) -> #NAME? | AH51: =+'QTR Raw'!C20 -> #NAME? | AI51: =+'QTR Raw'!D20 -> #NAME? | AJ51: =+'QTR Raw'!E20 -> #NAME? | AK51: =+'QTR Raw'!F20 -> #NAME? | AL51: =+'QTR Raw'!G20 -> #NAME? | AM51: =+'QTR Raw'!H20 -> #NAME? | AN51: =+'QTR Raw'!I20 -> #NAME? | AO51: =+'QTR Raw'!J20 -> #NAME? | ... BY51: =+'QTR Raw'!AT20 -> #NAME? | BZ51: =BZ50*0.26 -> #NAME? | CA51: =CA50*0.26 -> #NAME? | CB51: =CB50*0.26 -> #NAME? | CC51: =CC50*0.26 -> #NAME? | CD51: =CD50*0.26 -> #NAME? | CE51: =CE50*0.26 -> #NAME? | CF51: =CF50*0.26 -> #NAME? | CG51: =CG50*0.26 -> #NAME? | ... CO51: =CO50*0.26 -> #NAME? | CS51: 838.05
A52: PAT | B52: =B50-B51 -> #NAME? | C52: =C50-C51 -> #NAME? | D52: =D50-D51 -> #NAME? | E52: =E50-E51 -> #NAME? | F52: =F50-F51 -> #NAME? | G52: =G50-G51 -> #NAME? | H52: =H50-H51 -> #NAME? | I52: =I50-I51 -> #NAME? | ... AE52: =AE50-AE51 -> #NAME? | AH52: =AH50-AH51 -> #NAME? | AI52: =AI50-AI51 -> #NAME? | AJ52: =AJ50-AJ51 -> #NAME? | AK52: =AK50-AK51 -> #NAME? | AL52: =AL50-AL51 -> #NAME? | AM52: =AM50-AM51 -> #NAME? | AN52: =AN50-AN51 -> #NAME? | AO52: =AO50-AO51 -> #NAME? | ... CO52: =CO50-CO51 -> #NAME? | CS52: 7019.32
A53: Minority Interest | B53: =+'Annual Raw'!C25 -> #NAME? | C53: =+'Annual Raw'!D25 -> #NAME? | D53: =+'Annual Raw'!E25 -> #NAME? | E53: =+'Annual Raw'!F25 -> #NAME? | F53: =+'Annual Raw'!G25 -> #NAME? | G53: =+'Annual Raw'!H25 -> #NAME? | H53: =+'Annual Raw'!I25 -> #NAME? | I53: =+'Annual Raw'!J25 -> #NAME? | ... AA53: =+'Annual Raw'!AB25 -> #NAME? | AB53: =SUM(BZ53:CC53) -> 0 | AC53: =SUM(CD53:CG53) -> 0 | AD53: =SUM(CH53:CK53) -> 0 | AE53: =SUM(CL53:CO53) -> 0 | BZ53: =+BY53 -> 0 | CA53: =+BZ53 -> 0 | CB53: =+CA53 -> 0 | CC53: =+CB53 -> 0 | CD53: =+CC53 -> 0 | CE53: =+CD53 -> 0 | CF53: =+CE53 -> 0 | CG53: =+CF53 -> 0 | ... CO53: =+CN53 -> 0 | CS53: 0
A54: Share of Associates | B54: =+'Annual Raw'!C26 -> #NAME? | C54: =+'Annual Raw'!D26 -> #NAME? | D54: =+'Annual Raw'!E26 -> #NAME? | E54: =+'Annual Raw'!F26 -> #NAME? | F54: =+'Annual Raw'!G26 -> #NAME? | G54: =+'Annual Raw'!H26 -> #NAME? | H54: =+'Annual Raw'!I26 -> #NAME? | I54: =+'Annual Raw'!J26 -> #NAME? | ... AA54: =+'Annual Raw'!AB26 -> #NAME? | AB54: =SUM(BZ54:CC54) -> 0 | AC54: =SUM(CD54:CG54) -> 0 | AD54: =SUM(CH54:CK54) -> 0 | AE54: =SUM(CL54:CO54) -> 0 | BZ54: =+BY54 -> 0 | CA54: =+BZ54 -> 0 | CB54: =+CA54 -> 0 | CC54: =+CB54 -> 0 | CD54: =+CC54 -> 0 | CE54: =+CD54 -> 0 | CF54: =+CE54 -> 0 | CG54: =+CF54 -> 0 | ... CO54: =+CN54 -> 0 | CS54: 0
A55: Exceptional items | AH55: =+'QTR Raw'!C15 -> #NAME? | AI55: =+'QTR Raw'!D15 -> #NAME? | AJ55: =+'QTR Raw'!E15 -> #NAME? | AK55: =+'QTR Raw'!F15 -> #NAME? | AL55: =+'QTR Raw'!G15 -> #NAME? | AM55: =+'QTR Raw'!H15 -> #NAME? | AN55: =+'QTR Raw'!I15 -> #NAME? | AO55: =+'QTR Raw'!J15 -> #NAME? | ... BY55: =+'QTR Raw'!AT15 -> #NAME?
A56: Consolidated Net Profit | B56: =B52+B53+B54 -> #NAME? | C56: =C52+C53+C54 -> #NAME? | D56: =D52+D53+D54 -> #NAME? | E56: =E52+E53+E54 -> #NAME? | F56: =F52+F53+F54 -> #NAME? | G56: =G52+G53+G54 -> #NAME? | H56: =H52+H53+H54 -> #NAME? | I56: =I52+I53+I54 -> #NAME? | ... AE56: =AE52+AE53+AE54 -> #NAME? | AH56: =AH52+AH53+AH54+AH55 -> #NAME? | AI56: =AI52+AI53+AI54+AI55 -> #NAME? | AJ56: =AJ52+AJ53+AJ54+AJ55 -> #NAME? | AK56: =AK52+AK53+AK54+AK55 -> #NAME? | AL56: =AL52+AL53+AL54+AL55 -> #NAME? | AM56: =AM52+AM53+AM54+AM55 -> #NAME? | AN56: =AN52+AN53+AN54+AN55 -> #NAME? | AO56: =AO52+AO53+AO54+AO55 -> #NAME? | ... CO56: =CO52+CO53+CO54+CO55 -> #NAME? | CS56: 7019.32
A57: YOY% | C57: =+IF(B56<0,1-C56/B56,C56/B56-1) -> #NAME? | D57: =+IF(C56<0,1-D56/C56,D56/C56-1) -> #NAME? | E57: =+IF(D56<0,1-E56/D56,E56/D56-1) -> #NAME? | F57: =+IF(E56<0,1-F56/E56,F56/E56-1) -> #NAME? | G57: =+IF(F56<0,1-G56/F56,G56/F56-1) -> #NAME? | H57: =+IF(G56<0,1-H56/G56,H56/G56-1) -> #NAME? | I57: =+IF(H56<0,1-I56/H56,I56/H56-1) -> #NAME? | J57: =+IF(I56<0,1-J56/I56,J56/I56-1) -> #NAME? | ... AB57: =+IF(AA56<0,1-AB56/AA56,AB56/AA56-1) -> #NAME? | AC57: =+AC56/AB56-1 -> #NAME? | AD57: =+AD56/AC56-1 -> #NAME? | AE57: =+AE56/AD56-1 -> #NAME? | AL57: =+IF(AH56<0,1-AL56/AH56,AL56/AH56-1) -> #NAME? | AM57: =+IF(AI56<0,1-AM56/AI56,AM56/AI56-1) -> #NAME? | AN57: =+IF(AJ56<0,1-AN56/AJ56,AN56/AJ56-1) -> #NAME? | AO57: =+IF(AK56<0,1-AO56/AK56,AO56/AK56-1) -> #NAME? | AP57: =+IF(AL56<0,1-AP56/AL56,AP56/AL56-1) -> #NAME? | AQ57: =+IF(AM56<0,1-AQ56/AM56,AQ56/AM56-1) -> #NAME? | AR57: =+IF(AN56<0,1-AR56/AN56,AR56/AN56-1) -> #NAME? | AS57: =+IF(AO56<0,1-AS56/AO56,AS56/AO56-1) -> #NAME? | ... CO57: =+IF(CK56<0,1-CO56/CK56,CO56/CK56-1) -> #NAME? | CS57: 0.27166527
A58: Profit & Loss- Annual (End)
A59: ACE | B59: =+'Annual Raw'!C22 -> #NAME? | C59: =+'Annual Raw'!D22 -> #NAME? | D59: =+'Annual Raw'!E22 -> #NAME? | E59: =+'Annual Raw'!F22 -> #NAME? | F59: =+'Annual Raw'!G22 -> #NAME? | G59: =+'Annual Raw'!H22 -> #NAME? | H59: =+'Annual Raw'!I22 -> #NAME? | I59: =+'Annual Raw'!J22 -> #NAME? | ... AA59: =+'Annual Raw'!AB22 -> #NAME? | AH59: =+'QTR Raw'!C21 -> #NAME? | AI59: =+'QTR Raw'!D21 -> #NAME? | AJ59: =+'QTR Raw'!E21 -> #NAME? | AK59: =+'QTR Raw'!F21 -> #NAME? | AL59: =+'QTR Raw'!G21 -> #NAME? | AM59: =+'QTR Raw'!H21 -> #NAME? | AN59: =+'QTR Raw'!I21 -> #NAME? | AO59: =+'QTR Raw'!J21 -> #NAME? | ... BY59: =+'QTR Raw'!AT21 -> #NAME?
A60: Checksum - PAT | B60: =+B56-B59 -> #NAME? | C60: =+C56-C59 -> #NAME? | D60: =+D56-D59 -> #NAME? | E60: =+E56-E59 -> #NAME? | F60: =+F56-F59 -> #NAME? | G60: =+G56-G59 -> #NAME? | H60: =+H56-H59 -> #NAME? | I60: =+I56-I59 -> #NAME? | ... AA60: =+AA56-AA59 -> #NAME? | AH60: =+AH56-AH59 -> #NAME? | AI60: =+AI56-AI59 -> #NAME? | AJ60: =+AJ56-AJ59 -> #NAME? | AK60: =+AK56-AK59 -> #NAME? | AL60: =+AL56-AL59 -> #NAME? | AM60: =+AM56-AM59 -> #NAME? | AN60: =+AN56-AN59 -> #NAME? | AO60: =+AO56-AO59 -> #NAME? | ... BY60: =+BY56-BY59 -> #NAME?
A61: Ratios (Start)
A62: Eq | B62: =+C62 -> #NAME? | C62: =+D62 -> #NAME? | D62: =+E62 -> #NAME? | E62: =+F62 -> #NAME? | F62: =+G62 -> #NAME? | G62: =+H62 -> #NAME? | H62: =+I62 -> #NAME? | I62: =+J62 -> #NAME? | ... Y62: =+Z62 -> #NAME? | Z62: =+'Annual Raw'!AA38 -> #NAME? | AA62: =+'Annual Raw'!AB38 -> #NAME? | AB62: =+CC62 -> #NAME? | AC62: =+CG62 -> #NAME? | AD62: =+CK62 -> #NAME? | AE62: =+CO62 -> #NAME? | AH62: =+'QTR Raw'!C29 -> #NAME? | AI62: =+'QTR Raw'!D29 -> #NAME? | AJ62: =+'QTR Raw'!E29 -> #NAME? | AK62: =+'QTR Raw'!F29 -> #NAME? | AL62: =+'QTR Raw'!G29 -> #NAME? | AM62: =+'QTR Raw'!H29 -> #NAME? | AN62: =+'QTR Raw'!I29 -> #NAME? | AO62: =+'QTR Raw'!J29 -> #NAME? | ... AS62: =+'QTR Raw'!N29 -> #NAME? | AT62: =+AU62 -> #NAME? | AU62: =+AV62 -> #NAME? | AV62: =+AW62 -> #NAME? | AW62: =+AX62 -> #NAME? | AX62: =+AY62 -> #NAME? | AY62: =+AZ62 -> #NAME? | AZ62: =+BA62 -> #NAME? | BA62: =+BB62 -> #NAME? | ... BV62: =+BW62 -> #NAME? | BW62: =+'QTR Raw'!AR29 -> #NAME? | BX62: =+'QTR Raw'!AS29 -> #NAME? | BY62: =+'QTR Raw'!AT29 -> #NAME? | BZ62: =+BY62 -> #NAME? | CA62: =+BZ62 -> #NAME? | CB62: =+CA62 -> #NAME? | CC62: =+CB62 -> #NAME? | CD62: =+CC62 -> #NAME? | CE62: =+CD62 -> #NAME? | CF62: =+CE62 -> #NAME? | CG62: =+CF62 -> #NAME? | ... CO62: =+CN62 -> #NAME? | CS62: 7691.55
A63: FV | B63: =+C63 -> #NAME? | C63: =+D63 -> #NAME? | D63: =+E63 -> #NAME? | E63: =+F63 -> #NAME? | F63: =+G63 -> #NAME? | G63: =+H63 -> #NAME? | H63: =+I63 -> #NAME? | I63: =+J63 -> #NAME? | ... Y63: =+Z63 -> #NAME? | Z63: =+'Annual Raw'!AA50 -> #NAME? | AA63: =+'Annual Raw'!AB50 -> #NAME? | AB63: =+CC63 -> #NAME? | AC63: =+CG63 -> #NAME? | AD63: =+CK63 -> #NAME? | AE63: =+CO63 -> #NAME? | AH63: =+'QTR Raw'!C30 -> #NAME? | AI63: =+'QTR Raw'!D30 -> #NAME? | AJ63: =+'QTR Raw'!E30 -> #NAME? | AK63: =+'QTR Raw'!F30 -> #NAME? | AL63: =+'QTR Raw'!G30 -> #NAME? | AM63: =+'QTR Raw'!H30 -> #NAME? | AN63: =+'QTR Raw'!I30 -> #NAME? | AO63: =+'QTR Raw'!J30 -> #NAME? | ... AS63: =+'QTR Raw'!N30 -> #NAME? | AT63: =+AU63 -> #NAME? | AU63: =+AV63 -> #NAME? | AV63: =+AW63 -> #NAME? | AW63: =+AX63 -> #NAME? | AX63: =+AY63 -> #NAME? | AY63: =+AZ63 -> #NAME? | AZ63: =+BA63 -> #NAME? | BA63: =+BB63 -> #NAME? | ... BV63: =+BW63 -> #NAME? | BW63: =+'QTR Raw'!AR30 -> #NAME? | BX63: =+'QTR Raw'!AS30 -> #NAME? | BY63: =+'QTR Raw'!AT30 -> #NAME? | BZ63: =+BY63 -> #NAME? | CA63: =+BZ63 -> #NAME? | CB63: =+CA63 -> #NAME? | CC63: =+CB63 -> #NAME? | CD63: =+CC63 -> #NAME? | CE63: =+CD63 -> #NAME? | CF63: =+CE63 -> #NAME? | CG63: =+CF63 -> #NAME? | ... CO63: =+CN63 -> #NAME? | CS63: 10
A64: No of share | B64: =B62/B63 -> #NAME? | C64: =C62/C63 -> #NAME? | D64: =D62/D63 -> #NAME? | E64: =E62/E63 -> #NAME? | F64: =F62/F63 -> #NAME? | G64: =G62/G63 -> #NAME? | H64: =H62/H63 -> #NAME? | I64: =I62/I63 -> #NAME? | ... AE64: =AE62/AE63 -> #NAME? | AH64: =AH62/AH63 -> #NAME? | AI64: =AI62/AI63 -> #NAME? | AJ64: =AJ62/AJ63 -> #NAME? | AK64: =AK62/AK63 -> #NAME? | AL64: =AL62/AL63 -> #NAME? | AM64: =AM62/AM63 -> #NAME? | AN64: =AN62/AN63 -> #NAME? | AO64: =AO62/AO63 -> #NAME? | ... CO64: =CO62/CO63 -> #NAME? | CS64: 769.155
A65: EPS | B65: =B56/B64 -> #NAME? | C65: =C56/C64 -> #NAME? | D65: =D56/D64 -> #NAME? | E65: =E56/E64 -> #NAME? | F65: =F56/F64 -> #NAME? | G65: =G56/G64 -> #NAME? | H65: =H56/H64 -> #NAME? | I65: =I56/I64 -> #NAME? | ... AE65: =AE56/AE64 -> #NAME? | AH65: =AH56/AH64 -> #NAME? | AI65: =AI56/AI64 -> #NAME? | AJ65: =AJ56/AJ64 -> #NAME? | AK65: =AK56/AK64 -> #NAME? | AL65: =AL56/AL64 -> #NAME? | AM65: =AM56/AM64 -> #NAME? | AN65: =AN56/AN64 -> #NAME? | AO65: =AO56/AO64 -> #NAME? | ... CO65: =CO56/CO64 -> #NAME? | CS65: 9.1260149
A66: EPS TTM | B66: =+B65 -> #NAME? | C66: =+C65 -> #NAME? | D66: =+D65 -> #NAME? | E66: =+E65 -> #NAME? | F66: =+F65 -> #NAME? | G66: =+G65 -> #NAME? | H66: =+H65 -> #NAME? | I66: =+I65 -> #NAME? | ... AE66: =+AE65 -> #NAME? | AK66: =AK65+AJ65+AI65+AH65 -> #NAME? | AL66: =AL65+AK65+AJ65+AI65 -> #NAME? | AM66: =AM65+AL65+AK65+AJ65 -> #NAME? | AN66: =AN65+AM65+AL65+AK65 -> #NAME? | AO66: =AO65+AN65+AM65+AL65 -> #NAME? | AP66: =AP65+AO65+AN65+AM65 -> #NAME? | AQ66: =AQ65+AP65+AO65+AN65 -> #NAME? | AR66: =AR65+AQ65+AP65+AO65 -> #NAME? | ... CO66: =CO65+CN65+CM65+CL65 -> #NAME? | CS66: 9.1260149
A67: Bloomberg Estimate
A68: Estimate Deviation | CC68: =+CC66/CC67-1 -> #NAME? | CG68: =+CG66/CG67-1 -> #NAME?
A69: BVPS | B69: =B109/B64 -> #NAME? | C69: =C109/C64 -> #NAME? | D69: =D109/D64 -> #NAME? | E69: =E109/E64 -> #NAME? | F69: =F109/F64 -> #NAME? | G69: =G109/G64 -> #NAME? | H69: =H109/H64 -> #NAME? | I69: =I109/I64 -> #NAME? | ... AE69: =AE109/AE64 -> #NAME? | AH69: =AH109/AH64 -> #NAME? | AI69: =AI109/AI64 -> #NAME? | AJ69: =AJ109/AJ64 -> #NAME? | AK69: =AK109/AK64 -> #NAME? | AL69: =AL109/AL64 -> #NAME? | AM69: =AM109/AM64 -> #NAME? | AN69: =AN109/AN64 -> #NAME? | AO69: =AO109/AO64 -> #NAME? | ... CO69: =CO109/CO64 -> #NAME? | CS69: 43.044406
A70: ABVPS | C70: =+C69-C78 -> #NAME? | D70: =+D69-D78 -> #NAME? | E70: =+E69-E78 -> #NAME? | F70: =+F69-F78 -> #NAME? | G70: =+G69-G78 -> #NAME? | H70: =+H69-H78 -> #NAME? | I70: =+I69-I78 -> #NAME? | J70: =+J69-J78 -> #NAME? | ... AE70: =+AE69-AE78 -> #NAME? | AI70: =+AI69-AI78 -> #NAME? | AJ70: =+AJ69-AJ78 -> #NAME? | AK70: =+AK69-AK78 -> #NAME? | AL70: =+AL69-AL78 -> #NAME? | AM70: =+AM69-AM78 -> #NAME? | AN70: =+AN69-AN78 -> #NAME? | AO70: =+AO69-AO78 -> #NAME? | AP70: =+AP69-AP78 -> #NAME? | ... CO70: =+CO69-CO78 -> #NAME? | CS70: 43.044406
A72: Capital Adequacy Ratio Basel III | B72: =+'Annual Raw'!C92 -> #NAME? | C72: =+'Annual Raw'!D92 -> #NAME? | D72: =+'Annual Raw'!E92 -> #NAME? | E72: =+'Annual Raw'!F92 -> #NAME? | F72: =+'Annual Raw'!G92 -> #NAME? | G72: =+'Annual Raw'!H92 -> #NAME? | H72: =+'Annual Raw'!I92 -> #NAME? | I72: =+'Annual Raw'!J92 -> #NAME? | ... AA72: =+'Annual Raw'!AB92 -> #NAME? | AI72: =+'QTR Raw'!D36 -> #NAME? | AJ72: =+'QTR Raw'!E36 -> #NAME? | AK72: =+'QTR Raw'!F36 -> #NAME? | AL72: =+'QTR Raw'!G36 -> #NAME? | AM72: =+'QTR Raw'!H36 -> #NAME? | AN72: =+'QTR Raw'!I36 -> #NAME? | AO72: =+'QTR Raw'!J36 -> #NAME? | AP72: =+'QTR Raw'!K36 -> #NAME? | ... BY72: =+'QTR Raw'!AT36 -> #NAME?
A73: Tier 1 Basel III | B73: =+'Annual Raw'!C93 -> #NAME? | C73: =+'Annual Raw'!D93 -> #NAME? | D73: =+'Annual Raw'!E93 -> #NAME? | E73: =+'Annual Raw'!F93 -> #NAME? | F73: =+'Annual Raw'!G93 -> #NAME? | G73: =+'Annual Raw'!H93 -> #NAME? | H73: =+'Annual Raw'!I93 -> #NAME? | I73: =+'Annual Raw'!J93 -> #NAME? | ... AA73: =+'Annual Raw'!AB93 -> #NAME? | AI73: =+'QTR Raw'!D37 -> #NAME? | AJ73: =+'QTR Raw'!E37 -> #NAME? | AK73: =+'QTR Raw'!F37 -> #NAME? | AL73: =+'QTR Raw'!G37 -> #NAME? | AM73: =+'QTR Raw'!H37 -> #NAME? | AN73: =+'QTR Raw'!I37 -> #NAME? | AO73: =+'QTR Raw'!J37 -> #NAME? | AP73: =+'QTR Raw'!K37 -> #NAME? | ... BY73: =+'QTR Raw'!AT37 -> #NAME?
A74: Tier 2 Basel III | B74: =+'Annual Raw'!C94 -> #NAME? | C74: =+'Annual Raw'!D94 -> #NAME? | D74: =+'Annual Raw'!E94 -> #NAME? | E74: =+'Annual Raw'!F94 -> #NAME? | F74: =+'Annual Raw'!G94 -> #NAME? | G74: =+'Annual Raw'!H94 -> #NAME? | H74: =+'Annual Raw'!I94 -> #NAME? | I74: =+'Annual Raw'!J94 -> #NAME? | ... AA74: =+'Annual Raw'!AB94 -> #NAME? | AI74: =+'QTR Raw'!D38 -> #NAME? | AJ74: =+'QTR Raw'!E38 -> #NAME? | AK74: =+'QTR Raw'!F38 -> #NAME? | AL74: =+'QTR Raw'!G38 -> #NAME? | AM74: =+'QTR Raw'!H38 -> #NAME? | AN74: =+'QTR Raw'!I38 -> #NAME? | AO74: =+'QTR Raw'!J38 -> #NAME? | AP74: =+'QTR Raw'!K38 -> #NAME? | ... BY74: =+'QTR Raw'!AT38 -> #NAME?
A76: GNPA | B76: =+'Annual Raw'!C52 -> #NAME? | C76: =+'Annual Raw'!D52 -> #NAME? | D76: =+'Annual Raw'!E52 -> #NAME? | E76: =+'Annual Raw'!F52 -> #NAME? | F76: =+'Annual Raw'!G52 -> #NAME? | G76: =+'Annual Raw'!H52 -> #NAME? | H76: =+'Annual Raw'!I52 -> #NAME? | I76: =+'Annual Raw'!J52 -> #NAME? | ... AA76: =+'Annual Raw'!AB52 -> #NAME? | AH76: =+'QTR Raw'!C40 -> #NAME? | AI76: =+'QTR Raw'!D40 -> #NAME? | AJ76: =+'QTR Raw'!E40 -> #NAME? | AK76: =+'QTR Raw'!F40 -> #NAME? | AL76: =+'QTR Raw'!G40 -> #NAME? | AM76: =+'QTR Raw'!H40 -> #NAME? | AN76: =+'QTR Raw'!I40 -> #NAME? | AO76: =+'QTR Raw'!J40 -> #NAME? | ... BY76: =+'QTR Raw'!AT40 -> #NAME?
A77: NNPA | B77: =+'Annual Raw'!C53 -> #NAME? | C77: =+'Annual Raw'!D53 -> #NAME? | D77: =+'Annual Raw'!E53 -> #NAME? | E77: =+'Annual Raw'!F53 -> #NAME? | F77: =+'Annual Raw'!G53 -> #NAME? | G77: =+'Annual Raw'!H53 -> #NAME? | H77: =+'Annual Raw'!I53 -> #NAME? | I77: =+'Annual Raw'!J53 -> #NAME? | ... AA77: =+'Annual Raw'!AB53 -> #NAME? | AH77: =+'QTR Raw'!C41 -> #NAME? | AI77: =+'QTR Raw'!D41 -> #NAME? | AJ77: =+'QTR Raw'!E41 -> #NAME? | AK77: =+'QTR Raw'!F41 -> #NAME? | AL77: =+'QTR Raw'!G41 -> #NAME? | AM77: =+'QTR Raw'!H41 -> #NAME? | AN77: =+'QTR Raw'!I41 -> #NAME? | AO77: =+'QTR Raw'!J41 -> #NAME? | ... BY77: =+'QTR Raw'!AT41 -> #NAME? | BZ77: =+BZ81*BZ119 -> #NAME? | CA77: =+CA81*CA119 -> #NAME? | CB77: =+CB81*CB119 -> #NAME? | CC77: =+CC81*CC119 -> #NAME? | CD77: =+CD81*CD119 -> #NAME? | CE77: =+CE81*CE119 -> #NAME? | CF77: =+CF81*CF119 -> #NAME? | CG77: =+CG81*CG119 -> #NAME? | ... CO77: =+CO81*CO119 -> #NAME?
A78: NNPA Per Share | C78: =+C77/C64 -> #NAME? | D78: =+D77/D64 -> #NAME? | E78: =+E77/E64 -> #NAME? | F78: =+F77/F64 -> #NAME? | G78: =+G77/G64 -> #NAME? | H78: =+H77/H64 -> #NAME? | I78: =+I77/I64 -> #NAME? | J78: =+J77/J64 -> #NAME? | ... AA78: =+AA77/AA64 -> #NAME? | AI78: =+AI77/AI64 -> #NAME? | AJ78: =+AJ77/AJ64 -> #NAME? | AK78: =+AK77/AK64 -> #NAME? | AL78: =+AL77/AL64 -> #NAME? | AM78: =+AM77/AM64 -> #NAME? | AN78: =+AN77/AN64 -> #NAME? | AO78: =+AO77/AO64 -> #NAME? | AP78: =+AP77/AP64 -> #NAME? | ... CO78: =+CO77/CO64 -> #NAME?
A80: GNPA % | B80: =+B76/B119 -> #NAME? | C80: =+C76/C119 -> #NAME? | D80: =+D76/D119 -> #NAME? | E80: =+E76/E119 -> #NAME? | F80: =+F76/F119 -> #NAME? | G80: =+G76/G119 -> #NAME? | H80: =+H76/H119 -> #NAME? | I80: =+I76/I119 -> #NAME? | ... AA80: =+AA76/AA119 -> #NAME? | AI80: =+AI76/AI119 -> #NAME? | AJ80: =+AJ76/AJ119 -> #NAME? | AK80: =+AK76/AK119 -> #NAME? | AL80: =+AL76/AL119 -> #NAME? | AM80: =+AM76/AM119 -> #NAME? | AN80: =+AN76/AN119 -> #NAME? | AO80: =+AO76/AO119 -> #NAME? | AP80: =+AP76/AP119 -> #NAME? | ... BY80: =+BY76/BY119 -> #NAME?
A81: NNPA % | B81: =+B77/B119 -> #NAME? | C81: =+C77/C119 -> #NAME? | D81: =+D77/D119 -> #NAME? | E81: =+E77/E119 -> #NAME? | F81: =+F77/F119 -> #NAME? | G81: =+G77/G119 -> #NAME? | H81: =+H77/H119 -> #NAME? | I81: =+I77/I119 -> #NAME? | ... AA81: =+AA77/AA119 -> #NAME? | AI81: =+AI77/AI119 -> #NAME? | AJ81: =+AJ77/AJ119 -> #NAME? | AK81: =+AK77/AK119 -> #NAME? | AL81: =+AL77/AL119 -> #NAME? | AM81: =+AM77/AM119 -> #NAME? | AN81: =+AN77/AN119 -> #NAME? | AO81: =+AO77/AO119 -> #NAME? | AP81: =+AP77/AP119 -> #NAME? | ... BY81: =+BY77/BY119 -> #NAME? | BZ81: =+BY81 -> #NAME? | CA81: =+BZ81 -> #NAME? | CB81: =+CA81 -> #NAME? | CC81: =+CB81 -> #NAME? | CD81: =+CC81 -> #NAME? | CE81: =+CD81 -> #NAME? | CF81: =+CE81 -> #NAME? | CG81: =+CF81 -> #NAME? | ... CO81: =+CN81 -> #NAME?
A83: NIM %(Reported) | B83: =+'Annual Raw'!C54 -> #NAME? | C83: =+'Annual Raw'!D54 -> #NAME? | D83: =+'Annual Raw'!E54 -> #NAME? | E83: =+'Annual Raw'!F54 -> #NAME? | F83: =+'Annual Raw'!G54 -> #NAME? | G83: =+'Annual Raw'!H54 -> #NAME? | H83: =+'Annual Raw'!I54 -> #NAME? | I83: =+'Annual Raw'!J54 -> #NAME? | ... AA83: =+'Annual Raw'!AB54 -> #NAME? | AH83: =+'QTR Raw'!C48 -> #NAME? | AI83: =+'QTR Raw'!D48 -> #NAME? | AJ83: =+'QTR Raw'!E48 -> #NAME? | AK83: =+'QTR Raw'!F48 -> #NAME? | AL83: =+'QTR Raw'!G48 -> #NAME? | AM83: =+'QTR Raw'!H48 -> #NAME? | AN83: =+'QTR Raw'!I48 -> #NAME? | AO83: =+'QTR Raw'!J48 -> #NAME? | ... BY83: =+'QTR Raw'!AT48 -> #NAME?
A84: NIIM %(Calculated) | D84: =+D36/D86 -> #NAME? | E84: =+E36/E86 -> #NAME? | F84: =+F36/F86 -> #NAME? | G84: =+G36/G86 -> #NAME? | H84: =+H36/H86 -> #NAME? | I84: =+I36/I86 -> #NAME? | J84: =+J36/J86 -> #NAME? | K84: =+K36/K86 -> #NAME? | ... AA84: =+AA36/AA86 -> #NAME? | AI84: =+AI36/AI86*4 -> #NAME? | AJ84: =+AJ36/AJ86*4 -> #NAME? | AK84: =+AK36/AK86*4 -> #NAME? | AL84: =+AL36/AL86*4 -> #NAME? | AM84: =+AM36/AM86*4 -> #NAME? | AN84: =+AN36/AN86*4 -> #NAME? | AO84: =+AO36/AO86*4 -> #NAME? | AP84: =+AP36/AP86*4 -> #NAME? | ... CO84: =+CO36/CO86*4 -> #NAME?
A85: Earning Asset | C85: =+SUM(C118:C119) -> #NAME? | D85: =+SUM(D118:D119) -> #NAME? | E85: =+SUM(E118:E119) -> #NAME? | F85: =+SUM(F118:F119) -> #NAME? | G85: =+SUM(G118:G119) -> #NAME? | H85: =+SUM(H118:H119) -> #NAME? | I85: =+SUM(I118:I119) -> #NAME? | J85: =+SUM(J118:J119) -> #NAME? | ... AA85: =+SUM(AA118:AA119) -> #NAME? | AI85: =+SUM(AI118:AI119) -> #NAME? | AJ85: =+SUM(AJ118:AJ119) -> #NAME? | AK85: =+SUM(AK118:AK119) -> #NAME? | AL85: =+SUM(AL118:AL119) -> #NAME? | AM85: =+SUM(AM118:AM119) -> #NAME? | AN85: =+SUM(AN118:AN119) -> #NAME? | AO85: =+SUM(AO118:AO119) -> #NAME? | AP85: =+SUM(AP118:AP119) -> #NAME? | ... CO85: =+SUM(CO118:CO119) -> #NAME?
A86: Average Earning Asset | D86: =+AVERAGE(C85:D85) -> #NAME? | E86: =+AVERAGE(D85:E85) -> #NAME? | F86: =+AVERAGE(E85:F85) -> #NAME? | G86: =+AVERAGE(F85:G85) -> #NAME? | H86: =+AVERAGE(G85:H85) -> #NAME? | I86: =+AVERAGE(H85:I85) -> #NAME? | J86: =+AVERAGE(I85:J85) -> #NAME? | K86: =+AVERAGE(J85:K85) -> #NAME? | ... AA86: =+AVERAGE(Z85:AA85) -> #NAME? | AI86: =+AVERAGE(AH85:AI85) -> #NAME? | AJ86: =+AVERAGE(AI85:AJ85) -> #NAME? | AK86: =+AVERAGE(AJ85:AK85) -> #NAME? | AL86: =+AVERAGE(AK85:AL85) -> #NAME? | AM86: =+AVERAGE(AL85:AM85) -> #NAME? | AN86: =+AVERAGE(AM85:AN85) -> #NAME? | AO86: =+AVERAGE(AN85:AO85) -> #NAME? | AP86: =+AVERAGE(AO85:AP85) -> #NAME? | ... CO86: =+AVERAGE(CN85:CO85) -> #NAME?
A87: ROE % | D87: =D56/D109 -> #NAME? | E87: =E56/E109 -> #NAME? | F87: =F56/F109 -> #NAME? | G87: =G56/G109 -> #NAME? | H87: =H56/H109 -> #NAME? | I87: =I56/I109 -> #NAME? | J87: =J56/J109 -> #NAME? | K87: =K56/K109 -> #NAME? | ... AE87: =AE56/AE109 -> #NAME? | BN87: =SUM(BK56:BN56)/BN109 -> #NAME? | BO87: =SUM(BL56:BO56)/BO109 -> #NAME? | BP87: =SUM(BM56:BP56)/BP109 -> #NAME? | BQ87: =SUM(BN56:BQ56)/BQ109 -> #NAME? | BR87: =SUM(BO56:BR56)/BR109 -> #NAME? | BS87: =SUM(BP56:BS56)/BS109 -> #NAME? | BT87: =SUM(BQ56:BT56)/BT109 -> #NAME? | BU87: =SUM(BR56:BU56)/BU109 -> #NAME? | ... CG87: =SUM(CD56:CG56)/CG109 -> #NAME? | CS87: 0.21201396
A89: Ratios (End)
A90: Valuation (Start)
A92: Share Price
A93: Close | B93: =+'Annual Raw'!C45 -> #NAME? | C93: =+'Annual Raw'!D45 -> #NAME? | D93: =+'Annual Raw'!E45 -> #NAME? | E93: =+'Annual Raw'!F45 -> #NAME? | F93: =+'Annual Raw'!G45 -> #NAME? | G93: =+'Annual Raw'!H45 -> #NAME? | H93: =+'Annual Raw'!I45 -> #NAME? | I93: =+'Annual Raw'!J45 -> #NAME? | ... AA93: =+'Annual Raw'!AB45 -> #NAME? | AB93: =+CC93 -> 75.5 | AC93: =+CG93 -> 75.5 | AD93: =+CK93 -> 75.5 | AE93: =+CO93 -> 75.5 | AH93: =+'QTR Share Price'!IA21 -> #NAME? | AI93: =+'QTR Share Price'!IB21 -> #NAME? | AJ93: =+'QTR Share Price'!IC21 -> #NAME? | AK93: =+'QTR Share Price'!ID21 -> #NAME? | AL93: =+'QTR Share Price'!IE21 -> #NAME? | AM93: =+'QTR Share Price'!IF21 -> #NAME? | AN93: =+'QTR Share Price'!IG21 -> #NAME? | AO93: =+'QTR Share Price'!IH21 -> #NAME? | ... BY93: =+'QTR Share Price'!JR21 -> #NAME? | BZ93: 75.5 | CA93: =+BZ93 -> 75.5 | CB93: =+CA93 -> 75.5 | CC93: =+CB93 -> 75.5 | CD93: =+CC93 -> 75.5 | CE93: =+CD93 -> 75.5 | CF93: =+CE93 -> 75.5 | CG93: =+CF93 -> 75.5 | CH93: =+CG93 -> 75.5 | ... CO93: =+CN93 -> 75.5 | CS93: 61.32
A94: High | B94: =+'Annual Raw'!C46 -> #NAME? | C94: =+'Annual Raw'!D46 -> #NAME? | D94: =+'Annual Raw'!E46 -> #NAME? | E94: =+'Annual Raw'!F46 -> #NAME? | F94: =+'Annual Raw'!G46 -> #NAME? | G94: =+'Annual Raw'!H46 -> #NAME? | H94: =+'Annual Raw'!I46 -> #NAME? | I94: =+'Annual Raw'!J46 -> #NAME? | ... AA94: =+'Annual Raw'!AB46 -> #NAME? | AB94: =+MAX(BZ94:CC94) -> #NAME? | AC94: =+MAX(CD94:CG94) -> #NAME? | AD94: =+MAX(CH94:CK94) -> #NAME? | AE94: =+MAX(CL94:CO94) -> #NAME? | AH94: =+'QTR Share Price'!IA19 -> #NAME? | AI94: =+'QTR Share Price'!IB19 -> #NAME? | AJ94: =+'QTR Share Price'!IC19 -> #NAME? | AK94: =+'QTR Share Price'!ID19 -> #NAME? | AL94: =+'QTR Share Price'!IE19 -> #NAME? | AM94: =+'QTR Share Price'!IF19 -> #NAME? | AN94: =+'QTR Share Price'!IG19 -> #NAME? | AO94: =+'QTR Share Price'!IH19 -> #NAME? | ... BY94: =+'QTR Share Price'!JR19 -> #NAME? | BZ94: =+BZ102*BZ70 -> #NAME? | CA94: =+CA102*CA70 -> #NAME? | CB94: =+CB102*CB70 -> #NAME? | CC94: =+CC102*CC70 -> #NAME? | CD94: =+CD102*CD70 -> #NAME? | CE94: =+CE102*CE70 -> #NAME? | CF94: =+CF102*CF70 -> #NAME? | CG94: =+CG102*CG70 -> #NAME? | ... CO94: =+CO102*CO70 -> #NAME? | CS94: 76.99
A95: Low | B95: =+'Annual Raw'!C47 -> #NAME? | C95: =+'Annual Raw'!D47 -> #NAME? | D95: =+'Annual Raw'!E47 -> #NAME? | E95: =+'Annual Raw'!F47 -> #NAME? | F95: =+'Annual Raw'!G47 -> #NAME? | G95: =+'Annual Raw'!H47 -> #NAME? | H95: =+'Annual Raw'!I47 -> #NAME? | I95: =+'Annual Raw'!J47 -> #NAME? | ... AA95: =+'Annual Raw'!AB47 -> #NAME? | AB95: =+MIN(BZ95:CC95) -> #NAME? | AC95: =+MIN(CD95:CG95) -> #NAME? | AD95: =+MIN(CH95:CK95) -> #NAME? | AE95: =+MIN(CL95:CO95) -> #NAME? | AH95: =+'QTR Share Price'!IA20 -> #NAME? | AI95: =+'QTR Share Price'!IB20 -> #NAME? | AJ95: =+'QTR Share Price'!IC20 -> #NAME? | AK95: =+'QTR Share Price'!ID20 -> #NAME? | AL95: =+'QTR Share Price'!IE20 -> #NAME? | AM95: =+'QTR Share Price'!IF20 -> #NAME? | AN95: =+'QTR Share Price'!IG20 -> #NAME? | AO95: =+'QTR Share Price'!IH20 -> #NAME? | ... BY95: =+'QTR Share Price'!JR20 -> #NAME? | BZ95: =+BZ103*BZ70 -> #NAME? | CA95: =+CA103*CA70 -> #NAME? | CB95: =+CB103*CB70 -> #NAME? | CC95: =+CC103*CC70 -> #NAME? | CD95: =+CD103*CD70 -> #NAME? | CE95: =+CE103*CE70 -> #NAME? | CF95: =+CF103*CF70 -> #NAME? | CG95: =+CG103*CG70 -> #NAME? | ... CO95: =+CO103*CO70 -> #NAME? | CS95: 38.11
A97: Upside (%) | BZ97: =+BZ94/BZ93-1 -> #NAME? | CA97: =+CA94/CA93-1 -> #NAME? | CB97: =+CB94/CB93-1 -> #NAME? | CC97: =+CC94/CC93-1 -> #NAME? | CD97: =+CD94/CD93-1 -> #NAME? | CE97: =+CE94/CE93-1 -> #NAME? | CF97: =+CF94/CF93-1 -> #NAME? | CG97: =+CG94/CG93-1 -> #NAME? | ... CO97: =+CO94/CO93-1 -> #NAME?
A98: Downside (%) | BZ98: =+BZ95/BZ93-1 -> #NAME? | CA98: =+CA95/CA93-1 -> #NAME? | CB98: =+CB95/CB93-1 -> #NAME? | CC98: =+CC95/CC93-1 -> #NAME? | CD98: =+CD95/CD93-1 -> #NAME? | CE98: =+CE95/CE93-1 -> #NAME? | CF98: =+CF95/CF93-1 -> #NAME? | CG98: =+CG95/CG93-1 -> #NAME? | ... CO98: =+CO95/CO93-1 -> #NAME?
A100: P/ABVPS
A101: Close | B101: =+B93/B70 -> #NAME? | C101: =+C93/C70 -> #NAME? | D101: =+D93/D70 -> #NAME? | E101: =+E93/E70 -> #NAME? | F101: =+F93/F70 -> #NAME? | G101: =+G93/G70 -> #NAME? | H101: =+H93/H70 -> #NAME? | I101: =+I93/I70 -> #NAME? | ... AE101: =+AE93/AE70 -> #NAME? | AH101: =+AH93/AH70 -> #NAME? | AI101: =+AI93/AI70 -> #NAME? | AJ101: =+AJ93/AJ70 -> #NAME? | AK101: =+AK93/AK70 -> #NAME? | AL101: =+AL93/AL70 -> #NAME? | AM101: =+AM93/AM70 -> #NAME? | AN101: =+AN93/AN70 -> #NAME? | AO101: =+AO93/AO70 -> #NAME? | ... CO101: =+CO93/CO70 -> #NAME? | CS101: 1.4245754
A102: High | B102: =B94/B65 -> #NAME? | C102: =C94/C65 -> #NAME? | D102: =D94/D70 -> #NAME? | E102: =E94/E70 -> #NAME? | F102: =F94/F70 -> #NAME? | G102: =G94/G70 -> #NAME? | H102: =H94/H70 -> #NAME? | I102: =I94/I70 -> #NAME? | J102: =J94/J70 -> #NAME? | K102: =K94/K70 -> #NAME? | ... AE102: =AE94/AE70 -> #NAME? | AH102: =AH94/AH70 -> #NAME? | AI102: =AI94/AI70 -> #NAME? | AJ102: =AJ94/AJ70 -> #NAME? | AK102: =AK94/AK70 -> #NAME? | AL102: =AL94/AL70 -> #NAME? | AM102: =AM94/AM70 -> #NAME? | AN102: =AN94/AN70 -> #NAME? | AO102: =AO94/AO70 -> #NAME? | ... BY102: =BY94/BY70 -> #NAME? | BZ102: 2.2 | CA102: =BZ102 -> 2.2 | CB102: =CA102 -> 2.2 | CC102: =CB102 -> 2.2 | CD102: =CC102 -> 2.2 | CE102: =CD102 -> 2.2 | CF102: =CE102 -> 2.2 | CG102: =CF102 -> 2.2 | CH102: =CG102 -> 2.2 | ... CO102: =CN102 -> 2.2 | CS102: 1.788618
A103: Low | B103: =B95/B65 -> #NAME? | C103: =C95/C65 -> #NAME? | D103: =D95/D70 -> #NAME? | E103: =E95/E70 -> #NAME? | F103: =F95/F70 -> #NAME? | G103: =G95/G70 -> #NAME? | H103: =H95/H70 -> #NAME? | I103: =I95/I70 -> #NAME? | J103: =J95/J70 -> #NAME? | K103: =K95/K70 -> #NAME? | ... AE103: =AE95/AE70 -> #NAME? | AH103: =AH95/AH70 -> #NAME? | AI103: =AI95/AI70 -> #NAME? | AJ103: =AJ95/AJ70 -> #NAME? | AK103: =AK95/AK70 -> #NAME? | AL103: =AL95/AL70 -> #NAME? | AM103: =AM95/AM70 -> #NAME? | AN103: =AN95/AN70 -> #NAME? | AO103: =AO95/AO70 -> #NAME? | ... BY103: =BY95/BY70 -> #NAME? | BZ103: =BY103 -> #NAME? | CA103: =BZ103 -> #NAME? | CB103: =CA103 -> #NAME? | CC103: =CB103 -> #NAME? | CD103: =CC103 -> #NAME? | CE103: =CD103 -> #NAME? | CF103: =CE103 -> #NAME? | CG103: =CF103 -> #NAME? | ... CO103: =CN103 -> #NAME? | CS103: 0.88536476
A105: Valuation (End)
A106: Balance Sheet (Start)
A107: Share Capital | B107: =+'Annual Raw'!C63 -> #NAME? | C107: =+'Annual Raw'!D63 -> #NAME? | D107: =+'Annual Raw'!E63 -> #NAME? | E107: =+'Annual Raw'!F63 -> #NAME? | F107: =+'Annual Raw'!G63 -> #NAME? | G107: =+'Annual Raw'!H63 -> #NAME? | H107: =+'Annual Raw'!I63 -> #NAME? | I107: =+'Annual Raw'!J63 -> #NAME? | ... AA107: =+'Annual Raw'!AB63 -> #NAME? | AB107: =CC107 -> #NAME? | AC107: =CG107 -> #NAME? | AD107: =CK107 -> #NAME? | AE107: =CO107 -> #NAME? | AH107: =+'QTR Raw'!C54 -> #NAME? | AI107: =+'QTR Raw'!D54 -> #NAME? | AJ107: =+'QTR Raw'!E54 -> #NAME? | AK107: =+'QTR Raw'!F54 -> #NAME? | AL107: =+'QTR Raw'!G54 -> #NAME? | AM107: =+'QTR Raw'!H54 -> #NAME? | AN107: =+'QTR Raw'!I54 -> #NAME? | AO107: =+'QTR Raw'!J54 -> #NAME? | ... BY107: =+'QTR Raw'!AT54 -> #NAME? | BZ107: =BY107 -> #NAME? | CA107: =BZ107 -> #NAME? | CB107: =CA107 -> #NAME? | CC107: =CB107 -> #NAME? | CD107: =CC107 -> #NAME? | CE107: =CD107 -> #NAME? | CF107: =CE107 -> #NAME? | CG107: =CF107 -> #NAME? | ... CO107: =CN107 -> #NAME? | CS107: 7691.56
A108: Total Reserves | B108: =+'Annual Raw'!C65+'Annual Raw'!C64 -> #NAME? | C108: =+'Annual Raw'!D65+'Annual Raw'!D64 -> #NAME? | D108: =+'Annual Raw'!E65+'Annual Raw'!E64 -> #NAME? | E108: =+'Annual Raw'!F65+'Annual Raw'!F64 -> #NAME? | F108: =+'Annual Raw'!G65+'Annual Raw'!G64 -> #NAME? | G108: =+'Annual Raw'!H65+'Annual Raw'!H64 -> #NAME? | H108: =+'Annual Raw'!I65+'Annual Raw'!I64 -> #NAME? | I108: =+'Annual Raw'!J65+'Annual Raw'!J64 -> #NAME? | ... AA108: =+'Annual Raw'!AB65+'Annual Raw'!AB64 -> #NAME? | AB108: =CC108 -> #NAME? | AC108: =CG108 -> #NAME? | AD108: =CK108 -> #NAME? | AE108: =CO108 -> #NAME? | AH108: =+'QTR Raw'!C56+'QTR Raw'!C55 -> #NAME? | AI108: =+'QTR Raw'!D56+'QTR Raw'!D55 -> #NAME? | AJ108: =+'QTR Raw'!E56+'QTR Raw'!E55 -> #NAME? | AK108: =+'QTR Raw'!F56+'QTR Raw'!F55 -> #NAME? | AL108: =+'QTR Raw'!G56+'QTR Raw'!G55 -> #NAME? | AM108: =+'QTR Raw'!H56+'QTR Raw'!H55 -> #NAME? | AN108: =+'QTR Raw'!I56+'QTR Raw'!I55 -> #NAME? | AO108: =+'QTR Raw'!J56+'QTR Raw'!J55 -> #NAME? | ... BY108: =+'QTR Raw'!AT56+'QTR Raw'!AT55 -> #NAME? | BZ108: =BY108+BZ56 -> #NAME? | CA108: =BZ108+CA56 -> #NAME? | CB108: =CA108+CB56 -> #NAME? | CC108: =CB108+CC56 -> #NAME? | CD108: =CC108+CD56 -> #NAME? | CE108: =CD108+CE56 -> #NAME? | CF108: =CE108+CF56 -> #NAME? | CG108: =CF108+CG56 -> #NAME? | ... CO108: =CN108+CO56 -> #NAME? | CS108: 25416.26
A109: Shareholder's Funds | B109: =SUM(B107:B108) -> #NAME? | C109: =SUM(C107:C108) -> #NAME? | D109: =SUM(D107:D108) -> #NAME? | E109: =SUM(E107:E108) -> #NAME? | F109: =SUM(F107:F108) -> #NAME? | G109: =SUM(G107:G108) -> #NAME? | H109: =SUM(H107:H108) -> #NAME? | I109: =SUM(I107:I108) -> #NAME? | ... AE109: =SUM(AE107:AE108) -> #NAME? | AH109: =SUM(AH107:AH108) -> #NAME? | AI109: =SUM(AI107:AI108) -> #NAME? | AJ109: =SUM(AJ107:AJ108) -> #NAME? | AK109: =SUM(AK107:AK108) -> #NAME? | AL109: =SUM(AL107:AL108) -> #NAME? | AM109: =SUM(AM107:AM108) -> #NAME? | AN109: =SUM(AN107:AN108) -> #NAME? | AO109: =SUM(AO107:AO108) -> #NAME? | ... CO109: =SUM(CO107:CO108) -> #NAME? | CS109: 33107.82
A111: Minority Interest | B111: =+'Annual Raw'!C66 -> #NAME? | C111: =+'Annual Raw'!D66 -> #NAME? | D111: =+'Annual Raw'!E66 -> #NAME? | E111: =+'Annual Raw'!F66 -> #NAME? | F111: =+'Annual Raw'!G66 -> #NAME? | G111: =+'Annual Raw'!H66 -> #NAME? | H111: =+'Annual Raw'!I66 -> #NAME? | I111: =+'Annual Raw'!J66 -> #NAME? | ... AA111: =+'Annual Raw'!AB66 -> #NAME? | AB111: =CC111 -> #NAME? | AC111: =CG111 -> #NAME? | AD111: =CK111 -> #NAME? | AE111: =CO111 -> #NAME? | AH111: =+'QTR Raw'!C57 -> #NAME? | AI111: =+'QTR Raw'!D57 -> #NAME? | AJ111: =+'QTR Raw'!E57 -> #NAME? | AK111: =+'QTR Raw'!F57 -> #NAME? | AL111: =+'QTR Raw'!G57 -> #NAME? | AM111: =+'QTR Raw'!H57 -> #NAME? | AN111: =+'QTR Raw'!I57 -> #NAME? | AO111: =+'QTR Raw'!J57 -> #NAME? | ... BY111: =+'QTR Raw'!AT57 -> #NAME? | BZ111: =BY111 -> #NAME? | CA111: =BZ111 -> #NAME? | CB111: =CA111 -> #NAME? | CC111: =CB111 -> #NAME? | CD111: =CC111 -> #NAME? | CE111: =CD111 -> #NAME? | CF111: =CE111 -> #NAME? | CG111: =CF111 -> #NAME? | ... CO111: =CN111 -> #NAME? | CS111: 0
A113: Deposits | B113: =+'Annual Raw'!C67 -> #NAME? | C113: =+'Annual Raw'!D67 -> #NAME? | D113: =+'Annual Raw'!E67 -> #NAME? | E113: =+'Annual Raw'!F67 -> #NAME? | F113: =+'Annual Raw'!G67 -> #NAME? | G113: =+'Annual Raw'!H67 -> #NAME? | H113: =+'Annual Raw'!I67 -> #NAME? | I113: =+'Annual Raw'!J67 -> #NAME? | ... AA113: =+'Annual Raw'!AB67 -> #NAME? | AB113: =CC113 -> #NAME? | AC113: =CG113 -> #NAME? | AD113: =CK113 -> #NAME? | AE113: =CO113 -> #NAME? | AH113: =+'QTR Raw'!C58 -> #NAME? | AI113: =+'QTR Raw'!D58 -> #NAME? | AJ113: =+'QTR Raw'!E58 -> #NAME? | AK113: =+'QTR Raw'!F58 -> #NAME? | AL113: =+'QTR Raw'!G58 -> #NAME? | AM113: =+'QTR Raw'!H58 -> #NAME? | AN113: =+'QTR Raw'!I58 -> #NAME? | AO113: =+'QTR Raw'!J58 -> #NAME? | ... BY113: =+'QTR Raw'!AT58 -> #NAME? | BZ113: =+BV113+(BV113*BZ134) -> #NAME? | CA113: =+BW113+(BW113*CA134) -> #NAME? | CB113: =+BX113+(BX113*CB134) -> #NAME? | CC113: =+BY113+(BY113*CC134) -> #NAME? | CD113: =+BZ113+(BZ113*CD134) -> #NAME? | CE113: =+CA113+(CA113*CE134) -> #NAME? | CF113: =+CB113+(CB113*CF134) -> #NAME? | CG113: =+CC113+(CC113*CG134) -> #NAME? | ... CO113: =+CK113+(CK113*CO134) -> #NAME? | CS113: 350564.37
A114: Borrowings | B114: =+'Annual Raw'!C68 -> #NAME? | C114: =+'Annual Raw'!D68 -> #NAME? | D114: =+'Annual Raw'!E68 -> #NAME? | E114: =+'Annual Raw'!F68 -> #NAME? | F114: =+'Annual Raw'!G68 -> #NAME? | G114: =+'Annual Raw'!H68 -> #NAME? | H114: =+'Annual Raw'!I68 -> #NAME? | I114: =+'Annual Raw'!J68 -> #NAME? | ... AA114: =+'Annual Raw'!AB68 -> #NAME? | AB114: =CC114 -> #NAME? | AC114: =CG114 -> #NAME? | AD114: =CK114 -> #NAME? | AE114: =CO114 -> #NAME? | AH114: =+'QTR Raw'!C63 -> #NAME? | AI114: =+'QTR Raw'!D63 -> #NAME? | AJ114: =+'QTR Raw'!E63 -> #NAME? | AK114: =+'QTR Raw'!F63 -> #NAME? | AL114: =+'QTR Raw'!G63 -> #NAME? | AM114: =+'QTR Raw'!H63 -> #NAME? | AN114: =+'QTR Raw'!I63 -> #NAME? | AO114: =+'QTR Raw'!J63 -> #NAME? | ... BY114: =+'QTR Raw'!AT63 -> #NAME? | BZ114: =+BY114 -> #NAME? | CA114: =+BZ114 -> #NAME? | CB114: =+CA114 -> #NAME? | CC114: =+CB114 -> #NAME? | CD114: =+CC114 -> #NAME? | CE114: =+CD114 -> #NAME? | CF114: =+CE114 -> #NAME? | CG114: =+CF114 -> #NAME? | ... CO114: =+CN114 -> #NAME? | CS114: 35233.58
A115: Debt | B115: =SUM(B113:B114) -> #NAME? | C115: =SUM(C113:C114) -> #NAME? | D115: =SUM(D113:D114) -> #NAME? | E115: =SUM(E113:E114) -> #NAME? | F115: =SUM(F113:F114) -> #NAME? | G115: =SUM(G113:G114) -> #NAME? | H115: =SUM(H113:H114) -> #NAME? | I115: =SUM(I113:I114) -> #NAME? | ... AE115: =SUM(AE113:AE114) -> #NAME? | AH115: =SUM(AH113:AH114) -> #NAME? | AI115: =SUM(AI113:AI114) -> #NAME? | AJ115: =SUM(AJ113:AJ114) -> #NAME? | AK115: =SUM(AK113:AK114) -> #NAME? | AL115: =SUM(AL113:AL114) -> #NAME? | AM115: =SUM(AM113:AM114) -> #NAME? | AN115: =SUM(AN113:AN114) -> #NAME? | AO115: =SUM(AO113:AO114) -> #NAME? | ... CO115: =SUM(CO113:CO114) -> #NAME? | CS115: 385797.95
A116: Sources of Funds | B116: =B115+B111+B109 -> #NAME? | C116: =C115+C111+C109 -> #NAME? | D116: =D115+D111+D109 -> #NAME? | E116: =E115+E111+E109 -> #NAME? | F116: =F115+F111+F109 -> #NAME? | G116: =G115+G111+G109 -> #NAME? | H116: =H115+H111+H109 -> #NAME? | I116: =I115+I111+I109 -> #NAME? | ... AE116: =AE115+AE111+AE109 -> #NAME? | AH116: =AH115+AH111+AH109 -> #NAME? | AI116: =AI115+AI111+AI109 -> #NAME? | AJ116: =AJ115+AJ111+AJ109 -> #NAME? | AK116: =AK115+AK111+AK109 -> #NAME? | AL116: =AL115+AL111+AL109 -> #NAME? | AM116: =AM115+AM111+AM109 -> #NAME? | AN116: =AN115+AN111+AN109 -> #NAME? | AO116: =AO115+AO111+AO109 -> #NAME? | ... CO116: =CO115+CO111+CO109 -> #NAME? | CS116: 418905.77
A118: Investments | B118: =+'Annual Raw'!C73 -> #NAME? | C118: =+'Annual Raw'!D73 -> #NAME? | D118: =+'Annual Raw'!E73 -> #NAME? | E118: =+'Annual Raw'!F73 -> #NAME? | F118: =+'Annual Raw'!G73 -> #NAME? | G118: =+'Annual Raw'!H73 -> #NAME? | H118: =+'Annual Raw'!I73 -> #NAME? | I118: =+'Annual Raw'!J73 -> #NAME? | ... AA118: =+'Annual Raw'!AB73 -> #NAME? | AB118: =CC118 -> #NAME? | AC118: =CG118 -> #NAME? | AD118: =CK118 -> #NAME? | AE118: =CO118 -> #NAME? | AH118: =+'QTR Raw'!C68 -> #NAME? | AI118: =+'QTR Raw'!D68 -> #NAME? | AJ118: =+'QTR Raw'!E68 -> #NAME? | AK118: =+'QTR Raw'!F68 -> #NAME? | AL118: =+'QTR Raw'!G68 -> #NAME? | AM118: =+'QTR Raw'!H68 -> #NAME? | AN118: =+'QTR Raw'!I68 -> #NAME? | AO118: =+'QTR Raw'!J68 -> #NAME? | ... BY118: =+'QTR Raw'!AT68 -> #NAME? | BZ118: =+BZ115*BZ136 -> #NAME? | CA118: =+CA115*CA136 -> #NAME? | CB118: =+CB115*CB136 -> #NAME? | CC118: =+CC115*CC136 -> #NAME? | CD118: =+CD115*CD136 -> #NAME? | CE118: =+CE115*CE136 -> #NAME? | CF118: =+CF115*CF136 -> #NAME? | CG118: =+CG115*CG136 -> #NAME? | ... CO118: =+CO115*CO136 -> #NAME? | CS118: 101480.17
A119: Advances | B119: =+'Annual Raw'!C74 -> #NAME? | C119: =+'Annual Raw'!D74 -> #NAME? | D119: =+'Annual Raw'!E74 -> #NAME? | E119: =+'Annual Raw'!F74 -> #NAME? | F119: =+'Annual Raw'!G74 -> #NAME? | G119: =+'Annual Raw'!H74 -> #NAME? | H119: =+'Annual Raw'!I74 -> #NAME? | I119: =+'Annual Raw'!J74 -> #NAME? | ... AA119: =+'Annual Raw'!AB74 -> #NAME? | AB119: =CC119 -> #NAME? | AC119: =CG119 -> #NAME? | AD119: =CK119 -> #NAME? | AE119: =CO119 -> #NAME? | AH119: =+'QTR Raw'!C69 -> #NAME? | AI119: =+'QTR Raw'!D69 -> #NAME? | AJ119: =+'QTR Raw'!E69 -> #NAME? | AK119: =+'QTR Raw'!F69 -> #NAME? | AL119: =+'QTR Raw'!G69 -> #NAME? | AM119: =+'QTR Raw'!H69 -> #NAME? | AN119: =+'QTR Raw'!I69 -> #NAME? | AO119: =+'QTR Raw'!J69 -> #NAME? | ... BY119: =+'QTR Raw'!AT69 -> #NAME? | BZ119: =+BV119+(BV119*BZ135) -> #NAME? | CA119: =+BW119+(BW119*CA135) -> #NAME? | CB119: =+BX119+(BX119*CB135) -> #NAME? | CC119: =+BY119+(BY119*CC135) -> #NAME? | CD119: =+BZ119+(BZ119*CD135) -> #NAME? | CE119: =+CA119+(CA119*CE135) -> #NAME? | CF119: =+CB119+(CB119*CF135) -> #NAME? | CG119: =+CC119+(CC119*CG135) -> #NAME? | ... CO119: =+CK119+(CK119*CO135) -> #NAME? | CS119: 288104.3
...

Sheet Share price Daily
A1: =_xll.EQNXTH(B1,"[ADJC];[ADJH];[ADJL];[ADJO];[UCLS];[VOLUME]","2015-Jan-01","Y","All traded days","Asc") -> #NAME? | B1: =+'Annual Raw'!A1 -> 132525 | L1: =_xll.EQNXTH(B1,"[NADJC];[NADJH];[NADJLOW];[NADJOPEN];[NUCLOSE];[NVOLUME]","2015-Jan-01","Y","All traded days","Asc") -> #NAME?
A2: Bank Of Maharashtra | L2: Bank Of Maharashtra
A3: DATE | B3: ADJHIGH | C3: ADJCLOSE | D3: ADJLOW | E3: ADJOPEN | F3: CLOSE | G3: VOLUME | L3: DATE | M3: ADJCLOSE | N3: ADJHIGH | O3: ADJLOW | P3: ADJOPEN | Q3: CLOSE | R3: VOLUME
A4: 42005 | B4: 43.9 | C4: 43.4 | D4: 42.8 | E4: 43.2 | F4: 43.4 | G4: 87842 | L4: 42005 | M4: 43.3 | N4: 43.9 | O4: 42.55 | P4: 43.25 | Q4: 43.3 | R4: 359899
A5: 42006 | B5: 44.6 | C5: 44.25 | D5: 43.5 | E5: 43.7 | F5: 44.25 | G5: 93679 | L5: 42006 | M5: 44.2 | N5: 44.75 | O5: 43.45 | P5: 43.6 | Q5: 44.2 | R5: 439062
A6: 42009 | B6: 44.8 | C6: 43.8 | D6: 43.7 | E6: 44.75 | F6: 43.8 | G6: 54031 | L6: 42009 | M6: 43.75 | N6: 44.75 | O6: 43.6 | P6: 44.75 | Q6: 43.75 | R6: 233477
A7: 42010 | B7: 43.65 | C7: 42.6 | D7: 42.45 | E7: 43.65 | F7: 42.6 | G7: 41454 | L7: 42010 | M7: 42.75 | N7: 44 | O7: 42.6 | P7: 44 | Q7: 42.75 | R7: 183005
A8: 42011 | B8: 43.75 | C8: 42.35 | D8: 42.3 | E8: 43.75 | F8: 42.35 | G8: 36840 | L8: 42011 | M8: 42.5 | N8: 43.1 | O8: 42.25 | P8: 42.8 | Q8: 42.5 | R8: 116260
A9: 42012 | B9: 44.2 | C9: 43.65 | D9: 42.7 | E9: 42.95 | F9: 43.65 | G9: 105860 | L9: 42012 | M9: 43.9 | N9: 44.3 | O9: 42.75 | P9: 42.9 | Q9: 43.9 | R9: 351327
A10: 42013 | B10: 45.6 | C10: 44 | D10: 43.8 | E10: 45.1 | F10: 44 | G10: 162152 | L10: 42013 | M10: 44.1 | N10: 46 | O10: 43.9 | P10: 45.5 | Q10: 44.1 | R10: 790610
A11: 42016 | B11: 44.3 | C11: 44 | D11: 43.7 | E11: 44.1 | F11: 44 | G11: 47354 | L11: 42016 | M11: 43.95 | N11: 44.5 | O11: 43.8 | P11: 44.5 | Q11: 43.95 | R11: 166721
A12: 42017 | B12: 44.6 | C12: 43.75 | D12: 43.65 | E12: 44 | F12: 43.75 | G12: 61577 | L12: 42017 | M12: 43.8 | N12: 44.8 | O12: 43.65 | P12: 44.8 | Q12: 43.8 | R12: 188129
A13: 42018 | B13: 44.05 | C13: 43.3 | D13: 43 | E13: 44.05 | F13: 43.3 | G13: 22521 | L13: 42018 | M13: 43.1 | N13: 44 | O13: 42.9 | P13: 44 | Q13: 43.1 | R13: 131202
A14: 42019 | B14: 45 | C14: 44.1 | D14: 43.9 | E14: 44.2 | F14: 44.1 | G14: 120873 | L14: 42019 | M14: 44.15 | N14: 45 | O14: 44 | P14: 44.9 | Q14: 44.15 | R14: 361670
A15: 42020 | B15: 44.1 | C15: 43.65 | D15: 43.45 | E15: 44.1 | F15: 43.65 | G15: 27773 | L15: 42020 | M15: 43.6 | N15: 44.25 | O15: 43.4 | P15: 44.05 | Q15: 43.6 | R15: 98041
... A2800: 46129 | B2800: 72.97 | C2800: 72.72 | D2800: 71.24 | E2800: 71.45 | F2800: 72.72 | G2800: 723770 | L2800: 46129 | M2800: 72.73 | N2800: 72.99 | O2800: 71.24 | P2800: 71.8 | Q2800: 72.73 | R2800: 17291825

Sheet QTR Raw
A1: =+'Annual Raw'!A1 -> 132525
C2: 201506 | D2: 201509 | E2: 201512 | F2: 201603 | G2: 201606 | H2: 201609 | I2: 201612 | J2: 201703 | K2: 201706 | L2: 201709 | M2: 201712 | N2: 201803 | O2: 201806 | P2: 201809 | Q2: 201812 | R2: 201903 | S2: 201906 | T2: 201909 | U2: 201912 | V2: 202003 | W2: 202006 | X2: 202009 | Y2: 202012 | Z2: 202103 | AA2: 202106 | AB2: 202109 | AC2: 202112 | AD2: 202203 | AE2: 202206 | AF2: 202209 | AG2: 202212 | AH2: 202303 | AI2: 202306 | AJ2: 202309 | AK2: 202312 | AL2: 202403 | AM2: 202406 | AN2: 202409 | AO2: 202412 | AP2: 202503 | AQ2: 202506 | AR2: 202509 | AS2: 202512 | AT2: 202603 | AU2: 202606 | AV2: 202609 | AW2: 202612 | AX2: 202703 | AY2: 202706 | AZ2: 202709 | BA2: 202712 | BB2: 202803 | BC2: 202806 | BD2: 202809 | BE2: 202812 | BF2: 202903 | BG2: 202906 | BH2: 202909 | BI2: 202912 | BJ2: 203003
A4: Field Description | B4: Field Name
A5: Date End | B5: BQTR_DATE_END | C5: {=+_xll.EQNXTDZ($A$1,$B5,C$2)} -> #NAME? | D5: {=+_xll.EQNXTDZ($A$1,$B5,D$2)} -> #NAME? | E5: {=+_xll.EQNXTDZ($A$1,$B5,E$2)} -> #NAME? | F5: {=+_xll.EQNXTDZ($A$1,$B5,F$2)} -> #NAME? | G5: {=+_xll.EQNXTDZ($A$1,$B5,G$2)} -> #NAME? | H5: {=+_xll.EQNXTDZ($A$1,$B5,H$2)} -> #NAME? | I5: {=+_xll.EQNXTDZ($A$1,$B5,I$2)} -> #NAME? | J5: {=+_xll.EQNXTDZ($A$1,$B5,J$2)} -> #NAME? | ... BJ5: {=+_xll.EQNXTDZ($A$1,$B5,BJ$2)} -> #NAME?
A6: Interest Earned | B6: BQTR_NET_SALES | C6: {=+_xll.EQNXTDZ($A$1,$B6,C$2)} -> #NAME? | D6: {=+_xll.EQNXTDZ($A$1,$B6,D$2)} -> #NAME? | E6: {=+_xll.EQNXTDZ($A$1,$B6,E$2)} -> #NAME? | F6: {=+_xll.EQNXTDZ($A$1,$B6,F$2)} -> #NAME? | G6: {=+_xll.EQNXTDZ($A$1,$B6,G$2)} -> #NAME? | H6: {=+_xll.EQNXTDZ($A$1,$B6,H$2)} -> #NAME? | I6: {=+_xll.EQNXTDZ($A$1,$B6,I$2)} -> #NAME? | J6: {=+_xll.EQNXTDZ($A$1,$B6,J$2)} -> #NAME? | ... BJ6: {=+_xll.EQNXTDZ($A$1,$B6,BJ$2)} -> #NAME?
A7: Other Income | B7: BQTR_OTHER_INCOME | C7: {=+_xll.EQNXTDZ($A$1,$B7,C$2)} -> #NAME? | D7: {=+_xll.EQNXTDZ($A$1,$B7,D$2)} -> #NAME? | E7: {=+_xll.EQNXTDZ($A$1,$B7,E$2)} -> #NAME? | F7: {=+_xll.EQNXTDZ($A$1,$B7,F$2)} -> #NAME? | G7: {=+_xll.EQNXTDZ($A$1,$B7,G$2)} -> #NAME? | H7: {=+_xll.EQNXTDZ($A$1,$B7,H$2)} -> #NAME? | I7: {=+_xll.EQNXTDZ($A$1,$B7,I$2)} -> #NAME? | J7: {=+_xll.EQNXTDZ($A$1,$B7,J$2)} -> #NAME? | ... BJ7: {=+_xll.EQNXTDZ($A$1,$B7,BJ$2)} -> #NAME?
A8: Total Income | B8: BQTR_TOTAL_INCOME | C8: {=+_xll.EQNXTDZ($A$1,$B8,C$2)} -> #NAME? | D8: {=+_xll.EQNXTDZ($A$1,$B8,D$2)} -> #NAME? | E8: {=+_xll.EQNXTDZ($A$1,$B8,E$2)} -> #NAME? | F8: {=+_xll.EQNXTDZ($A$1,$B8,F$2)} -> #NAME? | G8: {=+_xll.EQNXTDZ($A$1,$B8,G$2)} -> #NAME? | H8: {=+_xll.EQNXTDZ($A$1,$B8,H$2)} -> #NAME? | I8: {=+_xll.EQNXTDZ($A$1,$B8,I$2)} -> #NAME? | J8: {=+_xll.EQNXTDZ($A$1,$B8,J$2)} -> #NAME? | ... BJ8: {=+_xll.EQNXTDZ($A$1,$B8,BJ$2)} -> #NAME?
A9: Interest Expended | B9: BQTR_INTEREST | C9: {=+_xll.EQNXTDZ($A$1,$B9,C$2)} -> #NAME? | D9: {=+_xll.EQNXTDZ($A$1,$B9,D$2)} -> #NAME? | E9: {=+_xll.EQNXTDZ($A$1,$B9,E$2)} -> #NAME? | F9: {=+_xll.EQNXTDZ($A$1,$B9,F$2)} -> #NAME? | G9: {=+_xll.EQNXTDZ($A$1,$B9,G$2)} -> #NAME? | H9: {=+_xll.EQNXTDZ($A$1,$B9,H$2)} -> #NAME? | I9: {=+_xll.EQNXTDZ($A$1,$B9,I$2)} -> #NAME? | J9: {=+_xll.EQNXTDZ($A$1,$B9,J$2)} -> #NAME? | ... BJ9: {=+_xll.EQNXTDZ($A$1,$B9,BJ$2)} -> #NAME?
A10: Operating Expenses | B10: BQTR_OPERATING_EX | C10: {=+_xll.EQNXTDZ($A$1,$B10,C$2)} -> #NAME? | D10: {=+_xll.EQNXTDZ($A$1,$B10,D$2)} -> #NAME? | E10: {=+_xll.EQNXTDZ($A$1,$B10,E$2)} -> #NAME? | F10: {=+_xll.EQNXTDZ($A$1,$B10,F$2)} -> #NAME? | G10: {=+_xll.EQNXTDZ($A$1,$B10,G$2)} -> #NAME? | H10: {=+_xll.EQNXTDZ($A$1,$B10,H$2)} -> #NAME? | I10: {=+_xll.EQNXTDZ($A$1,$B10,I$2)} -> #NAME? | J10: {=+_xll.EQNXTDZ($A$1,$B10,J$2)} -> #NAME? | ... BJ10: {=+_xll.EQNXTDZ($A$1,$B10,BJ$2)} -> #NAME?
A11: Payment To Provisions For Employees | B11: BQTR_PROV_EMP | C11: {=+_xll.EQNXTDZ($A$1,$B11,C$2)} -> #NAME? | D11: {=+_xll.EQNXTDZ($A$1,$B11,D$2)} -> #NAME? | E11: {=+_xll.EQNXTDZ($A$1,$B11,E$2)} -> #NAME? | F11: {=+_xll.EQNXTDZ($A$1,$B11,F$2)} -> #NAME? | G11: {=+_xll.EQNXTDZ($A$1,$B11,G$2)} -> #NAME? | H11: {=+_xll.EQNXTDZ($A$1,$B11,H$2)} -> #NAME? | I11: {=+_xll.EQNXTDZ($A$1,$B11,I$2)} -> #NAME? | J11: {=+_xll.EQNXTDZ($A$1,$B11,J$2)} -> #NAME? | ... BJ11: {=+_xll.EQNXTDZ($A$1,$B11,BJ$2)} -> #NAME?
A12: Depreciation | B12: BQTR_DEPRECIATION | C12: {=+_xll.EQNXTDZ($A$1,$B12,C$2)} -> #NAME? | D12: {=+_xll.EQNXTDZ($A$1,$B12,D$2)} -> #NAME? | E12: {=+_xll.EQNXTDZ($A$1,$B12,E$2)} -> #NAME? | F12: {=+_xll.EQNXTDZ($A$1,$B12,F$2)} -> #NAME? | G12: {=+_xll.EQNXTDZ($A$1,$B12,G$2)} -> #NAME? | H12: {=+_xll.EQNXTDZ($A$1,$B12,H$2)} -> #NAME? | I12: {=+_xll.EQNXTDZ($A$1,$B12,I$2)} -> #NAME? | J12: {=+_xll.EQNXTDZ($A$1,$B12,J$2)} -> #NAME? | ... BJ12: {=+_xll.EQNXTDZ($A$1,$B12,BJ$2)} -> #NAME?
A13: Total Expenditure | B13: BQTR_EXPENDITURE | C13: {=+_xll.EQNXTDZ($A$1,$B13,C$2)} -> #NAME? | D13: {=+_xll.EQNXTDZ($A$1,$B13,D$2)} -> #NAME? | E13: {=+_xll.EQNXTDZ($A$1,$B13,E$2)} -> #NAME? | F13: {=+_xll.EQNXTDZ($A$1,$B13,F$2)} -> #NAME? | G13: {=+_xll.EQNXTDZ($A$1,$B13,G$2)} -> #NAME? | H13: {=+_xll.EQNXTDZ($A$1,$B13,H$2)} -> #NAME? | I13: {=+_xll.EQNXTDZ($A$1,$B13,I$2)} -> #NAME? | J13: {=+_xll.EQNXTDZ($A$1,$B13,J$2)} -> #NAME? | ... BJ13: {=+_xll.EQNXTDZ($A$1,$B13,BJ$2)} -> #NAME?
A14: Operating Profit before Prov.& Cont. | B14: BQTR_OPERATING_PROFIT | C14: {=+_xll.EQNXTDZ($A$1,$B14,C$2)} -> #NAME? | D14: {=+_xll.EQNXTDZ($A$1,$B14,D$2)} -> #NAME? | E14: {=+_xll.EQNXTDZ($A$1,$B14,E$2)} -> #NAME? | F14: {=+_xll.EQNXTDZ($A$1,$B14,F$2)} -> #NAME? | G14: {=+_xll.EQNXTDZ($A$1,$B14,G$2)} -> #NAME? | H14: {=+_xll.EQNXTDZ($A$1,$B14,H$2)} -> #NAME? | I14: {=+_xll.EQNXTDZ($A$1,$B14,I$2)} -> #NAME? | J14: {=+_xll.EQNXTDZ($A$1,$B14,J$2)} -> #NAME? | ... BJ14: {=+_xll.EQNXTDZ($A$1,$B14,BJ$2)} -> #NAME?
A15: Exceptional Items | B15: BQTR_EXCEPTION_ITEMS | C15: {=+_xll.EQNXTDZ($A$1,$B15,C$2)} -> #NAME? | D15: {=+_xll.EQNXTDZ($A$1,$B15,D$2)} -> #NAME? | E15: {=+_xll.EQNXTDZ($A$1,$B15,E$2)} -> #NAME? | F15: {=+_xll.EQNXTDZ($A$1,$B15,F$2)} -> #NAME? | G15: {=+_xll.EQNXTDZ($A$1,$B15,G$2)} -> #NAME? | H15: {=+_xll.EQNXTDZ($A$1,$B15,H$2)} -> #NAME? | I15: {=+_xll.EQNXTDZ($A$1,$B15,I$2)} -> #NAME? | J15: {=+_xll.EQNXTDZ($A$1,$B15,J$2)} -> #NAME? | ... BJ15: {=+_xll.EQNXTDZ($A$1,$B15,BJ$2)} -> #NAME?
A16: Foreign Exchange Gain / Loss | B16: BQTR_EXC_FOREIGN_EXCH_GAIN | C16: {=+_xll.EQNXTDZ($A$1,$B16,C$2)} -> #NAME? | D16: {=+_xll.EQNXTDZ($A$1,$B16,D$2)} -> #NAME? | E16: {=+_xll.EQNXTDZ($A$1,$B16,E$2)} -> #NAME? | F16: {=+_xll.EQNXTDZ($A$1,$B16,F$2)} -> #NAME? | G16: {=+_xll.EQNXTDZ($A$1,$B16,G$2)} -> #NAME? | H16: {=+_xll.EQNXTDZ($A$1,$B16,H$2)} -> #NAME? | I16: {=+_xll.EQNXTDZ($A$1,$B16,I$2)} -> #NAME? | J16: {=+_xll.EQNXTDZ($A$1,$B16,J$2)} -> #NAME? | ... BJ16: {=+_xll.EQNXTDZ($A$1,$B16,BJ$2)} -> #NAME?
... A48: NIM % | B48: BQTR_NIM | C48: {=+_xll.EQNXTDZ($A$1,$B48,C$2)} -> #NAME? | D48: {=+_xll.EQNXTDZ($A$1,$B48,D$2)} -> #NAME? | E48: {=+_xll.EQNXTDZ($A$1,$B48,E$2)} -> #NAME? | F48: {=+_xll.EQNXTDZ($A$1,$B48,F$2)} -> #NAME? | G48: {=+_xll.EQNXTDZ($A$1,$B48,G$2)} -> #NAME? | H48: {=+_xll.EQNXTDZ($A$1,$B48,H$2)} -> #NAME? | I48: {=+_xll.EQNXTDZ($A$1,$B48,I$2)} -> #NAME? | J48: {=+_xll.EQNXTDZ($A$1,$B48,J$2)} -> #NAME? | ... BJ48: {=+_xll.EQNXTDZ($A$1,$B48,BJ$2)} -> #NAME?
C51: =C5 -> #NAME? | D51: =D5 -> #NAME? | E51: =E5 -> #NAME? | F51: =F5 -> #NAME? | G51: =G5 -> #NAME? | H51: =H5 -> #NAME? | I51: =I5 -> #NAME? | J51: =J5 -> #NAME? | ... BJ51: =BJ5 -> #NAME?
A52: Field Description | B52: Field Name
A53: Year End | B53: BQTRB_DATE_END | C53: {=+_xll.EQNXTDZ($A$1,$B53,C$51)} -> #NAME? | D53: {=+_xll.EQNXTDZ($A$1,$B53,D$51)} -> #NAME? | E53: {=+_xll.EQNXTDZ($A$1,$B53,E$51)} -> #NAME? | F53: {=+_xll.EQNXTDZ($A$1,$B53,F$51)} -> #NAME? | G53: {=+_xll.EQNXTDZ($A$1,$B53,G$51)} -> #NAME? | H53: {=+_xll.EQNXTDZ($A$1,$B53,H$51)} -> #NAME? | I53: {=+_xll.EQNXTDZ($A$1,$B53,I$51)} -> #NAME? | J53: {=+_xll.EQNXTDZ($A$1,$B53,J$51)} -> #NAME? | ... BJ53: {=+_xll.EQNXTDZ($A$1,$B53,BJ$51)} -> #NAME?
A54: Share Capital | B54: BQTRB_SHARE_CAPITAL | C54: {=+_xll.EQNXTDZ($A$1,$B54,C$51)} -> #NAME? | D54: {=+_xll.EQNXTDZ($A$1,$B54,D$51)} -> #NAME? | E54: {=+_xll.EQNXTDZ($A$1,$B54,E$51)} -> #NAME? | F54: {=+_xll.EQNXTDZ($A$1,$B54,F$51)} -> #NAME? | G54: {=+_xll.EQNXTDZ($A$1,$B54,G$51)} -> #NAME? | H54: {=+_xll.EQNXTDZ($A$1,$B54,H$51)} -> #NAME? | I54: {=+_xll.EQNXTDZ($A$1,$B54,I$51)} -> #NAME? | J54: {=+_xll.EQNXTDZ($A$1,$B54,J$51)} -> #NAME? | ... BJ54: {=+_xll.EQNXTDZ($A$1,$B54,BJ$51)} -> #NAME?
A55: Share Warrants & outstandings | B55: BQTRB_SHAREWARRANTS | C55: {=+_xll.EQNXTDZ($A$1,$B55,C$51)} -> #NAME? | D55: {=+_xll.EQNXTDZ($A$1,$B55,D$51)} -> #NAME? | E55: {=+_xll.EQNXTDZ($A$1,$B55,E$51)} -> #NAME? | F55: {=+_xll.EQNXTDZ($A$1,$B55,F$51)} -> #NAME? | G55: {=+_xll.EQNXTDZ($A$1,$B55,G$51)} -> #NAME? | H55: {=+_xll.EQNXTDZ($A$1,$B55,H$51)} -> #NAME? | I55: {=+_xll.EQNXTDZ($A$1,$B55,I$51)} -> #NAME? | J55: {=+_xll.EQNXTDZ($A$1,$B55,J$51)} -> #NAME? | ... BJ55: {=+_xll.EQNXTDZ($A$1,$B55,BJ$51)} -> #NAME?
A56: Reserves and Surplus | B56: BQTRB_RESERVE | C56: {=+_xll.EQNXTDZ($A$1,$B56,C$51)} -> #NAME? | D56: {=+_xll.EQNXTDZ($A$1,$B56,D$51)} -> #NAME? | E56: {=+_xll.EQNXTDZ($A$1,$B56,E$51)} -> #NAME? | F56: {=+_xll.EQNXTDZ($A$1,$B56,F$51)} -> #NAME? | G56: {=+_xll.EQNXTDZ($A$1,$B56,G$51)} -> #NAME? | H56: {=+_xll.EQNXTDZ($A$1,$B56,H$51)} -> #NAME? | I56: {=+_xll.EQNXTDZ($A$1,$B56,I$51)} -> #NAME? | J56: {=+_xll.EQNXTDZ($A$1,$B56,J$51)} -> #NAME? | ... BJ56: {=+_xll.EQNXTDZ($A$1,$B56,BJ$51)} -> #NAME?
A57: Minority Interest | B57: BQTRB_MINORITY_INTEREST_BS | C57: {=+_xll.EQNXTDZ($A$1,$B57,C$51)} -> #NAME? | D57: {=+_xll.EQNXTDZ($A$1,$B57,D$51)} -> #NAME? | E57: {=+_xll.EQNXTDZ($A$1,$B57,E$51)} -> #NAME? | F57: {=+_xll.EQNXTDZ($A$1,$B57,F$51)} -> #NAME? | G57: {=+_xll.EQNXTDZ($A$1,$B57,G$51)} -> #NAME? | H57: {=+_xll.EQNXTDZ($A$1,$B57,H$51)} -> #NAME? | I57: {=+_xll.EQNXTDZ($A$1,$B57,I$51)} -> #NAME? | J57: {=+_xll.EQNXTDZ($A$1,$B57,J$51)} -> #NAME? | ... BJ57: {=+_xll.EQNXTDZ($A$1,$B57,BJ$51)} -> #NAME?
A58: Deposits | B58: BQTRB_DEPOSITS | C58: {=+_xll.EQNXTDZ($A$1,$B58,C$51)} -> #NAME? | D58: {=+_xll.EQNXTDZ($A$1,$B58,D$51)} -> #NAME? | E58: {=+_xll.EQNXTDZ($A$1,$B58,E$51)} -> #NAME? | F58: {=+_xll.EQNXTDZ($A$1,$B58,F$51)} -> #NAME? | G58: {=+_xll.EQNXTDZ($A$1,$B58,G$51)} -> #NAME? | H58: {=+_xll.EQNXTDZ($A$1,$B58,H$51)} -> #NAME? | I58: {=+_xll.EQNXTDZ($A$1,$B58,I$51)} -> #NAME? | J58: {=+_xll.EQNXTDZ($A$1,$B58,J$51)} -> #NAME? | ... BJ58: {=+_xll.EQNXTDZ($A$1,$B58,BJ$51)} -> #NAME?
A59: Savings Deposits | B59: BQTRB_SAVING_DEPOSITS | C59: {=+_xll.EQNXTDZ($A$1,$B59,C$51)} -> #NAME? | D59: {=+_xll.EQNXTDZ($A$1,$B59,D$51)} -> #NAME? | E59: {=+_xll.EQNXTDZ($A$1,$B59,E$51)} -> #NAME? | F59: {=+_xll.EQNXTDZ($A$1,$B59,F$51)} -> #NAME? | G59: {=+_xll.EQNXTDZ($A$1,$B59,G$51)} -> #NAME? | H59: {=+_xll.EQNXTDZ($A$1,$B59,H$51)} -> #NAME? | I59: {=+_xll.EQNXTDZ($A$1,$B59,I$51)} -> #NAME? | J59: {=+_xll.EQNXTDZ($A$1,$B59,J$51)} -> #NAME? | ... BJ59: {=+_xll.EQNXTDZ($A$1,$B59,BJ$51)} -> #NAME?
A60: Term / Fixed Deposits | B60: BQTRB_TERM_FIXED_DEPOSITS | C60: {=+_xll.EQNXTDZ($A$1,$B60,C$51)} -> #NAME? | D60: {=+_xll.EQNXTDZ($A$1,$B60,D$51)} -> #NAME? | E60: {=+_xll.EQNXTDZ($A$1,$B60,E$51)} -> #NAME? | F60: {=+_xll.EQNXTDZ($A$1,$B60,F$51)} -> #NAME? | G60: {=+_xll.EQNXTDZ($A$1,$B60,G$51)} -> #NAME? | H60: {=+_xll.EQNXTDZ($A$1,$B60,H$51)} -> #NAME? | I60: {=+_xll.EQNXTDZ($A$1,$B60,I$51)} -> #NAME? | J60: {=+_xll.EQNXTDZ($A$1,$B60,J$51)} -> #NAME? | ... BJ60: {=+_xll.EQNXTDZ($A$1,$B60,BJ$51)} -> #NAME?
A61: Current Deposits | B61: BQTRB_CURRENT_DEPOSITS | C61: {=+_xll.EQNXTDZ($A$1,$B61,C$51)} -> #NAME? | D61: {=+_xll.EQNXTDZ($A$1,$B61,D$51)} -> #NAME? | E61: {=+_xll.EQNXTDZ($A$1,$B61,E$51)} -> #NAME? | F61: {=+_xll.EQNXTDZ($A$1,$B61,F$51)} -> #NAME? | G61: {=+_xll.EQNXTDZ($A$1,$B61,G$51)} -> #NAME? | H61: {=+_xll.EQNXTDZ($A$1,$B61,H$51)} -> #NAME? | I61: {=+_xll.EQNXTDZ($A$1,$B61,I$51)} -> #NAME? | J61: {=+_xll.EQNXTDZ($A$1,$B61,J$51)} -> #NAME? | ... BJ61: {=+_xll.EQNXTDZ($A$1,$B61,BJ$51)} -> #NAME?
A62: Other Deposits | B62: BQTRB_OTHER_DEPOSITS | C62: {=+_xll.EQNXTDZ($A$1,$B62,C$51)} -> #NAME? | D62: {=+_xll.EQNXTDZ($A$1,$B62,D$51)} -> #NAME? | E62: {=+_xll.EQNXTDZ($A$1,$B62,E$51)} -> #NAME? | F62: {=+_xll.EQNXTDZ($A$1,$B62,F$51)} -> #NAME? | G62: {=+_xll.EQNXTDZ($A$1,$B62,G$51)} -> #NAME? | H62: {=+_xll.EQNXTDZ($A$1,$B62,H$51)} -> #NAME? | I62: {=+_xll.EQNXTDZ($A$1,$B62,I$51)} -> #NAME? | J62: {=+_xll.EQNXTDZ($A$1,$B62,J$51)} -> #NAME? | ... BJ62: {=+_xll.EQNXTDZ($A$1,$B62,BJ$51)} -> #NAME?
A63: Borrowings | B63: BQTRB_BORROWINGS | C63: {=+_xll.EQNXTDZ($A$1,$B63,C$51)} -> #NAME? | D63: {=+_xll.EQNXTDZ($A$1,$B63,D$51)} -> #NAME? | E63: {=+_xll.EQNXTDZ($A$1,$B63,E$51)} -> #NAME? | F63: {=+_xll.EQNXTDZ($A$1,$B63,F$51)} -> #NAME? | G63: {=+_xll.EQNXTDZ($A$1,$B63,G$51)} -> #NAME? | H63: {=+_xll.EQNXTDZ($A$1,$B63,H$51)} -> #NAME? | I63: {=+_xll.EQNXTDZ($A$1,$B63,I$51)} -> #NAME? | J63: {=+_xll.EQNXTDZ($A$1,$B63,J$51)} -> #NAME? | ... BJ63: {=+_xll.EQNXTDZ($A$1,$B63,BJ$51)} -> #NAME?
A64: Other Liabilities & Provisions | B64: BQTRB_OTHER_LIABILITIES | C64: {=+_xll.EQNXTDZ($A$1,$B64,C$51)} -> #NAME? | D64: {=+_xll.EQNXTDZ($A$1,$B64,D$51)} -> #NAME? | E64: {=+_xll.EQNXTDZ($A$1,$B64,E$51)} -> #NAME? | F64: {=+_xll.EQNXTDZ($A$1,$B64,F$51)} -> #NAME? | G64: {=+_xll.EQNXTDZ($A$1,$B64,G$51)} -> #NAME? | H64: {=+_xll.EQNXTDZ($A$1,$B64,H$51)} -> #NAME? | I64: {=+_xll.EQNXTDZ($A$1,$B64,I$51)} -> #NAME? | J64: {=+_xll.EQNXTDZ($A$1,$B64,J$51)} -> #NAME? | ... BJ64: {=+_xll.EQNXTDZ($A$1,$B64,BJ$51)} -> #NAME?
... A83: Book Value | B83: BQTRB_BOOKVALUE | C83: {=+_xll.EQNXTDZ($A$1,$B83,C$51)} -> #NAME? | D83: {=+_xll.EQNXTDZ($A$1,$B83,D$51)} -> #NAME? | E83: {=+_xll.EQNXTDZ($A$1,$B83,E$51)} -> #NAME? | F83: {=+_xll.EQNXTDZ($A$1,$B83,F$51)} -> #NAME? | G83: {=+_xll.EQNXTDZ($A$1,$B83,G$51)} -> #NAME? | H83: {=+_xll.EQNXTDZ($A$1,$B83,H$51)} -> #NAME? | I83: {=+_xll.EQNXTDZ($A$1,$B83,I$51)} -> #NAME? | J83: {=+_xll.EQNXTDZ($A$1,$B83,J$51)} -> #NAME? | ... BJ83: {=+_xll.EQNXTDZ($A$1,$B83,BJ$51)} -> #NAME?

Sheet Annual Raw
A1: 132525 | C1: 200103 | D1: 200203 | E1: 200303 | F1: 200403 | G1: 200503 | H1: 200603 | I1: 200703 | J1: 200803 | K1: 200903 | L1: 201003 | M1: 201103 | N1: 201203 | O1: 201303 | P1: 201403 | Q1: 201503 | R1: 201603 | S1: 201703 | T1: 201803 | U1: 201903 | V1: 202003 | W1: 202103 | X1: 202203 | Y1: 202303 | Z1: 202403 | AA1: 202503 | AB1: 202603 | AC1: 202703 | AD1: 202803 | AE1: 202903 | AF1: 203003
A3: Company Name | B3: CD_COMPNAME | C3: {=_xll.EQNXTDZ($A$1,$B3,C$2)} -> #NAME?
A4: Field Description | B4: Field Name
A5: No of Months | B5: BPL_NO_MONTHS | C5: {=_xll.EQNXTDZ($A$1,$B5,C$1)} -> #NAME? | D5: {=_xll.EQNXTDZ($A$1,$B5,D$1)} -> #NAME? | E5: {=_xll.EQNXTDZ($A$1,$B5,E$1)} -> #NAME? | F5: {=_xll.EQNXTDZ($A$1,$B5,F$1)} -> #NAME? | G5: {=_xll.EQNXTDZ($A$1,$B5,G$1)} -> #NAME? | H5: {=_xll.EQNXTDZ($A$1,$B5,H$1)} -> #NAME? | I5: {=_xll.EQNXTDZ($A$1,$B5,I$1)} -> #NAME? | J5: {=_xll.EQNXTDZ($A$1,$B5,J$1)} -> #NAME? | ... AF5: {=_xll.EQNXTDZ($A$1,$B5,AF$1)} -> #NAME?
A6: Year end date | B6: BPL_YEAR_ENDDATE | C6: {=_xll.EQNXTDZ($A$1,$B6,C$1)} -> #NAME? | D6: {=_xll.EQNXTDZ($A$1,$B6,D$1)} -> #NAME? | E6: {=_xll.EQNXTDZ($A$1,$B6,E$1)} -> #NAME? | F6: {=_xll.EQNXTDZ($A$1,$B6,F$1)} -> #NAME? | G6: {=_xll.EQNXTDZ($A$1,$B6,G$1)} -> #NAME? | H6: {=_xll.EQNXTDZ($A$1,$B6,H$1)} -> #NAME? | I6: {=_xll.EQNXTDZ($A$1,$B6,I$1)} -> #NAME? | J6: {=_xll.EQNXTDZ($A$1,$B6,J$1)} -> #NAME? | ... AF6: {=_xll.EQNXTDZ($A$1,$B6,AF$1)} -> #NAME?
A7: Interest Earned | B7: BPL_INTEREST_EARNED | C7: {=_xll.EQNXTDZ($A$1,$B7,C$1)} -> #NAME? | D7: {=_xll.EQNXTDZ($A$1,$B7,D$1)} -> #NAME? | E7: {=_xll.EQNXTDZ($A$1,$B7,E$1)} -> #NAME? | F7: {=_xll.EQNXTDZ($A$1,$B7,F$1)} -> #NAME? | G7: {=_xll.EQNXTDZ($A$1,$B7,G$1)} -> #NAME? | H7: {=_xll.EQNXTDZ($A$1,$B7,H$1)} -> #NAME? | I7: {=_xll.EQNXTDZ($A$1,$B7,I$1)} -> #NAME? | J7: {=_xll.EQNXTDZ($A$1,$B7,J$1)} -> #NAME? | ... AF7: {=_xll.EQNXTDZ($A$1,$B7,AF$1)} -> #NAME?
A8: Other Income | B8: BPL_OTHER_INCOME | C8: {=_xll.EQNXTDZ($A$1,$B8,C$1)} -> #NAME? | D8: {=_xll.EQNXTDZ($A$1,$B8,D$1)} -> #NAME? | E8: {=_xll.EQNXTDZ($A$1,$B8,E$1)} -> #NAME? | F8: {=_xll.EQNXTDZ($A$1,$B8,F$1)} -> #NAME? | G8: {=_xll.EQNXTDZ($A$1,$B8,G$1)} -> #NAME? | H8: {=_xll.EQNXTDZ($A$1,$B8,H$1)} -> #NAME? | I8: {=_xll.EQNXTDZ($A$1,$B8,I$1)} -> #NAME? | J8: {=_xll.EQNXTDZ($A$1,$B8,J$1)} -> #NAME? | ... AF8: {=_xll.EQNXTDZ($A$1,$B8,AF$1)} -> #NAME?
A9: Total Income | B9: BPL_TOTAL_INCOME | C9: {=_xll.EQNXTDZ($A$1,$B9,C$1)} -> #NAME? | D9: {=_xll.EQNXTDZ($A$1,$B9,D$1)} -> #NAME? | E9: {=_xll.EQNXTDZ($A$1,$B9,E$1)} -> #NAME? | F9: {=_xll.EQNXTDZ($A$1,$B9,F$1)} -> #NAME? | G9: {=_xll.EQNXTDZ($A$1,$B9,G$1)} -> #NAME? | H9: {=_xll.EQNXTDZ($A$1,$B9,H$1)} -> #NAME? | I9: {=_xll.EQNXTDZ($A$1,$B9,I$1)} -> #NAME? | J9: {=_xll.EQNXTDZ($A$1,$B9,J$1)} -> #NAME? | ... AF9: {=_xll.EQNXTDZ($A$1,$B9,AF$1)} -> #NAME?
A10: Interest Expended | B10: BPL_INTEREST | C10: {=_xll.EQNXTDZ($A$1,$B10,C$1)} -> #NAME? | D10: {=_xll.EQNXTDZ($A$1,$B10,D$1)} -> #NAME? | E10: {=_xll.EQNXTDZ($A$1,$B10,E$1)} -> #NAME? | F10: {=_xll.EQNXTDZ($A$1,$B10,F$1)} -> #NAME? | G10: {=_xll.EQNXTDZ($A$1,$B10,G$1)} -> #NAME? | H10: {=_xll.EQNXTDZ($A$1,$B10,H$1)} -> #NAME? | I10: {=_xll.EQNXTDZ($A$1,$B10,I$1)} -> #NAME? | J10: {=_xll.EQNXTDZ($A$1,$B10,J$1)} -> #NAME? | ... AF10: {=_xll.EQNXTDZ($A$1,$B10,AF$1)} -> #NAME?
A11: Operating Expenses | B11: BPL_OPERATING_EXPENSES | C11: {=_xll.EQNXTDZ($A$1,$B11,C$1)} -> #NAME? | D11: {=_xll.EQNXTDZ($A$1,$B11,D$1)} -> #NAME? | E11: {=_xll.EQNXTDZ($A$1,$B11,E$1)} -> #NAME? | F11: {=_xll.EQNXTDZ($A$1,$B11,F$1)} -> #NAME? | G11: {=_xll.EQNXTDZ($A$1,$B11,G$1)} -> #NAME? | H11: {=_xll.EQNXTDZ($A$1,$B11,H$1)} -> #NAME? | I11: {=_xll.EQNXTDZ($A$1,$B11,I$1)} -> #NAME? | J11: {=_xll.EQNXTDZ($A$1,$B11,J$1)} -> #NAME? | ... AF11: {=_xll.EQNXTDZ($A$1,$B11,AF$1)} -> #NAME?
A12: Payments to and provisions for employees | B12: BPL_EMPLOYEES | C12: {=_xll.EQNXTDZ($A$1,$B12,C$1)} -> #NAME? | D12: {=_xll.EQNXTDZ($A$1,$B12,D$1)} -> #NAME? | E12: {=_xll.EQNXTDZ($A$1,$B12,E$1)} -> #NAME? | F12: {=_xll.EQNXTDZ($A$1,$B12,F$1)} -> #NAME? | G12: {=_xll.EQNXTDZ($A$1,$B12,G$1)} -> #NAME? | H12: {=_xll.EQNXTDZ($A$1,$B12,H$1)} -> #NAME? | I12: {=_xll.EQNXTDZ($A$1,$B12,I$1)} -> #NAME? | J12: {=_xll.EQNXTDZ($A$1,$B12,J$1)} -> #NAME? | ... AF12: {=_xll.EQNXTDZ($A$1,$B12,AF$1)} -> #NAME?
A13: Advertisement & Sales Promotion | B13: BPL_ADVERTISING | C13: {=_xll.EQNXTDZ($A$1,$B13,C$1)} -> #NAME? | D13: {=_xll.EQNXTDZ($A$1,$B13,D$1)} -> #NAME? | E13: {=_xll.EQNXTDZ($A$1,$B13,E$1)} -> #NAME? | F13: {=_xll.EQNXTDZ($A$1,$B13,F$1)} -> #NAME? | G13: {=_xll.EQNXTDZ($A$1,$B13,G$1)} -> #NAME? | H13: {=_xll.EQNXTDZ($A$1,$B13,H$1)} -> #NAME? | I13: {=_xll.EQNXTDZ($A$1,$B13,I$1)} -> #NAME? | J13: {=_xll.EQNXTDZ($A$1,$B13,J$1)} -> #NAME? | ... AF13: {=_xll.EQNXTDZ($A$1,$B13,AF$1)} -> #NAME?
A14: Rent, Taxes and lighting | B14: BPL_RENT_RATES_TAXES | C14: {=_xll.EQNXTDZ($A$1,$B14,C$1)} -> #NAME? | D14: {=_xll.EQNXTDZ($A$1,$B14,D$1)} -> #NAME? | E14: {=_xll.EQNXTDZ($A$1,$B14,E$1)} -> #NAME? | F14: {=_xll.EQNXTDZ($A$1,$B14,F$1)} -> #NAME? | G14: {=_xll.EQNXTDZ($A$1,$B14,G$1)} -> #NAME? | H14: {=_xll.EQNXTDZ($A$1,$B14,H$1)} -> #NAME? | I14: {=_xll.EQNXTDZ($A$1,$B14,I$1)} -> #NAME? | J14: {=_xll.EQNXTDZ($A$1,$B14,J$1)} -> #NAME? | ... AF14: {=_xll.EQNXTDZ($A$1,$B14,AF$1)} -> #NAME?
A15: Depreciation on Banks property | B15: BPL_DEPRECIATION | C15: {=_xll.EQNXTDZ($A$1,$B15,C$1)} -> #NAME? | D15: {=_xll.EQNXTDZ($A$1,$B15,D$1)} -> #NAME? | E15: {=_xll.EQNXTDZ($A$1,$B15,E$1)} -> #NAME? | F15: {=_xll.EQNXTDZ($A$1,$B15,F$1)} -> #NAME? | G15: {=_xll.EQNXTDZ($A$1,$B15,G$1)} -> #NAME? | H15: {=_xll.EQNXTDZ($A$1,$B15,H$1)} -> #NAME? | I15: {=_xll.EQNXTDZ($A$1,$B15,I$1)} -> #NAME? | J15: {=_xll.EQNXTDZ($A$1,$B15,J$1)} -> #NAME? | ... AF15: {=_xll.EQNXTDZ($A$1,$B15,AF$1)} -> #NAME?
A16: Depreciation on leased assets | B16: BPL_DEPRECIATION_LEASED_ASSETS | C16: {=_xll.EQNXTDZ($A$1,$B16,C$1)} -> #NAME? | D16: {=_xll.EQNXTDZ($A$1,$B16,D$1)} -> #NAME? | E16: {=_xll.EQNXTDZ($A$1,$B16,E$1)} -> #NAME? | F16: {=_xll.EQNXTDZ($A$1,$B16,F$1)} -> #NAME? | G16: {=_xll.EQNXTDZ($A$1,$B16,G$1)} -> #NAME? | H16: {=_xll.EQNXTDZ($A$1,$B16,H$1)} -> #NAME? | I16: {=_xll.EQNXTDZ($A$1,$B16,I$1)} -> #NAME? | J16: {=_xll.EQNXTDZ($A$1,$B16,J$1)} -> #NAME? | ... AF16: {=_xll.EQNXTDZ($A$1,$B16,AF$1)} -> #NAME?
... A35: Consolidated PAT | B35: BPL_CONSOLPAT | C35: {=_xll.EQNXTDZ($A$1,$B35,C$1)} -> #NAME? | D35: {=_xll.EQNXTDZ($A$1,$B35,D$1)} -> #NAME? | E35: {=_xll.EQNXTDZ($A$1,$B35,E$1)} -> #NAME? | F35: {=_xll.EQNXTDZ($A$1,$B35,F$1)} -> #NAME? | G35: {=_xll.EQNXTDZ($A$1,$B35,G$1)} -> #NAME? | H35: {=_xll.EQNXTDZ($A$1,$B35,H$1)} -> #NAME? | I35: {=_xll.EQNXTDZ($A$1,$B35,I$1)} -> #NAME? | J35: {=_xll.EQNXTDZ($A$1,$B35,J$1)} -> #NAME? | ... AF35: {=_xll.EQNXTDZ($A$1,$B35,AF$1)} -> #NAME?
A37: Field Description | B37: Field Name
A38: Equity Paid Up | B38: FH_EQUITY_PAIDUP | C38: {=_xll.EQNXTDZ($A$1,$B38,C$1)} -> #NAME? | D38: {=_xll.EQNXTDZ($A$1,$B38,D$1)} -> #NAME? | E38: {=_xll.EQNXTDZ($A$1,$B38,E$1)} -> #NAME? | F38: {=_xll.EQNXTDZ($A$1,$B38,F$1)} -> #NAME? | G38: {=_xll.EQNXTDZ($A$1,$B38,G$1)} -> #NAME? | H38: {=_xll.EQNXTDZ($A$1,$B38,H$1)} -> #NAME? | I38: {=_xll.EQNXTDZ($A$1,$B38,I$1)} -> #NAME? | J38: {=_xll.EQNXTDZ($A$1,$B38,J$1)} -> #NAME? | ... AF38: {=_xll.EQNXTDZ($A$1,$B38,AF$1)} -> #NAME?
A39: Reserves and Surplus | B39: FH_RESERVE | C39: {=_xll.EQNXTDZ($A$1,$B39,C$1)} -> #NAME? | D39: {=_xll.EQNXTDZ($A$1,$B39,D$1)} -> #NAME? | E39: {=_xll.EQNXTDZ($A$1,$B39,E$1)} -> #NAME? | F39: {=_xll.EQNXTDZ($A$1,$B39,F$1)} -> #NAME? | G39: {=_xll.EQNXTDZ($A$1,$B39,G$1)} -> #NAME? | H39: {=_xll.EQNXTDZ($A$1,$B39,H$1)} -> #NAME? | I39: {=_xll.EQNXTDZ($A$1,$B39,I$1)} -> #NAME? | J39: {=_xll.EQNXTDZ($A$1,$B39,J$1)} -> #NAME? | ... AF39: {=_xll.EQNXTDZ($A$1,$B39,AF$1)} -> #NAME?
A40: Net Worth | B40: FH_NET_WORTH | C40: {=_xll.EQNXTDZ($A$1,$B40,C$1)} -> #NAME? | D40: {=_xll.EQNXTDZ($A$1,$B40,D$1)} -> #NAME? | E40: {=_xll.EQNXTDZ($A$1,$B40,E$1)} -> #NAME? | F40: {=_xll.EQNXTDZ($A$1,$B40,F$1)} -> #NAME? | G40: {=_xll.EQNXTDZ($A$1,$B40,G$1)} -> #NAME? | H40: {=_xll.EQNXTDZ($A$1,$B40,H$1)} -> #NAME? | I40: {=_xll.EQNXTDZ($A$1,$B40,I$1)} -> #NAME? | J40: {=_xll.EQNXTDZ($A$1,$B40,J$1)} -> #NAME? | ... AF40: {=_xll.EQNXTDZ($A$1,$B40,AF$1)} -> #NAME?
A41: Total Debt | B41: FH_TOTAL_DEBTS | C41: {=_xll.EQNXTDZ($A$1,$B41,C$1)} -> #NAME? | D41: {=_xll.EQNXTDZ($A$1,$B41,D$1)} -> #NAME? | E41: {=_xll.EQNXTDZ($A$1,$B41,E$1)} -> #NAME? | F41: {=_xll.EQNXTDZ($A$1,$B41,F$1)} -> #NAME? | G41: {=_xll.EQNXTDZ($A$1,$B41,G$1)} -> #NAME? | H41: {=_xll.EQNXTDZ($A$1,$B41,H$1)} -> #NAME? | I41: {=_xll.EQNXTDZ($A$1,$B41,I$1)} -> #NAME? | J41: {=_xll.EQNXTDZ($A$1,$B41,J$1)} -> #NAME? | ... AF41: {=_xll.EQNXTDZ($A$1,$B41,AF$1)} -> #NAME?
A42: Deposits | B42: FH_DEPOSITS | C42: {=_xll.EQNXTDZ($A$1,$B42,C$1)} -> #NAME? | D42: {=_xll.EQNXTDZ($A$1,$B42,D$1)} -> #NAME? | E42: {=_xll.EQNXTDZ($A$1,$B42,E$1)} -> #NAME? | F42: {=_xll.EQNXTDZ($A$1,$B42,F$1)} -> #NAME? | G42: {=_xll.EQNXTDZ($A$1,$B42,G$1)} -> #NAME? | H42: {=_xll.EQNXTDZ($A$1,$B42,H$1)} -> #NAME? | I42: {=_xll.EQNXTDZ($A$1,$B42,I$1)} -> #NAME? | J42: {=_xll.EQNXTDZ($A$1,$B42,J$1)} -> #NAME? | ... AF42: {=_xll.EQNXTDZ($A$1,$B42,AF$1)} -> #NAME?
A43: Borrowings | B43: FH_BORROWINGS | C43: {=_xll.EQNXTDZ($A$1,$B43,C$1)} -> #NAME? | D43: {=_xll.EQNXTDZ($A$1,$B43,D$1)} -> #NAME? | E43: {=_xll.EQNXTDZ($A$1,$B43,E$1)} -> #NAME? | F43: {=_xll.EQNXTDZ($A$1,$B43,F$1)} -> #NAME? | G43: {=_xll.EQNXTDZ($A$1,$B43,G$1)} -> #NAME? | H43: {=_xll.EQNXTDZ($A$1,$B43,H$1)} -> #NAME? | I43: {=_xll.EQNXTDZ($A$1,$B43,I$1)} -> #NAME? | J43: {=_xll.EQNXTDZ($A$1,$B43,J$1)} -> #NAME? | ... AF43: {=_xll.EQNXTDZ($A$1,$B43,AF$1)} -> #NAME?
A44: Month End | B44: BMONTH_MONTHEND | C44: {=_xll.EQNXTDZ($A$1,$B44,C$1)} -> #NAME? | D44: {=_xll.EQNXTDZ($A$1,$B44,D$1)} -> #NAME? | E44: {=_xll.EQNXTDZ($A$1,$B44,E$1)} -> #NAME? | F44: {=_xll.EQNXTDZ($A$1,$B44,F$1)} -> #NAME? | G44: {=_xll.EQNXTDZ($A$1,$B44,G$1)} -> #NAME? | H44: {=_xll.EQNXTDZ($A$1,$B44,H$1)} -> #NAME? | I44: {=_xll.EQNXTDZ($A$1,$B44,I$1)} -> #NAME? | J44: {=_xll.EQNXTDZ($A$1,$B44,J$1)} -> #NAME? | ... AF44: {=_xll.EQNXTDZ($A$1,$B44,AF$1)} -> #NAME?
A45: Close Price (Unit Curr.) | B45: FH_YEAR_PRICE | C45: {=_xll.EQNXTDZ($A$1,$B45,C$1)} -> #NAME? | D45: {=_xll.EQNXTDZ($A$1,$B45,D$1)} -> #NAME? | E45: {=_xll.EQNXTDZ($A$1,$B45,E$1)} -> #NAME? | F45: {=_xll.EQNXTDZ($A$1,$B45,F$1)} -> #NAME? | G45: {=_xll.EQNXTDZ($A$1,$B45,G$1)} -> #NAME? | H45: {=_xll.EQNXTDZ($A$1,$B45,H$1)} -> #NAME? | I45: {=_xll.EQNXTDZ($A$1,$B45,I$1)} -> #NAME? | J45: {=_xll.EQNXTDZ($A$1,$B45,J$1)} -> #NAME? | ... AF45: {=_xll.EQNXTDZ($A$1,$B45,AF$1)} -> #NAME?
A46: High Price (Unit Curr.) | B46: FH_HIGH | C46: {=_xll.EQNXTDZ($A$1,$B46,C$1)} -> #NAME? | D46: {=_xll.EQNXTDZ($A$1,$B46,D$1)} -> #NAME? | E46: {=_xll.EQNXTDZ($A$1,$B46,E$1)} -> #NAME? | F46: {=_xll.EQNXTDZ($A$1,$B46,F$1)} -> #NAME? | G46: {=_xll.EQNXTDZ($A$1,$B46,G$1)} -> #NAME? | H46: {=_xll.EQNXTDZ($A$1,$B46,H$1)} -> #NAME? | I46: {=_xll.EQNXTDZ($A$1,$B46,I$1)} -> #NAME? | J46: {=_xll.EQNXTDZ($A$1,$B46,J$1)} -> #NAME? | ... AF46: {=_xll.EQNXTDZ($A$1,$B46,AF$1)} -> #NAME?
A47: Low Price (Unit Curr.) | B47: FH_LOW | C47: {=_xll.EQNXTDZ($A$1,$B47,C$1)} -> #NAME? | D47: {=_xll.EQNXTDZ($A$1,$B47,D$1)} -> #NAME? | E47: {=_xll.EQNXTDZ($A$1,$B47,E$1)} -> #NAME? | F47: {=_xll.EQNXTDZ($A$1,$B47,F$1)} -> #NAME? | G47: {=_xll.EQNXTDZ($A$1,$B47,G$1)} -> #NAME? | H47: {=_xll.EQNXTDZ($A$1,$B47,H$1)} -> #NAME? | I47: {=_xll.EQNXTDZ($A$1,$B47,I$1)} -> #NAME? | J47: {=_xll.EQNXTDZ($A$1,$B47,J$1)} -> #NAME? | ... AF47: {=_xll.EQNXTDZ($A$1,$B47,AF$1)} -> #NAME?
A48: Month end date | B48: BMONTH_CLOSEDATE | C48: {=_xll.EQNXTDZ($A$1,$B48,C$1)} -> #NAME? | D48: {=_xll.EQNXTDZ($A$1,$B48,D$1)} -> #NAME? | E48: {=_xll.EQNXTDZ($A$1,$B48,E$1)} -> #NAME? | F48: {=_xll.EQNXTDZ($A$1,$B48,F$1)} -> #NAME? | G48: {=_xll.EQNXTDZ($A$1,$B48,G$1)} -> #NAME? | H48: {=_xll.EQNXTDZ($A$1,$B48,H$1)} -> #NAME? | I48: {=_xll.EQNXTDZ($A$1,$B48,I$1)} -> #NAME? | J48: {=_xll.EQNXTDZ($A$1,$B48,J$1)} -> #NAME? | ... AF48: {=_xll.EQNXTDZ($A$1,$B48,AF$1)} -> #NAME?
A49: Volume ('000) | B49: BMONTH_VOLUME | C49: {=_xll.EQNXTDZ($A$1,$B49,C$1)} -> #NAME? | D49: {=_xll.EQNXTDZ($A$1,$B49,D$1)} -> #NAME? | E49: {=_xll.EQNXTDZ($A$1,$B49,E$1)} -> #NAME? | F49: {=_xll.EQNXTDZ($A$1,$B49,F$1)} -> #NAME? | G49: {=_xll.EQNXTDZ($A$1,$B49,G$1)} -> #NAME? | H49: {=_xll.EQNXTDZ($A$1,$B49,H$1)} -> #NAME? | I49: {=_xll.EQNXTDZ($A$1,$B49,I$1)} -> #NAME? | J49: {=_xll.EQNXTDZ($A$1,$B49,J$1)} -> #NAME? | ... AF49: {=_xll.EQNXTDZ($A$1,$B49,AF$1)} -> #NAME?
... A54: NIM_Reported (%) | B54: RBI_NIMAR | C54: {=_xll.EQNXTDZ($A$1,$B54,C$1)} -> #NAME? | D54: {=_xll.EQNXTDZ($A$1,$B54,D$1)} -> #NAME? | E54: {=_xll.EQNXTDZ($A$1,$B54,E$1)} -> #NAME? | F54: {=_xll.EQNXTDZ($A$1,$B54,F$1)} -> #NAME? | G54: {=_xll.EQNXTDZ($A$1,$B54,G$1)} -> #NAME? | H54: {=_xll.EQNXTDZ($A$1,$B54,H$1)} -> #NAME? | I54: {=_xll.EQNXTDZ($A$1,$B54,I$1)} -> #NAME? | J54: {=_xll.EQNXTDZ($A$1,$B54,J$1)} -> #NAME? | ... AF54: {=_xll.EQNXTDZ($A$1,$B54,AF$1)} -> #NAME?
A58: Field Description | B58: Field Name
A59: Year End | B59: BBS_YEAR_END | C59: {=_xll.EQNXTDZ($A$1,$B59,C$1)} -> #NAME? | D59: {=_xll.EQNXTDZ($A$1,$B59,D$1)} -> #NAME? | E59: {=_xll.EQNXTDZ($A$1,$B59,E$1)} -> #NAME? | F59: {=_xll.EQNXTDZ($A$1,$B59,F$1)} -> #NAME? | G59: {=_xll.EQNXTDZ($A$1,$B59,G$1)} -> #NAME? | H59: {=_xll.EQNXTDZ($A$1,$B59,H$1)} -> #NAME? | I59: {=_xll.EQNXTDZ($A$1,$B59,I$1)} -> #NAME? | J59: {=_xll.EQNXTDZ($A$1,$B59,J$1)} -> #NAME? | ... AF59: {=_xll.EQNXTDZ($A$1,$B59,AF$1)} -> #NAME?
A60: Year | B60: BBS_YEAR | C60: {=_xll.EQNXTDZ($A$1,$B60,C$1)} -> #NAME? | D60: {=_xll.EQNXTDZ($A$1,$B60,D$1)} -> #NAME? | E60: {=_xll.EQNXTDZ($A$1,$B60,E$1)} -> #NAME? | F60: {=_xll.EQNXTDZ($A$1,$B60,F$1)} -> #NAME? | G60: {=_xll.EQNXTDZ($A$1,$B60,G$1)} -> #NAME? | H60: {=_xll.EQNXTDZ($A$1,$B60,H$1)} -> #NAME? | I60: {=_xll.EQNXTDZ($A$1,$B60,I$1)} -> #NAME? | J60: {=_xll.EQNXTDZ($A$1,$B60,J$1)} -> #NAME? | ... AF60: {=_xll.EQNXTDZ($A$1,$B60,AF$1)} -> #NAME?
A61: No of Months | B61: BBS_NO_MONTHS | C61: {=_xll.EQNXTDZ($A$1,$B61,C$1)} -> #NAME? | D61: {=_xll.EQNXTDZ($A$1,$B61,D$1)} -> #NAME? | E61: {=_xll.EQNXTDZ($A$1,$B61,E$1)} -> #NAME? | F61: {=_xll.EQNXTDZ($A$1,$B61,F$1)} -> #NAME? | G61: {=_xll.EQNXTDZ($A$1,$B61,G$1)} -> #NAME? | H61: {=_xll.EQNXTDZ($A$1,$B61,H$1)} -> #NAME? | I61: {=_xll.EQNXTDZ($A$1,$B61,I$1)} -> #NAME? | J61: {=_xll.EQNXTDZ($A$1,$B61,J$1)} -> #NAME? | ... AF61: {=_xll.EQNXTDZ($A$1,$B61,AF$1)} -> #NAME?
A62: Year end date | B62: BBS_YEAR_ENDDATE | C62: {=_xll.EQNXTDZ($A$1,$B62,C$1)} -> #NAME? | D62: {=_xll.EQNXTDZ($A$1,$B62,D$1)} -> #NAME? | E62: {=_xll.EQNXTDZ($A$1,$B62,E$1)} -> #NAME? | F62: {=_xll.EQNXTDZ($A$1,$B62,F$1)} -> #NAME? | G62: {=_xll.EQNXTDZ($A$1,$B62,G$1)} -> #NAME? | H62: {=_xll.EQNXTDZ($A$1,$B62,H$1)} -> #NAME? | I62: {=_xll.EQNXTDZ($A$1,$B62,I$1)} -> #NAME? | J62: {=_xll.EQNXTDZ($A$1,$B62,J$1)} -> #NAME? | ... AF62: {=_xll.EQNXTDZ($A$1,$B62,AF$1)} -> #NAME?
A63: Share Capital | B63: BBS_SHARE_CAPITAL | C63: {=_xll.EQNXTDZ($A$1,$B63,C$1)} -> #NAME? | D63: {=_xll.EQNXTDZ($A$1,$B63,D$1)} -> #NAME? | E63: {=_xll.EQNXTDZ($A$1,$B63,E$1)} -> #NAME? | F63: {=_xll.EQNXTDZ($A$1,$B63,F$1)} -> #NAME? | G63: {=_xll.EQNXTDZ($A$1,$B63,G$1)} -> #NAME? | H63: {=_xll.EQNXTDZ($A$1,$B63,H$1)} -> #NAME? | I63: {=_xll.EQNXTDZ($A$1,$B63,I$1)} -> #NAME? | J63: {=_xll.EQNXTDZ($A$1,$B63,J$1)} -> #NAME? | ... AF63: {=_xll.EQNXTDZ($A$1,$B63,AF$1)} -> #NAME?
A64: Share Warrants & Outstandings | B64: BBS_SHAREWROUTST | C64: {=_xll.EQNXTDZ($A$1,$B64,C$1)} -> #NAME? | D64: {=_xll.EQNXTDZ($A$1,$B64,D$1)} -> #NAME? | E64: {=_xll.EQNXTDZ($A$1,$B64,E$1)} -> #NAME? | F64: {=_xll.EQNXTDZ($A$1,$B64,F$1)} -> #NAME? | G64: {=_xll.EQNXTDZ($A$1,$B64,G$1)} -> #NAME? | H64: {=_xll.EQNXTDZ($A$1,$B64,H$1)} -> #NAME? | I64: {=_xll.EQNXTDZ($A$1,$B64,I$1)} -> #NAME? | J64: {=_xll.EQNXTDZ($A$1,$B64,J$1)} -> #NAME? | ... AF64: {=_xll.EQNXTDZ($A$1,$B64,AF$1)} -> #NAME?
A65: Total Reserves | B65: BBS_RESERVE | C65: {=_xll.EQNXTDZ($A$1,$B65,C$1)} -> #NAME? | D65: {=_xll.EQNXTDZ($A$1,$B65,D$1)} -> #NAME? | E65: {=_xll.EQNXTDZ($A$1,$B65,E$1)} -> #NAME? | F65: {=_xll.EQNXTDZ($A$1,$B65,F$1)} -> #NAME? | G65: {=_xll.EQNXTDZ($A$1,$B65,G$1)} -> #NAME? | H65: {=_xll.EQNXTDZ($A$1,$B65,H$1)} -> #NAME? | I65: {=_xll.EQNXTDZ($A$1,$B65,I$1)} -> #NAME? | J65: {=_xll.EQNXTDZ($A$1,$B65,J$1)} -> #NAME? | ... AF65: {=_xll.EQNXTDZ($A$1,$B65,AF$1)} -> #NAME?
A66: Minority Interest | B66: BBS_MINORITY_INTEREST | C66: {=_xll.EQNXTDZ($A$1,$B66,C$1)} -> #NAME? | D66: {=_xll.EQNXTDZ($A$1,$B66,D$1)} -> #NAME? | E66: {=_xll.EQNXTDZ($A$1,$B66,E$1)} -> #NAME? | F66: {=_xll.EQNXTDZ($A$1,$B66,F$1)} -> #NAME? | G66: {=_xll.EQNXTDZ($A$1,$B66,G$1)} -> #NAME? | H66: {=_xll.EQNXTDZ($A$1,$B66,H$1)} -> #NAME? | I66: {=_xll.EQNXTDZ($A$1,$B66,I$1)} -> #NAME? | J66: {=_xll.EQNXTDZ($A$1,$B66,J$1)} -> #NAME? | ... AF66: {=_xll.EQNXTDZ($A$1,$B66,AF$1)} -> #NAME?
A67: Deposits | B67: BBS_DEPOSITS | C67: {=_xll.EQNXTDZ($A$1,$B67,C$1)} -> #NAME? | D67: {=_xll.EQNXTDZ($A$1,$B67,D$1)} -> #NAME? | E67: {=_xll.EQNXTDZ($A$1,$B67,E$1)} -> #NAME? | F67: {=_xll.EQNXTDZ($A$1,$B67,F$1)} -> #NAME? | G67: {=_xll.EQNXTDZ($A$1,$B67,G$1)} -> #NAME? | H67: {=_xll.EQNXTDZ($A$1,$B67,H$1)} -> #NAME? | I67: {=_xll.EQNXTDZ($A$1,$B67,I$1)} -> #NAME? | J67: {=_xll.EQNXTDZ($A$1,$B67,J$1)} -> #NAME? | ... AF67: {=_xll.EQNXTDZ($A$1,$B67,AF$1)} -> #NAME?
A68: Borrowings | B68: BBS_BORROWINGS | C68: {=_xll.EQNXTDZ($A$1,$B68,C$1)} -> #NAME? | D68: {=_xll.EQNXTDZ($A$1,$B68,D$1)} -> #NAME? | E68: {=_xll.EQNXTDZ($A$1,$B68,E$1)} -> #NAME? | F68: {=_xll.EQNXTDZ($A$1,$B68,F$1)} -> #NAME? | G68: {=_xll.EQNXTDZ($A$1,$B68,G$1)} -> #NAME? | H68: {=_xll.EQNXTDZ($A$1,$B68,H$1)} -> #NAME? | I68: {=_xll.EQNXTDZ($A$1,$B68,I$1)} -> #NAME? | J68: {=_xll.EQNXTDZ($A$1,$B68,J$1)} -> #NAME? | ... AF68: {=_xll.EQNXTDZ($A$1,$B68,AF$1)} -> #NAME?
A69: Other Liabilities & Provisions | B69: BBS_OTHER_LIABILITIES | C69: {=_xll.EQNXTDZ($A$1,$B69,C$1)} -> #NAME? | D69: {=_xll.EQNXTDZ($A$1,$B69,D$1)} -> #NAME? | E69: {=_xll.EQNXTDZ($A$1,$B69,E$1)} -> #NAME? | F69: {=_xll.EQNXTDZ($A$1,$B69,F$1)} -> #NAME? | G69: {=_xll.EQNXTDZ($A$1,$B69,G$1)} -> #NAME? | H69: {=_xll.EQNXTDZ($A$1,$B69,H$1)} -> #NAME? | I69: {=_xll.EQNXTDZ($A$1,$B69,I$1)} -> #NAME? | J69: {=_xll.EQNXTDZ($A$1,$B69,J$1)} -> #NAME? | ... AF69: {=_xll.EQNXTDZ($A$1,$B69,AF$1)} -> #NAME?
A70: Total Liabilities | B70: BBS_TOTAL_SOUNCES_FUNDS | C70: {=_xll.EQNXTDZ($A$1,$B70,C$1)} -> #NAME? | D70: {=_xll.EQNXTDZ($A$1,$B70,D$1)} -> #NAME? | E70: {=_xll.EQNXTDZ($A$1,$B70,E$1)} -> #NAME? | F70: {=_xll.EQNXTDZ($A$1,$B70,F$1)} -> #NAME? | G70: {=_xll.EQNXTDZ($A$1,$B70,G$1)} -> #NAME? | H70: {=_xll.EQNXTDZ($A$1,$B70,H$1)} -> #NAME? | I70: {=_xll.EQNXTDZ($A$1,$B70,I$1)} -> #NAME? | J70: {=_xll.EQNXTDZ($A$1,$B70,J$1)} -> #NAME? | ... AF70: {=_xll.EQNXTDZ($A$1,$B70,AF$1)} -> #NAME?
... A94: Tier 2 (Basel III) | B94: RBI_TII_CAR_B | C94: {=_xll.EQNXTDZ($A$1,$B94,C$1)} -> #NAME? | D94: {=_xll.EQNXTDZ($A$1,$B94,D$1)} -> #NAME? | E94: {=_xll.EQNXTDZ($A$1,$B94,E$1)} -> #NAME? | F94: {=_xll.EQNXTDZ($A$1,$B94,F$1)} -> #NAME? | G94: {=_xll.EQNXTDZ($A$1,$B94,G$1)} -> #NAME? | H94: {=_xll.EQNXTDZ($A$1,$B94,H$1)} -> #NAME? | I94: {=_xll.EQNXTDZ($A$1,$B94,I$1)} -> #NAME? | J94: {=_xll.EQNXTDZ($A$1,$B94,J$1)} -> #NAME? | ... AF94: {=_xll.EQNXTDZ($A$1,$B94,AF$1)} -> #NAME?

Sheet QTR Share Price
A1: =+'Annual Raw'!A1 -> 132525 | C1: 201206 | D1: 201207 | E1: 201208 | F1: 201209 | G1: 201210 | H1: 201211 | I1: 201212 | J1: 201301 | K1: 201302 | L1: 201303 | M1: 201304 | N1: 201305 | O1: 201306 | P1: 201307 | Q1: 201308 | R1: 201309 | S1: 201310 | T1: 201311 | U1: 201312 | V1: 201401 | W1: 201402 | X1: 201403 | Y1: 201404 | Z1: 201405 | AA1: 201406 | AB1: 201407 | AC1: 201408 | AD1: 201409 | AE1: 201410 | AF1: 201411 | AG1: 201412 | AH1: 201501 | AI1: 201502 | AJ1: 201503 | AK1: 201504 | AL1: 201505 | AM1: 201506 | AN1: 201507 | AO1: 201508 | AP1: 201509 | AQ1: 201510 | AR1: 201511 | AS1: 201512 | AT1: 201601 | AU1: 201602 | AV1: 201603 | AW1: 201604 | AX1: 201605 | AY1: 201606 | AZ1: 201607 | BA1: 201608 | BB1: 201609 | BC1: 201610 | BD1: 201611 | BE1: 201612 | BF1: 201701 | BG1: 201702 | BH1: 201703 | BI1: 201704 | BJ1: 201705 | BK1: 201706 | BL1: 201707 | BM1: 201708 | BN1: 201709 | BO1: 201710 | BP1: 201711 | BQ1: 201712 | BR1: 201801 | BS1: 201802 | BT1: 201803 | BU1: 201804 | BV1: 201805 | BW1: 201806 | BX1: 201807 | BY1: 201808 | BZ1: 201809 | CA1: 201810 | CB1: 201811 | CC1: 201812 | CD1: 201901 | CE1: 201902 | CF1: 201903 | CG1: 201904 | CH1: 201905 | CI1: 201906 | CJ1: 201907 | CK1: 201908 | CL1: 201909 | CM1: 201910 | CN1: 201911 | CO1: 201912 | CP1: 202001 | CQ1: 202002 | CR1: 202003 | CS1: 202004 | CT1: 202005 | CU1: 202006 | CV1: 202007 | CW1: 202008 | CX1: 202009 | CY1: 202010 | CZ1: 202011 | DA1: 202012 | DB1: 202101 | DC1: 202102 | DD1: 202103 | DE1: 202104 | DF1: 202105 | DG1: 202106 | DH1: 202107 | DI1: 202108 | DJ1: 202109 | DK1: 202110 | DL1: 202111 | DM1: 202112 | DN1: 202201 | DO1: 202202 | DP1: 202203 | DQ1: 202204 | DR1: 202205 | DS1: 202206 | DT1: 202207 | DU1: 202208 | DV1: 202209 | DW1: 202210 | DX1: 202211 | DY1: 202212 | DZ1: 202301 | EA1: 202302 | EB1: 202303 | EC1: 202304 | ED1: 202305 | EE1: 202306 | EF1: 202307 | EG1: 202308 | EH1: 202309 | EI1: 202310 | EJ1: 202311 | EK1: 202312 | EL1: 202401 | EM1: 202402 | EN1: 202403 | EO1: 202404 | EP1: 202405 | EQ1: 202406 | ER1: 202407 | ES1: 202408 | ET1: 202409 | EU1: 202410 | EV1: 202411 | EW1: 202412 | EX1: 202501 | EY1: 202502 | EZ1: 202503 | FA1: 202504 | FB1: 202505 | FC1: 202506 | FD1: 202507 | FE1: 202508 | FF1: 202509 | FG1: 202510 | FH1: 202511 | FI1: 202512 | FJ1: 202601 | FK1: 202602 | FL1: 202603 | FM1: 202604 | FN1: 202605 | FO1: 202606 | FP1: 202607 | FQ1: 202608 | FR1: 202609 | FS1: 202610 | FT1: 202611 | FU1: 202612 | FV1: 202701 | FW1: 202702 | FX1: 202703 | FY1: 202704 | FZ1: 202705 | GA1: 202706 | GB1: 202707 | GC1: 202708 | GD1: 202709 | GE1: 202710 | GF1: 202711 | GG1: 202712 | GH1: 202801 | GI1: 202802 | GJ1: 202803 | GK1: 202804 | GL1: 202805 | GM1: 202806 | GN1: 202807 | GO1: 202808 | GP1: 202809 | GQ1: 202810 | GR1: 202811 | GS1: 202812 | GT1: 202901 | GU1: 202902 | GV1: 202903 | GW1: 202904 | GX1: 202905 | GY1: 202906 | GZ1: 202907 | HA1: 202908 | HB1: 202909 | HC1: 202910 | HD1: 202911 | HE1: 202912 | HF1: 203001 | HG1: 203002 | HH1: 203003 | HM1: 201206 | HN1: 201207 | HO1: 201208 | HP1: 201209 | HQ1: 201212 | HR1: 201303 | HS1: 201306 | HT1: 201309 | HU1: 201312 | HV1: 201403 | HW1: 201406 | HX1: 201409 | HY1: 201412 | HZ1: 201503 | IA1: 201506 | IB1: 201509 | IC1: 201512 | ID1: 201603 | IE1: 201606 | IF1: 201609 | IG1: 201612 | IH1: 201703 | II1: 201706 | IJ1: 201709 | IK1: 201712 | IL1: 201803 | IM1: 201806 | IN1: 201809 | IO1: 201812 | IP1: 201903 | IQ1: 201906 | IR1: 201909 | IS1: 201912 | IT1: 202003 | IU1: 202006 | IV1: 202009 | IW1: 202012 | IX1: 202103 | IY1: 202106 | IZ1: 202109 | JA1: 202112 | JB1: 202203 | JC1: 202206 | JD1: 202209 | JE1: 202212 | JF1: 202303 | JG1: 202306 | JH1: 202309 | JI1: 202312 | JJ1: 202403 | JK1: 202406 | JL1: 202409 | JM1: 202412 | JN1: 202503 | JO1: 202506 | JP1: 202509 | JQ1: 202512 | JR1: 202603 | JS1: 202606 | JT1: 202609 | JU1: 202612 | JV1: 202703 | JW1: 202706 | JX1: 202709 | JY1: 202712 | JZ1: 202803 | KA1: 202806 | KB1: 202809 | KC1: 202812 | KD1: 202903 | KE1: 202906 | KF1: 202909 | KG1: 202912 | KH1: 203003
A4: Field Description | B4: Field Name
A5: MonthEnd | B5: NMONTH_MONTHEND | C5: {=_xll.EQNXTDZ($A$1,$B5,C$1)} -> #NAME? | D5: {=_xll.EQNXTDZ($A$1,$B5,D$1)} -> #NAME? | E5: {=_xll.EQNXTDZ($A$1,$B5,E$1)} -> #NAME? | F5: {=_xll.EQNXTDZ($A$1,$B5,F$1)} -> #NAME? | G5: {=_xll.EQNXTDZ($A$1,$B5,G$1)} -> #NAME? | H5: {=_xll.EQNXTDZ($A$1,$B5,H$1)} -> #NAME? | I5: {=_xll.EQNXTDZ($A$1,$B5,I$1)} -> #NAME? | J5: {=_xll.EQNXTDZ($A$1,$B5,J$1)} -> #NAME? | ... HH5: {=_xll.EQNXTDZ($A$1,$B5,HH$1)} -> #NAME?
A6: Open | B6: NMONTH_OPEN | C6: {=_xll.EQNXTDZ($A$1,$B6,C$1)} -> #NAME? | D6: {=_xll.EQNXTDZ($A$1,$B6,D$1)} -> #NAME? | E6: {=_xll.EQNXTDZ($A$1,$B6,E$1)} -> #NAME? | F6: {=_xll.EQNXTDZ($A$1,$B6,F$1)} -> #NAME? | G6: {=_xll.EQNXTDZ($A$1,$B6,G$1)} -> #NAME? | H6: {=_xll.EQNXTDZ($A$1,$B6,H$1)} -> #NAME? | I6: {=_xll.EQNXTDZ($A$1,$B6,I$1)} -> #NAME? | J6: {=_xll.EQNXTDZ($A$1,$B6,J$1)} -> #NAME? | ... HH6: {=_xll.EQNXTDZ($A$1,$B6,HH$1)} -> #NAME?
A7: High | B7: NMONTH_HIGH | C7: {=_xll.EQNXTDZ($A$1,$B7,C$1)} -> #NAME? | D7: {=_xll.EQNXTDZ($A$1,$B7,D$1)} -> #NAME? | E7: {=_xll.EQNXTDZ($A$1,$B7,E$1)} -> #NAME? | F7: {=_xll.EQNXTDZ($A$1,$B7,F$1)} -> #NAME? | G7: {=_xll.EQNXTDZ($A$1,$B7,G$1)} -> #NAME? | H7: {=_xll.EQNXTDZ($A$1,$B7,H$1)} -> #NAME? | I7: {=_xll.EQNXTDZ($A$1,$B7,I$1)} -> #NAME? | J7: {=_xll.EQNXTDZ($A$1,$B7,J$1)} -> #NAME? | ... HH7: {=_xll.EQNXTDZ($A$1,$B7,HH$1)} -> #NAME? | HP7: =+MAX(D7:F7) -> #NAME? | HQ7: =+MAX(G7:I7) -> #NAME? | HR7: =+MAX(J7:L7) -> #NAME? | HS7: =+MAX(M7:O7) -> #NAME? | HT7: =+MAX(P7:R7) -> #NAME? | HU7: =+MAX(S7:U7) -> #NAME? | HV7: =+MAX(V7:X7) -> #NAME? | HW7: =+MAX(Y7:AA7) -> #NAME? | HX7: =+MAX(AB7:AD7) -> #NAME? | HY7: =+MAX(AE7:AG7) -> #NAME? | HZ7: =+MAX(AH7:AJ7) -> #NAME? | IA7: =+MAX(AK7:AM7) -> #NAME? | IB7: =+MAX(AN7:AP7) -> #NAME? | IC7: =+MAX(AQ7:AS7) -> #NAME? | ID7: =+MAX(AT7:AV7) -> #NAME? | IE7: =+MAX(AW7:AY7) -> #NAME? | IF7: =+MAX(AZ7:BB7) -> #NAME? | IG7: =+MAX(BC7:BE7) -> #NAME? | IH7: =+MAX(BF7:BH7) -> #NAME? | II7: =+MAX(BI7:BK7) -> #NAME? | IJ7: =+MAX(BL7:BN7) -> #NAME? | IK7: =+MAX(BO7:BQ7) -> #NAME? | IL7: =+MAX(BR7:BT7) -> #NAME? | IM7: =+MAX(BU7:BW7) -> #NAME? | IN7: =+MAX(BX7:BZ7) -> #NAME? | IO7: =+MAX(CA7:CC7) -> #NAME? | IP7: =+MAX(CD7:CF7) -> #NAME? | IQ7: =+MAX(CG7:CI7) -> #NAME? | IR7: =+MAX(CJ7:CL7) -> #NAME? | IS7: =+MAX(CM7:CO7) -> #NAME? | IT7: =+MAX(CP7:CR7) -> #NAME? | IU7: =+MAX(CS7:CU7) -> #NAME? | IV7: =+MAX(CV7:CX7) -> #NAME? | IW7: =+MAX(CY7:DA7) -> #NAME? | IX7: =+MAX(DB7:DD7) -> #NAME? | IY7: =+MAX(DE7:DG7) -> #NAME? | IZ7: =+MAX(DH7:DJ7) -> #NAME? | JA7: =+MAX(DK7:DM7) -> #NAME? | JB7: =+MAX(DN7:DP7) -> #NAME? | JC7: =+MAX(DQ7:DS7) -> #NAME? | JD7: =+MAX(DT7:DV7) -> #NAME? | JE7: =+MAX(DW7:DY7) -> #NAME? | JF7: =+MAX(DZ7:EB7) -> #NAME? | JG7: =+MAX(EC7:EE7) -> #NAME? | JH7: =+MAX(EF7:EH7) -> #NAME? | JI7: =+MAX(EI7:EK7) -> #NAME? | JJ7: =+MAX(EL7:EN7) -> #NAME? | JK7: =MAX(EO7:EQ7) -> #NAME? | JL7: =MAX(ER7:ET7) -> #NAME? | JM7: =MAX(EU7:EW7) -> #NAME? | JN7: =MAX(EX7:EZ7) -> #NAME? | JO7: =MAX(FA7:FC7) -> #NAME? | JP7: =MAX(FD7:FF7) -> #NAME? | JQ7: =MAX(FG7:FI7) -> #NAME? | JR7: =MAX(FJ7:FL7) -> #NAME? | JS7: =MAX(FM7:FO7) -> #NAME? | JT7: =MAX(FP7:FR7) -> #NAME? | JU7: =MAX(FS7:FU7) -> #NAME? | JV7: =MAX(FV7:FX7) -> #NAME? | JW7: =MAX(FY7:GA7) -> #NAME? | JX7: =MAX(GB7:GD7) -> #NAME? | JY7: =MAX(GE7:GG7) -> #NAME? | JZ7: =MAX(GH7:GJ7) -> #NAME? | KA7: =MAX(GK7:GM7) -> #NAME? | KB7: =MAX(GN7:GP7) -> #NAME? | KC7: =MAX(GQ7:GS7) -> #NAME? | KD7: =MAX(GT7:GV7) -> #NAME? | KE7: =MAX(GW7:GY7) -> #NAME? | KF7: =MAX(GZ7:HB7) -> #NAME? | KG7: =MAX(HC7:HE7) -> #NAME? | KH7: =MAX(HF7:HH7) -> #NAME?
A8: Low | B8: NMONTH_LOW | C8: {=_xll.EQNXTDZ($A$1,$B8,C$1)} -> #NAME? | D8: {=_xll.EQNXTDZ($A$1,$B8,D$1)} -> #NAME? | E8: {=_xll.EQNXTDZ($A$1,$B8,E$1)} -> #NAME? | F8: {=_xll.EQNXTDZ($A$1,$B8,F$1)} -> #NAME? | G8: {=_xll.EQNXTDZ($A$1,$B8,G$1)} -> #NAME? | H8: {=_xll.EQNXTDZ($A$1,$B8,H$1)} -> #NAME? | I8: {=_xll.EQNXTDZ($A$1,$B8,I$1)} -> #NAME? | J8: {=_xll.EQNXTDZ($A$1,$B8,J$1)} -> #NAME? | ... HH8: {=_xll.EQNXTDZ($A$1,$B8,HH$1)} -> #NAME? | HP8: =+MIN(D8:F8) -> #NAME? | HQ8: =+MIN(G8:I8) -> #NAME? | HR8: =+MIN(J8:L8) -> #NAME? | HS8: =+MIN(M8:O8) -> #NAME? | HT8: =+MIN(P8:R8) -> #NAME? | HU8: =+MIN(S8:U8) -> #NAME? | HV8: =+MIN(V8:X8) -> #NAME? | HW8: =+MIN(Y8:AA8) -> #NAME? | HX8: =+MIN(AB8:AD8) -> #NAME? | HY8: =+MIN(AE8:AG8) -> #NAME? | HZ8: =+MIN(AH8:AJ8) -> #NAME? | IA8: =+MIN(AK8:AM8) -> #NAME? | IB8: =+MIN(AN8:AP8) -> #NAME? | IC8: =+MIN(AQ8:AS8) -> #NAME? | ID8: =+MIN(AT8:AV8) -> #NAME? | IE8: =+MIN(AW8:AY8) -> #NAME? | IF8: =+MIN(AZ8:BB8) -> #NAME? | IG8: =+MIN(BC8:BE8) -> #NAME? | IH8: =+MIN(BF8:BH8) -> #NAME? | II8: =+MIN(BI8:BK8) -> #NAME? | IJ8: =+MIN(BL8:BN8) -> #NAME? | IK8: =+MIN(BO8:BQ8) -> #NAME? | IL8: =+MIN(BR8:BT8) -> #NAME? | IM8: =+MIN(BU8:BW8) -> #NAME? | IN8: =+MIN(BX8:BZ8) -> #NAME? | IO8: =+MIN(CA8:CC8) -> #NAME? | IP8: =+MIN(CD8:CF8) -> #NAME? | IQ8: =+MIN(CG8:CI8) -> #NAME? | IR8: =+MIN(CJ8:CL8) -> #NAME? | IS8: =+MIN(CM8:CO8) -> #NAME? | IT8: =+MIN(CP8:CR8) -> #NAME? | IU8: =+MIN(CS8:CU8) -> #NAME? | IV8: =+MIN(CV8:CX8) -> #NAME? | IW8: =+MIN(CY8:DA8) -> #NAME? | IX8: =+MIN(DB8:DD8) -> #NAME? | IY8: =+MIN(DE8:DG8) -> #NAME? | IZ8: =+MIN(DH8:DJ8) -> #NAME? | JA8: =+MIN(DK8:DM8) -> #NAME? | JB8: =+MIN(DN8:DP8) -> #NAME? | JC8: =+MIN(DQ8:DS8) -> #NAME? | JD8: =+MIN(DT8:DV8) -> #NAME? | JE8: =+MIN(DW8:DY8) -> #NAME? | JF8: =+MIN(DZ8:EB8) -> #NAME? | JG8: =+MIN(EC8:EE8) -> #NAME? | JH8: =+MIN(EF8:EH8) -> #NAME? | JI8: =+MIN(EI8:EK8) -> #NAME? | JJ8: =+MIN(EL8:EN8) -> #NAME? | JK8: =MIN(EO8:EQ8) -> #NAME? | JL8: =MIN(ER8:ET8) -> #NAME? | JM8: =MIN(EU8:EW8) -> #NAME? | JN8: =MIN(EX8:EZ8) -> #NAME? | JO8: =MIN(FA8:FC8) -> #NAME? | JP8: =MIN(FD8:FF8) -> #NAME? | JQ8: =MIN(FG8:FI8) -> #NAME? | JR8: =MIN(FJ8:FL8) -> #NAME? | JS8: =MIN(FM8:FO8) -> #NAME? | JT8: =MIN(FP8:FR8) -> #NAME? | JU8: =MIN(FS8:FU8) -> #NAME? | JV8: =MIN(FV8:FX8) -> #NAME? | JW8: =MIN(FY8:GA8) -> #NAME? | JX8: =MIN(GB8:GD8) -> #NAME? | JY8: =MIN(GE8:GG8) -> #NAME? | JZ8: =MIN(GH8:GJ8) -> #NAME? | KA8: =MIN(GK8:GM8) -> #NAME? | KB8: =MIN(GN8:GP8) -> #NAME? | KC8: =MIN(GQ8:GS8) -> #NAME? | KD8: =MIN(GT8:GV8) -> #NAME? | KE8: =MIN(GW8:GY8) -> #NAME? | KF8: =MIN(GZ8:HB8) -> #NAME? | KG8: =MIN(HC8:HE8) -> #NAME? | KH8: =MIN(HF8:HH8) -> #NAME?
A9: Close | B9: NMONTH_CLOSE | C9: {=_xll.EQNXTDZ($A$1,$B9,C$1)} -> #NAME? | D9: {=_xll.EQNXTDZ($A$1,$B9,D$1)} -> #NAME? | E9: {=_xll.EQNXTDZ($A$1,$B9,E$1)} -> #NAME? | F9: {=_xll.EQNXTDZ($A$1,$B9,F$1)} -> #NAME? | G9: {=_xll.EQNXTDZ($A$1,$B9,G$1)} -> #NAME? | H9: {=_xll.EQNXTDZ($A$1,$B9,H$1)} -> #NAME? | I9: {=_xll.EQNXTDZ($A$1,$B9,I$1)} -> #NAME? | J9: {=_xll.EQNXTDZ($A$1,$B9,J$1)} -> #NAME? | ... HH9: {=_xll.EQNXTDZ($A$1,$B9,HH$1)} -> #NAME? | HP9: =+F9 -> #NAME? | HQ9: =+I9 -> #NAME? | HR9: =+L9 -> #NAME? | HS9: =+O9 -> #NAME? | HT9: =+R9 -> #NAME? | HU9: =+U9 -> #NAME? | HV9: =+X9 -> #NAME? | HW9: =+AA9 -> #NAME? | HX9: =+AD9 -> #NAME? | HY9: =+AG9 -> #NAME? | HZ9: =+AJ9 -> #NAME? | IA9: =+AM9 -> #NAME? | IB9: =+AP9 -> #NAME? | IC9: =+AS9 -> #NAME? | ID9: =+AV9 -> #NAME? | IE9: =+AY9 -> #NAME? | IF9: =+BB9 -> #NAME? | IG9: =+BE9 -> #NAME? | IH9: =+BH9 -> #NAME? | II9: =+BK9 -> #NAME? | IJ9: =+BN9 -> #NAME? | IK9: =+BQ9 -> #NAME? | IL9: =+BT9 -> #NAME? | IM9: =+BW9 -> #NAME? | IN9: =+BZ9 -> #NAME? | IO9: =+CC9 -> #NAME? | IP9: =+CF9 -> #NAME? | IQ9: =+CI9 -> #NAME? | IR9: =+CL9 -> #NAME? | IS9: =+CO9 -> #NAME? | IT9: =+CR9 -> #NAME? | IU9: =+CU9 -> #NAME? | IV9: =+CX9 -> #NAME? | IW9: =+DA9 -> #NAME? | IX9: =+DD9 -> #NAME? | IY9: =+DG9 -> #NAME? | IZ9: =+DJ9 -> #NAME? | JA9: =+DM9 -> #NAME? | JB9: =+DP9 -> #NAME? | JC9: =+DS9 -> #NAME? | JD9: =+DV9 -> #NAME? | JE9: =+DY9 -> #NAME? | JF9: =+EB9 -> #NAME? | JG9: =+EE9 -> #NAME? | JH9: =+EH9 -> #NAME? | JI9: =+EK9 -> #NAME? | JJ9: =+EN9 -> #NAME? | JK9: =EQ9 -> #NAME? | JL9: =ET9 -> #NAME? | JM9: =EW9 -> #NAME? | JN9: =EZ9 -> #NAME? | JO9: =FC9 -> #NAME? | JP9: =FF9 -> #NAME? | JQ9: =FI9 -> #NAME? | JR9: =FL9 -> #NAME? | JS9: =FO9 -> #NAME? | JT9: =FR9 -> #NAME? | JU9: =FU9 -> #NAME? | JV9: =FX9 -> #NAME? | JW9: =GA9 -> #NAME? | JX9: =GD9 -> #NAME? | JY9: =GG9 -> #NAME? | JZ9: =GJ9 -> #NAME? | KA9: =GM9 -> #NAME? | KB9: =GP9 -> #NAME? | KC9: =GS9 -> #NAME? | KD9: =GV9 -> #NAME? | KE9: =GY9 -> #NAME? | KF9: =HB9 -> #NAME? | KG9: =HE9 -> #NAME? | KH9: =HH9 -> #NAME?
A11: Field Description | B11: Field Name | C11: {=_xll.EQNXTDZ($A$1,$B11,C$1)} -> #NAME? | D11: {=_xll.EQNXTDZ($A$1,$B11,D$1)} -> #NAME? | E11: {=_xll.EQNXTDZ($A$1,$B11,E$1)} -> #NAME? | F11: {=_xll.EQNXTDZ($A$1,$B11,F$1)} -> #NAME? | G11: {=_xll.EQNXTDZ($A$1,$B11,G$1)} -> #NAME? | H11: {=_xll.EQNXTDZ($A$1,$B11,H$1)} -> #NAME? | I11: {=_xll.EQNXTDZ($A$1,$B11,I$1)} -> #NAME? | J11: {=_xll.EQNXTDZ($A$1,$B11,J$1)} -> #NAME? | ... HH11: {=_xll.EQNXTDZ($A$1,$B11,HH$1)} -> #NAME?
A12: Month End | B12: BMONTH_MONTHEND | C12: {=_xll.EQNXTDZ($A$1,$B12,C$1)} -> #NAME? | D12: {=_xll.EQNXTDZ($A$1,$B12,D$1)} -> #NAME? | E12: {=_xll.EQNXTDZ($A$1,$B12,E$1)} -> #NAME? | F12: {=_xll.EQNXTDZ($A$1,$B12,F$1)} -> #NAME? | G12: {=_xll.EQNXTDZ($A$1,$B12,G$1)} -> #NAME? | H12: {=_xll.EQNXTDZ($A$1,$B12,H$1)} -> #NAME? | I12: {=_xll.EQNXTDZ($A$1,$B12,I$1)} -> #NAME? | J12: {=_xll.EQNXTDZ($A$1,$B12,J$1)} -> #NAME? | ... HH12: {=_xll.EQNXTDZ($A$1,$B12,HH$1)} -> #NAME?
A13: Open | B13: BMONTH_OPEN | C13: {=_xll.EQNXTDZ($A$1,$B13,C$1)} -> #NAME? | D13: {=_xll.EQNXTDZ($A$1,$B13,D$1)} -> #NAME? | E13: {=_xll.EQNXTDZ($A$1,$B13,E$1)} -> #NAME? | F13: {=_xll.EQNXTDZ($A$1,$B13,F$1)} -> #NAME? | G13: {=_xll.EQNXTDZ($A$1,$B13,G$1)} -> #NAME? | H13: {=_xll.EQNXTDZ($A$1,$B13,H$1)} -> #NAME? | I13: {=_xll.EQNXTDZ($A$1,$B13,I$1)} -> #NAME? | J13: {=_xll.EQNXTDZ($A$1,$B13,J$1)} -> #NAME? | ... HH13: {=_xll.EQNXTDZ($A$1,$B13,HH$1)} -> #NAME?
A14: High | B14: BMONTH_HIGH | C14: {=_xll.EQNXTDZ($A$1,$B14,C$1)} -> #NAME? | D14: {=_xll.EQNXTDZ($A$1,$B14,D$1)} -> #NAME? | E14: {=_xll.EQNXTDZ($A$1,$B14,E$1)} -> #NAME? | F14: {=_xll.EQNXTDZ($A$1,$B14,F$1)} -> #NAME? | G14: {=_xll.EQNXTDZ($A$1,$B14,G$1)} -> #NAME? | H14: {=_xll.EQNXTDZ($A$1,$B14,H$1)} -> #NAME? | I14: {=_xll.EQNXTDZ($A$1,$B14,I$1)} -> #NAME? | J14: {=_xll.EQNXTDZ($A$1,$B14,J$1)} -> #NAME? | ... HH14: {=_xll.EQNXTDZ($A$1,$B14,HH$1)} -> #NAME? | HP14: =+MAX(D14:F14) -> #NAME? | HQ14: =+MAX(G14:I14) -> #NAME? | HR14: =+MAX(J14:L14) -> #NAME? | HS14: =+MAX(M14:O14) -> #NAME? | HT14: =+MAX(P14:R14) -> #NAME? | HU14: =+MAX(S14:U14) -> #NAME? | HV14: =+MAX(V14:X14) -> #NAME? | HW14: =+MAX(Y14:AA14) -> #NAME? | HX14: =+MAX(AB14:AD14) -> #NAME? | HY14: =+MAX(AE14:AG14) -> #NAME? | HZ14: =+MAX(AH14:AJ14) -> #NAME? | IA14: =+MAX(AK14:AM14) -> #NAME? | IB14: =+MAX(AN14:AP14) -> #NAME? | IC14: =+MAX(AQ14:AS14) -> #NAME? | ID14: =+MAX(AT14:AV14) -> #NAME? | IE14: =+MAX(AW14:AY14) -> #NAME? | IF14: =+MAX(AZ14:BB14) -> #NAME? | IG14: =+MAX(BC14:BE14) -> #NAME? | IH14: =+MAX(BF14:BH14) -> #NAME? | II14: =+MAX(BI14:BK14) -> #NAME? | IJ14: =+MAX(BL14:BN14) -> #NAME? | IK14: =+MAX(BO14:BQ14) -> #NAME? | IL14: =+MAX(BR14:BT14) -> #NAME? | IM14: =+MAX(BU14:BW14) -> #NAME? | IN14: =+MAX(BX14:BZ14) -> #NAME? | IO14: =+MAX(CA14:CC14) -> #NAME? | IP14: =+MAX(CD14:CF14) -> #NAME? | IQ14: =+MAX(CG14:CI14) -> #NAME? | IR14: =+MAX(CJ14:CL14) -> #NAME? | IS14: =+MAX(CM14:CO14) -> #NAME? | IT14: =+MAX(CP14:CR14) -> #NAME? | IU14: =+MAX(CS14:CU14) -> #NAME? | IV14: =+MAX(CV14:CX14) -> #NAME? | IW14: =+MAX(CY14:DA14) -> #NAME? | IX14: =+MAX(DB14:DD14) -> #NAME? | IY14: =+MAX(DE14:DG14) -> #NAME? | IZ14: =+MAX(DH14:DJ14) -> #NAME? | JA14: =+MAX(DK14:DM14) -> #NAME? | JB14: =+MAX(DN14:DP14) -> #NAME? | JC14: =+MAX(DQ14:DS14) -> #NAME? | JD14: =+MAX(DT14:DV14) -> #NAME? | JE14: =+MAX(DW14:DY14) -> #NAME? | JF14: =+MAX(DZ14:EB14) -> #NAME? | JG14: =+MAX(EC14:EE14) -> #NAME? | JH14: =+MAX(EF14:EH14) -> #NAME? | JI14: =+MAX(EI14:EK14) -> #NAME? | JJ14: =+MAX(EL14:EN14) -> #NAME? | JK14: =MAX(EO14:EQ14) -> #NAME? | JL14: =MAX(ER14:ET14) -> #NAME? | JM14: =MAX(EU14:EW14) -> #NAME? | JN14: =MAX(EX14:EZ14) -> #NAME? | JO14: =MAX(FA14:FC14) -> #NAME? | JP14: =MAX(FD14:FF14) -> #NAME? | JQ14: =MAX(FG14:FI14) -> #NAME? | JR14: =MAX(FJ14:FL14) -> #NAME? | JS14: =MAX(FM14:FO14) -> #NAME? | JT14: =MAX(FP14:FR14) -> #NAME? | JU14: =MAX(FS14:FU14) -> #NAME? | JV14: =MAX(FV14:FX14) -> #NAME? | JW14: =MAX(FY14:GA14) -> #NAME? | JX14: =MAX(GB14:GD14) -> #NAME? | JY14: =MAX(GE14:GG14) -> #NAME? | JZ14: =MAX(GH14:GJ14) -> #NAME? | KA14: =MAX(GK14:GM14) -> #NAME? | KB14: =MAX(GN14:GP14) -> #NAME? | KC14: =MAX(GQ14:GS14) -> #NAME? | KD14: =MAX(GT14:GV14) -> #NAME? | KE14: =MAX(GW14:GY14) -> #NAME? | KF14: =MAX(GZ14:HB14) -> #NAME? | KG14: =MAX(HC14:HE14) -> #NAME? | KH14: =MAX(HF14:HH14) -> #NAME?
A15: Low | B15: BMONTH_LOW | C15: {=_xll.EQNXTDZ($A$1,$B15,C$1)} -> #NAME? | D15: {=_xll.EQNXTDZ($A$1,$B15,D$1)} -> #NAME? | E15: {=_xll.EQNXTDZ($A$1,$B15,E$1)} -> #NAME? | F15: {=_xll.EQNXTDZ($A$1,$B15,F$1)} -> #NAME? | G15: {=_xll.EQNXTDZ($A$1,$B15,G$1)} -> #NAME? | H15: {=_xll.EQNXTDZ($A$1,$B15,H$1)} -> #NAME? | I15: {=_xll.EQNXTDZ($A$1,$B15,I$1)} -> #NAME? | J15: {=_xll.EQNXTDZ($A$1,$B15,J$1)} -> #NAME? | ... HH15: {=_xll.EQNXTDZ($A$1,$B15,HH$1)} -> #NAME? | HP15: =+MIN(D15:F15) -> #NAME? | HQ15: =+MIN(G15:I15) -> #NAME? | HR15: =+MIN(J15:L15) -> #NAME? | HS15: =+MIN(M15:O15) -> #NAME? | HT15: =+MIN(P15:R15) -> #NAME? | HU15: =+MIN(S15:U15) -> #NAME? | HV15: =+MIN(V15:X15) -> #NAME? | HW15: =+MIN(Y15:AA15) -> #NAME? | HX15: =+MIN(AB15:AD15) -> #NAME? | HY15: =+MIN(AE15:AG15) -> #NAME? | HZ15: =+MIN(AH15:AJ15) -> #NAME? | IA15: =+MIN(AK15:AM15) -> #NAME? | IB15: =+MIN(AN15:AP15) -> #NAME? | IC15: =+MIN(AQ15:AS15) -> #NAME? | ID15: =+MIN(AT15:AV15) -> #NAME? | IE15: =+MIN(AW15:AY15) -> #NAME? | IF15: =+MIN(AZ15:BB15) -> #NAME? | IG15: =+MIN(BC15:BE15) -> #NAME? | IH15: =+MIN(BF15:BH15) -> #NAME? | II15: =+MIN(BI15:BK15) -> #NAME? | IJ15: =+MIN(BL15:BN15) -> #NAME? | IK15: =+MIN(BO15:BQ15) -> #NAME? | IL15: =+MIN(BR15:BT15) -> #NAME? | IM15: =+MIN(BU15:BW15) -> #NAME? | IN15: =+MIN(BX15:BZ15) -> #NAME? | IO15: =+MIN(CA15:CC15) -> #NAME? | IP15: =+MIN(CD15:CF15) -> #NAME? | IQ15: =+MIN(CG15:CI15) -> #NAME? | IR15: =+MIN(CJ15:CL15) -> #NAME? | IS15: =+MIN(CM15:CO15) -> #NAME? | IT15: =+MIN(CP15:CR15) -> #NAME? | IU15: =+MIN(CS15:CU15) -> #NAME? | IV15: =+MIN(CV15:CX15) -> #NAME? | IW15: =+MIN(CY15:DA15) -> #NAME? | IX15: =+MIN(DB15:DD15) -> #NAME? | IY15: =+MIN(DE15:DG15) -> #NAME? | IZ15: =+MIN(DH15:DJ15) -> #NAME? | JA15: =+MIN(DK15:DM15) -> #NAME? | JB15: =+MIN(DN15:DP15) -> #NAME? | JC15: =+MIN(DQ15:DS15) -> #NAME? | JD15: =+MIN(DT15:DV15) -> #NAME? | JE15: =+MIN(DW15:DY15) -> #NAME? | JF15: =+MIN(DZ15:EB15) -> #NAME? | JG15: =+MIN(EC15:EE15) -> #NAME? | JH15: =+MIN(EF15:EH15) -> #NAME? | JI15: =+MIN(EI15:EK15) -> #NAME? | JJ15: =+MIN(EL15:EN15) -> #NAME? | JK15: =MIN(EO15:EQ15) -> #NAME? | JL15: =MIN(ER15:ET15) -> #NAME? | JM15: =MIN(EU15:EW15) -> #NAME? | JN15: =MIN(EX15:EZ15) -> #NAME? | JO15: =MIN(FA15:FC15) -> #NAME? | JP15: =MIN(FD15:FF15) -> #NAME? | JQ15: =MIN(FG15:FI15) -> #NAME? | JR15: =MIN(FJ15:FL15) -> #NAME? | JS15: =MIN(FM15:FO15) -> #NAME? | JT15: =MIN(FP15:FR15) -> #NAME? | JU15: =MIN(FS15:FU15) -> #NAME? | JV15: =MIN(FV15:FX15) -> #NAME? | JW15: =MIN(FY15:GA15) -> #NAME? | JX15: =MIN(GB15:GD15) -> #NAME? | JY15: =MIN(GE15:GG15) -> #NAME? | JZ15: =MIN(GH15:GJ15) -> #NAME? | KA15: =MIN(GK15:GM15) -> #NAME? | KB15: =MIN(GN15:GP15) -> #NAME? | KC15: =MIN(GQ15:GS15) -> #NAME? | KD15: =MIN(GT15:GV15) -> #NAME? | KE15: =MIN(GW15:GY15) -> #NAME? | KF15: =MIN(GZ15:HB15) -> #NAME? | KG15: =MIN(HC15:HE15) -> #NAME? | KH15: =MIN(HF15:HH15) -> #NAME?
A16: Close | B16: BMONTH_CLOSE | C16: {=_xll.EQNXTDZ($A$1,$B16,C$1)} -> #NAME? | D16: {=_xll.EQNXTDZ($A$1,$B16,D$1)} -> #NAME? | E16: {=_xll.EQNXTDZ($A$1,$B16,E$1)} -> #NAME? | F16: {=_xll.EQNXTDZ($A$1,$B16,F$1)} -> #NAME? | G16: {=_xll.EQNXTDZ($A$1,$B16,G$1)} -> #NAME? | H16: {=_xll.EQNXTDZ($A$1,$B16,H$1)} -> #NAME? | I16: {=_xll.EQNXTDZ($A$1,$B16,I$1)} -> #NAME? | J16: {=_xll.EQNXTDZ($A$1,$B16,J$1)} -> #NAME? | ... HH16: {=_xll.EQNXTDZ($A$1,$B16,HH$1)} -> #NAME? | HP16: =+F16 -> #NAME? | HQ16: =+I16 -> #NAME? | HR16: =+L16 -> #NAME? | HS16: =+O16 -> #NAME? | HT16: =+R16 -> #NAME? | HU16: =+U16 -> #NAME? | HV16: =+X16 -> #NAME? | HW16: =+AA16 -> #NAME? | HX16: =+AD16 -> #NAME? | HY16: =+AG16 -> #NAME? | HZ16: =+AJ16 -> #NAME? | IA16: =+AM16 -> #NAME? | IB16: =+AP16 -> #NAME? | IC16: =+AS16 -> #NAME? | ID16: =+AV16 -> #NAME? | IE16: =+AY16 -> #NAME? | IF16: =+BB16 -> #NAME? | IG16: =+BE16 -> #NAME? | IH16: =+BH16 -> #NAME? | II16: =+BK16 -> #NAME? | IJ16: =+BN16 -> #NAME? | IK16: =+BQ16 -> #NAME? | IL16: =+BT16 -> #NAME? | IM16: =+BW16 -> #NAME? | IN16: =+BZ16 -> #NAME? | IO16: =+CC16 -> #NAME? | IP16: =+CF16 -> #NAME? | IQ16: =+CI16 -> #NAME? | IR16: =+CL16 -> #NAME? | IS16: =+CO16 -> #NAME? | IT16: =+CR16 -> #NAME? | IU16: =+CU16 -> #NAME? | IV16: =+CX16 -> #NAME? | IW16: =+DA16 -> #NAME? | IX16: =+DD16 -> #NAME? | IY16: =+DG16 -> #NAME? | IZ16: =+DJ16 -> #NAME? | JA16: =+DM16 -> #NAME? | JB16: =+DP16 -> #NAME? | JC16: =+DS16 -> #NAME? | JD16: =+DV16 -> #NAME? | JE16: =+DY16 -> #NAME? | JF16: =+EB16 -> #NAME? | JG16: =+EE16 -> #NAME? | JH16: =+EH16 -> #NAME? | JI16: =+EK16 -> #NAME? | JJ16: =+EN16 -> #NAME? | JK16: =EQ16 -> #NAME? | JL16: =ET16 -> #NAME? | JM16: =EW16 -> #NAME? | JN16: =EZ16 -> #NAME? | JO16: =FC16 -> #NAME? | JP16: =FF16 -> #NAME? | JQ16: =FI16 -> #NAME? | JR16: =FL16 -> #NAME? | JS16: =FO16 -> #NAME? | JT16: =FR16 -> #NAME? | JU16: =FU16 -> #NAME? | JV16: =FX16 -> #NAME? | JW16: =GA16 -> #NAME? | JX16: =GD16 -> #NAME? | JY16: =GG16 -> #NAME? | JZ16: =GJ16 -> #NAME? | KA16: =GM16 -> #NAME? | KB16: =GP16 -> #NAME? | KC16: =GS16 -> #NAME? | KD16: =GV16 -> #NAME? | KE16: =GY16 -> #NAME? | KF16: =HB16 -> #NAME? | KG16: =HE16 -> #NAME? | KH16: =HH16 -> #NAME?
A19: High | HP19: =+IF(HP14=0,HP7,HP14) -> #NAME? | HQ19: =+IF(HQ14=0,HQ7,HQ14) -> #NAME? | HR19: =+IF(HR14=0,HR7,HR14) -> #NAME? | HS19: =+IF(HS14=0,HS7,HS14) -> #NAME? | HT19: =+IF(HT14=0,HT7,HT14) -> #NAME? | HU19: =+IF(HU14=0,HU7,HU14) -> #NAME? | HV19: =+IF(HV14=0,HV7,HV14) -> #NAME? | HW19: =+IF(HW14=0,HW7,HW14) -> #NAME? | ... KH19: =+IF(KH14=0,KH7,KH14) -> #NAME?
A20: Low | HP20: =+IF(HP15=0,HP8,HP15) -> #NAME? | HQ20: =+IF(HQ15=0,HQ8,HQ15) -> #NAME? | HR20: =+IF(HR15=0,HR8,HR15) -> #NAME? | HS20: =+IF(HS15=0,HS8,HS15) -> #NAME? | HT20: =+IF(HT15=0,HT8,HT15) -> #NAME? | HU20: =+IF(HU15=0,HU8,HU15) -> #NAME? | HV20: =+IF(HV15=0,HV8,HV15) -> #NAME? | HW20: =+IF(HW15=0,HW8,HW15) -> #NAME? | ... KH20: =+IF(KH15=0,KH8,KH15) -> #NAME?
A21: Close | HP21: =+IF(HP16=0,HP9,HP16) -> #NAME? | HQ21: =+IF(HQ16=0,HQ9,HQ16) -> #NAME? | HR21: =+IF(HR16=0,HR9,HR16) -> #NAME? | HS21: =+IF(HS16=0,HS9,HS16) -> #NAME? | HT21: =+IF(HT16=0,HT9,HT16) -> #NAME? | HU21: =+IF(HU16=0,HU9,HU16) -> #NAME? | HV21: =+IF(HV16=0,HV9,HV16) -> #NAME? | HW21: =+IF(HW16=0,HW9,HW16) -> #NAME? | ... KH21: =+IF(KH16=0,KH9,KH16) -> #NAME?

Sheet 4_Axis Bank Ltd._Balance Sheet
A1: 132215
A3: =_xll.EQNXTV("Company-Profit And Loss",A1,"Crores/INR/40/Asc/N2",C3,D3,E3,F3,G3,H3) -> #NAME? | C3: Standalone | D3: Abridged | E3: Actual | F3: 202503 | G3: Reported | H3: Gross Sales
A5: Profit And Loss - Standalone | C5: Axis Bank Ltd. | E5: INR Crores
A6: DESCRIPTION | B6: 34759 | C6: 35490 | D6: 35855 | E6: 36220 | F6: 36586 | G6: 36951 | H6: 37316 | I6: 37681 | J6: 38047 | K6: 38412 | L6: 38777 | M6: 39142 | N6: 39508 | O6: 39873 | P6: 40238 | Q6: 40603 | R6: 40969 | S6: 41334 | T6: 41699 | U6: 42064 | V6: 42430 | W6: 42795 | X6: 43160 | Y6: 43525 | Z6: 43891 | AA6: 44256 | AB6: 44621 | AC6: 44986 | AD6: 45352 | AE6: 45717
A8: No of Months | B8: 12 | C8: 12 | D8: 12 | E8: 12 | F8: 12 | G8: 12 | H8: 12 | I8: 12 | J8: 12 | K8: 12 | L8: 12 | M8: 12 | N8: 12 | O8: 12 | P8: 12 | Q8: 12 | R8: 12 | S8: 12 | T8: 12 | U8: 12 | V8: 12 | W8: 12 | X8: 12 | Y8: 12 | Z8: 12 | AA8: 12 | AB8: 12 | AC8: 12 | AD8: 12 | AE8: 12
A9: I. INCOME
A10: Interest Earned | B10: 29.1719 | C10: 157.6474 | D10: 255.61 | E10: 373.281 | F10: 483.2599 | G10: 889.6314 | H10: 1178.53 | I10: 1464.81 | J10: 1598.543 | K10: 1924.1582 | L10: 2888.7904 | M10: 4461.6552 | N10: 7005.3151 | O10: 10835.486 | P10: 11638.022 | Q10: 15154.806 | R10: 21994.647 | S10: 27182.574 | T10: 30641.155 | U10: 35478.598 | V10: 40988.036 | W10: 44542.158 | X10: 45780.312 | Y10: 54985.771 | Z10: 62635.157 | AA10: 63346.232 | AB10: 67376.83 | AC10: 85163.766 | AD10: 109368.63 | AE10: 122677.04
A11: Other Income | B11: 1.8346 | C11: 24.1029 | D11: 60.8991 | E11: 46.6287 | F11: 91.1659 | G11: 163.0001 | H11: 415.87 | I11: 410.47 | J11: 540.1456 | K11: 415.8196 | L11: 729.6344 | M11: 1010.1113 | N11: 1795.4888 | O11: 2896.8781 | P11: 3945.7819 | Q11: 4632.1338 | R11: 5420.2163 | S11: 6551.1063 | T11: 7405.2247 | U11: 8365.0458 | V11: 9371.4644 | W11: 11691.311 | X11: 10967.086 | Y11: 13130.339 | Z11: 15536.561 | AA11: 12263.599 | AB11: 15220.545 | AC11: 16143.419 | AD11: 22441.955 | AE11: 25257.056
A12: Total Income | B12: 31.0065 | C12: 181.7503 | D12: 316.5091 | E12: 419.9097 | F12: 574.4258 | G12: 1052.6315 | H12: 1594.4 | I12: 1875.28 | J12: 2138.6886 | K12: 2339.9778 | L12: 3618.4248 | M12: 5471.7665 | N12: 8800.8039 | O12: 13732.364 | P12: 15583.803 | Q12: 19786.94 | R12: 27414.864 | S12: 33733.681 | T12: 38046.38 | U12: 43843.643 | V12: 50359.501 | W12: 56233.469 | X12: 56747.399 | Y12: 68116.11 | Z12: 78171.718 | AA12: 75609.831 | AB12: 82597.375 | AC12: 101307.19 | AD12: 131810.59 | AE12: 147934.1
A13: II. EXPENDITURE
A14: Interest Expended | B14: 14.0985 | C14: 122.0736 | D14: 222.1898 | E14: 300.6328 | F14: 392.8564 | G14: 791.3638 | H14: 980 | I14: 1142.41 | J14: 1021.4487 | K14: 1192.9808 | L14: 1810.556 | M14: 2993.3172 | N14: 4419.9617 | O14: 7149.2742 | P14: 6633.5261 | Q14: 8591.823 | R14: 13976.902 | S14: 17516.311 | T14: 18689.522 | U14: 21254.46 | V14: 24155.068 | W14: 26449.042 | X14: 27162.582 | Y14: 33277.597 | Z14: 37428.954 | AA14: 34107.11 | AB14: 34244.613 | AC14: 42218.021 | AD14: 59474.146 | AE14: 68329.221
A15: Operating Expenses | B15: 7.8485 | C15: 26.6971 | D15: 39.7558 | E15: 51.0262 | F15: 65.4009 | G15: 128.7637 | H15: 207.12 | I15: 322.85 | J15: 419.2055 | K15: 581.3789 | L15: 814.0507 | M15: 1214.5984 | N15: 2154.9269 | O15: 2858.2127 | P15: 3709.7223 | Q15: 4779.4281 | R15: 6007.0995 | S15: 6914.2375 | T15: 7900.7739 | U15: 9203.7456 | V15: 10100.819 | W15: 12199.905 | X15: 13990.34 | Y15: 15833.408 | Z15: 17304.624 | AA15: 18375.149 | AB15: 23610.754 | AC15: 39298.538 | AD15: 35213.284 | AE15: 37499.943
A16: Provisions and Contingencies | B16: 3.077 | C16: 17.7587 | D16: 25.2068 | E16: 21.9707 | F16: 37.4932 | G16: 28.0513 | H16: 193.91 | I16: 108.73 | J16: 268.6724 | K16: 51.0104 | L16: 262.3844 | M16: 267.3626 | N16: 579.4163 | O16: 939.3984 | P16: 1388.8417 | Q16: 1279.2779 | R16: 1142.6664 | S16: 1750.0592 | T16: 2107.0376 | U16: 2327.6761 | V16: 3709.9119 | W16: 12116.962 | X16: 15472.906 | Y16: 12031.017 | Z16: 18533.915 | AA16: 14321.721 | AB16: 7359.4491 | AC16: 2884.7777 | AD16: 4063.0948 | AE16: 7758.3504
A17: Profit Before Tax | B17: 5.9825 | C17: 15.2209 | D17: 29.3567 | E17: 46.28 | F17: 78.6753 | G17: 104.4527 | H17: 213.37 | I17: 301.29 | J17: 429.362 | K17: 514.6077 | L17: 731.4337 | M17: 996.4883 | N17: 1646.499 | O17: 2785.4784 | P17: 3851.7133 | Q17: 5136.4106 | R17: 6288.1954 | S17: 7553.0729 | T17: 9349.0466 | U17: 11057.762 | V17: 12393.703 | W17: 5467.5592 | X17: 121.5713 | Y17: 6974.0883 | Z17: 4904.2254 | AA17: 8805.8506 | AB17: 17382.558 | AC17: 16905.849 | AD17: 33060.063 | AE17: 34346.582
A18: Taxes | B18: 3.6733 | C18: 0 | D18: 11.7398 | E18: 15.21 | F18: 27.75 | G18: 18.33 | H18: 79.23 | I18: 109.11 | J18: 151.05 | K18: 180.03 | L18: 246.35 | M18: 337.46 | N18: 575.47 | O18: 970.12 | P18: 1337.18 | Q18: 1747.92 | R18: 2045.99 | S18: 2373.64 | T18: 3131.38 | U18: 3699.94 | V18: 4170.04 | W18: 1788.28 | X18: -154.11 | Y18: 2297.48 | Z18: 3277.01 | AA18: 2217.35 | AB18: 4357.08 | AC18: 7326.17 | AD18: 8198.63 | AE18: 7973.1
A19: Total | B19: 28.6973 | C19: 166.5294 | D19: 298.8922 | E19: 388.8397 | F19: 523.5005 | G19: 966.5088 | H19: 1460.26 | I19: 1683.1 | J19: 1860.3766 | K19: 2005.4001 | L19: 3133.3411 | M19: 4812.7382 | N19: 7729.7749 | O19: 11917.005 | P19: 13069.27 | Q19: 16398.449 | R19: 23172.658 | S19: 28554.248 | T19: 31828.714 | U19: 36485.821 | V19: 42135.838 | W19: 52554.189 | X19: 56471.717 | Y19: 63439.502 | Z19: 76544.503 | AA19: 69021.33 | AB19: 69571.897 | AC19: 91727.507 | AD19: 106949.15 | AE19: 121560.61
A20: III. PROFIT AND LOSS
A21: Profit After Tax | B21: 2.3092 | C21: 15.2209 | D21: 17.6169 | E21: 31.07 | F21: 50.9253 | G21: 86.1227 | H21: 134.14 | I21: 192.18 | J21: 278.312 | K21: 334.5777 | L21: 485.0837 | M21: 659.0283 | N21: 1071.029 | O21: 1815.3584 | P21: 2514.5333 | Q21: 3388.4906 | R21: 4242.2054 | S21: 5179.4329 | T21: 6217.6666 | U21: 7357.8223 | V21: 8223.6628 | W21: 3679.2792 | X21: 275.6813 | Y21: 4676.6083 | Z21: 1627.2154 | AA21: 6588.5006 | AB21: 13025.478 | AC21: 9579.6785 | AD21: 24861.433 | AE21: 26373.482
A22: Extra items | C22: 0 | D22: -1.0307 | L22: 0 | M22: 0 | N22: 0 | O22: 0 | P22: 0 | R22: 0
A23: Profit brought forward | C23: 10.8176 | D23: 20.5338 | E23: 30.7108 | F23: 41.9893 | G23: 52.598 | H23: 74.37 | I23: 78.64 | J23: 122.4667 | K23: 182.1024 | L23: 197.4076 | M23: 731.039 | N23: 1029.074 | O23: 1553.8689 | P23: 2348.0865 | Q23: 3427.4337 | R23: 4969.7707 | S23: 7329.4476 | T23: 10029.262 | U23: 13501.446 | V23: 17623.491 | W23: 23766.456 | X23: 24448.327 | Y23: 23043.052 | Z23: 24322.995 | AA23: 26190.455 | AB23: 29985.281 | AC23: 38100.659 | AD23: 44144.93 | AE23: 60254.056
A24: Adjustments to PAT | C24: -0.2039 | D24: -0.5614 | E24: 0.0124 | F24: 0.1358 | G24: 0.0014 | H24: 2.39 | M24: -31.8028
A25: Total Profit & Loss | B25: 2.3092 | C25: 25.8346 | D25: 37.5893 | E25: 61.7932 | F25: 93.0504 | G25: 138.7221 | H25: 210.9 | I25: 270.82 | J25: 400.7787 | K25: 516.6801 | L25: 682.4913 | M25: 1358.2645 | N25: 2100.103 | O25: 3369.2273 | P25: 4862.6198 | Q25: 6815.9243 | R25: 9211.9761 | S25: 12508.88 | T25: 16246.929 | U25: 20859.268 | V25: 25847.154 | W25: 27445.735 | X25: 24724.009 | Y25: 27719.66 | Z25: 25950.211 | AA25: 32778.955 | AB25: 43010.759 | AC25: 47680.338 | AD25: 69006.363 | AE25: 86627.538
A26: IV. APPROPRIATIONS | B26: 2.3092 | C26: 25.8346 | D26: 36.5586 | E26: 61.7932 | F26: 93.0504 | G26: 138.7221 | H26: 210.9 | I26: 270.82 | J26: 400.7787 | K26: 516.6801 | L26: 682.4913 | M26: 1358.2645 | N26: 2100.103 | O26: 3369.2273 | P26: 4862.6198 | Q26: 6815.9243 | R26: 9211.9761 | S26: 12508.88 | T26: 16246.929 | U26: 20859.268 | V26: 25847.154 | W26: 27445.735 | X26: 24724.009 | Y26: 27719.66 | Z26: 25950.211 | AA26: 32778.955 | AB26: 43010.759 | AC26: 47680.338 | AD26: 69006.363 | AE26: 86627.538
A27: Equity Dividend % | E27: 10 | F27: 12 | G27: 15 | H27: 20 | I27: 22 | J27: 25 | K27: 28 | L27: 35 | M27: 45 | N27: 60 | O27: 100 | P27: 120 | Q27: 140 | R27: 160 | S27: 180 | T27: 200 | U27: 230 | V27: 250 | W27: 250 | Y27: 50 | AB27: 50 | AC27: 50 | AD27: 50 | AE27: 50
A28: Earnings Per Share(Calculated) | B28: 0.20079983 | C28: 1.3235554 | D28: 1.531903 | E28: 2.3555153 | F28: 3.8608085 | G28: 6.5292351 | H28: 6.9933789 | I28: 8.3487554 | J28: 12.017932 | K28: 12.219945 | L28: 17.4058 | M28: 23.4004 | N28: 29.9413 | O28: 50.5664 | P28: 62.0606 | Q28: 82.5362 | R28: 102.6662 | S28: 110.6824 | T28: 132.3345 | U28: 31.0388 | V28: 34.5121 | W28: 15.3621 | X28: 1.0741 | Y28: 18.1853 | Z28: 5.7668 | AA28: 21.5047 | AB28: 42.4318 | AC28: 31.134674 | AD28: 80.5471 | AE28: 85.148
A29: Adjusted EPS | B29: 0.040159965 | C29: 0.26471107 | D29: 0.3063806 | E29: 0.47110305 | F29: 0.77216171 | G29: 1.305847 | H29: 1.3986758 | I29: 1.6697511 | J29: 2.4035865 | K29: 2.443989 | L29: 3.4812 | M29: 4.6801 | N29: 5.9883 | O29: 10.1133 | P29: 12.4121 | Q29: 16.5072 | R29: 20.5332 | S29: 22.1365 | T29: 26.4669 | U29: 31.0388 | V29: 34.5121 | W29: 15.3621 | X29: 1.0741 | Y29: 18.1853 | Z29: 5.7668 | AA29: 21.5047 | AB29: 42.4318 | AC29: 31.1347 | AD29: 80.5471 | AE29: 85.148
A30: EPS - Basic (Reported) | E30: 2.36 | F30: 3.86 | G30: 6.53 | H30: 6.99 | I30: 8.35 | J30: 12.02 | K30: 12.22 | L30: 17.45 | M30: 23.5 | N30: 32.15 | O30: 50.61 | P30: 65.78 | Q30: 82.95 | R30: 102.94 | S30: 119.67 | T30: 26.51 | U30: 31.18 | V30: 34.59 | W30: 15.4 | X30: 1.13 | Y30: 18.2 | Z30: 5.99 | AA30: 22.15 | AB30: 42.48 | AC30: 31.17 | AD30: 80.67 | AE30: 85.28
A31: EPS - Diluted (Reported) | Q31: 81.61 | R31: 102.2 | U31: 30.85 | V31: 34.4 | X31: 1.12 | Y31: 18.09 | Z31: 5.97 | AA31: 22.09 | AB31: 42.35 | AC31: 31.02 | AD31: 80.1 | AE31: 84.77
