Workbook

Sheet Template
A1: =+'Annual Raw'!C3 -> Canara Bank | B1: =+EOMONTH(C1,-12) -> 36981 | C1: =+EOMONTH(D1,-12) -> 37346 | D1: =+EOMONTH(E1,-12) -> 37711 | E1: =+EOMONTH(F1,-12) -> 38077 | F1: =+EOMONTH(G1,-12) -> 38442 | G1: =+EOMONTH(H1,-12) -> 38807 | H1: =+EOMONTH(I1,-12) -> 39172 | I1: =+EOMONTH(J1,-12) -> 39538 | ... N1: =+EOMONTH(O1,-12) -> 41364 | O1: 41699 | P1: 42064 | Q1: 42430 | R1: 42795 | S1: 43160 | T1: 43525 | U1: 43891 | V1: 44256 | W1: 44621 | X1: 44986 | Y1: 45352 | Z1: 45717 | AA1: 46082 | AB1: 46447 | AC1: 46813 | AD1: 47178 | AE1: 47543 | AG1: Quarterly | AH1: 42185 | AI1: =+EOMONTH(AH1,3) -> 42277 | AJ1: =+EOMONTH(AI1,3) -> 42369 | AK1: =+EOMONTH(AJ1,3) -> 42460 | AL1: =+EOMONTH(AK1,3) -> 42551 | AM1: =+EOMONTH(AL1,3) -> 42643 | AN1: =+EOMONTH(AM1,3) -> 42735 | AO1: =+EOMONTH(AN1,3) -> 42825 | AP1: =+EOMONTH(AO1,3) -> 42916 | ... CO1: =+EOMONTH(CN1,3) -> 47573 | CS1: 46022 | CW1: HISTORICAL ESTIMATES | CX1: 46082
A2: Presentation Data (Start)
A4: Average eq | D4: =AVERAGE(C104:D104) -> 3810.1617 | E4: =AVERAGE(D104:E104) -> 4700.2357 | F4: =AVERAGE(E104:F104) -> 5680.3001 | G4: =AVERAGE(F104:G104) -> 6620.5965 | H4: =AVERAGE(G104:H104) -> 8743.111 | I4: =AVERAGE(H104:I104) -> 10427.239 | J4: =AVERAGE(I104:J104) -> 11354.131 | K4: =AVERAGE(J104:K104) -> 13439.776 | ... X4: =AVERAGE(W104:X104) -> 69859.246 | Y4: =+AVERAGE(BN4:BQ4) -> 80625.276 | Z4: =+AVERAGE(BR4:BU4) -> 95347.747 | AA4: =+AVERAGE(BV4:BY4) -> 108156.54 | AB4: =+AVERAGE(BZ4:CC4) -> 123100.66 | AC4: =+AVERAGE(CD4:CG4) -> 143148.07 | AD4: =+AVERAGE(CH4:CK4) -> 164224.27 | AE4: =+AVERAGE(CL4:CO4) -> 186884.59 | AH4: =AVERAGE(AG104:AH104) -> 33892.79 | AI4: =AVERAGE(AH104:AI104) -> 34686.46 | AJ4: =AVERAGE(AI104:AJ104) -> 35506.175 | AK4: =AVERAGE(AJ104:AK104) -> 33567.71 | AL4: =AVERAGE(AK104:AL104) -> 31705.9 | AM4: =AVERAGE(AL104:AM104) -> 31962.705 | AN4: =AVERAGE(AM104:AN104) -> 32272.755 | AO4: =AVERAGE(AN104:AO104) -> 33057.12 | ... CO4: =AVERAGE(CN104:CO104) -> 195884.77 | CS4: 110653.27
A5: Average assets | D5: =AVERAGE(C111:D111) -> 72053.188 | E5: =AVERAGE(D111:E111) -> 84344.285 | F5: =AVERAGE(E111:F111) -> 97685.068 | G5: =AVERAGE(F111:G111) -> 113490.17 | H5: =AVERAGE(G111:H111) -> 139135.54 | I5: =AVERAGE(H111:I111) -> 160699.97 | J5: =AVERAGE(I111:J111) -> 190095.69 | K5: =AVERAGE(J111:K111) -> 235432.51 | ... X5: =AVERAGE(W111:X111) -> 1254860.5 | Y5: =+AVERAGE(BN5:BQ5) -> 1392055.1 | Z5: =+AVERAGE(BR5:BU5) -> 1537863.1 | AA5: =+AVERAGE(BV5:BY5) -> 1735857.6 | AB5: =+AVERAGE(BZ5:CC5) -> 1936531.8 | AC5: =+AVERAGE(CD5:CG5) -> 2122534.6 | AD5: =+AVERAGE(CH5:CK5) -> 2326382.3 | AE5: =+AVERAGE(CL5:CO5) -> 2550111.4 | AH5: =AVERAGE(AG111:AH111) -> 529674.33 | AI5: =AVERAGE(AH111:AI111) -> 537262.43 | AJ5: =AVERAGE(AI111:AJ111) -> 548170.79 | AK5: =AVERAGE(AJ111:AK111) -> 544879.56 | AL5: =AVERAGE(AK111:AL111) -> 531967.85 | AM5: =AVERAGE(AL111:AM111) -> 533800.95 | AN5: =AVERAGE(AM111:AN111) -> 558001.03 | AO5: =AVERAGE(AN111:AO111) -> 571266.06 | ... CO5: =AVERAGE(CN111:CO111) -> 2608316.3 | CS5: 1723696.7
A7: Growth (%) | D7: =+D5/C5-1 -> #DIV/0! | E7: =+E5/D5-1 -> 0.17058366 | F7: =+F5/E5-1 -> 0.15817057 | G7: =+G5/F5-1 -> 0.16179645 | H7: =+H5/G5-1 -> 0.22597002 | I7: =+I5/H5-1 -> 0.15498863 | J7: =+J5/I5-1 -> 0.18292299 | K7: =+K5/J5-1 -> 0.23849473 | ... AE7: =+AE5/AD5-1 -> 0.096170408 | AM7: =AM5/AI5-1 -> -0.0064428012 | AN7: =AN5/AJ5-1 -> 0.017932814 | AO7: =AO5/AK5-1 -> 0.048426288 | AP7: =AP5/AL5-1 -> 0.064162186 | AQ7: =AQ5/AM5-1 -> 0.053384253 | AR7: =AR5/AN5-1 -> 0.026974108 | AS7: =AS5/AO5-1 -> 0.036672116 | AT7: =AT5/AP5-1 -> 0.062433626 | ... CO7: =CO5/CK5-1 -> 0.096228994 | CS7: 0.11228322
A9: Leverage | D9: =D110/D104 -> 17.399767 | E9: =E110/E104 -> 16.585182 | F9: =F110/F104 -> 15.863605 | G9: =G110/G104 -> 16.380425 | H9: =H110/H104 -> 13.903419 | I9: =I110/I104 -> 14.912601 | J9: =J110/J104 -> 16.456197 | K9: =K110/K104 -> 16.568674 | ... AE9: =AE110/AE104 -> 12.264108 | AH9: =AH110/AH104 -> 14.627935 | AI9: =AI110/AI104 -> 14.356497 | AJ9: =AJ110/AJ104 -> 14.520872 | AK9: =AK110/AK104 -> 16.032075 | AL9: =AL110/AL104 -> 15.525959 | AM9: =AM110/AM104 -> 15.873851 | AN9: =AN110/AN104 -> 16.70246 | AO9: =AO110/AO104 -> 15.875619 | ... CO9: =CO110/CO104 -> 12.264108 | CS9: 14.219563
A12: Interest Income | D12: =D29/C5 -> #DIV/0! | E12: =E29/D5 -> 0.097246505 | F12: =F29/E5 -> 0.089774533 | G12: =G29/F5 -> 0.089179569 | H12: =H29/G5 -> 0.10013692 | I12: =I29/H5 -> 0.10206405 | J12: =J29/I5 -> 0.10652805 | K12: =K29/J5 -> 0.09864486 | ... AE12: =AE29/AD5 -> 0.081566124 | AH12: =AH29/AG5 -> #DIV/0! | AI12: =AI29/AH5 -> 0.021272505 | AJ12: =AJ29/AI5 -> 0.020254664 | AK12: =AK29/AJ5 -> 0.0195795 | AL12: =AL29/AK5 -> 0.018722853 | AM12: =AM29/AL5 -> 0.019560111 | AN12: =AN29/AM5 -> 0.019272483 | AO12: =AO29/AN5 -> 0.018804481 | ... BY12: =BY29/BX5 -> 0.018142501 | BZ12: =+AVERAGE(BV12:BY12)*1.02 -> 0.019146751 | CA12: =+AVERAGE(BW12:BZ12)*1.02 -> 0.019098309 | CB12: =+AVERAGE(BX12:CA12)*1.01 -> 0.018961501 | CC12: =+AVERAGE(BY12:CB12)*1.01 -> 0.019025638 | CD12: =+AVERAGE(BZ12:CC12)*1.01 -> 0.01924863 | CE12: =+AVERAGE(CA12:CD12)*1.01 -> 0.019274355 | CF12: =+AVERAGE(CB12:CE12) -> 0.019127531 | CG12: =+AVERAGE(CC12:CF12) -> 0.019169038 | CH12: =+AVERAGE(CD12:CG12)*0.99 -> 0.01901284 | CI12: =+AVERAGE(CE12:CH12)*0.99 -> 0.018954482 | CJ12: =+AVERAGE(CF12:CI12) -> 0.019065973 | CK12: =+AVERAGE(CG12:CJ12) -> 0.019050583 | CL12: =+AVERAGE(CH12:CK12) -> 0.019020969 | CM12: =+AVERAGE(CI12:CL12) -> 0.019023002 | CN12: =+AVERAGE(CJ12:CM12) -> 0.019040132 | CO12: =+AVERAGE(CK12:CN12) -> 0.019033671 | CS12: 0.018898587
A13: Interest Expenses | D13: =D30/C5 -> #DIV/0! | E13: =E30/D5 -> 0.060019072 | F13: =F30/E5 -> 0.052422038 | G13: =G30/F5 -> 0.052515773 | H13: =H30/G5 -> 0.06465521 | I13: =I30/H5 -> 0.0766371 | J13: =J30/I5 -> 0.077170185 | K13: =K30/J5 -> 0.068762362 | ... AE13: =AE30/AD5 -> 0.056908294 | AH13: =AH30/AG5 -> #DIV/0! | AI13: =AI30/AH5 -> 0.016276039 | AJ13: =AJ30/AI5 -> 0.016110321 | AK13: =AK30/AJ5 -> 0.015249171 | AL13: =AL30/AK5 -> 0.014488156 | AM13: =AM30/AL5 -> 0.01496895 | AN13: =AN30/AM5 -> 0.014750573 | AO13: =AO30/AN5 -> 0.01395105 | ... BY13: =BY30/BX5 -> 0.012553521 | BZ13: =+AVERAGE(BV13:BY13)*1.01 -> 0.013379648 | CA13: =+AVERAGE(BW13:BZ13)*1.01 -> 0.013294244 | CB13: =+AVERAGE(BX13:CA13)*1.01 -> 0.013262007 | CC13: =+AVERAGE(BY13:CB13)*1.01 -> 0.013253579 | CD13: =+AVERAGE(BZ13:CC13) -> 0.01329737 | CE13: =+AVERAGE(CA13:CD13) -> 0.0132768 | CF13: =+AVERAGE(CB13:CE13) -> 0.013272439 | CG13: =+AVERAGE(CC13:CF13) -> 0.013275047 | CH13: =+AVERAGE(CD13:CG13) -> 0.013280414 | CI13: =+AVERAGE(CE13:CH13) -> 0.013276175 | CJ13: =+AVERAGE(CF13:CI13) -> 0.013276019 | CK13: =+AVERAGE(CG13:CJ13) -> 0.013276913 | ... CO13: =+AVERAGE(CK13:CN13) -> 0.013276912 | CS13: 0.013421914
A14: NII | D14: =D12-D13 -> #DIV/0! | E14: =E12-E13 -> 0.037227433 | F14: =F12-F13 -> 0.037352495 | G14: =G12-G13 -> 0.036663796 | H14: =H12-H13 -> 0.035481715 | I14: =I12-I13 -> 0.025426951 | J14: =J12-J13 -> 0.02935786 | K14: =K12-K13 -> 0.029882498 | ... AE14: =AE12-AE13 -> 0.02465783 | AH14: =AH12-AH13 -> #DIV/0! | AI14: =AI12-AI13 -> 0.0049964664 | AJ14: =AJ12-AJ13 -> 0.0041443434 | AK14: =AK12-AK13 -> 0.0043303293 | AL14: =AL12-AL13 -> 0.0042346973 | AM14: =AM12-AM13 -> 0.0045911609 | AN14: =AN12-AN13 -> 0.0045219103 | AO14: =AO12-AO13 -> 0.0048534319 | ... CO14: =CO12-CO13 -> 0.0057567592 | CS14: 0.005476673
A15: Others income | D15: =D32/C5 -> #DIV/0! | E15: =E32/D5 -> 0.028769209 | F15: =F32/E5 -> 0.018303876 | G15: =G32/F5 -> 0.014101591 | H15: =H32/G5 -> 0.012784806 | I15: =I32/H5 -> 0.015904437 | J15: =J32/I5 -> 0.014382163 | K15: =K32/J5 -> 0.01503402 | ... AE15: =AE32/AD5 -> 0.013468627 | AH15: =AH32/AG5 -> #DIV/0! | AI15: =AI32/AH5 -> 0.0022852722 | AJ15: =AJ32/AI5 -> 0.0021750265 | AK15: =AK32/AJ5 -> 0.0025233559 | AL15: =AL32/AK5 -> 0.0029082574 | AM15: =AM32/AL5 -> 0.0033493941 | AN15: =AN32/AM5 -> 0.0033564946 | AO15: =AO32/AN5 -> 0.0042944007 | ... BY15: =BY32/BX5 -> 0.0027491164 | BZ15: =+AVERAGE(BV15:BY15)*0.92 -> 0.0036799056 | CA15: =+AVERAGE(BW15:BZ15)*0.92 -> 0.0035134376 | CB15: =+AVERAGE(BX15:CA15)*0.92 -> 0.0033495255 | CC15: =+AVERAGE(BY15:CB15)*0.92 -> 0.0030571566 | CD15: =+AVERAGE(BZ15:CC15)*0.97 -> 0.0032980061 | CE15: =+AVERAGE(CA15:CD15)*0.97 -> 0.0032053955 | CF15: =+AVERAGE(CB15:CE15)*0.97 -> 0.0031306953 | CG15: =+AVERAGE(CC15:CF15)*0.97 -> 0.003077629 | CH15: =+AVERAGE(CD15:CG15) -> 0.0031779315 | CI15: =+AVERAGE(CE15:CH15) -> 0.0031479128 | CJ15: =+AVERAGE(CF15:CI15) -> 0.0031335421 | CK15: =+AVERAGE(CG15:CJ15) -> 0.0031342538 | CL15: =+AVERAGE(CH15:CK15) -> 0.0031484101 | CM15: =+AVERAGE(CI15:CL15) -> 0.0031410297 | CN15: =+AVERAGE(CJ15:CM15) -> 0.0031393089 | CO15: =+AVERAGE(CK15:CN15) -> 0.0031407506 | CS15: 0.0042260991
A16: Other non-operating income
A17: Total income | D17: =D14+D15+D16 -> #DIV/0! | E17: =E14+E15+E16 -> 0.065996641 | F17: =F14+F15+F16 -> 0.055656371 | G17: =G14+G15+G16 -> 0.050765387 | H17: =H14+H15+H16 -> 0.04826652 | I17: =I14+I15+I16 -> 0.041331388 | J17: =J14+J15+J16 -> 0.043740023 | K17: =K14+K15+K16 -> 0.044916518 | ... AE17: =AE14+AE15+AE16 -> 0.038126456 | AH17: =AH14+AH15+AH16 -> #DIV/0! | AI17: =AI14+AI15+AI16 -> 0.0072817386 | AJ17: =AJ14+AJ15+AJ16 -> 0.0063193699 | AK17: =AK14+AK15+AK16 -> 0.0068536852 | AL17: =AL14+AL15+AL16 -> 0.0071429546 | AM17: =AM14+AM15+AM16 -> 0.0079405551 | AN17: =AN14+AN15+AN16 -> 0.0078784049 | AO17: =AO14+AO15+AO16 -> 0.0091478326 | ... CO17: =CO14+CO15+CO16 -> 0.0088975098 | CS17: 0.0097027722
A18: TC | D18: =D41/C5 -> #DIV/0! | E18: =E41/D5 -> 0.026321515 | F18: =F41/E5 -> 0.025004321 | G18: =G41/F5 -> 0.024027576 | H18: =H41/G5 -> 0.022603768 | I18: =I41/H5 -> 0.02006167 | J18: =J41/I5 -> 0.01907435 | K18: =K41/J5 -> 0.018294068 | ... AE18: =AE41/AD5 -> 0.019651606 | AH18: =AH41/AG5 -> #DIV/0! | AI18: =AI41/AH5 -> 0.00361137 | AJ18: =AJ41/AI5 -> 0.0034298323 | AK18: =AK41/AJ5 -> 0.003849968 | AL18: =AL41/AK5 -> 0.0038048408 | AM18: =AM41/AL5 -> 0.0039163081 | AN18: =AN41/AM5 -> 0.0041666655 | AO18: =AO41/AN5 -> 0.0038200288 | ... BY18: =BY41/BX5 -> 0.0044874666 | BZ18: =+AVERAGE(BV18:BY18) -> 0.0046077231 | CA18: =+AVERAGE(BW18:BZ18) -> 0.0045877607 | CB18: =+AVERAGE(BX18:CA18) -> 0.0045953388 | CC18: =+AVERAGE(BY18:CB18) -> 0.0045695723 | CD18: =+AVERAGE(BZ18:CC18) -> 0.0045900987 | CE18: =+AVERAGE(CA18:CD18) -> 0.0045856926 | CF18: =+AVERAGE(CB18:CE18) -> 0.0045851756 | CG18: =+AVERAGE(CC18:CF18) -> 0.0045826348 | ... CO18: =+AVERAGE(CK18:CN18) -> 0.0045847351 | CS18: 0.0045574486
A19: PPP | D19: =D17-D18 -> #DIV/0! | E19: =E17-E18 -> 0.039675126 | F19: =F17-F18 -> 0.03065205 | G19: =G17-G18 -> 0.026737811 | H19: =H17-H18 -> 0.025662752 | I19: =I17-I18 -> 0.021269718 | J19: =J17-J18 -> 0.024665673 | K19: =K17-K18 -> 0.026622449 | ... AE19: =AE17-AE18 -> 0.01847485 | AH19: =AH17-AH18 -> #DIV/0! | AI19: =AI17-AI18 -> 0.0036703685 | AJ19: =AJ17-AJ18 -> 0.0028895376 | AK19: =AK17-AK18 -> 0.0030037172 | AL19: =AL17-AL18 -> 0.0033381138 | AM19: =AM17-AM18 -> 0.004024247 | AN19: =AN17-AN18 -> 0.0037117394 | AO19: =AO17-AO18 -> 0.0053278038 | ... CO19: =CO17-CO18 -> 0.0043127747 | CS19: 0.0051453235
A20: Provision | D20: =D44/C5 -> #DIV/0! | E20: =E44/D5 -> 0.016525483 | F20: =F44/E5 -> 0.015482029 | G20: =G44/F5 -> 0.0109399 | H20: =H44/G5 -> 0.010940684 | I20: =I44/H5 -> 0.0075779847 | J20: =J44/I5 -> 0.0086580776 | K20: =K44/J5 -> 0.0065197818 | ... AE20: =AE44/AD5 -> 0.0046992989 | AH20: =AH44/AG5 -> #DIV/0! | AI20: =AI44/AH5 -> 0.0022887838 | AJ20: =AJ44/AI5 -> 0.0026595011 | AK20: =AK44/AJ5 -> 0.011550305 | AL20: =AL44/AK5 -> 0.0027399082 | AM20: =AM44/AL5 -> 0.0029808944 | AN20: =AN44/AM5 -> 0.0027811303 | AO20: =AO44/AN5 -> 0.0048543638 | ... BY20: =BY44/BX5 -> 0.00056517365 | BZ20: =+AVERAGE(BV20:BY20)*1.005 -> 0.0012197084 | CA20: =+AVERAGE(BW20:BZ20)*1.005 -> 0.001157655 | CB20: =+AVERAGE(BX20:CA20)*1.005 -> 0.001094145 | CC20: =+AVERAGE(BY20:CB20)*1.005 -> 0.0010142164 | CD20: =+AVERAGE(BZ20:CC20)*1.005 -> 0.0011270384 | CE20: =+AVERAGE(CA20:CD20)*1.005 -> 0.001103755 | CF20: =+AVERAGE(CB20:CE20)*1.005 -> 0.0010902126 | CG20: =+AVERAGE(CC20:CF20)*1.005 -> 0.0010892246 | CH20: =+AVERAGE(CD20:CG20) -> 0.0011025577 | CI20: =+AVERAGE(CE20:CH20) -> 0.0010964375 | CJ20: =+AVERAGE(CF20:CI20) -> 0.0010946081 | CK20: =+AVERAGE(CG20:CJ20) -> 0.001095707 | CL20: =+AVERAGE(CH20:CK20) -> 0.0010973275 | CM20: =+AVERAGE(CI20:CL20) -> 0.00109602 | CN20: =+AVERAGE(CJ20:CM20) -> 0.0010959157 | CO20: =+AVERAGE(CK20:CN20) -> 0.0010962425 | CS20: 0.0014104312
A21: PBT | D21: =D19-D20 -> #DIV/0! | E21: =E19-E20 -> 0.023149643 | F21: =F19-F20 -> 0.01517002 | G21: =G19-G20 -> 0.015797911 | H21: =H19-H20 -> 0.014722069 | I21: =I19-I20 -> 0.013691733 | J21: =J19-J20 -> 0.016007595 | K21: =K19-K20 -> 0.020102668 | ... AE21: =AE19-AE20 -> 0.013775551 | AH21: =AH19-AH20 -> #DIV/0! | AI21: =AI19-AI20 -> 0.0013815848 | AJ21: =AJ19-AJ20 -> 0.00023003656 | AK21: =AK19-AK20 -> -0.0085465883 | AL21: =AL19-AL20 -> 0.00059820559 | AM21: =AM19-AM20 -> 0.0010433525 | AN21: =AN19-AN20 -> 0.00093060906 | AO21: =AO19-AO20 -> 0.00047343999 | ... CO21: =CO19-CO20 -> 0.0032165321 | CS21: 0.0037348923
A22: Tax | D22: =D46/C5 -> #DIV/0! | E22: =E46/D5 -> 0.00457995 | F22: =F46/E5 -> 0.0020155485 | G22: =G46/F5 -> 0.0020473958 | H22: =H46/G5 -> 0.002202834 | I22: =I46/H5 -> 0.0024436603 | J22: =J46/I5 -> 0.0031113883 | K22: =K46/J5 -> 0.0042084069 | ... AE22: =AE46/AD5 -> 0.0035816433 | AH22: =AH46/AG5 -> #DIV/0! | AI22: =AI46/AH5 -> 0.00038312221 | AJ22: =AJ46/AI5 -> 7.1882935e-05 | AK22: =AK46/AJ5 -> -0.0014220021 | AL22: =AL46/AK5 -> 0.00017802099 | AM22: =AM46/AL5 -> 0.00037242852 | AN22: =AN46/AM5 -> 0.00032761276 | AO22: =AO46/AN5 -> 8.9605569e-05 | ... CO22: =CO46/CN5 -> 0.00083629835 | CS22: 0.00097107201
A23: PAT | D23: =D21-D22 -> #DIV/0! | E23: =E21-E22 -> 0.018569693 | F23: =F21-F22 -> 0.013154472 | G23: =G21-G22 -> 0.013750515 | H23: =H21-H22 -> 0.012519235 | I23: =I21-I22 -> 0.011248073 | J23: =J21-J22 -> 0.012896207 | K23: =K21-K22 -> 0.015894261 | ... AE23: =AE21-AE22 -> 0.010193908 | AH23: =AH21-AH22 -> #DIV/0! | AI23: =AI21-AI22 -> 0.00099846258 | AJ23: =AJ21-AJ22 -> 0.00015815362 | AK23: =AK21-AK22 -> -0.0071245862 | AL23: =AL21-AL22 -> 0.0004201846 | AM23: =AM21-AM22 -> 0.000670924 | AN23: =AN21-AN22 -> 0.0006029963 | AO23: =AO21-AO22 -> 0.00038383442 | ... CO23: =CO21-CO22 -> 0.0023802338 | CS23: 0.0027638203
A25: CD Ratio % | B25: =+B114/B108 -> 0.47116968 | C25: =+C114/C108 -> 0.51736218 | D25: =+D114/D108 -> 0.56136622 | E25: =+E114/E108 -> 0.55172705 | F25: =+F114/F108 -> 0.62421438 | G25: =+G114/G108 -> 0.67999574 | H25: =+H114/H108 -> 0.69184353 | I25: =+I114/I108 -> 0.69602359 | ... AB25: =+AB114/AB108 -> 0.81956643 | AH25: =+AH114/AH108 -> 0.68675334 | AI25: =+AI114/AI108 -> 0.66585693 | AJ25: =+AJ114/AJ108 -> 0.6765504 | AK25: =+AK114/AK108 -> 0.67678312 | AL25: =+AL114/AL108 -> 0.6904653 | AM25: =+AM114/AM108 -> 0.67543869 | AN25: =+AN114/AN108 -> 0.64985014 | AO25: =+AO114/AO108 -> 0.69054282 | ... CO25: =+CO114/CO108 -> 0.9416547 | CS25: 0.76328756
A27: Presentation Data (End)
A28: Profit & Loss- Annual (Start)
A29: Interest Income | B29: =+'Annual Raw'!C7 -> 5618.2669 | C29: =+'Annual Raw'!D7 -> 6370.5611 | D29: =+'Annual Raw'!E7 -> 6657.7229 | E29: =+'Annual Raw'!F7 -> 7006.9207 | F29: =+'Annual Raw'!G7 -> 7571.9688 | G29: =+'Annual Raw'!H7 -> 8711.5123 | H29: =+'Annual Raw'!I7 -> 11364.556 | I29: =+'Annual Raw'!J7 -> 14200.737 | ... AA29: =+'Annual Raw'!AB7 -> 126366.17 | AB29: =SUM(BZ29:CC29) -> 144337.57 | AC29: =SUM(CD29:CG29) -> 159397.79 | AD29: =SUM(CH29:CK29) -> 173050.53 | AE29: =SUM(CL29:CO29) -> 189753.98 | AH29: =+'QTR Raw'!C6 -> 11139.65 | AI29: =+'QTR Raw'!D6 -> 11267.5 | AJ29: =+'QTR Raw'!E6 -> 10882.07 | AK29: =+'QTR Raw'!F6 -> 10732.91 | AL29: =+'QTR Raw'!G6 -> 10201.7 | AM29: =+'QTR Raw'!H6 -> 10405.35 | AN29: =+'QTR Raw'!I6 -> 10287.67 | AO29: =+'QTR Raw'!J6 -> 10492.92 | ... BW29: =+'QTR Raw'!AR6 -> 31543.89 | BX29: 31981.6 | BY29: =+'QTR Raw'!AT6 -> 31837.85 | BZ29: =BZ12*BY5 -> 34653.306 | CA29: =CA12*BZ5 -> 35653.96 | CB29: =CB12*CA5 -> 36658.544 | CC29: =CC12*CB5 -> 37371.757 | CD29: =CD12*CC5 -> 38144.318 | CE29: =CE12*CD5 -> 39385.522 | CF29: =CF12*CE5 -> 40583.065 | CG29: =CG12*CF5 -> 41284.887 | ... CO29: =CO12*CN5 -> 49248.808 | CS29: 32308.289 | CX29: 126366.17
A30: Interest exp | B30: =+'Annual Raw'!C10 -> 3735.2481 | C30: =+'Annual Raw'!D10 -> 4550.2484 | D30: =+'Annual Raw'!E10 -> 4424.7728 | E30: =+'Annual Raw'!F10 -> 4324.5655 | F30: =+'Annual Raw'!G10 -> 4421.4993 | G30: =+'Annual Raw'!H10 -> 5130.0069 | H30: =+'Annual Raw'!I10 -> 7337.7305 | I30: =+'Annual Raw'!J10 -> 10662.944 | ... AA30: =+'Annual Raw'!AB10 -> 89155.928 | AB30: =SUM(BZ30:CC30) -> 100707.53 | AC30: =SUM(CD30:CG30) -> 110232.04 | AD30: =SUM(CH30:CK30) -> 120790.07 | AE30: =SUM(CL30:CO30) -> 132390.45 | AH30: =+'QTR Raw'!C9 -> 8623.15 | AI30: =+'QTR Raw'!D9 -> 8621 | AJ30: =+'QTR Raw'!E9 -> 8655.47 | AK30: =+'QTR Raw'!F9 -> 8359.15 | AL30: =+'QTR Raw'!G9 -> 7894.3 | AM30: =+'QTR Raw'!H9 -> 7963 | AN30: =+'QTR Raw'!I9 -> 7873.87 | AO30: =+'QTR Raw'!J9 -> 7784.7 | ... BW30: =+'QTR Raw'!AR9 -> 22402.7 | BX30: 22729.28 | BY30: =+'QTR Raw'!AT9 -> 22029.88 | BZ30: =BZ13*BY5 -> 24215.546 | CA30: =CA13*BZ5 -> 24818.556 | CB30: =CB13*CA5 -> 25639.631 | CC30: =CC13*CB5 -> 26033.793 | CD30: =CD13*CC5 -> 26350.919 | CE30: =CE13*CD5 -> 27130.024 | CF30: =CF13*CE5 -> 28160.261 | CG30: =CG13*CF5 -> 28590.834 | ... CO30: =CO13*CN5 -> 34353.441 | CS30: 22945.582 | CX30: 89155.928
A31: NII | B31: =B29-B30 -> 1883.0188 | C31: =C29-C30 -> 1820.3127 | D31: =D29-D30 -> 2232.9501 | E31: =E29-E30 -> 2682.3552 | F31: =F29-F30 -> 3150.4695 | G31: =G29-G30 -> 3581.5054 | H31: =H29-H30 -> 4026.8257 | I31: =I29-I30 -> 3537.7926 | ... AE31: =AE29-AE30 -> 57363.538 | AH31: =AH29-AH30 -> 2516.5 | AI31: =AI29-AI30 -> 2646.5 | AJ31: =AJ29-AJ30 -> 2226.6 | AK31: =AK29-AK30 -> 2373.76 | AL31: =AL29-AL30 -> 2307.4 | AM31: =AM29-AM30 -> 2442.35 | AN31: =AN29-AN30 -> 2413.8 | AO31: =AO29-AO30 -> 2708.22 | ... CO31: =CO29-CO30 -> 14895.367 | CS31: 9362.7073 | CX31: 37210.24
A32: Other Income | B32: =+'Annual Raw'!C8 -> 917.787 | C32: =+'Annual Raw'!D8 -> 1428.5343 | D32: =+'Annual Raw'!E8 -> 1512.1313 | E32: =+'Annual Raw'!F8 -> 2072.9132 | F32: =+'Annual Raw'!G8 -> 1543.8273 | G32: =+'Annual Raw'!H8 -> 1377.5149 | H32: =+'Annual Raw'!I8 -> 1450.9497 | I32: =+'Annual Raw'!J8 -> 2212.8724 | ... AA32: =+'Annual Raw'!AB8 -> 26838.037 | AB32: =SUM(BZ32:CC32) -> 25700.107 | AC32: =SUM(CD32:CG32) -> 26356.297 | AD32: =SUM(CH32:CK32) -> 28637.526 | AE32: =SUM(CL32:CO32) -> 31333.174 | AH32: =+'QTR Raw'!C7 -> 1112.99 | AI32: =+'QTR Raw'!D7 -> 1210.45 | AJ32: =+'QTR Raw'!E7 -> 1168.56 | AK32: =+'QTR Raw'!F7 -> 1383.23 | AL32: =+'QTR Raw'!G7 -> 1584.65 | AM32: =+'QTR Raw'!H7 -> 1781.77 | AN32: =+'QTR Raw'!I7 -> 1791.7 | AO32: =+'QTR Raw'!J7 -> 2396.28 | ... BW32: =+'QTR Raw'!AR7 -> 7053.84 | BX32: 7899.36 | BY32: =+'QTR Raw'!AT7 -> 4824.36 | BZ32: =BZ15*BY5 -> 6660.1844 | CA32: =CA15*BZ5 -> 6559.1129 | CB32: =CB15*CA5 -> 6475.6861 | CC32: =CC15*CB5 -> 6005.1238 | CD32: =CD15*CC5 -> 6535.5402 | CE32: =CE15*CD5 -> 6549.956 | CF32: =CF15*CE5 -> 6642.4262 | CG32: =CG15*CF5 -> 6628.3744 | ... CO32: =CO15*CN5 -> 8126.5575 | CS32: 7224.7748 | CX32: 26838.037
A33: TI | B33: =B31+B32 -> 2800.8058 | C33: =C31+C32 -> 3248.847 | D33: =D31+D32 -> 3745.0814 | E33: =E31+E32 -> 4755.2684 | F33: =F31+F32 -> 4694.2968 | G33: =G31+G32 -> 4959.0203 | H33: =H31+H32 -> 5477.7754 | I33: =I31+I32 -> 5750.665 | ... AE33: =AE31+AE32 -> 88696.712 | AH33: =AH31+AH32 -> 3629.49 | AI33: =AI31+AI32 -> 3856.95 | AJ33: =AJ31+AJ32 -> 3395.16 | AK33: =AK31+AK32 -> 3756.99 | AL33: =AL31+AL32 -> 3892.05 | AM33: =AM31+AM32 -> 4224.12 | AN33: =AN31+AN32 -> 4205.5 | AO33: =AO31+AO32 -> 5104.5 | ... CO33: =CO31+CO32 -> 23021.925 | CS33: 16587.482 | CX33: 64048.277
A34: YOY% | C34: =+IF(B33<0,1-C33/B33,C33/B33-1) -> 0.15996868 | D34: =+IF(C33<0,1-D33/C33,D33/C33-1) -> 0.1527417 | E34: =+IF(D33<0,1-E33/D33,E33/D33-1) -> 0.26973699 | F34: =+IF(E33<0,1-F33/E33,F33/E33-1) -> -0.012821905 | G34: =+IF(F33<0,1-G33/F33,G33/F33-1) -> 0.056392578 | H34: =+IF(G33<0,1-H33/G33,H33/G33-1) -> 0.10460838 | I34: =+IF(H33<0,1-I33/H33,I33/H33-1) -> 0.049817596 | J34: =+IF(I33<0,1-J33/I33,J33/I33-1) -> 0.22229695 | ... AB34: =+IF(AA33<0,1-AB33/AA33,AB33/AA33-1) -> 0.082467019 | AC34: =AC33/AB33-1 -> 0.089310409 | AD34: =AD33/AC33-1 -> 0.071183757 | AE34: =AE33/AD33-1 -> 0.096401859 | AL34: =+IF(AH33<0,1-AL33/AH33,AL33/AH33-1) -> 0.072340742 | AM34: =+IF(AI33<0,1-AM33/AI33,AM33/AI33-1) -> 0.095196982 | AN34: =+IF(AJ33<0,1-AN33/AJ33,AN33/AJ33-1) -> 0.23867506 | AO34: =+IF(AK33<0,1-AO33/AK33,AO33/AK33-1) -> 0.35866744 | AP34: =+IF(AL33<0,1-AP33/AL33,AP33/AL33-1) -> 0.23887155 | AQ34: =+IF(AM33<0,1-AQ33/AM33,AQ33/AM33-1) -> 0.11728833 | AR34: =+IF(AN33<0,1-AR33/AN33,AR33/AN33-1) -> 0.24731423 | AS34: =+IF(AO33<0,1-AS33/AO33,AS33/AO33-1) -> -0.15382702 | ... CO34: =+IF(CK33<0,1-CO33/CK33,CO33/CK33-1) -> 0.094938444 | CS34: 0.10947641 | CX34: 0.075993897
A35: Employee Cost | B35: =+'Annual Raw'!C12 -> 1253.073 | C35: =+'Annual Raw'!D12 -> 1122.5201 | D35: =+'Annual Raw'!E12 -> 1162.199 | E35: =+'Annual Raw'!F12 -> 1273.2058 | F35: =+'Annual Raw'!G12 -> 1380.1499 | G35: =+'Annual Raw'!H12 -> 1515.3032 | H35: =+'Annual Raw'!I12 -> 1609.2919 | I35: =+'Annual Raw'!J12 -> 1661.2807 | ... AA35: =+'Annual Raw'!AB12 -> 19265.997 | AB35: =SUM(BZ35:CC35) -> 34764.324 | AC35: =SUM(CD35:CG35) -> 38064.669 | AD35: =SUM(CH35:CK35) -> 41711.478 | AE35: =SUM(CL35:CO35) -> 45717.149 | AH35: =+'QTR Raw'!C11 -> 1058.75 | AI35: =+'QTR Raw'!D11 -> 1107.84 | AJ35: =+'QTR Raw'!E11 -> 1039.75 | AK35: =+'QTR Raw'!F11 -> 1239.54 | AL35: =+'QTR Raw'!G11 -> 1208.17 | AM35: =+'QTR Raw'!H11 -> 1216.94 | AN35: =+'QTR Raw'!I11 -> 1305.74 | AO35: =+'QTR Raw'!J11 -> 1184.24 | ... BW35: =+'QTR Raw'!AR11 -> 4822.25 | BX35: 4904.57 | BY35: =+'QTR Raw'!AT11 -> 4743.64 | BZ35: =BZ18*BY5 -> 8339.422 | CA35: =CA18*BZ5 -> 8564.7289 | CB35: =CB18*CA5 -> 8884.2349 | CC35: =CC18*CB5 -> 8975.9378 | CD35: =CD18*CC5 -> 9096.0336 | CE35: =CE18*CD5 -> 9370.4771 | CF35: =CF18*CE5 -> 9728.411 | CG35: =CG18*CF5 -> 9869.7469 | ... CO35: =CO18*CN5 -> 11862.805 | CS35: 7791.2371 | CX35: 19265.997
A36: Operating & Establishment Expenses | B36: =+'Annual Raw'!C11-'Annual Raw'!C12-'Annual Raw'!C13-'Annual Raw'!C14-'Annual Raw'!C15-'Annual Raw'!C16-'Annual Raw'!C17 -> 188.1405 | C36: =+'Annual Raw'!D11-'Annual Raw'!D12-'Annual Raw'!D13-'Annual Raw'!D14-'Annual Raw'!D15-'Annual Raw'!D16-'Annual Raw'!D17 -> 196.247 | D36: =+'Annual Raw'!E11-'Annual Raw'!E12-'Annual Raw'!E13-'Annual Raw'!E14-'Annual Raw'!E15-'Annual Raw'!E16-'Annual Raw'!E17 -> 270.5371 | E36: =+'Annual Raw'!F11-'Annual Raw'!F12-'Annual Raw'!F13-'Annual Raw'!F14-'Annual Raw'!F15-'Annual Raw'!F16-'Annual Raw'!F17 -> 280.0778 | F36: =+'Annual Raw'!G11-'Annual Raw'!G12-'Annual Raw'!G13-'Annual Raw'!G14-'Annual Raw'!G15-'Annual Raw'!G16-'Annual Raw'!G17 -> 306.7664 | G36: =+'Annual Raw'!H11-'Annual Raw'!H12-'Annual Raw'!H13-'Annual Raw'!H14-'Annual Raw'!H15-'Annual Raw'!H16-'Annual Raw'!H17 -> 360.81 | H36: =+'Annual Raw'!I11-'Annual Raw'!I12-'Annual Raw'!I13-'Annual Raw'!I14-'Annual Raw'!I15-'Annual Raw'!I16-'Annual Raw'!I17 -> 420.066 | I36: =+'Annual Raw'!J11-'Annual Raw'!J12-'Annual Raw'!J13-'Annual Raw'!J14-'Annual Raw'!J15-'Annual Raw'!J16-'Annual Raw'!J17 -> 504.4824 | ... AA36: =+'Annual Raw'!AB11-'Annual Raw'!AB12-'Annual Raw'!AB13-'Annual Raw'!AB14-'Annual Raw'!AB15-'Annual Raw'!AB16-'Annual Raw'!AB17 -> 7605.5766 | AB36: =SUM(BZ36:CC36) -> 0 | AC36: =SUM(CD36:CG36) -> 0 | AD36: =SUM(CH36:CK36) -> 0 | AE36: =SUM(CL36:CO36) -> 0 | AH36: =+'QTR Raw'!C10-'QTR Raw'!C11-'QTR Raw'!C12 -> 567.17 | AI36: =+'QTR Raw'!D10-'QTR Raw'!D11-'QTR Raw'!D12 -> 805.01 | AJ36: =+'QTR Raw'!E10-'QTR Raw'!E11-'QTR Raw'!E12 -> 802.97 | AK36: =+'QTR Raw'!F10-'QTR Raw'!F11-'QTR Raw'!F12 -> 870.9 | AL36: =+'QTR Raw'!G10-'QTR Raw'!G11-'QTR Raw'!G12 -> 865.01 | AM36: =+'QTR Raw'!H10-'QTR Raw'!H11-'QTR Raw'!H12 -> 866.41 | AN36: =+'QTR Raw'!I10-'QTR Raw'!I11-'QTR Raw'!I12 -> 918.43 | AO36: =+'QTR Raw'!J10-'QTR Raw'!J11-'QTR Raw'!J12 -> 947.34 | ... BW36: =+'QTR Raw'!AR10-'QTR Raw'!AR11-'QTR Raw'!AR12 -> 2784.65 | BX36: 3127.64 | BY36: =+'QTR Raw'!AT10-'QTR Raw'!AT11-'QTR Raw'!AT12 -> 3131.31 | CX36: 7605.5766
A37: Insurance | B37: =+'Annual Raw'!C17 -> 25.3782 | C37: =+'Annual Raw'!D17 -> 30.8664 | D37: =+'Annual Raw'!E17 -> 33.7607 | E37: =+'Annual Raw'!F17 -> 38.4367 | F37: =+'Annual Raw'!G17 -> 69.3415 | G37: =+'Annual Raw'!H17 -> 97.6895 | H37: =+'Annual Raw'!I17 -> 115.5902 | I37: =+'Annual Raw'!J17 -> 139.7206 | ... AA37: =+'Annual Raw'!AB17 -> 1853.1619 | CX37: 1853.1619
A38: Rent, Rates & Taxes | B38: =+'Annual Raw'!C14 -> 133.7397 | C38: =+'Annual Raw'!D14 -> 144.3182 | D38: =+'Annual Raw'!E14 -> 162.8883 | E38: =+'Annual Raw'!F14 -> 175.2801 | F38: =+'Annual Raw'!G14 -> 205.462 | G38: =+'Annual Raw'!H14 -> 206.6958 | H38: =+'Annual Raw'!I14 -> 232.902 | I38: =+'Annual Raw'!J14 -> 270.1871 | ... AA38: =+'Annual Raw'!AB14 -> 1231.0793 | AB38: =SUM(BZ38:CC38) -> 0 | AC38: =SUM(CD38:CG38) -> 0 | AD38: =SUM(CH38:CK38) -> 0 | AE38: =SUM(CL38:CO38) -> 0 | CX38: 1231.0793
A39: Depreciation | B39: =+'Annual Raw'!C15+'Annual Raw'!C16 -> 65.9137 | C39: =+'Annual Raw'!D15+'Annual Raw'!D16 -> 92.6775 | D39: =+'Annual Raw'!E15+'Annual Raw'!E16 -> 108.6539 | E39: =+'Annual Raw'!F15+'Annual Raw'!F16 -> 113.7141 | F39: =+'Annual Raw'!G15+'Annual Raw'!G16 -> 132.9457 | G39: =+'Annual Raw'!H15+'Annual Raw'!H16 -> 145.0284 | H39: =+'Annual Raw'!I15+'Annual Raw'!I16 -> 148.177 | I39: =+'Annual Raw'!J15+'Annual Raw'!J16 -> 169.9684 | ... AA39: =+'Annual Raw'!AB15+'Annual Raw'!AB16 -> 917.3623 | AB39: =SUM(BZ39:CC39) -> 0 | AC39: =SUM(CD39:CG39) -> 0 | AD39: =SUM(CH39:CK39) -> 0 | AE39: =SUM(CL39:CO39) -> 0 | AH39: =+'QTR Raw'!C12 -> 0 | AI39: =+'QTR Raw'!D12 -> 0 | AJ39: =+'QTR Raw'!E12 -> 0 | AK39: =+'QTR Raw'!F12 -> 0 | AL39: =+'QTR Raw'!G12 -> 0 | AM39: =+'QTR Raw'!H12 -> 0 | AN39: =+'QTR Raw'!I12 -> 0 | AO39: =+'QTR Raw'!J12 -> 0 | ... BW39: =+'QTR Raw'!AR12 -> 0 | BY39: =+'QTR Raw'!AT12 -> 0 | CX39: 917.3623
A40: Advertisement & Sales Promotion | B40: =+'Annual Raw'!C13 -> 3.3333 | C40: =+'Annual Raw'!D13 -> 5.9777 | D40: =+'Annual Raw'!E13 -> 9.6667 | E40: =+'Annual Raw'!F13 -> 15.8346 | F40: =+'Annual Raw'!G13 -> 14.3061 | G40: =+'Annual Raw'!H13 -> 21.6085 | H40: =+'Annual Raw'!I13 -> 39.2783 | I40: =+'Annual Raw'!J13 -> 45.6521 | ... AA40: =+'Annual Raw'!AB13 -> 156.5283 | AB40: =SUM(BZ40:CC40) -> 0 | AC40: =SUM(CD40:CG40) -> 0 | AD40: =SUM(CH40:CK40) -> 0 | AE40: =SUM(CL40:CO40) -> 0 | CX40: 156.5283
A41: TC | B41: =SUM(B35:B40) -> 1669.5784 | C41: =SUM(C35:C40) -> 1592.6069 | D41: =SUM(D35:D40) -> 1747.7057 | E41: =SUM(E35:E40) -> 1896.5491 | F41: =SUM(F35:F40) -> 2108.9716 | G41: =SUM(G35:G40) -> 2347.1354 | H41: =SUM(H35:H40) -> 2565.3054 | I41: =SUM(I35:I40) -> 2791.2913 | ... AE41: =SUM(AE35:AE40) -> 45717.149 | AH41: =SUM(AH35:AH39) -> 1625.92 | AI41: =SUM(AI35:AI39) -> 1912.85 | AJ41: =SUM(AJ35:AJ39) -> 1842.72 | AK41: =SUM(AK35:AK39) -> 2110.44 | AL41: =SUM(AL35:AL39) -> 2073.18 | AM41: =SUM(AM35:AM39) -> 2083.35 | AN41: =SUM(AN35:AN39) -> 2224.17 | AO41: =SUM(AO35:AO39) -> 2131.58 | ... AS41: =SUM(AS35:AS39) -> 2554.64 | AT41: =SUM(AT35:AT40) -> 2783.02 | AU41: =SUM(AU35:AU40) -> 2509.2 | AV41: =SUM(AV35:AV40) -> 2781.35 | AW41: =SUM(AW35:AW40) -> 2388.64 | AX41: =SUM(AX35:AX40) -> 2662.47 | AY41: =SUM(AY35:AY40) -> 2654.74 | AZ41: =SUM(AZ35:AZ40) -> 2807.43 | BA41: =SUM(BA35:BA40) -> 3452.6 | ... CO41: =SUM(CO35:CO40) -> 11862.805 | CS41: 7791.2371 | CX41: 31029.706
A42: PPP | B42: =+B33-B41 -> 1131.2274 | C42: =+C33-C41 -> 1656.2401 | D42: =+D33-D41 -> 1997.3757 | E42: =+E33-E41 -> 2858.7193 | F42: =+F33-F41 -> 2585.3252 | G42: =+G33-G41 -> 2611.8849 | H42: =+H33-H41 -> 2912.47 | I42: =+I33-I41 -> 2959.3737 | ... AE42: =+AE33-AE41 -> 42979.563 | AH42: =+AH33-AH41 -> 2003.57 | AI42: =+AI33-AI41 -> 1944.1 | AJ42: =+AJ33-AJ41 -> 1552.44 | AK42: =+AK33-AK41 -> 1646.55 | AL42: =+AL33-AL41 -> 1818.87 | AM42: =+AM33-AM41 -> 2140.77 | AN42: =+AN33-AN41 -> 1981.33 | AO42: =+AO33-AO41 -> 2972.92 | ... CO42: =+CO33-CO41 -> 11159.119 | CS42: 8796.2451 | CX42: 33018.572
A43: YOY% | C43: =+IF(B42<0,1-C42/B42,C42/B42-1) -> 0.4641089 | D43: =+IF(C42<0,1-D42/C42,D42/C42-1) -> 0.2059699 | E43: =+IF(D42<0,1-E42/D42,E42/D42-1) -> 0.43123765 | F43: =+IF(E42<0,1-F42/E42,F42/E42-1) -> -0.095635168 | G43: =+IF(F42<0,1-G42/F42,G42/F42-1) -> 0.010273253 | H43: =+IF(G42<0,1-H42/G42,H42/G42-1) -> 0.11508359 | I43: =+IF(H42<0,1-I42/H42,I42/H42-1) -> 0.016104441 | J43: =+IF(I42<0,1-J42/I42,J42/I42-1) -> 0.33939583 | ... AB43: =+IF(AA42<0,1-AB42/AA42,AB42/AA42-1) -> 0.046860064 | AC43: =+AC42/AB42-1 -> 0.083653695 | AD43: =+AD42/AC42-1 -> 0.04616269 | AE43: =+AE42/AD42-1 -> 0.096794692 | AL43: =+IF(AH42<0,1-AL42/AH42,AL42/AH42-1) -> -0.092185449 | AM43: =+IF(AI42<0,1-AM42/AI42,AM42/AI42-1) -> 0.10116249 | AN43: =+IF(AJ42<0,1-AN42/AJ42,AN42/AJ42-1) -> 0.27626833 | AO43: =+IF(AK42<0,1-AO42/AK42,AO42/AK42-1) -> 0.80554493 | AP43: =+IF(AL42<0,1-AP42/AL42,AP42/AL42-1) -> 0.35929451 | AQ43: =+IF(AM42<0,1-AQ42/AM42,AQ42/AM42-1) -> 0.15837759 | AR43: =+IF(AN42<0,1-AR42/AN42,AR42/AN42-1) -> 0.42903504 | AS43: =+IF(AO42<0,1-AS42/AO42,AS42/AO42-1) -> -0.40642533 | ... CO43: =+IF(CK42<0,1-CO42/CK42,CO42/CK42-1) -> 0.093521601 | CS43: 0.12245395 | CX43: 0.051873037
A44: Provisions and Contingencies | B44: =+'Annual Raw'!C19 -> 655.1274 | C44: =+'Annual Raw'!D19 -> 604.8401 | D44: =+'Annual Raw'!E19 -> 678.1938 | E44: =+'Annual Raw'!F19 -> 1190.7137 | F44: =+'Annual Raw'!G19 -> 1305.8207 | G44: =+'Annual Raw'!H19 -> 1068.6649 | H44: =+'Annual Raw'!I19 -> 1241.66 | I44: =+'Annual Raw'!J19 -> 1054.367 | ... AA44: =+'Annual Raw'!AB19 -> 8111.9006 | AB44: =SUM(BZ44:CC44) -> 8476.2456 | AC44: =SUM(CD44:CG44) -> 9147.8496 | AD44: =SUM(CH44:CK44) -> 9982.1062 | AE44: =SUM(CL44:CO44) -> 10932.366 | AH44: =+'QTR Raw'!C18 -> 1359.73 | AI44: =+'QTR Raw'!D18 -> 1212.31 | AJ44: =+'QTR Raw'!E18 -> 1428.85 | AK44: =+'QTR Raw'!F18 -> 6331.54 | AL44: =+'QTR Raw'!G18 -> 1492.92 | AM44: =+'QTR Raw'!H18 -> 1585.74 | AN44: =+'QTR Raw'!I18 -> 1484.57 | AO44: =+'QTR Raw'!J18 -> 2708.74 | ... BW44: =+'QTR Raw'!AR18 -> 2354.17 | BX44: 2414.36 | BY44: =+'QTR Raw'!AT18 -> 991.81 | BZ44: =BZ20*BY5 -> 2207.5249 | CA44: =CA20*BZ5 -> 2161.1854 | CB44: =CB20*CA5 -> 2115.3264 | CC44: =CC20*CB5 -> 1992.209 | CD44: =CD20*CC5 -> 2233.4114 | CE44: =CE20*CD5 -> 2255.4305 | CF44: =CF20*CE5 -> 2313.1146 | CG44: =CG20*CF5 -> 2345.8931 | ... CO44: =CO20*CN5 -> 2836.4805 | CS44: 2411.2183 | CX44: 8111.9006
A45: PBT | B45: =B42-B44 -> 476.1 | C45: =C42-C44 -> 1051.4 | D45: =D42-D44 -> 1319.1819 | E45: =E42-E44 -> 1668.0056 | F45: =F42-F44 -> 1279.5045 | G45: =G42-G44 -> 1543.22 | H45: =H42-H44 -> 1670.81 | I45: =I42-I44 -> 1905.0067 | ... AE45: =AE42-AE44 -> 32047.198 | AH45: =AH42-AH44 -> 643.84 | AI45: =AI42-AI44 -> 731.79 | AJ45: =AJ42-AJ44 -> 123.59 | AK45: =AK42-AK44 -> -4684.99 | AL45: =AL42-AL44 -> 325.95 | AM45: =AM42-AM44 -> 555.03 | AN45: =AN42-AN44 -> 496.76 | AO45: =AO42-AO44 -> 264.18 | ... CO45: =CO42-CO44 -> 8322.6388 | CS45: 6385.0268 | CX45: 24906.671
A46: Tax | B46: =+'Annual Raw'!C18 -> 191 | C46: =+'Annual Raw'!D18 -> 310 | D46: =+'Annual Raw'!E18 -> 300.29 | E46: =+'Annual Raw'!F18 -> 330 | F46: =+'Annual Raw'!G18 -> 170 | G46: =+'Annual Raw'!H18 -> 200 | H46: =+'Annual Raw'!I18 -> 250 | I46: =+'Annual Raw'!J18 -> 340 | ... AA46: =+'Annual Raw'!AB18 -> 5720 | AB46: =SUM(BZ46:CC46) -> 6783.2904 | AC46: =SUM(CD46:CG46) -> 7360.4787 | AD46: =SUM(CH46:CK46) -> 7593.1467 | AE46: =SUM(CL46:CO46) -> 8332.2715 | AH46: =+'QTR Raw'!C20 -> 165 | AI46: =+'QTR Raw'!D20 -> 202.93 | AJ46: =+'QTR Raw'!E20 -> 38.62 | AK46: =+'QTR Raw'!F20 -> -779.5 | AL46: =+'QTR Raw'!G20 -> 97 | AM46: =+'QTR Raw'!H20 -> 198.12 | AN46: =+'QTR Raw'!I20 -> 174.88 | AO46: =+'QTR Raw'!J20 -> 50 | ... BW46: =+'QTR Raw'!AR20 -> 1460 | BX46: 1550 | BY46: =+'QTR Raw'!AT20 -> 1260 | BZ46: =BZ45*0.26 -> 1703.2592 | CA46: =CA45*0.26 -> 1733.8368 | CB46: =CB45*0.26 -> 1688.7097 | CC46: =CC45*0.26 -> 1657.4846 | CD46: =CD45*0.26 -> 1819.8685 | CE46: =CE45*0.26 -> 1866.6822 | CF46: =CF45*0.26 -> 1826.1634 | CG46: =CG45*0.26 -> 1847.7646 | ... CO46: =CO45*0.26 -> 2163.8861 | CS46: 1660.107 | CX46: 5720
A47: PAT | B47: =B45-B46 -> 285.1 | C47: =C45-C46 -> 741.4 | D47: =D45-D46 -> 1018.8919 | E47: =E45-E46 -> 1338.0056 | F47: =F45-F46 -> 1109.5045 | G47: =G45-G46 -> 1343.22 | H47: =H45-H46 -> 1420.81 | I47: =I45-I46 -> 1565.0067 | ... AE47: =AE45-AE46 -> 23714.926 | AH47: =AH45-AH46 -> 478.84 | AI47: =AI45-AI46 -> 528.86 | AJ47: =AJ45-AJ46 -> 84.97 | AK47: =AK45-AK46 -> -3905.49 | AL47: =AL45-AL46 -> 228.95 | AM47: =AM45-AM46 -> 356.91 | AN47: =AN45-AN46 -> 321.88 | AO47: =AO45-AO46 -> 214.18 | ... CO47: =CO45-CO46 -> 6158.7527 | CS47: 4724.9198 | CX47: 19186.671
A48: Minority Interest | B48: =+'Annual Raw'!C25 -> 0 | C48: =+'Annual Raw'!D25 -> 0 | D48: =+'Annual Raw'!E25 -> 0 | E48: =+'Annual Raw'!F25 -> 0 | F48: =+'Annual Raw'!G25 -> 0 | G48: =+'Annual Raw'!H25 -> 0 | H48: =+'Annual Raw'!I25 -> 0 | I48: =+'Annual Raw'!J25 -> 0 | ... AA48: =+'Annual Raw'!AB25 -> 0 | AB48: =SUM(BZ48:CC48) -> 0 | AC48: =SUM(CD48:CG48) -> 0 | AD48: =SUM(CH48:CK48) -> 0 | AE48: =SUM(CL48:CO48) -> 0 | BZ48: =+BY48 -> 0 | CA48: =+BZ48 -> 0 | CB48: =+CA48 -> 0 | CC48: =+CB48 -> 0 | CD48: =+CC48 -> 0 | CE48: =+CD48 -> 0 | CF48: =+CE48 -> 0 | CG48: =+CF48 -> 0 | ... CO48: =+CN48 -> 0 | CS48: 0 | CX48: 0
A49: Share of Associates | B49: =+'Annual Raw'!C26 -> 0 | C49: =+'Annual Raw'!D26 -> 0 | D49: =+'Annual Raw'!E26 -> 0 | E49: =+'Annual Raw'!F26 -> 0 | F49: =+'Annual Raw'!G26 -> 0 | G49: =+'Annual Raw'!H26 -> 0 | H49: =+'Annual Raw'!I26 -> 0 | I49: =+'Annual Raw'!J26 -> 0 | ... AA49: =+'Annual Raw'!AB26 -> 0 | AB49: =SUM(BZ49:CC49) -> 0 | AC49: =SUM(CD49:CG49) -> 0 | AD49: =SUM(CH49:CK49) -> 0 | AE49: =SUM(CL49:CO49) -> 0 | BZ49: =+BY49 -> 0 | CA49: =+BZ49 -> 0 | CB49: =+CA49 -> 0 | CC49: =+CB49 -> 0 | CD49: =+CC49 -> 0 | CE49: =+CD49 -> 0 | CF49: =+CE49 -> 0 | CG49: =+CF49 -> 0 | ... CO49: =+CN49 -> 0 | CS49: 0 | CX49: 0
A50: Exceptional items | AH50: =+'QTR Raw'!C15 -> 0 | AI50: =+'QTR Raw'!D15 -> 0 | AJ50: =+'QTR Raw'!E15 -> 0 | AK50: =+'QTR Raw'!F15 -> 0 | AL50: =+'QTR Raw'!G15 -> 0 | AM50: =+'QTR Raw'!H15 -> 0 | AN50: =+'QTR Raw'!I15 -> 0 | AO50: =+'QTR Raw'!J15 -> 0 | ... BY50: =+'QTR Raw'!AT15 -> 0
A51: Consolidated Net Profit | B51: =B47+B48+B49 -> 285.1 | C51: =C47+C48+C49 -> 741.4 | D51: =D47+D48+D49 -> 1018.8919 | E51: =E47+E48+E49 -> 1338.0056 | F51: =F47+F48+F49 -> 1109.5045 | G51: =G47+G48+G49 -> 1343.22 | H51: =H47+H48+H49 -> 1420.81 | I51: =I47+I48+I49 -> 1565.0067 | ... AE51: =AE47+AE48+AE49 -> 23714.926 | AH51: =AH47+AH48+AH49+AH50 -> 478.84 | AI51: =AI47+AI48+AI49+AI50 -> 528.86 | AJ51: =AJ47+AJ48+AJ49+AJ50 -> 84.97 | AK51: =AK47+AK48+AK49+AK50 -> -3905.49 | AL51: =AL47+AL48+AL49+AL50 -> 228.95 | AM51: =AM47+AM48+AM49+AM50 -> 356.91 | AN51: =AN47+AN48+AN49+AN50 -> 321.88 | AO51: =AO47+AO48+AO49+AO50 -> 214.18 | ... CO51: =CO47+CO48+CO49+CO50 -> 6158.7527 | CS51: 4724.9198 | CX51: 19186.671
A52: YOY% | C52: =+IF(B51<0,1-C51/B51,C51/B51-1) -> 1.6004911 | D52: =+IF(C51<0,1-D51/C51,D51/C51-1) -> 0.37428095 | E52: =+IF(D51<0,1-E51/D51,E51/D51-1) -> 0.31319682 | F52: =+IF(E51<0,1-F51/E51,F51/E51-1) -> -0.17077739 | G52: =+IF(F51<0,1-G51/F51,G51/F51-1) -> 0.21064854 | H52: =+IF(G51<0,1-H51/G51,H51/G51-1) -> 0.057764179 | I52: =+IF(H51<0,1-I51/H51,I51/H51-1) -> 0.10148908 | J52: =+IF(I51<0,1-J51/I51,J51/I51-1) -> 0.32422436 | ... AB52: =+IF(AA51<0,1-AB51/AA51,AB51/AA51-1) -> 0.0062343771 | AC52: =+AC51/AB51-1 -> 0.085089721 | AD52: =+AD51/AC51-1 -> 0.031610443 | AE52: =+AE51/AD51-1 -> 0.097341033 | AL52: =+IF(AH51<0,1-AL51/AH51,AL51/AH51-1) -> -0.52186534 | AM52: =+IF(AI51<0,1-AM51/AI51,AM51/AI51-1) -> -0.32513331 | AN52: =+IF(AJ51<0,1-AN51/AJ51,AN51/AJ51-1) -> 2.7881605 | AO52: =+IF(AK51<0,1-AO51/AK51,AO51/AK51-1) -> 1.0548407 | AP52: =+IF(AL51<0,1-AP51/AL51,AP51/AL51-1) -> 0.098929897 | AQ52: =+IF(AM51<0,1-AQ51/AM51,AQ51/AM51-1) -> -0.27102071 | AR52: =+IF(AN51<0,1-AR51/AN51,AR51/AN51-1) -> -0.60932646 | AS52: =+IF(AO51<0,1-AS51/AO51,AS51/AO51-1) -> -23.69012 | ... CO52: =+IF(CK51<0,1-CO51/CK51,CO51/CK51-1) -> 0.092423693 | CS52: 0.15124015 | CX52: 0.12685979
A53: Profit & Loss- Annual (End)
A54: ACE | B54: =+'Annual Raw'!C22 -> 285.1 | C54: =+'Annual Raw'!D22 -> 741.4 | D54: =+'Annual Raw'!E22 -> 1018.8919 | E54: =+'Annual Raw'!F22 -> 1338.0056 | F54: =+'Annual Raw'!G22 -> 1109.5045 | G54: =+'Annual Raw'!H22 -> 1343.22 | H54: =+'Annual Raw'!I22 -> 1420.81 | I54: =+'Annual Raw'!J22 -> 1565.0067 | ... AA54: =+'Annual Raw'!AB22 -> 19186.671 | AH54: =+'QTR Raw'!C21 -> 478.84 | AI54: =+'QTR Raw'!D21 -> 528.86 | AJ54: =+'QTR Raw'!E21 -> 84.97 | AK54: =+'QTR Raw'!F21 -> -3905.49 | AL54: =+'QTR Raw'!G21 -> 228.95 | AM54: =+'QTR Raw'!H21 -> 356.91 | AN54: =+'QTR Raw'!I21 -> 321.88 | AO54: =+'QTR Raw'!J21 -> 214.18 | ... BW54: =+'QTR Raw'!AR21 -> 4773.96 | BX54: 5155.11 | BY54: =+'QTR Raw'!AT21 -> 4505.57 | CX54: 19186.671
A55: Checksum - PAT | B55: =+B51-B54 -> 0 | C55: =+C51-C54 -> 0 | D55: =+D51-D54 -> 0 | E55: =+E51-E54 -> 0 | F55: =+F51-F54 -> 0 | G55: =+G51-G54 -> 0 | H55: =+H51-H54 -> 0 | I55: =+I51-I54 -> 0 | ... AA55: =+AA51-AA54 -> 0 | AH55: =+AH51-AH54 -> 0 | AI55: =+AI51-AI54 -> 0 | AJ55: =+AJ51-AJ54 -> 3.6948222e-13 | AK55: =+AK51-AK54 -> 0 | AL55: =+AL51-AL54 -> 7.3896445e-13 | AM55: =+AM51-AM54 -> 8.5265128e-13 | AN55: =+AN51-AN54 -> 0 | AO55: =+AO51-AO54 -> 2.8421709e-13 | ... BY55: =+BY51-BY54 -> 0 | CX55: 0
A56: Ratios (Start)
A57: Eq | B57: =+C57 -> 1814.1303 | C57: =+D57 -> 1814.1303 | D57: =+E57 -> 1814.1303 | E57: =+F57 -> 1814.1303 | F57: =+G57 -> 1814.1303 | G57: =+H57 -> 1814.1303 | H57: =+I57 -> 1814.1303 | I57: =+J57 -> 1814.1303 | ... Y57: =+Z57 -> 1814.1303 | Z57: =+'Annual Raw'!AA38 -> 1814.1303 | AA57: =+'Annual Raw'!AB38 -> 1814.1303 | AB57: =+CC57 -> 1814.13 | AC57: =+CG57 -> 1814.13 | AD57: =+CK57 -> 1814.13 | AE57: =+CO57 -> 1814.13 | AH57: =+'QTR Raw'!C29 -> 515.2 | AI57: =+'QTR Raw'!D29 -> 542.99 | AJ57: =+'QTR Raw'!E29 -> 542.99 | AK57: =+'QTR Raw'!F29 -> 542.99 | AL57: =+'QTR Raw'!G29 -> 542.99 | AM57: =+'QTR Raw'!H29 -> 542.99 | AN57: =+'QTR Raw'!I29 -> 542.99 | AO57: =+'QTR Raw'!J29 -> 597.29 | ... AS57: =+'QTR Raw'!N29 -> 733.24 | AT57: =+AU57 -> 1814.13 | AU57: =+AV57 -> 1814.13 | AV57: =+AW57 -> 1814.13 | AW57: =+AX57 -> 1814.13 | AX57: =+AY57 -> 1814.13 | AY57: =+AZ57 -> 1814.13 | AZ57: =+BA57 -> 1814.13 | BA57: =+BB57 -> 1814.13 | ... BV57: =+BW57 -> 1814.13 | BW57: =+'QTR Raw'!AR29 -> 1814.13 | BX57: 1814.13 | BY57: =+'QTR Raw'!AT29 -> 1814.13 | BZ57: =+BY57 -> 1814.13 | CA57: =+BZ57 -> 1814.13 | CB57: =+CA57 -> 1814.13 | CC57: =+CB57 -> 1814.13 | CD57: =+CC57 -> 1814.13 | CE57: =+CD57 -> 1814.13 | CF57: =+CE57 -> 1814.13 | CG57: =+CF57 -> 1814.13 | ... CO57: =+CN57 -> 1814.13 | CS57: 1814.13 | CX57: 1814.1303
A58: FV | B58: =+C58 -> 2 | C58: =+D58 -> 2 | D58: =+E58 -> 2 | E58: =+F58 -> 2 | F58: =+G58 -> 2 | G58: =+H58 -> 2 | H58: =+I58 -> 2 | I58: =+J58 -> 2 | ... Y58: =+Z58 -> 2 | Z58: =+'Annual Raw'!AA50 -> 2 | AA58: =+'Annual Raw'!AB50 -> 2 | AB58: =+CC58 -> 2 | AC58: =+CG58 -> 2 | AD58: =+CK58 -> 2 | AE58: =+CO58 -> 2 | AH58: =+'QTR Raw'!C30 -> 10 | AI58: =+'QTR Raw'!D30 -> 10 | AJ58: =+'QTR Raw'!E30 -> 10 | AK58: =+'QTR Raw'!F30 -> 10 | AL58: =+'QTR Raw'!G30 -> 10 | AM58: =+'QTR Raw'!H30 -> 10 | AN58: =+'QTR Raw'!I30 -> 10 | AO58: =+'QTR Raw'!J30 -> 10 | ... AS58: =+'QTR Raw'!N30 -> 10 | AT58: =+AU58 -> 2 | AU58: =+AV58 -> 2 | AV58: =+AW58 -> 2 | AW58: =+AX58 -> 2 | AX58: =+AY58 -> 2 | AY58: =+AZ58 -> 2 | AZ58: =+BA58 -> 2 | BA58: =+BB58 -> 2 | ... BV58: =+BW58 -> 2 | BW58: =+'QTR Raw'!AR30 -> 2 | BX58: =+BW58 -> 2 | BY58: =+'QTR Raw'!AT30 -> 2 | BZ58: =+BY58 -> 2 | CA58: =+BZ58 -> 2 | CB58: =+CA58 -> 2 | CC58: =+CB58 -> 2 | CD58: =+CC58 -> 2 | CE58: =+CD58 -> 2 | CF58: =+CE58 -> 2 | CG58: =+CF58 -> 2 | ... CO58: =+CN58 -> 2 | CS58: 2 | CX58: 2
A59: No of share | B59: =B57/B58 -> 907.06515 | C59: =C57/C58 -> 907.06515 | D59: =D57/D58 -> 907.06515 | E59: =E57/E58 -> 907.06515 | F59: =F57/F58 -> 907.06515 | G59: =G57/G58 -> 907.06515 | H59: =H57/H58 -> 907.06515 | I59: =I57/I58 -> 907.06515 | ... AE59: =AE57/AE58 -> 907.065 | AH59: =AH57/AH58 -> 51.52 | AI59: =AI57/AI58 -> 54.299 | AJ59: =AJ57/AJ58 -> 54.299 | AK59: =AK57/AK58 -> 54.299 | AL59: =AL57/AL58 -> 54.299 | AM59: =AM57/AM58 -> 54.299 | AN59: =AN57/AN58 -> 54.299 | AO59: =AO57/AO58 -> 59.729 | ... CO59: =CO57/CO58 -> 907.065 | CS59: 907.065 | CX59: 907.06515
A60: EPS | B60: =B51/B59 -> 0.31431039 | C60: =C51/C59 -> 0.81736135 | D60: =D51/D59 -> 1.1232841 | E60: =E51/E59 -> 1.4750932 | F60: =F51/F59 -> 1.2231806 | G60: =G51/G59 -> 1.4808418 | H60: =H51/H59 -> 1.5663814 | I60: =I51/I59 -> 1.725352 | ... AE60: =AE51/AE59 -> 26.144683 | AH60: =AH51/AH59 -> 9.2942547 | AI60: =AI51/AI59 -> 9.7397742 | AJ60: =AJ51/AJ59 -> 1.5648539 | AK60: =AK51/AK59 -> -71.925634 | AL60: =AL51/AL59 -> 4.2164681 | AM60: =AM51/AM59 -> 6.5730492 | AN60: =AN51/AN59 -> 5.9279176 | AO60: =AO51/AO59 -> 3.5858628 | ... CO60: =CO51/CO59 -> 6.7897589 | CS60: 5.2090201 | CX60: 21.152473
A61: EPS TTM | B61: =+B60 -> 0.31431039 | C61: =+C60 -> 0.81736135 | D61: =+D60 -> 1.1232841 | E61: =+E60 -> 1.4750932 | F61: =+F60 -> 1.2231806 | G61: =+G60 -> 1.4808418 | H61: =+H60 -> 1.5663814 | I61: =+I60 -> 1.725352 | ... AE61: =+AE60 -> 26.144683 | AK61: =AK60+AJ60+AI60+AH60 -> -51.326751 | AL61: =AL60+AK60+AJ60+AI60 -> -56.404538 | AM61: =AM60+AL60+AK60+AJ60 -> -59.571263 | AN61: =AN60+AM60+AL60+AK60 -> -55.208199 | AO61: =AO60+AN60+AM60+AL60 -> 20.303298 | AP61: =AP60+AO60+AN60+AM60 -> 20.299189 | AQ61: =AQ60+AP60+AO60+AN60 -> 18.082148 | AR61: =AR60+AQ60+AP60+AO60 -> 14.259572 | ... CO61: =CO60+CN60+CM60+CL60 -> 26.144683 | CS61: 21.226229 | CX61: 21.152473
A62: Bloomberg Estimate | CC62: 20.5 | CG62: 22.9 | CK62: 23.1
A63: Estimate Deviation | CC63: =+CC61/CC62-1 -> 0.038260933 | CG63: =+CG61/CG62-1 -> 0.0085339935 | CK63: =+CK61/CK62-1 -> 0.031406285
A64: BVPS | B64: =B104/B59 -> 3.1028091 | C64: =C104/C59 -> 3.8271727 | D64: =D104/D59 -> 4.5739033 | E64: =E104/E59 -> 5.7897087 | F64: =F104/F59 -> 6.7348604 | G64: =G104/G59 -> 7.8629807 | H64: =H104/H59 -> 11.414821 | I64: =I104/I59 -> 11.576337 | ... AE64: =AE104/AE59 -> 219.34938 | AH64: =AH104/AH59 -> 657.85695 | AI64: =AI104/AI59 -> 653.42143 | AJ64: =AJ104/AJ59 -> 654.38074 | AK64: =AK104/AK59 -> 582.02177 | AL64: =AL104/AL59 -> 585.80453 | AM64: =AM104/AM59 -> 591.48069 | AN64: =AN104/AN59 -> 597.22463 | AO64: =AO104/AO59 -> 563.97294 | ... CO64: =CO104/CO59 -> 219.34938 | CS64: 124.59496 | CX64: 124.99942
A65: ABVPS | C65: =+C64-C73 -> 2.4067786 | D65: =+D64-D73 -> 2.9710637 | E65: =+E64-E73 -> 4.2701817 | F65: =+F64-F73 -> 5.494288 | G65: =+G64-G73 -> 6.8937229 | H65: =+H64-H73 -> 10.392877 | I65: =+I64-I73 -> 10.585196 | J65: =+J64-J73 -> 11.796858 | ... AE65: =+AE64-AE73 -> 219.34938 | AI65: =+AI64-AI73 -> 480.62764 | AJ65: =+AJ64-AJ73 -> 416.0688 | AK65: =+AK64-AK73 -> 198.35154 | AL65: =+AL64-AL73 -> 189.96077 | AM65: =+AM64-AM73 -> 188.3961 | AN65: =+AN64-AN73 -> 186.6132 | AO65: =+AO64-AO73 -> 201.51953 | AP65: =+AP64-AP73 -> 160.1249 | ... CO65: =+CO64-CO73 -> 209.22132 | CS65: 117.69464 | CX65: 119.25672
A67: Capital Adequacy Ratio Basel III | B67: =+'Annual Raw'!C92 -> 0 | C67: =+'Annual Raw'!D92 -> 0 | D67: =+'Annual Raw'!E92 -> 0 | E67: =+'Annual Raw'!F92 -> 0 | F67: =+'Annual Raw'!G92 -> 0 | G67: =+'Annual Raw'!H92 -> 0 | H67: =+'Annual Raw'!I92 -> 0 | I67: =+'Annual Raw'!J92 -> 0 | ... AA67: =+'Annual Raw'!AB92 -> 17.04 | AI67: =+'QTR Raw'!D36 -> 11.04 | AJ67: =+'QTR Raw'!E36 -> 11.54 | AK67: =+'QTR Raw'!F36 -> 11.08 | AL67: =+'QTR Raw'!G36 -> 12.11 | AM67: =+'QTR Raw'!H36 -> 12.19 | AN67: =+'QTR Raw'!I36 -> 12.28 | AO67: =+'QTR Raw'!J36 -> 12.86 | AP67: =+'QTR Raw'!K36 -> 12.61 | ... BW67: =+'QTR Raw'!AR36 -> 16.2 | BY67: =+'QTR Raw'!AT36 -> 17.04 | CX67: 17.04
A68: Tier 1 Basel III | B68: =+'Annual Raw'!C93 -> 0 | C68: =+'Annual Raw'!D93 -> 0 | D68: =+'Annual Raw'!E93 -> 0 | E68: =+'Annual Raw'!F93 -> 0 | F68: =+'Annual Raw'!G93 -> 0 | G68: =+'Annual Raw'!H93 -> 0 | H68: =+'Annual Raw'!I93 -> 0 | I68: =+'Annual Raw'!J93 -> 0 | ... AA68: =+'Annual Raw'!AB93 -> 14.59 | AI68: =+'QTR Raw'!D37 -> 8.63 | AJ68: =+'QTR Raw'!E37 -> 8.68 | AK68: =+'QTR Raw'!F37 -> 8.8 | AL68: =+'QTR Raw'!G37 -> 8.83 | AM68: =+'QTR Raw'!H37 -> 8.87 | AN68: =+'QTR Raw'!I37 -> 9.01 | AO68: =+'QTR Raw'!J37 -> 9.77 | AP68: =+'QTR Raw'!K37 -> 9.57 | ... BW68: =+'QTR Raw'!AR37 -> 14.28 | BY68: =+'QTR Raw'!AT37 -> 14.59 | CX68: 14.59
A69: Tier 2 Basel III | B69: =+'Annual Raw'!C94 -> 0 | C69: =+'Annual Raw'!D94 -> 0 | D69: =+'Annual Raw'!E94 -> 0 | E69: =+'Annual Raw'!F94 -> 0 | F69: =+'Annual Raw'!G94 -> 0 | G69: =+'Annual Raw'!H94 -> 0 | H69: =+'Annual Raw'!I94 -> 0 | I69: =+'Annual Raw'!J94 -> 0 | ... AA69: =+'Annual Raw'!AB94 -> 2.45 | AI69: =+'QTR Raw'!D38 -> 2.41 | AJ69: =+'QTR Raw'!E38 -> 2.86 | AK69: =+'QTR Raw'!F38 -> 2.28 | AL69: =+'QTR Raw'!G38 -> 3.28 | AM69: =+'QTR Raw'!H38 -> 3.32 | AN69: =+'QTR Raw'!I38 -> 3.27 | AO69: =+'QTR Raw'!J38 -> 3.09 | AP69: =+'QTR Raw'!K38 -> 3.04 | ... BW69: =+'QTR Raw'!AR38 -> 1.92 | BY69: =+'QTR Raw'!AT38 -> 2.45 | CX69: 2.45
A71: GNPA | B71: =+'Annual Raw'!C52 -> 0 | C71: =+'Annual Raw'!D52 -> 2112.44 | D71: =+'Annual Raw'!E52 -> 2474.78 | E71: =+'Annual Raw'!F52 -> 3126.84 | F71: =+'Annual Raw'!G52 -> 2370.55 | G71: =+'Annual Raw'!H52 -> 1792.61 | H71: =+'Annual Raw'!I52 -> 1493.43 | I71: =+'Annual Raw'!J52 -> 1415.55 | ... AA71: =+'Annual Raw'!AB52 -> 22740 | AH71: =+'QTR Raw'!C40 -> 13080.63 | AI71: =+'QTR Raw'!D40 -> 14021.34 | AJ71: =+'QTR Raw'!E40 -> 19813.44 | AK71: =+'QTR Raw'!F40 -> 31637.83 | AL71: =+'QTR Raw'!G40 -> 32334.07 | AM71: =+'QTR Raw'!H40 -> 33315.4 | AN71: =+'QTR Raw'!I40 -> 34338.65 | AO71: =+'QTR Raw'!J40 -> 34202.04 | ... BW71: =+'QTR Raw'!AR40 -> 27040.27 | BX71: 24832.58 | BY71: =+'QTR Raw'!AT40 -> 22740.01 | CX71: 22740
A72: NNPA | B72: =+'Annual Raw'!C53 -> 0 | C72: =+'Annual Raw'!D53 -> 1288.39 | D72: =+'Annual Raw'!E53 -> 1453.88 | E72: =+'Annual Raw'!F53 -> 1378.31 | F72: =+'Annual Raw'!G53 -> 1125.28 | G72: =+'Annual Raw'!H53 -> 879.18 | H72: =+'Annual Raw'!I53 -> 926.97 | I72: =+'Annual Raw'!J53 -> 899.03 | ... AA72: =+'Annual Raw'!AB53 -> 5209 | AH72: =+'QTR Raw'!C41 -> 8888.14 | AI72: =+'QTR Raw'!D41 -> 9382.53 | AJ72: =+'QTR Raw'!E41 -> 12940.1 | AK72: =+'QTR Raw'!F41 -> 20832.91 | AL72: =+'QTR Raw'!G41 -> 21493.92 | AM72: =+'QTR Raw'!H41 -> 21887.09 | AN72: =+'QTR Raw'!I41 -> 22295.79 | AO72: =+'QTR Raw'!J41 -> 21648.98 | ... BW72: =+'QTR Raw'!AR41 -> 6113.22 | BX72: 5322.3 | BY72: =+'QTR Raw'!AT41 -> 5209.37 | BZ72: =+BZ76*BZ114 -> 5261.7972 | CA72: =+CA76*CA114 -> 5555.0722 | CB72: =+CB76*CB114 -> 5768.418 | CC72: =+CC76*CC114 -> 6008.7141 | CD72: =+CD76*CD114 -> 6056.8027 | CE72: =+CE76*CE114 -> 6398.8996 | CF72: =+CF76*CF114 -> 6645.6751 | CG72: =+CG76*CG114 -> 6922.8124 | ... CO72: =+CO76*CO114 -> 9186.81 | CS72: 6259.0384 | CX72: 5209
A73: NNPA Per Share | C73: =+C72/C59 -> 1.4203941 | D73: =+D72/D59 -> 1.6028397 | E73: =+E72/E59 -> 1.519527 | F73: =+F72/F59 -> 1.2405724 | G73: =+G72/G59 -> 0.96925783 | H73: =+H72/H59 -> 1.0219442 | I73: =+I72/I59 -> 0.9911416 | J73: =+J72/J59 -> 1.6616778 | ... AA73: =+AA72/AA59 -> 5.7426967 | AI73: =+AI72/AI59 -> 172.79379 | AJ73: =+AJ72/AJ59 -> 238.31194 | AK73: =+AK72/AK59 -> 383.67023 | AL73: =+AL72/AL59 -> 395.84375 | AM73: =+AM72/AM59 -> 403.08459 | AN73: =+AN72/AN59 -> 410.61143 | AO73: =+AO72/AO59 -> 362.45341 | AP73: =+AP72/AP59 -> 406.8481 | ... CO73: =+CO72/CO59 -> 10.128061 | CS73: 6.9003196 | CX73: 5.7426967
A75: GNPA % | B75: =+B71/B114 -> 0 | C75: =+C71/C114 -> 0.063768491 | D75: =+D71/D114 -> 0.061148561 | E75: =+E71/E114 -> 0.065636651 | F75: =+F71/F114 -> 0.039233613 | G75: =+G71/G114 -> 0.022569647 | H75: =+H71/H114 -> 0.015160851 | I75: =+I71/I114 -> 0.013200073 | ... AA75: =+AA71/AA114 -> 0.018639077 | AI75: =+AI71/AI114 -> 0.043399314 | AJ75: =+AJ71/AJ114 -> 0.059694345 | AK75: =+AK71/AK114 -> 0.097432661 | AL75: =+AL71/AL114 -> 0.10064038 | AM75: =+AM71/AM114 -> 0.10184168 | AN75: =+AN71/AN114 -> 0.10354307 | AO75: =+AO71/AO114 -> 0.1000034 | AP75: =+AP71/AP114 -> 0.10984844 | ... BY75: =+BY71/BY114 -> 0.018639086 | CX75: 0.018639077
A76: NNPA % | B76: =+B72/B114 -> 0 | C76: =+C72/C114 -> 0.03889279 | D76: =+D72/D114 -> 0.035923464 | E76: =+E72/E114 -> 0.028932613 | F76: =+F72/F114 -> 0.018623864 | G76: =+G72/G114 -> 0.011069213 | H76: =+H72/H114 -> 0.0094103196 | I76: =+I72/I114 -> 0.0083834989 | ... AA76: =+AA72/AA114 -> 0.004269611 | AI76: =+AI72/AI114 -> 0.029041116 | AJ76: =+AJ72/AJ114 -> 0.038986203 | AK76: =+AK72/AK114 -> 0.064157556 | AL76: =+AL72/AL114 -> 0.066900213 | AM76: =+AM72/AM114 -> 0.066906539 | AN76: =+AN72/AN114 -> 0.067229627 | AO76: =+AO72/AO114 -> 0.06329949 | AP76: =+AP72/AP114 -> 0.070885426 | ... BY76: =+BY72/BY114 -> 0.0042699143 | BZ76: =+BY76 -> 0.0042699143 | CA76: =+BZ76 -> 0.0042699143 | CB76: =+CA76 -> 0.0042699143 | CC76: =+CB76 -> 0.0042699143 | CD76: =+CC76 -> 0.0042699143 | CE76: =+CD76 -> 0.0042699143 | CF76: =+CE76 -> 0.0042699143 | CG76: =+CF76 -> 0.0042699143 | ... CO76: =+CN76 -> 0.0042699143 | CS76: 0.005409384 | CX76: 0.004269611
A78: NIM %(Reported) | B78: =+'Annual Raw'!C54 -> 0 | C78: =+'Annual Raw'!D54 -> 0 | D78: =+'Annual Raw'!E54 -> 3.53 | E78: =+'Annual Raw'!F54 -> 3.49 | F78: =+'Annual Raw'!G54 -> 3.41 | G78: =+'Annual Raw'!H54 -> 3.36 | H78: =+'Annual Raw'!I54 -> 3.15 | I78: =+'Annual Raw'!J54 -> 2.42 | ... AA78: =+'Annual Raw'!AB54 -> 2.51 | AH78: =+'QTR Raw'!C48 -> 2.21 | AI78: =+'QTR Raw'!D48 -> 2.38 | AJ78: =+'QTR Raw'!E48 -> 2.29 | AK78: =+'QTR Raw'!F48 -> 2.34 | AL78: =+'QTR Raw'!G48 -> 2.29 | AM78: =+'QTR Raw'!H48 -> 2.35 | AN78: =+'QTR Raw'!I48 -> 2.34 | AO78: =+'QTR Raw'!J48 -> 2.39 | ... BY78: =+'QTR Raw'!AT48 -> 2.54 | CX78: 2.51
A79: NIIM %(Calculated) | D79: =+D31/D81 -> 0.035088134 | E79: =+E31/E81 -> 0.034754209 | F79: =+F31/F81 -> 0.034638262 | G79: =+G31/G81 -> 0.033335684 | H79: =+H31/H81 -> 0.03095997 | I79: =+I31/I81 -> 0.023524056 | J79: =+J31/J81 -> 0.026726309 | K79: =+K31/K81 -> 0.026116924 | ... AA79: =+AA31/AA81 -> 0.024362085 | AI79: =+AI31/AI81*4 -> 0.022225119 | AJ79: =+AJ31/AJ81*4 -> 0.018475888 | AK79: =+AK31/AK81*4 -> 0.019888507 | AL79: =+AL31/AL81*4 -> 0.020086992 | AM79: =+AM31/AM81*4 -> 0.021227269 | AN79: =+AN31/AN81*4 -> 0.019924272 | AO79: =+AO31/AO81*4 -> 0.021819684 | AP79: =+AP31/AP81*4 -> 0.022081644 | ... CO79: =+CO31/CO81*4 -> 0.022203549 | CS79: 0.024292382 | CX79: 0.024362085
A80: Earning Asset | C80: =+SUM(C113:C114) -> 56346.811 | D80: =+SUM(D113:D114) -> 70929.842 | E80: =+SUM(E113:E114) -> 83431.617 | F80: =+SUM(F113:F114) -> 98475.288 | G80: =+SUM(G113:G114) -> 116399.88 | H80: =+SUM(H113:H114) -> 143731.23 | I80: =+SUM(I113:I114) -> 157049.61 | J80: =+SUM(J113:J114) -> 195996.3 | ... AA80: =+SUM(AA113:AA114) -> 1623432.1 | AI80: =+SUM(AI113:AI114) -> 476307.91 | AJ80: =+SUM(AJ113:AJ114) -> 487802.71 | AK80: =+SUM(AK113:AK114) -> 467024.13 | AL80: =+SUM(AL113:AL114) -> 451938.77 | AM80: =+SUM(AM113:AM114) -> 468518.79 | AN80: =+SUM(AN113:AN114) -> 500670.97 | AO80: =+SUM(AO113:AO114) -> 492274.65 | AP80: =+SUM(AP113:AP114) -> 490710.12 | ... CO80: =+SUM(CO113:CO114) -> 2733066.7 | CS80: 1558614.6 | CX80: 1623432.1
A81: Average Earning Asset | D81: =+AVERAGE(C80:D80) -> 63638.327 | E81: =+AVERAGE(D80:E80) -> 77180.73 | F81: =+AVERAGE(E80:F80) -> 90953.452 | G81: =+AVERAGE(F80:G80) -> 107437.59 | H81: =+AVERAGE(G80:H80) -> 130065.55 | I81: =+AVERAGE(H80:I80) -> 150390.42 | J81: =+AVERAGE(I80:J80) -> 176522.96 | K81: =+AVERAGE(J80:K80) -> 217503.94 | ... AA81: =+AVERAGE(Z80:AA80) -> 1527383.2 | AI81: =+AVERAGE(AH80:AI80) -> 476307.91 | AJ81: =+AVERAGE(AI80:AJ80) -> 482055.31 | AK81: =+AVERAGE(AJ80:AK80) -> 477413.42 | AL81: =+AVERAGE(AK80:AL80) -> 459481.45 | AM81: =+AVERAGE(AL80:AM80) -> 460228.78 | AN81: =+AVERAGE(AM80:AN80) -> 484594.88 | AO81: =+AVERAGE(AN80:AO80) -> 496472.81 | AP81: =+AVERAGE(AO80:AP80) -> 491492.39 | ... CO81: =+AVERAGE(CN80:CO80) -> 2683421 | CS81: 1541669.7 | CX81: 1527383.2
A82: ROE % | D82: =D51/D104 -> 0.24558546 | E82: =E51/E104 -> 0.25477848 | F82: =F51/F104 -> 0.1816193 | G82: =G51/G104 -> 0.18833085 | H82: =H51/H104 -> 0.13722348 | I82: =I51/I104 -> 0.14904127 | J82: =J51/J104 -> 0.16976238 | K82: =K51/K104 -> 0.20593477 | ... AE82: =AE51/AE104 -> 0.11919196 | CX82: 0.16922058
A84: Ratios (End)
A85: Valuation (Start)
A87: Share Price
A88: Close | B88: =+'Annual Raw'!C45 -> 0 | C88: =+'Annual Raw'!D45 -> 0 | D88: =+'Annual Raw'!E45 -> 13.850915 | E88: =+'Annual Raw'!F45 -> 28.129807 | F88: =+'Annual Raw'!G45 -> 38.984878 | G88: =+'Annual Raw'!H45 -> 51.921476 | H88: =+'Annual Raw'!I45 -> 37.876026 | I88: =+'Annual Raw'!J45 -> 43.809354 | ... AA88: =+'Annual Raw'!AB45 -> 123.55 | AB88: =+CC88 -> 128 | AC88: =+CG88 -> 128 | AD88: =+CK88 -> 128 | AE88: =+CO88 -> 128 | AH88: =+'QTR Share Price'!IA21 -> 54.071092 | AI88: =+'QTR Share Price'!IB21 -> 54.411528 | AJ88: =+'QTR Share Price'!IC21 -> 45.453177 | AK88: =+'QTR Share Price'!ID21 -> 36.93253 | AL88: =+'QTR Share Price'!IE21 -> 42.49624 | AM88: =+'QTR Share Price'!IF21 -> 59.984965 | AN88: =+'QTR Share Price'!IG21 -> 51.133608 | AO88: =+'QTR Share Price'!IH21 -> 60.6 | ... BY88: =+'QTR Share Price'!JR21 -> 123.55 | BZ88: 128 | CA88: =+BZ88 -> 128 | CB88: =+CA88 -> 128 | CC88: =+CB88 -> 128 | CD88: =+CC88 -> 128 | CE88: =+CD88 -> 128 | CF88: =+CE88 -> 128 | CG88: =+CF88 -> 128 | CH88: =+CG88 -> 128 | ... CO88: =+CN88 -> 128 | CS88: 148.55 | CX88: 123.55
A89: High | B89: =+'Annual Raw'!C46 -> 0 | C89: =+'Annual Raw'!D46 -> 0 | D89: =+'Annual Raw'!E46 -> 14.804138 | E89: =+'Annual Raw'!F46 -> 32.584666 | F89: =+'Annual Raw'!G46 -> 46.990006 | G89: =+'Annual Raw'!H46 -> 58.360595 | H89: =+'Annual Raw'!I46 -> 62.231848 | I89: =+'Annual Raw'!J46 -> 81.98691 | ... AA89: =+'Annual Raw'!AB46 -> 162.9 | AB89: =+MAX(BZ89:CC89) -> 167.59132 | AC89: =+MAX(CD89:CG89) -> 194.09653 | AD89: =+MAX(CH89:CK89) -> 221.29524 | AE89: =+MAX(CL89:CO89) -> 251.06558 | AH89: =+'QTR Share Price'!IA19 -> 80.041556 | AI89: =+'QTR Share Price'!IB19 -> 70.003534 | AJ89: =+'QTR Share Price'!IC19 -> 59.333272 | AK89: =+'QTR Share Price'!ID19 -> 46.591209 | AL89: =+'QTR Share Price'!IE19 -> 43.011759 | AM89: =+'QTR Share Price'!IF19 -> 62.04704 | AN89: =+'QTR Share Price'!IG19 -> 65.98638 | AO89: =+'QTR Share Price'!IH19 -> 61.910865 | ... BY89: =+'QTR Share Price'!JR19 -> 162.9 | BZ89: =+BZ97*BZ65 -> 149.45154 | CA89: =+CA97*CA65 -> 155.59199 | CB89: =+CB97*CB65 -> 161.66827 | CC89: =+CC97*CC65 -> 167.59132 | CD89: =+CD97*CD65 -> 174.38008 | CE89: =+CE97*CE65 -> 180.95615 | CF89: =+CF97*CF65 -> 187.50575 | CG89: =+CG97*CG65 -> 194.09653 | ... CO89: =+CO97*CO65 -> 251.06558 | CS89: 154.2 | CX89: 162.9
A90: Low | B90: =+'Annual Raw'!C47 -> 0 | C90: =+'Annual Raw'!D47 -> 0 | D90: =+'Annual Raw'!E47 -> 7.7814127 | E90: =+'Annual Raw'!F47 -> 13.831461 | F90: =+'Annual Raw'!G47 -> 17.741621 | G90: =+'Annual Raw'!H47 -> 33.177998 | H90: =+'Annual Raw'!I47 -> 32.117781 | I90: =+'Annual Raw'!J47 -> 34.34521 | ... AA90: =+'Annual Raw'!AB47 -> 83.36 | AB90: =+MIN(BZ90:CC90) -> 124.54295 | AC90: =+MIN(CD90:CG90) -> 145.31673 | AD90: =+MIN(CH90:CK90) -> 167.39541 | AE90: =+MIN(CL90:CO90) -> 190.57556 | AH90: =+'QTR Share Price'!IA20 -> 53.448579 | AI90: =+'QTR Share Price'!IB20 -> 48.799184 | AJ90: =+'QTR Share Price'!IC20 -> 45.346183 | AK90: =+'QTR Share Price'!ID20 -> 30.386417 | AL90: =+'QTR Share Price'!IE20 -> 34.199309 | AM90: =+'QTR Share Price'!IF20 -> 42.272525 | AN90: =+'QTR Share Price'!IG20 -> 50.384647 | AO90: =+'QTR Share Price'!IH20 -> 50.034484 | ... BY90: =+'QTR Share Price'!JR20 -> 123 | BZ90: =+BZ98*BZ65 -> 124.54295 | CA90: =+CA98*CA65 -> 129.65999 | CB90: =+CB98*CB65 -> 134.72356 | CC90: =+CC98*CC65 -> 139.65943 | CD90: =+CD98*CD65 -> 145.31673 | CE90: =+CE98*CE65 -> 150.79679 | CF90: =+CF98*CF65 -> 156.2548 | CG90: =+CG98*CG65 -> 161.74711 | ... CO90: =+CO98*CO65 -> 209.22132 | CS90: 121.2 | CX90: 83.36
A92: Upside (%) | BZ92: =+BZ89/BZ88-1 -> 0.16759015 | CA92: =+CA89/CA88-1 -> 0.21556244 | CB92: =+CB89/CB88-1 -> 0.26303335 | CC92: =+CC89/CC88-1 -> 0.30930719 | CD92: =+CD89/CD88-1 -> 0.36234436 | CE92: =+CE89/CE88-1 -> 0.41371989 | CF92: =+CF89/CF88-1 -> 0.4648887 | CG92: =+CG89/CG88-1 -> 0.51637914 | ... CO92: =+CO89/CO88-1 -> 0.96144984
A93: Downside (%) | BZ93: =+BZ90/BZ88-1 -> -0.027008207 | CA93: =+CA90/CA88-1 -> 0.012968699 | CB93: =+CB90/CB88-1 -> 0.052527794 | CC93: =+CC90/CC88-1 -> 0.091089324 | CD93: =+CD90/CD88-1 -> 0.13528697 | CE93: =+CE90/CE88-1 -> 0.17809991 | CF93: =+CF90/CF88-1 -> 0.22074059 | CG93: =+CG90/CG88-1 -> 0.26364928 | ... CO93: =+CO90/CO88-1 -> 0.63454153
A95: P/ABVPS
A96: Close | B96: =+B88/B65 -> #DIV/0! | C96: =+C88/C65 -> 0 | D96: =+D88/D65 -> 4.661938 | E96: =+E88/E65 -> 6.5874965 | F96: =+F88/F65 -> 7.0955286 | G96: =+G88/G65 -> 7.5317034 | H96: =+H88/H65 -> 3.6444219 | I96: =+I88/I65 -> 4.1387381 | ... AE96: =+AE88/AE65 -> 0.58354394 | AH96: =+AH88/AH65 -> #DIV/0! | AI96: =+AI88/AI65 -> 0.11320932 | AJ96: =+AJ88/AJ65 -> 0.10924438 | AK96: =+AK88/AK65 -> 0.18619735 | AL96: =+AL88/AL65 -> 0.22371061 | AM96: =+AM88/AM65 -> 0.31839812 | AN96: =+AN88/AN65 -> 0.27400853 | AO96: =+AO88/AO65 -> 0.30071527 | ... CO96: =+CO88/CO65 -> 0.61179235 | CS96: 1.2621645 | CX96: 1.0360003
A97: High | B97: =B89/B60 -> 0 | C97: =C89/C60 -> 0 | D97: =D89/D65 -> 4.9827736 | E97: =E89/E65 -> 7.6307446 | F97: =F89/F65 -> 8.5525196 | G97: =G89/G65 -> 8.4657588 | H97: =H89/H65 -> 5.987933 | I97: =I89/I65 -> 7.7454315 | J97: =J89/J65 -> 4.1226085 | K97: =K89/K65 -> 6.0522771 | ... AE97: =AE89/AE65 -> 1.1445922 | AH97: =AH89/AH65 -> #DIV/0! | AI97: =AI89/AI65 -> 0.14565025 | AJ97: =AJ89/AJ65 -> 0.14260447 | AK97: =AK89/AK65 -> 0.2348921 | AL97: =AL89/AL65 -> 0.22642442 | AM97: =AM89/AM65 -> 0.32934354 | AN97: =AN89/AN65 -> 0.35359975 | AO97: =AO89/AO65 -> 0.30722017 | ... BY97: =BY89/BY65 -> 1.3659653 | BZ97: 1.2 | CA97: =BZ97 -> 1.2 | CB97: =CA97 -> 1.2 | CC97: =CB97 -> 1.2 | CD97: =CC97 -> 1.2 | CE97: =CD97 -> 1.2 | CF97: =CE97 -> 1.2 | CG97: =CF97 -> 1.2 | CH97: =CG97 -> 1.2 | ... CO97: =CN97 -> 1.2 | CS97: 1.3101701 | CX97: 1.3659608
A98: Low | B98: =B90/B60 -> 0 | C98: =C90/C60 -> 0 | D98: =D90/D65 -> 2.6190663 | E98: =E90/E65 -> 3.2390802 | F98: =F90/F65 -> 3.2291028 | G98: =G90/G65 -> 4.8127839 | H98: =H90/H65 -> 3.0903649 | I98: =I90/I65 -> 3.2446457 | J98: =J90/J65 -> 2.2262086 | K98: =K90/K65 -> 2.172788 | ... AE98: =AE90/AE65 -> 0.86882199 | AH98: =AH90/AH65 -> #DIV/0! | AI98: =AI90/AI65 -> 0.10153221 | AJ98: =AJ90/AJ65 -> 0.10898722 | AK98: =AK90/AK65 -> 0.15319476 | AL98: =AL90/AL65 -> 0.18003353 | AM98: =AM90/AM65 -> 0.2243811 | AN98: =AN90/AN65 -> 0.26999509 | AO98: =AO90/AO65 -> 0.24828603 | ... BY98: =BY90/BY65 -> 1.0313918 | BZ98: 1 | CA98: =BZ98 -> 1 | CB98: =CA98 -> 1 | CC98: =CB98 -> 1 | CD98: =CC98 -> 1 | CE98: =CD98 -> 1 | CF98: =CE98 -> 1 | CG98: =CF98 -> 1 | CH98: =CG98 -> 1 | ... CO98: =CN98 -> 1 | CS98: 1.0297835 | CX98: 0.69899625
A100: Valuation (End)
A101: Balance Sheet (Start)
A102: Share Capital | B102: =+'Annual Raw'!C63 -> 577.8681 | C102: =+'Annual Raw'!D63 -> 577.8681 | D102: =+'Annual Raw'!E63 -> 410 | E102: =+'Annual Raw'!F63 -> 410 | F102: =+'Annual Raw'!G63 -> 410 | G102: =+'Annual Raw'!H63 -> 410 | H102: =+'Annual Raw'!I63 -> 410 | I102: =+'Annual Raw'!J63 -> 410 | ... AA102: =+'Annual Raw'!AB63 -> 1814.1303 | AB102: =CC102 -> 1814.13 | AC102: =CG102 -> 1814.13 | AD102: =CK102 -> 1814.13 | AE102: =CO102 -> 1814.13 | AH102: =+'QTR Raw'!C54 -> 515.2 | AI102: =+'QTR Raw'!D54 -> 542.99 | AJ102: =+'QTR Raw'!E54 -> 542.99 | AK102: =+'QTR Raw'!F54 -> 542.99 | AL102: =+'QTR Raw'!G54 -> 542.99 | AM102: =+'QTR Raw'!H54 -> 542.99 | AN102: =+'QTR Raw'!I54 -> 542.99 | AO102: =+'QTR Raw'!J54 -> 597.29 | ... BW102: =+'QTR Raw'!AR54 -> 1814.13 | BX102: 1814.13 | BY102: =+'QTR Raw'!AT54 -> 1814.13 | BZ102: =BY102 -> 1814.13 | CA102: =BZ102 -> 1814.13 | CB102: =CA102 -> 1814.13 | CC102: =CB102 -> 1814.13 | CD102: =CC102 -> 1814.13 | CE102: =CD102 -> 1814.13 | CF102: =CE102 -> 1814.13 | CG102: =CF102 -> 1814.13 | ... CO102: =CN102 -> 1814.13 | CS102: 1814.13 | CX102: 1814.1303
A103: Total Reserves | B103: =+'Annual Raw'!C65+'Annual Raw'!C64 -> 2236.5819 | C103: =+'Annual Raw'!D65+'Annual Raw'!D64 -> 2893.6269 | D103: =+'Annual Raw'!E65+'Annual Raw'!E64 -> 3738.8283 | E103: =+'Annual Raw'!F65+'Annual Raw'!F64 -> 4841.643 | F103: =+'Annual Raw'!G65+'Annual Raw'!G64 -> 5698.9572 | G103: =+'Annual Raw'!H65+'Annual Raw'!H64 -> 6722.2358 | H103: =+'Annual Raw'!I65+'Annual Raw'!I64 -> 9943.9861 | I103: =+'Annual Raw'!J65+'Annual Raw'!J64 -> 10090.492 | ... AA103: =+'Annual Raw'!AB65+'Annual Raw'!AB64 -> 111568.48 | AB103: =CC103 -> 130874.77 | AC103: =CG103 -> 151823.82 | AD103: =CK103 -> 173435.09 | AE103: =CO103 -> 197150.01 | AH103: =+'QTR Raw'!C56+'QTR Raw'!C55 -> 33377.59 | AI103: =+'QTR Raw'!D56+'QTR Raw'!D55 -> 34937.14 | AJ103: =+'QTR Raw'!E56+'QTR Raw'!E55 -> 34989.23 | AK103: =+'QTR Raw'!F56+'QTR Raw'!F55 -> 31060.21 | AL103: =+'QTR Raw'!G56+'QTR Raw'!G55 -> 31265.61 | AM103: =+'QTR Raw'!H56+'QTR Raw'!H55 -> 31573.82 | AN103: =+'QTR Raw'!I56+'QTR Raw'!I55 -> 31885.71 | AO103: =+'QTR Raw'!J56+'QTR Raw'!J55 -> 33088.25 | ... BW103: =+'QTR Raw'!AR56+'QTR Raw'!AR55 -> 106476.68 | BX103: 111425.09 | BY103: =+'QTR Raw'!AT56+'QTR Raw'!AT55 -> 111568.48 | BZ103: =BY103+BZ51 -> 116416.22 | CA103: =BZ103+CA51 -> 121350.98 | CB103: =CA103+CB51 -> 126157.31 | CC103: =CB103+CC51 -> 130874.77 | CD103: =CC103+CD51 -> 136054.39 | CE103: =CD103+CE51 -> 141367.26 | CF103: =CE103+CF51 -> 146564.8 | CG103: =CF103+CG51 -> 151823.82 | ... CO103: =CN103+CO51 -> 197150.01 | CS103: 111201.6 | CX103: 111568.48
A104: Shareholder's Funds | B104: =SUM(B102:B103) -> 2814.45 | C104: =SUM(C102:C103) -> 3471.495 | D104: =SUM(D102:D103) -> 4148.8283 | E104: =SUM(E102:E103) -> 5251.643 | F104: =SUM(F102:F103) -> 6108.9572 | G104: =SUM(G102:G103) -> 7132.2358 | H104: =SUM(H102:H103) -> 10353.986 | I104: =SUM(I102:I103) -> 10500.492 | ... AE104: =SUM(AE102:AE103) -> 198964.14 | AH104: =SUM(AH102:AH103) -> 33892.79 | AI104: =SUM(AI102:AI103) -> 35480.13 | AJ104: =SUM(AJ102:AJ103) -> 35532.22 | AK104: =SUM(AK102:AK103) -> 31603.2 | AL104: =SUM(AL102:AL103) -> 31808.6 | AM104: =SUM(AM102:AM103) -> 32116.81 | AN104: =SUM(AN102:AN103) -> 32428.7 | AO104: =SUM(AO102:AO103) -> 33685.54 | ... CO104: =SUM(CO102:CO103) -> 198964.14 | CS104: 113015.73 | CX104: 113382.61
A106: Minority Interest | B106: =+'Annual Raw'!C66 -> 0 | C106: =+'Annual Raw'!D66 -> 0 | D106: =+'Annual Raw'!E66 -> 0 | E106: =+'Annual Raw'!F66 -> 0 | F106: =+'Annual Raw'!G66 -> 0 | G106: =+'Annual Raw'!H66 -> 0 | H106: =+'Annual Raw'!I66 -> 0 | I106: =+'Annual Raw'!J66 -> 0 | ... AA106: =+'Annual Raw'!AB66 -> 0 | AB106: =CC106 -> 0 | AC106: =CG106 -> 0 | AD106: =CK106 -> 0 | AE106: =CO106 -> 0 | AH106: =+'QTR Raw'!C57 -> 0 | AI106: =+'QTR Raw'!D57 -> 0 | AJ106: =+'QTR Raw'!E57 -> 0 | AK106: =+'QTR Raw'!F57 -> 0 | AL106: =+'QTR Raw'!G57 -> 0 | AM106: =+'QTR Raw'!H57 -> 0 | AN106: =+'QTR Raw'!I57 -> 0 | AO106: =+'QTR Raw'!J57 -> 0 | ... BW106: =+'QTR Raw'!AR57 -> 0 | BX106: =BW106 -> 0 | BY106: =+'QTR Raw'!AT57 -> 0 | BZ106: =BY106 -> 0 | CA106: =BZ106 -> 0 | CB106: =CA106 -> 0 | CC106: =CB106 -> 0 | CD106: =CC106 -> 0 | CE106: =CD106 -> 0 | CF106: =CE106 -> 0 | CG106: =CF106 -> 0 | ... CO106: =CN106 -> 0 | CS106: 0 | CX106: 0
A108: Deposits | B108: =+'Annual Raw'!C67 -> 59069.528 | C108: =+'Annual Raw'!D67 -> 64030.009 | D108: =+'Annual Raw'!E67 -> 72094.822 | E108: =+'Annual Raw'!F67 -> 86344.557 | F108: =+'Annual Raw'!G67 -> 96795.919 | G108: =+'Annual Raw'!H67 -> 116803.23 | H108: =+'Annual Raw'!I67 -> 142381.45 | I108: =+'Annual Raw'!J67 -> 154072.42 | ... AA108: =+'Annual Raw'!AB67 -> 1568678.1 | AB108: =CC108 -> 1717031.3 | AC108: =CG108 -> 1887785.2 | AD108: =CK108 -> 2076775.4 | AE108: =CO108 -> 2284830 | AH108: =+'QTR Raw'!C58 -> 471876.73 | AI108: =+'QTR Raw'!D58 -> 485205.52 | AJ108: =+'QTR Raw'!E58 -> 490598.87 | AK108: =+'QTR Raw'!F58 -> 479791.56 | AL108: =+'QTR Raw'!G58 -> 465314.16 | AM108: =+'QTR Raw'!H58 -> 484321.25 | AN108: =+'QTR Raw'!I58 -> 510327.47 | AO108: =+'QTR Raw'!J58 -> 495275.24 | ... BW108: =+'QTR Raw'!AR58 -> 1527921.9 | BX108: 1521268.3 | BY108: =+'QTR Raw'!AT58 -> 1568678.1 | BZ108: =+BV108+(BV108*BZ129) -> 1622863.1 | CA108: =+BW108+(BW108*CA129) -> 1691795 | CB108: =+BX108+(BX108*CB129) -> 1675061.1 | CC108: =+BY108+(BY108*CC129) -> 1717031.3 | CD108: =+BZ108+(BZ108*CD129) -> 1788667.6 | CE108: =+CA108+(CA108*CE129) -> 1863126.3 | CF108: =+CB108+(CB108*CF129) -> 1842193.2 | CG108: =+CC108+(CC108*CG129) -> 1887785.2 | ... CO108: =+CK108+(CK108*CO129) -> 2284830 | CS108: 1515903.7 | CX108: 1568678.1
A109: Borrowings | B109: =+'Annual Raw'!C68 -> 1547.8468 | C109: =+'Annual Raw'!D68 -> 267.3984 | D109: =+'Annual Raw'!E68 -> 93.8223 | E109: =+'Annual Raw'!F68 -> 754.897 | F109: =+'Annual Raw'!G68 -> 114.1642 | G109: =+'Annual Raw'!H68 -> 25.824 | H109: =+'Annual Raw'!I68 -> 1574.3517 | I109: =+'Annual Raw'!J68 -> 2517.2322 | ... AA109: =+'Annual Raw'!AB68 -> 155287.68 | AB109: =CC109 -> 155287.68 | AC109: =CG109 -> 155287.68 | AD109: =CK109 -> 155287.68 | AE109: =CO109 -> 155287.68 | AH109: =+'QTR Raw'!C63 -> 23904.81 | AI109: =+'QTR Raw'!D63 -> 24164.87 | AJ109: =+'QTR Raw'!E63 -> 25359.96 | AK109: =+'QTR Raw'!F63 -> 26873.32 | AL109: =+'QTR Raw'!G63 -> 28544.86 | AM109: =+'QTR Raw'!H63 -> 25496.22 | AN109: =+'QTR Raw'!I63 -> 31311.61 | AO109: =+'QTR Raw'!J63 -> 39503.56 | ... BW109: =+'QTR Raw'!AR63 -> 91130.57 | BX109: 147902.37 | BY109: =+'QTR Raw'!AT63 -> 155287.68 | BZ109: =+BY109 -> 155287.68 | CA109: =+BZ109 -> 155287.68 | CB109: =+CA109 -> 155287.68 | CC109: =+CB109 -> 155287.68 | CD109: =+CC109 -> 155287.68 | CE109: =+CD109 -> 155287.68 | CF109: =+CE109 -> 155287.68 | CG109: =+CF109 -> 155287.68 | ... CO109: =+CN109 -> 155287.68 | CS109: 91130.57 | CX109: 155287.68
A110: Debt | B110: =SUM(B108:B109) -> 60617.375 | C110: =SUM(C108:C109) -> 64297.408 | D110: =SUM(D108:D109) -> 72188.645 | E110: =SUM(E108:E109) -> 87099.454 | F110: =SUM(F108:F109) -> 96910.083 | G110: =SUM(G108:G109) -> 116829.06 | H110: =SUM(H108:H109) -> 143955.8 | I110: =SUM(I108:I109) -> 156589.65 | ... AE110: =SUM(AE108:AE109) -> 2440117.7 | AH110: =SUM(AH108:AH109) -> 495781.54 | AI110: =SUM(AI108:AI109) -> 509370.39 | AJ110: =SUM(AJ108:AJ109) -> 515958.83 | AK110: =SUM(AK108:AK109) -> 506664.88 | AL110: =SUM(AL108:AL109) -> 493859.02 | AM110: =SUM(AM108:AM109) -> 509817.47 | AN110: =SUM(AN108:AN109) -> 541639.08 | AO110: =SUM(AO108:AO109) -> 534778.8 | ... CO110: =SUM(CO108:CO109) -> 2440117.7 | CS110: 1607034.3 | CX110: 1723965.8
A111: Sources of Funds | B111: =B110+B106+B104 -> 63431.825 | C111: =C110+C106+C104 -> 67768.903 | D111: =D110+D106+D104 -> 76337.473 | E111: =E110+E106+E104 -> 92351.096 | F111: =F110+F106+F104 -> 103019.04 | G111: =G110+G106+G104 -> 123961.29 | H111: =H110+H106+H104 -> 154309.79 | I111: =I110+I106+I104 -> 167090.15 | ... AE111: =AE110+AE106+AE104 -> 2639081.9 | AH111: =AH110+AH106+AH104 -> 529674.33 | AI111: =AI110+AI106+AI104 -> 544850.52 | AJ111: =AJ110+AJ106+AJ104 -> 551491.05 | AK111: =AK110+AK106+AK104 -> 538268.08 | AL111: =AL110+AL106+AL104 -> 525667.62 | AM111: =AM110+AM106+AM104 -> 541934.28 | AN111: =AN110+AN106+AN104 -> 574067.78 | AO111: =AO110+AO106+AO104 -> 568464.34 | ... CO111: =CO110+CO106+CO104 -> 2639081.9 | CS111: 1720050 | CX111: 1837348.4
A113: Investments | B113: =+'Annual Raw'!C73 -> 21445.461 | C113: =+'Annual Raw'!D73 -> 23220.106 | D113: =+'Annual Raw'!E73 -> 30458.244 | E113: =+'Annual Raw'!F73 -> 35792.989 | F113: =+'Annual Raw'!G73 -> 38053.884 | G113: =+'Annual Raw'!H73 -> 36974.183 | H113: =+'Annual Raw'!I73 -> 45225.538 | I113: =+'Annual Raw'!J73 -> 49811.572 | ... AA113: =+'Annual Raw'!AB73 -> 403414.58 | AB113: =CC113 -> 445419.87 | AC113: =CG113 -> 486887.7 | AD113: =CK113 -> 531971.72 | AE113: =CO113 -> 581545.79 | AH113: =+'QTR Raw'!C68 -> 149576.93 | AI113: =+'QTR Raw'!D68 -> 153230.45 | AJ113: =+'QTR Raw'!E68 -> 155887.85 | AK113: =+'QTR Raw'!F68 -> 142309.3 | AL113: =+'QTR Raw'!G68 -> 130655.49 | AM113: =+'QTR Raw'!H68 -> 141389.48 | AN113: =+'QTR Raw'!I68 -> 169034.59 | AO113: =+'QTR Raw'!J68 -> 150265.89 | ... BW113: =+'QTR Raw'!AR68 -> 394610.93 | BX113: 394736.39 | BY113: =+'QTR Raw'!AT68 -> 403414.58 | BZ113: =+BZ110*BZ131 -> 428769.98 | CA113: =+CA110*CA131 -> 441153.74 | CB113: =+CB110*CB131 -> 434918.76 | CC113: =+CC110*CC131 -> 445419.87 | CD113: =+CD110*CD131 -> 464354.2 | CE113: =+CE110*CE131 -> 480998.94 | CF113: =+CF110*CF131 -> 475744.46 | CG113: =+CG110*CG131 -> 486887.7 | ... CO113: =+CO110*CO131 -> 581545.79 | CS113: 401544.12 | CX113: 403414.58
A114: Advances | B114: =+'Annual Raw'!C74 -> 27831.771 | C114: =+'Annual Raw'!D74 -> 33126.705 | D114: =+'Annual Raw'!E74 -> 40471.598 | E114: =+'Annual Raw'!F74 -> 47638.628 | F114: =+'Annual Raw'!G74 -> 60421.404 | G114: =+'Annual Raw'!H74 -> 79425.7 | H114: =+'Annual Raw'!I74 -> 98505.687 | I114: =+'Annual Raw'!J74 -> 107238.04 | ... AA114: =+'Annual Raw'!AB74 -> 1220017.5 | AB114: =CC114 -> 1407221.2 | AC114: =CG114 -> 1621300.1 | AD114: =CK114 -> 1867698.4 | AE114: =CO114 -> 2151521 | AH114: =+'QTR Raw'!C69 -> 324062.92 | AI114: =+'QTR Raw'!D69 -> 323077.46 | AJ114: =+'QTR Raw'!E69 -> 331914.86 | AK114: =+'QTR Raw'!F69 -> 324714.83 | AL114: =+'QTR Raw'!G69 -> 321283.28 | AM114: =+'QTR Raw'!H69 -> 327129.31 | AN114: =+'QTR Raw'!I69 -> 331636.38 | AO114: =+'QTR Raw'!J69 -> 342008.76 | ... BW114: =+'QTR Raw'!AR69 -> 1130113.9 | BX114: 1172815.7 | BY114: =+'QTR Raw'!AT69 -> 1220017.5 | BZ114: =+BV114+(BV114*BZ130) -> 1232295.8 | CA114: =+BW114+(BW114*CA130) -> 1300979.8 | CB114: =+BX114+(BX114*CB130) -> 1350944.7 | CC114: =+BY114+(BY114*CC130) -> 1407221.2 | CD114: =+BZ114+(BZ114*CD130) -> 1418483.4 | CE114: =+CA114+(CA114*CE130) -> 1498601.4 | CF114: =+CB114+(CB114*CF130) -> 1556395.5 | CG114: =+CC114+(CC114*CG130) -> 1621300.1 | ... CO114: =+CK114+(CK114*CO130) -> 2151521 | CS114: 1157070.5 | CX114: 1220017.5
A116: FA | B116: =+'Annual Raw'!C78+'Annual Raw'!C79+'Annual Raw'!C80 -> 649.6478 | C116: =+'Annual Raw'!D78+'Annual Raw'!D79+'Annual Raw'!D80 -> 659.0125 | D116: =+'Annual Raw'!E78+'Annual Raw'!E79+'Annual Raw'!E80 -> 659.6163 | E116: =+'Annual Raw'!F78+'Annual Raw'!F79+'Annual Raw'!F80 -> 680.1955 | F116: =+'Annual Raw'!G78+'Annual Raw'!G79+'Annual Raw'!G80 -> 672.8143 | G116: =+'Annual Raw'!H78+'Annual Raw'!H79+'Annual Raw'!H80 -> 688.4717 | H116: =+'Annual Raw'!I78+'Annual Raw'!I79+'Annual Raw'!I80 -> 2861.3535 | I116: =+'Annual Raw'!J78+'Annual Raw'!J79+'Annual Raw'!J80 -> 2916.8725 | ... AA116: =+'Annual Raw'!AB78+'Annual Raw'!AB79+'Annual Raw'!AB80 -> 10570.436 | AC116: =CG116 -> 0 | AD116: =CK116 -> 0 | AE116: =CO116 -> 0 | AH116: =+'QTR Raw'!C73 -> 7089.9 | AI116: =+'QTR Raw'!D73 -> 7212 | AJ116: =+'QTR Raw'!E73 -> 7183.46 | AK116: =+'QTR Raw'!F73 -> 7198.1 | AL116: =+'QTR Raw'!G73 -> 7160.95 | AM116: =+'QTR Raw'!H73 -> 7151.6 | AN116: =+'QTR Raw'!I73 -> 7170.57 | AO116: =+'QTR Raw'!J73 -> 7168.31 | ... BW116: =+'QTR Raw'!AR73 -> 10147.93 | BX116: 10341.84 | BY116: =+'QTR Raw'!AT73 -> 10570.44 | CX116: 10570.436
A117: CA | B117: =+'Annual Raw'!C71+'Annual Raw'!C72+'Annual Raw'!C81 -> 16593.763 | C117: =+'Annual Raw'!D71+'Annual Raw'!D72+'Annual Raw'!D81 -> 15129.322 | D117: =+'Annual Raw'!E71+'Annual Raw'!E72+'Annual Raw'!E81 -> 10465.472 | E117: =+'Annual Raw'!F71+'Annual Raw'!F72+'Annual Raw'!F81 -> 15427.58 | F117: =+'Annual Raw'!G71+'Annual Raw'!G72+'Annual Raw'!G81 -> 11157.072 | G117: =+'Annual Raw'!H71+'Annual Raw'!H72+'Annual Raw'!H81 -> 15733.504 | H117: =+'Annual Raw'!I71+'Annual Raw'!I72+'Annual Raw'!I81 -> 19368.464 | I117: =+'Annual Raw'!J71+'Annual Raw'!J72+'Annual Raw'!J81 -> 20562.207 | ... AA117: =+'Annual Raw'!AB71+'Annual Raw'!AB72+'Annual Raw'!AB81 -> 249199.4 | AC117: =CG117 -> 0 | AD117: =CK117 -> 0 | AE117: =CO117 -> 0 | AH117: =+'QTR Raw'!C66+'QTR Raw'!C67+'QTR Raw'!C77+'QTR Raw'!C78 -> 63938.9 | AI117: =+'QTR Raw'!D66+'QTR Raw'!D67+'QTR Raw'!D77+'QTR Raw'!D78 -> 75328.54 | AJ117: =+'QTR Raw'!E66+'QTR Raw'!E67+'QTR Raw'!E77+'QTR Raw'!E78 -> 71699.8 | AK117: =+'QTR Raw'!F66+'QTR Raw'!F67+'QTR Raw'!F77+'QTR Raw'!F78 -> 78738.55 | AL117: =+'QTR Raw'!G66+'QTR Raw'!G67+'QTR Raw'!G77+'QTR Raw'!G78 -> 80667.49 | AM117: =+'QTR Raw'!H66+'QTR Raw'!H67+'QTR Raw'!H77+'QTR Raw'!H78 -> 86462.3 | AN117: =+'QTR Raw'!I66+'QTR Raw'!I67+'QTR Raw'!I77+'QTR Raw'!I78 -> 83174.41 | AO117: =+'QTR Raw'!J66+'QTR Raw'!J67+'QTR Raw'!J77+'QTR Raw'!J78 -> 84076.48 | ... BW117: =+'QTR Raw'!AR66+'QTR Raw'!AR67+'QTR Raw'!AR77+'QTR Raw'!AR78 -> 230012.14 | BX117: =49715.83+152708.42+42038.6 -> 244462.85 | BY117: =+'QTR Raw'!AT66+'QTR Raw'!AT67+'QTR Raw'!AT77+'QTR Raw'!AT78 -> 249199.4 | CX117: 249199.4
A118: CL | B118: =+'Annual Raw'!C69 -> 3088.8171 | C118: =+'Annual Raw'!D69 -> 4366.2429 | D118: =+'Annual Raw'!E69 -> 5717.4575 | E118: =+'Annual Raw'!F69 -> 7188.2958 | F118: =+'Annual Raw'!G69 -> 7286.1333 | G118: =+'Annual Raw'!H69 -> 8860.567 | H118: =+'Annual Raw'!I69 -> 11651.253 | I118: =+'Annual Raw'!J69 -> 13438.545 | ... AA118: =+'Annual Raw'!AB69 -> 45853.449 | AC118: =CG118 -> 0 | AD118: =CK118 -> 0 | AE118: =CO118 -> 0 | AH118: =+'QTR Raw'!C64 -> 14994.32 | AI118: =+'QTR Raw'!D64 -> 13997.93 | AJ118: =+'QTR Raw'!E64 -> 15194.92 | AK118: =+'QTR Raw'!F64 -> 14692.7 | AL118: =+'QTR Raw'!G64 -> 14099.59 | AM118: =+'QTR Raw'!H64 -> 20198.41 | AN118: =+'QTR Raw'!I64 -> 16948.17 | AO118: =+'QTR Raw'!J64 -> 15055.1 | ... BW118: =+'QTR Raw'!AR64 -> 37541.62 | BX118: 39946.87 | BY118: =+'QTR Raw'!AT64 -> 45853.45 | CX118: 45853.449
A120: NWC | B120: =+B117-B118 -> 13504.946 | C120: =+C117-C118 -> 10763.079 | D120: =+D117-D118 -> 4748.0145 | E120: =+E117-E118 -> 8239.2838 | F120: =+F117-F118 -> 3870.9382 | G120: =+G117-G118 -> 6872.9372 | H120: =+H117-H118 -> 7717.2108 | I120: =+I117-I118 -> 7123.6615 | ... AA120: =+AA117-AA118 -> 203345.95 | AB120: =CC120 -> 152366.8 | AC120: =CG120 -> 88523.053 | AD120: =CK120 -> 7642.2472 | AE120: =CO120 -> -93984.88 | AH120: =+AH117-AH118 -> 48944.58 | AI120: =+AI117-AI118 -> 61330.61 | AJ120: =+AJ117-AJ118 -> 56504.88 | AK120: =+AK117-AK118 -> 64045.85 | AL120: =+AL117-AL118 -> 66567.9 | AM120: =+AM117-AM118 -> 66263.89 | AN120: =+AN117-AN118 -> 66226.24 | AO120: =+AO117-AO118 -> 69021.38 | ... BY120: =+BY117-BY118 -> 203345.95 | BZ120: =+BZ111-BZ113-BZ114 -> 235315.37 | CA120: =+CA111-CA113-CA114 -> 228114.31 | CB120: =+CB111-CB113-CB114 -> 172456.72 | CC120: =+CC111-CC113-CC114 -> 152366.8 | CD120: =+CD111-CD113-CD114 -> 198986.17 | CE120: =+CE111-CE113-CE114 -> 181994.96 | CF120: =+CF111-CF113-CF114 -> 113719.89 | CG120: =+CG111-CG113-CG114 -> 88523.053 | ... CO120: =+CO111-CO113-CO114 -> -93984.88 | CS120: 161435.46 | CX120: 203345.95
A123: Application of Funds | B123: =+B120+B116+B114+B113 -> 63431.825 | C123: =+C120+C116+C114+C113 -> 67768.903 | D123: =+D120+D116+D114+D113 -> 76337.473 | E123: =+E120+E116+E114+E113 -> 92351.096 | F123: =+F120+F116+F114+F113 -> 103019.04 | G123: =+G120+G116+G114+G113 -> 123961.29 | H123: =+H120+H116+H114+H113 -> 154309.79 | I123: =+I120+I116+I114+I113 -> 167090.15 | ... AE123: =+AE120+AE116+AE114+AE113 -> 2639081.9 | AH123: =+AH113+AH114+AH116+AH120+AH122 -> 529674.33 | AI123: =+AI113+AI114+AI116+AI120+AI122 -> 544850.52 | AJ123: =+AJ113+AJ114+AJ116+AJ120+AJ122 -> 551491.05 | AK123: =+AK113+AK114+AK116+AK120+AK122 -> 538268.08 | AL123: =+AL113+AL114+AL116+AL120+AL122 -> 525667.62 | AM123: =+AM113+AM114+AM116+AM120+AM122 -> 541934.28 | AN123: =+AN113+AN114+AN116+AN120+AN122 -> 574067.78 | AO123: =+AO113+AO114+AO116+AO120+AO122 -> 568464.34 | ... CO123: =+CO113+CO114+CO116+CO120+CO122 -> 2639081.9 | CS123: 1720050 | CX123: 1837348.4
...

Sheet Share price Daily
A1: =_xll.EQNXTH(B1,"[ADJC];[ADJH];[ADJL];[ADJO];[UCLS];[VOLUME]","2015-Jan-01","Y","All traded days","Asc") -> EQNXTH | B1: =+'Annual Raw'!A1 -> 132483 | L1: =_xll.EQNXTH(B1,"[NADJC];[NADJH];[NADJLOW];[NADJOPEN];[NUCLOSE];[NVOLUME]","2015-Jan-01","Y","All traded days","Asc") -> EQNXTH
A2: Canara Bank | L2: Canara Bank
A3: DATE | B3: ADJHIGH | C3: ADJCLOSE | D3: ADJLOW | E3: ADJOPEN | F3: CLOSE | G3: VOLUME | L3: DATE | M3: ADJCLOSE | N3: ADJHIGH | O3: ADJLOW | P3: ADJOPEN | Q3: CLOSE | R3: VOLUME
A4: 42005 | B4: 88.066138 | C4: 87.453352 | D4: 87.122642 | E4: 87.229636 | F4: 449.55 | G4: 96217 | L4: 42005 | M4: 87.393062 | N4: 88.025287 | O4: 87.052632 | P4: 87.344429 | Q4: 449.25 | R4: 822446
A5: 42006 | B5: 88.678925 | C5: 87.336631 | D5: 86.967014 | E5: 87.735428 | F5: 448.95 | G5: 163216 | L5: 42006 | M5: 87.276343 | N5: 88.608881 | O5: 87.013726 | P5: 88.064194 | Q5: 448.65 | R5: 1552797
A6: 42009 | B6: 88.124499 | C6: 87.540893 | D6: 86.694664 | E6: 87.540893 | F6: 450 | G6: 142232 | L6: 42009 | M6: 87.616772 | N6: 88.151733 | O6: 86.66357 | P6: 87.383335 | Q6: 450.4 | R6: 1444209
A7: 42010 | B7: 87.054555 | C7: 85.080021 | D7: 84.739584 | E7: 87.054555 | F7: 437.35 | G7: 164083 | L7: 42010 | M7: 85.194861 | N7: 86.916461 | O7: 84.854432 | P7: 86.585758 | Q7: 437.95 | R7: 1863201
A8: 42011 | B8: 85.469092 | C8: 84.973027 | D8: 83.805815 | E8: 84.233793 | F8: 436.8 | G8: 143924 | L8: 42011 | M8: 85.048963 | N8: 85.554744 | O8: 83.745605 | P8: 84.620995 | Q8: 437.2 | R8: 1464071
A9: 42012 | B9: 88.377395 | C9: 88.036958 | D9: 85.401004 | E9: 85.809529 | F9: 452.55 | G9: 132504 | L9: 42012 | M9: 87.918295 | N9: 88.210092 | O9: 85.331033 | P9: 85.982712 | Q9: 451.95 | R9: 1579533
A10: 42013 | B10: 88.747012 | C10: 85.692807 | D10: 85.080021 | E10: 88.51357 | F10: 440.5 | G10: 199133 | L10: 42013 | M10: 85.739548 | N10: 88.793685 | O10: 85.010057 | P10: 88.793685 | Q10: 440.75 | R10: 1890184
A11: 42016 | B11: 87.074008 | C11: 86.441768 | D11: 84.613136 | E11: 85.401004 | F11: 444.35 | G11: 182974 | L11: 42016 | M11: 86.556578 | N11: 87.072085 | O11: 84.543182 | P11: 85.360212 | Q11: 444.95 | R11: 1298682
A12: 42017 | B12: 87.151822 | C12: 86.519583 | D12: 85.702534 | E12: 86.646031 | F12: 444.75 | G12: 115582 | L12: 42017 | M12: 86.507946 | N12: 87.169351 | O12: 85.652009 | P12: 86.712203 | Q12: 444.7 | R12: 1542933
A13: 42018 | B13: 86.879473 | C13: 85.32319 | D13: 84.768765 | E13: 86.081878 | F13: 438.6 | G13: 106996 | L13: 42018 | M13: 85.321306 | N13: 86.867828 | O13: 84.737713 | P13: 86.760836 | Q13: 438.6 | R13: 946520
A14: 42019 | B14: 90.916081 | C14: 88.824826 | D14: 87.929964 | E14: 90.283841 | F14: 456.6 | G14: 349202 | L14: 42019 | M14: 89.046575 | N14: 91.069698 | O14: 87.918295 | P14: 90.534738 | Q14: 457.75 | R14: 2264066
A15: 42020 | B15: 89.447339 | C15: 88.299581 | D15: 87.793789 | E15: 88.90264 | F15: 453.9 | G15: 118831 | L15: 42020 | M15: 88.492162 | N15: 89.464817 | O15: 87.772397 | P15: 89.066028 | Q15: 454.9 | R15: 1202830
... A2838: 46185 | B2838: 131.9 | C2838: 131.6 | D2838: 128.8 | E2838: 130.1 | F2838: 131.6 | G2838: 1802030 | L2838: 46185 | M2838: 131.67 | N2838: 131.92 | O2838: 128.8 | P2838: 130 | Q2838: 131.67 | R2838: 25287693

Sheet QTR Raw
A1: =+'Annual Raw'!A1 -> 132483
C2: 201506 | D2: 201509 | E2: 201512 | F2: 201603 | G2: 201606 | H2: 201609 | I2: 201612 | J2: 201703 | K2: 201706 | L2: 201709 | M2: 201712 | N2: 201803 | O2: 201806 | P2: 201809 | Q2: 201812 | R2: 201903 | S2: 201906 | T2: 201909 | U2: 201912 | V2: 202003 | W2: 202006 | X2: 202009 | Y2: 202012 | Z2: 202103 | AA2: 202106 | AB2: 202109 | AC2: 202112 | AD2: 202203 | AE2: 202206 | AF2: 202209 | AG2: 202212 | AH2: 202303 | AI2: 202306 | AJ2: 202309 | AK2: 202312 | AL2: 202403 | AM2: 202406 | AN2: 202409 | AO2: 202412 | AP2: 202503 | AQ2: 202506 | AR2: 202509 | AS2: 202512 | AT2: 202603 | AU2: 202606 | AV2: 202609 | AW2: 202612 | AX2: 202703 | AY2: 202706 | AZ2: 202709 | BA2: 202712 | BB2: 202803 | BC2: 202806 | BD2: 202809 | BE2: 202812 | BF2: 202903 | BG2: 202906 | BH2: 202909 | BI2: 202912 | BJ2: 203003
A4: Field Description | B4: Field Name
A5: Date End | B5: BQTR_DATE_END | C5: {=+_xll.EQNXTDZ($A$1,$B5,C$2)} -> 201506 | D5: {=+_xll.EQNXTDZ($A$1,$B5,D$2)} -> 201509 | E5: {=+_xll.EQNXTDZ($A$1,$B5,E$2)} -> 201512 | F5: {=+_xll.EQNXTDZ($A$1,$B5,F$2)} -> 201603 | G5: {=+_xll.EQNXTDZ($A$1,$B5,G$2)} -> 201606 | H5: {=+_xll.EQNXTDZ($A$1,$B5,H$2)} -> 201609 | I5: {=+_xll.EQNXTDZ($A$1,$B5,I$2)} -> 201612 | J5: {=+_xll.EQNXTDZ($A$1,$B5,J$2)} -> 201703 | ... BJ5: {=+_xll.EQNXTDZ($A$1,$B5,BJ$2)} -> 0
A6: Interest Earned | B6: BQTR_NET_SALES | C6: {=+_xll.EQNXTDZ($A$1,$B6,C$2)} -> 11139.65 | D6: {=+_xll.EQNXTDZ($A$1,$B6,D$2)} -> 11267.5 | E6: {=+_xll.EQNXTDZ($A$1,$B6,E$2)} -> 10882.07 | F6: {=+_xll.EQNXTDZ($A$1,$B6,F$2)} -> 10732.91 | G6: {=+_xll.EQNXTDZ($A$1,$B6,G$2)} -> 10201.7 | H6: {=+_xll.EQNXTDZ($A$1,$B6,H$2)} -> 10405.35 | I6: {=+_xll.EQNXTDZ($A$1,$B6,I$2)} -> 10287.67 | J6: {=+_xll.EQNXTDZ($A$1,$B6,J$2)} -> 10492.92 | ... BJ6: {=+_xll.EQNXTDZ($A$1,$B6,BJ$2)} -> 0
A7: Other Income | B7: BQTR_OTHER_INCOME | C7: {=+_xll.EQNXTDZ($A$1,$B7,C$2)} -> 1112.99 | D7: {=+_xll.EQNXTDZ($A$1,$B7,D$2)} -> 1210.45 | E7: {=+_xll.EQNXTDZ($A$1,$B7,E$2)} -> 1168.56 | F7: {=+_xll.EQNXTDZ($A$1,$B7,F$2)} -> 1383.23 | G7: {=+_xll.EQNXTDZ($A$1,$B7,G$2)} -> 1584.65 | H7: {=+_xll.EQNXTDZ($A$1,$B7,H$2)} -> 1781.77 | I7: {=+_xll.EQNXTDZ($A$1,$B7,I$2)} -> 1791.7 | J7: {=+_xll.EQNXTDZ($A$1,$B7,J$2)} -> 2396.28 | ... BJ7: {=+_xll.EQNXTDZ($A$1,$B7,BJ$2)} -> 0
A8: Total Income | B8: BQTR_TOTAL_INCOME | C8: {=+_xll.EQNXTDZ($A$1,$B8,C$2)} -> 12252.64 | D8: {=+_xll.EQNXTDZ($A$1,$B8,D$2)} -> 12477.95 | E8: {=+_xll.EQNXTDZ($A$1,$B8,E$2)} -> 12050.63 | F8: {=+_xll.EQNXTDZ($A$1,$B8,F$2)} -> 12116.14 | G8: {=+_xll.EQNXTDZ($A$1,$B8,G$2)} -> 11786.35 | H8: {=+_xll.EQNXTDZ($A$1,$B8,H$2)} -> 12187.12 | I8: {=+_xll.EQNXTDZ($A$1,$B8,I$2)} -> 12079.37 | J8: {=+_xll.EQNXTDZ($A$1,$B8,J$2)} -> 12889.2 | ... BJ8: {=+_xll.EQNXTDZ($A$1,$B8,BJ$2)} -> 0
A9: Interest Expended | B9: BQTR_INTEREST | C9: {=+_xll.EQNXTDZ($A$1,$B9,C$2)} -> 8623.15 | D9: {=+_xll.EQNXTDZ($A$1,$B9,D$2)} -> 8621 | E9: {=+_xll.EQNXTDZ($A$1,$B9,E$2)} -> 8655.47 | F9: {=+_xll.EQNXTDZ($A$1,$B9,F$2)} -> 8359.15 | G9: {=+_xll.EQNXTDZ($A$1,$B9,G$2)} -> 7894.3 | H9: {=+_xll.EQNXTDZ($A$1,$B9,H$2)} -> 7963 | I9: {=+_xll.EQNXTDZ($A$1,$B9,I$2)} -> 7873.87 | J9: {=+_xll.EQNXTDZ($A$1,$B9,J$2)} -> 7784.7 | ... BJ9: {=+_xll.EQNXTDZ($A$1,$B9,BJ$2)} -> 0
A10: Operating Expenses | B10: BQTR_OPERATING_EX | C10: {=+_xll.EQNXTDZ($A$1,$B10,C$2)} -> 1625.92 | D10: {=+_xll.EQNXTDZ($A$1,$B10,D$2)} -> 1912.85 | E10: {=+_xll.EQNXTDZ($A$1,$B10,E$2)} -> 1842.72 | F10: {=+_xll.EQNXTDZ($A$1,$B10,F$2)} -> 2110.44 | G10: {=+_xll.EQNXTDZ($A$1,$B10,G$2)} -> 2073.18 | H10: {=+_xll.EQNXTDZ($A$1,$B10,H$2)} -> 2083.35 | I10: {=+_xll.EQNXTDZ($A$1,$B10,I$2)} -> 2224.17 | J10: {=+_xll.EQNXTDZ($A$1,$B10,J$2)} -> 2131.58 | ... BJ10: {=+_xll.EQNXTDZ($A$1,$B10,BJ$2)} -> 0
A11: Payment To Provisions For Employees | B11: BQTR_PROV_EMP | C11: {=+_xll.EQNXTDZ($A$1,$B11,C$2)} -> 1058.75 | D11: {=+_xll.EQNXTDZ($A$1,$B11,D$2)} -> 1107.84 | E11: {=+_xll.EQNXTDZ($A$1,$B11,E$2)} -> 1039.75 | F11: {=+_xll.EQNXTDZ($A$1,$B11,F$2)} -> 1239.54 | G11: {=+_xll.EQNXTDZ($A$1,$B11,G$2)} -> 1208.17 | H11: {=+_xll.EQNXTDZ($A$1,$B11,H$2)} -> 1216.94 | I11: {=+_xll.EQNXTDZ($A$1,$B11,I$2)} -> 1305.74 | J11: {=+_xll.EQNXTDZ($A$1,$B11,J$2)} -> 1184.24 | ... BJ11: {=+_xll.EQNXTDZ($A$1,$B11,BJ$2)} -> 0
A12: Depreciation | B12: BQTR_DEPRECIATION | C12: {=+_xll.EQNXTDZ($A$1,$B12,C$2)} -> 0 | D12: {=+_xll.EQNXTDZ($A$1,$B12,D$2)} -> 0 | E12: {=+_xll.EQNXTDZ($A$1,$B12,E$2)} -> 0 | F12: {=+_xll.EQNXTDZ($A$1,$B12,F$2)} -> 0 | G12: {=+_xll.EQNXTDZ($A$1,$B12,G$2)} -> 0 | H12: {=+_xll.EQNXTDZ($A$1,$B12,H$2)} -> 0 | I12: {=+_xll.EQNXTDZ($A$1,$B12,I$2)} -> 0 | J12: {=+_xll.EQNXTDZ($A$1,$B12,J$2)} -> 0 | ... BJ12: {=+_xll.EQNXTDZ($A$1,$B12,BJ$2)} -> 0
A13: Total Expenditure | B13: BQTR_EXPENDITURE | C13: {=+_xll.EQNXTDZ($A$1,$B13,C$2)} -> 1625.92 | D13: {=+_xll.EQNXTDZ($A$1,$B13,D$2)} -> 1912.85 | E13: {=+_xll.EQNXTDZ($A$1,$B13,E$2)} -> 1842.72 | F13: {=+_xll.EQNXTDZ($A$1,$B13,F$2)} -> 2110.44 | G13: {=+_xll.EQNXTDZ($A$1,$B13,G$2)} -> 2073.18 | H13: {=+_xll.EQNXTDZ($A$1,$B13,H$2)} -> 2083.35 | I13: {=+_xll.EQNXTDZ($A$1,$B13,I$2)} -> 2224.17 | J13: {=+_xll.EQNXTDZ($A$1,$B13,J$2)} -> 2131.58 | ... BJ13: {=+_xll.EQNXTDZ($A$1,$B13,BJ$2)} -> 0
A14: Operating Profit before Prov.& Cont. | B14: BQTR_OPERATING_PROFIT | C14: {=+_xll.EQNXTDZ($A$1,$B14,C$2)} -> 2003.57 | D14: {=+_xll.EQNXTDZ($A$1,$B14,D$2)} -> 1944.1 | E14: {=+_xll.EQNXTDZ($A$1,$B14,E$2)} -> 1552.44 | F14: {=+_xll.EQNXTDZ($A$1,$B14,F$2)} -> 1646.55 | G14: {=+_xll.EQNXTDZ($A$1,$B14,G$2)} -> 1818.87 | H14: {=+_xll.EQNXTDZ($A$1,$B14,H$2)} -> 2140.77 | I14: {=+_xll.EQNXTDZ($A$1,$B14,I$2)} -> 1981.33 | J14: {=+_xll.EQNXTDZ($A$1,$B14,J$2)} -> 2972.92 | ... BJ14: {=+_xll.EQNXTDZ($A$1,$B14,BJ$2)} -> 0
A15: Exceptional Items | B15: BQTR_EXCEPTION_ITEMS | C15: {=+_xll.EQNXTDZ($A$1,$B15,C$2)} -> 0 | D15: {=+_xll.EQNXTDZ($A$1,$B15,D$2)} -> 0 | E15: {=+_xll.EQNXTDZ($A$1,$B15,E$2)} -> 0 | F15: {=+_xll.EQNXTDZ($A$1,$B15,F$2)} -> 0 | G15: {=+_xll.EQNXTDZ($A$1,$B15,G$2)} -> 0 | H15: {=+_xll.EQNXTDZ($A$1,$B15,H$2)} -> 0 | I15: {=+_xll.EQNXTDZ($A$1,$B15,I$2)} -> 0 | J15: {=+_xll.EQNXTDZ($A$1,$B15,J$2)} -> 0 | ... BJ15: {=+_xll.EQNXTDZ($A$1,$B15,BJ$2)} -> 0
A16: Foreign Exchange Gain / Loss | B16: BQTR_EXC_FOREIGN_EXCH_GAIN | C16: {=+_xll.EQNXTDZ($A$1,$B16,C$2)} -> 0 | D16: {=+_xll.EQNXTDZ($A$1,$B16,D$2)} -> 0 | E16: {=+_xll.EQNXTDZ($A$1,$B16,E$2)} -> 0 | F16: {=+_xll.EQNXTDZ($A$1,$B16,F$2)} -> 0 | G16: {=+_xll.EQNXTDZ($A$1,$B16,G$2)} -> 0 | H16: {=+_xll.EQNXTDZ($A$1,$B16,H$2)} -> 0 | I16: {=+_xll.EQNXTDZ($A$1,$B16,I$2)} -> 0 | J16: {=+_xll.EQNXTDZ($A$1,$B16,J$2)} -> 0 | ... BJ16: {=+_xll.EQNXTDZ($A$1,$B16,BJ$2)} -> 0
... A48: NIM % | B48: BQTR_NIM | C48: {=+_xll.EQNXTDZ($A$1,$B48,C$2)} -> 2.21 | D48: {=+_xll.EQNXTDZ($A$1,$B48,D$2)} -> 2.38 | E48: {=+_xll.EQNXTDZ($A$1,$B48,E$2)} -> 2.29 | F48: {=+_xll.EQNXTDZ($A$1,$B48,F$2)} -> 2.34 | G48: {=+_xll.EQNXTDZ($A$1,$B48,G$2)} -> 2.29 | H48: {=+_xll.EQNXTDZ($A$1,$B48,H$2)} -> 2.35 | I48: {=+_xll.EQNXTDZ($A$1,$B48,I$2)} -> 2.34 | J48: {=+_xll.EQNXTDZ($A$1,$B48,J$2)} -> 2.39 | ... BJ48: {=+_xll.EQNXTDZ($A$1,$B48,BJ$2)} -> 0
C51: =C5 -> 201506 | D51: =D5 -> 201509 | E51: =E5 -> 201512 | F51: =F5 -> 201603 | G51: =G5 -> 201606 | H51: =H5 -> 201609 | I51: =I5 -> 201612 | J51: =J5 -> 201703 | ... BJ51: =BJ5 -> 0
A52: Field Description | B52: Field Name
A53: Year End | B53: BQTRB_DATE_END | C53: {=+_xll.EQNXTDZ($A$1,$B53,C$51)} -> 201506 | D53: {=+_xll.EQNXTDZ($A$1,$B53,D$51)} -> 201509 | E53: {=+_xll.EQNXTDZ($A$1,$B53,E$51)} -> 201512 | F53: {=+_xll.EQNXTDZ($A$1,$B53,F$51)} -> 201603 | G53: {=+_xll.EQNXTDZ($A$1,$B53,G$51)} -> 201606 | H53: {=+_xll.EQNXTDZ($A$1,$B53,H$51)} -> 201609 | I53: {=+_xll.EQNXTDZ($A$1,$B53,I$51)} -> 201612 | J53: {=+_xll.EQNXTDZ($A$1,$B53,J$51)} -> 201703 | ... BJ53: {=+_xll.EQNXTDZ($A$1,$B53,BJ$51)} -> 0
A54: Share Capital | B54: BQTRB_SHARE_CAPITAL | C54: {=+_xll.EQNXTDZ($A$1,$B54,C$51)} -> 515.2 | D54: {=+_xll.EQNXTDZ($A$1,$B54,D$51)} -> 542.99 | E54: {=+_xll.EQNXTDZ($A$1,$B54,E$51)} -> 542.99 | F54: {=+_xll.EQNXTDZ($A$1,$B54,F$51)} -> 542.99 | G54: {=+_xll.EQNXTDZ($A$1,$B54,G$51)} -> 542.99 | H54: {=+_xll.EQNXTDZ($A$1,$B54,H$51)} -> 542.99 | I54: {=+_xll.EQNXTDZ($A$1,$B54,I$51)} -> 542.99 | J54: {=+_xll.EQNXTDZ($A$1,$B54,J$51)} -> 597.29 | ... BJ54: {=+_xll.EQNXTDZ($A$1,$B54,BJ$51)} -> 0
A55: Share Warrants & outstandings | B55: BQTRB_SHAREWARRANTS | C55: {=+_xll.EQNXTDZ($A$1,$B55,C$51)} -> 0 | D55: {=+_xll.EQNXTDZ($A$1,$B55,D$51)} -> 0 | E55: {=+_xll.EQNXTDZ($A$1,$B55,E$51)} -> 0 | F55: {=+_xll.EQNXTDZ($A$1,$B55,F$51)} -> 0 | G55: {=+_xll.EQNXTDZ($A$1,$B55,G$51)} -> 0 | H55: {=+_xll.EQNXTDZ($A$1,$B55,H$51)} -> 0 | I55: {=+_xll.EQNXTDZ($A$1,$B55,I$51)} -> 0 | J55: {=+_xll.EQNXTDZ($A$1,$B55,J$51)} -> 0 | ... BJ55: {=+_xll.EQNXTDZ($A$1,$B55,BJ$51)} -> 0
A56: Reserves and Surplus | B56: BQTRB_RESERVE | C56: {=+_xll.EQNXTDZ($A$1,$B56,C$51)} -> 33377.59 | D56: {=+_xll.EQNXTDZ($A$1,$B56,D$51)} -> 34937.14 | E56: {=+_xll.EQNXTDZ($A$1,$B56,E$51)} -> 34989.23 | F56: {=+_xll.EQNXTDZ($A$1,$B56,F$51)} -> 31060.21 | G56: {=+_xll.EQNXTDZ($A$1,$B56,G$51)} -> 31265.61 | H56: {=+_xll.EQNXTDZ($A$1,$B56,H$51)} -> 31573.82 | I56: {=+_xll.EQNXTDZ($A$1,$B56,I$51)} -> 31885.71 | J56: {=+_xll.EQNXTDZ($A$1,$B56,J$51)} -> 33088.25 | ... BJ56: {=+_xll.EQNXTDZ($A$1,$B56,BJ$51)} -> 0
A57: Minority Interest | B57: BQTRB_MINORITY_INTEREST_BS | C57: {=+_xll.EQNXTDZ($A$1,$B57,C$51)} -> 0 | D57: {=+_xll.EQNXTDZ($A$1,$B57,D$51)} -> 0 | E57: {=+_xll.EQNXTDZ($A$1,$B57,E$51)} -> 0 | F57: {=+_xll.EQNXTDZ($A$1,$B57,F$51)} -> 0 | G57: {=+_xll.EQNXTDZ($A$1,$B57,G$51)} -> 0 | H57: {=+_xll.EQNXTDZ($A$1,$B57,H$51)} -> 0 | I57: {=+_xll.EQNXTDZ($A$1,$B57,I$51)} -> 0 | J57: {=+_xll.EQNXTDZ($A$1,$B57,J$51)} -> 0 | ... BJ57: {=+_xll.EQNXTDZ($A$1,$B57,BJ$51)} -> 0
A58: Deposits | B58: BQTRB_DEPOSITS | C58: {=+_xll.EQNXTDZ($A$1,$B58,C$51)} -> 471876.73 | D58: {=+_xll.EQNXTDZ($A$1,$B58,D$51)} -> 485205.52 | E58: {=+_xll.EQNXTDZ($A$1,$B58,E$51)} -> 490598.87 | F58: {=+_xll.EQNXTDZ($A$1,$B58,F$51)} -> 479791.56 | G58: {=+_xll.EQNXTDZ($A$1,$B58,G$51)} -> 465314.16 | H58: {=+_xll.EQNXTDZ($A$1,$B58,H$51)} -> 484321.25 | I58: {=+_xll.EQNXTDZ($A$1,$B58,I$51)} -> 510327.47 | J58: {=+_xll.EQNXTDZ($A$1,$B58,J$51)} -> 495275.24 | ... BJ58: {=+_xll.EQNXTDZ($A$1,$B58,BJ$51)} -> 0
A59: Savings Deposits | B59: BQTRB_SAVING_DEPOSITS | C59: {=+_xll.EQNXTDZ($A$1,$B59,C$51)} -> 92149 | D59: {=+_xll.EQNXTDZ($A$1,$B59,D$51)} -> 96745 | E59: {=+_xll.EQNXTDZ($A$1,$B59,E$51)} -> 98878 | F59: {=+_xll.EQNXTDZ($A$1,$B59,F$51)} -> 103715 | G59: {=+_xll.EQNXTDZ($A$1,$B59,G$51)} -> 107839 | H59: {=+_xll.EQNXTDZ($A$1,$B59,H$51)} -> 111075 | I59: {=+_xll.EQNXTDZ($A$1,$B59,I$51)} -> 132087 | J59: {=+_xll.EQNXTDZ($A$1,$B59,J$51)} -> 127168 | ... BJ59: {=+_xll.EQNXTDZ($A$1,$B59,BJ$51)} -> 0
A60: Term / Fixed Deposits | B60: BQTRB_TERM_FIXED_DEPOSITS | C60: {=+_xll.EQNXTDZ($A$1,$B60,C$51)} -> 362193.73 | D60: {=+_xll.EQNXTDZ($A$1,$B60,D$51)} -> 369203.52 | E60: {=+_xll.EQNXTDZ($A$1,$B60,E$51)} -> 372473.87 | F60: {=+_xll.EQNXTDZ($A$1,$B60,F$51)} -> 356249.56 | G60: {=+_xll.EQNXTDZ($A$1,$B60,G$51)} -> 337044.16 | H60: {=+_xll.EQNXTDZ($A$1,$B60,H$51)} -> 352583.25 | I60: {=+_xll.EQNXTDZ($A$1,$B60,I$51)} -> 356622.47 | J60: {=+_xll.EQNXTDZ($A$1,$B60,J$51)} -> 345526.24 | ... BJ60: {=+_xll.EQNXTDZ($A$1,$B60,BJ$51)} -> 0
A61: Current Deposits | B61: BQTRB_CURRENT_DEPOSITS | C61: {=+_xll.EQNXTDZ($A$1,$B61,C$51)} -> 17534 | D61: {=+_xll.EQNXTDZ($A$1,$B61,D$51)} -> 19257 | E61: {=+_xll.EQNXTDZ($A$1,$B61,E$51)} -> 19247 | F61: {=+_xll.EQNXTDZ($A$1,$B61,F$51)} -> 19827 | G61: {=+_xll.EQNXTDZ($A$1,$B61,G$51)} -> 20431 | H61: {=+_xll.EQNXTDZ($A$1,$B61,H$51)} -> 20663 | I61: {=+_xll.EQNXTDZ($A$1,$B61,I$51)} -> 21618 | J61: {=+_xll.EQNXTDZ($A$1,$B61,J$51)} -> 22581 | ... BJ61: {=+_xll.EQNXTDZ($A$1,$B61,BJ$51)} -> 0
A62: Other Deposits | B62: BQTRB_OTHER_DEPOSITS | C62: {=+_xll.EQNXTDZ($A$1,$B62,C$51)} -> 0 | D62: {=+_xll.EQNXTDZ($A$1,$B62,D$51)} -> 0 | E62: {=+_xll.EQNXTDZ($A$1,$B62,E$51)} -> 0 | F62: {=+_xll.EQNXTDZ($A$1,$B62,F$51)} -> 0 | G62: {=+_xll.EQNXTDZ($A$1,$B62,G$51)} -> 0 | H62: {=+_xll.EQNXTDZ($A$1,$B62,H$51)} -> 0 | I62: {=+_xll.EQNXTDZ($A$1,$B62,I$51)} -> 0 | J62: {=+_xll.EQNXTDZ($A$1,$B62,J$51)} -> 0 | ... BJ62: {=+_xll.EQNXTDZ($A$1,$B62,BJ$51)} -> 0
A63: Borrowings | B63: BQTRB_BORROWINGS | C63: {=+_xll.EQNXTDZ($A$1,$B63,C$51)} -> 23904.81 | D63: {=+_xll.EQNXTDZ($A$1,$B63,D$51)} -> 24164.87 | E63: {=+_xll.EQNXTDZ($A$1,$B63,E$51)} -> 25359.96 | F63: {=+_xll.EQNXTDZ($A$1,$B63,F$51)} -> 26873.32 | G63: {=+_xll.EQNXTDZ($A$1,$B63,G$51)} -> 28544.86 | H63: {=+_xll.EQNXTDZ($A$1,$B63,H$51)} -> 25496.22 | I63: {=+_xll.EQNXTDZ($A$1,$B63,I$51)} -> 31311.61 | J63: {=+_xll.EQNXTDZ($A$1,$B63,J$51)} -> 39503.56 | ... BJ63: {=+_xll.EQNXTDZ($A$1,$B63,BJ$51)} -> 0
A64: Other Liabilities & Provisions | B64: BQTRB_OTHER_LIABILITIES | C64: {=+_xll.EQNXTDZ($A$1,$B64,C$51)} -> 14994.32 | D64: {=+_xll.EQNXTDZ($A$1,$B64,D$51)} -> 13997.93 | E64: {=+_xll.EQNXTDZ($A$1,$B64,E$51)} -> 15194.92 | F64: {=+_xll.EQNXTDZ($A$1,$B64,F$51)} -> 14692.7 | G64: {=+_xll.EQNXTDZ($A$1,$B64,G$51)} -> 14099.59 | H64: {=+_xll.EQNXTDZ($A$1,$B64,H$51)} -> 20198.41 | I64: {=+_xll.EQNXTDZ($A$1,$B64,I$51)} -> 16948.17 | J64: {=+_xll.EQNXTDZ($A$1,$B64,J$51)} -> 15055.1 | ... BJ64: {=+_xll.EQNXTDZ($A$1,$B64,BJ$51)} -> 0
... A83: Book Value | B83: BQTRB_BOOKVALUE | C83: {=+_xll.EQNXTDZ($A$1,$B83,C$51)} -> 0 | D83: {=+_xll.EQNXTDZ($A$1,$B83,D$51)} -> 0 | E83: {=+_xll.EQNXTDZ($A$1,$B83,E$51)} -> 0 | F83: {=+_xll.EQNXTDZ($A$1,$B83,F$51)} -> 0 | G83: {=+_xll.EQNXTDZ($A$1,$B83,G$51)} -> 0 | H83: {=+_xll.EQNXTDZ($A$1,$B83,H$51)} -> 0 | I83: {=+_xll.EQNXTDZ($A$1,$B83,I$51)} -> 0 | J83: {=+_xll.EQNXTDZ($A$1,$B83,J$51)} -> 0 | ... BJ83: {=+_xll.EQNXTDZ($A$1,$B83,BJ$51)} -> 0

Sheet Annual Raw
A1: 132483 | C1: 200103 | D1: 200203 | E1: 200303 | F1: 200403 | G1: 200503 | H1: 200603 | I1: 200703 | J1: 200803 | K1: 200903 | L1: 201003 | M1: 201103 | N1: 201203 | O1: 201303 | P1: 201403 | Q1: 201503 | R1: 201603 | S1: 201703 | T1: 201803 | U1: 201903 | V1: 202003 | W1: 202103 | X1: 202203 | Y1: 202303 | Z1: 202403 | AA1: 202503 | AB1: 202603 | AC1: 202703 | AD1: 202803 | AE1: 202903 | AF1: 203003
A3: Company Name | B3: CD_COMPNAME | C3: {=_xll.EQNXTDZ($A$1,$B3,C$2)} -> Canara Bank
A4: Field Description | B4: Field Name
A5: No of Months | B5: BPL_NO_MONTHS | C5: {=_xll.EQNXTDZ($A$1,$B5,C$1)} -> 12 | D5: {=_xll.EQNXTDZ($A$1,$B5,D$1)} -> 12 | E5: {=_xll.EQNXTDZ($A$1,$B5,E$1)} -> 12 | F5: {=_xll.EQNXTDZ($A$1,$B5,F$1)} -> 12 | G5: {=_xll.EQNXTDZ($A$1,$B5,G$1)} -> 12 | H5: {=_xll.EQNXTDZ($A$1,$B5,H$1)} -> 12 | I5: {=_xll.EQNXTDZ($A$1,$B5,I$1)} -> 12 | J5: {=_xll.EQNXTDZ($A$1,$B5,J$1)} -> 12 | ... AF5: {=_xll.EQNXTDZ($A$1,$B5,AF$1)} -> 0
A6: Year end date | B6: BPL_YEAR_ENDDATE | C6: {=_xll.EQNXTDZ($A$1,$B6,C$1)} -> 36981 | D6: {=_xll.EQNXTDZ($A$1,$B6,D$1)} -> 37346 | E6: {=_xll.EQNXTDZ($A$1,$B6,E$1)} -> 37711 | F6: {=_xll.EQNXTDZ($A$1,$B6,F$1)} -> 38077 | G6: {=_xll.EQNXTDZ($A$1,$B6,G$1)} -> 38442 | H6: {=_xll.EQNXTDZ($A$1,$B6,H$1)} -> 38807 | I6: {=_xll.EQNXTDZ($A$1,$B6,I$1)} -> 39172 | J6: {=_xll.EQNXTDZ($A$1,$B6,J$1)} -> 39538 | ... AF6: {=_xll.EQNXTDZ($A$1,$B6,AF$1)} -> 0
A7: Interest Earned | B7: BPL_INTEREST_EARNED | C7: {=_xll.EQNXTDZ($A$1,$B7,C$1)} -> 5618.2669 | D7: {=_xll.EQNXTDZ($A$1,$B7,D$1)} -> 6370.5611 | E7: {=_xll.EQNXTDZ($A$1,$B7,E$1)} -> 6657.7229 | F7: {=_xll.EQNXTDZ($A$1,$B7,F$1)} -> 7006.9207 | G7: {=_xll.EQNXTDZ($A$1,$B7,G$1)} -> 7571.9688 | H7: {=_xll.EQNXTDZ($A$1,$B7,H$1)} -> 8711.5123 | I7: {=_xll.EQNXTDZ($A$1,$B7,I$1)} -> 11364.556 | J7: {=_xll.EQNXTDZ($A$1,$B7,J$1)} -> 14200.737 | ... AF7: {=_xll.EQNXTDZ($A$1,$B7,AF$1)} -> 0
A8: Other Income | B8: BPL_OTHER_INCOME | C8: {=_xll.EQNXTDZ($A$1,$B8,C$1)} -> 917.787 | D8: {=_xll.EQNXTDZ($A$1,$B8,D$1)} -> 1428.5343 | E8: {=_xll.EQNXTDZ($A$1,$B8,E$1)} -> 1512.1313 | F8: {=_xll.EQNXTDZ($A$1,$B8,F$1)} -> 2072.9132 | G8: {=_xll.EQNXTDZ($A$1,$B8,G$1)} -> 1543.8273 | H8: {=_xll.EQNXTDZ($A$1,$B8,H$1)} -> 1377.5149 | I8: {=_xll.EQNXTDZ($A$1,$B8,I$1)} -> 1450.9497 | J8: {=_xll.EQNXTDZ($A$1,$B8,J$1)} -> 2212.8724 | ... AF8: {=_xll.EQNXTDZ($A$1,$B8,AF$1)} -> 0
A9: Total Income | B9: BPL_TOTAL_INCOME | C9: {=_xll.EQNXTDZ($A$1,$B9,C$1)} -> 6536.0539 | D9: {=_xll.EQNXTDZ($A$1,$B9,D$1)} -> 7799.0954 | E9: {=_xll.EQNXTDZ($A$1,$B9,E$1)} -> 8169.8542 | F9: {=_xll.EQNXTDZ($A$1,$B9,F$1)} -> 9079.8339 | G9: {=_xll.EQNXTDZ($A$1,$B9,G$1)} -> 9115.7961 | H9: {=_xll.EQNXTDZ($A$1,$B9,H$1)} -> 10089.027 | I9: {=_xll.EQNXTDZ($A$1,$B9,I$1)} -> 12815.506 | J9: {=_xll.EQNXTDZ($A$1,$B9,J$1)} -> 16413.609 | ... AF9: {=_xll.EQNXTDZ($A$1,$B9,AF$1)} -> 0
A10: Interest Expended | B10: BPL_INTEREST | C10: {=_xll.EQNXTDZ($A$1,$B10,C$1)} -> 3735.2481 | D10: {=_xll.EQNXTDZ($A$1,$B10,D$1)} -> 4550.2484 | E10: {=_xll.EQNXTDZ($A$1,$B10,E$1)} -> 4424.7728 | F10: {=_xll.EQNXTDZ($A$1,$B10,F$1)} -> 4324.5655 | G10: {=_xll.EQNXTDZ($A$1,$B10,G$1)} -> 4421.4993 | H10: {=_xll.EQNXTDZ($A$1,$B10,H$1)} -> 5130.0069 | I10: {=_xll.EQNXTDZ($A$1,$B10,I$1)} -> 7337.7305 | J10: {=_xll.EQNXTDZ($A$1,$B10,J$1)} -> 10662.944 | ... AF10: {=_xll.EQNXTDZ($A$1,$B10,AF$1)} -> 0
A11: Operating Expenses | B11: BPL_OPERATING_EXPENSES | C11: {=_xll.EQNXTDZ($A$1,$B11,C$1)} -> 1669.5784 | D11: {=_xll.EQNXTDZ($A$1,$B11,D$1)} -> 1592.6069 | E11: {=_xll.EQNXTDZ($A$1,$B11,E$1)} -> 1747.7057 | F11: {=_xll.EQNXTDZ($A$1,$B11,F$1)} -> 1896.5491 | G11: {=_xll.EQNXTDZ($A$1,$B11,G$1)} -> 2108.9716 | H11: {=_xll.EQNXTDZ($A$1,$B11,H$1)} -> 2347.1354 | I11: {=_xll.EQNXTDZ($A$1,$B11,I$1)} -> 2565.3054 | J11: {=_xll.EQNXTDZ($A$1,$B11,J$1)} -> 2791.2913 | ... AF11: {=_xll.EQNXTDZ($A$1,$B11,AF$1)} -> 0
A12: Payments to and provisions for employees | B12: BPL_EMPLOYEES | C12: {=_xll.EQNXTDZ($A$1,$B12,C$1)} -> 1253.073 | D12: {=_xll.EQNXTDZ($A$1,$B12,D$1)} -> 1122.5201 | E12: {=_xll.EQNXTDZ($A$1,$B12,E$1)} -> 1162.199 | F12: {=_xll.EQNXTDZ($A$1,$B12,F$1)} -> 1273.2058 | G12: {=_xll.EQNXTDZ($A$1,$B12,G$1)} -> 1380.1499 | H12: {=_xll.EQNXTDZ($A$1,$B12,H$1)} -> 1515.3032 | I12: {=_xll.EQNXTDZ($A$1,$B12,I$1)} -> 1609.2919 | J12: {=_xll.EQNXTDZ($A$1,$B12,J$1)} -> 1661.2807 | ... AF12: {=_xll.EQNXTDZ($A$1,$B12,AF$1)} -> 0
A13: Advertisement & Sales Promotion | B13: BPL_ADVERTISING | C13: {=_xll.EQNXTDZ($A$1,$B13,C$1)} -> 3.3333 | D13: {=_xll.EQNXTDZ($A$1,$B13,D$1)} -> 5.9777 | E13: {=_xll.EQNXTDZ($A$1,$B13,E$1)} -> 9.6667 | F13: {=_xll.EQNXTDZ($A$1,$B13,F$1)} -> 15.8346 | G13: {=_xll.EQNXTDZ($A$1,$B13,G$1)} -> 14.3061 | H13: {=_xll.EQNXTDZ($A$1,$B13,H$1)} -> 21.6085 | I13: {=_xll.EQNXTDZ($A$1,$B13,I$1)} -> 39.2783 | J13: {=_xll.EQNXTDZ($A$1,$B13,J$1)} -> 45.6521 | ... AF13: {=_xll.EQNXTDZ($A$1,$B13,AF$1)} -> 0
A14: Rent, Taxes and lighting | B14: BPL_RENT_RATES_TAXES | C14: {=_xll.EQNXTDZ($A$1,$B14,C$1)} -> 133.7397 | D14: {=_xll.EQNXTDZ($A$1,$B14,D$1)} -> 144.3182 | E14: {=_xll.EQNXTDZ($A$1,$B14,E$1)} -> 162.8883 | F14: {=_xll.EQNXTDZ($A$1,$B14,F$1)} -> 175.2801 | G14: {=_xll.EQNXTDZ($A$1,$B14,G$1)} -> 205.462 | H14: {=_xll.EQNXTDZ($A$1,$B14,H$1)} -> 206.6958 | I14: {=_xll.EQNXTDZ($A$1,$B14,I$1)} -> 232.902 | J14: {=_xll.EQNXTDZ($A$1,$B14,J$1)} -> 270.1871 | ... AF14: {=_xll.EQNXTDZ($A$1,$B14,AF$1)} -> 0
A15: Depreciation on Banks property | B15: BPL_DEPRECIATION | C15: {=_xll.EQNXTDZ($A$1,$B15,C$1)} -> 65.9137 | D15: {=_xll.EQNXTDZ($A$1,$B15,D$1)} -> 92.6775 | E15: {=_xll.EQNXTDZ($A$1,$B15,E$1)} -> 108.6539 | F15: {=_xll.EQNXTDZ($A$1,$B15,F$1)} -> 113.7141 | G15: {=_xll.EQNXTDZ($A$1,$B15,G$1)} -> 132.9457 | H15: {=_xll.EQNXTDZ($A$1,$B15,H$1)} -> 145.0284 | I15: {=_xll.EQNXTDZ($A$1,$B15,I$1)} -> 148.177 | J15: {=_xll.EQNXTDZ($A$1,$B15,J$1)} -> 169.9684 | ... AF15: {=_xll.EQNXTDZ($A$1,$B15,AF$1)} -> 0
A16: Depreciation on leased assets | B16: BPL_DEPRECIATION_LEASED_ASSETS | C16: {=_xll.EQNXTDZ($A$1,$B16,C$1)} -> 0 | D16: {=_xll.EQNXTDZ($A$1,$B16,D$1)} -> 0 | E16: {=_xll.EQNXTDZ($A$1,$B16,E$1)} -> 0 | F16: {=_xll.EQNXTDZ($A$1,$B16,F$1)} -> 0 | G16: {=_xll.EQNXTDZ($A$1,$B16,G$1)} -> 0 | H16: {=_xll.EQNXTDZ($A$1,$B16,H$1)} -> 0 | I16: {=_xll.EQNXTDZ($A$1,$B16,I$1)} -> 0 | J16: {=_xll.EQNXTDZ($A$1,$B16,J$1)} -> 0 | ... AF16: {=_xll.EQNXTDZ($A$1,$B16,AF$1)} -> 0
... A35: Consolidated PAT | B35: BPL_CONSOLPAT | C35: {=_xll.EQNXTDZ($A$1,$B35,C$1)} -> 285.1 | D35: {=_xll.EQNXTDZ($A$1,$B35,D$1)} -> 741.4 | E35: {=_xll.EQNXTDZ($A$1,$B35,E$1)} -> 1018.8919 | F35: {=_xll.EQNXTDZ($A$1,$B35,F$1)} -> 1338.0056 | G35: {=_xll.EQNXTDZ($A$1,$B35,G$1)} -> 1109.5045 | H35: {=_xll.EQNXTDZ($A$1,$B35,H$1)} -> 1343.22 | I35: {=_xll.EQNXTDZ($A$1,$B35,I$1)} -> 1420.81 | J35: {=_xll.EQNXTDZ($A$1,$B35,J$1)} -> 1565.0067 | ... AF35: {=_xll.EQNXTDZ($A$1,$B35,AF$1)} -> 0
A37: Field Description | B37: Field Name
A38: Equity Paid Up | B38: FH_EQUITY_PAIDUP | C38: {=_xll.EQNXTDZ($A$1,$B38,C$1)} -> 577.8681 | D38: {=_xll.EQNXTDZ($A$1,$B38,D$1)} -> 577.8681 | E38: {=_xll.EQNXTDZ($A$1,$B38,E$1)} -> 410 | F38: {=_xll.EQNXTDZ($A$1,$B38,F$1)} -> 410 | G38: {=_xll.EQNXTDZ($A$1,$B38,G$1)} -> 410 | H38: {=_xll.EQNXTDZ($A$1,$B38,H$1)} -> 410 | I38: {=_xll.EQNXTDZ($A$1,$B38,I$1)} -> 410 | J38: {=_xll.EQNXTDZ($A$1,$B38,J$1)} -> 410 | ... AF38: {=_xll.EQNXTDZ($A$1,$B38,AF$1)} -> 0
A39: Reserves and Surplus | B39: FH_RESERVE | C39: {=_xll.EQNXTDZ($A$1,$B39,C$1)} -> 2236.5819 | D39: {=_xll.EQNXTDZ($A$1,$B39,D$1)} -> 2893.6269 | E39: {=_xll.EQNXTDZ($A$1,$B39,E$1)} -> 3738.8283 | F39: {=_xll.EQNXTDZ($A$1,$B39,F$1)} -> 4841.643 | G39: {=_xll.EQNXTDZ($A$1,$B39,G$1)} -> 5698.9572 | H39: {=_xll.EQNXTDZ($A$1,$B39,H$1)} -> 6722.2358 | I39: {=_xll.EQNXTDZ($A$1,$B39,I$1)} -> 9943.9861 | J39: {=_xll.EQNXTDZ($A$1,$B39,J$1)} -> 10090.492 | ... AF39: {=_xll.EQNXTDZ($A$1,$B39,AF$1)} -> 0
A40: Net Worth | B40: FH_NET_WORTH | C40: {=_xll.EQNXTDZ($A$1,$B40,C$1)} -> 2681.2643 | D40: {=_xll.EQNXTDZ($A$1,$B40,D$1)} -> 3342.6643 | E40: {=_xll.EQNXTDZ($A$1,$B40,E$1)} -> 4024.1348 | F40: {=_xll.EQNXTDZ($A$1,$B40,F$1)} -> 5130.8799 | G40: {=_xll.EQNXTDZ($A$1,$B40,G$1)} -> 5992.0379 | H40: {=_xll.EQNXTDZ($A$1,$B40,H$1)} -> 7018.8582 | I40: {=_xll.EQNXTDZ($A$1,$B40,I$1)} -> 8111.1138 | J40: {=_xll.EQNXTDZ($A$1,$B40,J$1)} -> 8295.6333 | ... AF40: {=_xll.EQNXTDZ($A$1,$B40,AF$1)} -> 0
A41: Total Debt | B41: FH_TOTAL_DEBTS | C41: {=_xll.EQNXTDZ($A$1,$B41,C$1)} -> 0 | D41: {=_xll.EQNXTDZ($A$1,$B41,D$1)} -> 0 | E41: {=_xll.EQNXTDZ($A$1,$B41,E$1)} -> 0 | F41: {=_xll.EQNXTDZ($A$1,$B41,F$1)} -> 0 | G41: {=_xll.EQNXTDZ($A$1,$B41,G$1)} -> 0 | H41: {=_xll.EQNXTDZ($A$1,$B41,H$1)} -> 0 | I41: {=_xll.EQNXTDZ($A$1,$B41,I$1)} -> 0 | J41: {=_xll.EQNXTDZ($A$1,$B41,J$1)} -> 0 | ... AF41: {=_xll.EQNXTDZ($A$1,$B41,AF$1)} -> 0
A42: Deposits | B42: FH_DEPOSITS | C42: {=_xll.EQNXTDZ($A$1,$B42,C$1)} -> 59069.528 | D42: {=_xll.EQNXTDZ($A$1,$B42,D$1)} -> 64030.009 | E42: {=_xll.EQNXTDZ($A$1,$B42,E$1)} -> 72094.822 | F42: {=_xll.EQNXTDZ($A$1,$B42,F$1)} -> 86344.557 | G42: {=_xll.EQNXTDZ($A$1,$B42,G$1)} -> 96795.919 | H42: {=_xll.EQNXTDZ($A$1,$B42,H$1)} -> 116803.23 | I42: {=_xll.EQNXTDZ($A$1,$B42,I$1)} -> 142381.45 | J42: {=_xll.EQNXTDZ($A$1,$B42,J$1)} -> 154072.42 | ... AF42: {=_xll.EQNXTDZ($A$1,$B42,AF$1)} -> 0
A43: Borrowings | B43: FH_BORROWINGS | C43: {=_xll.EQNXTDZ($A$1,$B43,C$1)} -> 1547.8468 | D43: {=_xll.EQNXTDZ($A$1,$B43,D$1)} -> 267.3984 | E43: {=_xll.EQNXTDZ($A$1,$B43,E$1)} -> 93.8223 | F43: {=_xll.EQNXTDZ($A$1,$B43,F$1)} -> 754.897 | G43: {=_xll.EQNXTDZ($A$1,$B43,G$1)} -> 114.1642 | H43: {=_xll.EQNXTDZ($A$1,$B43,H$1)} -> 25.824 | I43: {=_xll.EQNXTDZ($A$1,$B43,I$1)} -> 1574.3517 | J43: {=_xll.EQNXTDZ($A$1,$B43,J$1)} -> 2517.2322 | ... AF43: {=_xll.EQNXTDZ($A$1,$B43,AF$1)} -> 0
A44: Month End | B44: BMONTH_MONTHEND | C44: {=_xll.EQNXTDZ($A$1,$B44,C$1)} -> 0 | D44: {=_xll.EQNXTDZ($A$1,$B44,D$1)} -> 0 | E44: {=_xll.EQNXTDZ($A$1,$B44,E$1)} -> 200303 | F44: {=_xll.EQNXTDZ($A$1,$B44,F$1)} -> 200403 | G44: {=_xll.EQNXTDZ($A$1,$B44,G$1)} -> 200503 | H44: {=_xll.EQNXTDZ($A$1,$B44,H$1)} -> 200603 | I44: {=_xll.EQNXTDZ($A$1,$B44,I$1)} -> 200703 | J44: {=_xll.EQNXTDZ($A$1,$B44,J$1)} -> 200803 | ... AF44: {=_xll.EQNXTDZ($A$1,$B44,AF$1)} -> 0
A45: Close Price (Unit Curr.) | B45: FH_YEAR_PRICE | C45: {=_xll.EQNXTDZ($A$1,$B45,C$1)} -> 0 | D45: {=_xll.EQNXTDZ($A$1,$B45,D$1)} -> 0 | E45: {=_xll.EQNXTDZ($A$1,$B45,E$1)} -> 13.850915 | F45: {=_xll.EQNXTDZ($A$1,$B45,F$1)} -> 28.129807 | G45: {=_xll.EQNXTDZ($A$1,$B45,G$1)} -> 38.984878 | H45: {=_xll.EQNXTDZ($A$1,$B45,H$1)} -> 51.921476 | I45: {=_xll.EQNXTDZ($A$1,$B45,I$1)} -> 37.876026 | J45: {=_xll.EQNXTDZ($A$1,$B45,J$1)} -> 43.809354 | ... AF45: {=_xll.EQNXTDZ($A$1,$B45,AF$1)} -> 0
A46: High Price (Unit Curr.) | B46: FH_HIGH | C46: {=_xll.EQNXTDZ($A$1,$B46,C$1)} -> 0 | D46: {=_xll.EQNXTDZ($A$1,$B46,D$1)} -> 0 | E46: {=_xll.EQNXTDZ($A$1,$B46,E$1)} -> 14.804138 | F46: {=_xll.EQNXTDZ($A$1,$B46,F$1)} -> 32.584666 | G46: {=_xll.EQNXTDZ($A$1,$B46,G$1)} -> 46.990006 | H46: {=_xll.EQNXTDZ($A$1,$B46,H$1)} -> 58.360595 | I46: {=_xll.EQNXTDZ($A$1,$B46,I$1)} -> 62.231848 | J46: {=_xll.EQNXTDZ($A$1,$B46,J$1)} -> 81.98691 | ... AF46: {=_xll.EQNXTDZ($A$1,$B46,AF$1)} -> 0
A47: Low Price (Unit Curr.) | B47: FH_LOW | C47: {=_xll.EQNXTDZ($A$1,$B47,C$1)} -> 0 | D47: {=_xll.EQNXTDZ($A$1,$B47,D$1)} -> 0 | E47: {=_xll.EQNXTDZ($A$1,$B47,E$1)} -> 7.7814127 | F47: {=_xll.EQNXTDZ($A$1,$B47,F$1)} -> 13.831461 | G47: {=_xll.EQNXTDZ($A$1,$B47,G$1)} -> 17.741621 | H47: {=_xll.EQNXTDZ($A$1,$B47,H$1)} -> 33.177998 | I47: {=_xll.EQNXTDZ($A$1,$B47,I$1)} -> 32.117781 | J47: {=_xll.EQNXTDZ($A$1,$B47,J$1)} -> 34.34521 | ... AF47: {=_xll.EQNXTDZ($A$1,$B47,AF$1)} -> 0
A48: Month end date | B48: BMONTH_CLOSEDATE | C48: {=_xll.EQNXTDZ($A$1,$B48,C$1)} -> 0 | D48: {=_xll.EQNXTDZ($A$1,$B48,D$1)} -> 0 | E48: {=_xll.EQNXTDZ($A$1,$B48,E$1)} -> 37711 | F48: {=_xll.EQNXTDZ($A$1,$B48,F$1)} -> 38077 | G48: {=_xll.EQNXTDZ($A$1,$B48,G$1)} -> 38442 | H48: {=_xll.EQNXTDZ($A$1,$B48,H$1)} -> 38807 | I48: {=_xll.EQNXTDZ($A$1,$B48,I$1)} -> 39171 | J48: {=_xll.EQNXTDZ($A$1,$B48,J$1)} -> 39538 | ... AF48: {=_xll.EQNXTDZ($A$1,$B48,AF$1)} -> 0
A49: Volume ('000) | B49: BMONTH_VOLUME | C49: {=_xll.EQNXTDZ($A$1,$B49,C$1)} -> 0 | D49: {=_xll.EQNXTDZ($A$1,$B49,D$1)} -> 0 | E49: {=_xll.EQNXTDZ($A$1,$B49,E$1)} -> 34310.911 | F49: {=_xll.EQNXTDZ($A$1,$B49,F$1)} -> 16377.975 | G49: {=_xll.EQNXTDZ($A$1,$B49,G$1)} -> 8456.756 | H49: {=_xll.EQNXTDZ($A$1,$B49,H$1)} -> 3519.011 | I49: {=_xll.EQNXTDZ($A$1,$B49,I$1)} -> 1976.786 | J49: {=_xll.EQNXTDZ($A$1,$B49,J$1)} -> 3402.566 | ... AF49: {=_xll.EQNXTDZ($A$1,$B49,AF$1)} -> 0
... A54: NIM_Reported (%) | B54: RBI_NIMAR | C54: {=_xll.EQNXTDZ($A$1,$B54,C$1)} -> 0 | D54: {=_xll.EQNXTDZ($A$1,$B54,D$1)} -> 0 | E54: {=_xll.EQNXTDZ($A$1,$B54,E$1)} -> 3.53 | F54: {=_xll.EQNXTDZ($A$1,$B54,F$1)} -> 3.49 | G54: {=_xll.EQNXTDZ($A$1,$B54,G$1)} -> 3.41 | H54: {=_xll.EQNXTDZ($A$1,$B54,H$1)} -> 3.36 | I54: {=_xll.EQNXTDZ($A$1,$B54,I$1)} -> 3.15 | J54: {=_xll.EQNXTDZ($A$1,$B54,J$1)} -> 2.42 | ... AF54: {=_xll.EQNXTDZ($A$1,$B54,AF$1)} -> 0
A58: Field Description | B58: Field Name
A59: Year End | B59: BBS_YEAR_END | C59: {=_xll.EQNXTDZ($A$1,$B59,C$1)} -> 200103 | D59: {=_xll.EQNXTDZ($A$1,$B59,D$1)} -> 200203 | E59: {=_xll.EQNXTDZ($A$1,$B59,E$1)} -> 200303 | F59: {=_xll.EQNXTDZ($A$1,$B59,F$1)} -> 200403 | G59: {=_xll.EQNXTDZ($A$1,$B59,G$1)} -> 200503 | H59: {=_xll.EQNXTDZ($A$1,$B59,H$1)} -> 200603 | I59: {=_xll.EQNXTDZ($A$1,$B59,I$1)} -> 200703 | J59: {=_xll.EQNXTDZ($A$1,$B59,J$1)} -> 200803 | ... AF59: {=_xll.EQNXTDZ($A$1,$B59,AF$1)} -> 0
A60: Year | B60: BBS_YEAR | C60: {=_xll.EQNXTDZ($A$1,$B60,C$1)} -> 2001 | D60: {=_xll.EQNXTDZ($A$1,$B60,D$1)} -> 2002 | E60: {=_xll.EQNXTDZ($A$1,$B60,E$1)} -> 2003 | F60: {=_xll.EQNXTDZ($A$1,$B60,F$1)} -> 2004 | G60: {=_xll.EQNXTDZ($A$1,$B60,G$1)} -> 2005 | H60: {=_xll.EQNXTDZ($A$1,$B60,H$1)} -> 2006 | I60: {=_xll.EQNXTDZ($A$1,$B60,I$1)} -> 2007 | J60: {=_xll.EQNXTDZ($A$1,$B60,J$1)} -> 2008 | ... AF60: {=_xll.EQNXTDZ($A$1,$B60,AF$1)} -> 0
A61: No of Months | B61: BBS_NO_MONTHS | C61: {=_xll.EQNXTDZ($A$1,$B61,C$1)} -> 12 | D61: {=_xll.EQNXTDZ($A$1,$B61,D$1)} -> 12 | E61: {=_xll.EQNXTDZ($A$1,$B61,E$1)} -> 12 | F61: {=_xll.EQNXTDZ($A$1,$B61,F$1)} -> 12 | G61: {=_xll.EQNXTDZ($A$1,$B61,G$1)} -> 12 | H61: {=_xll.EQNXTDZ($A$1,$B61,H$1)} -> 12 | I61: {=_xll.EQNXTDZ($A$1,$B61,I$1)} -> 12 | J61: {=_xll.EQNXTDZ($A$1,$B61,J$1)} -> 12 | ... AF61: {=_xll.EQNXTDZ($A$1,$B61,AF$1)} -> 0
A62: Year end date | B62: BBS_YEAR_ENDDATE | C62: {=_xll.EQNXTDZ($A$1,$B62,C$1)} -> 36981 | D62: {=_xll.EQNXTDZ($A$1,$B62,D$1)} -> 37346 | E62: {=_xll.EQNXTDZ($A$1,$B62,E$1)} -> 37711 | F62: {=_xll.EQNXTDZ($A$1,$B62,F$1)} -> 38077 | G62: {=_xll.EQNXTDZ($A$1,$B62,G$1)} -> 38442 | H62: {=_xll.EQNXTDZ($A$1,$B62,H$1)} -> 38807 | I62: {=_xll.EQNXTDZ($A$1,$B62,I$1)} -> 39172 | J62: {=_xll.EQNXTDZ($A$1,$B62,J$1)} -> 39538 | ... AF62: {=_xll.EQNXTDZ($A$1,$B62,AF$1)} -> 0
A63: Share Capital | B63: BBS_SHARE_CAPITAL | C63: {=_xll.EQNXTDZ($A$1,$B63,C$1)} -> 577.8681 | D63: {=_xll.EQNXTDZ($A$1,$B63,D$1)} -> 577.8681 | E63: {=_xll.EQNXTDZ($A$1,$B63,E$1)} -> 410 | F63: {=_xll.EQNXTDZ($A$1,$B63,F$1)} -> 410 | G63: {=_xll.EQNXTDZ($A$1,$B63,G$1)} -> 410 | H63: {=_xll.EQNXTDZ($A$1,$B63,H$1)} -> 410 | I63: {=_xll.EQNXTDZ($A$1,$B63,I$1)} -> 410 | J63: {=_xll.EQNXTDZ($A$1,$B63,J$1)} -> 410 | ... AF63: {=_xll.EQNXTDZ($A$1,$B63,AF$1)} -> 0
A64: Share Warrants & Outstandings | B64: BBS_SHAREWROUTST | C64: {=_xll.EQNXTDZ($A$1,$B64,C$1)} -> 0 | D64: {=_xll.EQNXTDZ($A$1,$B64,D$1)} -> 0 | E64: {=_xll.EQNXTDZ($A$1,$B64,E$1)} -> 0 | F64: {=_xll.EQNXTDZ($A$1,$B64,F$1)} -> 0 | G64: {=_xll.EQNXTDZ($A$1,$B64,G$1)} -> 0 | H64: {=_xll.EQNXTDZ($A$1,$B64,H$1)} -> 0 | I64: {=_xll.EQNXTDZ($A$1,$B64,I$1)} -> 0 | J64: {=_xll.EQNXTDZ($A$1,$B64,J$1)} -> 0 | ... AF64: {=_xll.EQNXTDZ($A$1,$B64,AF$1)} -> 0
A65: Total Reserves | B65: BBS_RESERVE | C65: {=_xll.EQNXTDZ($A$1,$B65,C$1)} -> 2236.5819 | D65: {=_xll.EQNXTDZ($A$1,$B65,D$1)} -> 2893.6269 | E65: {=_xll.EQNXTDZ($A$1,$B65,E$1)} -> 3738.8283 | F65: {=_xll.EQNXTDZ($A$1,$B65,F$1)} -> 4841.643 | G65: {=_xll.EQNXTDZ($A$1,$B65,G$1)} -> 5698.9572 | H65: {=_xll.EQNXTDZ($A$1,$B65,H$1)} -> 6722.2358 | I65: {=_xll.EQNXTDZ($A$1,$B65,I$1)} -> 9943.9861 | J65: {=_xll.EQNXTDZ($A$1,$B65,J$1)} -> 10090.492 | ... AF65: {=_xll.EQNXTDZ($A$1,$B65,AF$1)} -> 0
A66: Minority Interest | B66: BBS_MINORITY_INTEREST | C66: {=_xll.EQNXTDZ($A$1,$B66,C$1)} -> 0 | D66: {=_xll.EQNXTDZ($A$1,$B66,D$1)} -> 0 | E66: {=_xll.EQNXTDZ($A$1,$B66,E$1)} -> 0 | F66: {=_xll.EQNXTDZ($A$1,$B66,F$1)} -> 0 | G66: {=_xll.EQNXTDZ($A$1,$B66,G$1)} -> 0 | H66: {=_xll.EQNXTDZ($A$1,$B66,H$1)} -> 0 | I66: {=_xll.EQNXTDZ($A$1,$B66,I$1)} -> 0 | J66: {=_xll.EQNXTDZ($A$1,$B66,J$1)} -> 0 | ... AF66: {=_xll.EQNXTDZ($A$1,$B66,AF$1)} -> 0
A67: Deposits | B67: BBS_DEPOSITS | C67: {=_xll.EQNXTDZ($A$1,$B67,C$1)} -> 59069.528 | D67: {=_xll.EQNXTDZ($A$1,$B67,D$1)} -> 64030.009 | E67: {=_xll.EQNXTDZ($A$1,$B67,E$1)} -> 72094.822 | F67: {=_xll.EQNXTDZ($A$1,$B67,F$1)} -> 86344.557 | G67: {=_xll.EQNXTDZ($A$1,$B67,G$1)} -> 96795.919 | H67: {=_xll.EQNXTDZ($A$1,$B67,H$1)} -> 116803.23 | I67: {=_xll.EQNXTDZ($A$1,$B67,I$1)} -> 142381.45 | J67: {=_xll.EQNXTDZ($A$1,$B67,J$1)} -> 154072.42 | ... AF67: {=_xll.EQNXTDZ($A$1,$B67,AF$1)} -> 0
A68: Borrowings | B68: BBS_BORROWINGS | C68: {=_xll.EQNXTDZ($A$1,$B68,C$1)} -> 1547.8468 | D68: {=_xll.EQNXTDZ($A$1,$B68,D$1)} -> 267.3984 | E68: {=_xll.EQNXTDZ($A$1,$B68,E$1)} -> 93.8223 | F68: {=_xll.EQNXTDZ($A$1,$B68,F$1)} -> 754.897 | G68: {=_xll.EQNXTDZ($A$1,$B68,G$1)} -> 114.1642 | H68: {=_xll.EQNXTDZ($A$1,$B68,H$1)} -> 25.824 | I68: {=_xll.EQNXTDZ($A$1,$B68,I$1)} -> 1574.3517 | J68: {=_xll.EQNXTDZ($A$1,$B68,J$1)} -> 2517.2322 | ... AF68: {=_xll.EQNXTDZ($A$1,$B68,AF$1)} -> 0
A69: Other Liabilities & Provisions | B69: BBS_OTHER_LIABILITIES | C69: {=_xll.EQNXTDZ($A$1,$B69,C$1)} -> 3088.8171 | D69: {=_xll.EQNXTDZ($A$1,$B69,D$1)} -> 4366.2429 | E69: {=_xll.EQNXTDZ($A$1,$B69,E$1)} -> 5717.4575 | F69: {=_xll.EQNXTDZ($A$1,$B69,F$1)} -> 7188.2958 | G69: {=_xll.EQNXTDZ($A$1,$B69,G$1)} -> 7286.1333 | H69: {=_xll.EQNXTDZ($A$1,$B69,H$1)} -> 8860.567 | I69: {=_xll.EQNXTDZ($A$1,$B69,I$1)} -> 11651.253 | J69: {=_xll.EQNXTDZ($A$1,$B69,J$1)} -> 13438.545 | ... AF69: {=_xll.EQNXTDZ($A$1,$B69,AF$1)} -> 0
A70: Total Liabilities | B70: BBS_TOTAL_SOUNCES_FUNDS | C70: {=_xll.EQNXTDZ($A$1,$B70,C$1)} -> 66520.642 | D70: {=_xll.EQNXTDZ($A$1,$B70,D$1)} -> 72135.146 | E70: {=_xll.EQNXTDZ($A$1,$B70,E$1)} -> 82054.931 | F70: {=_xll.EQNXTDZ($A$1,$B70,F$1)} -> 99539.392 | G70: {=_xll.EQNXTDZ($A$1,$B70,G$1)} -> 110305.17 | H70: {=_xll.EQNXTDZ($A$1,$B70,H$1)} -> 132821.86 | I70: {=_xll.EQNXTDZ($A$1,$B70,I$1)} -> 165961.04 | J70: {=_xll.EQNXTDZ($A$1,$B70,J$1)} -> 180528.69 | ... AF70: {=_xll.EQNXTDZ($A$1,$B70,AF$1)} -> 0
... A94: Tier 2 (Basel III) | B94: RBI_TII_CAR_B | C94: {=_xll.EQNXTDZ($A$1,$B94,C$1)} -> 0 | D94: {=_xll.EQNXTDZ($A$1,$B94,D$1)} -> 0 | E94: {=_xll.EQNXTDZ($A$1,$B94,E$1)} -> 0 | F94: {=_xll.EQNXTDZ($A$1,$B94,F$1)} -> 0 | G94: {=_xll.EQNXTDZ($A$1,$B94,G$1)} -> 0 | H94: {=_xll.EQNXTDZ($A$1,$B94,H$1)} -> 0 | I94: {=_xll.EQNXTDZ($A$1,$B94,I$1)} -> 0 | J94: {=_xll.EQNXTDZ($A$1,$B94,J$1)} -> 0 | ... AF94: {=_xll.EQNXTDZ($A$1,$B94,AF$1)} -> 0

Sheet QTR Share Price
A1: =+'Annual Raw'!A1 -> 132483 | C1: 201206 | D1: 201207 | E1: 201208 | F1: 201209 | G1: 201210 | H1: 201211 | I1: 201212 | J1: 201301 | K1: 201302 | L1: 201303 | M1: 201304 | N1: 201305 | O1: 201306 | P1: 201307 | Q1: 201308 | R1: 201309 | S1: 201310 | T1: 201311 | U1: 201312 | V1: 201401 | W1: 201402 | X1: 201403 | Y1: 201404 | Z1: 201405 | AA1: 201406 | AB1: 201407 | AC1: 201408 | AD1: 201409 | AE1: 201410 | AF1: 201411 | AG1: 201412 | AH1: 201501 | AI1: 201502 | AJ1: 201503 | AK1: 201504 | AL1: 201505 | AM1: 201506 | AN1: 201507 | AO1: 201508 | AP1: 201509 | AQ1: 201510 | AR1: 201511 | AS1: 201512 | AT1: 201601 | AU1: 201602 | AV1: 201603 | AW1: 201604 | AX1: 201605 | AY1: 201606 | AZ1: 201607 | BA1: 201608 | BB1: 201609 | BC1: 201610 | BD1: 201611 | BE1: 201612 | BF1: 201701 | BG1: 201702 | BH1: 201703 | BI1: 201704 | BJ1: 201705 | BK1: 201706 | BL1: 201707 | BM1: 201708 | BN1: 201709 | BO1: 201710 | BP1: 201711 | BQ1: 201712 | BR1: 201801 | BS1: 201802 | BT1: 201803 | BU1: 201804 | BV1: 201805 | BW1: 201806 | BX1: 201807 | BY1: 201808 | BZ1: 201809 | CA1: 201810 | CB1: 201811 | CC1: 201812 | CD1: 201901 | CE1: 201902 | CF1: 201903 | CG1: 201904 | CH1: 201905 | CI1: 201906 | CJ1: 201907 | CK1: 201908 | CL1: 201909 | CM1: 201910 | CN1: 201911 | CO1: 201912 | CP1: 202001 | CQ1: 202002 | CR1: 202003 | CS1: 202004 | CT1: 202005 | CU1: 202006 | CV1: 202007 | CW1: 202008 | CX1: 202009 | CY1: 202010 | CZ1: 202011 | DA1: 202012 | DB1: 202101 | DC1: 202102 | DD1: 202103 | DE1: 202104 | DF1: 202105 | DG1: 202106 | DH1: 202107 | DI1: 202108 | DJ1: 202109 | DK1: 202110 | DL1: 202111 | DM1: 202112 | DN1: 202201 | DO1: 202202 | DP1: 202203 | DQ1: 202204 | DR1: 202205 | DS1: 202206 | DT1: 202207 | DU1: 202208 | DV1: 202209 | DW1: 202210 | DX1: 202211 | DY1: 202212 | DZ1: 202301 | EA1: 202302 | EB1: 202303 | EC1: 202304 | ED1: 202305 | EE1: 202306 | EF1: 202307 | EG1: 202308 | EH1: 202309 | EI1: 202310 | EJ1: 202311 | EK1: 202312 | EL1: 202401 | EM1: 202402 | EN1: 202403 | EO1: 202404 | EP1: 202405 | EQ1: 202406 | ER1: 202407 | ES1: 202408 | ET1: 202409 | EU1: 202410 | EV1: 202411 | EW1: 202412 | EX1: 202501 | EY1: 202502 | EZ1: 202503 | FA1: 202504 | FB1: 202505 | FC1: 202506 | FD1: 202507 | FE1: 202508 | FF1: 202509 | FG1: 202510 | FH1: 202511 | FI1: 202512 | FJ1: 202601 | FK1: 202602 | FL1: 202603 | FM1: 202604 | FN1: 202605 | FO1: 202606 | FP1: 202607 | FQ1: 202608 | FR1: 202609 | FS1: 202610 | FT1: 202611 | FU1: 202612 | FV1: 202701 | FW1: 202702 | FX1: 202703 | FY1: 202704 | FZ1: 202705 | GA1: 202706 | GB1: 202707 | GC1: 202708 | GD1: 202709 | GE1: 202710 | GF1: 202711 | GG1: 202712 | GH1: 202801 | GI1: 202802 | GJ1: 202803 | GK1: 202804 | GL1: 202805 | GM1: 202806 | GN1: 202807 | GO1: 202808 | GP1: 202809 | GQ1: 202810 | GR1: 202811 | GS1: 202812 | GT1: 202901 | GU1: 202902 | GV1: 202903 | GW1: 202904 | GX1: 202905 | GY1: 202906 | GZ1: 202907 | HA1: 202908 | HB1: 202909 | HC1: 202910 | HD1: 202911 | HE1: 202912 | HF1: 203001 | HG1: 203002 | HH1: 203003 | HM1: 201206 | HN1: 201207 | HO1: 201208 | HP1: 201209 | HQ1: 201212 | HR1: 201303 | HS1: 201306 | HT1: 201309 | HU1: 201312 | HV1: 201403 | HW1: 201406 | HX1: 201409 | HY1: 201412 | HZ1: 201503 | IA1: 201506 | IB1: 201509 | IC1: 201512 | ID1: 201603 | IE1: 201606 | IF1: 201609 | IG1: 201612 | IH1: 201703 | II1: 201706 | IJ1: 201709 | IK1: 201712 | IL1: 201803 | IM1: 201806 | IN1: 201809 | IO1: 201812 | IP1: 201903 | IQ1: 201906 | IR1: 201909 | IS1: 201912 | IT1: 202003 | IU1: 202006 | IV1: 202009 | IW1: 202012 | IX1: 202103 | IY1: 202106 | IZ1: 202109 | JA1: 202112 | JB1: 202203 | JC1: 202206 | JD1: 202209 | JE1: 202212 | JF1: 202303 | JG1: 202306 | JH1: 202309 | JI1: 202312 | JJ1: 202403 | JK1: 202406 | JL1: 202409 | JM1: 202412 | JN1: 202503 | JO1: 202506 | JP1: 202509 | JQ1: 202512 | JR1: 202603 | JS1: 202606 | JT1: 202609 | JU1: 202612 | JV1: 202703 | JW1: 202706 | JX1: 202709 | JY1: 202712 | JZ1: 202803 | KA1: 202806 | KB1: 202809 | KC1: 202812 | KD1: 202903 | KE1: 202906 | KF1: 202909 | KG1: 202912 | KH1: 203003
A4: Field Description | B4: Field Name
A5: MonthEnd | B5: NMONTH_MONTHEND | C5: {=_xll.EQNXTDZ($A$1,$B5,C$1)} -> 201206 | D5: {=_xll.EQNXTDZ($A$1,$B5,D$1)} -> 201207 | E5: {=_xll.EQNXTDZ($A$1,$B5,E$1)} -> 201208 | F5: {=_xll.EQNXTDZ($A$1,$B5,F$1)} -> 201209 | G5: {=_xll.EQNXTDZ($A$1,$B5,G$1)} -> 201210 | H5: {=_xll.EQNXTDZ($A$1,$B5,H$1)} -> 201211 | I5: {=_xll.EQNXTDZ($A$1,$B5,I$1)} -> 201212 | J5: {=_xll.EQNXTDZ($A$1,$B5,J$1)} -> 201301 | ... HH5: {=_xll.EQNXTDZ($A$1,$B5,HH$1)} -> 0
A6: Open | B6: NMONTH_OPEN | C6: {=_xll.EQNXTDZ($A$1,$B6,C$1)} -> 77.938854 | D6: {=_xll.EQNXTDZ($A$1,$B6,D$1)} -> 80.146781 | E6: {=_xll.EQNXTDZ($A$1,$B6,E$1)} -> 71.587416 | F6: {=_xll.EQNXTDZ($A$1,$B6,F$1)} -> 62.852973 | G6: {=_xll.EQNXTDZ($A$1,$B6,G$1)} -> 84.231933 | H6: {=_xll.EQNXTDZ($A$1,$B6,H$1)} -> 78.57108 | I6: {=_xll.EQNXTDZ($A$1,$B6,I$1)} -> 90.651456 | J6: {=_xll.EQNXTDZ($A$1,$B6,J$1)} -> 97.246058 | ... HH6: {=_xll.EQNXTDZ($A$1,$B6,HH$1)} -> 0
A7: High | B7: NMONTH_HIGH | C7: {=_xll.EQNXTDZ($A$1,$B7,C$1)} -> 85.107322 | D7: {=_xll.EQNXTDZ($A$1,$B7,D$1)} -> 85.476931 | E7: {=_xll.EQNXTDZ($A$1,$B7,E$1)} -> 72.11265 | F7: {=_xll.EQNXTDZ($A$1,$B7,F$1)} -> 88.676966 | G7: {=_xll.EQNXTDZ($A$1,$B7,G$1)} -> 88.297631 | H7: {=_xll.EQNXTDZ($A$1,$B7,H$1)} -> 91.030792 | I7: {=_xll.EQNXTDZ($A$1,$B7,I$1)} -> 97.226605 | J7: {=_xll.EQNXTDZ($A$1,$B7,J$1)} -> 103.68503 | ... HH7: {=_xll.EQNXTDZ($A$1,$B7,HH$1)} -> 0 | HP7: =+MAX(D7:F7) -> 88.676966 | HQ7: =+MAX(G7:I7) -> 97.226605 | HR7: =+MAX(J7:L7) -> 103.68503 | HS7: =+MAX(M7:O7) -> 88.959036 | HT7: =+MAX(P7:R7) -> 75.283506 | HU7: =+MAX(S7:U7) -> 57.289386 | HV7: =+MAX(V7:X7) -> 56.880871 | HW7: =+MAX(Y7:AA7) -> 96.876449 | HX7: =+MAX(AB7:AD7) -> 91.390674 | HY7: =+MAX(AE7:AG7) -> 88.278178 | HZ7: =+MAX(AH7:AJ7) -> 93.112274 | IA7: =+MAX(AK7:AM7) -> 80.039789 | IB7: =+MAX(AN7:AP7) -> 70.118707 | IC7: =+MAX(AQ7:AS7) -> 59.400048 | ID7: =+MAX(AT7:AV7) -> 46.609633 | IE7: =+MAX(AW7:AY7) -> 43.039989 | IF7: =+MAX(AZ7:BB7) -> 62.026216 | IG7: =+MAX(BC7:BE7) -> 65.926563 | IH7: =+MAX(BF7:BH7) -> 61.899771 | II7: =+MAX(BI7:BK7) -> 83.2 | IJ7: =+MAX(BL7:BN7) -> 74.94 | IK7: =+MAX(BO7:BQ7) -> 92.74 | IL7: =+MAX(BR7:BT7) -> 76.98 | IM7: =+MAX(BU7:BW7) -> 58.4 | IN7: =+MAX(BX7:BZ7) -> 60.46 | IO7: =+MAX(CA7:CC7) -> 56.32 | IP7: =+MAX(CD7:CF7) -> 60 | IQ7: =+MAX(CG7:CI7) -> 60.42 | IR7: =+MAX(CJ7:CL7) -> 59.31 | IS7: =+MAX(CM7:CO7) -> 46.85 | IT7: =+MAX(CP7:CR7) -> 45.96 | IU7: =+MAX(CS7:CU7) -> 23.66 | IV7: =+MAX(CV7:CX7) -> 23.89 | IW7: =+MAX(CY7:DA7) -> 29.33 | IX7: =+MAX(DB7:DD7) -> 34.92 | IY7: =+MAX(DE7:DG7) -> 33.15 | IZ7: =+MAX(DH7:DJ7) -> 35.5 | JA7: =+MAX(DK7:DM7) -> 49.52 | JB7: =+MAX(DN7:DP7) -> 54.56 | JC7: =+MAX(DQ7:DS7) -> 50.51 | JD7: =+MAX(DT7:DV7) -> 51.53 | JE7: =+MAX(DW7:DY7) -> 67.34 | JF7: =+MAX(DZ7:EB7) -> 68.34 | JG7: =+MAX(EC7:EE7) -> 65.37 | JH7: =+MAX(EF7:EH7) -> 77.2 | JI7: =+MAX(EI7:EK7) -> 90.94 | JJ7: =+MAX(EL7:EN7) -> 121.26 | JK7: =MAX(EO7:EQ7) -> 128.9 | JL7: =MAX(ER7:ET7) -> 120.19 | JM7: =MAX(EU7:EW7) -> 112.46 | JN7: =MAX(EX7:EZ7) -> 103.14 | JO7: =MAX(FA7:FC7) -> 119.3 | JP7: =MAX(FD7:FF7) -> 124.55 | JQ7: =MAX(FG7:FI7) -> 158 | JR7: =MAX(FJ7:FL7) -> 162.89 | JS7: =MAX(FM7:FO7) -> 146.89 | JT7: =MAX(FP7:FR7) -> 0 | JU7: =MAX(FS7:FU7) -> 0 | JV7: =MAX(FV7:FX7) -> 0 | JW7: =MAX(FY7:GA7) -> 0 | JX7: =MAX(GB7:GD7) -> 0 | JY7: =MAX(GE7:GG7) -> 0 | JZ7: =MAX(GH7:GJ7) -> 0 | KA7: =MAX(GK7:GM7) -> 0 | KB7: =MAX(GN7:GP7) -> 0 | KC7: =MAX(GQ7:GS7) -> 0 | KD7: =MAX(GT7:GV7) -> 0 | KE7: =MAX(GW7:GY7) -> 0 | KF7: =MAX(GZ7:HB7) -> 0 | KG7: =MAX(HC7:HE7) -> 0 | KH7: =MAX(HF7:HH7) -> 0
A8: Low | B8: NMONTH_LOW | C8: {=_xll.EQNXTDZ($A$1,$B8,C$1)} -> 74.894444 | D8: {=_xll.EQNXTDZ($A$1,$B8,D$1)} -> 66.860312 | E8: {=_xll.EQNXTDZ($A$1,$B8,E$1)} -> 59.575126 | F8: {=_xll.EQNXTDZ($A$1,$B8,F$1)} -> 60.236531 | G8: {=_xll.EQNXTDZ($A$1,$B8,G$1)} -> 75.896278 | H8: {=_xll.EQNXTDZ($A$1,$B8,H$1)} -> 77.72487 | I8: {=_xll.EQNXTDZ($A$1,$B8,I$1)} -> 88.005834 | J8: {=_xll.EQNXTDZ($A$1,$B8,J$1)} -> 89.960871 | ... HH8: {=_xll.EQNXTDZ($A$1,$B8,HH$1)} -> 0 | HP8: =+MIN(D8:F8) -> 59.575126 | HQ8: =+MIN(G8:I8) -> 75.896278 | HR8: =+MIN(J8:L8) -> 69.253044 | HS8: =+MIN(M8:O8) -> 65.167892 | HT8: =+MIN(P8:R8) -> 36.844176 | HU8: =+MIN(S8:U8) -> 42.6412 | HV8: =+MIN(V8:X8) -> 40.656984 | HW8: =+MIN(Y8:AA8) -> 50.25709 | HX8: =+MIN(AB8:AD8) -> 65.197072 | HY8: =+MIN(AE8:AG8) -> 66.928398 | HZ8: =+MIN(AH8:AJ8) -> 67.404999 | IA8: =+MIN(AK8:AM8) -> 53.398766 | IB8: =+MIN(AN8:AP8) -> 48.749474 | IC8: =+MIN(AQ8:AS8) -> 45.170103 | ID8: =+MIN(AT8:AV8) -> 30.346839 | IE8: =+MIN(AW8:AY8) -> 34.218007 | IF8: =+MIN(AZ8:BB8) -> 42.213232 | IG8: =+MIN(BC8:BE8) -> 49.060724 | IH8: =+MIN(BF8:BH8) -> 50.033379 | II8: =+MIN(BI8:BK8) -> 60.35 | IJ8: =+MIN(BL8:BN8) -> 61.32 | IK8: =+MIN(BO8:BQ8) -> 59.62 | IL8: =+MIN(BR8:BT8) -> 45.04 | IM8: =+MIN(BU8:BW8) -> 46.9 | IN8: =+MIN(BX8:BZ8) -> 41.86 | IO8: =+MIN(CA8:CC8) -> 40.95 | IP8: =+MIN(CD8:CF8) -> 42.56 | IQ8: =+MIN(CG8:CI8) -> 47.69 | IR8: =+MIN(CJ8:CL8) -> 36 | IS8: =+MIN(CM8:CO8) -> 34.12 | IT8: =+MIN(CP8:CR8) -> 14.73 | IU8: =+MIN(CS8:CU8) -> 15.15 | IV8: =+MIN(CV8:CX8) -> 16.45 | IW8: =+MIN(CY8:DA8) -> 16.87 | IX8: =+MIN(DB8:DD8) -> 24.74 | IY8: =+MIN(DE8:DG8) -> 24.86 | IZ8: =+MIN(DH8:DJ8) -> 28.42 | JA8: =+MIN(DK8:DM8) -> 33.6 | JB8: =+MIN(DN8:DP8) -> 39.28 | JC8: =+MIN(DQ8:DS8) -> 34.35 | JD8: =+MIN(DT8:DV8) -> 35.69 | JE8: =+MIN(DW8:DY8) -> 44.08 | JF8: =+MIN(DZ8:EB8) -> 53.76 | JG8: =+MIN(EC8:EE8) -> 56.24 | JH8: =+MIN(EF8:EH8) -> 60.51 | JI8: =+MIN(EI8:EK8) -> 68.42 | JJ8: =+MIN(EL8:EN8) -> 87.6 | JK8: =MIN(EO8:EQ8) -> 96.2 | JL8: =MIN(ER8:ET8) -> 100.69 | JM8: =MIN(EU8:EW8) -> 92.52 | JN8: =MIN(EX8:EZ8) -> 78.6 | JO8: =MIN(FA8:FC8) -> 83.7 | JP8: =MIN(FD8:FF8) -> 103.55 | JQ8: =MIN(FG8:FI8) -> 121.17 | JR8: =MIN(FJ8:FL8) -> 123 | JS8: =MIN(FM8:FO8) -> 121.79 | JT8: =MIN(FP8:FR8) -> 0 | JU8: =MIN(FS8:FU8) -> 0 | JV8: =MIN(FV8:FX8) -> 0 | JW8: =MIN(FY8:GA8) -> 0 | JX8: =MIN(GB8:GD8) -> 0 | JY8: =MIN(GE8:GG8) -> 0 | JZ8: =MIN(GH8:GJ8) -> 0 | KA8: =MIN(GK8:GM8) -> 0 | KB8: =MIN(GN8:GP8) -> 0 | KC8: =MIN(GQ8:GS8) -> 0 | KD8: =MIN(GT8:GV8) -> 0 | KE8: =MIN(GW8:GY8) -> 0 | KF8: =MIN(GZ8:HB8) -> 0 | KG8: =MIN(HC8:HE8) -> 0 | KH8: =MIN(HF8:HH8) -> 0
A9: Close | B9: NMONTH_CLOSE | C9: {=_xll.EQNXTDZ($A$1,$B9,C$1)} -> 80.273226 | D9: {=_xll.EQNXTDZ($A$1,$B9,D$1)} -> 71.23726 | E9: {=_xll.EQNXTDZ($A$1,$B9,E$1)} -> 61.880318 | F9: {=_xll.EQNXTDZ($A$1,$B9,F$1)} -> 83.930409 | G9: {=_xll.EQNXTDZ($A$1,$B9,G$1)} -> 77.987487 | H9: {=_xll.EQNXTDZ($A$1,$B9,H$1)} -> 90.369386 | I9: {=_xll.EQNXTDZ($A$1,$B9,I$1)} -> 96.662465 | J9: {=_xll.EQNXTDZ($A$1,$B9,J$1)} -> 93.588875 | ... HH9: {=_xll.EQNXTDZ($A$1,$B9,HH$1)} -> 0 | HP9: =+F9 -> 83.930409 | HQ9: =+I9 -> 96.662465 | HR9: =+L9 -> 74.709639 | HS9: =+O9 -> 70.147887 | HT9: =+R9 -> 43.078895 | HU9: =+U9 -> 54.906381 | HV9: =+X9 -> 51.424276 | HW9: =+AA9 -> 89.951145 | HX9: =+AD9 -> 68.260936 | HY9: =+AG9 -> 87.28607 | HZ9: =+AJ9 -> 71.54851 | IA9: =+AM9 -> 54.050444 | IB9: =+AP9 -> 54.42978 | IC9: =+AS9 -> 45.316002 | ID9: =+AV9 -> 36.970621 | IE9: =+AY9 -> 42.495302 | IF9: =+BB9 -> 59.983641 | IG9: =+BE9 -> 51.142206 | IH9: =+BH9 -> 60.55 | II9: =+BK9 -> 65.73 | IJ9: =+BN9 -> 61.6 | IK9: =+BQ9 -> 72.08 | IL9: =+BT9 -> 52.78 | IM9: =+BW9 -> 50.31 | IN9: =+BZ9 -> 44.17 | IO9: =+CC9 -> 55.01 | IP9: =+CF9 -> 58.26 | IQ9: =+CI9 -> 56.88 | IR9: =+CL9 -> 36.48 | IS9: =+CO9 -> 44.27 | IT9: =+CR9 -> 18.1 | IU9: =+CU9 -> 20.11 | IV9: =+CX9 -> 17.77 | IW9: =+DA9 -> 25.79 | IX9: =+DD9 -> 30.44 | IY9: =+DG9 -> 30.37 | IZ9: =+DJ9 -> 34.6 | JA9: =+DM9 -> 39.99 | JB9: =+DP9 -> 45.55 | JC9: =+DS9 -> 36.25 | JD9: =+DV9 -> 45.75 | JE9: =+DY9 -> 66.66 | JF9: =+EB9 -> 56.89 | JG9: =+EE9 -> 60.37 | JH9: =+EH9 -> 75.25 | JI9: =+EK9 -> 87.5 | JJ9: =+EN9 -> 116.21 | JK9: =EQ9 -> 119.47 | JL9: =ET9 -> 111.33 | JM9: =EW9 -> 100.12 | JN9: =EZ9 -> 89 | JO9: =FC9 -> 114.2 | JP9: =FF9 -> 123.71 | JQ9: =FI9 -> 154.91 | JR9: =FL9 -> 123.45 | JS9: =FO9 -> 131.67 | JT9: =FR9 -> 0 | JU9: =FU9 -> 0 | JV9: =FX9 -> 0 | JW9: =GA9 -> 0 | JX9: =GD9 -> 0 | JY9: =GG9 -> 0 | JZ9: =GJ9 -> 0 | KA9: =GM9 -> 0 | KB9: =GP9 -> 0 | KC9: =GS9 -> 0 | KD9: =GV9 -> 0 | KE9: =GY9 -> 0 | KF9: =HB9 -> 0 | KG9: =HE9 -> 0 | KH9: =HH9 -> 0
A11: Field Description | B11: Field Name | C11: {=_xll.EQNXTDZ($A$1,$B11,C$1)} -> 0 | D11: {=_xll.EQNXTDZ($A$1,$B11,D$1)} -> 0 | E11: {=_xll.EQNXTDZ($A$1,$B11,E$1)} -> 0 | F11: {=_xll.EQNXTDZ($A$1,$B11,F$1)} -> 0 | G11: {=_xll.EQNXTDZ($A$1,$B11,G$1)} -> 0 | H11: {=_xll.EQNXTDZ($A$1,$B11,H$1)} -> 0 | I11: {=_xll.EQNXTDZ($A$1,$B11,I$1)} -> 0 | J11: {=_xll.EQNXTDZ($A$1,$B11,J$1)} -> 0 | ... HH11: {=_xll.EQNXTDZ($A$1,$B11,HH$1)} -> 0
A12: Month End | B12: BMONTH_MONTHEND | C12: {=_xll.EQNXTDZ($A$1,$B12,C$1)} -> 201206 | D12: {=_xll.EQNXTDZ($A$1,$B12,D$1)} -> 201207 | E12: {=_xll.EQNXTDZ($A$1,$B12,E$1)} -> 201208 | F12: {=_xll.EQNXTDZ($A$1,$B12,F$1)} -> 201209 | G12: {=_xll.EQNXTDZ($A$1,$B12,G$1)} -> 201210 | H12: {=_xll.EQNXTDZ($A$1,$B12,H$1)} -> 201211 | I12: {=_xll.EQNXTDZ($A$1,$B12,I$1)} -> 201212 | J12: {=_xll.EQNXTDZ($A$1,$B12,J$1)} -> 201301 | ... HH12: {=_xll.EQNXTDZ($A$1,$B12,HH$1)} -> 0
A13: Open | B13: BMONTH_OPEN | C13: {=_xll.EQNXTDZ($A$1,$B13,C$1)} -> 76.860904 | D13: {=_xll.EQNXTDZ($A$1,$B13,D$1)} -> 81.422757 | E13: {=_xll.EQNXTDZ($A$1,$B13,E$1)} -> 71.005391 | F13: {=_xll.EQNXTDZ($A$1,$B13,F$1)} -> 62.251302 | G13: {=_xll.EQNXTDZ($A$1,$B13,G$1)} -> 83.650187 | H13: {=_xll.EQNXTDZ($A$1,$B13,H$1)} -> 78.203198 | I13: {=_xll.EQNXTDZ($A$1,$B13,I$1)} -> 73.048012 | J13: {=_xll.EQNXTDZ($A$1,$B13,J$1)} -> 97.160664 | ... HH13: {=_xll.EQNXTDZ($A$1,$B13,HH$1)} -> 0
A14: High | B14: BMONTH_HIGH | C14: {=_xll.EQNXTDZ($A$1,$B14,C$1)} -> 84.817399 | D14: {=_xll.EQNXTDZ($A$1,$B14,D$1)} -> 85.449638 | E14: {=_xll.EQNXTDZ($A$1,$B14,E$1)} -> 72.036428 | F14: {=_xll.EQNXTDZ($A$1,$B14,F$1)} -> 88.591384 | G14: {=_xll.EQNXTDZ($A$1,$B14,G$1)} -> 88.309307 | H14: {=_xll.EQNXTDZ($A$1,$B14,H$1)} -> 91.120343 | I14: {=_xll.EQNXTDZ($A$1,$B14,I$1)} -> 97.209298 | J14: {=_xll.EQNXTDZ($A$1,$B14,J$1)} -> 106.99442 | ... HH14: {=_xll.EQNXTDZ($A$1,$B14,HH$1)} -> 0 | HP14: =+MAX(D14:F14) -> 88.591384 | HQ14: =+MAX(G14:I14) -> 97.209298 | HR14: =+MAX(J14:L14) -> 106.99442 | HS14: =+MAX(M14:O14) -> 88.805373 | HT14: =+MAX(P14:R14) -> 75.576971 | HU14: =+MAX(S14:U14) -> 57.290651 | HV14: =+MAX(V14:X14) -> 56.84322 | HW14: =+MAX(Y14:AA14) -> 96.878588 | HX14: =+MAX(AB14:AD14) -> 91.412146 | HY14: =+MAX(AE14:AG14) -> 88.319034 | HZ14: =+MAX(AH14:AJ14) -> 93.065696 | IA14: =+MAX(AK14:AM14) -> 80.041556 | IB14: =+MAX(AN14:AP14) -> 70.003534 | IC14: =+MAX(AQ14:AS14) -> 59.333272 | ID14: =+MAX(AT14:AV14) -> 46.591209 | IE14: =+MAX(AW14:AY14) -> 43.011759 | IF14: =+MAX(AZ14:BB14) -> 62.04704 | IG14: =+MAX(BC14:BE14) -> 65.98638 | IH14: =+MAX(BF14:BH14) -> 61.910865 | II14: =+MAX(BI14:BK14) -> 82.98 | IJ14: =+MAX(BL14:BN14) -> 74.88 | IK14: =+MAX(BO14:BQ14) -> 92.68 | IL14: =+MAX(BR14:BT14) -> 76.99 | IM14: =+MAX(BU14:BW14) -> 59.18 | IN14: =+MAX(BX14:BZ14) -> 60.42 | IO14: =+MAX(CA14:CC14) -> 56.3 | IP14: =+MAX(CD14:CF14) -> 59.67 | IQ14: =+MAX(CG14:CI14) -> 60.4 | IR14: =+MAX(CJ14:CL14) -> 59.3 | IS14: =+MAX(CM14:CO14) -> 46.86 | IT14: =+MAX(CP14:CR14) -> 46 | IU14: =+MAX(CS14:CU14) -> 23.65 | IV14: =+MAX(CV14:CX14) -> 23.86 | IW14: =+MAX(CY14:DA14) -> 29.28 | IX14: =+MAX(DB14:DD14) -> 34.88 | IY14: =+MAX(DE14:DG14) -> 33.13 | IZ14: =+MAX(DH14:DJ14) -> 35.48 | JA14: =+MAX(DK14:DM14) -> 49.52 | JB14: =+MAX(DN14:DP14) -> 54.56 | JC14: =+MAX(DQ14:DS14) -> 50.5 | JD14: =+MAX(DT14:DV14) -> 51.51 | JE14: =+MAX(DW14:DY14) -> 67.33 | JF14: =+MAX(DZ14:EB14) -> 68.32 | JG14: =+MAX(EC14:EE14) -> 65.33 | JH14: =+MAX(EF14:EH14) -> 77.17 | JI14: =+MAX(EI14:EK14) -> 90.94 | JJ14: =+MAX(EL14:EN14) -> 121.2 | JK14: =MAX(EO14:EQ14) -> 129.35 | JL14: =MAX(ER14:ET14) -> 120.2 | JM14: =MAX(EU14:EW14) -> 112.45 | JN14: =MAX(EX14:EZ14) -> 103.1 | JO14: =MAX(FA14:FC14) -> 119.3 | JP14: =MAX(FD14:FF14) -> 124.6 | JQ14: =MAX(FG14:FI14) -> 158 | JR14: =MAX(FJ14:FL14) -> 162.9 | JS14: =MAX(FM14:FO14) -> 146.85 | JT14: =MAX(FP14:FR14) -> 0 | JU14: =MAX(FS14:FU14) -> 0 | JV14: =MAX(FV14:FX14) -> 0 | JW14: =MAX(FY14:GA14) -> 0 | JX14: =MAX(GB14:GD14) -> 0 | JY14: =MAX(GE14:GG14) -> 0 | JZ14: =MAX(GH14:GJ14) -> 0 | KA14: =MAX(GK14:GM14) -> 0 | KB14: =MAX(GN14:GP14) -> 0 | KC14: =MAX(GQ14:GS14) -> 0 | KD14: =MAX(GT14:GV14) -> 0 | KE14: =MAX(GW14:GY14) -> 0 | KF14: =MAX(GZ14:HB14) -> 0 | KG14: =MAX(HC14:HE14) -> 0 | KH14: =MAX(HF14:HH14) -> 0
A15: Low | B15: BMONTH_LOW | C15: {=_xll.EQNXTDZ($A$1,$B15,C$1)} -> 74.584841 | D15: {=_xll.EQNXTDZ($A$1,$B15,D$1)} -> 66.832608 | E15: {=_xll.EQNXTDZ($A$1,$B15,E$1)} -> 59.527807 | F15: {=_xll.EQNXTDZ($A$1,$B15,F$1)} -> 60.335129 | G15: {=_xll.EQNXTDZ($A$1,$B15,G$1)} -> 68.067908 | H15: {=_xll.EQNXTDZ($A$1,$B15,H$1)} -> 77.921122 | I15: {=_xll.EQNXTDZ($A$1,$B15,I$1)} -> 73.048012 | J15: {=_xll.EQNXTDZ($A$1,$B15,J$1)} -> 90.478376 | ... HH15: {=_xll.EQNXTDZ($A$1,$B15,HH$1)} -> 0 | HP15: =+MIN(D15:F15) -> 59.527807 | HQ15: =+MIN(G15:I15) -> 68.067908 | HR15: =+MIN(J15:L15) -> 69.254573 | HS15: =+MIN(M15:O15) -> 65.188785 | HT15: =+MIN(P15:R15) -> 36.942257 | HU15: =+MIN(S15:U15) -> 42.681049 | HV15: =+MIN(V15:X15) -> 40.657881 | HW15: =+MIN(Y15:AA15) -> 48.633829 | HX15: =+MIN(AB15:AD15) -> 65.198512 | HY15: =+MIN(AE15:AG15) -> 66.939603 | HZ15: =+MIN(AH15:AJ15) -> 67.396761 | IA15: =+MIN(AK15:AM15) -> 53.448579 | IB15: =+MIN(AN15:AP15) -> 48.799184 | IC15: =+MIN(AQ15:AS15) -> 45.346183 | ID15: =+MIN(AT15:AV15) -> 30.386417 | IE15: =+MIN(AW15:AY15) -> 34.199309 | IF15: =+MIN(AZ15:BB15) -> 42.272525 | IG15: =+MIN(BC15:BE15) -> 50.384647 | IH15: =+MIN(BF15:BH15) -> 50.034484 | II15: =+MIN(BI15:BK15) -> 60.41 | IJ15: =+MIN(BL15:BN15) -> 61.37 | IK15: =+MIN(BO15:BQ15) -> 59.37 | IL15: =+MIN(BR15:BT15) -> 45.07 | IM15: =+MIN(BU15:BW15) -> 46.8 | IN15: =+MIN(BX15:BZ15) -> 41.91 | IO15: =+MIN(CA15:CC15) -> 41.03 | IP15: =+MIN(CD15:CF15) -> 42.59 | IQ15: =+MIN(CG15:CI15) -> 47.76 | IR15: =+MIN(CJ15:CL15) -> 36 | IS15: =+MIN(CM15:CO15) -> 34.11 | IT15: =+MIN(CP15:CR15) -> 14.77 | IU15: =+MIN(CS15:CU15) -> 15.16 | IV15: =+MIN(CV15:CX15) -> 16.45 | IW15: =+MIN(CY15:DA15) -> 16.88 | IX15: =+MIN(DB15:DD15) -> 24.77 | IY15: =+MIN(DE15:DG15) -> 24.87 | IZ15: =+MIN(DH15:DJ15) -> 28.42 | JA15: =+MIN(DK15:DM15) -> 34 | JB15: =+MIN(DN15:DP15) -> 39.3 | JC15: =+MIN(DQ15:DS15) -> 34.34 | JD15: =+MIN(DT15:DV15) -> 35.7 | JE15: =+MIN(DW15:DY15) -> 44.1 | JF15: =+MIN(DZ15:EB15) -> 53.77 | JG15: =+MIN(EC15:EE15) -> 56.28 | JH15: =+MIN(EF15:EH15) -> 60.47 | JI15: =+MIN(EI15:EK15) -> 68.44 | JJ15: =+MIN(EL15:EN15) -> 87.7 | JK15: =MIN(EO15:EQ15) -> 99.6 | JL15: =MIN(ER15:ET15) -> 100.7 | JM15: =MIN(EU15:EW15) -> 92.55 | JN15: =MIN(EX15:EZ15) -> 78.58 | JO15: =MIN(FA15:FC15) -> 83.36 | JP15: =MIN(FD15:FF15) -> 103.5 | JQ15: =MIN(FG15:FI15) -> 121.2 | JR15: =MIN(FJ15:FL15) -> 123 | JS15: =MIN(FM15:FO15) -> 121.8 | JT15: =MIN(FP15:FR15) -> 0 | JU15: =MIN(FS15:FU15) -> 0 | JV15: =MIN(FV15:FX15) -> 0 | JW15: =MIN(FY15:GA15) -> 0 | JX15: =MIN(GB15:GD15) -> 0 | JY15: =MIN(GE15:GG15) -> 0 | JZ15: =MIN(GH15:GJ15) -> 0 | KA15: =MIN(GK15:GM15) -> 0 | KB15: =MIN(GN15:GP15) -> 0 | KC15: =MIN(GQ15:GS15) -> 0 | KD15: =MIN(GT15:GV15) -> 0 | KE15: =MIN(GW15:GY15) -> 0 | KF15: =MIN(GZ15:HB15) -> 0 | KG15: =MIN(HC15:HE15) -> 0 | KH15: =MIN(HF15:HH15) -> 0
A16: Close | B16: BMONTH_CLOSE | C16: {=_xll.EQNXTDZ($A$1,$B16,C$1)} -> 80.226365 | D16: {=_xll.EQNXTDZ($A$1,$B16,D$1)} -> 71.151292 | E16: {=_xll.EQNXTDZ($A$1,$B16,E$1)} -> 61.667696 | F16: {=_xll.EQNXTDZ($A$1,$B16,F$1)} -> 83.873902 | G16: {=_xll.EQNXTDZ($A$1,$B16,G$1)} -> 78.154564 | H16: {=_xll.EQNXTDZ($A$1,$B16,H$1)} -> 90.420016 | I16: {=_xll.EQNXTDZ($A$1,$B16,I$1)} -> 96.39225 | J16: {=_xll.EQNXTDZ($A$1,$B16,J$1)} -> 93.590941 | ... HH16: {=_xll.EQNXTDZ($A$1,$B16,HH$1)} -> 0 | HP16: =+F16 -> 83.873902 | HQ16: =+I16 -> 96.39225 | HR16: =+L16 -> 74.789103 | HS16: =+O16 -> 70.100802 | HT16: =+R16 -> 43.060393 | HU16: =+U16 -> 54.88814 | HV16: =+X16 -> 51.425411 | HW16: =+AA16 -> 89.914224 | HX16: =+AD16 -> 68.135995 | HY16: =+AG16 -> 87.307451 | HZ16: =+AJ16 -> 71.569543 | IA16: =+AM16 -> 54.071092 | IB16: =+AP16 -> 54.411528 | IC16: =+AS16 -> 45.453177 | ID16: =+AV16 -> 36.93253 | IE16: =+AY16 -> 42.49624 | IF16: =+BB16 -> 59.984965 | IG16: =+BE16 -> 51.133608 | IH16: =+BH16 -> 60.6 | II16: =+BK16 -> 65.8 | IJ16: =+BN16 -> 61.61 | IK16: =+BQ16 -> 72.18 | IL16: =+BT16 -> 52.85 | IM16: =+BW16 -> 50.32 | IN16: =+BZ16 -> 44.17 | IO16: =+CC16 -> 55 | IP16: =+CF16 -> 58.39 | IQ16: =+CI16 -> 56.88 | IR16: =+CL16 -> 36.46 | IS16: =+CO16 -> 44.26 | IT16: =+CR16 -> 18.08 | IU16: =+CU16 -> 20.12 | IV16: =+CX16 -> 17.78 | IW16: =+DA16 -> 25.79 | IX16: =+DD16 -> 30.45 | IY16: =+DG16 -> 30.37 | IZ16: =+DJ16 -> 34.6 | JA16: =+DM16 -> 39.98 | JB16: =+DP16 -> 45.52 | JC16: =+DS16 -> 36.25 | JD16: =+DV16 -> 45.74 | JE16: =+DY16 -> 66.71 | JF16: =+EB16 -> 56.9 | JG16: =+EE16 -> 60.36 | JH16: =+EH16 -> 75.27 | JI16: =+EK16 -> 87.54 | JJ16: =+EN16 -> 116.22 | JK16: =EQ16 -> 119.4 | JL16: =ET16 -> 111.45 | JM16: =EW16 -> 100.15 | JN16: =EZ16 -> 89.02 | JO16: =FC16 -> 114.2 | JP16: =FF16 -> 123.7 | JQ16: =FI16 -> 154.9 | JR16: =FL16 -> 123.55 | JS16: =FO16 -> 131.6 | JT16: =FR16 -> 0 | JU16: =FU16 -> 0 | JV16: =FX16 -> 0 | JW16: =GA16 -> 0 | JX16: =GD16 -> 0 | JY16: =GG16 -> 0 | JZ16: =GJ16 -> 0 | KA16: =GM16 -> 0 | KB16: =GP16 -> 0 | KC16: =GS16 -> 0 | KD16: =GV16 -> 0 | KE16: =GY16 -> 0 | KF16: =HB16 -> 0 | KG16: =HE16 -> 0 | KH16: =HH16 -> 0
A19: High | HP19: =+IF(HP14=0,HP7,HP14) -> 88.591384 | HQ19: =+IF(HQ14=0,HQ7,HQ14) -> 97.209298 | HR19: =+IF(HR14=0,HR7,HR14) -> 106.99442 | HS19: =+IF(HS14=0,HS7,HS14) -> 88.805373 | HT19: =+IF(HT14=0,HT7,HT14) -> 75.576971 | HU19: =+IF(HU14=0,HU7,HU14) -> 57.290651 | HV19: =+IF(HV14=0,HV7,HV14) -> 56.84322 | HW19: =+IF(HW14=0,HW7,HW14) -> 96.878588 | ... KH19: =+IF(KH14=0,KH7,KH14) -> 0
A20: Low | HP20: =+IF(HP15=0,HP8,HP15) -> 59.527807 | HQ20: =+IF(HQ15=0,HQ8,HQ15) -> 68.067908 | HR20: =+IF(HR15=0,HR8,HR15) -> 69.254573 | HS20: =+IF(HS15=0,HS8,HS15) -> 65.188785 | HT20: =+IF(HT15=0,HT8,HT15) -> 36.942257 | HU20: =+IF(HU15=0,HU8,HU15) -> 42.681049 | HV20: =+IF(HV15=0,HV8,HV15) -> 40.657881 | HW20: =+IF(HW15=0,HW8,HW15) -> 48.633829 | ... KH20: =+IF(KH15=0,KH8,KH15) -> 0
A21: Close | HP21: =+IF(HP16=0,HP9,HP16) -> 83.873902 | HQ21: =+IF(HQ16=0,HQ9,HQ16) -> 96.39225 | HR21: =+IF(HR16=0,HR9,HR16) -> 74.789103 | HS21: =+IF(HS16=0,HS9,HS16) -> 70.100802 | HT21: =+IF(HT16=0,HT9,HT16) -> 43.060393 | HU21: =+IF(HU16=0,HU9,HU16) -> 54.88814 | HV21: =+IF(HV16=0,HV9,HV16) -> 51.425411 | HW21: =+IF(HW16=0,HW9,HW16) -> 89.914224 | ... KH21: =+IF(KH16=0,KH9,KH16) -> 0

Sheet 4_Axis Bank Ltd._Balance Sheet
A1: 132215
A3: =_xll.EQNXTV("Company-Profit And Loss",A1,"Crores/INR/40/Asc/N2",C3,D3,E3,F3,G3,H3) -> EQNXTV | C3: Standalone | D3: Abridged | E3: Actual | F3: 202503 | G3: Reported | H3: Gross Sales
A5: Profit And Loss - Standalone | C5: Axis Bank Ltd. | E5: INR Crores
A6: DESCRIPTION | B6: 34759 | C6: 35490 | D6: 35855 | E6: 36220 | F6: 36586 | G6: 36951 | H6: 37316 | I6: 37681 | J6: 38047 | K6: 38412 | L6: 38777 | M6: 39142 | N6: 39508 | O6: 39873 | P6: 40238 | Q6: 40603 | R6: 40969 | S6: 41334 | T6: 41699 | U6: 42064 | V6: 42430 | W6: 42795 | X6: 43160 | Y6: 43525 | Z6: 43891 | AA6: 44256 | AB6: 44621 | AC6: 44986 | AD6: 45352 | AE6: 45717
A8: No of Months | B8: 12 | C8: 12 | D8: 12 | E8: 12 | F8: 12 | G8: 12 | H8: 12 | I8: 12 | J8: 12 | K8: 12 | L8: 12 | M8: 12 | N8: 12 | O8: 12 | P8: 12 | Q8: 12 | R8: 12 | S8: 12 | T8: 12 | U8: 12 | V8: 12 | W8: 12 | X8: 12 | Y8: 12 | Z8: 12 | AA8: 12 | AB8: 12 | AC8: 12 | AD8: 12 | AE8: 12
A9: I. INCOME
A10: Interest Earned | B10: 29.1719 | C10: 157.6474 | D10: 255.61 | E10: 373.281 | F10: 483.2599 | G10: 889.6314 | H10: 1178.53 | I10: 1464.81 | J10: 1598.543 | K10: 1924.1582 | L10: 2888.7904 | M10: 4461.6552 | N10: 7005.3151 | O10: 10835.486 | P10: 11638.022 | Q10: 15154.806 | R10: 21994.647 | S10: 27182.574 | T10: 30641.155 | U10: 35478.598 | V10: 40988.036 | W10: 44542.158 | X10: 45780.312 | Y10: 54985.771 | Z10: 62635.157 | AA10: 63346.232 | AB10: 67376.83 | AC10: 85163.766 | AD10: 109368.63 | AE10: 122677.04
A11: Other Income | B11: 1.8346 | C11: 24.1029 | D11: 60.8991 | E11: 46.6287 | F11: 91.1659 | G11: 163.0001 | H11: 415.87 | I11: 410.47 | J11: 540.1456 | K11: 415.8196 | L11: 729.6344 | M11: 1010.1113 | N11: 1795.4888 | O11: 2896.8781 | P11: 3945.7819 | Q11: 4632.1338 | R11: 5420.2163 | S11: 6551.1063 | T11: 7405.2247 | U11: 8365.0458 | V11: 9371.4644 | W11: 11691.311 | X11: 10967.086 | Y11: 13130.339 | Z11: 15536.561 | AA11: 12263.599 | AB11: 15220.545 | AC11: 16143.419 | AD11: 22441.955 | AE11: 25257.056
A12: Total Income | B12: 31.0065 | C12: 181.7503 | D12: 316.5091 | E12: 419.9097 | F12: 574.4258 | G12: 1052.6315 | H12: 1594.4 | I12: 1875.28 | J12: 2138.6886 | K12: 2339.9778 | L12: 3618.4248 | M12: 5471.7665 | N12: 8800.8039 | O12: 13732.364 | P12: 15583.803 | Q12: 19786.94 | R12: 27414.864 | S12: 33733.681 | T12: 38046.38 | U12: 43843.643 | V12: 50359.501 | W12: 56233.469 | X12: 56747.399 | Y12: 68116.11 | Z12: 78171.718 | AA12: 75609.831 | AB12: 82597.375 | AC12: 101307.19 | AD12: 131810.59 | AE12: 147934.1
A13: II. EXPENDITURE
A14: Interest Expended | B14: 14.0985 | C14: 122.0736 | D14: 222.1898 | E14: 300.6328 | F14: 392.8564 | G14: 791.3638 | H14: 980 | I14: 1142.41 | J14: 1021.4487 | K14: 1192.9808 | L14: 1810.556 | M14: 2993.3172 | N14: 4419.9617 | O14: 7149.2742 | P14: 6633.5261 | Q14: 8591.823 | R14: 13976.902 | S14: 17516.311 | T14: 18689.522 | U14: 21254.46 | V14: 24155.068 | W14: 26449.042 | X14: 27162.582 | Y14: 33277.597 | Z14: 37428.954 | AA14: 34107.11 | AB14: 34244.613 | AC14: 42218.021 | AD14: 59474.146 | AE14: 68329.221
A15: Operating Expenses | B15: 7.8485 | C15: 26.6971 | D15: 39.7558 | E15: 51.0262 | F15: 65.4009 | G15: 128.7637 | H15: 207.12 | I15: 322.85 | J15: 419.2055 | K15: 581.3789 | L15: 814.0507 | M15: 1214.5984 | N15: 2154.9269 | O15: 2858.2127 | P15: 3709.7223 | Q15: 4779.4281 | R15: 6007.0995 | S15: 6914.2375 | T15: 7900.7739 | U15: 9203.7456 | V15: 10100.819 | W15: 12199.905 | X15: 13990.34 | Y15: 15833.408 | Z15: 17304.624 | AA15: 18375.149 | AB15: 23610.754 | AC15: 39298.538 | AD15: 35213.284 | AE15: 37499.943
A16: Provisions and Contingencies | B16: 3.077 | C16: 17.7587 | D16: 25.2068 | E16: 21.9707 | F16: 37.4932 | G16: 28.0513 | H16: 193.91 | I16: 108.73 | J16: 268.6724 | K16: 51.0104 | L16: 262.3844 | M16: 267.3626 | N16: 579.4163 | O16: 939.3984 | P16: 1388.8417 | Q16: 1279.2779 | R16: 1142.6664 | S16: 1750.0592 | T16: 2107.0376 | U16: 2327.6761 | V16: 3709.9119 | W16: 12116.962 | X16: 15472.906 | Y16: 12031.017 | Z16: 18533.915 | AA16: 14321.721 | AB16: 7359.4491 | AC16: 2884.7777 | AD16: 4063.0948 | AE16: 7758.3504
A17: Profit Before Tax | B17: 5.9825 | C17: 15.2209 | D17: 29.3567 | E17: 46.28 | F17: 78.6753 | G17: 104.4527 | H17: 213.37 | I17: 301.29 | J17: 429.362 | K17: 514.6077 | L17: 731.4337 | M17: 996.4883 | N17: 1646.499 | O17: 2785.4784 | P17: 3851.7133 | Q17: 5136.4106 | R17: 6288.1954 | S17: 7553.0729 | T17: 9349.0466 | U17: 11057.762 | V17: 12393.703 | W17: 5467.5592 | X17: 121.5713 | Y17: 6974.0883 | Z17: 4904.2254 | AA17: 8805.8506 | AB17: 17382.558 | AC17: 16905.849 | AD17: 33060.063 | AE17: 34346.582
A18: Taxes | B18: 3.6733 | C18: 0 | D18: 11.7398 | E18: 15.21 | F18: 27.75 | G18: 18.33 | H18: 79.23 | I18: 109.11 | J18: 151.05 | K18: 180.03 | L18: 246.35 | M18: 337.46 | N18: 575.47 | O18: 970.12 | P18: 1337.18 | Q18: 1747.92 | R18: 2045.99 | S18: 2373.64 | T18: 3131.38 | U18: 3699.94 | V18: 4170.04 | W18: 1788.28 | X18: -154.11 | Y18: 2297.48 | Z18: 3277.01 | AA18: 2217.35 | AB18: 4357.08 | AC18: 7326.17 | AD18: 8198.63 | AE18: 7973.1
A19: Total | B19: 28.6973 | C19: 166.5294 | D19: 298.8922 | E19: 388.8397 | F19: 523.5005 | G19: 966.5088 | H19: 1460.26 | I19: 1683.1 | J19: 1860.3766 | K19: 2005.4001 | L19: 3133.3411 | M19: 4812.7382 | N19: 7729.7749 | O19: 11917.005 | P19: 13069.27 | Q19: 16398.449 | R19: 23172.658 | S19: 28554.248 | T19: 31828.714 | U19: 36485.821 | V19: 42135.838 | W19: 52554.189 | X19: 56471.717 | Y19: 63439.502 | Z19: 76544.503 | AA19: 69021.33 | AB19: 69571.897 | AC19: 91727.507 | AD19: 106949.15 | AE19: 121560.61
A20: III. PROFIT AND LOSS
A21: Profit After Tax | B21: 2.3092 | C21: 15.2209 | D21: 17.6169 | E21: 31.07 | F21: 50.9253 | G21: 86.1227 | H21: 134.14 | I21: 192.18 | J21: 278.312 | K21: 334.5777 | L21: 485.0837 | M21: 659.0283 | N21: 1071.029 | O21: 1815.3584 | P21: 2514.5333 | Q21: 3388.4906 | R21: 4242.2054 | S21: 5179.4329 | T21: 6217.6666 | U21: 7357.8223 | V21: 8223.6628 | W21: 3679.2792 | X21: 275.6813 | Y21: 4676.6083 | Z21: 1627.2154 | AA21: 6588.5006 | AB21: 13025.478 | AC21: 9579.6785 | AD21: 24861.433 | AE21: 26373.482
A22: Extra items | C22: 0 | D22: -1.0307 | L22: 0 | M22: 0 | N22: 0 | O22: 0 | P22: 0 | R22: 0
A23: Profit brought forward | C23: 10.8176 | D23: 20.5338 | E23: 30.7108 | F23: 41.9893 | G23: 52.598 | H23: 74.37 | I23: 78.64 | J23: 122.4667 | K23: 182.1024 | L23: 197.4076 | M23: 731.039 | N23: 1029.074 | O23: 1553.8689 | P23: 2348.0865 | Q23: 3427.4337 | R23: 4969.7707 | S23: 7329.4476 | T23: 10029.262 | U23: 13501.446 | V23: 17623.491 | W23: 23766.456 | X23: 24448.327 | Y23: 23043.052 | Z23: 24322.995 | AA23: 26190.455 | AB23: 29985.281 | AC23: 38100.659 | AD23: 44144.93 | AE23: 60254.056
A24: Adjustments to PAT | C24: -0.2039 | D24: -0.5614 | E24: 0.0124 | F24: 0.1358 | G24: 0.0014 | H24: 2.39 | M24: -31.8028
A25: Total Profit & Loss | B25: 2.3092 | C25: 25.8346 | D25: 37.5893 | E25: 61.7932 | F25: 93.0504 | G25: 138.7221 | H25: 210.9 | I25: 270.82 | J25: 400.7787 | K25: 516.6801 | L25: 682.4913 | M25: 1358.2645 | N25: 2100.103 | O25: 3369.2273 | P25: 4862.6198 | Q25: 6815.9243 | R25: 9211.9761 | S25: 12508.88 | T25: 16246.929 | U25: 20859.268 | V25: 25847.154 | W25: 27445.735 | X25: 24724.009 | Y25: 27719.66 | Z25: 25950.211 | AA25: 32778.955 | AB25: 43010.759 | AC25: 47680.338 | AD25: 69006.363 | AE25: 86627.538
A26: IV. APPROPRIATIONS | B26: 2.3092 | C26: 25.8346 | D26: 36.5586 | E26: 61.7932 | F26: 93.0504 | G26: 138.7221 | H26: 210.9 | I26: 270.82 | J26: 400.7787 | K26: 516.6801 | L26: 682.4913 | M26: 1358.2645 | N26: 2100.103 | O26: 3369.2273 | P26: 4862.6198 | Q26: 6815.9243 | R26: 9211.9761 | S26: 12508.88 | T26: 16246.929 | U26: 20859.268 | V26: 25847.154 | W26: 27445.735 | X26: 24724.009 | Y26: 27719.66 | Z26: 25950.211 | AA26: 32778.955 | AB26: 43010.759 | AC26: 47680.338 | AD26: 69006.363 | AE26: 86627.538
A27: Equity Dividend % | E27: 10 | F27: 12 | G27: 15 | H27: 20 | I27: 22 | J27: 25 | K27: 28 | L27: 35 | M27: 45 | N27: 60 | O27: 100 | P27: 120 | Q27: 140 | R27: 160 | S27: 180 | T27: 200 | U27: 230 | V27: 250 | W27: 250 | Y27: 50 | AB27: 50 | AC27: 50 | AD27: 50 | AE27: 50
A28: Earnings Per Share(Calculated) | B28: 0.20079983 | C28: 1.3235554 | D28: 1.531903 | E28: 2.3555153 | F28: 3.8608085 | G28: 6.5292351 | H28: 6.9933789 | I28: 8.3487554 | J28: 12.017932 | K28: 12.219945 | L28: 17.4058 | M28: 23.4004 | N28: 29.9413 | O28: 50.5664 | P28: 62.0606 | Q28: 82.5362 | R28: 102.6662 | S28: 110.6824 | T28: 132.3345 | U28: 31.0388 | V28: 34.5121 | W28: 15.3621 | X28: 1.0741 | Y28: 18.1853 | Z28: 5.7668 | AA28: 21.5047 | AB28: 42.4318 | AC28: 31.134674 | AD28: 80.5471 | AE28: 85.148
A29: Adjusted EPS | B29: 0.040159965 | C29: 0.26471107 | D29: 0.3063806 | E29: 0.47110305 | F29: 0.77216171 | G29: 1.305847 | H29: 1.3986758 | I29: 1.6697511 | J29: 2.4035865 | K29: 2.443989 | L29: 3.4812 | M29: 4.6801 | N29: 5.9883 | O29: 10.1133 | P29: 12.4121 | Q29: 16.5072 | R29: 20.5332 | S29: 22.1365 | T29: 26.4669 | U29: 31.0388 | V29: 34.5121 | W29: 15.3621 | X29: 1.0741 | Y29: 18.1853 | Z29: 5.7668 | AA29: 21.5047 | AB29: 42.4318 | AC29: 31.1347 | AD29: 80.5471 | AE29: 85.148
A30: EPS - Basic (Reported) | E30: 2.36 | F30: 3.86 | G30: 6.53 | H30: 6.99 | I30: 8.35 | J30: 12.02 | K30: 12.22 | L30: 17.45 | M30: 23.5 | N30: 32.15 | O30: 50.61 | P30: 65.78 | Q30: 82.95 | R30: 102.94 | S30: 119.67 | T30: 26.51 | U30: 31.18 | V30: 34.59 | W30: 15.4 | X30: 1.13 | Y30: 18.2 | Z30: 5.99 | AA30: 22.15 | AB30: 42.48 | AC30: 31.17 | AD30: 80.67 | AE30: 85.28
A31: EPS - Diluted (Reported) | Q31: 81.61 | R31: 102.2 | U31: 30.85 | V31: 34.4 | X31: 1.12 | Y31: 18.09 | Z31: 5.97 | AA31: 22.09 | AB31: 42.35 | AC31: 31.02 | AD31: 80.1 | AE31: 84.77
