Workbook

Sheet Template
A1: =+'Annual Raw'!C4 -> #NAME? | B1: 36951 | C1: =EOMONTH(B1,12) -> 37346 | D1: =EOMONTH(C1,12) -> 37711 | E1: =EOMONTH(D1,12) -> 38077 | F1: =EOMONTH(E1,12) -> 38442 | G1: =EOMONTH(F1,12) -> 38807 | H1: =EOMONTH(G1,12) -> 39172 | I1: =EOMONTH(H1,12) -> 39538 | J1: =EOMONTH(I1,12) -> 39903 | ... AE1: =EOMONTH(AD1,12) -> 47573 | AH1: QTR | AI1: 41061 | AJ1: 41153 | AK1: 41244 | AL1: 41334 | AM1: 41426 | AN1: 41518 | AO1: 41609 | AP1: 41699 | AQ1: 41791 | AR1: 41883 | AS1: 41974 | AT1: 42064 | AU1: 42156 | AV1: 42248 | AW1: 42339 | AX1: 42430 | AY1: 42522 | AZ1: 42614 | BA1: 42705 | BB1: 42795 | BC1: 42887 | BD1: 42979 | BE1: 43070 | BF1: 43160 | BG1: 43252 | BH1: 43344 | BI1: 43435 | BJ1: 43525 | BK1: 43617 | BL1: 43709 | BM1: 43800 | BN1: 43891 | BO1: 43983 | BP1: 44075 | BQ1: =EOMONTH(BP1,3) -> 44196 | BR1: =EOMONTH(BQ1,3) -> 44286 | BS1: =EOMONTH(BR1,3) -> 44377 | BT1: =EOMONTH(BS1,3) -> 44469 | BU1: =EOMONTH(BT1,3) -> 44561 | BV1: =EOMONTH(BU1,3) -> 44651 | BW1: =EOMONTH(BV1,3) -> 44742 | BX1: =EOMONTH(BW1,3) -> 44834 | ... DB1: =EOMONTH(DA1,3) -> 47573 | DE1: HISTORICAL ESTIMATES | DF1: 46112
A2: Presentation Data (Start)
A3: Sales
A4: Direct Export | BW4: 4.28 | BX4: 7.57 | BY4: 9.32 | BZ4: 10.37 | CA4: 9.63 | CB4: 12.59 | CC4: 14.82 | CD4: 22.42 | CE4: 16.62 | CF4: 24.53 | CG4: 25.73 | CH4: 41.85 | CI4: 30 | CJ4: 36 | CK4: 40 | CL4: =CH4+(CH4*CL11) -> 50.22 | CM4: =CI4+(CI4*CM11) -> 36 | CN4: =CJ4+(CJ4*CN11) -> 43.2 | CO4: =CK4+(CK4*CO11) -> 48 | CP4: =CL4+(CL4*CP11) -> 60.264 | CQ4: =CM4+(CM4*CQ11) -> 43.2 | CR4: =CN4+(CN4*CR11) -> 51.84 | CS4: =CO4+(CO4*CS11) -> 57.6 | ... DB4: =CX4+(CX4*DB11) -> 104.13619 | DF4: 50.22
A5: Third party and Tolling | BW5: 38.95 | BX5: 53.01 | BY5: 56.68 | BZ5: 53.47 | CA5: 39.16 | CB5: 46.43 | CC5: 48.83 | CD5: 62.54 | CE5: 36.39 | CF5: 44.79 | CG5: 36.02 | CH5: 58.59 | CI5: 45 | CJ5: 52 | CK5: 55 | CL5: =CH5+(CH5*CL12) -> 70.308 | CM5: =CI5+(CI5*CM12) -> 54 | CN5: =CJ5+(CJ5*CN12) -> 62.4 | CO5: =CK5+(CK5*CO12) -> 66 | CP5: =CL5+(CL5*CP12) -> 84.3696 | CQ5: =CM5+(CM5*CQ12) -> 64.8 | CR5: =CN5+(CN5*CR12) -> 74.88 | CS5: =CO5+(CO5*CS12) -> 79.2 | ... DB5: =CX5+(CX5*DB12) -> 145.79067 | DF5: 70.308
A6: Institutional sales | BW6: 0.95 | BX6: 2.07 | BY6: 3.11 | BZ6: 3.99 | CA6: 4.49 | CB6: 5.51 | CC6: 6.1 | CD6: 7.08 | CE6: 6.33 | CF6: 9.6 | CG6: 10.29 | CH6: 16.74 | CI6: 10 | CJ6: 14 | CK6: 15 | CL6: =CH6+(CH6*CL13) -> 21.762 | CM6: =CI6+(CI6*CM13) -> 13 | CN6: =CJ6+(CJ6*CN13) -> 18.2 | CO6: =CK6+(CK6*CO13) -> 19.5 | CP6: =CL6+(CL6*CP13) -> 28.2906 | CQ6: =CM6+(CM6*CQ13) -> 16.9 | CR6: =CN6+(CN6*CR13) -> 23.66 | CS6: =CO6+(CO6*CS13) -> 25.35 | ... DB6: =CX6+(CX6*DB13) -> 62.154448 | DF6: 21.762
A7: New age ( pet /nutra) | BW7: 3.33 | BX7: 6.19 | BY7: 8.54 | BZ7: 11.97 | CA7: 10.91 | CB7: 14.17 | CC7: 17.44 | CD7: 25.96 | CE7: 19.78 | CF7: 27.73 | CG7: 30.87 | CH7: 50.22 | CI7: 35 | CJ7: 43 | CK7: 50 | CL7: =CH7+(CH7*CL14) -> 75.33 | CM7: =CI7+(CI7*CM14) -> 52.5 | CN7: =CJ7+(CJ7*CN14) -> 64.5 | CO7: =CK7+(CK7*CO14) -> 75 | CP7: =CL7+(CL7*CP14) -> 112.995 | CQ7: =CM7+(CM7*CQ14) -> 78.75 | CR7: =CN7+(CN7*CR14) -> 96.75 | CS7: =CO7+(CO7*CS14) -> 112.5 | ... DB7: =CX7+(CX7*DB14) -> 381.35813 | DF7: 75.33
BW8: =SUM(BW4:BW7) -> 47.51 | BX8: =SUM(BX4:BX7) -> 68.84 | BY8: =SUM(BY4:BY7) -> 77.65 | BZ8: =SUM(BZ4:BZ7) -> 79.8 | CA8: =SUM(CA4:CA7) -> 64.19 | CB8: =SUM(CB4:CB7) -> 78.7 | CC8: =SUM(CC4:CC7) -> 87.19 | CD8: =SUM(CD4:CD7) -> 118 | ... DB8: =SUM(DB4:DB7) -> 693.43943 | DF8: 217.62
A10: YOY%
A11: Direct Export | CA11: =CA4/BW4-1 -> 1.25 | CB11: =CB4/BX4-1 -> 0.66314399 | CC11: =CC4/BY4-1 -> 0.59012876 | CD11: =CD4/BZ4-1 -> 1.1620058 | CE11: =CE4/CA4-1 -> 0.7258567 | CF11: =CF4/CB4-1 -> 0.94837172 | CG11: =CG4/CC4-1 -> 0.73616734 | CH11: =CH4/CD4-1 -> 0.86663693 | ... CK11: =CK4/CG4-1 -> 0.55460552 | CL11: 0.2 | CM11: 0.2 | CN11: 0.2 | CO11: 0.2 | CP11: 0.2 | CQ11: 0.2 | CR11: 0.2 | CS11: 0.2 | CT11: 0.2 | CU11: 0.2 | CV11: 0.2 | CW11: 0.2 | CX11: 0.2 | CY11: 0.2 | CZ11: 0.2 | DA11: 0.2 | DB11: 0.2 | DF11: 0.2
A12: Third party and Tolling | CA12: =CA5/BW5-1 -> 0.0053915276 | CB12: =CB5/BX5-1 -> -0.12412752 | CC12: =CC5/BY5-1 -> -0.13849682 | CD12: =CD5/BZ5-1 -> 0.16962783 | CE12: =CE5/CA5-1 -> -0.070735444 | CF12: =CF5/CB5-1 -> -0.03532199 | CG12: =CG5/CC5-1 -> -0.26233873 | CH12: =CH5/CD5-1 -> -0.063159578 | ... CK12: =CK5/CG5-1 -> 0.52692948 | CL12: 0.2 | CM12: 0.2 | CN12: 0.2 | CO12: 0.2 | CP12: 0.2 | CQ12: 0.2 | CR12: 0.2 | CS12: 0.2 | CT12: 0.2 | CU12: 0.2 | CV12: 0.2 | CW12: 0.2 | CX12: 0.2 | CY12: 0.2 | CZ12: 0.2 | DA12: 0.2 | DB12: 0.2 | DF12: 0.2
A13: Institutional sales | CA13: =CA6/BW6-1 -> 3.7263158 | CB13: =CB6/BX6-1 -> 1.6618357 | CC13: =CC6/BY6-1 -> 0.96141479 | CD13: =CD6/BZ6-1 -> 0.77443609 | CE13: =CE6/CA6-1 -> 0.40979955 | CF13: =CF6/CB6-1 -> 0.74228675 | CG13: =CG6/CC6-1 -> 0.68688525 | CH13: =CH6/CD6-1 -> 1.3644068 | ... CK13: =CK6/CG6-1 -> 0.45772595 | CL13: 0.3 | CM13: 0.3 | CN13: 0.3 | CO13: 0.3 | CP13: 0.3 | CQ13: 0.3 | CR13: 0.3 | CS13: 0.3 | CT13: 0.3 | CU13: 0.3 | CV13: 0.3 | CW13: 0.3 | CX13: 0.3 | CY13: 0.3 | CZ13: 0.3 | DA13: 0.3 | DB13: 0.3 | DF13: 0.3
A14: New age ( pet /nutra) | CA14: =CA7/BW7-1 -> 2.2762763 | CB14: =CB7/BX7-1 -> 1.2891761 | CC14: =CC7/BY7-1 -> 1.0421546 | CD14: =CD7/BZ7-1 -> 1.1687552 | CE14: =CE7/CA7-1 -> 0.81301558 | CF14: =CF7/CB7-1 -> 0.95695131 | CG14: =CG7/CC7-1 -> 0.77006881 | CH14: =CH7/CD7-1 -> 0.93451464 | ... CK14: =CK7/CG7-1 -> 0.6196955 | CL14: 0.5 | CM14: 0.5 | CN14: 0.5 | CO14: 0.5 | CP14: 0.5 | CQ14: 0.5 | CR14: 0.5 | CS14: 0.5 | CT14: 0.5 | CU14: 0.5 | CV14: 0.5 | CW14: 0.5 | CX14: 0.5 | CY14: 0.5 | CZ14: 0.5 | DA14: 0.5 | DB14: 0.5 | DF14: 0.5
A17: Presentation Data (End)
A18: Profit & Loss- Annual (Start)
A19: Gross Revenue | B19: ='Annual Raw'!C6 -> #NAME? | C19: ='Annual Raw'!D6 -> #NAME? | D19: ='Annual Raw'!E6 -> #NAME? | E19: ='Annual Raw'!F6 -> #NAME? | F19: ='Annual Raw'!G6 -> #NAME? | G19: ='Annual Raw'!H6 -> #NAME? | H19: ='Annual Raw'!I6 -> #NAME? | I19: ='Annual Raw'!J6 -> #NAME? | ... AA19: ='Annual Raw'!AB6 -> #NAME? | AB19: =+SUM(CM19:CP19) -> 838.2192 | AC19: =+SUM(CQ19:CT19) -> 1105.2606 | AD19: =+SUM(CU19:CX19) -> 1473.8292 | AE19: =+SUM(CY19:DB19) -> 1987.8161 | AI19: ='QTR Raw'!C6+'QTR Raw'!C8 -> #NAME? | AJ19: ='QTR Raw'!D6+'QTR Raw'!D8 -> #NAME? | AK19: ='QTR Raw'!E6+'QTR Raw'!E8 -> #NAME? | AL19: ='QTR Raw'!F6+'QTR Raw'!F8 -> #NAME? | AM19: ='QTR Raw'!G6+'QTR Raw'!G8 -> #NAME? | AN19: ='QTR Raw'!H6+'QTR Raw'!H8 -> #NAME? | AO19: ='QTR Raw'!I6+'QTR Raw'!I8 -> #NAME? | AP19: ='QTR Raw'!J6+'QTR Raw'!J8 -> #NAME? | ... CF19: ='QTR Raw'!AZ6+'QTR Raw'!AZ8 -> #NAME? | CG19: 102.697 | CH19: ='QTR Raw'!BB6+'QTR Raw'!BB8 -> #NAME? | CI19: ='QTR Raw'!BC6+'QTR Raw'!BC8 -> #NAME? | CJ19: ='QTR Raw'!BD6+'QTR Raw'!BD8 -> #NAME? | CK19: ='QTR Raw'!BE6+'QTR Raw'!BE8 -> #NAME? | CL19: ='QTR Raw'!BF6+'QTR Raw'!BF8 -> #NAME? | CM19: =CM8 -> 155.5 | CN19: =CN8 -> 188.3 | CO19: =CO8 -> 208.5 | CP19: =CP8 -> 285.9192 | CQ19: =CQ8 -> 203.65 | CR19: =CR8 -> 247.13 | CS19: =CS8 -> 274.65 | CT19: =CT8 -> 379.8306 | ... DB19: =DB8 -> 693.43943 | DF19: 639.124
A20: Less: Exise Duty | B20: ='Annual Raw'!C7+'Annual Raw'!C8+'Annual Raw'!C9 -> #NAME? | C20: ='Annual Raw'!D7+'Annual Raw'!D8+'Annual Raw'!D9 -> #NAME? | D20: ='Annual Raw'!E7+'Annual Raw'!E8+'Annual Raw'!E9 -> #NAME? | E20: ='Annual Raw'!F7+'Annual Raw'!F8+'Annual Raw'!F9 -> #NAME? | F20: ='Annual Raw'!G7+'Annual Raw'!G8+'Annual Raw'!G9 -> #NAME? | G20: ='Annual Raw'!H7+'Annual Raw'!H8+'Annual Raw'!H9 -> #NAME? | H20: ='Annual Raw'!I7+'Annual Raw'!I8+'Annual Raw'!I9 -> #NAME? | I20: ='Annual Raw'!J7+'Annual Raw'!J8+'Annual Raw'!J9 -> #NAME? | ... AA20: ='Annual Raw'!AB7+'Annual Raw'!AB8+'Annual Raw'!AB9 -> #NAME? | AB20: =+SUM(CM20:CP20) -> 0 | AC20: =+SUM(CQ20:CT20) -> 0 | AD20: =+SUM(CU20:CX20) -> 0 | AE20: =+SUM(CY20:DB20) -> 0 | AI20: =+'QTR Raw'!C20+'QTR Raw'!C19+'QTR Raw'!C13+'QTR Raw'!C7 -> #NAME? | AJ20: =+'QTR Raw'!D20+'QTR Raw'!D19+'QTR Raw'!D13+'QTR Raw'!D7 -> #NAME? | AK20: =+'QTR Raw'!E20+'QTR Raw'!E19+'QTR Raw'!E13+'QTR Raw'!E7 -> #NAME? | AL20: =+'QTR Raw'!F20+'QTR Raw'!F19+'QTR Raw'!F13+'QTR Raw'!F7 -> #NAME? | AM20: =+'QTR Raw'!G20+'QTR Raw'!G19+'QTR Raw'!G13+'QTR Raw'!G7 -> #NAME? | AN20: =+'QTR Raw'!H20+'QTR Raw'!H19+'QTR Raw'!H13+'QTR Raw'!H7 -> #NAME? | AO20: =+'QTR Raw'!I20+'QTR Raw'!I19+'QTR Raw'!I13+'QTR Raw'!I7 -> #NAME? | AP20: =+'QTR Raw'!J20+'QTR Raw'!J19+'QTR Raw'!J13+'QTR Raw'!J7 -> #NAME? | ... CF20: =+'QTR Raw'!AZ20+'QTR Raw'!AZ19+'QTR Raw'!AZ13+'QTR Raw'!AZ7 -> #NAME? | CG20: 0 | CH20: =+'QTR Raw'!BB20+'QTR Raw'!BB19+'QTR Raw'!BB13+'QTR Raw'!BB7 -> #NAME? | CI20: =+'QTR Raw'!BC20+'QTR Raw'!BC19+'QTR Raw'!BC13+'QTR Raw'!BC7 -> #NAME? | CJ20: =+'QTR Raw'!BD20+'QTR Raw'!BD19+'QTR Raw'!BD13+'QTR Raw'!BD7 -> #NAME? | CK20: =+'QTR Raw'!BE20+'QTR Raw'!BE19+'QTR Raw'!BE13+'QTR Raw'!BE7 -> #NAME? | CL20: =+'QTR Raw'!BF20+'QTR Raw'!BF19+'QTR Raw'!BF13+'QTR Raw'!BF7 -> #NAME? | DF20: 0
A21: Net Revenue | B21: =+B19-B20 -> #NAME? | C21: =+C19-C20 -> #NAME? | D21: =+D19-D20 -> #NAME? | E21: =+E19-E20 -> #NAME? | F21: =+F19-F20 -> #NAME? | G21: =+G19-G20 -> #NAME? | H21: =+H19-H20 -> #NAME? | I21: =+I19-I20 -> #NAME? | ... AE21: =+AE19-AE20 -> 1987.8161 | AI21: =+AI19-AI20 -> #NAME? | AJ21: =+AJ19-AJ20 -> #NAME? | AK21: =+AK19-AK20 -> #NAME? | AL21: =+AL19-AL20 -> #NAME? | AM21: =+AM19-AM20 -> #NAME? | AN21: =+AN19-AN20 -> #NAME? | AO21: =+AO19-AO20 -> #NAME? | AP21: =+AP19-AP20 -> #NAME? | ... CF21: =+CF19-CF20 -> #NAME? | CG21: 102.697 | CH21: =+CH19-CH20 -> #NAME? | CI21: =+CI19-CI20 -> #NAME? | CJ21: =+CJ19-CJ20 -> #NAME? | CK21: =+CK19-CK20 -> #NAME? | CL21: =+CL19-CL20 -> #NAME? | CM21: =+CM19-CM20 -> 155.5 | CN21: =+CN19-CN20 -> 188.3 | CO21: =+CO19-CO20 -> 208.5 | ... DB21: =+DB19-DB20 -> 693.43943 | DF21: 639.124
A22: Net Revenue YOY% | C22: =C21/B21-1 -> #NAME? | D22: =D21/C21-1 -> #NAME? | E22: =E21/D21-1 -> #NAME? | F22: =F21/E21-1 -> #NAME? | G22: =G21/F21-1 -> #NAME? | H22: =H21/G21-1 -> #NAME? | I22: =I21/H21-1 -> #NAME? | J22: =J21/I21-1 -> #NAME? | ... AE22: =AE21/AD21-1 -> 0.34874249 | AM22: =+IF(AI21<0,1-AM21/AI21,AM21/AI21-1) -> #NAME? | AN22: =+IF(AJ21<0,1-AN21/AJ21,AN21/AJ21-1) -> #NAME? | AO22: =+IF(AK21<0,1-AO21/AK21,AO21/AK21-1) -> #NAME? | AP22: =+IF(AL21<0,1-AP21/AL21,AP21/AL21-1) -> #NAME? | AQ22: =+IF(AM21<0,1-AQ21/AM21,AQ21/AM21-1) -> #NAME? | AR22: =+IF(AN21<0,1-AR21/AN21,AR21/AN21-1) -> #NAME? | AS22: =+IF(AO21<0,1-AS21/AO21,AS21/AO21-1) -> #NAME? | AT22: =+IF(AP21<0,1-AT21/AP21,AT21/AP21-1) -> #NAME? | ... CF22: =+IF(CB21<0,1-CF21/CB21,CF21/CB21-1) -> #NAME? | CG22: 0.18031675 | CH22: =+IF(CD21<0,1-CH21/CD21,CH21/CD21-1) -> #NAME? | CI22: =+IF(CE21<0,1-CI21/CE21,CI21/CE21-1) -> #NAME? | CJ22: =+IF(CF21<0,1-CJ21/CF21,CJ21/CF21-1) -> #NAME? | CK22: =+IF(CG21<0,1-CK21/CG21,CK21/CG21-1) -> #NAME? | CL22: =+IF(CH21<0,1-CL21/CH21,CL21/CH21-1) -> #NAME? | CM22: =+IF(CI21<0,1-CM21/CI21,CM21/CI21-1) -> #NAME? | CN22: =+IF(CJ21<0,1-CN21/CJ21,CN21/CJ21-1) -> #NAME? | CO22: =+IF(CK21<0,1-CO21/CK21,CO21/CK21-1) -> #NAME? | ... DB22: =+IF(CX21<0,1-DB21/CX21,DB21/CX21-1) -> 0.35882658 | DF22: 0.40832762
A23: Net Revenue QOQ% | AJ23: =+IF(AI21<0,1-AJ21/AI21,AJ21/AI21-1) -> #NAME? | AK23: =+IF(AJ21<0,1-AK21/AJ21,AK21/AJ21-1) -> #NAME? | AL23: =+IF(AK21<0,1-AL21/AK21,AL21/AK21-1) -> #NAME? | AM23: =+IF(AL21<0,1-AM21/AL21,AM21/AL21-1) -> #NAME? | AN23: =+IF(AM21<0,1-AN21/AM21,AN21/AM21-1) -> #NAME? | AO23: =+IF(AN21<0,1-AO21/AN21,AO21/AN21-1) -> #NAME? | AP23: =+IF(AO21<0,1-AP21/AO21,AP21/AO21-1) -> #NAME? | AQ23: =+IF(AP21<0,1-AQ21/AP21,AQ21/AP21-1) -> #NAME? | ... CF23: =+IF(CE21<0,1-CF21/CE21,CF21/CE21-1) -> #NAME? | CG23: -0.043379846 | CH23: =+IF(CG21<0,1-CH21/CG21,CH21/CG21-1) -> #NAME? | CI23: =+IF(CH21<0,1-CI21/CH21,CI21/CH21-1) -> #NAME? | CJ23: =+IF(CI21<0,1-CJ21/CI21,CJ21/CI21-1) -> #NAME? | CK23: =+IF(CJ21<0,1-CK21/CJ21,CK21/CJ21-1) -> #NAME? | CL23: =+IF(CK21<0,1-CL21/CK21,CL21/CK21-1) -> #NAME? | CM23: =+IF(CL21<0,1-CM21/CL21,CM21/CL21-1) -> #NAME? | CN23: =+IF(CM21<0,1-CN21/CM21,CN21/CM21-1) -> 0.21093248 | CO23: =+IF(CN21<0,1-CO21/CN21,CO21/CN21-1) -> 0.10727562 | ... DB23: =+IF(DA21<0,1-DB21/DA21,DB21/DA21-1) -> 0.40668927
A24: Increase/Decrease in Stock | B24: ='Annual Raw'!C11 -> #NAME? | C24: ='Annual Raw'!D11 -> #NAME? | D24: ='Annual Raw'!E11 -> #NAME? | E24: ='Annual Raw'!F11 -> #NAME? | F24: ='Annual Raw'!G11 -> #NAME? | G24: ='Annual Raw'!H11 -> #NAME? | H24: ='Annual Raw'!I11 -> #NAME? | I24: ='Annual Raw'!J11 -> #NAME? | ... AA24: ='Annual Raw'!AB11 -> #NAME? | AB24: =+SUM(CM24:CP24) -> 0 | AC24: =+SUM(CQ24:CT24) -> 0 | AD24: =+SUM(CU24:CX24) -> 0 | AE24: =+SUM(CY24:DB24) -> 0 | AI24: ='QTR Raw'!C10 -> #NAME? | AJ24: ='QTR Raw'!D10 -> #NAME? | AK24: ='QTR Raw'!E10 -> #NAME? | AL24: ='QTR Raw'!F10 -> #NAME? | AM24: ='QTR Raw'!G10 -> #NAME? | AN24: ='QTR Raw'!H10 -> #NAME? | AO24: ='QTR Raw'!I10 -> #NAME? | AP24: ='QTR Raw'!J10 -> #NAME? | ... CF24: ='QTR Raw'!AZ10 -> #NAME? | CG24: -0.261 | CH24: ='QTR Raw'!BB10 -> #NAME? | CI24: ='QTR Raw'!BC10 -> #NAME? | CJ24: ='QTR Raw'!BD10 -> #NAME? | CK24: ='QTR Raw'!BE10 -> #NAME? | CL24: ='QTR Raw'!BF10 -> #NAME? | DF24: -31.692
A25: Purchase of Finished Goods | B25: 0 | C25: 0 | D25: 0 | E25: 0 | F25: 0 | G25: 0 | H25: 0 | I25: 0 | J25: 0 | K25: 0 | L25: 0 | M25: 0 | N25: 0 | O25: 0 | P25: 0 | Q25: 0 | R25: 0 | S25: 0 | T25: 0 | U25: 0 | V25: 0 | W25: 0 | X25: 0 | Y25: 0 | Z25: 0 | AA25: 0 | AB25: =+SUM(CM25:CP25) -> 0 | AC25: =+SUM(CQ25:CT25) -> 0 | AD25: =+SUM(CU25:CX25) -> 0 | AE25: =+SUM(CY25:DB25) -> 0 | AI25: ='QTR Raw'!C12 -> #NAME? | AJ25: ='QTR Raw'!D12 -> #NAME? | AK25: ='QTR Raw'!E12 -> #NAME? | AL25: ='QTR Raw'!F12 -> #NAME? | AM25: ='QTR Raw'!G12 -> #NAME? | AN25: ='QTR Raw'!H12 -> #NAME? | AO25: ='QTR Raw'!I12 -> #NAME? | AP25: ='QTR Raw'!J12 -> #NAME? | ... CF25: ='QTR Raw'!AZ12 -> #NAME? | CG25: 0 | CH25: ='QTR Raw'!BB12 -> #NAME? | CI25: ='QTR Raw'!BC12 -> #NAME? | CJ25: ='QTR Raw'!BD12 -> #NAME? | CK25: ='QTR Raw'!BE12 -> #NAME? | CL25: ='QTR Raw'!BF12 -> #NAME? | DF25: 0
A26: Raw Material Consumed | B26: ='Annual Raw'!C12 -> #NAME? | C26: ='Annual Raw'!D12 -> #NAME? | D26: ='Annual Raw'!E12 -> #NAME? | E26: ='Annual Raw'!F12 -> #NAME? | F26: ='Annual Raw'!G12 -> #NAME? | G26: ='Annual Raw'!H12 -> #NAME? | H26: ='Annual Raw'!I12 -> #NAME? | I26: ='Annual Raw'!J12 -> #NAME? | ... AA26: ='Annual Raw'!AB12 -> #NAME? | AB26: =+SUM(CM26:CP26) -> #NAME? | AC26: =+SUM(CQ26:CT26) -> #NAME? | AD26: =+SUM(CU26:CX26) -> #NAME? | AE26: =+SUM(CY26:DB26) -> #NAME? | AI26: ='QTR Raw'!C11 -> #NAME? | AJ26: ='QTR Raw'!D11 -> #NAME? | AK26: ='QTR Raw'!E11 -> #NAME? | AL26: ='QTR Raw'!F11 -> #NAME? | AM26: ='QTR Raw'!G11 -> #NAME? | AN26: ='QTR Raw'!H11 -> #NAME? | AO26: ='QTR Raw'!I11 -> #NAME? | AP26: ='QTR Raw'!J11 -> #NAME? | ... CF26: ='QTR Raw'!AZ11 -> #NAME? | CG26: 73.179 | CH26: ='QTR Raw'!BB11 -> #NAME? | CI26: ='QTR Raw'!BC11 -> #NAME? | CJ26: ='QTR Raw'!BD11 -> #NAME? | CK26: ='QTR Raw'!BE11 -> #NAME? | CL26: ='QTR Raw'!BF11 -> #NAME? | CM26: =+CM21-CM27 -> #NAME? | CN26: =+CN21-CN27 -> #NAME? | CO26: =+CO21-CO27 -> #NAME? | CP26: =+CP21-CP27 -> #NAME? | CQ26: =+CQ21-CQ27 -> #NAME? | CR26: =+CR21-CR27 -> #NAME? | CS26: =+CS21-CS27 -> #NAME? | CT26: =+CT21-CT27 -> #NAME? | ... DB26: =+DB21-DB27 -> #NAME? | DF26: 485.838
A27: Gross Profit | B27: =B21-B24-B26-B25 -> #NAME? | C27: =C21-C24-C26-C25 -> #NAME? | D27: =D21-D24-D26-D25 -> #NAME? | E27: =E21-E24-E26-E25 -> #NAME? | F27: =F21-F24-F26-F25 -> #NAME? | G27: =G21-G24-G26-G25 -> #NAME? | H27: =H21-H24-H26-H25 -> #NAME? | I27: =I21-I24-I26-I25 -> #NAME? | ... AE27: =AE21-AE24-AE26-AE25 -> #NAME? | AI27: =AI21-AI24-AI26-AI25 -> #NAME? | AJ27: =AJ21-AJ24-AJ26-AJ25 -> #NAME? | AK27: =AK21-AK24-AK26-AK25 -> #NAME? | AL27: =AL21-AL24-AL26-AL25 -> #NAME? | AM27: =AM21-AM24-AM26-AM25 -> #NAME? | AN27: =AN21-AN24-AN26-AN25 -> #NAME? | AO27: =AO21-AO24-AO26-AO25 -> #NAME? | AP27: =AP21-AP24-AP26-AP25 -> #NAME? | ... CF27: =CF21-CF24-CF26-CF25 -> #NAME? | CG27: 29.779 | CH27: =CH21-CH24-CH26-CH25 -> #NAME? | CI27: =CI21-CI24-CI26-CI25 -> #NAME? | CJ27: =CJ21-CJ24-CJ26-CJ25 -> #NAME? | CK27: =CK21-CK24-CK26-CK25 -> #NAME? | CL27: =CL21-CL24-CL26-CL25 -> #NAME? | CM27: =+CM28*CM21 -> #NAME? | CN27: =+CN28*CN21 -> #NAME? | CO27: =+CO28*CO21 -> #NAME? | CP27: =+CP28*CP21 -> #NAME? | CQ27: =+CQ28*CQ21 -> #NAME? | CR27: =+CR28*CR21 -> #NAME? | CS27: =+CS28*CS21 -> #NAME? | CT27: =+CT28*CT21 -> #NAME? | ... DB27: =+DB28*DB21 -> #NAME? | DF27: 184.978
A28: GP% | B28: =B27/B21 -> #NAME? | C28: =C27/C21 -> #NAME? | D28: =D27/D21 -> #NAME? | E28: =E27/E21 -> #NAME? | F28: =F27/F21 -> #NAME? | G28: =G27/G21 -> #NAME? | H28: =H27/H21 -> #NAME? | I28: =I27/I21 -> #NAME? | ... AE28: =AE27/AE21 -> #NAME? | AI28: =AI27/AI21 -> #NAME? | AJ28: =AJ27/AJ21 -> #NAME? | AK28: =AK27/AK21 -> #NAME? | AL28: =AL27/AL21 -> #NAME? | AM28: =AM27/AM21 -> #NAME? | AN28: =AN27/AN21 -> #NAME? | AO28: =AO27/AO21 -> #NAME? | AP28: =AP27/AP21 -> #NAME? | ... CF28: =CF27/CF21 -> #NAME? | CG28: 0.28996952 | CH28: =CH27/CH21 -> #NAME? | CI28: =CI27/CI21 -> #NAME? | CJ28: =CJ27/CJ21 -> #NAME? | CK28: =CK27/CK21 -> #NAME? | CL28: =CL27/CL21 -> #NAME? | CM28: =AVERAGE(CI28:CL28)*0.98 -> #NAME? | CN28: =AVERAGE(CJ28:CM28)*0.98 -> #NAME? | CO28: =AVERAGE(CK28:CN28) -> #NAME? | CP28: =AVERAGE(CL28:CO28) -> #NAME? | CQ28: =AVERAGE(CM28:CP28) -> #NAME? | CR28: =AVERAGE(CN28:CQ28) -> #NAME? | CS28: =AVERAGE(CO28:CR28) -> #NAME? | CT28: =AVERAGE(CP28:CS28) -> #NAME? | CU28: =AVERAGE(CQ28:CT28) -> #NAME? | CV28: =AVERAGE(CR28:CU28) -> #NAME? | ... DB28: =AVERAGE(CX28:DA28) -> #NAME? | DF28: 0.28942427
A29: GP YOY% | C29: =+IF(B27<0,1-C27/B27,C27/B27-1) -> #NAME? | D29: =+IF(C27<0,1-D27/C27,D27/C27-1) -> #NAME? | E29: =+IF(D27<0,1-E27/D27,E27/D27-1) -> #NAME? | F29: =+IF(E27<0,1-F27/E27,F27/E27-1) -> #NAME? | G29: =+IF(F27<0,1-G27/F27,G27/F27-1) -> #NAME? | H29: =+IF(G27<0,1-H27/G27,H27/G27-1) -> #NAME? | I29: =+IF(H27<0,1-I27/H27,I27/H27-1) -> #NAME? | J29: =+IF(I27<0,1-J27/I27,J27/I27-1) -> #NAME? | ... AE29: =+IF(AD27<0,1-AE27/AD27,AE27/AD27-1) -> #NAME? | AM29: =+IF(AI27<0,1-AM27/AI27,AM27/AI27-1) -> #NAME? | AN29: =+IF(AJ27<0,1-AN27/AJ27,AN27/AJ27-1) -> #NAME? | AO29: =+IF(AK27<0,1-AO27/AK27,AO27/AK27-1) -> #NAME? | AP29: =+IF(AL27<0,1-AP27/AL27,AP27/AL27-1) -> #NAME? | AQ29: =+IF(AM27<0,1-AQ27/AM27,AQ27/AM27-1) -> #NAME? | AR29: =+IF(AN27<0,1-AR27/AN27,AR27/AN27-1) -> #NAME? | AS29: =+IF(AO27<0,1-AS27/AO27,AS27/AO27-1) -> #NAME? | AT29: =+IF(AP27<0,1-AT27/AP27,AT27/AP27-1) -> #NAME? | ... CF29: =+IF(CB27<0,1-CF27/CB27,CF27/CB27-1) -> #NAME? | CG29: 0.26649088 | CH29: =+IF(CD27<0,1-CH27/CD27,CH27/CD27-1) -> #NAME? | CI29: =+IF(CE27<0,1-CI27/CE27,CI27/CE27-1) -> #NAME? | CJ29: =+IF(CF27<0,1-CJ27/CF27,CJ27/CF27-1) -> #NAME? | CK29: =+IF(CG27<0,1-CK27/CG27,CK27/CG27-1) -> #NAME? | CL29: =+IF(CH27<0,1-CL27/CH27,CL27/CH27-1) -> #NAME? | CM29: =+CM27/CI27-1 -> #NAME? | CN29: =+CN27/CJ27-1 -> #NAME? | CO29: =+CO27/CK27-1 -> #NAME? | CP29: =+CP27/CL27-1 -> #NAME? | CQ29: =+CQ27/CM27-1 -> #NAME? | CR29: =+CR27/CN27-1 -> #NAME? | CS29: =+CS27/CO27-1 -> #NAME? | CT29: =+CT27/CP27-1 -> #NAME? | ... DB29: =+DB27/CX27-1 -> #NAME? | DF29: 0.49434424
A30: GP QOQ% | AJ30: =+IF(AI27<0,1-AJ27/AI27,AJ27/AI27-1) -> #NAME? | AK30: =+IF(AJ27<0,1-AK27/AJ27,AK27/AJ27-1) -> #NAME? | AL30: =+IF(AK27<0,1-AL27/AK27,AL27/AK27-1) -> #NAME? | AM30: =+IF(AL27<0,1-AM27/AL27,AM27/AL27-1) -> #NAME? | AN30: =+IF(AM27<0,1-AN27/AM27,AN27/AM27-1) -> #NAME? | AO30: =+IF(AN27<0,1-AO27/AN27,AO27/AN27-1) -> #NAME? | AP30: =+IF(AO27<0,1-AP27/AO27,AP27/AO27-1) -> #NAME? | AQ30: =+IF(AP27<0,1-AQ27/AP27,AQ27/AP27-1) -> #NAME? | ... CF30: =+IF(CE27<0,1-CF27/CE27,CF27/CE27-1) -> #NAME? | CG30: -0.056820701 | CH30: =+IF(CG27<0,1-CH27/CG27,CH27/CG27-1) -> #NAME? | CI30: =+IF(CH27<0,1-CI27/CH27,CI27/CH27-1) -> #NAME? | CJ30: =+IF(CI27<0,1-CJ27/CI27,CJ27/CI27-1) -> #NAME? | CK30: =+IF(CJ27<0,1-CK27/CJ27,CK27/CJ27-1) -> #NAME? | CL30: =+IF(CK27<0,1-CL27/CK27,CL27/CK27-1) -> #NAME? | CM30: =+CM27/CL27-1 -> #NAME? | CN30: =+CN27/CM27-1 -> #NAME? | CO30: =+CO27/CN27-1 -> #NAME? | CP30: =+CP27/CO27-1 -> #NAME? | CQ30: =+CQ27/CP27-1 -> #NAME? | CR30: =+CR27/CQ27-1 -> #NAME? | CS30: =+CS27/CR27-1 -> #NAME? | CT30: =+CT27/CS27-1 -> #NAME? | ... DB30: =+DB27/DA27-1 -> #NAME?
A31: Employee Cost | B31: ='Annual Raw'!C14 -> #NAME? | C31: ='Annual Raw'!D14 -> #NAME? | D31: ='Annual Raw'!E14 -> #NAME? | E31: ='Annual Raw'!F14 -> #NAME? | F31: ='Annual Raw'!G14 -> #NAME? | G31: ='Annual Raw'!H14 -> #NAME? | H31: ='Annual Raw'!I14 -> #NAME? | I31: ='Annual Raw'!J14 -> #NAME? | ... AA31: ='Annual Raw'!AB14 -> #NAME? | AB31: =+SUM(CM31:CP31) -> #NAME? | AC31: =+SUM(CQ31:CT31) -> #NAME? | AD31: =+SUM(CU31:CX31) -> #NAME? | AE31: =+SUM(CY31:DB31) -> #NAME? | AI31: ='QTR Raw'!C16 -> #NAME? | AJ31: ='QTR Raw'!D16 -> #NAME? | AK31: ='QTR Raw'!E16 -> #NAME? | AL31: ='QTR Raw'!F16 -> #NAME? | AM31: ='QTR Raw'!G16 -> #NAME? | AN31: ='QTR Raw'!H16 -> #NAME? | AO31: ='QTR Raw'!I16 -> #NAME? | AP31: ='QTR Raw'!J16 -> #NAME? | ... CF31: ='QTR Raw'!AZ16 -> #NAME? | CG31: 5.849 | CH31: ='QTR Raw'!BB16 -> #NAME? | CI31: ='QTR Raw'!BC16 -> #NAME? | CJ31: ='QTR Raw'!BD16 -> #NAME? | CK31: ='QTR Raw'!BE16 -> #NAME? | CL31: ='QTR Raw'!BF16 -> #NAME? | CM31: =CI31*107% -> #NAME? | CN31: =CJ31*107% -> #NAME? | CO31: =CK31*107% -> #NAME? | CP31: =CL31*107% -> #NAME? | CQ31: =CM31*107% -> #NAME? | CR31: =CN31*107% -> #NAME? | CS31: =CO31*107% -> #NAME? | CT31: =CP31*107% -> #NAME? | ... DB31: =CX31*107% -> #NAME? | DF31: 32.944
A32: General and Administration Expenses | B32: ='Annual Raw'!C17 -> #NAME? | C32: ='Annual Raw'!D17 -> #NAME? | D32: ='Annual Raw'!E17 -> #NAME? | E32: ='Annual Raw'!F17 -> #NAME? | F32: ='Annual Raw'!G17 -> #NAME? | G32: ='Annual Raw'!H17 -> #NAME? | H32: ='Annual Raw'!I17 -> #NAME? | I32: ='Annual Raw'!J17 -> #NAME? | ... AA32: ='Annual Raw'!AB17 -> #NAME? | AB32: =+SUM(CM32:CP32) -> 0 | AC32: =+SUM(CQ32:CT32) -> 0 | AD32: =+SUM(CU32:CX32) -> 0 | AE32: =+SUM(CY32:DB32) -> 0 | AI32: ='QTR Raw'!C17 -> #NAME? | AJ32: ='QTR Raw'!D17 -> #NAME? | AK32: ='QTR Raw'!E17 -> #NAME? | AL32: ='QTR Raw'!F17 -> #NAME? | AM32: ='QTR Raw'!G17 -> #NAME? | AN32: ='QTR Raw'!H17 -> #NAME? | AO32: ='QTR Raw'!I17 -> #NAME? | AP32: ='QTR Raw'!J17 -> #NAME? | ... CF32: ='QTR Raw'!AZ17 -> #NAME? | CG32: 0 | CH32: ='QTR Raw'!BB17 -> #NAME? | CI32: ='QTR Raw'!BC17 -> #NAME? | CJ32: ='QTR Raw'!BD17 -> #NAME? | CK32: ='QTR Raw'!BE17 -> #NAME? | CL32: ='QTR Raw'!BF17 -> #NAME? | DF32: 0
A33: Miscellaneous Expenses | B33: ='Annual Raw'!C19-'Annual Raw'!C20 -> #NAME? | C33: ='Annual Raw'!D19-'Annual Raw'!D20 -> #NAME? | D33: ='Annual Raw'!E19-'Annual Raw'!E20 -> #NAME? | E33: ='Annual Raw'!F19-'Annual Raw'!F20 -> #NAME? | F33: ='Annual Raw'!G19-'Annual Raw'!G20 -> #NAME? | G33: ='Annual Raw'!H19-'Annual Raw'!H20 -> #NAME? | H33: ='Annual Raw'!I19-'Annual Raw'!I20 -> #NAME? | I33: ='Annual Raw'!J19-'Annual Raw'!J20 -> #NAME? | ... AA33: ='Annual Raw'!AB19-'Annual Raw'!AB20 -> #NAME? | AB33: =+SUM(CM33:CP33) -> 0 | AC33: =+SUM(CQ33:CT33) -> 0 | AD33: =+SUM(CU33:CX33) -> 0 | AE33: =+SUM(CY33:DB33) -> 0 | AI33: =+'QTR Raw'!C21 -> #NAME? | AJ33: =+'QTR Raw'!D21 -> #NAME? | AK33: =+'QTR Raw'!E21 -> #NAME? | AL33: =+'QTR Raw'!F21 -> #NAME? | AM33: =+'QTR Raw'!G21 -> #NAME? | AN33: =+'QTR Raw'!H21 -> #NAME? | AO33: =+'QTR Raw'!I21 -> #NAME? | AP33: =+'QTR Raw'!J21 -> #NAME? | ... CF33: =+'QTR Raw'!AZ21 -> #NAME? | CG33: 0 | CH33: =+'QTR Raw'!BB21 -> #NAME? | CI33: =+'QTR Raw'!BC21 -> #NAME? | CJ33: =+'QTR Raw'!BD21 -> #NAME? | CK33: =+'QTR Raw'!BE21 -> #NAME? | CL33: =+'QTR Raw'!BF21 -> #NAME? | DF33: 0
A34: Other Manufacturing Expenses | B34: ='Annual Raw'!C15+'Annual Raw'!C16 -> #NAME? | C34: ='Annual Raw'!D15+'Annual Raw'!D16 -> #NAME? | D34: ='Annual Raw'!E15+'Annual Raw'!E16 -> #NAME? | E34: ='Annual Raw'!F15+'Annual Raw'!F16 -> #NAME? | F34: ='Annual Raw'!G15+'Annual Raw'!G16 -> #NAME? | G34: ='Annual Raw'!H15+'Annual Raw'!H16 -> #NAME? | H34: ='Annual Raw'!I15+'Annual Raw'!I16 -> #NAME? | I34: ='Annual Raw'!J15+'Annual Raw'!J16 -> #NAME? | ... AA34: ='Annual Raw'!AB15+'Annual Raw'!AB16 -> #NAME? | AB34: =+SUM(CM34:CP34) -> #NAME? | AC34: =+SUM(CQ34:CT34) -> #NAME? | AD34: =+SUM(CU34:CX34) -> #NAME? | AE34: =+SUM(CY34:DB34) -> #NAME? | AI34: ='QTR Raw'!C14 -> #NAME? | AJ34: ='QTR Raw'!D14 -> #NAME? | AK34: ='QTR Raw'!E14 -> #NAME? | AL34: ='QTR Raw'!F14 -> #NAME? | AM34: ='QTR Raw'!G14 -> #NAME? | AN34: ='QTR Raw'!H14 -> #NAME? | AO34: ='QTR Raw'!I14 -> #NAME? | AP34: ='QTR Raw'!J14 -> #NAME? | ... CF34: ='QTR Raw'!AZ14 -> #NAME? | CG34: 10.701 | CH34: ='QTR Raw'!BB14 -> #NAME? | CI34: ='QTR Raw'!BC14 -> #NAME? | CJ34: ='QTR Raw'!BD14 -> #NAME? | CK34: ='QTR Raw'!BE14 -> #NAME? | CL34: ='QTR Raw'!BF14 -> #NAME? | CM34: =CM37-CM31-CM32-CM33-CM35-CM36 -> #NAME? | CN34: =CN37-CN31-CN32-CN33-CN35-CN36 -> #NAME? | CO34: =CO37-CO31-CO32-CO33-CO35-CO36 -> #NAME? | CP34: =CP37-CP31-CP32-CP33-CP35-CP36 -> #NAME? | CQ34: =CQ37-CQ31-CQ32-CQ33-CQ35-CQ36 -> #NAME? | CR34: =CR37-CR31-CR32-CR33-CR35-CR36 -> #NAME? | CS34: =CS37-CS31-CS32-CS33-CS35-CS36 -> #NAME? | CT34: =CT37-CT31-CT32-CT33-CT35-CT36 -> #NAME? | ... DB34: =DB37-DB31-DB32-DB33-DB35-DB36 -> #NAME? | DF34: 57.496
A35: Power & Fuel Cost | B35: ='Annual Raw'!C13 -> #NAME? | C35: ='Annual Raw'!D13 -> #NAME? | D35: ='Annual Raw'!E13 -> #NAME? | E35: ='Annual Raw'!F13 -> #NAME? | F35: ='Annual Raw'!G13 -> #NAME? | G35: ='Annual Raw'!H13 -> #NAME? | H35: ='Annual Raw'!I13 -> #NAME? | I35: ='Annual Raw'!J13 -> #NAME? | ... AA35: ='Annual Raw'!AB13 -> #NAME? | AB35: =+SUM(CM35:CP35) -> 0 | AC35: =+SUM(CQ35:CT35) -> 0 | AD35: =+SUM(CU35:CX35) -> 0 | AE35: =+SUM(CY35:DB35) -> 0 | AI35: ='QTR Raw'!C15 -> #NAME? | AJ35: ='QTR Raw'!D15 -> #NAME? | AK35: ='QTR Raw'!E15 -> #NAME? | AL35: ='QTR Raw'!F15 -> #NAME? | AM35: ='QTR Raw'!G15 -> #NAME? | AN35: ='QTR Raw'!H15 -> #NAME? | AO35: ='QTR Raw'!I15 -> #NAME? | AP35: ='QTR Raw'!J15 -> #NAME? | ... CF35: ='QTR Raw'!AZ15 -> #NAME? | CG35: 0 | CH35: ='QTR Raw'!BB15 -> #NAME? | CI35: ='QTR Raw'!BC15 -> #NAME? | CJ35: ='QTR Raw'!BD15 -> #NAME? | CK35: ='QTR Raw'!BE15 -> #NAME? | CL35: ='QTR Raw'!BF15 -> #NAME? | DF35: 0
A36: Selling and Distribution Expenses | B36: ='Annual Raw'!C18 -> #NAME? | C36: ='Annual Raw'!D18 -> #NAME? | D36: ='Annual Raw'!E18 -> #NAME? | E36: ='Annual Raw'!F18 -> #NAME? | F36: ='Annual Raw'!G18 -> #NAME? | G36: ='Annual Raw'!H18 -> #NAME? | H36: ='Annual Raw'!I18 -> #NAME? | I36: ='Annual Raw'!J18 -> #NAME? | ... AA36: ='Annual Raw'!AB18 -> #NAME? | AB36: =+SUM(CM36:CP36) -> 0 | AC36: =+SUM(CQ36:CT36) -> 0 | AD36: =+SUM(CU36:CX36) -> 0 | AE36: =+SUM(CY36:DB36) -> 0 | AI36: ='QTR Raw'!C18 -> #NAME? | AJ36: ='QTR Raw'!D18 -> #NAME? | AK36: ='QTR Raw'!E18 -> #NAME? | AL36: ='QTR Raw'!F18 -> #NAME? | AM36: ='QTR Raw'!G18 -> #NAME? | AN36: ='QTR Raw'!H18 -> #NAME? | AO36: ='QTR Raw'!I18 -> #NAME? | AP36: ='QTR Raw'!J18 -> #NAME? | ... CF36: ='QTR Raw'!AZ18 -> #NAME? | CG36: 0 | CH36: ='QTR Raw'!BB18 -> #NAME? | CI36: ='QTR Raw'!BC18 -> #NAME? | CJ36: ='QTR Raw'!BD18 -> #NAME? | CK36: ='QTR Raw'!BE18 -> #NAME? | CL36: ='QTR Raw'!BF18 -> #NAME? | DF36: 0
A37: Total Cost | B37: =+SUM(B31:B36) -> #NAME? | C37: =+SUM(C31:C36) -> #NAME? | D37: =+SUM(D31:D36) -> #NAME? | E37: =+SUM(E31:E36) -> #NAME? | F37: =+SUM(F31:F36) -> #NAME? | G37: =+SUM(G31:G36) -> #NAME? | H37: =+SUM(H31:H36) -> #NAME? | I37: =+SUM(I31:I36) -> #NAME? | ... AE37: =+SUM(AE31:AE36) -> #NAME? | AI37: =+SUM(AI31:AI36) -> #NAME? | AJ37: =+SUM(AJ31:AJ36) -> #NAME? | AK37: =+SUM(AK31:AK36) -> #NAME? | AL37: =+SUM(AL31:AL36) -> #NAME? | AM37: =+SUM(AM31:AM36) -> #NAME? | AN37: =+SUM(AN31:AN36) -> #NAME? | AO37: =+SUM(AO31:AO36) -> #NAME? | AP37: =+SUM(AP31:AP36) -> #NAME? | ... CF37: =+SUM(CF31:CF36) -> #NAME? | CG37: 16.55 | CH37: =+SUM(CH31:CH36) -> #NAME? | CI37: =+SUM(CI31:CI36) -> #NAME? | CJ37: =+SUM(CJ31:CJ36) -> #NAME? | CK37: =+SUM(CK31:CK36) -> #NAME? | CL37: =+SUM(CL31:CL36) -> #NAME? | CM37: =CM38*CM21 -> #NAME? | CN37: =CN38*CN21 -> #NAME? | CO37: =CO38*CO21 -> #NAME? | CP37: =CP38*CP21 -> #NAME? | CQ37: =CQ38*CQ21 -> #NAME? | CR37: =CR38*CR21 -> #NAME? | CS37: =CS38*CS21 -> #NAME? | CT37: =CT38*CT21 -> #NAME? | ... DB37: =DB38*DB21 -> #NAME? | DF37: 90.44
A38: Cost % | B38: =B37/B21 -> #NAME? | C38: =C37/C21 -> #NAME? | D38: =D37/D21 -> #NAME? | E38: =E37/E21 -> #NAME? | F38: =F37/F21 -> #NAME? | G38: =G37/G21 -> #NAME? | H38: =H37/H21 -> #NAME? | I38: =I37/I21 -> #NAME? | ... AE38: =AE37/AE21 -> #NAME? | AI38: =AI37/AI21 -> #NAME? | AJ38: =AJ37/AJ21 -> #NAME? | AK38: =AK37/AK21 -> #NAME? | AL38: =AL37/AL21 -> #NAME? | AM38: =AM37/AM21 -> #NAME? | AN38: =AN37/AN21 -> #NAME? | AO38: =AO37/AO21 -> #NAME? | AP38: =AP37/AP21 -> #NAME? | ... CF38: =CF37/CF21 -> #NAME? | CG38: 0.16115369 | CH38: =CH37/CH21 -> #NAME? | CI38: =CI37/CI21 -> #NAME? | CJ38: =CJ37/CJ21 -> #NAME? | CK38: =CK37/CK21 -> #NAME? | CL38: =CL37/CL21 -> #NAME? | CM38: =AVERAGE(CI38:CL38) -> #NAME? | CN38: =AVERAGE(CJ38:CM38) -> #NAME? | CO38: =AVERAGE(CK38:CN38) -> #NAME? | CP38: =AVERAGE(CL38:CO38) -> #NAME? | CQ38: =AVERAGE(CM38:CP38) -> #NAME? | CR38: =AVERAGE(CN38:CQ38) -> #NAME? | CS38: =AVERAGE(CO38:CR38) -> #NAME? | CT38: =AVERAGE(CP38:CS38) -> #NAME? | ... DB38: =AVERAGE(CX38:DA38) -> #NAME? | DF38: 0.14150619
A39: EBITDA | B39: =B27-B37 -> #NAME? | C39: =C27-C37 -> #NAME? | D39: =D27-D37 -> #NAME? | E39: =E27-E37 -> #NAME? | F39: =F27-F37 -> #NAME? | G39: =G27-G37 -> #NAME? | H39: =H27-H37 -> #NAME? | I39: =I27-I37 -> #NAME? | ... AE39: =AE27-AE37 -> #NAME? | AI39: =AI27-AI37 -> #NAME? | AJ39: =AJ27-AJ37 -> #NAME? | AK39: =AK27-AK37 -> #NAME? | AL39: =AL27-AL37 -> #NAME? | AM39: =AM27-AM37 -> #NAME? | AN39: =AN27-AN37 -> #NAME? | AO39: =AO27-AO37 -> #NAME? | AP39: =AP27-AP37 -> #NAME? | ... CF39: =CF27-CF37 -> #NAME? | CG39: 13.229 | CH39: =CH27-CH37 -> #NAME? | CI39: =CI27-CI37 -> #NAME? | CJ39: =CJ27-CJ37 -> #NAME? | CK39: =CK27-CK37 -> #NAME? | CL39: =CL27-CL37 -> #NAME? | CM39: =CM27-CM37 -> #NAME? | CN39: =CN27-CN37 -> #NAME? | CO39: =CO27-CO37 -> #NAME? | ... DB39: =DB27-DB37 -> #NAME? | DF39: 94.538
A40: EBITDA Margins | B40: =B39/B21 -> #NAME? | C40: =C39/C21 -> #NAME? | D40: =D39/D21 -> #NAME? | E40: =E39/E21 -> #NAME? | F40: =F39/F21 -> #NAME? | G40: =G39/G21 -> #NAME? | H40: =H39/H21 -> #NAME? | I40: =I39/I21 -> #NAME? | ... AE40: =AE39/AE21 -> #NAME? | AI40: =AI39/AI21 -> #NAME? | AJ40: =AJ39/AJ21 -> #NAME? | AK40: =AK39/AK21 -> #NAME? | AL40: =AL39/AL21 -> #NAME? | AM40: =AM39/AM21 -> #NAME? | AN40: =AN39/AN21 -> #NAME? | AO40: =AO39/AO21 -> #NAME? | AP40: =AP39/AP21 -> #NAME? | ... CF40: =CF39/CF21 -> #NAME? | CG40: 0.12881584 | CH40: =CH39/CH21 -> #NAME? | CI40: =CI39/CI21 -> #NAME? | CJ40: =CJ39/CJ21 -> #NAME? | CK40: =CK39/CK21 -> #NAME? | CL40: =CL39/CL21 -> #NAME? | CM40: =CM39/CM21 -> #NAME? | CN40: =CN39/CN21 -> #NAME? | CO40: =CO39/CO21 -> #NAME? | ... DB40: =DB39/DB21 -> #NAME? | DF40: 0.14791809
A41: EBITDA YOY% | C41: =+IF(B39<0,1-C39/B39,C39/B39-1) -> #NAME? | D41: =+IF(C39<0,1-D39/C39,D39/C39-1) -> #NAME? | E41: =+IF(D39<0,1-E39/D39,E39/D39-1) -> #NAME? | F41: =+IF(E39<0,1-F39/E39,F39/E39-1) -> #NAME? | G41: =+IF(F39<0,1-G39/F39,G39/F39-1) -> #NAME? | H41: =+IF(G39<0,1-H39/G39,H39/G39-1) -> #NAME? | I41: =+IF(H39<0,1-I39/H39,I39/H39-1) -> #NAME? | J41: =+IF(I39<0,1-J39/I39,J39/I39-1) -> #NAME? | ... AE41: =+IF(AD39<0,1-AE39/AD39,AE39/AD39-1) -> #NAME? | AM41: =+IF(AI39<0,1-AM39/AI39,AM39/AI39-1) -> #NAME? | AN41: =+IF(AJ39<0,1-AN39/AJ39,AN39/AJ39-1) -> #NAME? | AO41: =+IF(AK39<0,1-AO39/AK39,AO39/AK39-1) -> #NAME? | AP41: =+IF(AL39<0,1-AP39/AL39,AP39/AL39-1) -> #NAME? | AQ41: =+IF(AM39<0,1-AQ39/AM39,AQ39/AM39-1) -> #NAME? | AR41: =+IF(AN39<0,1-AR39/AN39,AR39/AN39-1) -> #NAME? | AS41: =+IF(AO39<0,1-AS39/AO39,AS39/AO39-1) -> #NAME? | AT41: =+IF(AP39<0,1-AT39/AP39,AT39/AP39-1) -> #NAME? | ... CF41: =+IF(CB39<0,1-CF39/CB39,CF39/CB39-1) -> #NAME? | CG41: 0.25810747 | CH41: =+IF(CD39<0,1-CH39/CD39,CH39/CD39-1) -> #NAME? | CI41: =+IF(CE39<0,1-CI39/CE39,CI39/CE39-1) -> #NAME? | CJ41: =+IF(CF39<0,1-CJ39/CF39,CJ39/CF39-1) -> #NAME? | CK41: =+IF(CG39<0,1-CK39/CG39,CK39/CG39-1) -> #NAME? | CL41: =+IF(CH39<0,1-CL39/CH39,CL39/CH39-1) -> #NAME? | CM41: =+CM39/CI39-1 -> #NAME? | CN41: =+CN39/CJ39-1 -> #NAME? | CO41: =+CO39/CK39-1 -> #NAME? | CP41: =+CP39/CL39-1 -> #NAME? | CQ41: =+CQ39/CM39-1 -> #NAME? | CR41: =+CR39/CN39-1 -> #NAME? | CS41: =+CS39/CO39-1 -> #NAME? | CT41: =+CT39/CP39-1 -> #NAME? | ... DB41: =+DB39/CX39-1 -> #NAME? | DF41: 0.80214149
A42: EBITDA QOQ% | AJ42: =+IF(AI39<0,1-AJ39/AI39,AJ39/AI39-1) -> #NAME? | AK42: =+IF(AJ39<0,1-AK39/AJ39,AK39/AJ39-1) -> #NAME? | AL42: =+IF(AK39<0,1-AL39/AK39,AL39/AK39-1) -> #NAME? | AM42: =+IF(AL39<0,1-AM39/AL39,AM39/AL39-1) -> #NAME? | AN42: =+IF(AM39<0,1-AN39/AM39,AN39/AM39-1) -> #NAME? | AO42: =+IF(AN39<0,1-AO39/AN39,AO39/AN39-1) -> #NAME? | AP42: =+IF(AO39<0,1-AP39/AO39,AP39/AO39-1) -> #NAME? | AQ42: =+IF(AP39<0,1-AQ39/AP39,AQ39/AP39-1) -> #NAME? | ... CF42: =+IF(CE39<0,1-CF39/CE39,CF39/CE39-1) -> #NAME? | CG42: -0.051820528 | CH42: =+IF(CG39<0,1-CH39/CG39,CH39/CG39-1) -> #NAME? | CI42: =+IF(CH39<0,1-CI39/CH39,CI39/CH39-1) -> #NAME? | CJ42: =+IF(CI39>1,CJ39/CI39-1,1-CJ39/CI39) -> #NAME? | CK42: =+IF(CJ39>1,CK39/CJ39-1,1-CK39/CJ39) -> #NAME? | CL42: =+IF(CK39>1,CL39/CK39-1,1-CL39/CK39) -> #NAME? | CM42: =+CM39/CL39-1 -> #NAME? | CN42: =+CN39/CM39-1 -> #NAME? | CO42: =+CO39/CN39-1 -> #NAME? | CP42: =+CP39/CO39-1 -> #NAME? | CQ42: =+CQ39/CP39-1 -> #NAME? | CR42: =+CR39/CQ39-1 -> #NAME? | CS42: =+CS39/CR39-1 -> #NAME? | CT42: =+CT39/CS39-1 -> #NAME? | ... DB42: =+DB39/DA39-1 -> #NAME?
A43: Depreciation | B43: ='Annual Raw'!C27 -> #NAME? | C43: ='Annual Raw'!D27 -> #NAME? | D43: ='Annual Raw'!E27 -> #NAME? | E43: ='Annual Raw'!F27 -> #NAME? | F43: ='Annual Raw'!G27 -> #NAME? | G43: ='Annual Raw'!H27 -> #NAME? | H43: ='Annual Raw'!I27 -> #NAME? | I43: ='Annual Raw'!J27 -> #NAME? | ... AA43: ='Annual Raw'!AB27 -> #NAME? | AB43: =+SUM(CM43:CP43) -> #NAME? | AC43: =+SUM(CQ43:CT43) -> #NAME? | AD43: =+SUM(CU43:CX43) -> #NAME? | AE43: =+SUM(CY43:DB43) -> #NAME? | AI43: ='QTR Raw'!C28 -> #NAME? | AJ43: ='QTR Raw'!D28 -> #NAME? | AK43: ='QTR Raw'!E28 -> #NAME? | AL43: ='QTR Raw'!F28 -> #NAME? | AM43: ='QTR Raw'!G28 -> #NAME? | AN43: ='QTR Raw'!H28 -> #NAME? | AO43: ='QTR Raw'!I28 -> #NAME? | AP43: ='QTR Raw'!J28 -> #NAME? | ... CF43: ='QTR Raw'!AZ28 -> #NAME? | CG43: 1.089 | CH43: ='QTR Raw'!BB28 -> #NAME? | CI43: ='QTR Raw'!BC28 -> #NAME? | CJ43: ='QTR Raw'!BD28 -> #NAME? | CK43: ='QTR Raw'!BE28 -> #NAME? | CL43: ='QTR Raw'!BF28 -> #NAME? | CM43: =CM44*CL145 -> #NAME? | CN43: =CN44*CM145 -> #NAME? | CO43: =CO44*CN145 -> #NAME? | CP43: =CP44*CO145 -> #NAME? | CQ43: =CQ44*CP145 -> #NAME? | CR43: =CR44*CQ145 -> #NAME? | CS43: =CS44*CR145 -> #NAME? | CT43: =CT44*CS145 -> #NAME? | ... DB43: =DB44*DA145 -> #NAME? | DF43: 8.247
A44: Depreciation % of Net Block | B44: =+B43/B145 -> #NAME? | C44: =+C43/C145 -> #NAME? | D44: =+D43/D145 -> #NAME? | E44: =+E43/E145 -> #NAME? | F44: =+F43/F145 -> #NAME? | G44: =+G43/G145 -> #NAME? | H44: =+H43/H145 -> #NAME? | I44: =+I43/I145 -> #NAME? | ... AE44: =+AE43/AE145 -> #NAME? | AI44: =+AI43/AH145 -> #NAME? | AJ44: =+AJ43/AI145 -> #NAME? | AK44: =+AK43/AJ145 -> #NAME? | AL44: =+AL43/AK145 -> #NAME? | AM44: =+AM43/AL145 -> #NAME? | AN44: =+AN43/AM145 -> #NAME? | AO44: =+AO43/AN145 -> #NAME? | AP44: =+AP43/AO145 -> #NAME? | ... CF44: =+CF43/CE145 -> #NAME? | CG44: 0.02263845 | CH44: =+CH43/CG145 -> #NAME? | CI44: =+CI43/CH145 -> #NAME? | CJ44: =+CJ43/CI145 -> #NAME? | CK44: =+CK43/CJ145 -> #NAME? | CL44: =+CL43/CK145 -> #NAME? | CM44: 0.03 | CN44: =CM44 -> 0.03 | CO44: =CN44 -> 0.03 | CP44: =CO44 -> 0.03 | CQ44: =CP44 -> 0.03 | CR44: =CQ44 -> 0.03 | CS44: =CR44 -> 0.03 | CT44: =CS44 -> 0.03 | CU44: =CT44 -> 0.03 | ... DB44: =DA44 -> 0.03 | DF44: 0.069735585
A45: EBIT | B45: =B39-B43 -> #NAME? | C45: =C39-C43 -> #NAME? | D45: =D39-D43 -> #NAME? | E45: =E39-E43 -> #NAME? | F45: =F39-F43 -> #NAME? | G45: =G39-G43 -> #NAME? | H45: =H39-H43 -> #NAME? | I45: =I39-I43 -> #NAME? | ... AE45: =AE39-AE43 -> #NAME? | AI45: =AI39-AI43 -> #NAME? | AJ45: =AJ39-AJ43 -> #NAME? | AK45: =AK39-AK43 -> #NAME? | AL45: =AL39-AL43 -> #NAME? | AM45: =AM39-AM43 -> #NAME? | AN45: =AN39-AN43 -> #NAME? | AO45: =AO39-AO43 -> #NAME? | AP45: =AP39-AP43 -> #NAME? | ... CF45: =CF39-CF43 -> #NAME? | CG45: 12.14 | CH45: =CH39-CH43 -> #NAME? | CI45: =CI39-CI43 -> #NAME? | CJ45: =CJ39-CJ43 -> #NAME? | CK45: =CK39-CK43 -> #NAME? | CL45: =CL39-CL43 -> #NAME? | CM45: =CM39-CM43 -> #NAME? | CN45: =CN39-CN43 -> #NAME? | CO45: =CO39-CO43 -> #NAME? | ... DB45: =DB39-DB43 -> #NAME? | DF45: 86.291
A46: Other Income | B46: ='Annual Raw'!C23 -> #NAME? | C46: ='Annual Raw'!D23 -> #NAME? | D46: ='Annual Raw'!E23 -> #NAME? | E46: ='Annual Raw'!F23 -> #NAME? | F46: ='Annual Raw'!G23 -> #NAME? | G46: ='Annual Raw'!H23 -> #NAME? | H46: ='Annual Raw'!I23 -> #NAME? | I46: ='Annual Raw'!J23 -> #NAME? | ... AA46: ='Annual Raw'!AB23 -> #NAME? | AB46: =+SUM(CM46:CP46) -> 0 | AC46: =+SUM(CQ46:CT46) -> 0 | AD46: =+SUM(CU46:CX46) -> 0 | AE46: =+SUM(CY46:DB46) -> 0 | AI46: ='QTR Raw'!C23 -> #NAME? | AJ46: ='QTR Raw'!D23 -> #NAME? | AK46: ='QTR Raw'!E23 -> #NAME? | AL46: ='QTR Raw'!F23 -> #NAME? | AM46: ='QTR Raw'!G23 -> #NAME? | AN46: ='QTR Raw'!H23 -> #NAME? | AO46: ='QTR Raw'!I23 -> #NAME? | AP46: ='QTR Raw'!J23 -> #NAME? | ... CF46: ='QTR Raw'!AZ23 -> #NAME? | CG46: 0 | CH46: ='QTR Raw'!BB23 -> #NAME? | CI46: ='QTR Raw'!BC23 -> #NAME? | CJ46: ='QTR Raw'!BD23 -> #NAME? | CK46: ='QTR Raw'!BE23 -> #NAME? | CL46: ='QTR Raw'!BF23 -> #NAME? | DF46: 0
A47: Interest | B47: ='Annual Raw'!C25 -> #NAME? | C47: ='Annual Raw'!D25 -> #NAME? | D47: ='Annual Raw'!E25 -> #NAME? | E47: ='Annual Raw'!F25 -> #NAME? | F47: ='Annual Raw'!G25 -> #NAME? | G47: ='Annual Raw'!H25 -> #NAME? | H47: ='Annual Raw'!I25 -> #NAME? | I47: ='Annual Raw'!J25 -> #NAME? | ... AA47: ='Annual Raw'!AB25 -> #NAME? | AB47: =+SUM(CM47:CP47) -> #NAME? | AC47: =+SUM(CQ47:CT47) -> #NAME? | AD47: =+SUM(CU47:CX47) -> #NAME? | AE47: =+SUM(CY47:DB47) -> #NAME? | AI47: ='QTR Raw'!C25 -> #NAME? | AJ47: ='QTR Raw'!D25 -> #NAME? | AK47: ='QTR Raw'!E25 -> #NAME? | AL47: ='QTR Raw'!F25 -> #NAME? | AM47: ='QTR Raw'!G25 -> #NAME? | AN47: ='QTR Raw'!H25 -> #NAME? | AO47: ='QTR Raw'!I25 -> #NAME? | AP47: ='QTR Raw'!J25 -> #NAME? | ... CF47: ='QTR Raw'!AZ25 -> #NAME? | CG47: 5.005 | CH47: ='QTR Raw'!BB25 -> #NAME? | CI47: ='QTR Raw'!BC25 -> #NAME? | CJ47: ='QTR Raw'!BD25 -> #NAME? | CK47: ='QTR Raw'!BE25 -> #NAME? | CL47: ='QTR Raw'!BF25 -> #NAME? | CM47: =CM48*CL179 -> #NAME? | CN47: =CN48*CM179 -> #NAME? | CO47: =CO48*CN179 -> #NAME? | CP47: =CP48*CO179 -> #NAME? | CQ47: =CQ48*CP179 -> #NAME? | CR47: =CR48*CQ179 -> #NAME? | CS47: =CS48*CR179 -> #NAME? | CT47: =CT48*CS179 -> #NAME? | ... DB47: =DB48*DA179 -> #NAME? | DF47: 39.298
A48: Interest % of Debt | B48: =+B47/B139 -> #NAME? | C48: =+C47/C139 -> #NAME? | D48: =+D47/D139 -> #NAME? | E48: =+E47/E139 -> #NAME? | F48: =+F47/F139 -> #NAME? | G48: =+G47/G139 -> #NAME? | H48: =+H47/H139 -> #NAME? | I48: =+I47/I139 -> #NAME? | ... AE48: =+AE47/AE139 -> #NAME? | AI48: =(AI47-AI46)/AH179 -> #NAME? | AJ48: =(AJ47-AJ46)/AI179 -> #NAME? | AK48: =(AK47-AK46)/AJ179 -> #NAME? | AL48: =(AL47-AL46)/AK179 -> #NAME? | AM48: =(AM47-AM46)/AL179 -> #NAME? | AN48: =(AN47-AN46)/AM179 -> #NAME? | AO48: =(AO47-AO46)/AN179 -> #NAME? | AP48: =(AP47-AP46)/AO179 -> #NAME? | ... CF48: =(CF47-CF46)/CE179 -> #NAME? | CG48: 0.036958544 | CH48: =(CH47-CH46)/CG179 -> #NAME? | CI48: =(CI47-CI46)/CH179 -> #NAME? | CJ48: =(CJ47-CJ46)/CI179 -> #NAME? | CK48: =(CK47-CK46)/CJ179 -> #NAME? | CL48: =(CL47-CL46)/CK179 -> #NAME? | CM48: =+CL48 -> #NAME? | CN48: =+CM48 -> #NAME? | CO48: =+CN48 -> #NAME? | CP48: =+CO48 -> #NAME? | CQ48: =+CP48 -> #NAME? | CR48: =+CQ48 -> #NAME? | CS48: =+CR48 -> #NAME? | CT48: =+CS48 -> #NAME? | ... DB48: =+DA48 -> #NAME? | DF48: 0.17669964
A49: PBT | B49: =B45+B46-B47 -> #NAME? | C49: =C45+C46-C47 -> #NAME? | D49: =D45+D46-D47 -> #NAME? | E49: =E45+E46-E47 -> #NAME? | F49: =F45+F46-F47 -> #NAME? | G49: =G45+G46-G47 -> #NAME? | H49: =H45+H46-H47 -> #NAME? | I49: =I45+I46-I47 -> #NAME? | ... AE49: =AE45+AE46-AE47 -> #NAME? | AI49: =AI45+AI46-AI47 -> #NAME? | AJ49: =AJ45+AJ46-AJ47 -> #NAME? | AK49: =AK45+AK46-AK47 -> #NAME? | AL49: =AL45+AL46-AL47 -> #NAME? | AM49: =AM45+AM46-AM47 -> #NAME? | AN49: =AN45+AN46-AN47 -> #NAME? | AO49: =AO45+AO46-AO47 -> #NAME? | AP49: =AP45+AP46-AP47 -> #NAME? | ... CF49: =CF45+CF46-CF47 -> #NAME? | CG49: 7.135 | CH49: =CH45+CH46-CH47 -> #NAME? | CI49: =CI45+CI46-CI47 -> #NAME? | CJ49: =CJ45+CJ46-CJ47 -> #NAME? | CK49: =CK45+CK46-CK47 -> #NAME? | CL49: =CL45+CL46-CL47 -> #NAME? | CM49: =CM45+CM46-CM47 -> #NAME? | CN49: =CN45+CN46-CN47 -> #NAME? | CO49: =CO45+CO46-CO47 -> #NAME? | ... DB49: =DB45+DB46-DB47 -> #NAME? | DF49: 46.993
A50: Tax | B50: ='Annual Raw'!C30 -> #NAME? | C50: ='Annual Raw'!D30 -> #NAME? | D50: ='Annual Raw'!E30 -> #NAME? | E50: ='Annual Raw'!F30 -> #NAME? | F50: ='Annual Raw'!G30 -> #NAME? | G50: ='Annual Raw'!H30 -> #NAME? | H50: ='Annual Raw'!I30 -> #NAME? | I50: ='Annual Raw'!J30 -> #NAME? | ... AA50: ='Annual Raw'!AB30 -> #NAME? | AB50: =+SUM(CM50:CP50) -> #NAME? | AC50: =+SUM(CQ50:CT50) -> #NAME? | AD50: =+SUM(CU50:CX50) -> #NAME? | AE50: =+SUM(CY50:DB50) -> #NAME? | AI50: ='QTR Raw'!C29 -> #NAME? | AJ50: ='QTR Raw'!D29 -> #NAME? | AK50: ='QTR Raw'!E29 -> #NAME? | AL50: ='QTR Raw'!F29 -> #NAME? | AM50: ='QTR Raw'!G29 -> #NAME? | AN50: ='QTR Raw'!H29 -> #NAME? | AO50: ='QTR Raw'!I29 -> #NAME? | AP50: ='QTR Raw'!J29 -> #NAME? | ... CF50: ='QTR Raw'!AZ29 -> #NAME? | CG50: 1.802 | CH50: ='QTR Raw'!BB29 -> #NAME? | CI50: ='QTR Raw'!BC29 -> #NAME? | CJ50: ='QTR Raw'!BD29 -> #NAME? | CK50: ='QTR Raw'!BE29 -> #NAME? | CL50: ='QTR Raw'!BF29 -> #NAME? | CM50: =+CM49*CM51 -> #NAME? | CN50: =+CN49*CN51 -> #NAME? | CO50: =+CO49*CO51 -> #NAME? | CP50: =+CP49*CP51 -> #NAME? | CQ50: =+CQ49*CQ51 -> #NAME? | CR50: =+CR49*CR51 -> #NAME? | CS50: =+CS49*CS51 -> #NAME? | CT50: =+CT49*CT51 -> #NAME? | ... DB50: =+DB49*DB51 -> #NAME? | DF50: 9.541
A51: Tax Rate % | B51: =B50/B49 -> #NAME? | C51: =C50/C49 -> #NAME? | D51: =D50/D49 -> #NAME? | E51: =E50/E49 -> #NAME? | F51: =F50/F49 -> #NAME? | G51: =G50/G49 -> #NAME? | H51: =H50/H49 -> #NAME? | I51: =I50/I49 -> #NAME? | ... AE51: =AE50/AE49 -> #NAME? | AI51: =AI50/AI49 -> #NAME? | AJ51: =AJ50/AJ49 -> #NAME? | AK51: =AK50/AK49 -> #NAME? | AL51: =AL50/AL49 -> #NAME? | AM51: =AM50/AM49 -> #NAME? | AN51: =AN50/AN49 -> #NAME? | AO51: =AO50/AO49 -> #NAME? | AP51: =AP50/AP49 -> #NAME? | ... CF51: =CF50/CF49 -> #NAME? | CG51: 0.25255781 | CH51: =CH50/CH49 -> #NAME? | CI51: =CI50/CI49 -> #NAME? | CJ51: =CJ50/CJ49 -> #NAME? | CK51: =CK50/CK49 -> #NAME? | CL51: =CL50/CL49 -> #NAME? | CM51: =AVERAGE(CI51:CL51) -> #NAME? | CN51: =AVERAGE(CJ51:CM51) -> #NAME? | CO51: =AVERAGE(CK51:CN51) -> #NAME? | CP51: =AVERAGE(CL51:CO51) -> #NAME? | CQ51: =AVERAGE(CM51:CP51) -> #NAME? | CR51: =AVERAGE(CN51:CQ51) -> #NAME? | CS51: =AVERAGE(CO51:CR51) -> #NAME? | CT51: =AVERAGE(CP51:CS51) -> #NAME? | ... DB51: =AVERAGE(CX51:DA51) -> #NAME? | DF51: 0.20303024
A52: PAT | B52: =B49-B50 -> #NAME? | C52: =C49-C50 -> #NAME? | D52: =D49-D50 -> #NAME? | E52: =E49-E50 -> #NAME? | F52: =F49-F50 -> #NAME? | G52: =G49-G50 -> #NAME? | H52: =H49-H50 -> #NAME? | I52: =I49-I50 -> #NAME? | ... AE52: =AE49-AE50 -> #NAME? | AI52: =AI49-AI50 -> #NAME? | AJ52: =AJ49-AJ50 -> #NAME? | AK52: =AK49-AK50 -> #NAME? | AL52: =AL49-AL50 -> #NAME? | AM52: =AM49-AM50 -> #NAME? | AN52: =AN49-AN50 -> #NAME? | AO52: =AO49-AO50 -> #NAME? | AP52: =AP49-AP50 -> #NAME? | ... CF52: =CF49-CF50 -> #NAME? | CG52: 5.333 | CH52: =CH49-CH50 -> #NAME? | CI52: =CI49-CI50 -> #NAME? | CJ52: =CJ49-CJ50 -> #NAME? | CK52: =CK49-CK50 -> #NAME? | CL52: =CL49-CL50 -> #NAME? | CM52: =CM49-CM50 -> #NAME? | CN52: =CN49-CN50 -> #NAME? | CO52: =CO49-CO50 -> #NAME? | ... DB52: =DB49-DB50 -> #NAME? | DF52: 37.452
A53: PAT % | B53: =+B52/B21 -> #NAME? | C53: =+C52/C21 -> #NAME? | D53: =+D52/D21 -> #NAME? | E53: =+E52/E21 -> #NAME? | F53: =+F52/F21 -> #NAME? | G53: =+G52/G21 -> #NAME? | H53: =+H52/H21 -> #NAME? | I53: =+I52/I21 -> #NAME? | ... AE53: =+AE52/AE21 -> #NAME? | AI53: =+AI52/AI21 -> #NAME? | AJ53: =+AJ52/AJ21 -> #NAME? | AK53: =+AK52/AK21 -> #NAME? | AL53: =+AL52/AL21 -> #NAME? | AM53: =+AM52/AM21 -> #NAME? | AN53: =+AN52/AN21 -> #NAME? | AO53: =+AO52/AO21 -> #NAME? | AP53: =+AP52/AP21 -> #NAME? | ... CF53: =+CF52/CF21 -> #NAME? | CG53: 0.051929462 | CH53: =+CH52/CH21 -> #NAME? | CI53: =+CI52/CI21 -> #NAME? | CJ53: =+CJ52/CJ21 -> #NAME? | CK53: =+CK52/CK21 -> #NAME? | CL53: =+CL52/CL21 -> #NAME? | CM53: =+CM52/CM21 -> #NAME? | CN53: =+CN52/CN21 -> #NAME? | CO53: =+CO52/CO21 -> #NAME? | ... DB53: =+DB52/DB21 -> #NAME? | DF53: 0.058598957
A54: PAT YOY% | C54: =+IF(B52<0,1-C52/B52,C52/B52-1) -> #NAME? | D54: =+IF(C52<0,1-D52/C52,D52/C52-1) -> #NAME? | E54: =+IF(D52<0,1-E52/D52,E52/D52-1) -> #NAME? | F54: =+IF(E52<0,1-F52/E52,F52/E52-1) -> #NAME? | G54: =+IF(F52<0,1-G52/F52,G52/F52-1) -> #NAME? | H54: =+IF(G52<0,1-H52/G52,H52/G52-1) -> #NAME? | I54: =+IF(H52<0,1-I52/H52,I52/H52-1) -> #NAME? | J54: =+IF(I52<0,1-J52/I52,J52/I52-1) -> #NAME? | ... AE54: =+IF(AD52<0,1-AE52/AD52,AE52/AD52-1) -> #NAME? | AM54: =+IF(AI52<0,1-AM52/AI52,AM52/AI52-1) -> #NAME? | AN54: =+IF(AJ52<0,1-AN52/AJ52,AN52/AJ52-1) -> #NAME? | AO54: =+IF(AK52<0,1-AO52/AK52,AO52/AK52-1) -> #NAME? | AP54: =+IF(AL52<0,1-AP52/AL52,AP52/AL52-1) -> #NAME? | AQ54: =+IF(AM52<0,1-AQ52/AM52,AQ52/AM52-1) -> #NAME? | AR54: =+IF(AN52<0,1-AR52/AN52,AR52/AN52-1) -> #NAME? | AS54: =+IF(AO52<0,1-AS52/AO52,AS52/AO52-1) -> #NAME? | AT54: =+IF(AP52<0,1-AT52/AP52,AT52/AP52-1) -> #NAME? | ... CF54: =+IF(CB52<0,1-CF52/CB52,CF52/CB52-1) -> #NAME? | CG54: 0.26344468 | CH54: =+IF(CD52<0,1-CH52/CD52,CH52/CD52-1) -> #NAME? | CI54: =+IF(CE52<0,1-CI52/CE52,CI52/CE52-1) -> #NAME? | CJ54: =+IF(CF52<0,1-CJ52/CF52,CJ52/CF52-1) -> #NAME? | CK54: =+IF(CG52<0,1-CK52/CG52,CK52/CG52-1) -> #NAME? | CL54: =+IF(CH52<0,1-CL52/CH52,CL52/CH52-1) -> #NAME? | CM54: =+CM52/CI52-1 -> #NAME? | CN54: =+CN52/CJ52-1 -> #NAME? | CO54: =+CO52/CK52-1 -> #NAME? | CP54: =+CP52/CL52-1 -> #NAME? | CQ54: =+CQ52/CM52-1 -> #NAME? | CR54: =+CR52/CN52-1 -> #NAME? | CS54: =+CS52/CO52-1 -> #NAME? | CT54: =+CT52/CP52-1 -> #NAME? | ... DB54: =+DB52/CX52-1 -> #NAME? | DF54: 0.89733172
A55: PAT QOQ% | AJ55: =+IF(AI52<0,1-AJ52/AI52,AJ52/AI52-1) -> #NAME? | AK55: =+IF(AJ52<0,1-AK52/AJ52,AK52/AJ52-1) -> #NAME? | AL55: =+IF(AK52<0,1-AL52/AK52,AL52/AK52-1) -> #NAME? | AM55: =+IF(AL52<0,1-AM52/AL52,AM52/AL52-1) -> #NAME? | AN55: =+IF(AM52<0,1-AN52/AM52,AN52/AM52-1) -> #NAME? | AO55: =+IF(AN52<0,1-AO52/AN52,AO52/AN52-1) -> #NAME? | AP55: =+IF(AO52<0,1-AP52/AO52,AP52/AO52-1) -> #NAME? | AQ55: =+IF(AP52<0,1-AQ52/AP52,AQ52/AP52-1) -> #NAME? | ... CF55: =+IF(CE52<0,1-CF52/CE52,CF52/CE52-1) -> #NAME? | CG55: 0.24777726 | CH55: =+IF(CG52<0,1-CH52/CG52,CH52/CG52-1) -> #NAME? | CI55: =+IF(CH52<0,1-CI52/CH52,CI52/CH52-1) -> #NAME? | CJ55: =+IF(CI52<0,1-CJ52/CI52,CJ52/CI52-1) -> #NAME? | CK55: =+IF(CJ52<0,1-CK52/CJ52,CK52/CJ52-1) -> #NAME? | CL55: =+IF(CK52<0,1-CL52/CK52,CL52/CK52-1) -> #NAME? | CM55: =+CM52/CL52-1 -> #NAME? | CN55: =+CN52/CM52-1 -> #NAME? | CO55: =+CO52/CN52-1 -> #NAME? | CP55: =+CP52/CO52-1 -> #NAME? | CQ55: =+CQ52/CP52-1 -> #NAME? | CR55: =+CR52/CQ52-1 -> #NAME? | CS55: =+CS52/CR52-1 -> #NAME? | CT55: =+CT52/CS52-1 -> #NAME? | ... DB55: =+DB52/DA52-1 -> #NAME?
A56: Minority Interest | B56: ='Annual Raw'!C32 -> #NAME? | C56: ='Annual Raw'!D32 -> #NAME? | D56: ='Annual Raw'!E32 -> #NAME? | E56: ='Annual Raw'!F32 -> #NAME? | F56: ='Annual Raw'!G32 -> #NAME? | G56: ='Annual Raw'!H32 -> #NAME? | H56: ='Annual Raw'!I32 -> #NAME? | I56: ='Annual Raw'!J32 -> #NAME? | ... AA56: ='Annual Raw'!AB32 -> #NAME? | AB56: =+SUM(CM56:CP56) -> #NAME? | AC56: =+SUM(CQ56:CT56) -> #NAME? | AD56: =+SUM(CU56:CX56) -> #NAME? | AE56: =+SUM(CY56:DB56) -> #NAME? | AI56: ='QTR Raw'!C34 -> #NAME? | AJ56: ='QTR Raw'!D34 -> #NAME? | AK56: ='QTR Raw'!E34 -> #NAME? | AL56: ='QTR Raw'!F34 -> #NAME? | AM56: ='QTR Raw'!G34 -> #NAME? | AN56: ='QTR Raw'!H34 -> #NAME? | AO56: ='QTR Raw'!I34 -> #NAME? | AP56: ='QTR Raw'!J34 -> #NAME? | ... CF56: ='QTR Raw'!AZ34 -> #NAME? | CG56: 0 | CH56: ='QTR Raw'!BB34 -> #NAME? | CI56: ='QTR Raw'!BC34 -> #NAME? | CJ56: ='QTR Raw'!BD34 -> #NAME? | CK56: ='QTR Raw'!BE34 -> #NAME? | CL56: ='QTR Raw'!BF34 -> #NAME? | CM56: =+CL56 -> #NAME? | CN56: =+CM56 -> #NAME? | CO56: =+CN56 -> #NAME? | CP56: =+CO56 -> #NAME? | CQ56: =+CP56 -> #NAME? | CR56: =+CQ56 -> #NAME? | CS56: =+CR56 -> #NAME? | CT56: =+CS56 -> #NAME? | ... DB56: =+DA56 -> #NAME? | DF56: 0
A57: Share of Associate | B57: ='Annual Raw'!C33+'Annual Raw'!C28 -> #NAME? | C57: ='Annual Raw'!D33+'Annual Raw'!D28 -> #NAME? | D57: ='Annual Raw'!E33+'Annual Raw'!E28 -> #NAME? | E57: ='Annual Raw'!F33+'Annual Raw'!F28 -> #NAME? | F57: ='Annual Raw'!G33+'Annual Raw'!G28 -> #NAME? | G57: ='Annual Raw'!H33+'Annual Raw'!H28 -> #NAME? | H57: ='Annual Raw'!I33+'Annual Raw'!I28 -> #NAME? | I57: ='Annual Raw'!J33+'Annual Raw'!J28 -> #NAME? | ... AA57: ='Annual Raw'!AB33+'Annual Raw'!AB28 -> #NAME? | AB57: =+SUM(CM57:CP57) -> #NAME? | AC57: =+SUM(CQ57:CT57) -> #NAME? | AD57: =+SUM(CU57:CX57) -> #NAME? | AE57: =+SUM(CY57:DB57) -> #NAME? | AI57: ='QTR Raw'!C35 -> #NAME? | AJ57: ='QTR Raw'!D35 -> #NAME? | AK57: ='QTR Raw'!E35 -> #NAME? | AL57: ='QTR Raw'!F35 -> #NAME? | AM57: ='QTR Raw'!G35 -> #NAME? | AN57: ='QTR Raw'!H35 -> #NAME? | AO57: ='QTR Raw'!I35 -> #NAME? | AP57: ='QTR Raw'!J35 -> #NAME? | ... CF57: ='QTR Raw'!AZ35 -> #NAME? | CG57: 0 | CH57: ='QTR Raw'!BB35 -> #NAME? | CI57: ='QTR Raw'!BC35 -> #NAME? | CJ57: ='QTR Raw'!BD35 -> #NAME? | CK57: ='QTR Raw'!BE35 -> #NAME? | CL57: ='QTR Raw'!BF35 -> #NAME? | CM57: =+CL57 -> #NAME? | CN57: =+CM57 -> #NAME? | CO57: =+CN57 -> #NAME? | CP57: =+CO57 -> #NAME? | CQ57: =+CP57 -> #NAME? | CR57: =+CQ57 -> #NAME? | CS57: =+CR57 -> #NAME? | CT57: =+CS57 -> #NAME? | ... DB57: =+DA57 -> #NAME? | DF57: 0
A58: Exceptional Income / Expenses | B58: ='Annual Raw'!C29+'Annual Raw'!C31+'Annual Raw'!C34+'Annual Raw'!C36 -> #NAME? | C58: ='Annual Raw'!D29+'Annual Raw'!D31+'Annual Raw'!D34+'Annual Raw'!D36 -> #NAME? | D58: ='Annual Raw'!E29+'Annual Raw'!E31+'Annual Raw'!E34+'Annual Raw'!E36 -> #NAME? | E58: ='Annual Raw'!F29+'Annual Raw'!F31+'Annual Raw'!F34+'Annual Raw'!F36 -> #NAME? | F58: ='Annual Raw'!G29+'Annual Raw'!G31+'Annual Raw'!G34+'Annual Raw'!G36 -> #NAME? | G58: ='Annual Raw'!H29+'Annual Raw'!H31+'Annual Raw'!H34+'Annual Raw'!H36 -> #NAME? | H58: ='Annual Raw'!I29+'Annual Raw'!I31+'Annual Raw'!I34+'Annual Raw'!I36 -> #NAME? | I58: ='Annual Raw'!J29+'Annual Raw'!J31+'Annual Raw'!J34+'Annual Raw'!J36 -> #NAME? | ... AA58: ='Annual Raw'!AB29+'Annual Raw'!AB31+'Annual Raw'!AB34+'Annual Raw'!AB36 -> #NAME? | AB58: =+SUM(CM58:CP58) -> 0 | AC58: =+SUM(CQ58:CT58) -> 0 | AD58: =+SUM(CU58:CX58) -> 0 | AE58: =+SUM(CY58:DB58) -> 0 | AI58: ='QTR Raw'!C26+'QTR Raw'!C31+'QTR Raw'!C32+'QTR Raw'!C33+'QTR Raw'!C36+'QTR Raw'!C37+'QTR Raw'!C39 -> #NAME? | AJ58: ='QTR Raw'!D26+'QTR Raw'!D31+'QTR Raw'!D32+'QTR Raw'!D33+'QTR Raw'!D36+'QTR Raw'!D37+'QTR Raw'!D39 -> #NAME? | AK58: ='QTR Raw'!E26+'QTR Raw'!E31+'QTR Raw'!E32+'QTR Raw'!E33+'QTR Raw'!E36+'QTR Raw'!E37+'QTR Raw'!E39 -> #NAME? | AL58: ='QTR Raw'!F26+'QTR Raw'!F31+'QTR Raw'!F32+'QTR Raw'!F33+'QTR Raw'!F36+'QTR Raw'!F37+'QTR Raw'!F39 -> #NAME? | AM58: ='QTR Raw'!G26+'QTR Raw'!G31+'QTR Raw'!G32+'QTR Raw'!G33+'QTR Raw'!G36+'QTR Raw'!G37+'QTR Raw'!G39 -> #NAME? | AN58: ='QTR Raw'!H26+'QTR Raw'!H31+'QTR Raw'!H32+'QTR Raw'!H33+'QTR Raw'!H36+'QTR Raw'!H37+'QTR Raw'!H39 -> #NAME? | AO58: ='QTR Raw'!I26+'QTR Raw'!I31+'QTR Raw'!I32+'QTR Raw'!I33+'QTR Raw'!I36+'QTR Raw'!I37+'QTR Raw'!I39 -> #NAME? | AP58: ='QTR Raw'!J26+'QTR Raw'!J31+'QTR Raw'!J32+'QTR Raw'!J33+'QTR Raw'!J36+'QTR Raw'!J37+'QTR Raw'!J39 -> #NAME? | ... CF58: ='QTR Raw'!AZ26+'QTR Raw'!AZ31+'QTR Raw'!AZ32+'QTR Raw'!AZ33+'QTR Raw'!AZ36+'QTR Raw'!AZ37+'QTR Raw'!AZ39 -> #NAME? | CG58: 0 | CH58: ='QTR Raw'!BB26+'QTR Raw'!BB31+'QTR Raw'!BB32+'QTR Raw'!BB33+'QTR Raw'!BB36+'QTR Raw'!BB37+'QTR Raw'!BB39 -> #NAME? | CI58: ='QTR Raw'!BC26+'QTR Raw'!BC31+'QTR Raw'!BC32+'QTR Raw'!BC33+'QTR Raw'!BC36+'QTR Raw'!BC37+'QTR Raw'!BC39 -> #NAME? | CJ58: ='QTR Raw'!BD26+'QTR Raw'!BD31+'QTR Raw'!BD32+'QTR Raw'!BD33+'QTR Raw'!BD36+'QTR Raw'!BD37+'QTR Raw'!BD39 -> #NAME? | CK58: ='QTR Raw'!BE26+'QTR Raw'!BE31+'QTR Raw'!BE32+'QTR Raw'!BE33+'QTR Raw'!BE36+'QTR Raw'!BE37+'QTR Raw'!BE39 -> #NAME? | CL58: ='QTR Raw'!BF26+'QTR Raw'!BF31+'QTR Raw'!BF32+'QTR Raw'!BF33+'QTR Raw'!BF36+'QTR Raw'!BF37+'QTR Raw'!BF39 -> #NAME? | DF58: 0
A59: Consolidated Net Profit | B59: =B52+B56+B57+B58 -> #NAME? | C59: =C52+C56+C57+C58 -> #NAME? | D59: =D52+D56+D57+D58 -> #NAME? | E59: =E52+E56+E57+E58 -> #NAME? | F59: =F52+F56+F57+F58 -> #NAME? | G59: =G52+G56+G57+G58 -> #NAME? | H59: =H52+H56+H57+H58 -> #NAME? | I59: =I52+I56+I57+I58 -> #NAME? | ... AE59: =AE52+AE56+AE57+AE58 -> #NAME? | AI59: =AI52+AI56+AI57+AI58 -> #NAME? | AJ59: =AJ52+AJ56+AJ57+AJ58 -> #NAME? | AK59: =AK52+AK56+AK57+AK58 -> #NAME? | AL59: =AL52+AL56+AL57+AL58 -> #NAME? | AM59: =AM52+AM56+AM57+AM58 -> #NAME? | AN59: =AN52+AN56+AN57+AN58 -> #NAME? | AO59: =AO52+AO56+AO57+AO58 -> #NAME? | AP59: =AP52+AP56+AP57+AP58 -> #NAME? | ... CF59: =CF52+CF56+CF57+CF58 -> #NAME? | CG59: 5.333 | CH59: =CH52+CH56+CH57+CH58 -> #NAME? | CI59: =CI52+CI56+CI57+CI58 -> #NAME? | CJ59: =CJ52+CJ56+CJ57+CJ58 -> #NAME? | CK59: =CK52+CK56+CK57+CK58 -> #NAME? | CL59: =CL52+CL56+CL57+CL58 -> #NAME? | CM59: =CM52+CM56+CM57+CM58 -> #NAME? | CN59: =CN52+CN56+CN57+CN58 -> #NAME? | CO59: =CO52+CO56+CO57+CO58 -> #NAME? | ... DB59: =DB52+DB56+DB57+DB58 -> #NAME? | DF59: 37.452
A60: Profit & Loss- Annual (End)
A62: Ace - PAT | B62: ='Annual Raw'!C35 -> #NAME? | C62: ='Annual Raw'!D35 -> #NAME? | D62: ='Annual Raw'!E35 -> #NAME? | E62: ='Annual Raw'!F35 -> #NAME? | F62: ='Annual Raw'!G35 -> #NAME? | G62: ='Annual Raw'!H35 -> #NAME? | H62: ='Annual Raw'!I35 -> #NAME? | I62: ='Annual Raw'!J35 -> #NAME? | ... AA62: ='Annual Raw'!AB35 -> #NAME? | AB62: =+AB59 -> #NAME? | AC62: =+AC59 -> #NAME? | AD62: =+AD59 -> #NAME? | AE62: =+AE59 -> #NAME? | AI62: ='QTR Raw'!C42 -> #NAME? | AJ62: ='QTR Raw'!D42 -> #NAME? | AK62: ='QTR Raw'!E42 -> #NAME? | AL62: ='QTR Raw'!F42 -> #NAME? | AM62: ='QTR Raw'!G42 -> #NAME? | AN62: ='QTR Raw'!H42 -> #NAME? | AO62: ='QTR Raw'!I42 -> #NAME? | AP62: ='QTR Raw'!J42 -> #NAME? | ... CF62: ='QTR Raw'!AZ42 -> #NAME? | CG62: 5.33 | CH62: ='QTR Raw'!BB42 -> #NAME? | CI62: ='QTR Raw'!BC42 -> #NAME? | CJ62: ='QTR Raw'!BD42 -> #NAME? | CK62: ='QTR Raw'!BE42 -> #NAME? | CL62: ='QTR Raw'!BF42 -> #NAME? | DF62: 37.452
A63: Checksum - PAT | B63: =B62-B59 -> #NAME? | C63: =C62-C59 -> #NAME? | D63: =D62-D59 -> #NAME? | E63: =E62-E59 -> #NAME? | F63: =F62-F59 -> #NAME? | G63: =G62-G59 -> #NAME? | H63: =H62-H59 -> #NAME? | I63: =I62-I59 -> #NAME? | ... AE63: =AE62-AE59 -> #NAME? | AI63: =AI62-AI59 -> #NAME? | AJ63: =AJ62-AJ59 -> #NAME? | AK63: =AK62-AK59 -> #NAME? | AL63: =AL62-AL59 -> #NAME? | AM63: =AM62-AM59 -> #NAME? | AN63: =AN62-AN59 -> #NAME? | AO63: =AO62-AO59 -> #NAME? | AP63: =AP62-AP59 -> #NAME? | ... CL63: =CL62-CL59 -> #NAME? | DF63: 0
A64: Ratios (Start)
A65: ROE (%) | B65: =(B59-B58)/B131 -> #NAME? | C65: =(C59-C58)/C131 -> #NAME? | D65: =(D59-D58)/D131 -> #NAME? | E65: =(E59-E58)/E131 -> #NAME? | F65: =(F59-F58)/F131 -> #NAME? | G65: =(G59-G58)/G131 -> #NAME? | H65: =(H59-H58)/H131 -> #NAME? | I65: =(I59-I58)/I131 -> #NAME? | ... AE65: =(AE59-AE58)/AE131 -> #NAME? | AL65: =(SUM(AI59:AL59)-SUM(AI58:AL58))/AL131 -> #NAME? | AM65: =(SUM(AJ59:AM59)-SUM(AJ58:AM58))/AM131 -> #NAME? | AN65: =(SUM(AK59:AN59)-SUM(AK58:AN58))/AN131 -> #NAME? | AO65: =(SUM(AL59:AO59)-SUM(AL58:AO58))/AO131 -> #NAME? | AP65: =(SUM(AM59:AP59)-SUM(AM58:AP58))/AP131 -> #NAME? | AQ65: =(SUM(AN59:AQ59)-SUM(AN58:AQ58))/AQ131 -> #NAME? | AR65: =(SUM(AO59:AR59)-SUM(AO58:AR58))/AR131 -> #NAME? | AS65: =(SUM(AP59:AS59)-SUM(AP58:AS58))/AS131 -> #NAME? | ... DB65: =(SUM(CY59:DB59)-SUM(CY58:DB58))/DB131 -> #NAME? | DF65: 0.13466711
A66: ROCE (%) | B66: =+B45/B140 -> #NAME? | C66: =+C45/C140 -> #NAME? | D66: =+D45/D140 -> #NAME? | E66: =+E45/E140 -> #NAME? | F66: =+F45/F140 -> #NAME? | G66: =+G45/G140 -> #NAME? | H66: =+H45/H140 -> #NAME? | I66: =+I45/I140 -> #NAME? | ... AE66: =+AE45/AE140 -> #NAME? | AL66: =+SUM(AI45:AL45)/AL140 -> #NAME? | AM66: =+SUM(AJ45:AM45)/AM140 -> #NAME? | AN66: =+SUM(AK45:AN45)/AN140 -> #NAME? | AO66: =+SUM(AL45:AO45)/AO140 -> #NAME? | AP66: =+SUM(AM45:AP45)/AP140 -> #NAME? | AQ66: =+SUM(AN45:AQ45)/AQ140 -> #NAME? | AR66: =+SUM(AO45:AR45)/AR140 -> #NAME? | AS66: =+SUM(AP45:AS45)/AS140 -> #NAME? | ... DB66: =+SUM(CY45:DB45)/DB140 -> #NAME? | DF66: 0.17240683
A67: Ratios (End)
A68: Checksum Of qtr to Annual
A69: Revenue - Checksum Of qtr to Annual | N69: =N21-SUM(AI21:AL21) -> #NAME? | O69: =O21-SUM(AM21:AP21) -> #NAME? | P69: =P21-SUM(AQ21:AT21) -> #NAME? | Q69: =Q21-SUM(AU21:AX21) -> #NAME? | R69: =R21-SUM(AY21:BB21) -> #NAME? | S69: =S21-SUM(BC21:BF21) -> #NAME? | T69: =T21-SUM(BG21:BJ21) -> #NAME? | U69: =U21-SUM(BK21:BN21) -> #NAME? | V69: =V21-SUM(BO21:BR21) -> #NAME? | W69: =W21-SUM(BS21:BV21) -> #NAME? | X69: =X21-SUM(BW21:BZ21) -> #NAME? | Y69: =Y21-SUM(CA21:CD21) -> #NAME? | Z69: =Z21-SUM(CE21:CH21) -> #NAME? | AA69: =AA21-SUM(CF21:CI21) -> #NAME? | AB69: =AB21-SUM(CM21:CP21) -> 0 | AC69: =AC21-SUM(CQ21:CT21) -> 0 | AD69: =AD21-SUM(CU21:CX21) -> 0 | AE69: =AE21-SUM(CY21:DB21) -> 0 | DF69: 0
A70: GP - Checksum Of qtr to Annual | N70: =N27-SUM(AI27:AL27) -> #NAME? | O70: =O27-SUM(AM27:AP27) -> #NAME? | P70: =P27-SUM(AQ27:AT27) -> #NAME? | Q70: =Q27-SUM(AU27:AX27) -> #NAME? | R70: =R27-SUM(AY27:BB27) -> #NAME? | S70: =S27-SUM(BC27:BF27) -> #NAME? | T70: =T27-SUM(BG27:BJ27) -> #NAME? | U70: =U27-SUM(BK27:BN27) -> #NAME? | V70: =V27-SUM(BO27:BR27) -> #NAME? | W70: =W27-SUM(BS27:BV27) -> #NAME? | X70: =X27-SUM(BW27:BZ27) -> #NAME? | Y70: =Y27-SUM(CA27:CD27) -> #NAME? | Z70: =Z27-SUM(CE27:CH27) -> #NAME? | AA70: =AA27-SUM(CF27:CI27) -> #NAME? | AB70: =AB27-SUM(CM27:CP27) -> #NAME? | AC70: =AC27-SUM(CQ27:CT27) -> #NAME? | AD70: =AD27-SUM(CU27:CX27) -> #NAME? | AE70: =AE27-SUM(CY27:DB27) -> #NAME? | DF70: 0
A71: EBITDA - Checksum Of qtr to Annual | N71: =N39-SUM(AI39:AL39) -> #NAME? | O71: =O39-SUM(AM39:AP39) -> #NAME? | P71: =P39-SUM(AQ39:AT39) -> #NAME? | Q71: =Q39-SUM(AU39:AX39) -> #NAME? | R71: =R39-SUM(AY39:BB39) -> #NAME? | S71: =S39-SUM(BC39:BF39) -> #NAME? | T71: =T39-SUM(BG39:BJ39) -> #NAME? | U71: =U39-SUM(BK39:BN39) -> #NAME? | V71: =V39-SUM(BO39:BR39) -> #NAME? | W71: =W39-SUM(BS39:BV39) -> #NAME? | X71: =X39-SUM(BW39:BZ39) -> #NAME? | Y71: =Y39-SUM(CA39:CD39) -> #NAME? | Z71: =Z39-SUM(CE39:CH39) -> #NAME? | AA71: =AA39-SUM(CF39:CI39) -> #NAME? | AB71: =AB39-SUM(CM39:CP39) -> #NAME? | AC71: =AC39-SUM(CQ39:CT39) -> #NAME? | AD71: =AD39-SUM(CU39:CX39) -> #NAME? | AE71: =AE39-SUM(CY39:DB39) -> #NAME? | DF71: 0
A72: PAT - Checksum Of qtr to Annual | N72: =N59-SUM(AI59:AL59) -> #NAME? | O72: =O59-SUM(AM59:AP59) -> #NAME? | P72: =P59-SUM(AQ59:AT59) -> #NAME? | Q72: =Q59-SUM(AU59:AX59) -> #NAME? | R72: =R59-SUM(AY59:BB59) -> #NAME? | S72: =S59-SUM(BC59:BF59) -> #NAME? | T72: =T59-SUM(BG59:BJ59) -> #NAME? | U72: =U59-SUM(BK59:BN59) -> #NAME? | V72: =V59-SUM(BO59:BR59) -> #NAME? | W72: =W52-SUM(BS52:BV52) -> #NAME? | X72: =X52-SUM(BW52:BZ52) -> #NAME? | Y72: =Y52-SUM(CA52:CD52) -> #NAME? | Z72: =Z52-SUM(CE52:CH52) -> #NAME? | AA72: =AA52-SUM(CF52:CI52) -> #NAME? | AB72: =AB52-SUM(CM52:CP52) -> #NAME? | AC72: =AC52-SUM(CQ52:CT52) -> #NAME? | AD72: =AD52-SUM(CU52:CX52) -> #NAME? | AE72: =AE52-SUM(CY52:DB52) -> #NAME? | DF72: 5.6843419e-14
A73: Valuation (Start) | CM73: 16.41
A74: Eq | B74: ='Annual Raw'!C104 -> #NAME? | C74: ='Annual Raw'!D104 -> #NAME? | D74: ='Annual Raw'!E104 -> #NAME? | E74: =+F74 -> 5.473 | F74: =+G74 -> 5.473 | G74: =+H74 -> 5.473 | H74: =+I74 -> 5.473 | I74: =+J74 -> 5.473 | J74: =+K74 -> 5.473 | K74: =+L74 -> 5.473 | L74: =+M74 -> 5.473 | ... AA74: =+AB74 -> 5.473 | AB74: =AA74 -> 5.473 | AC74: =AB74 -> 5.473 | AD74: =AC74 -> 5.473 | AE74: =AD74 -> 5.473 | AI74: =+AJ74 -> #NAME? | AJ74: =+AK74 -> #NAME? | AK74: =+AL74 -> #NAME? | AL74: =+AM74 -> #NAME? | AM74: =+AN74 -> #NAME? | AN74: =+AO74 -> #NAME? | AO74: =+AP74 -> #NAME? | AP74: =+AQ74 -> #NAME? | ... CK74: =+CL74 -> #NAME? | CL74: ='QTR Raw'!BF45 -> #NAME? | CM74: =+CL74 -> #NAME? | CN74: =+CM74 -> #NAME? | CO74: =+CN74 -> #NAME? | CP74: =+CO74 -> #NAME? | CQ74: =+CP74 -> #NAME? | CR74: =+CQ74 -> #NAME? | CS74: =+CR74 -> #NAME? | CT74: =+CS74 -> #NAME? | ... DB74: =+DA74 -> #NAME? | DF74: 5.473
A75: FV | B75: ='Annual Raw'!C105 -> #NAME? | C75: ='Annual Raw'!D105 -> #NAME? | D75: ='Annual Raw'!E105 -> #NAME? | E75: =+F75 -> 10 | F75: =+G75 -> 10 | G75: =+H75 -> 10 | H75: =+I75 -> 10 | I75: =+J75 -> 10 | J75: =+K75 -> 10 | K75: =+L75 -> 10 | L75: =+M75 -> 10 | ... AA75: =+AB75 -> 10 | AB75: =AA75 -> 10 | AC75: =AB75 -> 10 | AD75: =AC75 -> 10 | AE75: =AD75 -> 10 | AI75: =AJ75 -> #NAME? | AJ75: =AK75 -> #NAME? | AK75: =AL75 -> #NAME? | AL75: =AM75 -> #NAME? | AM75: =AN75 -> #NAME? | AN75: =AO75 -> #NAME? | AO75: =AP75 -> #NAME? | AP75: =AQ75 -> #NAME? | ... CK75: =CL75 -> #NAME? | CL75: ='QTR Raw'!BF46 -> #NAME? | CM75: =+CL75 -> #NAME? | CN75: =+CM75 -> #NAME? | CO75: =+CN75 -> #NAME? | CP75: =+CO75 -> #NAME? | CQ75: =+CP75 -> #NAME? | CR75: =+CQ75 -> #NAME? | CS75: =+CR75 -> #NAME? | CT75: =+CS75 -> #NAME? | ... DB75: =+DA75 -> #NAME? | DF75: 10
A76: No of share | B76: =B74/B75 -> #NAME? | C76: =C74/C75 -> #NAME? | D76: =D74/D75 -> #NAME? | E76: =E74/E75 -> 0.5473 | F76: =F74/F75 -> 0.5473 | G76: =G74/G75 -> 0.5473 | H76: =H74/H75 -> 0.5473 | I76: =I74/I75 -> 0.5473 | ... AE76: =AE74/AE75 -> 0.5473 | AI76: =AI74/AI75 -> #NAME? | AJ76: =AJ74/AJ75 -> #NAME? | AK76: =AK74/AK75 -> #NAME? | AL76: =AL74/AL75 -> #NAME? | AM76: =AM74/AM75 -> #NAME? | AN76: =AN74/AN75 -> #NAME? | AO76: =AO74/AO75 -> #NAME? | AP76: =AP74/AP75 -> #NAME? | ... DB76: =DB74/DB75 -> #NAME? | DF76: 0.5473
A77: EPS | B77: =(B59-B58)/B76 -> #NAME? | C77: =(C59-C58)/C76 -> #NAME? | D77: =(D59-D58)/D76 -> #NAME? | E77: =(E59-E58)/E76 -> 0 | F77: =(F59-F58)/F76 -> 0 | G77: =(G59-G58)/G76 -> 0 | H77: =(H59-H58)/H76 -> 0 | I77: =(I59-I58)/I76 -> 0.15579993 | ... AE77: =(AE59-AE58)/AE76 -> 308.37772 | AI77: =(AI59-AI58)/AI76 -> #NAME? | AJ77: =(AJ59-AJ58)/AJ76 -> #NAME? | AK77: =(AK59-AK58)/AK76 -> #NAME? | AL77: =(AL59-AL58)/AL76 -> #NAME? | AM77: =(AM59-AM58)/AM76 -> #NAME? | AN77: =(AN59-AN58)/AN76 -> #NAME? | AO77: =(AO59-AO58)/AO76 -> #NAME? | AP77: =(AP59-AP58)/AP76 -> #NAME? | ... DB77: =(DB59-DB58)/DB76 -> #NAME? | DF77: 68.430477
A78: DPS | B78: ='Annual Raw'!C110 -> #NAME? | C78: ='Annual Raw'!D110 -> #NAME? | D78: ='Annual Raw'!E110 -> #NAME? | E78: ='Annual Raw'!F110 -> #NAME? | F78: ='Annual Raw'!G110 -> #NAME? | G78: ='Annual Raw'!H110 -> #NAME? | H78: ='Annual Raw'!I110 -> #NAME? | I78: ='Annual Raw'!J110 -> #NAME? | ... AA78: ='Annual Raw'!AB110 -> #NAME?
A79: DPS % of EPS | B79: =B78/B77 -> #NAME? | C79: =C78/C77 -> #NAME? | D79: =D78/D77 -> #NAME? | E79: =E78/E77 -> #DIV/0! | F79: =F78/F77 -> #DIV/0! | G79: =G78/G77 -> #DIV/0! | H79: =H78/H77 -> #DIV/0! | I79: =I78/I77 -> 0 | ... AE79: =AE78/AE77 -> 0 | DF79: 0
A80: EPS TTM | B80: =+B77 -> #NAME? | C80: =+C77 -> #NAME? | D80: =+D77 -> #NAME? | E80: =+E77 -> 0 | F80: =+F77 -> 0 | G80: =+G77 -> 0 | H80: =+H77 -> 0 | I80: =+I77 -> 0.15579993 | ... AE80: =+AE77 -> 308.37772 | AL80: =SUM(AI77:AL77) -> #NAME? | AM80: =SUM(AJ77:AM77) -> #NAME? | AN80: =SUM(AK77:AN77) -> #NAME? | AO80: =SUM(AL77:AO77) -> #NAME? | AP80: =SUM(AM77:AP77) -> #NAME? | AQ80: =SUM(AN77:AQ77) -> #NAME? | AR80: =SUM(AO77:AR77) -> #NAME? | AS80: =SUM(AP77:AS77) -> #NAME? | ... DB80: =SUM(CY77:DB77) -> #NAME? | DF80: 68.430477
A81: EPS Growth YoY % | C81: =+C80/B80-1 -> #NAME? | D81: =+D80/C80-1 -> #NAME? | E81: =+E80/D80-1 -> #DIV/0! | F81: =+F80/E80-1 -> #DIV/0! | G81: =+G80/F80-1 -> #DIV/0! | H81: =+H80/G80-1 -> #DIV/0! | I81: =+I80/H80-1 -> #DIV/0! | J81: =+J80/I80-1 -> -0.27327889 | ... AE81: =+AE80/AD80-1 -> 0.42250294 | AP81: =+IF(AL80<0,1-AP80/AL80,AP80/AL80-1) -> #NAME? | AQ81: =+IF(AM80<0,1-AQ80/AM80,AQ80/AM80-1) -> #NAME? | AR81: =+IF(AN80<0,1-AR80/AN80,AR80/AN80-1) -> #NAME? | AS81: =+IF(AO80<0,1-AS80/AO80,AS80/AO80-1) -> #NAME? | AT81: =+IF(AP80<0,1-AT80/AP80,AT80/AP80-1) -> #NAME? | AU81: =+IF(AQ80<0,1-AU80/AQ80,AU80/AQ80-1) -> #NAME? | AV81: =+IF(AR80<0,1-AV80/AR80,AV80/AR80-1) -> #NAME? | AW81: =+IF(AS80<0,1-AW80/AS80,AW80/AS80-1) -> #NAME? | ... DB81: =+IF(CX80<0,1-DB80/CX80,DB80/CX80-1) -> #NAME? | DF81: 0.89751436
A82: Bloomberg Estimate
A83: Estimate deviation | DB83: =+DB80/DB82-1 -> #NAME?
A84: Promoter Share holding % | B84: ='Annual Raw'!C112 -> #NAME? | C84: ='Annual Raw'!D112 -> #NAME? | D84: ='Annual Raw'!E112 -> #NAME? | E84: ='Annual Raw'!F112 -> #NAME? | F84: ='Annual Raw'!G112 -> #NAME? | G84: ='Annual Raw'!H112 -> #NAME? | H84: ='Annual Raw'!I112 -> #NAME? | I84: ='Annual Raw'!J112 -> #NAME? | ... AA84: ='Annual Raw'!AB112 -> #NAME? | AI84: ='QTR Raw'!C49 -> #NAME? | AJ84: ='QTR Raw'!D49 -> #NAME? | AK84: ='QTR Raw'!E49 -> #NAME? | AL84: ='QTR Raw'!F49 -> #NAME? | AM84: ='QTR Raw'!G49 -> #NAME? | AN84: ='QTR Raw'!H49 -> #NAME? | AO84: ='QTR Raw'!I49 -> #NAME? | AP84: ='QTR Raw'!J49 -> #NAME? | ... CL84: ='QTR Raw'!BF49 -> #NAME?
A85: Pledge Share % | B85: ='Annual Raw'!C113 -> #NAME? | C85: ='Annual Raw'!D113 -> #NAME? | D85: ='Annual Raw'!E113 -> #NAME? | E85: ='Annual Raw'!F113 -> #NAME? | F85: ='Annual Raw'!G113 -> #NAME? | G85: ='Annual Raw'!H113 -> #NAME? | H85: ='Annual Raw'!I113 -> #NAME? | I85: ='Annual Raw'!J113 -> #NAME? | ... AA85: ='Annual Raw'!AB113 -> #NAME? | AI85: ='QTR Raw'!C50 -> #NAME? | AJ85: ='QTR Raw'!D50 -> #NAME? | AK85: ='QTR Raw'!E50 -> #NAME? | AL85: ='QTR Raw'!F50 -> #NAME? | AM85: ='QTR Raw'!G50 -> #NAME? | AN85: ='QTR Raw'!H50 -> #NAME? | AO85: ='QTR Raw'!I50 -> #NAME? | AP85: ='QTR Raw'!J50 -> #NAME? | ... CL85: ='QTR Raw'!BF50 -> #NAME?
A87: Share Price
A88: Share Price - Close | B88: ='Annual Raw'!C106 -> #NAME? | C88: ='Annual Raw'!D106 -> #NAME? | D88: ='Annual Raw'!E106 -> #NAME? | E88: ='Annual Raw'!F106 -> #NAME? | F88: ='Annual Raw'!G106 -> #NAME? | G88: ='Annual Raw'!H106 -> #NAME? | H88: ='Annual Raw'!I106 -> #NAME? | I88: ='Annual Raw'!J106 -> #NAME? | ... AA88: ='Annual Raw'!AB106 -> #NAME? | AB88: =+CP88 -> 2384 | AC88: =+CT88 -> 2384 | AD88: =+CX88 -> 2384 | AE88: =+DB88 -> 2384 | AJ88: ='QTR Share Price'!HP21 -> #NAME? | AK88: ='QTR Share Price'!HQ21 -> #NAME? | AL88: ='QTR Share Price'!HR21 -> #NAME? | AM88: ='QTR Share Price'!HS21 -> #NAME? | AN88: ='QTR Share Price'!HT21 -> #NAME? | AO88: ='QTR Share Price'!HU21 -> #NAME? | AP88: ='QTR Share Price'!HV21 -> #NAME? | AQ88: ='QTR Share Price'!HW21 -> #NAME? | ... CL88: ='QTR Share Price'!JR21 -> #NAME? | CM88: 2384 | CN88: =+CM88 -> 2384 | CO88: =+CN88 -> 2384 | CP88: =+CO88 -> 2384 | CQ88: =+CP88 -> 2384 | CR88: =+CQ88 -> 2384 | CS88: =+CR88 -> 2384 | CT88: =+CS88 -> 2384 | CU88: =+CT88 -> 2384 | ... DB88: =+DA88 -> 2384 | DF88: 1671.8
A89: Share Price - High | B89: ='Annual Raw'!C107 -> #NAME? | C89: ='Annual Raw'!D107 -> #NAME? | D89: ='Annual Raw'!E107 -> #NAME? | E89: ='Annual Raw'!F107 -> #NAME? | F89: ='Annual Raw'!G107 -> #NAME? | G89: ='Annual Raw'!H107 -> #NAME? | H89: ='Annual Raw'!I107 -> #NAME? | I89: ='Annual Raw'!J107 -> #NAME? | ... AA89: ='Annual Raw'!AB107 -> #NAME? | AB89: =+MAX(CM89:CP89) -> #NAME? | AC89: =+MAX(CQ89:CT89) -> #NAME? | AD89: =+MAX(CU89:CX89) -> #NAME? | AE89: =+MAX(CY89:DB89) -> #NAME? | AJ89: ='QTR Share Price'!HP19 -> #NAME? | AK89: ='QTR Share Price'!HQ19 -> #NAME? | AL89: ='QTR Share Price'!HR19 -> #NAME? | AM89: ='QTR Share Price'!HS19 -> #NAME? | AN89: ='QTR Share Price'!HT19 -> #NAME? | AO89: ='QTR Share Price'!HU19 -> #NAME? | AP89: ='QTR Share Price'!HV19 -> #NAME? | AQ89: ='QTR Share Price'!HW19 -> #NAME? | ... CL89: ='QTR Share Price'!JR19 -> #NAME? | CM89: =+CM80*CM97 -> #NAME? | CN89: =+CN80*CN97 -> #NAME? | CO89: =+CO80*CO97 -> #NAME? | CP89: =+CP80*CP97 -> #NAME? | CQ89: =+CQ80*CQ97 -> #NAME? | CR89: =+CR80*CR97 -> #NAME? | CS89: =+CS80*CS97 -> #NAME? | CT89: =+CT80*CT97 -> #NAME? | ... DB89: =+DB80*DB97 -> #NAME? | DF89: 1999
A90: Share Price - Low | B90: ='Annual Raw'!C108 -> #NAME? | C90: ='Annual Raw'!D108 -> #NAME? | D90: ='Annual Raw'!E108 -> #NAME? | E90: ='Annual Raw'!F108 -> #NAME? | F90: ='Annual Raw'!G108 -> #NAME? | G90: ='Annual Raw'!H108 -> #NAME? | H90: ='Annual Raw'!I108 -> #NAME? | I90: ='Annual Raw'!J108 -> #NAME? | ... AA90: ='Annual Raw'!AB108 -> #NAME? | AB90: =+MIN(CM90:CP90) -> #NAME? | AC90: =+MIN(CQ90:CT90) -> #NAME? | AD90: =+MIN(CU90:CX90) -> #NAME? | AE90: =+MIN(CY90:DB90) -> #NAME? | AJ90: =+'QTR Share Price'!HP20 -> #NAME? | AK90: =+'QTR Share Price'!HQ20 -> #NAME? | AL90: =+'QTR Share Price'!HR20 -> #NAME? | AM90: =+'QTR Share Price'!HS20 -> #NAME? | AN90: =+'QTR Share Price'!HT20 -> #NAME? | AO90: =+'QTR Share Price'!HU20 -> #NAME? | AP90: =+'QTR Share Price'!HV20 -> #NAME? | AQ90: =+'QTR Share Price'!HW20 -> #NAME? | ... CL90: =+'QTR Share Price'!JR20 -> #NAME? | CM90: =+CM98*CM80 -> #NAME? | CN90: =+CN98*CN80 -> #NAME? | CO90: =+CO98*CO80 -> #NAME? | CP90: =+CP98*CP80 -> #NAME? | CQ90: =+CQ98*CQ80 -> #NAME? | CR90: =+CR98*CR80 -> #NAME? | CS90: =+CS98*CS80 -> #NAME? | CT90: =+CT98*CT80 -> #NAME? | ... DB90: =+DB98*DB80 -> #NAME? | DF90: 635.05
A92: Upside (%) | AB92: =+AB89/AB88-1 -> #NAME? | AC92: =+AC89/AC88-1 -> #NAME? | AD92: =+AD89/AD88-1 -> #NAME? | AE92: =+AE89/AE88-1 -> #NAME? | CM92: =+CM89/CM88-1 -> #NAME? | CN92: =+CN89/CN88-1 -> #NAME? | CO92: =+CO89/CO88-1 -> #NAME? | CP92: =+CP89/CP88-1 -> #NAME? | CQ92: =+CQ89/CQ88-1 -> #NAME? | CR92: =+CR89/CR88-1 -> #NAME? | CS92: =+CS89/CS88-1 -> #NAME? | CT92: =+CT89/CT88-1 -> #NAME? | ... DB92: =+DB89/DB88-1 -> #NAME? | DF92: 0.19571719
A93: Downside (%) | AB93: =+AB90/AB88-1 -> #NAME? | AC93: =+AC90/AC88-1 -> #NAME? | AD93: =+AD90/AD88-1 -> #NAME? | AE93: =+AE90/AE88-1 -> #NAME? | CM93: =+CM90/CM88-1 -> #NAME? | CN93: =+CN90/CN88-1 -> #NAME? | CO93: =+CO90/CO88-1 -> #NAME? | CP93: =+CP90/CP88-1 -> #NAME? | CQ93: =+CQ90/CQ88-1 -> #NAME? | CR93: =+CR90/CR88-1 -> #NAME? | CS93: =+CS90/CS88-1 -> #NAME? | CT93: =+CT90/CT88-1 -> #NAME? | ... DB93: =+DB90/DB88-1 -> #NAME? | DF93: -0.62013997
A95: PE
A96: PE - Close | B96: =+B88/B80 -> #NAME? | C96: =+C88/C80 -> #NAME? | D96: =+D88/D80 -> #NAME? | E96: =+E88/E80 -> #DIV/0! | F96: =+F88/F80 -> #DIV/0! | G96: =+G88/G80 -> #DIV/0! | H96: =+H88/H80 -> #DIV/0! | I96: =+I88/I80 -> 0 | ... AE96: =+AE88/AE80 -> 7.7307791 | AL96: =+AL88/AL80 -> #NAME? | AM96: =+AM88/AM80 -> #NAME? | AN96: =+AN88/AN80 -> #NAME? | AO96: =+AO88/AO80 -> #NAME? | AP96: =+AP88/AP80 -> #NAME? | AQ96: =+AQ88/AQ80 -> #NAME? | AR96: =+AR88/AR80 -> #NAME? | AS96: =+AS88/AS80 -> #NAME? | ... DB96: =+DB88/DB80 -> #NAME? | DF96: 24.430635
A97: PE - High | B97: =+B89/B80 -> #NAME? | C97: =+C89/C80 -> #NAME? | D97: =+D89/D80 -> #NAME? | E97: =+E89/E80 -> #DIV/0! | F97: =+F89/F80 -> #DIV/0! | G97: =+G89/G80 -> #DIV/0! | H97: =+H89/H80 -> #DIV/0! | I97: =+I89/I80 -> 0 | ... AE97: =+AE89/AE80 -> 40 | AL97: =+AL89/AL80 -> #NAME? | AM97: =+AM89/AM80 -> #NAME? | AN97: =+AN89/AN80 -> #NAME? | AO97: =+AO89/AO80 -> #NAME? | AP97: =+AP89/AP80 -> #NAME? | AQ97: =+AQ89/AQ80 -> #NAME? | AR97: =+AR89/AR80 -> #NAME? | AS97: =+AS89/AS80 -> #NAME? | ... CL97: =+CL89/CL80 -> #NAME? | CM97: 40 | CN97: =+CM97 -> 40 | CO97: =+CN97 -> 40 | CP97: =+CO97 -> 40 | CQ97: =+CP97 -> 40 | CR97: =+CQ97 -> 40 | CS97: =+CR97 -> 40 | CT97: =+CS97 -> 40 | CU97: =+CT97 -> 40 | ... DB97: =+DA97 -> 40 | DF97: 29.21213
A98: PE - Low | B98: =+B90/B80 -> #NAME? | C98: =+C90/C80 -> #NAME? | D98: =+D90/D80 -> #NAME? | E98: =+E90/E80 -> #DIV/0! | F98: =+F90/F80 -> #DIV/0! | G98: =+G90/G80 -> #DIV/0! | H98: =+H90/H80 -> #DIV/0! | I98: =+I90/I80 -> 0 | ... AE98: =+AE90/AE80 -> 19.153379 | AL98: =+AL90/AL80 -> #NAME? | AM98: =+AM90/AM80 -> #NAME? | AN98: =+AN90/AN80 -> #NAME? | AO98: =+AO90/AO80 -> #NAME? | AP98: =+AP90/AP80 -> #NAME? | AQ98: =+AQ90/AQ80 -> #NAME? | AR98: =+AR90/AR80 -> #NAME? | AS98: =+AS90/AS80 -> #NAME? | ... CL98: =+CL90/CL80 -> #NAME? | CM98: 26 | CN98: =+CM98 -> 26 | CO98: =+CN98 -> 26 | CP98: =+CO98 -> 26 | CQ98: =+CP98 -> 26 | CR98: =+CQ98 -> 26 | CS98: =+CR98 -> 26 | CT98: =+CS98 -> 26 | CU98: =+CT98 -> 26 | ... DB98: =+DA98 -> 26 | DF98: 9.2802218
A100: PE - 1Yr Fwd | B100: =+B89/C80 -> #NAME? | C100: =+C89/D80 -> #NAME? | D100: =+D89/E80 -> #DIV/0! | E100: =+E89/F80 -> #DIV/0! | F100: =+F89/G80 -> #DIV/0! | G100: =+G89/H80 -> #DIV/0! | H100: =+H89/I80 -> 0 | I100: =+I89/J80 -> 0 | ... AD100: =+AD89/AE80 -> 28.11945 | AL100: =+AL89/AP80 -> #NAME? | AM100: =+AM89/AQ80 -> #NAME? | AN100: =+AN89/AR80 -> #NAME? | AO100: =+AO89/AS80 -> #NAME? | AP100: =+AP89/AT80 -> #NAME? | AQ100: =+AQ89/AU80 -> #NAME? | AR100: =+AR89/AV80 -> #NAME? | AS100: =+AS89/AW80 -> #NAME? | ... CL100: =+CL89/CP80 -> #NAME? | DF100: 18.642369
A101: Correlation | AO101: =+CORREL(AL80:AO80,AL97:AO97) -> #NAME? | AP101: =+CORREL(AM80:AP80,AM97:AP97) -> #NAME? | AQ101: =+CORREL(AN80:AQ80,AN97:AQ97) -> #NAME? | AR101: =+CORREL(AO80:AR80,AO97:AR97) -> #NAME? | AS101: =+CORREL(AP80:AS80,AP97:AS97) -> #NAME? | AT101: =+CORREL(AQ80:AT80,AQ97:AT97) -> #NAME? | AU101: =+CORREL(AR80:AU80,AR97:AU97) -> #NAME? | AV101: =+CORREL(AS80:AV80,AS97:AV97) -> #NAME? | ... CL101: =+CORREL(CI80:CL80,CI97:CL97) -> #NAME?
A103: BVPS | E103: =+E$131/E$76 -> 0 | F103: =+F$131/F$76 -> 0 | G103: =+G$131/G$76 -> 0 | H103: =+H$131/H$76 -> 0 | I103: =+I$131/I$76 -> 5.7395591 | J103: =+J$131/J$76 -> 5.6258885 | K103: =+K$131/K$76 -> 5.5525343 | L103: =+L$131/L$76 -> 5.3686757 | ... AE103: =+AE$131/AE$76 -> 1292.7633 | AL103: =+AL$131/AL$76 -> #NAME? | AM103: =+AM$131/AM$76 -> #NAME? | AN103: =+AN$131/AN$76 -> #NAME? | AO103: =+AO$131/AO$76 -> #NAME? | AP103: =+AP$131/AP$76 -> #NAME? | AQ103: =+AQ$131/AQ$76 -> #NAME? | AR103: =+AR$131/AR$76 -> #NAME? | AS103: =+AS$131/AS$76 -> #NAME? | ... DB103: =+DB$131/DB$76 -> #NAME? | DF103: 508.14544
A104: PB
A105: PB - Close | E105: =+E88/E$103 -> #DIV/0! | F105: =+F88/F$103 -> #DIV/0! | G105: =+G88/G$103 -> #DIV/0! | H105: =+H88/H$103 -> #DIV/0! | I105: =+I88/I$103 -> 0 | J105: =+J88/J$103 -> 0 | K105: =+K88/K$103 -> 0 | L105: =+L88/L$103 -> 0 | ... AE105: =+AE88/AE$103 -> 1.8441118 | AL105: =+AL88/AL$103 -> #NAME? | AM105: =+AM88/AM$103 -> #NAME? | AN105: =+AN88/AN$103 -> #NAME? | AO105: =+AO88/AO$103 -> #NAME? | AP105: =+AP88/AP$103 -> #NAME? | AQ105: =+AQ88/AQ$103 -> #NAME? | AR105: =+AR88/AR$103 -> #NAME? | AS105: =+AS88/AS$103 -> #NAME? | ... DB105: =+DB88/DB$103 -> #NAME? | DF105: 3.2900029
A106: PB - High | E106: =+E89/E$103 -> #DIV/0! | F106: =+F89/F$103 -> #DIV/0! | G106: =+G89/G$103 -> #DIV/0! | H106: =+H89/H$103 -> #DIV/0! | I106: =+I89/I$103 -> 0 | J106: =+J89/J$103 -> 0 | K106: =+K89/K$103 -> 0 | L106: =+L89/L$103 -> 0 | ... AE106: =+AE89/AE$103 -> 9.5416609 | AL106: =+AL89/AL$103 -> #NAME? | AM106: =+AM89/AM$103 -> #NAME? | AN106: =+AN89/AN$103 -> #NAME? | AO106: =+AO89/AO$103 -> #NAME? | AP106: =+AP89/AP$103 -> #NAME? | AQ106: =+AQ89/AQ$103 -> #NAME? | AR106: =+AR89/AR$103 -> #NAME? | AS106: =+AS89/AS$103 -> #NAME? | ... CL106: =+CL89/CL$103 -> #NAME? | CM106: =+CL106 -> #NAME? | CN106: =+CM106 -> #NAME? | CO106: =+CN106 -> #NAME? | CP106: =+CO106 -> #NAME? | CQ106: =+CP106 -> #NAME? | CR106: =+CQ106 -> #NAME? | CS106: =+CR106 -> #NAME? | CT106: =+CS106 -> #NAME? | ... DB106: =+DA106 -> #NAME? | DF106: 3.9339131
A107: PB - Low | E107: =+E90/E$103 -> #DIV/0! | F107: =+F90/F$103 -> #DIV/0! | G107: =+G90/G$103 -> #DIV/0! | H107: =+H90/H$103 -> #DIV/0! | I107: =+I90/I$103 -> 0 | J107: =+J90/J$103 -> 0 | K107: =+K90/K$103 -> 0 | L107: =+L90/L$103 -> 0 | ... AE107: =+AE90/AE$103 -> 4.5688761 | AL107: =+AL90/AL$103 -> #NAME? | AM107: =+AM90/AM$103 -> #NAME? | AN107: =+AN90/AN$103 -> #NAME? | AO107: =+AO90/AO$103 -> #NAME? | AP107: =+AP90/AP$103 -> #NAME? | AQ107: =+AQ90/AQ$103 -> #NAME? | AR107: =+AR90/AR$103 -> #NAME? | AS107: =+AS90/AS$103 -> #NAME? | ... CL107: =+CL90/CL$103 -> #NAME? | CM107: =+CL107 -> #NAME? | CN107: =+CM107 -> #NAME? | CO107: =+CN107 -> #NAME? | CP107: =+CO107 -> #NAME? | CQ107: =+CP107 -> #NAME? | CR107: =+CQ107 -> #NAME? | CS107: =+CR107 -> #NAME? | CT107: =+CS107 -> #NAME? | ... DB107: =+DA107 -> #NAME? | DF107: 1.2497406
A109: Sales Rolling | E109: =+E21 -> #NAME? | F109: =+F21 -> #NAME? | G109: =+G21 -> #NAME? | H109: =+H21 -> #NAME? | I109: =+I21 -> #NAME? | J109: =+J21 -> #NAME? | K109: =+K21 -> #NAME? | L109: =+L21 -> #NAME? | ... AE109: =+AE21 -> 1987.8161 | AL109: =+SUM(AI19:AL19) -> #NAME? | AM109: =+SUM(AJ19:AM19) -> #NAME? | AN109: =+SUM(AK19:AN19) -> #NAME? | AO109: =+SUM(AL19:AO19) -> #NAME? | AP109: =+SUM(AM19:AP19) -> #NAME? | AQ109: =+SUM(AN19:AQ19) -> #NAME? | AR109: =+SUM(AO19:AR19) -> #NAME? | AS109: =+SUM(AP19:AS19) -> #NAME? | ... DB109: =+SUM(CY19:DB19) -> 1987.8161 | DF109: 639.124
A110: Sales Per Share | E110: =+E109/E76 -> 0 | F110: =+F109/F76 -> 0 | G110: =+G109/G76 -> 0 | H110: =+H109/H76 -> 0 | I110: =+I109/I76 -> 8.5016512 | J110: =+J109/J76 -> 7.2757312 | K110: =+K109/K76 -> 8.3945251 | L110: =+L109/L76 -> 14.560441 | ... AE110: =+AE109/AE76 -> 3632.0412 | AL110: =+AL109/AL76 -> #NAME? | AM110: =+AM109/AM76 -> #NAME? | AN110: =+AN109/AN76 -> #NAME? | AO110: =+AO109/AO76 -> #NAME? | AP110: =+AP109/AP76 -> #NAME? | AQ110: =+AQ109/AQ76 -> #NAME? | AR110: =+AR109/AR76 -> #NAME? | AS110: =+AS109/AS76 -> #NAME? | ... DB110: =+DB109/DB76 -> #NAME? | DF110: 1167.7764
...

Sheet Sheet1
B1: Quarter | C1: Total Sales | D1: Direct Exports (Branded) | E1: Institutional Sales | F1: Third-Party & Tolling | G1: New Age (Pet/Nutra)
A2: =A1+1 -> 1 | B2: Q1 FY23 | C2: 47.5 | D2: 4.28 | E2: 0.95 | F2: 38.95 | G2: 3.33
A3: =A2+1 -> 2 | B3: Q2 FY23 | C3: 68.84 | D3: 7.57 | E3: 2.07 | F3: 53.01 | G3: 6.19 | J3: Quarter | K3: Q1 FY23 | L3: Q2 FY23 | M3: Q3 FY23 | N3: Q4 FY23 | O3: Q1 FY24 | P3: Q2 FY24 | Q3: Q3 FY24 | R3: Q4 FY24 | S3: Q1 FY25 | T3: Q2 FY25 | U3: Q3 FY25 | V3: Q4 FY25
A4: =A3+1 -> 3 | B4: Q3 FY23 | C4: 77.65 | D4: 9.32 | E4: 3.11 | F4: 56.68 | G4: 8.54 | J4: Total Sales | K4: 47.5 | L4: 68.84 | M4: 77.65 | N4: 79.8 | O4: 64.2 | P4: 78.7 | Q4: 87.2 | R4: 118 | S4: 79.12 | T4: 106.65 | U4: 102.9 | V4: 167.41
A5: =A4+1 -> 4 | B5: Q4 FY23 | C5: 79.8 | D5: 10.37 | E5: 3.99 | F5: 53.47 | G5: 11.97 | J5: Direct Exports (Branded) | K5: 4.28 | L5: 7.57 | M5: 9.32 | N5: 10.37 | O5: 9.63 | P5: 12.59 | Q5: 14.82 | R5: 22.42 | S5: 16.62 | T5: 24.53 | U5: 25.73 | V5: 41.85
A6: =A5+1 -> 5 | B6: Q1 FY24 | C6: 64.2 | D6: 9.63 | E6: 4.49 | F6: 39.16 | G6: 10.91 | J6: Institutional Sales | K6: 0.95 | L6: 2.07 | M6: 3.11 | N6: 3.99 | O6: 4.49 | P6: 5.51 | Q6: 6.1 | R6: 7.08 | S6: 6.33 | T6: 9.6 | U6: 10.29 | V6: 16.74
A7: =A6+1 -> 6 | B7: Q2 FY24 | C7: 78.7 | D7: 12.59 | E7: 5.51 | F7: 46.43 | G7: 14.17 | J7: Third-Party & Tolling | K7: 38.95 | L7: 53.01 | M7: 56.68 | N7: 53.47 | O7: 39.16 | P7: 46.43 | Q7: 48.83 | R7: 62.54 | S7: 36.39 | T7: 44.79 | U7: 36.02 | V7: 58.59
A8: =A7+1 -> 7 | B8: Q3 FY24 | C8: 87.2 | D8: 14.82 | E8: 6.1 | F8: 48.83 | G8: 17.44 | J8: New Age (Pet/Nutra) | K8: 3.33 | L8: 6.19 | M8: 8.54 | N8: 11.97 | O8: 10.91 | P8: 14.17 | Q8: 17.44 | R8: 25.96 | S8: 19.78 | T8: 27.73 | U8: 30.87 | V8: 50.22
A9: =A8+1 -> 8 | B9: Q4 FY24 | C9: 118 | D9: 22.42 | E9: 7.08 | F9: 62.54 | G9: 25.96
A10: =A9+1 -> 9 | B10: Q1 FY25 | C10: 79.12 | D10: 16.62 | E10: 6.33 | F10: 36.39 | G10: 19.78
A11: =A10+1 -> 10 | B11: Q2 FY25 | C11: 106.65 | D11: 24.53 | E11: 9.6 | F11: 44.79 | G11: 27.73
A12: =A11+1 -> 11 | B12: Q3 FY25 | C12: 102.9 | D12: 25.73 | E12: 10.29 | F12: 36.02 | G12: 30.87
A13: 1 | B13: Q4 FY25 | C13: 167.41 | D13: 41.85 | E13: 16.74 | F13: 58.59 | G13: 50.22

Sheet QTR Raw
A1: ='Annual Raw'!A1 -> 219412 | B1: X | C1: 201206 | D1: 201209 | E1: 201212 | F1: 201303 | G1: 201306 | H1: 201309 | I1: 201312 | J1: 201403 | K1: 201406 | L1: 201409 | M1: 201412 | N1: 201503 | O1: 201506 | P1: 201509 | Q1: 201512 | R1: 201603 | S1: 201606 | T1: 201609 | U1: 201612 | V1: 201703 | W1: 201706 | X1: 201709 | Y1: 201712 | Z1: 201803 | AA1: 201806 | AB1: 201809 | AC1: 201812 | AD1: 201903 | AE1: 201906 | AF1: 201909 | AG1: 201912 | AH1: 202003 | AI1: 202006 | AJ1: 202009 | AK1: 202012 | AL1: 202103 | AM1: 202106 | AN1: 202109 | AO1: 202112 | AP1: 202203 | AQ1: 202206 | AR1: 202209 | AS1: 202212 | AT1: 202303 | AU1: 202306 | AV1: 202309 | AW1: 202312 | AX1: 202403 | AY1: 202406 | AZ1: 202409 | BA1: 202412 | BB1: 202503 | BC1: 202506 | BD1: 202509 | BE1: 202512 | BF1: 202603 | BG1: 202606 | BH1: 202609 | BI1: 202612 | BJ1: 202703 | BK1: 202706 | BL1: 202709 | BM1: 202712 | BN1: 202803 | BO1: 202806 | BP1: 202809 | BQ1: 202812 | BR1: 202903 | BS1: 202906 | BT1: 202909 | BU1: 202912 | BV1: 203003
A3: Field Description | B3: Field Name
A4: Company Name | B4: CD_COMPNAME | C4: =_xll.EQNXTDZ(A1,B4,C1) -> #NAME?
A5: Date End | B5: QTR_DATE_END | C5: =_xll.EQNXTDZ($A$1,$B5,C$1,$B$1) -> #NAME? | D5: =_xll.EQNXTDZ($A$1,$B5,D$1,$B$1) -> #NAME? | E5: =_xll.EQNXTDZ($A$1,$B5,E$1,$B$1) -> #NAME? | F5: =_xll.EQNXTDZ($A$1,$B5,F$1,$B$1) -> #NAME? | G5: =_xll.EQNXTDZ($A$1,$B5,G$1,$B$1) -> #NAME? | H5: =_xll.EQNXTDZ($A$1,$B5,H$1,$B$1) -> #NAME? | I5: =_xll.EQNXTDZ($A$1,$B5,I$1,$B$1) -> #NAME? | J5: =_xll.EQNXTDZ($A$1,$B5,J$1,$B$1) -> #NAME? | ... BV5: =_xll.EQNXTDZ($A$1,$B5,BV$1,$B$1) -> #NAME?
A6: Gross Sales | B6: QTR_GROSS_SALE | C6: =_xll.EQNXTDZ($A$1,$B6,C$1,$B$1) -> #NAME? | D6: =_xll.EQNXTDZ($A$1,$B6,D$1,$B$1) -> #NAME? | E6: =_xll.EQNXTDZ($A$1,$B6,E$1,$B$1) -> #NAME? | F6: =_xll.EQNXTDZ($A$1,$B6,F$1,$B$1) -> #NAME? | G6: =_xll.EQNXTDZ($A$1,$B6,G$1,$B$1) -> #NAME? | H6: =_xll.EQNXTDZ($A$1,$B6,H$1,$B$1) -> #NAME? | I6: =_xll.EQNXTDZ($A$1,$B6,I$1,$B$1) -> #NAME? | J6: =_xll.EQNXTDZ($A$1,$B6,J$1,$B$1) -> #NAME? | ... BV6: =_xll.EQNXTDZ($A$1,$B6,BV$1,$B$1) -> #NAME?
A7: Less: Excise Duty | B7: QTR_EXCISE_DUTY | C7: =_xll.EQNXTDZ($A$1,$B7,C$1,$B$1) -> #NAME? | D7: =_xll.EQNXTDZ($A$1,$B7,D$1,$B$1) -> #NAME? | E7: =_xll.EQNXTDZ($A$1,$B7,E$1,$B$1) -> #NAME? | F7: =_xll.EQNXTDZ($A$1,$B7,F$1,$B$1) -> #NAME? | G7: =_xll.EQNXTDZ($A$1,$B7,G$1,$B$1) -> #NAME? | H7: =_xll.EQNXTDZ($A$1,$B7,H$1,$B$1) -> #NAME? | I7: =_xll.EQNXTDZ($A$1,$B7,I$1,$B$1) -> #NAME? | J7: =_xll.EQNXTDZ($A$1,$B7,J$1,$B$1) -> #NAME? | ... BV7: =_xll.EQNXTDZ($A$1,$B7,BV$1,$B$1) -> #NAME?
A8: Other operating income | B8: QTR_JOB_WORKS | C8: =_xll.EQNXTDZ($A$1,$B8,C$1,$B$1) -> #NAME? | D8: =_xll.EQNXTDZ($A$1,$B8,D$1,$B$1) -> #NAME? | E8: =_xll.EQNXTDZ($A$1,$B8,E$1,$B$1) -> #NAME? | F8: =_xll.EQNXTDZ($A$1,$B8,F$1,$B$1) -> #NAME? | G8: =_xll.EQNXTDZ($A$1,$B8,G$1,$B$1) -> #NAME? | H8: =_xll.EQNXTDZ($A$1,$B8,H$1,$B$1) -> #NAME? | I8: =_xll.EQNXTDZ($A$1,$B8,I$1,$B$1) -> #NAME? | J8: =_xll.EQNXTDZ($A$1,$B8,J$1,$B$1) -> #NAME? | ... BV8: =_xll.EQNXTDZ($A$1,$B8,BV$1,$B$1) -> #NAME?
A9: Net Sales & Other Operating Income | B9: QTR_NET_SALES | C9: =_xll.EQNXTDZ($A$1,$B9,C$1,$B$1) -> #NAME? | D9: =_xll.EQNXTDZ($A$1,$B9,D$1,$B$1) -> #NAME? | E9: =_xll.EQNXTDZ($A$1,$B9,E$1,$B$1) -> #NAME? | F9: =_xll.EQNXTDZ($A$1,$B9,F$1,$B$1) -> #NAME? | G9: =_xll.EQNXTDZ($A$1,$B9,G$1,$B$1) -> #NAME? | H9: =_xll.EQNXTDZ($A$1,$B9,H$1,$B$1) -> #NAME? | I9: =_xll.EQNXTDZ($A$1,$B9,I$1,$B$1) -> #NAME? | J9: =_xll.EQNXTDZ($A$1,$B9,J$1,$B$1) -> #NAME? | ... BV9: =_xll.EQNXTDZ($A$1,$B9,BV$1,$B$1) -> #NAME?
A10: (Increase) / Decrease In Stocks | B10: QTR_INC_DEC_INVENTORY | C10: =_xll.EQNXTDZ($A$1,$B10,C$1,$B$1) -> #NAME? | D10: =_xll.EQNXTDZ($A$1,$B10,D$1,$B$1) -> #NAME? | E10: =_xll.EQNXTDZ($A$1,$B10,E$1,$B$1) -> #NAME? | F10: =_xll.EQNXTDZ($A$1,$B10,F$1,$B$1) -> #NAME? | G10: =_xll.EQNXTDZ($A$1,$B10,G$1,$B$1) -> #NAME? | H10: =_xll.EQNXTDZ($A$1,$B10,H$1,$B$1) -> #NAME? | I10: =_xll.EQNXTDZ($A$1,$B10,I$1,$B$1) -> #NAME? | J10: =_xll.EQNXTDZ($A$1,$B10,J$1,$B$1) -> #NAME? | ... BV10: =_xll.EQNXTDZ($A$1,$B10,BV$1,$B$1) -> #NAME?
A11: Cost of Services & Raw Materials | B11: QTR_RAW_MATERIAL_COST | C11: =_xll.EQNXTDZ($A$1,$B11,C$1,$B$1) -> #NAME? | D11: =_xll.EQNXTDZ($A$1,$B11,D$1,$B$1) -> #NAME? | E11: =_xll.EQNXTDZ($A$1,$B11,E$1,$B$1) -> #NAME? | F11: =_xll.EQNXTDZ($A$1,$B11,F$1,$B$1) -> #NAME? | G11: =_xll.EQNXTDZ($A$1,$B11,G$1,$B$1) -> #NAME? | H11: =_xll.EQNXTDZ($A$1,$B11,H$1,$B$1) -> #NAME? | I11: =_xll.EQNXTDZ($A$1,$B11,I$1,$B$1) -> #NAME? | J11: =_xll.EQNXTDZ($A$1,$B11,J$1,$B$1) -> #NAME? | ... BV11: =_xll.EQNXTDZ($A$1,$B11,BV$1,$B$1) -> #NAME?
A12: Purchase of Finished Goods | B12: QTR_PURCHASE_FIN_GOOD | C12: =_xll.EQNXTDZ($A$1,$B12,C$1,$B$1) -> #NAME? | D12: =_xll.EQNXTDZ($A$1,$B12,D$1,$B$1) -> #NAME? | E12: =_xll.EQNXTDZ($A$1,$B12,E$1,$B$1) -> #NAME? | F12: =_xll.EQNXTDZ($A$1,$B12,F$1,$B$1) -> #NAME? | G12: =_xll.EQNXTDZ($A$1,$B12,G$1,$B$1) -> #NAME? | H12: =_xll.EQNXTDZ($A$1,$B12,H$1,$B$1) -> #NAME? | I12: =_xll.EQNXTDZ($A$1,$B12,I$1,$B$1) -> #NAME? | J12: =_xll.EQNXTDZ($A$1,$B12,J$1,$B$1) -> #NAME? | ... BV12: =_xll.EQNXTDZ($A$1,$B12,BV$1,$B$1) -> #NAME?
A13: Excise Duty | B13: QTR_EXCISE | C13: =_xll.EQNXTDZ($A$1,$B13,C$1,$B$1) -> #NAME? | D13: =_xll.EQNXTDZ($A$1,$B13,D$1,$B$1) -> #NAME? | E13: =_xll.EQNXTDZ($A$1,$B13,E$1,$B$1) -> #NAME? | F13: =_xll.EQNXTDZ($A$1,$B13,F$1,$B$1) -> #NAME? | G13: =_xll.EQNXTDZ($A$1,$B13,G$1,$B$1) -> #NAME? | H13: =_xll.EQNXTDZ($A$1,$B13,H$1,$B$1) -> #NAME? | I13: =_xll.EQNXTDZ($A$1,$B13,I$1,$B$1) -> #NAME? | J13: =_xll.EQNXTDZ($A$1,$B13,J$1,$B$1) -> #NAME? | ... BV13: =_xll.EQNXTDZ($A$1,$B13,BV$1,$B$1) -> #NAME?
A14: Operating & Manufacturing Expenses | B14: QTR_MFG_EXPS | C14: =_xll.EQNXTDZ($A$1,$B14,C$1,$B$1) -> #NAME? | D14: =_xll.EQNXTDZ($A$1,$B14,D$1,$B$1) -> #NAME? | E14: =_xll.EQNXTDZ($A$1,$B14,E$1,$B$1) -> #NAME? | F14: =_xll.EQNXTDZ($A$1,$B14,F$1,$B$1) -> #NAME? | G14: =_xll.EQNXTDZ($A$1,$B14,G$1,$B$1) -> #NAME? | H14: =_xll.EQNXTDZ($A$1,$B14,H$1,$B$1) -> #NAME? | I14: =_xll.EQNXTDZ($A$1,$B14,I$1,$B$1) -> #NAME? | J14: =_xll.EQNXTDZ($A$1,$B14,J$1,$B$1) -> #NAME? | ... BV14: =_xll.EQNXTDZ($A$1,$B14,BV$1,$B$1) -> #NAME?
A15: Electricity Power & Fuel Cost | B15: QTR_ELECTRICITY_POWER_FUEL | C15: =_xll.EQNXTDZ($A$1,$B15,C$1,$B$1) -> #NAME? | D15: =_xll.EQNXTDZ($A$1,$B15,D$1,$B$1) -> #NAME? | E15: =_xll.EQNXTDZ($A$1,$B15,E$1,$B$1) -> #NAME? | F15: =_xll.EQNXTDZ($A$1,$B15,F$1,$B$1) -> #NAME? | G15: =_xll.EQNXTDZ($A$1,$B15,G$1,$B$1) -> #NAME? | H15: =_xll.EQNXTDZ($A$1,$B15,H$1,$B$1) -> #NAME? | I15: =_xll.EQNXTDZ($A$1,$B15,I$1,$B$1) -> #NAME? | J15: =_xll.EQNXTDZ($A$1,$B15,J$1,$B$1) -> #NAME? | ... BV15: =_xll.EQNXTDZ($A$1,$B15,BV$1,$B$1) -> #NAME?
A16: Employee Cost | B16: QTR_EXPLOYEE_COST | C16: =_xll.EQNXTDZ($A$1,$B16,C$1,$B$1) -> #NAME? | D16: =_xll.EQNXTDZ($A$1,$B16,D$1,$B$1) -> #NAME? | E16: =_xll.EQNXTDZ($A$1,$B16,E$1,$B$1) -> #NAME? | F16: =_xll.EQNXTDZ($A$1,$B16,F$1,$B$1) -> #NAME? | G16: =_xll.EQNXTDZ($A$1,$B16,G$1,$B$1) -> #NAME? | H16: =_xll.EQNXTDZ($A$1,$B16,H$1,$B$1) -> #NAME? | I16: =_xll.EQNXTDZ($A$1,$B16,I$1,$B$1) -> #NAME? | J16: =_xll.EQNXTDZ($A$1,$B16,J$1,$B$1) -> #NAME? | ... BV16: =_xll.EQNXTDZ($A$1,$B16,BV$1,$B$1) -> #NAME?
... A42: Consolidated PAT(after extra items) | B42: QTR_CONS_PAT_EXITM | C42: =_xll.EQNXTDZ($A$1,$B42,C$1,$B$1) -> #NAME? | D42: =_xll.EQNXTDZ($A$1,$B42,D$1,$B$1) -> #NAME? | E42: =_xll.EQNXTDZ($A$1,$B42,E$1,$B$1) -> #NAME? | F42: =_xll.EQNXTDZ($A$1,$B42,F$1,$B$1) -> #NAME? | G42: =_xll.EQNXTDZ($A$1,$B42,G$1,$B$1) -> #NAME? | H42: =_xll.EQNXTDZ($A$1,$B42,H$1,$B$1) -> #NAME? | I42: =_xll.EQNXTDZ($A$1,$B42,I$1,$B$1) -> #NAME? | J42: =_xll.EQNXTDZ($A$1,$B42,J$1,$B$1) -> #NAME? | ... BV42: =_xll.EQNXTDZ($A$1,$B42,BV$1,$B$1) -> #NAME?
A44: Field Description | B44: Field Name
A45: Equity Capital | B45: QTR_EQUITY_CAP | C45: =_xll.EQNXTDZ($A$1,$B45,C$1,$B$1) -> #NAME? | D45: =_xll.EQNXTDZ($A$1,$B45,D$1,$B$1) -> #NAME? | E45: =_xll.EQNXTDZ($A$1,$B45,E$1,$B$1) -> #NAME? | F45: =_xll.EQNXTDZ($A$1,$B45,F$1,$B$1) -> #NAME? | G45: =_xll.EQNXTDZ($A$1,$B45,G$1,$B$1) -> #NAME? | H45: =_xll.EQNXTDZ($A$1,$B45,H$1,$B$1) -> #NAME? | I45: =_xll.EQNXTDZ($A$1,$B45,I$1,$B$1) -> #NAME? | J45: =_xll.EQNXTDZ($A$1,$B45,J$1,$B$1) -> #NAME? | ... BV45: =_xll.EQNXTDZ($A$1,$B45,BV$1,$B$1) -> #NAME?
A46: Face Value | B46: QTR_FV | C46: =_xll.EQNXTDZ($A$1,$B46,C$1,$B$1) -> #NAME? | D46: =_xll.EQNXTDZ($A$1,$B46,D$1,$B$1) -> #NAME? | E46: =_xll.EQNXTDZ($A$1,$B46,E$1,$B$1) -> #NAME? | F46: =_xll.EQNXTDZ($A$1,$B46,F$1,$B$1) -> #NAME? | G46: =_xll.EQNXTDZ($A$1,$B46,G$1,$B$1) -> #NAME? | H46: =_xll.EQNXTDZ($A$1,$B46,H$1,$B$1) -> #NAME? | I46: =_xll.EQNXTDZ($A$1,$B46,I$1,$B$1) -> #NAME? | J46: =_xll.EQNXTDZ($A$1,$B46,J$1,$B$1) -> #NAME? | ... BV46: =_xll.EQNXTDZ($A$1,$B46,BV$1,$B$1) -> #NAME?
A47: Month End | B47: BMONTH_MONTHEND | C47: =_xll.EQNXTDZ($A$1,$B47,C$5) -> #NAME? | D47: =_xll.EQNXTDZ($A$1,$B47,D$5) -> #NAME? | E47: =_xll.EQNXTDZ($A$1,$B47,E$5) -> #NAME? | F47: =_xll.EQNXTDZ($A$1,$B47,F$5) -> #NAME? | G47: =_xll.EQNXTDZ($A$1,$B47,G$5) -> #NAME? | H47: =_xll.EQNXTDZ($A$1,$B47,H$5) -> #NAME? | I47: =_xll.EQNXTDZ($A$1,$B47,I$5) -> #NAME? | J47: =_xll.EQNXTDZ($A$1,$B47,J$5) -> #NAME? | ... BV47: =_xll.EQNXTDZ($A$1,$B47,BV$5) -> #NAME?
A48: Close | B48: BMONTH_CLOSE | C48: =_xll.EQNXTDZ($A$1,$B48,C$5) -> #NAME? | D48: =_xll.EQNXTDZ($A$1,$B48,D$5) -> #NAME? | E48: =_xll.EQNXTDZ($A$1,$B48,E$5) -> #NAME? | F48: =_xll.EQNXTDZ($A$1,$B48,F$5) -> #NAME? | G48: =_xll.EQNXTDZ($A$1,$B48,G$5) -> #NAME? | H48: =_xll.EQNXTDZ($A$1,$B48,H$5) -> #NAME? | I48: =_xll.EQNXTDZ($A$1,$B48,I$5) -> #NAME? | J48: =_xll.EQNXTDZ($A$1,$B48,J$5) -> #NAME? | ... BV48: =_xll.EQNXTDZ($A$1,$B48,BV$5) -> #NAME?
A49: Total of Promoter and Promoter Group | B49: SHP_TPFTOTALPROMOTER | C49: =_xll.EQNXTDZ($A$1,$B49,C$5) -> #NAME? | D49: =_xll.EQNXTDZ($A$1,$B49,D$5) -> #NAME? | E49: =_xll.EQNXTDZ($A$1,$B49,E$5) -> #NAME? | F49: =_xll.EQNXTDZ($A$1,$B49,F$5) -> #NAME? | G49: =_xll.EQNXTDZ($A$1,$B49,G$5) -> #NAME? | H49: =_xll.EQNXTDZ($A$1,$B49,H$5) -> #NAME? | I49: =_xll.EQNXTDZ($A$1,$B49,I$5) -> #NAME? | J49: =_xll.EQNXTDZ($A$1,$B49,J$5) -> #NAME? | ... BV49: =_xll.EQNXTDZ($A$1,$B49,BV$5) -> #NAME?
A50: Total of Promoter and Promoter Group Pledged | B50: SHP_PSHFTOTALPROMOTER | C50: =_xll.EQNXTDZ($A$1,$B50,C$5) -> #NAME? | D50: =_xll.EQNXTDZ($A$1,$B50,D$5) -> #NAME? | E50: =_xll.EQNXTDZ($A$1,$B50,E$5) -> #NAME? | F50: =_xll.EQNXTDZ($A$1,$B50,F$5) -> #NAME? | G50: =_xll.EQNXTDZ($A$1,$B50,G$5) -> #NAME? | H50: =_xll.EQNXTDZ($A$1,$B50,H$5) -> #NAME? | I50: =_xll.EQNXTDZ($A$1,$B50,I$5) -> #NAME? | J50: =_xll.EQNXTDZ($A$1,$B50,J$5) -> #NAME? | ... BV50: =_xll.EQNXTDZ($A$1,$B50,BV$5) -> #NAME?
A54: Field Description | B54: Field Name | C54: =_xll.EQNXTDZ($A$1,$B54,C$5) -> #NAME? | D54: =_xll.EQNXTDZ($A$1,$B54,D$5) -> #NAME? | E54: =_xll.EQNXTDZ($A$1,$B54,E$5) -> #NAME? | F54: =_xll.EQNXTDZ($A$1,$B54,F$5) -> #NAME? | G54: =_xll.EQNXTDZ($A$1,$B54,G$5) -> #NAME? | H54: =_xll.EQNXTDZ($A$1,$B54,H$5) -> #NAME? | I54: =_xll.EQNXTDZ($A$1,$B54,I$5) -> #NAME? | J54: =_xll.EQNXTDZ($A$1,$B54,J$5) -> #NAME? | ... BV54: =_xll.EQNXTDZ($A$1,$B54,BV$5) -> #NAME?
A55: Year End | B55: QTRB_DATE_END | C55: =_xll.EQNXTDZ($A$1,$B55,C$5,$B$1) -> #NAME? | D55: =_xll.EQNXTDZ($A$1,$B55,D$5,$B$1) -> #NAME? | E55: =_xll.EQNXTDZ($A$1,$B55,E$5,$B$1) -> #NAME? | F55: =_xll.EQNXTDZ($A$1,$B55,F$5,$B$1) -> #NAME? | G55: =_xll.EQNXTDZ($A$1,$B55,G$5,$B$1) -> #NAME? | H55: =_xll.EQNXTDZ($A$1,$B55,H$5,$B$1) -> #NAME? | I55: =_xll.EQNXTDZ($A$1,$B55,I$5,$B$1) -> #NAME? | J55: =_xll.EQNXTDZ($A$1,$B55,J$5,$B$1) -> #NAME? | ... BV55: =_xll.EQNXTDZ($A$1,$B55,BV$5,$B$1) -> #NAME?
A56: Share Capital | B56: QTRB_SHARE_CAPITAL | C56: =_xll.EQNXTDZ($A$1,$B56,C$5,$B$1) -> #NAME? | D56: =_xll.EQNXTDZ($A$1,$B56,D$5,$B$1) -> #NAME? | E56: =_xll.EQNXTDZ($A$1,$B56,E$5,$B$1) -> #NAME? | F56: =_xll.EQNXTDZ($A$1,$B56,F$5,$B$1) -> #NAME? | G56: =_xll.EQNXTDZ($A$1,$B56,G$5,$B$1) -> #NAME? | H56: =_xll.EQNXTDZ($A$1,$B56,H$5,$B$1) -> #NAME? | I56: =_xll.EQNXTDZ($A$1,$B56,I$5,$B$1) -> #NAME? | J56: =_xll.EQNXTDZ($A$1,$B56,J$5,$B$1) -> #NAME? | ... BV56: =_xll.EQNXTDZ($A$1,$B56,BV$5,$B$1) -> #NAME?
A57: Share Warrants & outstandings | B57: QTRB_SHAREWARNDOUT | C57: =_xll.EQNXTDZ($A$1,$B57,C$5,$B$1) -> #NAME? | D57: =_xll.EQNXTDZ($A$1,$B57,D$5,$B$1) -> #NAME? | E57: =_xll.EQNXTDZ($A$1,$B57,E$5,$B$1) -> #NAME? | F57: =_xll.EQNXTDZ($A$1,$B57,F$5,$B$1) -> #NAME? | G57: =_xll.EQNXTDZ($A$1,$B57,G$5,$B$1) -> #NAME? | H57: =_xll.EQNXTDZ($A$1,$B57,H$5,$B$1) -> #NAME? | I57: =_xll.EQNXTDZ($A$1,$B57,I$5,$B$1) -> #NAME? | J57: =_xll.EQNXTDZ($A$1,$B57,J$5,$B$1) -> #NAME? | ... BV57: =_xll.EQNXTDZ($A$1,$B57,BV$5,$B$1) -> #NAME?
A58: Reserves & Surplus | B58: QTRB_RESERVE | C58: =_xll.EQNXTDZ($A$1,$B58,C$5,$B$1) -> #NAME? | D58: =_xll.EQNXTDZ($A$1,$B58,D$5,$B$1) -> #NAME? | E58: =_xll.EQNXTDZ($A$1,$B58,E$5,$B$1) -> #NAME? | F58: =_xll.EQNXTDZ($A$1,$B58,F$5,$B$1) -> #NAME? | G58: =_xll.EQNXTDZ($A$1,$B58,G$5,$B$1) -> #NAME? | H58: =_xll.EQNXTDZ($A$1,$B58,H$5,$B$1) -> #NAME? | I58: =_xll.EQNXTDZ($A$1,$B58,I$5,$B$1) -> #NAME? | J58: =_xll.EQNXTDZ($A$1,$B58,J$5,$B$1) -> #NAME? | ... BV58: =_xll.EQNXTDZ($A$1,$B58,BV$5,$B$1) -> #NAME?
A59: Shareholder's Funds | B59: QTRB_SHAREHODERS_FUNDS | C59: =_xll.EQNXTDZ($A$1,$B59,C$5,$B$1) -> #NAME? | D59: =_xll.EQNXTDZ($A$1,$B59,D$5,$B$1) -> #NAME? | E59: =_xll.EQNXTDZ($A$1,$B59,E$5,$B$1) -> #NAME? | F59: =_xll.EQNXTDZ($A$1,$B59,F$5,$B$1) -> #NAME? | G59: =_xll.EQNXTDZ($A$1,$B59,G$5,$B$1) -> #NAME? | H59: =_xll.EQNXTDZ($A$1,$B59,H$5,$B$1) -> #NAME? | I59: =_xll.EQNXTDZ($A$1,$B59,I$5,$B$1) -> #NAME? | J59: =_xll.EQNXTDZ($A$1,$B59,J$5,$B$1) -> #NAME? | ... BV59: =_xll.EQNXTDZ($A$1,$B59,BV$5,$B$1) -> #NAME?
A60: Minority Interest | B60: QTRB_MINORITY_INTEREST_BS | C60: =_xll.EQNXTDZ($A$1,$B60,C$5,$B$1) -> #NAME? | D60: =_xll.EQNXTDZ($A$1,$B60,D$5,$B$1) -> #NAME? | E60: =_xll.EQNXTDZ($A$1,$B60,E$5,$B$1) -> #NAME? | F60: =_xll.EQNXTDZ($A$1,$B60,F$5,$B$1) -> #NAME? | G60: =_xll.EQNXTDZ($A$1,$B60,G$5,$B$1) -> #NAME? | H60: =_xll.EQNXTDZ($A$1,$B60,H$5,$B$1) -> #NAME? | I60: =_xll.EQNXTDZ($A$1,$B60,I$5,$B$1) -> #NAME? | J60: =_xll.EQNXTDZ($A$1,$B60,J$5,$B$1) -> #NAME? | ... BV60: =_xll.EQNXTDZ($A$1,$B60,BV$5,$B$1) -> #NAME?
A61: Long Term Borrowings | B61: QTRB_TOTAL_DEBTS | C61: =_xll.EQNXTDZ($A$1,$B61,C$5,$B$1) -> #NAME? | D61: =_xll.EQNXTDZ($A$1,$B61,D$5,$B$1) -> #NAME? | E61: =_xll.EQNXTDZ($A$1,$B61,E$5,$B$1) -> #NAME? | F61: =_xll.EQNXTDZ($A$1,$B61,F$5,$B$1) -> #NAME? | G61: =_xll.EQNXTDZ($A$1,$B61,G$5,$B$1) -> #NAME? | H61: =_xll.EQNXTDZ($A$1,$B61,H$5,$B$1) -> #NAME? | I61: =_xll.EQNXTDZ($A$1,$B61,I$5,$B$1) -> #NAME? | J61: =_xll.EQNXTDZ($A$1,$B61,J$5,$B$1) -> #NAME? | ... BV61: =_xll.EQNXTDZ($A$1,$B61,BV$5,$B$1) -> #NAME?
A62: Secured Loans | B62: QTRB_SECURED_LOANS | C62: =_xll.EQNXTDZ($A$1,$B62,C$5,$B$1) -> #NAME? | D62: =_xll.EQNXTDZ($A$1,$B62,D$5,$B$1) -> #NAME? | E62: =_xll.EQNXTDZ($A$1,$B62,E$5,$B$1) -> #NAME? | F62: =_xll.EQNXTDZ($A$1,$B62,F$5,$B$1) -> #NAME? | G62: =_xll.EQNXTDZ($A$1,$B62,G$5,$B$1) -> #NAME? | H62: =_xll.EQNXTDZ($A$1,$B62,H$5,$B$1) -> #NAME? | I62: =_xll.EQNXTDZ($A$1,$B62,I$5,$B$1) -> #NAME? | J62: =_xll.EQNXTDZ($A$1,$B62,J$5,$B$1) -> #NAME? | ... BV62: =_xll.EQNXTDZ($A$1,$B62,BV$5,$B$1) -> #NAME?
A63: Unsecured Loans | B63: QTRB_UNSECURED_LOANS_NF | C63: =_xll.EQNXTDZ($A$1,$B63,C$5,$B$1) -> #NAME? | D63: =_xll.EQNXTDZ($A$1,$B63,D$5,$B$1) -> #NAME? | E63: =_xll.EQNXTDZ($A$1,$B63,E$5,$B$1) -> #NAME? | F63: =_xll.EQNXTDZ($A$1,$B63,F$5,$B$1) -> #NAME? | G63: =_xll.EQNXTDZ($A$1,$B63,G$5,$B$1) -> #NAME? | H63: =_xll.EQNXTDZ($A$1,$B63,H$5,$B$1) -> #NAME? | I63: =_xll.EQNXTDZ($A$1,$B63,I$5,$B$1) -> #NAME? | J63: =_xll.EQNXTDZ($A$1,$B63,J$5,$B$1) -> #NAME? | ... BV63: =_xll.EQNXTDZ($A$1,$B63,BV$5,$B$1) -> #NAME?
A64: Other Long Term Liabilities | B64: QTRB_OTHER_LT_LIABILITIES | C64: =_xll.EQNXTDZ($A$1,$B64,C$5,$B$1) -> #NAME? | D64: =_xll.EQNXTDZ($A$1,$B64,D$5,$B$1) -> #NAME? | E64: =_xll.EQNXTDZ($A$1,$B64,E$5,$B$1) -> #NAME? | F64: =_xll.EQNXTDZ($A$1,$B64,F$5,$B$1) -> #NAME? | G64: =_xll.EQNXTDZ($A$1,$B64,G$5,$B$1) -> #NAME? | H64: =_xll.EQNXTDZ($A$1,$B64,H$5,$B$1) -> #NAME? | I64: =_xll.EQNXTDZ($A$1,$B64,I$5,$B$1) -> #NAME? | J64: =_xll.EQNXTDZ($A$1,$B64,J$5,$B$1) -> #NAME? | ... BV64: =_xll.EQNXTDZ($A$1,$B64,BV$5,$B$1) -> #NAME?
A65: Long Term Trade Payables | B65: QTRB_LT_TRADE_PAYABLE | C65: =_xll.EQNXTDZ($A$1,$B65,C$5,$B$1) -> #NAME? | D65: =_xll.EQNXTDZ($A$1,$B65,D$5,$B$1) -> #NAME? | E65: =_xll.EQNXTDZ($A$1,$B65,E$5,$B$1) -> #NAME? | F65: =_xll.EQNXTDZ($A$1,$B65,F$5,$B$1) -> #NAME? | G65: =_xll.EQNXTDZ($A$1,$B65,G$5,$B$1) -> #NAME? | H65: =_xll.EQNXTDZ($A$1,$B65,H$5,$B$1) -> #NAME? | I65: =_xll.EQNXTDZ($A$1,$B65,I$5,$B$1) -> #NAME? | J65: =_xll.EQNXTDZ($A$1,$B65,J$5,$B$1) -> #NAME? | ... BV65: =_xll.EQNXTDZ($A$1,$B65,BV$5,$B$1) -> #NAME?
A66: Lont Term Provisions | B66: QTRB_LT_PROVISIONS | C66: =_xll.EQNXTDZ($A$1,$B66,C$5,$B$1) -> #NAME? | D66: =_xll.EQNXTDZ($A$1,$B66,D$5,$B$1) -> #NAME? | E66: =_xll.EQNXTDZ($A$1,$B66,E$5,$B$1) -> #NAME? | F66: =_xll.EQNXTDZ($A$1,$B66,F$5,$B$1) -> #NAME? | G66: =_xll.EQNXTDZ($A$1,$B66,G$5,$B$1) -> #NAME? | H66: =_xll.EQNXTDZ($A$1,$B66,H$5,$B$1) -> #NAME? | I66: =_xll.EQNXTDZ($A$1,$B66,I$5,$B$1) -> #NAME? | J66: =_xll.EQNXTDZ($A$1,$B66,J$5,$B$1) -> #NAME? | ... BV66: =_xll.EQNXTDZ($A$1,$B66,BV$5,$B$1) -> #NAME?
... A97: Total Assets | B97: QTRB_TOTAL_APPLICATIONS | C97: =_xll.EQNXTDZ($A$1,$B97,C$5,$B$1) -> #NAME? | D97: =_xll.EQNXTDZ($A$1,$B97,D$5,$B$1) -> #NAME? | E97: =_xll.EQNXTDZ($A$1,$B97,E$5,$B$1) -> #NAME? | F97: =_xll.EQNXTDZ($A$1,$B97,F$5,$B$1) -> #NAME? | G97: =_xll.EQNXTDZ($A$1,$B97,G$5,$B$1) -> #NAME? | H97: =_xll.EQNXTDZ($A$1,$B97,H$5,$B$1) -> #NAME? | I97: =_xll.EQNXTDZ($A$1,$B97,I$5,$B$1) -> #NAME? | J97: =_xll.EQNXTDZ($A$1,$B97,J$5,$B$1) -> #NAME? | ... BV97: =_xll.EQNXTDZ($A$1,$B97,BV$5,$B$1) -> #NAME?

Sheet Annual Raw
A1: 219412 | B1: X | C1: 200103 | D1: 200203 | E1: 200303 | F1: 200403 | G1: 200503 | H1: 200603 | I1: 200703 | J1: 200803 | K1: 200903 | L1: 201003 | M1: 201103 | N1: 201203 | O1: 201303 | P1: 201403 | Q1: 201503 | R1: 201603 | S1: 201703 | T1: 201803 | U1: 201903 | V1: 202003 | W1: 202103 | X1: 202203 | Y1: 202303 | Z1: 202403 | AA1: 202503 | AB1: 202603 | AC1: 202703 | AD1: 202803 | AE1: 202903 | AF1: 203003
A3: Field Description | B3: Field Name
A4: Company Name | B4: CD_COMPNAME | C4: =_xll.EQNXTDZ(A1,B4,"L") -> #NAME?
A5: Year End | B5: PL_YEAR_END | C5: =_xll.EQNXTDZ($A$1,$B5,C$1,$B$1) -> #NAME? | D5: =_xll.EQNXTDZ($A$1,$B5,D$1,$B$1) -> #NAME? | E5: =_xll.EQNXTDZ($A$1,$B5,E$1,$B$1) -> #NAME? | F5: =_xll.EQNXTDZ($A$1,$B5,F$1,$B$1) -> #NAME? | G5: =_xll.EQNXTDZ($A$1,$B5,G$1,$B$1) -> #NAME? | H5: =_xll.EQNXTDZ($A$1,$B5,H$1,$B$1) -> #NAME? | I5: =_xll.EQNXTDZ($A$1,$B5,I$1,$B$1) -> #NAME? | J5: =_xll.EQNXTDZ($A$1,$B5,J$1,$B$1) -> #NAME? | ... AF5: =_xll.EQNXTDZ($A$1,$B5,AF$1,$B$1) -> #NAME?
A6: Sales Turnover | B6: PL_TOTAL_GROSS_SALES | C6: =_xll.EQNXTDZ($A$1,$B6,C$1,$B$1) -> #NAME? | D6: =_xll.EQNXTDZ($A$1,$B6,D$1,$B$1) -> #NAME? | E6: =_xll.EQNXTDZ($A$1,$B6,E$1,$B$1) -> #NAME? | F6: =_xll.EQNXTDZ($A$1,$B6,F$1,$B$1) -> #NAME? | G6: =_xll.EQNXTDZ($A$1,$B6,G$1,$B$1) -> #NAME? | H6: =_xll.EQNXTDZ($A$1,$B6,H$1,$B$1) -> #NAME? | I6: =_xll.EQNXTDZ($A$1,$B6,I$1,$B$1) -> #NAME? | J6: =_xll.EQNXTDZ($A$1,$B6,J$1,$B$1) -> #NAME? | ... AF6: =_xll.EQNXTDZ($A$1,$B6,AF$1,$B$1) -> #NAME?
A7: Less: Inter divisional transfers | B7: PL_INTER_DIV_TRF | C7: =_xll.EQNXTDZ($A$1,$B7,C$1,$B$1) -> #NAME? | D7: =_xll.EQNXTDZ($A$1,$B7,D$1,$B$1) -> #NAME? | E7: =_xll.EQNXTDZ($A$1,$B7,E$1,$B$1) -> #NAME? | F7: =_xll.EQNXTDZ($A$1,$B7,F$1,$B$1) -> #NAME? | G7: =_xll.EQNXTDZ($A$1,$B7,G$1,$B$1) -> #NAME? | H7: =_xll.EQNXTDZ($A$1,$B7,H$1,$B$1) -> #NAME? | I7: =_xll.EQNXTDZ($A$1,$B7,I$1,$B$1) -> #NAME? | J7: =_xll.EQNXTDZ($A$1,$B7,J$1,$B$1) -> #NAME? | ... AF7: =_xll.EQNXTDZ($A$1,$B7,AF$1,$B$1) -> #NAME?
A8: Less: Sales Returns | B8: PL_SALES_RETURN | C8: =_xll.EQNXTDZ($A$1,$B8,C$1,$B$1) -> #NAME? | D8: =_xll.EQNXTDZ($A$1,$B8,D$1,$B$1) -> #NAME? | E8: =_xll.EQNXTDZ($A$1,$B8,E$1,$B$1) -> #NAME? | F8: =_xll.EQNXTDZ($A$1,$B8,F$1,$B$1) -> #NAME? | G8: =_xll.EQNXTDZ($A$1,$B8,G$1,$B$1) -> #NAME? | H8: =_xll.EQNXTDZ($A$1,$B8,H$1,$B$1) -> #NAME? | I8: =_xll.EQNXTDZ($A$1,$B8,I$1,$B$1) -> #NAME? | J8: =_xll.EQNXTDZ($A$1,$B8,J$1,$B$1) -> #NAME? | ... AF8: =_xll.EQNXTDZ($A$1,$B8,AF$1,$B$1) -> #NAME?
A9: Less: Excise | B9: PL_EXCISE | C9: =_xll.EQNXTDZ($A$1,$B9,C$1,$B$1) -> #NAME? | D9: =_xll.EQNXTDZ($A$1,$B9,D$1,$B$1) -> #NAME? | E9: =_xll.EQNXTDZ($A$1,$B9,E$1,$B$1) -> #NAME? | F9: =_xll.EQNXTDZ($A$1,$B9,F$1,$B$1) -> #NAME? | G9: =_xll.EQNXTDZ($A$1,$B9,G$1,$B$1) -> #NAME? | H9: =_xll.EQNXTDZ($A$1,$B9,H$1,$B$1) -> #NAME? | I9: =_xll.EQNXTDZ($A$1,$B9,I$1,$B$1) -> #NAME? | J9: =_xll.EQNXTDZ($A$1,$B9,J$1,$B$1) -> #NAME? | ... AF9: =_xll.EQNXTDZ($A$1,$B9,AF$1,$B$1) -> #NAME?
A10: Net Sales | B10: PL_NET_SALES | C10: =_xll.EQNXTDZ($A$1,$B10,C$1,$B$1) -> #NAME? | D10: =_xll.EQNXTDZ($A$1,$B10,D$1,$B$1) -> #NAME? | E10: =_xll.EQNXTDZ($A$1,$B10,E$1,$B$1) -> #NAME? | F10: =_xll.EQNXTDZ($A$1,$B10,F$1,$B$1) -> #NAME? | G10: =_xll.EQNXTDZ($A$1,$B10,G$1,$B$1) -> #NAME? | H10: =_xll.EQNXTDZ($A$1,$B10,H$1,$B$1) -> #NAME? | I10: =_xll.EQNXTDZ($A$1,$B10,I$1,$B$1) -> #NAME? | J10: =_xll.EQNXTDZ($A$1,$B10,J$1,$B$1) -> #NAME? | ... AF10: =_xll.EQNXTDZ($A$1,$B10,AF$1,$B$1) -> #NAME?
A11: Increase/Decrease in Stock | B11: PL_INC_DEC_INVENTORY | C11: =_xll.EQNXTDZ($A$1,$B11,C$1,$B$1) -> #NAME? | D11: =_xll.EQNXTDZ($A$1,$B11,D$1,$B$1) -> #NAME? | E11: =_xll.EQNXTDZ($A$1,$B11,E$1,$B$1) -> #NAME? | F11: =_xll.EQNXTDZ($A$1,$B11,F$1,$B$1) -> #NAME? | G11: =_xll.EQNXTDZ($A$1,$B11,G$1,$B$1) -> #NAME? | H11: =_xll.EQNXTDZ($A$1,$B11,H$1,$B$1) -> #NAME? | I11: =_xll.EQNXTDZ($A$1,$B11,I$1,$B$1) -> #NAME? | J11: =_xll.EQNXTDZ($A$1,$B11,J$1,$B$1) -> #NAME? | ... AF11: =_xll.EQNXTDZ($A$1,$B11,AF$1,$B$1) -> #NAME?
A12: Raw Material Consumed | B12: PL_RAW_MATRS_CONSUMED | C12: =_xll.EQNXTDZ($A$1,$B12,C$1,$B$1) -> #NAME? | D12: =_xll.EQNXTDZ($A$1,$B12,D$1,$B$1) -> #NAME? | E12: =_xll.EQNXTDZ($A$1,$B12,E$1,$B$1) -> #NAME? | F12: =_xll.EQNXTDZ($A$1,$B12,F$1,$B$1) -> #NAME? | G12: =_xll.EQNXTDZ($A$1,$B12,G$1,$B$1) -> #NAME? | H12: =_xll.EQNXTDZ($A$1,$B12,H$1,$B$1) -> #NAME? | I12: =_xll.EQNXTDZ($A$1,$B12,I$1,$B$1) -> #NAME? | J12: =_xll.EQNXTDZ($A$1,$B12,J$1,$B$1) -> #NAME? | ... AF12: =_xll.EQNXTDZ($A$1,$B12,AF$1,$B$1) -> #NAME?
A13: Power & Fuel Cost | B13: PL_POWER_FUEL | C13: =_xll.EQNXTDZ($A$1,$B13,C$1,$B$1) -> #NAME? | D13: =_xll.EQNXTDZ($A$1,$B13,D$1,$B$1) -> #NAME? | E13: =_xll.EQNXTDZ($A$1,$B13,E$1,$B$1) -> #NAME? | F13: =_xll.EQNXTDZ($A$1,$B13,F$1,$B$1) -> #NAME? | G13: =_xll.EQNXTDZ($A$1,$B13,G$1,$B$1) -> #NAME? | H13: =_xll.EQNXTDZ($A$1,$B13,H$1,$B$1) -> #NAME? | I13: =_xll.EQNXTDZ($A$1,$B13,I$1,$B$1) -> #NAME? | J13: =_xll.EQNXTDZ($A$1,$B13,J$1,$B$1) -> #NAME? | ... AF13: =_xll.EQNXTDZ($A$1,$B13,AF$1,$B$1) -> #NAME?
A14: Employee Cost | B14: PL_EMPLOYEES | C14: =_xll.EQNXTDZ($A$1,$B14,C$1,$B$1) -> #NAME? | D14: =_xll.EQNXTDZ($A$1,$B14,D$1,$B$1) -> #NAME? | E14: =_xll.EQNXTDZ($A$1,$B14,E$1,$B$1) -> #NAME? | F14: =_xll.EQNXTDZ($A$1,$B14,F$1,$B$1) -> #NAME? | G14: =_xll.EQNXTDZ($A$1,$B14,G$1,$B$1) -> #NAME? | H14: =_xll.EQNXTDZ($A$1,$B14,H$1,$B$1) -> #NAME? | I14: =_xll.EQNXTDZ($A$1,$B14,I$1,$B$1) -> #NAME? | J14: =_xll.EQNXTDZ($A$1,$B14,J$1,$B$1) -> #NAME? | ... AF14: =_xll.EQNXTDZ($A$1,$B14,AF$1,$B$1) -> #NAME?
A15: Operating & Manufacturing Expenses | B15: PL_GEN_OTHER_MFG_EXPS | C15: =_xll.EQNXTDZ($A$1,$B15,C$1,$B$1) -> #NAME? | D15: =_xll.EQNXTDZ($A$1,$B15,D$1,$B$1) -> #NAME? | E15: =_xll.EQNXTDZ($A$1,$B15,E$1,$B$1) -> #NAME? | F15: =_xll.EQNXTDZ($A$1,$B15,F$1,$B$1) -> #NAME? | G15: =_xll.EQNXTDZ($A$1,$B15,G$1,$B$1) -> #NAME? | H15: =_xll.EQNXTDZ($A$1,$B15,H$1,$B$1) -> #NAME? | I15: =_xll.EQNXTDZ($A$1,$B15,I$1,$B$1) -> #NAME? | J15: =_xll.EQNXTDZ($A$1,$B15,J$1,$B$1) -> #NAME? | ... AF15: =_xll.EQNXTDZ($A$1,$B15,AF$1,$B$1) -> #NAME?
A16: Cost of Software development | B16: PL_COST_SW | C16: =_xll.EQNXTDZ($A$1,$B16,C$1,$B$1) -> #NAME? | D16: =_xll.EQNXTDZ($A$1,$B16,D$1,$B$1) -> #NAME? | E16: =_xll.EQNXTDZ($A$1,$B16,E$1,$B$1) -> #NAME? | F16: =_xll.EQNXTDZ($A$1,$B16,F$1,$B$1) -> #NAME? | G16: =_xll.EQNXTDZ($A$1,$B16,G$1,$B$1) -> #NAME? | H16: =_xll.EQNXTDZ($A$1,$B16,H$1,$B$1) -> #NAME? | I16: =_xll.EQNXTDZ($A$1,$B16,I$1,$B$1) -> #NAME? | J16: =_xll.EQNXTDZ($A$1,$B16,J$1,$B$1) -> #NAME? | ... AF16: =_xll.EQNXTDZ($A$1,$B16,AF$1,$B$1) -> #NAME?
... A36: Profit After Tax from Discontinued Operations | B36: PL_PAT_DIS_OP | C36: =_xll.EQNXTDZ($A$1,$B36,C$1,$B$1) -> #NAME? | D36: =_xll.EQNXTDZ($A$1,$B36,D$1,$B$1) -> #NAME? | E36: =_xll.EQNXTDZ($A$1,$B36,E$1,$B$1) -> #NAME? | F36: =_xll.EQNXTDZ($A$1,$B36,F$1,$B$1) -> #NAME? | G36: =_xll.EQNXTDZ($A$1,$B36,G$1,$B$1) -> #NAME? | H36: =_xll.EQNXTDZ($A$1,$B36,H$1,$B$1) -> #NAME? | I36: =_xll.EQNXTDZ($A$1,$B36,I$1,$B$1) -> #NAME? | J36: =_xll.EQNXTDZ($A$1,$B36,J$1,$B$1) -> #NAME? | ... AF36: =_xll.EQNXTDZ($A$1,$B36,AF$1,$B$1) -> #NAME?
A39: Field Description | B39: Field Name
A40: Year End | B40: BS_YEAR_END | C40: =_xll.EQNXTDZ($A$1,$B40,C$1,$B$1) -> #NAME? | D40: =_xll.EQNXTDZ($A$1,$B40,D$1,$B$1) -> #NAME? | E40: =_xll.EQNXTDZ($A$1,$B40,E$1,$B$1) -> #NAME? | F40: =_xll.EQNXTDZ($A$1,$B40,F$1,$B$1) -> #NAME? | G40: =_xll.EQNXTDZ($A$1,$B40,G$1,$B$1) -> #NAME? | H40: =_xll.EQNXTDZ($A$1,$B40,H$1,$B$1) -> #NAME? | I40: =_xll.EQNXTDZ($A$1,$B40,I$1,$B$1) -> #NAME? | J40: =_xll.EQNXTDZ($A$1,$B40,J$1,$B$1) -> #NAME? | ... AF40: =_xll.EQNXTDZ($A$1,$B40,AF$1,$B$1) -> #NAME?
A41: Share Capital | B41: BS_SHARE_CAPITAL | C41: =_xll.EQNXTDZ($A$1,$B41,C$1,$B$1) -> #NAME? | D41: =_xll.EQNXTDZ($A$1,$B41,D$1,$B$1) -> #NAME? | E41: =_xll.EQNXTDZ($A$1,$B41,E$1,$B$1) -> #NAME? | F41: =_xll.EQNXTDZ($A$1,$B41,F$1,$B$1) -> #NAME? | G41: =_xll.EQNXTDZ($A$1,$B41,G$1,$B$1) -> #NAME? | H41: =_xll.EQNXTDZ($A$1,$B41,H$1,$B$1) -> #NAME? | I41: =_xll.EQNXTDZ($A$1,$B41,I$1,$B$1) -> #NAME? | J41: =_xll.EQNXTDZ($A$1,$B41,J$1,$B$1) -> #NAME? | ... AF41: =_xll.EQNXTDZ($A$1,$B41,AF$1,$B$1) -> #NAME?
A42: Share Warrants & Outstandings | B42: BS_SHAREWROUTST | C42: =_xll.EQNXTDZ($A$1,$B42,C$1,$B$1) -> #NAME? | D42: =_xll.EQNXTDZ($A$1,$B42,D$1,$B$1) -> #NAME? | E42: =_xll.EQNXTDZ($A$1,$B42,E$1,$B$1) -> #NAME? | F42: =_xll.EQNXTDZ($A$1,$B42,F$1,$B$1) -> #NAME? | G42: =_xll.EQNXTDZ($A$1,$B42,G$1,$B$1) -> #NAME? | H42: =_xll.EQNXTDZ($A$1,$B42,H$1,$B$1) -> #NAME? | I42: =_xll.EQNXTDZ($A$1,$B42,I$1,$B$1) -> #NAME? | J42: =_xll.EQNXTDZ($A$1,$B42,J$1,$B$1) -> #NAME? | ... AF42: =_xll.EQNXTDZ($A$1,$B42,AF$1,$B$1) -> #NAME?
A43: Total Reserves | B43: BS_RESERVE | C43: =_xll.EQNXTDZ($A$1,$B43,C$1,$B$1) -> #NAME? | D43: =_xll.EQNXTDZ($A$1,$B43,D$1,$B$1) -> #NAME? | E43: =_xll.EQNXTDZ($A$1,$B43,E$1,$B$1) -> #NAME? | F43: =_xll.EQNXTDZ($A$1,$B43,F$1,$B$1) -> #NAME? | G43: =_xll.EQNXTDZ($A$1,$B43,G$1,$B$1) -> #NAME? | H43: =_xll.EQNXTDZ($A$1,$B43,H$1,$B$1) -> #NAME? | I43: =_xll.EQNXTDZ($A$1,$B43,I$1,$B$1) -> #NAME? | J43: =_xll.EQNXTDZ($A$1,$B43,J$1,$B$1) -> #NAME? | ... AF43: =_xll.EQNXTDZ($A$1,$B43,AF$1,$B$1) -> #NAME?
A44: Shareholder's Funds | B44: BS_SHAREHODERS_FUNDS | C44: =_xll.EQNXTDZ($A$1,$B44,C$1,$B$1) -> #NAME? | D44: =_xll.EQNXTDZ($A$1,$B44,D$1,$B$1) -> #NAME? | E44: =_xll.EQNXTDZ($A$1,$B44,E$1,$B$1) -> #NAME? | F44: =_xll.EQNXTDZ($A$1,$B44,F$1,$B$1) -> #NAME? | G44: =_xll.EQNXTDZ($A$1,$B44,G$1,$B$1) -> #NAME? | H44: =_xll.EQNXTDZ($A$1,$B44,H$1,$B$1) -> #NAME? | I44: =_xll.EQNXTDZ($A$1,$B44,I$1,$B$1) -> #NAME? | J44: =_xll.EQNXTDZ($A$1,$B44,J$1,$B$1) -> #NAME? | ... AF44: =_xll.EQNXTDZ($A$1,$B44,AF$1,$B$1) -> #NAME?
A45: Minority Interest | B45: BS_MINORITY_INTEREST | C45: =_xll.EQNXTDZ($A$1,$B45,C$1,$B$1) -> #NAME? | D45: =_xll.EQNXTDZ($A$1,$B45,D$1,$B$1) -> #NAME? | E45: =_xll.EQNXTDZ($A$1,$B45,E$1,$B$1) -> #NAME? | F45: =_xll.EQNXTDZ($A$1,$B45,F$1,$B$1) -> #NAME? | G45: =_xll.EQNXTDZ($A$1,$B45,G$1,$B$1) -> #NAME? | H45: =_xll.EQNXTDZ($A$1,$B45,H$1,$B$1) -> #NAME? | I45: =_xll.EQNXTDZ($A$1,$B45,I$1,$B$1) -> #NAME? | J45: =_xll.EQNXTDZ($A$1,$B45,J$1,$B$1) -> #NAME? | ... AF45: =_xll.EQNXTDZ($A$1,$B45,AF$1,$B$1) -> #NAME?
A46: Long-Term Borrowings | B46: BS_LTRM_BORROWING | C46: =_xll.EQNXTDZ($A$1,$B46,C$1,$B$1) -> #NAME? | D46: =_xll.EQNXTDZ($A$1,$B46,D$1,$B$1) -> #NAME? | E46: =_xll.EQNXTDZ($A$1,$B46,E$1,$B$1) -> #NAME? | F46: =_xll.EQNXTDZ($A$1,$B46,F$1,$B$1) -> #NAME? | G46: =_xll.EQNXTDZ($A$1,$B46,G$1,$B$1) -> #NAME? | H46: =_xll.EQNXTDZ($A$1,$B46,H$1,$B$1) -> #NAME? | I46: =_xll.EQNXTDZ($A$1,$B46,I$1,$B$1) -> #NAME? | J46: =_xll.EQNXTDZ($A$1,$B46,J$1,$B$1) -> #NAME? | ... AF46: =_xll.EQNXTDZ($A$1,$B46,AF$1,$B$1) -> #NAME?
A47: Secured Loans | B47: BS_SECURED_LOANS | C47: =_xll.EQNXTDZ($A$1,$B47,C$1,$B$1) -> #NAME? | D47: =_xll.EQNXTDZ($A$1,$B47,D$1,$B$1) -> #NAME? | E47: =_xll.EQNXTDZ($A$1,$B47,E$1,$B$1) -> #NAME? | F47: =_xll.EQNXTDZ($A$1,$B47,F$1,$B$1) -> #NAME? | G47: =_xll.EQNXTDZ($A$1,$B47,G$1,$B$1) -> #NAME? | H47: =_xll.EQNXTDZ($A$1,$B47,H$1,$B$1) -> #NAME? | I47: =_xll.EQNXTDZ($A$1,$B47,I$1,$B$1) -> #NAME? | J47: =_xll.EQNXTDZ($A$1,$B47,J$1,$B$1) -> #NAME? | ... AF47: =_xll.EQNXTDZ($A$1,$B47,AF$1,$B$1) -> #NAME?
A48: Unsecured Loans | B48: BS_UNSECURED_LOANS_NF | C48: =_xll.EQNXTDZ($A$1,$B48,C$1,$B$1) -> #NAME? | D48: =_xll.EQNXTDZ($A$1,$B48,D$1,$B$1) -> #NAME? | E48: =_xll.EQNXTDZ($A$1,$B48,E$1,$B$1) -> #NAME? | F48: =_xll.EQNXTDZ($A$1,$B48,F$1,$B$1) -> #NAME? | G48: =_xll.EQNXTDZ($A$1,$B48,G$1,$B$1) -> #NAME? | H48: =_xll.EQNXTDZ($A$1,$B48,H$1,$B$1) -> #NAME? | I48: =_xll.EQNXTDZ($A$1,$B48,I$1,$B$1) -> #NAME? | J48: =_xll.EQNXTDZ($A$1,$B48,J$1,$B$1) -> #NAME? | ... AF48: =_xll.EQNXTDZ($A$1,$B48,AF$1,$B$1) -> #NAME?
A49: Deferred Tax Assets / Liabilities | B49: BS_NET_DEF_TAX_NF | C49: =_xll.EQNXTDZ($A$1,$B49,C$1,$B$1) -> #NAME? | D49: =_xll.EQNXTDZ($A$1,$B49,D$1,$B$1) -> #NAME? | E49: =_xll.EQNXTDZ($A$1,$B49,E$1,$B$1) -> #NAME? | F49: =_xll.EQNXTDZ($A$1,$B49,F$1,$B$1) -> #NAME? | G49: =_xll.EQNXTDZ($A$1,$B49,G$1,$B$1) -> #NAME? | H49: =_xll.EQNXTDZ($A$1,$B49,H$1,$B$1) -> #NAME? | I49: =_xll.EQNXTDZ($A$1,$B49,I$1,$B$1) -> #NAME? | J49: =_xll.EQNXTDZ($A$1,$B49,J$1,$B$1) -> #NAME? | ... AF49: =_xll.EQNXTDZ($A$1,$B49,AF$1,$B$1) -> #NAME?
A50: Other Long Term Liabilities | B50: BS_OTH_LT_LIAB | C50: =_xll.EQNXTDZ($A$1,$B50,C$1,$B$1) -> #NAME? | D50: =_xll.EQNXTDZ($A$1,$B50,D$1,$B$1) -> #NAME? | E50: =_xll.EQNXTDZ($A$1,$B50,E$1,$B$1) -> #NAME? | F50: =_xll.EQNXTDZ($A$1,$B50,F$1,$B$1) -> #NAME? | G50: =_xll.EQNXTDZ($A$1,$B50,G$1,$B$1) -> #NAME? | H50: =_xll.EQNXTDZ($A$1,$B50,H$1,$B$1) -> #NAME? | I50: =_xll.EQNXTDZ($A$1,$B50,I$1,$B$1) -> #NAME? | J50: =_xll.EQNXTDZ($A$1,$B50,J$1,$B$1) -> #NAME? | ... AF50: =_xll.EQNXTDZ($A$1,$B50,AF$1,$B$1) -> #NAME?
A51: Long Term Trade Payables | B51: BS_LT_TRADE_PAYABLES | C51: =_xll.EQNXTDZ($A$1,$B51,C$1,$B$1) -> #NAME? | D51: =_xll.EQNXTDZ($A$1,$B51,D$1,$B$1) -> #NAME? | E51: =_xll.EQNXTDZ($A$1,$B51,E$1,$B$1) -> #NAME? | F51: =_xll.EQNXTDZ($A$1,$B51,F$1,$B$1) -> #NAME? | G51: =_xll.EQNXTDZ($A$1,$B51,G$1,$B$1) -> #NAME? | H51: =_xll.EQNXTDZ($A$1,$B51,H$1,$B$1) -> #NAME? | I51: =_xll.EQNXTDZ($A$1,$B51,I$1,$B$1) -> #NAME? | J51: =_xll.EQNXTDZ($A$1,$B51,J$1,$B$1) -> #NAME? | ... AF51: =_xll.EQNXTDZ($A$1,$B51,AF$1,$B$1) -> #NAME?
... A99: Estimated Capital Contracts Remaining | B99: BS_ESTIMATED_CAPITAL_CONTRACT | C99: =_xll.EQNXTDZ($A$1,$B99,C$1,$B$1) -> #NAME? | D99: =_xll.EQNXTDZ($A$1,$B99,D$1,$B$1) -> #NAME? | E99: =_xll.EQNXTDZ($A$1,$B99,E$1,$B$1) -> #NAME? | F99: =_xll.EQNXTDZ($A$1,$B99,F$1,$B$1) -> #NAME? | G99: =_xll.EQNXTDZ($A$1,$B99,G$1,$B$1) -> #NAME? | H99: =_xll.EQNXTDZ($A$1,$B99,H$1,$B$1) -> #NAME? | I99: =_xll.EQNXTDZ($A$1,$B99,I$1,$B$1) -> #NAME? | J99: =_xll.EQNXTDZ($A$1,$B99,J$1,$B$1) -> #NAME? | ... AF99: =_xll.EQNXTDZ($A$1,$B99,AF$1,$B$1) -> #NAME?
A103: Field Description | B103: Field Name
A104: Equity Paid Up | B104: BS_EQUITY_PAIDUP | C104: =_xll.EQNXTDZ($A$1,$B104,C$1,$B$1) -> #NAME? | D104: =_xll.EQNXTDZ($A$1,$B104,D$1,$B$1) -> #NAME? | E104: =_xll.EQNXTDZ($A$1,$B104,E$1,$B$1) -> #NAME? | F104: =_xll.EQNXTDZ($A$1,$B104,F$1,$B$1) -> #NAME? | G104: =_xll.EQNXTDZ($A$1,$B104,G$1,$B$1) -> #NAME? | H104: =_xll.EQNXTDZ($A$1,$B104,H$1,$B$1) -> #NAME? | I104: =_xll.EQNXTDZ($A$1,$B104,I$1,$B$1) -> #NAME? | J104: =_xll.EQNXTDZ($A$1,$B104,J$1,$B$1) -> #NAME? | ... AF104: =_xll.EQNXTDZ($A$1,$B104,AF$1,$B$1) -> #NAME?
A105: Face Value | B105: BS_FACE_VALUE | C105: =_xll.EQNXTDZ($A$1,$B105,C$1,$B$1) -> #NAME? | D105: =_xll.EQNXTDZ($A$1,$B105,D$1,$B$1) -> #NAME? | E105: =_xll.EQNXTDZ($A$1,$B105,E$1,$B$1) -> #NAME? | F105: =_xll.EQNXTDZ($A$1,$B105,F$1,$B$1) -> #NAME? | G105: =_xll.EQNXTDZ($A$1,$B105,G$1,$B$1) -> #NAME? | H105: =_xll.EQNXTDZ($A$1,$B105,H$1,$B$1) -> #NAME? | I105: =_xll.EQNXTDZ($A$1,$B105,I$1,$B$1) -> #NAME? | J105: =_xll.EQNXTDZ($A$1,$B105,J$1,$B$1) -> #NAME? | ... AF105: =_xll.EQNXTDZ($A$1,$B105,AF$1,$B$1) -> #NAME?
A106: Close Price (Unit Curr.) | B106: FH_YEAR_PRICE | C106: =_xll.EQNXTDZ($A$1,$B106,C$1,$B$1) -> #NAME? | D106: =_xll.EQNXTDZ($A$1,$B106,D$1,$B$1) -> #NAME? | E106: =_xll.EQNXTDZ($A$1,$B106,E$1,$B$1) -> #NAME? | F106: =_xll.EQNXTDZ($A$1,$B106,F$1,$B$1) -> #NAME? | G106: =_xll.EQNXTDZ($A$1,$B106,G$1,$B$1) -> #NAME? | H106: =_xll.EQNXTDZ($A$1,$B106,H$1,$B$1) -> #NAME? | I106: =_xll.EQNXTDZ($A$1,$B106,I$1,$B$1) -> #NAME? | J106: =_xll.EQNXTDZ($A$1,$B106,J$1,$B$1) -> #NAME? | ... AF106: =_xll.EQNXTDZ($A$1,$B106,AF$1,$B$1) -> #NAME?
A107: High Price (Unit Curr.) | B107: FH_HIGH | C107: =_xll.EQNXTDZ($A$1,$B107,C$1,$B$1) -> #NAME? | D107: =_xll.EQNXTDZ($A$1,$B107,D$1,$B$1) -> #NAME? | E107: =_xll.EQNXTDZ($A$1,$B107,E$1,$B$1) -> #NAME? | F107: =_xll.EQNXTDZ($A$1,$B107,F$1,$B$1) -> #NAME? | G107: =_xll.EQNXTDZ($A$1,$B107,G$1,$B$1) -> #NAME? | H107: =_xll.EQNXTDZ($A$1,$B107,H$1,$B$1) -> #NAME? | I107: =_xll.EQNXTDZ($A$1,$B107,I$1,$B$1) -> #NAME? | J107: =_xll.EQNXTDZ($A$1,$B107,J$1,$B$1) -> #NAME? | ... AF107: =_xll.EQNXTDZ($A$1,$B107,AF$1,$B$1) -> #NAME?
A108: Low Price (Unit Curr.) | B108: FH_LOW | C108: =_xll.EQNXTDZ($A$1,$B108,C$1,$B$1) -> #NAME? | D108: =_xll.EQNXTDZ($A$1,$B108,D$1,$B$1) -> #NAME? | E108: =_xll.EQNXTDZ($A$1,$B108,E$1,$B$1) -> #NAME? | F108: =_xll.EQNXTDZ($A$1,$B108,F$1,$B$1) -> #NAME? | G108: =_xll.EQNXTDZ($A$1,$B108,G$1,$B$1) -> #NAME? | H108: =_xll.EQNXTDZ($A$1,$B108,H$1,$B$1) -> #NAME? | I108: =_xll.EQNXTDZ($A$1,$B108,I$1,$B$1) -> #NAME? | J108: =_xll.EQNXTDZ($A$1,$B108,J$1,$B$1) -> #NAME? | ... AF108: =_xll.EQNXTDZ($A$1,$B108,AF$1,$B$1) -> #NAME?
A109: Market Capitalization | B109: FH_MCAP | C109: =_xll.EQNXTDZ($A$1,$B109,C$1,$B$1) -> #NAME? | D109: =_xll.EQNXTDZ($A$1,$B109,D$1,$B$1) -> #NAME? | E109: =_xll.EQNXTDZ($A$1,$B109,E$1,$B$1) -> #NAME? | F109: =_xll.EQNXTDZ($A$1,$B109,F$1,$B$1) -> #NAME? | G109: =_xll.EQNXTDZ($A$1,$B109,G$1,$B$1) -> #NAME? | H109: =_xll.EQNXTDZ($A$1,$B109,H$1,$B$1) -> #NAME? | I109: =_xll.EQNXTDZ($A$1,$B109,I$1,$B$1) -> #NAME? | J109: =_xll.EQNXTDZ($A$1,$B109,J$1,$B$1) -> #NAME? | ... AF109: =_xll.EQNXTDZ($A$1,$B109,AF$1,$B$1) -> #NAME?
A110: Adj DPS(Rs) | B110: FR_ADJ_DPS | C110: =_xll.EQNXTDZ($A$1,$B110,C$1,$B$1) -> #NAME? | D110: =_xll.EQNXTDZ($A$1,$B110,D$1,$B$1) -> #NAME? | E110: =_xll.EQNXTDZ($A$1,$B110,E$1,$B$1) -> #NAME? | F110: =_xll.EQNXTDZ($A$1,$B110,F$1,$B$1) -> #NAME? | G110: =_xll.EQNXTDZ($A$1,$B110,G$1,$B$1) -> #NAME? | H110: =_xll.EQNXTDZ($A$1,$B110,H$1,$B$1) -> #NAME? | I110: =_xll.EQNXTDZ($A$1,$B110,I$1,$B$1) -> #NAME? | J110: =_xll.EQNXTDZ($A$1,$B110,J$1,$B$1) -> #NAME? | ... AF110: =_xll.EQNXTDZ($A$1,$B110,AF$1,$B$1) -> #NAME?
A111: Date End | B111: SHP_DATE_END | C111: =_xll.EQNXTDZ($A$1,$B111,C$5) -> #NAME? | D111: =_xll.EQNXTDZ($A$1,$B111,D$5) -> #NAME? | E111: =_xll.EQNXTDZ($A$1,$B111,E$5) -> #NAME? | F111: =_xll.EQNXTDZ($A$1,$B111,F$5) -> #NAME? | G111: =_xll.EQNXTDZ($A$1,$B111,G$5) -> #NAME? | H111: =_xll.EQNXTDZ($A$1,$B111,H$5) -> #NAME? | I111: =_xll.EQNXTDZ($A$1,$B111,I$5) -> #NAME? | J111: =_xll.EQNXTDZ($A$1,$B111,J$5) -> #NAME? | ... AF111: =_xll.EQNXTDZ($A$1,$B111,AF$5) -> #NAME?
A112: Total of Promoter and Promoter Group | B112: SHP_TPFTOTALPROMOTER | C112: =_xll.EQNXTDZ($A$1,$B112,C$5) -> #NAME? | D112: =_xll.EQNXTDZ($A$1,$B112,D$5) -> #NAME? | E112: =_xll.EQNXTDZ($A$1,$B112,E$5) -> #NAME? | F112: =_xll.EQNXTDZ($A$1,$B112,F$5) -> #NAME? | G112: =_xll.EQNXTDZ($A$1,$B112,G$5) -> #NAME? | H112: =_xll.EQNXTDZ($A$1,$B112,H$5) -> #NAME? | I112: =_xll.EQNXTDZ($A$1,$B112,I$5) -> #NAME? | J112: =_xll.EQNXTDZ($A$1,$B112,J$5) -> #NAME? | ... AF112: =_xll.EQNXTDZ($A$1,$B112,AF$5) -> #NAME?
A113: Total of Promoter and Promoter Group Pledged | B113: SHP_PSHFTOTALPROMOTER | C113: =_xll.EQNXTDZ($A$1,$B113,C$5) -> #NAME? | D113: =_xll.EQNXTDZ($A$1,$B113,D$5) -> #NAME? | E113: =_xll.EQNXTDZ($A$1,$B113,E$5) -> #NAME? | F113: =_xll.EQNXTDZ($A$1,$B113,F$5) -> #NAME? | G113: =_xll.EQNXTDZ($A$1,$B113,G$5) -> #NAME? | H113: =_xll.EQNXTDZ($A$1,$B113,H$5) -> #NAME? | I113: =_xll.EQNXTDZ($A$1,$B113,I$5) -> #NAME? | J113: =_xll.EQNXTDZ($A$1,$B113,J$5) -> #NAME? | ... AF113: =_xll.EQNXTDZ($A$1,$B113,AF$5) -> #NAME?

Sheet QTR Share Price
A1: ='QTR Raw'!A1 -> 219412 | C1: 201206 | D1: 201207 | E1: 201208 | F1: 201209 | G1: 201210 | H1: 201211 | I1: 201212 | J1: 201301 | K1: 201302 | L1: 201303 | M1: 201304 | N1: 201305 | O1: 201306 | P1: 201307 | Q1: 201308 | R1: 201309 | S1: 201310 | T1: 201311 | U1: 201312 | V1: 201401 | W1: 201402 | X1: 201403 | Y1: 201404 | Z1: 201405 | AA1: 201406 | AB1: 201407 | AC1: 201408 | AD1: 201409 | AE1: 201410 | AF1: 201411 | AG1: 201412 | AH1: 201501 | AI1: 201502 | AJ1: 201503 | AK1: 201504 | AL1: 201505 | AM1: 201506 | AN1: 201507 | AO1: 201508 | AP1: 201509 | AQ1: 201510 | AR1: 201511 | AS1: 201512 | AT1: 201601 | AU1: 201602 | AV1: 201603 | AW1: 201604 | AX1: 201605 | AY1: 201606 | AZ1: 201607 | BA1: 201608 | BB1: 201609 | BC1: 201610 | BD1: 201611 | BE1: 201612 | BF1: 201701 | BG1: 201702 | BH1: 201703 | BI1: 201704 | BJ1: 201705 | BK1: 201706 | BL1: 201707 | BM1: 201708 | BN1: 201709 | BO1: 201710 | BP1: 201711 | BQ1: 201712 | BR1: 201801 | BS1: 201802 | BT1: 201803 | BU1: 201804 | BV1: 201805 | BW1: 201806 | BX1: 201807 | BY1: 201808 | BZ1: 201809 | CA1: 201810 | CB1: 201811 | CC1: 201812 | CD1: 201901 | CE1: 201902 | CF1: 201903 | CG1: 201904 | CH1: 201905 | CI1: 201906 | CJ1: 201907 | CK1: 201908 | CL1: 201909 | CM1: 201910 | CN1: 201911 | CO1: 201912 | CP1: 202001 | CQ1: 202002 | CR1: 202003 | CS1: 202004 | CT1: 202005 | CU1: 202006 | CV1: 202007 | CW1: 202008 | CX1: 202009 | CY1: 202010 | CZ1: 202011 | DA1: 202012 | DB1: 202101 | DC1: 202102 | DD1: 202103 | DE1: 202104 | DF1: 202105 | DG1: 202106 | DH1: 202107 | DI1: 202108 | DJ1: 202109 | DK1: 202110 | DL1: 202111 | DM1: 202112 | DN1: 202201 | DO1: 202202 | DP1: 202203 | DQ1: 202204 | DR1: 202205 | DS1: 202206 | DT1: 202207 | DU1: 202208 | DV1: 202209 | DW1: 202210 | DX1: 202211 | DY1: 202212 | DZ1: 202301 | EA1: 202302 | EB1: 202303 | EC1: 202304 | ED1: 202305 | EE1: 202306 | EF1: 202307 | EG1: 202308 | EH1: 202309 | EI1: 202310 | EJ1: 202311 | EK1: 202312 | EL1: 202401 | EM1: 202402 | EN1: 202403 | EO1: 202404 | EP1: 202405 | EQ1: 202406 | ER1: 202407 | ES1: 202408 | ET1: 202409 | EU1: 202410 | EV1: 202411 | EW1: 202412 | EX1: 202501 | EY1: 202502 | EZ1: 202503 | FA1: 202504 | FB1: 202505 | FC1: 202506 | FD1: 202507 | FE1: 202508 | FF1: 202509 | FG1: 202510 | FH1: 202511 | FI1: 202512 | FJ1: 202601 | FK1: 202602 | FL1: 202603 | FM1: 202604 | FN1: 202605 | FO1: 202606 | FP1: 202607 | FQ1: 202608 | FR1: 202609 | FS1: 202610 | FT1: 202611 | FU1: 202612 | FV1: 202701 | FW1: 202702 | FX1: 202703 | FY1: 202704 | FZ1: 202705 | GA1: 202706 | GB1: 202707 | GC1: 202708 | GD1: 202709 | GE1: 202710 | GF1: 202711 | GG1: 202712 | GH1: 202801 | GI1: 202802 | GJ1: 202803 | GK1: 202804 | GL1: 202805 | GM1: 202806 | GN1: 202807 | GO1: 202808 | GP1: 202809 | GQ1: 202810 | GR1: 202811 | GS1: 202812 | GT1: 202901 | GU1: 202902 | GV1: 202903 | GW1: 202904 | GX1: 202905 | GY1: 202906 | GZ1: 202907 | HA1: 202908 | HB1: 202909 | HC1: 202910 | HD1: 202911 | HE1: 202912 | HF1: 203001 | HG1: 203002 | HH1: 203003 | HM1: 201206 | HN1: 201207 | HO1: 201208 | HP1: 201209 | HQ1: 201212 | HR1: 201303 | HS1: 201306 | HT1: 201309 | HU1: 201312 | HV1: 201403 | HW1: 201406 | HX1: 201409 | HY1: 201412 | HZ1: 201503 | IA1: 201506 | IB1: 201509 | IC1: 201512 | ID1: 201603 | IE1: 201606 | IF1: 201609 | IG1: 201612 | IH1: 201703 | II1: 201706 | IJ1: 201709 | IK1: 201712 | IL1: 201803 | IM1: 201806 | IN1: 201809 | IO1: 201812 | IP1: 201903 | IQ1: 201906 | IR1: 201909 | IS1: 201912 | IT1: 202003 | IU1: 202006 | IV1: 202009 | IW1: 202012 | IX1: 202103 | IY1: 202106 | IZ1: 202109 | JA1: 202112 | JB1: 202203 | JC1: 202206 | JD1: 202209 | JE1: 202212 | JF1: 202303 | JG1: 202306 | JH1: 202309 | JI1: 202312 | JJ1: 202403 | JK1: 202406 | JL1: 202409 | JM1: 202412 | JN1: 202503 | JO1: 202506 | JP1: 202509 | JQ1: 202512 | JR1: 202603 | JS1: 202606 | JT1: 202609 | JU1: 202612 | JV1: 202703 | JW1: 202706 | JX1: 202709 | JY1: 202712 | JZ1: 202803 | KA1: 202806 | KB1: 202809 | KC1: 202812 | KD1: 202903 | KE1: 202906 | KF1: 202909 | KG1: 202912 | KH1: 203003
FF2: 45901 | FG2: =+EOMONTH(FF2,1) -> 45961 | FH2: =+EOMONTH(FG2,1) -> 45991 | FI2: =+EOMONTH(FH2,1) -> 46022 | FJ2: =+EOMONTH(FI2,1) -> 46053 | FK2: =+EOMONTH(FJ2,1) -> 46081 | FL2: =+EOMONTH(FK2,1) -> 46112 | FM2: =+EOMONTH(FL2,1) -> 46142 | FN2: =+EOMONTH(FM2,1) -> 46173 | ... HH2: =+EOMONTH(HG2,1) -> 47573
A4: Field Description | B4: Field Name
A5: MonthEnd | B5: NMONTH_MONTHEND | C5: {=_xll.EQNXTDZ($A$1,$B5,C$1)} -> #NAME? | D5: {=_xll.EQNXTDZ($A$1,$B5,D$1)} -> #NAME? | E5: {=_xll.EQNXTDZ($A$1,$B5,E$1)} -> #NAME? | F5: {=_xll.EQNXTDZ($A$1,$B5,F$1)} -> #NAME? | G5: {=_xll.EQNXTDZ($A$1,$B5,G$1)} -> #NAME? | H5: {=_xll.EQNXTDZ($A$1,$B5,H$1)} -> #NAME? | I5: {=_xll.EQNXTDZ($A$1,$B5,I$1)} -> #NAME? | J5: {=_xll.EQNXTDZ($A$1,$B5,J$1)} -> #NAME? | ... HH5: {=_xll.EQNXTDZ($A$1,$B5,HH$1)} -> #NAME?
A6: Open | B6: NMONTH_OPEN | C6: {=_xll.EQNXTDZ($A$1,$B6,C$1)} -> #NAME? | D6: {=_xll.EQNXTDZ($A$1,$B6,D$1)} -> #NAME? | E6: {=_xll.EQNXTDZ($A$1,$B6,E$1)} -> #NAME? | F6: {=_xll.EQNXTDZ($A$1,$B6,F$1)} -> #NAME? | G6: {=_xll.EQNXTDZ($A$1,$B6,G$1)} -> #NAME? | H6: {=_xll.EQNXTDZ($A$1,$B6,H$1)} -> #NAME? | I6: {=_xll.EQNXTDZ($A$1,$B6,I$1)} -> #NAME? | J6: {=_xll.EQNXTDZ($A$1,$B6,J$1)} -> #NAME? | ... HH6: {=_xll.EQNXTDZ($A$1,$B6,HH$1)} -> #NAME?
A7: High | B7: NMONTH_HIGH | C7: {=_xll.EQNXTDZ($A$1,$B7,C$1)} -> #NAME? | D7: {=_xll.EQNXTDZ($A$1,$B7,D$1)} -> #NAME? | E7: {=_xll.EQNXTDZ($A$1,$B7,E$1)} -> #NAME? | F7: {=_xll.EQNXTDZ($A$1,$B7,F$1)} -> #NAME? | G7: {=_xll.EQNXTDZ($A$1,$B7,G$1)} -> #NAME? | H7: {=_xll.EQNXTDZ($A$1,$B7,H$1)} -> #NAME? | I7: {=_xll.EQNXTDZ($A$1,$B7,I$1)} -> #NAME? | J7: {=_xll.EQNXTDZ($A$1,$B7,J$1)} -> #NAME? | ... HH7: {=_xll.EQNXTDZ($A$1,$B7,HH$1)} -> #NAME? | HP7: =+MAX(D7:F7) -> #NAME? | HQ7: =+MAX(G7:I7) -> #NAME? | HR7: =+MAX(J7:L7) -> #NAME? | HS7: =+MAX(M7:O7) -> #NAME? | HT7: =+MAX(P7:R7) -> #NAME? | HU7: =+MAX(S7:U7) -> #NAME? | HV7: =+MAX(V7:X7) -> #NAME? | HW7: =+MAX(Y7:AA7) -> #NAME? | HX7: =+MAX(AB7:AD7) -> #NAME? | HY7: =+MAX(AE7:AG7) -> #NAME? | HZ7: =+MAX(AH7:AJ7) -> #NAME? | IA7: =+MAX(AK7:AM7) -> #NAME? | IB7: =+MAX(AN7:AP7) -> #NAME? | IC7: =+MAX(AQ7:AS7) -> #NAME? | ID7: =+MAX(AT7:AV7) -> #NAME? | IE7: =+MAX(AW7:AY7) -> #NAME? | IF7: =+MAX(AZ7:BB7) -> #NAME? | IG7: =+MAX(BC7:BE7) -> #NAME? | IH7: =+MAX(BF7:BH7) -> #NAME? | II7: =+MAX(BI7:BK7) -> #NAME? | IJ7: =+MAX(BL7:BN7) -> #NAME? | IK7: =+MAX(BO7:BQ7) -> #NAME? | IL7: =+MAX(BR7:BT7) -> #NAME? | IM7: =+MAX(BU7:BW7) -> #NAME? | IN7: =+MAX(BX7:BZ7) -> #NAME? | IO7: =+MAX(CA7:CC7) -> #NAME? | IP7: =+MAX(CD7:CF7) -> #NAME? | IQ7: =+MAX(CG7:CI7) -> #NAME? | IR7: =+MAX(CJ7:CL7) -> #NAME? | IS7: =+MAX(CM7:CO7) -> #NAME? | IT7: =+MAX(CP7:CR7) -> #NAME? | IU7: =+MAX(CS7:CU7) -> #NAME? | IV7: =+MAX(CV7:CX7) -> #NAME? | IW7: =+MAX(CY7:DA7) -> #NAME? | IX7: =+MAX(DB7:DD7) -> #NAME? | IY7: =+MAX(DE7:DG7) -> #NAME? | IZ7: =+MAX(DH7:DJ7) -> #NAME? | JA7: =+MAX(DK7:DM7) -> #NAME? | JB7: =+MAX(DN7:DP7) -> #NAME? | JC7: =+MAX(DQ7:DS7) -> #NAME? | JD7: =+MAX(DT7:DV7) -> #NAME? | JE7: =+MAX(DW7:DY7) -> #NAME? | JF7: =+MAX(DZ7:EB7) -> #NAME? | JG7: =+MAX(EC7:EE7) -> #NAME? | JH7: =+MAX(EF7:EH7) -> #NAME? | JI7: =+MAX(EI7:EK7) -> #NAME? | JJ7: =+MAX(EL7:EN7) -> #NAME? | JK7: =MAX(EO7:EQ7) -> #NAME? | JL7: =MAX(ER7:ET7) -> #NAME? | JM7: =MAX(EU7:EW7) -> #NAME? | JN7: =MAX(EX7:EZ7) -> #NAME? | JO7: =MAX(FA7:FC7) -> #NAME? | JP7: =MAX(FD7:FF7) -> #NAME? | JQ7: =MAX(FG7:FI7) -> #NAME? | JR7: =MAX(FJ7:FL7) -> #NAME? | JS7: =MAX(FM7:FO7) -> #NAME? | JT7: =MAX(FP7:FR7) -> #NAME? | JU7: =MAX(FS7:FU7) -> #NAME? | JV7: =MAX(FV7:FX7) -> #NAME? | JW7: =MAX(FY7:GA7) -> #NAME? | JX7: =MAX(GB7:GD7) -> #NAME? | JY7: =MAX(GE7:GG7) -> #NAME? | JZ7: =MAX(GH7:GJ7) -> #NAME? | KA7: =MAX(GK7:GM7) -> #NAME? | KB7: =MAX(GN7:GP7) -> #NAME? | KC7: =MAX(GQ7:GS7) -> #NAME? | KD7: =MAX(GT7:GV7) -> #NAME? | KE7: =MAX(GW7:GY7) -> #NAME? | KF7: =MAX(GZ7:HB7) -> #NAME? | KG7: =MAX(HC7:HE7) -> #NAME? | KH7: =MAX(HF7:HH7) -> #NAME?
A8: Low | B8: NMONTH_LOW | C8: {=_xll.EQNXTDZ($A$1,$B8,C$1)} -> #NAME? | D8: {=_xll.EQNXTDZ($A$1,$B8,D$1)} -> #NAME? | E8: {=_xll.EQNXTDZ($A$1,$B8,E$1)} -> #NAME? | F8: {=_xll.EQNXTDZ($A$1,$B8,F$1)} -> #NAME? | G8: {=_xll.EQNXTDZ($A$1,$B8,G$1)} -> #NAME? | H8: {=_xll.EQNXTDZ($A$1,$B8,H$1)} -> #NAME? | I8: {=_xll.EQNXTDZ($A$1,$B8,I$1)} -> #NAME? | J8: {=_xll.EQNXTDZ($A$1,$B8,J$1)} -> #NAME? | ... HH8: {=_xll.EQNXTDZ($A$1,$B8,HH$1)} -> #NAME? | HP8: =+MIN(D8:F8) -> #NAME? | HQ8: =+MIN(G8:I8) -> #NAME? | HR8: =+MIN(J8:L8) -> #NAME? | HS8: =+MIN(M8:O8) -> #NAME? | HT8: =+MIN(P8:R8) -> #NAME? | HU8: =+MIN(S8:U8) -> #NAME? | HV8: =+MIN(V8:X8) -> #NAME? | HW8: =+MIN(Y8:AA8) -> #NAME? | HX8: =+MIN(AB8:AD8) -> #NAME? | HY8: =+MIN(AE8:AG8) -> #NAME? | HZ8: =+MIN(AH8:AJ8) -> #NAME? | IA8: =+MIN(AK8:AM8) -> #NAME? | IB8: =+MIN(AN8:AP8) -> #NAME? | IC8: =+MIN(AQ8:AS8) -> #NAME? | ID8: =+MIN(AT8:AV8) -> #NAME? | IE8: =+MIN(AW8:AY8) -> #NAME? | IF8: =+MIN(AZ8:BB8) -> #NAME? | IG8: =+MIN(BC8:BE8) -> #NAME? | IH8: =+MIN(BF8:BH8) -> #NAME? | II8: =+MIN(BI8:BK8) -> #NAME? | IJ8: =+MIN(BL8:BN8) -> #NAME? | IK8: =+MIN(BO8:BQ8) -> #NAME? | IL8: =+MIN(BR8:BT8) -> #NAME? | IM8: =+MIN(BU8:BW8) -> #NAME? | IN8: =+MIN(BX8:BZ8) -> #NAME? | IO8: =+MIN(CA8:CC8) -> #NAME? | IP8: =+MIN(CD8:CF8) -> #NAME? | IQ8: =+MIN(CG8:CI8) -> #NAME? | IR8: =+MIN(CJ8:CL8) -> #NAME? | IS8: =+MIN(CM8:CO8) -> #NAME? | IT8: =+MIN(CP8:CR8) -> #NAME? | IU8: =+MIN(CS8:CU8) -> #NAME? | IV8: =+MIN(CV8:CX8) -> #NAME? | IW8: =+MIN(CY8:DA8) -> #NAME? | IX8: =+MIN(DB8:DD8) -> #NAME? | IY8: =+MIN(DE8:DG8) -> #NAME? | IZ8: =+MIN(DH8:DJ8) -> #NAME? | JA8: =+MIN(DK8:DM8) -> #NAME? | JB8: =+MIN(DN8:DP8) -> #NAME? | JC8: =+MIN(DQ8:DS8) -> #NAME? | JD8: =+MIN(DT8:DV8) -> #NAME? | JE8: =+MIN(DW8:DY8) -> #NAME? | JF8: =+MIN(DZ8:EB8) -> #NAME? | JG8: =+MIN(EC8:EE8) -> #NAME? | JH8: =+MIN(EF8:EH8) -> #NAME? | JI8: =+MIN(EI8:EK8) -> #NAME? | JJ8: =+MIN(EL8:EN8) -> #NAME? | JK8: =MIN(EO8:EQ8) -> #NAME? | JL8: =MIN(ER8:ET8) -> #NAME? | JM8: =MIN(EU8:EW8) -> #NAME? | JN8: =MIN(EX8:EZ8) -> #NAME? | JO8: =MIN(FA8:FC8) -> #NAME? | JP8: =MIN(FD8:FF8) -> #NAME? | JQ8: =MIN(FG8:FI8) -> #NAME? | JR8: =MIN(FJ8:FL8) -> #NAME? | JS8: =MIN(FM8:FO8) -> #NAME? | JT8: =MIN(FP8:FR8) -> #NAME? | JU8: =MIN(FS8:FU8) -> #NAME? | JV8: =MIN(FV8:FX8) -> #NAME? | JW8: =MIN(FY8:GA8) -> #NAME? | JX8: =MIN(GB8:GD8) -> #NAME? | JY8: =MIN(GE8:GG8) -> #NAME? | JZ8: =MIN(GH8:GJ8) -> #NAME? | KA8: =MIN(GK8:GM8) -> #NAME? | KB8: =MIN(GN8:GP8) -> #NAME? | KC8: =MIN(GQ8:GS8) -> #NAME? | KD8: =MIN(GT8:GV8) -> #NAME? | KE8: =MIN(GW8:GY8) -> #NAME? | KF8: =MIN(GZ8:HB8) -> #NAME? | KG8: =MIN(HC8:HE8) -> #NAME? | KH8: =MIN(HF8:HH8) -> #NAME?
A9: Close | B9: NMONTH_CLOSE | C9: {=_xll.EQNXTDZ($A$1,$B9,C$1)} -> #NAME? | D9: {=_xll.EQNXTDZ($A$1,$B9,D$1)} -> #NAME? | E9: {=_xll.EQNXTDZ($A$1,$B9,E$1)} -> #NAME? | F9: {=_xll.EQNXTDZ($A$1,$B9,F$1)} -> #NAME? | G9: {=_xll.EQNXTDZ($A$1,$B9,G$1)} -> #NAME? | H9: {=_xll.EQNXTDZ($A$1,$B9,H$1)} -> #NAME? | I9: {=_xll.EQNXTDZ($A$1,$B9,I$1)} -> #NAME? | J9: {=_xll.EQNXTDZ($A$1,$B9,J$1)} -> #NAME? | ... HH9: {=_xll.EQNXTDZ($A$1,$B9,HH$1)} -> #NAME? | HP9: =+F9 -> #NAME? | HQ9: =+I9 -> #NAME? | HR9: =+L9 -> #NAME? | HS9: =+O9 -> #NAME? | HT9: =+R9 -> #NAME? | HU9: =+U9 -> #NAME? | HV9: =+X9 -> #NAME? | HW9: =+AA9 -> #NAME? | HX9: =+AD9 -> #NAME? | HY9: =+AG9 -> #NAME? | HZ9: =+AJ9 -> #NAME? | IA9: =+AM9 -> #NAME? | IB9: =+AP9 -> #NAME? | IC9: =+AS9 -> #NAME? | ID9: =+AV9 -> #NAME? | IE9: =+AY9 -> #NAME? | IF9: =+BB9 -> #NAME? | IG9: =+BE9 -> #NAME? | IH9: =+BH9 -> #NAME? | II9: =+BK9 -> #NAME? | IJ9: =+BN9 -> #NAME? | IK9: =+BQ9 -> #NAME? | IL9: =+BT9 -> #NAME? | IM9: =+BW9 -> #NAME? | IN9: =+BZ9 -> #NAME? | IO9: =+CC9 -> #NAME? | IP9: =+CF9 -> #NAME? | IQ9: =+CI9 -> #NAME? | IR9: =+CL9 -> #NAME? | IS9: =+CO9 -> #NAME? | IT9: =+CR9 -> #NAME? | IU9: =+CU9 -> #NAME? | IV9: =+CX9 -> #NAME? | IW9: =+DA9 -> #NAME? | IX9: =+DD9 -> #NAME? | IY9: =+DG9 -> #NAME? | IZ9: =+DJ9 -> #NAME? | JA9: =+DM9 -> #NAME? | JB9: =+DP9 -> #NAME? | JC9: =+DS9 -> #NAME? | JD9: =+DV9 -> #NAME? | JE9: =+DY9 -> #NAME? | JF9: =+EB9 -> #NAME? | JG9: =+EE9 -> #NAME? | JH9: =+EH9 -> #NAME? | JI9: =+EK9 -> #NAME? | JJ9: =+EN9 -> #NAME? | JK9: =EQ9 -> #NAME? | JL9: =ET9 -> #NAME? | JM9: =EW9 -> #NAME? | JN9: =EZ9 -> #NAME? | JO9: =FC9 -> #NAME? | JP9: =FF9 -> #NAME? | JQ9: =FI9 -> #NAME? | JR9: =FL9 -> #NAME? | JS9: =FO9 -> #NAME? | JT9: =FR9 -> #NAME? | JU9: =FU9 -> #NAME? | JV9: =FX9 -> #NAME? | JW9: =GA9 -> #NAME? | JX9: =GD9 -> #NAME? | JY9: =GG9 -> #NAME? | JZ9: =GJ9 -> #NAME? | KA9: =GM9 -> #NAME? | KB9: =GP9 -> #NAME? | KC9: =GS9 -> #NAME? | KD9: =GV9 -> #NAME? | KE9: =GY9 -> #NAME? | KF9: =HB9 -> #NAME? | KG9: =HE9 -> #NAME? | KH9: =HH9 -> #NAME?
A11: Field Description | B11: Field Name | C11: {=_xll.EQNXTDZ($A$1,$B11,C$1)} -> #NAME? | D11: {=_xll.EQNXTDZ($A$1,$B11,D$1)} -> #NAME? | E11: {=_xll.EQNXTDZ($A$1,$B11,E$1)} -> #NAME? | F11: {=_xll.EQNXTDZ($A$1,$B11,F$1)} -> #NAME? | G11: {=_xll.EQNXTDZ($A$1,$B11,G$1)} -> #NAME? | H11: {=_xll.EQNXTDZ($A$1,$B11,H$1)} -> #NAME? | I11: {=_xll.EQNXTDZ($A$1,$B11,I$1)} -> #NAME? | J11: {=_xll.EQNXTDZ($A$1,$B11,J$1)} -> #NAME? | ... HH11: {=_xll.EQNXTDZ($A$1,$B11,HH$1)} -> #NAME?
A12: Month End | B12: BMONTH_MONTHEND | C12: {=_xll.EQNXTDZ($A$1,$B12,C$1)} -> #NAME? | D12: {=_xll.EQNXTDZ($A$1,$B12,D$1)} -> #NAME? | E12: {=_xll.EQNXTDZ($A$1,$B12,E$1)} -> #NAME? | F12: {=_xll.EQNXTDZ($A$1,$B12,F$1)} -> #NAME? | G12: {=_xll.EQNXTDZ($A$1,$B12,G$1)} -> #NAME? | H12: {=_xll.EQNXTDZ($A$1,$B12,H$1)} -> #NAME? | I12: {=_xll.EQNXTDZ($A$1,$B12,I$1)} -> #NAME? | J12: {=_xll.EQNXTDZ($A$1,$B12,J$1)} -> #NAME? | ... HH12: {=_xll.EQNXTDZ($A$1,$B12,HH$1)} -> #NAME?
A13: Open | B13: BMONTH_OPEN | C13: {=_xll.EQNXTDZ($A$1,$B13,C$1)} -> #NAME? | D13: {=_xll.EQNXTDZ($A$1,$B13,D$1)} -> #NAME? | E13: {=_xll.EQNXTDZ($A$1,$B13,E$1)} -> #NAME? | F13: {=_xll.EQNXTDZ($A$1,$B13,F$1)} -> #NAME? | G13: {=_xll.EQNXTDZ($A$1,$B13,G$1)} -> #NAME? | H13: {=_xll.EQNXTDZ($A$1,$B13,H$1)} -> #NAME? | I13: {=_xll.EQNXTDZ($A$1,$B13,I$1)} -> #NAME? | J13: {=_xll.EQNXTDZ($A$1,$B13,J$1)} -> #NAME? | ... HH13: {=_xll.EQNXTDZ($A$1,$B13,HH$1)} -> #NAME?
A14: High | B14: BMONTH_HIGH | C14: {=_xll.EQNXTDZ($A$1,$B14,C$1)} -> #NAME? | D14: {=_xll.EQNXTDZ($A$1,$B14,D$1)} -> #NAME? | E14: {=_xll.EQNXTDZ($A$1,$B14,E$1)} -> #NAME? | F14: {=_xll.EQNXTDZ($A$1,$B14,F$1)} -> #NAME? | G14: {=_xll.EQNXTDZ($A$1,$B14,G$1)} -> #NAME? | H14: {=_xll.EQNXTDZ($A$1,$B14,H$1)} -> #NAME? | I14: {=_xll.EQNXTDZ($A$1,$B14,I$1)} -> #NAME? | J14: {=_xll.EQNXTDZ($A$1,$B14,J$1)} -> #NAME? | ... HH14: {=_xll.EQNXTDZ($A$1,$B14,HH$1)} -> #NAME? | HP14: =+MAX(D14:F14) -> #NAME? | HQ14: =+MAX(G14:I14) -> #NAME? | HR14: =+MAX(J14:L14) -> #NAME? | HS14: =+MAX(M14:O14) -> #NAME? | HT14: =+MAX(P14:R14) -> #NAME? | HU14: =+MAX(S14:U14) -> #NAME? | HV14: =+MAX(V14:X14) -> #NAME? | HW14: =+MAX(Y14:AA14) -> #NAME? | HX14: =+MAX(AB14:AD14) -> #NAME? | HY14: =+MAX(AE14:AG14) -> #NAME? | HZ14: =+MAX(AH14:AJ14) -> #NAME? | IA14: =+MAX(AK14:AM14) -> #NAME? | IB14: =+MAX(AN14:AP14) -> #NAME? | IC14: =+MAX(AQ14:AS14) -> #NAME? | ID14: =+MAX(AT14:AV14) -> #NAME? | IE14: =+MAX(AW14:AY14) -> #NAME? | IF14: =+MAX(AZ14:BB14) -> #NAME? | IG14: =+MAX(BC14:BE14) -> #NAME? | IH14: =+MAX(BF14:BH14) -> #NAME? | II14: =+MAX(BI14:BK14) -> #NAME? | IJ14: =+MAX(BL14:BN14) -> #NAME? | IK14: =+MAX(BO14:BQ14) -> #NAME? | IL14: =+MAX(BR14:BT14) -> #NAME? | IM14: =+MAX(BU14:BW14) -> #NAME? | IN14: =+MAX(BX14:BZ14) -> #NAME? | IO14: =+MAX(CA14:CC14) -> #NAME? | IP14: =+MAX(CD14:CF14) -> #NAME? | IQ14: =+MAX(CG14:CI14) -> #NAME? | IR14: =+MAX(CJ14:CL14) -> #NAME? | IS14: =+MAX(CM14:CO14) -> #NAME? | IT14: =+MAX(CP14:CR14) -> #NAME? | IU14: =+MAX(CS14:CU14) -> #NAME? | IV14: =+MAX(CV14:CX14) -> #NAME? | IW14: =+MAX(CY14:DA14) -> #NAME? | IX14: =+MAX(DB14:DD14) -> #NAME? | IY14: =+MAX(DE14:DG14) -> #NAME? | IZ14: =+MAX(DH14:DJ14) -> #NAME? | JA14: =+MAX(DK14:DM14) -> #NAME? | JB14: =+MAX(DN14:DP14) -> #NAME? | JC14: =+MAX(DQ14:DS14) -> #NAME? | JD14: =+MAX(DT14:DV14) -> #NAME? | JE14: =+MAX(DW14:DY14) -> #NAME? | JF14: =+MAX(DZ14:EB14) -> #NAME? | JG14: =+MAX(EC14:EE14) -> #NAME? | JH14: =+MAX(EF14:EH14) -> #NAME? | JI14: =+MAX(EI14:EK14) -> #NAME? | JJ14: =+MAX(EL14:EN14) -> #NAME? | JK14: =MAX(EO14:EQ14) -> #NAME? | JL14: =MAX(ER14:ET14) -> #NAME? | JM14: =MAX(EU14:EW14) -> #NAME? | JN14: =MAX(EX14:EZ14) -> #NAME? | JO14: =MAX(FA14:FC14) -> #NAME? | JP14: =MAX(FD14:FF14) -> #NAME? | JQ14: =MAX(FG14:FI14) -> #NAME? | JR14: =MAX(FJ14:FL14) -> #NAME? | JS14: =MAX(FM14:FO14) -> #NAME? | JT14: =MAX(FP14:FR14) -> #NAME? | JU14: =MAX(FS14:FU14) -> #NAME? | JV14: =MAX(FV14:FX14) -> #NAME? | JW14: =MAX(FY14:GA14) -> #NAME? | JX14: =MAX(GB14:GD14) -> #NAME? | JY14: =MAX(GE14:GG14) -> #NAME? | JZ14: =MAX(GH14:GJ14) -> #NAME? | KA14: =MAX(GK14:GM14) -> #NAME? | KB14: =MAX(GN14:GP14) -> #NAME? | KC14: =MAX(GQ14:GS14) -> #NAME? | KD14: =MAX(GT14:GV14) -> #NAME? | KE14: =MAX(GW14:GY14) -> #NAME? | KF14: =MAX(GZ14:HB14) -> #NAME? | KG14: =MAX(HC14:HE14) -> #NAME? | KH14: =MAX(HF14:HH14) -> #NAME?
A15: Low | B15: BMONTH_LOW | C15: {=_xll.EQNXTDZ($A$1,$B15,C$1)} -> #NAME? | D15: {=_xll.EQNXTDZ($A$1,$B15,D$1)} -> #NAME? | E15: {=_xll.EQNXTDZ($A$1,$B15,E$1)} -> #NAME? | F15: {=_xll.EQNXTDZ($A$1,$B15,F$1)} -> #NAME? | G15: {=_xll.EQNXTDZ($A$1,$B15,G$1)} -> #NAME? | H15: {=_xll.EQNXTDZ($A$1,$B15,H$1)} -> #NAME? | I15: {=_xll.EQNXTDZ($A$1,$B15,I$1)} -> #NAME? | J15: {=_xll.EQNXTDZ($A$1,$B15,J$1)} -> #NAME? | ... HH15: {=_xll.EQNXTDZ($A$1,$B15,HH$1)} -> #NAME? | HP15: =+MIN(D15:F15) -> #NAME? | HQ15: =+MIN(G15:I15) -> #NAME? | HR15: =+MIN(J15:L15) -> #NAME? | HS15: =+MIN(M15:O15) -> #NAME? | HT15: =+MIN(P15:R15) -> #NAME? | HU15: =+MIN(S15:U15) -> #NAME? | HV15: =+MIN(V15:X15) -> #NAME? | HW15: =+MIN(Y15:AA15) -> #NAME? | HX15: =+MIN(AB15:AD15) -> #NAME? | HY15: =+MIN(AE15:AG15) -> #NAME? | HZ15: =+MIN(AH15:AJ15) -> #NAME? | IA15: =+MIN(AK15:AM15) -> #NAME? | IB15: =+MIN(AN15:AP15) -> #NAME? | IC15: =+MIN(AQ15:AS15) -> #NAME? | ID15: =+MIN(AT15:AV15) -> #NAME? | IE15: =+MIN(AW15:AY15) -> #NAME? | IF15: =+MIN(AZ15:BB15) -> #NAME? | IG15: =+MIN(BC15:BE15) -> #NAME? | IH15: =+MIN(BF15:BH15) -> #NAME? | II15: =+MIN(BI15:BK15) -> #NAME? | IJ15: =+MIN(BL15:BN15) -> #NAME? | IK15: =+MIN(BO15:BQ15) -> #NAME? | IL15: =+MIN(BR15:BT15) -> #NAME? | IM15: =+MIN(BU15:BW15) -> #NAME? | IN15: =+MIN(BX15:BZ15) -> #NAME? | IO15: =+MIN(CA15:CC15) -> #NAME? | IP15: =+MIN(CD15:CF15) -> #NAME? | IQ15: =+MIN(CG15:CI15) -> #NAME? | IR15: =+MIN(CJ15:CL15) -> #NAME? | IS15: =+MIN(CM15:CO15) -> #NAME? | IT15: =+MIN(CP15:CR15) -> #NAME? | IU15: =+MIN(CS15:CU15) -> #NAME? | IV15: =+MIN(CV15:CX15) -> #NAME? | IW15: =+MIN(CY15:DA15) -> #NAME? | IX15: =+MIN(DB15:DD15) -> #NAME? | IY15: =+MIN(DE15:DG15) -> #NAME? | IZ15: =+MIN(DH15:DJ15) -> #NAME? | JA15: =+MIN(DK15:DM15) -> #NAME? | JB15: =+MIN(DN15:DP15) -> #NAME? | JC15: =+MIN(DQ15:DS15) -> #NAME? | JD15: =+MIN(DT15:DV15) -> #NAME? | JE15: =+MIN(DW15:DY15) -> #NAME? | JF15: =+MIN(DZ15:EB15) -> #NAME? | JG15: =+MIN(EC15:EE15) -> #NAME? | JH15: =+MIN(EF15:EH15) -> #NAME? | JI15: =+MIN(EI15:EK15) -> #NAME? | JJ15: =+MIN(EL15:EN15) -> #NAME? | JK15: =MIN(EO15:EQ15) -> #NAME? | JL15: =MIN(ER15:ET15) -> #NAME? | JM15: =MIN(EU15:EW15) -> #NAME? | JN15: =MIN(EX15:EZ15) -> #NAME? | JO15: =MIN(FA15:FC15) -> #NAME? | JP15: =MIN(FD15:FF15) -> #NAME? | JQ15: =MIN(FG15:FI15) -> #NAME? | JR15: =MIN(FJ15:FL15) -> #NAME? | JS15: =MIN(FM15:FO15) -> #NAME? | JT15: =MIN(FP15:FR15) -> #NAME? | JU15: =MIN(FS15:FU15) -> #NAME? | JV15: =MIN(FV15:FX15) -> #NAME? | JW15: =MIN(FY15:GA15) -> #NAME? | JX15: =MIN(GB15:GD15) -> #NAME? | JY15: =MIN(GE15:GG15) -> #NAME? | JZ15: =MIN(GH15:GJ15) -> #NAME? | KA15: =MIN(GK15:GM15) -> #NAME? | KB15: =MIN(GN15:GP15) -> #NAME? | KC15: =MIN(GQ15:GS15) -> #NAME? | KD15: =MIN(GT15:GV15) -> #NAME? | KE15: =MIN(GW15:GY15) -> #NAME? | KF15: =MIN(GZ15:HB15) -> #NAME? | KG15: =MIN(HC15:HE15) -> #NAME? | KH15: =MIN(HF15:HH15) -> #NAME?
A16: Close | B16: BMONTH_CLOSE | C16: {=_xll.EQNXTDZ($A$1,$B16,C$1)} -> #NAME? | D16: {=_xll.EQNXTDZ($A$1,$B16,D$1)} -> #NAME? | E16: {=_xll.EQNXTDZ($A$1,$B16,E$1)} -> #NAME? | F16: {=_xll.EQNXTDZ($A$1,$B16,F$1)} -> #NAME? | G16: {=_xll.EQNXTDZ($A$1,$B16,G$1)} -> #NAME? | H16: {=_xll.EQNXTDZ($A$1,$B16,H$1)} -> #NAME? | I16: {=_xll.EQNXTDZ($A$1,$B16,I$1)} -> #NAME? | J16: {=_xll.EQNXTDZ($A$1,$B16,J$1)} -> #NAME? | ... HH16: {=_xll.EQNXTDZ($A$1,$B16,HH$1)} -> #NAME? | HP16: =+F16 -> #NAME? | HQ16: =+I16 -> #NAME? | HR16: =+L16 -> #NAME? | HS16: =+O16 -> #NAME? | HT16: =+R16 -> #NAME? | HU16: =+U16 -> #NAME? | HV16: =+X16 -> #NAME? | HW16: =+AA16 -> #NAME? | HX16: =+AD16 -> #NAME? | HY16: =+AG16 -> #NAME? | HZ16: =+AJ16 -> #NAME? | IA16: =+AM16 -> #NAME? | IB16: =+AP16 -> #NAME? | IC16: =+AS16 -> #NAME? | ID16: =+AV16 -> #NAME? | IE16: =+AY16 -> #NAME? | IF16: =+BB16 -> #NAME? | IG16: =+BE16 -> #NAME? | IH16: =+BH16 -> #NAME? | II16: =+BK16 -> #NAME? | IJ16: =+BN16 -> #NAME? | IK16: =+BQ16 -> #NAME? | IL16: =+BT16 -> #NAME? | IM16: =+BW16 -> #NAME? | IN16: =+BZ16 -> #NAME? | IO16: =+CC16 -> #NAME? | IP16: =+CF16 -> #NAME? | IQ16: =+CI16 -> #NAME? | IR16: =+CL16 -> #NAME? | IS16: =+CO16 -> #NAME? | IT16: =+CR16 -> #NAME? | IU16: =+CU16 -> #NAME? | IV16: =+CX16 -> #NAME? | IW16: =+DA16 -> #NAME? | IX16: =+DD16 -> #NAME? | IY16: =+DG16 -> #NAME? | IZ16: =+DJ16 -> #NAME? | JA16: =+DM16 -> #NAME? | JB16: =+DP16 -> #NAME? | JC16: =+DS16 -> #NAME? | JD16: =+DV16 -> #NAME? | JE16: =+DY16 -> #NAME? | JF16: =+EB16 -> #NAME? | JG16: =+EE16 -> #NAME? | JH16: =+EH16 -> #NAME? | JI16: =+EK16 -> #NAME? | JJ16: =+EN16 -> #NAME? | JK16: =EQ16 -> #NAME? | JL16: =ET16 -> #NAME? | JM16: =EW16 -> #NAME? | JN16: =EZ16 -> #NAME? | JO16: =FC16 -> #NAME? | JP16: =FF16 -> #NAME? | JQ16: =FI16 -> #NAME? | JR16: =FL16 -> #NAME? | JS16: =FO16 -> #NAME? | JT16: =FR16 -> #NAME? | JU16: =FU16 -> #NAME? | JV16: =FX16 -> #NAME? | JW16: =GA16 -> #NAME? | JX16: =GD16 -> #NAME? | JY16: =GG16 -> #NAME? | JZ16: =GJ16 -> #NAME? | KA16: =GM16 -> #NAME? | KB16: =GP16 -> #NAME? | KC16: =GS16 -> #NAME? | KD16: =GV16 -> #NAME? | KE16: =GY16 -> #NAME? | KF16: =HB16 -> #NAME? | KG16: =HE16 -> #NAME? | KH16: =HH16 -> #NAME?
A19: High | HP19: =+IF(HP14=0,HP7,HP14) -> #NAME? | HQ19: =+IF(HQ14=0,HQ7,HQ14) -> #NAME? | HR19: =+IF(HR14=0,HR7,HR14) -> #NAME? | HS19: =+IF(HS14=0,HS7,HS14) -> #NAME? | HT19: =+IF(HT14=0,HT7,HT14) -> #NAME? | HU19: =+IF(HU14=0,HU7,HU14) -> #NAME? | HV19: =+IF(HV14=0,HV7,HV14) -> #NAME? | HW19: =+IF(HW14=0,HW7,HW14) -> #NAME? | ... KH19: =+IF(KH14=0,KH7,KH14) -> #NAME?
A20: Low | HP20: =+IF(HP15=0,HP8,HP15) -> #NAME? | HQ20: =+IF(HQ15=0,HQ8,HQ15) -> #NAME? | HR20: =+IF(HR15=0,HR8,HR15) -> #NAME? | HS20: =+IF(HS15=0,HS8,HS15) -> #NAME? | HT20: =+IF(HT15=0,HT8,HT15) -> #NAME? | HU20: =+IF(HU15=0,HU8,HU15) -> #NAME? | HV20: =+IF(HV15=0,HV8,HV15) -> #NAME? | HW20: =+IF(HW15=0,HW8,HW15) -> #NAME? | ... KH20: =+IF(KH15=0,KH8,KH15) -> #NAME?
A21: Close | HP21: =+IF(HP16=0,HP9,HP16) -> #NAME? | HQ21: =+IF(HQ16=0,HQ9,HQ16) -> #NAME? | HR21: =+IF(HR16=0,HR9,HR16) -> #NAME? | HS21: =+IF(HS16=0,HS9,HS16) -> #NAME? | HT21: =+IF(HT16=0,HT9,HT16) -> #NAME? | HU21: =+IF(HU16=0,HU9,HU16) -> #NAME? | HV21: =+IF(HV16=0,HV9,HV16) -> #NAME? | HW21: =+IF(HW16=0,HW9,HW16) -> #NAME? | ... KH21: =+IF(KH16=0,KH9,KH16) -> #NAME?

Sheet QTR No. of Shares
A1: ='QTR Raw'!A1 -> 219412 | C1: 201206 | D1: 201209 | E1: 201212 | F1: 201303 | G1: 201306 | H1: 201309 | I1: 201312 | J1: 201403 | K1: 201406 | L1: 201409 | M1: 201412 | N1: 201503 | O1: 201506 | P1: 201509 | Q1: 201512 | R1: 201603 | S1: 201606 | T1: 201609 | U1: 201612 | V1: 201703 | W1: 201706 | X1: 201709 | Y1: 201712 | Z1: 201803 | AA1: 201806 | AB1: 201809 | AC1: 201812 | AD1: 201903 | AE1: 201906 | AF1: 201909 | AG1: 201912 | AH1: 202003 | AI1: 202006 | AJ1: 202009 | AK1: 202012 | AL1: 202103 | AM1: 202106 | AN1: 202109 | AO1: 202112 | AP1: 202203 | AQ1: 202206 | AR1: 202209 | AS1: 202212 | AT1: 202303 | AU1: 202306 | AV1: 202309 | AW1: 202312 | AX1: 202403 | AY1: 202406 | AZ1: 202409 | BA1: 202412
A4: Field Description | B4: Field Name
A5: Date End | B5: SHP_DATE_END | C5: {=_xll.EQNXTDZ($A$1,$B5,C$1)} -> #NAME? | D5: {=_xll.EQNXTDZ($A$1,$B5,D$1)} -> #NAME? | E5: {=_xll.EQNXTDZ($A$1,$B5,E$1)} -> #NAME? | F5: {=_xll.EQNXTDZ($A$1,$B5,F$1)} -> #NAME? | G5: {=_xll.EQNXTDZ($A$1,$B5,G$1)} -> #NAME? | H5: {=_xll.EQNXTDZ($A$1,$B5,H$1)} -> #NAME? | I5: {=_xll.EQNXTDZ($A$1,$B5,I$1)} -> #NAME? | J5: {=_xll.EQNXTDZ($A$1,$B5,J$1)} -> #NAME? | ... BA5: {=_xll.EQNXTDZ($A$1,$B5,BA$1)} -> #NAME?
A6: Grand Total | B6: SHP_NSGRANDTOTAL | C6: {=_xll.EQNXTDZ($A$1,$B6,C$1)} -> #NAME? | D6: {=_xll.EQNXTDZ($A$1,$B6,D$1)} -> #NAME? | E6: {=_xll.EQNXTDZ($A$1,$B6,E$1)} -> #NAME? | F6: {=_xll.EQNXTDZ($A$1,$B6,F$1)} -> #NAME? | G6: {=_xll.EQNXTDZ($A$1,$B6,G$1)} -> #NAME? | H6: {=_xll.EQNXTDZ($A$1,$B6,H$1)} -> #NAME? | I6: {=_xll.EQNXTDZ($A$1,$B6,I$1)} -> #NAME? | J6: {=_xll.EQNXTDZ($A$1,$B6,J$1)} -> #NAME? | ... BA6: {=_xll.EQNXTDZ($A$1,$B6,BA$1)} -> #NAME?
B7: In Crs. | C7: =+C6/10^7 -> #NAME? | D7: =+D6/10^7 -> #NAME? | E7: =+E6/10^7 -> #NAME? | F7: =+F6/10^7 -> #NAME? | G7: =+G6/10^7 -> #NAME? | H7: =+H6/10^7 -> #NAME? | I7: =+I6/10^7 -> #NAME? | J7: =+J6/10^7 -> #NAME? | ... BA7: =+BA6/10^7 -> #NAME?

Sheet Share price Daily
A1: =_xll.EQNXTH(B1,"[ADJC];[ADJH];[ADJL];[ADJO];[UCLS];[VOLUME]","2015-Jan-01","Y","All traded days","Asc") -> #NAME? | B1: =+'Annual Raw'!A1 -> 219412 | L1: =_xll.EQNXTH(B1,"[NADJC];[NADJH];[NADJLOW];[NADJOPEN];[NUCLOSE];[NVOLUME]","2015-Jan-01","Y","All traded days","Asc") -> #NAME?
A2: Fredun Pharmaceuticals Ltd. | L2: Fredun Pharmaceuticals Ltd.
A3: DATE | B3: ADJHIGH | C3: ADJCLOSE | D3: ADJLOW | E3: ADJOPEN | F3: CLOSE | G3: VOLUME | L3: DATE | M3: ADJCLOSE | N3: ADJHIGH | O3: ADJLOW | P3: ADJOPEN | Q3: CLOSE | R3: VOLUME
A4: 42457 | B4: 12.5 | C4: 12.5 | D4: 12.5 | E4: 12.5 | F4: 12.5 | G4: 10
A5: 42468 | B5: 13.12 | C5: 13.12 | D5: 13.12 | E5: 13.12 | F5: 13.12 | G5: 1
A6: 42473 | B6: 13.14 | C6: 13.14 | D6: 13.14 | E6: 13.14 | F6: 13.14 | G6: 1
A7: 42478 | B7: 13.79 | C7: 13.79 | D7: 13.79 | E7: 13.79 | F7: 13.79 | G7: 1
A8: 42489 | B8: 14.47 | C8: 14.47 | D8: 14.47 | E8: 14.47 | F8: 14.47 | G8: 10
A9: 42516 | B9: 15.19 | C9: 15.19 | D9: 15.19 | E9: 15.19 | F9: 15.19 | G9: 13
A10: 42527 | B10: 15.9 | C10: 15.9 | D10: 15.9 | E10: 15.9 | F10: 15.9 | G10: 4
A11: 42528 | B11: 16.65 | C11: 16.65 | D11: 16.65 | E11: 16.65 | F11: 16.65 | G11: 4
A12: 42530 | B12: 17.45 | C12: 17.45 | D12: 17.45 | E12: 17.45 | F12: 17.45 | G12: 19
A13: 42531 | B13: 18.2 | C13: 18.2 | D13: 18.2 | E13: 18.2 | F13: 18.2 | G13: 10
A14: 42534 | B14: 19.1 | C14: 19.1 | D14: 19.1 | E14: 19.1 | F14: 19.1 | G14: 14
A15: 42535 | B15: 20 | C15: 20 | D15: 20 | E15: 20 | F15: 20 | G15: 24
... A153: 43266 | B153: 322.6 | C153: 322.45 | D153: 311 | E153: 321.95 | F153: 322.45 | G153: 1311
A154: 43269 | B154: 327.4 | C154: 316.1 | D154: 316.1 | E154: 319 | F154: 316.1 | G154: 310 | L154: 42223 | M154: 317.6 | N154: 329 | O154: 316.3 | P154: 327.9 | Q154: 317.6 | R154: 1792348
A155: 43270 | B155: 322.4 | C155: 309.8 | D155: 309.8 | E155: 322.4 | F155: 309.8 | G155: 1173 | L155: 42226 | M155: 305.35 | N155: 319.75 | O155: 303 | P155: 316.6 | Q155: 305.35 | R155: 2216198
A156: 43271 | B156: 309.8 | C156: 305 | D156: 303.65 | E156: 307 | F156: 305 | G156: 1679 | L156: 42227 | M156: 305.25 | N156: 310 | O156: 302.7 | P156: 306 | Q156: 305.25 | R156: 1519542
A157: 43272 | B157: 310.4 | C157: 298.9 | D157: 298.9 | E157: 310.4 | F157: 298.9 | G157: 1479 | L157: 42228 | M157: 298.55 | N157: 305.85 | O157: 281.45 | P157: 304.2 | Q157: 298.55 | R157: 7136664
A158: 43273 | B158: 293 | C158: 292.95 | D158: 292.95 | E158: 293 | F158: 292.95 | G158: 417 | L158: 42229 | M158: 304.2 | N158: 307 | O158: 293 | P158: 298 | Q158: 304.2 | R158: 2715476
A159: 43276 | B159: 297.9 | C159: 297.55 | D159: 287.1 | E159: 287.1 | F159: 297.55 | G159: 2137 | L159: 42230 | M159: 315.3 | N159: 317 | O159: 302 | P159: 302 | Q159: 315.3 | R159: 2293045
A160: 43277 | B160: 300 | C160: 298.45 | D160: 291.6 | E160: 291.6 | F160: 298.45 | G160: 3119 | L160: 42233 | M160: 314.55 | N160: 322.1 | O160: 311.1 | P160: 313.55 | Q160: 314.55 | R160: 1978816
A161: 43278 | B161: 295 | C161: 292.5 | D161: 292.5 | E161: 295 | F161: 292.5 | G161: 1972 | L161: 42234 | M161: 304.6 | N161: 318.4 | O161: 303.75 | P161: 313 | Q161: 304.6 | R161: 1833406
A162: 43279 | B162: 286.65 | C162: 286.65 | D162: 286.65 | E162: 286.65 | F162: 286.65 | G162: 1236 | L162: 42235 | M162: 306.35 | N162: 308.75 | O162: 298.6 | P162: 303 | Q162: 306.35 | R162: 1243817
A163: 43280 | B163: 286.65 | C163: 280.95 | D163: 280.95 | E163: 286.65 | F163: 280.95 | G163: 664 | L163: 42236 | M163: 296.6 | N163: 304.9 | O163: 293.4 | P163: 304.9 | Q163: 296.6 | R163: 3189239
A164: 43283 | B164: 284.9 | C164: 280 | D164: 275.35 | E164: 275.35 | F164: 280 | G164: 3250 | L164: 42237 | M164: 288.9 | N164: 294.35 | O164: 283.15 | P164: 291 | Q164: 288.9 | R164: 2854277
A165: 43284 | B165: 276 | C165: 274.4 | D165: 274.4 | E165: 276 | F165: 274.4 | G165: 641 | L165: 42240 | M165: 264.35 | N165: 281 | O165: 250.8 | P165: 280.3 | Q165: 264.35 | R165: 5630357
... A2082: 46111 | B2082: 1699 | C2082: 1671.8 | D2082: 1670 | E2082: 1699 | F2082: 1671.8 | G2082: 6972 | L2082: 45071 | M2082: 812.25 | N2082: 814 | O2082: 801.5 | P2082: 804 | Q2082: 812.25 | R2082: 745354
L2083: 45072 | M2083: 814.55 | N2083: 817.95 | O2083: 809.2 | P2083: 815.05 | Q2083: 814.55 | R2083: 446811
L2084: 45075 | M2084: 825.75 | N2084: 827.5 | O2084: 815 | P2084: 818 | Q2084: 825.75 | R2084: 982588
L2085: 45076 | M2085: 821.85 | N2085: 831 | O2085: 819.05 | P2085: 826 | Q2085: 821.85 | R2085: 610358
L2086: 45077 | M2086: 821.35 | N2086: 826.8 | O2086: 817 | P2086: 819.15 | Q2086: 821.35 | R2086: 805009
L2087: 45078 | M2087: 825.4 | N2087: 831.95 | O2087: 819.05 | P2087: 820.05 | Q2087: 825.4 | R2087: 804182
L2088: 45079 | M2088: 818.9 | N2088: 830.8 | O2088: 817.05 | P2088: 830 | Q2088: 818.9 | R2088: 713546
L2089: 45082 | M2089: 823.25 | N2089: 826.4 | O2089: 821.05 | P2089: 822 | Q2089: 823.25 | R2089: 356474
L2090: 45083 | M2090: 803.3 | N2090: 825 | O2090: 791.4 | P2090: 824 | Q2090: 803.3 | R2090: 1881812
L2091: 45084 | M2091: 806.1 | N2091: 809 | O2091: 801.15 | P2091: 809 | Q2091: 806.1 | R2091: 520388
L2092: 45085 | M2092: 804.95 | N2092: 811 | O2092: 801.55 | P2092: 811 | Q2092: 804.95 | R2092: 958527
L2093: 45086 | M2093: 777.95 | N2093: 805.4 | O2093: 777 | P2093: 804.2 | Q2093: 777.95 | R2093: 2202969
L2094: 45089 | M2094: 790.65 | N2094: 795.7 | O2094: 774.2 | P2094: 780.05 | Q2094: 790.65 | R2094: 1935001
... L2232: 45292 | M2232: 977.95 | N2232: 982.35 | O2232: 972.5 | P2232: 979 | Q2232: 977.95 | R2232: 764752
A2233: 45293 | B2233: 998 | C2233: 994.9 | D2233: 968.05 | E2233: 978.8 | F2233: 994.9 | G2233: 210148 | L2233: 45293 | M2233: 992.2 | N2233: 998 | O2233: 968 | P2233: 977.4 | Q2233: 992.2 | R2233: 1525164
A2234: 45294 | B2234: 1000 | C2234: 991.8 | D2234: 983 | E2234: 990.15 | F2234: 991.8 | G2234: 232348 | L2234: 45294 | M2234: 986.9 | N2234: 1000.15 | O2234: 983 | P2234: 992.35 | Q2234: 986.9 | R2234: 1252415
A2235: 45295 | B2235: 1022.75 | C2235: 1013.85 | D2235: 985.85 | E2235: 985.85 | F2235: 1013.85 | G2235: 114439 | L2235: 45295 | M2235: 1014.1 | N2235: 1022.95 | O2235: 986.2 | P2235: 986.9 | Q2235: 1014.1 | R2235: 2398169
A2236: 45296 | B2236: 1013.75 | C2236: 1009.25 | D2236: 998.65 | E2236: 1013.75 | F2236: 1009.25 | G2236: 15946 | L2236: 45296 | M2236: 1009.2 | N2236: 1013.15 | O2236: 998.3 | P2236: 1010 | Q2236: 1009.2 | R2236: 871685
A2237: 45299 | B2237: 1009.25 | C2237: 988.65 | D2237: 985.15 | E2237: 1000.4 | F2237: 988.65 | G2237: 47586 | L2237: 45299 | M2237: 990.05 | N2237: 1011.4 | O2237: 985.2 | P2237: 1009.15 | Q2237: 990.05 | R2237: 1283342
A2238: 45300 | B2238: 1003.05 | C2238: 993.15 | D2238: 990.1 | E2238: 990.1 | F2238: 993.15 | G2238: 17802 | L2238: 45300 | M2238: 993.4 | N2238: 1004.3 | O2238: 990.05 | P2238: 994.3 | Q2238: 993.4 | R2238: 1497125
A2239: 45301 | B2239: 1025.7 | C2239: 1012.2 | D2239: 991.95 | E2239: 991.95 | F2239: 1012.2 | G2239: 67013 | L2239: 45301 | M2239: 1012.15 | N2239: 1025.8 | O2239: 990 | P2239: 993 | Q2239: 1012.15 | R2239: 3880133
A2240: 45302 | B2240: 1060 | C2240: 1055.45 | D2240: 1012.7 | E2240: 1012.7 | F2240: 1055.45 | G2240: 266165 | L2240: 45302 | M2240: 1055.7 | N2240: 1060 | O2240: 1011.95 | P2240: 1015 | Q2240: 1055.7 | R2240: 3915284
A2241: 45303 | B2241: 1060.85 | C2241: 1058.6 | D2241: 1048 | E2241: 1051.05 | F2241: 1058.6 | G2241: 40453 | L2241: 45303 | M2241: 1056.9 | N2241: 1061.5 | O2241: 1047.4 | P2241: 1055 | Q2241: 1056.9 | R2241: 1135534
A2242: 45306 | B2242: 1067.95 | C2242: 1060.7 | D2242: 1045 | E2242: 1055.35 | F2242: 1060.7 | G2242: 83404 | L2242: 45306 | M2242: 1060.85 | N2242: 1068.25 | O2242: 1044.6 | P2242: 1056.9 | Q2242: 1060.85 | R2242: 1480681
A2243: 45307 | B2243: 1067.5 | C2243: 1051.3 | D2243: 1047.9 | E2243: 1060.7 | F2243: 1051.3 | G2243: 28432 | L2243: 45307 | M2243: 1051.4 | N2243: 1068.05 | O2243: 1047.4 | P2243: 1059 | Q2243: 1051.4 | R2243: 1406227
A2244: 45308 | B2244: 1061.4 | C2244: 1053.3 | D2244: 1025.15 | E2244: 1025.15 | F2244: 1053.3 | G2244: 35522 | L2244: 45308 | M2244: 1052.7 | N2244: 1061.95 | O2244: 1032.7 | P2244: 1035 | Q2244: 1052.7 | R2244: 1388891
... A2732: 46027 | B2732: 1494.8 | C2732: 1477.25 | D2732: 1422.8 | E2732: 1429 | F2732: 1477.25 | G2732: 66113 | L2732: 46027 | M2732: 1476.8 | N2732: 1494.6 | O2732: 1423.2 | P2732: 1429.5 | Q2732: 1476.8 | R2732: 1588073

Sheet Sheet2
J19: 219.3 | K19: 186.25 | L19: 186.75
J20: 192.9 | K20: 135.5 | L20: 146.9 | N20: 219.3 | O20: 192.9 | P20: 186 | Q20: 178.7 | R20: 207 | S20: 255.15 | T20: 348.25 | U20: 374 | V20: 495.9 | W20: 659.9 | X20: 613.4 | Y20: 607.9 | Z20: 555.95 | AA20: 497.8 | AB20: 459.9 | AC20: 374 | AD20: 362 | AE20: 341.5 | AF20: 384.2 | AG20: 433.8 | AH20: 460 | AI20: 474.4 | AJ20: 414.4 | AK20: 318.7 | AL20: 303.25 | AM20: 332.7 | AN20: 295 | AO20: 247 | AP20: 214.4 | AQ20: 179.5 | AR20: 97.9 | AS20: 119.1 | AT20: 130.65 | AU20: 148.55 | AV20: 153.8 | AW20: 152.9 | AX20: 136 | AY20: 141.15 | AZ20: 128.1 | BA20: 142.5 | BB20: 143.55 | BC20: 124.5 | BD20: 241 | BE20: 450 | BF20: 503.35
J21: 186 | K21: 145.4 | L21: 169.1 | N21: 186.25 | O21: 135.5 | P21: 145.4 | Q21: 108.95 | R21: 137 | S21: 170 | T21: 243.15 | U21: 307.5 | V21: 325.1 | W21: 463 | X21: 467.05 | Y21: 436.5 | Z21: 467 | AA21: 348.2 | AB21: 325 | AC21: 313.1 | AD21: 285 | AE21: 277.85 | AF21: 327 | AG21: 317 | AH21: 370.7 | AI21: 360 | AJ21: 271.15 | AK21: 233.15 | AL21: 218.8 | AM21: 262 | AN21: 223.6 | AO21: 137.6 | AP21: 142 | AQ21: 59.3 | AR21: 58 | AS21: 72.8 | AT21: 80 | AU21: 107.25 | AV21: 106 | AW21: 125.1 | AX21: 112.25 | AY21: 81.45 | AZ21: 88 | BA21: 90.35 | BB21: 106.05 | BC21: 98.55 | BD21: 119.25 | BE21: 210 | BF21: 349
J22: 178.7 | K22: 108.95 | L22: 139.75 | N22: 186.75 | O22: 146.9 | P22: 169.1 | Q22: 139.75 | R22: 202.15 | S22: 249.05 | T22: 346.4 | U22: 349.2 | V22: 469.9 | W22: 584.8 | X22: 536.15 | Y22: 513.35 | Z22: 474 | AA22: 438.55 | AB22: 355.4 | AC22: 334.95 | AD22: 298.8 | AE22: 328.35 | AF22: 343 | AG22: 389.9 | AH22: 443.05 | AI22: 407.5 | AJ22: 290.1 | AK22: 235.75 | AL22: 292.65 | AM22: 276.1 | AN22: 237.05 | AO22: 190.1 | AP22: 147.2 | AQ22: 71.9 | AR22: 75.2 | AS22: 90.1 | AT22: 117.2 | AU22: 116.3 | AV22: 140.5 | AW22: 128.6 | AX22: 133.65 | AY22: 91.65 | AZ22: 97.65 | BA22: 125 | BB22: 115.35 | BC22: 119.25 | BD22: 219.3 | BE22: 442.65 | BF22: 503.35
J23: 207 | K23: 137 | L23: 202.15
J24: 255.15 | K24: 170 | L24: 249.05
J25: 348.25 | K25: 243.15 | L25: 346.4
J26: 374 | K26: 307.5 | L26: 349.2
J27: 495.9 | K27: 325.1 | L27: 469.9
J28: 659.9 | K28: 463 | L28: 584.8
J29: 613.4 | K29: 467.05 | L29: 536.15
J30: 607.9 | K30: 436.5 | L30: 513.35
J31: 555.95 | K31: 467 | L31: 474
J32: 497.8 | K32: 348.2 | L32: 438.55
J33: 459.9 | K33: 325 | L33: 355.4
J34: 374 | K34: 313.1 | L34: 334.95
... J63: 503.35 | K63: 349 | L63: 503.35
