Workbook

Sheet Template
A1: =+'Annual Raw'!C4 -> Huhtamaki India Ltd. | B1: 36951 | C1: =EOMONTH(B1,12) -> 37346 | D1: 37591 | E1: =EOMONTH(D1,12) -> 37986 | F1: =EOMONTH(E1,12) -> 38352 | G1: =EOMONTH(F1,12) -> 38717 | H1: =EOMONTH(G1,12) -> 39082 | I1: =EOMONTH(H1,12) -> 39447 | J1: =EOMONTH(I1,12) -> 39813 | K1: =EOMONTH(J1,12) -> 40178 | L1: =EOMONTH(K1,12) -> 40543 | ... AE1: =EOMONTH(AD1,12) -> 47483 | AH1: QTR | AI1: 41061 | AJ1: 41153 | AK1: 41244 | AL1: 41334 | AM1: 41426 | AN1: 41518 | AO1: 41609 | AP1: 41699 | AQ1: 41791 | AR1: 41883 | AS1: 41974 | AT1: 42064 | AU1: 42156 | AV1: 42248 | AW1: 42339 | AX1: 42430 | AY1: 42522 | AZ1: 42614 | BA1: 42705 | BB1: 42795 | BC1: 42887 | BD1: 42979 | BE1: 43070 | BF1: 43160 | BG1: 43252 | BH1: 43344 | BI1: 43435 | BJ1: 43525 | BK1: 43617 | BL1: 43709 | BM1: 43800 | BN1: 43891 | BO1: 43983 | BP1: 44075 | BQ1: =EOMONTH(BP1,3) -> 44196 | BR1: =EOMONTH(BQ1,3) -> 44286 | BS1: =EOMONTH(BR1,3) -> 44377 | BT1: =EOMONTH(BS1,3) -> 44469 | BU1: =EOMONTH(BT1,3) -> 44561 | BV1: =EOMONTH(BU1,3) -> 44651 | BW1: =EOMONTH(BV1,3) -> 44742 | BX1: =EOMONTH(BW1,3) -> 44834 | ... DA1: =EOMONTH(CZ1,3) -> 47483 | DD1: HISTORICAL ESTIMATES | DE1: 46022
A2: Presentation Data (Start)
A6: Presentation Data (End)
A7: Profit & Loss- Annual (Start)
A8: Gross Revenue | B8: ='Annual Raw'!C6 -> 0 | C8: ='Annual Raw'!D6 -> 0 | D8: ='Annual Raw'!E6 -> 354.2851 | E8: ='Annual Raw'!F6 -> 416.1824 | F8: ='Annual Raw'!G6 -> 424.9527 | G8: ='Annual Raw'!H6 -> 468.3587 | H8: ='Annual Raw'!I6 -> 547.3669 | I8: ='Annual Raw'!J6 -> 607.7681 | ... AA8: ='Annual Raw'!AB6 -> 2488.1 | AB8: =+SUM(CL8:CO8) -> 2450.1155 | AC8: =+SUM(CP8:CS8) -> 2427.9481 | AD8: =+SUM(CT8:CW8) -> 2405.9096 | AE8: =+SUM(CX8:DA8) -> 2384.1383 | AI8: ='QTR Raw'!C6+'QTR Raw'!C8 -> 255.55 | AJ8: ='QTR Raw'!D6+'QTR Raw'!D8 -> 237.4 | AK8: ='QTR Raw'!E6+'QTR Raw'!E8 -> 245.25 | AL8: ='QTR Raw'!F6+'QTR Raw'!F8 -> 275.29 | AM8: ='QTR Raw'!G6+'QTR Raw'!G8 -> 296.68 | AN8: ='QTR Raw'!H6+'QTR Raw'!H8 -> 286.89 | AO8: ='QTR Raw'!I6+'QTR Raw'!I8 -> 299.86 | AP8: ='QTR Raw'!J6+'QTR Raw'!J8 -> 312.14 | ... CL8: ='QTR Raw'!BF6+'QTR Raw'!BF8 -> 613.1 | CM8: =+CI10+(CM11*CI10) -> 600.83916 | CN8: =+CJ10+(CN11*CJ10) -> 616.84908 | CO8: =+CK10+(CO11*CK10) -> 619.32722 | CP8: =+CL10+(CP11*CL10) -> 608.32519 | CQ8: =+CM10+(CQ11*CM10) -> 594.20932 | CR8: =+CN10+(CR11*CN10) -> 611.21016 | CS8: =+CO10+(CS11*CO10) -> 614.20344 | CT8: =+CP10+(CT11*CP10) -> 602.81424 | ... DA8: =+CW10+(DA11*CW10) -> 603.23332 | DE8: 2469.41
A9: Less: Exise Duty | B9: ='Annual Raw'!C7+'Annual Raw'!C8+'Annual Raw'!C9 -> 0 | C9: ='Annual Raw'!D7+'Annual Raw'!D8+'Annual Raw'!D9 -> 0 | D9: ='Annual Raw'!E7+'Annual Raw'!E8+'Annual Raw'!E9 -> 32.0978 | E9: ='Annual Raw'!F7+'Annual Raw'!F8+'Annual Raw'!F9 -> 33.5645 | F9: ='Annual Raw'!G7+'Annual Raw'!G8+'Annual Raw'!G9 -> 30.9316 | G9: ='Annual Raw'!H7+'Annual Raw'!H8+'Annual Raw'!H9 -> 35.4983 | H9: ='Annual Raw'!I7+'Annual Raw'!I8+'Annual Raw'!I9 -> 46.162 | I9: ='Annual Raw'!J7+'Annual Raw'!J8+'Annual Raw'!J9 -> 37.1807 | ... AA9: ='Annual Raw'!AB7+'Annual Raw'!AB8+'Annual Raw'!AB9 -> 18.69 | AB9: =+SUM(CL9:CO9) -> 0 | AC9: =+SUM(CP9:CS9) -> 0 | AD9: =+SUM(CT9:CW9) -> 0 | AE9: =+SUM(CX9:DA9) -> 0 | AI9: ='QTR Raw'!C21+'QTR Raw'!C20+'QTR Raw'!C19+'QTR Raw'!C13+'QTR Raw'!C7 -> 18.07 | AJ9: ='QTR Raw'!D21+'QTR Raw'!D20+'QTR Raw'!D19+'QTR Raw'!D13+'QTR Raw'!D7 -> 14.6 | AK9: ='QTR Raw'!E21+'QTR Raw'!E20+'QTR Raw'!E19+'QTR Raw'!E13+'QTR Raw'!E7 -> 16.1 | AL9: ='QTR Raw'!F21+'QTR Raw'!F20+'QTR Raw'!F19+'QTR Raw'!F13+'QTR Raw'!F7 -> 18.48 | AM9: ='QTR Raw'!G21+'QTR Raw'!G20+'QTR Raw'!G19+'QTR Raw'!G13+'QTR Raw'!G7 -> 20.13 | AN9: ='QTR Raw'!H21+'QTR Raw'!H20+'QTR Raw'!H19+'QTR Raw'!H13+'QTR Raw'!H7 -> 18.52 | AO9: ='QTR Raw'!I21+'QTR Raw'!I20+'QTR Raw'!I19+'QTR Raw'!I13+'QTR Raw'!I7 -> 18.54 | AP9: ='QTR Raw'!J21+'QTR Raw'!J20+'QTR Raw'!J19+'QTR Raw'!J13+'QTR Raw'!J7 -> 21.08 | ... CL9: ='QTR Raw'!BF21+'QTR Raw'!BF20+'QTR Raw'!BF19+'QTR Raw'!BF13+'QTR Raw'!BF7 -> 0 | DE9: 0
A10: Net Revenue | B10: =+B8-B9 -> 0 | C10: =+C8-C9 -> 0 | D10: =+D8-D9 -> 322.1873 | E10: =+E8-E9 -> 382.6179 | F10: =+F8-F9 -> 394.0211 | G10: =+G8-G9 -> 432.8604 | H10: =+H8-H9 -> 501.2049 | I10: =+I8-I9 -> 570.5874 | ... AE10: =+AE8-AE9 -> 2384.1383 | AI10: =+AI8-AI9 -> 237.48 | AJ10: =+AJ8-AJ9 -> 222.8 | AK10: =+AK8-AK9 -> 229.15 | AL10: =+AL8-AL9 -> 256.81 | AM10: =+AM8-AM9 -> 276.55 | AN10: =+AN8-AN9 -> 268.37 | AO10: =+AO8-AO9 -> 281.32 | AP10: =+AP8-AP9 -> 291.06 | ... DA10: =+DA8-DA9 -> 603.23332 | DE10: 2469.41
A11: Net Revenue YOY% | C11: =C10/B10-1 -> #DIV/0! | D11: =D10/C10-1 -> #DIV/0! | E11: =E10/D10-1 -> 0.18756357 | F11: =F10/E10-1 -> 0.029803101 | G11: =G10/F10-1 -> 0.098571625 | H11: =H10/G10-1 -> 0.1578904 | I11: =I10/H10-1 -> 0.13843141 | J11: =J10/I10-1 -> 0.072733818 | ... AE11: =AE10/AD10-1 -> -0.00904912 | AM11: =+IF(AI10<0,1-AM10/AI10,AM10/AI10-1) -> 0.16451912 | AN11: =+IF(AJ10<0,1-AN10/AJ10,AN10/AJ10-1) -> 0.20453321 | AO11: =+IF(AK10<0,1-AO10/AK10,AO10/AK10-1) -> 0.22766747 | AP11: =+IF(AL10<0,1-AP10/AL10,AP10/AL10-1) -> 0.13336708 | AQ11: =+IF(AM10<0,1-AQ10/AM10,AQ10/AM10-1) -> 0.11831495 | AR11: =+IF(AN10<0,1-AR10/AN10,AR10/AN10-1) -> 0.17133063 | AS11: =+IF(AO10<0,1-AS10/AO10,AS10/AO10-1) -> 0.10244561 | AT11: =+IF(AP10<0,1-AT10/AP10,AT10/AP10-1) -> 0.51982409 | ... CL11: =+IF(CH10<0,1-CL10/CH10,CL10/CH10-1) -> 0.0051973177 | CM11: =+AVERAGE(CI11:CL11) -> -0.018605499 | CN11: =+AVERAGE(CJ11:CM11) -> -0.012614915 | CO11: =+AVERAGE(CK11:CN11) -> -0.0051287974 | CP11: =+AVERAGE(CL11:CO11) -> -0.0077879734 | CQ11: =+AVERAGE(CM11:CP11) -> -0.011034296 | CR11: =+AVERAGE(CN11:CQ11) -> -0.0091414956 | CS11: =+AVERAGE(CO11:CR11) -> -0.0082731407 | CT11: =+AVERAGE(CP11:CS11) -> -0.0090592265 | ... DA11: =+AVERAGE(CW11:CZ11) -> -0.0090231557 | DE11: -0.020534036
A12: Net Revenue QOQ% | AJ12: =+IF(AI10<0,1-AJ10/AI10,AJ10/AI10-1) -> -0.061815732 | AK12: =+IF(AJ10<0,1-AK10/AJ10,AK10/AJ10-1) -> 0.028500898 | AL12: =+IF(AK10<0,1-AL10/AK10,AL10/AK10-1) -> 0.12070696 | AM12: =+IF(AL10<0,1-AM10/AL10,AM10/AL10-1) -> 0.076866166 | AN12: =+IF(AM10<0,1-AN10/AM10,AN10/AM10-1) -> -0.029578738 | AO12: =+IF(AN10<0,1-AO10/AN10,AO10/AN10-1) -> 0.048254276 | AP12: =+IF(AO10<0,1-AP10/AO10,AP10/AO10-1) -> 0.034622494 | AQ12: =+IF(AP10<0,1-AQ10/AP10,AQ10/AP10-1) -> 0.06256442 | ... CL12: =+IF(CK10<0,1-CL10/CK10,CL10/CK10-1) -> -0.015132044 | CM12: =+CM10/CL10-1 -> -0.019998115 | CN12: =+CN10/CM10-1 -> 0.026645947 | CO12: =+CO10/CN10-1 -> 0.0040174123 | CP12: =+CP10/CO10-1 -> -0.017764482 | CQ12: =+CQ10/CP10-1 -> -0.023204489 | CR12: =+CR10/CQ10-1 -> 0.028610865 | CS12: =+CS10/CR10-1 -> 0.0048972992 | CT12: =+CT10/CS10-1 -> -0.018543045 | ... DA12: =+DA10/CZ10-1 -> 0.0049303606
A13: Increase/Decrease in Stock | B13: ='Annual Raw'!C11 -> 0 | C13: ='Annual Raw'!D11 -> 0 | D13: ='Annual Raw'!E11 -> 1.5387 | E13: ='Annual Raw'!F11 -> -3.5805 | F13: ='Annual Raw'!G11 -> 0.9135 | G13: ='Annual Raw'!H11 -> -3.0595 | H13: ='Annual Raw'!I11 -> 0.1137 | I13: ='Annual Raw'!J11 -> -7.5251 | ... AA13: ='Annual Raw'!AB11 -> 10.15 | AB13: =+SUM(CL13:CO13) -> -26.24 | AC13: =+SUM(CP13:CS13) -> 0 | AD13: =+SUM(CT13:CW13) -> 0 | AE13: =+SUM(CX13:DA13) -> 0 | AI13: ='QTR Raw'!C10 -> -1.23 | AJ13: ='QTR Raw'!D10 -> -2.47 | AK13: ='QTR Raw'!E10 -> 2.45 | AL13: ='QTR Raw'!F10 -> -2.98 | AM13: ='QTR Raw'!G10 -> -2.74 | AN13: ='QTR Raw'!H10 -> 3 | AO13: ='QTR Raw'!I10 -> 5.15 | AP13: ='QTR Raw'!J10 -> -6.94 | ... CL13: ='QTR Raw'!BF10 -> -26.24 | DE13: 10.15
A14: Purchase of Finished Goods | B14: 0 | C14: 0 | D14: 0 | E14: 0 | F14: 0 | G14: 0 | H14: 0 | I14: 0 | J14: 0 | K14: 0 | L14: 0 | M14: 0 | N14: 0 | O14: 0 | P14: 0 | Q14: 0 | R14: 0 | S14: 0 | T14: 0 | U14: 0 | V14: 0 | W14: 0 | X14: 0 | Y14: 0 | Z14: 0 | AA14: 0 | AB14: =+SUM(CL14:CO14) -> 0 | AC14: =+SUM(CP14:CS14) -> 0 | AD14: =+SUM(CT14:CW14) -> 0 | AE14: =+SUM(CX14:DA14) -> 0 | AI14: ='QTR Raw'!C12 -> 0 | AJ14: ='QTR Raw'!D12 -> 0 | AK14: ='QTR Raw'!E12 -> 0 | AL14: ='QTR Raw'!F12 -> 0 | AM14: ='QTR Raw'!G12 -> 0 | AN14: ='QTR Raw'!H12 -> 0 | AO14: ='QTR Raw'!I12 -> 0 | AP14: ='QTR Raw'!J12 -> 0 | ... CL14: ='QTR Raw'!BF12 -> 0 | DE14: 0
A15: Raw Material Consumed | B15: ='Annual Raw'!C12 -> 0 | C15: ='Annual Raw'!D12 -> 0 | D15: ='Annual Raw'!E12 -> 203.7736 | E15: ='Annual Raw'!F12 -> 259.7068 | F15: ='Annual Raw'!G12 -> 266.155 | G15: ='Annual Raw'!H12 -> 297.6002 | H15: ='Annual Raw'!I12 -> 345.8754 | I15: ='Annual Raw'!J12 -> 409.0374 | ... AA15: ='Annual Raw'!AB12 -> 1620.07 | AB15: =+SUM(CL15:CO15) -> 1640.2056 | AC15: =+SUM(CP15:CS15) -> 1600.5461 | AD15: =+SUM(CT15:CW15) -> 1586.2078 | AE15: =+SUM(CX15:DA15) -> 1571.8796 | AI15: ='QTR Raw'!C11 -> 167.83 | AJ15: ='QTR Raw'!D11 -> 161.33 | AK15: ='QTR Raw'!E11 -> 153.51 | AL15: ='QTR Raw'!F11 -> 177.39 | AM15: ='QTR Raw'!G11 -> 193.29 | AN15: ='QTR Raw'!H11 -> 184.36 | AO15: ='QTR Raw'!I11 -> 194.83 | AP15: ='QTR Raw'!J11 -> 212.07 | ... CL15: ='QTR Raw'!BF11 -> 428.49 | CM15: =+CM10-CM16 -> 396.04076 | CN15: =+CN10-CN16 -> 407.11983 | CO15: =+CO10-CO16 -> 408.55496 | CP15: =+CP10-CP16 -> 400.72093 | CQ15: =+CQ10-CQ16 -> 391.81401 | CR15: =+CR10-CR16 -> 403.06099 | CS15: =+CS10-CS16 -> 404.9502 | CT15: =+CT10-CT16 -> 397.38605 | ... DA15: =+DA10-DA16 -> 397.71516 | DE15: 1620.07
A16: Gross Profit | B16: =B10-B13-B15-B14 -> 0 | C16: =C10-C13-C15-C14 -> 0 | D16: =D10-D13-D15-D14 -> 116.875 | E16: =E10-E13-E15-E14 -> 126.4916 | F16: =F10-F13-F15-F14 -> 126.9526 | G16: =G10-G13-G15-G14 -> 138.3197 | H16: =H10-H13-H15-H14 -> 155.2158 | I16: =I10-I13-I15-I14 -> 169.0751 | ... AE16: =AE10-AE13-AE15-AE14 -> 812.25869 | AI16: =AI10-AI13-AI15-AI14 -> 70.88 | AJ16: =AJ10-AJ13-AJ15-AJ14 -> 63.94 | AK16: =AK10-AK13-AK15-AK14 -> 73.19 | AL16: =AL10-AL13-AL15-AL14 -> 82.4 | AM16: =AM10-AM13-AM15-AM14 -> 86 | AN16: =AN10-AN13-AN15-AN14 -> 81.01 | AO16: =AO10-AO13-AO15-AO14 -> 81.34 | AP16: =AP10-AP13-AP15-AP14 -> 85.93 | ... CL16: =CL10-CL13-CL15-CL14 -> 210.85 | CM16: =+CM17*CM10 -> 204.79839 | CN16: =+CN17*CN10 -> 209.72925 | CO16: =+CO17*CO10 -> 210.77226 | CP16: =+CP17*CP10 -> 207.60427 | CQ16: =+CQ17*CQ10 -> 202.39531 | CR16: =+CR17*CR10 -> 208.14917 | CS16: =+CS17*CS10 -> 209.25324 | CT16: =+CT17*CT10 -> 205.42819 | ... DA16: =+DA17*DA10 -> 205.51817 | DE16: 839.19
A17: GP% | B17: =B16/B10 -> #DIV/0! | C17: =C16/C10 -> #DIV/0! | D17: =D16/D10 -> 0.36275483 | E17: =E16/E10 -> 0.33059509 | F17: =F16/F10 -> 0.32219747 | G17: =G16/G10 -> 0.31954806 | H17: =H16/H10 -> 0.30968532 | I17: =I16/I10 -> 0.29631762 | ... AE17: =AE16/AE10 -> 0.34069278 | AI17: =AI16/AI10 -> 0.29846724 | AJ17: =AJ16/AJ10 -> 0.28698384 | AK17: =AK16/AK10 -> 0.31939777 | AL17: =AL16/AL10 -> 0.32085978 | AM17: =AM16/AM10 -> 0.31097451 | AN17: =AN16/AN10 -> 0.30185937 | AO17: =AO16/AO10 -> 0.28913693 | AP17: =AP16/AP10 -> 0.29523122 | ... CL17: =CL16/CL10 -> 0.34390801 | CM17: =AVERAGE(CI17:CL17) -> 0.34085394 | CN17: =AVERAGE(CJ17:CM17) -> 0.34000091 | CO17: =AVERAGE(CK17:CN17) -> 0.34032456 | CP17: =AVERAGE(CL17:CO17) -> 0.34127185 | CQ17: =AVERAGE(CM17:CP17) -> 0.34061281 | CR17: =AVERAGE(CN17:CQ17) -> 0.34055253 | CS17: =AVERAGE(CO17:CR17) -> 0.34069044 | CT17: =AVERAGE(CP17:CS17) -> 0.34078191 | ... DA17: =AVERAGE(CW17:CZ17) -> 0.34069432 | DE17: 0.33983421
A18: GP YOY% | C18: =+IF(B16<0,1-C16/B16,C16/B16-1) -> #DIV/0! | D18: =+IF(C16<0,1-D16/C16,D16/C16-1) -> #DIV/0! | E18: =+IF(D16<0,1-E16/D16,E16/D16-1) -> 0.08228107 | F18: =+IF(E16<0,1-F16/E16,F16/E16-1) -> 0.0036445108 | G18: =+IF(F16<0,1-G16/F16,G16/F16-1) -> 0.089538143 | H18: =+IF(G16<0,1-H16/G16,H16/G16-1) -> 0.12215252 | I18: =+IF(H16<0,1-I16/H16,I16/H16-1) -> 0.089290523 | J18: =+IF(I16<0,1-J16/I16,J16/I16-1) -> 0.12870494 | ... AE18: =+IF(AD16<0,1-AE16/AD16,AE16/AD16-1) -> -0.0090802849 | AM18: =+IF(AI16<0,1-AM16/AI16,AM16/AI16-1) -> 0.21331828 | AN18: =+IF(AJ16<0,1-AN16/AJ16,AN16/AJ16-1) -> 0.26696903 | AO18: =+IF(AK16<0,1-AO16/AK16,AO16/AK16-1) -> 0.11135401 | AP18: =+IF(AL16<0,1-AP16/AL16,AP16/AL16-1) -> 0.042839806 | AQ18: =+IF(AM16<0,1-AQ16/AM16,AQ16/AM16-1) -> 0.029651163 | AR18: =+IF(AN16<0,1-AR16/AN16,AR16/AN16-1) -> 0.090606098 | AS18: =+IF(AO16<0,1-AS16/AO16,AS16/AO16-1) -> 0.10966314 | AT18: =+IF(AP16<0,1-AT16/AP16,AT16/AP16-1) -> 0.68893285 | ... CL18: =+IF(CH16<0,1-CL16/CH16,CL16/CH16-1) -> 0.017026818 | CM18: =+CM16/CI16-1 -> -0.028332346 | CN18: =+CN16/CJ16-1 -> -0.0088409753 | CO18: =+CO16/CK16-1 -> 0.0060728495 | CP18: =+CP16/CL16-1 -> -0.015393569 | CQ18: =+CQ16/CM16-1 -> -0.011733898 | CR18: =+CR16/CN16-1 -> -0.0075339088 | CS18: =+CS16/CO16-1 -> -0.0072069365 | CT18: =+CT16/CP16-1 -> -0.010481859 | ... DA18: =+DA16/CW16-1 -> -0.0090417417 | DE18: 0.073943256
A19: GP QOQ% | AJ19: =+IF(AI16<0,1-AJ16/AI16,AJ16/AI16-1) -> -0.097911964 | AK19: =+IF(AJ16<0,1-AK16/AJ16,AK16/AJ16-1) -> 0.14466688 | AL19: =+IF(AK16<0,1-AL16/AK16,AL16/AK16-1) -> 0.12583686 | AM19: =+IF(AL16<0,1-AM16/AL16,AM16/AL16-1) -> 0.04368932 | AN19: =+IF(AM16<0,1-AN16/AM16,AN16/AM16-1) -> -0.058023256 | AO19: =+IF(AN16<0,1-AO16/AN16,AO16/AN16-1) -> 0.0040735712 | AP19: =+IF(AO16<0,1-AP16/AO16,AP16/AO16-1) -> 0.056429801 | AQ19: =+IF(AP16<0,1-AQ16/AP16,AQ16/AP16-1) -> 0.030489934 | ... CL19: =+IF(CK16<0,1-CL16/CK16,CL16/CK16-1) -> 0.0064439141 | CM19: =+CM16/CL16-1 -> -0.028701013 | CN19: =+CN16/CM16-1 -> 0.024076646 | CO19: =+CO16/CN16-1 -> 0.0049731372 | CP19: =+CP16/CO16-1 -> -0.015030422 | CQ19: =+CQ16/CP16-1 -> -0.025090804 | CR19: =+CR16/CQ16-1 -> 0.028428824 | CS19: =+CS16/CR16-1 -> 0.0053042299 | CT19: =+CT16/CS16-1 -> -0.018279538 | ... DA19: =+DA16/CZ16-1 -> 0.0049440742
A20: Power & Fuel Cost | B20: ='Annual Raw'!C13 -> 0 | C20: ='Annual Raw'!D13 -> 0 | D20: ='Annual Raw'!E13 -> 10.014 | E20: ='Annual Raw'!F13 -> 12.0829 | F20: ='Annual Raw'!G13 -> 12.3519 | G20: ='Annual Raw'!H13 -> 15.2928 | H20: ='Annual Raw'!I13 -> 17.8088 | I20: ='Annual Raw'!J13 -> 16.9449 | ... AA20: ='Annual Raw'!AB13 -> 81.59 | AB20: =+SUM(CL20:CO20) -> 0 | AC20: =+SUM(CP20:CS20) -> 0 | AD20: =+SUM(CT20:CW20) -> 0 | AE20: =+SUM(CX20:DA20) -> 0 | AI20: ='QTR Raw'!C15 -> 0 | AJ20: ='QTR Raw'!D15 -> 0 | AK20: ='QTR Raw'!E15 -> 0 | AL20: ='QTR Raw'!F15 -> 0 | AM20: ='QTR Raw'!G15 -> 0 | AN20: ='QTR Raw'!H15 -> 0 | AO20: ='QTR Raw'!I15 -> 0 | AP20: ='QTR Raw'!J15 -> 0 | ... CL20: ='QTR Raw'!BF15 -> 0 | DE20: 0
A21: Selling and Distribution Expenses | B21: =('Annual Raw'!C18) -> 0 | C21: =('Annual Raw'!D18) -> 0 | D21: =('Annual Raw'!E18) -> 5.4636 | E21: =('Annual Raw'!F18) -> 6.3055 | F21: =('Annual Raw'!G18) -> 7.4863 | G21: =('Annual Raw'!H18) -> 9.3989 | H21: =('Annual Raw'!I18) -> 9.6156 | I21: =('Annual Raw'!J18) -> 12.6259 | ... AA21: =('Annual Raw'!AB18) -> 48.11 | AB21: =+SUM(CL21:CO21) -> 0 | AC21: =+SUM(CP21:CS21) -> 0 | AD21: =+SUM(CT21:CW21) -> 0 | AE21: =+SUM(CX21:DA21) -> 0 | AI21: ='QTR Raw'!C18 -> 0 | AJ21: ='QTR Raw'!D18 -> 0 | AK21: ='QTR Raw'!E18 -> 0 | AL21: ='QTR Raw'!F18 -> 0 | AM21: ='QTR Raw'!G18 -> 0 | AN21: ='QTR Raw'!H18 -> 0 | AO21: ='QTR Raw'!I18 -> 0 | AP21: ='QTR Raw'!J18 -> 0 | ... CL21: ='QTR Raw'!BF18 -> 0 | DE21: 0
A22: Other Manufacturing Expenses | B22: ='Annual Raw'!C15+'Annual Raw'!C16 -> 0 | C22: ='Annual Raw'!D15+'Annual Raw'!D16 -> 0 | D22: ='Annual Raw'!E15+'Annual Raw'!E16 -> 9.2349 | E22: ='Annual Raw'!F15+'Annual Raw'!F16 -> 11.8431 | F22: ='Annual Raw'!G15+'Annual Raw'!G16 -> 13.27 | G22: ='Annual Raw'!H15+'Annual Raw'!H16 -> 14.5692 | H22: ='Annual Raw'!I15+'Annual Raw'!I16 -> 20.0295 | I22: ='Annual Raw'!J15+'Annual Raw'!J16 -> 22.351 | ... AA22: ='Annual Raw'!AB15+'Annual Raw'!AB16 -> 130.14 | AB22: =+SUM(CL22:CO22) -> 382.8804 | AC22: =+SUM(CP22:CS22) -> 352.91369 | AD22: =+SUM(CT22:CW22) -> 326.11897 | AE22: =+SUM(CX22:DA22) -> 298.66355 | AI22: ='QTR Raw'!C14 -> 28.78 | AJ22: ='QTR Raw'!D14 -> 28.05 | AK22: ='QTR Raw'!E14 -> 31.03 | AL22: ='QTR Raw'!F14 -> 31.11 | AM22: ='QTR Raw'!G14 -> 32.84 | AN22: ='QTR Raw'!H14 -> 33.19 | AO22: ='QTR Raw'!I14 -> 35.19 | AP22: ='QTR Raw'!J14 -> 33.33 | ... CL22: ='QTR Raw'!BF14 -> 106.16 | CM22: =CM26-CM23 -> 82.032635 | CN22: =CN26-CN23 -> 96.383674 | CO22: =CO26-CO23 -> 98.304088 | CP22: =CP26-CP23 -> 92.77605 | CQ22: =CQ26-CQ23 -> 74.957773 | CR22: =CR26-CR23 -> 92.165269 | CS22: =CS26-CS23 -> 93.014599 | CT22: =CT26-CT23 -> 85.170143 | ... DA22: =DA26-DA23 -> 80.037274 | DE22: 389.42
A23: Employee Cost | B23: ='Annual Raw'!C14 -> 0 | C23: ='Annual Raw'!D14 -> 0 | D23: ='Annual Raw'!E14 -> 22.0504 | E23: ='Annual Raw'!F14 -> 26.0119 | F23: ='Annual Raw'!G14 -> 28.7538 | G23: ='Annual Raw'!H14 -> 30.7647 | H23: ='Annual Raw'!I14 -> 36.0581 | I23: ='Annual Raw'!J14 -> 41.7776 | ... AA23: ='Annual Raw'!AB14 -> 258.95 | AB23: =+SUM(CL23:CO23) -> 269.742 | AC23: =+SUM(CP23:CS23) -> 288.62394 | AD23: =+SUM(CT23:CW23) -> 308.82762 | AE23: =+SUM(CX23:DA23) -> 330.44555 | AI23: ='QTR Raw'!C16 -> 17.92 | AJ23: ='QTR Raw'!D16 -> 18.19 | AK23: ='QTR Raw'!E16 -> 18.34 | AL23: ='QTR Raw'!F16 -> 20.18 | AM23: ='QTR Raw'!G16 -> 22.05 | AN23: ='QTR Raw'!H16 -> 22.89 | AO23: ='QTR Raw'!I16 -> 18.98 | AP23: ='QTR Raw'!J16 -> 21.1 | ... CL23: ='QTR Raw'!BF16 -> 64.73 | CM23: =CI23*107% -> 76.1519 | CN23: =CJ23*107% -> 64.2535 | CO23: =CK23*107% -> 64.6066 | CP23: =CL23*107% -> 69.2611 | CQ23: =CM23*107% -> 81.482533 | CR23: =CN23*107% -> 68.751245 | CS23: =CO23*107% -> 69.129062 | CT23: =CP23*107% -> 74.109377 | ... DA23: =CW23*107% -> 79.145863 | DE23: 258.95
A24: General and Administration Expenses | B24: ='Annual Raw'!C17 -> 0 | C24: ='Annual Raw'!D17 -> 0 | D24: ='Annual Raw'!E17 -> 9.5995 | E24: ='Annual Raw'!F17 -> 9.5275 | F24: ='Annual Raw'!G17 -> 9.9198 | G24: ='Annual Raw'!H17 -> 9.9044 | H24: ='Annual Raw'!I17 -> 11.8175 | I24: ='Annual Raw'!J17 -> 13.9604 | ... AA24: ='Annual Raw'!AB17 -> 97.36 | AB24: =+SUM(CL24:CO24) -> 0 | AC24: =+SUM(CP24:CS24) -> 0 | AD24: =+SUM(CT24:CW24) -> 0 | AE24: =+SUM(CX24:DA24) -> 0 | AI24: ='QTR Raw'!C17 -> 0 | AJ24: ='QTR Raw'!D17 -> 0 | AK24: ='QTR Raw'!E17 -> 0 | AL24: ='QTR Raw'!F17 -> 0 | AM24: ='QTR Raw'!G17 -> 0 | AN24: ='QTR Raw'!H17 -> 0 | AO24: ='QTR Raw'!I17 -> 0 | AP24: ='QTR Raw'!J17 -> 0 | ... CL24: ='QTR Raw'!BF17 -> 0 | DE24: 0
A25: Miscellaneous Expenses | B25: ='Annual Raw'!C19-'Annual Raw'!C20 -> 0 | C25: ='Annual Raw'!D19-'Annual Raw'!D20 -> 0 | D25: ='Annual Raw'!E19-'Annual Raw'!E20 -> 4.4305 | E25: ='Annual Raw'!F19-'Annual Raw'!F20 -> 4.4523 | F25: ='Annual Raw'!G19-'Annual Raw'!G20 -> 4.3217 | G25: ='Annual Raw'!H19-'Annual Raw'!H20 -> 3.7147 | H25: ='Annual Raw'!I19-'Annual Raw'!I20 -> 4.8745 | I25: ='Annual Raw'!J19-'Annual Raw'!J20 -> 5.5657 | ... AA25: ='Annual Raw'!AB19-'Annual Raw'!AB20 -> 31.47 | AB25: =+SUM(CL25:CO25) -> 0 | AC25: =+SUM(CP25:CS25) -> 0 | AD25: =+SUM(CT25:CW25) -> 0 | AE25: =+SUM(CX25:DA25) -> 0 | DE25: 0
A26: Total Cost | B26: =+SUM(B20:B25) -> 0 | C26: =+SUM(C20:C25) -> 0 | D26: =+SUM(D20:D25) -> 60.7929 | E26: =+SUM(E20:E25) -> 70.2232 | F26: =+SUM(F20:F25) -> 76.1035 | G26: =+SUM(G20:G25) -> 83.6447 | H26: =+SUM(H20:H25) -> 100.204 | I26: =+SUM(I20:I25) -> 113.2255 | ... AE26: =+SUM(AE20:AE25) -> 629.1091 | AI26: =+SUM(AI20:AI25) -> 46.7 | AJ26: =+SUM(AJ20:AJ25) -> 46.24 | AK26: =+SUM(AK20:AK25) -> 49.37 | AL26: =+SUM(AL20:AL25) -> 51.29 | AM26: =+SUM(AM20:AM25) -> 54.89 | AN26: =+SUM(AN20:AN25) -> 56.08 | AO26: =+SUM(AO20:AO25) -> 54.17 | AP26: =+SUM(AP20:AP25) -> 54.43 | ... CL26: =+SUM(CL20:CL25) -> 170.89 | CM26: =CM27*CM10 -> 158.18454 | CN26: =CN27*CN10 -> 160.63717 | CO26: =CO27*CO10 -> 162.91069 | CP26: =CP27*CP10 -> 162.03715 | CQ26: =CQ27*CQ10 -> 156.44031 | CR26: =CR27*CR10 -> 160.91651 | CS26: =CS27*CS10 -> 162.14366 | CT26: =CT27*CT10 -> 159.27952 | ... DA26: =DA27*DA10 -> 159.18314 | DE26: 648.37
A27: Cost % | B27: =B26/B10 -> #DIV/0! | C27: =C26/C10 -> #DIV/0! | D27: =D26/D10 -> 0.18868807 | E27: =E26/E10 -> 0.18353349 | F27: =F26/F10 -> 0.19314575 | G27: =G26/G10 -> 0.19323713 | H27: =H26/H10 -> 0.19992622 | I27: =I26/I10 -> 0.19843673 | ... AE27: =AE26/AE10 -> 0.26387274 | AI27: =AI26/AI10 -> 0.19664814 | AJ27: =AJ26/AJ10 -> 0.20754039 | AK27: =AK26/AK10 -> 0.2154484 | AL27: =AL26/AL10 -> 0.19971964 | AM27: =AM26/AM10 -> 0.19848129 | AN27: =AN26/AN10 -> 0.20896523 | AO27: =AO26/AO10 -> 0.19255652 | AP27: =AP26/AP10 -> 0.18700612 | ... CL27: =CL26/CL10 -> 0.27873104 | CM27: =AVERAGE(CI27:CL27) -> 0.26327268 | CN27: =AVERAGE(CJ27:CM27) -> 0.26041568 | CO27: =AVERAGE(CK27:CN27) -> 0.26304461 | CP27: =AVERAGE(CL27:CO27) -> 0.266366 | CQ27: =AVERAGE(CM27:CP27) -> 0.26327474 | CR27: =AVERAGE(CN27:CQ27) -> 0.26327526 | CS27: =AVERAGE(CO27:CR27) -> 0.26399015 | CT27: =AVERAGE(CP27:CS27) -> 0.26422654 | ... DA27: =AVERAGE(CW27:CZ27) -> 0.26388319 | DE27: 0.26256069
A28: EBITDA | B28: =B16-B26 -> 0 | C28: =C16-C26 -> 0 | D28: =D16-D26 -> 56.0821 | E28: =E16-E26 -> 56.2684 | F28: =F16-F26 -> 50.8491 | G28: =G16-G26 -> 54.675 | H28: =H16-H26 -> 55.0118 | I28: =I16-I26 -> 55.8496 | ... AE28: =AE16-AE26 -> 183.1496 | AI28: =AI16-AI26 -> 24.18 | AJ28: =AJ16-AJ26 -> 17.7 | AK28: =AK16-AK26 -> 23.82 | AL28: =AL16-AL26 -> 31.11 | AM28: =AM16-AM26 -> 31.11 | AN28: =AN16-AN26 -> 24.93 | AO28: =AO16-AO26 -> 27.17 | AP28: =AP16-AP26 -> 31.5 | ... DA28: =DA16-DA26 -> 46.335032 | DE28: 190.82
A29: EBITDA Margins | B29: =B28/B10 -> #DIV/0! | C29: =C28/C10 -> #DIV/0! | D29: =D28/D10 -> 0.17406676 | E29: =E28/E10 -> 0.1470616 | F29: =F28/F10 -> 0.12905172 | G29: =G28/G10 -> 0.12631093 | H29: =H28/H10 -> 0.1097591 | I29: =I28/I10 -> 0.097880886 | ... AE29: =AE28/AE10 -> 0.07682004 | AI29: =AI28/AI10 -> 0.1018191 | AJ29: =AJ28/AJ10 -> 0.079443447 | AK29: =AK28/AK10 -> 0.10394938 | AL29: =AL28/AL10 -> 0.12114014 | AM29: =AM28/AM10 -> 0.11249322 | AN29: =AN28/AN10 -> 0.092894139 | AO29: =AO28/AO10 -> 0.096580407 | AP29: =AP28/AP10 -> 0.10822511 | ... DA29: =DA28/DA10 -> 0.076811128 | DE29: 0.077273519
A30: EBITDA YOY% | C30: =+IF(B28<0,1-C28/B28,C28/B28-1) -> #DIV/0! | D30: =+IF(C28<0,1-D28/C28,D28/C28-1) -> #DIV/0! | E30: =+IF(D28<0,1-E28/D28,E28/D28-1) -> 0.0033219155 | F30: =+IF(E28<0,1-F28/E28,F28/E28-1) -> -0.096311607 | G30: =+IF(F28<0,1-G28/F28,G28/F28-1) -> 0.07524027 | H30: =+IF(G28<0,1-H28/G28,H28/G28-1) -> 0.0061600366 | I30: =+IF(H28<0,1-I28/H28,I28/H28-1) -> 0.01522946 | J30: =+IF(I28<0,1-J28/I28,J28/I28-1) -> -0.11966424 | ... AE30: =+IF(AD28<0,1-AE28/AD28,AE28/AD28-1) -> -0.0086906208 | AM30: =+IF(AI28<0,1-AM28/AI28,AM28/AI28-1) -> 0.2866005 | AN30: =+IF(AJ28<0,1-AN28/AJ28,AN28/AJ28-1) -> 0.40847458 | AO30: =+IF(AK28<0,1-AO28/AK28,AO28/AK28-1) -> 0.14063812 | AP30: =+IF(AL28<0,1-AP28/AL28,AP28/AL28-1) -> 0.012536162 | AQ30: =+IF(AM28<0,1-AQ28/AM28,AQ28/AM28-1) -> 0.0099646416 | AR30: =+IF(AN28<0,1-AR28/AN28,AR28/AN28-1) -> 0.080625752 | AS30: =+IF(AO28<0,1-AS28/AO28,AS28/AO28-1) -> 0.054839897 | AT30: =+IF(AP28<0,1-AT28/AP28,AT28/AP28-1) -> 0.71777778 | ... CL30: =+IF(CH28<0,1-CL28/CH28,CL28/CH28-1) -> 0.031758327 | CM30: =+CM28/CI28-1 -> 0.094478892 | CN30: =+CN28/CJ28-1 -> -0.11513922 | CO30: =+CO28/CK28-1 -> -0.1140027 | CP30: =+CP28/CL28-1 -> 0.14031821 | CQ30: =+CQ28/CM28-1 -> -0.014134296 | CR30: =+CR28/CN28-1 -> -0.037876192 | CS30: =+CS28/CO28-1 -> -0.015711877 | CT30: =+CT28/CP28-1 -> 0.012762518 | ... DA30: =+DA28/CW28-1 -> -0.0085522284 | DE30: 0.69814007
A31: EBITDA QOQ% | AJ31: =+IF(AI28<0,1-AJ28/AI28,AJ28/AI28-1) -> -0.26799007 | AK31: =+IF(AJ28<0,1-AK28/AJ28,AK28/AJ28-1) -> 0.34576271 | AL31: =+IF(AK28<0,1-AL28/AK28,AL28/AK28-1) -> 0.30604534 | AM31: =+IF(AL28<0,1-AM28/AL28,AM28/AL28-1) -> 1.5543122e-15 | AN31: =+IF(AM28<0,1-AN28/AM28,AN28/AM28-1) -> -0.19864995 | AO31: =+IF(AN28<0,1-AO28/AN28,AO28/AN28-1) -> 0.089851584 | AP31: =+IF(AO28<0,1-AP28/AO28,AP28/AO28-1) -> 0.15936695 | AQ31: =+IF(AP28<0,1-AQ28/AP28,AQ28/AP28-1) -> -0.0025396825 | ... CI31: =+IF(CH28<0,1-CI28/CH28,CI28/CH28-1) -> 0.099664343 | CJ31: =+IF(CI28>1,CJ28/CI28-1,1-CJ28/CI28) -> 0.3026532 | CK31: =+IF(CJ28>1,CK28/CJ28-1,1-CK28/CJ28) -> -0.026315789 | CL31: =+IF(CK28>1,CL28/CK28-1,1-CL28/CK28) -> -0.26027397 | CM31: =+CM28/CL28-1 -> 0.16651291 | CN31: =+CN28/CM28-1 -> 0.053164876 | CO31: =+CO28/CN28-1 -> -0.025065183 | CP31: =+CP28/CO28-1 -> -0.047939466 | CQ31: =+CQ28/CP28-1 -> 0.0085124159 | CR31: =+CR28/CQ28-1 -> 0.027802262 | CS31: =+CS28/CR28-1 -> -0.0026057422 | CT31: =+CT28/CS28-1 -> -0.02039738 | ... DA31: =+DA28/CZ28-1 -> 0.0047628155
A32: Depreciation | B32: ='Annual Raw'!C27 -> 0 | C32: ='Annual Raw'!D27 -> 0 | D32: ='Annual Raw'!E27 -> 19.8197 | E32: ='Annual Raw'!F27 -> 21.5098 | F32: ='Annual Raw'!G27 -> 22.0886 | G32: ='Annual Raw'!H27 -> 24.936 | H32: ='Annual Raw'!I27 -> 23.059 | I32: ='Annual Raw'!J27 -> 28.8597 | ... AA32: ='Annual Raw'!AB27 -> 52.16 | AB32: =+SUM(CL32:CO32) -> 94.04 | AC32: =+SUM(CP32:CS32) -> 94.04 | AD32: =+SUM(CT32:CW32) -> 94.04 | AE32: =+SUM(CX32:DA32) -> 94.04 | AI32: ='QTR Raw'!C28 -> 8.64 | AJ32: ='QTR Raw'!D28 -> 8.74 | AK32: ='QTR Raw'!E28 -> 9.82 | AL32: ='QTR Raw'!F28 -> 10.26 | AM32: ='QTR Raw'!G28 -> 10.39 | AN32: ='QTR Raw'!H28 -> 10.6 | AO32: ='QTR Raw'!I28 -> 10.77 | AP32: ='QTR Raw'!J28 -> 10.93 | ... CL32: ='QTR Raw'!BF28 -> 23.51 | CM32: =CM33*CL134 -> 23.51 | CN32: =CN33*CM134 -> 23.51 | CO32: =CO33*CN134 -> 23.51 | CP32: =CP33*CO134 -> 23.51 | CQ32: =CQ33*CP134 -> 23.51 | CR32: =CR33*CQ134 -> 23.51 | CS32: =CS33*CR134 -> 23.51 | CT32: =CT33*CS134 -> 23.51 | ... DA32: =DA33*CZ134 -> 23.51 | DE32: 52.16
A33: Depreciation % of Net Block | B33: =+B32/B134 -> #DIV/0! | C33: =+C32/C134 -> #DIV/0! | D33: =+D32/D134 -> 0.18376399 | E33: =+E32/E134 -> 0.1966979 | F33: =+F32/F134 -> 0.16511397 | G33: =+G32/G134 -> 0.21377703 | H33: =+H32/H134 -> 0.20950804 | I33: =+I32/I134 -> 0.1623063 | ... AE33: =+AE32/AE134 -> 0.16860601 | AI33: =+AI32/AH134 -> #DIV/0! | AJ33: =+AJ32/AI134 -> 0.047319978 | AK33: =+AK32/AJ134 -> 0.053167298 | AL33: =+AL32/AK134 -> 0.045023697 | AM33: =+AM32/AL134 -> 0.045594172 | AN33: =+AN32/AM134 -> 0.046792919 | AO33: =+AO32/AN134 -> 0.047543372 | AP33: =+AP32/AO134 -> 0.048962953 | ... CE33: =+CE32/CD134 -> 0.02904292 | CF33: =+CF32/CE131 -> 0.023465773 | CG33: =+CG32/CF134 -> 0.026603527 | CH33: =+CH32/CG134 -> 0.023691192 | CI33: =+CI32/CH134 -> 0.024457233 | CJ33: =+CJ32/CI134 -> 0.022967279 | CK33: =+CK32/CJ134 -> 0.024347826 | CL33: =+CL32/CK134 -> 0.042151502 | CM33: =CL33 -> 0.042151502 | CN33: =CM33 -> 0.042151502 | CO33: =CN33 -> 0.042151502 | CP33: =CO33 -> 0.042151502 | CQ33: =CP33 -> 0.042151502 | CR33: =CQ33 -> 0.042151502 | CS33: =CR33 -> 0.042151502 | CT33: =CS33 -> 0.042151502 | ... DA33: =CZ33 -> 0.042151502 | DE33: 0.093518602
A34: EBIT | B34: =B28-B32 -> 0 | C34: =C28-C32 -> 0 | D34: =D28-D32 -> 36.2624 | E34: =E28-E32 -> 34.7586 | F34: =F28-F32 -> 28.7605 | G34: =G28-G32 -> 29.739 | H34: =H28-H32 -> 31.9528 | I34: =I28-I32 -> 26.9899 | ... AE34: =AE28-AE32 -> 89.109597 | AI34: =AI28-AI32 -> 15.54 | AJ34: =AJ28-AJ32 -> 8.96 | AK34: =AK28-AK32 -> 14 | AL34: =AL28-AL32 -> 20.85 | AM34: =AM28-AM32 -> 20.72 | AN34: =AN28-AN32 -> 14.33 | AO34: =AO28-AO32 -> 16.4 | AP34: =AP28-AP32 -> 20.57 | ... DA34: =DA28-DA32 -> 22.825032 | DE34: 138.66
A35: Other Income | B35: ='Annual Raw'!C23 -> 0 | C35: ='Annual Raw'!D23 -> 0 | D35: ='Annual Raw'!E23 -> 3.4891 | E35: ='Annual Raw'!F23 -> 4.4457 | F35: ='Annual Raw'!G23 -> 5.6584 | G35: ='Annual Raw'!H23 -> 9.6564 | H35: ='Annual Raw'!I23 -> 11.4766 | I35: ='Annual Raw'!J23 -> 11.822 | ... AA35: ='Annual Raw'!AB23 -> 35.22 | AB35: =+SUM(CL35:CO35) -> 22.12 | AC35: =+SUM(CP35:CS35) -> 0 | AD35: =+SUM(CT35:CW35) -> 0 | AE35: =+SUM(CX35:DA35) -> 0 | AI35: ='QTR Raw'!C23 -> 2.59 | AJ35: ='QTR Raw'!D23 -> 1.78 | AK35: ='QTR Raw'!E23 -> 1.72 | AL35: ='QTR Raw'!F23 -> 1.69 | AM35: ='QTR Raw'!G23 -> 2.01 | AN35: ='QTR Raw'!H23 -> 0.68 | AO35: ='QTR Raw'!I23 -> 0.77 | AP35: ='QTR Raw'!J23 -> 1.39 | ... CL35: ='QTR Raw'!BF23 -> 22.12 | DE35: 35.22
A36: Interest | B36: ='Annual Raw'!C25 -> 0 | C36: ='Annual Raw'!D25 -> 0 | D36: ='Annual Raw'!E25 -> 3.9831 | E36: ='Annual Raw'!F25 -> 1.2751 | F36: ='Annual Raw'!G25 -> 0.7696 | G36: ='Annual Raw'!H25 -> 0.705 | H36: ='Annual Raw'!I25 -> 0.6115 | I36: ='Annual Raw'!J25 -> 1.8473 | ... AA36: ='Annual Raw'!AB25 -> 17.31 | AB36: =+SUM(CL36:CO36) -> -68.548744 | AC36: =+SUM(CP36:CS36) -> -138.61989 | AD36: =+SUM(CT36:CW36) -> -198.55659 | AE36: =+SUM(CX36:DA36) -> -273.31789 | AI36: ='QTR Raw'!C25 -> 0 | AJ36: ='QTR Raw'!D25 -> 0 | AK36: ='QTR Raw'!E25 -> 0.57 | AL36: ='QTR Raw'!F25 -> 0.88 | AM36: ='QTR Raw'!G25 -> 0.95 | AN36: ='QTR Raw'!H25 -> 0.99 | AO36: ='QTR Raw'!I25 -> 0.93 | AP36: ='QTR Raw'!J25 -> 0.79 | ... CL36: ='QTR Raw'!BF25 -> 3.53 | CM36: =CM37*CL168 -> -21.137596 | CN36: =CN37*CM168 -> -24.48782 | CO36: =CO37*CN168 -> -26.453327 | CP36: =CP37*CO168 -> -29.261114 | CQ36: =CQ37*CP168 -> -32.90145 | CR36: =CR37*CQ168 -> -36.968917 | CS36: =CS37*CR168 -> -39.488405 | CT36: =CT37*CS168 -> -42.981769 | ... DA36: =DA37*CZ168 -> -76.001031 | DE36: 16.56
A37: Interest % of Debt | B37: =+B36/B128 -> #DIV/0! | C37: =+C36/C128 -> #DIV/0! | D37: =+D36/D128 -> 0.43410641 | E37: =+E36/E128 -> 0.12422548 | F37: =+F36/F128 -> 0.059105885 | G37: =+G36/G128 -> 0.043265602 | H37: =+H36/H128 -> 0.018105858 | I37: =+I36/I128 -> 0.027508536 | ... AE37: =+AE36/AE128 -> -2.6184891 | AI37: =(AI36-AI35)/AH168 -> #DIV/0! | AJ37: =(AJ36-AJ35)/AI168 -> 0.028200253 | AK37: =(AK36-AK35)/AJ168 -> 0.011174155 | AL37: =(AL36-AL35)/AK168 -> 0.030201342 | AM37: =(AM36-AM35)/AL168 -> 0.028781234 | AN37: =(AN36-AN35)/AM168 -> -0.045857988 | AO37: =(AO36-AO35)/AN168 -> -0.0035431149 | AP37: =(AP36-AP35)/AO168 -> 0.019940179 | ... CL37: =(CL36-CL35)/CK168 -> 0.078880103 | CM37: =+CL37 -> 0.078880103 | CN37: =+CM37 -> 0.078880103 | CO37: =+CN37 -> 0.078880103 | CP37: =+CO37 -> 0.078880103 | CQ37: =+CP37 -> 0.078880103 | CR37: =+CQ37 -> 0.078880103 | CS37: =+CR37 -> 0.078880103 | CT37: =+CS37 -> 0.078880103 | ... DA37: =+CZ37 -> 0.078880103 | DE37: 0.15865108
A38: PBT | B38: =B34+B35-B36 -> 0 | C38: =C34+C35-C36 -> 0 | D38: =D34+D35-D36 -> 35.7684 | E38: =E34+E35-E36 -> 37.9292 | F38: =F34+F35-F36 -> 33.6493 | G38: =G34+G35-G36 -> 38.6904 | H38: =H34+H35-H36 -> 42.8179 | I38: =I34+I35-I36 -> 36.9646 | ... AE38: =AE34+AE35-AE36 -> 362.42749 | AI38: =AI34+AI35-AI36 -> 18.13 | AJ38: =AJ34+AJ35-AJ36 -> 10.74 | AK38: =AK34+AK35-AK36 -> 15.15 | AL38: =AL34+AL35-AL36 -> 21.66 | AM38: =AM34+AM35-AM36 -> 21.78 | AN38: =AN34+AN35-AN36 -> 14.02 | AO38: =AO34+AO35-AO36 -> 16.24 | AP38: =AP34+AP35-AP36 -> 21.17 | ... DA38: =DA34+DA35-DA36 -> 98.826063 | DE38: 157.32
A39: Tax | B39: ='Annual Raw'!C30 -> 0 | C39: ='Annual Raw'!D30 -> 0 | D39: ='Annual Raw'!E30 -> 10.6214 | E39: ='Annual Raw'!F30 -> 10.0028 | F39: ='Annual Raw'!G30 -> 9.5394 | G39: ='Annual Raw'!H30 -> 10.2194 | H39: ='Annual Raw'!I30 -> 14.9674 | I39: ='Annual Raw'!J30 -> 5.4123 | ... AA39: ='Annual Raw'!AB30 -> 40.11 | AB39: =+SUM(CL39:CO39) -> 47.28934 | AC39: =+SUM(CP39:CS39) -> 60.377944 | AD39: =+SUM(CT39:CW39) -> 75.769042 | AE39: =+SUM(CX39:DA39) -> 94.929272 | AI39: ='QTR Raw'!C29 -> 4.77 | AJ39: ='QTR Raw'!D29 -> 1.96 | AK39: ='QTR Raw'!E29 -> 5.08 | AL39: ='QTR Raw'!F29 -> 5.5 | AM39: ='QTR Raw'!G29 -> 6.71 | AN39: ='QTR Raw'!H29 -> 4.78 | AO39: ='QTR Raw'!I29 -> 5.94 | AP39: ='QTR Raw'!J29 -> 5.07 | ... CL39: ='QTR Raw'!BF29 -> 9.44 | CM39: =+CM38*CM40 -> 11.476702 | CN39: =+CN38*CN40 -> 13.038429 | CO39: =+CO38*CO40 -> 13.33421 | CP39: =+CP38*CP40 -> 13.492597 | CQ39: =+CQ38*CQ40 -> 14.461951 | CR39: =+CR38*CR40 -> 15.88727 | CS39: =+CS38*CS40 -> 16.536126 | CT39: =+CT38*CT40 -> 17.19422 | ... DA39: =+DA38*DA40 -> 25.885911 | DE39: 40.11
A40: Tax Rate % | B40: =B39/B38 -> #DIV/0! | C40: =C39/C38 -> #DIV/0! | D40: =D39/D38 -> 0.29694926 | E40: =E39/E38 -> 0.26372294 | F40: =F39/F38 -> 0.28349475 | G40: =G39/G38 -> 0.2641327 | H40: =H39/H38 -> 0.34955941 | I40: =I39/I38 -> 0.14641847 | ... AE40: =AE39/AE38 -> 0.26192625 | AI40: =AI39/AI38 -> 0.26309983 | AJ40: =AJ39/AJ38 -> 0.18249534 | AK40: =AK39/AK38 -> 0.33531353 | AL40: =AL39/AL38 -> 0.25392428 | AM40: =AM39/AM38 -> 0.30808081 | AN40: =AN39/AN38 -> 0.34094151 | AO40: =AO39/AO38 -> 0.36576355 | AP40: =AP39/AP38 -> 0.23948984 | ... CL40: =CL39/CL38 -> 0.26940639 | CM40: =AVERAGE(CI40:CL40) -> 0.2594106 | CN40: =AVERAGE(CJ40:CM40) -> 0.26040455 | CO40: =AVERAGE(CK40:CN40) -> 0.26245912 | CP40: =AVERAGE(CL40:CO40) -> 0.26292017 | CQ40: =AVERAGE(CM40:CP40) -> 0.26129861 | CR40: =AVERAGE(CN40:CQ40) -> 0.26177061 | CS40: =AVERAGE(CO40:CR40) -> 0.26211213 | CT40: =AVERAGE(CP40:CS40) -> 0.26202538 | ... DA40: =AVERAGE(CW40:CZ40) -> 0.26193405 | DE40: 0.25495805
A41: PAT | B41: =B38-B39 -> 0 | C41: =C38-C39 -> 0 | D41: =D38-D39 -> 25.147 | E41: =E38-E39 -> 27.9264 | F41: =F38-F39 -> 24.1099 | G41: =G38-G39 -> 28.471 | H41: =H38-H39 -> 27.8505 | I41: =I38-I39 -> 31.5523 | ... AE41: =AE38-AE39 -> 267.49821 | AI41: =AI38-AI39 -> 13.36 | AJ41: =AJ38-AJ39 -> 8.78 | AK41: =AK38-AK39 -> 10.07 | AL41: =AL38-AL39 -> 16.16 | AM41: =AM38-AM39 -> 15.07 | AN41: =AN38-AN39 -> 9.24 | AO41: =AO38-AO39 -> 10.3 | AP41: =AP38-AP39 -> 16.1 | ... DA41: =DA38-DA39 -> 72.940152 | DE41: 117.21
A42: PAT % | B42: =+B41/B10 -> #DIV/0! | C42: =+C41/C10 -> #DIV/0! | D42: =+D41/D10 -> 0.078050873 | E42: =+E41/E10 -> 0.072987699 | F42: =+F41/F10 -> 0.061189363 | G42: =+G41/G10 -> 0.065774093 | H42: =+H41/H10 -> 0.055567094 | I42: =+I41/I10 -> 0.055297926 | ... AE42: =+AE41/AE10 -> 0.11219912 | AI42: =+AI41/AI10 -> 0.056257369 | AJ42: =+AJ41/AJ10 -> 0.03940754 | AK42: =+AK41/AK10 -> 0.043945014 | AL42: =+AL41/AL10 -> 0.062925899 | AM42: =+AM41/AM10 -> 0.054492858 | AN42: =+AN41/AN10 -> 0.034430078 | AO42: =+AO41/AO10 -> 0.03661311 | AP42: =+AP41/AP10 -> 0.055315055 | ... DA42: =+DA41/DA10 -> 0.12091532 | DE42: 0.047464779
A43: PAT YOY% | C43: =+IF(B41<0,1-C41/B41,C41/B41-1) -> #DIV/0! | D43: =+IF(C41<0,1-D41/C41,D41/C41-1) -> #DIV/0! | E43: =+IF(D41<0,1-E41/D41,E41/D41-1) -> 0.11052611 | F43: =+IF(E41<0,1-F41/E41,F41/E41-1) -> -0.1366628 | G43: =+IF(F41<0,1-G41/F41,G41/F41-1) -> 0.1808842 | H43: =+IF(G41<0,1-H41/G41,H41/G41-1) -> -0.021794106 | I43: =+IF(H41<0,1-I41/H41,I41/H41-1) -> 0.13291682 | J43: =+IF(I41<0,1-J41/I41,J41/I41-1) -> -0.32531701 | ... AE43: =+IF(AD41<0,1-AE41/AD41,AE41/AD41-1) -> 0.25290269 | AM43: =+IF(AI41<0,1-AM41/AI41,AM41/AI41-1) -> 0.12799401 | AN43: =+IF(AJ41<0,1-AN41/AJ41,AN41/AJ41-1) -> 0.0523918 | AO43: =+IF(AK41<0,1-AO41/AK41,AO41/AK41-1) -> 0.022840119 | AP43: =+IF(AL41<0,1-AP41/AL41,AP41/AL41-1) -> -0.0037128713 | AQ43: =+IF(AM41<0,1-AQ41/AM41,AQ41/AM41-1) -> 0.10218978 | AR43: =+IF(AN41<0,1-AR41/AN41,AR41/AN41-1) -> 0.49134199 | AS43: =+IF(AO41<0,1-AS41/AO41,AS41/AO41-1) -> 0.52815534 | AT43: =+IF(AP41<0,1-AT41/AP41,AT41/AP41-1) -> 0.32173913 | ... CL43: =+IF(CH41<0,1-CL41/CH41,CL41/CH41-1) -> 0.0047095761 | CM43: =+CM41/CI41-1 -> 0.3286598 | CN43: =+CN41/CJ41-1 -> 0.0071108762 | CO43: =+CO41/CK41-1 -> 0.23665648 | CP43: =+CP41/CL41-1 -> 0.47756375 | CQ43: =+CQ41/CM41-1 -> 0.24781968 | CR43: =+CR41/CN41-1 -> 0.20989812 | CS43: =+CS41/CO41-1 -> 0.24235385 | CT43: =+CT41/CP41-1 -> 0.2802487 | ... DA43: =+DA41/CW41-1 -> 0.25170474 | DE43: 1.0527145
A44: PAT QOQ% | AJ44: =+IF(AI41<0,1-AJ41/AI41,AJ41/AI41-1) -> -0.34281437 | AK44: =+IF(AJ41<0,1-AK41/AJ41,AK41/AJ41-1) -> 0.14692483 | AL44: =+IF(AK41<0,1-AL41/AK41,AL41/AK41-1) -> 0.60476663 | AM44: =+IF(AL41<0,1-AM41/AL41,AM41/AL41-1) -> -0.067450495 | AN44: =+IF(AM41<0,1-AN41/AM41,AN41/AM41-1) -> -0.38686131 | AO44: =+IF(AN41<0,1-AO41/AN41,AO41/AN41-1) -> 0.11471861 | AP44: =+IF(AO41<0,1-AP41/AO41,AP41/AO41-1) -> 0.5631068 | AQ44: =+IF(AP41<0,1-AQ41/AP41,AQ41/AP41-1) -> 0.031677019 | ... CL44: =+IF(CK41<0,1-CL41/CK41,CL41/CK41-1) -> -0.15511551 | CM44: =+CM41/CL41-1 -> 0.27987307 | CN44: =+CN41/CM41-1 -> 0.13022276 | CO44: =+CO41/CN41-1 -> 0.011860847 | CP44: =+CP41/CO41-1 -> 0.0094724817 | CQ44: =+CQ41/CP41-1 -> 0.080867623 | CR44: =+CR41/CQ41-1 -> 0.095874995 | CS44: =+CS41/CR41-1 -> 0.039004195 | CT44: =+CT41/CS41-1 -> 0.040263874 | ... DA44: =+DA41/CZ41-1 -> 0.049782447
A45: Minority Interest | B45: ='Annual Raw'!C32 -> 0 | C45: ='Annual Raw'!D32 -> 0 | D45: ='Annual Raw'!E32 -> 0 | E45: ='Annual Raw'!F32 -> 0 | F45: ='Annual Raw'!G32 -> 0 | G45: ='Annual Raw'!H32 -> 0 | H45: ='Annual Raw'!I32 -> 0 | I45: ='Annual Raw'!J32 -> 0 | ... AA45: ='Annual Raw'!AB32 -> 0 | AB45: =+SUM(CL45:CO45) -> 0 | AC45: =+SUM(CP45:CS45) -> 0 | AD45: =+SUM(CT45:CW45) -> 0 | AE45: =+SUM(CX45:DA45) -> 0 | AI45: ='QTR Raw'!C34 -> 0 | AJ45: ='QTR Raw'!D34 -> 0 | AK45: ='QTR Raw'!E34 -> -0.04 | AL45: ='QTR Raw'!F34 -> -0.53 | AM45: ='QTR Raw'!G34 -> -0.3 | AN45: ='QTR Raw'!H34 -> -0.09 | AO45: ='QTR Raw'!I34 -> -0.69 | AP45: ='QTR Raw'!J34 -> -0.43 | ... CL45: ='QTR Raw'!BF34 -> 0 | CM45: =+CL45 -> 0 | CN45: =+CM45 -> 0 | CO45: =+CN45 -> 0 | CP45: =+CO45 -> 0 | CQ45: =+CP45 -> 0 | CR45: =+CQ45 -> 0 | CS45: =+CR45 -> 0 | CT45: =+CS45 -> 0 | ... DA45: =+CZ45 -> 0 | DE45: 0
A46: Share of Associate | B46: ='Annual Raw'!C33+'Annual Raw'!C28 -> 0 | C46: ='Annual Raw'!D33+'Annual Raw'!D28 -> 0 | D46: ='Annual Raw'!E33+'Annual Raw'!E28 -> 0 | E46: ='Annual Raw'!F33+'Annual Raw'!F28 -> 0 | F46: ='Annual Raw'!G33+'Annual Raw'!G28 -> 0 | G46: ='Annual Raw'!H33+'Annual Raw'!H28 -> 0 | H46: ='Annual Raw'!I33+'Annual Raw'!I28 -> 0 | I46: ='Annual Raw'!J33+'Annual Raw'!J28 -> 0 | ... AA46: ='Annual Raw'!AB33+'Annual Raw'!AB28 -> 0 | AB46: =+SUM(CL46:CO46) -> 0 | AC46: =+SUM(CP46:CS46) -> 0 | AD46: =+SUM(CT46:CW46) -> 0 | AE46: =+SUM(CX46:DA46) -> 0 | AI46: ='QTR Raw'!C35 -> 0 | AJ46: ='QTR Raw'!D35 -> 0 | AK46: ='QTR Raw'!E35 -> 0 | AL46: ='QTR Raw'!F35 -> 0 | AM46: ='QTR Raw'!G35 -> 0 | AN46: ='QTR Raw'!H35 -> 0 | AO46: ='QTR Raw'!I35 -> 0 | AP46: ='QTR Raw'!J35 -> 0 | ... CL46: ='QTR Raw'!BF35 -> 0 | CM46: =+CL46 -> 0 | CN46: =+CM46 -> 0 | CO46: =+CN46 -> 0 | CP46: =+CO46 -> 0 | CQ46: =+CP46 -> 0 | CR46: =+CQ46 -> 0 | CS46: =+CR46 -> 0 | CT46: =+CS46 -> 0 | ... DA46: =+CZ46 -> 0 | DE46: 0
A47: Exceptional Income / Expenses | B47: ='Annual Raw'!C29+'Annual Raw'!C31+'Annual Raw'!C34+'Annual Raw'!C36 -> 0 | C47: ='Annual Raw'!D29+'Annual Raw'!D31+'Annual Raw'!D34+'Annual Raw'!D36 -> 0 | D47: ='Annual Raw'!E29+'Annual Raw'!E31+'Annual Raw'!E34+'Annual Raw'!E36 -> 0 | E47: ='Annual Raw'!F29+'Annual Raw'!F31+'Annual Raw'!F34+'Annual Raw'!F36 -> 0 | F47: ='Annual Raw'!G29+'Annual Raw'!G31+'Annual Raw'!G34+'Annual Raw'!G36 -> 0 | G47: ='Annual Raw'!H29+'Annual Raw'!H31+'Annual Raw'!H34+'Annual Raw'!H36 -> -0.7959 | H47: ='Annual Raw'!I29+'Annual Raw'!I31+'Annual Raw'!I34+'Annual Raw'!I36 -> 12.0848 | I47: ='Annual Raw'!J29+'Annual Raw'!J31+'Annual Raw'!J34+'Annual Raw'!J36 -> -3.1848 | ... AA47: ='Annual Raw'!AB29+'Annual Raw'!AB31+'Annual Raw'!AB34+'Annual Raw'!AB36 -> 0.95 | AB47: =+SUM(CL47:CO47) -> 0 | AC47: =+SUM(CP47:CS47) -> 0 | AD47: =+SUM(CT47:CW47) -> 0 | AE47: =+SUM(CX47:DA47) -> 0 | AI47: ='QTR Raw'!C26+'QTR Raw'!C31+'QTR Raw'!C32+'QTR Raw'!C33+'QTR Raw'!C36+'QTR Raw'!C37+'QTR Raw'!C39 -> 0 | AJ47: ='QTR Raw'!D26+'QTR Raw'!D31+'QTR Raw'!D32+'QTR Raw'!D33+'QTR Raw'!D36+'QTR Raw'!D37+'QTR Raw'!D39 -> 0 | AK47: ='QTR Raw'!E26+'QTR Raw'!E31+'QTR Raw'!E32+'QTR Raw'!E33+'QTR Raw'!E36+'QTR Raw'!E37+'QTR Raw'!E39 -> 0 | AL47: ='QTR Raw'!F26+'QTR Raw'!F31+'QTR Raw'!F32+'QTR Raw'!F33+'QTR Raw'!F36+'QTR Raw'!F37+'QTR Raw'!F39 -> 0 | AM47: ='QTR Raw'!G26+'QTR Raw'!G31+'QTR Raw'!G32+'QTR Raw'!G33+'QTR Raw'!G36+'QTR Raw'!G37+'QTR Raw'!G39 -> 0 | AN47: ='QTR Raw'!H26+'QTR Raw'!H31+'QTR Raw'!H32+'QTR Raw'!H33+'QTR Raw'!H36+'QTR Raw'!H37+'QTR Raw'!H39 -> 0 | AO47: ='QTR Raw'!I26+'QTR Raw'!I31+'QTR Raw'!I32+'QTR Raw'!I33+'QTR Raw'!I36+'QTR Raw'!I37+'QTR Raw'!I39 -> 7.05 | AP47: ='QTR Raw'!J26+'QTR Raw'!J31+'QTR Raw'!J32+'QTR Raw'!J33+'QTR Raw'!J36+'QTR Raw'!J37+'QTR Raw'!J39 -> 1.25 | ... CL47: ='QTR Raw'!BF26+'QTR Raw'!BF31+'QTR Raw'!BF32+'QTR Raw'!BF33+'QTR Raw'!BF36+'QTR Raw'!BF37+'QTR Raw'!BF39 -> 0 | DE47: 0.95
A48: Consolidated Net Profit | B48: =B41+B45+B46+B47 -> 0 | C48: =C41+C45+C46+C47 -> 0 | D48: =D41+D45+D46+D47 -> 25.147 | E48: =E41+E45+E46+E47 -> 27.9264 | F48: =F41+F45+F46+F47 -> 24.1099 | G48: =G41+G45+G46+G47 -> 27.6751 | H48: =H41+H45+H46+H47 -> 39.9353 | I48: =I41+I45+I46+I47 -> 28.3675 | ... AE48: =AE41+AE45+AE46+AE47 -> 267.49821 | AI48: =AI41+AI45+AI46+AI47 -> 13.36 | AJ48: =AJ41+AJ45+AJ46+AJ47 -> 8.78 | AK48: =AK41+AK45+AK46+AK47 -> 10.03 | AL48: =AL41+AL45+AL46+AL47 -> 15.63 | AM48: =AM41+AM45+AM46+AM47 -> 14.77 | AN48: =AN41+AN45+AN46+AN47 -> 9.15 | AO48: =AO41+AO45+AO46+AO47 -> 16.66 | AP48: =AP41+AP45+AP46+AP47 -> 16.92 | ... DA48: =DA41+DA45+DA46+DA47 -> 72.940152 | DE48: 118.16
A49: Profit & Loss- Annual (End)
A50: Rat
A51: Ace - PAT | B51: ='Annual Raw'!C35 -> 0 | C51: ='Annual Raw'!D35 -> 0 | D51: ='Annual Raw'!E35 -> 25.147 | E51: ='Annual Raw'!F35 -> 27.9264 | F51: ='Annual Raw'!G35 -> 24.1099 | G51: ='Annual Raw'!H35 -> 27.6751 | H51: ='Annual Raw'!I35 -> 39.9353 | I51: ='Annual Raw'!J35 -> 28.3675 | ... AA51: ='Annual Raw'!AB35 -> 118.16 | AB51: =+AB48 -> 132.86691 | AC51: =+AC48 -> 170.06629 | AD51: =+AD48 -> 213.50279 | AE51: =+AE48 -> 267.49821 | AI51: ='QTR Raw'!C42 -> 13.36 | AJ51: ='QTR Raw'!D42 -> 8.78 | AK51: ='QTR Raw'!E42 -> 10.03 | AL51: ='QTR Raw'!F42 -> 15.63 | AM51: ='QTR Raw'!G42 -> 14.77 | AN51: ='QTR Raw'!H42 -> 9.15 | AO51: ='QTR Raw'!I42 -> 16.66 | AP51: ='QTR Raw'!J42 -> 16.92 | ... CL51: ='QTR Raw'!BF42 -> 25.6 | DE51: 118.16
A52: Checksum - PAT | B52: =B51-B48 -> 0 | C52: =C51-C48 -> 0 | D52: =D51-D48 -> 0 | E52: =E51-E48 -> 4.2632564e-14 | F52: =F51-F48 -> 0 | G52: =G51-G48 -> -8.1712415e-14 | H52: =H51-H48 -> 0 | I52: =I51-I48 -> 0 | ... AE52: =AE51-AE48 -> 0 | AI52: =AI51-AI48 -> 3.5527137e-14 | AJ52: =AJ51-AJ48 -> 3.375078e-14 | AK52: =AK51-AK48 -> -2.3092639e-14 | AL52: =AL51-AL48 -> 1.7763568e-14 | AM52: =AM51-AM48 -> -2.4868996e-14 | AN52: =AN51-AN48 -> 0 | AO52: =AO51-AO48 -> 0 | AP52: =AP51-AP48 -> 0 | ... CL52: =CL51-CL48 -> -3.5527137e-14 | DE52: 0
A53: Ratios (Start)
A54: ROE (%) | B54: =(B48-B47)/B120 -> #DIV/0! | C54: =(C48-C47)/C120 -> #DIV/0! | D54: =(D48-D47)/D120 -> 0.15473744 | E54: =(E48-E47)/E120 -> 0.17032208 | F54: =(F48-F47)/F120 -> 0.13430322 | G54: =(G48-G47)/G120 -> 0.14468368 | H54: =(H48-H47)/H120 -> 0.12441585 | I54: =(I48-I47)/I120 -> 0.13242313 | ... AE54: =(AE48-AE47)/AE120 -> 0.12856447 | AL54: =(SUM(AI48:AL48)-SUM(AI47:AL47))/AL120 -> 0.12898351 | AM54: =(SUM(AJ48:AM48)-SUM(AJ47:AM47))/AM120 -> 0.12773855 | AN54: =(SUM(AK48:AN48)-SUM(AK47:AN47))/AN120 -> 0.12571313 | AO54: =(SUM(AL48:AO48)-SUM(AL47:AO47))/AO120 -> 0.12579324 | AP54: =(SUM(AM48:AP48)-SUM(AM47:AP47))/AP120 -> 0.12067105 | AQ54: =(SUM(AN48:AQ48)-SUM(AN47:AQ47))/AQ120 -> 0.11834236 | AR54: =(SUM(AO48:AR48)-SUM(AO47:AR47))/AR120 -> 0.12404176 | AS54: =(SUM(AP48:AS48)-SUM(AP47:AS47))/AS120 -> 0.10631212 | ... DA54: =(SUM(CX48:DA48)-SUM(CX47:DA47))/DA120 -> 0.12856447 | DE54: 0.090389598
A55: ROCE (%) | B55: =+B34/B129 -> #DIV/0! | C55: =+C34/C129 -> #DIV/0! | D55: =+D34/D129 -> 0.21120931 | E55: =+E34/E129 -> 0.19950214 | F55: =+F34/F129 -> 0.14937485 | G55: =+G34/G129 -> 0.13957012 | H55: =+H34/H129 -> 0.12402896 | I55: =+I34/I129 -> 0.088369063 | ... AE55: =+AE34/AE129 -> 0.040781786 | AL55: =+SUM(AI34:AL34)/AL129 -> 0.13567885 | AM55: =+SUM(AJ34:AM34)/AM129 -> 0.1427055 | AN55: =+SUM(AK34:AN34)/AN129 -> 0.15151515 | AO55: =+SUM(AL34:AO34)/AO129 -> 0.16015772 | AP55: =+SUM(AM34:AP34)/AP129 -> 0.15377389 | AQ55: =+SUM(AN34:AQ34)/AQ129 -> 0.14539969 | AR55: =+SUM(AO34:AR34)/AR129 -> 0.14513903 | AS55: =+SUM(AP34:AS34)/AS129 -> 0.1190294 | ... DA55: =+SUM(CX34:DA34)/DA129 -> 0.040781786 | DE55: 0.098965099
A56: Ratios (End)
A57: Checksum Of qtr to Annual
A58: Revenue - Checksum Of qtr to Annual | N58: =N10-SUM(AI10:AL10) -> -45.6527 | R58: =R10-SUM(AX10:BA10) -> 4.3079 | S58: =S10-SUM(BB10:BE10) -> 2.5222 | T58: =T10-SUM(BF10:BI10) -> -0.9083 | U58: =U10-SUM(BJ10:BM10) -> 9.85 | V58: =V10-SUM(BN10:BQ10) -> 0 | W58: =W10-SUM(BR10:BU10) -> 0 | X58: =X10-SUM(BV10:BY10) -> 0 | Y58: =Y10-SUM(BZ10:CC10) -> 0 | Z58: =Z10-SUM(CD10:CG10) -> 0 | AA58: =AA10-SUM(CE10:CH10) -> -51.58 | AB58: =AB10-SUM(CL10:CO10) -> 0 | AC58: =AC10-SUM(CP10:CS10) -> 0 | AD58: =AD10-SUM(CT10:CW10) -> 0 | AE58: =AE10-SUM(CX10:DA10) -> 0 | DE58: 0
A59: GP - Checksum Of qtr to Annual | N59: =N16-SUM(AI16:AL16) -> -14.7295 | R59: =R16-SUM(AX16:BA16) -> 4.2349 | S59: =S16-SUM(BB16:BE16) -> 2.5265 | T59: =T16-SUM(BF16:BI16) -> -0.9035 | U59: =U16-SUM(BJ16:BM16) -> 1.83 | V59: =V16-SUM(BN16:BQ16) -> 0 | W59: =W16-SUM(BR16:BU16) -> 0 | X59: =X16-SUM(BV16:BY16) -> 0 | Y59: =Y16-SUM(BZ16:CC16) -> 0 | Z59: =Z16-SUM(CD16:CG16) -> 0.01 | AA59: =AA16-SUM(CE16:CH16) -> 55.89 | AB59: =AB16-SUM(CL16:CO16) -> 0 | AC59: =AC16-SUM(CP16:CS16) -> 0 | AD59: =AD16-SUM(CT16:CW16) -> 0 | AE59: =AE16-SUM(CX16:DA16) -> 0 | DE59: 0
A60: EBITDA - Checksum Of qtr to Annual | N60: =N28-SUM(AI28:AL28) -> -6.3908 | R60: =R28-SUM(AX28:BA28) -> 3.5482 | S60: =S28-SUM(BB28:BE28) -> 1.6902 | T60: =T28-SUM(BF28:BI28) -> 0.6671 | U60: =U28-SUM(BJ28:BM28) -> 3.18 | V60: =V28-SUM(BN28:BQ28) -> 4.11 | W60: =W28-SUM(BR28:BU28) -> 2.69 | X60: =X28-SUM(BV28:BY28) -> 0.67 | Y60: =Y28-SUM(BZ28:CC28) -> -1.69 | Z60: =Z28-SUM(CD28:CG28) -> -4.96 | AA60: =AA28-SUM(CE28:CH28) -> 76.56 | AB60: =AB28-SUM(CL28:CO28) -> 0 | AC60: =AC28-SUM(CP28:CS28) -> 0 | AD60: =AD28-SUM(CT28:CW28) -> -2.5579538e-13 | AE60: =AE28-SUM(CX28:DA28) -> 0 | DE60: 0
A61: PAT - Checksum Of qtr to Annual | N61: =N48-SUM(AI48:AL48) -> -2.7248 | R61: =R41-SUM(AX41:BA41) -> -4.5889 | S61: =S41-SUM(BB41:BE41) -> -0.004 | T61: =T41-SUM(BF41:BI41) -> -0.0051 | U61: =U41-SUM(BJ41:BM41) -> -3.9790393e-13 | V61: =V41-SUM(BN41:BQ41) -> -1.4210855e-13 | W61: =W41-SUM(BR41:BU41) -> 2.3270275e-13 | X61: =X41-SUM(BV41:BY41) -> -4.4764192e-13 | Y61: =Y41-SUM(BZ41:CC41) -> -0.01 | Z61: =Z41-SUM(CD41:CG41) -> -1.4921397e-13 | AA61: =AA41-SUM(CE41:CH41) -> 60.66 | AB61: =AB41-SUM(CL41:CO41) -> 0 | AC61: =AC41-SUM(CP41:CS41) -> 0 | AD61: =AD41-SUM(CT41:CW41) -> -2.5579538e-13 | AE61: =AE41-SUM(CX41:DA41) -> 0 | DE61: -1.9895197e-13
A62: Valuation (Start)
A63: Eq | B63: ='Annual Raw'!C104 -> 0 | C63: ='Annual Raw'!D104 -> 0 | D63: ='Annual Raw'!E104 -> 12.5374 | E63: =+F63 -> 15.11 | F63: =+G63 -> 15.11 | G63: =+H63 -> 15.11 | H63: =+I63 -> 15.11 | I63: =+J63 -> 15.11 | J63: =+K63 -> 15.11 | K63: =+L63 -> 15.11 | L63: =+M63 -> 15.11 | ... AA63: =+AB63 -> 15.11 | AB63: =AA63 -> 15.11 | AC63: =AB63 -> 15.11 | AD63: =AC63 -> 15.11 | AE63: =AD63 -> 15.11 | AI63: =+AJ63 -> 15.11 | AJ63: =+AK63 -> 15.11 | AK63: =+AL63 -> 15.11 | AL63: =+AM63 -> 15.11 | AM63: =+AN63 -> 15.11 | AN63: =+AO63 -> 15.11 | AO63: =+AP63 -> 15.11 | AP63: =+AQ63 -> 15.11 | ... CI63: =+CJ63 -> 15.11 | CJ63: ='QTR Raw'!BD45 -> 15.11 | CK63: ='QTR Raw'!BE45 -> 15.11 | CL63: ='QTR Raw'!BF45 -> 15.11 | CM63: =+CL63 -> 15.11 | CN63: =+CM63 -> 15.11 | CO63: =+CN63 -> 15.11 | CP63: =+CO63 -> 15.11 | CQ63: =+CP63 -> 15.11 | CR63: =+CQ63 -> 15.11 | CS63: =+CR63 -> 15.11 | CT63: =+CS63 -> 15.11 | ... DA63: =+CZ63 -> 15.11 | DE63: 15.11
A64: FV | B64: ='Annual Raw'!C105 -> 0 | C64: ='Annual Raw'!D105 -> 0 | D64: ='Annual Raw'!E105 -> 10 | E64: =+F64 -> 2 | F64: =+G64 -> 2 | G64: =+H64 -> 2 | H64: =+I64 -> 2 | I64: =+J64 -> 2 | J64: =+K64 -> 2 | K64: =+L64 -> 2 | L64: =+M64 -> 2 | ... AA64: =+AB64 -> 2 | AB64: =AA64 -> 2 | AC64: =AB64 -> 2 | AD64: =AC64 -> 2 | AE64: =AD64 -> 2 | AI64: =AJ64 -> 2 | AJ64: =AK64 -> 2 | AK64: =AL64 -> 2 | AL64: =AM64 -> 2 | AM64: =AN64 -> 2 | AN64: =AO64 -> 2 | AO64: =AP64 -> 2 | AP64: =AQ64 -> 2 | ... CI64: =CJ64 -> 2 | CJ64: ='QTR Raw'!BD46 -> 2 | CK64: ='QTR Raw'!BE46 -> 2 | CL64: ='QTR Raw'!BF46 -> 2 | CM64: =+CL64 -> 2 | CN64: =+CM64 -> 2 | CO64: =+CN64 -> 2 | CP64: =+CO64 -> 2 | CQ64: =+CP64 -> 2 | CR64: =+CQ64 -> 2 | CS64: =+CR64 -> 2 | CT64: =+CS64 -> 2 | ... DA64: =+CZ64 -> 2 | DE64: 2
A65: No of share | B65: =B63/B64 -> #DIV/0! | C65: =C63/C64 -> #DIV/0! | D65: =D63/D64 -> 1.25374 | E65: =E63/E64 -> 7.555 | F65: =F63/F64 -> 7.555 | G65: =G63/G64 -> 7.555 | H65: =H63/H64 -> 7.555 | I65: =I63/I64 -> 7.555 | ... AE65: =AE63/AE64 -> 7.555 | AI65: =AI63/AI64 -> 7.555 | AJ65: =AJ63/AJ64 -> 7.555 | AK65: =AK63/AK64 -> 7.555 | AL65: =AL63/AL64 -> 7.555 | AM65: =AM63/AM64 -> 7.555 | AN65: =AN63/AN64 -> 7.555 | AO65: =AO63/AO64 -> 7.555 | AP65: =AP63/AP64 -> 7.555 | ... DA65: =DA63/DA64 -> 7.555 | DE65: 7.555
A66: EPS | B66: =(B48-B47)/B65 -> #DIV/0! | C66: =(C48-C47)/C65 -> #DIV/0! | D66: =(D48-D47)/D65 -> 20.057588 | E66: =(E48-E47)/E65 -> 3.696413 | F66: =(F48-F47)/F65 -> 3.1912508 | G66: =(G48-G47)/G65 -> 3.7684977 | H66: =(H48-H47)/H65 -> 3.6863666 | I66: =(I48-I47)/I65 -> 4.1763468 | ... AE66: =(AE48-AE47)/AE65 -> 35.406779 | AI66: =(AI48-AI47)/AI65 -> 1.7683653 | AJ66: =(AJ48-AJ47)/AJ65 -> 1.1621443 | AK66: =(AK48-AK47)/AK65 -> 1.3275976 | AL66: =(AL48-AL47)/AL65 -> 2.0688286 | AM66: =(AM48-AM47)/AM65 -> 1.9549967 | AN66: =(AN48-AN47)/AN65 -> 1.2111185 | AO66: =(AO48-AO47)/AO65 -> 1.2720053 | AP66: =(AP48-AP47)/AP65 -> 2.0741231 | ... DA66: =(DA48-DA47)/DA65 -> 9.6545536 | DE66: 15.514229
A67: DPS | B67: ='Annual Raw'!C110 -> 0 | C67: ='Annual Raw'!D110 -> 0 | D67: ='Annual Raw'!E110 -> 1 | E67: ='Annual Raw'!F110 -> 3 | F67: ='Annual Raw'!G110 -> 1.2 | G67: ='Annual Raw'!H110 -> 1.4 | H67: ='Annual Raw'!I110 -> 1.8 | I67: ='Annual Raw'!J110 -> 1.8 | ... AA67: ='Annual Raw'!AB110 -> 2
A68: DPS % of EPS | B68: =B67/B66 -> #DIV/0! | C68: =C67/C66 -> #DIV/0! | D68: =D67/D66 -> 0.049856444 | E68: =E67/E66 -> 0.81159763 | F68: =F67/F66 -> 0.3760281 | G68: =G67/G66 -> 0.37150083 | H68: =H67/H66 -> 0.48828567 | I68: =I67/I66 -> 0.43099869 | ... AE68: =AE67/AE66 -> 0 | DE68: 0
A69: EPS TTM | B69: =+B66 -> #DIV/0! | C69: =+C66 -> #DIV/0! | D69: =+D66 -> 20.057588 | E69: =+E66 -> 3.696413 | F69: =+F66 -> 3.1912508 | G69: =+G66 -> 3.7684977 | H69: =+H66 -> 3.6863666 | I69: =+I66 -> 4.1763468 | ... AE69: =+AE66 -> 35.406779 | AL69: =SUM(AI66:AL66) -> 6.3269358 | AM69: =SUM(AJ66:AM66) -> 6.5135672 | AN69: =SUM(AK66:AN66) -> 6.5625414 | AO69: =SUM(AL66:AO66) -> 6.506949 | AP69: =SUM(AM66:AP66) -> 6.5122435 | AQ69: =SUM(AN66:AQ66) -> 6.6790205 | AR69: =SUM(AO66:AR66) -> 7.2177366 | AS69: =SUM(AP66:AS66) -> 7.9854401 | ... DA69: =SUM(CX66:DA66) -> 35.406779 | DE69: 15.514229
A70: EPS Growth YoY % | C70: =+C69/B69-1 -> #DIV/0! | D70: =+D69/C69-1 -> #DIV/0! | E70: =+E69/D69-1 -> -0.81570999 | F70: =+F69/E69-1 -> -0.1366628 | G70: =+G69/F69-1 -> 0.1808842 | H70: =+H69/G69-1 -> -0.021794106 | I70: =+I69/H69-1 -> 0.13291682 | J70: =+J69/I69-1 -> -0.32531701 | ... AE70: =+AE69/AD69-1 -> 0.25290269 | AP70: =+IF(AL69<0,1-AP69/AL69,AP69/AL69-1) -> 0.029288703 | AQ70: =+IF(AM69<0,1-AQ69/AM69,AQ69/AM69-1) -> 0.025401341 | AR70: =+IF(AN69<0,1-AR69/AN69,AR69/AN69-1) -> 0.099838645 | AS70: =+IF(AO69<0,1-AS69/AO69,AS69/AO69-1) -> 0.22721725 | AT70: =+IF(AP69<0,1-AT69/AP69,AT69/AP69-1) -> 0.32398374 | AU70: =+IF(AQ69<0,1-AU69/AQ69,AU69/AQ69-1) -> 0.36801427 | AV70: =+IF(AR69<0,1-AV69/AR69,AV69/AR69-1) -> 0.31633963 | AW70: =+IF(AS69<0,1-AW69/AS69,AW69/AS69-1) -> 0.27515332 | ... DA70: =+IF(CW69<0,1-DA69/CW69,DA69/CW69-1) -> 0.25290269 | DE70: 1.0527145
A71: Bloomberg Estimate
A72: Estimate deviation
A73: Promoter Share holding % | B73: ='Annual Raw'!C112 -> 0 | C73: ='Annual Raw'!D112 -> 0 | D73: ='Annual Raw'!E112 -> 65.7 | E73: ='Annual Raw'!F112 -> 65.16 | F73: ='Annual Raw'!G112 -> 63.73 | G73: ='Annual Raw'!H112 -> 63.73 | H73: ='Annual Raw'!I112 -> 63.73 | I73: ='Annual Raw'!J112 -> 63.73 | ... AA73: ='Annual Raw'!AB112 -> 67.73 | AI73: ='QTR Raw'!C49 -> 63.7 | AJ73: ='QTR Raw'!D49 -> 63.7 | AK73: ='QTR Raw'!E49 -> 63.7 | AL73: ='QTR Raw'!F49 -> 63.7 | AM73: ='QTR Raw'!G49 -> 63.7 | AN73: ='QTR Raw'!H49 -> 63.78 | AO73: ='QTR Raw'!I49 -> 63.78 | AP73: ='QTR Raw'!J49 -> 63.78 | ... CL73: ='QTR Raw'!BF49 -> 67.73
A74: Pledge Share % | B74: ='Annual Raw'!C113 -> 0 | C74: ='Annual Raw'!D113 -> 0 | D74: ='Annual Raw'!E113 -> 0 | E74: ='Annual Raw'!F113 -> 0 | F74: ='Annual Raw'!G113 -> 0 | G74: ='Annual Raw'!H113 -> 0 | H74: ='Annual Raw'!I113 -> 0 | I74: ='Annual Raw'!J113 -> 0 | ... AA74: ='Annual Raw'!AB113 -> 0 | AI74: ='QTR Raw'!C50 -> 0 | AJ74: ='QTR Raw'!D50 -> 0 | AK74: ='QTR Raw'!E50 -> 0 | AL74: ='QTR Raw'!F50 -> 0 | AM74: ='QTR Raw'!G50 -> 0 | AN74: ='QTR Raw'!H50 -> 0 | AO74: ='QTR Raw'!I50 -> 0 | AP74: ='QTR Raw'!J50 -> 0 | ... CL74: ='QTR Raw'!BF50 -> 0
A76: Share Price
A77: Share Price - Close | B77: ='Annual Raw'!C106 -> 0 | C77: ='Annual Raw'!D106 -> 0 | D77: ='Annual Raw'!E106 -> 27 | E77: ='Annual Raw'!F106 -> 39.45 | F77: ='Annual Raw'!G106 -> 43.39 | G77: ='Annual Raw'!H106 -> 60.51 | H77: ='Annual Raw'!I106 -> 73.7 | I77: ='Annual Raw'!J106 -> 73.2 | ... AA77: ='Annual Raw'!AB106 -> 211.65 | AB77: =+CO77 -> 150.15 | AC77: =+CS77 -> 150.15 | AD77: =+CW77 -> 150.15 | AE77: =+DA77 -> 150.15 | AJ77: ='QTR Share Price'!HP21 -> 71.65 | AK77: ='QTR Share Price'!HQ21 -> 72.35 | AL77: ='QTR Share Price'!HR21 -> 62.15 | AM77: ='QTR Share Price'!HS21 -> 62.85 | AN77: ='QTR Share Price'!HT21 -> 60.1 | AO77: ='QTR Share Price'!HU21 -> 74.6 | AP77: ='QTR Share Price'!HV21 -> 89.5 | AQ77: ='QTR Share Price'!HW21 -> 134.3 | ... CL77: ='QTR Share Price'!JR21 -> 150.15 | CM77: =+CL77 -> 150.15 | CN77: =+CM77 -> 150.15 | CO77: =+CN77 -> 150.15 | CP77: =+CO77 -> 150.15 | CQ77: =+CP77 -> 150.15 | CR77: =+CQ77 -> 150.15 | CS77: =+CR77 -> 150.15 | CT77: =+CS77 -> 150.15 | ... DA77: =+CZ77 -> 150.15 | DE77: 211.65
A78: Share Price - High | B78: ='Annual Raw'!C107 -> 0 | C78: ='Annual Raw'!D107 -> 0 | D78: ='Annual Raw'!E107 -> 27.4 | E78: ='Annual Raw'!F107 -> 42.35 | F78: ='Annual Raw'!G107 -> 48.4 | G78: ='Annual Raw'!H107 -> 65.6 | H78: ='Annual Raw'!I107 -> 99.76 | I78: ='Annual Raw'!J107 -> 83.74 | ... AA78: ='Annual Raw'!AB107 -> 284.9 | AB78: =+MAX(CL78:CO78) -> 241.60194 | AC78: =+MAX(CP78:CS78) -> 309.24438 | AD78: =+MAX(CT78:CW78) -> 388.22824 | AE78: =+MAX(CX78:DA78) -> 486.41221 | AJ78: ='QTR Share Price'!HP19 -> 75.45 | AK78: ='QTR Share Price'!HQ19 -> 77 | AL78: ='QTR Share Price'!HR19 -> 81.8 | AM78: ='QTR Share Price'!HS19 -> 74.3 | AN78: ='QTR Share Price'!HT19 -> 72 | AO78: ='QTR Share Price'!HU19 -> 77.1 | AP78: ='QTR Share Price'!HV19 -> 100.8 | AQ78: ='QTR Share Price'!HW19 -> 145 | ... CL78: ='QTR Share Price'!JR19 -> 213.35 | CM78: =+CM69*CM86 -> 228.08748 | CN78: =+CN69*CN86 -> 228.56293 | CO78: =+CO69*CO86 -> 241.60194 | CP78: =+CP69*CP86 -> 263.83273 | CQ78: =+CQ69*CQ86 -> 278.59748 | CR78: =+CR69*CR86 -> 292.73141 | CS78: =+CS69*CS86 -> 309.24438 | CT78: =+CT69*CT86 -> 328.52023 | ... DA78: =+DA69*DA86 -> 486.41221 | DE78: 284.9
A79: Share Price - Low | B79: ='Annual Raw'!C108 -> 0 | C79: ='Annual Raw'!D108 -> 0 | D79: ='Annual Raw'!E108 -> 10.46 | E79: ='Annual Raw'!F108 -> 21 | F79: ='Annual Raw'!G108 -> 31.45 | G79: ='Annual Raw'!H108 -> 40.5 | H79: ='Annual Raw'!I108 -> 48 | I79: ='Annual Raw'!J108 -> 45.25 | ... AA79: ='Annual Raw'!AB108 -> 170.4 | AB79: =+MIN(CL79:CO79) -> 148.95 | AC79: =+MIN(CP79:CS79) -> 184.19444 | AD79: =+MIN(CT79:CW79) -> 229.35593 | AE79: =+MIN(CX79:DA79) -> 286.87551 | AJ79: =+'QTR Share Price'!HP20 -> 63.75 | AK79: =+'QTR Share Price'!HQ20 -> 65.25 | AL79: =+'QTR Share Price'!HR20 -> 61 | AM79: =+'QTR Share Price'!HS20 -> 56.5 | AN79: =+'QTR Share Price'!HT20 -> 56.85 | AO79: =+'QTR Share Price'!HU20 -> 60.1 | AP79: =+'QTR Share Price'!HV20 -> 68.5 | AQ79: =+'QTR Share Price'!HW20 -> 88.15 | ... CL79: =+'QTR Share Price'!JR20 -> 148.95 | CM79: =+CM87*CM69 -> 159.23895 | CN79: =+CN87*CN69 -> 159.57088 | CO79: =+CO87*CO69 -> 168.67405 | CP79: =+CP87*CP69 -> 184.19444 | CQ79: =+CQ87*CQ69 -> 194.50244 | CR79: =+CR87*CR69 -> 204.37002 | CS79: =+CS87*CS69 -> 215.89853 | CT79: =+CT87*CT69 -> 229.35593 | ... DA79: =+DA87*DA69 -> 339.58799 | DE79: 170.4
A81: Upside (%) | AB81: =+AB78/AB77-1 -> 0.6090705 | AC81: =+AC78/AC77-1 -> 1.0595697 | AD81: =+AD78/AD77-1 -> 1.5856027 | AE81: =+AE78/AE77-1 -> 2.2395085 | CM81: =+CM78/CM77-1 -> 0.51906414 | CN81: =+CN78/CN77-1 -> 0.52223061 | CO81: =+CO78/CO77-1 -> 0.6090705 | CP81: =+CP78/CP77-1 -> 0.75712771 | CQ81: =+CQ78/CQ77-1 -> 0.85546107 | CR81: =+CR78/CR77-1 -> 0.94959316 | CS81: =+CS78/CS77-1 -> 1.0595697 | CT81: =+CT78/CT77-1 -> 1.1879469 | ... DA81: =+DA78/DA77-1 -> 2.2395085 | DE81: 0.34609024
A82: Downside (%) | AB82: =+AB79/AB77-1 -> -0.007992008 | AC82: =+AC79/AC77-1 -> 0.22673622 | AD82: =+AD79/AD77-1 -> 0.52751203 | AE82: =+AE79/AE77-1 -> 0.91059283 | CM82: =+CM79/CM77-1 -> 0.060532474 | CN82: =+CN79/CN77-1 -> 0.062743139 | CO82: =+CO79/CO77-1 -> 0.12337029 | CP82: =+CP79/CP77-1 -> 0.22673622 | CQ82: =+CQ79/CQ77-1 -> 0.29538752 | CR82: =+CR79/CR77-1 -> 0.3611057 | CS82: =+CS79/CS77-1 -> 0.43788564 | CT82: =+CT79/CT77-1 -> 0.52751203 | ... DA82: =+DA79/DA77-1 -> 1.2616583 | DE82: -0.19489724
A84: PE
A85: PE - Close | B85: =+B77/B69 -> #DIV/0! | C85: =+C77/C69 -> #DIV/0! | D85: =+D77/D69 -> 1.346124 | E85: =+E77/E69 -> 10.672509 | F85: =+F77/F69 -> 13.59655 | G85: =+G77/G69 -> 16.056796 | H85: =+H77/H69 -> 19.992585 | I85: =+I77/I69 -> 17.52728 | ... AE85: =+AE77/AE69 -> 4.2407134 | AL85: =+AL77/AL69 -> 9.8230805 | AM85: =+AM77/AM69 -> 9.6490906 | AN85: =+AN77/AN69 -> 9.1580375 | AO85: =+AO77/AO69 -> 11.464666 | AP85: =+AP77/AP69 -> 13.743343 | AQ85: =+AQ77/AQ69 -> 20.107739 | AR85: =+AR77/AR69 -> 26.608064 | AS85: =+AS77/AS69 -> 22.628684 | ... DA85: =+DA77/DA69 -> 4.2407134 | DE85: 13.642315
A86: PE - High | B86: =+B78/B69 -> #DIV/0! | C86: =+C78/C69 -> #DIV/0! | D86: =+D78/D69 -> 1.3660666 | E86: =+E78/E69 -> 11.457053 | F86: =+F78/F69 -> 15.166467 | G86: =+G78/G69 -> 17.407467 | H86: =+H78/H69 -> 27.061877 | I86: =+I78/I69 -> 20.051017 | ... AE86: =+AE78/AE69 -> 13.737827 | AL86: =+AL78/AL69 -> 12.928849 | AM86: =+AM78/AM69 -> 11.40696 | AN86: =+AN78/AN69 -> 10.971359 | AO86: =+AO78/AO69 -> 11.848871 | AP86: =+AP78/AP69 -> 15.478537 | AQ86: =+AQ78/AQ69 -> 21.70977 | AR86: =+AR78/AR69 -> 29.372089 | AS86: =+AS78/AS69 -> 24.914093 | ... CL86: =+CL78/CL69 -> 13.737827 | CM86: =+CL86 -> 13.737827 | CN86: =+CM86 -> 13.737827 | CO86: =+CN86 -> 13.737827 | CP86: =+CO86 -> 13.737827 | CQ86: =+CP86 -> 13.737827 | CR86: =+CQ86 -> 13.737827 | CS86: =+CR86 -> 13.737827 | CT86: =+CS86 -> 13.737827 | ... DA86: =+CZ86 -> 13.737827 | DE86: 18.363787
A87: PE - Low | B87: =+B79/B69 -> #DIV/0! | C87: =+C79/C69 -> #DIV/0! | D87: =+D79/D69 -> 0.52149841 | E87: =+E79/E69 -> 5.6811834 | F87: =+F79/F69 -> 9.8550699 | G87: =+G79/G69 -> 10.746988 | H87: =+H79/H69 -> 13.020951 | I87: =+I79/I69 -> 10.834828 | ... AE87: =+AE79/AE69 -> 8.1022765 | AL87: =+AL79/AL69 -> 9.641318 | AM87: =+AM79/AM69 -> 8.6742024 | AN87: =+AN79/AN69 -> 8.6628025 | AO87: =+AO79/AO69 -> 9.2362795 | AP87: =+AP79/AP69 -> 10.518648 | AQ87: =+AQ79/AQ69 -> 13.198043 | AR87: =+AR79/AR69 -> 18.059678 | AS87: =+AS79/AS69 -> 20.925584 | ... CL87: =+CL79/CL69 -> 9.5910445 | CM87: =+CL87 -> 9.5910445 | CN87: =+CM87 -> 9.5910445 | CO87: =+CN87 -> 9.5910445 | CP87: =+CO87 -> 9.5910445 | CQ87: =+CP87 -> 9.5910445 | CR87: =+CQ87 -> 9.5910445 | CS87: =+CR87 -> 9.5910445 | CT87: =+CS87 -> 9.5910445 | ... DA87: =+CZ87 -> 9.5910445 | DE87: 10.983466
A89: PE - 1Yr Fwd | B89: =+B78/C69 -> #DIV/0! | C89: =+C78/D69 -> 0 | D89: =+D78/E69 -> 7.4125917 | E89: =+E78/F69 -> 13.270659 | F89: =+F78/G69 -> 12.843314 | G89: =+G78/H69 -> 17.7953 | H89: =+H78/I69 -> 23.886905 | I89: =+I78/J69 -> 29.719168 | ... AD89: =+AD78/AE69 -> 10.9648 | AL89: =+AL78/AP69 -> 12.560955 | AM89: =+AM78/AQ69 -> 11.124386 | AN89: =+AN78/AR69 -> 9.9754264 | AO89: =+AO78/AS69 -> 9.6550721 | AP89: =+AP78/AT69 -> 11.690881 | AQ89: =+AQ78/AU69 -> 15.869549 | AR89: =+AR78/AV69 -> 22.313458 | AS89: =+AS78/AW69 -> 19.538116 | ... CL89: =+CL78/CP69 -> 11.109181 | DE89: 16.199816
A90: Correlation | AO90: =+CORREL(AL69:AO69,AL86:AO86) -> -0.97156059 | AP90: =+CORREL(AM69:AP69,AM86:AP86) -> -0.44408671 | AQ90: =+CORREL(AN69:AQ69,AN86:AQ86) -> 0.7973312 | AR90: =+CORREL(AO69:AR69,AO86:AR86) -> 0.94231627 | AS90: =+CORREL(AP69:AS69,AP86:AS86) -> 0.63696517 | AT90: =+CORREL(AQ69:AT69,AQ86:AT86) -> 0.45728452 | AU90: =+CORREL(AR69:AU69,AR86:AU86) -> -0.081715466 | AV90: =+CORREL(AS69:AV69,AS86:AV86) -> 0.89474287 | ... CL90: =+CORREL(CI69:CL69,CI86:CL86) -> -0.91855605
A92: BVPS | E92: =+E$120/E$65 -> 21.702488 | F92: =+F$120/F$65 -> 23.761535 | G92: =+G$120/G$65 -> 26.046459 | H92: =+H$120/H$65 -> 29.629398 | I92: =+I$120/I$65 -> 31.537895 | J92: =+J$120/J$65 -> 32.583719 | K92: =+K$120/K$65 -> 34.618968 | L92: =+L$120/L$65 -> 38.869782 | ... AE92: =+AE$120/AE$65 -> 275.40095 | AL92: =+AL$120/AL$65 -> 49.052283 | AM92: =+AM$120/AM$65 -> 50.991396 | AN92: =+AN$120/AN$65 -> 52.202515 | AO92: =+AO$120/AO$65 -> 51.727333 | AP92: =+AP$120/AP$65 -> 53.966909 | AQ92: =+AQ$120/AQ$65 -> 56.43812 | AR92: =+AR$120/AR$65 -> 58.187955 | AS92: =+AS$120/AS$65 -> 75.11317 | ... DA92: =+DA$120/DA$65 -> 275.40095 | DE92: 171.63733
A93: PB
A94: PB - Close | E94: =+E77/E$92 -> 1.8177639 | F94: =+F77/F$92 -> 1.8260604 | G94: =+G77/G$92 -> 2.3231565 | H94: =+H77/H$92 -> 2.4873945 | I94: =+I77/I$92 -> 2.3210173 | J94: =+J77/J$92 -> 0.96367145 | K94: =+K77/K$92 -> 1.743264 | L94: =+L77/L$92 -> 1.4587167 | ... AE94: =+AE77/AE$92 -> 0.54520508 | AL94: =+AL77/AL$92 -> 1.2670154 | AM94: =+AM77/AM$92 -> 1.2325609 | AN94: =+AN77/AN$92 -> 1.1512855 | AO94: =+AO77/AO$92 -> 1.4421776 | AP94: =+AP77/AP$92 -> 1.6584237 | AQ94: =+AQ77/AQ$92 -> 2.3795973 | AR94: =+AR77/AR$92 -> 3.3005112 | AS94: =+AS77/AS$92 -> 2.4057033 | ... DA94: =+DA77/DA$92 -> 0.54520508 | DE94: 1.2331234
A95: PB - High | E95: =+E78/E$92 -> 1.9513891 | F95: =+F78/F$92 -> 2.0369054 | G95: =+G78/G$92 -> 2.5185765 | H95: =+H78/H$92 -> 3.3669263 | I95: =+I78/I$92 -> 2.6552184 | J95: =+J78/J$92 -> 2.3846265 | K95: =+K78/K$92 -> 2.1924397 | L95: =+L78/L$92 -> 1.8394752 | ... AE95: =+AE78/AE$92 -> 1.7661965 | AL95: =+AL78/AL$92 -> 1.6676084 | AM95: =+AM78/AM$92 -> 1.4571086 | AN95: =+AN78/AN$92 -> 1.3792439 | AO95: =+AO78/AO$92 -> 1.4905079 | AP95: =+AP78/AP$92 -> 1.8678112 | AQ95: =+AQ78/AQ$92 -> 2.5691855 | AR95: =+AR78/AR$92 -> 3.6433657 | AS95: =+AS78/AS$92 -> 2.64867 | ... CL95: =+CL78/CL$92 -> 1.2189631 | CM95: =+CL95 -> 1.2189631 | CN95: =+CM95 -> 1.2189631 | CO95: =+CN95 -> 1.2189631 | CP95: =+CO95 -> 1.2189631 | CQ95: =+CP95 -> 1.2189631 | CR95: =+CQ95 -> 1.2189631 | CS95: =+CR95 -> 1.2189631 | CT95: =+CS95 -> 1.2189631 | ... DA95: =+CZ95 -> 1.2189631 | DE95: 1.6598954
A96: PB - Low | E96: =+E79/E$92 -> 0.96763097 | F96: =+F79/F$92 -> 1.3235677 | G96: =+G79/G$92 -> 1.5549138 | H96: =+H79/H$92 -> 1.6200127 | I96: =+I79/I$92 -> 1.4347819 | J96: =+J79/J$92 -> 0.70587399 | K96: =+K79/K$92 -> 0.78425216 | L96: =+L79/L$92 -> 1.2863463 | ... AE96: =+AE79/AE$92 -> 1.0416649 | AL96: =+AL79/AL$92 -> 1.2435711 | AM96: =+AM79/AM$92 -> 1.1080301 | AN96: =+AN79/AN$92 -> 1.089028 | AO96: =+AO79/AO$92 -> 1.1618616 | AP96: =+AP79/AP$92 -> 1.2692963 | AQ96: =+AQ79/AQ$92 -> 1.5618876 | AR96: =+AR79/AR$92 -> 2.2401543 | AS96: =+AS79/AS$92 -> 2.2246432 | ... CL96: =+CL79/CL$92 -> 0.85101734 | CM96: =+CL96 -> 0.85101734 | CN96: =+CM96 -> 0.85101734 | CO96: =+CN96 -> 0.85101734 | CP96: =+CO96 -> 0.85101734 | CQ96: =+CP96 -> 0.85101734 | CR96: =+CQ96 -> 0.85101734 | CS96: =+CR96 -> 0.85101734 | CT96: =+CS96 -> 0.85101734 | ... DA96: =+CZ96 -> 0.85101734 | DE96: 0.99279104
A98: Sales Rolling | E98: =+E10 -> 382.6179 | F98: =+F10 -> 394.0211 | G98: =+G10 -> 432.8604 | H98: =+H10 -> 501.2049 | I98: =+I10 -> 570.5874 | J98: =+J10 -> 612.0884 | K98: =+K10 -> 577.6923 | L98: =+L10 -> 716.3364 | ... AE98: =+AE10 -> 2384.1383 | AL98: =+SUM(AI8:AL8) -> 1013.49 | AM98: =+SUM(AJ8:AM8) -> 1054.62 | AN98: =+SUM(AK8:AN8) -> 1104.11 | AO98: =+SUM(AL8:AO8) -> 1158.72 | AP98: =+SUM(AM8:AP8) -> 1195.57 | AQ98: =+SUM(AN8:AQ8) -> 1230.45 | AR98: =+SUM(AO8:AR8) -> 1280.58 | AS98: =+SUM(AP8:AS8) -> 1290.86 | ... DA98: =+SUM(CX8:DA8) -> 2384.1383 | DE98: 2469.41
A99: Sales Per Share | E99: =+E98/E65 -> 50.644328 | F99: =+F98/F65 -> 52.153686 | G99: =+G98/G65 -> 57.29456 | H99: =+H98/H65 -> 66.340821 | I99: =+I98/I65 -> 75.524474 | J99: =+J98/J65 -> 81.017657 | K99: =+K98/K65 -> 76.464897 | L99: =+L98/L65 -> 94.816201 | ... AE99: =+AE98/AE65 -> 315.57092 | AL99: =+AL98/AL65 -> 134.14825 | AM99: =+AM98/AM65 -> 139.59232 | AN99: =+AN98/AN65 -> 146.14295 | AO99: =+AO98/AO65 -> 153.37128 | AP99: =+AP98/AP65 -> 158.24884 | AQ99: =+AQ98/AQ65 -> 162.86565 | AR99: =+AR98/AR65 -> 169.50099 | AS99: =+AS98/AS65 -> 170.86168 | ... DA99: =+DA98/DA65 -> 315.57092 | DE99: 326.85771
A101: Price to Sales
A102: Price to Sales - Close | E102: =+E77/E$99 -> 0.77896186 | F102: =+F77/F$99 -> 0.8319642 | G102: =+G77/G$99 -> 1.0561212 | H102: =+H77/H$99 -> 1.1109299 | I102: =+I77/I$99 -> 0.96922224 | J102: =+J77/J$99 -> 0.38756983 | K102: =+K77/K$99 -> 0.78925104 | L102: =+L77/L$99 -> 0.59799907 | ... AE102: =+AE77/AE$99 -> 0.4758043 | AL102: =+AL77/AL99 -> 0.46329342 | AM102: =+AM77/AM99 -> 0.45023966 | AN102: =+AN77/AN99 -> 0.41124118 | AO102: =+AO77/AO99 -> 0.48640137 | AP102: =+AP77/AP99 -> 0.56556496 | AQ102: =+AQ77/AQ99 -> 0.82460604 | AR102: =+AR77/AR99 -> 1.1330317 | AS102: =+AS77/AS99 -> 1.0575806 | ... DA102: =+DA77/DA99 -> 0.4758043 | DE102: 0.64752947
A103: Price to Sales - High | E103: =+E78/E$99 -> 0.83622395 | F103: =+F78/F$99 -> 0.92802644 | G103: =+G78/G$99 -> 1.1449604 | H103: =+H78/H$99 -> 1.5037499 | I103: =+I78/I$99 -> 1.1087797 | J103: =+J78/J$99 -> 0.9590502 | K103: =+K78/K$99 -> 0.99261233 | L103: =+L78/L$99 -> 0.75409054 | ... AE103: =+AE78/AE$99 -> 1.5413721 | AL103: =+AL78/AL99 -> 0.60977316 | AM103: =+AM78/AM99 -> 0.53226423 | AN103: =+AN78/AN99 -> 0.4926683 | AO103: =+AO78/AO99 -> 0.50270169 | AP103: =+AP78/AP99 -> 0.63697149 | AQ103: =+AQ78/AQ99 -> 0.89030436 | AR103: =+AR78/AR99 -> 1.2507301 | AS103: =+AS78/AS99 -> 1.1643921 | ... CL103: =+CL78/CL99 -> 0.65189367 | CM103: =+CL103 -> 0.65189367 | CN103: =+CM103 -> 0.65189367 | CO103: =+CN103 -> 0.65189367 | CP103: =+CO103 -> 0.65189367 | CQ103: =+CP103 -> 0.65189367 | CR103: =+CQ103 -> 0.65189367 | CS103: =+CR103 -> 0.65189367 | CT103: =+CS103 -> 0.65189367 | ... DA103: =+CZ103 -> 0.65189367 | DE103: 0.8716331
A104: Price to Sales - Low | E104: =+E79/E$99 -> 0.4146565 | F104: =+F79/F$99 -> 0.60302545 | G104: =+G79/G$99 -> 0.70687339 | H104: =+H79/H$99 -> 0.72353642 | I104: =+I79/I$99 -> 0.59914353 | J104: =+J79/J$99 -> 0.28388873 | K104: =+K79/K$99 -> 0.35506488 | L104: =+L79/L$99 -> 0.52733604 | ... AE104: =+AE79/AE$99 -> 0.90906829 | AL104: =+AL79/AL99 -> 0.45472082 | AM104: =+AM79/AM99 -> 0.40475005 | AN104: =+AN79/AN99 -> 0.38900268 | AO104: =+AO79/AO99 -> 0.39185955 | AP104: =+AP79/AP99 -> 0.43286257 | AQ104: =+AQ79/AQ99 -> 0.54124365 | AR104: =+AR79/AR99 -> 0.76902204 | AS104: =+AS79/AS99 -> 0.97798406 | ... CL104: =+CL79/CL99 -> 0.45511864 | CM104: =+CL104 -> 0.45511864 | CN104: =+CM104 -> 0.45511864 | CO104: =+CN104 -> 0.45511864 | CP104: =+CO104 -> 0.45511864 | CQ104: =+CP104 -> 0.45511864 | CR104: =+CQ104 -> 0.45511864 | CS104: =+CR104 -> 0.45511864 | CT104: =+CS104 -> 0.45511864 | ... DA104: =+CZ104 -> 0.45511864 | DE104: 0.52132777
A107: Market Cap High | B107: =+B78*B65 -> #DIV/0! | C107: =+C78*C65 -> #DIV/0! | D107: =+D78*D65 -> 34.352476 | E107: =+E78*E65 -> 319.95425 | F107: =+F78*F65 -> 365.662 | G107: =+G78*G65 -> 495.608 | H107: =+H78*H65 -> 753.6868 | I107: =+I78*I65 -> 632.6557 | ... AE107: =+AE78*AE65 -> 3674.8442 | AL107: =+AL78*AL65 -> 617.999 | AM107: =+AM78*AM65 -> 561.3365 | AN107: =+AN78*AN65 -> 543.96 | AO107: =+AO78*AO65 -> 582.4905 | AP107: =+AP78*AP65 -> 761.544 | AQ107: =+AQ78*AQ65 -> 1095.475 | AR107: =+AR78*AR65 -> 1601.66 | AS107: =+AS78*AS65 -> 1503.0672 | ... DA107: =+DA78*DA65 -> 3674.8442 | DE107: 2152.4195
A108: Market Cap Low | B108: =+B79*B65 -> #DIV/0! | C108: =+C79*C65 -> #DIV/0! | D108: =+D79*D65 -> 13.11412 | E108: =+E79*E65 -> 158.655 | F108: =+F79*F65 -> 237.60475 | G108: =+G79*G65 -> 305.9775 | H108: =+H79*H65 -> 362.64 | I108: =+I79*I65 -> 341.86375 | ... AE108: =+AE79*AE65 -> 2167.3445 | AL108: =+AL79*AL65 -> 460.855 | AM108: =+AM79*AM65 -> 426.8575 | AN108: =+AN79*AN65 -> 429.50175 | AO108: =+AO79*AO65 -> 454.0555 | AP108: =+AP79*AP65 -> 517.5175 | AQ108: =+AQ79*AQ65 -> 665.97325 | AR108: =+AR79*AR65 -> 984.79425 | AS108: =+AS79*AS65 -> 1262.4405 | ... DA108: =+DA79*DA65 -> 2565.5873 | DE108: 1287.372
A109: Net Debt | B109: =+B168 -> 0 | C109: =+C168 -> 0 | D109: =+D168 -> -4.8113 | E109: =+E168 -> -30.4495 | F109: =+F168 -> -9.3086 | G109: =+G168 -> -5.479 | H109: =+H168 -> 18.1975 | I109: =+I168 -> 49.6678 | ... AE109: =+AE168 -> -1034.2015 | AL109: =+AL168 -> -36.829554 | AM109: =+AM168 -> -6.76 | AN109: =+AN168 -> -45.158005 | AO109: =+AO168 -> -30.09 | AP109: =+AP168 -> -51.518291 | AQ109: =+AQ168 -> -18.74 | AR109: =+AR168 -> -40.344399 | AS109: =+AS168 -> -160.26 | ... DA109: =+DA168 -> -1034.2015 | DE109: -235.67414
A110: EV High | B110: =+B107+B109 -> #DIV/0! | C110: =+C107+C109 -> #DIV/0! | D110: =+D107+D109 -> 29.541176 | E110: =+E107+E109 -> 289.50475 | F110: =+F107+F109 -> 356.3534 | G110: =+G107+G109 -> 490.129 | H110: =+H107+H109 -> 771.8843 | I110: =+I107+I109 -> 682.3235 | ... AE110: =+AE107+AE109 -> 2640.6427 | AL110: =+AL107+AL109 -> 581.16945 | AM110: =+AM107+AM109 -> 554.5765 | AN110: =+AN107+AN109 -> 498.802 | AO110: =+AO107+AO109 -> 552.4005 | AP110: =+AP107+AP109 -> 710.02571 | AQ110: =+AQ107+AQ109 -> 1076.735 | AR110: =+AR107+AR109 -> 1561.3156 | AS110: =+AS107+AS109 -> 1342.8072 | ... DA110: =+DA107+DA109 -> 2640.6427 | DE110: 1916.7454
A111: EV Low | B111: =+B108+B109 -> #DIV/0! | C111: =+C108+C109 -> #DIV/0! | D111: =+D108+D109 -> 8.3028204 | E111: =+E108+E109 -> 128.2055 | F111: =+F108+F109 -> 228.29615 | G111: =+G108+G109 -> 300.4985 | H111: =+H108+H109 -> 380.8375 | I111: =+I108+I109 -> 391.53155 | ... AE111: =+AE108+AE109 -> 1133.143 | AL111: =+AL108+AL109 -> 424.02545 | AM111: =+AM108+AM109 -> 420.0975 | AN111: =+AN108+AN109 -> 384.34375 | AO111: =+AO108+AO109 -> 423.9655 | AP111: =+AP108+AP109 -> 465.99921 | AQ111: =+AQ108+AQ109 -> 647.23325 | AR111: =+AR108+AR109 -> 944.44985 | AS111: =+AS108+AS109 -> 1102.1805 | ... DA111: =+DA108+DA109 -> 1531.3858 | DE111: 1051.6979
A112: EBITDA | B112: =+B28 -> 0 | C112: =+C28 -> 0 | D112: =+D28 -> 56.0821 | E112: =+E28 -> 56.2684 | F112: =+F28 -> 50.8491 | G112: =+G28 -> 54.675 | H112: =+H28 -> 55.0118 | I112: =+I28 -> 55.8496 | ... AE112: =+AE28 -> 183.1496 | AL112: =+SUM(AI28:AL28) -> 96.81 | AM112: =+SUM(AJ28:AM28) -> 103.74 | AN112: =+SUM(AK28:AN28) -> 110.97 | AO112: =+SUM(AL28:AO28) -> 114.32 | AP112: =+SUM(AM28:AP28) -> 114.71 | AQ112: =+SUM(AN28:AQ28) -> 115.02 | AR112: =+SUM(AO28:AR28) -> 117.03 | AS112: =+SUM(AP28:AS28) -> 118.52 | ... DA112: =+SUM(CX28:DA28) -> 183.1496 | DE112: 190.82
...

Sheet QTR Raw
A1: ='Annual Raw'!A1 -> 109820 | B1: X | C1: 201206 | D1: 201209 | E1: 201212 | F1: 201303 | G1: 201306 | H1: 201309 | I1: 201312 | J1: 201403 | K1: 201406 | L1: 201409 | M1: 201412 | N1: 201503 | O1: 201506 | P1: 201509 | Q1: 201512 | R1: 201603 | S1: 201606 | T1: 201609 | U1: 201612 | V1: 201703 | W1: 201706 | X1: 201709 | Y1: 201712 | Z1: 201803 | AA1: 201806 | AB1: 201809 | AC1: 201812 | AD1: 201903 | AE1: 201906 | AF1: 201909 | AG1: 201912 | AH1: 202003 | AI1: 202006 | AJ1: 202009 | AK1: 202012 | AL1: 202103 | AM1: 202106 | AN1: 202109 | AO1: 202112 | AP1: 202203 | AQ1: 202206 | AR1: 202209 | AS1: 202212 | AT1: 202303 | AU1: 202306 | AV1: 202309 | AW1: 202312 | AX1: 202403 | AY1: 202406 | AZ1: 202409 | BA1: 202412 | BB1: 202503 | BC1: 202506 | BD1: 202509 | BE1: 202512 | BF1: 202603 | BG1: 202606 | BH1: 202609 | BI1: 202612 | BJ1: 202703 | BK1: 202706 | BL1: 202709 | BM1: 202712 | BN1: 202803 | BO1: 202806 | BP1: 202809 | BQ1: 202812 | BR1: 202903 | BS1: 202906 | BT1: 202909 | BU1: 202912
A3: Field Description | B3: Field Name
A4: Company Name | B4: CD_COMPNAME | C4: =_xll.EQNXTDZ(A1,B4,C1) -> Huhtamaki India Ltd.
A5: Date End | B5: QTR_DATE_END | C5: =_xll.EQNXTDZ($A$1,$B5,C$1,$B$1) -> 201206 | D5: =_xll.EQNXTDZ($A$1,$B5,D$1,$B$1) -> 201209 | E5: =_xll.EQNXTDZ($A$1,$B5,E$1,$B$1) -> 201212 | F5: =_xll.EQNXTDZ($A$1,$B5,F$1,$B$1) -> 201303 | G5: =_xll.EQNXTDZ($A$1,$B5,G$1,$B$1) -> 201306 | H5: =_xll.EQNXTDZ($A$1,$B5,H$1,$B$1) -> 201309 | I5: =_xll.EQNXTDZ($A$1,$B5,I$1,$B$1) -> 201312 | J5: =_xll.EQNXTDZ($A$1,$B5,J$1,$B$1) -> 201403 | ... BU5: =_xll.EQNXTDZ($A$1,$B5,BU$1,$B$1) -> 0
A6: Gross Sales | B6: QTR_GROSS_SALE | C6: =_xll.EQNXTDZ($A$1,$B6,C$1,$B$1) -> 253.76 | D6: =_xll.EQNXTDZ($A$1,$B6,D$1,$B$1) -> 235.39 | E6: =_xll.EQNXTDZ($A$1,$B6,E$1,$B$1) -> 243.41 | F6: =_xll.EQNXTDZ($A$1,$B6,F$1,$B$1) -> 273.21 | G6: =_xll.EQNXTDZ($A$1,$B6,G$1,$B$1) -> 294.64 | H6: =_xll.EQNXTDZ($A$1,$B6,H$1,$B$1) -> 282.76 | I6: =_xll.EQNXTDZ($A$1,$B6,I$1,$B$1) -> 297.41 | J6: =_xll.EQNXTDZ($A$1,$B6,J$1,$B$1) -> 309.59 | ... BU6: =_xll.EQNXTDZ($A$1,$B6,BU$1,$B$1) -> 0
A7: Less: Excise Duty | B7: QTR_EXCISE_DUTY | C7: =_xll.EQNXTDZ($A$1,$B7,C$1,$B$1) -> 16.98 | D7: =_xll.EQNXTDZ($A$1,$B7,D$1,$B$1) -> 14.36 | E7: =_xll.EQNXTDZ($A$1,$B7,E$1,$B$1) -> 15.86 | F7: =_xll.EQNXTDZ($A$1,$B7,F$1,$B$1) -> 18.48 | G7: =_xll.EQNXTDZ($A$1,$B7,G$1,$B$1) -> 18.9 | H7: =_xll.EQNXTDZ($A$1,$B7,H$1,$B$1) -> 17.45 | I7: =_xll.EQNXTDZ($A$1,$B7,I$1,$B$1) -> 18.39 | J7: =_xll.EQNXTDZ($A$1,$B7,J$1,$B$1) -> 20.56 | ... BU7: =_xll.EQNXTDZ($A$1,$B7,BU$1,$B$1) -> 0
A8: Other operating income | B8: QTR_JOB_WORKS | C8: =_xll.EQNXTDZ($A$1,$B8,C$1,$B$1) -> 1.79 | D8: =_xll.EQNXTDZ($A$1,$B8,D$1,$B$1) -> 2.01 | E8: =_xll.EQNXTDZ($A$1,$B8,E$1,$B$1) -> 1.84 | F8: =_xll.EQNXTDZ($A$1,$B8,F$1,$B$1) -> 2.08 | G8: =_xll.EQNXTDZ($A$1,$B8,G$1,$B$1) -> 2.04 | H8: =_xll.EQNXTDZ($A$1,$B8,H$1,$B$1) -> 4.13 | I8: =_xll.EQNXTDZ($A$1,$B8,I$1,$B$1) -> 2.45 | J8: =_xll.EQNXTDZ($A$1,$B8,J$1,$B$1) -> 2.55 | ... BU8: =_xll.EQNXTDZ($A$1,$B8,BU$1,$B$1) -> 0
A9: Net Sales & Other Operating Income | B9: QTR_NET_SALES | C9: =_xll.EQNXTDZ($A$1,$B9,C$1,$B$1) -> 238.57 | D9: =_xll.EQNXTDZ($A$1,$B9,D$1,$B$1) -> 223.04 | E9: =_xll.EQNXTDZ($A$1,$B9,E$1,$B$1) -> 229.39 | F9: =_xll.EQNXTDZ($A$1,$B9,F$1,$B$1) -> 256.81 | G9: =_xll.EQNXTDZ($A$1,$B9,G$1,$B$1) -> 277.78 | H9: =_xll.EQNXTDZ($A$1,$B9,H$1,$B$1) -> 269.44 | I9: =_xll.EQNXTDZ($A$1,$B9,I$1,$B$1) -> 281.47 | J9: =_xll.EQNXTDZ($A$1,$B9,J$1,$B$1) -> 291.58 | ... BU9: =_xll.EQNXTDZ($A$1,$B9,BU$1,$B$1) -> 0
A10: (Increase) / Decrease In Stocks | B10: QTR_INC_DEC_INVENTORY | C10: =_xll.EQNXTDZ($A$1,$B10,C$1,$B$1) -> -1.23 | D10: =_xll.EQNXTDZ($A$1,$B10,D$1,$B$1) -> -2.47 | E10: =_xll.EQNXTDZ($A$1,$B10,E$1,$B$1) -> 2.45 | F10: =_xll.EQNXTDZ($A$1,$B10,F$1,$B$1) -> -2.98 | G10: =_xll.EQNXTDZ($A$1,$B10,G$1,$B$1) -> -2.74 | H10: =_xll.EQNXTDZ($A$1,$B10,H$1,$B$1) -> 3 | I10: =_xll.EQNXTDZ($A$1,$B10,I$1,$B$1) -> 5.15 | J10: =_xll.EQNXTDZ($A$1,$B10,J$1,$B$1) -> -6.94 | ... BU10: =_xll.EQNXTDZ($A$1,$B10,BU$1,$B$1) -> 0
A11: Cost of Services & Raw Materials | B11: QTR_RAW_MATERIAL_COST | C11: =_xll.EQNXTDZ($A$1,$B11,C$1,$B$1) -> 167.83 | D11: =_xll.EQNXTDZ($A$1,$B11,D$1,$B$1) -> 161.33 | E11: =_xll.EQNXTDZ($A$1,$B11,E$1,$B$1) -> 153.51 | F11: =_xll.EQNXTDZ($A$1,$B11,F$1,$B$1) -> 177.39 | G11: =_xll.EQNXTDZ($A$1,$B11,G$1,$B$1) -> 193.29 | H11: =_xll.EQNXTDZ($A$1,$B11,H$1,$B$1) -> 184.36 | I11: =_xll.EQNXTDZ($A$1,$B11,I$1,$B$1) -> 194.83 | J11: =_xll.EQNXTDZ($A$1,$B11,J$1,$B$1) -> 212.07 | ... BU11: =_xll.EQNXTDZ($A$1,$B11,BU$1,$B$1) -> 0
A12: Purchase of Finished Goods | B12: QTR_PURCHASE_FIN_GOOD | C12: =_xll.EQNXTDZ($A$1,$B12,C$1,$B$1) -> 0 | D12: =_xll.EQNXTDZ($A$1,$B12,D$1,$B$1) -> 0 | E12: =_xll.EQNXTDZ($A$1,$B12,E$1,$B$1) -> 0 | F12: =_xll.EQNXTDZ($A$1,$B12,F$1,$B$1) -> 0 | G12: =_xll.EQNXTDZ($A$1,$B12,G$1,$B$1) -> 0 | H12: =_xll.EQNXTDZ($A$1,$B12,H$1,$B$1) -> 0 | I12: =_xll.EQNXTDZ($A$1,$B12,I$1,$B$1) -> 0 | J12: =_xll.EQNXTDZ($A$1,$B12,J$1,$B$1) -> 0 | ... BU12: =_xll.EQNXTDZ($A$1,$B12,BU$1,$B$1) -> 0
A13: Excise Duty | B13: QTR_EXCISE | C13: =_xll.EQNXTDZ($A$1,$B13,C$1,$B$1) -> 0 | D13: =_xll.EQNXTDZ($A$1,$B13,D$1,$B$1) -> 0 | E13: =_xll.EQNXTDZ($A$1,$B13,E$1,$B$1) -> 0 | F13: =_xll.EQNXTDZ($A$1,$B13,F$1,$B$1) -> 0 | G13: =_xll.EQNXTDZ($A$1,$B13,G$1,$B$1) -> 0 | H13: =_xll.EQNXTDZ($A$1,$B13,H$1,$B$1) -> 0 | I13: =_xll.EQNXTDZ($A$1,$B13,I$1,$B$1) -> 0 | J13: =_xll.EQNXTDZ($A$1,$B13,J$1,$B$1) -> 0 | ... BU13: =_xll.EQNXTDZ($A$1,$B13,BU$1,$B$1) -> 0
A14: Operating & Manufacturing Expenses | B14: QTR_MFG_EXPS | C14: =_xll.EQNXTDZ($A$1,$B14,C$1,$B$1) -> 28.78 | D14: =_xll.EQNXTDZ($A$1,$B14,D$1,$B$1) -> 28.05 | E14: =_xll.EQNXTDZ($A$1,$B14,E$1,$B$1) -> 31.03 | F14: =_xll.EQNXTDZ($A$1,$B14,F$1,$B$1) -> 31.11 | G14: =_xll.EQNXTDZ($A$1,$B14,G$1,$B$1) -> 32.84 | H14: =_xll.EQNXTDZ($A$1,$B14,H$1,$B$1) -> 33.19 | I14: =_xll.EQNXTDZ($A$1,$B14,I$1,$B$1) -> 35.19 | J14: =_xll.EQNXTDZ($A$1,$B14,J$1,$B$1) -> 33.33 | ... BU14: =_xll.EQNXTDZ($A$1,$B14,BU$1,$B$1) -> 0
A15: Electricity Power & Fuel Cost | B15: QTR_ELECTRICITY_POWER_FUEL | C15: =_xll.EQNXTDZ($A$1,$B15,C$1,$B$1) -> 0 | D15: =_xll.EQNXTDZ($A$1,$B15,D$1,$B$1) -> 0 | E15: =_xll.EQNXTDZ($A$1,$B15,E$1,$B$1) -> 0 | F15: =_xll.EQNXTDZ($A$1,$B15,F$1,$B$1) -> 0 | G15: =_xll.EQNXTDZ($A$1,$B15,G$1,$B$1) -> 0 | H15: =_xll.EQNXTDZ($A$1,$B15,H$1,$B$1) -> 0 | I15: =_xll.EQNXTDZ($A$1,$B15,I$1,$B$1) -> 0 | J15: =_xll.EQNXTDZ($A$1,$B15,J$1,$B$1) -> 0 | ... BU15: =_xll.EQNXTDZ($A$1,$B15,BU$1,$B$1) -> 0
A16: Employee Cost | B16: QTR_EXPLOYEE_COST | C16: =_xll.EQNXTDZ($A$1,$B16,C$1,$B$1) -> 17.92 | D16: =_xll.EQNXTDZ($A$1,$B16,D$1,$B$1) -> 18.19 | E16: =_xll.EQNXTDZ($A$1,$B16,E$1,$B$1) -> 18.34 | F16: =_xll.EQNXTDZ($A$1,$B16,F$1,$B$1) -> 20.18 | G16: =_xll.EQNXTDZ($A$1,$B16,G$1,$B$1) -> 22.05 | H16: =_xll.EQNXTDZ($A$1,$B16,H$1,$B$1) -> 22.89 | I16: =_xll.EQNXTDZ($A$1,$B16,I$1,$B$1) -> 18.98 | J16: =_xll.EQNXTDZ($A$1,$B16,J$1,$B$1) -> 21.1 | ... BU16: =_xll.EQNXTDZ($A$1,$B16,BU$1,$B$1) -> 0
... A42: Consolidated PAT(after extra items) | B42: QTR_CONS_PAT_EXITM | C42: =_xll.EQNXTDZ($A$1,$B42,C$1,$B$1) -> 13.36 | D42: =_xll.EQNXTDZ($A$1,$B42,D$1,$B$1) -> 8.78 | E42: =_xll.EQNXTDZ($A$1,$B42,E$1,$B$1) -> 10.03 | F42: =_xll.EQNXTDZ($A$1,$B42,F$1,$B$1) -> 15.63 | G42: =_xll.EQNXTDZ($A$1,$B42,G$1,$B$1) -> 14.77 | H42: =_xll.EQNXTDZ($A$1,$B42,H$1,$B$1) -> 9.15 | I42: =_xll.EQNXTDZ($A$1,$B42,I$1,$B$1) -> 16.66 | J42: =_xll.EQNXTDZ($A$1,$B42,J$1,$B$1) -> 16.92 | ... BU42: =_xll.EQNXTDZ($A$1,$B42,BU$1,$B$1) -> 0
A44: Field Description | B44: Field Name
A45: Equity Capital | B45: QTR_EQUITY_CAP | C45: =_xll.EQNXTDZ($A$1,$B45,C$1,$B$1) -> 12.54 | D45: =_xll.EQNXTDZ($A$1,$B45,D$1,$B$1) -> 12.54 | E45: =_xll.EQNXTDZ($A$1,$B45,E$1,$B$1) -> 12.54 | F45: =_xll.EQNXTDZ($A$1,$B45,F$1,$B$1) -> 12.54 | G45: =_xll.EQNXTDZ($A$1,$B45,G$1,$B$1) -> 12.54 | H45: =_xll.EQNXTDZ($A$1,$B45,H$1,$B$1) -> 12.54 | I45: =_xll.EQNXTDZ($A$1,$B45,I$1,$B$1) -> 12.54 | J45: =_xll.EQNXTDZ($A$1,$B45,J$1,$B$1) -> 12.54 | ... BU45: =_xll.EQNXTDZ($A$1,$B45,BU$1,$B$1) -> 0
A46: Face Value | B46: QTR_FV | C46: =_xll.EQNXTDZ($A$1,$B46,C$1,$B$1) -> 2 | D46: =_xll.EQNXTDZ($A$1,$B46,D$1,$B$1) -> 2 | E46: =_xll.EQNXTDZ($A$1,$B46,E$1,$B$1) -> 2 | F46: =_xll.EQNXTDZ($A$1,$B46,F$1,$B$1) -> 2 | G46: =_xll.EQNXTDZ($A$1,$B46,G$1,$B$1) -> 2 | H46: =_xll.EQNXTDZ($A$1,$B46,H$1,$B$1) -> 2 | I46: =_xll.EQNXTDZ($A$1,$B46,I$1,$B$1) -> 2 | J46: =_xll.EQNXTDZ($A$1,$B46,J$1,$B$1) -> 2 | ... BU46: =_xll.EQNXTDZ($A$1,$B46,BU$1,$B$1) -> 0
A47: Month End | B47: BMONTH_MONTHEND | C47: =_xll.EQNXTDZ($A$1,$B47,C$5) -> 201206 | D47: =_xll.EQNXTDZ($A$1,$B47,D$5) -> 201209 | E47: =_xll.EQNXTDZ($A$1,$B47,E$5) -> 201212 | F47: =_xll.EQNXTDZ($A$1,$B47,F$5) -> 201303 | G47: =_xll.EQNXTDZ($A$1,$B47,G$5) -> 201306 | H47: =_xll.EQNXTDZ($A$1,$B47,H$5) -> 201309 | I47: =_xll.EQNXTDZ($A$1,$B47,I$5) -> 201312 | J47: =_xll.EQNXTDZ($A$1,$B47,J$5) -> 201403 | ... BU47: =_xll.EQNXTDZ($A$1,$B47,BU$5) -> 0
A48: Close | B48: BMONTH_CLOSE | C48: =_xll.EQNXTDZ($A$1,$B48,C$5) -> 71.4 | D48: =_xll.EQNXTDZ($A$1,$B48,D$5) -> 71.65 | E48: =_xll.EQNXTDZ($A$1,$B48,E$5) -> 72.35 | F48: =_xll.EQNXTDZ($A$1,$B48,F$5) -> 62.15 | G48: =_xll.EQNXTDZ($A$1,$B48,G$5) -> 62.85 | H48: =_xll.EQNXTDZ($A$1,$B48,H$5) -> 60.1 | I48: =_xll.EQNXTDZ($A$1,$B48,I$5) -> 74.6 | J48: =_xll.EQNXTDZ($A$1,$B48,J$5) -> 89.5 | ... BU48: =_xll.EQNXTDZ($A$1,$B48,BU$5) -> 0
A49: Total of Promoter and Promoter Group | B49: SHP_TPFTOTALPROMOTER | C49: =_xll.EQNXTDZ($A$1,$B49,C$5) -> 63.7 | D49: =_xll.EQNXTDZ($A$1,$B49,D$5) -> 63.7 | E49: =_xll.EQNXTDZ($A$1,$B49,E$5) -> 63.7 | F49: =_xll.EQNXTDZ($A$1,$B49,F$5) -> 63.7 | G49: =_xll.EQNXTDZ($A$1,$B49,G$5) -> 63.7 | H49: =_xll.EQNXTDZ($A$1,$B49,H$5) -> 63.78 | I49: =_xll.EQNXTDZ($A$1,$B49,I$5) -> 63.78 | J49: =_xll.EQNXTDZ($A$1,$B49,J$5) -> 63.78 | ... BU49: =_xll.EQNXTDZ($A$1,$B49,BU$5) -> 0
A50: Total of Promoter and Promoter Group Pledged | B50: SHP_PSHFTOTALPROMOTER | C50: =_xll.EQNXTDZ($A$1,$B50,C$5) -> 0 | D50: =_xll.EQNXTDZ($A$1,$B50,D$5) -> 0 | E50: =_xll.EQNXTDZ($A$1,$B50,E$5) -> 0 | F50: =_xll.EQNXTDZ($A$1,$B50,F$5) -> 0 | G50: =_xll.EQNXTDZ($A$1,$B50,G$5) -> 0 | H50: =_xll.EQNXTDZ($A$1,$B50,H$5) -> 0 | I50: =_xll.EQNXTDZ($A$1,$B50,I$5) -> 0 | J50: =_xll.EQNXTDZ($A$1,$B50,J$5) -> 0 | ... BU50: =_xll.EQNXTDZ($A$1,$B50,BU$5) -> 0
A54: Field Description | B54: Field Name | C54: =_xll.EQNXTDZ($A$1,$B54,C$5) -> 0 | D54: =_xll.EQNXTDZ($A$1,$B54,D$5) -> 0 | E54: =_xll.EQNXTDZ($A$1,$B54,E$5) -> 0 | F54: =_xll.EQNXTDZ($A$1,$B54,F$5) -> 0 | G54: =_xll.EQNXTDZ($A$1,$B54,G$5) -> 0 | H54: =_xll.EQNXTDZ($A$1,$B54,H$5) -> 0 | I54: =_xll.EQNXTDZ($A$1,$B54,I$5) -> 0 | J54: =_xll.EQNXTDZ($A$1,$B54,J$5) -> 0 | ... BU54: =_xll.EQNXTDZ($A$1,$B54,BU$5) -> 0
A55: Year End | B55: QTRB_DATE_END | C55: =_xll.EQNXTDZ($A$1,$B55,C$5,$B$1) -> 201206 | D55: =_xll.EQNXTDZ($A$1,$B55,D$5,$B$1) -> 0 | E55: =_xll.EQNXTDZ($A$1,$B55,E$5,$B$1) -> 201212 | F55: =_xll.EQNXTDZ($A$1,$B55,F$5,$B$1) -> 0 | G55: =_xll.EQNXTDZ($A$1,$B55,G$5,$B$1) -> 201306 | H55: =_xll.EQNXTDZ($A$1,$B55,H$5,$B$1) -> 0 | I55: =_xll.EQNXTDZ($A$1,$B55,I$5,$B$1) -> 201312 | J55: =_xll.EQNXTDZ($A$1,$B55,J$5,$B$1) -> 0 | ... BU55: =_xll.EQNXTDZ($A$1,$B55,BU$5,$B$1) -> 0
A56: Share Capital | B56: QTRB_SHARE_CAPITAL | C56: =_xll.EQNXTDZ($A$1,$B56,C$5,$B$1) -> 12.54 | D56: =_xll.EQNXTDZ($A$1,$B56,D$5,$B$1) -> 0 | E56: =_xll.EQNXTDZ($A$1,$B56,E$5,$B$1) -> 12.54 | F56: =_xll.EQNXTDZ($A$1,$B56,F$5,$B$1) -> 0 | G56: =_xll.EQNXTDZ($A$1,$B56,G$5,$B$1) -> 12.54 | H56: =_xll.EQNXTDZ($A$1,$B56,H$5,$B$1) -> 0 | I56: =_xll.EQNXTDZ($A$1,$B56,I$5,$B$1) -> 12.54 | J56: =_xll.EQNXTDZ($A$1,$B56,J$5,$B$1) -> 0 | ... BU56: =_xll.EQNXTDZ($A$1,$B56,BU$5,$B$1) -> 0
A57: Share Warrants & outstandings | B57: QTRB_SHAREWARNDOUT | C57: =_xll.EQNXTDZ($A$1,$B57,C$5,$B$1) -> 0 | D57: =_xll.EQNXTDZ($A$1,$B57,D$5,$B$1) -> 0 | E57: =_xll.EQNXTDZ($A$1,$B57,E$5,$B$1) -> 0 | F57: =_xll.EQNXTDZ($A$1,$B57,F$5,$B$1) -> 0 | G57: =_xll.EQNXTDZ($A$1,$B57,G$5,$B$1) -> 0 | H57: =_xll.EQNXTDZ($A$1,$B57,H$5,$B$1) -> 0 | I57: =_xll.EQNXTDZ($A$1,$B57,I$5,$B$1) -> 0 | J57: =_xll.EQNXTDZ($A$1,$B57,J$5,$B$1) -> 0 | ... BU57: =_xll.EQNXTDZ($A$1,$B57,BU$5,$B$1) -> 0
A58: Reserves & Surplus | B58: QTRB_RESERVE | C58: =_xll.EQNXTDZ($A$1,$B58,C$5,$B$1) -> 342.57 | D58: =_xll.EQNXTDZ($A$1,$B58,D$5,$B$1) -> 0 | E58: =_xll.EQNXTDZ($A$1,$B58,E$5,$B$1) -> 342.42 | F58: =_xll.EQNXTDZ($A$1,$B58,F$5,$B$1) -> 0 | G58: =_xll.EQNXTDZ($A$1,$B58,G$5,$B$1) -> 372.7 | H58: =_xll.EQNXTDZ($A$1,$B58,H$5,$B$1) -> 0 | I58: =_xll.EQNXTDZ($A$1,$B58,I$5,$B$1) -> 378.26 | J58: =_xll.EQNXTDZ($A$1,$B58,J$5,$B$1) -> 0 | ... BU58: =_xll.EQNXTDZ($A$1,$B58,BU$5,$B$1) -> 0
A59: Shareholder's Funds | B59: QTRB_SHAREHODERS_FUNDS | C59: =_xll.EQNXTDZ($A$1,$B59,C$5,$B$1) -> 355.11 | D59: =_xll.EQNXTDZ($A$1,$B59,D$5,$B$1) -> 0 | E59: =_xll.EQNXTDZ($A$1,$B59,E$5,$B$1) -> 354.96 | F59: =_xll.EQNXTDZ($A$1,$B59,F$5,$B$1) -> 0 | G59: =_xll.EQNXTDZ($A$1,$B59,G$5,$B$1) -> 385.24 | H59: =_xll.EQNXTDZ($A$1,$B59,H$5,$B$1) -> 0 | I59: =_xll.EQNXTDZ($A$1,$B59,I$5,$B$1) -> 390.8 | J59: =_xll.EQNXTDZ($A$1,$B59,J$5,$B$1) -> 0 | ... BU59: =_xll.EQNXTDZ($A$1,$B59,BU$5,$B$1) -> 0
A60: Minority Interest | B60: QTRB_MINORITY_INTEREST_BS | C60: =_xll.EQNXTDZ($A$1,$B60,C$5,$B$1) -> 0 | D60: =_xll.EQNXTDZ($A$1,$B60,D$5,$B$1) -> 0 | E60: =_xll.EQNXTDZ($A$1,$B60,E$5,$B$1) -> 18.52 | F60: =_xll.EQNXTDZ($A$1,$B60,F$5,$B$1) -> 0 | G60: =_xll.EQNXTDZ($A$1,$B60,G$5,$B$1) -> 19.35 | H60: =_xll.EQNXTDZ($A$1,$B60,H$5,$B$1) -> 0 | I60: =_xll.EQNXTDZ($A$1,$B60,I$5,$B$1) -> 20.13 | J60: =_xll.EQNXTDZ($A$1,$B60,J$5,$B$1) -> 0 | ... BU60: =_xll.EQNXTDZ($A$1,$B60,BU$5,$B$1) -> 0
A61: Long Term Borrowings | B61: QTRB_TOTAL_DEBTS | C61: =_xll.EQNXTDZ($A$1,$B61,C$5,$B$1) -> 20.61 | D61: =_xll.EQNXTDZ($A$1,$B61,D$5,$B$1) -> 0 | E61: =_xll.EQNXTDZ($A$1,$B61,E$5,$B$1) -> 34.26 | F61: =_xll.EQNXTDZ($A$1,$B61,F$5,$B$1) -> 0 | G61: =_xll.EQNXTDZ($A$1,$B61,G$5,$B$1) -> 36.09 | H61: =_xll.EQNXTDZ($A$1,$B61,H$5,$B$1) -> 0 | I61: =_xll.EQNXTDZ($A$1,$B61,I$5,$B$1) -> 39.91 | J61: =_xll.EQNXTDZ($A$1,$B61,J$5,$B$1) -> 0 | ... BU61: =_xll.EQNXTDZ($A$1,$B61,BU$5,$B$1) -> 0
A62: Secured Loans | B62: QTRB_SECURED_LOANS | C62: =_xll.EQNXTDZ($A$1,$B62,C$5,$B$1) -> 0 | D62: =_xll.EQNXTDZ($A$1,$B62,D$5,$B$1) -> 0 | E62: =_xll.EQNXTDZ($A$1,$B62,E$5,$B$1) -> 0 | F62: =_xll.EQNXTDZ($A$1,$B62,F$5,$B$1) -> 0 | G62: =_xll.EQNXTDZ($A$1,$B62,G$5,$B$1) -> 0 | H62: =_xll.EQNXTDZ($A$1,$B62,H$5,$B$1) -> 0 | I62: =_xll.EQNXTDZ($A$1,$B62,I$5,$B$1) -> 0 | J62: =_xll.EQNXTDZ($A$1,$B62,J$5,$B$1) -> 0 | ... BU62: =_xll.EQNXTDZ($A$1,$B62,BU$5,$B$1) -> 0
A63: Unsecured Loans | B63: QTRB_UNSECURED_LOANS_NF | C63: =_xll.EQNXTDZ($A$1,$B63,C$5,$B$1) -> 20.61 | D63: =_xll.EQNXTDZ($A$1,$B63,D$5,$B$1) -> 0 | E63: =_xll.EQNXTDZ($A$1,$B63,E$5,$B$1) -> 34.26 | F63: =_xll.EQNXTDZ($A$1,$B63,F$5,$B$1) -> 0 | G63: =_xll.EQNXTDZ($A$1,$B63,G$5,$B$1) -> 36.09 | H63: =_xll.EQNXTDZ($A$1,$B63,H$5,$B$1) -> 0 | I63: =_xll.EQNXTDZ($A$1,$B63,I$5,$B$1) -> 39.91 | J63: =_xll.EQNXTDZ($A$1,$B63,J$5,$B$1) -> 0 | ... BU63: =_xll.EQNXTDZ($A$1,$B63,BU$5,$B$1) -> 0
A64: Other Long Term Liabilities | B64: QTRB_OTHER_LT_LIABILITIES | C64: =_xll.EQNXTDZ($A$1,$B64,C$5,$B$1) -> 0 | D64: =_xll.EQNXTDZ($A$1,$B64,D$5,$B$1) -> 0 | E64: =_xll.EQNXTDZ($A$1,$B64,E$5,$B$1) -> 0 | F64: =_xll.EQNXTDZ($A$1,$B64,F$5,$B$1) -> 0 | G64: =_xll.EQNXTDZ($A$1,$B64,G$5,$B$1) -> 0 | H64: =_xll.EQNXTDZ($A$1,$B64,H$5,$B$1) -> 0 | I64: =_xll.EQNXTDZ($A$1,$B64,I$5,$B$1) -> 0 | J64: =_xll.EQNXTDZ($A$1,$B64,J$5,$B$1) -> 0 | ... BU64: =_xll.EQNXTDZ($A$1,$B64,BU$5,$B$1) -> 0
A65: Long Term Trade Payables | B65: QTRB_LT_TRADE_PAYABLE | C65: =_xll.EQNXTDZ($A$1,$B65,C$5,$B$1) -> 0 | D65: =_xll.EQNXTDZ($A$1,$B65,D$5,$B$1) -> 0 | E65: =_xll.EQNXTDZ($A$1,$B65,E$5,$B$1) -> 0 | F65: =_xll.EQNXTDZ($A$1,$B65,F$5,$B$1) -> 0 | G65: =_xll.EQNXTDZ($A$1,$B65,G$5,$B$1) -> 0 | H65: =_xll.EQNXTDZ($A$1,$B65,H$5,$B$1) -> 0 | I65: =_xll.EQNXTDZ($A$1,$B65,I$5,$B$1) -> 0 | J65: =_xll.EQNXTDZ($A$1,$B65,J$5,$B$1) -> 0 | ... BU65: =_xll.EQNXTDZ($A$1,$B65,BU$5,$B$1) -> 0
A66: Lont Term Provisions | B66: QTRB_LT_PROVISIONS | C66: =_xll.EQNXTDZ($A$1,$B66,C$5,$B$1) -> 3.53 | D66: =_xll.EQNXTDZ($A$1,$B66,D$5,$B$1) -> 0 | E66: =_xll.EQNXTDZ($A$1,$B66,E$5,$B$1) -> 1.52 | F66: =_xll.EQNXTDZ($A$1,$B66,F$5,$B$1) -> 0 | G66: =_xll.EQNXTDZ($A$1,$B66,G$5,$B$1) -> 1.41 | H66: =_xll.EQNXTDZ($A$1,$B66,H$5,$B$1) -> 0 | I66: =_xll.EQNXTDZ($A$1,$B66,I$5,$B$1) -> 1.27 | J66: =_xll.EQNXTDZ($A$1,$B66,J$5,$B$1) -> 0 | ... BU66: =_xll.EQNXTDZ($A$1,$B66,BU$5,$B$1) -> 0
... A97: Total Assets | B97: QTRB_TOTAL_APPLICATIONS | C97: =_xll.EQNXTDZ($A$1,$B97,C$5,$B$1) -> 379.25 | D97: =_xll.EQNXTDZ($A$1,$B97,D$5,$B$1) -> 0 | E97: =_xll.EQNXTDZ($A$1,$B97,E$5,$B$1) -> 409.26 | F97: =_xll.EQNXTDZ($A$1,$B97,F$5,$B$1) -> 0 | G97: =_xll.EQNXTDZ($A$1,$B97,G$5,$B$1) -> 442.09 | H97: =_xll.EQNXTDZ($A$1,$B97,H$5,$B$1) -> 0 | I97: =_xll.EQNXTDZ($A$1,$B97,I$5,$B$1) -> 452.11 | J97: =_xll.EQNXTDZ($A$1,$B97,J$5,$B$1) -> 0 | ... BU97: =_xll.EQNXTDZ($A$1,$B97,BU$5,$B$1) -> 0

Sheet Annual Raw
A1: 109820 | B1: X | C1: 200003 | D1: 200103 | E1: 200212 | F1: 200312 | G1: 200412 | H1: 200512 | I1: 200612 | J1: 200712 | K1: 200812 | L1: 200912 | M1: 201012 | N1: 201112 | O1: 201212 | P1: 201312 | Q1: 201412 | R1: 201512 | S1: 201612 | T1: 201712 | U1: 201812 | V1: 201912 | W1: 202012 | X1: 202112 | Y1: 202212 | Z1: 202312 | AA1: 202412 | AB1: 202512 | AC1: 202612 | AD1: 202712 | AE1: 202812 | AF1: 202912 | AG1: 203012
A3: Field Description | B3: Field Name
A4: Company Name | B4: CD_COMPNAME | C4: =_xll.EQNXTDZ(A1,B4,"L") -> Huhtamaki India Ltd.
A5: Year End | B5: PL_YEAR_END | C5: =_xll.EQNXTDZ($A$1,$B5,C$1,$B$1) -> 0 | D5: =_xll.EQNXTDZ($A$1,$B5,D$1,$B$1) -> 0 | E5: =_xll.EQNXTDZ($A$1,$B5,E$1,$B$1) -> 200212 | F5: =_xll.EQNXTDZ($A$1,$B5,F$1,$B$1) -> 200312 | G5: =_xll.EQNXTDZ($A$1,$B5,G$1,$B$1) -> 200412 | H5: =_xll.EQNXTDZ($A$1,$B5,H$1,$B$1) -> 200512 | I5: =_xll.EQNXTDZ($A$1,$B5,I$1,$B$1) -> 200612 | J5: =_xll.EQNXTDZ($A$1,$B5,J$1,$B$1) -> 200712 | ... AG5: =_xll.EQNXTDZ($A$1,$B5,AG$1,$B$1) -> 0
A6: Sales Turnover | B6: PL_TOTAL_GROSS_SALES | C6: =_xll.EQNXTDZ($A$1,$B6,C$1,$B$1) -> 0 | D6: =_xll.EQNXTDZ($A$1,$B6,D$1,$B$1) -> 0 | E6: =_xll.EQNXTDZ($A$1,$B6,E$1,$B$1) -> 354.2851 | F6: =_xll.EQNXTDZ($A$1,$B6,F$1,$B$1) -> 416.1824 | G6: =_xll.EQNXTDZ($A$1,$B6,G$1,$B$1) -> 424.9527 | H6: =_xll.EQNXTDZ($A$1,$B6,H$1,$B$1) -> 468.3587 | I6: =_xll.EQNXTDZ($A$1,$B6,I$1,$B$1) -> 547.3669 | J6: =_xll.EQNXTDZ($A$1,$B6,J$1,$B$1) -> 607.7681 | ... AG6: =_xll.EQNXTDZ($A$1,$B6,AG$1,$B$1) -> 0
A7: Less: Inter divisional transfers | B7: PL_INTER_DIV_TRF | C7: =_xll.EQNXTDZ($A$1,$B7,C$1,$B$1) -> 0 | D7: =_xll.EQNXTDZ($A$1,$B7,D$1,$B$1) -> 0 | E7: =_xll.EQNXTDZ($A$1,$B7,E$1,$B$1) -> -25.2562 | F7: =_xll.EQNXTDZ($A$1,$B7,F$1,$B$1) -> -32.4669 | G7: =_xll.EQNXTDZ($A$1,$B7,G$1,$B$1) -> -34.2293 | H7: =_xll.EQNXTDZ($A$1,$B7,H$1,$B$1) -> -37.0204 | I7: =_xll.EQNXTDZ($A$1,$B7,I$1,$B$1) -> -38.8644 | J7: =_xll.EQNXTDZ($A$1,$B7,J$1,$B$1) -> -40.482 | ... AG7: =_xll.EQNXTDZ($A$1,$B7,AG$1,$B$1) -> 0
A8: Less: Sales Returns | B8: PL_SALES_RETURN | C8: =_xll.EQNXTDZ($A$1,$B8,C$1,$B$1) -> 0 | D8: =_xll.EQNXTDZ($A$1,$B8,D$1,$B$1) -> 0 | E8: =_xll.EQNXTDZ($A$1,$B8,E$1,$B$1) -> 3.6471 | F8: =_xll.EQNXTDZ($A$1,$B8,F$1,$B$1) -> 5.4856 | G8: =_xll.EQNXTDZ($A$1,$B8,G$1,$B$1) -> 5.2703 | H8: =_xll.EQNXTDZ($A$1,$B8,H$1,$B$1) -> 6.9714 | I8: =_xll.EQNXTDZ($A$1,$B8,I$1,$B$1) -> 6.6637 | J8: =_xll.EQNXTDZ($A$1,$B8,J$1,$B$1) -> 4.9824 | ... AG8: =_xll.EQNXTDZ($A$1,$B8,AG$1,$B$1) -> 0
A9: Less: Excise | B9: PL_EXCISE | C9: =_xll.EQNXTDZ($A$1,$B9,C$1,$B$1) -> 0 | D9: =_xll.EQNXTDZ($A$1,$B9,D$1,$B$1) -> 0 | E9: =_xll.EQNXTDZ($A$1,$B9,E$1,$B$1) -> 53.7069 | F9: =_xll.EQNXTDZ($A$1,$B9,F$1,$B$1) -> 60.5458 | G9: =_xll.EQNXTDZ($A$1,$B9,G$1,$B$1) -> 59.8906 | H9: =_xll.EQNXTDZ($A$1,$B9,H$1,$B$1) -> 65.5473 | I9: =_xll.EQNXTDZ($A$1,$B9,I$1,$B$1) -> 78.3627 | J9: =_xll.EQNXTDZ($A$1,$B9,J$1,$B$1) -> 72.6803 | ... AG9: =_xll.EQNXTDZ($A$1,$B9,AG$1,$B$1) -> 0
A10: Net Sales | B10: PL_NET_SALES | C10: =_xll.EQNXTDZ($A$1,$B10,C$1,$B$1) -> 0 | D10: =_xll.EQNXTDZ($A$1,$B10,D$1,$B$1) -> 0 | E10: =_xll.EQNXTDZ($A$1,$B10,E$1,$B$1) -> 322.1873 | F10: =_xll.EQNXTDZ($A$1,$B10,F$1,$B$1) -> 382.6179 | G10: =_xll.EQNXTDZ($A$1,$B10,G$1,$B$1) -> 394.0211 | H10: =_xll.EQNXTDZ($A$1,$B10,H$1,$B$1) -> 432.8604 | I10: =_xll.EQNXTDZ($A$1,$B10,I$1,$B$1) -> 501.2049 | J10: =_xll.EQNXTDZ($A$1,$B10,J$1,$B$1) -> 570.5874 | ... AG10: =_xll.EQNXTDZ($A$1,$B10,AG$1,$B$1) -> 0
A11: Increase/Decrease in Stock | B11: PL_INC_DEC_INVENTORY | C11: =_xll.EQNXTDZ($A$1,$B11,C$1,$B$1) -> 0 | D11: =_xll.EQNXTDZ($A$1,$B11,D$1,$B$1) -> 0 | E11: =_xll.EQNXTDZ($A$1,$B11,E$1,$B$1) -> 1.5387 | F11: =_xll.EQNXTDZ($A$1,$B11,F$1,$B$1) -> -3.5805 | G11: =_xll.EQNXTDZ($A$1,$B11,G$1,$B$1) -> 0.9135 | H11: =_xll.EQNXTDZ($A$1,$B11,H$1,$B$1) -> -3.0595 | I11: =_xll.EQNXTDZ($A$1,$B11,I$1,$B$1) -> 0.1137 | J11: =_xll.EQNXTDZ($A$1,$B11,J$1,$B$1) -> -7.5251 | ... AG11: =_xll.EQNXTDZ($A$1,$B11,AG$1,$B$1) -> 0
A12: Raw Material Consumed | B12: PL_RAW_MATRS_CONSUMED | C12: =_xll.EQNXTDZ($A$1,$B12,C$1,$B$1) -> 0 | D12: =_xll.EQNXTDZ($A$1,$B12,D$1,$B$1) -> 0 | E12: =_xll.EQNXTDZ($A$1,$B12,E$1,$B$1) -> 203.7736 | F12: =_xll.EQNXTDZ($A$1,$B12,F$1,$B$1) -> 259.7068 | G12: =_xll.EQNXTDZ($A$1,$B12,G$1,$B$1) -> 266.155 | H12: =_xll.EQNXTDZ($A$1,$B12,H$1,$B$1) -> 297.6002 | I12: =_xll.EQNXTDZ($A$1,$B12,I$1,$B$1) -> 345.8754 | J12: =_xll.EQNXTDZ($A$1,$B12,J$1,$B$1) -> 409.0374 | ... AG12: =_xll.EQNXTDZ($A$1,$B12,AG$1,$B$1) -> 0
A13: Power & Fuel Cost | B13: PL_POWER_FUEL | C13: =_xll.EQNXTDZ($A$1,$B13,C$1,$B$1) -> 0 | D13: =_xll.EQNXTDZ($A$1,$B13,D$1,$B$1) -> 0 | E13: =_xll.EQNXTDZ($A$1,$B13,E$1,$B$1) -> 10.014 | F13: =_xll.EQNXTDZ($A$1,$B13,F$1,$B$1) -> 12.0829 | G13: =_xll.EQNXTDZ($A$1,$B13,G$1,$B$1) -> 12.3519 | H13: =_xll.EQNXTDZ($A$1,$B13,H$1,$B$1) -> 15.2928 | I13: =_xll.EQNXTDZ($A$1,$B13,I$1,$B$1) -> 17.8088 | J13: =_xll.EQNXTDZ($A$1,$B13,J$1,$B$1) -> 16.9449 | ... AG13: =_xll.EQNXTDZ($A$1,$B13,AG$1,$B$1) -> 0
A14: Employee Cost | B14: PL_EMPLOYEES | C14: =_xll.EQNXTDZ($A$1,$B14,C$1,$B$1) -> 0 | D14: =_xll.EQNXTDZ($A$1,$B14,D$1,$B$1) -> 0 | E14: =_xll.EQNXTDZ($A$1,$B14,E$1,$B$1) -> 22.0504 | F14: =_xll.EQNXTDZ($A$1,$B14,F$1,$B$1) -> 26.0119 | G14: =_xll.EQNXTDZ($A$1,$B14,G$1,$B$1) -> 28.7538 | H14: =_xll.EQNXTDZ($A$1,$B14,H$1,$B$1) -> 30.7647 | I14: =_xll.EQNXTDZ($A$1,$B14,I$1,$B$1) -> 36.0581 | J14: =_xll.EQNXTDZ($A$1,$B14,J$1,$B$1) -> 41.7776 | ... AG14: =_xll.EQNXTDZ($A$1,$B14,AG$1,$B$1) -> 0
A15: Operating & Manufacturing Expenses | B15: PL_GEN_OTHER_MFG_EXPS | C15: =_xll.EQNXTDZ($A$1,$B15,C$1,$B$1) -> 0 | D15: =_xll.EQNXTDZ($A$1,$B15,D$1,$B$1) -> 0 | E15: =_xll.EQNXTDZ($A$1,$B15,E$1,$B$1) -> 9.2349 | F15: =_xll.EQNXTDZ($A$1,$B15,F$1,$B$1) -> 11.8431 | G15: =_xll.EQNXTDZ($A$1,$B15,G$1,$B$1) -> 13.27 | H15: =_xll.EQNXTDZ($A$1,$B15,H$1,$B$1) -> 14.5692 | I15: =_xll.EQNXTDZ($A$1,$B15,I$1,$B$1) -> 20.0295 | J15: =_xll.EQNXTDZ($A$1,$B15,J$1,$B$1) -> 22.351 | ... AG15: =_xll.EQNXTDZ($A$1,$B15,AG$1,$B$1) -> 0
A16: Cost of Software development | B16: PL_COST_SW | C16: =_xll.EQNXTDZ($A$1,$B16,C$1,$B$1) -> 0 | D16: =_xll.EQNXTDZ($A$1,$B16,D$1,$B$1) -> 0 | E16: =_xll.EQNXTDZ($A$1,$B16,E$1,$B$1) -> 0 | F16: =_xll.EQNXTDZ($A$1,$B16,F$1,$B$1) -> 0 | G16: =_xll.EQNXTDZ($A$1,$B16,G$1,$B$1) -> 0 | H16: =_xll.EQNXTDZ($A$1,$B16,H$1,$B$1) -> 0 | I16: =_xll.EQNXTDZ($A$1,$B16,I$1,$B$1) -> 0 | J16: =_xll.EQNXTDZ($A$1,$B16,J$1,$B$1) -> 0 | ... AG16: =_xll.EQNXTDZ($A$1,$B16,AG$1,$B$1) -> 0
... A36: Profit After Tax from Discontinued Operations | B36: PL_PAT_DIS_OP | C36: =_xll.EQNXTDZ($A$1,$B36,C$1,$B$1) -> 0 | D36: =_xll.EQNXTDZ($A$1,$B36,D$1,$B$1) -> 0 | E36: =_xll.EQNXTDZ($A$1,$B36,E$1,$B$1) -> 0 | F36: =_xll.EQNXTDZ($A$1,$B36,F$1,$B$1) -> 0 | G36: =_xll.EQNXTDZ($A$1,$B36,G$1,$B$1) -> 0 | H36: =_xll.EQNXTDZ($A$1,$B36,H$1,$B$1) -> 0 | I36: =_xll.EQNXTDZ($A$1,$B36,I$1,$B$1) -> 0 | J36: =_xll.EQNXTDZ($A$1,$B36,J$1,$B$1) -> 0 | ... AG36: =_xll.EQNXTDZ($A$1,$B36,AG$1,$B$1) -> 0
A39: Field Description | B39: Field Name
A40: Year End | B40: BS_YEAR_END | C40: =_xll.EQNXTDZ($A$1,$B40,C$1,$B$1) -> 0 | D40: =_xll.EQNXTDZ($A$1,$B40,D$1,$B$1) -> 0 | E40: =_xll.EQNXTDZ($A$1,$B40,E$1,$B$1) -> 200212 | F40: =_xll.EQNXTDZ($A$1,$B40,F$1,$B$1) -> 200312 | G40: =_xll.EQNXTDZ($A$1,$B40,G$1,$B$1) -> 200412 | H40: =_xll.EQNXTDZ($A$1,$B40,H$1,$B$1) -> 200512 | I40: =_xll.EQNXTDZ($A$1,$B40,I$1,$B$1) -> 200612 | J40: =_xll.EQNXTDZ($A$1,$B40,J$1,$B$1) -> 200712 | ... AG40: =_xll.EQNXTDZ($A$1,$B40,AG$1,$B$1) -> 0
A41: Share Capital | B41: BS_SHARE_CAPITAL | C41: =_xll.EQNXTDZ($A$1,$B41,C$1,$B$1) -> 0 | D41: =_xll.EQNXTDZ($A$1,$B41,D$1,$B$1) -> 0 | E41: =_xll.EQNXTDZ($A$1,$B41,E$1,$B$1) -> 12.5383 | F41: =_xll.EQNXTDZ($A$1,$B41,F$1,$B$1) -> 12.5383 | G41: =_xll.EQNXTDZ($A$1,$B41,G$1,$B$1) -> 12.5383 | H41: =_xll.EQNXTDZ($A$1,$B41,H$1,$B$1) -> 12.5383 | I41: =_xll.EQNXTDZ($A$1,$B41,I$1,$B$1) -> 12.5383 | J41: =_xll.EQNXTDZ($A$1,$B41,J$1,$B$1) -> 12.5383 | ... AG41: =_xll.EQNXTDZ($A$1,$B41,AG$1,$B$1) -> 0
A42: Share Warrants & Outstandings | B42: BS_SHAREWROUTST | C42: =_xll.EQNXTDZ($A$1,$B42,C$1,$B$1) -> 0 | D42: =_xll.EQNXTDZ($A$1,$B42,D$1,$B$1) -> 0 | E42: =_xll.EQNXTDZ($A$1,$B42,E$1,$B$1) -> 0 | F42: =_xll.EQNXTDZ($A$1,$B42,F$1,$B$1) -> 0 | G42: =_xll.EQNXTDZ($A$1,$B42,G$1,$B$1) -> 0 | H42: =_xll.EQNXTDZ($A$1,$B42,H$1,$B$1) -> 0 | I42: =_xll.EQNXTDZ($A$1,$B42,I$1,$B$1) -> 0 | J42: =_xll.EQNXTDZ($A$1,$B42,J$1,$B$1) -> 0 | ... AG42: =_xll.EQNXTDZ($A$1,$B42,AG$1,$B$1) -> 0
A43: Total Reserves | B43: BS_RESERVE | C43: =_xll.EQNXTDZ($A$1,$B43,C$1,$B$1) -> 0 | D43: =_xll.EQNXTDZ($A$1,$B43,D$1,$B$1) -> 0 | E43: =_xll.EQNXTDZ($A$1,$B43,E$1,$B$1) -> 149.9757 | F43: =_xll.EQNXTDZ($A$1,$B43,F$1,$B$1) -> 151.424 | G43: =_xll.EQNXTDZ($A$1,$B43,G$1,$B$1) -> 166.9801 | H43: =_xll.EQNXTDZ($A$1,$B43,H$1,$B$1) -> 184.2427 | I43: =_xll.EQNXTDZ($A$1,$B43,I$1,$B$1) -> 211.3118 | J43: =_xll.EQNXTDZ($A$1,$B43,J$1,$B$1) -> 225.7305 | ... AG43: =_xll.EQNXTDZ($A$1,$B43,AG$1,$B$1) -> 0
A44: Shareholder's Funds | B44: BS_SHAREHODERS_FUNDS | C44: =_xll.EQNXTDZ($A$1,$B44,C$1,$B$1) -> 0 | D44: =_xll.EQNXTDZ($A$1,$B44,D$1,$B$1) -> 0 | E44: =_xll.EQNXTDZ($A$1,$B44,E$1,$B$1) -> 162.514 | F44: =_xll.EQNXTDZ($A$1,$B44,F$1,$B$1) -> 163.9623 | G44: =_xll.EQNXTDZ($A$1,$B44,G$1,$B$1) -> 179.5184 | H44: =_xll.EQNXTDZ($A$1,$B44,H$1,$B$1) -> 196.781 | I44: =_xll.EQNXTDZ($A$1,$B44,I$1,$B$1) -> 223.8501 | J44: =_xll.EQNXTDZ($A$1,$B44,J$1,$B$1) -> 238.2688 | ... AG44: =_xll.EQNXTDZ($A$1,$B44,AG$1,$B$1) -> 0
A45: Minority Interest | B45: BS_MINORITY_INTEREST | C45: =_xll.EQNXTDZ($A$1,$B45,C$1,$B$1) -> 0 | D45: =_xll.EQNXTDZ($A$1,$B45,D$1,$B$1) -> 0 | E45: =_xll.EQNXTDZ($A$1,$B45,E$1,$B$1) -> 0 | F45: =_xll.EQNXTDZ($A$1,$B45,F$1,$B$1) -> 0 | G45: =_xll.EQNXTDZ($A$1,$B45,G$1,$B$1) -> 0 | H45: =_xll.EQNXTDZ($A$1,$B45,H$1,$B$1) -> 0 | I45: =_xll.EQNXTDZ($A$1,$B45,I$1,$B$1) -> 0 | J45: =_xll.EQNXTDZ($A$1,$B45,J$1,$B$1) -> 0 | ... AG45: =_xll.EQNXTDZ($A$1,$B45,AG$1,$B$1) -> 0
A46: Long-Term Borrowings | B46: BS_LTRM_BORROWING | C46: =_xll.EQNXTDZ($A$1,$B46,C$1,$B$1) -> 0 | D46: =_xll.EQNXTDZ($A$1,$B46,D$1,$B$1) -> 0 | E46: =_xll.EQNXTDZ($A$1,$B46,E$1,$B$1) -> 0 | F46: =_xll.EQNXTDZ($A$1,$B46,F$1,$B$1) -> 0 | G46: =_xll.EQNXTDZ($A$1,$B46,G$1,$B$1) -> 0 | H46: =_xll.EQNXTDZ($A$1,$B46,H$1,$B$1) -> 0 | I46: =_xll.EQNXTDZ($A$1,$B46,I$1,$B$1) -> 0 | J46: =_xll.EQNXTDZ($A$1,$B46,J$1,$B$1) -> 0 | ... AG46: =_xll.EQNXTDZ($A$1,$B46,AG$1,$B$1) -> 0
A47: Secured Loans | B47: BS_SECURED_LOANS | C47: =_xll.EQNXTDZ($A$1,$B47,C$1,$B$1) -> 0 | D47: =_xll.EQNXTDZ($A$1,$B47,D$1,$B$1) -> 0 | E47: =_xll.EQNXTDZ($A$1,$B47,E$1,$B$1) -> 1.6451 | F47: =_xll.EQNXTDZ($A$1,$B47,F$1,$B$1) -> 0 | G47: =_xll.EQNXTDZ($A$1,$B47,G$1,$B$1) -> 0 | H47: =_xll.EQNXTDZ($A$1,$B47,H$1,$B$1) -> 0 | I47: =_xll.EQNXTDZ($A$1,$B47,I$1,$B$1) -> 0 | J47: =_xll.EQNXTDZ($A$1,$B47,J$1,$B$1) -> 4.2894 | ... AG47: =_xll.EQNXTDZ($A$1,$B47,AG$1,$B$1) -> 0
A48: Unsecured Loans | B48: BS_UNSECURED_LOANS_NF | C48: =_xll.EQNXTDZ($A$1,$B48,C$1,$B$1) -> 0 | D48: =_xll.EQNXTDZ($A$1,$B48,D$1,$B$1) -> 0 | E48: =_xll.EQNXTDZ($A$1,$B48,E$1,$B$1) -> 7.5303 | F48: =_xll.EQNXTDZ($A$1,$B48,F$1,$B$1) -> 10.2644 | G48: =_xll.EQNXTDZ($A$1,$B48,G$1,$B$1) -> 13.0207 | H48: =_xll.EQNXTDZ($A$1,$B48,H$1,$B$1) -> 16.2947 | I48: =_xll.EQNXTDZ($A$1,$B48,I$1,$B$1) -> 33.7736 | J48: =_xll.EQNXTDZ($A$1,$B48,J$1,$B$1) -> 62.8643 | ... AG48: =_xll.EQNXTDZ($A$1,$B48,AG$1,$B$1) -> 0
A49: Deferred Tax Assets / Liabilities | B49: BS_NET_DEF_TAX_NF | C49: =_xll.EQNXTDZ($A$1,$B49,C$1,$B$1) -> 0 | D49: =_xll.EQNXTDZ($A$1,$B49,D$1,$B$1) -> 0 | E49: =_xll.EQNXTDZ($A$1,$B49,E$1,$B$1) -> 7.4984 | F49: =_xll.EQNXTDZ($A$1,$B49,F$1,$B$1) -> 9.6239 | G49: =_xll.EQNXTDZ($A$1,$B49,G$1,$B$1) -> 8.9906 | H49: =_xll.EQNXTDZ($A$1,$B49,H$1,$B$1) -> 6.02 | I49: =_xll.EQNXTDZ($A$1,$B49,I$1,$B$1) -> 8.3916 | J49: =_xll.EQNXTDZ($A$1,$B49,J$1,$B$1) -> 8.5149 | ... AG49: =_xll.EQNXTDZ($A$1,$B49,AG$1,$B$1) -> 0
A50: Other Long Term Liabilities | B50: BS_OTH_LT_LIAB | C50: =_xll.EQNXTDZ($A$1,$B50,C$1,$B$1) -> 0 | D50: =_xll.EQNXTDZ($A$1,$B50,D$1,$B$1) -> 0 | E50: =_xll.EQNXTDZ($A$1,$B50,E$1,$B$1) -> 0 | F50: =_xll.EQNXTDZ($A$1,$B50,F$1,$B$1) -> 0 | G50: =_xll.EQNXTDZ($A$1,$B50,G$1,$B$1) -> 0 | H50: =_xll.EQNXTDZ($A$1,$B50,H$1,$B$1) -> 0 | I50: =_xll.EQNXTDZ($A$1,$B50,I$1,$B$1) -> 0 | J50: =_xll.EQNXTDZ($A$1,$B50,J$1,$B$1) -> 0 | ... AG50: =_xll.EQNXTDZ($A$1,$B50,AG$1,$B$1) -> 0
A51: Long Term Trade Payables | B51: BS_LT_TRADE_PAYABLES | C51: =_xll.EQNXTDZ($A$1,$B51,C$1,$B$1) -> 0 | D51: =_xll.EQNXTDZ($A$1,$B51,D$1,$B$1) -> 0 | E51: =_xll.EQNXTDZ($A$1,$B51,E$1,$B$1) -> 0 | F51: =_xll.EQNXTDZ($A$1,$B51,F$1,$B$1) -> 0 | G51: =_xll.EQNXTDZ($A$1,$B51,G$1,$B$1) -> 0 | H51: =_xll.EQNXTDZ($A$1,$B51,H$1,$B$1) -> 0 | I51: =_xll.EQNXTDZ($A$1,$B51,I$1,$B$1) -> 0 | J51: =_xll.EQNXTDZ($A$1,$B51,J$1,$B$1) -> 0 | ... AG51: =_xll.EQNXTDZ($A$1,$B51,AG$1,$B$1) -> 0
... A99: Estimated Capital Contracts Remaining | B99: BS_ESTIMATED_CAPITAL_CONTRACT | C99: =_xll.EQNXTDZ($A$1,$B99,C$1,$B$1) -> 0 | D99: =_xll.EQNXTDZ($A$1,$B99,D$1,$B$1) -> 0 | E99: =_xll.EQNXTDZ($A$1,$B99,E$1,$B$1) -> 0.0691 | F99: =_xll.EQNXTDZ($A$1,$B99,F$1,$B$1) -> 21.6604 | G99: =_xll.EQNXTDZ($A$1,$B99,G$1,$B$1) -> 0.3277 | H99: =_xll.EQNXTDZ($A$1,$B99,H$1,$B$1) -> 30.1971 | I99: =_xll.EQNXTDZ($A$1,$B99,I$1,$B$1) -> 54.1048 | J99: =_xll.EQNXTDZ($A$1,$B99,J$1,$B$1) -> 21.576 | ... AG99: =_xll.EQNXTDZ($A$1,$B99,AG$1,$B$1) -> 0
A103: Field Description | B103: Field Name
A104: Equity Paid Up | B104: BS_EQUITY_PAIDUP | C104: =_xll.EQNXTDZ($A$1,$B104,C$1,$B$1) -> 0 | D104: =_xll.EQNXTDZ($A$1,$B104,D$1,$B$1) -> 0 | E104: =_xll.EQNXTDZ($A$1,$B104,E$1,$B$1) -> 12.5374 | F104: =_xll.EQNXTDZ($A$1,$B104,F$1,$B$1) -> 12.5374 | G104: =_xll.EQNXTDZ($A$1,$B104,G$1,$B$1) -> 12.5374 | H104: =_xll.EQNXTDZ($A$1,$B104,H$1,$B$1) -> 12.5374 | I104: =_xll.EQNXTDZ($A$1,$B104,I$1,$B$1) -> 12.5374 | J104: =_xll.EQNXTDZ($A$1,$B104,J$1,$B$1) -> 12.5374 | ... AG104: =_xll.EQNXTDZ($A$1,$B104,AG$1,$B$1) -> 0
A105: Face Value | B105: BS_FACE_VALUE | C105: =_xll.EQNXTDZ($A$1,$B105,C$1,$B$1) -> 0 | D105: =_xll.EQNXTDZ($A$1,$B105,D$1,$B$1) -> 0 | E105: =_xll.EQNXTDZ($A$1,$B105,E$1,$B$1) -> 10 | F105: =_xll.EQNXTDZ($A$1,$B105,F$1,$B$1) -> 10 | G105: =_xll.EQNXTDZ($A$1,$B105,G$1,$B$1) -> 10 | H105: =_xll.EQNXTDZ($A$1,$B105,H$1,$B$1) -> 10 | I105: =_xll.EQNXTDZ($A$1,$B105,I$1,$B$1) -> 10 | J105: =_xll.EQNXTDZ($A$1,$B105,J$1,$B$1) -> 2 | ... AG105: =_xll.EQNXTDZ($A$1,$B105,AG$1,$B$1) -> 0
A106: Close Price (Unit Curr.) | B106: FH_YEAR_PRICE | C106: =_xll.EQNXTDZ($A$1,$B106,C$1,$B$1) -> 0 | D106: =_xll.EQNXTDZ($A$1,$B106,D$1,$B$1) -> 0 | E106: =_xll.EQNXTDZ($A$1,$B106,E$1,$B$1) -> 27 | F106: =_xll.EQNXTDZ($A$1,$B106,F$1,$B$1) -> 39.45 | G106: =_xll.EQNXTDZ($A$1,$B106,G$1,$B$1) -> 43.39 | H106: =_xll.EQNXTDZ($A$1,$B106,H$1,$B$1) -> 60.51 | I106: =_xll.EQNXTDZ($A$1,$B106,I$1,$B$1) -> 73.7 | J106: =_xll.EQNXTDZ($A$1,$B106,J$1,$B$1) -> 73.2 | ... AG106: =_xll.EQNXTDZ($A$1,$B106,AG$1,$B$1) -> 0
A107: High Price (Unit Curr.) | B107: FH_HIGH | C107: =_xll.EQNXTDZ($A$1,$B107,C$1,$B$1) -> 0 | D107: =_xll.EQNXTDZ($A$1,$B107,D$1,$B$1) -> 0 | E107: =_xll.EQNXTDZ($A$1,$B107,E$1,$B$1) -> 27.4 | F107: =_xll.EQNXTDZ($A$1,$B107,F$1,$B$1) -> 42.35 | G107: =_xll.EQNXTDZ($A$1,$B107,G$1,$B$1) -> 48.4 | H107: =_xll.EQNXTDZ($A$1,$B107,H$1,$B$1) -> 65.6 | I107: =_xll.EQNXTDZ($A$1,$B107,I$1,$B$1) -> 99.76 | J107: =_xll.EQNXTDZ($A$1,$B107,J$1,$B$1) -> 83.74 | ... AG107: =_xll.EQNXTDZ($A$1,$B107,AG$1,$B$1) -> 0
A108: Low Price (Unit Curr.) | B108: FH_LOW | C108: =_xll.EQNXTDZ($A$1,$B108,C$1,$B$1) -> 0 | D108: =_xll.EQNXTDZ($A$1,$B108,D$1,$B$1) -> 0 | E108: =_xll.EQNXTDZ($A$1,$B108,E$1,$B$1) -> 10.46 | F108: =_xll.EQNXTDZ($A$1,$B108,F$1,$B$1) -> 21 | G108: =_xll.EQNXTDZ($A$1,$B108,G$1,$B$1) -> 31.45 | H108: =_xll.EQNXTDZ($A$1,$B108,H$1,$B$1) -> 40.5 | I108: =_xll.EQNXTDZ($A$1,$B108,I$1,$B$1) -> 48 | J108: =_xll.EQNXTDZ($A$1,$B108,J$1,$B$1) -> 45.25 | ... AG108: =_xll.EQNXTDZ($A$1,$B108,AG$1,$B$1) -> 0
A109: Market Capitalization | B109: FH_MCAP | C109: =_xll.EQNXTDZ($A$1,$B109,C$1,$B$1) -> 0 | D109: =_xll.EQNXTDZ($A$1,$B109,D$1,$B$1) -> 0 | E109: =_xll.EQNXTDZ($A$1,$B109,E$1,$B$1) -> 169.2549 | F109: =_xll.EQNXTDZ($A$1,$B109,F$1,$B$1) -> 247.30022 | G109: =_xll.EQNXTDZ($A$1,$B109,G$1,$B$1) -> 271.99889 | H109: =_xll.EQNXTDZ($A$1,$B109,H$1,$B$1) -> 379.31904 | I109: =_xll.EQNXTDZ($A$1,$B109,I$1,$B$1) -> 462.00319 | J109: =_xll.EQNXTDZ($A$1,$B109,J$1,$B$1) -> 458.86884 | ... AG109: =_xll.EQNXTDZ($A$1,$B109,AG$1,$B$1) -> 0
A110: Adj DPS(Rs) | B110: FR_ADJ_DPS | C110: =_xll.EQNXTDZ($A$1,$B110,C$1,$B$1) -> 0 | D110: =_xll.EQNXTDZ($A$1,$B110,D$1,$B$1) -> 0 | E110: =_xll.EQNXTDZ($A$1,$B110,E$1,$B$1) -> 1 | F110: =_xll.EQNXTDZ($A$1,$B110,F$1,$B$1) -> 3 | G110: =_xll.EQNXTDZ($A$1,$B110,G$1,$B$1) -> 1.2 | H110: =_xll.EQNXTDZ($A$1,$B110,H$1,$B$1) -> 1.4 | I110: =_xll.EQNXTDZ($A$1,$B110,I$1,$B$1) -> 1.8 | J110: =_xll.EQNXTDZ($A$1,$B110,J$1,$B$1) -> 1.8 | ... AG110: =_xll.EQNXTDZ($A$1,$B110,AG$1,$B$1) -> 0
A111: Date End | B111: SHP_DATE_END | C111: =_xll.EQNXTDZ($A$1,$B111,C$5) -> 0 | D111: =_xll.EQNXTDZ($A$1,$B111,D$5) -> 0 | E111: =_xll.EQNXTDZ($A$1,$B111,E$5) -> 200212 | F111: =_xll.EQNXTDZ($A$1,$B111,F$5) -> 200312 | G111: =_xll.EQNXTDZ($A$1,$B111,G$5) -> 200412 | H111: =_xll.EQNXTDZ($A$1,$B111,H$5) -> 200512 | I111: =_xll.EQNXTDZ($A$1,$B111,I$5) -> 200612 | J111: =_xll.EQNXTDZ($A$1,$B111,J$5) -> 200712 | ... AG111: =_xll.EQNXTDZ($A$1,$B111,AG$5) -> 0
A112: Total of Promoter and Promoter Group | B112: SHP_TPFTOTALPROMOTER | C112: =_xll.EQNXTDZ($A$1,$B112,C$5) -> 0 | D112: =_xll.EQNXTDZ($A$1,$B112,D$5) -> 0 | E112: =_xll.EQNXTDZ($A$1,$B112,E$5) -> 65.7 | F112: =_xll.EQNXTDZ($A$1,$B112,F$5) -> 65.16 | G112: =_xll.EQNXTDZ($A$1,$B112,G$5) -> 63.73 | H112: =_xll.EQNXTDZ($A$1,$B112,H$5) -> 63.73 | I112: =_xll.EQNXTDZ($A$1,$B112,I$5) -> 63.73 | J112: =_xll.EQNXTDZ($A$1,$B112,J$5) -> 63.73 | ... AG112: =_xll.EQNXTDZ($A$1,$B112,AG$5) -> 0
A113: Total of Promoter and Promoter Group Pledged | B113: SHP_PSHFTOTALPROMOTER | C113: =_xll.EQNXTDZ($A$1,$B113,C$5) -> 0 | D113: =_xll.EQNXTDZ($A$1,$B113,D$5) -> 0 | E113: =_xll.EQNXTDZ($A$1,$B113,E$5) -> 0 | F113: =_xll.EQNXTDZ($A$1,$B113,F$5) -> 0 | G113: =_xll.EQNXTDZ($A$1,$B113,G$5) -> 0 | H113: =_xll.EQNXTDZ($A$1,$B113,H$5) -> 0 | I113: =_xll.EQNXTDZ($A$1,$B113,I$5) -> 0 | J113: =_xll.EQNXTDZ($A$1,$B113,J$5) -> 0 | ... AG113: =_xll.EQNXTDZ($A$1,$B113,AG$5) -> 0

Sheet QTR Share Price
A1: ='QTR Raw'!A1 -> 109820 | C1: 201206 | D1: 201207 | E1: 201208 | F1: 201209 | G1: 201210 | H1: 201211 | I1: 201212 | J1: 201301 | K1: 201302 | L1: 201303 | M1: 201304 | N1: 201305 | O1: 201306 | P1: 201307 | Q1: 201308 | R1: 201309 | S1: 201310 | T1: 201311 | U1: 201312 | V1: 201401 | W1: 201402 | X1: 201403 | Y1: 201404 | Z1: 201405 | AA1: 201406 | AB1: 201407 | AC1: 201408 | AD1: 201409 | AE1: 201410 | AF1: 201411 | AG1: 201412 | AH1: 201501 | AI1: 201502 | AJ1: 201503 | AK1: 201504 | AL1: 201505 | AM1: 201506 | AN1: 201507 | AO1: 201508 | AP1: 201509 | AQ1: 201510 | AR1: 201511 | AS1: 201512 | AT1: 201601 | AU1: 201602 | AV1: 201603 | AW1: 201604 | AX1: 201605 | AY1: 201606 | AZ1: 201607 | BA1: 201608 | BB1: 201609 | BC1: 201610 | BD1: 201611 | BE1: 201612 | BF1: 201701 | BG1: 201702 | BH1: 201703 | BI1: 201704 | BJ1: 201705 | BK1: 201706 | BL1: 201707 | BM1: 201708 | BN1: 201709 | BO1: 201710 | BP1: 201711 | BQ1: 201712 | BR1: 201801 | BS1: 201802 | BT1: 201803 | BU1: 201804 | BV1: 201805 | BW1: 201806 | BX1: 201807 | BY1: 201808 | BZ1: 201809 | CA1: 201810 | CB1: 201811 | CC1: 201812 | CD1: 201901 | CE1: 201902 | CF1: 201903 | CG1: 201904 | CH1: 201905 | CI1: 201906 | CJ1: 201907 | CK1: 201908 | CL1: 201909 | CM1: 201910 | CN1: 201911 | CO1: 201912 | CP1: 202001 | CQ1: 202002 | CR1: 202003 | CS1: 202004 | CT1: 202005 | CU1: 202006 | CV1: 202007 | CW1: 202008 | CX1: 202009 | CY1: 202010 | CZ1: 202011 | DA1: 202012 | DB1: 202101 | DC1: 202102 | DD1: 202103 | DE1: 202104 | DF1: 202105 | DG1: 202106 | DH1: 202107 | DI1: 202108 | DJ1: 202109 | DK1: 202110 | DL1: 202111 | DM1: 202112 | DN1: 202201 | DO1: 202202 | DP1: 202203 | DQ1: 202204 | DR1: 202205 | DS1: 202206 | DT1: 202207 | DU1: 202208 | DV1: 202209 | DW1: 202210 | DX1: 202211 | DY1: 202212 | DZ1: 202301 | EA1: 202302 | EB1: 202303 | EC1: 202304 | ED1: 202305 | EE1: 202306 | EF1: 202307 | EG1: 202308 | EH1: 202309 | EI1: 202310 | EJ1: 202311 | EK1: 202312 | EL1: 202401 | EM1: 202402 | EN1: 202403 | EO1: 202404 | EP1: 202405 | EQ1: 202406 | ER1: 202407 | ES1: 202408 | ET1: 202409 | EU1: 202410 | EV1: 202411 | EW1: 202412 | EX1: 202501 | EY1: 202502 | EZ1: 202503 | FA1: 202504 | FB1: 202505 | FC1: 202506 | FD1: 202507 | FE1: 202508 | FF1: 202509 | FG1: 202510 | FH1: 202511 | FI1: 202512 | FJ1: 202601 | FK1: 202602 | FL1: 202603 | FM1: 202604 | FN1: 202605 | FO1: 202606 | FP1: 202607 | FQ1: 202608 | FR1: 202609 | FS1: 202610 | FT1: 202611 | FU1: 202612 | FV1: 202701 | FW1: 202702 | FX1: 202703 | FY1: 202704 | FZ1: 202705 | GA1: 202706 | GB1: 202707 | GC1: 202708 | GD1: 202709 | GE1: 202710 | GF1: 202711 | GG1: 202712 | GH1: 202801 | GI1: 202802 | GJ1: 202803 | GK1: 202804 | GL1: 202805 | GM1: 202806 | GN1: 202807 | GO1: 202808 | GP1: 202809 | GQ1: 202810 | GR1: 202811 | GS1: 202812 | GT1: 202901 | GU1: 202902 | GV1: 202903 | GW1: 202904 | GX1: 202905 | GY1: 202906 | GZ1: 202907 | HA1: 202908 | HB1: 202909 | HC1: 202910 | HD1: 202911 | HE1: 202912 | HF1: 203001 | HG1: 203002 | HH1: 203003 | HM1: 201206 | HN1: 201207 | HO1: 201208 | HP1: 201209 | HQ1: 201212 | HR1: 201303 | HS1: 201306 | HT1: 201309 | HU1: 201312 | HV1: 201403 | HW1: 201406 | HX1: 201409 | HY1: 201412 | HZ1: 201503 | IA1: 201506 | IB1: 201509 | IC1: 201512 | ID1: 201603 | IE1: 201606 | IF1: 201609 | IG1: 201612 | IH1: 201703 | II1: 201706 | IJ1: 201709 | IK1: 201712 | IL1: 201803 | IM1: 201806 | IN1: 201809 | IO1: 201812 | IP1: 201903 | IQ1: 201906 | IR1: 201909 | IS1: 201912 | IT1: 202003 | IU1: 202006 | IV1: 202009 | IW1: 202012 | IX1: 202103 | IY1: 202106 | IZ1: 202109 | JA1: 202112 | JB1: 202203 | JC1: 202206 | JD1: 202209 | JE1: 202212 | JF1: 202303 | JG1: 202306 | JH1: 202309 | JI1: 202312 | JJ1: 202403 | JK1: 202406 | JL1: 202409 | JM1: 202412 | JN1: 202503 | JO1: 202506 | JP1: 202509 | JQ1: 202512 | JR1: 202603 | JS1: 202606 | JT1: 202609 | JU1: 202612 | JV1: 202703 | JW1: 202706 | JX1: 202709 | JY1: 202712 | JZ1: 202803 | KA1: 202806 | KB1: 202809 | KC1: 202812 | KD1: 202903 | KE1: 202906 | KF1: 202909 | KG1: 202912 | KH1: 203003
A4: Field Description | B4: Field Name
A5: MonthEnd | B5: NMONTH_MONTHEND | C5: {=_xll.EQNXTDZ($A$1,$B5,C$1)} -> 201206 | D5: {=_xll.EQNXTDZ($A$1,$B5,D$1)} -> 201207 | E5: {=_xll.EQNXTDZ($A$1,$B5,E$1)} -> 201208 | F5: {=_xll.EQNXTDZ($A$1,$B5,F$1)} -> 201209 | G5: {=_xll.EQNXTDZ($A$1,$B5,G$1)} -> 201210 | H5: {=_xll.EQNXTDZ($A$1,$B5,H$1)} -> 201211 | I5: {=_xll.EQNXTDZ($A$1,$B5,I$1)} -> 201212 | J5: {=_xll.EQNXTDZ($A$1,$B5,J$1)} -> 201301 | ... HH5: {=_xll.EQNXTDZ($A$1,$B5,HH$1)} -> 0
A6: Open | B6: NMONTH_OPEN | C6: {=_xll.EQNXTDZ($A$1,$B6,C$1)} -> 59 | D6: {=_xll.EQNXTDZ($A$1,$B6,D$1)} -> 71 | E6: {=_xll.EQNXTDZ($A$1,$B6,E$1)} -> 64.5 | F6: {=_xll.EQNXTDZ($A$1,$B6,F$1)} -> 70.15 | G6: {=_xll.EQNXTDZ($A$1,$B6,G$1)} -> 71.35 | H6: {=_xll.EQNXTDZ($A$1,$B6,H$1)} -> 69 | I6: {=_xll.EQNXTDZ($A$1,$B6,I$1)} -> 67.7 | J6: {=_xll.EQNXTDZ($A$1,$B6,J$1)} -> 72.9 | ... HH6: {=_xll.EQNXTDZ($A$1,$B6,HH$1)} -> 0
A7: High | B7: NMONTH_HIGH | C7: {=_xll.EQNXTDZ($A$1,$B7,C$1)} -> 71.5 | D7: {=_xll.EQNXTDZ($A$1,$B7,D$1)} -> 75 | E7: {=_xll.EQNXTDZ($A$1,$B7,E$1)} -> 71.9 | F7: {=_xll.EQNXTDZ($A$1,$B7,F$1)} -> 75.4 | G7: {=_xll.EQNXTDZ($A$1,$B7,G$1)} -> 76.5 | H7: {=_xll.EQNXTDZ($A$1,$B7,H$1)} -> 72.4 | I7: {=_xll.EQNXTDZ($A$1,$B7,I$1)} -> 76.5 | J7: {=_xll.EQNXTDZ($A$1,$B7,J$1)} -> 82 | ... HH7: {=_xll.EQNXTDZ($A$1,$B7,HH$1)} -> 0 | HP7: =+MAX(D7:F7) -> 75.4 | HQ7: =+MAX(G7:I7) -> 76.5 | HR7: =+MAX(J7:L7) -> 82 | HS7: =+MAX(M7:O7) -> 74 | HT7: =+MAX(P7:R7) -> 68.35 | HU7: =+MAX(S7:U7) -> 77.5 | HV7: =+MAX(V7:X7) -> 101.95 | HW7: =+MAX(Y7:AA7) -> 145 | HX7: =+MAX(AB7:AD7) -> 211.7 | HY7: =+MAX(AE7:AG7) -> 198.95 | HZ7: =+MAX(AH7:AJ7) -> 239 | IA7: =+MAX(AK7:AM7) -> 259.9 | IB7: =+MAX(AN7:AP7) -> 331.95 | IC7: =+MAX(AQ7:AS7) -> 292.8 | ID7: =+MAX(AT7:AV7) -> 253.2 | IE7: =+MAX(AW7:AY7) -> 310 | IF7: =+MAX(AZ7:BB7) -> 326.45 | IG7: =+MAX(BC7:BE7) -> 294 | IH7: =+MAX(BF7:BH7) -> 258 | II7: =+MAX(BI7:BK7) -> 276.15 | IJ7: =+MAX(BL7:BN7) -> 274 | IK7: =+MAX(BO7:BQ7) -> 368.7 | IL7: =+MAX(BR7:BT7) -> 373.8 | IM7: =+MAX(BU7:BW7) -> 365.9 | IN7: =+MAX(BX7:BZ7) -> 298 | IO7: =+MAX(CA7:CC7) -> 242 | IP7: =+MAX(CD7:CF7) -> 217.7 | IQ7: =+MAX(CG7:CI7) -> 284.8 | IR7: =+MAX(CJ7:CL7) -> 271.95 | IS7: =+MAX(CM7:CO7) -> 275.8 | IT7: =+MAX(CP7:CR7) -> 305 | IU7: =+MAX(CS7:CU7) -> 235 | IV7: =+MAX(CV7:CX7) -> 337.6 | IW7: =+MAX(CY7:DA7) -> 320 | IX7: =+MAX(DB7:DD7) -> 352.15 | IY7: =+MAX(DE7:DG7) -> 309.7 | IZ7: =+MAX(DH7:DJ7) -> 328 | JA7: =+MAX(DK7:DM7) -> 272.8 | JB7: =+MAX(DN7:DP7) -> 232.75 | JC7: =+MAX(DQ7:DS7) -> 208.35 | JD7: =+MAX(DT7:DV7) -> 223.6 | JE7: =+MAX(DW7:DY7) -> 236.9 | JF7: =+MAX(DZ7:EB7) -> 214.7 | JG7: =+MAX(EC7:EE7) -> 298 | JH7: =+MAX(EF7:EH7) -> 297.95 | JI7: =+MAX(EI7:EK7) -> 323.65 | JJ7: =+MAX(EL7:EN7) -> 371 | JK7: =MAX(EO7:EQ7) -> 399 | JL7: =MAX(ER7:ET7) -> 451.85 | JM7: =MAX(EU7:EW7) -> 404.95 | JN7: =MAX(EX7:EZ7) -> 282.7 | JO7: =MAX(FA7:FC7) -> 222.94 | JP7: =MAX(FD7:FF7) -> 253.7 | JQ7: =MAX(FG7:FI7) -> 272.65 | JR7: =MAX(FJ7:FL7) -> 213.95 | JS7: =MAX(FM7:FO7) -> 193.8 | JT7: =MAX(FP7:FR7) -> 0 | JU7: =MAX(FS7:FU7) -> 0 | JV7: =MAX(FV7:FX7) -> 0 | JW7: =MAX(FY7:GA7) -> 0 | JX7: =MAX(GB7:GD7) -> 0 | JY7: =MAX(GE7:GG7) -> 0 | JZ7: =MAX(GH7:GJ7) -> 0 | KA7: =MAX(GK7:GM7) -> 0 | KB7: =MAX(GN7:GP7) -> 0 | KC7: =MAX(GQ7:GS7) -> 0 | KD7: =MAX(GT7:GV7) -> 0 | KE7: =MAX(GW7:GY7) -> 0 | KF7: =MAX(GZ7:HB7) -> 0 | KG7: =MAX(HC7:HE7) -> 0 | KH7: =MAX(HF7:HH7) -> 0
A8: Low | B8: NMONTH_LOW | C8: {=_xll.EQNXTDZ($A$1,$B8,C$1)} -> 58.05 | D8: {=_xll.EQNXTDZ($A$1,$B8,D$1)} -> 63.85 | E8: {=_xll.EQNXTDZ($A$1,$B8,E$1)} -> 64.05 | F8: {=_xll.EQNXTDZ($A$1,$B8,F$1)} -> 67.75 | G8: {=_xll.EQNXTDZ($A$1,$B8,G$1)} -> 68.05 | H8: {=_xll.EQNXTDZ($A$1,$B8,H$1)} -> 65.1 | I8: {=_xll.EQNXTDZ($A$1,$B8,I$1)} -> 67.2 | J8: {=_xll.EQNXTDZ($A$1,$B8,J$1)} -> 68.05 | ... HH8: {=_xll.EQNXTDZ($A$1,$B8,HH$1)} -> 0 | HP8: =+MIN(D8:F8) -> 63.85 | HQ8: =+MIN(G8:I8) -> 65.1 | HR8: =+MIN(J8:L8) -> 60.75 | HS8: =+MIN(M8:O8) -> 59.65 | HT8: =+MIN(P8:R8) -> 56.25 | HU8: =+MIN(S8:U8) -> 60 | HV8: =+MIN(V8:X8) -> 68.1 | HW8: =+MIN(Y8:AA8) -> 89.4 | HX8: =+MIN(AB8:AD8) -> 131.6 | HY8: =+MIN(AE8:AG8) -> 167.05 | HZ8: =+MIN(AH8:AJ8) -> 175 | IA8: =+MIN(AK8:AM8) -> 210.3 | IB8: =+MIN(AN8:AP8) -> 235.15 | IC8: =+MIN(AQ8:AS8) -> 226.3 | ID8: =+MIN(AT8:AV8) -> 176 | IE8: =+MIN(AW8:AY8) -> 208.65 | IF8: =+MIN(AZ8:BB8) -> 253 | IG8: =+MIN(BC8:BE8) -> 226.35 | IH8: =+MIN(BF8:BH8) -> 227.55 | II8: =+MIN(BI8:BK8) -> 232 | IJ8: =+MIN(BL8:BN8) -> 200.95 | IK8: =+MIN(BO8:BQ8) -> 215.25 | IL8: =+MIN(BR8:BT8) -> 285.85 | IM8: =+MIN(BU8:BW8) -> 266.1 | IN8: =+MIN(BX8:BZ8) -> 234.05 | IO8: =+MIN(CA8:CC8) -> 185 | IP8: =+MIN(CD8:CF8) -> 155 | IQ8: =+MIN(CG8:CI8) -> 196.7 | IR8: =+MIN(CJ8:CL8) -> 200.6 | IS8: =+MIN(CM8:CO8) -> 221 | IT8: =+MIN(CP8:CR8) -> 161.9 | IU8: =+MIN(CS8:CU8) -> 174 | IV8: =+MIN(CV8:CX8) -> 199 | IW8: =+MIN(CY8:DA8) -> 268 | IX8: =+MIN(DB8:DD8) -> 270 | IY8: =+MIN(DE8:DG8) -> 260.2 | IZ8: =+MIN(DH8:DJ8) -> 260.55 | JA8: =+MIN(DK8:DM8) -> 206 | JB8: =+MIN(DN8:DP8) -> 148.4 | JC8: =+MIN(DQ8:DS8) -> 150.8 | JD8: =+MIN(DT8:DV8) -> 162.9 | JE8: =+MIN(DW8:DY8) -> 181.6 | JF8: =+MIN(DZ8:EB8) -> 187.5 | JG8: =+MIN(EC8:EE8) -> 189 | JH8: =+MIN(EF8:EH8) -> 244.1 | JI8: =+MIN(EI8:EK8) -> 251.05 | JJ8: =+MIN(EL8:EN8) -> 288.55 | JK8: =MIN(EO8:EQ8) -> 261.65 | JL8: =MIN(ER8:ET8) -> 358.15 | JM8: =MIN(EU8:EW8) -> 259.2 | JN8: =MIN(EX8:EZ8) -> 170.56 | JO8: =MIN(FA8:FC8) -> 175 | JP8: =MIN(FD8:FF8) -> 203.42 | JQ8: =MIN(FG8:FI8) -> 202.1 | JR8: =MIN(FJ8:FL8) -> 148.6 | JS8: =MIN(FM8:FO8) -> 153.05 | JT8: =MIN(FP8:FR8) -> 0 | JU8: =MIN(FS8:FU8) -> 0 | JV8: =MIN(FV8:FX8) -> 0 | JW8: =MIN(FY8:GA8) -> 0 | JX8: =MIN(GB8:GD8) -> 0 | JY8: =MIN(GE8:GG8) -> 0 | JZ8: =MIN(GH8:GJ8) -> 0 | KA8: =MIN(GK8:GM8) -> 0 | KB8: =MIN(GN8:GP8) -> 0 | KC8: =MIN(GQ8:GS8) -> 0 | KD8: =MIN(GT8:GV8) -> 0 | KE8: =MIN(GW8:GY8) -> 0 | KF8: =MIN(GZ8:HB8) -> 0 | KG8: =MIN(HC8:HE8) -> 0 | KH8: =MIN(HF8:HH8) -> 0
A9: Close | B9: NMONTH_CLOSE | C9: {=_xll.EQNXTDZ($A$1,$B9,C$1)} -> 71.05 | D9: {=_xll.EQNXTDZ($A$1,$B9,D$1)} -> 64.15 | E9: {=_xll.EQNXTDZ($A$1,$B9,E$1)} -> 68.9 | F9: {=_xll.EQNXTDZ($A$1,$B9,F$1)} -> 71.75 | G9: {=_xll.EQNXTDZ($A$1,$B9,G$1)} -> 68.2 | H9: {=_xll.EQNXTDZ($A$1,$B9,H$1)} -> 67.95 | I9: {=_xll.EQNXTDZ($A$1,$B9,I$1)} -> 72.25 | J9: {=_xll.EQNXTDZ($A$1,$B9,J$1)} -> 69.2 | ... HH9: {=_xll.EQNXTDZ($A$1,$B9,HH$1)} -> 0 | HP9: =+F9 -> 71.75 | HQ9: =+I9 -> 72.25 | HR9: =+L9 -> 62.3 | HS9: =+O9 -> 62.95 | HT9: =+R9 -> 60.4 | HU9: =+U9 -> 74.7 | HV9: =+X9 -> 89.4 | HW9: =+AA9 -> 134.6 | HX9: =+AD9 -> 192 | HY9: =+AG9 -> 181.05 | HZ9: =+AJ9 -> 232.1 | IA9: =+AM9 -> 236.45 | IB9: =+AP9 -> 273.7 | IC9: =+AS9 -> 239.75 | ID9: =+AV9 -> 209.55 | IE9: =+AY9 -> 298.4 | IF9: =+BB9 -> 257.15 | IG9: =+BE9 -> 242.3 | IH9: =+BH9 -> 239.2 | II9: =+BK9 -> 257.15 | IJ9: =+BN9 -> 220.65 | IK9: =+BQ9 -> 355 | IL9: =+BT9 -> 321.3 | IM9: =+BW9 -> 277.45 | IN9: =+BZ9 -> 236.95 | IO9: =+CC9 -> 194.85 | IP9: =+CF9 -> 195.25 | IQ9: =+CI9 -> 258.35 | IR9: =+CL9 -> 244.15 | IS9: =+CO9 -> 246.95 | IT9: =+CR9 -> 195.6 | IU9: =+CU9 -> 203.45 | IV9: =+CX9 -> 310.5 | IW9: =+DA9 -> 313.55 | IX9: =+DD9 -> 279.9 | IY9: =+DG9 -> 293.7 | IZ9: =+DJ9 -> 265.65 | JA9: =+DM9 -> 227.65 | JB9: =+DP9 -> 150.9 | JC9: =+DS9 -> 165.05 | JD9: =+DV9 -> 218.8 | JE9: =+DY9 -> 199.35 | JF9: =+EB9 -> 189.5 | JG9: =+EE9 -> 273.1 | JH9: =+EH9 -> 257.25 | JI9: =+EK9 -> 286.9 | JJ9: =+EN9 -> 299.15 | JK9: =EQ9 -> 360.45 | JL9: =ET9 -> 385.45 | JM9: =EW9 -> 273.6 | JN9: =EZ9 -> 180.66 | JO9: =FC9 -> 211.16 | JP9: =FF9 -> 234.17 | JQ9: =FI9 -> 211.7 | JR9: =FL9 -> 149.9 | JS9: =FO9 -> 173.95 | JT9: =FR9 -> 0 | JU9: =FU9 -> 0 | JV9: =FX9 -> 0 | JW9: =GA9 -> 0 | JX9: =GD9 -> 0 | JY9: =GG9 -> 0 | JZ9: =GJ9 -> 0 | KA9: =GM9 -> 0 | KB9: =GP9 -> 0 | KC9: =GS9 -> 0 | KD9: =GV9 -> 0 | KE9: =GY9 -> 0 | KF9: =HB9 -> 0 | KG9: =HE9 -> 0 | KH9: =HH9 -> 0
A11: Field Description | B11: Field Name | C11: {=_xll.EQNXTDZ($A$1,$B11,C$1)} -> 0 | D11: {=_xll.EQNXTDZ($A$1,$B11,D$1)} -> 0 | E11: {=_xll.EQNXTDZ($A$1,$B11,E$1)} -> 0 | F11: {=_xll.EQNXTDZ($A$1,$B11,F$1)} -> 0 | G11: {=_xll.EQNXTDZ($A$1,$B11,G$1)} -> 0 | H11: {=_xll.EQNXTDZ($A$1,$B11,H$1)} -> 0 | I11: {=_xll.EQNXTDZ($A$1,$B11,I$1)} -> 0 | J11: {=_xll.EQNXTDZ($A$1,$B11,J$1)} -> 0 | ... HH11: {=_xll.EQNXTDZ($A$1,$B11,HH$1)} -> 0
A12: Month End | B12: BMONTH_MONTHEND | C12: {=_xll.EQNXTDZ($A$1,$B12,C$1)} -> 201206 | D12: {=_xll.EQNXTDZ($A$1,$B12,D$1)} -> 201207 | E12: {=_xll.EQNXTDZ($A$1,$B12,E$1)} -> 201208 | F12: {=_xll.EQNXTDZ($A$1,$B12,F$1)} -> 201209 | G12: {=_xll.EQNXTDZ($A$1,$B12,G$1)} -> 201210 | H12: {=_xll.EQNXTDZ($A$1,$B12,H$1)} -> 201211 | I12: {=_xll.EQNXTDZ($A$1,$B12,I$1)} -> 201212 | J12: {=_xll.EQNXTDZ($A$1,$B12,J$1)} -> 201301 | ... HH12: {=_xll.EQNXTDZ($A$1,$B12,HH$1)} -> 0
A13: Open | B13: BMONTH_OPEN | C13: {=_xll.EQNXTDZ($A$1,$B13,C$1)} -> 59.85 | D13: {=_xll.EQNXTDZ($A$1,$B13,D$1)} -> 71.4 | E13: {=_xll.EQNXTDZ($A$1,$B13,E$1)} -> 64.75 | F13: {=_xll.EQNXTDZ($A$1,$B13,F$1)} -> 69.75 | G13: {=_xll.EQNXTDZ($A$1,$B13,G$1)} -> 72.1 | H13: {=_xll.EQNXTDZ($A$1,$B13,H$1)} -> 68.9 | I13: {=_xll.EQNXTDZ($A$1,$B13,I$1)} -> 68.45 | J13: {=_xll.EQNXTDZ($A$1,$B13,J$1)} -> 72.5 | ... HH13: {=_xll.EQNXTDZ($A$1,$B13,HH$1)} -> 0
A14: High | B14: BMONTH_HIGH | C14: {=_xll.EQNXTDZ($A$1,$B14,C$1)} -> 74.7 | D14: {=_xll.EQNXTDZ($A$1,$B14,D$1)} -> 74 | E14: {=_xll.EQNXTDZ($A$1,$B14,E$1)} -> 71.8 | F14: {=_xll.EQNXTDZ($A$1,$B14,F$1)} -> 75.45 | G14: {=_xll.EQNXTDZ($A$1,$B14,G$1)} -> 77 | H14: {=_xll.EQNXTDZ($A$1,$B14,H$1)} -> 70 | I14: {=_xll.EQNXTDZ($A$1,$B14,I$1)} -> 76.5 | J14: {=_xll.EQNXTDZ($A$1,$B14,J$1)} -> 81.8 | ... HH14: {=_xll.EQNXTDZ($A$1,$B14,HH$1)} -> 0 | HP14: =+MAX(D14:F14) -> 75.45 | HQ14: =+MAX(G14:I14) -> 77 | HR14: =+MAX(J14:L14) -> 81.8 | HS14: =+MAX(M14:O14) -> 74.3 | HT14: =+MAX(P14:R14) -> 72 | HU14: =+MAX(S14:U14) -> 77.1 | HV14: =+MAX(V14:X14) -> 100.8 | HW14: =+MAX(Y14:AA14) -> 145 | HX14: =+MAX(AB14:AD14) -> 212 | HY14: =+MAX(AE14:AG14) -> 198.95 | HZ14: =+MAX(AH14:AJ14) -> 238.2 | IA14: =+MAX(AK14:AM14) -> 259.6 | IB14: =+MAX(AN14:AP14) -> 334 | IC14: =+MAX(AQ14:AS14) -> 294 | ID14: =+MAX(AT14:AV14) -> 249 | IE14: =+MAX(AW14:AY14) -> 315.1 | IF14: =+MAX(AZ14:BB14) -> 327 | IG14: =+MAX(BC14:BE14) -> 296 | IH14: =+MAX(BF14:BH14) -> 258 | II14: =+MAX(BI14:BK14) -> 277.4 | IJ14: =+MAX(BL14:BN14) -> 273.3 | IK14: =+MAX(BO14:BQ14) -> 387 | IL14: =+MAX(BR14:BT14) -> 373.05 | IM14: =+MAX(BU14:BW14) -> 363.85 | IN14: =+MAX(BX14:BZ14) -> 298.1 | IO14: =+MAX(CA14:CC14) -> 237.45 | IP14: =+MAX(CD14:CF14) -> 214 | IQ14: =+MAX(CG14:CI14) -> 289.8 | IR14: =+MAX(CJ14:CL14) -> 271 | IS14: =+MAX(CM14:CO14) -> 275 | IT14: =+MAX(CP14:CR14) -> 303 | IU14: =+MAX(CS14:CU14) -> 235 | IV14: =+MAX(CV14:CX14) -> 336 | IW14: =+MAX(CY14:DA14) -> 320 | IX14: =+MAX(DB14:DD14) -> 352.45 | IY14: =+MAX(DE14:DG14) -> 309.75 | IZ14: =+MAX(DH14:DJ14) -> 328 | JA14: =+MAX(DK14:DM14) -> 272.8 | JB14: =+MAX(DN14:DP14) -> 230 | JC14: =+MAX(DQ14:DS14) -> 207.95 | JD14: =+MAX(DT14:DV14) -> 223.6 | JE14: =+MAX(DW14:DY14) -> 236.95 | JF14: =+MAX(DZ14:EB14) -> 213.45 | JG14: =+MAX(EC14:EE14) -> 300 | JH14: =+MAX(EF14:EH14) -> 297.8 | JI14: =+MAX(EI14:EK14) -> 323.4 | JJ14: =+MAX(EL14:EN14) -> 371.3 | JK14: =MAX(EO14:EQ14) -> 398.9 | JL14: =MAX(ER14:ET14) -> 451.5 | JM14: =MAX(EU14:EW14) -> 410 | JN14: =MAX(EX14:EZ14) -> 284.9 | JO14: =MAX(FA14:FC14) -> 222.95 | JP14: =MAX(FD14:FF14) -> 253.25 | JQ14: =MAX(FG14:FI14) -> 272.45 | JR14: =MAX(FJ14:FL14) -> 213.35 | JS14: =MAX(FM14:FO14) -> 193.7 | JT14: =MAX(FP14:FR14) -> 0 | JU14: =MAX(FS14:FU14) -> 0 | JV14: =MAX(FV14:FX14) -> 0 | JW14: =MAX(FY14:GA14) -> 0 | JX14: =MAX(GB14:GD14) -> 0 | JY14: =MAX(GE14:GG14) -> 0 | JZ14: =MAX(GH14:GJ14) -> 0 | KA14: =MAX(GK14:GM14) -> 0 | KB14: =MAX(GN14:GP14) -> 0 | KC14: =MAX(GQ14:GS14) -> 0 | KD14: =MAX(GT14:GV14) -> 0 | KE14: =MAX(GW14:GY14) -> 0 | KF14: =MAX(GZ14:HB14) -> 0 | KG14: =MAX(HC14:HE14) -> 0 | KH14: =MAX(HF14:HH14) -> 0
A15: Low | B15: BMONTH_LOW | C15: {=_xll.EQNXTDZ($A$1,$B15,C$1)} -> 58 | D15: {=_xll.EQNXTDZ($A$1,$B15,D$1)} -> 63.75 | E15: {=_xll.EQNXTDZ($A$1,$B15,E$1)} -> 64.15 | F15: {=_xll.EQNXTDZ($A$1,$B15,F$1)} -> 68.05 | G15: {=_xll.EQNXTDZ($A$1,$B15,G$1)} -> 67.8 | H15: {=_xll.EQNXTDZ($A$1,$B15,H$1)} -> 65.25 | I15: {=_xll.EQNXTDZ($A$1,$B15,I$1)} -> 68.45 | J15: {=_xll.EQNXTDZ($A$1,$B15,J$1)} -> 68.35 | ... HH15: {=_xll.EQNXTDZ($A$1,$B15,HH$1)} -> 0 | HP15: =+MIN(D15:F15) -> 63.75 | HQ15: =+MIN(G15:I15) -> 65.25 | HR15: =+MIN(J15:L15) -> 61 | HS15: =+MIN(M15:O15) -> 56.5 | HT15: =+MIN(P15:R15) -> 56.85 | HU15: =+MIN(S15:U15) -> 60.1 | HV15: =+MIN(V15:X15) -> 68.5 | HW15: =+MIN(Y15:AA15) -> 88.15 | HX15: =+MIN(AB15:AD15) -> 130.35 | HY15: =+MIN(AE15:AG15) -> 167.1 | HZ15: =+MIN(AH15:AJ15) -> 175.1 | IA15: =+MIN(AK15:AM15) -> 213.1 | IB15: =+MIN(AN15:AP15) -> 222.1 | IC15: =+MIN(AQ15:AS15) -> 227 | ID15: =+MIN(AT15:AV15) -> 176.9 | IE15: =+MIN(AW15:AY15) -> 210.6 | IF15: =+MIN(AZ15:BB15) -> 255.1 | IG15: =+MIN(BC15:BE15) -> 228.35 | IH15: =+MIN(BF15:BH15) -> 227 | II15: =+MIN(BI15:BK15) -> 232 | IJ15: =+MIN(BL15:BN15) -> 201 | IK15: =+MIN(BO15:BQ15) -> 215.2 | IL15: =+MIN(BR15:BT15) -> 276 | IM15: =+MIN(BU15:BW15) -> 265 | IN15: =+MIN(BX15:BZ15) -> 233.5 | IO15: =+MIN(CA15:CC15) -> 186 | IP15: =+MIN(CD15:CF15) -> 155 | IQ15: =+MIN(CG15:CI15) -> 196.1 | IR15: =+MIN(CJ15:CL15) -> 201.05 | IS15: =+MIN(CM15:CO15) -> 222.45 | IT15: =+MIN(CP15:CR15) -> 165 | IU15: =+MIN(CS15:CU15) -> 174.6 | IV15: =+MIN(CV15:CX15) -> 200 | IW15: =+MIN(CY15:DA15) -> 268.15 | IX15: =+MIN(DB15:DD15) -> 262.05 | IY15: =+MIN(DE15:DG15) -> 260 | IZ15: =+MIN(DH15:DJ15) -> 260.5 | JA15: =+MIN(DK15:DM15) -> 205.1 | JB15: =+MIN(DN15:DP15) -> 148 | JC15: =+MIN(DQ15:DS15) -> 151.95 | JD15: =+MIN(DT15:DV15) -> 163 | JE15: =+MIN(DW15:DY15) -> 182.1 | JF15: =+MIN(DZ15:EB15) -> 186 | JG15: =+MIN(EC15:EE15) -> 189.75 | JH15: =+MIN(EF15:EH15) -> 243.9 | JI15: =+MIN(EI15:EK15) -> 251 | JJ15: =+MIN(EL15:EN15) -> 288.65 | JK15: =MIN(EO15:EQ15) -> 262.2 | JL15: =MIN(ER15:ET15) -> 358.05 | JM15: =MIN(EU15:EW15) -> 259.8 | JN15: =MIN(EX15:EZ15) -> 170.4 | JO15: =MIN(FA15:FC15) -> 177.1 | JP15: =MIN(FD15:FF15) -> 203.1 | JQ15: =MIN(FG15:FI15) -> 202.55 | JR15: =MIN(FJ15:FL15) -> 148.95 | JS15: =MIN(FM15:FO15) -> 150.5 | JT15: =MIN(FP15:FR15) -> 0 | JU15: =MIN(FS15:FU15) -> 0 | JV15: =MIN(FV15:FX15) -> 0 | JW15: =MIN(FY15:GA15) -> 0 | JX15: =MIN(GB15:GD15) -> 0 | JY15: =MIN(GE15:GG15) -> 0 | JZ15: =MIN(GH15:GJ15) -> 0 | KA15: =MIN(GK15:GM15) -> 0 | KB15: =MIN(GN15:GP15) -> 0 | KC15: =MIN(GQ15:GS15) -> 0 | KD15: =MIN(GT15:GV15) -> 0 | KE15: =MIN(GW15:GY15) -> 0 | KF15: =MIN(GZ15:HB15) -> 0 | KG15: =MIN(HC15:HE15) -> 0 | KH15: =MIN(HF15:HH15) -> 0
A16: Close | B16: BMONTH_CLOSE | C16: {=_xll.EQNXTDZ($A$1,$B16,C$1)} -> 71.4 | D16: {=_xll.EQNXTDZ($A$1,$B16,D$1)} -> 64.2 | E16: {=_xll.EQNXTDZ($A$1,$B16,E$1)} -> 69 | F16: {=_xll.EQNXTDZ($A$1,$B16,F$1)} -> 71.65 | G16: {=_xll.EQNXTDZ($A$1,$B16,G$1)} -> 68.25 | H16: {=_xll.EQNXTDZ($A$1,$B16,H$1)} -> 67.6 | I16: {=_xll.EQNXTDZ($A$1,$B16,I$1)} -> 72.35 | J16: {=_xll.EQNXTDZ($A$1,$B16,J$1)} -> 69.6 | ... HH16: {=_xll.EQNXTDZ($A$1,$B16,HH$1)} -> 0 | HP16: =+F16 -> 71.65 | HQ16: =+I16 -> 72.35 | HR16: =+L16 -> 62.15 | HS16: =+O16 -> 62.85 | HT16: =+R16 -> 60.1 | HU16: =+U16 -> 74.6 | HV16: =+X16 -> 89.5 | HW16: =+AA16 -> 134.3 | HX16: =+AD16 -> 192.05 | HY16: =+AG16 -> 180.7 | HZ16: =+AJ16 -> 231.1 | IA16: =+AM16 -> 236.7 | IB16: =+AP16 -> 272.4 | IC16: =+AS16 -> 239.7 | ID16: =+AV16 -> 209.6 | IE16: =+AY16 -> 297.7 | IF16: =+BB16 -> 257.5 | IG16: =+BE16 -> 242 | IH16: =+BH16 -> 237.4 | II16: =+BK16 -> 259.75 | IJ16: =+BN16 -> 218.35 | IK16: =+BQ16 -> 353.65 | IL16: =+BT16 -> 320.1 | IM16: =+BW16 -> 275.05 | IN16: =+BZ16 -> 237 | IO16: =+CC16 -> 194 | IP16: =+CF16 -> 196.75 | IQ16: =+CI16 -> 258.75 | IR16: =+CL16 -> 244.1 | IS16: =+CO16 -> 246.3 | IT16: =+CR16 -> 195.75 | IU16: =+CU16 -> 203.9 | IV16: =+CX16 -> 310.5 | IW16: =+DA16 -> 312.6 | IX16: =+DD16 -> 280.3 | IY16: =+DG16 -> 293.1 | IZ16: =+DJ16 -> 265.5 | JA16: =+DM16 -> 227.8 | JB16: =+DP16 -> 151 | JC16: =+DS16 -> 165 | JD16: =+DV16 -> 217.75 | JE16: =+DY16 -> 198.85 | JF16: =+EB16 -> 189.8 | JG16: =+EE16 -> 273 | JH16: =+EH16 -> 256.55 | JI16: =+EK16 -> 286.6 | JJ16: =+EN16 -> 299.5 | JK16: =EQ16 -> 360.65 | JL16: =ET16 -> 385 | JM16: =EW16 -> 272.4 | JN16: =EZ16 -> 180.95 | JO16: =FC16 -> 211.6 | JP16: =FF16 -> 233.9 | JQ16: =FI16 -> 211.65 | JR16: =FL16 -> 150.15 | JS16: =FO16 -> 173.9 | JT16: =FR16 -> 0 | JU16: =FU16 -> 0 | JV16: =FX16 -> 0 | JW16: =GA16 -> 0 | JX16: =GD16 -> 0 | JY16: =GG16 -> 0 | JZ16: =GJ16 -> 0 | KA16: =GM16 -> 0 | KB16: =GP16 -> 0 | KC16: =GS16 -> 0 | KD16: =GV16 -> 0 | KE16: =GY16 -> 0 | KF16: =HB16 -> 0 | KG16: =HE16 -> 0 | KH16: =HH16 -> 0
A19: High | HP19: =+IF(HP14=0,HP7,HP14) -> 75.45 | HQ19: =+IF(HQ14=0,HQ7,HQ14) -> 77 | HR19: =+IF(HR14=0,HR7,HR14) -> 81.8 | HS19: =+IF(HS14=0,HS7,HS14) -> 74.3 | HT19: =+IF(HT14=0,HT7,HT14) -> 72 | HU19: =+IF(HU14=0,HU7,HU14) -> 77.1 | HV19: =+IF(HV14=0,HV7,HV14) -> 100.8 | HW19: =+IF(HW14=0,HW7,HW14) -> 145 | ... KH19: =+IF(KH14=0,KH7,KH14) -> 0
A20: Low | HP20: =+IF(HP15=0,HP8,HP15) -> 63.75 | HQ20: =+IF(HQ15=0,HQ8,HQ15) -> 65.25 | HR20: =+IF(HR15=0,HR8,HR15) -> 61 | HS20: =+IF(HS15=0,HS8,HS15) -> 56.5 | HT20: =+IF(HT15=0,HT8,HT15) -> 56.85 | HU20: =+IF(HU15=0,HU8,HU15) -> 60.1 | HV20: =+IF(HV15=0,HV8,HV15) -> 68.5 | HW20: =+IF(HW15=0,HW8,HW15) -> 88.15 | ... KH20: =+IF(KH15=0,KH8,KH15) -> 0
A21: Close | HP21: =+IF(HP16=0,HP9,HP16) -> 71.65 | HQ21: =+IF(HQ16=0,HQ9,HQ16) -> 72.35 | HR21: =+IF(HR16=0,HR9,HR16) -> 62.15 | HS21: =+IF(HS16=0,HS9,HS16) -> 62.85 | HT21: =+IF(HT16=0,HT9,HT16) -> 60.1 | HU21: =+IF(HU16=0,HU9,HU16) -> 74.6 | HV21: =+IF(HV16=0,HV9,HV16) -> 89.5 | HW21: =+IF(HW16=0,HW9,HW16) -> 134.3 | ... KH21: =+IF(KH16=0,KH9,KH16) -> 0

Sheet QTR No. of Shares
A1: ='QTR Raw'!A1 -> 109820 | C1: 201206 | D1: 201209 | E1: 201212 | F1: 201303 | G1: 201306 | H1: 201309 | I1: 201312 | J1: 201403 | K1: 201406 | L1: 201409 | M1: 201412 | N1: 201503 | O1: 201506 | P1: 201509 | Q1: 201512 | R1: 201603 | S1: 201606 | T1: 201609 | U1: 201612 | V1: 201703 | W1: 201706 | X1: 201709 | Y1: 201712 | Z1: 201803 | AA1: 201806 | AB1: 201809 | AC1: 201812 | AD1: 201903 | AE1: 201906 | AF1: 201909 | AG1: 201912 | AH1: 202003 | AI1: 202006 | AJ1: 202009 | AK1: 202012 | AL1: 202103 | AM1: 202106 | AN1: 202109 | AO1: 202112 | AP1: 202203 | AQ1: 202206 | AR1: 202209 | AS1: 202212 | AT1: 202303 | AU1: 202306 | AV1: 202309 | AW1: 202312 | AX1: 202403 | AY1: 202406
A4: Field Description | B4: Field Name
A5: Date End | B5: SHP_DATE_END | C5: {=_xll.EQNXTDZ($A$1,$B5,C$1)} -> 201206 | D5: {=_xll.EQNXTDZ($A$1,$B5,D$1)} -> 201209 | E5: {=_xll.EQNXTDZ($A$1,$B5,E$1)} -> 201212 | F5: {=_xll.EQNXTDZ($A$1,$B5,F$1)} -> 201303 | G5: {=_xll.EQNXTDZ($A$1,$B5,G$1)} -> 201306 | H5: {=_xll.EQNXTDZ($A$1,$B5,H$1)} -> 201309 | I5: {=_xll.EQNXTDZ($A$1,$B5,I$1)} -> 201312 | J5: {=_xll.EQNXTDZ($A$1,$B5,J$1)} -> 201403 | ... AY5: {=_xll.EQNXTDZ($A$1,$B5,AY$1)} -> 202406
A6: Grand Total | B6: SHP_NSGRANDTOTAL | C6: {=_xll.EQNXTDZ($A$1,$B6,C$1)} -> 62687190 | D6: {=_xll.EQNXTDZ($A$1,$B6,D$1)} -> 62687190 | E6: {=_xll.EQNXTDZ($A$1,$B6,E$1)} -> 62687190 | F6: {=_xll.EQNXTDZ($A$1,$B6,F$1)} -> 62687190 | G6: {=_xll.EQNXTDZ($A$1,$B6,G$1)} -> 62687190 | H6: {=_xll.EQNXTDZ($A$1,$B6,H$1)} -> 62687190 | I6: {=_xll.EQNXTDZ($A$1,$B6,I$1)} -> 62687190 | J6: {=_xll.EQNXTDZ($A$1,$B6,J$1)} -> 62687190 | ... AY6: {=_xll.EQNXTDZ($A$1,$B6,AY$1)} -> 75521934
B7: In Crs. | C7: =+C6/10^7 -> 6.268719 | D7: =+D6/10^7 -> 6.268719 | E7: =+E6/10^7 -> 6.268719 | F7: =+F6/10^7 -> 6.268719 | G7: =+G6/10^7 -> 6.268719 | H7: =+H6/10^7 -> 6.268719 | I7: =+I6/10^7 -> 6.268719 | J7: =+J6/10^7 -> 6.268719 | ... AY7: =+AY6/10^7 -> 7.5521934

Sheet Share price Daily
A1: =_xll.EQNXTH(B1,"[ADJC];[ADJH];[ADJL];[ADJO];[UCLS];[VOLUME]","2015-Jan-01","Y","All traded days","Asc") -> EQNXTH | B1: =+'Annual Raw'!A1 -> 109820 | L1: =_xll.EQNXTH(B1,"[NADJC];[NADJH];[NADJLOW];[NADJOPEN];[NUCLOSE];[NVOLUME]","2015-Jan-01","Y","All traded days","Asc") -> EQNXTH
A2: Huhtamaki India Ltd. | L2: Huhtamaki India Ltd.
A3: DATE | B3: ADJHIGH | C3: ADJCLOSE | D3: ADJLOW | E3: ADJOPEN | F3: CLOSE | G3: VOLUME | L3: DATE | M3: ADJCLOSE | N3: ADJHIGH | O3: ADJLOW | P3: ADJOPEN | Q3: CLOSE | R3: VOLUME
A4: 42005 | B4: 187.2 | C4: 186.05 | D4: 180 | E4: 180 | F4: 186.05 | G4: 7670 | L4: 42005 | M4: 186.8 | N4: 187.1 | O4: 180 | P4: 181.55 | Q4: 186.8 | R4: 57143
A5: 42006 | B5: 191.4 | C5: 185.75 | D5: 184.1 | E5: 189.5 | F5: 185.75 | G5: 8727 | L5: 42006 | M5: 185.75 | N5: 190.8 | O5: 182 | P5: 186.8 | Q5: 185.75 | R5: 38962
A6: 42009 | B6: 186.5 | C6: 183.35 | D6: 180.1 | E6: 186 | F6: 183.35 | G6: 9647 | L6: 42009 | M6: 183.4 | N6: 187.3 | O6: 179.5 | P6: 181.8 | Q6: 183.4 | R6: 29406
A7: 42010 | B7: 182.5 | C7: 179.3 | D7: 178.5 | E7: 181.55 | F7: 179.3 | G7: 12338 | L7: 42010 | M7: 179.8 | N7: 184.15 | O7: 179 | P7: 182.5 | Q7: 179.8 | R7: 36707
A8: 42011 | B8: 180.85 | C8: 178.5 | D8: 175.1 | E8: 180.1 | F8: 178.5 | G8: 9521 | L8: 42011 | M8: 178.15 | N8: 181.1 | O8: 175 | P8: 179.8 | Q8: 178.15 | R8: 26653
A9: 42012 | B9: 185.5 | C9: 182.8 | D9: 181 | E9: 181 | F9: 182.8 | G9: 8455 | L9: 42012 | M9: 183.05 | N9: 185.95 | O9: 178.7 | P9: 178.7 | Q9: 183.05 | R9: 78751
A10: 42013 | B10: 185.95 | C10: 184.5 | D10: 182.55 | E10: 184.4 | F10: 184.5 | G10: 3672 | L10: 42013 | M10: 185.45 | N10: 186 | O10: 182.6 | P10: 185 | Q10: 185.45 | R10: 34266
A11: 42016 | B11: 188.6 | C11: 186.85 | D11: 181.1 | E11: 182 | F11: 186.85 | G11: 4071 | L11: 42016 | M11: 187.2 | N11: 188.8 | O11: 181.2 | P11: 183.9 | Q11: 187.2 | R11: 25812
A12: 42017 | B12: 188 | C12: 184.95 | D12: 184 | E12: 185.8 | F12: 184.95 | G12: 4394 | L12: 42017 | M12: 184.5 | N12: 188.5 | O12: 184 | P12: 186.5 | Q12: 184.5 | R12: 14388
A13: 42018 | B13: 186 | C13: 183.65 | D13: 183 | E13: 185.15 | F13: 183.65 | G13: 3035 | L13: 42018 | M13: 183 | N13: 186.5 | O13: 182 | P13: 184.5 | Q13: 183 | R13: 10555
A14: 42019 | B14: 186.65 | C14: 185 | D14: 184 | E14: 186.65 | F14: 185 | G14: 6379 | L14: 42019 | M14: 184.35 | N14: 186.95 | O14: 183.5 | P14: 185.9 | Q14: 184.35 | R14: 15239
A15: 42020 | B15: 186.5 | C15: 185.75 | D15: 184.1 | E15: 186 | F15: 185.75 | G15: 1588 | L15: 42020 | M15: 185.45 | N15: 187.35 | O15: 184 | P15: 187.05 | Q15: 185.45 | R15: 12431
... A2837: 46185 | B2837: 174.45 | C2837: 173.9 | D2837: 169.25 | E2837: 170.4 | F2837: 173.9 | G2837: 8528 | L2837: 46184 | M2837: 168.96 | N2837: 172.38 | O2837: 167.86 | P2837: 170.92 | Q2837: 168.96 | R2837: 112321
L2838: 46185 | M2838: 173.95 | N2838: 175 | O2838: 169.1 | P2838: 170 | Q2838: 173.95 | R2838: 131850

Sheet Sheet2
J19: 219.3 | K19: 186.25 | L19: 186.75
J20: 192.9 | K20: 135.5 | L20: 146.9 | N20: 219.3 | O20: 192.9 | P20: 186 | Q20: 178.7 | R20: 207 | S20: 255.15 | T20: 348.25 | U20: 374 | V20: 495.9 | W20: 659.9 | X20: 613.4 | Y20: 607.9 | Z20: 555.95 | AA20: 497.8 | AB20: 459.9 | AC20: 374 | AD20: 362 | AE20: 341.5 | AF20: 384.2 | AG20: 433.8 | AH20: 460 | AI20: 474.4 | AJ20: 414.4 | AK20: 318.7 | AL20: 303.25 | AM20: 332.7 | AN20: 295 | AO20: 247 | AP20: 214.4 | AQ20: 179.5 | AR20: 97.9 | AS20: 119.1 | AT20: 130.65 | AU20: 148.55 | AV20: 153.8 | AW20: 152.9 | AX20: 136 | AY20: 141.15 | AZ20: 128.1 | BA20: 142.5 | BB20: 143.55 | BC20: 124.5 | BD20: 241 | BE20: 450 | BF20: 503.35
J21: 186 | K21: 145.4 | L21: 169.1 | N21: 186.25 | O21: 135.5 | P21: 145.4 | Q21: 108.95 | R21: 137 | S21: 170 | T21: 243.15 | U21: 307.5 | V21: 325.1 | W21: 463 | X21: 467.05 | Y21: 436.5 | Z21: 467 | AA21: 348.2 | AB21: 325 | AC21: 313.1 | AD21: 285 | AE21: 277.85 | AF21: 327 | AG21: 317 | AH21: 370.7 | AI21: 360 | AJ21: 271.15 | AK21: 233.15 | AL21: 218.8 | AM21: 262 | AN21: 223.6 | AO21: 137.6 | AP21: 142 | AQ21: 59.3 | AR21: 58 | AS21: 72.8 | AT21: 80 | AU21: 107.25 | AV21: 106 | AW21: 125.1 | AX21: 112.25 | AY21: 81.45 | AZ21: 88 | BA21: 90.35 | BB21: 106.05 | BC21: 98.55 | BD21: 119.25 | BE21: 210 | BF21: 349
J22: 178.7 | K22: 108.95 | L22: 139.75 | N22: 186.75 | O22: 146.9 | P22: 169.1 | Q22: 139.75 | R22: 202.15 | S22: 249.05 | T22: 346.4 | U22: 349.2 | V22: 469.9 | W22: 584.8 | X22: 536.15 | Y22: 513.35 | Z22: 474 | AA22: 438.55 | AB22: 355.4 | AC22: 334.95 | AD22: 298.8 | AE22: 328.35 | AF22: 343 | AG22: 389.9 | AH22: 443.05 | AI22: 407.5 | AJ22: 290.1 | AK22: 235.75 | AL22: 292.65 | AM22: 276.1 | AN22: 237.05 | AO22: 190.1 | AP22: 147.2 | AQ22: 71.9 | AR22: 75.2 | AS22: 90.1 | AT22: 117.2 | AU22: 116.3 | AV22: 140.5 | AW22: 128.6 | AX22: 133.65 | AY22: 91.65 | AZ22: 97.65 | BA22: 125 | BB22: 115.35 | BC22: 119.25 | BD22: 219.3 | BE22: 442.65 | BF22: 503.35
J23: 207 | K23: 137 | L23: 202.15
J24: 255.15 | K24: 170 | L24: 249.05
J25: 348.25 | K25: 243.15 | L25: 346.4
J26: 374 | K26: 307.5 | L26: 349.2
J27: 495.9 | K27: 325.1 | L27: 469.9
J28: 659.9 | K28: 463 | L28: 584.8
J29: 613.4 | K29: 467.05 | L29: 536.15
J30: 607.9 | K30: 436.5 | L30: 513.35
J31: 555.95 | K31: 467 | L31: 474
J32: 497.8 | K32: 348.2 | L32: 438.55
J33: 459.9 | K33: 325 | L33: 355.4
J34: 374 | K34: 313.1 | L34: 334.95
... J63: 503.35 | K63: 349 | L63: 503.35
