Workbook

Sheet Template
A1: =+'Annual Raw'!C4 -> ABB India Ltd. | B1: 37226 | C1: =EOMONTH(B1,12) -> 37621 | D1: =EOMONTH(C1,12) -> 37986 | E1: =EOMONTH(D1,12) -> 38352 | F1: =EOMONTH(E1,12) -> 38717 | G1: =EOMONTH(F1,12) -> 39082 | H1: =EOMONTH(G1,12) -> 39447 | I1: =EOMONTH(H1,12) -> 39813 | J1: =EOMONTH(I1,12) -> 40178 | ... AD1: =EOMONTH(AC1,12) -> 47483 | AG1: QTR | AH1: 41061 | AI1: 41153 | AJ1: 41244 | AK1: 41334 | AL1: 41426 | AM1: 41518 | AN1: 41609 | AO1: 41699 | AP1: 41791 | AQ1: 41883 | AR1: 41974 | AS1: 42064 | AT1: 42156 | AU1: 42248 | AV1: 42339 | AW1: 42430 | AX1: 42522 | AY1: 42614 | AZ1: 42705 | BA1: 42795 | BB1: 42887 | BC1: 42979 | BD1: 43070 | BE1: 43160 | BF1: 43252 | BG1: 43344 | BH1: 43435 | BI1: 43525 | BJ1: 43617 | BK1: 43709 | BL1: 43800 | BM1: 43891 | BN1: 43983 | BO1: 44075 | BP1: =EOMONTH(BO1,3) -> 44196 | BQ1: =EOMONTH(BP1,3) -> 44286 | BR1: =EOMONTH(BQ1,3) -> 44377 | BS1: =EOMONTH(BR1,3) -> 44469 | BT1: =EOMONTH(BS1,3) -> 44561 | BU1: =EOMONTH(BT1,3) -> 44651 | BV1: =EOMONTH(BU1,3) -> 44742 | BW1: =EOMONTH(BV1,3) -> 44834 | ... CZ1: =EOMONTH(CY1,3) -> 47483 | DB1: HISTORICAL ESTIMATES | DC1: 46022
A2: Presentation Data (Start)
A5: Order Book - Opening | U5: =+T8 -> 0 | V5: =+U8 -> 4114 | W5: =+V8 -> 4912 | X5: =+W8 -> 6468 | Y5: =+X8 -> 8404 | Z5: =+Y8 -> 9380 | AA5: =+Z8 -> 9709 | AB5: =+AA8 -> 12360.32 | ... AD5: =+AC8 -> 17770.987 | BP5: =+BO8 -> 4390 | BQ5: =+BP8 -> 4114 | BR5: =+BQ8 -> 4328 | BS5: =+BR8 -> 4583 | BT5: =+BS8 -> 4765 | BU5: =+BT8 -> 4912 | BV5: =+BU8 -> 5229 | BW5: =+BV8 -> 5995 | ... CZ5: =+CY8 -> 19118.974
A6: Order Book - Addition | U6: =+U8+U7-U5 -> 9934.95 | V6: =+V8+V7-V5 -> 7732 | W6: =+W8+W7-W5 -> 10123.53 | X6: =+X8+X7-X5 -> 12382.52 | Y6: =+Y8+Y7-Y5 -> 13164.31 | Z6: =+Z8+Z7-Z5 -> 13531.73 | AA6: =+AA8+AA7-AA5 -> 17137.516 | AB6: =+AB8+AB7-AB5 -> 19538.394 | ... AD6: =+AD8+AD7-AD5 -> 25507.537 | BP6: 1308 | BQ6: 1308 | BR6: 1689 | BS6: 1960.39 | BT6: 2248.5 | BU6: 2285.37 | BV6: 2818.51 | BW6: 2643.74 | BX6: 2375.91 | BY6: 3113.21 | BZ6: 3065.63 | CA6: 3050.19 | CB6: 3153.49 | CC6: 3611.36 | CD6: 3412.86 | CE6: 3390.16 | CF6: 2749.93 | CG6: 3737.56 | CH6: 3281.44 | CI6: 3233 | CJ6: 4096 | CK6: =+CK8+CK7-CK5 -> 4569.06 | CL6: =+CH6*(1+CL11) -> 3773.656 | CM6: =+CI6*(1+CM11) -> 3879.6 | CN6: =+CJ6*(1+CN11) -> 4915.2 | CO6: =+CK6*(1+CO11) -> 5274.9536 | CP6: =+CL6*(1+CP11) -> 4305.3598 | CQ6: =+CM6*(1+CQ11) -> 4419.1694 | CR6: =+CN6*(1+CR11) -> 5538.9111 | CS6: =+CO6*(1+CS11) -> 6000.4427 | ... CZ6: =+CV6*(1+CZ11) -> 7249.9721
A7: Order Book - Executed | U7: =+U18 -> 5820.95 | V7: =+V18 -> 6934 | W7: =+W18 -> 8567.53 | X7: =+X18 -> 10446.52 | Y7: =+Y18 -> 12188.31 | Z7: =+Z18 -> 13202.73 | AA7: =+AA18 -> 14486.196 | AB7: =+AB18 -> 17087.616 | ... AD7: =+AD18 -> 22645.674 | BP7: =+BP18 -> 1700.76 | BQ7: =+BQ18 -> 1629.15 | BR7: =+BR18 -> 1424.96 | BS7: =+BS18 -> 1778.39 | BT7: =+BT18 -> 2101.5 | BU7: =+BU18 -> 1974.86 | BV7: =+BV18 -> 2097.85 | BW7: =+BW18 -> 2119.74 | ... CK7: =+CK18 -> 3184.06 | CL7: =+CK8*CL10 -> 3703.3845 | CM7: =+CL8*CM10 -> 3768.5281 | CN7: =+CM8*CN10 -> 3830.223 | CO7: =+CN8*CO10 -> 4013.5473 | CP7: =+CO8*CP10 -> 4412.4484 | CQ7: =+CP8*CQ10 -> 4345.3423 | CR7: =+CQ8*CR10 -> 4316.2776 | CS7: =+CR8*CS10 -> 4577.7344 | ... CZ7: =+CY8*CZ10 -> 5736.0968
A8: Order Book - Closing | U8: =+BP8 -> 4114 | V8: =+BT8 -> 4912 | W8: =+BX8 -> 6468 | X8: =+CB8 -> 8404 | Y8: =+CF8 -> 9380 | Z8: =+CJ8 -> 9709 | AA8: =+CN8 -> 12360.32 | AB8: =+CR8 -> 14811.099 | AC8: =+CV8 -> 17770.987 | AD8: =+CZ8 -> 20632.849 | BO8: 4390 | BP8: 4114 | BQ8: 4328 | BR8: 4583 | BS8: 4765 | BT8: 4912 | BU8: 5229 | BV8: 5995 | BW8: 6519 | BX8: 6468 | BY8: 7170 | BZ8: 7727 | CA8: 8008 | CB8: 8404 | CC8: 8935 | CD8: 9517 | CE8: 9995 | CF8: 9380 | CG8: 9958 | CH8: 10064 | CI8: 9895 | CJ8: 9709 | CK8: 11094 | CL8: =+CL5+CL6-CL7 -> 11164.272 | CM8: =+CM5+CM6-CM7 -> 11275.343 | CN8: =+CN5+CN6-CN7 -> 12360.32 | CO8: =+CO5+CO6-CO7 -> 13621.727 | CP8: =+CP5+CP6-CP7 -> 13514.638 | CQ8: =+CQ5+CQ6-CQ7 -> 13588.465 | CR8: =+CR5+CR6-CR7 -> 14811.099 | CS8: =+CS5+CS6-CS7 -> 16233.807 | ... CZ8: =+CZ5+CZ6-CZ7 -> 20632.849
A10: Execution % Opening order book | V10: =+V7/U8 -> 1.6854643 | W10: =+W7/V8 -> 1.744204 | X10: =+X7/W8 -> 1.6151082 | Y10: =+Y7/X8 -> 1.4502987 | Z10: =+Z7/Y8 -> 1.4075405 | AA10: =+AA7/Z8 -> 1.4920379 | AB10: =+AB7/AA8 -> 1.3824573 | AC10: =+AC7/AB8 -> 1.298185 | AD10: =+AD7/AC8 -> 1.2743059 | BP10: =+BP7/BO8 -> 0.38741686 | BQ10: =+BQ7/BP8 -> 0.39600146 | BR10: =+BR7/BQ8 -> 0.32924214 | BS10: =+BS7/BR8 -> 0.38804058 | BT10: =+BT7/BS8 -> 0.44102833 | BU10: =+BU7/BT8 -> 0.40204805 | BV10: =+BV7/BU8 -> 0.40119526 | BW10: =+BW7/BV8 -> 0.35358465 | ... CK10: =+CK7/CJ8 -> 0.32794933 | CL10: =+AVERAGE(CH10:CK10) -> 0.33381869 | CM10: =+AVERAGE(CI10:CL10) -> 0.33755253 | CN10: =+AVERAGE(CJ10:CM10) -> 0.33969901 | CO10: =+AVERAGE(CK10:CN10)*0.97 -> 0.32471224 | CP10: =+AVERAGE(CL10:CO10)*0.97 -> 0.32392725 | CQ10: =+AVERAGE(CM10:CP10)*0.97 -> 0.32152857 | CR10: =+AVERAGE(CN10:CQ10)*0.97 -> 0.31764276 | CS10: =+AVERAGE(CO10:CR10)*0.96 -> 0.3090746 | CT10: =+AVERAGE(CP10:CS10)*0.96 -> 0.30532156 | CU10: =+AVERAGE(CQ10:CT10)*0.96 -> 0.3008562 | CV10: =+AVERAGE(CR10:CU10)*0.96 -> 0.29589483 | CW10: =+AVERAGE(CS10:CV10) -> 0.3027868 | CX10: =+AVERAGE(CT10:CW10) -> 0.30121485 | CY10: =+AVERAGE(CU10:CX10) -> 0.30018817 | CZ10: =+AVERAGE(CV10:CY10) -> 0.30002116
A11: Additions YOY% | V11: =+V6/U6-1 -> -0.2217374 | W11: =+W6/V6-1 -> 0.3093029 | X11: =+X6/W6-1 -> 0.22314252 | Y11: =+Y6/X6-1 -> 0.063136583 | Z11: =+Z6/Y6-1 -> 0.027910312 | AA11: =+AA6/Z6-1 -> 0.26646896 | AB11: =+AB6/AA6-1 -> 0.14009486 | AC11: =+AC6/AB6-1 -> 0.1355813 | AD11: =+AD6/AC6-1 -> 0.14963885 | BT11: =+BT6/BP6-1 -> 0.7190367 | BU11: =+BU6/BQ6-1 -> 0.74722477 | BV11: =+BV6/BR6-1 -> 0.66874482 | BW11: =+BW6/BS6-1 -> 0.3485786 | BX11: =+BX6/BT6-1 -> 0.056664443 | BY11: =+BY6/BU6-1 -> 0.36223456 | BZ11: =+BZ6/BV6-1 -> 0.087677532 | CA11: =+CA6/BW6-1 -> 0.15374053 | ... CK11: =+CK6/CG6-1 -> 0.22247134 | CL11: 0.15 | CM11: 0.2 | CN11: 0.2 | CO11: =+AVERAGE(CK11:CN11)*0.8 -> 0.15449427 | CP11: =+AVERAGE(CL11:CO11)*0.8 -> 0.14089885 | CQ11: =+AVERAGE(CM11:CP11)*0.8 -> 0.13907862 | CR11: =+AVERAGE(CN11:CQ11)*0.8 -> 0.12689435 | CS11: =+AVERAGE(CO11:CR11)*0.98 -> 0.13753469 | CT11: =+AVERAGE(CP11:CS11) -> 0.13610163 | CU11: =+AVERAGE(CQ11:CT11) -> 0.13490232 | CV11: =+AVERAGE(CR11:CU11) -> 0.13385825 | CW11: =+AVERAGE(CS11:CV11)+1% -> 0.14559922 | CX11: =+AVERAGE(CT11:CW11)+1% -> 0.14761536 | CY11: =+AVERAGE(CU11:CX11)+1% -> 0.15049379 | CZ11: =+AVERAGE(CV11:CY11)+1% -> 0.15439166
A14: Presentation Data (End)
A15: Profit & Loss- Annual (Start)
A16: Gross Revenue | B16: ='Annual Raw'!C6 -> 1041.599 | C16: ='Annual Raw'!D6 -> 1175.7576 | D16: ='Annual Raw'!E6 -> 1576.73 | E16: ='Annual Raw'!F6 -> 2445.7977 | F16: ='Annual Raw'!G6 -> 3199.9328 | G16: ='Annual Raw'!H6 -> 4604.5615 | H16: ='Annual Raw'!I6 -> 6383.2682 | I16: ='Annual Raw'!J6 -> 7340.2391 | ... Z16: ='Annual Raw'!AA6 -> 13280.31 | AA16: =+SUM(CK16:CN16) -> 14486.196 | AB16: =+SUM(CO16:CR16) -> 17087.616 | AC16: =+SUM(CS16:CV16) -> 19227.547 | AD16: =SUM(CW16:CZ16) -> 22645.674 | AH16: ='QTR Raw'!C6+'QTR Raw'!C8 -> 1883.79 | AI16: ='QTR Raw'!D6+'QTR Raw'!D8 -> 1808.61 | AJ16: ='QTR Raw'!E6+'QTR Raw'!E8 -> 2082.28 | AK16: ='QTR Raw'!F6+'QTR Raw'!F8 -> 1981.07 | AL16: ='QTR Raw'!G6+'QTR Raw'!G8 -> 1751.15 | AM16: ='QTR Raw'!H6+'QTR Raw'!H8 -> 1785.9 | AN16: ='QTR Raw'!I6+'QTR Raw'!I8 -> 2203.87 | AO16: ='QTR Raw'!J6+'QTR Raw'!J8 -> 1827.71 | ... CI16: ='QTR Raw'!BD6+'QTR Raw'!BD8 -> 3310.72 | CJ16: 3557.01 | CK16: ='QTR Raw'!BF6+'QTR Raw'!BF8 -> 3184.06 | CL16: =+CL7 -> 3703.3845 | CM16: =+CM7 -> 3768.5281 | CN16: =+CN7 -> 3830.223 | CO16: =+CO7 -> 4013.5473 | CP16: =+CP7 -> 4412.4484 | CQ16: =+CQ7 -> 4345.3423 | CR16: =+CR7 -> 4316.2776 | CS16: =+CS7 -> 4577.7344 | ... CZ16: =+CZ7 -> 5736.0968 | DC16: 0
A17: Less: Exise Duty | B17: ='Annual Raw'!C7+'Annual Raw'!C8+'Annual Raw'!C9 -> 0 | C17: ='Annual Raw'!D7+'Annual Raw'!D8+'Annual Raw'!D9 -> 0 | D17: ='Annual Raw'!E7+'Annual Raw'!E8+'Annual Raw'!E9 -> 108.3725 | E17: ='Annual Raw'!F7+'Annual Raw'!F8+'Annual Raw'!F9 -> 185.5751 | F17: ='Annual Raw'!G7+'Annual Raw'!G8+'Annual Raw'!G9 -> 236.8802 | G17: ='Annual Raw'!H7+'Annual Raw'!H8+'Annual Raw'!H9 -> 330.5522 | H17: ='Annual Raw'!I7+'Annual Raw'!I8+'Annual Raw'!I9 -> 452.9568 | I17: ='Annual Raw'!J7+'Annual Raw'!J8+'Annual Raw'!J9 -> 503.2076 | ... Z17: ='Annual Raw'!AA7+'Annual Raw'!AA8+'Annual Raw'!AA9 -> 77.58 | AA17: =+SUM(CK17:CN17) -> 0 | AB17: =+SUM(CO17:CR17) -> 0 | AC17: =+SUM(CS17:CV17) -> 0 | AD17: =SUM(CW17:CZ17) -> 0 | AH17: =+'QTR Raw'!C20+'QTR Raw'!C19+'QTR Raw'!C13+'QTR Raw'!C7 -> 0 | AI17: =+'QTR Raw'!D20+'QTR Raw'!D19+'QTR Raw'!D13+'QTR Raw'!D7 -> 0 | AJ17: =+'QTR Raw'!E20+'QTR Raw'!E19+'QTR Raw'!E13+'QTR Raw'!E7 -> 0 | AK17: =+'QTR Raw'!F20+'QTR Raw'!F19+'QTR Raw'!F13+'QTR Raw'!F7 -> 0 | AL17: =+'QTR Raw'!G20+'QTR Raw'!G19+'QTR Raw'!G13+'QTR Raw'!G7 -> 0 | AM17: =+'QTR Raw'!H20+'QTR Raw'!H19+'QTR Raw'!H13+'QTR Raw'!H7 -> 0 | AN17: =+'QTR Raw'!I20+'QTR Raw'!I19+'QTR Raw'!I13+'QTR Raw'!I7 -> 0 | AO17: =+'QTR Raw'!J20+'QTR Raw'!J19+'QTR Raw'!J13+'QTR Raw'!J7 -> 0 | ... CI17: =+'QTR Raw'!BD20+'QTR Raw'!BD19+'QTR Raw'!BD13+'QTR Raw'!BD7 -> 0 | CK17: =+'QTR Raw'!BF20+'QTR Raw'!BF19+'QTR Raw'!BF13+'QTR Raw'!BF7 -> 0 | DC17: 0
A18: Net Revenue | B18: =+B16-B17 -> 1041.599 | C18: =+C16-C17 -> 1175.7576 | D18: =+D16-D17 -> 1468.3575 | E18: =+E16-E17 -> 2260.2226 | F18: =+F16-F17 -> 2963.0526 | G18: =+G16-G17 -> 4274.0093 | H18: =+H16-H17 -> 5930.3114 | I18: =+I16-I17 -> 6837.0315 | ... AD18: =+AD16-AD17 -> 22645.674 | AH18: =+AH16-AH17 -> 1883.79 | AI18: =+AI16-AI17 -> 1808.61 | AJ18: =+AJ16-AJ17 -> 2082.28 | AK18: =+AK16-AK17 -> 1981.07 | AL18: =+AL16-AL17 -> 1751.15 | AM18: =+AM16-AM17 -> 1785.9 | AN18: =+AN16-AN17 -> 2203.87 | AO18: =+AO16-AO17 -> 1827.71 | ... CZ18: =+CZ16-CZ17 -> 5736.0968 | DC18: 0
A19: Net Revenue YOY% | C19: =C18/B18-1 -> 0.12880062 | D19: =D18/C18-1 -> 0.24886073 | E19: =E18/D18-1 -> 0.53928631 | F19: =F18/E18-1 -> 0.3109561 | G19: =G18/F18-1 -> 0.4424345 | H19: =H18/G18-1 -> 0.38752889 | I19: =I18/H18-1 -> 0.15289587 | J19: =J18/I18-1 -> -0.087732534 | ... AD19: =AD18/AC18-1 -> 0.17777243 | AL19: =+IF(AH18<0,1-AL18/AH18,AL18/AH18-1) -> -0.070411245 | AM19: =+IF(AI18<0,1-AM18/AI18,AM18/AI18-1) -> -0.012556604 | AN19: =+IF(AJ18<0,1-AN18/AJ18,AN18/AJ18-1) -> 0.058392723 | AO19: =+IF(AK18<0,1-AO18/AK18,AO18/AK18-1) -> -0.077412711 | AP19: =+IF(AL18<0,1-AP18/AL18,AP18/AL18-1) -> 0.040561916 | AQ19: =+IF(AM18<0,1-AQ18/AM18,AQ18/AM18-1) -> 0.03307576 | AR19: =+IF(AN18<0,1-AR18/AN18,AR18/AN18-1) -> 0.015672431 | AS19: =+IF(AO18<0,1-AS18/AO18,AS18/AO18-1) -> -0.0071893243 | ... CZ19: =+IF(CV18<0,1-CZ18/CV18,CZ18/CV18-1) -> 0.18787887 | DC19: #DIV/0!
A20: Net Revenue QOQ% | AI20: =+IF(AH18<0,1-AI18/AH18,AI18/AH18-1) -> -0.039908907 | AJ20: =+IF(AI18<0,1-AJ18/AI18,AJ18/AI18-1) -> 0.1513151 | AK20: =+IF(AJ18<0,1-AK18/AJ18,AK18/AJ18-1) -> -0.048605375 | AL20: =+IF(AK18<0,1-AL18/AK18,AL18/AK18-1) -> -0.11605849 | AM20: =+IF(AL18<0,1-AM18/AL18,AM18/AL18-1) -> 0.019844102 | AN20: =+IF(AM18<0,1-AN18/AM18,AN18/AM18-1) -> 0.23403886 | AO20: =+IF(AN18<0,1-AO18/AN18,AO18/AN18-1) -> -0.17068157 | AP20: =+IF(AO18<0,1-AP18/AO18,AP18/AO18-1) -> -0.0030256441 | ... CK20: =+IF(CJ18<0,1-CK18/CJ18,CK18/CJ18-1) -> -0.1048493 | CL20: =+CL18/CK18-1 -> 0.16310135 | CM20: =+CM18/CL18-1 -> 0.017590285 | CN20: =+CN18/CM18-1 -> 0.016371085 | CO20: =+CO18/CN18-1 -> 0.047862584 | CP20: =+CP18/CO18-1 -> 0.099388658 | CQ20: =+CQ18/CP18-1 -> -0.015208366 | CR20: =+CR18/CQ18-1 -> -0.0066886908 | CS20: =+CS18/CR18-1 -> 0.060574583 | ... CZ20: =+CZ18/CY18-1 -> 0.0017505197
A21: Increase/Decrease in Stock | B21: ='Annual Raw'!C11 -> 0.9139 | C21: ='Annual Raw'!D11 -> 5.4548 | D21: ='Annual Raw'!E11 -> 9.3257 | E21: ='Annual Raw'!F11 -> -23.5813 | F21: ='Annual Raw'!G11 -> -7.7979 | G21: ='Annual Raw'!H11 -> -53.0166 | H21: ='Annual Raw'!I11 -> -52.0728 | I21: ='Annual Raw'!J11 -> -73.7869 | ... Z21: ='Annual Raw'!AA11 -> -130.89 | AA21: =+SUM(CK21:CN21) -> -51.54 | AB21: =+SUM(CO21:CR21) -> 0 | AC21: =+SUM(CS21:CV21) -> 0 | AD21: =SUM(CW21:CZ21) -> 0 | AH21: ='QTR Raw'!C10 -> -6.98 | AI21: ='QTR Raw'!D10 -> -28.04 | AJ21: ='QTR Raw'!E10 -> 42.06 | AK21: ='QTR Raw'!F10 -> -24.13 | AL21: ='QTR Raw'!G10 -> 3.8 | AM21: ='QTR Raw'!H10 -> -17.94 | AN21: ='QTR Raw'!I10 -> 25.29 | AO21: ='QTR Raw'!J10 -> 10.39 | ... CI21: ='QTR Raw'!BD10 -> -34.29 | CJ21: 151.65 | CK21: ='QTR Raw'!BF10 -> -51.54 | DC21: 0
A22: Purchase of Finished Goods | B22: 0 | C22: 0 | D22: 0 | E22: 0 | F22: 0 | G22: 0 | H22: 0 | I22: 0 | J22: 0 | K22: 0 | L22: 0 | M22: 0 | N22: 0 | O22: 0 | P22: 0 | Q22: 0 | R22: 0 | S22: 0 | T22: 0 | U22: 0 | V22: 0 | W22: 0 | X22: 0 | Y22: 0 | Z22: 0 | AA22: =+SUM(CK22:CN22) -> 241.3 | AB22: =+SUM(CO22:CR22) -> 0 | AC22: =+SUM(CS22:CV22) -> 0 | AD22: =SUM(CW22:CZ22) -> 0 | AH22: ='QTR Raw'!C12 -> 62.16 | AI22: ='QTR Raw'!D12 -> 65.26 | AJ22: ='QTR Raw'!E12 -> 70.39 | AK22: ='QTR Raw'!F12 -> 49.09 | AL22: ='QTR Raw'!G12 -> 76.15 | AM22: ='QTR Raw'!H12 -> 85.97 | AN22: ='QTR Raw'!I12 -> 102.86 | AO22: ='QTR Raw'!J12 -> 82.33 | ... CI22: ='QTR Raw'!BD12 -> 240.26 | CJ22: 271.47 | CK22: ='QTR Raw'!BF12 -> 241.3 | DC22: 0
A23: Raw Material Consumed | B23: ='Annual Raw'!C12 -> 419.0008 | C23: ='Annual Raw'!D12 -> 467.2112 | D23: ='Annual Raw'!E12 -> 527.9141 | E23: ='Annual Raw'!F12 -> 719.4776 | F23: ='Annual Raw'!G12 -> 875.9128 | G23: ='Annual Raw'!H12 -> 1265.495 | H23: ='Annual Raw'!I12 -> 1577.0845 | I23: ='Annual Raw'!J12 -> 2083.501 | ... Z23: ='Annual Raw'!AA12 -> 7755.65 | AA23: =+SUM(CK23:CN23) -> 8227.2139 | AB23: =+SUM(CO23:CR23) -> 9937.5202 | AC23: =+SUM(CS23:CV23) -> 11183.228 | AD23: =SUM(CW23:CZ23) -> 13171.343 | AH23: ='QTR Raw'!C11 -> 1163.55 | AI23: ='QTR Raw'!D11 -> 1109.66 | AJ23: ='QTR Raw'!E11 -> 1312.81 | AK23: ='QTR Raw'!F11 -> 1277.21 | AL23: ='QTR Raw'!G11 -> 1004.15 | AM23: ='QTR Raw'!H11 -> 1063.55 | AN23: ='QTR Raw'!I11 -> 1284.28 | AO23: ='QTR Raw'!J11 -> 1033.35 | ... CI23: ='QTR Raw'!BD11 -> 1755.97 | CJ23: 1646.63 | CK23: ='QTR Raw'!BF11 -> 1644.22 | CL23: =+CL18-CL24 -> 2159.0102 | CM23: =+CM18-CM24 -> 2198.4201 | CN23: =+CN18-CN24 -> 2225.5636 | CO23: =+CO18-CO24 -> 2331.2562 | CP23: =+CP18-CP24 -> 2568.3165 | CQ23: =+CQ18-CQ24 -> 2528.2556 | CR23: =+CR18-CR24 -> 2509.6919 | CS23: =+CS18-CS24 -> 2662.1674 | ... CZ23: =+CZ18-CZ24 -> 3336.2257 | DC23: 0
A24: Gross Profit | B24: =B18-B21-B23-B22 -> 621.6843 | C24: =C18-C21-C23-C22 -> 703.0916 | D24: =D18-D21-D23-D22 -> 931.1177 | E24: =E18-E21-E23-E22 -> 1564.3263 | F24: =F18-F21-F23-F22 -> 2094.9377 | G24: =G18-G21-G23-G22 -> 3061.5309 | H24: =H18-H21-H23-H22 -> 4405.2997 | I24: =I18-I21-I23-I22 -> 4827.3174 | ... AD24: =AD18-AD21-AD23-AD22 -> 9474.3311 | AH24: =AH18-AH21-AH23-AH22 -> 665.06 | AI24: =AI18-AI21-AI23-AI22 -> 661.73 | AJ24: =AJ18-AJ21-AJ23-AJ22 -> 657.02 | AK24: =AK18-AK21-AK23-AK22 -> 678.9 | AL24: =AL18-AL21-AL23-AL22 -> 667.05 | AM24: =AM18-AM21-AM23-AM22 -> 654.32 | AN24: =AN18-AN21-AN23-AN22 -> 791.44 | AO24: =AO18-AO21-AO23-AO22 -> 701.64 | ... CK24: =CK18-CK21-CK23-CK22 -> 1350.08 | CL24: =+CL25*CL18 -> 1544.3743 | CM24: =+CM25*CM18 -> 1570.108 | CN24: =+CN25*CN18 -> 1604.6594 | CO24: =+CO25*CO18 -> 1682.2912 | CP24: =+CP25*CP18 -> 1844.1319 | CQ24: =+CQ25*CQ18 -> 1817.0867 | CR24: =+CR25*CR18 -> 1806.5858 | CS24: =+CS25*CS18 -> 1915.567 | ... CZ24: =+CZ25*CZ18 -> 2399.8711 | DC24: 0
A25: GP% | B25: =B24/B18 -> 0.5968557 | C25: =C24/C18 -> 0.59799027 | D25: =D24/D18 -> 0.63412194 | E25: =E24/E18 -> 0.69211161 | F25: =F24/F18 -> 0.70702008 | G25: =G24/G18 -> 0.71631358 | H25: =H24/H18 -> 0.74284458 | I25: =I24/I18 -> 0.70605458 | ... AD25: =AD24/AD18 -> 0.41837267 | AH25: =AH24/AH18 -> 0.3530436 | AI25: =AI24/AI18 -> 0.36587766 | AJ25: =AJ24/AJ18 -> 0.31552913 | AK25: =AK24/AK18 -> 0.34269359 | AL25: =AL24/AL18 -> 0.38092111 | AM25: =AM24/AM18 -> 0.3663811 | AN25: =AN24/AN18 -> 0.35911374 | AO25: =AO24/AO18 -> 0.38389022 | ... CK25: =CK24/CK18 -> 0.42401211 | CL25: =AVERAGE(CH25:CK25) -> 0.417017 | CM25: =AVERAGE(CI25:CL25) -> 0.41663693 | CN25: =AVERAGE(CJ25:CM25) -> 0.41894672 | CO25: =AVERAGE(CK25:CN25) -> 0.41915319 | CP25: =AVERAGE(CL25:CO25) -> 0.41793846 | CQ25: =AVERAGE(CM25:CP25) -> 0.41816883 | CR25: =AVERAGE(CN25:CQ25) -> 0.4185518 | CS25: =AVERAGE(CO25:CR25) -> 0.41845307 | ... CZ25: =AVERAGE(CV25:CY25) -> 0.41838051 | DC25: #DIV/0!
A26: GP YOY% | C26: =+IF(B24<0,1-C24/B24,C24/B24-1) -> 0.13094637 | D26: =+IF(C24<0,1-D24/C24,D24/C24-1) -> 0.32431919 | E26: =+IF(D24<0,1-E24/D24,E24/D24-1) -> 0.68005216 | F26: =+IF(E24<0,1-F24/E24,F24/E24-1) -> 0.33919483 | G26: =+IF(F24<0,1-G24/F24,G24/F24-1) -> 0.46139472 | H26: =+IF(G24<0,1-H24/G24,H24/G24-1) -> 0.43892054 | I26: =+IF(H24<0,1-I24/H24,I24/H24-1) -> 0.095797727 | J26: =+IF(I24<0,1-J24/I24,J24/I24-1) -> -0.085530071 | ... AD26: =+IF(AC24<0,1-AD24/AC24,AD24/AC24-1) -> 0.17776671 | AL26: =+IF(AH24<0,1-AL24/AH24,AL24/AH24-1) -> 0.0029922112 | AM26: =+IF(AI24<0,1-AM24/AI24,AM24/AI24-1) -> -0.011197921 | AN26: =+IF(AJ24<0,1-AN24/AJ24,AN24/AJ24-1) -> 0.20459042 | AO26: =+IF(AK24<0,1-AO24/AK24,AO24/AK24-1) -> 0.03349536 | AP26: =+IF(AL24<0,1-AP24/AL24,AP24/AL24-1) -> 0.021677535 | AQ26: =+IF(AM24<0,1-AQ24/AM24,AQ24/AM24-1) -> 0.074764641 | AR26: =+IF(AN24<0,1-AR24/AN24,AR24/AN24-1) -> 0.023236127 | AS26: =+IF(AO24<0,1-AS24/AO24,AS24/AO24-1) -> 0.041844821 | ... CK26: =+IF(CG24<0,1-CK24/CG24,CK24/CG24-1) -> -0.014425042 | CL26: =+CL24/CH24-1 -> 0.16202244 | CM26: =+CM24/CI24-1 -> 0.16409495 | CN26: =+CN24/CJ24-1 -> 0.078936673 | CO26: =+CO24/CK24-1 -> 0.24606777 | CP26: =+CP24/CL24-1 -> 0.19409648 | CQ26: =+CQ24/CM24-1 -> 0.15730046 | CR26: =+CR24/CN24-1 -> 0.12583756 | CS26: =+CS24/CO24-1 -> 0.13866554 | ... CZ26: =+CZ24/CV24-1 -> 0.18779099 | DC26: #DIV/0!
A27: GP QOQ% | AI27: =+IF(AH24<0,1-AI24/AH24,AI24/AH24-1) -> -0.005007067 | AJ27: =+IF(AI24<0,1-AJ24/AI24,AJ24/AI24-1) -> -0.0071177066 | AK27: =+IF(AJ24<0,1-AK24/AJ24,AK24/AJ24-1) -> 0.033301878 | AL27: =+IF(AK24<0,1-AL24/AK24,AL24/AK24-1) -> -0.017454706 | AM27: =+IF(AL24<0,1-AM24/AL24,AM24/AL24-1) -> -0.019084027 | AN27: =+IF(AM24<0,1-AN24/AM24,AN24/AM24-1) -> 0.20956107 | AO27: =+IF(AN24<0,1-AO24/AN24,AO24/AN24-1) -> -0.11346407 | AP27: =+IF(AO24<0,1-AP24/AO24,AP24/AO24-1) -> -0.028689926 | ... CK27: =+IF(CJ24<0,1-CK24/CJ24,CK24/CJ24-1) -> -0.092236731 | CL27: =+CL24/CK24-1 -> 0.14391318 | CM27: =+CM24/CL24-1 -> 0.016662856 | CN27: =+CN24/CM24-1 -> 0.022005728 | CO27: =+CO24/CN24-1 -> 0.048379005 | CP27: =+CP24/CO24-1 -> 0.096202568 | CQ27: =+CQ24/CP24-1 -> -0.014665555 | CR27: =+CR24/CQ24-1 -> -0.0057789823 | CS27: =+CS24/CR24-1 -> 0.060324409 | ... CZ27: =+CZ24/CY24-1 -> 0.0017589355
A28: Employee Cost | B28: ='Annual Raw'!C14 -> 112.5039 | C28: ='Annual Raw'!D14 -> 120.0603 | D28: ='Annual Raw'!E14 -> 115.2921 | E28: ='Annual Raw'!F14 -> 135.0213 | F28: ='Annual Raw'!G14 -> 176.864 | G28: ='Annual Raw'!H14 -> 238.5327 | H28: ='Annual Raw'!I14 -> 303.5365 | I28: ='Annual Raw'!J14 -> 400.3824 | ... Z28: ='Annual Raw'!AA14 -> 974.81 | AA28: =+SUM(CK28:CN28) -> 962.9976 | AB28: =+SUM(CO28:CR28) -> 1030.4074 | AC28: =+SUM(CS28:CV28) -> 1102.536 | AD28: =SUM(CW28:CZ28) -> 1179.7135 | AH28: ='QTR Raw'!C16 -> 175.29 | AI28: ='QTR Raw'!D16 -> 149.52 | AJ28: ='QTR Raw'!E16 -> 145.86 | AK28: ='QTR Raw'!F16 -> 170.24 | AL28: ='QTR Raw'!G16 -> 156.41 | AM28: ='QTR Raw'!H16 -> 162.65 | AN28: ='QTR Raw'!I16 -> 187.76 | AO28: ='QTR Raw'!J16 -> 168.14 | ... CI28: ='QTR Raw'!BD16 -> 222.25 | CJ28: =291.37-65.94 -> 225.43 | CK28: ='QTR Raw'!BF16 -> 252.86 | CL28: =CH28*107% -> 231.12 | CM28: =CI28*107% -> 237.8075 | CN28: =CJ28*107% -> 241.2101 | CO28: =CK28*107% -> 270.5602 | CP28: =CL28*107% -> 247.2984 | CQ28: =CM28*107% -> 254.45403 | CR28: =CN28*107% -> 258.09481 | CS28: =CO28*107% -> 289.49941 | ... CZ28: =CV28*107% -> 295.49274 | DC28: 0
A29: General and Administration Expenses | B29: ='Annual Raw'!C17 -> 63.0905 | C29: ='Annual Raw'!D17 -> 62.2025 | D29: ='Annual Raw'!E17 -> 66.7747 | E29: ='Annual Raw'!F17 -> 68.8673 | F29: ='Annual Raw'!G17 -> 89.4623 | G29: ='Annual Raw'!H17 -> 149.5943 | H29: ='Annual Raw'!I17 -> 199.0484 | I29: ='Annual Raw'!J17 -> 268.4378 | ... Z29: ='Annual Raw'!AA17 -> 1313.84 | AA29: =+SUM(CK29:CN29) -> 0 | AB29: =+SUM(CO29:CR29) -> 0 | AC29: =+SUM(CS29:CV29) -> 0 | AD29: =SUM(CW29:CZ29) -> 0 | AH29: ='QTR Raw'!C17 -> 0 | AI29: ='QTR Raw'!D17 -> 0 | AJ29: ='QTR Raw'!E17 -> 0 | AK29: ='QTR Raw'!F17 -> 0 | AL29: ='QTR Raw'!G17 -> 0 | AM29: ='QTR Raw'!H17 -> 0 | AN29: ='QTR Raw'!I17 -> 0 | AO29: ='QTR Raw'!J17 -> 0 | ... CI29: ='QTR Raw'!BD17 -> 0 | CK29: ='QTR Raw'!BF17 -> 0 | DC29: 0
A30: Miscellaneous Expenses | B30: ='Annual Raw'!C19-'Annual Raw'!C20 -> 41.7367 | C30: ='Annual Raw'!D19-'Annual Raw'!D20 -> 54.4336 | D30: ='Annual Raw'!E19-'Annual Raw'!E20 -> 58.5664 | E30: ='Annual Raw'!F19-'Annual Raw'!F20 -> 83.9485 | F30: ='Annual Raw'!G19-'Annual Raw'!G20 -> 121.5091 | G30: ='Annual Raw'!H19-'Annual Raw'!H20 -> 105.0291 | H30: ='Annual Raw'!I19-'Annual Raw'!I20 -> 163.0677 | I30: ='Annual Raw'!J19-'Annual Raw'!J20 -> 159.2586 | ... Z30: ='Annual Raw'!AA19-'Annual Raw'!AA20 -> 120.9 | AA30: =+SUM(CK30:CN30) -> 0 | AB30: =+SUM(CO30:CR30) -> 0 | AC30: =+SUM(CS30:CV30) -> 0 | AD30: =SUM(CW30:CZ30) -> 0 | AH30: =+'QTR Raw'!C21 -> 0 | AI30: =+'QTR Raw'!D21 -> 0 | AJ30: =+'QTR Raw'!E21 -> 0 | AK30: =+'QTR Raw'!F21 -> 0 | AL30: =+'QTR Raw'!G21 -> 0 | AM30: =+'QTR Raw'!H21 -> 0 | AN30: =+'QTR Raw'!I21 -> 0 | AO30: =+'QTR Raw'!J21 -> 0 | ... CI30: =+'QTR Raw'!BD21 -> 0 | CK30: =+'QTR Raw'!BF21 -> 0 | DC30: 0
A31: Other Manufacturing Expenses | B31: ='Annual Raw'!C15+'Annual Raw'!C16 -> 279.5401 | C31: ='Annual Raw'!D15+'Annual Raw'!D16 -> 320.9275 | D31: ='Annual Raw'!E15+'Annual Raw'!E16 -> 514.5465 | E31: ='Annual Raw'!F15+'Annual Raw'!F16 -> 1003.1039 | F31: ='Annual Raw'!G15+'Annual Raw'!G16 -> 1316.8397 | G31: ='Annual Raw'!H15+'Annual Raw'!H16 -> 2004.3239 | H31: ='Annual Raw'!I15+'Annual Raw'!I16 -> 2902.9148 | I31: ='Annual Raw'!J15+'Annual Raw'!J16 -> 3117.4154 | ... Z31: ='Annual Raw'!AA15+'Annual Raw'!AA16 -> 950.16 | AA31: =+SUM(CK31:CN31) -> 3065.7087 | AB31: =+SUM(CO31:CR31) -> 3547.1207 | AC31: =+SUM(CS31:CV31) -> 4178.4729 | AD31: =SUM(CW31:CZ31) -> 5050.9265 | AH31: ='QTR Raw'!C14 -> 383.78 | AI31: ='QTR Raw'!D14 -> 445.82 | AJ31: ='QTR Raw'!E14 -> 444.57 | AK31: ='QTR Raw'!F14 -> 401.5 | AL31: ='QTR Raw'!G14 -> 402.76 | AM31: ='QTR Raw'!H14 -> 386.25 | AN31: ='QTR Raw'!I14 -> 454.22 | AO31: ='QTR Raw'!J14 -> 407.78 | ... CI31: ='QTR Raw'!BD14 -> 626.14 | CJ31: =118.98+530.66 -> 649.64 | CK31: ='QTR Raw'!BF14 -> 688.82 | CL31: =CL34-CL28-CL29-CL30-CL32-CL33 -> 784.5436 | CM31: =CM34-CM28-CM29-CM30-CM32-CM33 -> 782.51388 | CN31: =CN34-CN28-CN29-CN30-CN32-CN33 -> 809.83124 | CO31: =CO34-CO28-CO29-CO30-CO32-CO33 -> 825.99433 | CP31: =CP34-CP28-CP29-CP30-CP32-CP33 -> 933.87987 | CQ31: =CQ34-CQ28-CQ29-CQ30-CQ32-CQ33 -> 901.77603 | CR31: =CR34-CR28-CR29-CR30-CR32-CR33 -> 885.47045 | CS31: =CS34-CS28-CS29-CS30-CS32-CS33 -> 961.79178 | ... CZ31: =CZ34-CZ28-CZ29-CZ30-CZ32-CZ33 -> 1284.8825 | DC31: 0
A32: Power & Fuel Cost | B32: ='Annual Raw'!C13 -> 9.3438 | C32: ='Annual Raw'!D13 -> 9.5228 | D32: ='Annual Raw'!E13 -> 9.1404 | E32: ='Annual Raw'!F13 -> 12.178 | F32: ='Annual Raw'!G13 -> 14.9088 | G32: ='Annual Raw'!H13 -> 19.0068 | H32: ='Annual Raw'!I13 -> 22.3333 | I32: ='Annual Raw'!J13 -> 27.4312 | ... Z32: ='Annual Raw'!AA13 -> 28.8 | AA32: =+SUM(CK32:CN32) -> 0 | AB32: =+SUM(CO32:CR32) -> 0 | AC32: =+SUM(CS32:CV32) -> 0 | AD32: =SUM(CW32:CZ32) -> 0 | AH32: ='QTR Raw'!C15 -> 0 | AI32: ='QTR Raw'!D15 -> 0 | AJ32: ='QTR Raw'!E15 -> 0 | AK32: ='QTR Raw'!F15 -> 0 | AL32: ='QTR Raw'!G15 -> 0 | AM32: ='QTR Raw'!H15 -> 0 | AN32: ='QTR Raw'!I15 -> 0 | AO32: ='QTR Raw'!J15 -> 0 | ... CI32: ='QTR Raw'!BD15 -> 0 | CK32: ='QTR Raw'!BF15 -> 0 | DC32: 0
A33: Selling and Distribution Expenses | B33: ='Annual Raw'!C18 -> 14.4992 | C33: ='Annual Raw'!D18 -> 16.6277 | D33: ='Annual Raw'!E18 -> 24.8867 | E33: ='Annual Raw'!F18 -> 42.8444 | F33: ='Annual Raw'!G18 -> 50.4217 | G33: ='Annual Raw'!H18 -> 63.7147 | H33: ='Annual Raw'!I18 -> 74.6586 | I33: ='Annual Raw'!J18 -> 65.5072 | ... Z33: ='Annual Raw'!AA18 -> 179.36 | AA33: =+SUM(CK33:CN33) -> 0 | AB33: =+SUM(CO33:CR33) -> 0 | AC33: =+SUM(CS33:CV33) -> 0 | AD33: =SUM(CW33:CZ33) -> 0 | AH33: ='QTR Raw'!C18 -> 0 | AI33: ='QTR Raw'!D18 -> 0 | AJ33: ='QTR Raw'!E18 -> 0 | AK33: ='QTR Raw'!F18 -> 0 | AL33: ='QTR Raw'!G18 -> 0 | AM33: ='QTR Raw'!H18 -> 0 | AN33: ='QTR Raw'!I18 -> 0 | AO33: ='QTR Raw'!J18 -> 0 | ... CI33: ='QTR Raw'!BD18 -> 0 | CK33: ='QTR Raw'!BF18 -> 0 | DC33: 0
A34: Total Cost | B34: =+SUM(B28:B33) -> 520.7142 | C34: =+SUM(C28:C33) -> 583.7744 | D34: =+SUM(D28:D33) -> 789.2068 | E34: =+SUM(E28:E33) -> 1345.9634 | F34: =+SUM(F28:F33) -> 1770.0056 | G34: =+SUM(G28:G33) -> 2580.2015 | H34: =+SUM(H28:H33) -> 3665.5593 | I34: =+SUM(I28:I33) -> 4038.4326 | ... AD34: =+SUM(AD28:AD33) -> 6230.64 | AH34: =+SUM(AH28:AH33) -> 559.07 | AI34: =+SUM(AI28:AI33) -> 595.34 | AJ34: =+SUM(AJ28:AJ33) -> 590.43 | AK34: =+SUM(AK28:AK33) -> 571.74 | AL34: =+SUM(AL28:AL33) -> 559.17 | AM34: =+SUM(AM28:AM33) -> 548.9 | AN34: =+SUM(AN28:AN33) -> 641.98 | AO34: =+SUM(AO28:AO33) -> 575.92 | ... CK34: =+SUM(CK28:CK33) -> 941.68 | CL34: =CL35*CL18 -> 1015.6636 | CM34: =CM35*CM18 -> 1020.3214 | CN34: =CN35*CN18 -> 1051.0413 | CO34: =CO35*CO18 -> 1096.5545 | CP34: =CP35*CP18 -> 1181.1783 | CQ34: =CQ35*CQ18 -> 1156.2301 | CR34: =CR35*CR18 -> 1143.5653 | CS34: =CS35*CS18 -> 1251.2912 | ... CZ34: =CZ35*CZ18 -> 1580.3752 | DC34: 0
A35: Cost % | B35: =B34/B18 -> 0.49991811 | C35: =C34/C18 -> 0.49650914 | D35: =D34/D18 -> 0.53747592 | E35: =E34/E18 -> 0.59550037 | F35: =F34/F18 -> 0.59735882 | G35: =G34/G18 -> 0.60369581 | H35: =H34/H18 -> 0.6181057 | I35: =I34/I18 -> 0.59067047 | ... AD35: =AD34/AD18 -> 0.27513599 | AH35: =AH34/AH18 -> 0.29677937 | AI35: =AI34/AI18 -> 0.32916992 | AJ35: =AJ34/AJ18 -> 0.28354976 | AK35: =AK34/AK18 -> 0.28860161 | AL35: =AL34/AL18 -> 0.31931588 | AM35: =AM34/AM18 -> 0.30735204 | AN35: =AN34/AN18 -> 0.29129667 | AO35: =AO34/AO18 -> 0.31510469 | ... CK35: =CK34/CK18 -> 0.2957482 | CL35: =AVERAGE(CH35:CK35)*1.01 -> 0.27425281 | CM35: =AVERAGE(CI35:CL35)*1.01 -> 0.27074798 | CN35: =AVERAGE(CJ35:CM35)*1.01 -> 0.27440735 | CO35: =AVERAGE(CK35:CN35)*0.98 -> 0.2732133 | CP35: =AVERAGE(CL35:CO35)*0.98 -> 0.26769225 | CQ35: =AVERAGE(CM35:CP35)*0.98 -> 0.26608492 | CR35: =AVERAGE(CN35:CQ35)*0.98 -> 0.26494247 | CS35: =AVERAGE(CO35:CR35)*1.02 -> 0.2733429 | CT35: =AVERAGE(CP35:CS35)*1.02 -> 0.27337595 | CU35: =AVERAGE(CQ35:CT35)*1.02 -> 0.27482529 | CV35: =AVERAGE(CR35:CU35)*1.02 -> 0.27705408 | CW35: =AVERAGE(CS35:CV35) -> 0.27464956 | CX35: =AVERAGE(CT35:CW35) -> 0.27497622 | CY35: =AVERAGE(CU35:CX35) -> 0.27537629 | CZ35: =AVERAGE(CV35:CY35) -> 0.27551404 | DC35: #DIV/0!
A36: EBITDA | B36: =B24-B34 -> 100.9701 | C36: =C24-C34 -> 119.3172 | D36: =D24-D34 -> 141.9109 | E36: =E24-E34 -> 218.3629 | F36: =F24-F34 -> 324.9321 | G36: =G24-G34 -> 481.3294 | H36: =H24-H34 -> 739.7404 | I36: =I24-I34 -> 788.8848 | ... AD36: =AD24-AD34 -> 3243.6911 | AH36: =AH24-AH34 -> 105.99 | AI36: =AI24-AI34 -> 66.39 | AJ36: =AJ24-AJ34 -> 66.59 | AK36: =AK24-AK34 -> 107.16 | AL36: =AL24-AL34 -> 107.88 | AM36: =AM24-AM34 -> 105.42 | AN36: =AN24-AN34 -> 149.46 | AO36: =AO24-AO34 -> 125.72 | ... CZ36: =CZ24-CZ34 -> 819.49592 | DC36: 0
A37: EBITDA Margins | B37: =B36/B18 -> 0.096937593 | C37: =C36/C18 -> 0.10148112 | D37: =D36/D18 -> 0.096646014 | E37: =E36/E18 -> 0.096611236 | F37: =F36/F18 -> 0.10966127 | G37: =G36/G18 -> 0.11261777 | H37: =H36/H18 -> 0.12473888 | I37: =I36/I18 -> 0.11538411 | ... AD37: =AD36/AD18 -> 0.14323668 | AH37: =AH36/AH18 -> 0.056264233 | AI37: =AI36/AI18 -> 0.036707748 | AJ37: =AJ36/AJ18 -> 0.031979369 | AK37: =AK36/AK18 -> 0.054091981 | AL37: =AL36/AL18 -> 0.061605231 | AM37: =AM36/AM18 -> 0.059029061 | AN37: =AN36/AN18 -> 0.067817067 | AO37: =AO36/AO18 -> 0.068785529 | ... CZ37: =CZ36/CZ18 -> 0.14286647 | DC37: #DIV/0!
A38: EBITDA YOY% | C38: =+IF(B36<0,1-C36/B36,C36/B36-1) -> 0.18170825 | D38: =+IF(C36<0,1-D36/C36,D36/C36-1) -> 0.18935828 | E38: =+IF(D36<0,1-E36/D36,E36/D36-1) -> 0.5387324 | F38: =+IF(E36<0,1-F36/E36,F36/E36-1) -> 0.48803712 | G38: =+IF(F36<0,1-G36/F36,G36/F36-1) -> 0.48132302 | H38: =+IF(G36<0,1-H36/G36,H36/G36-1) -> 0.53686935 | I38: =+IF(H36<0,1-I36/H36,I36/H36-1) -> 0.066434657 | J38: =+IF(I36<0,1-J36/I36,J36/I36-1) -> -0.30575313 | ... AD38: =+IF(AC36<0,1-AD36/AC36,AD36/AC36-1) -> 0.17384262 | AL38: =+IF(AH36<0,1-AL36/AH36,AL36/AH36-1) -> 0.017831871 | AM38: =+IF(AI36<0,1-AM36/AI36,AM36/AI36-1) -> 0.58788974 | AN38: =+IF(AJ36<0,1-AN36/AJ36,AN36/AJ36-1) -> 1.2444812 | AO38: =+IF(AK36<0,1-AO36/AK36,AO36/AK36-1) -> 0.17319895 | AP38: =+IF(AL36<0,1-AP36/AL36,AP36/AL36-1) -> 0.16620319 | AQ38: =+IF(AM36<0,1-AQ36/AM36,AQ36/AM36-1) -> 0.17748055 | AR38: =+IF(AN36<0,1-AR36/AN36,AR36/AN36-1) -> 0.20453633 | AS38: =+IF(AO36<0,1-AS36/AO36,AS36/AO36-1) -> 0.14222081 | ... CK38: =+IF(CG36<0,1-CK36/CG36,CK36/CG36-1) -> -0.27019299 | CL38: =+CL36/CH36-1 -> 0.27680143 | CM38: =+CM36/CI36-1 -> 0.098716213 | CN38: =+CN36/CJ36-1 -> -0.095676159 | CO38: =+CO36/CK36-1 -> 0.43422295 | CP38: =+CP36/CL36-1 -> 0.25390623 | CQ38: =+CQ36/CM36-1 -> 0.2020239 | CR38: =+CR36/CN36-1 -> 0.19761372 | CS38: =+CS36/CO36-1 -> 0.13408612 | ... CZ38: =+CZ36/CV36-1 -> 0.20056036 | DC38: #DIV/0!
A39: EBITDA QOQ% | AI39: =+IF(AH36<0,1-AI36/AH36,AI36/AH36-1) -> -0.37362015 | AJ39: =+IF(AI36<0,1-AJ36/AI36,AJ36/AI36-1) -> 0.0030125019 | AK39: =+IF(AJ36<0,1-AK36/AJ36,AK36/AJ36-1) -> 0.60925064 | AL39: =+IF(AK36<0,1-AL36/AK36,AL36/AK36-1) -> 0.006718925 | AM39: =+IF(AL36<0,1-AM36/AL36,AM36/AL36-1) -> -0.022803115 | AN39: =+IF(AM36<0,1-AN36/AM36,AN36/AM36-1) -> 0.41775754 | AO39: =+IF(AN36<0,1-AO36/AN36,AO36/AN36-1) -> -0.15883849 | AP39: =+IF(AO36<0,1-AP36/AO36,AP36/AO36-1) -> 0.00071587655 | ... CH39: =+IF(CG36<0,1-CH36/CG36,CH36/CG36-1) -> -0.26002502 | CI39: =+IF(CH36>1,CI36/CH36-1,1-CI36/CH36) -> 0.2084088 | CJ39: =+IF(CI36>1,CJ36/CI36-1,1-CJ36/CI36) -> 0.22342573 | CK39: =+IF(CJ36>1,CK36/CJ36-1,1-CK36/CJ36) -> -0.33288685 | CL39: =+CL36/CK36-1 -> 0.29459036 | CM39: =+CM36/CL36-1 -> 0.039862825 | CN39: =+CN36/CM36-1 -> 0.0069688967 | CO39: =+CO36/CN36-1 -> 0.058015888 | CP39: =+CP36/CO36-1 -> 0.13182885 | CQ39: =+CQ36/CP36-1 -> -0.0031631223 | CR39: =+CR36/CQ36-1 -> 0.0032743694 | CS39: =+CS36/CR36-1 -> 0.0018932769 | ... CZ39: =+CZ36/CY36-1 -> 0.00081017802
A40: Depreciation | B40: ='Annual Raw'!C27 -> 18.2483 | C40: ='Annual Raw'!D27 -> 18.3223 | D40: ='Annual Raw'!E27 -> 18.435 | E40: ='Annual Raw'!F27 -> 20.3597 | F40: ='Annual Raw'!G27 -> 23.1407 | G40: ='Annual Raw'!H27 -> 26.4675 | H40: ='Annual Raw'!I27 -> 32.4057 | I40: ='Annual Raw'!J27 -> 36.6805 | ... Z40: ='Annual Raw'!AA27 -> 145.53 | AA40: =+SUM(CK40:CN40) -> 163.75452 | AB40: =+SUM(CO40:CR40) -> 161.58798 | AC40: =+SUM(CS40:CV40) -> 161.32508 | AD40: =SUM(CW40:CZ40) -> 161.1057 | AH40: ='QTR Raw'!C28 -> 23.13 | AI40: ='QTR Raw'!D28 -> 24.03 | AJ40: ='QTR Raw'!E28 -> 24.59 | AK40: ='QTR Raw'!F28 -> 24.63 | AL40: ='QTR Raw'!G28 -> 25.95 | AM40: ='QTR Raw'!H28 -> 25.73 | AN40: ='QTR Raw'!I28 -> 27 | AO40: ='QTR Raw'!J28 -> 27.41 | ... CI40: ='QTR Raw'!BD28 -> 36.59 | CJ40: 39.64 | CK40: ='QTR Raw'!BF28 -> 42.36 | CL40: =CL41*CK142 -> 40.486024 | CM40: =CM41*CL142 -> 40.464523 | CN40: =CN41*CM142 -> 40.443972 | CO40: =CO41*CN142 -> 40.424331 | CP40: =CP41*CO142 -> 40.405559 | CQ40: =CQ41*CP142 -> 40.387618 | CR40: =CR41*CQ142 -> 40.37047 | CS40: =CS41*CR142 -> 40.35408 | ... CZ40: =CZ41*CY142 -> 40.257956 | DC40: 0
A41: Depreciation % of Net Block | B41: =+B40/B142 -> 0.11681058 | C41: =+C40/C142 -> 0.12736954 | D41: =+D40/D142 -> 0.1154104 | E41: =+E40/E142 -> 0.10715367 | F41: =+F40/F142 -> 0.10209383 | G41: =+G40/G142 -> 0.086165052 | H41: =+H40/H142 -> 0.092080011 | I41: =+I40/I142 -> 0.067201019 | ... AD41: =+AD40/AD142 -> 0.17693094 | AH41: =+AH40/AG142 -> #DIV/0! | AI41: =+AI40/AH142 -> #DIV/0! | AJ41: =+AJ40/AI142 -> -1.0233042 | AK41: =+AK40/AJ142 -> 0.018233639 | AL41: =+AL40/AK142 -> 0.019567627 | AM41: =+AM40/AL142 -> 0.018284277 | AN41: =+AN40/AM142 -> 0.019544115 | AO41: =+AO40/AN142 -> 0.01904795 | ... CI41: =+CI40/CH142 -> 0.035395405 | CJ41: =CI41 -> 0.035395405 | CK41: =+CK40/CJ142 -> 0.044239285 | CL41: =+CK41 -> 0.044239285 | CM41: =+CL41 -> 0.044239285 | CN41: =+CM41 -> 0.044239285 | CO41: =+CN41 -> 0.044239285 | CP41: =+CO41 -> 0.044239285 | CQ41: =+CP41 -> 0.044239285 | CR41: =+CQ41 -> 0.044239285 | CS41: =+CR41 -> 0.044239285 | ... CZ41: =+CY41 -> 0.044239285 | DC41: #DIV/0!
A42: EBIT | B42: =B36-B40 -> 82.7218 | C42: =C36-C40 -> 100.9949 | D42: =D36-D40 -> 123.4759 | E42: =E36-E40 -> 198.0032 | F42: =F36-F40 -> 301.7914 | G42: =G36-G40 -> 454.8619 | H42: =H36-H40 -> 707.3347 | I42: =I36-I40 -> 752.2043 | ... AD42: =AD36-AD40 -> 3082.5854 | AH42: =AH36-AH40 -> 82.86 | AI42: =AI36-AI40 -> 42.36 | AJ42: =AJ36-AJ40 -> 42 | AK42: =AK36-AK40 -> 82.53 | AL42: =AL36-AL40 -> 81.93 | AM42: =AM36-AM40 -> 79.69 | AN42: =AN36-AN40 -> 122.46 | AO42: =AO36-AO40 -> 98.31 | ... CZ42: =CZ36-CZ40 -> 779.23796 | DC42: 0
A43: Other Income | B43: ='Annual Raw'!C23 -> 14.5845 | C43: ='Annual Raw'!D23 -> 27.8675 | D43: ='Annual Raw'!E23 -> 34.6994 | E43: ='Annual Raw'!F23 -> 45.5203 | F43: ='Annual Raw'!G23 -> 51.0857 | G43: ='Annual Raw'!H23 -> 78.4399 | H43: ='Annual Raw'!I23 -> 71.0454 | I43: ='Annual Raw'!J23 -> 130.4192 | ... Z43: ='Annual Raw'!AA23 -> 385.26 | AA43: =+SUM(CK43:CN43) -> 99.64 | AB43: =+SUM(CO43:CR43) -> 0 | AC43: =+SUM(CS43:CV43) -> 0 | AD43: =SUM(CW43:CZ43) -> 0 | AH43: ='QTR Raw'!C23 -> 1.42 | AI43: ='QTR Raw'!D23 -> 0.95 | AJ43: ='QTR Raw'!E23 -> 2.82 | AK43: ='QTR Raw'!F23 -> 1.54 | AL43: ='QTR Raw'!G23 -> 3.84 | AM43: ='QTR Raw'!H23 -> 0.92 | AN43: ='QTR Raw'!I23 -> 0.69 | AO43: ='QTR Raw'!J23 -> 1.13 | ... CI43: ='QTR Raw'!BD23 -> 83.95 | CJ43: 76.33 | CK43: ='QTR Raw'!BF23 -> 99.64 | DC43: 0
A44: Interest | B44: ='Annual Raw'!C25 -> 12.2274 | C44: ='Annual Raw'!D25 -> 5.8942 | D44: ='Annual Raw'!E25 -> 5.2826 | E44: ='Annual Raw'!F25 -> 7.0035 | F44: ='Annual Raw'!G25 -> 13.4001 | G44: ='Annual Raw'!H25 -> 10.0956 | H44: ='Annual Raw'!I25 -> 21.9232 | I44: ='Annual Raw'!J25 -> 49.3795 | ... Z44: ='Annual Raw'!AA25 -> 19.89 | AA44: =+SUM(CK44:CN44) -> -348.16173 | AB44: =+SUM(CO44:CR44) -> -560.27913 | AC44: =+SUM(CS44:CV44) -> -685.14545 | AD44: =SUM(CW44:CZ44) -> -823.73665 | AH44: ='QTR Raw'!C25 -> 7.65 | AI44: ='QTR Raw'!D25 -> 11.72 | AJ44: ='QTR Raw'!E25 -> 18.47 | AK44: ='QTR Raw'!F25 -> 19.75 | AL44: ='QTR Raw'!G25 -> 25.6 | AM44: ='QTR Raw'!H25 -> 26.99 | AN44: ='QTR Raw'!I25 -> 28.79 | AO44: ='QTR Raw'!J25 -> 22.07 | ... CI44: ='QTR Raw'!BD25 -> 5.64 | CJ44: 5.35 | CK44: ='QTR Raw'!BF25 -> 3.81 | CL44: =CL45*CK176 -> -112.05587 | CM44: =CM45*CL176 -> -116.74354 | CN44: =CN45*CM176 -> -123.17232 | CO44: =CO45*CN176 -> -129.72542 | CP44: =CP45*CO176 -> -136.25287 | CQ44: =CQ45*CP176 -> -143.0063 | CR44: =CR45*CQ176 -> -151.29455 | CS44: =CS45*CR176 -> -159.56827 | ... CZ44: =CZ45*CY176 -> -220.52766 | DC44: 0
A45: Interest % of Debt | B45: =+B44/B136 -> 1.1325127 | C45: =+C44/C136 -> 0.47649922 | D45: =+D44/D136 -> 0.52281747 | E45: =+E44/E136 -> 4.6902625 | F45: =+F44/F136 -> 4.914402 | G45: =+G44/G136 -> 6.5314097 | H45: =+H44/H136 -> 38.733569 | I45: =+I44/I136 -> 2444.5297 | ... AD45: =+AD44/AD136 -> #DIV/0! | AH45: =(AH44-AH43)/AG176 -> #DIV/0! | AI45: =(AI44-AI43)/AH176 -> #DIV/0! | AJ45: =(AJ44-AJ43)/AI176 -> -0.34471366 | AK45: =(AK44-AK43)/AJ176 -> 0.075635488 | AL45: =(AL44-AL43)/AK176 -> 0.21311662 | AM45: =(AM44-AM43)/AL176 -> 0.041849937 | AN45: =(AN44-AN43)/AM176 -> 0.04716603 | AO45: =(AO44-AO43)/AN176 -> 0.069006426 | ... CK45: =(CK44-CK43)/CJ176 -> 0.015727336 | CL45: 0.014 | CM45: =+CL45 -> 0.014 | CN45: =+CM45 -> 0.014 | CO45: =+CN45 -> 0.014 | CP45: =+CO45 -> 0.014 | CQ45: =+CP45 -> 0.014 | CR45: =+CQ45 -> 0.014 | CS45: =+CR45 -> 0.014 | CT45: =+CS45 -> 0.014 | ... CZ45: =+CY45 -> 0.014 | DC45: #DIV/0!
A46: PBT | B46: =B42+B43-B44 -> 85.0789 | C46: =C42+C43-C44 -> 122.9682 | D46: =D42+D43-D44 -> 152.8927 | E46: =E42+E43-E44 -> 236.52 | F46: =F42+F43-F44 -> 339.477 | G46: =G42+G43-G44 -> 523.2062 | H46: =H42+H43-H44 -> 756.4569 | I46: =I42+I43-I44 -> 833.244 | ... AD46: =AD42+AD43-AD44 -> 3906.3221 | AH46: =AH42+AH43-AH44 -> 76.63 | AI46: =AI42+AI43-AI44 -> 31.59 | AJ46: =AJ42+AJ43-AJ44 -> 26.35 | AK46: =AK42+AK43-AK44 -> 64.32 | AL46: =AL42+AL43-AL44 -> 60.17 | AM46: =AM42+AM43-AM44 -> 53.62 | AN46: =AN42+AN43-AN44 -> 94.36 | AO46: =AO42+AO43-AO44 -> 77.37 | ... CZ46: =CZ42+CZ43-CZ44 -> 999.76562 | DC46: 0
A47: Tax | B47: ='Annual Raw'!C30 -> 19.753 | C47: ='Annual Raw'!D30 -> 41.62 | D47: ='Annual Raw'!E30 -> 52 | E47: ='Annual Raw'!F30 -> 86 | F47: ='Annual Raw'!G30 -> 120.8 | G47: ='Annual Raw'!H30 -> 182.9 | H47: ='Annual Raw'!I30 -> 264.7879 | I47: ='Annual Raw'!J30 -> 285.831 | ... Z47: ='Annual Raw'!AA30 -> 560.54 | AA47: =+SUM(CK47:CN47) -> 575.06937 | AB47: =+SUM(CO47:CR47) -> 730.73831 | AC47: =+SUM(CS47:CV47) -> 807.40301 | AD47: =SUM(CW47:CZ47) -> 959.30286 | AH47: ='QTR Raw'!C29 -> 25 | AI47: ='QTR Raw'!D29 -> 10.22 | AJ47: ='QTR Raw'!E29 -> 9.58 | AK47: ='QTR Raw'!F29 -> 21.26 | AL47: ='QTR Raw'!G29 -> 20.54 | AM47: ='QTR Raw'!H29 -> 18.01 | AN47: ='QTR Raw'!I29 -> 35.77 | AO47: ='QTR Raw'!J29 -> 25.69 | ... CI47: ='QTR Raw'!BD29 -> 133.23 | CJ47: 143.27 | CK47: ='QTR Raw'!BF29 -> 119.96 | CL47: =+CL46*CL48 -> 147.89527 | CM47: =+CM46*CM48 -> 152.52477 | CN47: =+CN46*CN48 -> 154.68933 | CO47: =+CO46*CO48 -> 167.54737 | CP47: =+CP46*CP48 -> 186.15198 | CQ47: =+CQ46*CQ48 -> 187.09772 | CR47: =+CR46*CR48 -> 189.94124 | CS47: =+CS46*CS48 -> 192.74022 | ... CZ47: =+CZ46*CZ48 -> 245.5226 | DC47: 0
A48: Tax Rate % | B48: =B47/B46 -> 0.23217272 | C48: =C47/C46 -> 0.33846149 | D48: =D47/D46 -> 0.3401078 | E48: =E47/E46 -> 0.36360561 | F48: =F47/F46 -> 0.35584149 | G48: =G47/G46 -> 0.34957537 | H48: =H47/H46 -> 0.35003699 | I48: =I47/I46 -> 0.34303397 | ... AD48: =AD47/AD46 -> 0.245577 | AH48: =AH47/AH46 -> 0.32624299 | AI48: =AI47/AI46 -> 0.3235201 | AJ48: =AJ47/AJ46 -> 0.36356736 | AK48: =AK47/AK46 -> 0.33053483 | AL48: =AL47/AL46 -> 0.34136613 | AM48: =AM47/AM46 -> 0.33588213 | AN48: =AN47/AN46 -> 0.37908012 | AO48: =AO47/AO46 -> 0.33204084 | ... CK48: =CK47/CK46 -> 0.25972676 | CL48: =AVERAGE(CH48:CK48) -> 0.24637691 | CM48: =AVERAGE(CI48:CL48) -> 0.24362426 | CN48: =AVERAGE(CJ48:CM48) -> 0.24308984 | CO48: =AVERAGE(CK48:CN48) -> 0.24820444 | CP48: =AVERAGE(CL48:CO48) -> 0.24532386 | CQ48: =AVERAGE(CM48:CP48) -> 0.2450606 | CR48: =AVERAGE(CN48:CQ48) -> 0.24541969 | CS48: =AVERAGE(CO48:CR48) -> 0.24600215 | ... CZ48: =AVERAGE(CV48:CY48) -> 0.24558016 | DC48: #DIV/0!
A49: PAT | B49: =B46-B47 -> 65.3259 | C49: =C46-C47 -> 81.3482 | D49: =D46-D47 -> 100.8927 | E49: =E46-E47 -> 150.52 | F49: =F46-F47 -> 218.677 | G49: =G46-G47 -> 340.3062 | H49: =H46-H47 -> 491.669 | I49: =I46-I47 -> 547.413 | ... AD49: =AD46-AD47 -> 2947.0192 | AH49: =AH46-AH47 -> 51.63 | AI49: =AI46-AI47 -> 21.37 | AJ49: =AJ46-AJ47 -> 16.77 | AK49: =AK46-AK47 -> 43.06 | AL49: =AL46-AL47 -> 39.63 | AM49: =AM46-AM47 -> 35.61 | AN49: =AN46-AN47 -> 58.59 | AO49: =AO46-AO47 -> 51.68 | ... CZ49: =CZ46-CZ47 -> 754.24302 | DC49: 0
A50: PAT % | B50: =+B49/B18 -> 0.062716938 | C50: =+C49/C18 -> 0.069187901 | D50: =+D49/D18 -> 0.068711264 | E50: =+E49/E18 -> 0.066595211 | F50: =+F49/F18 -> 0.073801255 | G50: =+G49/G18 -> 0.079622241 | H50: =+H49/H18 -> 0.082907788 | I50: =+I49/I18 -> 0.080065888 | ... AD50: =+AD49/AD18 -> 0.13013608 | AH50: =+AH49/AH18 -> 0.027407514 | AI50: =+AI49/AI18 -> 0.011815704 | AJ50: =+AJ49/AJ18 -> 0.0080536719 | AK50: =+AK49/AK18 -> 0.021735729 | AL50: =+AL49/AL18 -> 0.022630843 | AM50: =+AM49/AM18 -> 0.019939526 | AN50: =+AN49/AN18 -> 0.026585053 | AO50: =+AO49/AO18 -> 0.028275821 | ... CZ50: =+CZ49/CZ18 -> 0.13149064 | DC50: #DIV/0!
A51: PAT YOY% | C51: =+IF(B49<0,1-C49/B49,C49/B49-1) -> 0.24526719 | D51: =+IF(C49<0,1-D49/C49,D49/C49-1) -> 0.24025731 | E51: =+IF(D49<0,1-E49/D49,E49/D49-1) -> 0.49188197 | F51: =+IF(E49<0,1-F49/E49,F49/E49-1) -> 0.45281026 | G51: =+IF(F49<0,1-G49/F49,G49/F49-1) -> 0.55620481 | H51: =+IF(G49<0,1-H49/G49,H49/G49-1) -> 0.44478414 | I51: =+IF(H49<0,1-I49/H49,I49/H49-1) -> 0.11337709 | J51: =+IF(I49<0,1-J49/I49,J49/I49-1) -> -0.35215441 | ... AD51: =+IF(AC49<0,1-AD49/AC49,AD49/AC49-1) -> 0.18844482 | AL51: =+IF(AH49<0,1-AL49/AH49,AL49/AH49-1) -> -0.23242301 | AM51: =+IF(AI49<0,1-AM49/AI49,AM49/AI49-1) -> 0.6663547 | AN51: =+IF(AJ49<0,1-AN49/AJ49,AN49/AJ49-1) -> 2.4937388 | AO51: =+IF(AK49<0,1-AO49/AK49,AO49/AK49-1) -> 0.20018579 | AP51: =+IF(AL49<0,1-AP49/AL49,AP49/AL49-1) -> 0.20338128 | AQ51: =+IF(AM49<0,1-AQ49/AM49,AQ49/AM49-1) -> 0.26312833 | AR51: =+IF(AN49<0,1-AR49/AN49,AR49/AN49-1) -> 0.4364226 | AS51: =+IF(AO49<0,1-AS49/AO49,AS49/AO49-1) -> 0.050503096 | ... CK51: =+IF(CG49<0,1-CK49/CG49,CK49/CG49-1) -> -0.25234524 | CL51: =+CL49/CH49-1 -> 0.28489344 | CM51: =+CM49/CI49-1 -> 0.15814138 | CN51: =+CN49/CJ49-1 -> -0.037186611 | CO51: =+CO49/CK49-1 -> 0.48428058 | CP51: =+CP49/CL49-1 -> 0.26584351 | CQ51: =+CQ49/CM49-1 -> 0.21716553 | CR51: =+CR49/CN49-1 -> 0.212488 | CS51: =+CS49/CO49-1 -> 0.16406105 | ... CZ51: =+CZ49/CV49-1 -> 0.21021664 | DC51: #DIV/0!
A52: PAT QOQ% | AI52: =+IF(AH49<0,1-AI49/AH49,AI49/AH49-1) -> -0.58609336 | AJ52: =+IF(AI49<0,1-AJ49/AI49,AJ49/AI49-1) -> -0.21525503 | AK52: =+IF(AJ49<0,1-AK49/AJ49,AK49/AJ49-1) -> 1.5676804 | AL52: =+IF(AK49<0,1-AL49/AK49,AL49/AK49-1) -> -0.079656294 | AM52: =+IF(AL49<0,1-AM49/AL49,AM49/AL49-1) -> -0.1014383 | AN52: =+IF(AM49<0,1-AN49/AM49,AN49/AM49-1) -> 0.64532435 | AO52: =+IF(AN49<0,1-AO49/AN49,AO49/AN49-1) -> -0.11793821 | AP52: =+IF(AO49<0,1-AP49/AO49,AP49/AO49-1) -> -0.077205882 | ... CK52: =+IF(CJ49<0,1-CK49/CJ49,CK49/CJ49-1) -> -0.3165354 | CL52: =+CL49/CK49-1 -> 0.32311217 | CM52: =+CM49/CL49-1 -> 0.046764489 | CN52: =+CN49/CM49-1 -> 0.017139339 | CO52: =+CO49/CN49-1 -> 0.053634319 | CP52: =+CP49/CO49-1 -> 0.12839377 | CQ52: =+CQ49/CP49-1 -> 0.006511192 | CR52: =+CR49/CQ49-1 -> 0.013230501 | CS52: =+CS49/CR49-1 -> 0.011552007 | ... CZ52: =+CZ49/CY49-1 -> 0.011469958
A53: Minority Interest | B53: ='Annual Raw'!C32 -> 0 | C53: ='Annual Raw'!D32 -> 0 | D53: ='Annual Raw'!E32 -> 0 | E53: ='Annual Raw'!F32 -> 0 | F53: ='Annual Raw'!G32 -> 0 | G53: ='Annual Raw'!H32 -> 0 | H53: ='Annual Raw'!I32 -> 0 | I53: ='Annual Raw'!J32 -> 0 | ... Z53: ='Annual Raw'!AA32 -> 0 | AA53: =+SUM(CK53:CN53) -> 0 | AB53: =+SUM(CO53:CR53) -> 0 | AC53: =+SUM(CS53:CV53) -> 0 | AD53: =SUM(CW53:CZ53) -> 0 | AH53: ='QTR Raw'!C34 -> 0 | AI53: ='QTR Raw'!D34 -> 0 | AJ53: ='QTR Raw'!E34 -> 0 | AK53: ='QTR Raw'!F34 -> 0 | AL53: ='QTR Raw'!G34 -> 0 | AM53: ='QTR Raw'!H34 -> 0 | AN53: ='QTR Raw'!I34 -> 0 | AO53: ='QTR Raw'!J34 -> 0 | ... CI53: ='QTR Raw'!BD34 -> 0 | CJ53: =+CI53 -> 0 | CK53: ='QTR Raw'!BF34 -> 0 | CL53: =+CK53 -> 0 | CM53: =+CL53 -> 0 | CN53: =+CM53 -> 0 | CO53: =+CN53 -> 0 | CP53: =+CO53 -> 0 | CQ53: =+CP53 -> 0 | CR53: =+CQ53 -> 0 | CS53: =+CR53 -> 0 | ... CZ53: =+CY53 -> 0 | DC53: 0
A54: Share of Associate | B54: ='Annual Raw'!C33+'Annual Raw'!C28 -> 0 | C54: ='Annual Raw'!D33+'Annual Raw'!D28 -> 0 | D54: ='Annual Raw'!E33+'Annual Raw'!E28 -> 0 | E54: ='Annual Raw'!F33+'Annual Raw'!F28 -> 0 | F54: ='Annual Raw'!G33+'Annual Raw'!G28 -> 0 | G54: ='Annual Raw'!H33+'Annual Raw'!H28 -> 0 | H54: ='Annual Raw'!I33+'Annual Raw'!I28 -> 0 | I54: ='Annual Raw'!J33+'Annual Raw'!J28 -> 0 | ... Z54: ='Annual Raw'!AA33+'Annual Raw'!AA28 -> 0 | AA54: =+SUM(CK54:CN54) -> 0 | AB54: =+SUM(CO54:CR54) -> 0 | AC54: =+SUM(CS54:CV54) -> 0 | AD54: =SUM(CW54:CZ54) -> 0 | AH54: ='QTR Raw'!C35 -> 0 | AI54: ='QTR Raw'!D35 -> 0 | AJ54: ='QTR Raw'!E35 -> 0 | AK54: ='QTR Raw'!F35 -> 0 | AL54: ='QTR Raw'!G35 -> 0 | AM54: ='QTR Raw'!H35 -> 0 | AN54: ='QTR Raw'!I35 -> 0 | AO54: ='QTR Raw'!J35 -> 0 | ... CI54: ='QTR Raw'!BD35 -> 0 | CJ54: =+CI54 -> 0 | CK54: ='QTR Raw'!BF35 -> 0 | CL54: =+CK54 -> 0 | CM54: =+CL54 -> 0 | CN54: =+CM54 -> 0 | CO54: =+CN54 -> 0 | CP54: =+CO54 -> 0 | CQ54: =+CP54 -> 0 | CR54: =+CQ54 -> 0 | CS54: =+CR54 -> 0 | ... CZ54: =+CY54 -> 0 | DC54: 0
A55: Exceptional Income / Expenses | B55: ='Annual Raw'!C29+'Annual Raw'!C31+'Annual Raw'!C34+'Annual Raw'!C36 -> 0 | C55: ='Annual Raw'!D29+'Annual Raw'!D31+'Annual Raw'!D34+'Annual Raw'!D36 -> 15.8259 | D55: ='Annual Raw'!E29+'Annual Raw'!E31+'Annual Raw'!E34+'Annual Raw'!E36 -> 23.3008 | E55: ='Annual Raw'!F29+'Annual Raw'!F31+'Annual Raw'!F34+'Annual Raw'!F36 -> 3.7991 | F55: ='Annual Raw'!G29+'Annual Raw'!G31+'Annual Raw'!G34+'Annual Raw'!G36 -> 0 | G55: ='Annual Raw'!H29+'Annual Raw'!H31+'Annual Raw'!H34+'Annual Raw'!H36 -> 0 | H55: ='Annual Raw'!I29+'Annual Raw'!I31+'Annual Raw'!I34+'Annual Raw'!I36 -> 0 | I55: ='Annual Raw'!J29+'Annual Raw'!J31+'Annual Raw'!J34+'Annual Raw'!J36 -> 0 | ... Z55: ='Annual Raw'!AA29+'Annual Raw'!AA31+'Annual Raw'!AA34+'Annual Raw'!AA36 -> -1.14 | AA55: =+SUM(CK55:CN55) -> 1441.74 | AB55: =+SUM(CO55:CR55) -> 0 | AC55: =+SUM(CS55:CV55) -> 0 | AD55: =SUM(CW55:CZ55) -> 0 | AH55: ='QTR Raw'!C26+'QTR Raw'!C31+'QTR Raw'!C32+'QTR Raw'!C33+'QTR Raw'!C36+'QTR Raw'!C37+'QTR Raw'!C39 -> 0 | AI55: ='QTR Raw'!D26+'QTR Raw'!D31+'QTR Raw'!D32+'QTR Raw'!D33+'QTR Raw'!D36+'QTR Raw'!D37+'QTR Raw'!D39 -> 0 | AJ55: ='QTR Raw'!E26+'QTR Raw'!E31+'QTR Raw'!E32+'QTR Raw'!E33+'QTR Raw'!E36+'QTR Raw'!E37+'QTR Raw'!E39 -> 0 | AK55: ='QTR Raw'!F26+'QTR Raw'!F31+'QTR Raw'!F32+'QTR Raw'!F33+'QTR Raw'!F36+'QTR Raw'!F37+'QTR Raw'!F39 -> 0 | AL55: ='QTR Raw'!G26+'QTR Raw'!G31+'QTR Raw'!G32+'QTR Raw'!G33+'QTR Raw'!G36+'QTR Raw'!G37+'QTR Raw'!G39 -> 0 | AM55: ='QTR Raw'!H26+'QTR Raw'!H31+'QTR Raw'!H32+'QTR Raw'!H33+'QTR Raw'!H36+'QTR Raw'!H37+'QTR Raw'!H39 -> 2.42 | AN55: ='QTR Raw'!I26+'QTR Raw'!I31+'QTR Raw'!I32+'QTR Raw'!I33+'QTR Raw'!I36+'QTR Raw'!I37+'QTR Raw'!I39 -> 0 | AO55: ='QTR Raw'!J26+'QTR Raw'!J31+'QTR Raw'!J32+'QTR Raw'!J33+'QTR Raw'!J36+'QTR Raw'!J37+'QTR Raw'!J39 -> 0 | ... CI55: ='QTR Raw'!BD26+'QTR Raw'!BD31+'QTR Raw'!BD32+'QTR Raw'!BD33+'QTR Raw'!BD36+'QTR Raw'!BD37+'QTR Raw'!BD39 -> 0.16 | CJ55: =-1.47-65.94 -> -67.41 | CK55: ='QTR Raw'!BF26+'QTR Raw'!BF31+'QTR Raw'!BF32+'QTR Raw'!BF33+'QTR Raw'!BF36+'QTR Raw'!BF37+'QTR Raw'!BF39 -> 1441.74 | DC55: 0
A56: Consolidated Net Profit | B56: =B49+B53+B54+B55 -> 65.3259 | C56: =C49+C53+C54+C55 -> 97.1741 | D56: =D49+D53+D54+D55 -> 124.1935 | E56: =E49+E53+E54+E55 -> 154.3191 | F56: =F49+F53+F54+F55 -> 218.677 | G56: =G49+G53+G54+G55 -> 340.3062 | H56: =H49+H53+H54+H55 -> 491.669 | I56: =I49+I53+I54+I55 -> 547.413 | ... AD56: =AD49+AD53+AD54+AD55 -> 2947.0192 | AH56: =AH49+AH53+AH54+AH55 -> 51.63 | AI56: =AI49+AI53+AI54+AI55 -> 21.37 | AJ56: =AJ49+AJ53+AJ54+AJ55 -> 16.77 | AK56: =AK49+AK53+AK54+AK55 -> 43.06 | AL56: =AL49+AL53+AL54+AL55 -> 39.63 | AM56: =AM49+AM53+AM54+AM55 -> 38.03 | AN56: =AN49+AN53+AN54+AN55 -> 58.59 | AO56: =AO49+AO53+AO54+AO55 -> 51.68 | ... CZ56: =CZ49+CZ53+CZ54+CZ55 -> 754.24302 | DC56: 0
A57: Profit & Loss- Annual (End)
A59: Ace - PAT | B59: ='Annual Raw'!C35 -> 65.3259 | C59: ='Annual Raw'!D35 -> 97.1741 | D59: ='Annual Raw'!E35 -> 124.1935 | E59: ='Annual Raw'!F35 -> 154.3191 | F59: ='Annual Raw'!G35 -> 218.677 | G59: ='Annual Raw'!H35 -> 340.3062 | H59: ='Annual Raw'!I35 -> 491.669 | I59: ='Annual Raw'!J35 -> 547.413 | ... Z59: ='Annual Raw'!AA35 -> 1668.26 | AA59: =+AA56 -> 3191.2332 | AB59: =+AB56 -> 2240.5203 | AC59: =+AC56 -> 2479.7274 | AD59: =+AD56 -> 2947.0192 | AH59: ='QTR Raw'!C42 -> 51.63 | AI59: ='QTR Raw'!D42 -> 21.37 | AJ59: ='QTR Raw'!E42 -> 16.77 | AK59: ='QTR Raw'!F42 -> 43.06 | AL59: ='QTR Raw'!G42 -> 39.63 | AM59: ='QTR Raw'!H42 -> 38.03 | AN59: ='QTR Raw'!I42 -> 58.59 | AO59: ='QTR Raw'!J42 -> 51.68 | ... CI59: ='QTR Raw'!BD42 -> 409.04 | CJ59: 432.85 | CK59: ='QTR Raw'!BF42 -> 1783.65 | DC59: 0
A60: Checksum - PAT | B60: =B59-B56 -> 1.1368684e-13 | C60: =C59-C56 -> 0 | D60: =D59-D56 -> 0 | E60: =E59-E56 -> 0 | F60: =F59-F56 -> 0 | G60: =G59-G56 -> 0 | H60: =H59-H56 -> -6.2527761e-13 | I60: =I59-I56 -> 0 | ... AD60: =AD59-AD56 -> 0 | AH60: =AH59-AH56 -> -1.2079227e-13 | AI60: =AI59-AI56 -> 2.3803182e-13 | AJ60: =AJ59-AJ56 -> -2.593481e-13 | AK60: =AK59-AK56 -> 0 | AL60: =AL59-AL56 -> -2.2026825e-13 | AM60: =AM59-AM56 -> -1.8474111e-13 | AN60: =AN59-AN56 -> 7.8159701e-14 | AO60: =AO59-AO56 -> 0 | ... CK60: =CK59-CK56 -> 0 | DC60: 0
A61: Ratios (Start)
A62: ROE (%) | B62: =(B56-B55)/B128 -> 0.14589897 | C62: =(C56-C55)/C128 -> 0.15882988 | D62: =(D56-D55)/D128 -> 0.16699845 | E62: =(E56-E55)/E128 -> 0.20771072 | F62: =(F56-F55)/F128 -> 0.24186512 | G62: =(G56-G55)/G128 -> 0.2845746 | H62: =(H56-H55)/H128 -> 0.30231544 | I62: =(I56-I55)/I128 -> 0.25834124 | ... AD62: =(AD56-AD55)/AD128 -> 0.17704012 | AK62: =(SUM(AH56:AK56)-SUM(AH55:AK55))/AK128 -> 0.050224978 | AL62: =(SUM(AI56:AL56)-SUM(AI55:AL55))/AL128 -> 0.045463439 | AM62: =(SUM(AJ56:AM56)-SUM(AJ55:AM55))/AM128 -> 0.050104423 | AN62: =(SUM(AK56:AN56)-SUM(AK55:AN55))/AN128 -> 0.066063879 | AO62: =(SUM(AL56:AO56)-SUM(AL55:AO55))/AO128 -> 0.067971303 | AP62: =(SUM(AM56:AP56)-SUM(AM55:AP55))/AP128 -> 0.069706474 | AQ62: =(SUM(AN56:AQ56)-SUM(AN55:AQ55))/AQ128 -> 0.07191583 | AR62: =(SUM(AO56:AR56)-SUM(AO55:AR55))/AR128 -> 0.081263025 | ... CZ62: =(SUM(CW56:CZ56)-SUM(CW55:CZ55))/CZ128 -> 0.15597051 | DC62: #DIV/0!
A63: ROCE (%) | B63: =+B42/B137 -> 0.18040093 | C63: =+C42/C137 -> 0.19253932 | D63: =+D42/D137 -> 0.20101648 | E63: =+E42/E137 -> 0.2726735 | F63: =+F42/F137 -> 0.33278918 | G63: =+G42/G137 -> 0.37987861 | H63: =+H42/H137 -> 0.43477179 | I63: =+I42/I137 -> 0.35498525 | ... AD63: =+AD42/AD137 -> 0.18518416 | AK63: =+SUM(AH42:AK42)/AK137 -> 0.084023577 | AL63: =+SUM(AI42:AL42)/AL137 -> 0.072207551 | AM63: =+SUM(AJ42:AM42)/AM137 -> 0.082134256 | AN63: =+SUM(AK42:AN42)/AN137 -> 0.11117243 | AO63: =+SUM(AL42:AO42)/AO137 -> 0.11416842 | AP63: =+SUM(AM42:AP42)/AP137 -> 0.11113467 | AQ63: =+SUM(AN42:AQ42)/AQ137 -> 0.11419291 | AR63: =+SUM(AO42:AR42)/AR137 -> 0.13913699 | ... CZ63: =+SUM(CW42:CZ42)/CZ137 -> 0.16314533 | DC63: #DIV/0!
A64: Ratios (End)
A65: Checksum Of qtr to Annual
A66: Revenue - Checksum Of qtr to Annual | X66: =X18-SUM(BY18:CB18) -> 0 | Y66: =Y18-SUM(CC18:CF18) -> 0 | Z66: =Z18-SUM(CD18:CG18) -> 1084.71 | AA66: =AA18-SUM(CK18:CN18) -> 0 | AB66: =AB18-SUM(CO18:CR18) -> 0 | AC66: =AC18-SUM(CS18:CV18) -> 0 | AD66: =AD18-SUM(CW18:CZ18) -> 0 | DC66: 0
A67: GP - Checksum Of qtr to Annual | X67: =X24-SUM(BY24:CB24) -> 0 | Y67: =Y24-SUM(CC24:CF24) -> 0 | Z67: =Z24-SUM(CD24:CG24) -> 87.57 | AA67: =AA24-SUM(CK24:CN24) -> 0 | AB67: =AB24-SUM(CO24:CR24) -> 0 | AC67: =AC24-SUM(CS24:CV24) -> 0 | AD67: =AD24-SUM(CW24:CZ24) -> 0 | DC67: 0
A68: EBITDA - Checksum Of qtr to Annual | X68: =X36-SUM(BY36:CB36) -> 0 | Y68: =Y36-SUM(CC36:CF36) -> -8.77 | Z68: =Z36-SUM(CD36:CG36) -> -289.55 | AA68: =AA36-SUM(CK36:CN36) -> 0 | AB68: =AB36-SUM(CO36:CR36) -> 0 | AC68: =AC36-SUM(CS36:CV36) -> 0 | AD68: =AD36-SUM(CW36:CZ36) -> 0 | DC68: 0
A69: PAT - Checksum Of qtr to Annual | X69: =X49-SUM(BY49:CB49) -> 0 | Y69: =Y49-SUM(CC49:CF49) -> 0 | Z69: =Z49-SUM(CD49:CG49) -> -202.92 | AA69: =AA49-SUM(CK49:CN49) -> 0 | AB69: =AB49-SUM(CO49:CR49) -> 0 | AC69: =AC49-SUM(CS49:CV49) -> 0 | AD69: =AD49-SUM(CW49:CZ49) -> 0 | DC69: 0
A70: Valuation (Start)
A71: Eq | B71: ='Annual Raw'!C104 -> 42.3817 | C71: ='Annual Raw'!D104 -> 42.3817 | D71: ='Annual Raw'!E104 -> 42.3817 | E71: =+F71 -> 42.38 | F71: =+G71 -> 42.38 | G71: =+H71 -> 42.38 | H71: =+I71 -> 42.38 | I71: =+J71 -> 42.38 | J71: =+K71 -> 42.38 | K71: =+L71 -> 42.38 | L71: =+M71 -> 42.38 | ... Z71: =+AA71 -> 42.38 | AA71: =+CK71 -> 42.38 | AB71: =CR71 -> 42.38 | AC71: =CV71 -> 42.38 | AD71: =CZ71 -> 42.38 | AH71: =+AI71 -> 42.38 | AI71: =+AJ71 -> 42.38 | AJ71: =+AK71 -> 42.38 | AK71: =+AL71 -> 42.38 | AL71: =+AM71 -> 42.38 | AM71: =+AN71 -> 42.38 | AN71: =+AO71 -> 42.38 | AO71: =+AP71 -> 42.38 | ... CJ71: =+CK71 -> 42.38 | CK71: ='QTR Raw'!BF45 -> 42.38 | CL71: =+CK71 -> 42.38 | CM71: =+CL71 -> 42.38 | CN71: =+CM71 -> 42.38 | CO71: =+CN71 -> 42.38 | CP71: =+CO71 -> 42.38 | CQ71: =+CP71 -> 42.38 | CR71: =+CQ71 -> 42.38 | CS71: =+CR71 -> 42.38 | ... CZ71: =+CY71 -> 42.38 | DC71: 0
A72: FV | B72: ='Annual Raw'!C105 -> 10 | C72: ='Annual Raw'!D105 -> 10 | D72: ='Annual Raw'!E105 -> 10 | E72: =+F72 -> 2 | F72: =+G72 -> 2 | G72: =+H72 -> 2 | H72: =+I72 -> 2 | I72: =+J72 -> 2 | J72: =+K72 -> 2 | K72: =+L72 -> 2 | L72: =+M72 -> 2 | ... Z72: =+AA72 -> 2 | AA72: =+CK72 -> 2 | AB72: =CR72 -> 2 | AC72: =CV72 -> 2 | AD72: =CZ72 -> 2 | AH72: =AI72 -> 2 | AI72: =AJ72 -> 2 | AJ72: =AK72 -> 2 | AK72: =AL72 -> 2 | AL72: =AM72 -> 2 | AM72: =AN72 -> 2 | AN72: =AO72 -> 2 | AO72: =AP72 -> 2 | ... CJ72: =CK72 -> 2 | CK72: ='QTR Raw'!BF46 -> 2 | CL72: =+CK72 -> 2 | CM72: =+CL72 -> 2 | CN72: =+CM72 -> 2 | CO72: =+CN72 -> 2 | CP72: =+CO72 -> 2 | CQ72: =+CP72 -> 2 | CR72: =+CQ72 -> 2 | CS72: =+CR72 -> 2 | ... CZ72: =+CY72 -> 2 | DC72: 0
A73: No of share | B73: =B71/B72 -> 4.23817 | C73: =C71/C72 -> 4.23817 | D73: =D71/D72 -> 4.23817 | E73: =E71/E72 -> 21.19 | F73: =F71/F72 -> 21.19 | G73: =G71/G72 -> 21.19 | H73: =H71/H72 -> 21.19 | I73: =I71/I72 -> 21.19 | ... AD73: =AD71/AD72 -> 21.19 | AH73: =AH71/AH72 -> 21.19 | AI73: =AI71/AI72 -> 21.19 | AJ73: =AJ71/AJ72 -> 21.19 | AK73: =AK71/AK72 -> 21.19 | AL73: =AL71/AL72 -> 21.19 | AM73: =AM71/AM72 -> 21.19 | AN73: =AN71/AN72 -> 21.19 | AO73: =AO71/AO72 -> 21.19 | ... CZ73: =CZ71/CZ72 -> 21.19 | DC73: #DIV/0!
A74: EPS | B74: =(B56-B55)/B73 -> 15.413704 | C74: =(C56-C55)/C73 -> 19.194181 | D74: =(D56-D55)/D73 -> 23.805723 | E74: =(E56-E55)/E73 -> 7.1033506 | F74: =(F56-F55)/F73 -> 10.319821 | G74: =(G56-G55)/G73 -> 16.059755 | H74: =(H56-H55)/H73 -> 23.202879 | I74: =(I56-I55)/I73 -> 25.833554 | ... AD74: =(AD56-AD55)/AD73 -> 139.07594 | AH74: =(AH56-AH55)/AH73 -> 2.4365267 | AI74: =(AI56-AI55)/AI73 -> 1.0084946 | AJ74: =(AJ56-AJ55)/AJ73 -> 0.79141104 | AK74: =(AK56-AK55)/AK73 -> 2.0320906 | AL74: =(AL56-AL55)/AL73 -> 1.8702218 | AM74: =(AM56-AM55)/AM73 -> 1.6805097 | AN74: =(AN56-AN55)/AN73 -> 2.7649835 | AO74: =(AO56-AO55)/AO73 -> 2.4388863 | ... CZ74: =(CZ56-CZ55)/CZ73 -> 35.594291 | DC74: #DIV/0!
A75: DPS | B75: ='Annual Raw'!C110 -> 1 | C75: ='Annual Raw'!D110 -> 1.2 | D75: ='Annual Raw'!E110 -> 1.2 | E75: ='Annual Raw'!F110 -> 1.4 | F75: ='Annual Raw'!G110 -> 1.6 | G75: ='Annual Raw'!H110 -> 2 | H75: ='Annual Raw'!I110 -> 2.2 | I75: ='Annual Raw'!J110 -> 2.2 | ... Z75: ='Annual Raw'!AA110 -> 39.37 | DC75: 0
A76: DPS % of EPS | B76: =B75/B74 -> 0.06487733 | C76: =C75/C74 -> 0.062518949 | D76: =D75/D74 -> 0.050408047 | E76: =E75/E74 -> 0.19709009 | F76: =F75/F74 -> 0.15504145 | G76: =G75/G74 -> 0.1245349 | H76: =H75/H74 -> 0.094815821 | I76: =I75/I74 -> 0.085160564 | ... AD76: =AD75/AD74 -> 0 | DC76: #DIV/0!
A77: EPS TTM | B77: =+B74 -> 15.413704 | C77: =+C74 -> 19.194181 | D77: =+D74 -> 23.805723 | E77: =+E74 -> 7.1033506 | F77: =+F74 -> 10.319821 | G77: =+G74 -> 16.059755 | H77: =+H74 -> 23.202879 | I77: =+I74 -> 25.833554 | ... AD77: =+AD74 -> 139.07594 | AK77: =SUM(AH74:AK74) -> 6.2685229 | AL77: =SUM(AI74:AL74) -> 5.702218 | AM77: =SUM(AJ74:AM74) -> 6.3742331 | AN77: =SUM(AK74:AN74) -> 8.3478056 | AO77: =SUM(AL74:AO74) -> 8.7546012 | AP77: =SUM(AM74:AP74) -> 9.1349693 | AQ77: =SUM(AN74:AQ74) -> 9.577159 | AR77: =SUM(AO74:AR74) -> 10.78386 | ... CZ77: =SUM(CW74:CZ74) -> 139.07594 | DC77: #DIV/0!
A78: EPS Growth YoY % | C78: =+C77/B77-1 -> 0.24526719 | D78: =+D77/C77-1 -> 0.24025731 | E78: =+E77/D77-1 -> -0.70161164 | F78: =+F77/E77-1 -> 0.45281026 | G78: =+G77/F77-1 -> 0.55620481 | H78: =+H77/G77-1 -> 0.44478414 | I78: =+I77/H77-1 -> 0.11337709 | J78: =+J77/I77-1 -> -0.35215441 | ... AD78: =+AD77/AC77-1 -> 0.18844482 | AO78: =+IF(AK77<0,1-AO77/AK77,AO77/AK77-1) -> 0.39659715 | AP78: =+IF(AL77<0,1-AP77/AL77,AP77/AL77-1) -> 0.60200281 | AQ78: =+IF(AM77<0,1-AQ77/AM77,AQ77/AM77-1) -> 0.5024802 | AR78: =+IF(AN77<0,1-AR77/AN77,AR77/AN77-1) -> 0.29181978 | AS78: =+IF(AO77<0,1-AS77/AO77,AS77/AO77-1) -> 0.24586276 | AT78: =+IF(AP77<0,1-AT77/AP77,AT77/AP77-1) -> 0.24440771 | AU78: =+IF(AQ77<0,1-AU77/AQ77,AU77/AQ77-1) -> 0.2547551 | AV78: =+IF(AR77<0,1-AV77/AR77,AV77/AR77-1) -> 0.31232769 | ... CZ78: =+IF(CV77<0,1-CZ77/CV77,CZ77/CV77-1) -> 0.18844482 | DC78: #DIV/0!
A79: Bloomberg Estimate | CN79: 90.2 | CR79: 104.4 | CV79: 118.9
A80: Estimate deviation | CN80: =CN77/CN79-1 -> -0.084676202 | CR80: =CR77/CR79-1 -> 0.012785395 | CV80: =CV77/CV79-1 -> -0.015782383
A81: Promoter Share holding % | B81: ='Annual Raw'!C112 -> 52.11 | C81: ='Annual Raw'!D112 -> 52.11 | D81: ='Annual Raw'!E112 -> 52.11 | E81: ='Annual Raw'!F112 -> 52.11 | F81: ='Annual Raw'!G112 -> 52.11 | G81: ='Annual Raw'!H112 -> 52.11 | H81: ='Annual Raw'!I112 -> 52.11 | I81: ='Annual Raw'!J112 -> 52.11 | ... Z81: ='Annual Raw'!AA112 -> 75 | AH81: ='QTR Raw'!C49 -> 75 | AI81: ='QTR Raw'!D49 -> 75 | AJ81: ='QTR Raw'!E49 -> 75 | AK81: ='QTR Raw'!F49 -> 75 | AL81: ='QTR Raw'!G49 -> 75 | AM81: ='QTR Raw'!H49 -> 75 | AN81: ='QTR Raw'!I49 -> 75 | AO81: ='QTR Raw'!J49 -> 75 | ... CK81: ='QTR Raw'!BF49 -> 75 | DC81: 0
A82: Pledge Share % | B82: ='Annual Raw'!C113 -> 0 | C82: ='Annual Raw'!D113 -> 0 | D82: ='Annual Raw'!E113 -> 0 | E82: ='Annual Raw'!F113 -> 0 | F82: ='Annual Raw'!G113 -> 0 | G82: ='Annual Raw'!H113 -> 0 | H82: ='Annual Raw'!I113 -> 0 | I82: ='Annual Raw'!J113 -> 0 | ... Z82: ='Annual Raw'!AA113 -> 0 | AH82: ='QTR Raw'!C50 -> 0 | AI82: ='QTR Raw'!D50 -> 0 | AJ82: ='QTR Raw'!E50 -> 0 | AK82: ='QTR Raw'!F50 -> 0 | AL82: ='QTR Raw'!G50 -> 0 | AM82: ='QTR Raw'!H50 -> 0 | AN82: ='QTR Raw'!I50 -> 0 | AO82: ='QTR Raw'!J50 -> 0 | ... CK82: ='QTR Raw'!BF50 -> 0 | DC82: 0
A84: Share Price
A85: Share Price - Close | B85: ='Annual Raw'!C106 -> 40.8 | C85: ='Annual Raw'!D106 -> 49.73 | D85: ='Annual Raw'!E106 -> 134.75 | E85: ='Annual Raw'!F106 -> 194.02 | F85: ='Annual Raw'!G106 -> 385.79 | G85: ='Annual Raw'!H106 -> 742.3 | H85: ='Annual Raw'!I106 -> 1512.35 | I85: ='Annual Raw'!J106 -> 453.45 | ... Z85: ='Annual Raw'!AA106 -> 5170.3 | AA85: =+CK85 -> 5936.5 | AB85: =+CO85 -> 6535 | AC85: =+CS85 -> 6535 | AD85: =+CW85 -> 6535 | AI85: ='QTR Share Price'!HP21 -> 797.75 | AJ85: ='QTR Share Price'!HQ21 -> 700.4 | AK85: ='QTR Share Price'!HR21 -> 489.2 | AL85: ='QTR Share Price'!HS21 -> 610.85 | AM85: ='QTR Share Price'!HT21 -> 543.9 | AN85: ='QTR Share Price'!HU21 -> 692.8 | AO85: ='QTR Share Price'!HV21 -> 849.95 | AP85: ='QTR Share Price'!HW21 -> 1122.05 | ... CK85: ='QTR Share Price'!JR21 -> 5936.5 | CL85: 6535 | CM85: =+CL85 -> 6535 | CN85: =+CM85 -> 6535 | CO85: =+CN85 -> 6535 | CP85: =+CO85 -> 6535 | CQ85: =+CP85 -> 6535 | CR85: =+CQ85 -> 6535 | CS85: =+CR85 -> 6535 | CT85: =+CS85 -> 6535 | ... CZ85: =+CY85 -> 6535 | DC85: 0
A86: Share Price - High | B86: ='Annual Raw'!C107 -> 66.8 | C86: ='Annual Raw'!D107 -> 58.39 | D86: ='Annual Raw'!E107 -> 135.39 | E86: ='Annual Raw'!F107 -> 200 | F86: ='Annual Raw'!G107 -> 410.2 | G86: ='Annual Raw'!H107 -> 789 | H86: ='Annual Raw'!I107 -> 1670 | I86: ='Annual Raw'!J107 -> 1528 | ... Z86: ='Annual Raw'!AA107 -> 6947.45 | AA86: =MAX(CH86:CK86) -> 6555 | AB86: =+MAX(CL86:CO86) -> 7830.4985 | AC86: =+MAX(CP86:CS86) -> 9501.6474 | AD86: =+MAX(CT86:CW86) -> 10579.273 | AI86: ='QTR Share Price'!HP19 -> 822.25 | AJ86: ='QTR Share Price'!HQ19 -> 830 | AK86: ='QTR Share Price'!HR19 -> 737 | AL86: ='QTR Share Price'!HS19 -> 694.4 | AM86: ='QTR Share Price'!HT19 -> 627.2 | AN86: ='QTR Share Price'!HU19 -> 720.2 | AO86: ='QTR Share Price'!HV19 -> 858 | AP86: ='QTR Share Price'!HW19 -> 1125 | ... CK86: ='QTR Share Price'!JR19 -> 6555 | CL86: =+CL77*CL94 -> 6965.1359 | CM86: =+CM77*CM94 -> 7229.5261 | CN86: =+CN77*CN94 -> 7153.4608 | CO86: =+CO77*CO94 -> 7830.4985 | CP86: =+CP77*CP94 -> 8322.2418 | CQ86: =+CQ77*CQ94 -> 8742.7285 | CR86: =+CR77*CR94 -> 9161.21 | CS86: =+CS77*CS94 -> 9501.6474 | ... CZ86: =+CZ77*CZ94 -> 12049.997 | DC86: 0
A87: Share Price - Low | B87: ='Annual Raw'!C108 -> 35.6 | C87: ='Annual Raw'!D108 -> 40.75 | D87: ='Annual Raw'!E108 -> 49.47 | E87: ='Annual Raw'!F108 -> 119.4 | F87: ='Annual Raw'!G108 -> 177 | G87: ='Annual Raw'!H108 -> 382 | H87: ='Annual Raw'!I108 -> 638 | I87: ='Annual Raw'!J108 -> 379.15 | ... Z87: ='Annual Raw'!AA108 -> 4590.05 | AA87: =MIN(CH87:CK87) -> 4590.05 | AB87: =+MIN(CL87:CO87) -> 4421.3752 | AC87: =+MIN(CP87:CS87) -> 5282.8479 | AD87: =+MIN(CT87:CW87) -> 6199.8613 | AI87: =+'QTR Share Price'!HP20 -> 707.5 | AJ87: =+'QTR Share Price'!HQ20 -> 676.95 | AK87: =+'QTR Share Price'!HR20 -> 484.3 | AL87: =+'QTR Share Price'!HS20 -> 469 | AM87: =+'QTR Share Price'!HT20 -> 448.1 | AN87: =+'QTR Share Price'!HU20 -> 535.15 | AO87: =+'QTR Share Price'!HV20 -> 568.05 | AP87: =+'QTR Share Price'!HW20 -> 807.3 | ... CK87: =+'QTR Share Price'!JR20 -> 4640.5 | CL87: =+CL95*CL77 -> 4421.3752 | CM87: =+CM95*CM77 -> 4589.2066 | CN87: =+CN95*CN77 -> 4540.9214 | CO87: =+CO95*CO77 -> 4970.6958 | CP87: =+CP95*CP77 -> 5282.8479 | CQ87: =+CQ95*CQ77 -> 5549.7673 | CR87: =+CR95*CR77 -> 5815.4137 | CS87: =+CS95*CS77 -> 6031.5188 | ... CZ87: =+CZ95*CZ77 -> 7649.1768 | DC87: 0
A89: Upside (%) | AA89: =+AA86/AA85-1 -> 0.10418597 | AB89: =+AB86/AB85-1 -> 0.19824001 | AC89: =+AC86/AC85-1 -> 0.45396288 | AD89: =+AD86/AD85-1 -> 0.61886343 | CL89: =+CL86/CL85-1 -> 0.065820333 | CM89: =+CM86/CM85-1 -> 0.1062779 | CN89: =+CN86/CN85-1 -> 0.094638229 | CO89: =+CO86/CO85-1 -> 0.19824001 | CP89: =+CP86/CP85-1 -> 0.27348765 | CQ89: =+CQ86/CQ85-1 -> 0.33783145 | CR89: =+CR86/CR85-1 -> 0.40186841 | CS89: =+CS86/CS85-1 -> 0.45396288 | ... CZ89: =+CZ86/CZ85-1 -> 0.84391684
A90: Downside (%) | AA90: =+AA87/AA85-1 -> -0.22680873 | AB90: =+AB87/AB85-1 -> -0.32343149 | AC90: =+AC87/AC85-1 -> -0.19160705 | AD90: =+AD87/AD85-1 -> -0.051283663 | CL90: =+CL87/CL85-1 -> -0.32343149 | CM90: =+CM87/CM85-1 -> -0.29774957 | CN90: =+CN87/CN85-1 -> -0.30513828 | CO90: =+CO87/CO85-1 -> -0.23937325 | CP90: =+CP87/CP85-1 -> -0.19160705 | CQ90: =+CQ87/CQ85-1 -> -0.15076247 | CR90: =+CR87/CR85-1 -> -0.11011266 | CS90: =+CS87/CS85-1 -> -0.077043788 | ... CZ90: =+CZ87/CZ85-1 -> 0.17049378
A92: PE
A93: PE - Close | B93: =+B85/B77 -> 2.6469951 | C93: =+C85/C77 -> 2.5908895 | D93: =+D85/D77 -> 5.6604037 | E93: =+E85/E77 -> 27.313871 | F93: =+F85/F77 -> 37.383402 | G93: =+G85/G77 -> 46.22113 | H93: =+H85/H77 -> 65.179412 | I93: =+I85/I77 -> 17.552754 | ... AD93: =+AD85/AD77 -> 46.988716 | AK93: =+AK85/AK77 -> 78.040714 | AL93: =+AL85/AL77 -> 107.12498 | AM93: =+AM85/AM77 -> 85.327911 | AN93: =+AN85/AN77 -> 82.991871 | AO93: =+AO85/AO77 -> 97.08609 | AP93: =+AP85/AP77 -> 122.83019 | AQ93: =+AQ85/AQ77 -> 119.79544 | AR93: =+AR85/AR77 -> 119.27083 | ... CZ93: =+CZ85/CZ77 -> 46.988716 | DC93: #DIV/0!
A94: PE - High | B94: =+B86/B77 -> 4.3338057 | C94: =+C86/C77 -> 3.0420679 | D94: =+D86/D77 -> 5.6872879 | E94: =+E86/E77 -> 28.155727 | F94: =+F86/F77 -> 39.748753 | G94: =+G86/G77 -> 49.12902 | H94: =+H86/H77 -> 71.973828 | I94: =+I86/I77 -> 59.147883 | ... AD94: =+AD86/AD77 -> 76.068314 | AK94: =+AK86/AK77 -> 117.57156 | AL94: =+AL86/AL77 -> 121.77717 | AM94: =+AM86/AM77 -> 98.39615 | AN94: =+AN86/AN77 -> 86.27417 | AO94: =+AO86/AO77 -> 98.005606 | AP94: =+AP86/AP77 -> 123.15312 | AQ94: =+AQ86/AQ77 -> 131.92848 | AR94: =+AR86/AR77 -> 129.51763 | ... CK94: =+CK86/CK77 -> 86.643285 | CL94: =+CK94 -> 86.643285 | CM94: =+CL94 -> 86.643285 | CN94: =+CM94 -> 86.643285 | CO94: =+CN94 -> 86.643285 | CP94: =+CO94 -> 86.643285 | CQ94: =+CP94 -> 86.643285 | CR94: =+CQ94 -> 86.643285 | CS94: =+CR94 -> 86.643285 | ... CZ94: =+CY94 -> 86.643285 | DC94: #DIV/0!
A95: PE - Low | B95: =+B87/B77 -> 2.309633 | C95: =+C87/C77 -> 2.1230393 | D95: =+D87/D77 -> 2.0780718 | E95: =+E87/E77 -> 16.808969 | F95: =+F87/F77 -> 17.151461 | G95: =+G87/G77 -> 23.786167 | H95: =+H87/H77 -> 27.496588 | I95: =+I87/I77 -> 14.676649 | ... AD95: =+AD87/AD77 -> 44.578963 | AK95: =+AK87/AK77 -> 77.25903 | AL95: =+AL87/AL77 -> 82.248697 | AM95: =+AM87/AM77 -> 70.298653 | AN95: =+AN87/AN77 -> 64.106668 | AO95: =+AO87/AO77 -> 64.885879 | AP95: =+AP87/AP77 -> 88.374681 | AQ95: =+AQ87/AQ77 -> 99.831275 | AR95: =+AR87/AR77 -> 91.64158 | ... CK95: =+CK87/CK77 -> 61.33763 | CL95: 55 | CM95: =+CL95 -> 55 | CN95: =+CM95 -> 55 | CO95: =+CN95 -> 55 | CP95: =+CO95 -> 55 | CQ95: =+CP95 -> 55 | CR95: =+CQ95 -> 55 | CS95: =+CR95 -> 55 | CT95: =+CS95 -> 55 | ... CZ95: =+CY95 -> 55 | DC95: #DIV/0!
A97: PE - 1Yr Fwd | B97: =+B86/C77 -> 3.4802215 | C97: =+C86/D77 -> 2.4527716 | D97: =+D86/E77 -> 19.060019 | E97: =+E86/F77 -> 19.380182 | F97: =+F86/G77 -> 25.542109 | G97: =+G86/H77 -> 34.004401 | H97: =+H86/I77 -> 64.64461 | I97: =+I86/J77 -> 91.299352 | ... AC97: =+AC86/AD77 -> 68.319849 | AD97: =+AD86/#REF! -> #REF! | AK97: =+AK86/AO77 -> 84.184303 | AL97: =+AL86/AP77 -> 76.015581 | AM97: =+AM86/AQ77 -> 65.48915 | AN97: =+AN86/AR77 -> 66.78499 | AO97: =+AO86/AS77 -> 78.664849 | AP97: =+AP86/AT77 -> 98.965252 | AQ97: =+AQ86/AU77 -> 105.14281 | AR97: =+AR86/AV77 -> 98.693054 | ... CK97: =+CK86/CO77 -> 72.530087 | DC97: #DIV/0!
A98: Correlation | AN98: =+CORREL(AK77:AN77,AK94:AN94) -> -0.88108985 | AO98: =+CORREL(AL77:AO77,AL94:AO94) -> -0.76240149 | AP98: =+CORREL(AM77:AP77,AM94:AP94) -> 0.37964906 | AQ98: =+CORREL(AN77:AQ77,AN94:AQ94) -> 0.97763193 | AR98: =+CORREL(AO77:AR77,AO94:AR94) -> 0.68705348 | AS98: =+CORREL(AP77:AS77,AP94:AS94) -> 0.72521948 | AT98: =+CORREL(AQ77:AT77,AQ94:AT94) -> -0.1911971 | AU98: =+CORREL(AR77:AU77,AR94:AU94) -> -0.8000034 | ... CK98: =+CORREL(CH77:CK77,CH94:CK94) -> -0.68723601
A100: BVPS | E100: =+E$128/E$73 -> 34.198287 | F100: =+F$128/F$73 -> 42.667669 | G100: =+G$128/G$73 -> 56.434252 | H100: =+H$128/H$73 -> 76.750557 | I100: =+I$128/I$73 -> 99.997791 | J100: =+J$128/J$73 -> 114.38099 | K100: =+K$128/K$73 -> 114.37959 | L100: =+L$128/L$73 -> 119.69939 | ... AD100: =+AD$128/AD$73 -> 785.56175 | AK100: =+AK$128/AK$73 -> 124.80887 | AL100: =+AL$128/AL$73 -> 125.42426 | AM100: =+AM$128/AM$73 -> 127.21897 | AN100: =+AN$128/AN$73 -> 126.3596 | AO100: =+AO$128/AO$73 -> 128.79849 | AP100: =+AP$128/AP$73 -> 131.04908 | AQ100: =+AQ$128/AQ$73 -> 133.17178 | AR100: =+AR$128/AR$73 -> 132.70316 | ... CZ100: =+CZ$128/CZ$73 -> 891.68099 | DC100: #DIV/0!
A101: PB
A102: PB - Close | E102: =+E85/E$100 -> 5.6733836 | F102: =+F85/F$100 -> 9.0417408 | G102: =+G85/G$100 -> 13.153359 | H102: =+H85/H$100 -> 19.704743 | I102: =+I85/I$100 -> 4.5346002 | J102: =+J85/J$100 -> 6.7078454 | K102: =+K85/K$100 -> 6.9264977 | L102: =+L85/L$100 -> 4.8755471 | ... AD102: =+AD85/AD$100 -> 8.3188878 | AK102: =+AK85/AK$100 -> 3.9195931 | AL102: =+AL85/AL$100 -> 4.87027 | AM102: =+AM85/AM$100 -> 4.2753058 | AN102: =+AN85/AN$100 -> 5.4827649 | AO102: =+AO85/AO$100 -> 6.5990681 | AP102: =+AP85/AP$100 -> 8.5620594 | AQ102: =+AQ85/AQ$100 -> 8.6151886 | AR102: =+AR85/AR$100 -> 9.6923086 | ... CZ102: =+CZ85/CZ$100 -> 7.3288543 | DC102: #DIV/0!
A103: PB - High | E103: =+E86/E$100 -> 5.8482462 | F103: =+F86/F$100 -> 9.6138367 | G103: =+G86/G$100 -> 13.980871 | H103: =+H86/H$100 -> 21.7588 | I103: =+I86/I$100 -> 15.280337 | J103: =+J86/J$100 -> 7.2914213 | K103: =+K86/K$100 -> 8.5233735 | L103: =+L86/L$100 -> 7.5814925 | ... AD103: =+AD86/AD$100 -> 13.467143 | AK103: =+AK86/AK$100 -> 5.9050289 | AL103: =+AL86/AL$100 -> 5.5364091 | AM103: =+AM86/AM$100 -> 4.9300823 | AN103: =+AN86/AN$100 -> 5.6996064 | AO103: =+AO86/AO$100 -> 6.6615688 | AP103: =+AP86/AP$100 -> 8.58457 | AQ103: =+AQ86/AQ$100 -> 9.4877459 | AR103: =+AR86/AR$100 -> 10.524994 | ... CK103: =+CK86/CK$100 -> 14.144836 | CL103: =+CK103 -> 14.144836 | CM103: =+CL103 -> 14.144836 | CN103: =+CM103 -> 14.144836 | CO103: =+CN103 -> 14.144836 | CP103: =+CO103 -> 14.144836 | CQ103: =+CP103 -> 14.144836 | CR103: =+CQ103 -> 14.144836 | CS103: =+CR103 -> 14.144836 | ... CZ103: =+CY103 -> 14.144836 | DC103: #DIV/0!
A104: PB - Low | E104: =+E87/E$100 -> 3.491403 | F104: =+F87/F$100 -> 4.1483401 | G104: =+G87/G$100 -> 6.7689388 | H104: =+H87/H$100 -> 8.3126433 | I104: =+I87/I$100 -> 3.7915837 | J104: =+J87/J$100 -> 3.0074927 | K104: =+K87/K$100 -> 5.850694 | L104: =+L87/L$100 -> 4.520491 | ... AD104: =+AD87/AD$100 -> 7.8922647 | AK104: =+AK87/AK$100 -> 3.8803331 | AL104: =+AL87/AL$100 -> 3.7393086 | AM104: =+AM87/AM$100 -> 3.5222734 | AN104: =+AN87/AN$100 -> 4.2351352 | AO104: =+AO87/AO$100 -> 4.4103778 | AP104: =+AP87/AP$100 -> 6.1602874 | AQ104: =+AQ87/AQ$100 -> 7.179449 | AR104: =+AR87/AR$100 -> 7.447072 | ... CK104: =+CK87/CK$100 -> 10.013594 | CL104: =+CK104 -> 10.013594 | CM104: =+CL104 -> 10.013594 | CN104: =+CM104 -> 10.013594 | CO104: =+CN104 -> 10.013594 | CP104: =+CO104 -> 10.013594 | CQ104: =+CP104 -> 10.013594 | CR104: =+CQ104 -> 10.013594 | CS104: =+CR104 -> 10.013594 | ... CZ104: =+CY104 -> 10.013594 | DC104: #DIV/0!
A106: Sales Rolling | E106: =+E18 -> 2260.2226 | F106: =+F18 -> 2963.0526 | G106: =+G18 -> 4274.0093 | H106: =+H18 -> 5930.3114 | I106: =+I18 -> 6837.0315 | J106: =+J18 -> 6237.2014 | K106: =+K18 -> 6287.1118 | L106: =+L18 -> 7451.79 | ... AD106: =+AD18 -> 22645.674 | AK106: =+SUM(AH16:AK16) -> 7755.75 | AL106: =+SUM(AI16:AL16) -> 7623.11 | AM106: =+SUM(AJ16:AM16) -> 7600.4 | AN106: =+SUM(AK16:AN16) -> 7721.99 | AO106: =+SUM(AL16:AO16) -> 7568.63 | AP106: =+SUM(AM16:AP16) -> 7639.66 | AQ106: =+SUM(AN16:AQ16) -> 7698.73 | AR106: =+SUM(AO16:AR16) -> 7733.27 | ... CZ106: =+SUM(CW16:CZ16) -> 22645.674 | DC106: 0
A107: Sales Per Share | E107: =+E106/E73 -> 106.66459 | F107: =+F106/F73 -> 139.83259 | G107: =+G106/G73 -> 201.69935 | H107: =+H106/H73 -> 279.86368 | I107: =+I106/I73 -> 322.65368 | J107: =+J106/J73 -> 294.34646 | K107: =+K106/K73 -> 296.70183 | L107: =+L106/L73 -> 351.66541 | ... AD107: =+AD106/AD73 -> 1068.6963 | AK107: =+AK106/AK73 -> 366.00991 | AL107: =+AL106/AL73 -> 359.75035 | AM107: =+AM106/AM73 -> 358.67862 | AN107: =+AN106/AN73 -> 364.41671 | AO107: =+AO106/AO73 -> 357.17933 | AP107: =+AP106/AP73 -> 360.53138 | AQ107: =+AQ106/AQ73 -> 363.31902 | AR107: =+AR106/AR73 -> 364.94903 | ... CZ107: =+CZ106/CZ73 -> 1068.6963 | DC107: #DIV/0!
A109: Price to Sales
A110: Price to Sales - Close | E110: =+E85/E$107 -> 1.818973 | F110: =+F85/F$107 -> 2.7589419 | G110: =+G85/G$107 -> 3.6802299 | H110: =+H85/H$107 -> 5.4038809 | I110: =+I85/I$107 -> 1.4053768 | J110: =+J85/J$107 -> 2.6066222 | K110: =+K85/K$107 -> 2.6701891 | L110: =+L85/L$107 -> 1.659532 | ... AD110: =+AD85/AD$107 -> 6.1149272 | AK110: =+AK85/AK107 -> 1.3365758 | AL110: =+AL85/AL107 -> 1.697983 | AM110: =+AM85/AM107 -> 1.5163993 | AN110: =+AN85/AN107 -> 1.9011203 | AO110: =+AO85/AO107 -> 2.379617 | AP110: =+AP85/AP107 -> 3.1122117 | AQ110: =+AQ85/AQ107 -> 3.1578308 | AR110: =+AR85/AR107 -> 3.5243277 | ... CZ110: =+CZ85/CZ107 -> 6.1149272 | DC110: #DIV/0!
A111: Price to Sales - High | E111: =+E86/E$107 -> 1.8750366 | F111: =+F86/F$107 -> 2.9335078 | G111: =+G86/G$107 -> 3.9117627 | H111: =+H86/H$107 -> 5.9671909 | I111: =+I86/I$107 -> 4.7357278 | J111: =+J86/J$107 -> 2.8333958 | K111: =+K86/K$107 -> 3.2857903 | L111: =+L86/L$107 -> 2.580578 | ... AD111: =+AD86/AD$107 -> 9.8992321 | AK111: =+AK86/AK107 -> 2.0136067 | AL111: =+AL86/AL107 -> 1.9302274 | AM111: =+AM86/AM107 -> 1.7486406 | AN111: =+AN86/AN107 -> 1.976309 | AO111: =+AO86/AO107 -> 2.4021547 | AP111: =+AP86/AP107 -> 3.1203941 | AQ111: =+AQ86/AQ107 -> 3.47766 | AR111: =+AR86/AR107 -> 3.8271097 | ... CK111: =+CK86/CK107 -> 10.501099 | CL111: =+CK111 -> 10.501099 | CM111: =+CL111 -> 10.501099 | CN111: =+CM111 -> 10.501099 | CO111: =+CN111 -> 10.501099 | CP111: =+CO111 -> 10.501099 | CQ111: =+CP111 -> 10.501099 | CR111: =+CQ111 -> 10.501099 | CS111: =+CR111 -> 10.501099 | ... CZ111: =+CY111 -> 10.501099 | DC111: #DIV/0!
A112: Price to Sales - Low | E112: =+E87/E$107 -> 1.1193968 | F112: =+F87/F$107 -> 1.2657993 | G112: =+G87/G$107 -> 1.8939079 | H112: =+H87/H$107 -> 2.2796813 | I112: =+I87/I$107 -> 1.1750989 | J112: =+J87/J$107 -> 1.1686908 | K112: =+K87/K$107 -> 2.255463 | L112: =+L87/L$107 -> 1.5386785 | ... AD112: =+AD87/AD$107 -> 5.8013314 | AK112: =+AK87/AK107 -> 1.3231882 | AL112: =+AL87/AL107 -> 1.3036818 | AM112: =+AM87/AM107 -> 1.2493078 | AN112: =+AN87/AN107 -> 1.4685112 | AO112: =+AO87/AO107 -> 1.5903776 | AP112: =+AP87/AP107 -> 2.2391948 | AQ112: =+AQ87/AQ107 -> 2.6315716 | AR112: =+AR87/AR107 -> 2.7079124 | ... CK112: =+CK87/CK107 -> 7.4340731 | CL112: =+CK112 -> 7.4340731 | CM112: =+CL112 -> 7.4340731 | CN112: =+CM112 -> 7.4340731 | CO112: =+CN112 -> 7.4340731 | CP112: =+CO112 -> 7.4340731 | CQ112: =+CP112 -> 7.4340731 | CR112: =+CQ112 -> 7.4340731 | CS112: =+CR112 -> 7.4340731 | ... CZ112: =+CY112 -> 7.4340731 | DC112: #DIV/0!
A115: Market Cap High | B115: =+B86*B73 -> 283.10976 | C115: =+C86*C73 -> 247.46675 | D115: =+D86*D73 -> 573.80584 | E115: =+E86*E73 -> 4238 | F115: =+F86*F73 -> 8692.138 | G115: =+G86*G73 -> 16718.91 | H115: =+H86*H73 -> 35387.3 | I115: =+I86*I73 -> 32378.32 | ... AD115: =+AD86*AD73 -> 224174.78 | AK115: =+AK86*AK73 -> 15617.03 | AL115: =+AL86*AL73 -> 14714.336 | AM115: =+AM86*AM73 -> 13290.368 | AN115: =+AN86*AN73 -> 15261.038 | AO115: =+AO86*AO73 -> 18181.02 | AP115: =+AP86*AP73 -> 23838.75 | AQ115: =+AQ86*AQ73 -> 26773.565 | AR115: =+AR86*AR73 -> 29596.073 | ... CZ115: =+CZ86*CZ73 -> 255339.43 | DC115: #DIV/0!
...

Sheet QTR Raw
A1: ='Annual Raw'!A1 -> 100002 | B1: X | C1: 201206 | D1: 201209 | E1: 201212 | F1: 201303 | G1: 201306 | H1: 201309 | I1: 201312 | J1: 201403 | K1: 201406 | L1: 201409 | M1: 201412 | N1: 201503 | O1: 201506 | P1: 201509 | Q1: 201512 | R1: 201603 | S1: 201606 | T1: 201609 | U1: 201612 | V1: 201703 | W1: 201706 | X1: 201709 | Y1: 201712 | Z1: 201803 | AA1: 201806 | AB1: 201809 | AC1: 201812 | AD1: 201903 | AE1: 201906 | AF1: 201909 | AG1: 201912 | AH1: 202003 | AI1: 202006 | AJ1: 202009 | AK1: 202012 | AL1: 202103 | AM1: 202106 | AN1: 202109 | AO1: 202112 | AP1: 202203 | AQ1: 202206 | AR1: 202209 | AS1: 202212 | AT1: 202303 | AU1: 202306 | AV1: 202309 | AW1: 202312 | AX1: 202403 | AY1: 202406 | AZ1: 202409 | BA1: 202412 | BB1: 202503 | BC1: 202506 | BD1: 202509 | BE1: 202512 | BF1: 202603 | BG1: 202606 | BH1: 202609 | BI1: 202612 | BJ1: 202703 | BK1: 202706 | BL1: 202709 | BM1: 202712 | BN1: 202803 | BO1: 202806 | BP1: 202809 | BQ1: 202812 | BR1: 202903 | BS1: 202906 | BT1: 202909 | BU1: 202912 | BV1: 203003
A3: Field Description | B3: Field Name
A4: Company Name | B4: CD_COMPNAME | C4: =_xll.EQNXTDZ(A1,B4,C1) -> ABB India Ltd.
A5: Date End | B5: QTR_DATE_END | C5: =_xll.EQNXTDZ($A$1,$B5,C$1,$B$1) -> 201206 | D5: =_xll.EQNXTDZ($A$1,$B5,D$1,$B$1) -> 201209 | E5: =_xll.EQNXTDZ($A$1,$B5,E$1,$B$1) -> 201212 | F5: =_xll.EQNXTDZ($A$1,$B5,F$1,$B$1) -> 201303 | G5: =_xll.EQNXTDZ($A$1,$B5,G$1,$B$1) -> 201306 | H5: =_xll.EQNXTDZ($A$1,$B5,H$1,$B$1) -> 201309 | I5: =_xll.EQNXTDZ($A$1,$B5,I$1,$B$1) -> 201312 | J5: =_xll.EQNXTDZ($A$1,$B5,J$1,$B$1) -> 201403 | ... BV5: =_xll.EQNXTDZ($A$1,$B5,BV$1,$B$1) -> 0
A6: Gross Sales | B6: QTR_GROSS_SALE | C6: =_xll.EQNXTDZ($A$1,$B6,C$1,$B$1) -> 1858.45 | D6: =_xll.EQNXTDZ($A$1,$B6,D$1,$B$1) -> 1786.06 | E6: =_xll.EQNXTDZ($A$1,$B6,E$1,$B$1) -> 2052.76 | F6: =_xll.EQNXTDZ($A$1,$B6,F$1,$B$1) -> 1964.36 | G6: =_xll.EQNXTDZ($A$1,$B6,G$1,$B$1) -> 1729.95 | H6: =_xll.EQNXTDZ($A$1,$B6,H$1,$B$1) -> 1762.4 | I6: =_xll.EQNXTDZ($A$1,$B6,I$1,$B$1) -> 2174.91 | J6: =_xll.EQNXTDZ($A$1,$B6,J$1,$B$1) -> 1809.98 | ... BV6: =_xll.EQNXTDZ($A$1,$B6,BV$1,$B$1) -> 0
A7: Less: Excise Duty | B7: QTR_EXCISE_DUTY | C7: =_xll.EQNXTDZ($A$1,$B7,C$1,$B$1) -> 0 | D7: =_xll.EQNXTDZ($A$1,$B7,D$1,$B$1) -> 0 | E7: =_xll.EQNXTDZ($A$1,$B7,E$1,$B$1) -> 0 | F7: =_xll.EQNXTDZ($A$1,$B7,F$1,$B$1) -> 0 | G7: =_xll.EQNXTDZ($A$1,$B7,G$1,$B$1) -> 0 | H7: =_xll.EQNXTDZ($A$1,$B7,H$1,$B$1) -> 0 | I7: =_xll.EQNXTDZ($A$1,$B7,I$1,$B$1) -> 0 | J7: =_xll.EQNXTDZ($A$1,$B7,J$1,$B$1) -> 0 | ... BV7: =_xll.EQNXTDZ($A$1,$B7,BV$1,$B$1) -> 0
A8: Other operating income | B8: QTR_JOB_WORKS | C8: =_xll.EQNXTDZ($A$1,$B8,C$1,$B$1) -> 25.34 | D8: =_xll.EQNXTDZ($A$1,$B8,D$1,$B$1) -> 22.55 | E8: =_xll.EQNXTDZ($A$1,$B8,E$1,$B$1) -> 29.52 | F8: =_xll.EQNXTDZ($A$1,$B8,F$1,$B$1) -> 16.71 | G8: =_xll.EQNXTDZ($A$1,$B8,G$1,$B$1) -> 21.2 | H8: =_xll.EQNXTDZ($A$1,$B8,H$1,$B$1) -> 23.5 | I8: =_xll.EQNXTDZ($A$1,$B8,I$1,$B$1) -> 28.96 | J8: =_xll.EQNXTDZ($A$1,$B8,J$1,$B$1) -> 17.73 | ... BV8: =_xll.EQNXTDZ($A$1,$B8,BV$1,$B$1) -> 0
A9: Net Sales & Other Operating Income | B9: QTR_NET_SALES | C9: =_xll.EQNXTDZ($A$1,$B9,C$1,$B$1) -> 1883.79 | D9: =_xll.EQNXTDZ($A$1,$B9,D$1,$B$1) -> 1808.61 | E9: =_xll.EQNXTDZ($A$1,$B9,E$1,$B$1) -> 2082.28 | F9: =_xll.EQNXTDZ($A$1,$B9,F$1,$B$1) -> 1981.07 | G9: =_xll.EQNXTDZ($A$1,$B9,G$1,$B$1) -> 1751.15 | H9: =_xll.EQNXTDZ($A$1,$B9,H$1,$B$1) -> 1785.9 | I9: =_xll.EQNXTDZ($A$1,$B9,I$1,$B$1) -> 2203.87 | J9: =_xll.EQNXTDZ($A$1,$B9,J$1,$B$1) -> 1827.71 | ... BV9: =_xll.EQNXTDZ($A$1,$B9,BV$1,$B$1) -> 0
A10: (Increase) / Decrease In Stocks | B10: QTR_INC_DEC_INVENTORY | C10: =_xll.EQNXTDZ($A$1,$B10,C$1,$B$1) -> -6.98 | D10: =_xll.EQNXTDZ($A$1,$B10,D$1,$B$1) -> -28.04 | E10: =_xll.EQNXTDZ($A$1,$B10,E$1,$B$1) -> 42.06 | F10: =_xll.EQNXTDZ($A$1,$B10,F$1,$B$1) -> -24.13 | G10: =_xll.EQNXTDZ($A$1,$B10,G$1,$B$1) -> 3.8 | H10: =_xll.EQNXTDZ($A$1,$B10,H$1,$B$1) -> -17.94 | I10: =_xll.EQNXTDZ($A$1,$B10,I$1,$B$1) -> 25.29 | J10: =_xll.EQNXTDZ($A$1,$B10,J$1,$B$1) -> 10.39 | ... BV10: =_xll.EQNXTDZ($A$1,$B10,BV$1,$B$1) -> 0
A11: Cost of Services & Raw Materials | B11: QTR_RAW_MATERIAL_COST | C11: =_xll.EQNXTDZ($A$1,$B11,C$1,$B$1) -> 1163.55 | D11: =_xll.EQNXTDZ($A$1,$B11,D$1,$B$1) -> 1109.66 | E11: =_xll.EQNXTDZ($A$1,$B11,E$1,$B$1) -> 1312.81 | F11: =_xll.EQNXTDZ($A$1,$B11,F$1,$B$1) -> 1277.21 | G11: =_xll.EQNXTDZ($A$1,$B11,G$1,$B$1) -> 1004.15 | H11: =_xll.EQNXTDZ($A$1,$B11,H$1,$B$1) -> 1063.55 | I11: =_xll.EQNXTDZ($A$1,$B11,I$1,$B$1) -> 1284.28 | J11: =_xll.EQNXTDZ($A$1,$B11,J$1,$B$1) -> 1033.35 | ... BV11: =_xll.EQNXTDZ($A$1,$B11,BV$1,$B$1) -> 0
A12: Purchase of Finished Goods | B12: QTR_PURCHASE_FIN_GOOD | C12: =_xll.EQNXTDZ($A$1,$B12,C$1,$B$1) -> 62.16 | D12: =_xll.EQNXTDZ($A$1,$B12,D$1,$B$1) -> 65.26 | E12: =_xll.EQNXTDZ($A$1,$B12,E$1,$B$1) -> 70.39 | F12: =_xll.EQNXTDZ($A$1,$B12,F$1,$B$1) -> 49.09 | G12: =_xll.EQNXTDZ($A$1,$B12,G$1,$B$1) -> 76.15 | H12: =_xll.EQNXTDZ($A$1,$B12,H$1,$B$1) -> 85.97 | I12: =_xll.EQNXTDZ($A$1,$B12,I$1,$B$1) -> 102.86 | J12: =_xll.EQNXTDZ($A$1,$B12,J$1,$B$1) -> 82.33 | ... BV12: =_xll.EQNXTDZ($A$1,$B12,BV$1,$B$1) -> 0
A13: Excise Duty | B13: QTR_EXCISE | C13: =_xll.EQNXTDZ($A$1,$B13,C$1,$B$1) -> 0 | D13: =_xll.EQNXTDZ($A$1,$B13,D$1,$B$1) -> 0 | E13: =_xll.EQNXTDZ($A$1,$B13,E$1,$B$1) -> 0 | F13: =_xll.EQNXTDZ($A$1,$B13,F$1,$B$1) -> 0 | G13: =_xll.EQNXTDZ($A$1,$B13,G$1,$B$1) -> 0 | H13: =_xll.EQNXTDZ($A$1,$B13,H$1,$B$1) -> 0 | I13: =_xll.EQNXTDZ($A$1,$B13,I$1,$B$1) -> 0 | J13: =_xll.EQNXTDZ($A$1,$B13,J$1,$B$1) -> 0 | ... BV13: =_xll.EQNXTDZ($A$1,$B13,BV$1,$B$1) -> 0
A14: Operating & Manufacturing Expenses | B14: QTR_MFG_EXPS | C14: =_xll.EQNXTDZ($A$1,$B14,C$1,$B$1) -> 383.78 | D14: =_xll.EQNXTDZ($A$1,$B14,D$1,$B$1) -> 445.82 | E14: =_xll.EQNXTDZ($A$1,$B14,E$1,$B$1) -> 444.57 | F14: =_xll.EQNXTDZ($A$1,$B14,F$1,$B$1) -> 401.5 | G14: =_xll.EQNXTDZ($A$1,$B14,G$1,$B$1) -> 402.76 | H14: =_xll.EQNXTDZ($A$1,$B14,H$1,$B$1) -> 386.25 | I14: =_xll.EQNXTDZ($A$1,$B14,I$1,$B$1) -> 454.22 | J14: =_xll.EQNXTDZ($A$1,$B14,J$1,$B$1) -> 407.78 | ... BV14: =_xll.EQNXTDZ($A$1,$B14,BV$1,$B$1) -> 0
A15: Electricity Power & Fuel Cost | B15: QTR_ELECTRICITY_POWER_FUEL | C15: =_xll.EQNXTDZ($A$1,$B15,C$1,$B$1) -> 0 | D15: =_xll.EQNXTDZ($A$1,$B15,D$1,$B$1) -> 0 | E15: =_xll.EQNXTDZ($A$1,$B15,E$1,$B$1) -> 0 | F15: =_xll.EQNXTDZ($A$1,$B15,F$1,$B$1) -> 0 | G15: =_xll.EQNXTDZ($A$1,$B15,G$1,$B$1) -> 0 | H15: =_xll.EQNXTDZ($A$1,$B15,H$1,$B$1) -> 0 | I15: =_xll.EQNXTDZ($A$1,$B15,I$1,$B$1) -> 0 | J15: =_xll.EQNXTDZ($A$1,$B15,J$1,$B$1) -> 0 | ... BV15: =_xll.EQNXTDZ($A$1,$B15,BV$1,$B$1) -> 0
A16: Employee Cost | B16: QTR_EXPLOYEE_COST | C16: =_xll.EQNXTDZ($A$1,$B16,C$1,$B$1) -> 175.29 | D16: =_xll.EQNXTDZ($A$1,$B16,D$1,$B$1) -> 149.52 | E16: =_xll.EQNXTDZ($A$1,$B16,E$1,$B$1) -> 145.86 | F16: =_xll.EQNXTDZ($A$1,$B16,F$1,$B$1) -> 170.24 | G16: =_xll.EQNXTDZ($A$1,$B16,G$1,$B$1) -> 156.41 | H16: =_xll.EQNXTDZ($A$1,$B16,H$1,$B$1) -> 162.65 | I16: =_xll.EQNXTDZ($A$1,$B16,I$1,$B$1) -> 187.76 | J16: =_xll.EQNXTDZ($A$1,$B16,J$1,$B$1) -> 168.14 | ... BV16: =_xll.EQNXTDZ($A$1,$B16,BV$1,$B$1) -> 0
... A42: Consolidated PAT(after extra items) | B42: QTR_CONS_PAT_EXITM | C42: =_xll.EQNXTDZ($A$1,$B42,C$1,$B$1) -> 51.63 | D42: =_xll.EQNXTDZ($A$1,$B42,D$1,$B$1) -> 21.37 | E42: =_xll.EQNXTDZ($A$1,$B42,E$1,$B$1) -> 16.77 | F42: =_xll.EQNXTDZ($A$1,$B42,F$1,$B$1) -> 43.06 | G42: =_xll.EQNXTDZ($A$1,$B42,G$1,$B$1) -> 39.63 | H42: =_xll.EQNXTDZ($A$1,$B42,H$1,$B$1) -> 38.03 | I42: =_xll.EQNXTDZ($A$1,$B42,I$1,$B$1) -> 58.59 | J42: =_xll.EQNXTDZ($A$1,$B42,J$1,$B$1) -> 51.68 | ... BV42: =_xll.EQNXTDZ($A$1,$B42,BV$1,$B$1) -> 0
A44: Field Description | B44: Field Name
A45: Equity Capital | B45: QTR_EQUITY_CAP | C45: =_xll.EQNXTDZ($A$1,$B45,C$1,$B$1) -> 42.38 | D45: =_xll.EQNXTDZ($A$1,$B45,D$1,$B$1) -> 42.38 | E45: =_xll.EQNXTDZ($A$1,$B45,E$1,$B$1) -> 42.38 | F45: =_xll.EQNXTDZ($A$1,$B45,F$1,$B$1) -> 42.38 | G45: =_xll.EQNXTDZ($A$1,$B45,G$1,$B$1) -> 42.38 | H45: =_xll.EQNXTDZ($A$1,$B45,H$1,$B$1) -> 42.38 | I45: =_xll.EQNXTDZ($A$1,$B45,I$1,$B$1) -> 42.38 | J45: =_xll.EQNXTDZ($A$1,$B45,J$1,$B$1) -> 42.38 | ... BV45: =_xll.EQNXTDZ($A$1,$B45,BV$1,$B$1) -> 0
A46: Face Value | B46: QTR_FV | C46: =_xll.EQNXTDZ($A$1,$B46,C$1,$B$1) -> 2 | D46: =_xll.EQNXTDZ($A$1,$B46,D$1,$B$1) -> 2 | E46: =_xll.EQNXTDZ($A$1,$B46,E$1,$B$1) -> 2 | F46: =_xll.EQNXTDZ($A$1,$B46,F$1,$B$1) -> 2 | G46: =_xll.EQNXTDZ($A$1,$B46,G$1,$B$1) -> 2 | H46: =_xll.EQNXTDZ($A$1,$B46,H$1,$B$1) -> 2 | I46: =_xll.EQNXTDZ($A$1,$B46,I$1,$B$1) -> 2 | J46: =_xll.EQNXTDZ($A$1,$B46,J$1,$B$1) -> 2 | ... BV46: =_xll.EQNXTDZ($A$1,$B46,BV$1,$B$1) -> 0
A47: Month End | B47: BMONTH_MONTHEND | C47: =_xll.EQNXTDZ($A$1,$B47,C$5) -> 201206 | D47: =_xll.EQNXTDZ($A$1,$B47,D$5) -> 201209 | E47: =_xll.EQNXTDZ($A$1,$B47,E$5) -> 201212 | F47: =_xll.EQNXTDZ($A$1,$B47,F$5) -> 201303 | G47: =_xll.EQNXTDZ($A$1,$B47,G$5) -> 201306 | H47: =_xll.EQNXTDZ($A$1,$B47,H$5) -> 201309 | I47: =_xll.EQNXTDZ($A$1,$B47,I$5) -> 201312 | J47: =_xll.EQNXTDZ($A$1,$B47,J$5) -> 201403 | ... BV47: =_xll.EQNXTDZ($A$1,$B47,BV$5) -> 0
A48: Close | B48: BMONTH_CLOSE | C48: =_xll.EQNXTDZ($A$1,$B48,C$5) -> 800.8 | D48: =_xll.EQNXTDZ($A$1,$B48,D$5) -> 797.75 | E48: =_xll.EQNXTDZ($A$1,$B48,E$5) -> 700.4 | F48: =_xll.EQNXTDZ($A$1,$B48,F$5) -> 489.2 | G48: =_xll.EQNXTDZ($A$1,$B48,G$5) -> 610.85 | H48: =_xll.EQNXTDZ($A$1,$B48,H$5) -> 543.9 | I48: =_xll.EQNXTDZ($A$1,$B48,I$5) -> 692.8 | J48: =_xll.EQNXTDZ($A$1,$B48,J$5) -> 849.95 | ... BV48: =_xll.EQNXTDZ($A$1,$B48,BV$5) -> 0
A49: Total of Promoter and Promoter Group | B49: SHP_TPFTOTALPROMOTER | C49: =_xll.EQNXTDZ($A$1,$B49,C$5) -> 75 | D49: =_xll.EQNXTDZ($A$1,$B49,D$5) -> 75 | E49: =_xll.EQNXTDZ($A$1,$B49,E$5) -> 75 | F49: =_xll.EQNXTDZ($A$1,$B49,F$5) -> 75 | G49: =_xll.EQNXTDZ($A$1,$B49,G$5) -> 75 | H49: =_xll.EQNXTDZ($A$1,$B49,H$5) -> 75 | I49: =_xll.EQNXTDZ($A$1,$B49,I$5) -> 75 | J49: =_xll.EQNXTDZ($A$1,$B49,J$5) -> 75 | ... BV49: =_xll.EQNXTDZ($A$1,$B49,BV$5) -> 0
A50: Total of Promoter and Promoter Group Pledged | B50: SHP_PSHFTOTALPROMOTER | C50: =_xll.EQNXTDZ($A$1,$B50,C$5) -> 0 | D50: =_xll.EQNXTDZ($A$1,$B50,D$5) -> 0 | E50: =_xll.EQNXTDZ($A$1,$B50,E$5) -> 0 | F50: =_xll.EQNXTDZ($A$1,$B50,F$5) -> 0 | G50: =_xll.EQNXTDZ($A$1,$B50,G$5) -> 0 | H50: =_xll.EQNXTDZ($A$1,$B50,H$5) -> 0 | I50: =_xll.EQNXTDZ($A$1,$B50,I$5) -> 0 | J50: =_xll.EQNXTDZ($A$1,$B50,J$5) -> 0 | ... BV50: =_xll.EQNXTDZ($A$1,$B50,BV$5) -> 0
A54: Field Description | B54: Field Name | C54: =_xll.EQNXTDZ($A$1,$B54,C$5) -> 0 | D54: =_xll.EQNXTDZ($A$1,$B54,D$5) -> 0 | E54: =_xll.EQNXTDZ($A$1,$B54,E$5) -> 0 | F54: =_xll.EQNXTDZ($A$1,$B54,F$5) -> 0 | G54: =_xll.EQNXTDZ($A$1,$B54,G$5) -> 0 | H54: =_xll.EQNXTDZ($A$1,$B54,H$5) -> 0 | I54: =_xll.EQNXTDZ($A$1,$B54,I$5) -> 0 | J54: =_xll.EQNXTDZ($A$1,$B54,J$5) -> 0 | ... BV54: =_xll.EQNXTDZ($A$1,$B54,BV$5) -> 0
A55: Year End | B55: QTRB_DATE_END | C55: =_xll.EQNXTDZ($A$1,$B55,C$5,$B$1) -> 201206 | D55: =_xll.EQNXTDZ($A$1,$B55,D$5,$B$1) -> 0 | E55: =_xll.EQNXTDZ($A$1,$B55,E$5,$B$1) -> 201212 | F55: =_xll.EQNXTDZ($A$1,$B55,F$5,$B$1) -> 0 | G55: =_xll.EQNXTDZ($A$1,$B55,G$5,$B$1) -> 201306 | H55: =_xll.EQNXTDZ($A$1,$B55,H$5,$B$1) -> 0 | I55: =_xll.EQNXTDZ($A$1,$B55,I$5,$B$1) -> 201312 | J55: =_xll.EQNXTDZ($A$1,$B55,J$5,$B$1) -> 0 | ... BV55: =_xll.EQNXTDZ($A$1,$B55,BV$5,$B$1) -> 0
A56: Share Capital | B56: QTRB_SHARE_CAPITAL | C56: =_xll.EQNXTDZ($A$1,$B56,C$5,$B$1) -> 42.38 | D56: =_xll.EQNXTDZ($A$1,$B56,D$5,$B$1) -> 0 | E56: =_xll.EQNXTDZ($A$1,$B56,E$5,$B$1) -> 42.38 | F56: =_xll.EQNXTDZ($A$1,$B56,F$5,$B$1) -> 0 | G56: =_xll.EQNXTDZ($A$1,$B56,G$5,$B$1) -> 42.38 | H56: =_xll.EQNXTDZ($A$1,$B56,H$5,$B$1) -> 0 | I56: =_xll.EQNXTDZ($A$1,$B56,I$5,$B$1) -> 42.38 | J56: =_xll.EQNXTDZ($A$1,$B56,J$5,$B$1) -> 0 | ... BV56: =_xll.EQNXTDZ($A$1,$B56,BV$5,$B$1) -> 0
A57: Share Warrants & outstandings | B57: QTRB_SHAREWARNDOUT | C57: =_xll.EQNXTDZ($A$1,$B57,C$5,$B$1) -> 0 | D57: =_xll.EQNXTDZ($A$1,$B57,D$5,$B$1) -> 0 | E57: =_xll.EQNXTDZ($A$1,$B57,E$5,$B$1) -> 0 | F57: =_xll.EQNXTDZ($A$1,$B57,F$5,$B$1) -> 0 | G57: =_xll.EQNXTDZ($A$1,$B57,G$5,$B$1) -> 0 | H57: =_xll.EQNXTDZ($A$1,$B57,H$5,$B$1) -> 0 | I57: =_xll.EQNXTDZ($A$1,$B57,I$5,$B$1) -> 0 | J57: =_xll.EQNXTDZ($A$1,$B57,J$5,$B$1) -> 0 | ... BV57: =_xll.EQNXTDZ($A$1,$B57,BV$5,$B$1) -> 0
A58: Reserves & Surplus | B58: QTRB_RESERVE | C58: =_xll.EQNXTDZ($A$1,$B58,C$5,$B$1) -> 2591.41 | D58: =_xll.EQNXTDZ($A$1,$B58,D$5,$B$1) -> 0 | E58: =_xll.EQNXTDZ($A$1,$B58,E$5,$B$1) -> 2559.26 | F58: =_xll.EQNXTDZ($A$1,$B58,F$5,$B$1) -> 0 | G58: =_xll.EQNXTDZ($A$1,$B58,G$5,$B$1) -> 2615.36 | H58: =_xll.EQNXTDZ($A$1,$B58,H$5,$B$1) -> 0 | I58: =_xll.EQNXTDZ($A$1,$B58,I$5,$B$1) -> 2635.18 | J58: =_xll.EQNXTDZ($A$1,$B58,J$5,$B$1) -> 0 | ... BV58: =_xll.EQNXTDZ($A$1,$B58,BV$5,$B$1) -> 0
A59: Shareholder's Funds | B59: QTRB_SHAREHODERS_FUNDS | C59: =_xll.EQNXTDZ($A$1,$B59,C$5,$B$1) -> 2633.79 | D59: =_xll.EQNXTDZ($A$1,$B59,D$5,$B$1) -> 0 | E59: =_xll.EQNXTDZ($A$1,$B59,E$5,$B$1) -> 2601.64 | F59: =_xll.EQNXTDZ($A$1,$B59,F$5,$B$1) -> 0 | G59: =_xll.EQNXTDZ($A$1,$B59,G$5,$B$1) -> 2657.74 | H59: =_xll.EQNXTDZ($A$1,$B59,H$5,$B$1) -> 0 | I59: =_xll.EQNXTDZ($A$1,$B59,I$5,$B$1) -> 2677.56 | J59: =_xll.EQNXTDZ($A$1,$B59,J$5,$B$1) -> 0 | ... BV59: =_xll.EQNXTDZ($A$1,$B59,BV$5,$B$1) -> 0
A60: Minority Interest | B60: QTRB_MINORITY_INTEREST_BS | C60: =_xll.EQNXTDZ($A$1,$B60,C$5,$B$1) -> 0 | D60: =_xll.EQNXTDZ($A$1,$B60,D$5,$B$1) -> 0 | E60: =_xll.EQNXTDZ($A$1,$B60,E$5,$B$1) -> 0 | F60: =_xll.EQNXTDZ($A$1,$B60,F$5,$B$1) -> 0 | G60: =_xll.EQNXTDZ($A$1,$B60,G$5,$B$1) -> 0 | H60: =_xll.EQNXTDZ($A$1,$B60,H$5,$B$1) -> 0 | I60: =_xll.EQNXTDZ($A$1,$B60,I$5,$B$1) -> 0 | J60: =_xll.EQNXTDZ($A$1,$B60,J$5,$B$1) -> 0 | ... BV60: =_xll.EQNXTDZ($A$1,$B60,BV$5,$B$1) -> 0
A61: Long Term Borrowings | B61: QTRB_TOTAL_DEBTS | C61: =_xll.EQNXTDZ($A$1,$B61,C$5,$B$1) -> 0 | D61: =_xll.EQNXTDZ($A$1,$B61,D$5,$B$1) -> 0 | E61: =_xll.EQNXTDZ($A$1,$B61,E$5,$B$1) -> 0 | F61: =_xll.EQNXTDZ($A$1,$B61,F$5,$B$1) -> 0 | G61: =_xll.EQNXTDZ($A$1,$B61,G$5,$B$1) -> 0 | H61: =_xll.EQNXTDZ($A$1,$B61,H$5,$B$1) -> 0 | I61: =_xll.EQNXTDZ($A$1,$B61,I$5,$B$1) -> 0 | J61: =_xll.EQNXTDZ($A$1,$B61,J$5,$B$1) -> 0 | ... BV61: =_xll.EQNXTDZ($A$1,$B61,BV$5,$B$1) -> 0
A62: Secured Loans | B62: QTRB_SECURED_LOANS | C62: =_xll.EQNXTDZ($A$1,$B62,C$5,$B$1) -> 0 | D62: =_xll.EQNXTDZ($A$1,$B62,D$5,$B$1) -> 0 | E62: =_xll.EQNXTDZ($A$1,$B62,E$5,$B$1) -> 0 | F62: =_xll.EQNXTDZ($A$1,$B62,F$5,$B$1) -> 0 | G62: =_xll.EQNXTDZ($A$1,$B62,G$5,$B$1) -> 0 | H62: =_xll.EQNXTDZ($A$1,$B62,H$5,$B$1) -> 0 | I62: =_xll.EQNXTDZ($A$1,$B62,I$5,$B$1) -> 0 | J62: =_xll.EQNXTDZ($A$1,$B62,J$5,$B$1) -> 0 | ... BV62: =_xll.EQNXTDZ($A$1,$B62,BV$5,$B$1) -> 0
A63: Unsecured Loans | B63: QTRB_UNSECURED_LOANS_NF | C63: =_xll.EQNXTDZ($A$1,$B63,C$5,$B$1) -> 0 | D63: =_xll.EQNXTDZ($A$1,$B63,D$5,$B$1) -> 0 | E63: =_xll.EQNXTDZ($A$1,$B63,E$5,$B$1) -> 0 | F63: =_xll.EQNXTDZ($A$1,$B63,F$5,$B$1) -> 0 | G63: =_xll.EQNXTDZ($A$1,$B63,G$5,$B$1) -> 0 | H63: =_xll.EQNXTDZ($A$1,$B63,H$5,$B$1) -> 0 | I63: =_xll.EQNXTDZ($A$1,$B63,I$5,$B$1) -> 0 | J63: =_xll.EQNXTDZ($A$1,$B63,J$5,$B$1) -> 0 | ... BV63: =_xll.EQNXTDZ($A$1,$B63,BV$5,$B$1) -> 0
A64: Other Long Term Liabilities | B64: QTRB_OTHER_LT_LIABILITIES | C64: =_xll.EQNXTDZ($A$1,$B64,C$5,$B$1) -> 3.84 | D64: =_xll.EQNXTDZ($A$1,$B64,D$5,$B$1) -> 0 | E64: =_xll.EQNXTDZ($A$1,$B64,E$5,$B$1) -> 3.89 | F64: =_xll.EQNXTDZ($A$1,$B64,F$5,$B$1) -> 0 | G64: =_xll.EQNXTDZ($A$1,$B64,G$5,$B$1) -> 4.04 | H64: =_xll.EQNXTDZ($A$1,$B64,H$5,$B$1) -> 0 | I64: =_xll.EQNXTDZ($A$1,$B64,I$5,$B$1) -> 4.17 | J64: =_xll.EQNXTDZ($A$1,$B64,J$5,$B$1) -> 0 | ... BV64: =_xll.EQNXTDZ($A$1,$B64,BV$5,$B$1) -> 0
A65: Long Term Trade Payables | B65: QTRB_LT_TRADE_PAYABLE | C65: =_xll.EQNXTDZ($A$1,$B65,C$5,$B$1) -> 0 | D65: =_xll.EQNXTDZ($A$1,$B65,D$5,$B$1) -> 0 | E65: =_xll.EQNXTDZ($A$1,$B65,E$5,$B$1) -> 5.71 | F65: =_xll.EQNXTDZ($A$1,$B65,F$5,$B$1) -> 0 | G65: =_xll.EQNXTDZ($A$1,$B65,G$5,$B$1) -> 0 | H65: =_xll.EQNXTDZ($A$1,$B65,H$5,$B$1) -> 0 | I65: =_xll.EQNXTDZ($A$1,$B65,I$5,$B$1) -> 0 | J65: =_xll.EQNXTDZ($A$1,$B65,J$5,$B$1) -> 0 | ... BV65: =_xll.EQNXTDZ($A$1,$B65,BV$5,$B$1) -> 0
A66: Lont Term Provisions | B66: QTRB_LT_PROVISIONS | C66: =_xll.EQNXTDZ($A$1,$B66,C$5,$B$1) -> 5.71 | D66: =_xll.EQNXTDZ($A$1,$B66,D$5,$B$1) -> 0 | E66: =_xll.EQNXTDZ($A$1,$B66,E$5,$B$1) -> 0 | F66: =_xll.EQNXTDZ($A$1,$B66,F$5,$B$1) -> 0 | G66: =_xll.EQNXTDZ($A$1,$B66,G$5,$B$1) -> 5.71 | H66: =_xll.EQNXTDZ($A$1,$B66,H$5,$B$1) -> 0 | I66: =_xll.EQNXTDZ($A$1,$B66,I$5,$B$1) -> 18.11 | J66: =_xll.EQNXTDZ($A$1,$B66,J$5,$B$1) -> 0 | ... BV66: =_xll.EQNXTDZ($A$1,$B66,BV$5,$B$1) -> 0
... A97: Total Assets | B97: QTRB_TOTAL_APPLICATIONS | C97: =_xll.EQNXTDZ($A$1,$B97,C$5,$B$1) -> 2643.34 | D97: =_xll.EQNXTDZ($A$1,$B97,D$5,$B$1) -> 0 | E97: =_xll.EQNXTDZ($A$1,$B97,E$5,$B$1) -> 2611.24 | F97: =_xll.EQNXTDZ($A$1,$B97,F$5,$B$1) -> 0 | G97: =_xll.EQNXTDZ($A$1,$B97,G$5,$B$1) -> 2667.49 | H97: =_xll.EQNXTDZ($A$1,$B97,H$5,$B$1) -> 0 | I97: =_xll.EQNXTDZ($A$1,$B97,I$5,$B$1) -> 2699.84 | J97: =_xll.EQNXTDZ($A$1,$B97,J$5,$B$1) -> 0 | ... BV97: =_xll.EQNXTDZ($A$1,$B97,BV$5,$B$1) -> 0

Sheet Annual Raw
A1: 100002 | B1: X | C1: 200112 | D1: 200212 | E1: 200312 | F1: 200412 | G1: 200512 | H1: 200612 | I1: 200712 | J1: 200812 | K1: 200912 | L1: 201012 | M1: 201112 | N1: 201212 | O1: 201312 | P1: 201412 | Q1: 201512 | R1: 201612 | S1: 201712 | T1: 201812 | U1: 201912 | V1: 202012 | W1: 202112 | X1: 202212 | Y1: 202312 | Z1: 202412 | AA1: 202512 | AB1: 202612 | AC1: 202712 | AD1: 202812 | AE1: 202912 | AF1: 203012
A3: Field Description | B3: Field Name
A4: Company Name | B4: CD_COMPNAME | C4: =_xll.EQNXTDZ(A1,B4,"L") -> ABB India Ltd.
A5: Year End | B5: PL_YEAR_END | C5: =_xll.EQNXTDZ($A$1,$B5,C$1,$B$1) -> 200112 | D5: =_xll.EQNXTDZ($A$1,$B5,D$1,$B$1) -> 200212 | E5: =_xll.EQNXTDZ($A$1,$B5,E$1,$B$1) -> 200312 | F5: =_xll.EQNXTDZ($A$1,$B5,F$1,$B$1) -> 200412 | G5: =_xll.EQNXTDZ($A$1,$B5,G$1,$B$1) -> 200512 | H5: =_xll.EQNXTDZ($A$1,$B5,H$1,$B$1) -> 200612 | I5: =_xll.EQNXTDZ($A$1,$B5,I$1,$B$1) -> 200712 | J5: =_xll.EQNXTDZ($A$1,$B5,J$1,$B$1) -> 200812 | ... AF5: =_xll.EQNXTDZ($A$1,$B5,AF$1,$B$1) -> 0
A6: Sales Turnover | B6: PL_TOTAL_GROSS_SALES | C6: =_xll.EQNXTDZ($A$1,$B6,C$1,$B$1) -> 1041.599 | D6: =_xll.EQNXTDZ($A$1,$B6,D$1,$B$1) -> 1175.7576 | E6: =_xll.EQNXTDZ($A$1,$B6,E$1,$B$1) -> 1576.73 | F6: =_xll.EQNXTDZ($A$1,$B6,F$1,$B$1) -> 2445.7977 | G6: =_xll.EQNXTDZ($A$1,$B6,G$1,$B$1) -> 3199.9328 | H6: =_xll.EQNXTDZ($A$1,$B6,H$1,$B$1) -> 4604.5615 | I6: =_xll.EQNXTDZ($A$1,$B6,I$1,$B$1) -> 6383.2682 | J6: =_xll.EQNXTDZ($A$1,$B6,J$1,$B$1) -> 7340.2391 | ... AF6: =_xll.EQNXTDZ($A$1,$B6,AF$1,$B$1) -> 0
A7: Less: Inter divisional transfers | B7: PL_INTER_DIV_TRF | C7: =_xll.EQNXTDZ($A$1,$B7,C$1,$B$1) -> 0 | D7: =_xll.EQNXTDZ($A$1,$B7,D$1,$B$1) -> 0 | E7: =_xll.EQNXTDZ($A$1,$B7,E$1,$B$1) -> 0 | F7: =_xll.EQNXTDZ($A$1,$B7,F$1,$B$1) -> 0 | G7: =_xll.EQNXTDZ($A$1,$B7,G$1,$B$1) -> 0 | H7: =_xll.EQNXTDZ($A$1,$B7,H$1,$B$1) -> 0 | I7: =_xll.EQNXTDZ($A$1,$B7,I$1,$B$1) -> 0 | J7: =_xll.EQNXTDZ($A$1,$B7,J$1,$B$1) -> 0 | ... AF7: =_xll.EQNXTDZ($A$1,$B7,AF$1,$B$1) -> 0
A8: Less: Sales Returns | B8: PL_SALES_RETURN | C8: =_xll.EQNXTDZ($A$1,$B8,C$1,$B$1) -> 0 | D8: =_xll.EQNXTDZ($A$1,$B8,D$1,$B$1) -> 0 | E8: =_xll.EQNXTDZ($A$1,$B8,E$1,$B$1) -> 0 | F8: =_xll.EQNXTDZ($A$1,$B8,F$1,$B$1) -> 0 | G8: =_xll.EQNXTDZ($A$1,$B8,G$1,$B$1) -> 0 | H8: =_xll.EQNXTDZ($A$1,$B8,H$1,$B$1) -> 0 | I8: =_xll.EQNXTDZ($A$1,$B8,I$1,$B$1) -> 0 | J8: =_xll.EQNXTDZ($A$1,$B8,J$1,$B$1) -> 0 | ... AF8: =_xll.EQNXTDZ($A$1,$B8,AF$1,$B$1) -> 0
A9: Less: Excise | B9: PL_EXCISE | C9: =_xll.EQNXTDZ($A$1,$B9,C$1,$B$1) -> 0 | D9: =_xll.EQNXTDZ($A$1,$B9,D$1,$B$1) -> 0 | E9: =_xll.EQNXTDZ($A$1,$B9,E$1,$B$1) -> 108.3725 | F9: =_xll.EQNXTDZ($A$1,$B9,F$1,$B$1) -> 185.5751 | G9: =_xll.EQNXTDZ($A$1,$B9,G$1,$B$1) -> 236.8802 | H9: =_xll.EQNXTDZ($A$1,$B9,H$1,$B$1) -> 330.5522 | I9: =_xll.EQNXTDZ($A$1,$B9,I$1,$B$1) -> 452.9568 | J9: =_xll.EQNXTDZ($A$1,$B9,J$1,$B$1) -> 503.2076 | ... AF9: =_xll.EQNXTDZ($A$1,$B9,AF$1,$B$1) -> 0
A10: Net Sales | B10: PL_NET_SALES | C10: =_xll.EQNXTDZ($A$1,$B10,C$1,$B$1) -> 1041.599 | D10: =_xll.EQNXTDZ($A$1,$B10,D$1,$B$1) -> 1175.7576 | E10: =_xll.EQNXTDZ($A$1,$B10,E$1,$B$1) -> 1468.3575 | F10: =_xll.EQNXTDZ($A$1,$B10,F$1,$B$1) -> 2260.2226 | G10: =_xll.EQNXTDZ($A$1,$B10,G$1,$B$1) -> 2963.0526 | H10: =_xll.EQNXTDZ($A$1,$B10,H$1,$B$1) -> 4274.0093 | I10: =_xll.EQNXTDZ($A$1,$B10,I$1,$B$1) -> 5930.3114 | J10: =_xll.EQNXTDZ($A$1,$B10,J$1,$B$1) -> 6837.0315 | ... AF10: =_xll.EQNXTDZ($A$1,$B10,AF$1,$B$1) -> 0
A11: Increase/Decrease in Stock | B11: PL_INC_DEC_INVENTORY | C11: =_xll.EQNXTDZ($A$1,$B11,C$1,$B$1) -> 0.9139 | D11: =_xll.EQNXTDZ($A$1,$B11,D$1,$B$1) -> 5.4548 | E11: =_xll.EQNXTDZ($A$1,$B11,E$1,$B$1) -> 9.3257 | F11: =_xll.EQNXTDZ($A$1,$B11,F$1,$B$1) -> -23.5813 | G11: =_xll.EQNXTDZ($A$1,$B11,G$1,$B$1) -> -7.7979 | H11: =_xll.EQNXTDZ($A$1,$B11,H$1,$B$1) -> -53.0166 | I11: =_xll.EQNXTDZ($A$1,$B11,I$1,$B$1) -> -52.0728 | J11: =_xll.EQNXTDZ($A$1,$B11,J$1,$B$1) -> -73.7869 | ... AF11: =_xll.EQNXTDZ($A$1,$B11,AF$1,$B$1) -> 0
A12: Raw Material Consumed | B12: PL_RAW_MATRS_CONSUMED | C12: =_xll.EQNXTDZ($A$1,$B12,C$1,$B$1) -> 419.0008 | D12: =_xll.EQNXTDZ($A$1,$B12,D$1,$B$1) -> 467.2112 | E12: =_xll.EQNXTDZ($A$1,$B12,E$1,$B$1) -> 527.9141 | F12: =_xll.EQNXTDZ($A$1,$B12,F$1,$B$1) -> 719.4776 | G12: =_xll.EQNXTDZ($A$1,$B12,G$1,$B$1) -> 875.9128 | H12: =_xll.EQNXTDZ($A$1,$B12,H$1,$B$1) -> 1265.495 | I12: =_xll.EQNXTDZ($A$1,$B12,I$1,$B$1) -> 1577.0845 | J12: =_xll.EQNXTDZ($A$1,$B12,J$1,$B$1) -> 2083.501 | ... AF12: =_xll.EQNXTDZ($A$1,$B12,AF$1,$B$1) -> 0
A13: Power & Fuel Cost | B13: PL_POWER_FUEL | C13: =_xll.EQNXTDZ($A$1,$B13,C$1,$B$1) -> 9.3438 | D13: =_xll.EQNXTDZ($A$1,$B13,D$1,$B$1) -> 9.5228 | E13: =_xll.EQNXTDZ($A$1,$B13,E$1,$B$1) -> 9.1404 | F13: =_xll.EQNXTDZ($A$1,$B13,F$1,$B$1) -> 12.178 | G13: =_xll.EQNXTDZ($A$1,$B13,G$1,$B$1) -> 14.9088 | H13: =_xll.EQNXTDZ($A$1,$B13,H$1,$B$1) -> 19.0068 | I13: =_xll.EQNXTDZ($A$1,$B13,I$1,$B$1) -> 22.3333 | J13: =_xll.EQNXTDZ($A$1,$B13,J$1,$B$1) -> 27.4312 | ... AF13: =_xll.EQNXTDZ($A$1,$B13,AF$1,$B$1) -> 0
A14: Employee Cost | B14: PL_EMPLOYEES | C14: =_xll.EQNXTDZ($A$1,$B14,C$1,$B$1) -> 112.5039 | D14: =_xll.EQNXTDZ($A$1,$B14,D$1,$B$1) -> 120.0603 | E14: =_xll.EQNXTDZ($A$1,$B14,E$1,$B$1) -> 115.2921 | F14: =_xll.EQNXTDZ($A$1,$B14,F$1,$B$1) -> 135.0213 | G14: =_xll.EQNXTDZ($A$1,$B14,G$1,$B$1) -> 176.864 | H14: =_xll.EQNXTDZ($A$1,$B14,H$1,$B$1) -> 238.5327 | I14: =_xll.EQNXTDZ($A$1,$B14,I$1,$B$1) -> 303.5365 | J14: =_xll.EQNXTDZ($A$1,$B14,J$1,$B$1) -> 400.3824 | ... AF14: =_xll.EQNXTDZ($A$1,$B14,AF$1,$B$1) -> 0
A15: Operating & Manufacturing Expenses | B15: PL_GEN_OTHER_MFG_EXPS | C15: =_xll.EQNXTDZ($A$1,$B15,C$1,$B$1) -> 279.5401 | D15: =_xll.EQNXTDZ($A$1,$B15,D$1,$B$1) -> 320.9275 | E15: =_xll.EQNXTDZ($A$1,$B15,E$1,$B$1) -> 514.5465 | F15: =_xll.EQNXTDZ($A$1,$B15,F$1,$B$1) -> 1003.1039 | G15: =_xll.EQNXTDZ($A$1,$B15,G$1,$B$1) -> 1316.8397 | H15: =_xll.EQNXTDZ($A$1,$B15,H$1,$B$1) -> 2004.3239 | I15: =_xll.EQNXTDZ($A$1,$B15,I$1,$B$1) -> 2902.9148 | J15: =_xll.EQNXTDZ($A$1,$B15,J$1,$B$1) -> 3117.4154 | ... AF15: =_xll.EQNXTDZ($A$1,$B15,AF$1,$B$1) -> 0
A16: Cost of Software development | B16: PL_COST_SW | C16: =_xll.EQNXTDZ($A$1,$B16,C$1,$B$1) -> 0 | D16: =_xll.EQNXTDZ($A$1,$B16,D$1,$B$1) -> 0 | E16: =_xll.EQNXTDZ($A$1,$B16,E$1,$B$1) -> 0 | F16: =_xll.EQNXTDZ($A$1,$B16,F$1,$B$1) -> 0 | G16: =_xll.EQNXTDZ($A$1,$B16,G$1,$B$1) -> 0 | H16: =_xll.EQNXTDZ($A$1,$B16,H$1,$B$1) -> 0 | I16: =_xll.EQNXTDZ($A$1,$B16,I$1,$B$1) -> 0 | J16: =_xll.EQNXTDZ($A$1,$B16,J$1,$B$1) -> 0 | ... AF16: =_xll.EQNXTDZ($A$1,$B16,AF$1,$B$1) -> 0
... A36: Profit After Tax from Discontinued Operations | B36: PL_PAT_DIS_OP | C36: =_xll.EQNXTDZ($A$1,$B36,C$1,$B$1) -> 0 | D36: =_xll.EQNXTDZ($A$1,$B36,D$1,$B$1) -> 0 | E36: =_xll.EQNXTDZ($A$1,$B36,E$1,$B$1) -> 0 | F36: =_xll.EQNXTDZ($A$1,$B36,F$1,$B$1) -> 0 | G36: =_xll.EQNXTDZ($A$1,$B36,G$1,$B$1) -> 0 | H36: =_xll.EQNXTDZ($A$1,$B36,H$1,$B$1) -> 0 | I36: =_xll.EQNXTDZ($A$1,$B36,I$1,$B$1) -> 0 | J36: =_xll.EQNXTDZ($A$1,$B36,J$1,$B$1) -> 0 | ... AF36: =_xll.EQNXTDZ($A$1,$B36,AF$1,$B$1) -> 0
A39: Field Description | B39: Field Name
A40: Year End | B40: BS_YEAR_END | C40: =_xll.EQNXTDZ($A$1,$B40,C$1,$B$1) -> 200112 | D40: =_xll.EQNXTDZ($A$1,$B40,D$1,$B$1) -> 200212 | E40: =_xll.EQNXTDZ($A$1,$B40,E$1,$B$1) -> 200312 | F40: =_xll.EQNXTDZ($A$1,$B40,F$1,$B$1) -> 200412 | G40: =_xll.EQNXTDZ($A$1,$B40,G$1,$B$1) -> 200512 | H40: =_xll.EQNXTDZ($A$1,$B40,H$1,$B$1) -> 200612 | I40: =_xll.EQNXTDZ($A$1,$B40,I$1,$B$1) -> 200712 | J40: =_xll.EQNXTDZ($A$1,$B40,J$1,$B$1) -> 200812 | ... AF40: =_xll.EQNXTDZ($A$1,$B40,AF$1,$B$1) -> 0
A41: Share Capital | B41: BS_SHARE_CAPITAL | C41: =_xll.EQNXTDZ($A$1,$B41,C$1,$B$1) -> 49.8817 | D41: =_xll.EQNXTDZ($A$1,$B41,D$1,$B$1) -> 42.3817 | E41: =_xll.EQNXTDZ($A$1,$B41,E$1,$B$1) -> 42.3817 | F41: =_xll.EQNXTDZ($A$1,$B41,F$1,$B$1) -> 42.3817 | G41: =_xll.EQNXTDZ($A$1,$B41,G$1,$B$1) -> 42.3817 | H41: =_xll.EQNXTDZ($A$1,$B41,H$1,$B$1) -> 42.3817 | I41: =_xll.EQNXTDZ($A$1,$B41,I$1,$B$1) -> 42.3817 | J41: =_xll.EQNXTDZ($A$1,$B41,J$1,$B$1) -> 42.3817 | ... AF41: =_xll.EQNXTDZ($A$1,$B41,AF$1,$B$1) -> 0
A42: Share Warrants & Outstandings | B42: BS_SHAREWROUTST | C42: =_xll.EQNXTDZ($A$1,$B42,C$1,$B$1) -> 0 | D42: =_xll.EQNXTDZ($A$1,$B42,D$1,$B$1) -> 0 | E42: =_xll.EQNXTDZ($A$1,$B42,E$1,$B$1) -> 0 | F42: =_xll.EQNXTDZ($A$1,$B42,F$1,$B$1) -> 0 | G42: =_xll.EQNXTDZ($A$1,$B42,G$1,$B$1) -> 0 | H42: =_xll.EQNXTDZ($A$1,$B42,H$1,$B$1) -> 0 | I42: =_xll.EQNXTDZ($A$1,$B42,I$1,$B$1) -> 0 | J42: =_xll.EQNXTDZ($A$1,$B42,J$1,$B$1) -> 0 | ... AF42: =_xll.EQNXTDZ($A$1,$B42,AF$1,$B$1) -> 0
A43: Total Reserves | B43: BS_RESERVE | C43: =_xll.EQNXTDZ($A$1,$B43,C$1,$B$1) -> 397.8658 | D43: =_xll.EQNXTDZ($A$1,$B43,D$1,$B$1) -> 469.7902 | E43: =_xll.EQNXTDZ($A$1,$B43,E$1,$B$1) -> 561.7718 | F43: =_xll.EQNXTDZ($A$1,$B43,F$1,$B$1) -> 682.28 | G43: =_xll.EQNXTDZ($A$1,$B43,G$1,$B$1) -> 861.7462 | H43: =_xll.EQNXTDZ($A$1,$B43,H$1,$B$1) -> 1153.4601 | I43: =_xll.EQNXTDZ($A$1,$B43,I$1,$B$1) -> 1583.9626 | J43: =_xll.EQNXTDZ($A$1,$B43,J$1,$B$1) -> 2076.5715 | ... AF43: =_xll.EQNXTDZ($A$1,$B43,AF$1,$B$1) -> 0
A44: Shareholder's Funds | B44: BS_SHAREHODERS_FUNDS | C44: =_xll.EQNXTDZ($A$1,$B44,C$1,$B$1) -> 447.7475 | D44: =_xll.EQNXTDZ($A$1,$B44,D$1,$B$1) -> 512.1719 | E44: =_xll.EQNXTDZ($A$1,$B44,E$1,$B$1) -> 604.1535 | F44: =_xll.EQNXTDZ($A$1,$B44,F$1,$B$1) -> 724.6617 | G44: =_xll.EQNXTDZ($A$1,$B44,G$1,$B$1) -> 904.1279 | H44: =_xll.EQNXTDZ($A$1,$B44,H$1,$B$1) -> 1195.8418 | I44: =_xll.EQNXTDZ($A$1,$B44,I$1,$B$1) -> 1626.3443 | J44: =_xll.EQNXTDZ($A$1,$B44,J$1,$B$1) -> 2118.9532 | ... AF44: =_xll.EQNXTDZ($A$1,$B44,AF$1,$B$1) -> 0
A45: Minority Interest | B45: BS_MINORITY_INTEREST | C45: =_xll.EQNXTDZ($A$1,$B45,C$1,$B$1) -> 0 | D45: =_xll.EQNXTDZ($A$1,$B45,D$1,$B$1) -> 0 | E45: =_xll.EQNXTDZ($A$1,$B45,E$1,$B$1) -> 0 | F45: =_xll.EQNXTDZ($A$1,$B45,F$1,$B$1) -> 0 | G45: =_xll.EQNXTDZ($A$1,$B45,G$1,$B$1) -> 0 | H45: =_xll.EQNXTDZ($A$1,$B45,H$1,$B$1) -> 0 | I45: =_xll.EQNXTDZ($A$1,$B45,I$1,$B$1) -> 0 | J45: =_xll.EQNXTDZ($A$1,$B45,J$1,$B$1) -> 0 | ... AF45: =_xll.EQNXTDZ($A$1,$B45,AF$1,$B$1) -> 0
A46: Long-Term Borrowings | B46: BS_LTRM_BORROWING | C46: =_xll.EQNXTDZ($A$1,$B46,C$1,$B$1) -> 0 | D46: =_xll.EQNXTDZ($A$1,$B46,D$1,$B$1) -> 0 | E46: =_xll.EQNXTDZ($A$1,$B46,E$1,$B$1) -> 0 | F46: =_xll.EQNXTDZ($A$1,$B46,F$1,$B$1) -> 0 | G46: =_xll.EQNXTDZ($A$1,$B46,G$1,$B$1) -> 0 | H46: =_xll.EQNXTDZ($A$1,$B46,H$1,$B$1) -> 0 | I46: =_xll.EQNXTDZ($A$1,$B46,I$1,$B$1) -> 0 | J46: =_xll.EQNXTDZ($A$1,$B46,J$1,$B$1) -> 0 | ... AF46: =_xll.EQNXTDZ($A$1,$B46,AF$1,$B$1) -> 0
A47: Secured Loans | B47: BS_SECURED_LOANS | C47: =_xll.EQNXTDZ($A$1,$B47,C$1,$B$1) -> 3.2882 | D47: =_xll.EQNXTDZ($A$1,$B47,D$1,$B$1) -> 4.4597 | E47: =_xll.EQNXTDZ($A$1,$B47,E$1,$B$1) -> 2.9632 | F47: =_xll.EQNXTDZ($A$1,$B47,F$1,$B$1) -> 1.4312 | G47: =_xll.EQNXTDZ($A$1,$B47,G$1,$B$1) -> 2.6957 | H47: =_xll.EQNXTDZ($A$1,$B47,H$1,$B$1) -> 1.5457 | I47: =_xll.EQNXTDZ($A$1,$B47,I$1,$B$1) -> 0.566 | J47: =_xll.EQNXTDZ($A$1,$B47,J$1,$B$1) -> 0.0202 | ... AF47: =_xll.EQNXTDZ($A$1,$B47,AF$1,$B$1) -> 0
A48: Unsecured Loans | B48: BS_UNSECURED_LOANS_NF | C48: =_xll.EQNXTDZ($A$1,$B48,C$1,$B$1) -> 7.5085 | D48: =_xll.EQNXTDZ($A$1,$B48,D$1,$B$1) -> 7.9101 | E48: =_xll.EQNXTDZ($A$1,$B48,E$1,$B$1) -> 7.1409 | F48: =_xll.EQNXTDZ($A$1,$B48,F$1,$B$1) -> 0.062 | G48: =_xll.EQNXTDZ($A$1,$B48,G$1,$B$1) -> 0.031 | H48: =_xll.EQNXTDZ($A$1,$B48,H$1,$B$1) -> 0 | I48: =_xll.EQNXTDZ($A$1,$B48,I$1,$B$1) -> 0 | J48: =_xll.EQNXTDZ($A$1,$B48,J$1,$B$1) -> 0 | ... AF48: =_xll.EQNXTDZ($A$1,$B48,AF$1,$B$1) -> 0
A49: Deferred Tax Assets / Liabilities | B49: BS_NET_DEF_TAX_NF | C49: =_xll.EQNXTDZ($A$1,$B49,C$1,$B$1) -> 13.9071 | D49: =_xll.EQNXTDZ($A$1,$B49,D$1,$B$1) -> 15.0271 | E49: =_xll.EQNXTDZ($A$1,$B49,E$1,$B$1) -> 14.6271 | F49: =_xll.EQNXTDZ($A$1,$B49,F$1,$B$1) -> 13.2271 | G49: =_xll.EQNXTDZ($A$1,$B49,G$1,$B$1) -> 8.4271 | H49: =_xll.EQNXTDZ($A$1,$B49,H$1,$B$1) -> 16.5271 | I49: =_xll.EQNXTDZ($A$1,$B49,I$1,$B$1) -> 12.8034 | J49: =_xll.EQNXTDZ($A$1,$B49,J$1,$B$1) -> 3.8034 | ... AF49: =_xll.EQNXTDZ($A$1,$B49,AF$1,$B$1) -> 0
A50: Other Long Term Liabilities | B50: BS_OTH_LT_LIAB | C50: =_xll.EQNXTDZ($A$1,$B50,C$1,$B$1) -> 0 | D50: =_xll.EQNXTDZ($A$1,$B50,D$1,$B$1) -> 0 | E50: =_xll.EQNXTDZ($A$1,$B50,E$1,$B$1) -> 0 | F50: =_xll.EQNXTDZ($A$1,$B50,F$1,$B$1) -> 0 | G50: =_xll.EQNXTDZ($A$1,$B50,G$1,$B$1) -> 0 | H50: =_xll.EQNXTDZ($A$1,$B50,H$1,$B$1) -> 0 | I50: =_xll.EQNXTDZ($A$1,$B50,I$1,$B$1) -> 0 | J50: =_xll.EQNXTDZ($A$1,$B50,J$1,$B$1) -> 0 | ... AF50: =_xll.EQNXTDZ($A$1,$B50,AF$1,$B$1) -> 0
A51: Long Term Trade Payables | B51: BS_LT_TRADE_PAYABLES | C51: =_xll.EQNXTDZ($A$1,$B51,C$1,$B$1) -> 0 | D51: =_xll.EQNXTDZ($A$1,$B51,D$1,$B$1) -> 0 | E51: =_xll.EQNXTDZ($A$1,$B51,E$1,$B$1) -> 0 | F51: =_xll.EQNXTDZ($A$1,$B51,F$1,$B$1) -> 0 | G51: =_xll.EQNXTDZ($A$1,$B51,G$1,$B$1) -> 0 | H51: =_xll.EQNXTDZ($A$1,$B51,H$1,$B$1) -> 0 | I51: =_xll.EQNXTDZ($A$1,$B51,I$1,$B$1) -> 0 | J51: =_xll.EQNXTDZ($A$1,$B51,J$1,$B$1) -> 0 | ... AF51: =_xll.EQNXTDZ($A$1,$B51,AF$1,$B$1) -> 0
... A99: Estimated Capital Contracts Remaining | B99: BS_ESTIMATED_CAPITAL_CONTRACT | C99: =_xll.EQNXTDZ($A$1,$B99,C$1,$B$1) -> 0 | D99: =_xll.EQNXTDZ($A$1,$B99,D$1,$B$1) -> 0 | E99: =_xll.EQNXTDZ($A$1,$B99,E$1,$B$1) -> 0 | F99: =_xll.EQNXTDZ($A$1,$B99,F$1,$B$1) -> 0 | G99: =_xll.EQNXTDZ($A$1,$B99,G$1,$B$1) -> 0 | H99: =_xll.EQNXTDZ($A$1,$B99,H$1,$B$1) -> 0 | I99: =_xll.EQNXTDZ($A$1,$B99,I$1,$B$1) -> 0 | J99: =_xll.EQNXTDZ($A$1,$B99,J$1,$B$1) -> 0 | ... AF99: =_xll.EQNXTDZ($A$1,$B99,AF$1,$B$1) -> 0
A103: Field Description | B103: Field Name
A104: Equity Paid Up | B104: BS_EQUITY_PAIDUP | C104: =_xll.EQNXTDZ($A$1,$B104,C$1,$B$1) -> 42.3817 | D104: =_xll.EQNXTDZ($A$1,$B104,D$1,$B$1) -> 42.3817 | E104: =_xll.EQNXTDZ($A$1,$B104,E$1,$B$1) -> 42.3817 | F104: =_xll.EQNXTDZ($A$1,$B104,F$1,$B$1) -> 42.3817 | G104: =_xll.EQNXTDZ($A$1,$B104,G$1,$B$1) -> 42.3817 | H104: =_xll.EQNXTDZ($A$1,$B104,H$1,$B$1) -> 42.3817 | I104: =_xll.EQNXTDZ($A$1,$B104,I$1,$B$1) -> 42.3817 | J104: =_xll.EQNXTDZ($A$1,$B104,J$1,$B$1) -> 42.3817 | ... AF104: =_xll.EQNXTDZ($A$1,$B104,AF$1,$B$1) -> 0
A105: Face Value | B105: BS_FACE_VALUE | C105: =_xll.EQNXTDZ($A$1,$B105,C$1,$B$1) -> 10 | D105: =_xll.EQNXTDZ($A$1,$B105,D$1,$B$1) -> 10 | E105: =_xll.EQNXTDZ($A$1,$B105,E$1,$B$1) -> 10 | F105: =_xll.EQNXTDZ($A$1,$B105,F$1,$B$1) -> 10 | G105: =_xll.EQNXTDZ($A$1,$B105,G$1,$B$1) -> 10 | H105: =_xll.EQNXTDZ($A$1,$B105,H$1,$B$1) -> 10 | I105: =_xll.EQNXTDZ($A$1,$B105,I$1,$B$1) -> 2 | J105: =_xll.EQNXTDZ($A$1,$B105,J$1,$B$1) -> 2 | ... AF105: =_xll.EQNXTDZ($A$1,$B105,AF$1,$B$1) -> 0
A106: Close Price (Unit Curr.) | B106: FH_YEAR_PRICE | C106: =_xll.EQNXTDZ($A$1,$B106,C$1,$B$1) -> 40.8 | D106: =_xll.EQNXTDZ($A$1,$B106,D$1,$B$1) -> 49.73 | E106: =_xll.EQNXTDZ($A$1,$B106,E$1,$B$1) -> 134.75 | F106: =_xll.EQNXTDZ($A$1,$B106,F$1,$B$1) -> 194.02 | G106: =_xll.EQNXTDZ($A$1,$B106,G$1,$B$1) -> 385.79 | H106: =_xll.EQNXTDZ($A$1,$B106,H$1,$B$1) -> 742.3 | I106: =_xll.EQNXTDZ($A$1,$B106,I$1,$B$1) -> 1512.35 | J106: =_xll.EQNXTDZ($A$1,$B106,J$1,$B$1) -> 453.45 | ... AF106: =_xll.EQNXTDZ($A$1,$B106,AF$1,$B$1) -> 0
A107: High Price (Unit Curr.) | B107: FH_HIGH | C107: =_xll.EQNXTDZ($A$1,$B107,C$1,$B$1) -> 66.8 | D107: =_xll.EQNXTDZ($A$1,$B107,D$1,$B$1) -> 58.39 | E107: =_xll.EQNXTDZ($A$1,$B107,E$1,$B$1) -> 135.39 | F107: =_xll.EQNXTDZ($A$1,$B107,F$1,$B$1) -> 200 | G107: =_xll.EQNXTDZ($A$1,$B107,G$1,$B$1) -> 410.2 | H107: =_xll.EQNXTDZ($A$1,$B107,H$1,$B$1) -> 789 | I107: =_xll.EQNXTDZ($A$1,$B107,I$1,$B$1) -> 1670 | J107: =_xll.EQNXTDZ($A$1,$B107,J$1,$B$1) -> 1528 | ... AF107: =_xll.EQNXTDZ($A$1,$B107,AF$1,$B$1) -> 0
A108: Low Price (Unit Curr.) | B108: FH_LOW | C108: =_xll.EQNXTDZ($A$1,$B108,C$1,$B$1) -> 35.6 | D108: =_xll.EQNXTDZ($A$1,$B108,D$1,$B$1) -> 40.75 | E108: =_xll.EQNXTDZ($A$1,$B108,E$1,$B$1) -> 49.47 | F108: =_xll.EQNXTDZ($A$1,$B108,F$1,$B$1) -> 119.4 | G108: =_xll.EQNXTDZ($A$1,$B108,G$1,$B$1) -> 177 | H108: =_xll.EQNXTDZ($A$1,$B108,H$1,$B$1) -> 382 | I108: =_xll.EQNXTDZ($A$1,$B108,I$1,$B$1) -> 638 | J108: =_xll.EQNXTDZ($A$1,$B108,J$1,$B$1) -> 379.15 | ... AF108: =_xll.EQNXTDZ($A$1,$B108,AF$1,$B$1) -> 0
A109: Market Capitalization | B109: FH_MCAP | C109: =_xll.EQNXTDZ($A$1,$B109,C$1,$B$1) -> 864.58668 | D109: =_xll.EQNXTDZ($A$1,$B109,D$1,$B$1) -> 1053.821 | E109: =_xll.EQNXTDZ($A$1,$B109,E$1,$B$1) -> 2855.467 | F109: =_xll.EQNXTDZ($A$1,$B109,F$1,$B$1) -> 4111.4487 | G109: =_xll.EQNXTDZ($A$1,$B109,G$1,$B$1) -> 8175.218 | H109: =_xll.EQNXTDZ($A$1,$B109,H$1,$B$1) -> 15729.968 | I109: =_xll.EQNXTDZ($A$1,$B109,I$1,$B$1) -> 32047.982 | J109: =_xll.EQNXTDZ($A$1,$B109,J$1,$B$1) -> 9608.9909 | ... AF109: =_xll.EQNXTDZ($A$1,$B109,AF$1,$B$1) -> 0
A110: Adj DPS(Rs) | B110: FR_ADJ_DPS | C110: =_xll.EQNXTDZ($A$1,$B110,C$1,$B$1) -> 1 | D110: =_xll.EQNXTDZ($A$1,$B110,D$1,$B$1) -> 1.2 | E110: =_xll.EQNXTDZ($A$1,$B110,E$1,$B$1) -> 1.2 | F110: =_xll.EQNXTDZ($A$1,$B110,F$1,$B$1) -> 1.4 | G110: =_xll.EQNXTDZ($A$1,$B110,G$1,$B$1) -> 1.6 | H110: =_xll.EQNXTDZ($A$1,$B110,H$1,$B$1) -> 2 | I110: =_xll.EQNXTDZ($A$1,$B110,I$1,$B$1) -> 2.2 | J110: =_xll.EQNXTDZ($A$1,$B110,J$1,$B$1) -> 2.2 | ... AF110: =_xll.EQNXTDZ($A$1,$B110,AF$1,$B$1) -> 0
A111: Date End | B111: SHP_DATE_END | C111: =_xll.EQNXTDZ($A$1,$B111,C$5) -> 200112 | D111: =_xll.EQNXTDZ($A$1,$B111,D$5) -> 200212 | E111: =_xll.EQNXTDZ($A$1,$B111,E$5) -> 200312 | F111: =_xll.EQNXTDZ($A$1,$B111,F$5) -> 200412 | G111: =_xll.EQNXTDZ($A$1,$B111,G$5) -> 200512 | H111: =_xll.EQNXTDZ($A$1,$B111,H$5) -> 200612 | I111: =_xll.EQNXTDZ($A$1,$B111,I$5) -> 200712 | J111: =_xll.EQNXTDZ($A$1,$B111,J$5) -> 200812 | ... AF111: =_xll.EQNXTDZ($A$1,$B111,AF$5) -> 0
A112: Total of Promoter and Promoter Group | B112: SHP_TPFTOTALPROMOTER | C112: =_xll.EQNXTDZ($A$1,$B112,C$5) -> 52.11 | D112: =_xll.EQNXTDZ($A$1,$B112,D$5) -> 52.11 | E112: =_xll.EQNXTDZ($A$1,$B112,E$5) -> 52.11 | F112: =_xll.EQNXTDZ($A$1,$B112,F$5) -> 52.11 | G112: =_xll.EQNXTDZ($A$1,$B112,G$5) -> 52.11 | H112: =_xll.EQNXTDZ($A$1,$B112,H$5) -> 52.11 | I112: =_xll.EQNXTDZ($A$1,$B112,I$5) -> 52.11 | J112: =_xll.EQNXTDZ($A$1,$B112,J$5) -> 52.11 | ... AF112: =_xll.EQNXTDZ($A$1,$B112,AF$5) -> 0
A113: Total of Promoter and Promoter Group Pledged | B113: SHP_PSHFTOTALPROMOTER | C113: =_xll.EQNXTDZ($A$1,$B113,C$5) -> 0 | D113: =_xll.EQNXTDZ($A$1,$B113,D$5) -> 0 | E113: =_xll.EQNXTDZ($A$1,$B113,E$5) -> 0 | F113: =_xll.EQNXTDZ($A$1,$B113,F$5) -> 0 | G113: =_xll.EQNXTDZ($A$1,$B113,G$5) -> 0 | H113: =_xll.EQNXTDZ($A$1,$B113,H$5) -> 0 | I113: =_xll.EQNXTDZ($A$1,$B113,I$5) -> 0 | J113: =_xll.EQNXTDZ($A$1,$B113,J$5) -> 0 | ... AF113: =_xll.EQNXTDZ($A$1,$B113,AF$5) -> 0

Sheet QTR Share Price
A1: ='QTR Raw'!A1 -> 100002 | C1: 201206 | D1: 201207 | E1: 201208 | F1: 201209 | G1: 201210 | H1: 201211 | I1: 201212 | J1: 201301 | K1: 201302 | L1: 201303 | M1: 201304 | N1: 201305 | O1: 201306 | P1: 201307 | Q1: 201308 | R1: 201309 | S1: 201310 | T1: 201311 | U1: 201312 | V1: 201401 | W1: 201402 | X1: 201403 | Y1: 201404 | Z1: 201405 | AA1: 201406 | AB1: 201407 | AC1: 201408 | AD1: 201409 | AE1: 201410 | AF1: 201411 | AG1: 201412 | AH1: 201501 | AI1: 201502 | AJ1: 201503 | AK1: 201504 | AL1: 201505 | AM1: 201506 | AN1: 201507 | AO1: 201508 | AP1: 201509 | AQ1: 201510 | AR1: 201511 | AS1: 201512 | AT1: 201601 | AU1: 201602 | AV1: 201603 | AW1: 201604 | AX1: 201605 | AY1: 201606 | AZ1: 201607 | BA1: 201608 | BB1: 201609 | BC1: 201610 | BD1: 201611 | BE1: 201612 | BF1: 201701 | BG1: 201702 | BH1: 201703 | BI1: 201704 | BJ1: 201705 | BK1: 201706 | BL1: 201707 | BM1: 201708 | BN1: 201709 | BO1: 201710 | BP1: 201711 | BQ1: 201712 | BR1: 201801 | BS1: 201802 | BT1: 201803 | BU1: 201804 | BV1: 201805 | BW1: 201806 | BX1: 201807 | BY1: 201808 | BZ1: 201809 | CA1: 201810 | CB1: 201811 | CC1: 201812 | CD1: 201901 | CE1: 201902 | CF1: 201903 | CG1: 201904 | CH1: 201905 | CI1: 201906 | CJ1: 201907 | CK1: 201908 | CL1: 201909 | CM1: 201910 | CN1: 201911 | CO1: 201912 | CP1: 202001 | CQ1: 202002 | CR1: 202003 | CS1: 202004 | CT1: 202005 | CU1: 202006 | CV1: 202007 | CW1: 202008 | CX1: 202009 | CY1: 202010 | CZ1: 202011 | DA1: 202012 | DB1: 202101 | DC1: 202102 | DD1: 202103 | DE1: 202104 | DF1: 202105 | DG1: 202106 | DH1: 202107 | DI1: 202108 | DJ1: 202109 | DK1: 202110 | DL1: 202111 | DM1: 202112 | DN1: 202201 | DO1: 202202 | DP1: 202203 | DQ1: 202204 | DR1: 202205 | DS1: 202206 | DT1: 202207 | DU1: 202208 | DV1: 202209 | DW1: 202210 | DX1: 202211 | DY1: 202212 | DZ1: 202301 | EA1: 202302 | EB1: 202303 | EC1: 202304 | ED1: 202305 | EE1: 202306 | EF1: 202307 | EG1: 202308 | EH1: 202309 | EI1: 202310 | EJ1: 202311 | EK1: 202312 | EL1: 202401 | EM1: 202402 | EN1: 202403 | EO1: 202404 | EP1: 202405 | EQ1: 202406 | ER1: 202407 | ES1: 202408 | ET1: 202409 | EU1: 202410 | EV1: 202411 | EW1: 202412 | EX1: 202501 | EY1: 202502 | EZ1: 202503 | FA1: 202504 | FB1: 202505 | FC1: 202506 | FD1: 202507 | FE1: 202508 | FF1: 202509 | FG1: 202510 | FH1: 202511 | FI1: 202512 | FJ1: 202601 | FK1: 202602 | FL1: 202603 | FM1: 202604 | FN1: 202605 | FO1: 202606 | FP1: 202607 | FQ1: 202608 | FR1: 202609 | FS1: 202610 | FT1: 202611 | FU1: 202612 | FV1: 202701 | FW1: 202702 | FX1: 202703 | FY1: 202704 | FZ1: 202705 | GA1: 202706 | GB1: 202707 | GC1: 202708 | GD1: 202709 | GE1: 202710 | GF1: 202711 | GG1: 202712 | GH1: 202801 | GI1: 202802 | GJ1: 202803 | GK1: 202804 | GL1: 202805 | GM1: 202806 | GN1: 202807 | GO1: 202808 | GP1: 202809 | GQ1: 202810 | GR1: 202811 | GS1: 202812 | GT1: 202901 | GU1: 202902 | GV1: 202903 | GW1: 202904 | GX1: 202905 | GY1: 202906 | GZ1: 202907 | HA1: 202908 | HB1: 202909 | HC1: 202910 | HD1: 202911 | HE1: 202912 | HF1: 203001 | HG1: 203002 | HH1: 203003 | HM1: 201206 | HN1: 201207 | HO1: 201208 | HP1: 201209 | HQ1: 201212 | HR1: 201303 | HS1: 201306 | HT1: 201309 | HU1: 201312 | HV1: 201403 | HW1: 201406 | HX1: 201409 | HY1: 201412 | HZ1: 201503 | IA1: 201506 | IB1: 201509 | IC1: 201512 | ID1: 201603 | IE1: 201606 | IF1: 201609 | IG1: 201612 | IH1: 201703 | II1: 201706 | IJ1: 201709 | IK1: 201712 | IL1: 201803 | IM1: 201806 | IN1: 201809 | IO1: 201812 | IP1: 201903 | IQ1: 201906 | IR1: 201909 | IS1: 201912 | IT1: 202003 | IU1: 202006 | IV1: 202009 | IW1: 202012 | IX1: 202103 | IY1: 202106 | IZ1: 202109 | JA1: 202112 | JB1: 202203 | JC1: 202206 | JD1: 202209 | JE1: 202212 | JF1: 202303 | JG1: 202306 | JH1: 202309 | JI1: 202312 | JJ1: 202403 | JK1: 202406 | JL1: 202409 | JM1: 202412 | JN1: 202503 | JO1: 202506 | JP1: 202509 | JQ1: 202512 | JR1: 202603 | JS1: 202606 | JT1: 202609 | JU1: 202612 | JV1: 202703 | JW1: 202706 | JX1: 202709 | JY1: 202712 | JZ1: 202803 | KA1: 202806 | KB1: 202809 | KC1: 202812 | KD1: 202903 | KE1: 202906 | KF1: 202909 | KG1: 202912 | KH1: 203003
FF2: 45901 | FG2: =+EOMONTH(FF2,1) -> 45961 | FH2: =+EOMONTH(FG2,1) -> 45991 | FI2: =+EOMONTH(FH2,1) -> 46022 | FJ2: =+EOMONTH(FI2,1) -> 46053 | FK2: =+EOMONTH(FJ2,1) -> 46081 | FL2: =+EOMONTH(FK2,1) -> 46112 | FM2: =+EOMONTH(FL2,1) -> 46142 | FN2: =+EOMONTH(FM2,1) -> 46173 | ... HH2: =+EOMONTH(HG2,1) -> 47573
A4: Field Description | B4: Field Name
A5: MonthEnd | B5: NMONTH_MONTHEND | C5: {=_xll.EQNXTDZ($A$1,$B5,C$1)} -> 201206 | D5: {=_xll.EQNXTDZ($A$1,$B5,D$1)} -> 201207 | E5: {=_xll.EQNXTDZ($A$1,$B5,E$1)} -> 201208 | F5: {=_xll.EQNXTDZ($A$1,$B5,F$1)} -> 201209 | G5: {=_xll.EQNXTDZ($A$1,$B5,G$1)} -> 201210 | H5: {=_xll.EQNXTDZ($A$1,$B5,H$1)} -> 201211 | I5: {=_xll.EQNXTDZ($A$1,$B5,I$1)} -> 201212 | J5: {=_xll.EQNXTDZ($A$1,$B5,J$1)} -> 201301 | ... HH5: {=_xll.EQNXTDZ($A$1,$B5,HH$1)} -> 0
A6: Open | B6: NMONTH_OPEN | C6: {=_xll.EQNXTDZ($A$1,$B6,C$1)} -> 738 | D6: {=_xll.EQNXTDZ($A$1,$B6,D$1)} -> 801 | E6: {=_xll.EQNXTDZ($A$1,$B6,E$1)} -> 799.9 | F6: {=_xll.EQNXTDZ($A$1,$B6,F$1)} -> 712 | G6: {=_xll.EQNXTDZ($A$1,$B6,G$1)} -> 800 | H6: {=_xll.EQNXTDZ($A$1,$B6,H$1)} -> 738.05 | I6: {=_xll.EQNXTDZ($A$1,$B6,I$1)} -> 724 | J6: {=_xll.EQNXTDZ($A$1,$B6,J$1)} -> 707.3 | ... HH6: {=_xll.EQNXTDZ($A$1,$B6,HH$1)} -> 0
A7: High | B7: NMONTH_HIGH | C7: {=_xll.EQNXTDZ($A$1,$B7,C$1)} -> 821 | D7: {=_xll.EQNXTDZ($A$1,$B7,D$1)} -> 812 | E7: {=_xll.EQNXTDZ($A$1,$B7,E$1)} -> 814.45 | F7: {=_xll.EQNXTDZ($A$1,$B7,F$1)} -> 804.9 | G7: {=_xll.EQNXTDZ($A$1,$B7,G$1)} -> 810.7 | H7: {=_xll.EQNXTDZ($A$1,$B7,H$1)} -> 746.75 | I7: {=_xll.EQNXTDZ($A$1,$B7,I$1)} -> 731 | J7: {=_xll.EQNXTDZ($A$1,$B7,J$1)} -> 737 | ... HH7: {=_xll.EQNXTDZ($A$1,$B7,HH$1)} -> 0 | HP7: =+MAX(D7:F7) -> 814.45 | HQ7: =+MAX(G7:I7) -> 810.7 | HR7: =+MAX(J7:L7) -> 737 | HS7: =+MAX(M7:O7) -> 694.75 | HT7: =+MAX(P7:R7) -> 627.8 | HU7: =+MAX(S7:U7) -> 720.8 | HV7: =+MAX(V7:X7) -> 862 | HW7: =+MAX(Y7:AA7) -> 1125.6 | HX7: =+MAX(AB7:AD7) -> 1263.5 | HY7: =+MAX(AE7:AG7) -> 1398.6 | HZ7: =+MAX(AH7:AJ7) -> 1526.3 | IA7: =+MAX(AK7:AM7) -> 1432.5 | IB7: =+MAX(AN7:AP7) -> 1445 | IC7: =+MAX(AQ7:AS7) -> 1295.5 | ID7: =+MAX(AT7:AV7) -> 1296.8 | IE7: =+MAX(AW7:AY7) -> 1434 | IF7: =+MAX(AZ7:BB7) -> 1324 | IG7: =+MAX(BC7:BE7) -> 1187.95 | IH7: =+MAX(BF7:BH7) -> 1292 | II7: =+MAX(BI7:BK7) -> 1620 | IJ7: =+MAX(BL7:BN7) -> 1549.65 | IK7: =+MAX(BO7:BQ7) -> 1448 | IL7: =+MAX(BR7:BT7) -> 1749.2 | IM7: =+MAX(BU7:BW7) -> 1384 | IN7: =+MAX(BX7:BZ7) -> 1517 | IO7: =+MAX(CA7:CC7) -> 1464 | IP7: =+MAX(CD7:CF7) -> 1358 | IQ7: =+MAX(CG7:CI7) -> 1640 | IR7: =+MAX(CJ7:CL7) -> 1670 | IS7: =+MAX(CM7:CO7) -> 1580 | IT7: =+MAX(CP7:CR7) -> 1411 | IU7: =+MAX(CS7:CU7) -> 1050 | IV7: =+MAX(CV7:CX7) -> 1017 | IW7: =+MAX(CY7:DA7) -> 1260 | IX7: =+MAX(DB7:DD7) -> 1635 | IY7: =+MAX(DE7:DG7) -> 1857 | IZ7: =+MAX(DH7:DJ7) -> 1943.9 | JA7: =+MAX(DK7:DM7) -> 2375 | JB7: =+MAX(DN7:DP7) -> 2468.1 | JC7: =+MAX(DQ7:DS7) -> 2487.85 | JD7: =+MAX(DT7:DV7) -> 3446.3 | JE7: =+MAX(DW7:DY7) -> 3335 | JF7: =+MAX(DZ7:EB7) -> 3434 | JG7: =+MAX(EC7:EE7) -> 4444 | JH7: =+MAX(EF7:EH7) -> 4678 | JI7: =+MAX(EI7:EK7) -> 4957 | JJ7: =+MAX(EL7:EN7) -> 6471.95 | JK7: =MAX(EO7:EQ7) -> 9149.95 | JL7: =MAX(ER7:ET7) -> 8808.7 | JM7: =MAX(EU7:EW7) -> 8940.6 | JN7: =MAX(EX7:EZ7) -> 6947.7 | JO7: =MAX(FA7:FC7) -> 6260 | JP7: =MAX(FD7:FF7) -> 6144.5 | JQ7: =MAX(FG7:FI7) -> 5343 | JR7: =MAX(FJ7:FL7) -> 6554 | JS7: =MAX(FM7:FO7) -> 7822.5 | JT7: =MAX(FP7:FR7) -> 0 | JU7: =MAX(FS7:FU7) -> 0 | JV7: =MAX(FV7:FX7) -> 0 | JW7: =MAX(FY7:GA7) -> 0 | JX7: =MAX(GB7:GD7) -> 0 | JY7: =MAX(GE7:GG7) -> 0 | JZ7: =MAX(GH7:GJ7) -> 0 | KA7: =MAX(GK7:GM7) -> 0 | KB7: =MAX(GN7:GP7) -> 0 | KC7: =MAX(GQ7:GS7) -> 0 | KD7: =MAX(GT7:GV7) -> 0 | KE7: =MAX(GW7:GY7) -> 0 | KF7: =MAX(GZ7:HB7) -> 0 | KG7: =MAX(HC7:HE7) -> 0 | KH7: =MAX(HF7:HH7) -> 0
A8: Low | B8: NMONTH_LOW | C8: {=_xll.EQNXTDZ($A$1,$B8,C$1)} -> 699 | D8: {=_xll.EQNXTDZ($A$1,$B8,D$1)} -> 730.1 | E8: {=_xll.EQNXTDZ($A$1,$B8,E$1)} -> 704.95 | F8: {=_xll.EQNXTDZ($A$1,$B8,F$1)} -> 710 | G8: {=_xll.EQNXTDZ($A$1,$B8,G$1)} -> 732 | H8: {=_xll.EQNXTDZ($A$1,$B8,H$1)} -> 621.55 | I8: {=_xll.EQNXTDZ($A$1,$B8,I$1)} -> 685 | J8: {=_xll.EQNXTDZ($A$1,$B8,J$1)} -> 638.6 | ... HH8: {=_xll.EQNXTDZ($A$1,$B8,HH$1)} -> 0 | HP8: =+MIN(D8:F8) -> 704.95 | HQ8: =+MIN(G8:I8) -> 621.55 | HR8: =+MIN(J8:L8) -> 482.6 | HS8: =+MIN(M8:O8) -> 468 | HT8: =+MIN(P8:R8) -> 430 | HU8: =+MIN(S8:U8) -> 535 | HV8: =+MIN(V8:X8) -> 566.95 | HW8: =+MIN(Y8:AA8) -> 808.1 | HX8: =+MIN(AB8:AD8) -> 970 | HY8: =+MIN(AE8:AG8) -> 985 | HZ8: =+MIN(AH8:AJ8) -> 1181.7 | IA8: =+MIN(AK8:AM8) -> 1240.1 | IB8: =+MIN(AN8:AP8) -> 1018.6 | IC8: =+MIN(AQ8:AS8) -> 1046.05 | ID8: =+MIN(AT8:AV8) -> 955.2 | IE8: =+MIN(AW8:AY8) -> 1178.9 | IF8: =+MIN(AZ8:BB8) -> 1107 | IG8: =+MIN(BC8:BE8) -> 931.35 | IH8: =+MIN(BF8:BH8) -> 1029.15 | II8: =+MIN(BI8:BK8) -> 1282.5 | IJ8: =+MIN(BL8:BN8) -> 1298.8 | IK8: =+MIN(BO8:BQ8) -> 1305.1 | IL8: =+MIN(BR8:BT8) -> 1267.25 | IM8: =+MIN(BU8:BW8) -> 1149 | IN8: =+MIN(BX8:BZ8) -> 1129 | IO8: =+MIN(CA8:CC8) -> 1190 | IP8: =+MIN(CD8:CF8) -> 1212 | IQ8: =+MIN(CG8:CI8) -> 1308 | IR8: =+MIN(CJ8:CL8) -> 1310 | IS8: =+MIN(CM8:CO8) -> 1200 | IT8: =+MIN(CP8:CR8) -> 801 | IU8: =+MIN(CS8:CU8) -> 722 | IV8: =+MIN(CV8:CX8) -> 846.6 | IW8: =+MIN(CY8:DA8) -> 848 | IX8: =+MIN(DB8:DD8) -> 1212 | IY8: =+MIN(DE8:DG8) -> 1298.55 | IZ8: =+MIN(DH8:DJ8) -> 1618.05 | JA8: =+MIN(DK8:DM8) -> 1800 | JB8: =+MIN(DN8:DP8) -> 1944.6 | JC8: =+MIN(DQ8:DS8) -> 2000 | JD8: =+MIN(DT8:DV8) -> 2260.35 | JE8: =+MIN(DW8:DY8) -> 2640 | JF8: =+MIN(DZ8:EB8) -> 2662.5 | JG8: =+MIN(EC8:EE8) -> 3141.15 | JH8: =+MIN(EF8:EH8) -> 4087.7 | JI8: =+MIN(EI8:EK8) -> 3850 | JJ8: =+MIN(EL8:EN8) -> 4340.3 | JK8: =MIN(EO8:EQ8) -> 6245 | JL8: =MIN(ER8:ET8) -> 7053.2 | JM8: =MIN(EU8:EW8) -> 6605 | JN8: =MIN(EX8:EZ8) -> 4890 | JO8: =MIN(FA8:FC8) -> 4684.45 | JP8: =MIN(FD8:FF8) -> 4939.5 | JQ8: =MIN(FG8:FI8) -> 4896 | JR8: =MIN(FJ8:FL8) -> 4637.5 | JS8: =MIN(FM8:FO8) -> 5916.5 | JT8: =MIN(FP8:FR8) -> 0 | JU8: =MIN(FS8:FU8) -> 0 | JV8: =MIN(FV8:FX8) -> 0 | JW8: =MIN(FY8:GA8) -> 0 | JX8: =MIN(GB8:GD8) -> 0 | JY8: =MIN(GE8:GG8) -> 0 | JZ8: =MIN(GH8:GJ8) -> 0 | KA8: =MIN(GK8:GM8) -> 0 | KB8: =MIN(GN8:GP8) -> 0 | KC8: =MIN(GQ8:GS8) -> 0 | KD8: =MIN(GT8:GV8) -> 0 | KE8: =MIN(GW8:GY8) -> 0 | KF8: =MIN(GZ8:HB8) -> 0 | KG8: =MIN(HC8:HE8) -> 0 | KH8: =MIN(HF8:HH8) -> 0
A9: Close | B9: NMONTH_CLOSE | C9: {=_xll.EQNXTDZ($A$1,$B9,C$1)} -> 802.15 | D9: {=_xll.EQNXTDZ($A$1,$B9,D$1)} -> 795.95 | E9: {=_xll.EQNXTDZ($A$1,$B9,E$1)} -> 713.95 | F9: {=_xll.EQNXTDZ($A$1,$B9,F$1)} -> 800.65 | G9: {=_xll.EQNXTDZ($A$1,$B9,G$1)} -> 737.85 | H9: {=_xll.EQNXTDZ($A$1,$B9,H$1)} -> 713.4 | I9: {=_xll.EQNXTDZ($A$1,$B9,I$1)} -> 700.75 | J9: {=_xll.EQNXTDZ($A$1,$B9,J$1)} -> 649.1 | ... HH9: {=_xll.EQNXTDZ($A$1,$B9,HH$1)} -> 0 | HP9: =+F9 -> 800.65 | HQ9: =+I9 -> 700.75 | HR9: =+L9 -> 488.75 | HS9: =+O9 -> 612.35 | HT9: =+R9 -> 542.45 | HU9: =+U9 -> 693.3 | HV9: =+X9 -> 853.9 | HW9: =+AA9 -> 1121.1 | HX9: =+AD9 -> 1150.35 | HY9: =+AG9 -> 1288.3 | HZ9: =+AJ9 -> 1260.1 | IA9: =+AM9 -> 1324.3 | IB9: =+AP9 -> 1059.75 | IC9: =+AS9 -> 1114.5 | ID9: =+AV9 -> 1282.15 | IE9: =+AY9 -> 1223.95 | IF9: =+BB9 -> 1141.9 | IG9: =+BE9 -> 1043.75 | IH9: =+BH9 -> 1279.9 | II9: =+BK9 -> 1450.65 | IJ9: =+BN9 -> 1398.9 | IK9: =+BQ9 -> 1402.9 | IL9: =+BT9 -> 1294.65 | IM9: =+BW9 -> 1178.5 | IN9: =+BZ9 -> 1409.8 | IO9: =+CC9 -> 1336.75 | IP9: =+CF9 -> 1316 | IQ9: =+CI9 -> 1602.45 | IR9: =+CL9 -> 1515.35 | IS9: =+CO9 -> 1285.25 | IT9: =+CR9 -> 935.4 | IU9: =+CU9 -> 941.15 | IV9: =+CX9 -> 859.5 | IW9: =+DA9 -> 1212.05 | IX9: =+DD9 -> 1410.05 | IY9: =+DG9 -> 1808.2 | IZ9: =+DJ9 -> 1870.6 | JA9: =+DM9 -> 2233.6 | JB9: =+DP9 -> 2157.95 | JC9: =+DS9 -> 2300.9 | JD9: =+DV9 -> 3088.4 | JE9: =+DY9 -> 2683 | JF9: =+EB9 -> 3365.15 | JG9: =+EE9 -> 4423 | JH9: =+EH9 -> 4098.25 | JI9: =+EK9 -> 4674.85 | JJ9: =+EN9 -> 6360.85 | JK9: =EQ9 -> 8490.9 | JL9: =ET9 -> 8055 | JM9: =EW9 -> 6912.25 | JN9: =EZ9 -> 5546.25 | JO9: =FC9 -> 6080.5 | JP9: =FF9 -> 5183.3 | JQ9: =FI9 -> 5170 | JR9: =FL9 -> 5941.5 | JS9: =FO9 -> 7021 | JT9: =FR9 -> 0 | JU9: =FU9 -> 0 | JV9: =FX9 -> 0 | JW9: =GA9 -> 0 | JX9: =GD9 -> 0 | JY9: =GG9 -> 0 | JZ9: =GJ9 -> 0 | KA9: =GM9 -> 0 | KB9: =GP9 -> 0 | KC9: =GS9 -> 0 | KD9: =GV9 -> 0 | KE9: =GY9 -> 0 | KF9: =HB9 -> 0 | KG9: =HE9 -> 0 | KH9: =HH9 -> 0
A11: Field Description | B11: Field Name | C11: {=_xll.EQNXTDZ($A$1,$B11,C$1)} -> 0 | D11: {=_xll.EQNXTDZ($A$1,$B11,D$1)} -> 0 | E11: {=_xll.EQNXTDZ($A$1,$B11,E$1)} -> 0 | F11: {=_xll.EQNXTDZ($A$1,$B11,F$1)} -> 0 | G11: {=_xll.EQNXTDZ($A$1,$B11,G$1)} -> 0 | H11: {=_xll.EQNXTDZ($A$1,$B11,H$1)} -> 0 | I11: {=_xll.EQNXTDZ($A$1,$B11,I$1)} -> 0 | J11: {=_xll.EQNXTDZ($A$1,$B11,J$1)} -> 0 | ... HH11: {=_xll.EQNXTDZ($A$1,$B11,HH$1)} -> 0
A12: Month End | B12: BMONTH_MONTHEND | C12: {=_xll.EQNXTDZ($A$1,$B12,C$1)} -> 201206 | D12: {=_xll.EQNXTDZ($A$1,$B12,D$1)} -> 201207 | E12: {=_xll.EQNXTDZ($A$1,$B12,E$1)} -> 201208 | F12: {=_xll.EQNXTDZ($A$1,$B12,F$1)} -> 201209 | G12: {=_xll.EQNXTDZ($A$1,$B12,G$1)} -> 201210 | H12: {=_xll.EQNXTDZ($A$1,$B12,H$1)} -> 201211 | I12: {=_xll.EQNXTDZ($A$1,$B12,I$1)} -> 201212 | J12: {=_xll.EQNXTDZ($A$1,$B12,J$1)} -> 201301 | ... HH12: {=_xll.EQNXTDZ($A$1,$B12,HH$1)} -> 0
A13: Open | B13: BMONTH_OPEN | C13: {=_xll.EQNXTDZ($A$1,$B13,C$1)} -> 736.6 | D13: {=_xll.EQNXTDZ($A$1,$B13,D$1)} -> 802 | E13: {=_xll.EQNXTDZ($A$1,$B13,E$1)} -> 797.9 | F13: {=_xll.EQNXTDZ($A$1,$B13,F$1)} -> 724 | G13: {=_xll.EQNXTDZ($A$1,$B13,G$1)} -> 797 | H13: {=_xll.EQNXTDZ($A$1,$B13,H$1)} -> 735.5 | I13: {=_xll.EQNXTDZ($A$1,$B13,I$1)} -> 718.95 | J13: {=_xll.EQNXTDZ($A$1,$B13,J$1)} -> 707.4 | ... HH13: {=_xll.EQNXTDZ($A$1,$B13,HH$1)} -> 0
A14: High | B14: BMONTH_HIGH | C14: {=_xll.EQNXTDZ($A$1,$B14,C$1)} -> 819.4 | D14: {=_xll.EQNXTDZ($A$1,$B14,D$1)} -> 822.25 | E14: {=_xll.EQNXTDZ($A$1,$B14,E$1)} -> 814.7 | F14: {=_xll.EQNXTDZ($A$1,$B14,F$1)} -> 803.35 | G14: {=_xll.EQNXTDZ($A$1,$B14,G$1)} -> 810.3 | H14: {=_xll.EQNXTDZ($A$1,$B14,H$1)} -> 830 | I14: {=_xll.EQNXTDZ($A$1,$B14,I$1)} -> 730 | J14: {=_xll.EQNXTDZ($A$1,$B14,J$1)} -> 737 | ... HH14: {=_xll.EQNXTDZ($A$1,$B14,HH$1)} -> 0 | HP14: =+MAX(D14:F14) -> 822.25 | HQ14: =+MAX(G14:I14) -> 830 | HR14: =+MAX(J14:L14) -> 737 | HS14: =+MAX(M14:O14) -> 694.4 | HT14: =+MAX(P14:R14) -> 627.2 | HU14: =+MAX(S14:U14) -> 720.2 | HV14: =+MAX(V14:X14) -> 858 | HW14: =+MAX(Y14:AA14) -> 1125 | HX14: =+MAX(AB14:AD14) -> 1263.5 | HY14: =+MAX(AE14:AG14) -> 1396.7 | HZ14: =+MAX(AH14:AJ14) -> 1525 | IA14: =+MAX(AK14:AM14) -> 1431.85 | IB14: =+MAX(AN14:AP14) -> 1444.4 | IC14: =+MAX(AQ14:AS14) -> 1299.05 | ID14: =+MAX(AT14:AV14) -> 1295.15 | IE14: =+MAX(AW14:AY14) -> 1432.7 | IF14: =+MAX(AZ14:BB14) -> 1322.1 | IG14: =+MAX(BC14:BE14) -> 1189 | IH14: =+MAX(BF14:BH14) -> 1292.9 | II14: =+MAX(BI14:BK14) -> 1619.45 | IJ14: =+MAX(BL14:BN14) -> 1548.4 | IK14: =+MAX(BO14:BQ14) -> 1444 | IL14: =+MAX(BR14:BT14) -> 1744.4 | IM14: =+MAX(BU14:BW14) -> 1380 | IN14: =+MAX(BX14:BZ14) -> 1516.55 | IO14: =+MAX(CA14:CC14) -> 1465 | IP14: =+MAX(CD14:CF14) -> 1359 | IQ14: =+MAX(CG14:CI14) -> 1639.7 | IR14: =+MAX(CJ14:CL14) -> 1669 | IS14: =+MAX(CM14:CO14) -> 1580.05 | IT14: =+MAX(CP14:CR14) -> 1411.8 | IU14: =+MAX(CS14:CU14) -> 1100 | IV14: =+MAX(CV14:CX14) -> 1016.75 | IW14: =+MAX(CY14:DA14) -> 1260 | IX14: =+MAX(DB14:DD14) -> 1699.9 | IY14: =+MAX(DE14:DG14) -> 1856.1 | IZ14: =+MAX(DH14:DJ14) -> 1941 | JA14: =+MAX(DK14:DM14) -> 2370 | JB14: =+MAX(DN14:DP14) -> 2469.6 | JC14: =+MAX(DQ14:DS14) -> 2488.45 | JD14: =+MAX(DT14:DV14) -> 3445.65 | JE14: =+MAX(DW14:DY14) -> 3328 | JF14: =+MAX(DZ14:EB14) -> 3433.7 | JG14: =+MAX(EC14:EE14) -> 4444.5 | JH14: =+MAX(EF14:EH14) -> 4675.85 | JI14: =+MAX(EI14:EK14) -> 4953.2 | JJ14: =+MAX(EL14:EN14) -> 6470 | JK14: =MAX(EO14:EQ14) -> 9200 | JL14: =MAX(ER14:ET14) -> 8809 | JM14: =MAX(EU14:EW14) -> 8941.45 | JN14: =MAX(EX14:EZ14) -> 6947.45 | JO14: =MAX(FA14:FC14) -> 6299.8 | JP14: =MAX(FD14:FF14) -> 6143.5 | JQ14: =MAX(FG14:FI14) -> 5359.95 | JR14: =MAX(FJ14:FL14) -> 6555 | JS14: =MAX(FM14:FO14) -> 7824.95 | JT14: =MAX(FP14:FR14) -> 0 | JU14: =MAX(FS14:FU14) -> 0 | JV14: =MAX(FV14:FX14) -> 0 | JW14: =MAX(FY14:GA14) -> 0 | JX14: =MAX(GB14:GD14) -> 0 | JY14: =MAX(GE14:GG14) -> 0 | JZ14: =MAX(GH14:GJ14) -> 0 | KA14: =MAX(GK14:GM14) -> 0 | KB14: =MAX(GN14:GP14) -> 0 | KC14: =MAX(GQ14:GS14) -> 0 | KD14: =MAX(GT14:GV14) -> 0 | KE14: =MAX(GW14:GY14) -> 0 | KF14: =MAX(GZ14:HB14) -> 0 | KG14: =MAX(HC14:HE14) -> 0 | KH14: =MAX(HF14:HH14) -> 0
A15: Low | B15: BMONTH_LOW | C15: {=_xll.EQNXTDZ($A$1,$B15,C$1)} -> 697.5 | D15: {=_xll.EQNXTDZ($A$1,$B15,D$1)} -> 725.1 | E15: {=_xll.EQNXTDZ($A$1,$B15,E$1)} -> 707.5 | F15: {=_xll.EQNXTDZ($A$1,$B15,F$1)} -> 711.55 | G15: {=_xll.EQNXTDZ($A$1,$B15,G$1)} -> 732 | H15: {=_xll.EQNXTDZ($A$1,$B15,H$1)} -> 700 | I15: {=_xll.EQNXTDZ($A$1,$B15,I$1)} -> 676.95 | J15: {=_xll.EQNXTDZ($A$1,$B15,J$1)} -> 644 | ... HH15: {=_xll.EQNXTDZ($A$1,$B15,HH$1)} -> 0 | HP15: =+MIN(D15:F15) -> 707.5 | HQ15: =+MIN(G15:I15) -> 676.95 | HR15: =+MIN(J15:L15) -> 484.3 | HS15: =+MIN(M15:O15) -> 469 | HT15: =+MIN(P15:R15) -> 448.1 | HU15: =+MIN(S15:U15) -> 535.15 | HV15: =+MIN(V15:X15) -> 568.05 | HW15: =+MIN(Y15:AA15) -> 807.3 | HX15: =+MIN(AB15:AD15) -> 956.1 | HY15: =+MIN(AE15:AG15) -> 988.25 | HZ15: =+MIN(AH15:AJ15) -> 1184 | IA15: =+MIN(AK15:AM15) -> 1245 | IB15: =+MIN(AN15:AP15) -> 1021.05 | IC15: =+MIN(AQ15:AS15) -> 1045 | ID15: =+MIN(AT15:AV15) -> 963.05 | IE15: =+MIN(AW15:AY15) -> 1182.75 | IF15: =+MIN(AZ15:BB15) -> 1109.55 | IG15: =+MIN(BC15:BE15) -> 950 | IH15: =+MIN(BF15:BH15) -> 1029.55 | II15: =+MIN(BI15:BK15) -> 1280.7 | IJ15: =+MIN(BL15:BN15) -> 1175 | IK15: =+MIN(BO15:BQ15) -> 1306.65 | IL15: =+MIN(BR15:BT15) -> 1267.15 | IM15: =+MIN(BU15:BW15) -> 1123 | IN15: =+MIN(BX15:BZ15) -> 1130 | IO15: =+MIN(CA15:CC15) -> 1191 | IP15: =+MIN(CD15:CF15) -> 1209.95 | IQ15: =+MIN(CG15:CI15) -> 1306.35 | IR15: =+MIN(CJ15:CL15) -> 1307.1 | IS15: =+MIN(CM15:CO15) -> 1230 | IT15: =+MIN(CP15:CR15) -> 795 | IU15: =+MIN(CS15:CU15) -> 722.45 | IV15: =+MIN(CV15:CX15) -> 848.5 | IW15: =+MIN(CY15:DA15) -> 848.5 | IX15: =+MIN(DB15:DD15) -> 1214.15 | IY15: =+MIN(DE15:DG15) -> 1300 | IZ15: =+MIN(DH15:DJ15) -> 1619.3 | JA15: =+MIN(DK15:DM15) -> 1801 | JB15: =+MIN(DN15:DP15) -> 1944.6 | JC15: =+MIN(DQ15:DS15) -> 2001 | JD15: =+MIN(DT15:DV15) -> 2261.05 | JE15: =+MIN(DW15:DY15) -> 2640.45 | JF15: =+MIN(DZ15:EB15) -> 2662.95 | JG15: =+MIN(EC15:EE15) -> 3143.2 | JH15: =+MIN(EF15:EH15) -> 4089.65 | JI15: =+MIN(EI15:EK15) -> 3847.5 | JJ15: =+MIN(EL15:EN15) -> 4342.15 | JK15: =MIN(EO15:EQ15) -> 6247.45 | JL15: =MIN(ER15:ET15) -> 7067.8 | JM15: =MIN(EU15:EW15) -> 6606.2 | JN15: =MIN(EX15:EZ15) -> 4893.1 | JO15: =MIN(FA15:FC15) -> 4590.05 | JP15: =MIN(FD15:FF15) -> 4940.5 | JQ15: =MIN(FG15:FI15) -> 4896 | JR15: =MIN(FJ15:FL15) -> 4640.5 | JS15: =MIN(FM15:FO15) -> 5917.95 | JT15: =MIN(FP15:FR15) -> 0 | JU15: =MIN(FS15:FU15) -> 0 | JV15: =MIN(FV15:FX15) -> 0 | JW15: =MIN(FY15:GA15) -> 0 | JX15: =MIN(GB15:GD15) -> 0 | JY15: =MIN(GE15:GG15) -> 0 | JZ15: =MIN(GH15:GJ15) -> 0 | KA15: =MIN(GK15:GM15) -> 0 | KB15: =MIN(GN15:GP15) -> 0 | KC15: =MIN(GQ15:GS15) -> 0 | KD15: =MIN(GT15:GV15) -> 0 | KE15: =MIN(GW15:GY15) -> 0 | KF15: =MIN(GZ15:HB15) -> 0 | KG15: =MIN(HC15:HE15) -> 0 | KH15: =MIN(HF15:HH15) -> 0
A16: Close | B16: BMONTH_CLOSE | C16: {=_xll.EQNXTDZ($A$1,$B16,C$1)} -> 800.8 | D16: {=_xll.EQNXTDZ($A$1,$B16,D$1)} -> 792.6 | E16: {=_xll.EQNXTDZ($A$1,$B16,E$1)} -> 715.35 | F16: {=_xll.EQNXTDZ($A$1,$B16,F$1)} -> 797.75 | G16: {=_xll.EQNXTDZ($A$1,$B16,G$1)} -> 737.35 | H16: {=_xll.EQNXTDZ($A$1,$B16,H$1)} -> 712.85 | I16: {=_xll.EQNXTDZ($A$1,$B16,I$1)} -> 700.4 | J16: {=_xll.EQNXTDZ($A$1,$B16,J$1)} -> 650.9 | ... HH16: {=_xll.EQNXTDZ($A$1,$B16,HH$1)} -> 0 | HP16: =+F16 -> 797.75 | HQ16: =+I16 -> 700.4 | HR16: =+L16 -> 489.2 | HS16: =+O16 -> 610.85 | HT16: =+R16 -> 543.9 | HU16: =+U16 -> 692.8 | HV16: =+X16 -> 849.95 | HW16: =+AA16 -> 1122.05 | HX16: =+AD16 -> 1147.3 | HY16: =+AG16 -> 1286.2 | HZ16: =+AJ16 -> 1257 | IA16: =+AM16 -> 1322.75 | IB16: =+AP16 -> 1057.9 | IC16: =+AS16 -> 1118.1 | ID16: =+AV16 -> 1276.5 | IE16: =+AY16 -> 1224.7 | IF16: =+BB16 -> 1134.7 | IG16: =+BE16 -> 1039.1 | IH16: =+BH16 -> 1279.65 | II16: =+BK16 -> 1451.1 | IJ16: =+BN16 -> 1396.05 | IK16: =+BQ16 -> 1399.5 | IL16: =+BT16 -> 1286.6 | IM16: =+BW16 -> 1180.6 | IN16: =+BZ16 -> 1402.55 | IO16: =+CC16 -> 1332 | IP16: =+CF16 -> 1319.85 | IQ16: =+CI16 -> 1603.35 | IR16: =+CL16 -> 1521 | IS16: =+CO16 -> 1284.1 | IT16: =+CR16 -> 932.65 | IU16: =+CU16 -> 943.6 | IV16: =+CX16 -> 859.45 | IW16: =+DA16 -> 1212.15 | IX16: =+DD16 -> 1417.4 | IY16: =+DG16 -> 1806.05 | IZ16: =+DJ16 -> 1869.05 | JA16: =+DM16 -> 2234.85 | JB16: =+DP16 -> 2154.3 | JC16: =+DS16 -> 2296.25 | JD16: =+DV16 -> 3090.4 | JE16: =+DY16 -> 2683.15 | JF16: =+EB16 -> 3365.5 | JG16: =+EE16 -> 4421.25 | JH16: =+EH16 -> 4100.35 | JI16: =+EK16 -> 4673.95 | JJ16: =+EN16 -> 6363.3 | JK16: =EQ16 -> 8492.6 | JL16: =ET16 -> 8061.5 | JM16: =EW16 -> 6913.95 | JN16: =EZ16 -> 5542.55 | JO16: =FC16 -> 6076.95 | JP16: =FF16 -> 5184.95 | JQ16: =FI16 -> 5170.3 | JR16: =FL16 -> 5936.5 | JS16: =FO16 -> 7017.2 | JT16: =FR16 -> 0 | JU16: =FU16 -> 0 | JV16: =FX16 -> 0 | JW16: =GA16 -> 0 | JX16: =GD16 -> 0 | JY16: =GG16 -> 0 | JZ16: =GJ16 -> 0 | KA16: =GM16 -> 0 | KB16: =GP16 -> 0 | KC16: =GS16 -> 0 | KD16: =GV16 -> 0 | KE16: =GY16 -> 0 | KF16: =HB16 -> 0 | KG16: =HE16 -> 0 | KH16: =HH16 -> 0
A19: High | HP19: =+IF(HP14=0,HP7,HP14) -> 822.25 | HQ19: =+IF(HQ14=0,HQ7,HQ14) -> 830 | HR19: =+IF(HR14=0,HR7,HR14) -> 737 | HS19: =+IF(HS14=0,HS7,HS14) -> 694.4 | HT19: =+IF(HT14=0,HT7,HT14) -> 627.2 | HU19: =+IF(HU14=0,HU7,HU14) -> 720.2 | HV19: =+IF(HV14=0,HV7,HV14) -> 858 | HW19: =+IF(HW14=0,HW7,HW14) -> 1125 | ... KH19: =+IF(KH14=0,KH7,KH14) -> 0
A20: Low | HP20: =+IF(HP15=0,HP8,HP15) -> 707.5 | HQ20: =+IF(HQ15=0,HQ8,HQ15) -> 676.95 | HR20: =+IF(HR15=0,HR8,HR15) -> 484.3 | HS20: =+IF(HS15=0,HS8,HS15) -> 469 | HT20: =+IF(HT15=0,HT8,HT15) -> 448.1 | HU20: =+IF(HU15=0,HU8,HU15) -> 535.15 | HV20: =+IF(HV15=0,HV8,HV15) -> 568.05 | HW20: =+IF(HW15=0,HW8,HW15) -> 807.3 | ... KH20: =+IF(KH15=0,KH8,KH15) -> 0
A21: Close | HP21: =+IF(HP16=0,HP9,HP16) -> 797.75 | HQ21: =+IF(HQ16=0,HQ9,HQ16) -> 700.4 | HR21: =+IF(HR16=0,HR9,HR16) -> 489.2 | HS21: =+IF(HS16=0,HS9,HS16) -> 610.85 | HT21: =+IF(HT16=0,HT9,HT16) -> 543.9 | HU21: =+IF(HU16=0,HU9,HU16) -> 692.8 | HV21: =+IF(HV16=0,HV9,HV16) -> 849.95 | HW21: =+IF(HW16=0,HW9,HW16) -> 1122.05 | ... KH21: =+IF(KH16=0,KH9,KH16) -> 0

Sheet QTR No. of Shares
A1: ='QTR Raw'!A1 -> 100002 | C1: 201206 | D1: 201209 | E1: 201212 | F1: 201303 | G1: 201306 | H1: 201309 | I1: 201312 | J1: 201403 | K1: 201406 | L1: 201409 | M1: 201412 | N1: 201503 | O1: 201506 | P1: 201509 | Q1: 201512 | R1: 201603 | S1: 201606 | T1: 201609 | U1: 201612 | V1: 201703 | W1: 201706 | X1: 201709 | Y1: 201712 | Z1: 201803 | AA1: 201806 | AB1: 201809 | AC1: 201812 | AD1: 201903 | AE1: 201906 | AF1: 201909 | AG1: 201912 | AH1: 202003 | AI1: 202006 | AJ1: 202009 | AK1: 202012 | AL1: 202103 | AM1: 202106 | AN1: 202109 | AO1: 202112 | AP1: 202203 | AQ1: 202206 | AR1: 202209 | AS1: 202212 | AT1: 202303 | AU1: 202306 | AV1: 202309 | AW1: 202312 | AX1: 202403 | AY1: 202406
A4: Field Description | B4: Field Name
A5: Date End | B5: SHP_DATE_END | C5: {=_xll.EQNXTDZ($A$1,$B5,C$1)} -> 201206 | D5: {=_xll.EQNXTDZ($A$1,$B5,D$1)} -> 201209 | E5: {=_xll.EQNXTDZ($A$1,$B5,E$1)} -> 201212 | F5: {=_xll.EQNXTDZ($A$1,$B5,F$1)} -> 201303 | G5: {=_xll.EQNXTDZ($A$1,$B5,G$1)} -> 201306 | H5: {=_xll.EQNXTDZ($A$1,$B5,H$1)} -> 201309 | I5: {=_xll.EQNXTDZ($A$1,$B5,I$1)} -> 201312 | J5: {=_xll.EQNXTDZ($A$1,$B5,J$1)} -> 201403 | ... AY5: {=_xll.EQNXTDZ($A$1,$B5,AY$1)} -> 202406
A6: Grand Total | B6: SHP_NSGRANDTOTAL | C6: {=_xll.EQNXTDZ($A$1,$B6,C$1)} -> 211908375 | D6: {=_xll.EQNXTDZ($A$1,$B6,D$1)} -> 211908375 | E6: {=_xll.EQNXTDZ($A$1,$B6,E$1)} -> 211908375 | F6: {=_xll.EQNXTDZ($A$1,$B6,F$1)} -> 211908375 | G6: {=_xll.EQNXTDZ($A$1,$B6,G$1)} -> 211908375 | H6: {=_xll.EQNXTDZ($A$1,$B6,H$1)} -> 211908375 | I6: {=_xll.EQNXTDZ($A$1,$B6,I$1)} -> 211908375 | J6: {=_xll.EQNXTDZ($A$1,$B6,J$1)} -> 211908375 | ... AY6: {=_xll.EQNXTDZ($A$1,$B6,AY$1)} -> 211908375
B7: In Crs. | C7: =+C6/10^7 -> 21.190838 | D7: =+D6/10^7 -> 21.190838 | E7: =+E6/10^7 -> 21.190838 | F7: =+F6/10^7 -> 21.190838 | G7: =+G6/10^7 -> 21.190838 | H7: =+H6/10^7 -> 21.190838 | I7: =+I6/10^7 -> 21.190838 | J7: =+J6/10^7 -> 21.190838 | ... AY7: =+AY6/10^7 -> 21.190838

Sheet Share price Daily
A1: =_xll.EQNXTH(B1,"[ADJC];[ADJH];[ADJL];[ADJO];[UCLS];[VOLUME]","2015-Jan-01","Y","All traded days","Asc") -> EQNXTH | B1: =+'Annual Raw'!A1 -> 100002 | L1: =_xll.EQNXTH(B1,"[NADJC];[NADJH];[NADJLOW];[NADJOPEN];[NUCLOSE];[NVOLUME]","2015-Jan-01","Y","All traded days","Asc") -> EQNXTH
A2: ABB India Ltd. | L2: ABB India Ltd.
A3: DATE | B3: ADJHIGH | C3: ADJCLOSE | D3: ADJLOW | E3: ADJOPEN | F3: CLOSE | G3: VOLUME | L3: DATE | M3: ADJCLOSE | N3: ADJHIGH | O3: ADJLOW | P3: ADJOPEN | Q3: CLOSE | R3: VOLUME
A4: 42005 | B4: 1329.8 | C4: 1299.85 | D4: 1272 | E4: 1285 | F4: 1299.85 | G4: 18165 | L4: 42005 | M4: 1301.5 | N4: 1330.95 | O4: 1272 | P4: 1280 | Q4: 1301.5 | R4: 101186
A5: 42006 | B5: 1322.2 | C5: 1289.75 | D5: 1280.2 | E5: 1308.7 | F5: 1289.75 | G5: 8526 | L5: 42006 | M5: 1288 | N5: 1323 | O5: 1284 | P5: 1313.75 | Q5: 1288 | R5: 45892
A6: 42009 | B6: 1313.65 | C6: 1285.3 | D6: 1282.25 | E6: 1299.3 | F6: 1285.3 | G6: 7683 | L6: 42009 | M6: 1288.3 | N6: 1314 | O6: 1285 | P6: 1298 | Q6: 1288.3 | R6: 36267
A7: 42010 | B7: 1286 | C7: 1277.5 | D7: 1252.05 | E7: 1282.6 | F7: 1277.5 | G7: 10516 | L7: 42010 | M7: 1276.6 | N7: 1287.95 | O7: 1251.3 | P7: 1286.45 | Q7: 1276.6 | R7: 58285
A8: 42011 | B8: 1290 | C8: 1260.05 | D8: 1255.15 | E8: 1284 | F8: 1260.05 | G8: 9783 | L8: 42011 | M8: 1258.2 | N8: 1291.9 | O8: 1253.1 | P8: 1287.9 | Q8: 1258.2 | R8: 41375
A9: 42012 | B9: 1320 | C9: 1289.55 | D9: 1275 | E9: 1280.65 | F9: 1289.55 | G9: 8764 | L9: 42012 | M9: 1288 | N9: 1320 | O9: 1264 | P9: 1264 | Q9: 1288 | R9: 69647
A10: 42013 | B10: 1303.25 | C10: 1267.85 | D10: 1260 | E10: 1300 | F10: 1267.85 | G10: 15028 | L10: 42013 | M10: 1265.05 | N10: 1302.9 | O10: 1256 | P10: 1294.95 | Q10: 1265.05 | R10: 125042
A11: 42016 | B11: 1280 | C11: 1266.7 | D11: 1258.25 | E11: 1270 | F11: 1266.7 | G11: 4849 | L11: 42016 | M11: 1267 | N11: 1279.95 | O11: 1259.4 | P11: 1272.9 | Q11: 1267 | R11: 35173
A12: 42017 | B12: 1304.5 | C12: 1271.95 | D12: 1266.7 | E12: 1269.85 | F12: 1271.95 | G12: 10894 | L12: 42017 | M12: 1271.3 | N12: 1304 | O12: 1266 | P12: 1267 | Q12: 1271.3 | R12: 82551
A13: 42018 | B13: 1300 | C13: 1256.9 | D13: 1250 | E13: 1274 | F13: 1256.9 | G13: 14091 | L13: 42018 | M13: 1262.5 | N13: 1302 | O13: 1254 | P13: 1270 | Q13: 1262.5 | R13: 53309
A14: 42019 | B14: 1299 | C14: 1267.65 | D14: 1261.1 | E14: 1299 | F14: 1267.65 | G14: 6934 | L14: 42019 | M14: 1268.15 | N14: 1287 | O14: 1261.05 | P14: 1262 | Q14: 1268.15 | R14: 43272
A15: 42020 | B15: 1288 | C15: 1276.75 | D15: 1253.2 | E15: 1270 | F15: 1276.75 | G15: 10486 | L15: 42020 | M15: 1276.45 | N15: 1288 | O15: 1253.9 | P15: 1261 | Q15: 1276.45 | R15: 67445
... A2840: 46189 | B2840: 7079.05 | C2840: 7017.2 | D2840: 6936.25 | E2840: 6936.25 | F2840: 7017.2 | G2840: 11992 | L2840: 46189 | M2840: 7021 | N2840: 7079.5 | O2840: 6939 | P2840: 6955 | Q2840: 7021 | R2840: 366666

Sheet Sheet2
J19: 219.3 | K19: 186.25 | L19: 186.75
J20: 192.9 | K20: 135.5 | L20: 146.9 | N20: 219.3 | O20: 192.9 | P20: 186 | Q20: 178.7 | R20: 207 | S20: 255.15 | T20: 348.25 | U20: 374 | V20: 495.9 | W20: 659.9 | X20: 613.4 | Y20: 607.9 | Z20: 555.95 | AA20: 497.8 | AB20: 459.9 | AC20: 374 | AD20: 362 | AE20: 341.5 | AF20: 384.2 | AG20: 433.8 | AH20: 460 | AI20: 474.4 | AJ20: 414.4 | AK20: 318.7 | AL20: 303.25 | AM20: 332.7 | AN20: 295 | AO20: 247 | AP20: 214.4 | AQ20: 179.5 | AR20: 97.9 | AS20: 119.1 | AT20: 130.65 | AU20: 148.55 | AV20: 153.8 | AW20: 152.9 | AX20: 136 | AY20: 141.15 | AZ20: 128.1 | BA20: 142.5 | BB20: 143.55 | BC20: 124.5 | BD20: 241 | BE20: 450 | BF20: 503.35
J21: 186 | K21: 145.4 | L21: 169.1 | N21: 186.25 | O21: 135.5 | P21: 145.4 | Q21: 108.95 | R21: 137 | S21: 170 | T21: 243.15 | U21: 307.5 | V21: 325.1 | W21: 463 | X21: 467.05 | Y21: 436.5 | Z21: 467 | AA21: 348.2 | AB21: 325 | AC21: 313.1 | AD21: 285 | AE21: 277.85 | AF21: 327 | AG21: 317 | AH21: 370.7 | AI21: 360 | AJ21: 271.15 | AK21: 233.15 | AL21: 218.8 | AM21: 262 | AN21: 223.6 | AO21: 137.6 | AP21: 142 | AQ21: 59.3 | AR21: 58 | AS21: 72.8 | AT21: 80 | AU21: 107.25 | AV21: 106 | AW21: 125.1 | AX21: 112.25 | AY21: 81.45 | AZ21: 88 | BA21: 90.35 | BB21: 106.05 | BC21: 98.55 | BD21: 119.25 | BE21: 210 | BF21: 349
J22: 178.7 | K22: 108.95 | L22: 139.75 | N22: 186.75 | O22: 146.9 | P22: 169.1 | Q22: 139.75 | R22: 202.15 | S22: 249.05 | T22: 346.4 | U22: 349.2 | V22: 469.9 | W22: 584.8 | X22: 536.15 | Y22: 513.35 | Z22: 474 | AA22: 438.55 | AB22: 355.4 | AC22: 334.95 | AD22: 298.8 | AE22: 328.35 | AF22: 343 | AG22: 389.9 | AH22: 443.05 | AI22: 407.5 | AJ22: 290.1 | AK22: 235.75 | AL22: 292.65 | AM22: 276.1 | AN22: 237.05 | AO22: 190.1 | AP22: 147.2 | AQ22: 71.9 | AR22: 75.2 | AS22: 90.1 | AT22: 117.2 | AU22: 116.3 | AV22: 140.5 | AW22: 128.6 | AX22: 133.65 | AY22: 91.65 | AZ22: 97.65 | BA22: 125 | BB22: 115.35 | BC22: 119.25 | BD22: 219.3 | BE22: 442.65 | BF22: 503.35
J23: 207 | K23: 137 | L23: 202.15
J24: 255.15 | K24: 170 | L24: 249.05
J25: 348.25 | K25: 243.15 | L25: 346.4
J26: 374 | K26: 307.5 | L26: 349.2
J27: 495.9 | K27: 325.1 | L27: 469.9
J28: 659.9 | K28: 463 | L28: 584.8
J29: 613.4 | K29: 467.05 | L29: 536.15
J30: 607.9 | K30: 436.5 | L30: 513.35
J31: 555.95 | K31: 467 | L31: 474
J32: 497.8 | K32: 348.2 | L32: 438.55
J33: 459.9 | K33: 325 | L33: 355.4
J34: 374 | K34: 313.1 | L34: 334.95
... J63: 503.35 | K63: 349 | L63: 503.35
