Workbook

Sheet Template
A1: =+'Annual Raw'!C4 -> Adani Energy Solutions Ltd. | B1: 36951 | C1: =EOMONTH(B1,12) -> 37346 | D1: =EOMONTH(C1,12) -> 37711 | E1: =EOMONTH(D1,12) -> 38077 | F1: =EOMONTH(E1,12) -> 38442 | G1: =EOMONTH(F1,12) -> 38807 | H1: =EOMONTH(G1,12) -> 39172 | I1: =EOMONTH(H1,12) -> 39538 | J1: =EOMONTH(I1,12) -> 39903 | ... AE1: =EOMONTH(AD1,12) -> 47573 | AH1: QTR | AI1: 41061 | AJ1: 41153 | AK1: 41244 | AL1: 41334 | AM1: 41426 | AN1: 41518 | AO1: 41609 | AP1: 41699 | AQ1: 41791 | AR1: 41883 | AS1: 41974 | AT1: 42064 | AU1: 42156 | AV1: 42248 | AW1: 42339 | AX1: 42430 | AY1: 42522 | AZ1: 42614 | BA1: 42705 | BB1: 42795 | BC1: 42887 | BD1: 42979 | BE1: 43070 | BF1: 43160 | BG1: 43252 | BH1: 43344 | BI1: 43435 | BJ1: 43525 | BK1: 43617 | BL1: 43709 | BM1: 43800 | BN1: 43891 | BO1: 43983 | BP1: 44075 | BQ1: =EOMONTH(BP1,3) -> 44196 | BR1: =EOMONTH(BQ1,3) -> 44286 | BS1: =EOMONTH(BR1,3) -> 44377 | BT1: =EOMONTH(BS1,3) -> 44469 | BU1: =EOMONTH(BT1,3) -> 44561 | BV1: =EOMONTH(BU1,3) -> 44651 | BW1: =EOMONTH(BV1,3) -> 44742 | BX1: =EOMONTH(BW1,3) -> 44834 | ... DB1: =EOMONTH(DA1,3) -> 47573 | DE1: HISTORICAL ESTIMATES | DF1: 46112 | DG1: 46112
A2: Presentation Data (Start)
A4: Unit metrics
A5: Distribution unit metrics
A6: MU solds | W6: =SUM(BS6:BV6) -> 7955 | X6: =SUM(BW6:BZ6) -> 9051 | Y6: =SUM(CA6:CD6) -> 9916 | Z6: =SUM(CE6:CH6) -> 10558 | AA6: =CL6 -> 2508 | AB6: =CP6 -> 2583.24 | AC6: =CT6 -> 2673.6534 | AD6: =CX6 -> 2774.9451 | AE6: =DB6 -> 2888.7403 | BR6: 1873 | BS6: 2036 | BT6: 1975 | BU6: 2060 | BV6: 1884 | BW6: 2560 | BX6: 2233 | BY6: 2169 | BZ6: 2089 | CA6: 2754 | CB6: 2446 | CC6: 2489 | CD6: =9916-SUM(CA6:CC6) -> 2227 | CE6: 2962 | CF6: 2609 | CG6: 2574 | CH6: =10558-SUM(CE6:CG6) -> 2413 | CI6: 2939 | CJ6: 2650 | CK6: =8076-SUM(CI6:CJ6) -> 2487 | CL6: 2508 | CM6: =CI6*(1+CM11) -> 3027.17 | CN6: =CJ6*(1+CN11) -> 2729.5 | CO6: =CK6*(1+CO11) -> 2561.61 | CP6: =CL6*(1+CP11) -> 2583.24 | CQ6: =CM6*(1+CQ11) -> 3133.1209 | CR6: =CN6*(1+CR11) -> 2825.0325 | CS6: =CO6*(1+CS11) -> 2651.2663 | CT6: =CP6*(1+CT11) -> 2673.6534 | ... DB6: =CX6*(1+DB11) -> 2888.7403 | DG6: 2508
A7: Revenue per MU sold (in cr) | W7: =W25*10/W6 -> 8.7571087 | X7: =X25*10/X6 -> 9.4927743 | Y7: =Y25*10/Y6 -> 10.258945 | Z7: =Z25*10/Z6 -> 11.618185 | AA7: =AA25*10/AA6 -> 49.644139 | AB7: =AB25*10/AB6 -> 49.99706 | AC7: =AC25*10/AC6 -> 50.560001 | AD7: =AD25*10/AD6 -> 51.071509 | AE7: =AE25*10/AE6 -> 51.60437 | BR7: =BR25*10/BR6 -> 8.3054992 | BS7: =BS25*10/BS6 -> 8.555501 | BT7: =BT25*10/BT6 -> 8.559038 | BU7: =BU25*10/BU6 -> 8.7246602 | BV7: =BV25*10/BV6 -> 9.2180998 | BW7: =BW25*10/BW6 -> 8.6435156 | BX7: =BX25*10/BX6 -> 9.6904165 | BY7: =BY25*10/BY6 -> 9.6996312 | ... CL7: =CL25*10/CL6 -> 11.439394 | CM7: =CI7*(1+CM12) -> 11.600558 | CN7: =CJ7*(1+CN12) -> 11.974977 | CO7: =CK7*(1+CO12) -> 12.700454 | CP7: =CL7*(1+CP12) -> 11.438174 | CQ7: =CM7*(1+CQ12) -> 11.748536 | CR7: =CN7*(1+CR12) -> 12.121636 | CS7: =CO7*(1+CS12) -> 12.838055 | CT7: =CP7*(1+CT12) -> 11.542392 | ... DB7: =CX7*(1+DB12) -> 11.807892 | DG7: 12.480901
A8: Transmission availability | W8: =AVERAGE(BS8:BV8) -> 0.9999 | X8: =AVERAGE(BW8:BZ8) -> 0.9999 | Y8: =AVERAGE(CA8:CD8) -> 0.996525 | Z8: =AVERAGE(CE8:CH8) -> 0.993075 | AA8: =AVERAGE(CI8:CL8) -> 0.9947 | AB8: =AVERAGE(CM8:CP8) -> 0.99437773 | AC8: =AVERAGE(CQ8:CT8) -> 0.99432689 | AD8: =AVERAGE(CQ8:CT8) -> 0.99432689 | AE8: =AVERAGE(CY8:DB8) -> 0.99431995 | BR8: 0.9999 | BS8: 0.9999 | BT8: 0.9999 | BU8: 0.9999 | BV8: 0.9999 | BW8: 0.9999 | BX8: 0.9999 | BY8: 0.9999 | BZ8: 0.9999 | CA8: 0.9966 | CB8: 0.9947 | CC8: 0.9969 | CD8: 0.9979 | CE8: 0.997 | CF8: 0.9891 | CG8: 0.991 | CH8: 0.9952 | CI8: 0.9964 | CJ8: 0.9946 | CK8: 0.9936 | CL8: 0.9942 | CM8: =AVERAGE(CI8:CL8) -> 0.9947 | CN8: =AVERAGE(CJ8:CM8) -> 0.994275 | CO8: =AVERAGE(CK8:CN8) -> 0.99419375 | CP8: =AVERAGE(CL8:CO8) -> 0.99434219 | CQ8: =AVERAGE(CM8:CP8) -> 0.99437773 | CR8: =AVERAGE(CN8:CQ8) -> 0.99429717 | CS8: =AVERAGE(CO8:CR8) -> 0.99430271 | CT8: =AVERAGE(CP8:CS8) -> 0.99432995 | ... DB8: =AVERAGE(CX8:DA8) -> 0.99432043 | DG8: 0.9942
A10: Growth % Y-o-Y
A11: MU solds % | X11: =X6/W6-1 -> 0.13777498 | Y11: =Y6/X6-1 -> 0.09556955 | Z11: =Z6/Y6-1 -> 0.064743848 | AA11: =AA6/Z6-1 -> -0.76245501 | AB11: =AB6/AA6-1 -> 0.03 | AC11: =AC6/AB6-1 -> 0.035 | AD11: =AD6/AC6-1 -> 0.037885126 | AE11: =AE6/AD6-1 -> 0.041008078 | BV11: =BV6/BR6-1 -> 0.0058729311 | BW11: =BW6/BS6-1 -> 0.25736739 | BX11: =BX6/BT6-1 -> 0.13063291 | BY11: =BY6/BU6-1 -> 0.052912621 | BZ11: =BZ6/BV6-1 -> 0.10881104 | CA11: =CA6/BW6-1 -> 0.07578125 | CB11: =CB6/BX6-1 -> 0.095387371 | CC11: =CC6/BY6-1 -> 0.14753343 | ... CL11: =CL6/CH6-1 -> 0.039370079 | CM11: 0.03 | CN11: 0.03 | CO11: 0.03 | CP11: 0.03 | CQ11: 0.035 | CR11: =+CQ11 -> 0.035 | CS11: =+CR11 -> 0.035 | CT11: =+CS11 -> 0.035 | CU11: =+CT11*1.02 -> 0.0357 | CV11: =+CU11*1.02 -> 0.036414 | CW11: =+CV11*1.02 -> 0.03714228 | CX11: =+CW11*1.02 -> 0.037885126 | CY11: =+CX11*1.02 -> 0.038642828 | CZ11: =+CY11*1.02 -> 0.039415685 | DA11: =+CZ11*1.02 -> 0.040203998 | DB11: =+DA11*1.02 -> 0.041008078 | DG11: 0.039370079
A12: Revenue per MU sold % | X12: =X7/W7-1 -> 0.084007812 | Y12: =Y7/X7-1 -> 0.080710953 | Z12: =Z7/Y7-1 -> 0.13249317 | AA12: =AA7/Z7-1 -> 3.2729684 | AB12: =AB7/AA7-1 -> 0.0071090218 | AC12: =AC7/AB7-1 -> 0.011259482 | AD12: =AD7/AC7-1 -> 0.010116856 | AE12: =AE7/AD7-1 -> 0.010433611 | BV12: =BV7/BR7-1 -> 0.10987908 | BW12: =BW7/BS7-1 -> 0.010287491 | BX12: =BX7/BT7-1 -> 0.13218524 | BY12: =BY7/BU7-1 -> 0.11174888 | BZ12: =BZ7/BV7-1 -> 0.096480611 | CA12: =CA7/BW7-1 -> 0.15009333 | CB12: =CB7/BX7-1 -> 0.04614405 | CC12: =CC7/BY7-1 -> 0.060330336 | ... CL12: =CL7/CH7-1 -> -0.050511061 | CM12: =AVERAGE(CI12:CL12)*1.12 -> 0.014751932 | CN12: =AVERAGE(CJ12:CM12)*1.12 -> 0.01778724 | CO12: =AVERAGE(CK12:CN12)*1.12 -> 0.017591146 | CP12: =AVERAGE(CL12:CO12)*1.12 -> -0.00010660809 | CQ12: =AVERAGE(CM12:CP12)*1.02 -> 0.012756046 | CR12: =AVERAGE(CN12:CQ12)*1.02 -> 0.012247095 | CS12: =AVERAGE(CO12:CR12)*1.02 -> 0.010834358 | CT12: =AVERAGE(CP12:CS12)*1.02 -> 0.0091113773 | CU12: =AVERAGE(CQ12:CT12)*1.03 -> 0.011574336 | CV12: =AVERAGE(CR12:CU12)*1.03 -> 0.011270045 | CW12: =AVERAGE(CS12:CV12)*1.03 -> 0.011018455 | CX12: =AVERAGE(CT12:CW12)*1.03 -> 0.01106586 | CY12: =AVERAGE(CU12:CX12)*1.03 -> 0.011569139 | CZ12: =AVERAGE(CV12:CY12)*1.03 -> 0.011567801 | DA12: =AVERAGE(CW12:CZ12)*1.03 -> 0.011644473 | DB12: =AVERAGE(CX12:DA12)*1.03 -> 0.011805673 | DG12: 0.03593575
A14: Transmission unit Metrics
A15: Transmission network length (CKM) | U15: =BN15 -> 14740 | V15: =BR15 -> 17276 | W15: =BV15 -> 18795 | X15: =BZ15 -> 19779 | Y15: =CD15 -> 20509 | Z15: =CH15 -> 26696 | AA15: =CL15 -> 27949 | AB15: =CP15 -> 29511 | AC15: =CT15 -> 30401 | AD15: =CX15 -> 32801 | AE15: =DB15 -> 34001 | BL15: 14738 | BM15: 14738 | BN15: 14740 | BO15: 14814 | BP15: 14837 | BQ15: 15487 | BR15: 17276 | BS15: 18801 | BT15: 18336 | BU15: 18567 | BV15: 18795 | BW15: 18795 | BX15: 18795 | BY15: 18795 | BZ15: 19779 | CA15: 19778 | CB15: 19862 | CC15: 20422 | CD15: 20509 | CE15: 21187 | CF15: 23269 | CG15: 25778 | CH15: 26696 | CI15: 26696 | CJ15: 26705 | CK15: 27901 | CL15: 27949 | CM15: =+CL15 -> 27949 | CN15: =+CM15+260 -> 28209 | CO15: =+CN15+658+644 -> 29511 | CP15: =+CO15 -> 29511 | CQ15: =+CP15+740 -> 30251 | CR15: =+CQ15 -> 30251 | CS15: =+CR15 -> 30251 | CT15: =+CS15+150 -> 30401 | CU15: =+CT15 -> 30401 | CV15: =+CU15 -> 30401 | CW15: =+CV15+2400 -> 32801 | CX15: =+CW15 -> 32801 | CY15: =+CX15 -> 32801 | CZ15: =+CY15 -> 32801 | DA15: =CZ15+1200 -> 34001 | DB15: =DA15 -> 34001 | DG15: 27949
A16: Power transmission capacity (MVA) | U16: =BN16 -> 27280 | V16: =BR16 -> 30905 | W16: =BV16 -> 40001 | X16: =BZ16 -> 46001 | Y16: =CD16 -> 57011 | Z16: =CH16 -> 90236 | AA16: =CL16 -> 123175 | AB16: =CP16 -> 138675 | AC16: =CT16 -> 147475 | AD16: =CX16 -> 169375 | AE16: =DB16 -> 186950 | BL16: 27280 | BM16: 27280 | BN16: 27280 | BO16: 27280 | BP16: 30905 | BQ16: 36766 | BR16: 30905 | BS16: 36766 | BT16: 36766 | BU16: 38641 | BV16: 40001 | BW16: 40001 | BX16: 40001 | BY16: 40001 | BZ16: 46001 | CA16: 46001 | CB16: 53161 | CC16: 54661 | CD16: 57011 | CE16: 57186 | CF16: 70686 | CG16: 84186 | CH16: 90236 | CI16: 93236 | CJ16: 97236 | CK16: 118175 | CL16: 123175 | CM16: =+CL16 -> 123175 | CN16: =+CM16+6000 -> 129175 | CO16: =+CN16+9500 -> 138675 | CP16: =CO16 -> 138675 | CQ16: =+CP16+2800 -> 141475 | CR16: =+CQ16 -> 141475 | CS16: =+CR16 -> 141475 | CT16: =+CS16+6000 -> 147475 | CU16: =+CT16 -> 147475 | CV16: =+CU16 -> 147475 | CW16: =+CV16+21900 -> 169375 | CX16: =+CW16 -> 169375 | CY16: =+CX16 -> 169375 | CZ16: =+CY16 -> 169375 | DA16: =CZ16+5400 -> 174775 | DB16: =DA16+9175+3000 -> 186950 | DG16: 123175
A17: Revenue Per MVA (in cr) | U17: =U26/U16 -> 0.10318915 | V17: =V26/V16 -> 0.10102119 | W17: =W26/W16 -> 0.086731082 | X17: =X26/X16 -> 0.085762483 | Y17: =Y26/Y16 -> 0.089704443 | Z17: =Z26/Z16 -> 0.092320027 | AA17: =AA26/AA16 -> 0.07975547 | AB17: =AB26/AB16 -> 0.08748011 | ... AE17: =AE26/AE16 -> 0.090123051 | BL17: =BL26/BL16 -> 0.024719575 | BM17: =BM26/BM16 -> 0.024880865 | BN17: =BN26/BN16 -> 0.029094575 | BO17: =BO26/BO16 -> 0.036991935 | BP17: =BP26/BP16 -> 0.022275684 | BQ17: =BQ26/BQ16 -> 0.019155198 | BR17: =BR26/BR16 -> 0.023304643 | BS17: =BS26/BS16 -> 0.028424359 | ... CL17: =CL26/CL16 -> 0.023032271 | CM17: =AVERAGE(CI17:CL17)*1.01 -> 0.023086087 | CN17: =AVERAGE(CJ17:CM17)*1.01 -> 0.022989308 | CO17: =AVERAGE(CK17:CN17)*1.01 -> 0.022635364 | CP17: =AVERAGE(CL17:CO17)*1.01 -> 0.023165115 | CQ17: =AVERAGE(CM17:CP17)*1.03 -> 0.023658038 | CR17: =AVERAGE(CN17:CQ17)*1.03 -> 0.023805315 | CS17: =AVERAGE(CO17:CR17)*1.03 -> 0.024015437 | CT17: =AVERAGE(CP17:CS17)*1.03 -> 0.024370805 | CU17: =AVERAGE(CQ17:CT17)*1.02 -> 0.024441647 | CV17: =AVERAGE(CR17:CU17)*1.02 -> 0.024641467 | CW17: =AVERAGE(CS17:CV17)*1.02 -> 0.024854686 | CX17: =AVERAGE(CT17:CW17)*1.02 -> 0.025068694 | CY17: =AVERAGE(CU17:CX17)*0.98 -> 0.024256591 | CZ17: =AVERAGE(CV17:CY17)*0.98 -> 0.024211252 | DA17: =AVERAGE(CW17:CZ17)*0.98 -> 0.02410585 | DB17: =AVERAGE(CX17:DA17)*0.98 -> 0.023922385 | DG17: 0.020537339
A18: Average System Availibity | V18: =AVERAGE(BO18:BR18) -> 0.99855 | W18: =AVERAGE(BS18:BV18) -> 0.9965 | X18: =AVERAGE(BW18:BZ18) -> 0.995975 | Y18: =AVERAGE(CA18:CD18) -> 0.997 | Z18: =AVERAGE(CE18:CH18) -> 0.996975 | AA18: =AVERAGE(CI18:CL18) -> 0.997325 | AB18: =AVERAGE(CM18:CP18) -> 0.99725713 | AC18: =AVERAGE(CQ18:CT18) -> 0.99726447 | AD18: =AVERAGE(CQ18:CT18) -> 0.99726447 | AE18: =AVERAGE(CY18:DB18) -> 0.99726976 | BL18: 99.8 | BM18: 0.9959 | BN18: 0.9961 | BO18: 0.9987 | BP18: 0.999 | BQ18: 0.9983 | BR18: 0.9982 | BS18: 0.9985 | BT18: 0.9936 | BU18: 0.9969 | BV18: 0.997 | BW18: 0.9918 | BX18: 0.9976 | BY18: 0.9975 | BZ18: 0.997 | CA18: 0.9977 | CB18: 0.9974 | CC18: 0.9967 | CD18: 0.9962 | CE18: 0.997 | CF18: 0.997 | CG18: 0.9971 | CH18: 0.9968 | CI18: 0.9983 | CJ18: 0.9963 | CK18: 0.997 | CL18: 0.9977 | CM18: =AVERAGE(CI18:CL18) -> 0.997325 | CN18: =AVERAGE(CJ18:CM18) -> 0.99708125 | CO18: =AVERAGE(CK18:CN18) -> 0.99727656 | CP18: =AVERAGE(CL18:CO18) -> 0.9973457 | CQ18: =AVERAGE(CM18:CP18) -> 0.99725713 | CR18: =AVERAGE(CN18:CQ18) -> 0.99724016 | CS18: =AVERAGE(CO18:CR18) -> 0.99727989 | CT18: =AVERAGE(CP18:CS18) -> 0.99728072 | ... DB18: =AVERAGE(CX18:DA18) -> 0.99727002 | DG18: 0.9977
A20: Meter unit metrics
A21: cumlative meters Installed (in mn) | Y21: =CD21 -> 0 | Z21: =CH21 -> 3.13 | AA21: =CL21 -> 10.13 | AB21: =CP21 -> 17.73 | AC21: =CT21 -> 29.01 | AD21: =CX21 -> 34.45 | AE21: =DB21 -> 42.61 | CF21: 0.68 | CG21: 1 | CH21: 3.13 | CI21: 5.54 | CJ21: 7.37 | CK21: 9.25 | CL21: 10.13 | CM21: =CL21+1.9 -> 12.03 | CN21: =CM21+1.9 -> 13.93 | CO21: =CN21+1.9 -> 15.83 | CP21: =CO21+1.9 -> 17.73 | CQ21: =CP21+2.82 -> 20.55 | CR21: =CQ21+2.82 -> 23.37 | CS21: =CR21+2.82 -> 26.19 | CT21: =CS21+2.82 -> 29.01 | CU21: =CT21+1.36 -> 30.37 | CV21: =CU21+1.36 -> 31.73 | CW21: =CV21+1.36 -> 33.09 | CX21: =CW21+1.36 -> 34.45 | CY21: =CX21+2.04 -> 36.49 | CZ21: =CY21+2.04 -> 38.53 | DA21: =CZ21+2.04 -> 40.57 | DB21: =DA21+2.04 -> 42.61 | DG21: 10.13
A22: Revenue per meter (in cr) | Z22: =Z28*10/Z21 -> 5291.5016 | AA22: =0+(AA28*10/AA21) -> 3528.8154 | AB22: =0+(AB28*10/AB21) -> 3554.3064 | AC22: =0+(AC28*10/AC21) -> 3683.4679 | AD22: =0+(AD28*10/AD21) -> 4236.4793 | AE22: =0+(AE28*10/AE21) -> 4380.8085 | CF22: =CF28*10/CF21 -> 3576.0294 | CG22: =CG28*10/CG21 -> 4784.8 | CH22: =CH28*10/CH21 -> 2691.4696 | CI22: =CI28*10/CI21 -> 1760.9386 | CJ22: =CJ28*10/CJ21 -> 1106.0109 | CK22: =CK28*10/CK21 -> 873.51351 | CL22: =CL28*10/CL21 -> 963.47483 | CM22: =AVERAGE(CI22:CL22) -> 1175.9845 | CN22: =AVERAGE(CJ22:CM22) -> 1029.7459 | CO22: =AVERAGE(CK22:CN22) -> 1010.6797 | CP22: =AVERAGE(CL22:CO22) -> 1044.9712 | CQ22: =AVERAGE(CM22:CP22)*1.02 -> 1086.6522 | CR22: =AVERAGE(CN22:CQ22)*1.02 -> 1063.8725 | CS22: =AVERAGE(CO22:CR22)*1.02 -> 1072.5748 | CT22: =AVERAGE(CP22:CS22)*1.02 -> 1088.358 | CU22: =AVERAGE(CQ22:CT22)*1.03 -> 1110.2003 | CV22: =AVERAGE(CR22:CU22)*1.03 -> 1116.264 | CW22: =AVERAGE(CS22:CV22)*1.03 -> 1129.7548 | CX22: =AVERAGE(CT22:CW22)*1.03 -> 1144.4786 | CY22: =AVERAGE(CU22:CX22)*1.03 -> 1158.9296 | CZ22: =AVERAGE(CV22:CY22)*1.03 -> 1171.4774 | DA22: =AVERAGE(CW22:CZ22)*1.03 -> 1185.6949 | DB22: =AVERAGE(CX22:DA22)*1.03 -> 1200.0995 | DG22: 1045.1891
A24: Revenue Breakup - Segment wise
A25: Distribution | S25: =SUM(BC25:BF25) -> 0 | T25: =SUM(BG25:BJ25) -> 4351.75 | U25: =SUM(BK25:BN25) -> 7676.35 | V25: =SUM(BO25:BR25) -> 6047.64 | W25: =SUM(BS25:BV25) -> 6966.28 | X25: =SUM(BW25:BZ25) -> 8591.91 | Y25: =SUM(CA25:CD25) -> 10172.77 | Z25: =SUM(CE25:CH25) -> 12266.48 | AA25: =SUM(CI25:CL25) -> 12450.75 | AB25: =SUM(CM25:CP25) -> 12915.441 | AC25: =SUM(CQ25:CT25) -> 13517.992 | AD25: =SUM(CU25:CX25) -> 14172.063 | AE25: =SUM(CY25:DB25) -> 14907.162 | BH25: 649.93 | BI25: 2005.94 | BJ25: 1695.88 | BK25: 2189.42 | BL25: 1913.6 | BM25: 1892.91 | BN25: 1680.42 | BO25: 1437.02 | BP25: 1467.16 | BQ25: 1587.84 | BR25: 1555.62 | BS25: 1741.9 | BT25: 1690.41 | BU25: 1797.28 | BV25: 1736.69 | BW25: 2212.74 | BX25: 2163.87 | BY25: 2103.85 | BZ25: 2111.45 | CA25: 2737.71 | CB25: 2479.65 | CC25: 2559.89 | CD25: 2395.52 | CE25: 3372.94 | CF25: 3013.95 | CG25: 2972.42 | CH25: 2907.17 | CI25: 3359.84 | CJ25: 3117.91 | CK25: 3104 | CL25: 2869 | CM25: =CM7*CM6*CM8/10 -> 3493.0743 | CN25: =CN7*CN6*CN8/10 -> 3249.8575 | CO25: =CO7*CO6*CO8/10 -> 3234.4712 | CP25: =CP7*CP6*CP8/10 -> 2938.0375 | CQ25: =CQ7*CQ6*CQ8/10 -> 3660.263 | CR25: =CR7*CR6*CR8/10 -> 3404.8728 | CS25: =CS7*CS6*CS8/10 -> 3384.3185 | CT25: =CT7*CT6*CT8/10 -> 3068.5376 | ... DB25: =DB7*DB6*DB8/10 -> 3391.6203 | DG25: 3112.0547
A26: Transmission | S26: =SUM(BC26:BF26) -> 3131.8 | T26: =SUM(BG26:BJ26) -> 2192.88 | U26: =SUM(BK26:BN26) -> 2815 | V26: =SUM(BO26:BR26) -> 3122.06 | W26: =SUM(BS26:BV26) -> 3469.33 | X26: =SUM(BW26:BZ26) -> 3945.16 | Y26: =SUM(CA26:CD26) -> 5114.14 | Z26: =SUM(CE26:CH26) -> 8330.59 | AA26: =SUM(CI26:CL26) -> 9823.88 | AB26: =SUM(CM26:CP26) -> 12131.304 | AC26: =SUM(CQ26:CT26) -> 13669.056 | AD26: =SUM(CU26:CX26) -> 15651.442 | AE26: =SUM(CY26:DB26) -> 16848.504 | AZ26: 498.37 | BA26: 508.03 | BB26: 508.99 | BC26: 497.09 | BD26: 506.71 | BE26: 1540.48 | BF26: 587.52 | BG26: 552.76 | BH26: 476.56 | BI26: 577.73 | BJ26: 585.83 | BK26: 668.2 | BL26: 674.35 | BM26: 678.75 | BN26: 793.7 | BO26: 1009.14 | BP26: 688.43 | BQ26: 704.26 | BR26: 720.23 | BS26: 1045.05 | BT26: 788.81 | BU26: 816.07 | BV26: 819.4 | BW26: 835.94 | BX26: 868.2 | BY26: 1173.18 | BZ26: 1067.84 | CA26: 926.19 | CB26: 1017.35 | CC26: 1264.54 | CD26: 1906.06 | CE26: 1746.18 | CF26: 2302.95 | CG26: 2034.76 | CH26: 2246.7 | CI26: 2188.19 | CJ26: 2371.69 | CK26: 2427 | CL26: 2837 | CM26: =CM16*CM17*CM18 -> 2836.022 | CN26: =CN16*CN17*CN18 -> 2960.9763 | CO26: =CO16*CO17*CO18 -> 3130.4103 | CP26: =CP16*CP17*CP18 -> 3203.8956 | CQ26: =CQ16*CQ17*CQ18 -> 3337.8404 | CR26: =CR16*CR17*CR18 -> 3358.5622 | CS26: =CS16*CS17*CS18 -> 3388.3421 | CT26: =CT16*CT17*CT18 -> 3584.3112 | ... DB26: =DB16*DB17*DB18 -> 4460.0806 | DG26: 2523.8684
A27: Trading | S27: =SUM(BC27:BF27) -> 815.78 | T27: =SUM(BG27:BJ27) -> 755.43 | U27: =SUM(BK27:BN27) -> 924.61 | V27: =SUM(BO27:BR27) -> 756.63 | W27: =SUM(BS27:BV27) -> 821.91 | X27: =SUM(BW27:BZ27) -> 755.65 | Y27: =SUM(CA27:CD27) -> 1029.59 | Z27: =SUM(CE27:CH27) -> 1380.44 | AA27: =SUM(CI27:CL27) -> 1091.071 | AB27: =SUM(CM27:CP27) -> 1145.6245 | AC27: =SUM(CQ27:CT27) -> 1191.4495 | AD27: =SUM(CU27:CX27) -> 1239.1075 | AE27: =SUM(CY27:DB27) -> 1288.6718 | AZ27: 184.33 | BA27: 221.19 | BB27: 326.53 | BC27: 112.23 | BD27: 239.32 | BE27: 241.81 | BF27: 222.42 | BG27: 67.94 | BH27: 264.24 | BI27: =246.3-86.9 -> 159.4 | BJ27: 263.85 | BK27: 0.46 | BL27: 5.45 | BM27: 205.86 | BN27: 712.84 | BO27: 0.35 | BP27: 0.6 | BQ27: 304.92 | BR27: 450.76 | BS27: 42.7 | BT27: 62.22 | BU27: 298.35 | BV27: 418.64 | BW27: 83.2 | BX27: 219.41 | BY27: 274.67 | BZ27: 178.37 | CA27: 0.01 | CB27: 176.87 | CC27: 738.3 | CD27: 114.41 | CE27: 167.27 | CF27: 490.29 | CG27: 344.6 | CH27: 378.28 | CI27: 209.71 | CJ27: 200.361 | CK27: 255 | CL27: 426 | CM27: =CI27*(1+CM37) -> 220.1955 | CN27: =CJ27*(1+CN37) -> 210.37905 | CO27: =CK27*(1+CO37) -> 267.75 | CP27: =CL27*(1+CP37) -> 447.3 | CQ27: =CM27*(1+CQ37) -> 229.00332 | CR27: =CN27*(1+CR37) -> 218.79421 | CS27: =CO27*(1+CS37) -> 278.46 | CT27: =CP27*(1+CT37) -> 465.192 | ... DB27: =CX27*(1+DB37) -> 503.15167 | DG27: 397.194
A28: Smart Meter | S28: =SUM(BC28:BF28) -> 0 | T28: =SUM(BG28:BJ28) -> 0 | U28: =SUM(BK28:BN28) -> 0 | V28: =SUM(BO28:BR28) -> 0 | W28: =SUM(BS28:BV28) -> 0 | X28: =SUM(BW28:BZ28) -> 0 | Y28: =SUM(CA28:CD28) -> 290.86 | Z28: =SUM(CE28:CH28) -> 1656.24 | AA28: =SUM(CI28:CL28) -> 3574.69 | AB28: =SUM(CM28:CP28) -> 6301.7853 | AC28: =SUM(CQ28:CT28) -> 10685.74 | AD28: =SUM(CU28:CX28) -> 14594.671 | AE28: =SUM(CY28:DB28) -> 18666.625 | CD28: 290.86 | CE28: 92.16 | CF28: 243.17 | CG28: 478.48 | CH28: 842.43 | CI28: 975.56 | CJ28: =181.64+633.49 -> 815.13 | CK28: 808 | CL28: 976 | CM28: =CM22*CM21/10 -> 1414.7093 | CN28: =CN22*CN21/10 -> 1434.4361 | CO28: =CO22*CO21/10 -> 1599.9059 | CP28: =CP22*CP21/10 -> 1852.734 | CQ28: =CQ22*CQ21/10 -> 2233.0703 | CR28: =CR22*CR21/10 -> 2486.27 | CS28: =CS22*CS21/10 -> 2809.0734 | CT28: =CT22*CT21/10 -> 3157.3267 | ... DB28: =DB22*DB21/10 -> 5113.624 | DG28: 1058.7765
A29: Others | S29: =SUM(BC29:BF29) -> 0 | T29: =SUM(BG29:BJ29) -> 0 | U29: =SUM(BK29:BN29) -> 0 | V29: =SUM(BO29:BR29) -> 0 | W29: =SUM(BS29:BV29) -> 0 | X29: =SUM(BW29:BZ29) -> 0 | Y29: =SUM(CA29:CD29) -> 0 | Z29: =SUM(CE29:CH29) -> 133.34 | AA29: =SUM(CI29:CL29) -> 648.2 | AB29: =SUM(CM29:CP29) -> 648.2 | AC29: =SUM(CQ29:CT29) -> 648.2 | AD29: =SUM(CU29:CX29) -> 648.2 | AE29: =SUM(CY29:DB29) -> 648.2 | CF29: 133.34 | CI29: 85.98 | CJ29: 90.22 | CK29: 137 | CL29: 335 | CM29: =CI29*(1+CM39) -> 85.98 | CN29: =CJ29*(1+CN39) -> 90.22 | CO29: =CK29*(1+CO39) -> 137 | CP29: =CL29*(1+CP39) -> 335 | CQ29: =CM29*(1+CQ39) -> 85.98 | CR29: =CN29*(1+CR39) -> 90.22 | CS29: =CO29*(1+CS39) -> 137 | CT29: =CP29*(1+CT39) -> 335 | ... DB29: =CX29*(1+DB39) -> 335 | DG29: 50
A30: Others (b/f) | S30: =SUM(BC30:BF30) -> 0 | T30: =SUM(BG30:BJ30) -> 0 | U30: =SUM(BK30:BN30) -> 0 | V30: =SUM(BO30:BR30) -> 0 | W30: =SUM(BS30:BV30) -> 0 | X30: =SUM(BW30:BZ30) -> 0 | Y30: =SUM(CA30:CD30) -> 0 | Z30: =SUM(CE30:CH30) -> 0 | AA30: =SUM(CI30:CL30) -> -1.08 | AB30: =SUM(CM30:CP30) -> 0 | AC30: =SUM(CQ30:CT30) -> 0 | AD30: =SUM(CU30:CX30) -> 0 | AE30: =SUM(CY30:DB30) -> 0 | CK30: -1.35 | CL30: 0.27 | CM30: 0 | CN30: 0 | CO30: 0 | CP30: 0 | CQ30: 0 | CR30: 0 | CS30: 0 | CT30: 0 | CU30: 0 | CV30: 0 | CW30: 0 | CX30: 0 | CY30: 0 | CZ30: 0 | DA30: 0 | DB30: 0 | DG30: 0
A31: Total | S31: =SUM(S25:S30) -> 3947.58 | T31: =SUM(T25:T30) -> 7300.06 | U31: =SUM(U25:U30) -> 11415.96 | V31: =SUM(V25:V30) -> 9926.33 | W31: =SUM(W25:W30) -> 11257.52 | X31: =SUM(X25:X30) -> 13292.72 | Y31: =SUM(Y25:Y30) -> 16607.36 | Z31: =SUM(Z25:Z30) -> 23767.09 | ... AE31: =SUM(AE25:AE30) -> 52359.163 | AZ31: =SUM(AZ25:AZ30) -> 682.7 | BA31: =SUM(BA25:BA30) -> 729.22 | BB31: =SUM(BB25:BB30) -> 835.52 | BC31: =SUM(BC25:BC30) -> 609.32 | BD31: =SUM(BD25:BD30) -> 746.03 | BE31: =SUM(BE25:BE30) -> 1782.29 | BF31: =SUM(BF25:BF30) -> 809.94 | BG31: =SUM(BG25:BG30) -> 620.7 | ... DB31: =SUM(DB25:DB30) -> 13803.477 | DG31: 7141.8936
A32: Checksum | S32: =S61-S31 -> -3.1 | T32: =T61-T31 -> 5.39 | U32: =U61-U31 -> 0 | V32: =V61-V31 -> 0 | W32: =W61-W31 -> 0 | X32: =X61-X31 -> 0 | Y32: =Y61-Y31 -> 0 | Z32: =Z61-Z31 -> 0 | ... AE32: =AE61-AE31 -> 0 | AZ32: =AZ61-AZ31 -> 0 | BA32: =BA61-BA31 -> 0 | BB32: =BB61-BB31 -> -0.9 | BC32: =BC61-BC31 -> -0.84 | BD32: =BD61-BD31 -> -0.95 | BE32: =BE61-BE31 -> -1.31 | BF32: =BF61-BF31 -> 0 | BG32: =BG61-BG31 -> 0 | ... DB32: =DB61-DB31 -> 0 | DG32: 0
A34: Revenue Growth % Y-o-Y
A35: Distribution % | U35: =U25/T25-1 -> 0.76396852 | V35: =V25/U25-1 -> -0.21217245 | W35: =W25/V25-1 -> 0.15190058 | X35: =X25/W25-1 -> 0.23335697 | Y35: =Y25/X25-1 -> 0.18399401 | Z35: =Z25/Y25-1 -> 0.20581513 | AA35: =AA25/Z25-1 -> 0.015022239 | AB35: =AB25/AA25-1 -> 0.037322292 | ... AE35: =AE25/AD25-1 -> 0.051869552 | BM35: =BM25/BI25-1 -> -0.056347647 | BN35: =BN25/BJ25-1 -> -0.0091162111 | BO35: =BO25/BK25-1 -> -0.34365266 | BP35: =BP25/BL25-1 -> -0.23329849 | BQ35: =BQ25/BM25-1 -> -0.16116456 | BR35: =BR25/BN25-1 -> -0.074267147 | BS35: =BS25/BO25-1 -> 0.21216128 | BT35: =BT25/BP25-1 -> 0.15216473 | ... DB35: =DB25/CX25-1 -> 0.053295832 | DG35: 0.070475643
A36: Transmission % | T36: =T26/S26-1 -> -0.29980203 | U36: =U26/T26-1 -> 0.28369997 | V36: =V26/U26-1 -> 0.10907993 | W36: =W26/V26-1 -> 0.11123105 | X36: =X26/W26-1 -> 0.13715328 | Y36: =Y26/X26-1 -> 0.29630737 | Z36: =Z26/Y26-1 -> 0.62893272 | AA36: =AA26/Z26-1 -> 0.17925381 | ... AE36: =AE26/AD26-1 -> 0.076482527 | BD36: =BD26/AZ26-1 -> 0.016734555 | BE36: =BE26/BA26-1 -> 2.0322619 | BF36: =BF26/BB26-1 -> 0.15428594 | BG36: =BG26/BC26-1 -> 0.11199179 | BH36: =BH26/BD26-1 -> -0.05950149 | BI36: =BI26/BE26-1 -> -0.62496754 | BJ36: =BJ26/BF26-1 -> -0.0028764978 | BK36: =BK26/BG26-1 -> 0.2088429 | ... DB36: =DB26/CX26-1 -> 0.053291202 | DG36: 0.1233669
A37: Trading % | T37: =T27/S27-1 -> -0.073978278 | U37: =U27/T27-1 -> 0.22395192 | V37: =V27/U27-1 -> -0.1816766 | W37: =W27/V27-1 -> 0.086277309 | X37: =X27/W27-1 -> -0.080617099 | Y37: =Y27/X27-1 -> 0.36252233 | Z37: =Z27/Y27-1 -> 0.34076671 | AA37: =AA27/Z27-1 -> -0.20962085 | ... AE37: =AE27/AD27-1 -> 0.04 | BD37: =BD27/AZ27-1 -> 0.29832366 | BE37: =BE27/BA27-1 -> 0.093223021 | BF37: =BF27/BB27-1 -> -0.31883747 | BG37: =BG27/BC27-1 -> -0.39463602 | BH37: =BH27/BD27-1 -> 0.10412836 | BI37: =BI27/BE27-1 -> -0.34080476 | BJ37: =BJ27/BF27-1 -> 0.18626922 | BK37: =BK27/BG27-1 -> -0.99322932 | ... CK37: =CK27/CG27-1 -> -0.26001161 | CL37: 0.05 | CM37: 0.05 | CN37: 0.05 | CO37: 0.05 | CP37: 0.05 | CQ37: 0.04 | CR37: 0.04 | CS37: 0.04 | CT37: 0.04 | CU37: 0.04 | CV37: 0.04 | CW37: 0.04 | CX37: 0.04 | CY37: 0.04 | CZ37: 0.04 | DA37: 0.04 | DB37: 0.04 | DG37: 0.05
A38: Smart Meter % | Z38: =Z28/Y28-1 -> 4.6942859 | AA38: =AA28/Z28-1 -> 1.1583164 | AB38: =AB28/AA28-1 -> 0.76289 | AC38: =AC28/AB28-1 -> 0.69566876 | AD38: =AD28/AC28-1 -> 0.36580813 | AE38: =AE28/AD28-1 -> 0.27900278 | CH38: =CH28/CD28-1 -> 1.8963419 | CI38: =CI28/CE28-1 -> 9.5855035 | CJ38: =CJ28/CF28-1 -> 2.3520994 | CK38: =CK28/CG28-1 -> 0.68868082 | CL38: =CL28/CH28-1 -> 0.15855323 | CM38: =CM28/CI28-1 -> 0.45015099 | CN38: =CN28/CJ28-1 -> 0.75976354 | CO38: =CO28/CK28-1 -> 0.9800816 | ... DB38: =DB28/CX28-1 -> 0.29697585 | DG38: 0.25681245
A39: Others % | AA39: =AA29/Z29-1 -> 3.8612569 | AB39: =AB29/AA29-1 -> 0 | AC39: =AC29/AB29-1 -> 0 | AD39: =AD29/AC29-1 -> 0 | AE39: =AE29/AD29-1 -> 0 | CJ39: =CJ29/CF29-1 -> -0.32338383 | CL39: 0 | CM39: 0 | CN39: 0 | CO39: 0 | CP39: 0 | CQ39: 0 | CR39: 0 | CS39: 0 | CT39: 0 | CU39: 0 | CV39: 0 | CW39: 0 | CX39: 0 | CY39: 0 | CZ39: 0 | DA39: 0 | DB39: 0 | DG39: 0
A41: EBITDA - Segment Wise
A42: Distribution - EBITDA | W42: =SUM(BS42:BV42) -> 0 | X42: =SUM(BW42:BZ42) -> 1895 | Y42: =SUM(CA42:CD42) -> 2339 | Z42: =SUM(CE42:CH42) -> 1864 | AA42: =SUM(CI42:CL42) -> 2090 | AB42: =SUM(CM42:CP42) -> 2685.1513 | AC42: =SUM(CQ42:CT42) -> 3003.0483 | AD42: =SUM(CU42:CX42) -> 3172.3451 | AE42: =SUM(CY42:DB42) -> 3342.2674 | BW42: 516 | BY42: 545 | BZ42: 834 | CA42: 516 | CB42: 516 | CC42: 677 | CD42: 630 | CE42: -79 | CF42: 588 | CG42: 482 | CH42: 873 | CI42: =1486-SUM(CJ42:CK42) -> 497 | CJ42: 492 | CK42: 497 | CL42: 604 | CM42: =CM25*CM51 -> 695.43967 | CN42: =CN25*CN51 -> 688.589 | CO42: =CO25*CO51 -> 664.37342 | CP42: =CP25*CP51 -> 636.74925 | CQ42: =CQ25*CQ51 -> 792.83865 | CR42: =CR25*CR51 -> 753.02569 | CS42: =CS25*CS51 -> 756.6441 | CT42: =CT25*CT51 -> 700.53984 | ... DB42: =DB25*DB51 -> 760.83068
A43: Transmission - EBITDA | W43: =SUM(BS43:BV43) -> 0 | X43: =SUM(BW43:BZ43) -> 3112 | Y43: =SUM(CA43:CD43) -> 3865 | Z43: =SUM(CE43:CH43) -> 5449 | AA43: =SUM(CI43:CL43) -> 5126 | AB43: =SUM(CM43:CP43) -> 6403.7424 | AC43: =SUM(CQ43:CT43) -> 7403.3865 | AD43: =SUM(CU43:CX43) -> 8491.4519 | AE43: =SUM(CY43:DB43) -> 9144.0792 | BW43: 810 | BY43: 1163 | BZ43: 1139 | CA43: 862 | CB43: 810 | CC43: 1055 | CD43: 1138 | CE43: 1707 | CF43: 1278 | CG43: 1138 | CH43: 1326 | CI43: 1213 | CJ43: 1322 | CK43: 1291 | CL43: 1300 | CM43: =CM26*CM52 -> 1518.6266 | CN43: =CN26*CN52 -> 1571.5745 | CO43: =CO26*CO52 -> 1640.6503 | CP43: =CP26*CP52 -> 1672.8911 | CQ43: =CQ26*CQ52 -> 1798.0389 | CR43: =CR26*CR52 -> 1811.9467 | CS43: =CS26*CS52 -> 1835.5633 | CT43: =CT26*CT52 -> 1957.8377 | ... DB43: =DB26*DB52 -> 2421.036
A44: Trading - EBITDA | W44: =SUM(BS44:BV44) -> 0 | X44: =SUM(BW44:BZ44) -> 0 | Y44: =SUM(CA44:CD44) -> 0 | Z44: =SUM(CE44:CH44) -> 26 | AA44: =SUM(CI44:CL44) -> 84 | AB44: =SUM(CM44:CP44) -> 105.99374 | AC44: =SUM(CQ44:CT44) -> 117.75884 | AD44: =SUM(CU44:CX44) -> 122.8324 | AE44: =SUM(CY44:DB44) -> 127.85405 | CE44: 1 | CF44: 0 | CG44: 1 | CH44: 24 | CI44: =52-SUM(CJ44:CK44) -> 17 | CJ44: 12 | CK44: 23 | CL44: 32 | CM44: =CM27*CM53 -> 19.061756 | CN44: =CN27*CN53 -> 18.501405 | CO44: =CO27*CO53 -> 25.424473 | CP44: =CP27*CP53 -> 43.006105 | CQ44: =CQ27*CQ53 -> 21.768891 | CR44: =CR27*CR53 -> 21.281493 | CS44: =CS27*CS53 -> 27.760067 | CT44: =CT27*CT53 -> 46.948386 | ... DB44: =DB27*DB53 -> 49.935029
A45: Smart Meter - EBITDA | W45: =SUM(BS45:BV45) -> 0 | X45: =SUM(BW45:BZ45) -> 0 | Y45: =SUM(CA45:CD45) -> 0 | Z45: =SUM(CE45:CH45) -> 150 | AA45: =SUM(CI45:CL45) -> 548 | AB45: =SUM(CM45:CP45) -> 1205.3147 | AC45: =SUM(CQ45:CT45) -> 2184.292 | AD45: =SUM(CU45:CX45) -> 3000.7588 | AE45: =SUM(CY45:DB45) -> 3843.2819 | CE45: 21 | CF45: 25 | CG45: 35 | CH45: 69 | CI45: 62 | CJ45: 116 | CK45: 156 | CL45: 214 | CM45: =CM28*CM54 -> 232.78809 | CN45: =CN28*CN54 -> 272.25186 | CO45: =CO28*CO54 -> 322.65187 | CP45: =CP28*CP54 -> 377.62288 | CQ45: =CQ28*CQ54 -> 436.91643 | CR45: =CR28*CR54 -> 506.37317 | CS45: =CS28*CS54 -> 582.15097 | CT45: =CT28*CT54 -> 658.85148 | ... DB45: =DB28*DB54 -> 1053.106
A46: Other (b/f) - EBITDA | W46: =SUM(BS46:BV46) -> 0 | X46: =SUM(BW46:BZ46) -> -522.59 | Y46: =SUM(CA46:CD46) -> -492.8 | Z46: =SUM(CE46:CH46) -> -421.9 | AA46: =SUM(CI46:CL46) -> 138.69 | AB46: =SUM(CM46:CP46) -> 154.42685 | AC46: =SUM(CQ46:CT46) -> 153.99463 | AD46: =SUM(CU46:CX46) -> 153.92052 | AE46: =SUM(CY46:DB46) -> 153.91979 | BW46: -118.07 | BZ46: -404.52 | CA46: -108.7 | CB46: 24.14 | CC46: -261.36 | CD46: -146.88 | CE46: 1 | CF46: -175.86 | CG46: 5 | CH46: -252.04 | CI46: 21.69 | CJ46: 12 | CK46: 28 | CL46: 77 | CM46: =CM29*CM55 -> 20.194692 | CN46: =CN29*CN55 -> 20.798307 | CO46: =CO29*CO55 -> 32.182523 | CP46: =CP29*CP55 -> 81.251325 | CQ46: =CQ29*CQ55 -> 20.286948 | CR46: =CR29*CR55 -> 21.3116 | CS46: =CS29*CS55 -> 32.556939 | CT46: =CT29*CT55 -> 79.839148 | ... DB46: =DB29*DB55 -> 79.551744
X47: =SUM(X42:X46) -> 4484.41 | Y47: =SUM(Y42:Y46) -> 5711.2 | Z47: =SUM(Z42:Z46) -> 7067.1 | AA47: =SUM(AA42:AA46) -> 7986.69 | AB47: =SUM(AB42:AB46) -> 10554.629 | AC47: =SUM(AC42:AC46) -> 12862.48 | AD47: =SUM(AD42:AD46) -> 14941.309 | AE47: =SUM(AE42:AE46) -> 16611.402 | BW47: =SUM(BW42:BW46) -> 1207.93 | BX47: =SUM(BX42:BX46) -> 0 | BY47: =SUM(BY42:BY46) -> 1708 | BZ47: =SUM(BZ42:BZ46) -> 1568.48 | CA47: =SUM(CA42:CA46) -> 1269.3 | CB47: =SUM(CB42:CB46) -> 1350.14 | CC47: =SUM(CC42:CC46) -> 1470.64 | CD47: =SUM(CD42:CD46) -> 1621.12 | ... DB47: =SUM(DB42:DB46) -> 4364.4595
X48: =X47-X81 -> -33.2 | Y48: =Y47-Y81 -> 0 | Z48: =Z47-Z81 -> 0.58 | AA48: =AA47-AA81 -> -2.15 | AB48: =AB47-AB81 -> 0 | AC48: =AC47-AC81 -> 0 | AD48: =AD47-AD81 -> 0 | AE48: =AE47-AE81 -> 0 | BW48: =BW47-BW81 -> 0 | BX48: =BX47-BX81 -> -1236.61 | BY48: =BY47-BY81 -> 167.83 | BZ48: =BZ47-BZ81 -> 0 | CA48: =CA47-CA81 -> 0 | CB48: =CB47-CB81 -> 0 | CC48: =CC47-CC81 -> 0 | CD48: =CD47-CD81 -> 0 | ... DB48: =DB47-DB81 -> 0
A50: EBITDA -Margin
A51: Distribution - EBITDA Margin | X51: =X42/X25 -> 0.22055631 | Y51: =Y42/Y25 -> 0.22992754 | Z51: =Z42/Z25 -> 0.15195883 | BY51: =BY42/BY25 -> 0.25904889 | BZ51: =BZ42/BZ25 -> 0.39498923 | CA51: =CA42/CA25 -> 0.18847869 | CB51: =CB42/CB25 -> 0.20809388 | CC51: =CC42/CC25 -> 0.26446449 | CD51: =CD42/CD25 -> 0.26299092 | CE51: =CE42/CE25 -> -0.023421703 | CF51: =CF42/CF25 -> 0.19509282 | ... CL51: =CL42/CL25 -> 0.21052632 | CM51: =AVERAGE(CI51:CL51)+3% -> 0.199091 | CN51: =AVERAGE(CJ51:CM51)+3% -> 0.21188283 | CO51: =AVERAGE(CK51:CN51)+1% -> 0.20540403 | CP51: =AVERAGE(CL51:CO51)+1% -> 0.21672605 | CQ51: =AVERAGE(CM51:CP51)*1.04 -> 0.21660702 | CR51: =AVERAGE(CN51:CQ51)*1.04 -> 0.22116118 | CS51: =AVERAGE(CO51:CR51)*1.04 -> 0.22357355 | CT51: =AVERAGE(CP51:CS51)*1.04 -> 0.22829763 | CU51: =AVERAGE(CQ51:CT51) -> 0.22240984 | CV51: =AVERAGE(CR51:CU51) -> 0.22386055 | CW51: =AVERAGE(CS51:CV51) -> 0.22453539 | CX51: =AVERAGE(CT51:CW51) -> 0.22477585 | CY51: =AVERAGE(CU51:CX51) -> 0.22389541 | CZ51: =AVERAGE(CV51:CY51) -> 0.2242668 | DA51: =AVERAGE(CW51:CZ51) -> 0.22436836 | DB51: =AVERAGE(CX51:DA51) -> 0.22432661
A52: Transmission - EBITDA Margin | X52: =X43/X26 -> 0.78881465 | Y52: =Y43/Y26 -> 0.75574779 | Z52: =Z43/Z26 -> 0.65409533 | BY52: =BY43/BY26 -> 0.99132273 | BZ52: =BZ43/BZ26 -> 1.0666392 | CA52: =CA43/CA26 -> 0.93069457 | CB52: =CB43/CB26 -> 0.79618617 | CC52: =CC43/CC26 -> 0.83429548 | CD52: =CD43/CD26 -> 0.59704312 | CE52: =CE43/CE26 -> 0.97756245 | CF52: =CF43/CF26 -> 0.5549404 | ... CL52: =CL43/CL26 -> 0.45823053 | CM52: =AVERAGE(CI52:CL52)+1% -> 0.5354777 | CN52: =AVERAGE(CJ52:CM52)+1% -> 0.53076227 | CO52: =AVERAGE(CK52:CN52)+1% -> 0.52410073 | CP52: =AVERAGE(CL52:CO52)+1% -> 0.52214281 | CQ52: =AVERAGE(CM52:CP52)*1.02 -> 0.5386833 | CR52: =AVERAGE(CN52:CQ52)*1.02 -> 0.53950072 | CS52: =AVERAGE(CO52:CR52)*1.02 -> 0.54172903 | CT52: =AVERAGE(CP52:CS52)*1.02 -> 0.54622424 | CU52: =AVERAGE(CQ52:CT52) -> 0.54153432 | CV52: =AVERAGE(CR52:CU52) -> 0.54224708 | CW52: =AVERAGE(CS52:CV52) -> 0.54293367 | CX52: =AVERAGE(CT52:CW52) -> 0.54323483 | CY52: =AVERAGE(CU52:CX52) -> 0.54248747 | CZ52: =AVERAGE(CV52:CY52) -> 0.54272576 | DA52: =AVERAGE(CW52:CZ52) -> 0.54284543 | DB52: =AVERAGE(CX52:DA52) -> 0.54282337
A53: Trading - EBITDA Margin | X53: =X44/X27 -> 0 | Y53: =Y44/Y27 -> 0 | Z53: =Z44/Z27 -> 0.018834574 | BY53: =BY44/BY27 -> 0 | BZ53: =BZ44/BZ27 -> 0 | CA53: =CA44/CA27 -> 0 | CB53: =CB44/CB27 -> 0 | CC53: =CC44/CC27 -> 0 | CD53: =CD44/CD27 -> 0 | CE53: =CE44/CE27 -> 0.0059783583 | CF53: =CF44/CF27 -> 0 | ... CL53: =CL44/CL27 -> 0.075117371 | CM53: =AVERAGE(CI53:CL53)+1% -> 0.086567418 | CN53: =AVERAGE(CJ53:CM53)+1% -> 0.087943191 | CO53: =AVERAGE(CK53:CN53)+1% -> 0.094956014 | CP53: =AVERAGE(CL53:CO53)+1% -> 0.096145998 | CQ53: =AVERAGE(CM53:CP53)*1.04 -> 0.095059282 | CR53: =AVERAGE(CN53:CQ53)*1.04 -> 0.097267166 | CS53: =AVERAGE(CO53:CR53)*1.04 -> 0.0996914 | CT53: =AVERAGE(CP53:CS53)*1.04 -> 0.1009226 | CU53: =AVERAGE(CQ53:CT53) -> 0.098235112 | CV53: =AVERAGE(CR53:CU53) -> 0.099029069 | CW53: =AVERAGE(CS53:CV53) -> 0.099469545 | CX53: =AVERAGE(CT53:CW53) -> 0.099414082 | CY53: =AVERAGE(CU53:CX53) -> 0.099036952 | CZ53: =AVERAGE(CV53:CY53) -> 0.099237412 | DA53: =AVERAGE(CW53:CZ53) -> 0.099289498 | DB53: =AVERAGE(CX53:DA53) -> 0.099244486
A54: Smart Meter - EBITDA Margin | X54: =X45/X28 -> #DIV/0! | Y54: =Y45/Y28 -> 0 | Z54: =Z45/Z28 -> 0.090566585 | BY54: =BY45/BY28 -> #DIV/0! | BZ54: =BZ45/BZ28 -> #DIV/0! | CA54: =CA45/CA28 -> #DIV/0! | CB54: =CB45/CB28 -> #DIV/0! | CC54: =CC45/CC28 -> #DIV/0! | CD54: =CD45/CD28 -> 0 | CE54: =CE45/CE28 -> 0.22786458 | CF54: =CF45/CF28 -> 0.10280873 | ... CL54: =CL45/CL28 -> 0.2192623 | CM54: =AVERAGE(CI54:CL54)+1% -> 0.16454836 | CN54: =AVERAGE(CJ54:CM54)+1% -> 0.18979714 | CO54: =AVERAGE(CK54:CN54)+1% -> 0.20166927 | CP54: =AVERAGE(CL54:CO54)+1% -> 0.20381927 | CQ54: =AVERAGE(CM54:CP54)*1.03 -> 0.19565726 | CR54: =AVERAGE(CN54:CQ54)*1.03 -> 0.20366781 | CS54: =AVERAGE(CO54:CR54)*1.03 -> 0.20723951 | CT54: =AVERAGE(CP54:CS54)*1.03 -> 0.20867384 | CU54: =AVERAGE(CQ54:CT54) -> 0.2038096 | CV54: =AVERAGE(CR54:CU54) -> 0.20584769 | CW54: =AVERAGE(CS54:CV54) -> 0.20639266 | CX54: =AVERAGE(CT54:CW54) -> 0.20618095 | CY54: =AVERAGE(CU54:CX54) -> 0.20555773 | CZ54: =AVERAGE(CV54:CY54) -> 0.20599476 | DA54: =AVERAGE(CW54:CZ54) -> 0.20603152 | DB54: =AVERAGE(CX54:DA54) -> 0.20594124
A55: Other - EBITDA Margin | X55: =X46/X29 -> #DIV/0! | Y55: =Y46/Y29 -> #DIV/0! | Z55: =Z46/Z29 -> -3.1640918 | CI55: =CI46/CI29 -> 0.25226797 | CJ55: =CJ46/CJ29 -> 0.1330082 | CK55: =CK46/CK29 -> 0.20437956 | CL55: =CL46/CL29 -> 0.22985075 | CM55: =AVERAGE(CI55:CL55)+3% -> 0.23487662 | CN55: =AVERAGE(CJ55:CM55)+3% -> 0.23052878 | CO55: =AVERAGE(CK55:CN55)+1% -> 0.23490893 | CP55: =AVERAGE(CL55:CO55)+1% -> 0.24254127 | CQ55: =AVERAGE(CM55:CP55)*1.001 -> 0.23594961 | CR55: =AVERAGE(CN55:CQ55)*1.001 -> 0.23621813 | CS55: =AVERAGE(CO55:CR55)*1.001 -> 0.23764189 | CT55: =AVERAGE(CP55:CS55)*1.001 -> 0.23832581 | CU55: =AVERAGE(CQ55:CT55) -> 0.23703386 | CV55: =AVERAGE(CR55:CU55) -> 0.23730492 | CW55: =AVERAGE(CS55:CV55) -> 0.23757662 | CX55: =AVERAGE(CT55:CW55) -> 0.23756031 | CY55: =AVERAGE(CU55:CX55) -> 0.23736893 | CZ55: =AVERAGE(CV55:CY55) -> 0.23745269 | DA55: =AVERAGE(CW55:CZ55) -> 0.23748964 | DB55: =AVERAGE(CX55:DA55) -> 0.23746789
A57: Presentation Data (End)
A58: Profit & Loss- Annual (Start)
A59: Gross Revenue | B59: ='Annual Raw'!C6 -> 0 | C59: ='Annual Raw'!D6 -> 0 | D59: ='Annual Raw'!E6 -> 0 | E59: ='Annual Raw'!F6 -> 0 | F59: ='Annual Raw'!G6 -> 0 | G59: ='Annual Raw'!H6 -> 0 | H59: ='Annual Raw'!I6 -> 0 | I59: ='Annual Raw'!J6 -> 0 | ... AA59: ='Annual Raw'!AB6 -> 27588.03 | AB59: =+SUM(CM59:CP59) -> 33142.355 | AC59: =+SUM(CQ59:CT59) -> 39712.438 | AD59: =+SUM(CU59:CX59) -> 46305.484 | AE59: =+SUM(CY59:DB59) -> 52359.163 | AI59: ='QTR Raw'!C6+'QTR Raw'!C8 -> 0 | AJ59: ='QTR Raw'!D6+'QTR Raw'!D8 -> 0 | AK59: ='QTR Raw'!E6+'QTR Raw'!E8 -> 0 | AL59: ='QTR Raw'!F6+'QTR Raw'!F8 -> 0 | AM59: ='QTR Raw'!G6+'QTR Raw'!G8 -> 0 | AN59: ='QTR Raw'!H6+'QTR Raw'!H8 -> 0 | AO59: ='QTR Raw'!I6+'QTR Raw'!I8 -> 0 | AP59: ='QTR Raw'!J6+'QTR Raw'!J8 -> 0 | ... CL59: ='QTR Raw'!BF6+'QTR Raw'!BF8 -> 7443.27 | CM59: =CM31 -> 8049.9812 | CN59: =CN31 -> 7945.8689 | CO59: =CO31 -> 8369.5374 | CP59: =CP31 -> 8776.9671 | CQ59: =CQ31 -> 9546.1571 | CR59: =CR31 -> 9558.7192 | CS59: =CS31 -> 9997.1939 | CT59: =CT31 -> 10610.367 | ... DB59: =DB31 -> 13803.477 | DF59: 0 | DG59: 7141.8936
A60: Less: Exise Duty | B60: ='Annual Raw'!C7+'Annual Raw'!C8+'Annual Raw'!C9 -> 0 | C60: ='Annual Raw'!D7+'Annual Raw'!D8+'Annual Raw'!D9 -> 0 | D60: ='Annual Raw'!E7+'Annual Raw'!E8+'Annual Raw'!E9 -> 0 | E60: ='Annual Raw'!F7+'Annual Raw'!F8+'Annual Raw'!F9 -> 0 | F60: ='Annual Raw'!G7+'Annual Raw'!G8+'Annual Raw'!G9 -> 0 | G60: ='Annual Raw'!H7+'Annual Raw'!H8+'Annual Raw'!H9 -> 0 | H60: ='Annual Raw'!I7+'Annual Raw'!I8+'Annual Raw'!I9 -> 0 | I60: ='Annual Raw'!J7+'Annual Raw'!J8+'Annual Raw'!J9 -> 0 | ... AA60: ='Annual Raw'!AB7+'Annual Raw'!AB8+'Annual Raw'!AB9 -> 0 | AB60: =+SUM(CM60:CP60) -> 0 | AC60: =+SUM(CQ60:CT60) -> 0 | AD60: =+SUM(CU60:CX60) -> 0 | AE60: =+SUM(CY60:DB60) -> 0 | AI60: =+'QTR Raw'!C20+'QTR Raw'!C19+'QTR Raw'!C13+'QTR Raw'!C7 -> 0 | AJ60: =+'QTR Raw'!D20+'QTR Raw'!D19+'QTR Raw'!D13+'QTR Raw'!D7 -> 0 | AK60: =+'QTR Raw'!E20+'QTR Raw'!E19+'QTR Raw'!E13+'QTR Raw'!E7 -> 0 | AL60: =+'QTR Raw'!F20+'QTR Raw'!F19+'QTR Raw'!F13+'QTR Raw'!F7 -> 0 | AM60: =+'QTR Raw'!G20+'QTR Raw'!G19+'QTR Raw'!G13+'QTR Raw'!G7 -> 0 | AN60: =+'QTR Raw'!H20+'QTR Raw'!H19+'QTR Raw'!H13+'QTR Raw'!H7 -> 0 | AO60: =+'QTR Raw'!I20+'QTR Raw'!I19+'QTR Raw'!I13+'QTR Raw'!I7 -> 0 | AP60: =+'QTR Raw'!J20+'QTR Raw'!J19+'QTR Raw'!J13+'QTR Raw'!J7 -> 0 | ... CL60: =+'QTR Raw'!BF20+'QTR Raw'!BF19+'QTR Raw'!BF13+'QTR Raw'!BF7 -> 0 | DF60: 0
A61: Net Revenue | B61: =+B59-B60 -> 0 | C61: =+C59-C60 -> 0 | D61: =+D59-D60 -> 0 | E61: =+E59-E60 -> 0 | F61: =+F59-F60 -> 0 | G61: =+G59-G60 -> 0 | H61: =+H59-H60 -> 0 | I61: =+I59-I60 -> 0 | ... AE61: =+AE59-AE60 -> 52359.163 | AI61: =+AI59-AI60 -> 0 | AJ61: =+AJ59-AJ60 -> 0 | AK61: =+AK59-AK60 -> 0 | AL61: =+AL59-AL60 -> 0 | AM61: =+AM59-AM60 -> 0 | AN61: =+AN59-AN60 -> 0 | AO61: =+AO59-AO60 -> 0 | AP61: =+AP59-AP60 -> 0 | ... DB61: =+DB59-DB60 -> 13803.477 | DF61: 0 | DG61: 7141.8936
A62: Net Revenue YOY% | C62: =C61/B61-1 -> #DIV/0! | D62: =D61/C61-1 -> #DIV/0! | E62: =E61/D61-1 -> #DIV/0! | F62: =F61/E61-1 -> #DIV/0! | G62: =G61/F61-1 -> #DIV/0! | H62: =H61/G61-1 -> #DIV/0! | I62: =I61/H61-1 -> #DIV/0! | J62: =J61/I61-1 -> #DIV/0! | ... AE62: =AE61/AD61-1 -> 0.13073351 | AM62: =+IF(AI61<0,1-AM61/AI61,AM61/AI61-1) -> #DIV/0! | AN62: =+IF(AJ61<0,1-AN61/AJ61,AN61/AJ61-1) -> #DIV/0! | AO62: =+IF(AK61<0,1-AO61/AK61,AO61/AK61-1) -> #DIV/0! | AP62: =+IF(AL61<0,1-AP61/AL61,AP61/AL61-1) -> #DIV/0! | AQ62: =+IF(AM61<0,1-AQ61/AM61,AQ61/AM61-1) -> #DIV/0! | AR62: =+IF(AN61<0,1-AR61/AN61,AR61/AN61-1) -> #DIV/0! | AS62: =+IF(AO61<0,1-AS61/AO61,AS61/AO61-1) -> #DIV/0! | AT62: =+IF(AP61<0,1-AT61/AP61,AT61/AP61-1) -> #DIV/0! | ... CL62: =+IF(CH61<0,1-CL61/CH61,CL61/CH61-1) -> 0.16764869 | CM62: =+AVERAGE(CI62:CL62)+5% -> 0.2141062 | CN62: =+AVERAGE(CJ62:CM62)+5% -> 0.20066628 | CO62: =+AVERAGE(CK62:CN62)+5% -> 0.2341709 | CP62: =+AVERAGE(CL62:CO62)+5% -> 0.25414801 | CQ62: =+AVERAGE(CM62:CP62)-12% -> 0.10577285 | CR62: =+AVERAGE(CN62:CQ62)-12% -> 0.078689508 | CS62: =+AVERAGE(CO62:CR62)-12% -> 0.048195316 | CT62: =+AVERAGE(CP62:CS62)-12% -> 0.0017014211 | CU62: =+AVERAGE(CQ62:CT62) -> 0.058589773 | CV62: =+AVERAGE(CR62:CU62) -> 0.046794004 | CW62: =+AVERAGE(CS62:CV62) -> 0.038820129 | CX62: =+AVERAGE(CT62:CW62) -> 0.036476332 | CY62: =+AVERAGE(CU62:CX62) -> 0.045170059 | CZ62: =+AVERAGE(CV62:CY62) -> 0.041815131 | DA62: =+AVERAGE(CW62:CZ62) -> 0.040570413 | DB62: =+AVERAGE(CX62:DA62) -> 0.041007984 | DF62: #DIV/0! | DG62: 0.21077396
A63: Net Revenue QOQ% | AJ63: =+IF(AI61<0,1-AJ61/AI61,AJ61/AI61-1) -> #DIV/0! | AK63: =+IF(AJ61<0,1-AK61/AJ61,AK61/AJ61-1) -> #DIV/0! | AL63: =+IF(AK61<0,1-AL61/AK61,AL61/AK61-1) -> #DIV/0! | AM63: =+IF(AL61<0,1-AM61/AL61,AM61/AL61-1) -> #DIV/0! | AN63: =+IF(AM61<0,1-AN61/AM61,AN61/AM61-1) -> #DIV/0! | AO63: =+IF(AN61<0,1-AO61/AN61,AO61/AN61-1) -> #DIV/0! | AP63: =+IF(AO61<0,1-AP61/AO61,AP61/AO61-1) -> #DIV/0! | AQ63: =+IF(AP61<0,1-AQ61/AP61,AQ61/AP61-1) -> #DIV/0! | ... CL63: =+IF(CK61<0,1-CL61/CK61,CL61/CK61-1) -> 0.10604118 | CM63: =+CM61/CL61-1 -> 0.081511374 | CN63: =+CN61/CM61-1 -> -0.012933232 | CO63: =+CO61/CN61-1 -> 0.053319346 | CP63: =+CP61/CO61-1 -> 0.048680072 | CQ63: =+CQ61/CP61-1 -> 0.087637331 | CR63: =+CR61/CQ61-1 -> 0.00131594 | CS63: =+CS61/CR61-1 -> 0.045871697 | CT63: =+CT61/CS61-1 -> 0.061334562 | ... DB63: =+DB61/DA61-1 -> 0.04694231 | DG63: 0.061257807
A64: Increase/Decrease in Stock | B64: ='Annual Raw'!C11 -> 0 | C64: ='Annual Raw'!D11 -> 0 | D64: ='Annual Raw'!E11 -> 0 | E64: ='Annual Raw'!F11 -> 0 | F64: ='Annual Raw'!G11 -> 0 | G64: ='Annual Raw'!H11 -> 0 | H64: ='Annual Raw'!I11 -> 0 | I64: ='Annual Raw'!J11 -> 0 | ... AA64: ='Annual Raw'!AB11 -> 0 | AB64: =+SUM(CM64:CP64) -> 0 | AC64: =+SUM(CQ64:CT64) -> 0 | AD64: =+SUM(CU64:CX64) -> 0 | AE64: =+SUM(CY64:DB64) -> 0 | AI64: ='QTR Raw'!C10 -> 0 | AJ64: ='QTR Raw'!D10 -> 0 | AK64: ='QTR Raw'!E10 -> 0 | AL64: ='QTR Raw'!F10 -> 0 | AM64: ='QTR Raw'!G10 -> 0 | AN64: ='QTR Raw'!H10 -> 0 | AO64: ='QTR Raw'!I10 -> 0 | AP64: ='QTR Raw'!J10 -> 0 | ... CL64: ='QTR Raw'!BF10 -> 0 | DF64: 0
A65: Purchase of Finished Goods | B65: 0 | C65: 0 | D65: 0 | E65: 0 | F65: 0 | G65: 0 | H65: 0 | I65: 0 | J65: 0 | K65: 0 | L65: 0 | M65: 0 | N65: 0 | O65: 0 | P65: 0 | Q65: 0 | R65: 0 | S65: 0 | T65: 0 | U65: 0 | V65: 0 | W65: 0 | X65: 0 | Y65: 0 | Z65: 0 | AA65: 0 | AB65: =+SUM(CM65:CP65) -> 0 | AC65: =+SUM(CQ65:CT65) -> 0 | AD65: =+SUM(CU65:CX65) -> 0 | AE65: =+SUM(CY65:DB65) -> 0 | AI65: ='QTR Raw'!C12 -> 0 | AJ65: ='QTR Raw'!D12 -> 0 | AK65: ='QTR Raw'!E12 -> 0 | AL65: ='QTR Raw'!F12 -> 0 | AM65: ='QTR Raw'!G12 -> 0 | AN65: ='QTR Raw'!H12 -> 0 | AO65: ='QTR Raw'!I12 -> 0 | AP65: ='QTR Raw'!J12 -> 0 | ... CL65: ='QTR Raw'!BF12 -> 391.94 | DF65: 0
A66: Raw Material Consumed | B66: ='Annual Raw'!C12 -> 0 | C66: ='Annual Raw'!D12 -> 0 | D66: ='Annual Raw'!E12 -> 0 | E66: ='Annual Raw'!F12 -> 0 | F66: ='Annual Raw'!G12 -> 0 | G66: ='Annual Raw'!H12 -> 0 | H66: ='Annual Raw'!I12 -> 0 | I66: ='Annual Raw'!J12 -> 0 | ... AA66: ='Annual Raw'!AB12 -> 0 | AB66: =+SUM(CM66:CP66) -> 1447.9177 | AC66: =+SUM(CQ66:CT66) -> 1734.7422 | AD66: =+SUM(CU66:CX66) -> 2025.469 | AE66: =+SUM(CY66:DB66) -> 2291.2018 | AI66: ='QTR Raw'!C11 -> 0 | AJ66: ='QTR Raw'!D11 -> 0 | AK66: ='QTR Raw'!E11 -> 0 | AL66: ='QTR Raw'!F11 -> 0 | AM66: ='QTR Raw'!G11 -> 0 | AN66: ='QTR Raw'!H11 -> 0 | AO66: ='QTR Raw'!I11 -> 0 | AP66: ='QTR Raw'!J11 -> 0 | ... CL66: ='QTR Raw'!BF11 -> 0 | CM66: =+CM61-CM67 -> 367.04981 | CN66: =+CN61-CN67 -> 320.3351 | CO66: =+CO61-CO67 -> 361.66369 | CP66: =+CP61-CP67 -> 398.86905 | CQ66: =+CQ61-CQ67 -> 416.61318 | CR66: =+CR61-CR67 -> 412.49108 | CS66: =+CS61-CS67 -> 438.50753 | CT66: =+CT61-CT67 -> 467.13044 | ... DB66: =+DB61-DB67 -> 604.12924 | DF66: 0 | DG66: -147.33628
A67: Gross Profit | B67: =B61-B64-B66-B65 -> 0 | C67: =C61-C64-C66-C65 -> 0 | D67: =D61-D64-D66-D65 -> 0 | E67: =E61-E64-E66-E65 -> 0 | F67: =F61-F64-F66-F65 -> 0 | G67: =G61-G64-G66-G65 -> 0 | H67: =H61-H64-H66-H65 -> 0 | I67: =I61-I64-I66-I65 -> 0 | ... AE67: =AE61-AE64-AE66-AE65 -> 50067.961 | AI67: =AI61-AI64-AI66-AI65 -> 0 | AJ67: =AJ61-AJ64-AJ66-AJ65 -> 0 | AK67: =AK61-AK64-AK66-AK65 -> 0 | AL67: =AL61-AL64-AL66-AL65 -> 0 | AM67: =AM61-AM64-AM66-AM65 -> 0 | AN67: =AN61-AN64-AN66-AN65 -> 0 | AO67: =AO61-AO64-AO66-AO65 -> 0 | AP67: =AP61-AP64-AP66-AP65 -> 0 | ... CL67: =CL61-CL64-CL66-CL65 -> 7051.33 | CM67: =+CM68*CM61 -> 7682.9314 | CN67: =+CN68*CN61 -> 7625.5338 | CO67: =+CO68*CO61 -> 8007.8737 | CP67: =+CP68*CP61 -> 8378.0981 | CQ67: =+CQ68*CQ61 -> 9129.5439 | CR67: =+CR68*CR61 -> 9146.2282 | CS67: =+CS68*CS61 -> 9558.6864 | CT67: =+CT68*CT61 -> 10143.237 | ... DB67: =+DB68*DB61 -> 13199.347 | DF67: 0 | DG67: 7289.2299
A68: GP% | B68: =B67/B61 -> #DIV/0! | C68: =C67/C61 -> #DIV/0! | D68: =D67/D61 -> #DIV/0! | E68: =E67/E61 -> #DIV/0! | F68: =F67/F61 -> #DIV/0! | G68: =G67/G61 -> #DIV/0! | H68: =H67/H61 -> #DIV/0! | I68: =I67/I61 -> #DIV/0! | ... AE68: =AE67/AE61 -> 0.95624067 | AI68: =AI67/AI61 -> #DIV/0! | AJ68: =AJ67/AJ61 -> #DIV/0! | AK68: =AK67/AK61 -> #DIV/0! | AL68: =AL67/AL61 -> #DIV/0! | AM68: =AM67/AM61 -> #DIV/0! | AN68: =AN67/AN61 -> #DIV/0! | AO68: =AO67/AO61 -> #DIV/0! | AP68: =AP67/AP61 -> #DIV/0! | ... CL68: =CL67/CL61 -> 0.94734304 | CM68: =AVERAGE(CI68:CL68)*0.99 -> 0.95440364 | CN68: =AVERAGE(CJ68:CM68) -> 0.95968533 | CO68: =AVERAGE(CK68:CN68) -> 0.95678809 | CP68: =AVERAGE(CL68:CO68) -> 0.95455502 | CQ68: =AVERAGE(CM68:CP68) -> 0.95635802 | CR68: =AVERAGE(CN68:CQ68) -> 0.95684662 | CS68: =AVERAGE(CO68:CR68) -> 0.95613694 | CT68: =AVERAGE(CP68:CS68) -> 0.95597415 | CU68: =AVERAGE(CQ68:CT68) -> 0.95632893 | ... DB68: =AVERAGE(CX68:DA68) -> 0.95623354 | DF68: #DIV/0! | DG68: 1.0206299
A69: GP YOY% | C69: =+IF(B67<0,1-C67/B67,C67/B67-1) -> #DIV/0! | D69: =+IF(C67<0,1-D67/C67,D67/C67-1) -> #DIV/0! | E69: =+IF(D67<0,1-E67/D67,E67/D67-1) -> #DIV/0! | F69: =+IF(E67<0,1-F67/E67,F67/E67-1) -> #DIV/0! | G69: =+IF(F67<0,1-G67/F67,G67/F67-1) -> #DIV/0! | H69: =+IF(G67<0,1-H67/G67,H67/G67-1) -> #DIV/0! | I69: =+IF(H67<0,1-I67/H67,I67/H67-1) -> #DIV/0! | J69: =+IF(I67<0,1-J67/I67,J67/I67-1) -> #DIV/0! | ... AE69: =+IF(AD67<0,1-AE67/AD67,AE67/AD67-1) -> 0.13071237 | AM69: =+IF(AI67<0,1-AM67/AI67,AM67/AI67-1) -> #DIV/0! | AN69: =+IF(AJ67<0,1-AN67/AJ67,AN67/AJ67-1) -> #DIV/0! | AO69: =+IF(AK67<0,1-AO67/AK67,AO67/AK67-1) -> #DIV/0! | AP69: =+IF(AL67<0,1-AP67/AL67,AP67/AL67-1) -> #DIV/0! | AQ69: =+IF(AM67<0,1-AQ67/AM67,AQ67/AM67-1) -> #DIV/0! | AR69: =+IF(AN67<0,1-AR67/AN67,AR67/AN67-1) -> #DIV/0! | AS69: =+IF(AO67<0,1-AS67/AO67,AS67/AO67-1) -> #DIV/0! | AT69: =+IF(AP67<0,1-AT67/AP67,AT67/AP67-1) -> #DIV/0! | ... CL69: =+IF(CH67<0,1-CL67/CH67,CL67/CH67-1) -> 0.17352397 | CM69: =+CM67/CI67-1 -> 0.15929578 | CN69: =+CN67/CJ67-1 -> 0.19030679 | CO69: =+CO67/CK67-1 -> 0.23217772 | CP69: =+CP67/CL67-1 -> 0.18815855 | CQ69: =+CQ67/CM67-1 -> 0.18828914 | CR69: =+CR67/CN67-1 -> 0.19942137 | CS69: =+CS67/CO67-1 -> 0.19366098 | CT69: =+CT67/CP67-1 -> 0.21068492 | ... DB69: =+DB67/CX67-1 -> 0.12998956 | DF69: #DIV/0! | DG69: 0.21311667
A70: GP QOQ% | AJ70: =+IF(AI67<0,1-AJ67/AI67,AJ67/AI67-1) -> #DIV/0! | AK70: =+IF(AJ67<0,1-AK67/AJ67,AK67/AJ67-1) -> #DIV/0! | AL70: =+IF(AK67<0,1-AL67/AK67,AL67/AK67-1) -> #DIV/0! | AM70: =+IF(AL67<0,1-AM67/AL67,AM67/AL67-1) -> #DIV/0! | AN70: =+IF(AM67<0,1-AN67/AM67,AN67/AM67-1) -> #DIV/0! | AO70: =+IF(AN67<0,1-AO67/AN67,AO67/AN67-1) -> #DIV/0! | AP70: =+IF(AO67<0,1-AP67/AO67,AP67/AO67-1) -> #DIV/0! | AQ70: =+IF(AP67<0,1-AQ67/AP67,AQ67/AP67-1) -> #DIV/0! | ... CL70: =+IF(CK67<0,1-CL67/CK67,CL67/CK67-1) -> 0.084993599 | CM70: =+CM67/CL67-1 -> 0.089571946 | CN70: =+CN67/CM67-1 -> -0.0074707892 | CO70: =+CO67/CN67-1 -> 0.050139433 | CP70: =+CP67/CO67-1 -> 0.046232537 | CQ70: =+CQ67/CP67-1 -> 0.089691698 | CR70: =+CR67/CQ67-1 -> 0.0018275032 | CS70: =+CS67/CR67-1 -> 0.045095991 | CT70: =+CT67/CS67-1 -> 0.061153863 | ... DB70: =+DB67/DA67-1 -> 0.046951753 | DG70: 0.12159944
A71: Employee Cost | B71: ='Annual Raw'!C14 -> 0 | C71: ='Annual Raw'!D14 -> 0 | D71: ='Annual Raw'!E14 -> 0 | E71: ='Annual Raw'!F14 -> 0 | F71: ='Annual Raw'!G14 -> 0 | G71: ='Annual Raw'!H14 -> 0 | H71: ='Annual Raw'!I14 -> 0 | I71: ='Annual Raw'!J14 -> 0 | ... AA71: ='Annual Raw'!AB14 -> 1092.64 | AB71: =+SUM(CM71:CP71) -> 1169.1248 | AC71: =+SUM(CQ71:CT71) -> 1250.9635 | AD71: =+SUM(CU71:CX71) -> 1338.531 | AE71: =+SUM(CY71:DB71) -> 1432.2282 | AI71: ='QTR Raw'!C16 -> 0 | AJ71: ='QTR Raw'!D16 -> 0 | AK71: ='QTR Raw'!E16 -> 0 | AL71: ='QTR Raw'!F16 -> 0 | AM71: ='QTR Raw'!G16 -> 0 | AN71: ='QTR Raw'!H16 -> 0 | AO71: ='QTR Raw'!I16 -> 0 | AP71: ='QTR Raw'!J16 -> 0 | ... CL71: ='QTR Raw'!BF16 -> 307.64 | CM71: =CI71*107% -> 247.4161 | CN71: =CJ71*107% -> 252.7982 | CO71: =CK71*107% -> 339.7357 | CP71: =CL71*107% -> 329.1748 | CQ71: =CM71*107% -> 264.73523 | CR71: =CN71*107% -> 270.49407 | CS71: =CO71*107% -> 363.5172 | CT71: =CP71*107% -> 352.21704 | ... DB71: =CX71*107% -> 403.25328 | DF71: 0 | DG71: 250.2944
A72: General and Administration Expenses | B72: ='Annual Raw'!C17 -> 0 | C72: ='Annual Raw'!D17 -> 0 | D72: ='Annual Raw'!E17 -> 0 | E72: ='Annual Raw'!F17 -> 0 | F72: ='Annual Raw'!G17 -> 0 | G72: ='Annual Raw'!H17 -> 0 | H72: ='Annual Raw'!I17 -> 0 | I72: ='Annual Raw'!J17 -> 0 | ... O72: ='Annual Raw'!P17 -> 0.0005618 | P72: =('Annual Raw'!Q17)-6.34 -> 3.14 | Q72: =('Annual Raw'!R17)-13.01 -> 20.31 | R72: =('Annual Raw'!S17)-23.04 -> 15.84 | S72: =('Annual Raw'!T17)-41.62 -> 17.33 | T72: =('Annual Raw'!U17)-141.21 -> 104.2 | U72: =('Annual Raw'!V17)-164.92 -> 137.72 | V72: =('Annual Raw'!W17)-152.62 -> 138.73 | W72: =('Annual Raw'!X17)-200.36 -> 124.58 | X72: =('Annual Raw'!Y17)-232.37 -> 149.13 | Y72: =('Annual Raw'!Z17)-295.1 -> 146.15 | Z72: =('Annual Raw'!AA17)-292.37 -> 173.85 | AA72: =('Annual Raw'!AB17)-292.37 -> 278.74 | AB72: =+SUM(CM72:CP72) -> 0 | AC72: =+SUM(CQ72:CT72) -> 0 | AD72: =+SUM(CU72:CX72) -> 0 | AE72: =+SUM(CY72:DB72) -> 0 | AI72: ='QTR Raw'!C17 -> 0 | AJ72: ='QTR Raw'!D17 -> 0 | AK72: ='QTR Raw'!E17 -> 0 | AL72: ='QTR Raw'!F17 -> 0 | AM72: ='QTR Raw'!G17 -> 0 | AN72: ='QTR Raw'!H17 -> 0 | AO72: ='QTR Raw'!I17 -> 0 | AP72: ='QTR Raw'!J17 -> 0 | ... CL72: ='QTR Raw'!BF17 -> 0 | DF72: -292.37
A73: Professional fees (G&A) | P73: 6.34 | Q73: 13.01 | R73: 23.04 | S73: 41.62 | T73: 141.21 | U73: 164.92 | V73: 152.62 | W73: 200.36 | X73: 232.37 | Y73: 295.1 | Z73: 292.37 | AA73: 292.37 | DF73: 292.37
A74: Miscellaneous Expenses | B74: ='Annual Raw'!C19-'Annual Raw'!C20 -> 0 | C74: ='Annual Raw'!D19-'Annual Raw'!D20 -> 0 | D74: ='Annual Raw'!E19-'Annual Raw'!E20 -> 0 | E74: ='Annual Raw'!F19-'Annual Raw'!F20 -> 0 | F74: ='Annual Raw'!G19-'Annual Raw'!G20 -> 0 | G74: ='Annual Raw'!H19-'Annual Raw'!H20 -> 0 | H74: ='Annual Raw'!I19-'Annual Raw'!I20 -> 0 | I74: ='Annual Raw'!J19-'Annual Raw'!J20 -> 0 | ... AA74: ='Annual Raw'!AB19-'Annual Raw'!AB20 -> 1277.34 | AB74: =+SUM(CM74:CP74) -> 0 | AC74: =+SUM(CQ74:CT74) -> 0 | AD74: =+SUM(CU74:CX74) -> 0 | AE74: =+SUM(CY74:DB74) -> 0 | AI74: =+'QTR Raw'!C21 -> 0 | AJ74: =+'QTR Raw'!D21 -> 0 | AK74: =+'QTR Raw'!E21 -> 0 | AL74: =+'QTR Raw'!F21 -> 0 | AM74: =+'QTR Raw'!G21 -> 0 | AN74: =+'QTR Raw'!H21 -> 0 | AO74: =+'QTR Raw'!I21 -> 0 | AP74: =+'QTR Raw'!J21 -> 0 | ... CL74: =+'QTR Raw'!BF21 -> -82.32 | DF74: 0
A75: Other Manufacturing Expenses | B75: ='Annual Raw'!C15+'Annual Raw'!C16 -> 0 | C75: ='Annual Raw'!D15+'Annual Raw'!D16 -> 0 | D75: ='Annual Raw'!E15+'Annual Raw'!E16 -> 0 | E75: ='Annual Raw'!F15+'Annual Raw'!F16 -> 0 | F75: ='Annual Raw'!G15+'Annual Raw'!G16 -> 0 | G75: ='Annual Raw'!H15+'Annual Raw'!H16 -> 0 | H75: ='Annual Raw'!I15+'Annual Raw'!I16 -> 0 | I75: ='Annual Raw'!J15+'Annual Raw'!J16 -> 0 | ... O75: ='Annual Raw'!P15+'Annual Raw'!P16 -> 0 | P75: =('Annual Raw'!Q15+'Annual Raw'!Q16)-0.26 -> 1.52 | Q75: =('Annual Raw'!R15+'Annual Raw'!R16)-2.54 -> 39.53 | R75: =('Annual Raw'!S15+'Annual Raw'!S16)-19.26 -> 7.8 | S75: =('Annual Raw'!T15+'Annual Raw'!T16)-72.12 -> 106.01 | T75: =('Annual Raw'!U15+'Annual Raw'!U16)-215.47 -> 55.23 | U75: =('Annual Raw'!V15+'Annual Raw'!V16)-370.69 -> 65.7 | V75: =('Annual Raw'!W15+'Annual Raw'!W16)-459.37 -> 58.18 | W75: =('Annual Raw'!X15+'Annual Raw'!X16)-495.73 -> 60.99 | X75: =('Annual Raw'!Y15+'Annual Raw'!Y16)-531.88 -> 59.29 | Y75: =('Annual Raw'!Z15+'Annual Raw'!Z16)-675.76 -> 1174.64 | Z75: =('Annual Raw'!AA15+'Annual Raw'!AA16)-558.91 -> 4995.94 | AA75: =('Annual Raw'!AB15+'Annual Raw'!AB16)-558.91 -> 7801.16 | AB75: =+SUM(CM75:CP75) -> 19970.683 | AC75: =+SUM(CQ75:CT75) -> 23864.252 | AD75: =+SUM(CU75:CX75) -> 28000.176 | AE75: =+SUM(CY75:DB75) -> 32024.331 | AI75: ='QTR Raw'!C14 -> 0 | AJ75: ='QTR Raw'!D14 -> 0 | AK75: ='QTR Raw'!E14 -> 0 | AL75: ='QTR Raw'!F14 -> 0 | AM75: ='QTR Raw'!G14 -> 0 | AN75: ='QTR Raw'!H14 -> 0 | AO75: ='QTR Raw'!I14 -> 0 | AP75: ='QTR Raw'!J14 -> 0 | ... CL75: ='QTR Raw'!BF14 -> 3082.92 | CM75: =+CM67-CM71-CM47 -> 4949.4045 | CN75: =+CN67-CN71-CN47 -> 4801.0205 | CO75: =+CO67-CO71-CO47 -> 4982.8554 | CP75: =+CP67-CP71-CP47 -> 5237.4026 | CQ75: =+CQ67-CQ71-CQ47 -> 5794.9589 | CR75: =+CR67-CR71-CR47 -> 5761.7954 | CS75: =+CS67-CS71-CS47 -> 5960.4938 | CT75: =+CT67-CT71-CT47 -> 6347.0034 | ... DB75: =+DB67-DB71-DB47 -> 8431.6345 | DF75: -558.91 | DG75: 4522.1363
A76: Repairs and Maintenance | P76: 0.26 | Q76: 2.54 | R76: 19.26 | S76: 72.12 | T76: 215.47 | U76: 370.69 | V76: 459.37 | W76: 495.73 | X76: 531.88 | Y76: 675.76 | Z76: 558.91 | AA76: 558.91 | DF76: 558.91
A77: Power & Fuel Cost | B77: ='Annual Raw'!C13 -> 0 | C77: ='Annual Raw'!D13 -> 0 | D77: ='Annual Raw'!E13 -> 0 | E77: ='Annual Raw'!F13 -> 0 | F77: ='Annual Raw'!G13 -> 0 | G77: ='Annual Raw'!H13 -> 0 | H77: ='Annual Raw'!I13 -> 0 | I77: ='Annual Raw'!J13 -> 0 | ... AA77: ='Annual Raw'!AB13 -> 8248.48 | AB77: =+SUM(CM77:CP77) -> 0 | AC77: =+SUM(CQ77:CT77) -> 0 | AD77: =+SUM(CU77:CX77) -> 0 | AE77: =+SUM(CY77:DB77) -> 0 | AI77: ='QTR Raw'!C15 -> 0 | AJ77: ='QTR Raw'!D15 -> 0 | AK77: ='QTR Raw'!E15 -> 0 | AL77: ='QTR Raw'!F15 -> 0 | AM77: ='QTR Raw'!G15 -> 0 | AN77: ='QTR Raw'!H15 -> 0 | AO77: ='QTR Raw'!I15 -> 0 | AP77: ='QTR Raw'!J15 -> 0 | ... CL77: ='QTR Raw'!BF15 -> 1515.76 | DF77: 0
A78: Selling and Distribution Expenses | B78: ='Annual Raw'!C18 -> 0 | C78: ='Annual Raw'!D18 -> 0 | D78: ='Annual Raw'!E18 -> 0 | E78: ='Annual Raw'!F18 -> 0 | F78: ='Annual Raw'!G18 -> 0 | G78: ='Annual Raw'!H18 -> 0 | H78: ='Annual Raw'!I18 -> 0 | I78: ='Annual Raw'!J18 -> 0 | ... AA78: ='Annual Raw'!AB18 -> 49.55 | AB78: =+SUM(CM78:CP78) -> 0 | AC78: =+SUM(CQ78:CT78) -> 0 | AD78: =+SUM(CU78:CX78) -> 0 | AE78: =+SUM(CY78:DB78) -> 0 | AI78: ='QTR Raw'!C18 -> 0 | AJ78: ='QTR Raw'!D18 -> 0 | AK78: ='QTR Raw'!E18 -> 0 | AL78: ='QTR Raw'!F18 -> 0 | AM78: ='QTR Raw'!G18 -> 0 | AN78: ='QTR Raw'!H18 -> 0 | AO78: ='QTR Raw'!I18 -> 0 | AP78: ='QTR Raw'!J18 -> 0 | ... CL78: ='QTR Raw'!BF18 -> 0 | DF78: 0
A79: Total Cost | B79: =+SUM(B71:B78) -> 0 | C79: =+SUM(C71:C78) -> 0 | D79: =+SUM(D71:D78) -> 0 | E79: =+SUM(E71:E78) -> 0 | F79: =+SUM(F71:F78) -> 0 | G79: =+SUM(G71:G78) -> 0 | H79: =+SUM(H71:H78) -> 0 | I79: =+SUM(I71:I78) -> 0 | ... AE79: =+SUM(AE71:AE78) -> 33456.559 | AI79: =+SUM(AI71:AI78) -> 0 | AJ79: =+SUM(AJ71:AJ78) -> 0 | AK79: =+SUM(AK71:AK78) -> 0 | AL79: =+SUM(AL71:AL78) -> 0 | AM79: =+SUM(AM71:AM78) -> 0 | AN79: =+SUM(AN71:AN78) -> 0 | AO79: =+SUM(AO71:AO78) -> 0 | AP79: =+SUM(AP71:AP78) -> 0 | ... DB79: =+SUM(DB71:DB78) -> 8834.8878 | DF79: 0 | DG79: 4772.4307
A80: Cost % | B80: =B79/B61 -> #DIV/0! | C80: =C79/C61 -> #DIV/0! | D80: =D79/D61 -> #DIV/0! | E80: =E79/E61 -> #DIV/0! | F80: =F79/F61 -> #DIV/0! | G80: =G79/G61 -> #DIV/0! | H80: =H79/H61 -> #DIV/0! | I80: =I79/I61 -> #DIV/0! | ... AE80: =AE79/AE61 -> 0.63898193 | AI80: =AI79/AI61 -> #DIV/0! | AJ80: =AJ79/AJ61 -> #DIV/0! | AK80: =AK79/AK61 -> #DIV/0! | AL80: =AL79/AL61 -> #DIV/0! | AM80: =AM79/AM61 -> #DIV/0! | AN80: =AN79/AN61 -> #DIV/0! | AO80: =AO79/AO61 -> #DIV/0! | AP80: =AP79/AP61 -> #DIV/0! | ... DB80: =DB79/DB61 -> 0.64004802 | DF80: #DIV/0! | DG80: 0.66823043
A81: EBITDA | B81: =B67-B79 -> 0 | C81: =C67-C79 -> 0 | D81: =D67-D79 -> 0 | E81: =E67-E79 -> 0 | F81: =F67-F79 -> 0 | G81: =G67-G79 -> 0 | H81: =H67-H79 -> 0 | I81: =I67-I79 -> 0 | ... AE81: =AE67-AE79 -> 16611.402 | AI81: =AI67-AI79 -> 0 | AJ81: =AJ67-AJ79 -> 0 | AK81: =AK67-AK79 -> 0 | AL81: =AL67-AL79 -> 0 | AM81: =AM67-AM79 -> 0 | AN81: =AN67-AN79 -> 0 | AO81: =AO67-AO79 -> 0 | AP81: =AP67-AP79 -> 0 | ... DB81: =DB67-DB79 -> 4364.4595 | DF81: 0 | DG81: 2516.7992
A82: EBITDA Margins | B82: =B81/B61 -> #DIV/0! | C82: =C81/C61 -> #DIV/0! | D82: =D81/D61 -> #DIV/0! | E82: =E81/E61 -> #DIV/0! | F82: =F81/F61 -> #DIV/0! | G82: =G81/G61 -> #DIV/0! | H82: =H81/H61 -> #DIV/0! | I82: =I81/I61 -> #DIV/0! | ... AE82: =AE81/AE61 -> 0.31725874 | AI82: =AI81/AI61 -> #DIV/0! | AJ82: =AJ81/AJ61 -> #DIV/0! | AK82: =AK81/AK61 -> #DIV/0! | AL82: =AL81/AL61 -> #DIV/0! | AM82: =AM81/AM61 -> #DIV/0! | AN82: =AN81/AN61 -> #DIV/0! | AO82: =AO81/AO61 -> #DIV/0! | AP82: =AP81/AP61 -> #DIV/0! | ... DB82: =DB81/DB61 -> 0.31618553 | DF82: #DIV/0! | DG82: 0.35239943
A83: EBITDA YOY% | C83: =+IF(B81<0,1-C81/B81,C81/B81-1) -> #DIV/0! | D83: =+IF(C81<0,1-D81/C81,D81/C81-1) -> #DIV/0! | E83: =+IF(D81<0,1-E81/D81,E81/D81-1) -> #DIV/0! | F83: =+IF(E81<0,1-F81/E81,F81/E81-1) -> #DIV/0! | G83: =+IF(F81<0,1-G81/F81,G81/F81-1) -> #DIV/0! | H83: =+IF(G81<0,1-H81/G81,H81/G81-1) -> #DIV/0! | I83: =+IF(H81<0,1-I81/H81,I81/H81-1) -> #DIV/0! | J83: =+IF(I81<0,1-J81/I81,J81/I81-1) -> #DIV/0! | ... AE83: =+IF(AD81<0,1-AE81/AD81,AE81/AD81-1) -> 0.11177693 | AM83: =+IF(AI81<0,1-AM81/AI81,AM81/AI81-1) -> #DIV/0! | AN83: =+IF(AJ81<0,1-AN81/AJ81,AN81/AJ81-1) -> #DIV/0! | AO83: =+IF(AK81<0,1-AO81/AK81,AO81/AK81-1) -> #DIV/0! | AP83: =+IF(AL81<0,1-AP81/AL81,AP81/AL81-1) -> #DIV/0! | AQ83: =+IF(AM81<0,1-AQ81/AM81,AQ81/AM81-1) -> #DIV/0! | AR83: =+IF(AN81<0,1-AR81/AN81,AR81/AN81-1) -> #DIV/0! | AS83: =+IF(AO81<0,1-AS81/AO81,AS81/AO81-1) -> #DIV/0! | AT83: =+IF(AP81<0,1-AT81/AP81,AT81/AP81-1) -> #DIV/0! | ... DB83: =+IF(CX81<0,1-DB81/CX81,DB81/CX81-1) -> 0.10084059 | DF83: #DIV/0! | DG83: 0.2337493
A84: EBITDA QOQ% | AJ84: =+IF(AI81<0,1-AJ81/AI81,AJ81/AI81-1) -> #DIV/0! | AK84: =+IF(AJ81<0,1-AK81/AJ81,AK81/AJ81-1) -> #DIV/0! | AL84: =+IF(AK81<0,1-AL81/AK81,AL81/AK81-1) -> #DIV/0! | AM84: =+IF(AL81<0,1-AM81/AL81,AM81/AL81-1) -> #DIV/0! | AN84: =+IF(AM81<0,1-AN81/AM81,AN81/AM81-1) -> #DIV/0! | AO84: =+IF(AN81<0,1-AO81/AN81,AO81/AN81-1) -> #DIV/0! | AP84: =+IF(AO81<0,1-AP81/AO81,AP81/AO81-1) -> #DIV/0! | AQ84: =+IF(AP81<0,1-AQ81/AP81,AQ81/AP81-1) -> #DIV/0! | ... CI84: =+IF(CH81<0,1-CI81/CH81,CI81/CH81-1) -> -0.11238946 | CJ84: =+IF(CI81>1,CJ81/CI81-1,1-CJ81/CI81) -> 0.079930855 | CK84: =+IF(CJ81>1,CK81/CJ81-1,1-CK81/CJ81) -> 0.020445735 | CL84: =+IF(CK81>1,CL81/CK81-1,1-CL81/CK81) -> 0.11623233 | CM84: =+IF(CL81>1,CM81/CL81-1,1-CM81/CL81) -> 0.1161843 | CN84: =+IF(CM81>1,CN81/CM81-1,1-CN81/CM81) -> 0.034433008 | CO84: =+IF(CN81>1,CO81/CN81-1,1-CO81/CN81) -> 0.044160244 | CP84: =+IF(CO81>1,CP81/CO81-1,1-CP81/CO81) -> 0.047011064 | CQ84: =+IF(CP81>1,CQ81/CP81-1,1-CQ81/CP81) -> 0.091882373 | ... DB84: =+IF(DA81>1,DB81/DA81-1,1-DB81/DA81) -> 0.046073213 | DG84: 0.26130061
A85: Depreciation | B85: ='Annual Raw'!C27 -> 0 | C85: ='Annual Raw'!D27 -> 0 | D85: ='Annual Raw'!E27 -> 0 | E85: ='Annual Raw'!F27 -> 0 | F85: ='Annual Raw'!G27 -> 0 | G85: ='Annual Raw'!H27 -> 0 | H85: ='Annual Raw'!I27 -> 0 | I85: ='Annual Raw'!J27 -> 0 | ... AA85: ='Annual Raw'!AB27 -> 1978.23 | AB85: =+SUM(CM85:CP85) -> 2799.3155 | AC85: =+SUM(CQ85:CT85) -> 3819.7127 | AD85: =+SUM(CU85:CX85) -> 4680.9598 | AE85: =+SUM(CY85:DB85) -> 5270.8473 | AI85: ='QTR Raw'!C28 -> 0 | AJ85: ='QTR Raw'!D28 -> 0 | AK85: ='QTR Raw'!E28 -> 0 | AL85: ='QTR Raw'!F28 -> 0 | AM85: ='QTR Raw'!G28 -> 0 | AN85: ='QTR Raw'!H28 -> 0 | AO85: ='QTR Raw'!I28 -> 0 | AP85: ='QTR Raw'!J28 -> 0 | ... CL85: ='QTR Raw'!BF28 -> 507.81 | CM85: =CM86*CL187 -> 603.06105 | CN85: =CN86*CM187 -> 668.14774 | CO85: =CO86*CN187 -> 732.36935 | CP85: =CP86*CO187 -> 795.73737 | CQ85: =CQ86*CP187 -> 858.26314 | CR85: =CR86*CQ187 -> 923.28069 | CS85: =CS86*CR187 -> 987.43408 | CT85: =CT86*CS187 -> 1050.7348 | ... DB85: =DB86*DA187 -> 1371.3045 | DF85: 0 | DG85: 955.15475
A86: Depreciation % of Net Block | B86: =+B85/B187 -> #DIV/0! | C86: =+C85/C187 -> #DIV/0! | D86: =+D85/D187 -> #DIV/0! | E86: =+E85/E187 -> #DIV/0! | F86: =+F85/F187 -> #DIV/0! | G86: =+G85/G187 -> #DIV/0! | H86: =+H85/H187 -> #DIV/0! | I86: =+I85/I187 -> #DIV/0! | ... AE86: =+AE85/AE187 -> 0.049818136 | AI86: =+AI85/AH187 -> #DIV/0! | AJ86: =+AJ85/AI187 -> #DIV/0! | AK86: =+AK85/AJ187 -> #DIV/0! | AL86: =+AL85/AK187 -> #DIV/0! | AM86: =+AM85/AL187 -> #DIV/0! | AN86: =+AN85/AM187 -> #DIV/0! | AO86: =+AO85/AN187 -> #DIV/0! | AP86: =+AP85/AO187 -> #DIV/0! | ... CL86: =+CL85/CK187 -> 0.013291302 | CM86: =+CL86 -> 0.013291302 | CN86: =+CM86 -> 0.013291302 | CO86: =+CN86 -> 0.013291302 | CP86: =+CO86 -> 0.013291302 | CQ86: =+CP86 -> 0.013291302 | CR86: =+CQ86 -> 0.013291302 | CS86: =+CR86 -> 0.013291302 | CT86: =+CS86 -> 0.013291302 | ... DB86: =+DA86 -> 0.013291302 | DF86: #DIV/0! | DG86: 0.025
A87: EBIT | B87: =B81-B85 -> 0 | C87: =C81-C85 -> 0 | D87: =D81-D85 -> 0 | E87: =E81-E85 -> 0 | F87: =F81-F85 -> 0 | G87: =G81-G85 -> 0 | H87: =H81-H85 -> 0 | I87: =I81-I85 -> 0 | ... AE87: =AE81-AE85 -> 11340.555 | AI87: =AI81-AI85 -> 0 | AJ87: =AJ81-AJ85 -> 0 | AK87: =AK81-AK85 -> 0 | AL87: =AL81-AL85 -> 0 | AM87: =AM81-AM85 -> 0 | AN87: =AN81-AN85 -> 0 | AO87: =AO81-AO85 -> 0 | AP87: =AP81-AP85 -> 0 | ... DB87: =DB81-DB85 -> 2993.155 | DF87: 0 | DG87: 1561.6445
A88: Other Income | B88: ='Annual Raw'!C23 -> 0 | C88: ='Annual Raw'!D23 -> 0 | D88: ='Annual Raw'!E23 -> 0 | E88: ='Annual Raw'!F23 -> 0 | F88: ='Annual Raw'!G23 -> 0 | G88: ='Annual Raw'!H23 -> 0 | H88: ='Annual Raw'!I23 -> 0 | I88: ='Annual Raw'!J23 -> 0 | ... AA88: ='Annual Raw'!AB23 -> 737.13 | AB88: =+SUM(CM88:CP88) -> 0 | AC88: =+SUM(CQ88:CT88) -> 0 | AD88: =+SUM(CU88:CX88) -> 0 | AE88: =+SUM(CY88:DB88) -> 0 | AI88: ='QTR Raw'!C23 -> 0 | AJ88: ='QTR Raw'!D23 -> 0 | AK88: ='QTR Raw'!E23 -> 0 | AL88: ='QTR Raw'!F23 -> 0 | AM88: ='QTR Raw'!G23 -> 0 | AN88: ='QTR Raw'!H23 -> 0 | AO88: ='QTR Raw'!I23 -> 0 | AP88: ='QTR Raw'!J23 -> 0 | ... CL88: ='QTR Raw'!BF23 -> 144.81 | DF88: 0
A89: Interest | B89: ='Annual Raw'!C25 -> 0 | C89: ='Annual Raw'!D25 -> 0 | D89: ='Annual Raw'!E25 -> 0 | E89: ='Annual Raw'!F25 -> 0 | F89: ='Annual Raw'!G25 -> 0 | G89: ='Annual Raw'!H25 -> 0 | H89: ='Annual Raw'!I25 -> 0 | I89: ='Annual Raw'!J25 -> 0 | ... AA89: ='Annual Raw'!AB25 -> 3632.9 | AB89: =+SUM(CM89:CP89) -> 2566.1315 | AC89: =+SUM(CQ89:CT89) -> 3409.1275 | AD89: =+SUM(CU89:CX89) -> 2949.1293 | AE89: =+SUM(CY89:DB89) -> 3287.9041 | AI89: ='QTR Raw'!C25 -> 0 | AJ89: ='QTR Raw'!D25 -> 0 | AK89: ='QTR Raw'!E25 -> 0 | AL89: ='QTR Raw'!F25 -> 0 | AM89: ='QTR Raw'!G25 -> 0 | AN89: ='QTR Raw'!H25 -> 0 | AO89: ='QTR Raw'!I25 -> 0 | AP89: ='QTR Raw'!J25 -> 0 | ... CL89: ='QTR Raw'!BF25 -> 954.26 | CM89: =CM90*CL235 -> 469.86269 | CN89: =CN90*CM235 -> 616.24973 | CO89: =CO90*CN235 -> 689.81242 | CP89: =CP90*CO235 -> 790.20662 | CQ89: =CQ90*CP235 -> 787.40838 | CR89: =CR90*CQ235 -> 846.54428 | CS89: =CS90*CR235 -> 867.95682 | CT89: =CT90*CS235 -> 907.21799 | ... DB89: =DB90*DA235 -> 851.33697 | DF89: 0 | DG89: 779.73557
A90: Interest % of Debt | B90: =+B89/B181 -> #DIV/0! | C90: =+C89/C181 -> #DIV/0! | D90: =+D89/D181 -> #DIV/0! | E90: =+E89/E181 -> #DIV/0! | F90: =+F89/F181 -> #DIV/0! | G90: =+G89/G181 -> #DIV/0! | H90: =+H89/H181 -> #DIV/0! | I90: =+I89/I181 -> #DIV/0! | ... AE90: =+AE89/AE181 -> 0.067239434 | AI90: =(AI89-AI88)/AH235 -> #DIV/0! | AJ90: =(AJ89-AJ88)/AI235 -> #DIV/0! | AK90: =(AK89-AK88)/AJ235 -> #DIV/0! | AL90: =(AL89-AL88)/AK235 -> #DIV/0! | AM90: =(AM89-AM88)/AL235 -> #DIV/0! | AN90: =(AN89-AN88)/AM235 -> #DIV/0! | AO90: =(AO89-AO88)/AN235 -> #DIV/0! | AP90: =(AP89-AP88)/AO235 -> #DIV/0! | ... CL90: =(CL89-CL88)/CK235 -> 0.020762167 | CM90: 0.011 | CN90: =+CM90 -> 0.011 | CO90: =+CN90 -> 0.011 | CP90: =+CO90 -> 0.011 | CQ90: 0.01 | CR90: =+CQ90 -> 0.01 | CS90: =+CR90 -> 0.01 | CT90: =+CS90 -> 0.01 | CU90: 0.0075 | CV90: =+CU90 -> 0.0075 | CW90: =+CV90 -> 0.0075 | CX90: =+CW90 -> 0.0075 | CY90: =+CX90 -> 0.0075 | CZ90: =+CY90 -> 0.0075 | DA90: =+CZ90 -> 0.0075 | DB90: =+DA90 -> 0.0075 | DF90: #DIV/0! | DG90: 0.02
A91: PBT | B91: =B87+B88-B89 -> 0 | C91: =C87+C88-C89 -> 0 | D91: =D87+D88-D89 -> 0 | E91: =E87+E88-E89 -> 0 | F91: =F87+F88-F89 -> 0 | G91: =G87+G88-G89 -> 0 | H91: =H87+H88-H89 -> 0 | I91: =I87+I88-I89 -> 0 | ... AE91: =AE87+AE88-AE89 -> 8052.6509 | AI91: =AI87+AI88-AI89 -> 0 | AJ91: =AJ87+AJ88-AJ89 -> 0 | AK91: =AK87+AK88-AK89 -> 0 | AL91: =AL87+AL88-AL89 -> 0 | AM91: =AM87+AM88-AM89 -> 0 | AN91: =AN87+AN88-AN89 -> 0 | AO91: =AO87+AO88-AO89 -> 0 | AP91: =AP87+AP88-AP89 -> 0 | ... DB91: =DB87+DB88-DB89 -> 2141.818 | DF91: 0 | DG91: 781.90891
A92: Tax | B92: ='Annual Raw'!C30 -> 0 | C92: ='Annual Raw'!D30 -> 0 | D92: ='Annual Raw'!E30 -> 0 | E92: ='Annual Raw'!F30 -> 0 | F92: ='Annual Raw'!G30 -> 0 | G92: ='Annual Raw'!H30 -> 0 | H92: ='Annual Raw'!I30 -> 0 | I92: ='Annual Raw'!J30 -> 0 | ... AA92: ='Annual Raw'!AB30 -> 722.09 | AB92: =+SUM(CM92:CP92) -> 1386.1594 | AC92: =+SUM(CQ92:CT92) -> 1524.4316 | AD92: =+SUM(CU92:CX92) -> 1982.0676 | AE92: =+SUM(CY92:DB92) -> 2183.5309 | AI92: ='QTR Raw'!C29 -> 0 | AJ92: ='QTR Raw'!D29 -> 0 | AK92: ='QTR Raw'!E29 -> 0 | AL92: ='QTR Raw'!F29 -> 0 | AM92: ='QTR Raw'!G29 -> 0 | AN92: ='QTR Raw'!H29 -> 0 | AO92: ='QTR Raw'!I29 -> 0 | AP92: ='QTR Raw'!J29 -> 0 | ... CL92: ='QTR Raw'!BF29 -> 240.98 | CM92: =+CM91*CM93 -> 355.33916 | CN92: =+CN91*CN93 -> 348.04233 | CO92: =+CO91*CO93 -> 347.67189 | CP92: =+CP91*CP93 -> 335.10598 | CQ92: =+CQ91*CQ93 -> 381.14128 | CR92: =+CR91*CR93 -> 365.15006 | CS92: =+CS91*CS93 -> 375.15427 | CT92: =+CT91*CT93 -> 402.98597 | ... DB92: =+DB91*DB93 -> 580.74936 | DF92: 0 | DG92: 235.90013
A93: Tax Rate % | B93: =B92/B91 -> #DIV/0! | C93: =C92/C91 -> #DIV/0! | D93: =D92/D91 -> #DIV/0! | E93: =E92/E91 -> #DIV/0! | F93: =F92/F91 -> #DIV/0! | G93: =G92/G91 -> #DIV/0! | H93: =H92/H91 -> #DIV/0! | I93: =I92/I91 -> #DIV/0! | ... AE93: =AE92/AE91 -> 0.27115679 | AI93: =AI92/AI91 -> #DIV/0! | AJ93: =AJ92/AJ91 -> #DIV/0! | AK93: =AK92/AK91 -> #DIV/0! | AL93: =AL92/AL91 -> #DIV/0! | AM93: =AM92/AM91 -> #DIV/0! | AN93: =AN92/AN91 -> #DIV/0! | AO93: =AO92/AO91 -> #DIV/0! | AP93: =AP92/AP91 -> #DIV/0! | ... CL93: =CL92/CL91 -> 0.26479282 | CM93: =AVERAGE(CI93:CL93)*1.03 -> 0.25144525 | CN93: =AVERAGE(CJ93:CM93)*1.03 -> 0.27036244 | CO93: =AVERAGE(CK93:CN93)*1.03 -> 0.27525268 | CP93: =AVERAGE(CL93:CO93)*1.03 -> 0.2734272 | CQ93: =AVERAGE(CM93:CP93) -> 0.26762189 | CR93: =AVERAGE(CN93:CQ93) -> 0.27166605 | CS93: =AVERAGE(CO93:CR93) -> 0.27199195 | CT93: =AVERAGE(CP93:CS93) -> 0.27117677 | CU93: =AVERAGE(CQ93:CT93) -> 0.27061417 | CV93: =AVERAGE(CR93:CU93) -> 0.27136224 | CW93: =AVERAGE(CS93:CV93) -> 0.27128628 | CX93: =AVERAGE(CT93:CW93) -> 0.27110986 | ... DB93: =AVERAGE(CX93:DA93) -> 0.27114786 | DF93: #DIV/0! | DG93: 0.30169771
A94: PAT | B94: =B91-B92 -> 0 | C94: =C91-C92 -> 0 | D94: =D91-D92 -> 0 | E94: =E91-E92 -> 0 | F94: =F91-F92 -> 0 | G94: =G91-G92 -> 0 | H94: =H91-H92 -> 0 | I94: =I91-I92 -> 0 | ... AE94: =AE91-AE92 -> 5869.12 | AI94: =AI91-AI92 -> 0 | AJ94: =AJ91-AJ92 -> 0 | AK94: =AK91-AK92 -> 0 | AL94: =AL91-AL92 -> 0 | AM94: =AM91-AM92 -> 0 | AN94: =AN91-AN92 -> 0 | AO94: =AO91-AO92 -> 0 | AP94: =AP91-AP92 -> 0 | ... DB94: =DB91-DB92 -> 1561.0686 | DF94: 0 | DG94: 546.00878
A95: PAT % | B95: =+B94/B61 -> #DIV/0! | C95: =+C94/C61 -> #DIV/0! | D95: =+D94/D61 -> #DIV/0! | E95: =+E94/E61 -> #DIV/0! | F95: =+F94/F61 -> #DIV/0! | G95: =+G94/G61 -> #DIV/0! | H95: =+H94/H61 -> #DIV/0! | I95: =+I94/I61 -> #DIV/0! | ... AE95: =+AE94/AE61 -> 0.11209346 | AI95: =+AI94/AI61 -> #DIV/0! | AJ95: =+AJ94/AJ61 -> #DIV/0! | AK95: =+AK94/AK61 -> #DIV/0! | AL95: =+AL94/AL61 -> #DIV/0! | AM95: =+AM94/AM61 -> #DIV/0! | AN95: =+AN94/AN61 -> #DIV/0! | AO95: =+AO94/AO61 -> #DIV/0! | AP95: =+AP94/AP61 -> #DIV/0! | ... DB95: =+DB94/DB61 -> 0.11309243 | DF95: #DIV/0! | DG95: 0.076451542
A96: PAT YOY% | C96: =+IF(B94<0,1-C94/B94,C94/B94-1) -> #DIV/0! | D96: =+IF(C94<0,1-D94/C94,D94/C94-1) -> #DIV/0! | E96: =+IF(D94<0,1-E94/D94,E94/D94-1) -> #DIV/0! | F96: =+IF(E94<0,1-F94/E94,F94/E94-1) -> #DIV/0! | G96: =+IF(F94<0,1-G94/F94,G94/F94-1) -> #DIV/0! | H96: =+IF(G94<0,1-H94/G94,H94/G94-1) -> #DIV/0! | I96: =+IF(H94<0,1-I94/H94,I94/H94-1) -> #DIV/0! | J96: =+IF(I94<0,1-J94/I94,J94/I94-1) -> #DIV/0! | ... AE96: =+IF(AD94<0,1-AE94/AD94,AE94/AD94-1) -> 0.10132343 | AM96: =+IF(AI94<0,1-AM94/AI94,AM94/AI94-1) -> #DIV/0! | AN96: =+IF(AJ94<0,1-AN94/AJ94,AN94/AJ94-1) -> #DIV/0! | AO96: =+IF(AK94<0,1-AO94/AK94,AO94/AK94-1) -> #DIV/0! | AP96: =+IF(AL94<0,1-AP94/AL94,AP94/AL94-1) -> #DIV/0! | AQ96: =+IF(AM94<0,1-AQ94/AM94,AQ94/AM94-1) -> #DIV/0! | AR96: =+IF(AN94<0,1-AR94/AN94,AR94/AN94-1) -> #DIV/0! | AS96: =+IF(AO94<0,1-AS94/AO94,AS94/AO94-1) -> #DIV/0! | AT96: =+IF(AP94<0,1-AT94/AP94,AT94/AP94-1) -> #DIV/0! | ... CL96: =+IF(CH94<0,1-CL94/CH94,CL94/CH94-1) -> -0.02541731 | CM96: =+CM94/CI94-1 -> 0.95560956 | CN96: =+CN94/CJ94-1 -> 0.68259544 | CO96: =+CO94/CK94-1 -> 0.59238269 | CP96: =+CP94/CL94-1 -> 0.33086826 | CQ96: =+CQ94/CM94-1 -> -0.014000962 | CR96: =+CR94/CN94-1 -> 0.042254263 | CS96: =+CS94/CO94-1 -> 0.096895793 | CT96: =+CT94/CP94-1 -> 0.21629813 | ... DB96: =+DB94/CX94-1 -> 0.090086756 | DF96: #DIV/0! | DG96: -0.20469488
A97: PAT QOQ% | AJ97: =+IF(AI94<0,1-AJ94/AI94,AJ94/AI94-1) -> #DIV/0! | AK97: =+IF(AJ94<0,1-AK94/AJ94,AK94/AJ94-1) -> #DIV/0! | AL97: =+IF(AK94<0,1-AL94/AK94,AL94/AK94-1) -> #DIV/0! | AM97: =+IF(AL94<0,1-AM94/AL94,AM94/AL94-1) -> #DIV/0! | AN97: =+IF(AM94<0,1-AN94/AM94,AN94/AM94-1) -> #DIV/0! | AO97: =+IF(AN94<0,1-AO94/AN94,AO94/AN94-1) -> #DIV/0! | AP97: =+IF(AO94<0,1-AP94/AO94,AP94/AO94-1) -> #DIV/0! | AQ97: =+IF(AP94<0,1-AQ94/AP94,AQ94/AP94-1) -> #DIV/0! | ... CL97: =+IF(CK94<0,1-CL94/CK94,CL94/CK94-1) -> 0.16387768 | CM97: =+CM94/CL94-1 -> 0.5810248 | CN97: =+CN94/CM94-1 -> -0.11208854 | CO97: =+CO94/CN94-1 -> -0.025387973 | CP97: =+CP94/CO94-1 -> -0.027264061 | CQ97: =+CQ94/CP94-1 -> 0.17133226 | CR97: =+CR94/CQ94-1 -> -0.061429612 | CS97: =+CS94/CR94-1 -> 0.025707326 | CT97: =+CT94/CS94-1 -> 0.078622886 | ... DB97: =+DB94/DA94-1 -> 0.065898143 | DG97: -0.050221304
A98: Minority Interest | B98: ='Annual Raw'!C32 -> 0 | C98: ='Annual Raw'!D32 -> 0 | D98: ='Annual Raw'!E32 -> 0 | E98: ='Annual Raw'!F32 -> 0 | F98: ='Annual Raw'!G32 -> 0 | G98: ='Annual Raw'!H32 -> 0 | H98: ='Annual Raw'!I32 -> 0 | I98: ='Annual Raw'!J32 -> 0 | ... AA98: ='Annual Raw'!AB32 -> -110.21 | AB98: =+SUM(CM98:CP98) -> -155.48 | AC98: =+SUM(CQ98:CT98) -> -155.48 | AD98: =+SUM(CU98:CX98) -> -155.48 | AE98: =+SUM(CY98:DB98) -> -155.48 | AI98: ='QTR Raw'!C34 -> 0 | AJ98: ='QTR Raw'!D34 -> 0 | AK98: ='QTR Raw'!E34 -> 0 | AL98: ='QTR Raw'!F34 -> 0 | AM98: ='QTR Raw'!G34 -> 0 | AN98: ='QTR Raw'!H34 -> 0 | AO98: ='QTR Raw'!I34 -> 0 | AP98: ='QTR Raw'!J34 -> 0 | ... CL98: ='QTR Raw'!BF34 -> -38.87 | CM98: =+CL98 -> -38.87 | CN98: =+CM98 -> -38.87 | CO98: =+CN98 -> -38.87 | CP98: =+CO98 -> -38.87 | CQ98: =+CP98 -> -38.87 | CR98: =+CQ98 -> -38.87 | CS98: =+CR98 -> -38.87 | CT98: =+CS98 -> -38.87 | ... DB98: =+DA98 -> -38.87 | DF98: 0 | DG98: -21.75
A99: Share of Associate | B99: ='Annual Raw'!C33+'Annual Raw'!C28 -> 0 | C99: ='Annual Raw'!D33+'Annual Raw'!D28 -> 0 | D99: ='Annual Raw'!E33+'Annual Raw'!E28 -> 0 | E99: ='Annual Raw'!F33+'Annual Raw'!F28 -> 0 | F99: ='Annual Raw'!G33+'Annual Raw'!G28 -> 0 | G99: ='Annual Raw'!H33+'Annual Raw'!H28 -> 0 | H99: ='Annual Raw'!I33+'Annual Raw'!I28 -> 0 | I99: ='Annual Raw'!J33+'Annual Raw'!J28 -> 0 | ... AA99: ='Annual Raw'!AB33+'Annual Raw'!AB28 -> 0 | AB99: =+SUM(CM99:CP99) -> 0 | AC99: =+SUM(CQ99:CT99) -> 0 | AD99: =+SUM(CU99:CX99) -> 0 | AE99: =+SUM(CY99:DB99) -> 0 | AI99: ='QTR Raw'!C35 -> 0 | AJ99: ='QTR Raw'!D35 -> 0 | AK99: ='QTR Raw'!E35 -> 0 | AL99: ='QTR Raw'!F35 -> 0 | AM99: ='QTR Raw'!G35 -> 0 | AN99: ='QTR Raw'!H35 -> 0 | AO99: ='QTR Raw'!I35 -> 0 | AP99: ='QTR Raw'!J35 -> 0 | ... CL99: ='QTR Raw'!BF35 -> 0 | CM99: =+CL99 -> 0 | CN99: =+CM99 -> 0 | CO99: =+CN99 -> 0 | CP99: =+CO99 -> 0 | CQ99: =+CP99 -> 0 | CR99: =+CQ99 -> 0 | CS99: =+CR99 -> 0 | CT99: =+CS99 -> 0 | ... DB99: =+DA99 -> 0 | DF99: 0 | DG99: 0
A100: Exceptional Income / Expenses | B100: ='Annual Raw'!C29+'Annual Raw'!C31+'Annual Raw'!C34+'Annual Raw'!C36 -> 0 | C100: ='Annual Raw'!D29+'Annual Raw'!D31+'Annual Raw'!D34+'Annual Raw'!D36 -> 0 | D100: ='Annual Raw'!E29+'Annual Raw'!E31+'Annual Raw'!E34+'Annual Raw'!E36 -> 0 | E100: ='Annual Raw'!F29+'Annual Raw'!F31+'Annual Raw'!F34+'Annual Raw'!F36 -> 0 | F100: ='Annual Raw'!G29+'Annual Raw'!G31+'Annual Raw'!G34+'Annual Raw'!G36 -> 0 | G100: ='Annual Raw'!H29+'Annual Raw'!H31+'Annual Raw'!H34+'Annual Raw'!H36 -> 0 | H100: ='Annual Raw'!I29+'Annual Raw'!I31+'Annual Raw'!I34+'Annual Raw'!I36 -> 0 | I100: ='Annual Raw'!J29+'Annual Raw'!J31+'Annual Raw'!J34+'Annual Raw'!J36 -> 0 | ... AA100: ='Annual Raw'!AB29+'Annual Raw'!AB31+'Annual Raw'!AB34+'Annual Raw'!AB36 -> 0 | AB100: =+SUM(CM100:CP100) -> 0 | AC100: =+SUM(CQ100:CT100) -> 0 | AD100: =+SUM(CU100:CX100) -> 0 | AE100: =+SUM(CY100:DB100) -> 0 | AI100: ='QTR Raw'!C26+'QTR Raw'!C31+'QTR Raw'!C32+'QTR Raw'!C33+'QTR Raw'!C36+'QTR Raw'!C37+'QTR Raw'!C39 -> 0 | AJ100: ='QTR Raw'!D26+'QTR Raw'!D31+'QTR Raw'!D32+'QTR Raw'!D33+'QTR Raw'!D36+'QTR Raw'!D37+'QTR Raw'!D39 -> 0 | AK100: ='QTR Raw'!E26+'QTR Raw'!E31+'QTR Raw'!E32+'QTR Raw'!E33+'QTR Raw'!E36+'QTR Raw'!E37+'QTR Raw'!E39 -> 0 | AL100: ='QTR Raw'!F26+'QTR Raw'!F31+'QTR Raw'!F32+'QTR Raw'!F33+'QTR Raw'!F36+'QTR Raw'!F37+'QTR Raw'!F39 -> 0 | AM100: ='QTR Raw'!G26+'QTR Raw'!G31+'QTR Raw'!G32+'QTR Raw'!G33+'QTR Raw'!G36+'QTR Raw'!G37+'QTR Raw'!G39 -> 0 | AN100: ='QTR Raw'!H26+'QTR Raw'!H31+'QTR Raw'!H32+'QTR Raw'!H33+'QTR Raw'!H36+'QTR Raw'!H37+'QTR Raw'!H39 -> 0 | AO100: ='QTR Raw'!I26+'QTR Raw'!I31+'QTR Raw'!I32+'QTR Raw'!I33+'QTR Raw'!I36+'QTR Raw'!I37+'QTR Raw'!I39 -> 0 | AP100: ='QTR Raw'!J26+'QTR Raw'!J31+'QTR Raw'!J32+'QTR Raw'!J33+'QTR Raw'!J36+'QTR Raw'!J37+'QTR Raw'!J39 -> 0 | ... CL100: ='QTR Raw'!BF26+'QTR Raw'!BF31+'QTR Raw'!BF32+'QTR Raw'!BF33+'QTR Raw'!BF36+'QTR Raw'!BF37+'QTR Raw'!BF39 -> 53.56 | DF100: 0
A101: Consolidated Net Profit | B101: =B94+B98+B99+B100 -> 0 | C101: =C94+C98+C99+C100 -> 0 | D101: =D94+D98+D99+D100 -> 0 | E101: =E94+E98+E99+E100 -> 0 | F101: =F94+F98+F99+F100 -> 0 | G101: =G94+G98+G99+G100 -> 0 | H101: =H94+H98+H99+H100 -> 0 | I101: =I94+I98+I99+I100 -> 0 | ... AE101: =AE94+AE98+AE99+AE100 -> 5713.64 | AI101: =AI94+AI98+AI99+AI100 -> 0 | AJ101: =AJ94+AJ98+AJ99+AJ100 -> 0 | AK101: =AK94+AK98+AK99+AK100 -> 0 | AL101: =AL94+AL98+AL99+AL100 -> 0 | AM101: =AM94+AM98+AM99+AM100 -> 0 | AN101: =AN94+AN98+AN99+AN100 -> 0 | AO101: =AO94+AO98+AO99+AO100 -> 0 | AP101: =AP94+AP98+AP99+AP100 -> 0 | ... DB101: =DB94+DB98+DB99+DB100 -> 1522.1986 | DF101: 0 | DG101: 524.25878
A102: Profit & Loss- Annual (End)
A104: Ace - PAT | B104: ='Annual Raw'!C35 -> 0 | C104: ='Annual Raw'!D35 -> 0 | D104: ='Annual Raw'!E35 -> 0 | E104: ='Annual Raw'!F35 -> 0 | F104: ='Annual Raw'!G35 -> 0 | G104: ='Annual Raw'!H35 -> 0 | H104: ='Annual Raw'!I35 -> 0 | I104: ='Annual Raw'!J35 -> 0 | ... AA104: ='Annual Raw'!AB35 -> 2282.54 | AB104: =+AB101 -> 3647.5427 | AC104: =+AC101 -> 3953.7286 | AD104: =+AD101 -> 5173.672 | AE104: =+AE101 -> 5713.64 | AI104: ='QTR Raw'!C42 -> 0 | AJ104: ='QTR Raw'!D42 -> 0 | AK104: ='QTR Raw'!E42 -> 0 | AL104: ='QTR Raw'!F42 -> 0 | AM104: ='QTR Raw'!G42 -> 0 | AN104: ='QTR Raw'!H42 -> 0 | AO104: ='QTR Raw'!I42 -> 0 | AP104: ='QTR Raw'!J42 -> 0 | ... CL104: ='QTR Raw'!BF42 -> 683.78 | DF104: 0
A105: Checksum - PAT | B105: =B104-B101 -> 0 | C105: =C104-C101 -> 0 | D105: =D104-D101 -> 0 | E105: =E104-E101 -> 0 | F105: =F104-F101 -> 0 | G105: =G104-G101 -> 0 | H105: =H104-H101 -> 0 | I105: =I104-I101 -> 0 | ... AE105: =AE104-AE101 -> 0 | AI105: =AI104-AI101 -> 0 | AJ105: =AJ104-AJ101 -> 0 | AK105: =AK104-AK101 -> 0 | AL105: =AL104-AL101 -> 0 | AM105: =AM104-AM101 -> 0 | AN105: =AN104-AN101 -> 0 | AO105: =AO104-AO101 -> 0 | AP105: =AP104-AP101 -> 0 | ... CL105: =CL104-CL101 -> -9.094947e-13 | DF105: 0
A106: Ratios (Start)
A107: ROE (%) | B107: =(B101-B100)/B173 -> #DIV/0! | C107: =(C101-C100)/C173 -> #DIV/0! | D107: =(D101-D100)/D173 -> #DIV/0! | E107: =(E101-E100)/E173 -> #DIV/0! | F107: =(F101-F100)/F173 -> #DIV/0! | G107: =(G101-G100)/G173 -> #DIV/0! | H107: =(H101-H100)/H173 -> #DIV/0! | I107: =(I101-I100)/I173 -> #DIV/0! | ... AE107: =(AE101-AE100)/AE173 -> 0.13010347 | AL107: =(SUM(AI101:AL101)-SUM(AI100:AL100))/AL173 -> #DIV/0! | AM107: =(SUM(AJ101:AM101)-SUM(AJ100:AM100))/AM173 -> #DIV/0! | AN107: =(SUM(AK101:AN101)-SUM(AK100:AN100))/AN173 -> #DIV/0! | AO107: =(SUM(AL101:AO101)-SUM(AL100:AO100))/AO173 -> #DIV/0! | AP107: =(SUM(AM101:AP101)-SUM(AM100:AP100))/AP173 -> #DIV/0! | AQ107: =(SUM(AN101:AQ101)-SUM(AN100:AQ100))/AQ173 -> #DIV/0! | AR107: =(SUM(AO101:AR101)-SUM(AO100:AR100))/AR173 -> #DIV/0! | AS107: =(SUM(AP101:AS101)-SUM(AP100:AS100))/AS173 -> 1 | ... DB107: =(SUM(CY101:DB101)-SUM(CY100:DB100))/DB173 -> 0.13010347 | DF107: #DIV/0! | DG107: 0.086955196
A108: ROCE (%) | B108: =+B87/B182 -> #DIV/0! | C108: =+C87/C182 -> #DIV/0! | D108: =+D87/D182 -> #DIV/0! | E108: =+E87/E182 -> #DIV/0! | F108: =+F87/F182 -> #DIV/0! | G108: =+G87/G182 -> #DIV/0! | H108: =+H87/H182 -> #DIV/0! | I108: =+I87/I182 -> #DIV/0! | ... AE108: =+AE87/AE182 -> 0.12075639 | AL108: =+SUM(AI87:AL87)/AL182 -> #DIV/0! | AM108: =+SUM(AJ87:AM87)/AM182 -> #DIV/0! | AN108: =+SUM(AK87:AN87)/AN182 -> #DIV/0! | AO108: =+SUM(AL87:AO87)/AO182 -> #DIV/0! | AP108: =+SUM(AM87:AP87)/AP182 -> #DIV/0! | AQ108: =+SUM(AN87:AQ87)/AQ182 -> #DIV/0! | AR108: =+SUM(AO87:AR87)/AR182 -> #DIV/0! | AS108: =+SUM(AP87:AS87)/AS182 -> 1.0097245 | ... DB108: =+SUM(CY87:DB87)/DB182 -> 0.12075639 | DF108: #DIV/0! | DG108: 0.082606203
A109: Ratios (End)
A110: Checksum Of qtr to Annual
...

Sheet QTR Raw
A1: ='Annual Raw'!A1 -> 271875 | B1: X | C1: 201206 | D1: 201209 | E1: 201212 | F1: 201303 | G1: 201306 | H1: 201309 | I1: 201312 | J1: 201403 | K1: 201406 | L1: 201409 | M1: 201412 | N1: 201503 | O1: 201506 | P1: 201509 | Q1: 201512 | R1: 201603 | S1: 201606 | T1: 201609 | U1: 201612 | V1: 201703 | W1: 201706 | X1: 201709 | Y1: 201712 | Z1: 201803 | AA1: 201806 | AB1: 201809 | AC1: 201812 | AD1: 201903 | AE1: 201906 | AF1: 201909 | AG1: 201912 | AH1: 202003 | AI1: 202006 | AJ1: 202009 | AK1: 202012 | AL1: 202103 | AM1: 202106 | AN1: 202109 | AO1: 202112 | AP1: 202203 | AQ1: 202206 | AR1: 202209 | AS1: 202212 | AT1: 202303 | AU1: 202306 | AV1: 202309 | AW1: 202312 | AX1: 202403 | AY1: 202406 | AZ1: 202409 | BA1: 202412 | BB1: 202503 | BC1: 202506 | BD1: 202509 | BE1: 202512 | BF1: 202603 | BG1: 202606 | BH1: 202609 | BI1: 202612 | BJ1: 202703 | BK1: 202706 | BL1: 202709 | BM1: 202712 | BN1: 202803 | BO1: 202806 | BP1: 202809 | BQ1: 202812 | BR1: 202903 | BS1: 202906 | BT1: 202909 | BU1: 202912 | BV1: 203003
A3: Field Description | B3: Field Name
A4: Company Name | B4: CD_COMPNAME | C4: =_xll.EQNXTDZ(A1,B4,C1) -> Adani Energy Solutions Ltd.
A5: Date End | B5: QTR_DATE_END | C5: =_xll.EQNXTDZ($A$1,$B5,C$1,$B$1) -> 0 | D5: =_xll.EQNXTDZ($A$1,$B5,D$1,$B$1) -> 0 | E5: =_xll.EQNXTDZ($A$1,$B5,E$1,$B$1) -> 0 | F5: =_xll.EQNXTDZ($A$1,$B5,F$1,$B$1) -> 0 | G5: =_xll.EQNXTDZ($A$1,$B5,G$1,$B$1) -> 0 | H5: =_xll.EQNXTDZ($A$1,$B5,H$1,$B$1) -> 0 | I5: =_xll.EQNXTDZ($A$1,$B5,I$1,$B$1) -> 0 | J5: =_xll.EQNXTDZ($A$1,$B5,J$1,$B$1) -> 0 | ... BV5: =_xll.EQNXTDZ($A$1,$B5,BV$1,$B$1) -> 0
A6: Gross Sales | B6: QTR_GROSS_SALE | C6: =_xll.EQNXTDZ($A$1,$B6,C$1,$B$1) -> 0 | D6: =_xll.EQNXTDZ($A$1,$B6,D$1,$B$1) -> 0 | E6: =_xll.EQNXTDZ($A$1,$B6,E$1,$B$1) -> 0 | F6: =_xll.EQNXTDZ($A$1,$B6,F$1,$B$1) -> 0 | G6: =_xll.EQNXTDZ($A$1,$B6,G$1,$B$1) -> 0 | H6: =_xll.EQNXTDZ($A$1,$B6,H$1,$B$1) -> 0 | I6: =_xll.EQNXTDZ($A$1,$B6,I$1,$B$1) -> 0 | J6: =_xll.EQNXTDZ($A$1,$B6,J$1,$B$1) -> 0 | ... BV6: =_xll.EQNXTDZ($A$1,$B6,BV$1,$B$1) -> 0
A7: Less: Excise Duty | B7: QTR_EXCISE_DUTY | C7: =_xll.EQNXTDZ($A$1,$B7,C$1,$B$1) -> 0 | D7: =_xll.EQNXTDZ($A$1,$B7,D$1,$B$1) -> 0 | E7: =_xll.EQNXTDZ($A$1,$B7,E$1,$B$1) -> 0 | F7: =_xll.EQNXTDZ($A$1,$B7,F$1,$B$1) -> 0 | G7: =_xll.EQNXTDZ($A$1,$B7,G$1,$B$1) -> 0 | H7: =_xll.EQNXTDZ($A$1,$B7,H$1,$B$1) -> 0 | I7: =_xll.EQNXTDZ($A$1,$B7,I$1,$B$1) -> 0 | J7: =_xll.EQNXTDZ($A$1,$B7,J$1,$B$1) -> 0 | ... BV7: =_xll.EQNXTDZ($A$1,$B7,BV$1,$B$1) -> 0
A8: Other operating income | B8: QTR_JOB_WORKS | C8: =_xll.EQNXTDZ($A$1,$B8,C$1,$B$1) -> 0 | D8: =_xll.EQNXTDZ($A$1,$B8,D$1,$B$1) -> 0 | E8: =_xll.EQNXTDZ($A$1,$B8,E$1,$B$1) -> 0 | F8: =_xll.EQNXTDZ($A$1,$B8,F$1,$B$1) -> 0 | G8: =_xll.EQNXTDZ($A$1,$B8,G$1,$B$1) -> 0 | H8: =_xll.EQNXTDZ($A$1,$B8,H$1,$B$1) -> 0 | I8: =_xll.EQNXTDZ($A$1,$B8,I$1,$B$1) -> 0 | J8: =_xll.EQNXTDZ($A$1,$B8,J$1,$B$1) -> 0 | ... BV8: =_xll.EQNXTDZ($A$1,$B8,BV$1,$B$1) -> 0
A9: Net Sales & Other Operating Income | B9: QTR_NET_SALES | C9: =_xll.EQNXTDZ($A$1,$B9,C$1,$B$1) -> 0 | D9: =_xll.EQNXTDZ($A$1,$B9,D$1,$B$1) -> 0 | E9: =_xll.EQNXTDZ($A$1,$B9,E$1,$B$1) -> 0 | F9: =_xll.EQNXTDZ($A$1,$B9,F$1,$B$1) -> 0 | G9: =_xll.EQNXTDZ($A$1,$B9,G$1,$B$1) -> 0 | H9: =_xll.EQNXTDZ($A$1,$B9,H$1,$B$1) -> 0 | I9: =_xll.EQNXTDZ($A$1,$B9,I$1,$B$1) -> 0 | J9: =_xll.EQNXTDZ($A$1,$B9,J$1,$B$1) -> 0 | ... BV9: =_xll.EQNXTDZ($A$1,$B9,BV$1,$B$1) -> 0
A10: (Increase) / Decrease In Stocks | B10: QTR_INC_DEC_INVENTORY | C10: =_xll.EQNXTDZ($A$1,$B10,C$1,$B$1) -> 0 | D10: =_xll.EQNXTDZ($A$1,$B10,D$1,$B$1) -> 0 | E10: =_xll.EQNXTDZ($A$1,$B10,E$1,$B$1) -> 0 | F10: =_xll.EQNXTDZ($A$1,$B10,F$1,$B$1) -> 0 | G10: =_xll.EQNXTDZ($A$1,$B10,G$1,$B$1) -> 0 | H10: =_xll.EQNXTDZ($A$1,$B10,H$1,$B$1) -> 0 | I10: =_xll.EQNXTDZ($A$1,$B10,I$1,$B$1) -> 0 | J10: =_xll.EQNXTDZ($A$1,$B10,J$1,$B$1) -> 0 | ... BV10: =_xll.EQNXTDZ($A$1,$B10,BV$1,$B$1) -> 0
A11: Cost of Services & Raw Materials | B11: QTR_RAW_MATERIAL_COST | C11: =_xll.EQNXTDZ($A$1,$B11,C$1,$B$1) -> 0 | D11: =_xll.EQNXTDZ($A$1,$B11,D$1,$B$1) -> 0 | E11: =_xll.EQNXTDZ($A$1,$B11,E$1,$B$1) -> 0 | F11: =_xll.EQNXTDZ($A$1,$B11,F$1,$B$1) -> 0 | G11: =_xll.EQNXTDZ($A$1,$B11,G$1,$B$1) -> 0 | H11: =_xll.EQNXTDZ($A$1,$B11,H$1,$B$1) -> 0 | I11: =_xll.EQNXTDZ($A$1,$B11,I$1,$B$1) -> 0 | J11: =_xll.EQNXTDZ($A$1,$B11,J$1,$B$1) -> 0 | ... BV11: =_xll.EQNXTDZ($A$1,$B11,BV$1,$B$1) -> 0
A12: Purchase of Finished Goods | B12: QTR_PURCHASE_FIN_GOOD | C12: =_xll.EQNXTDZ($A$1,$B12,C$1,$B$1) -> 0 | D12: =_xll.EQNXTDZ($A$1,$B12,D$1,$B$1) -> 0 | E12: =_xll.EQNXTDZ($A$1,$B12,E$1,$B$1) -> 0 | F12: =_xll.EQNXTDZ($A$1,$B12,F$1,$B$1) -> 0 | G12: =_xll.EQNXTDZ($A$1,$B12,G$1,$B$1) -> 0 | H12: =_xll.EQNXTDZ($A$1,$B12,H$1,$B$1) -> 0 | I12: =_xll.EQNXTDZ($A$1,$B12,I$1,$B$1) -> 0 | J12: =_xll.EQNXTDZ($A$1,$B12,J$1,$B$1) -> 0 | ... BV12: =_xll.EQNXTDZ($A$1,$B12,BV$1,$B$1) -> 0
A13: Excise Duty | B13: QTR_EXCISE | C13: =_xll.EQNXTDZ($A$1,$B13,C$1,$B$1) -> 0 | D13: =_xll.EQNXTDZ($A$1,$B13,D$1,$B$1) -> 0 | E13: =_xll.EQNXTDZ($A$1,$B13,E$1,$B$1) -> 0 | F13: =_xll.EQNXTDZ($A$1,$B13,F$1,$B$1) -> 0 | G13: =_xll.EQNXTDZ($A$1,$B13,G$1,$B$1) -> 0 | H13: =_xll.EQNXTDZ($A$1,$B13,H$1,$B$1) -> 0 | I13: =_xll.EQNXTDZ($A$1,$B13,I$1,$B$1) -> 0 | J13: =_xll.EQNXTDZ($A$1,$B13,J$1,$B$1) -> 0 | ... BV13: =_xll.EQNXTDZ($A$1,$B13,BV$1,$B$1) -> 0
A14: Operating & Manufacturing Expenses | B14: QTR_MFG_EXPS | C14: =_xll.EQNXTDZ($A$1,$B14,C$1,$B$1) -> 0 | D14: =_xll.EQNXTDZ($A$1,$B14,D$1,$B$1) -> 0 | E14: =_xll.EQNXTDZ($A$1,$B14,E$1,$B$1) -> 0 | F14: =_xll.EQNXTDZ($A$1,$B14,F$1,$B$1) -> 0 | G14: =_xll.EQNXTDZ($A$1,$B14,G$1,$B$1) -> 0 | H14: =_xll.EQNXTDZ($A$1,$B14,H$1,$B$1) -> 0 | I14: =_xll.EQNXTDZ($A$1,$B14,I$1,$B$1) -> 0 | J14: =_xll.EQNXTDZ($A$1,$B14,J$1,$B$1) -> 0 | ... BV14: =_xll.EQNXTDZ($A$1,$B14,BV$1,$B$1) -> 0
A15: Electricity Power & Fuel Cost | B15: QTR_ELECTRICITY_POWER_FUEL | C15: =_xll.EQNXTDZ($A$1,$B15,C$1,$B$1) -> 0 | D15: =_xll.EQNXTDZ($A$1,$B15,D$1,$B$1) -> 0 | E15: =_xll.EQNXTDZ($A$1,$B15,E$1,$B$1) -> 0 | F15: =_xll.EQNXTDZ($A$1,$B15,F$1,$B$1) -> 0 | G15: =_xll.EQNXTDZ($A$1,$B15,G$1,$B$1) -> 0 | H15: =_xll.EQNXTDZ($A$1,$B15,H$1,$B$1) -> 0 | I15: =_xll.EQNXTDZ($A$1,$B15,I$1,$B$1) -> 0 | J15: =_xll.EQNXTDZ($A$1,$B15,J$1,$B$1) -> 0 | ... BV15: =_xll.EQNXTDZ($A$1,$B15,BV$1,$B$1) -> 0
A16: Employee Cost | B16: QTR_EXPLOYEE_COST | C16: =_xll.EQNXTDZ($A$1,$B16,C$1,$B$1) -> 0 | D16: =_xll.EQNXTDZ($A$1,$B16,D$1,$B$1) -> 0 | E16: =_xll.EQNXTDZ($A$1,$B16,E$1,$B$1) -> 0 | F16: =_xll.EQNXTDZ($A$1,$B16,F$1,$B$1) -> 0 | G16: =_xll.EQNXTDZ($A$1,$B16,G$1,$B$1) -> 0 | H16: =_xll.EQNXTDZ($A$1,$B16,H$1,$B$1) -> 0 | I16: =_xll.EQNXTDZ($A$1,$B16,I$1,$B$1) -> 0 | J16: =_xll.EQNXTDZ($A$1,$B16,J$1,$B$1) -> 0 | ... BV16: =_xll.EQNXTDZ($A$1,$B16,BV$1,$B$1) -> 0
... A42: Consolidated PAT(after extra items) | B42: QTR_CONS_PAT_EXITM | C42: =_xll.EQNXTDZ($A$1,$B42,C$1,$B$1) -> 0 | D42: =_xll.EQNXTDZ($A$1,$B42,D$1,$B$1) -> 0 | E42: =_xll.EQNXTDZ($A$1,$B42,E$1,$B$1) -> 0 | F42: =_xll.EQNXTDZ($A$1,$B42,F$1,$B$1) -> 0 | G42: =_xll.EQNXTDZ($A$1,$B42,G$1,$B$1) -> 0 | H42: =_xll.EQNXTDZ($A$1,$B42,H$1,$B$1) -> 0 | I42: =_xll.EQNXTDZ($A$1,$B42,I$1,$B$1) -> 0 | J42: =_xll.EQNXTDZ($A$1,$B42,J$1,$B$1) -> 0 | ... BV42: =_xll.EQNXTDZ($A$1,$B42,BV$1,$B$1) -> 0
A44: Field Description | B44: Field Name
A45: Equity Capital | B45: QTR_EQUITY_CAP | C45: =_xll.EQNXTDZ($A$1,$B45,C$1,$B$1) -> 0 | D45: =_xll.EQNXTDZ($A$1,$B45,D$1,$B$1) -> 0 | E45: =_xll.EQNXTDZ($A$1,$B45,E$1,$B$1) -> 0 | F45: =_xll.EQNXTDZ($A$1,$B45,F$1,$B$1) -> 0 | G45: =_xll.EQNXTDZ($A$1,$B45,G$1,$B$1) -> 0 | H45: =_xll.EQNXTDZ($A$1,$B45,H$1,$B$1) -> 0 | I45: =_xll.EQNXTDZ($A$1,$B45,I$1,$B$1) -> 0 | J45: =_xll.EQNXTDZ($A$1,$B45,J$1,$B$1) -> 0 | ... BV45: =_xll.EQNXTDZ($A$1,$B45,BV$1,$B$1) -> 0
A46: Face Value | B46: QTR_FV | C46: =_xll.EQNXTDZ($A$1,$B46,C$1,$B$1) -> 0 | D46: =_xll.EQNXTDZ($A$1,$B46,D$1,$B$1) -> 0 | E46: =_xll.EQNXTDZ($A$1,$B46,E$1,$B$1) -> 0 | F46: =_xll.EQNXTDZ($A$1,$B46,F$1,$B$1) -> 0 | G46: =_xll.EQNXTDZ($A$1,$B46,G$1,$B$1) -> 0 | H46: =_xll.EQNXTDZ($A$1,$B46,H$1,$B$1) -> 0 | I46: =_xll.EQNXTDZ($A$1,$B46,I$1,$B$1) -> 0 | J46: =_xll.EQNXTDZ($A$1,$B46,J$1,$B$1) -> 0 | ... BV46: =_xll.EQNXTDZ($A$1,$B46,BV$1,$B$1) -> 0
A47: Month End | B47: BMONTH_MONTHEND | C47: =_xll.EQNXTDZ($A$1,$B47,C$5) -> 0 | D47: =_xll.EQNXTDZ($A$1,$B47,D$5) -> 0 | E47: =_xll.EQNXTDZ($A$1,$B47,E$5) -> 0 | F47: =_xll.EQNXTDZ($A$1,$B47,F$5) -> 0 | G47: =_xll.EQNXTDZ($A$1,$B47,G$5) -> 0 | H47: =_xll.EQNXTDZ($A$1,$B47,H$5) -> 0 | I47: =_xll.EQNXTDZ($A$1,$B47,I$5) -> 0 | J47: =_xll.EQNXTDZ($A$1,$B47,J$5) -> 0 | ... BV47: =_xll.EQNXTDZ($A$1,$B47,BV$5) -> 0
A48: Close | B48: BMONTH_CLOSE | C48: =_xll.EQNXTDZ($A$1,$B48,C$5) -> 0 | D48: =_xll.EQNXTDZ($A$1,$B48,D$5) -> 0 | E48: =_xll.EQNXTDZ($A$1,$B48,E$5) -> 0 | F48: =_xll.EQNXTDZ($A$1,$B48,F$5) -> 0 | G48: =_xll.EQNXTDZ($A$1,$B48,G$5) -> 0 | H48: =_xll.EQNXTDZ($A$1,$B48,H$5) -> 0 | I48: =_xll.EQNXTDZ($A$1,$B48,I$5) -> 0 | J48: =_xll.EQNXTDZ($A$1,$B48,J$5) -> 0 | ... BV48: =_xll.EQNXTDZ($A$1,$B48,BV$5) -> 0
A49: Total of Promoter and Promoter Group | B49: SHP_TPFTOTALPROMOTER | C49: =_xll.EQNXTDZ($A$1,$B49,C$5) -> 0 | D49: =_xll.EQNXTDZ($A$1,$B49,D$5) -> 0 | E49: =_xll.EQNXTDZ($A$1,$B49,E$5) -> 0 | F49: =_xll.EQNXTDZ($A$1,$B49,F$5) -> 0 | G49: =_xll.EQNXTDZ($A$1,$B49,G$5) -> 0 | H49: =_xll.EQNXTDZ($A$1,$B49,H$5) -> 0 | I49: =_xll.EQNXTDZ($A$1,$B49,I$5) -> 0 | J49: =_xll.EQNXTDZ($A$1,$B49,J$5) -> 0 | ... BV49: =_xll.EQNXTDZ($A$1,$B49,BV$5) -> 0
A50: Total of Promoter and Promoter Group Pledged | B50: SHP_PSHFTOTALPROMOTER | C50: =_xll.EQNXTDZ($A$1,$B50,C$5) -> 0 | D50: =_xll.EQNXTDZ($A$1,$B50,D$5) -> 0 | E50: =_xll.EQNXTDZ($A$1,$B50,E$5) -> 0 | F50: =_xll.EQNXTDZ($A$1,$B50,F$5) -> 0 | G50: =_xll.EQNXTDZ($A$1,$B50,G$5) -> 0 | H50: =_xll.EQNXTDZ($A$1,$B50,H$5) -> 0 | I50: =_xll.EQNXTDZ($A$1,$B50,I$5) -> 0 | J50: =_xll.EQNXTDZ($A$1,$B50,J$5) -> 0 | ... BV50: =_xll.EQNXTDZ($A$1,$B50,BV$5) -> 0
A54: Field Description | B54: Field Name | C54: =_xll.EQNXTDZ($A$1,$B54,C$5) -> 0 | D54: =_xll.EQNXTDZ($A$1,$B54,D$5) -> 0 | E54: =_xll.EQNXTDZ($A$1,$B54,E$5) -> 0 | F54: =_xll.EQNXTDZ($A$1,$B54,F$5) -> 0 | G54: =_xll.EQNXTDZ($A$1,$B54,G$5) -> 0 | H54: =_xll.EQNXTDZ($A$1,$B54,H$5) -> 0 | I54: =_xll.EQNXTDZ($A$1,$B54,I$5) -> 0 | J54: =_xll.EQNXTDZ($A$1,$B54,J$5) -> 0 | ... BV54: =_xll.EQNXTDZ($A$1,$B54,BV$5) -> 0
A55: Year End | B55: QTRB_DATE_END | C55: =_xll.EQNXTDZ($A$1,$B55,C$5,$B$1) -> 0 | D55: =_xll.EQNXTDZ($A$1,$B55,D$5,$B$1) -> 0 | E55: =_xll.EQNXTDZ($A$1,$B55,E$5,$B$1) -> 0 | F55: =_xll.EQNXTDZ($A$1,$B55,F$5,$B$1) -> 0 | G55: =_xll.EQNXTDZ($A$1,$B55,G$5,$B$1) -> 0 | H55: =_xll.EQNXTDZ($A$1,$B55,H$5,$B$1) -> 0 | I55: =_xll.EQNXTDZ($A$1,$B55,I$5,$B$1) -> 0 | J55: =_xll.EQNXTDZ($A$1,$B55,J$5,$B$1) -> 0 | ... BV55: =_xll.EQNXTDZ($A$1,$B55,BV$5,$B$1) -> 0
A56: Share Capital | B56: QTRB_SHARE_CAPITAL | C56: =_xll.EQNXTDZ($A$1,$B56,C$5,$B$1) -> 0 | D56: =_xll.EQNXTDZ($A$1,$B56,D$5,$B$1) -> 0 | E56: =_xll.EQNXTDZ($A$1,$B56,E$5,$B$1) -> 0 | F56: =_xll.EQNXTDZ($A$1,$B56,F$5,$B$1) -> 0 | G56: =_xll.EQNXTDZ($A$1,$B56,G$5,$B$1) -> 0 | H56: =_xll.EQNXTDZ($A$1,$B56,H$5,$B$1) -> 0 | I56: =_xll.EQNXTDZ($A$1,$B56,I$5,$B$1) -> 0 | J56: =_xll.EQNXTDZ($A$1,$B56,J$5,$B$1) -> 0 | ... BV56: =_xll.EQNXTDZ($A$1,$B56,BV$5,$B$1) -> 0
A57: Share Warrants & outstandings | B57: QTRB_SHAREWARNDOUT | C57: =_xll.EQNXTDZ($A$1,$B57,C$5,$B$1) -> 0 | D57: =_xll.EQNXTDZ($A$1,$B57,D$5,$B$1) -> 0 | E57: =_xll.EQNXTDZ($A$1,$B57,E$5,$B$1) -> 0 | F57: =_xll.EQNXTDZ($A$1,$B57,F$5,$B$1) -> 0 | G57: =_xll.EQNXTDZ($A$1,$B57,G$5,$B$1) -> 0 | H57: =_xll.EQNXTDZ($A$1,$B57,H$5,$B$1) -> 0 | I57: =_xll.EQNXTDZ($A$1,$B57,I$5,$B$1) -> 0 | J57: =_xll.EQNXTDZ($A$1,$B57,J$5,$B$1) -> 0 | ... BV57: =_xll.EQNXTDZ($A$1,$B57,BV$5,$B$1) -> 0
A58: Reserves & Surplus | B58: QTRB_RESERVE | C58: =_xll.EQNXTDZ($A$1,$B58,C$5,$B$1) -> 0 | D58: =_xll.EQNXTDZ($A$1,$B58,D$5,$B$1) -> 0 | E58: =_xll.EQNXTDZ($A$1,$B58,E$5,$B$1) -> 0 | F58: =_xll.EQNXTDZ($A$1,$B58,F$5,$B$1) -> 0 | G58: =_xll.EQNXTDZ($A$1,$B58,G$5,$B$1) -> 0 | H58: =_xll.EQNXTDZ($A$1,$B58,H$5,$B$1) -> 0 | I58: =_xll.EQNXTDZ($A$1,$B58,I$5,$B$1) -> 0 | J58: =_xll.EQNXTDZ($A$1,$B58,J$5,$B$1) -> 0 | ... BV58: =_xll.EQNXTDZ($A$1,$B58,BV$5,$B$1) -> 0
A59: Shareholder's Funds | B59: QTRB_SHAREHODERS_FUNDS | C59: =_xll.EQNXTDZ($A$1,$B59,C$5,$B$1) -> 0 | D59: =_xll.EQNXTDZ($A$1,$B59,D$5,$B$1) -> 0 | E59: =_xll.EQNXTDZ($A$1,$B59,E$5,$B$1) -> 0 | F59: =_xll.EQNXTDZ($A$1,$B59,F$5,$B$1) -> 0 | G59: =_xll.EQNXTDZ($A$1,$B59,G$5,$B$1) -> 0 | H59: =_xll.EQNXTDZ($A$1,$B59,H$5,$B$1) -> 0 | I59: =_xll.EQNXTDZ($A$1,$B59,I$5,$B$1) -> 0 | J59: =_xll.EQNXTDZ($A$1,$B59,J$5,$B$1) -> 0 | ... BV59: =_xll.EQNXTDZ($A$1,$B59,BV$5,$B$1) -> 0
A60: Minority Interest | B60: QTRB_MINORITY_INTEREST_BS | C60: =_xll.EQNXTDZ($A$1,$B60,C$5,$B$1) -> 0 | D60: =_xll.EQNXTDZ($A$1,$B60,D$5,$B$1) -> 0 | E60: =_xll.EQNXTDZ($A$1,$B60,E$5,$B$1) -> 0 | F60: =_xll.EQNXTDZ($A$1,$B60,F$5,$B$1) -> 0 | G60: =_xll.EQNXTDZ($A$1,$B60,G$5,$B$1) -> 0 | H60: =_xll.EQNXTDZ($A$1,$B60,H$5,$B$1) -> 0 | I60: =_xll.EQNXTDZ($A$1,$B60,I$5,$B$1) -> 0 | J60: =_xll.EQNXTDZ($A$1,$B60,J$5,$B$1) -> 0 | ... BV60: =_xll.EQNXTDZ($A$1,$B60,BV$5,$B$1) -> 0
A61: Long Term Borrowings | B61: QTRB_TOTAL_DEBTS | C61: =_xll.EQNXTDZ($A$1,$B61,C$5,$B$1) -> 0 | D61: =_xll.EQNXTDZ($A$1,$B61,D$5,$B$1) -> 0 | E61: =_xll.EQNXTDZ($A$1,$B61,E$5,$B$1) -> 0 | F61: =_xll.EQNXTDZ($A$1,$B61,F$5,$B$1) -> 0 | G61: =_xll.EQNXTDZ($A$1,$B61,G$5,$B$1) -> 0 | H61: =_xll.EQNXTDZ($A$1,$B61,H$5,$B$1) -> 0 | I61: =_xll.EQNXTDZ($A$1,$B61,I$5,$B$1) -> 0 | J61: =_xll.EQNXTDZ($A$1,$B61,J$5,$B$1) -> 0 | ... BV61: =_xll.EQNXTDZ($A$1,$B61,BV$5,$B$1) -> 0
A62: Secured Loans | B62: QTRB_SECURED_LOANS | C62: =_xll.EQNXTDZ($A$1,$B62,C$5,$B$1) -> 0 | D62: =_xll.EQNXTDZ($A$1,$B62,D$5,$B$1) -> 0 | E62: =_xll.EQNXTDZ($A$1,$B62,E$5,$B$1) -> 0 | F62: =_xll.EQNXTDZ($A$1,$B62,F$5,$B$1) -> 0 | G62: =_xll.EQNXTDZ($A$1,$B62,G$5,$B$1) -> 0 | H62: =_xll.EQNXTDZ($A$1,$B62,H$5,$B$1) -> 0 | I62: =_xll.EQNXTDZ($A$1,$B62,I$5,$B$1) -> 0 | J62: =_xll.EQNXTDZ($A$1,$B62,J$5,$B$1) -> 0 | ... BV62: =_xll.EQNXTDZ($A$1,$B62,BV$5,$B$1) -> 0
A63: Unsecured Loans | B63: QTRB_UNSECURED_LOANS_NF | C63: =_xll.EQNXTDZ($A$1,$B63,C$5,$B$1) -> 0 | D63: =_xll.EQNXTDZ($A$1,$B63,D$5,$B$1) -> 0 | E63: =_xll.EQNXTDZ($A$1,$B63,E$5,$B$1) -> 0 | F63: =_xll.EQNXTDZ($A$1,$B63,F$5,$B$1) -> 0 | G63: =_xll.EQNXTDZ($A$1,$B63,G$5,$B$1) -> 0 | H63: =_xll.EQNXTDZ($A$1,$B63,H$5,$B$1) -> 0 | I63: =_xll.EQNXTDZ($A$1,$B63,I$5,$B$1) -> 0 | J63: =_xll.EQNXTDZ($A$1,$B63,J$5,$B$1) -> 0 | ... BV63: =_xll.EQNXTDZ($A$1,$B63,BV$5,$B$1) -> 0
A64: Other Long Term Liabilities | B64: QTRB_OTHER_LT_LIABILITIES | C64: =_xll.EQNXTDZ($A$1,$B64,C$5,$B$1) -> 0 | D64: =_xll.EQNXTDZ($A$1,$B64,D$5,$B$1) -> 0 | E64: =_xll.EQNXTDZ($A$1,$B64,E$5,$B$1) -> 0 | F64: =_xll.EQNXTDZ($A$1,$B64,F$5,$B$1) -> 0 | G64: =_xll.EQNXTDZ($A$1,$B64,G$5,$B$1) -> 0 | H64: =_xll.EQNXTDZ($A$1,$B64,H$5,$B$1) -> 0 | I64: =_xll.EQNXTDZ($A$1,$B64,I$5,$B$1) -> 0 | J64: =_xll.EQNXTDZ($A$1,$B64,J$5,$B$1) -> 0 | ... BV64: =_xll.EQNXTDZ($A$1,$B64,BV$5,$B$1) -> 0
A65: Long Term Trade Payables | B65: QTRB_LT_TRADE_PAYABLE | C65: =_xll.EQNXTDZ($A$1,$B65,C$5,$B$1) -> 0 | D65: =_xll.EQNXTDZ($A$1,$B65,D$5,$B$1) -> 0 | E65: =_xll.EQNXTDZ($A$1,$B65,E$5,$B$1) -> 0 | F65: =_xll.EQNXTDZ($A$1,$B65,F$5,$B$1) -> 0 | G65: =_xll.EQNXTDZ($A$1,$B65,G$5,$B$1) -> 0 | H65: =_xll.EQNXTDZ($A$1,$B65,H$5,$B$1) -> 0 | I65: =_xll.EQNXTDZ($A$1,$B65,I$5,$B$1) -> 0 | J65: =_xll.EQNXTDZ($A$1,$B65,J$5,$B$1) -> 0 | ... BV65: =_xll.EQNXTDZ($A$1,$B65,BV$5,$B$1) -> 0
A66: Lont Term Provisions | B66: QTRB_LT_PROVISIONS | C66: =_xll.EQNXTDZ($A$1,$B66,C$5,$B$1) -> 0 | D66: =_xll.EQNXTDZ($A$1,$B66,D$5,$B$1) -> 0 | E66: =_xll.EQNXTDZ($A$1,$B66,E$5,$B$1) -> 0 | F66: =_xll.EQNXTDZ($A$1,$B66,F$5,$B$1) -> 0 | G66: =_xll.EQNXTDZ($A$1,$B66,G$5,$B$1) -> 0 | H66: =_xll.EQNXTDZ($A$1,$B66,H$5,$B$1) -> 0 | I66: =_xll.EQNXTDZ($A$1,$B66,I$5,$B$1) -> 0 | J66: =_xll.EQNXTDZ($A$1,$B66,J$5,$B$1) -> 0 | ... BV66: =_xll.EQNXTDZ($A$1,$B66,BV$5,$B$1) -> 0
... A97: Total Assets | B97: QTRB_TOTAL_APPLICATIONS | C97: =_xll.EQNXTDZ($A$1,$B97,C$5,$B$1) -> 0 | D97: =_xll.EQNXTDZ($A$1,$B97,D$5,$B$1) -> 0 | E97: =_xll.EQNXTDZ($A$1,$B97,E$5,$B$1) -> 0 | F97: =_xll.EQNXTDZ($A$1,$B97,F$5,$B$1) -> 0 | G97: =_xll.EQNXTDZ($A$1,$B97,G$5,$B$1) -> 0 | H97: =_xll.EQNXTDZ($A$1,$B97,H$5,$B$1) -> 0 | I97: =_xll.EQNXTDZ($A$1,$B97,I$5,$B$1) -> 0 | J97: =_xll.EQNXTDZ($A$1,$B97,J$5,$B$1) -> 0 | ... BV97: =_xll.EQNXTDZ($A$1,$B97,BV$5,$B$1) -> 0

Sheet Annual Raw
A1: 271875 | B1: X | C1: 200103 | D1: 200203 | E1: 200303 | F1: 200403 | G1: 200503 | H1: 200603 | I1: 200703 | J1: 200803 | K1: 200903 | L1: 201003 | M1: 201103 | N1: 201203 | O1: 201303 | P1: 201403 | Q1: 201503 | R1: 201603 | S1: 201703 | T1: 201803 | U1: 201903 | V1: 202003 | W1: 202103 | X1: 202203 | Y1: 202303 | Z1: 202403 | AA1: 202503 | AB1: 202603 | AC1: 202703 | AD1: 202803 | AE1: 202903 | AF1: 203003
A3: Field Description | B3: Field Name
A4: Company Name | B4: CD_COMPNAME | C4: =_xll.EQNXTDZ(A1,B4,"L") -> Adani Energy Solutions Ltd.
A5: Year End | B5: PL_YEAR_END | C5: =_xll.EQNXTDZ($A$1,$B5,C$1,$B$1) -> 0 | D5: =_xll.EQNXTDZ($A$1,$B5,D$1,$B$1) -> 0 | E5: =_xll.EQNXTDZ($A$1,$B5,E$1,$B$1) -> 0 | F5: =_xll.EQNXTDZ($A$1,$B5,F$1,$B$1) -> 0 | G5: =_xll.EQNXTDZ($A$1,$B5,G$1,$B$1) -> 0 | H5: =_xll.EQNXTDZ($A$1,$B5,H$1,$B$1) -> 0 | I5: =_xll.EQNXTDZ($A$1,$B5,I$1,$B$1) -> 0 | J5: =_xll.EQNXTDZ($A$1,$B5,J$1,$B$1) -> 0 | ... AF5: =_xll.EQNXTDZ($A$1,$B5,AF$1,$B$1) -> 0
A6: Sales Turnover | B6: PL_TOTAL_GROSS_SALES | C6: =_xll.EQNXTDZ($A$1,$B6,C$1,$B$1) -> 0 | D6: =_xll.EQNXTDZ($A$1,$B6,D$1,$B$1) -> 0 | E6: =_xll.EQNXTDZ($A$1,$B6,E$1,$B$1) -> 0 | F6: =_xll.EQNXTDZ($A$1,$B6,F$1,$B$1) -> 0 | G6: =_xll.EQNXTDZ($A$1,$B6,G$1,$B$1) -> 0 | H6: =_xll.EQNXTDZ($A$1,$B6,H$1,$B$1) -> 0 | I6: =_xll.EQNXTDZ($A$1,$B6,I$1,$B$1) -> 0 | J6: =_xll.EQNXTDZ($A$1,$B6,J$1,$B$1) -> 0 | ... AF6: =_xll.EQNXTDZ($A$1,$B6,AF$1,$B$1) -> 0
A7: Less: Inter divisional transfers | B7: PL_INTER_DIV_TRF | C7: =_xll.EQNXTDZ($A$1,$B7,C$1,$B$1) -> 0 | D7: =_xll.EQNXTDZ($A$1,$B7,D$1,$B$1) -> 0 | E7: =_xll.EQNXTDZ($A$1,$B7,E$1,$B$1) -> 0 | F7: =_xll.EQNXTDZ($A$1,$B7,F$1,$B$1) -> 0 | G7: =_xll.EQNXTDZ($A$1,$B7,G$1,$B$1) -> 0 | H7: =_xll.EQNXTDZ($A$1,$B7,H$1,$B$1) -> 0 | I7: =_xll.EQNXTDZ($A$1,$B7,I$1,$B$1) -> 0 | J7: =_xll.EQNXTDZ($A$1,$B7,J$1,$B$1) -> 0 | ... AF7: =_xll.EQNXTDZ($A$1,$B7,AF$1,$B$1) -> 0
A8: Less: Sales Returns | B8: PL_SALES_RETURN | C8: =_xll.EQNXTDZ($A$1,$B8,C$1,$B$1) -> 0 | D8: =_xll.EQNXTDZ($A$1,$B8,D$1,$B$1) -> 0 | E8: =_xll.EQNXTDZ($A$1,$B8,E$1,$B$1) -> 0 | F8: =_xll.EQNXTDZ($A$1,$B8,F$1,$B$1) -> 0 | G8: =_xll.EQNXTDZ($A$1,$B8,G$1,$B$1) -> 0 | H8: =_xll.EQNXTDZ($A$1,$B8,H$1,$B$1) -> 0 | I8: =_xll.EQNXTDZ($A$1,$B8,I$1,$B$1) -> 0 | J8: =_xll.EQNXTDZ($A$1,$B8,J$1,$B$1) -> 0 | ... AF8: =_xll.EQNXTDZ($A$1,$B8,AF$1,$B$1) -> 0
A9: Less: Excise | B9: PL_EXCISE | C9: =_xll.EQNXTDZ($A$1,$B9,C$1,$B$1) -> 0 | D9: =_xll.EQNXTDZ($A$1,$B9,D$1,$B$1) -> 0 | E9: =_xll.EQNXTDZ($A$1,$B9,E$1,$B$1) -> 0 | F9: =_xll.EQNXTDZ($A$1,$B9,F$1,$B$1) -> 0 | G9: =_xll.EQNXTDZ($A$1,$B9,G$1,$B$1) -> 0 | H9: =_xll.EQNXTDZ($A$1,$B9,H$1,$B$1) -> 0 | I9: =_xll.EQNXTDZ($A$1,$B9,I$1,$B$1) -> 0 | J9: =_xll.EQNXTDZ($A$1,$B9,J$1,$B$1) -> 0 | ... AF9: =_xll.EQNXTDZ($A$1,$B9,AF$1,$B$1) -> 0
A10: Net Sales | B10: PL_NET_SALES | C10: =_xll.EQNXTDZ($A$1,$B10,C$1,$B$1) -> 0 | D10: =_xll.EQNXTDZ($A$1,$B10,D$1,$B$1) -> 0 | E10: =_xll.EQNXTDZ($A$1,$B10,E$1,$B$1) -> 0 | F10: =_xll.EQNXTDZ($A$1,$B10,F$1,$B$1) -> 0 | G10: =_xll.EQNXTDZ($A$1,$B10,G$1,$B$1) -> 0 | H10: =_xll.EQNXTDZ($A$1,$B10,H$1,$B$1) -> 0 | I10: =_xll.EQNXTDZ($A$1,$B10,I$1,$B$1) -> 0 | J10: =_xll.EQNXTDZ($A$1,$B10,J$1,$B$1) -> 0 | ... AF10: =_xll.EQNXTDZ($A$1,$B10,AF$1,$B$1) -> 0
A11: Increase/Decrease in Stock | B11: PL_INC_DEC_INVENTORY | C11: =_xll.EQNXTDZ($A$1,$B11,C$1,$B$1) -> 0 | D11: =_xll.EQNXTDZ($A$1,$B11,D$1,$B$1) -> 0 | E11: =_xll.EQNXTDZ($A$1,$B11,E$1,$B$1) -> 0 | F11: =_xll.EQNXTDZ($A$1,$B11,F$1,$B$1) -> 0 | G11: =_xll.EQNXTDZ($A$1,$B11,G$1,$B$1) -> 0 | H11: =_xll.EQNXTDZ($A$1,$B11,H$1,$B$1) -> 0 | I11: =_xll.EQNXTDZ($A$1,$B11,I$1,$B$1) -> 0 | J11: =_xll.EQNXTDZ($A$1,$B11,J$1,$B$1) -> 0 | ... AF11: =_xll.EQNXTDZ($A$1,$B11,AF$1,$B$1) -> 0
A12: Raw Material Consumed | B12: PL_RAW_MATRS_CONSUMED | C12: =_xll.EQNXTDZ($A$1,$B12,C$1,$B$1) -> 0 | D12: =_xll.EQNXTDZ($A$1,$B12,D$1,$B$1) -> 0 | E12: =_xll.EQNXTDZ($A$1,$B12,E$1,$B$1) -> 0 | F12: =_xll.EQNXTDZ($A$1,$B12,F$1,$B$1) -> 0 | G12: =_xll.EQNXTDZ($A$1,$B12,G$1,$B$1) -> 0 | H12: =_xll.EQNXTDZ($A$1,$B12,H$1,$B$1) -> 0 | I12: =_xll.EQNXTDZ($A$1,$B12,I$1,$B$1) -> 0 | J12: =_xll.EQNXTDZ($A$1,$B12,J$1,$B$1) -> 0 | ... AF12: =_xll.EQNXTDZ($A$1,$B12,AF$1,$B$1) -> 0
A13: Power & Fuel Cost | B13: PL_POWER_FUEL | C13: =_xll.EQNXTDZ($A$1,$B13,C$1,$B$1) -> 0 | D13: =_xll.EQNXTDZ($A$1,$B13,D$1,$B$1) -> 0 | E13: =_xll.EQNXTDZ($A$1,$B13,E$1,$B$1) -> 0 | F13: =_xll.EQNXTDZ($A$1,$B13,F$1,$B$1) -> 0 | G13: =_xll.EQNXTDZ($A$1,$B13,G$1,$B$1) -> 0 | H13: =_xll.EQNXTDZ($A$1,$B13,H$1,$B$1) -> 0 | I13: =_xll.EQNXTDZ($A$1,$B13,I$1,$B$1) -> 0 | J13: =_xll.EQNXTDZ($A$1,$B13,J$1,$B$1) -> 0 | ... AF13: =_xll.EQNXTDZ($A$1,$B13,AF$1,$B$1) -> 0
A14: Employee Cost | B14: PL_EMPLOYEES | C14: =_xll.EQNXTDZ($A$1,$B14,C$1,$B$1) -> 0 | D14: =_xll.EQNXTDZ($A$1,$B14,D$1,$B$1) -> 0 | E14: =_xll.EQNXTDZ($A$1,$B14,E$1,$B$1) -> 0 | F14: =_xll.EQNXTDZ($A$1,$B14,F$1,$B$1) -> 0 | G14: =_xll.EQNXTDZ($A$1,$B14,G$1,$B$1) -> 0 | H14: =_xll.EQNXTDZ($A$1,$B14,H$1,$B$1) -> 0 | I14: =_xll.EQNXTDZ($A$1,$B14,I$1,$B$1) -> 0 | J14: =_xll.EQNXTDZ($A$1,$B14,J$1,$B$1) -> 0 | ... AF14: =_xll.EQNXTDZ($A$1,$B14,AF$1,$B$1) -> 0
A15: Operating & Manufacturing Expenses | B15: PL_GEN_OTHER_MFG_EXPS | C15: =_xll.EQNXTDZ($A$1,$B15,C$1,$B$1) -> 0 | D15: =_xll.EQNXTDZ($A$1,$B15,D$1,$B$1) -> 0 | E15: =_xll.EQNXTDZ($A$1,$B15,E$1,$B$1) -> 0 | F15: =_xll.EQNXTDZ($A$1,$B15,F$1,$B$1) -> 0 | G15: =_xll.EQNXTDZ($A$1,$B15,G$1,$B$1) -> 0 | H15: =_xll.EQNXTDZ($A$1,$B15,H$1,$B$1) -> 0 | I15: =_xll.EQNXTDZ($A$1,$B15,I$1,$B$1) -> 0 | J15: =_xll.EQNXTDZ($A$1,$B15,J$1,$B$1) -> 0 | ... AF15: =_xll.EQNXTDZ($A$1,$B15,AF$1,$B$1) -> 0
A16: Cost of Software development | B16: PL_COST_SW | C16: =_xll.EQNXTDZ($A$1,$B16,C$1,$B$1) -> 0 | D16: =_xll.EQNXTDZ($A$1,$B16,D$1,$B$1) -> 0 | E16: =_xll.EQNXTDZ($A$1,$B16,E$1,$B$1) -> 0 | F16: =_xll.EQNXTDZ($A$1,$B16,F$1,$B$1) -> 0 | G16: =_xll.EQNXTDZ($A$1,$B16,G$1,$B$1) -> 0 | H16: =_xll.EQNXTDZ($A$1,$B16,H$1,$B$1) -> 0 | I16: =_xll.EQNXTDZ($A$1,$B16,I$1,$B$1) -> 0 | J16: =_xll.EQNXTDZ($A$1,$B16,J$1,$B$1) -> 0 | ... AF16: =_xll.EQNXTDZ($A$1,$B16,AF$1,$B$1) -> 0
... A36: Profit After Tax from Discontinued Operations | B36: PL_PAT_DIS_OP | C36: =_xll.EQNXTDZ($A$1,$B36,C$1,$B$1) -> 0 | D36: =_xll.EQNXTDZ($A$1,$B36,D$1,$B$1) -> 0 | E36: =_xll.EQNXTDZ($A$1,$B36,E$1,$B$1) -> 0 | F36: =_xll.EQNXTDZ($A$1,$B36,F$1,$B$1) -> 0 | G36: =_xll.EQNXTDZ($A$1,$B36,G$1,$B$1) -> 0 | H36: =_xll.EQNXTDZ($A$1,$B36,H$1,$B$1) -> 0 | I36: =_xll.EQNXTDZ($A$1,$B36,I$1,$B$1) -> 0 | J36: =_xll.EQNXTDZ($A$1,$B36,J$1,$B$1) -> 0 | ... AF36: =_xll.EQNXTDZ($A$1,$B36,AF$1,$B$1) -> 0
A39: Field Description | B39: Field Name
A40: Year End | B40: BS_YEAR_END | C40: =_xll.EQNXTDZ($A$1,$B40,C$1,$B$1) -> 0 | D40: =_xll.EQNXTDZ($A$1,$B40,D$1,$B$1) -> 0 | E40: =_xll.EQNXTDZ($A$1,$B40,E$1,$B$1) -> 0 | F40: =_xll.EQNXTDZ($A$1,$B40,F$1,$B$1) -> 0 | G40: =_xll.EQNXTDZ($A$1,$B40,G$1,$B$1) -> 0 | H40: =_xll.EQNXTDZ($A$1,$B40,H$1,$B$1) -> 0 | I40: =_xll.EQNXTDZ($A$1,$B40,I$1,$B$1) -> 0 | J40: =_xll.EQNXTDZ($A$1,$B40,J$1,$B$1) -> 0 | ... AF40: =_xll.EQNXTDZ($A$1,$B40,AF$1,$B$1) -> 0
A41: Share Capital | B41: BS_SHARE_CAPITAL | C41: =_xll.EQNXTDZ($A$1,$B41,C$1,$B$1) -> 0 | D41: =_xll.EQNXTDZ($A$1,$B41,D$1,$B$1) -> 0 | E41: =_xll.EQNXTDZ($A$1,$B41,E$1,$B$1) -> 0 | F41: =_xll.EQNXTDZ($A$1,$B41,F$1,$B$1) -> 0 | G41: =_xll.EQNXTDZ($A$1,$B41,G$1,$B$1) -> 0 | H41: =_xll.EQNXTDZ($A$1,$B41,H$1,$B$1) -> 0 | I41: =_xll.EQNXTDZ($A$1,$B41,I$1,$B$1) -> 0 | J41: =_xll.EQNXTDZ($A$1,$B41,J$1,$B$1) -> 0 | ... AF41: =_xll.EQNXTDZ($A$1,$B41,AF$1,$B$1) -> 0
A42: Share Warrants & Outstandings | B42: BS_SHAREWROUTST | C42: =_xll.EQNXTDZ($A$1,$B42,C$1,$B$1) -> 0 | D42: =_xll.EQNXTDZ($A$1,$B42,D$1,$B$1) -> 0 | E42: =_xll.EQNXTDZ($A$1,$B42,E$1,$B$1) -> 0 | F42: =_xll.EQNXTDZ($A$1,$B42,F$1,$B$1) -> 0 | G42: =_xll.EQNXTDZ($A$1,$B42,G$1,$B$1) -> 0 | H42: =_xll.EQNXTDZ($A$1,$B42,H$1,$B$1) -> 0 | I42: =_xll.EQNXTDZ($A$1,$B42,I$1,$B$1) -> 0 | J42: =_xll.EQNXTDZ($A$1,$B42,J$1,$B$1) -> 0 | ... AF42: =_xll.EQNXTDZ($A$1,$B42,AF$1,$B$1) -> 0
A43: Total Reserves | B43: BS_RESERVE | C43: =_xll.EQNXTDZ($A$1,$B43,C$1,$B$1) -> 0 | D43: =_xll.EQNXTDZ($A$1,$B43,D$1,$B$1) -> 0 | E43: =_xll.EQNXTDZ($A$1,$B43,E$1,$B$1) -> 0 | F43: =_xll.EQNXTDZ($A$1,$B43,F$1,$B$1) -> 0 | G43: =_xll.EQNXTDZ($A$1,$B43,G$1,$B$1) -> 0 | H43: =_xll.EQNXTDZ($A$1,$B43,H$1,$B$1) -> 0 | I43: =_xll.EQNXTDZ($A$1,$B43,I$1,$B$1) -> 0 | J43: =_xll.EQNXTDZ($A$1,$B43,J$1,$B$1) -> 0 | ... AF43: =_xll.EQNXTDZ($A$1,$B43,AF$1,$B$1) -> 0
A44: Shareholder's Funds | B44: BS_SHAREHODERS_FUNDS | C44: =_xll.EQNXTDZ($A$1,$B44,C$1,$B$1) -> 0 | D44: =_xll.EQNXTDZ($A$1,$B44,D$1,$B$1) -> 0 | E44: =_xll.EQNXTDZ($A$1,$B44,E$1,$B$1) -> 0 | F44: =_xll.EQNXTDZ($A$1,$B44,F$1,$B$1) -> 0 | G44: =_xll.EQNXTDZ($A$1,$B44,G$1,$B$1) -> 0 | H44: =_xll.EQNXTDZ($A$1,$B44,H$1,$B$1) -> 0 | I44: =_xll.EQNXTDZ($A$1,$B44,I$1,$B$1) -> 0 | J44: =_xll.EQNXTDZ($A$1,$B44,J$1,$B$1) -> 0 | ... AF44: =_xll.EQNXTDZ($A$1,$B44,AF$1,$B$1) -> 0
A45: Minority Interest | B45: BS_MINORITY_INTEREST | C45: =_xll.EQNXTDZ($A$1,$B45,C$1,$B$1) -> 0 | D45: =_xll.EQNXTDZ($A$1,$B45,D$1,$B$1) -> 0 | E45: =_xll.EQNXTDZ($A$1,$B45,E$1,$B$1) -> 0 | F45: =_xll.EQNXTDZ($A$1,$B45,F$1,$B$1) -> 0 | G45: =_xll.EQNXTDZ($A$1,$B45,G$1,$B$1) -> 0 | H45: =_xll.EQNXTDZ($A$1,$B45,H$1,$B$1) -> 0 | I45: =_xll.EQNXTDZ($A$1,$B45,I$1,$B$1) -> 0 | J45: =_xll.EQNXTDZ($A$1,$B45,J$1,$B$1) -> 0 | ... AF45: =_xll.EQNXTDZ($A$1,$B45,AF$1,$B$1) -> 0
A46: Long-Term Borrowings | B46: BS_LTRM_BORROWING | C46: =_xll.EQNXTDZ($A$1,$B46,C$1,$B$1) -> 0 | D46: =_xll.EQNXTDZ($A$1,$B46,D$1,$B$1) -> 0 | E46: =_xll.EQNXTDZ($A$1,$B46,E$1,$B$1) -> 0 | F46: =_xll.EQNXTDZ($A$1,$B46,F$1,$B$1) -> 0 | G46: =_xll.EQNXTDZ($A$1,$B46,G$1,$B$1) -> 0 | H46: =_xll.EQNXTDZ($A$1,$B46,H$1,$B$1) -> 0 | I46: =_xll.EQNXTDZ($A$1,$B46,I$1,$B$1) -> 0 | J46: =_xll.EQNXTDZ($A$1,$B46,J$1,$B$1) -> 0 | ... AF46: =_xll.EQNXTDZ($A$1,$B46,AF$1,$B$1) -> 0
A47: Secured Loans | B47: BS_SECURED_LOANS | C47: =_xll.EQNXTDZ($A$1,$B47,C$1,$B$1) -> 0 | D47: =_xll.EQNXTDZ($A$1,$B47,D$1,$B$1) -> 0 | E47: =_xll.EQNXTDZ($A$1,$B47,E$1,$B$1) -> 0 | F47: =_xll.EQNXTDZ($A$1,$B47,F$1,$B$1) -> 0 | G47: =_xll.EQNXTDZ($A$1,$B47,G$1,$B$1) -> 0 | H47: =_xll.EQNXTDZ($A$1,$B47,H$1,$B$1) -> 0 | I47: =_xll.EQNXTDZ($A$1,$B47,I$1,$B$1) -> 0 | J47: =_xll.EQNXTDZ($A$1,$B47,J$1,$B$1) -> 0 | ... AF47: =_xll.EQNXTDZ($A$1,$B47,AF$1,$B$1) -> 0
A48: Unsecured Loans | B48: BS_UNSECURED_LOANS_NF | C48: =_xll.EQNXTDZ($A$1,$B48,C$1,$B$1) -> 0 | D48: =_xll.EQNXTDZ($A$1,$B48,D$1,$B$1) -> 0 | E48: =_xll.EQNXTDZ($A$1,$B48,E$1,$B$1) -> 0 | F48: =_xll.EQNXTDZ($A$1,$B48,F$1,$B$1) -> 0 | G48: =_xll.EQNXTDZ($A$1,$B48,G$1,$B$1) -> 0 | H48: =_xll.EQNXTDZ($A$1,$B48,H$1,$B$1) -> 0 | I48: =_xll.EQNXTDZ($A$1,$B48,I$1,$B$1) -> 0 | J48: =_xll.EQNXTDZ($A$1,$B48,J$1,$B$1) -> 0 | ... AF48: =_xll.EQNXTDZ($A$1,$B48,AF$1,$B$1) -> 0
A49: Deferred Tax Assets / Liabilities | B49: BS_NET_DEF_TAX_NF | C49: =_xll.EQNXTDZ($A$1,$B49,C$1,$B$1) -> 0 | D49: =_xll.EQNXTDZ($A$1,$B49,D$1,$B$1) -> 0 | E49: =_xll.EQNXTDZ($A$1,$B49,E$1,$B$1) -> 0 | F49: =_xll.EQNXTDZ($A$1,$B49,F$1,$B$1) -> 0 | G49: =_xll.EQNXTDZ($A$1,$B49,G$1,$B$1) -> 0 | H49: =_xll.EQNXTDZ($A$1,$B49,H$1,$B$1) -> 0 | I49: =_xll.EQNXTDZ($A$1,$B49,I$1,$B$1) -> 0 | J49: =_xll.EQNXTDZ($A$1,$B49,J$1,$B$1) -> 0 | ... AF49: =_xll.EQNXTDZ($A$1,$B49,AF$1,$B$1) -> 0
A50: Other Long Term Liabilities | B50: BS_OTH_LT_LIAB | C50: =_xll.EQNXTDZ($A$1,$B50,C$1,$B$1) -> 0 | D50: =_xll.EQNXTDZ($A$1,$B50,D$1,$B$1) -> 0 | E50: =_xll.EQNXTDZ($A$1,$B50,E$1,$B$1) -> 0 | F50: =_xll.EQNXTDZ($A$1,$B50,F$1,$B$1) -> 0 | G50: =_xll.EQNXTDZ($A$1,$B50,G$1,$B$1) -> 0 | H50: =_xll.EQNXTDZ($A$1,$B50,H$1,$B$1) -> 0 | I50: =_xll.EQNXTDZ($A$1,$B50,I$1,$B$1) -> 0 | J50: =_xll.EQNXTDZ($A$1,$B50,J$1,$B$1) -> 0 | ... AF50: =_xll.EQNXTDZ($A$1,$B50,AF$1,$B$1) -> 0
A51: Long Term Trade Payables | B51: BS_LT_TRADE_PAYABLES | C51: =_xll.EQNXTDZ($A$1,$B51,C$1,$B$1) -> 0 | D51: =_xll.EQNXTDZ($A$1,$B51,D$1,$B$1) -> 0 | E51: =_xll.EQNXTDZ($A$1,$B51,E$1,$B$1) -> 0 | F51: =_xll.EQNXTDZ($A$1,$B51,F$1,$B$1) -> 0 | G51: =_xll.EQNXTDZ($A$1,$B51,G$1,$B$1) -> 0 | H51: =_xll.EQNXTDZ($A$1,$B51,H$1,$B$1) -> 0 | I51: =_xll.EQNXTDZ($A$1,$B51,I$1,$B$1) -> 0 | J51: =_xll.EQNXTDZ($A$1,$B51,J$1,$B$1) -> 0 | ... AF51: =_xll.EQNXTDZ($A$1,$B51,AF$1,$B$1) -> 0
... A99: Estimated Capital Contracts Remaining | B99: BS_ESTIMATED_CAPITAL_CONTRACT | C99: =_xll.EQNXTDZ($A$1,$B99,C$1,$B$1) -> 0 | D99: =_xll.EQNXTDZ($A$1,$B99,D$1,$B$1) -> 0 | E99: =_xll.EQNXTDZ($A$1,$B99,E$1,$B$1) -> 0 | F99: =_xll.EQNXTDZ($A$1,$B99,F$1,$B$1) -> 0 | G99: =_xll.EQNXTDZ($A$1,$B99,G$1,$B$1) -> 0 | H99: =_xll.EQNXTDZ($A$1,$B99,H$1,$B$1) -> 0 | I99: =_xll.EQNXTDZ($A$1,$B99,I$1,$B$1) -> 0 | J99: =_xll.EQNXTDZ($A$1,$B99,J$1,$B$1) -> 0 | ... AF99: =_xll.EQNXTDZ($A$1,$B99,AF$1,$B$1) -> 0
A103: Field Description | B103: Field Name
A104: Equity Paid Up | B104: BS_EQUITY_PAIDUP | C104: =_xll.EQNXTDZ($A$1,$B104,C$1,$B$1) -> 0 | D104: =_xll.EQNXTDZ($A$1,$B104,D$1,$B$1) -> 0 | E104: =_xll.EQNXTDZ($A$1,$B104,E$1,$B$1) -> 0 | F104: =_xll.EQNXTDZ($A$1,$B104,F$1,$B$1) -> 0 | G104: =_xll.EQNXTDZ($A$1,$B104,G$1,$B$1) -> 0 | H104: =_xll.EQNXTDZ($A$1,$B104,H$1,$B$1) -> 0 | I104: =_xll.EQNXTDZ($A$1,$B104,I$1,$B$1) -> 0 | J104: =_xll.EQNXTDZ($A$1,$B104,J$1,$B$1) -> 0 | ... AF104: =_xll.EQNXTDZ($A$1,$B104,AF$1,$B$1) -> 0
A105: Face Value | B105: BS_FACE_VALUE | C105: =_xll.EQNXTDZ($A$1,$B105,C$1,$B$1) -> 0 | D105: =_xll.EQNXTDZ($A$1,$B105,D$1,$B$1) -> 0 | E105: =_xll.EQNXTDZ($A$1,$B105,E$1,$B$1) -> 0 | F105: =_xll.EQNXTDZ($A$1,$B105,F$1,$B$1) -> 0 | G105: =_xll.EQNXTDZ($A$1,$B105,G$1,$B$1) -> 0 | H105: =_xll.EQNXTDZ($A$1,$B105,H$1,$B$1) -> 0 | I105: =_xll.EQNXTDZ($A$1,$B105,I$1,$B$1) -> 0 | J105: =_xll.EQNXTDZ($A$1,$B105,J$1,$B$1) -> 0 | ... AF105: =_xll.EQNXTDZ($A$1,$B105,AF$1,$B$1) -> 0
A106: Close Price (Unit Curr.) | B106: FH_YEAR_PRICE | C106: =_xll.EQNXTDZ($A$1,$B106,C$1,$B$1) -> 0 | D106: =_xll.EQNXTDZ($A$1,$B106,D$1,$B$1) -> 0 | E106: =_xll.EQNXTDZ($A$1,$B106,E$1,$B$1) -> 0 | F106: =_xll.EQNXTDZ($A$1,$B106,F$1,$B$1) -> 0 | G106: =_xll.EQNXTDZ($A$1,$B106,G$1,$B$1) -> 0 | H106: =_xll.EQNXTDZ($A$1,$B106,H$1,$B$1) -> 0 | I106: =_xll.EQNXTDZ($A$1,$B106,I$1,$B$1) -> 0 | J106: =_xll.EQNXTDZ($A$1,$B106,J$1,$B$1) -> 0 | ... AF106: =_xll.EQNXTDZ($A$1,$B106,AF$1,$B$1) -> 0
A107: High Price (Unit Curr.) | B107: FH_HIGH | C107: =_xll.EQNXTDZ($A$1,$B107,C$1,$B$1) -> 0 | D107: =_xll.EQNXTDZ($A$1,$B107,D$1,$B$1) -> 0 | E107: =_xll.EQNXTDZ($A$1,$B107,E$1,$B$1) -> 0 | F107: =_xll.EQNXTDZ($A$1,$B107,F$1,$B$1) -> 0 | G107: =_xll.EQNXTDZ($A$1,$B107,G$1,$B$1) -> 0 | H107: =_xll.EQNXTDZ($A$1,$B107,H$1,$B$1) -> 0 | I107: =_xll.EQNXTDZ($A$1,$B107,I$1,$B$1) -> 0 | J107: =_xll.EQNXTDZ($A$1,$B107,J$1,$B$1) -> 0 | ... AF107: =_xll.EQNXTDZ($A$1,$B107,AF$1,$B$1) -> 0
A108: Low Price (Unit Curr.) | B108: FH_LOW | C108: =_xll.EQNXTDZ($A$1,$B108,C$1,$B$1) -> 0 | D108: =_xll.EQNXTDZ($A$1,$B108,D$1,$B$1) -> 0 | E108: =_xll.EQNXTDZ($A$1,$B108,E$1,$B$1) -> 0 | F108: =_xll.EQNXTDZ($A$1,$B108,F$1,$B$1) -> 0 | G108: =_xll.EQNXTDZ($A$1,$B108,G$1,$B$1) -> 0 | H108: =_xll.EQNXTDZ($A$1,$B108,H$1,$B$1) -> 0 | I108: =_xll.EQNXTDZ($A$1,$B108,I$1,$B$1) -> 0 | J108: =_xll.EQNXTDZ($A$1,$B108,J$1,$B$1) -> 0 | ... AF108: =_xll.EQNXTDZ($A$1,$B108,AF$1,$B$1) -> 0
A109: Market Capitalization | B109: FH_MCAP | C109: =_xll.EQNXTDZ($A$1,$B109,C$1,$B$1) -> 0 | D109: =_xll.EQNXTDZ($A$1,$B109,D$1,$B$1) -> 0 | E109: =_xll.EQNXTDZ($A$1,$B109,E$1,$B$1) -> 0 | F109: =_xll.EQNXTDZ($A$1,$B109,F$1,$B$1) -> 0 | G109: =_xll.EQNXTDZ($A$1,$B109,G$1,$B$1) -> 0 | H109: =_xll.EQNXTDZ($A$1,$B109,H$1,$B$1) -> 0 | I109: =_xll.EQNXTDZ($A$1,$B109,I$1,$B$1) -> 0 | J109: =_xll.EQNXTDZ($A$1,$B109,J$1,$B$1) -> 0 | ... AF109: =_xll.EQNXTDZ($A$1,$B109,AF$1,$B$1) -> 0
A110: Adj DPS(Rs) | B110: FR_ADJ_DPS | C110: =_xll.EQNXTDZ($A$1,$B110,C$1,$B$1) -> 0 | D110: =_xll.EQNXTDZ($A$1,$B110,D$1,$B$1) -> 0 | E110: =_xll.EQNXTDZ($A$1,$B110,E$1,$B$1) -> 0 | F110: =_xll.EQNXTDZ($A$1,$B110,F$1,$B$1) -> 0 | G110: =_xll.EQNXTDZ($A$1,$B110,G$1,$B$1) -> 0 | H110: =_xll.EQNXTDZ($A$1,$B110,H$1,$B$1) -> 0 | I110: =_xll.EQNXTDZ($A$1,$B110,I$1,$B$1) -> 0 | J110: =_xll.EQNXTDZ($A$1,$B110,J$1,$B$1) -> 0 | ... AF110: =_xll.EQNXTDZ($A$1,$B110,AF$1,$B$1) -> 0
A111: Date End | B111: SHP_DATE_END | C111: =_xll.EQNXTDZ($A$1,$B111,C$5) -> 0 | D111: =_xll.EQNXTDZ($A$1,$B111,D$5) -> 0 | E111: =_xll.EQNXTDZ($A$1,$B111,E$5) -> 0 | F111: =_xll.EQNXTDZ($A$1,$B111,F$5) -> 0 | G111: =_xll.EQNXTDZ($A$1,$B111,G$5) -> 0 | H111: =_xll.EQNXTDZ($A$1,$B111,H$5) -> 0 | I111: =_xll.EQNXTDZ($A$1,$B111,I$5) -> 0 | J111: =_xll.EQNXTDZ($A$1,$B111,J$5) -> 0 | ... AF111: =_xll.EQNXTDZ($A$1,$B111,AF$5) -> 0
A112: Total of Promoter and Promoter Group | B112: SHP_TPFTOTALPROMOTER | C112: =_xll.EQNXTDZ($A$1,$B112,C$5) -> 0 | D112: =_xll.EQNXTDZ($A$1,$B112,D$5) -> 0 | E112: =_xll.EQNXTDZ($A$1,$B112,E$5) -> 0 | F112: =_xll.EQNXTDZ($A$1,$B112,F$5) -> 0 | G112: =_xll.EQNXTDZ($A$1,$B112,G$5) -> 0 | H112: =_xll.EQNXTDZ($A$1,$B112,H$5) -> 0 | I112: =_xll.EQNXTDZ($A$1,$B112,I$5) -> 0 | J112: =_xll.EQNXTDZ($A$1,$B112,J$5) -> 0 | ... AF112: =_xll.EQNXTDZ($A$1,$B112,AF$5) -> 0
A113: Total of Promoter and Promoter Group Pledged | B113: SHP_PSHFTOTALPROMOTER | C113: =_xll.EQNXTDZ($A$1,$B113,C$5) -> 0 | D113: =_xll.EQNXTDZ($A$1,$B113,D$5) -> 0 | E113: =_xll.EQNXTDZ($A$1,$B113,E$5) -> 0 | F113: =_xll.EQNXTDZ($A$1,$B113,F$5) -> 0 | G113: =_xll.EQNXTDZ($A$1,$B113,G$5) -> 0 | H113: =_xll.EQNXTDZ($A$1,$B113,H$5) -> 0 | I113: =_xll.EQNXTDZ($A$1,$B113,I$5) -> 0 | J113: =_xll.EQNXTDZ($A$1,$B113,J$5) -> 0 | ... AF113: =_xll.EQNXTDZ($A$1,$B113,AF$5) -> 0

Sheet QTR Share Price
A1: ='QTR Raw'!A1 -> 271875 | C1: 201206 | D1: 201207 | E1: 201208 | F1: 201209 | G1: 201210 | H1: 201211 | I1: 201212 | J1: 201301 | K1: 201302 | L1: 201303 | M1: 201304 | N1: 201305 | O1: 201306 | P1: 201307 | Q1: 201308 | R1: 201309 | S1: 201310 | T1: 201311 | U1: 201312 | V1: 201401 | W1: 201402 | X1: 201403 | Y1: 201404 | Z1: 201405 | AA1: 201406 | AB1: 201407 | AC1: 201408 | AD1: 201409 | AE1: 201410 | AF1: 201411 | AG1: 201412 | AH1: 201501 | AI1: 201502 | AJ1: 201503 | AK1: 201504 | AL1: 201505 | AM1: 201506 | AN1: 201507 | AO1: 201508 | AP1: 201509 | AQ1: 201510 | AR1: 201511 | AS1: 201512 | AT1: 201601 | AU1: 201602 | AV1: 201603 | AW1: 201604 | AX1: 201605 | AY1: 201606 | AZ1: 201607 | BA1: 201608 | BB1: 201609 | BC1: 201610 | BD1: 201611 | BE1: 201612 | BF1: 201701 | BG1: 201702 | BH1: 201703 | BI1: 201704 | BJ1: 201705 | BK1: 201706 | BL1: 201707 | BM1: 201708 | BN1: 201709 | BO1: 201710 | BP1: 201711 | BQ1: 201712 | BR1: 201801 | BS1: 201802 | BT1: 201803 | BU1: 201804 | BV1: 201805 | BW1: 201806 | BX1: 201807 | BY1: 201808 | BZ1: 201809 | CA1: 201810 | CB1: 201811 | CC1: 201812 | CD1: 201901 | CE1: 201902 | CF1: 201903 | CG1: 201904 | CH1: 201905 | CI1: 201906 | CJ1: 201907 | CK1: 201908 | CL1: 201909 | CM1: 201910 | CN1: 201911 | CO1: 201912 | CP1: 202001 | CQ1: 202002 | CR1: 202003 | CS1: 202004 | CT1: 202005 | CU1: 202006 | CV1: 202007 | CW1: 202008 | CX1: 202009 | CY1: 202010 | CZ1: 202011 | DA1: 202012 | DB1: 202101 | DC1: 202102 | DD1: 202103 | DE1: 202104 | DF1: 202105 | DG1: 202106 | DH1: 202107 | DI1: 202108 | DJ1: 202109 | DK1: 202110 | DL1: 202111 | DM1: 202112 | DN1: 202201 | DO1: 202202 | DP1: 202203 | DQ1: 202204 | DR1: 202205 | DS1: 202206 | DT1: 202207 | DU1: 202208 | DV1: 202209 | DW1: 202210 | DX1: 202211 | DY1: 202212 | DZ1: 202301 | EA1: 202302 | EB1: 202303 | EC1: 202304 | ED1: 202305 | EE1: 202306 | EF1: 202307 | EG1: 202308 | EH1: 202309 | EI1: 202310 | EJ1: 202311 | EK1: 202312 | EL1: 202401 | EM1: 202402 | EN1: 202403 | EO1: 202404 | EP1: 202405 | EQ1: 202406 | ER1: 202407 | ES1: 202408 | ET1: 202409 | EU1: 202410 | EV1: 202411 | EW1: 202412 | EX1: 202501 | EY1: 202502 | EZ1: 202503 | FA1: 202504 | FB1: 202505 | FC1: 202506 | FD1: 202507 | FE1: 202508 | FF1: 202509 | FG1: 202510 | FH1: 202511 | FI1: 202512 | FJ1: 202601 | FK1: 202602 | FL1: 202603 | FM1: 202604 | FN1: 202605 | FO1: 202606 | FP1: 202607 | FQ1: 202608 | FR1: 202609 | FS1: 202610 | FT1: 202611 | FU1: 202612 | FV1: 202701 | FW1: 202702 | FX1: 202703 | FY1: 202704 | FZ1: 202705 | GA1: 202706 | GB1: 202707 | GC1: 202708 | GD1: 202709 | GE1: 202710 | GF1: 202711 | GG1: 202712 | GH1: 202801 | GI1: 202802 | GJ1: 202803 | GK1: 202804 | GL1: 202805 | GM1: 202806 | GN1: 202807 | GO1: 202808 | GP1: 202809 | GQ1: 202810 | GR1: 202811 | GS1: 202812 | GT1: 202901 | GU1: 202902 | GV1: 202903 | GW1: 202904 | GX1: 202905 | GY1: 202906 | GZ1: 202907 | HA1: 202908 | HB1: 202909 | HC1: 202910 | HD1: 202911 | HE1: 202912 | HF1: 203001 | HG1: 203002 | HH1: 203003 | HM1: 201206 | HN1: 201207 | HO1: 201208 | HP1: 201209 | HQ1: 201212 | HR1: 201303 | HS1: 201306 | HT1: 201309 | HU1: 201312 | HV1: 201403 | HW1: 201406 | HX1: 201409 | HY1: 201412 | HZ1: 201503 | IA1: 201506 | IB1: 201509 | IC1: 201512 | ID1: 201603 | IE1: 201606 | IF1: 201609 | IG1: 201612 | IH1: 201703 | II1: 201706 | IJ1: 201709 | IK1: 201712 | IL1: 201803 | IM1: 201806 | IN1: 201809 | IO1: 201812 | IP1: 201903 | IQ1: 201906 | IR1: 201909 | IS1: 201912 | IT1: 202003 | IU1: 202006 | IV1: 202009 | IW1: 202012 | IX1: 202103 | IY1: 202106 | IZ1: 202109 | JA1: 202112 | JB1: 202203 | JC1: 202206 | JD1: 202209 | JE1: 202212 | JF1: 202303 | JG1: 202306 | JH1: 202309 | JI1: 202312 | JJ1: 202403 | JK1: 202406 | JL1: 202409 | JM1: 202412 | JN1: 202503 | JO1: 202506 | JP1: 202509 | JQ1: 202512 | JR1: 202603 | JS1: 202606 | JT1: 202609 | JU1: 202612 | JV1: 202703 | JW1: 202706 | JX1: 202709 | JY1: 202712 | JZ1: 202803 | KA1: 202806 | KB1: 202809 | KC1: 202812 | KD1: 202903 | KE1: 202906 | KF1: 202909 | KG1: 202912 | KH1: 203003
FF2: 45901 | FG2: =+EOMONTH(FF2,1) -> 45961 | FH2: =+EOMONTH(FG2,1) -> 45991 | FI2: =+EOMONTH(FH2,1) -> 46022 | FJ2: =+EOMONTH(FI2,1) -> 46053 | FK2: =+EOMONTH(FJ2,1) -> 46081 | FL2: =+EOMONTH(FK2,1) -> 46112 | FM2: =+EOMONTH(FL2,1) -> 46142 | FN2: =+EOMONTH(FM2,1) -> 46173 | ... HH2: =+EOMONTH(HG2,1) -> 47573
A4: Field Description | B4: Field Name
A5: MonthEnd | B5: NMONTH_MONTHEND | C5: {=_xll.EQNXTDZ($A$1,$B5,C$1)} -> 0 | D5: {=_xll.EQNXTDZ($A$1,$B5,D$1)} -> 0 | E5: {=_xll.EQNXTDZ($A$1,$B5,E$1)} -> 0 | F5: {=_xll.EQNXTDZ($A$1,$B5,F$1)} -> 0 | G5: {=_xll.EQNXTDZ($A$1,$B5,G$1)} -> 0 | H5: {=_xll.EQNXTDZ($A$1,$B5,H$1)} -> 0 | I5: {=_xll.EQNXTDZ($A$1,$B5,I$1)} -> 0 | J5: {=_xll.EQNXTDZ($A$1,$B5,J$1)} -> 0 | ... HH5: {=_xll.EQNXTDZ($A$1,$B5,HH$1)} -> 0
A6: Open | B6: NMONTH_OPEN | C6: {=_xll.EQNXTDZ($A$1,$B6,C$1)} -> 0 | D6: {=_xll.EQNXTDZ($A$1,$B6,D$1)} -> 0 | E6: {=_xll.EQNXTDZ($A$1,$B6,E$1)} -> 0 | F6: {=_xll.EQNXTDZ($A$1,$B6,F$1)} -> 0 | G6: {=_xll.EQNXTDZ($A$1,$B6,G$1)} -> 0 | H6: {=_xll.EQNXTDZ($A$1,$B6,H$1)} -> 0 | I6: {=_xll.EQNXTDZ($A$1,$B6,I$1)} -> 0 | J6: {=_xll.EQNXTDZ($A$1,$B6,J$1)} -> 0 | ... HH6: {=_xll.EQNXTDZ($A$1,$B6,HH$1)} -> 0
A7: High | B7: NMONTH_HIGH | C7: {=_xll.EQNXTDZ($A$1,$B7,C$1)} -> 0 | D7: {=_xll.EQNXTDZ($A$1,$B7,D$1)} -> 0 | E7: {=_xll.EQNXTDZ($A$1,$B7,E$1)} -> 0 | F7: {=_xll.EQNXTDZ($A$1,$B7,F$1)} -> 0 | G7: {=_xll.EQNXTDZ($A$1,$B7,G$1)} -> 0 | H7: {=_xll.EQNXTDZ($A$1,$B7,H$1)} -> 0 | I7: {=_xll.EQNXTDZ($A$1,$B7,I$1)} -> 0 | J7: {=_xll.EQNXTDZ($A$1,$B7,J$1)} -> 0 | ... HH7: {=_xll.EQNXTDZ($A$1,$B7,HH$1)} -> 0 | HP7: =+MAX(D7:F7) -> 0 | HQ7: =+MAX(G7:I7) -> 0 | HR7: =+MAX(J7:L7) -> 0 | HS7: =+MAX(M7:O7) -> 0 | HT7: =+MAX(P7:R7) -> 0 | HU7: =+MAX(S7:U7) -> 0 | HV7: =+MAX(V7:X7) -> 0 | HW7: =+MAX(Y7:AA7) -> 0 | HX7: =+MAX(AB7:AD7) -> 0 | HY7: =+MAX(AE7:AG7) -> 0 | HZ7: =+MAX(AH7:AJ7) -> 0 | IA7: =+MAX(AK7:AM7) -> 0 | IB7: =+MAX(AN7:AP7) -> 42.8 | IC7: =+MAX(AQ7:AS7) -> 41.15 | ID7: =+MAX(AT7:AV7) -> 42.7 | IE7: =+MAX(AW7:AY7) -> 40.5 | IF7: =+MAX(AZ7:BB7) -> 42.8 | IG7: =+MAX(BC7:BE7) -> 66.25 | IH7: =+MAX(BF7:BH7) -> 69.7 | II7: =+MAX(BI7:BK7) -> 137.2 | IJ7: =+MAX(BL7:BN7) -> 156 | IK7: =+MAX(BO7:BQ7) -> 248 | IL7: =+MAX(BR7:BT7) -> 254.2 | IM7: =+MAX(BU7:BW7) -> 199.25 | IN7: =+MAX(BX7:BZ7) -> 244.9 | IO7: =+MAX(CA7:CC7) -> 256.3 | IP7: =+MAX(CD7:CF7) -> 244.3 | IQ7: =+MAX(CG7:CI7) -> 252.7 | IR7: =+MAX(CJ7:CL7) -> 246.8 | IS7: =+MAX(CM7:CO7) -> 350.95 | IT7: =+MAX(CP7:CR7) -> 366.4 | IU7: =+MAX(CS7:CU7) -> 280.7 | IV7: =+MAX(CV7:CX7) -> 303 | IW7: =+MAX(CY7:DA7) -> 455.15 | IX7: =+MAX(DB7:DD7) -> 920 | IY7: =+MAX(DE7:DG7) -> 1644.95 | IZ7: =+MAX(DH7:DJ7) -> 1990 | JA7: =+MAX(DK7:DM7) -> 2045 | JB7: =+MAX(DN7:DP7) -> 2583.9 | JC7: =+MAX(DQ7:DS7) -> 3000 | JD7: =+MAX(DT7:DV7) -> 4236.75 | JE7: =+MAX(DW7:DY7) -> 3420 | JF7: =+MAX(DZ7:EB7) -> 2799.95 | JG7: =+MAX(EC7:EE7) -> 1099 | JH7: =+MAX(EF7:EH7) -> 976.95 | JI7: =+MAX(EI7:EK7) -> 1246 | JJ7: =+MAX(EL7:EN7) -> 1250 | JK7: =MAX(EO7:EQ7) -> 1249.4 | JL7: =MAX(ER7:ET7) -> 1348 | JM7: =MAX(EU7:EW7) -> 1090.95 | JN7: =MAX(EX7:EZ7) -> 894.9 | JO7: =MAX(FA7:FC7) -> 981 | JP7: =MAX(FD7:FF7) -> 957.9 | JQ7: =MAX(FG7:FI7) -> 1050 | JR7: =MAX(FJ7:FL7) -> 1067.7 | JS7: =MAX(FM7:FO7) -> 1614.8 | JT7: =MAX(FP7:FR7) -> 0 | JU7: =MAX(FS7:FU7) -> 0 | JV7: =MAX(FV7:FX7) -> 0 | JW7: =MAX(FY7:GA7) -> 0 | JX7: =MAX(GB7:GD7) -> 0 | JY7: =MAX(GE7:GG7) -> 0 | JZ7: =MAX(GH7:GJ7) -> 0 | KA7: =MAX(GK7:GM7) -> 0 | KB7: =MAX(GN7:GP7) -> 0 | KC7: =MAX(GQ7:GS7) -> 0 | KD7: =MAX(GT7:GV7) -> 0 | KE7: =MAX(GW7:GY7) -> 0 | KF7: =MAX(GZ7:HB7) -> 0 | KG7: =MAX(HC7:HE7) -> 0 | KH7: =MAX(HF7:HH7) -> 0
A8: Low | B8: NMONTH_LOW | C8: {=_xll.EQNXTDZ($A$1,$B8,C$1)} -> 0 | D8: {=_xll.EQNXTDZ($A$1,$B8,D$1)} -> 0 | E8: {=_xll.EQNXTDZ($A$1,$B8,E$1)} -> 0 | F8: {=_xll.EQNXTDZ($A$1,$B8,F$1)} -> 0 | G8: {=_xll.EQNXTDZ($A$1,$B8,G$1)} -> 0 | H8: {=_xll.EQNXTDZ($A$1,$B8,H$1)} -> 0 | I8: {=_xll.EQNXTDZ($A$1,$B8,I$1)} -> 0 | J8: {=_xll.EQNXTDZ($A$1,$B8,J$1)} -> 0 | ... HH8: {=_xll.EQNXTDZ($A$1,$B8,HH$1)} -> 0 | HP8: =+MIN(D8:F8) -> 0 | HQ8: =+MIN(G8:I8) -> 0 | HR8: =+MIN(J8:L8) -> 0 | HS8: =+MIN(M8:O8) -> 0 | HT8: =+MIN(P8:R8) -> 0 | HU8: =+MIN(S8:U8) -> 0 | HV8: =+MIN(V8:X8) -> 0 | HW8: =+MIN(Y8:AA8) -> 0 | HX8: =+MIN(AB8:AD8) -> 0 | HY8: =+MIN(AE8:AG8) -> 0 | HZ8: =+MIN(AH8:AJ8) -> 0 | IA8: =+MIN(AK8:AM8) -> 0 | IB8: =+MIN(AN8:AP8) -> 25 | IC8: =+MIN(AQ8:AS8) -> 26.55 | ID8: =+MIN(AT8:AV8) -> 26.3 | IE8: =+MIN(AW8:AY8) -> 28.5 | IF8: =+MIN(AZ8:BB8) -> 36 | IG8: =+MIN(BC8:BE8) -> 38.1 | IH8: =+MIN(BF8:BH8) -> 56.3 | II8: =+MIN(BI8:BK8) -> 64.2 | IJ8: =+MIN(BL8:BN8) -> 105 | IK8: =+MIN(BO8:BQ8) -> 153.15 | IL8: =+MIN(BR8:BT8) -> 155.65 | IM8: =+MIN(BU8:BW8) -> 115.7 | IN8: =+MIN(BX8:BZ8) -> 145.1 | IO8: =+MIN(CA8:CC8) -> 141 | IP8: =+MIN(CD8:CF8) -> 191.45 | IQ8: =+MIN(CG8:CI8) -> 202.3 | IR8: =+MIN(CJ8:CL8) -> 192 | IS8: =+MIN(CM8:CO8) -> 220.05 | IT8: =+MIN(CP8:CR8) -> 147.5 | IU8: =+MIN(CS8:CU8) -> 167 | IV8: =+MIN(CV8:CX8) -> 221.5 | IW8: =+MIN(CY8:DA8) -> 244 | IX8: =+MIN(DB8:DD8) -> 397.15 | IY8: =+MIN(DE8:DG8) -> 860.1 | IZ8: =+MIN(DH8:DJ8) -> 863 | JA8: =+MIN(DK8:DM8) -> 1525 | JB8: =+MIN(DN8:DP8) -> 1700 | JC8: =+MIN(DQ8:DS8) -> 1870.55 | JD8: =+MIN(DT8:DV8) -> 2226.3 | JE8: =+MIN(DW8:DY8) -> 2181.5 | JF8: =+MIN(DZ8:EB8) -> 631.5 | JG8: =+MIN(EC8:EE8) -> 714.05 | JH8: =+MIN(EF8:EH8) -> 738.4 | JI8: =+MIN(EI8:EK8) -> 686 | JJ8: =+MIN(EL8:EN8) -> 915.3 | JK8: =MIN(EO8:EQ8) -> 831.5 | JL8: =MIN(ER8:ET8) -> 967.05 | JM8: =MIN(EU8:EW8) -> 588 | JN8: =MIN(EX8:EZ8) -> 639.45 | JO8: =MIN(FA8:FC8) -> 780.5 | JP8: =MIN(FD8:FF8) -> 744.9 | JQ8: =MIN(FG8:FI8) -> 870.1 | JR8: =MIN(FJ8:FL8) -> 803.1 | JS8: =MIN(FM8:FO8) -> 903.15 | JT8: =MIN(FP8:FR8) -> 0 | JU8: =MIN(FS8:FU8) -> 0 | JV8: =MIN(FV8:FX8) -> 0 | JW8: =MIN(FY8:GA8) -> 0 | JX8: =MIN(GB8:GD8) -> 0 | JY8: =MIN(GE8:GG8) -> 0 | JZ8: =MIN(GH8:GJ8) -> 0 | KA8: =MIN(GK8:GM8) -> 0 | KB8: =MIN(GN8:GP8) -> 0 | KC8: =MIN(GQ8:GS8) -> 0 | KD8: =MIN(GT8:GV8) -> 0 | KE8: =MIN(GW8:GY8) -> 0 | KF8: =MIN(GZ8:HB8) -> 0 | KG8: =MIN(HC8:HE8) -> 0 | KH8: =MIN(HF8:HH8) -> 0
A9: Close | B9: NMONTH_CLOSE | C9: {=_xll.EQNXTDZ($A$1,$B9,C$1)} -> 0 | D9: {=_xll.EQNXTDZ($A$1,$B9,D$1)} -> 0 | E9: {=_xll.EQNXTDZ($A$1,$B9,E$1)} -> 0 | F9: {=_xll.EQNXTDZ($A$1,$B9,F$1)} -> 0 | G9: {=_xll.EQNXTDZ($A$1,$B9,G$1)} -> 0 | H9: {=_xll.EQNXTDZ($A$1,$B9,H$1)} -> 0 | I9: {=_xll.EQNXTDZ($A$1,$B9,I$1)} -> 0 | J9: {=_xll.EQNXTDZ($A$1,$B9,J$1)} -> 0 | ... HH9: {=_xll.EQNXTDZ($A$1,$B9,HH$1)} -> 0 | HP9: =+F9 -> 0 | HQ9: =+I9 -> 0 | HR9: =+L9 -> 0 | HS9: =+O9 -> 0 | HT9: =+R9 -> 0 | HU9: =+U9 -> 0 | HV9: =+X9 -> 0 | HW9: =+AA9 -> 0 | HX9: =+AD9 -> 0 | HY9: =+AG9 -> 0 | HZ9: =+AJ9 -> 0 | IA9: =+AM9 -> 0 | IB9: =+AP9 -> 26.85 | IC9: =+AS9 -> 36.9 | ID9: =+AV9 -> 34.35 | IE9: =+AY9 -> 38.7 | IF9: =+BB9 -> 38.15 | IG9: =+BE9 -> 56.75 | IH9: =+BH9 -> 64.15 | II9: =+BK9 -> 124.05 | IJ9: =+BN9 -> 152.8 | IK9: =+BQ9 -> 224.15 | IL9: =+BT9 -> 193.7 | IM9: =+BW9 -> 156.15 | IN9: =+BZ9 -> 160.4 | IO9: =+CC9 -> 198.4 | IP9: =+CF9 -> 217.4 | IQ9: =+CI9 -> 224.15 | IR9: =+CL9 -> 228.6 | IS9: =+CO9 -> 331.4 | IT9: =+CR9 -> 189.05 | IU9: =+CU9 -> 260.2 | IV9: =+CX9 -> 241.8 | IW9: =+DA9 -> 437.5 | IX9: =+DD9 -> 908.4 | IY9: =+DG9 -> 1059.45 | IZ9: =+DJ9 -> 1558.5 | JA9: =+DM9 -> 1740.85 | JB9: =+DP9 -> 2368.15 | JC9: =+DS9 -> 2473.65 | JD9: =+DV9 -> 3289.8 | JE9: =+DY9 -> 2589.25 | JF9: =+EB9 -> 993.05 | JG9: =+EE9 -> 767.25 | JH9: =+EH9 -> 810.25 | JI9: =+EK9 -> 1045.75 | JJ9: =+EN9 -> 1026.7 | JK9: =EQ9 -> 997.35 | JL9: =ET9 -> 1009.65 | JM9: =EW9 -> 806.2 | JN9: =EZ9 -> 872 | JO9: =FC9 -> 881.75 | JP9: =FF9 -> 872.25 | JQ9: =FI9 -> 1027.35 | JR9: =FL9 -> 934.9 | JS9: =FO9 -> 1491.1 | JT9: =FR9 -> 0 | JU9: =FU9 -> 0 | JV9: =FX9 -> 0 | JW9: =GA9 -> 0 | JX9: =GD9 -> 0 | JY9: =GG9 -> 0 | JZ9: =GJ9 -> 0 | KA9: =GM9 -> 0 | KB9: =GP9 -> 0 | KC9: =GS9 -> 0 | KD9: =GV9 -> 0 | KE9: =GY9 -> 0 | KF9: =HB9 -> 0 | KG9: =HE9 -> 0 | KH9: =HH9 -> 0
A11: Field Description | B11: Field Name | C11: {=_xll.EQNXTDZ($A$1,$B11,C$1)} -> 0 | D11: {=_xll.EQNXTDZ($A$1,$B11,D$1)} -> 0 | E11: {=_xll.EQNXTDZ($A$1,$B11,E$1)} -> 0 | F11: {=_xll.EQNXTDZ($A$1,$B11,F$1)} -> 0 | G11: {=_xll.EQNXTDZ($A$1,$B11,G$1)} -> 0 | H11: {=_xll.EQNXTDZ($A$1,$B11,H$1)} -> 0 | I11: {=_xll.EQNXTDZ($A$1,$B11,I$1)} -> 0 | J11: {=_xll.EQNXTDZ($A$1,$B11,J$1)} -> 0 | ... HH11: {=_xll.EQNXTDZ($A$1,$B11,HH$1)} -> 0
A12: Month End | B12: BMONTH_MONTHEND | C12: {=_xll.EQNXTDZ($A$1,$B12,C$1)} -> 0 | D12: {=_xll.EQNXTDZ($A$1,$B12,D$1)} -> 0 | E12: {=_xll.EQNXTDZ($A$1,$B12,E$1)} -> 0 | F12: {=_xll.EQNXTDZ($A$1,$B12,F$1)} -> 0 | G12: {=_xll.EQNXTDZ($A$1,$B12,G$1)} -> 0 | H12: {=_xll.EQNXTDZ($A$1,$B12,H$1)} -> 0 | I12: {=_xll.EQNXTDZ($A$1,$B12,I$1)} -> 0 | J12: {=_xll.EQNXTDZ($A$1,$B12,J$1)} -> 0 | ... HH12: {=_xll.EQNXTDZ($A$1,$B12,HH$1)} -> 0
A13: Open | B13: BMONTH_OPEN | C13: {=_xll.EQNXTDZ($A$1,$B13,C$1)} -> 0 | D13: {=_xll.EQNXTDZ($A$1,$B13,D$1)} -> 0 | E13: {=_xll.EQNXTDZ($A$1,$B13,E$1)} -> 0 | F13: {=_xll.EQNXTDZ($A$1,$B13,F$1)} -> 0 | G13: {=_xll.EQNXTDZ($A$1,$B13,G$1)} -> 0 | H13: {=_xll.EQNXTDZ($A$1,$B13,H$1)} -> 0 | I13: {=_xll.EQNXTDZ($A$1,$B13,I$1)} -> 0 | J13: {=_xll.EQNXTDZ($A$1,$B13,J$1)} -> 0 | ... HH13: {=_xll.EQNXTDZ($A$1,$B13,HH$1)} -> 0
A14: High | B14: BMONTH_HIGH | C14: {=_xll.EQNXTDZ($A$1,$B14,C$1)} -> 0 | D14: {=_xll.EQNXTDZ($A$1,$B14,D$1)} -> 0 | E14: {=_xll.EQNXTDZ($A$1,$B14,E$1)} -> 0 | F14: {=_xll.EQNXTDZ($A$1,$B14,F$1)} -> 0 | G14: {=_xll.EQNXTDZ($A$1,$B14,G$1)} -> 0 | H14: {=_xll.EQNXTDZ($A$1,$B14,H$1)} -> 0 | I14: {=_xll.EQNXTDZ($A$1,$B14,I$1)} -> 0 | J14: {=_xll.EQNXTDZ($A$1,$B14,J$1)} -> 0 | ... HH14: {=_xll.EQNXTDZ($A$1,$B14,HH$1)} -> 0 | HP14: =+MAX(D14:F14) -> 0 | HQ14: =+MAX(G14:I14) -> 0 | HR14: =+MAX(J14:L14) -> 0 | HS14: =+MAX(M14:O14) -> 0 | HT14: =+MAX(P14:R14) -> 0 | HU14: =+MAX(S14:U14) -> 0 | HV14: =+MAX(V14:X14) -> 0 | HW14: =+MAX(Y14:AA14) -> 0 | HX14: =+MAX(AB14:AD14) -> 0 | HY14: =+MAX(AE14:AG14) -> 0 | HZ14: =+MAX(AH14:AJ14) -> 0 | IA14: =+MAX(AK14:AM14) -> 0 | IB14: =+MAX(AN14:AP14) -> 42.5 | IC14: =+MAX(AQ14:AS14) -> 41.45 | ID14: =+MAX(AT14:AV14) -> 42.6 | IE14: =+MAX(AW14:AY14) -> 40.4 | IF14: =+MAX(AZ14:BB14) -> 42.8 | IG14: =+MAX(BC14:BE14) -> 66 | IH14: =+MAX(BF14:BH14) -> 69.7 | II14: =+MAX(BI14:BK14) -> 137 | IJ14: =+MAX(BL14:BN14) -> 156 | IK14: =+MAX(BO14:BQ14) -> 247.75 | IL14: =+MAX(BR14:BT14) -> 252 | IM14: =+MAX(BU14:BW14) -> 198.9 | IN14: =+MAX(BX14:BZ14) -> 245 | IO14: =+MAX(CA14:CC14) -> 256.3 | IP14: =+MAX(CD14:CF14) -> 242.5 | IQ14: =+MAX(CG14:CI14) -> 253.05 | IR14: =+MAX(CJ14:CL14) -> 247 | IS14: =+MAX(CM14:CO14) -> 350.05 | IT14: =+MAX(CP14:CR14) -> 365.8 | IU14: =+MAX(CS14:CU14) -> 281.95 | IV14: =+MAX(CV14:CX14) -> 303.1 | IW14: =+MAX(CY14:DA14) -> 455 | IX14: =+MAX(DB14:DD14) -> 924.4 | IY14: =+MAX(DE14:DG14) -> 1647.7 | IZ14: =+MAX(DH14:DJ14) -> 1990 | JA14: =+MAX(DK14:DM14) -> 2030 | JB14: =+MAX(DN14:DP14) -> 2577.65 | JC14: =+MAX(DQ14:DS14) -> 3000 | JD14: =+MAX(DT14:DV14) -> 4238.55 | JE14: =+MAX(DW14:DY14) -> 3420.25 | JF14: =+MAX(DZ14:EB14) -> 2798.6 | JG14: =+MAX(EC14:EE14) -> 1098.75 | JH14: =+MAX(EF14:EH14) -> 976.45 | JI14: =+MAX(EI14:EK14) -> 1246 | JJ14: =+MAX(EL14:EN14) -> 1250 | JK14: =MAX(EO14:EQ14) -> 1249 | JL14: =MAX(ER14:ET14) -> 1347.9 | JM14: =MAX(EU14:EW14) -> 1090.65 | JN14: =MAX(EX14:EZ14) -> 894.5 | JO14: =MAX(FA14:FC14) -> 981.95 | JP14: =MAX(FD14:FF14) -> 957.95 | JQ14: =MAX(FG14:FI14) -> 1050 | JR14: =MAX(FJ14:FL14) -> 1067.3 | JS14: =MAX(FM14:FO14) -> 1614 | JT14: =MAX(FP14:FR14) -> 0 | JU14: =MAX(FS14:FU14) -> 0 | JV14: =MAX(FV14:FX14) -> 0 | JW14: =MAX(FY14:GA14) -> 0 | JX14: =MAX(GB14:GD14) -> 0 | JY14: =MAX(GE14:GG14) -> 0 | JZ14: =MAX(GH14:GJ14) -> 0 | KA14: =MAX(GK14:GM14) -> 0 | KB14: =MAX(GN14:GP14) -> 0 | KC14: =MAX(GQ14:GS14) -> 0 | KD14: =MAX(GT14:GV14) -> 0 | KE14: =MAX(GW14:GY14) -> 0 | KF14: =MAX(GZ14:HB14) -> 0 | KG14: =MAX(HC14:HE14) -> 0 | KH14: =MAX(HF14:HH14) -> 0
A15: Low | B15: BMONTH_LOW | C15: {=_xll.EQNXTDZ($A$1,$B15,C$1)} -> 0 | D15: {=_xll.EQNXTDZ($A$1,$B15,D$1)} -> 0 | E15: {=_xll.EQNXTDZ($A$1,$B15,E$1)} -> 0 | F15: {=_xll.EQNXTDZ($A$1,$B15,F$1)} -> 0 | G15: {=_xll.EQNXTDZ($A$1,$B15,G$1)} -> 0 | H15: {=_xll.EQNXTDZ($A$1,$B15,H$1)} -> 0 | I15: {=_xll.EQNXTDZ($A$1,$B15,I$1)} -> 0 | J15: {=_xll.EQNXTDZ($A$1,$B15,J$1)} -> 0 | ... HH15: {=_xll.EQNXTDZ($A$1,$B15,HH$1)} -> 0 | HP15: =+MIN(D15:F15) -> 0 | HQ15: =+MIN(G15:I15) -> 0 | HR15: =+MIN(J15:L15) -> 0 | HS15: =+MIN(M15:O15) -> 0 | HT15: =+MIN(P15:R15) -> 0 | HU15: =+MIN(S15:U15) -> 0 | HV15: =+MIN(V15:X15) -> 0 | HW15: =+MIN(Y15:AA15) -> 0 | HX15: =+MIN(AB15:AD15) -> 0 | HY15: =+MIN(AE15:AG15) -> 0 | HZ15: =+MIN(AH15:AJ15) -> 0 | IA15: =+MIN(AK15:AM15) -> 0 | IB15: =+MIN(AN15:AP15) -> 25.25 | IC15: =+MIN(AQ15:AS15) -> 26.6 | ID15: =+MIN(AT15:AV15) -> 26.3 | IE15: =+MIN(AW15:AY15) -> 28.35 | IF15: =+MIN(AZ15:BB15) -> 34 | IG15: =+MIN(BC15:BE15) -> 38.25 | IH15: =+MIN(BF15:BH15) -> 56.3 | II15: =+MIN(BI15:BK15) -> 64.5 | IJ15: =+MIN(BL15:BN15) -> 103 | IK15: =+MIN(BO15:BQ15) -> 153.05 | IL15: =+MIN(BR15:BT15) -> 154.8 | IM15: =+MIN(BU15:BW15) -> 115 | IN15: =+MIN(BX15:BZ15) -> 145.65 | IO15: =+MIN(CA15:CC15) -> 141.35 | IP15: =+MIN(CD15:CF15) -> 180 | IQ15: =+MIN(CG15:CI15) -> 202.9 | IR15: =+MIN(CJ15:CL15) -> 193 | IS15: =+MIN(CM15:CO15) -> 220.75 | IT15: =+MIN(CP15:CR15) -> 147.5 | IU15: =+MIN(CS15:CU15) -> 167.2 | IV15: =+MIN(CV15:CX15) -> 221 | IW15: =+MIN(CY15:DA15) -> 241.65 | IX15: =+MIN(DB15:DD15) -> 400 | IY15: =+MIN(DE15:DG15) -> 865.1 | IZ15: =+MIN(DH15:DJ15) -> 860.5 | JA15: =+MIN(DK15:DM15) -> 1511.4 | JB15: =+MIN(DN15:DP15) -> 1670 | JC15: =+MIN(DQ15:DS15) -> 1900 | JD15: =+MIN(DT15:DV15) -> 2226.4 | JE15: =+MIN(DW15:DY15) -> 2179.85 | JF15: =+MIN(DZ15:EB15) -> 630 | JG15: =+MIN(EC15:EE15) -> 713.8 | JH15: =+MIN(EF15:EH15) -> 738.15 | JI15: =+MIN(EI15:EK15) -> 686.9 | JJ15: =+MIN(EL15:EN15) -> 918.1 | JK15: =MIN(EO15:EQ15) -> 832.2 | JL15: =MIN(ER15:ET15) -> 915.7 | JM15: =MIN(EU15:EW15) -> 588.25 | JN15: =MIN(EX15:EZ15) -> 639.35 | JO15: =MIN(FA15:FC15) -> 778.1 | JP15: =MIN(FD15:FF15) -> 745.45 | JQ15: =MIN(FG15:FI15) -> 869.6 | JR15: =MIN(FJ15:FL15) -> 804.7 | JS15: =MIN(FM15:FO15) -> 903.25 | JT15: =MIN(FP15:FR15) -> 0 | JU15: =MIN(FS15:FU15) -> 0 | JV15: =MIN(FV15:FX15) -> 0 | JW15: =MIN(FY15:GA15) -> 0 | JX15: =MIN(GB15:GD15) -> 0 | JY15: =MIN(GE15:GG15) -> 0 | JZ15: =MIN(GH15:GJ15) -> 0 | KA15: =MIN(GK15:GM15) -> 0 | KB15: =MIN(GN15:GP15) -> 0 | KC15: =MIN(GQ15:GS15) -> 0 | KD15: =MIN(GT15:GV15) -> 0 | KE15: =MIN(GW15:GY15) -> 0 | KF15: =MIN(GZ15:HB15) -> 0 | KG15: =MIN(HC15:HE15) -> 0 | KH15: =MIN(HF15:HH15) -> 0
A16: Close | B16: BMONTH_CLOSE | C16: {=_xll.EQNXTDZ($A$1,$B16,C$1)} -> 0 | D16: {=_xll.EQNXTDZ($A$1,$B16,D$1)} -> 0 | E16: {=_xll.EQNXTDZ($A$1,$B16,E$1)} -> 0 | F16: {=_xll.EQNXTDZ($A$1,$B16,F$1)} -> 0 | G16: {=_xll.EQNXTDZ($A$1,$B16,G$1)} -> 0 | H16: {=_xll.EQNXTDZ($A$1,$B16,H$1)} -> 0 | I16: {=_xll.EQNXTDZ($A$1,$B16,I$1)} -> 0 | J16: {=_xll.EQNXTDZ($A$1,$B16,J$1)} -> 0 | ... HH16: {=_xll.EQNXTDZ($A$1,$B16,HH$1)} -> 0 | HP16: =+F16 -> 0 | HQ16: =+I16 -> 0 | HR16: =+L16 -> 0 | HS16: =+O16 -> 0 | HT16: =+R16 -> 0 | HU16: =+U16 -> 0 | HV16: =+X16 -> 0 | HW16: =+AA16 -> 0 | HX16: =+AD16 -> 0 | HY16: =+AG16 -> 0 | HZ16: =+AJ16 -> 0 | IA16: =+AM16 -> 0 | IB16: =+AP16 -> 26.85 | IC16: =+AS16 -> 36.85 | ID16: =+AV16 -> 34.3 | IE16: =+AY16 -> 38.55 | IF16: =+BB16 -> 38.1 | IG16: =+BE16 -> 56.5 | IH16: =+BH16 -> 64.35 | II16: =+BK16 -> 123.9 | IJ16: =+BN16 -> 152.45 | IK16: =+BQ16 -> 223.5 | IL16: =+BT16 -> 191.25 | IM16: =+BW16 -> 155.95 | IN16: =+BZ16 -> 160.25 | IO16: =+CC16 -> 198.9 | IP16: =+CF16 -> 217.9 | IQ16: =+CI16 -> 224.35 | IR16: =+CL16 -> 228.6 | IS16: =+CO16 -> 331.9 | IT16: =+CR16 -> 188.75 | IU16: =+CU16 -> 259.7 | IV16: =+CX16 -> 242.3 | IW16: =+DA16 -> 437.7 | IX16: =+DD16 -> 908.35 | IY16: =+DG16 -> 1062.95 | IZ16: =+DJ16 -> 1552.35 | JA16: =+DM16 -> 1732.85 | JB16: =+DP16 -> 2372.3 | JC16: =+DS16 -> 2473.75 | JD16: =+DV16 -> 3290.7 | JE16: =+DY16 -> 2591.55 | JF16: =+EB16 -> 997.9 | JG16: =+EE16 -> 767.5 | JH16: =+EH16 -> 809 | JI16: =+EK16 -> 1046 | JJ16: =+EN16 -> 1025.8 | JK16: =EQ16 -> 997.95 | JL16: =ET16 -> 1009.65 | JM16: =EW16 -> 806.4 | JN16: =EZ16 -> 871.5 | JO16: =FC16 -> 881.8 | JP16: =FF16 -> 871.6 | JQ16: =FI16 -> 1029.25 | JR16: =FL16 -> 934.2 | JS16: =FO16 -> 1491.7 | JT16: =FR16 -> 0 | JU16: =FU16 -> 0 | JV16: =FX16 -> 0 | JW16: =GA16 -> 0 | JX16: =GD16 -> 0 | JY16: =GG16 -> 0 | JZ16: =GJ16 -> 0 | KA16: =GM16 -> 0 | KB16: =GP16 -> 0 | KC16: =GS16 -> 0 | KD16: =GV16 -> 0 | KE16: =GY16 -> 0 | KF16: =HB16 -> 0 | KG16: =HE16 -> 0 | KH16: =HH16 -> 0
A19: High | HP19: =+IF(HP14=0,HP7,HP14) -> 0 | HQ19: =+IF(HQ14=0,HQ7,HQ14) -> 0 | HR19: =+IF(HR14=0,HR7,HR14) -> 0 | HS19: =+IF(HS14=0,HS7,HS14) -> 0 | HT19: =+IF(HT14=0,HT7,HT14) -> 0 | HU19: =+IF(HU14=0,HU7,HU14) -> 0 | HV19: =+IF(HV14=0,HV7,HV14) -> 0 | HW19: =+IF(HW14=0,HW7,HW14) -> 0 | ... KH19: =+IF(KH14=0,KH7,KH14) -> 0
A20: Low | HP20: =+IF(HP15=0,HP8,HP15) -> 0 | HQ20: =+IF(HQ15=0,HQ8,HQ15) -> 0 | HR20: =+IF(HR15=0,HR8,HR15) -> 0 | HS20: =+IF(HS15=0,HS8,HS15) -> 0 | HT20: =+IF(HT15=0,HT8,HT15) -> 0 | HU20: =+IF(HU15=0,HU8,HU15) -> 0 | HV20: =+IF(HV15=0,HV8,HV15) -> 0 | HW20: =+IF(HW15=0,HW8,HW15) -> 0 | ... KH20: =+IF(KH15=0,KH8,KH15) -> 0
A21: Close | HP21: =+IF(HP16=0,HP9,HP16) -> 0 | HQ21: =+IF(HQ16=0,HQ9,HQ16) -> 0 | HR21: =+IF(HR16=0,HR9,HR16) -> 0 | HS21: =+IF(HS16=0,HS9,HS16) -> 0 | HT21: =+IF(HT16=0,HT9,HT16) -> 0 | HU21: =+IF(HU16=0,HU9,HU16) -> 0 | HV21: =+IF(HV16=0,HV9,HV16) -> 0 | HW21: =+IF(HW16=0,HW9,HW16) -> 0 | ... KH21: =+IF(KH16=0,KH9,KH16) -> 0

Sheet QTR No. of Shares
A1: ='QTR Raw'!A1 -> 271875 | C1: 201206 | D1: 201209 | E1: 201212 | F1: 201303 | G1: 201306 | H1: 201309 | I1: 201312 | J1: 201403 | K1: 201406 | L1: 201409 | M1: 201412 | N1: 201503 | O1: 201506 | P1: 201509 | Q1: 201512 | R1: 201603 | S1: 201606 | T1: 201609 | U1: 201612 | V1: 201703 | W1: 201706 | X1: 201709 | Y1: 201712 | Z1: 201803 | AA1: 201806 | AB1: 201809 | AC1: 201812 | AD1: 201903 | AE1: 201906 | AF1: 201909 | AG1: 201912 | AH1: 202003 | AI1: 202006 | AJ1: 202009 | AK1: 202012 | AL1: 202103 | AM1: 202106 | AN1: 202109 | AO1: 202112 | AP1: 202203 | AQ1: 202206 | AR1: 202209 | AS1: 202212 | AT1: 202303 | AU1: 202306 | AV1: 202309 | AW1: 202312 | AX1: 202403 | AY1: 202406
A4: Field Description | B4: Field Name
A5: Date End | B5: SHP_DATE_END | C5: {=_xll.EQNXTDZ($A$1,$B5,C$1)} -> 0 | D5: {=_xll.EQNXTDZ($A$1,$B5,D$1)} -> 0 | E5: {=_xll.EQNXTDZ($A$1,$B5,E$1)} -> 0 | F5: {=_xll.EQNXTDZ($A$1,$B5,F$1)} -> 0 | G5: {=_xll.EQNXTDZ($A$1,$B5,G$1)} -> 0 | H5: {=_xll.EQNXTDZ($A$1,$B5,H$1)} -> 0 | I5: {=_xll.EQNXTDZ($A$1,$B5,I$1)} -> 0 | J5: {=_xll.EQNXTDZ($A$1,$B5,J$1)} -> 0 | ... AY5: {=_xll.EQNXTDZ($A$1,$B5,AY$1)} -> 202406
A6: Grand Total | B6: SHP_NSGRANDTOTAL | C6: {=_xll.EQNXTDZ($A$1,$B6,C$1)} -> 0 | D6: {=_xll.EQNXTDZ($A$1,$B6,D$1)} -> 0 | E6: {=_xll.EQNXTDZ($A$1,$B6,E$1)} -> 0 | F6: {=_xll.EQNXTDZ($A$1,$B6,F$1)} -> 0 | G6: {=_xll.EQNXTDZ($A$1,$B6,G$1)} -> 0 | H6: {=_xll.EQNXTDZ($A$1,$B6,H$1)} -> 0 | I6: {=_xll.EQNXTDZ($A$1,$B6,I$1)} -> 0 | J6: {=_xll.EQNXTDZ($A$1,$B6,J$1)} -> 0 | ... AY6: {=_xll.EQNXTDZ($A$1,$B6,AY$1)} -> 1115492683
B7: In Crs. | C7: =+C6/10^7 -> 0 | D7: =+D6/10^7 -> 0 | E7: =+E6/10^7 -> 0 | F7: =+F6/10^7 -> 0 | G7: =+G6/10^7 -> 0 | H7: =+H6/10^7 -> 0 | I7: =+I6/10^7 -> 0 | J7: =+J6/10^7 -> 0 | ... AY7: =+AY6/10^7 -> 111.54927

Sheet Share price Daily
A1: =_xll.EQNXTH(B1,"[ADJC];[ADJH];[ADJL];[ADJO];[UCLS];[VOLUME]","2015-Jan-01","Y","All traded days","Asc") -> EQNXTH | B1: =+'Annual Raw'!A1 -> 271875 | L1: =_xll.EQNXTH(B1,"[NADJC];[NADJH];[NADJLOW];[NADJOPEN];[NUCLOSE];[NVOLUME]","2015-Jan-01","Y","All traded days","Asc") -> EQNXTH
A2: Adani Energy Solutions Ltd. | L2: Adani Energy Solutions Ltd.
A3: DATE | B3: ADJHIGH | C3: ADJCLOSE | D3: ADJLOW | E3: ADJOPEN | F3: CLOSE | G3: VOLUME | L3: DATE | M3: ADJCLOSE | N3: ADJHIGH | O3: ADJLOW | P3: ADJOPEN | Q3: CLOSE | R3: VOLUME
A4: 42216 | B4: 28.35 | C4: 28.35 | D4: 25.65 | E4: 27 | F4: 28.35 | G4: 8571999 | L4: 42216 | M4: 27.6 | N4: 27.6 | O4: 26 | P4: 26.3 | Q4: 27.6 | R4: 1024657
A5: 42219 | B5: 29.75 | C5: 29.75 | D5: 27 | E5: 28.8 | F5: 29.75 | G5: 2911021 | L5: 42219 | M5: 28.95 | N5: 28.95 | O5: 27.7 | P5: 28.45 | Q5: 28.95 | R5: 1737709
A6: 42220 | B6: 31.2 | C6: 31.2 | D6: 31.2 | E6: 31.2 | F6: 31.2 | G6: 590269 | L6: 42220 | M6: 30.35 | N6: 30.35 | O6: 30.35 | P6: 30.35 | Q6: 30.35 | R6: 52219
A7: 42221 | B7: 32.75 | C7: 32.75 | D7: 32.75 | E7: 32.75 | F7: 32.75 | G7: 225728 | L7: 42221 | M7: 31.85 | N7: 31.85 | O7: 31.85 | P7: 31.85 | Q7: 31.85 | R7: 95349
A8: 42222 | B8: 34.35 | C8: 34.35 | D8: 33 | E8: 34.35 | F8: 34.35 | G8: 3059350 | L8: 42222 | M8: 33.4 | N8: 33.4 | O8: 33.4 | P8: 33.4 | Q8: 33.4 | R8: 472314
A9: 42223 | B9: 36.05 | C9: 36.05 | D9: 36.05 | E9: 36.05 | F9: 36.05 | G9: 142003 | L9: 42223 | M9: 35.05 | N9: 35.05 | O9: 35.05 | P9: 35.05 | Q9: 35.05 | R9: 144093
A10: 42226 | B10: 37.85 | C10: 35.75 | D10: 35 | E10: 37.85 | F10: 35.75 | G10: 4195970 | L10: 42226 | M10: 36.05 | N10: 36.8 | O10: 34.95 | P10: 36.8 | Q10: 36.05 | R10: 2275461
A11: 42227 | B11: 37.5 | C11: 37.45 | D11: 34 | E11: 35.9 | F11: 37.45 | G11: 711618 | L11: 42227 | M11: 37.45 | N11: 37.85 | O11: 34.25 | P11: 35.8 | Q11: 37.45 | R11: 1558964
A12: 42228 | B12: 37.75 | C12: 35.65 | D12: 35.6 | E12: 37.35 | F12: 35.65 | G12: 670025 | L12: 42228 | M12: 35.6 | N12: 37.45 | O12: 35.6 | P12: 37 | Q12: 35.6 | R12: 864261
A13: 42229 | B13: 36.6 | C13: 35.15 | D13: 33.95 | E13: 35.5 | F13: 35.15 | G13: 149070 | L13: 42229 | M13: 35.25 | N13: 36.7 | O13: 33.9 | P13: 35.5 | Q13: 35.25 | R13: 454471
A14: 42230 | B14: 40.7 | C14: 40.1 | D14: 34.5 | E14: 37 | F14: 40.1 | G14: 1132065 | L14: 42230 | M14: 39.95 | N14: 40.8 | O14: 34.45 | P14: 36.2 | Q14: 39.95 | R14: 2384960
A15: 42233 | B15: 42.5 | C15: 41.05 | D15: 40.25 | E15: 41 | F15: 41.05 | G15: 648026 | L15: 42233 | M15: 41 | N15: 42.8 | O15: 40.4 | P15: 40.65 | Q15: 41 | R15: 1353169
... A2695: 46189 | B2695: 1518.65 | C2695: 1491.7 | D2695: 1476 | E2695: 1494.65 | F2695: 1491.7 | G2695: 111018 | L2695: 46189 | M2695: 1491.1 | N2695: 1519 | O2695: 1475.5 | P2695: 1498 | Q2695: 1491.1 | R2695: 1686111

Sheet Sheet2
J19: 219.3 | K19: 186.25 | L19: 186.75
J20: 192.9 | K20: 135.5 | L20: 146.9 | N20: 219.3 | O20: 192.9 | P20: 186 | Q20: 178.7 | R20: 207 | S20: 255.15 | T20: 348.25 | U20: 374 | V20: 495.9 | W20: 659.9 | X20: 613.4 | Y20: 607.9 | Z20: 555.95 | AA20: 497.8 | AB20: 459.9 | AC20: 374 | AD20: 362 | AE20: 341.5 | AF20: 384.2 | AG20: 433.8 | AH20: 460 | AI20: 474.4 | AJ20: 414.4 | AK20: 318.7 | AL20: 303.25 | AM20: 332.7 | AN20: 295 | AO20: 247 | AP20: 214.4 | AQ20: 179.5 | AR20: 97.9 | AS20: 119.1 | AT20: 130.65 | AU20: 148.55 | AV20: 153.8 | AW20: 152.9 | AX20: 136 | AY20: 141.15 | AZ20: 128.1 | BA20: 142.5 | BB20: 143.55 | BC20: 124.5 | BD20: 241 | BE20: 450 | BF20: 503.35
J21: 186 | K21: 145.4 | L21: 169.1 | N21: 186.25 | O21: 135.5 | P21: 145.4 | Q21: 108.95 | R21: 137 | S21: 170 | T21: 243.15 | U21: 307.5 | V21: 325.1 | W21: 463 | X21: 467.05 | Y21: 436.5 | Z21: 467 | AA21: 348.2 | AB21: 325 | AC21: 313.1 | AD21: 285 | AE21: 277.85 | AF21: 327 | AG21: 317 | AH21: 370.7 | AI21: 360 | AJ21: 271.15 | AK21: 233.15 | AL21: 218.8 | AM21: 262 | AN21: 223.6 | AO21: 137.6 | AP21: 142 | AQ21: 59.3 | AR21: 58 | AS21: 72.8 | AT21: 80 | AU21: 107.25 | AV21: 106 | AW21: 125.1 | AX21: 112.25 | AY21: 81.45 | AZ21: 88 | BA21: 90.35 | BB21: 106.05 | BC21: 98.55 | BD21: 119.25 | BE21: 210 | BF21: 349
J22: 178.7 | K22: 108.95 | L22: 139.75 | N22: 186.75 | O22: 146.9 | P22: 169.1 | Q22: 139.75 | R22: 202.15 | S22: 249.05 | T22: 346.4 | U22: 349.2 | V22: 469.9 | W22: 584.8 | X22: 536.15 | Y22: 513.35 | Z22: 474 | AA22: 438.55 | AB22: 355.4 | AC22: 334.95 | AD22: 298.8 | AE22: 328.35 | AF22: 343 | AG22: 389.9 | AH22: 443.05 | AI22: 407.5 | AJ22: 290.1 | AK22: 235.75 | AL22: 292.65 | AM22: 276.1 | AN22: 237.05 | AO22: 190.1 | AP22: 147.2 | AQ22: 71.9 | AR22: 75.2 | AS22: 90.1 | AT22: 117.2 | AU22: 116.3 | AV22: 140.5 | AW22: 128.6 | AX22: 133.65 | AY22: 91.65 | AZ22: 97.65 | BA22: 125 | BB22: 115.35 | BC22: 119.25 | BD22: 219.3 | BE22: 442.65 | BF22: 503.35
J23: 207 | K23: 137 | L23: 202.15
J24: 255.15 | K24: 170 | L24: 249.05
J25: 348.25 | K25: 243.15 | L25: 346.4
J26: 374 | K26: 307.5 | L26: 349.2
J27: 495.9 | K27: 325.1 | L27: 469.9
J28: 659.9 | K28: 463 | L28: 584.8
J29: 613.4 | K29: 467.05 | L29: 536.15
J30: 607.9 | K30: 436.5 | L30: 513.35
J31: 555.95 | K31: 467 | L31: 474
J32: 497.8 | K32: 348.2 | L32: 438.55
J33: 459.9 | K33: 325 | L33: 355.4
J34: 374 | K34: 313.1 | L34: 334.95
... J63: 503.35 | K63: 349 | L63: 503.35
