Workbook

Sheet Template
A1: =+'Annual Raw'!C4 -> Archean Chemical Industries Ltd. | B1: 36951 | C1: =EOMONTH(B1,12) -> 37346 | D1: =EOMONTH(C1,12) -> 37711 | E1: =EOMONTH(D1,12) -> 38077 | F1: =EOMONTH(E1,12) -> 38442 | G1: =EOMONTH(F1,12) -> 38807 | H1: =EOMONTH(G1,12) -> 39172 | I1: =EOMONTH(H1,12) -> 39538 | J1: =EOMONTH(I1,12) -> 39903 | ... AE1: =EOMONTH(AD1,12) -> 47573 | AH1: QTR | AI1: 41061 | AJ1: 41153 | AK1: 41244 | AL1: 41334 | AM1: 41426 | AN1: 41518 | AO1: 41609 | AP1: 41699 | AQ1: 41791 | AR1: 41883 | AS1: 41974 | AT1: 42064 | AU1: 42156 | AV1: 42248 | AW1: 42339 | AX1: 42430 | AY1: 42522 | AZ1: 42614 | BA1: 42705 | BB1: 42795 | BC1: 42887 | BD1: 42979 | BE1: 43070 | BF1: 43160 | BG1: 43252 | BH1: 43344 | BI1: 43435 | BJ1: 43525 | BK1: 43617 | BL1: 43709 | BM1: 43800 | BN1: 43891 | BO1: 43983 | BP1: 44075 | BQ1: =EOMONTH(BP1,3) -> 44196 | BR1: =EOMONTH(BQ1,3) -> 44286 | BS1: =EOMONTH(BR1,3) -> 44377 | BT1: =EOMONTH(BS1,3) -> 44469 | BU1: =EOMONTH(BT1,3) -> 44561 | BV1: =EOMONTH(BU1,3) -> 44651 | BW1: =EOMONTH(BV1,3) -> 44742 | BX1: =EOMONTH(BW1,3) -> 44834 | ... DB1: =EOMONTH(DA1,3) -> 47573 | DE1: HISTORICAL ESTIMATES | DF1: 46112
A2: Presentation Data (Start)
A6: Presentation Data (End)
A7: Profit & Loss- Annual (Start)
A8: Gross Revenue | B8: ='Annual Raw'!C6 -> 0 | C8: ='Annual Raw'!D6 -> 0 | D8: ='Annual Raw'!E6 -> 0 | E8: ='Annual Raw'!F6 -> 0 | F8: ='Annual Raw'!G6 -> 0 | G8: ='Annual Raw'!H6 -> 0 | H8: ='Annual Raw'!I6 -> 0 | I8: ='Annual Raw'!J6 -> 0 | ... AA8: ='Annual Raw'!AB6 -> 1081.0507 | AB8: =+SUM(CM8:CP8) -> 1310.3951 | AC8: =+SUM(CQ8:CT8) -> 1451.8195 | AD8: =+SUM(CU8:CX8) -> 1608.2275 | AE8: =+SUM(CY8:DB8) -> 1781.582 | AI8: ='QTR Raw'!C6+'QTR Raw'!C8 -> 0 | AJ8: ='QTR Raw'!D6+'QTR Raw'!D8 -> 0 | AK8: ='QTR Raw'!E6+'QTR Raw'!E8 -> 0 | AL8: ='QTR Raw'!F6+'QTR Raw'!F8 -> 0 | AM8: ='QTR Raw'!G6+'QTR Raw'!G8 -> 0 | AN8: ='QTR Raw'!H6+'QTR Raw'!H8 -> 0 | AO8: ='QTR Raw'!I6+'QTR Raw'!I8 -> 0 | AP8: ='QTR Raw'!J6+'QTR Raw'!J8 -> 0 | ... CK8: ='QTR Raw'!BE6+'QTR Raw'!BE8 -> 254.565 | CL8: =+CH10+(CL11*CH10) -> 398.4675 | CM8: =+CI10+(CM11*CI10) -> 332.41375 | CN8: =+CJ10+(CN11*CJ10) -> 251.28268 | CO8: =+CK10+(CO11*CK10) -> 281.18714 | CP8: =+CL10+(CP11*CL10) -> 445.51152 | CQ8: =+CM10+(CQ11*CM10) -> 368.75174 | CR8: =+CN10+(CR11*CN10) -> 277.01229 | CS8: =+CO10+(CS11*CO10) -> 311.72054 | ... DB8: =+CX10+(DB11*CX10) -> 606.82331 | DF8: 1081.0507
A9: Less: Exise Duty | B9: ='Annual Raw'!C7+'Annual Raw'!C8+'Annual Raw'!C9 -> 0 | C9: ='Annual Raw'!D7+'Annual Raw'!D8+'Annual Raw'!D9 -> 0 | D9: ='Annual Raw'!E7+'Annual Raw'!E8+'Annual Raw'!E9 -> 0 | E9: ='Annual Raw'!F7+'Annual Raw'!F8+'Annual Raw'!F9 -> 0 | F9: ='Annual Raw'!G7+'Annual Raw'!G8+'Annual Raw'!G9 -> 0 | G9: ='Annual Raw'!H7+'Annual Raw'!H8+'Annual Raw'!H9 -> 0 | H9: ='Annual Raw'!I7+'Annual Raw'!I8+'Annual Raw'!I9 -> 0 | I9: ='Annual Raw'!J7+'Annual Raw'!J8+'Annual Raw'!J9 -> 0 | ... AA9: ='Annual Raw'!AB7+'Annual Raw'!AB8+'Annual Raw'!AB9 -> 0 | AB9: =+SUM(CM9:CP9) -> 0 | AC9: =+SUM(CQ9:CT9) -> 0 | AD9: =+SUM(CU9:CX9) -> 0 | AE9: =+SUM(CY9:DB9) -> 0 | AI9: =+'QTR Raw'!C20+'QTR Raw'!C19+'QTR Raw'!C13+'QTR Raw'!C7 -> 0 | AJ9: =+'QTR Raw'!D20+'QTR Raw'!D19+'QTR Raw'!D13+'QTR Raw'!D7 -> 0 | AK9: =+'QTR Raw'!E20+'QTR Raw'!E19+'QTR Raw'!E13+'QTR Raw'!E7 -> 0 | AL9: =+'QTR Raw'!F20+'QTR Raw'!F19+'QTR Raw'!F13+'QTR Raw'!F7 -> 0 | AM9: =+'QTR Raw'!G20+'QTR Raw'!G19+'QTR Raw'!G13+'QTR Raw'!G7 -> 0 | AN9: =+'QTR Raw'!H20+'QTR Raw'!H19+'QTR Raw'!H13+'QTR Raw'!H7 -> 0 | AO9: =+'QTR Raw'!I20+'QTR Raw'!I19+'QTR Raw'!I13+'QTR Raw'!I7 -> 0 | AP9: =+'QTR Raw'!J20+'QTR Raw'!J19+'QTR Raw'!J13+'QTR Raw'!J7 -> 0 | ... CK9: =+'QTR Raw'!BE20+'QTR Raw'!BE19+'QTR Raw'!BE13+'QTR Raw'!BE7 -> 0 | DF9: 0
A10: Net Revenue | B10: =+B8-B9 -> 0 | C10: =+C8-C9 -> 0 | D10: =+D8-D9 -> 0 | E10: =+E8-E9 -> 0 | F10: =+F8-F9 -> 0 | G10: =+G8-G9 -> 0 | H10: =+H8-H9 -> 0 | I10: =+I8-I9 -> 0 | ... AE10: =+AE8-AE9 -> 1781.582 | AI10: =+AI8-AI9 -> 0 | AJ10: =+AJ8-AJ9 -> 0 | AK10: =+AK8-AK9 -> 0 | AL10: =+AL8-AL9 -> 0 | AM10: =+AM8-AM9 -> 0 | AN10: =+AN8-AN9 -> 0 | AO10: =+AO8-AO9 -> 0 | AP10: =+AP8-AP9 -> 0 | ... DB10: =+DB8-DB9 -> 606.82331 | DF10: 1081.0507
A11: Net Revenue YOY% | C11: =C10/B10-1 -> #DIV/0! | D11: =D10/C10-1 -> #DIV/0! | E11: =E10/D10-1 -> #DIV/0! | F11: =F10/E10-1 -> #DIV/0! | G11: =G10/F10-1 -> #DIV/0! | H11: =H10/G10-1 -> #DIV/0! | I11: =I10/H10-1 -> #DIV/0! | J11: =J10/I10-1 -> #DIV/0! | ... AE11: =AE10/AD10-1 -> 0.10779227 | AM11: =+IF(AI10<0,1-AM10/AI10,AM10/AI10-1) -> #DIV/0! | AN11: =+IF(AJ10<0,1-AN10/AJ10,AN10/AJ10-1) -> #DIV/0! | AO11: =+IF(AK10<0,1-AO10/AK10,AO10/AK10-1) -> #DIV/0! | AP11: =+IF(AL10<0,1-AP10/AL10,AP10/AL10-1) -> #DIV/0! | AQ11: =+IF(AM10<0,1-AQ10/AM10,AQ10/AM10-1) -> #DIV/0! | AR11: =+IF(AN10<0,1-AR10/AN10,AR10/AN10-1) -> #DIV/0! | AS11: =+IF(AO10<0,1-AS10/AO10,AS10/AO10-1) -> #DIV/0! | AT11: =+IF(AP10<0,1-AT10/AP10,AT10/AP10-1) -> #DIV/0! | ... CK11: =+IF(CG10<0,1-CK10/CG10,CK10/CG10-1) -> 0.050645084 | CL11: =+AVERAGE(CH11:CK11) -> 0.15304982 | CM11: =+AVERAGE(CI11:CL11) -> 0.13700537 | CN11: =+AVERAGE(CJ11:CM11) -> 0.077615442 | CO11: =+AVERAGE(CK11:CN11) -> 0.10457893 | CP11: =+AVERAGE(CL11:CO11) -> 0.11806239 | CQ11: =+AVERAGE(CM11:CP11) -> 0.10931553 | CR11: =+AVERAGE(CN11:CQ11) -> 0.10239307 | CS11: =+AVERAGE(CO11:CR11) -> 0.10858748 | ... DB11: =+AVERAGE(CX11:DA11) -> 0.10784251 | DF11: 0.038455439
A12: Net Revenue QOQ% | AJ12: =+IF(AI10<0,1-AJ10/AI10,AJ10/AI10-1) -> #DIV/0! | AK12: =+IF(AJ10<0,1-AK10/AJ10,AK10/AJ10-1) -> #DIV/0! | AL12: =+IF(AK10<0,1-AL10/AK10,AL10/AK10-1) -> #DIV/0! | AM12: =+IF(AL10<0,1-AM10/AL10,AM10/AL10-1) -> #DIV/0! | AN12: =+IF(AM10<0,1-AN10/AM10,AN10/AM10-1) -> #DIV/0! | AO12: =+IF(AN10<0,1-AO10/AN10,AO10/AN10-1) -> #DIV/0! | AP12: =+IF(AO10<0,1-AP10/AO10,AP10/AO10-1) -> #DIV/0! | AQ12: =+IF(AP10<0,1-AQ10/AP10,AQ10/AP10-1) -> #DIV/0! | ... CK12: =+IF(CJ10<0,1-CK10/CJ10,CK10/CJ10-1) -> 0.09169154 | CL12: =+CL10/CK10-1 -> 0.56528783 | CM12: =+CM10/CL10-1 -> -0.16576946 | CN12: =+CN10/CM10-1 -> -0.24406654 | CO12: =+CO10/CN10-1 -> 0.11900723 | CP12: =+CP10/CO10-1 -> 0.58439511 | CQ12: =+CQ10/CP10-1 -> -0.17229584 | CR12: =+CR10/CQ10-1 -> -0.24878379 | CS12: =+CS10/CR10-1 -> 0.12529499 | ... DB12: =+DB10/DA10-1 -> 0.58558389
A13: Increase/Decrease in Stock | B13: ='Annual Raw'!C11 -> 0 | C13: ='Annual Raw'!D11 -> 0 | D13: ='Annual Raw'!E11 -> 0 | E13: ='Annual Raw'!F11 -> 0 | F13: ='Annual Raw'!G11 -> 0 | G13: ='Annual Raw'!H11 -> 0 | H13: ='Annual Raw'!I11 -> 0 | I13: ='Annual Raw'!J11 -> 0 | ... AA13: ='Annual Raw'!AB11 -> -39.9347 | AB13: =+SUM(CM13:CP13) -> 0 | AC13: =+SUM(CQ13:CT13) -> 0 | AD13: =+SUM(CU13:CX13) -> 0 | AE13: =+SUM(CY13:DB13) -> 0 | AI13: ='QTR Raw'!C10 -> 0 | AJ13: ='QTR Raw'!D10 -> 0 | AK13: ='QTR Raw'!E10 -> 0 | AL13: ='QTR Raw'!F10 -> 0 | AM13: ='QTR Raw'!G10 -> 0 | AN13: ='QTR Raw'!H10 -> 0 | AO13: ='QTR Raw'!I10 -> 0 | AP13: ='QTR Raw'!J10 -> 0 | ... CK13: ='QTR Raw'!BE10 -> -16.359 | DF13: -39.9347
A14: Purchase of Finished Goods | B14: 0 | C14: 0 | D14: 0 | E14: 0 | F14: 0 | G14: 0 | H14: 0 | I14: 0 | J14: 0 | K14: 0 | L14: 0 | M14: 0 | N14: 0 | O14: 0 | P14: 0 | Q14: 0 | R14: 0 | S14: 0 | T14: 0 | U14: 0 | V14: 0 | W14: 0 | X14: 0 | Y14: 0 | Z14: 0 | AA14: 0 | AB14: =+SUM(CM14:CP14) -> 0 | AC14: =+SUM(CQ14:CT14) -> 0 | AD14: =+SUM(CU14:CX14) -> 0 | AE14: =+SUM(CY14:DB14) -> 0 | AI14: ='QTR Raw'!C12 -> 0 | AJ14: ='QTR Raw'!D12 -> 0 | AK14: ='QTR Raw'!E12 -> 0 | AL14: ='QTR Raw'!F12 -> 0 | AM14: ='QTR Raw'!G12 -> 0 | AN14: ='QTR Raw'!H12 -> 0 | AO14: ='QTR Raw'!I12 -> 0 | AP14: ='QTR Raw'!J12 -> 0 | ... CK14: ='QTR Raw'!BE12 -> 0 | DF14: 0
A15: Raw Material Consumed | B15: ='Annual Raw'!C12 -> 0 | C15: ='Annual Raw'!D12 -> 0 | D15: ='Annual Raw'!E12 -> 0 | E15: ='Annual Raw'!F12 -> 0 | F15: ='Annual Raw'!G12 -> 0 | G15: ='Annual Raw'!H12 -> 0 | H15: ='Annual Raw'!I12 -> 0 | I15: ='Annual Raw'!J12 -> 0 | ... AA15: ='Annual Raw'!AB12 -> 104.2016 | AB15: =+SUM(CM15:CP15) -> 28.040136 | AC15: =+SUM(CQ15:CT15) -> 29.076109 | AD15: =+SUM(CU15:CX15) -> 32.019503 | AE15: =+SUM(CY15:DB15) -> 35.477519 | AI15: ='QTR Raw'!C11 -> 0 | AJ15: ='QTR Raw'!D11 -> 0 | AK15: ='QTR Raw'!E11 -> 0 | AL15: ='QTR Raw'!F11 -> 0 | AM15: ='QTR Raw'!G11 -> 0 | AN15: ='QTR Raw'!H11 -> 0 | AO15: ='QTR Raw'!I11 -> 0 | AP15: ='QTR Raw'!J11 -> 0 | ... CK15: ='QTR Raw'!BE11 -> 15.425 | CL15: =+CL10-CL16 -> 12.03959 | CM15: =+CM10-CM16 -> 9.5848473 | CN15: =+CN10-CN16 -> 3.5137505 | CO15: =+CO10-CO16 -> 4.8760013 | CP15: =+CP10-CP16 -> 10.065537 | CQ15: =+CQ10-CQ16 -> 7.6286741 | CR15: =+CR10-CR16 -> 5.1666304 | CS15: =+CS10-CS16 -> 6.177762 | ... DB15: =+DB10-DB16 -> 12.093567 | DF15: 104.2016
A16: Gross Profit | B16: =B10-B13-B15-B14 -> 0 | C16: =C10-C13-C15-C14 -> 0 | D16: =D10-D13-D15-D14 -> 0 | E16: =E10-E13-E15-E14 -> 0 | F16: =F10-F13-F15-F14 -> 0 | G16: =G10-G13-G15-G14 -> 0 | H16: =H10-H13-H15-H14 -> 0 | I16: =I10-I13-I15-I14 -> 0 | ... AE16: =AE10-AE13-AE15-AE14 -> 1746.1045 | AI16: =AI10-AI13-AI15-AI14 -> 0 | AJ16: =AJ10-AJ13-AJ15-AJ14 -> 0 | AK16: =AK10-AK13-AK15-AK14 -> 0 | AL16: =AL10-AL13-AL15-AL14 -> 0 | AM16: =AM10-AM13-AM15-AM14 -> 0 | AN16: =AN10-AN13-AN15-AN14 -> 0 | AO16: =AO10-AO13-AO15-AO14 -> 0 | AP16: =AP10-AP13-AP15-AP14 -> 0 | ... CK16: =CK10-CK13-CK15-CK14 -> 255.499 | CL16: =+CL17*CL10 -> 386.42791 | CM16: =+CM17*CM10 -> 322.82891 | CN16: =+CN17*CN10 -> 247.76893 | CO16: =+CO17*CO10 -> 276.31113 | CP16: =+CP17*CP10 -> 435.44599 | CQ16: =+CQ17*CQ10 -> 361.12307 | CR16: =+CR17*CR10 -> 271.84565 | CS16: =+CS17*CS10 -> 305.54278 | ... DB16: =+DB17*DB10 -> 594.72974 | DF16: 1016.7838
A17: GP% | B17: =B16/B10 -> #DIV/0! | C17: =C16/C10 -> #DIV/0! | D17: =D16/D10 -> #DIV/0! | E17: =E16/E10 -> #DIV/0! | F17: =F16/F10 -> #DIV/0! | G17: =G16/G10 -> #DIV/0! | H17: =H16/H10 -> #DIV/0! | I17: =I16/I10 -> #DIV/0! | ... AE17: =AE16/AE10 -> 0.98008651 | AI17: =AI16/AI10 -> #DIV/0! | AJ17: =AJ16/AJ10 -> #DIV/0! | AK17: =AK16/AK10 -> #DIV/0! | AL17: =AL16/AL10 -> #DIV/0! | AM17: =AM16/AM10 -> #DIV/0! | AN17: =AN16/AN10 -> #DIV/0! | AO17: =AO16/AO10 -> #DIV/0! | AP17: =AP16/AP10 -> #DIV/0! | ... CK17: =CK16/CK10 -> 1.003669 | CL17: =AVERAGE(CH17:CK17) -> 0.96978526 | CM17: =AVERAGE(CI17:CL17) -> 0.97116591 | CN17: =AVERAGE(CJ17:CM17) -> 0.98601674 | CO17: =AVERAGE(CK17:CN17) -> 0.98265923 | CP17: =AVERAGE(CL17:CO17) -> 0.97740679 | CQ17: =AVERAGE(CM17:CP17) -> 0.97931217 | CR17: =AVERAGE(CN17:CQ17) -> 0.98134873 | CS17: =AVERAGE(CO17:CR17) -> 0.98018173 | ... DB17: =AVERAGE(CX17:DA17) -> 0.98007069 | DF17: 0.94055145
A18: GP YOY% | C18: =+IF(B16<0,1-C16/B16,C16/B16-1) -> #DIV/0! | D18: =+IF(C16<0,1-D16/C16,D16/C16-1) -> #DIV/0! | E18: =+IF(D16<0,1-E16/D16,E16/D16-1) -> #DIV/0! | F18: =+IF(E16<0,1-F16/E16,F16/E16-1) -> #DIV/0! | G18: =+IF(F16<0,1-G16/F16,G16/F16-1) -> #DIV/0! | H18: =+IF(G16<0,1-H16/G16,H16/G16-1) -> #DIV/0! | I18: =+IF(H16<0,1-I16/H16,I16/H16-1) -> #DIV/0! | J18: =+IF(I16<0,1-J16/I16,J16/I16-1) -> #DIV/0! | ... AE18: =+IF(AD16<0,1-AE16/AD16,AE16/AD16-1) -> 0.10778811 | AM18: =+IF(AI16<0,1-AM16/AI16,AM16/AI16-1) -> #DIV/0! | AN18: =+IF(AJ16<0,1-AN16/AJ16,AN16/AJ16-1) -> #DIV/0! | AO18: =+IF(AK16<0,1-AO16/AK16,AO16/AK16-1) -> #DIV/0! | AP18: =+IF(AL16<0,1-AP16/AL16,AP16/AL16-1) -> #DIV/0! | AQ18: =+IF(AM16<0,1-AQ16/AM16,AQ16/AM16-1) -> #DIV/0! | AR18: =+IF(AN16<0,1-AR16/AN16,AR16/AN16-1) -> #DIV/0! | AS18: =+IF(AO16<0,1-AS16/AO16,AS16/AO16-1) -> #DIV/0! | AT18: =+IF(AP16<0,1-AT16/AP16,AT16/AP16-1) -> #DIV/0! | ... CL18: =+IF(CH16<0,1-CL16/CH16,CL16/CH16-1) -> 0.15965365 | CM18: =+CM16/CI16-1 -> 0.21108375 | CN18: =+CN16/CJ16-1 -> 0.063135006 | CO18: =+CO16/CK16-1 -> 0.081456811 | CP18: =+CP16/CL16-1 -> 0.12684922 | CQ18: =+CQ16/CM16-1 -> 0.11862061 | CR18: =+CR16/CN16-1 -> 0.097174114 | CS18: =+CS16/CO16-1 -> 0.10579249 | CT18: =+CT16/CP16-1 -> 0.1120367 | ... DB18: =+DB16/CX16-1 -> 0.10792297 | DF18: -0.030537506
A19: GP QOQ% | AJ19: =+IF(AI16<0,1-AJ16/AI16,AJ16/AI16-1) -> #DIV/0! | AK19: =+IF(AJ16<0,1-AK16/AJ16,AK16/AJ16-1) -> #DIV/0! | AL19: =+IF(AK16<0,1-AL16/AK16,AL16/AK16-1) -> #DIV/0! | AM19: =+IF(AL16<0,1-AM16/AL16,AM16/AL16-1) -> #DIV/0! | AN19: =+IF(AM16<0,1-AN16/AM16,AN16/AM16-1) -> #DIV/0! | AO19: =+IF(AN16<0,1-AO16/AN16,AO16/AN16-1) -> #DIV/0! | AP19: =+IF(AO16<0,1-AP16/AO16,AP16/AO16-1) -> #DIV/0! | AQ19: =+IF(AP16<0,1-AQ16/AP16,AQ16/AP16-1) -> #DIV/0! | ... CL19: =+IF(CK16<0,1-CL16/CK16,CL16/CK16-1) -> 0.51244391 | CM19: =+CM16/CL16-1 -> -0.1645818 | CN19: =+CN16/CM16-1 -> -0.23250699 | CO19: =+CO16/CN16-1 -> 0.11519687 | CP19: =+CP16/CO16-1 -> 0.57592631 | CQ19: =+CQ16/CP16-1 -> -0.17068229 | CR19: =+CR16/CQ16-1 -> -0.24722157 | CS19: =+CS16/CR16-1 -> 0.12395681 | CT19: =+CT16/CS16-1 -> 0.58482529 | ... DB19: =+DB16/DA16-1 -> 0.58559513
A20: Employee Cost | B20: ='Annual Raw'!C14 -> 0 | C20: ='Annual Raw'!D14 -> 0 | D20: ='Annual Raw'!E14 -> 0 | E20: ='Annual Raw'!F14 -> 0 | F20: ='Annual Raw'!G14 -> 0 | G20: ='Annual Raw'!H14 -> 0 | H20: ='Annual Raw'!I14 -> 0 | I20: ='Annual Raw'!J14 -> 0 | ... AA20: ='Annual Raw'!AB14 -> 74.1867 | AB20: =+SUM(CM20:CP20) -> 79.018976 | AC20: =+SUM(CQ20:CT20) -> 84.550304 | AD20: =+SUM(CU20:CX20) -> 90.468825 | AE20: =+SUM(CY20:DB20) -> 96.801643 | AI20: ='QTR Raw'!C16 -> 0 | AJ20: ='QTR Raw'!D16 -> 0 | AK20: ='QTR Raw'!E16 -> 0 | AL20: ='QTR Raw'!F16 -> 0 | AM20: ='QTR Raw'!G16 -> 0 | AN20: ='QTR Raw'!H16 -> 0 | AO20: ='QTR Raw'!I16 -> 0 | AP20: ='QTR Raw'!J16 -> 0 | ... CK20: ='QTR Raw'!BE16 -> 17.301 | CL20: =CH20*107% -> 20.96451 | CM20: =CI20*107% -> 20.0411 | CN20: =CJ20*107% -> 18.03378 | CO20: =CK20*107% -> 18.51207 | CP20: =CL20*107% -> 22.432026 | CQ20: =CM20*107% -> 21.443977 | CR20: =CN20*107% -> 19.296145 | CS20: =CO20*107% -> 19.807915 | ... DB20: =CX20*107% -> 27.480196 | DF20: 74.1867
A21: General and Administration Expenses | B21: ='Annual Raw'!C17 -> 0 | C21: ='Annual Raw'!D17 -> 0 | D21: ='Annual Raw'!E17 -> 0 | E21: ='Annual Raw'!F17 -> 0 | F21: ='Annual Raw'!G17 -> 0 | G21: ='Annual Raw'!H17 -> 0 | H21: ='Annual Raw'!I17 -> 0 | I21: ='Annual Raw'!J17 -> 0 | ... AA21: ='Annual Raw'!AB17 -> 58.0667 | AB21: =+SUM(CM21:CP21) -> 0 | AC21: =+SUM(CQ21:CT21) -> 0 | AD21: =+SUM(CU21:CX21) -> 0 | AE21: =+SUM(CY21:DB21) -> 0 | AI21: ='QTR Raw'!C17 -> 0 | AJ21: ='QTR Raw'!D17 -> 0 | AK21: ='QTR Raw'!E17 -> 0 | AL21: ='QTR Raw'!F17 -> 0 | AM21: ='QTR Raw'!G17 -> 0 | AN21: ='QTR Raw'!H17 -> 0 | AO21: ='QTR Raw'!I17 -> 0 | AP21: ='QTR Raw'!J17 -> 0 | ... CK21: ='QTR Raw'!BE17 -> 0 | DF21: 58.0667
A22: Miscellaneous Expenses | B22: ='Annual Raw'!C19-'Annual Raw'!C20 -> 0 | C22: ='Annual Raw'!D19-'Annual Raw'!D20 -> 0 | D22: ='Annual Raw'!E19-'Annual Raw'!E20 -> 0 | E22: ='Annual Raw'!F19-'Annual Raw'!F20 -> 0 | F22: ='Annual Raw'!G19-'Annual Raw'!G20 -> 0 | G22: ='Annual Raw'!H19-'Annual Raw'!H20 -> 0 | H22: ='Annual Raw'!I19-'Annual Raw'!I20 -> 0 | I22: ='Annual Raw'!J19-'Annual Raw'!J20 -> 0 | ... AA22: ='Annual Raw'!AB19-'Annual Raw'!AB20 -> 12.6905 | AB22: =+SUM(CM22:CP22) -> 0 | AC22: =+SUM(CQ22:CT22) -> 0 | AD22: =+SUM(CU22:CX22) -> 0 | AE22: =+SUM(CY22:DB22) -> 0 | AI22: =+'QTR Raw'!C21 -> 0 | AJ22: =+'QTR Raw'!D21 -> 0 | AK22: =+'QTR Raw'!E21 -> 0 | AL22: =+'QTR Raw'!F21 -> 0 | AM22: =+'QTR Raw'!G21 -> 0 | AN22: =+'QTR Raw'!H21 -> 0 | AO22: =+'QTR Raw'!I21 -> 0 | AP22: =+'QTR Raw'!J21 -> 0 | ... CK22: =+'QTR Raw'!BE21 -> 0 | DF22: 12.6905
A23: Other Manufacturing Expenses | B23: ='Annual Raw'!C15+'Annual Raw'!C16 -> 0 | C23: ='Annual Raw'!D15+'Annual Raw'!D16 -> 0 | D23: ='Annual Raw'!E15+'Annual Raw'!E16 -> 0 | E23: ='Annual Raw'!F15+'Annual Raw'!F16 -> 0 | F23: ='Annual Raw'!G15+'Annual Raw'!G16 -> 0 | G23: ='Annual Raw'!H15+'Annual Raw'!H16 -> 0 | H23: ='Annual Raw'!I15+'Annual Raw'!I16 -> 0 | I23: ='Annual Raw'!J15+'Annual Raw'!J16 -> 0 | ... AA23: ='Annual Raw'!AB15+'Annual Raw'!AB16 -> 48.1256 | AB23: =+SUM(CM23:CP23) -> 880.90293 | AC23: =+SUM(CQ23:CT23) -> 982.30868 | AD23: =+SUM(CU23:CX23) -> 1091.7357 | AE23: =+SUM(CY23:DB23) -> 1212.8514 | AI23: ='QTR Raw'!C14 -> 0 | AJ23: ='QTR Raw'!D14 -> 0 | AK23: ='QTR Raw'!E14 -> 0 | AL23: ='QTR Raw'!F14 -> 0 | AM23: ='QTR Raw'!G14 -> 0 | AN23: ='QTR Raw'!H14 -> 0 | AO23: ='QTR Raw'!I14 -> 0 | AP23: ='QTR Raw'!J14 -> 0 | ... CK23: ='QTR Raw'!BE14 -> 183.803 | CL23: =CL26-CL20-CL21-CL22-CL24-CL25 -> 265.37369 | CM23: =CM26-CM20-CM21-CM22-CM24-CM25 -> 219.64816 | CN23: =CN26-CN20-CN21-CN22-CN24-CN25 -> 167.95533 | CO23: =CO26-CO20-CO21-CO22-CO24-CO25 -> 190.25569 | CP23: =CP26-CP20-CP21-CP22-CP24-CP25 -> 303.04375 | CQ23: =CQ26-CQ20-CQ21-CQ22-CQ24-CQ25 -> 249.05697 | CR23: =CR26-CR20-CR21-CR22-CR24-CR25 -> 184.77431 | CS23: =CS26-CS20-CS21-CS22-CS24-CS25 -> 209.56073 | ... DB23: =DB26-DB20-DB21-DB22-DB24-DB25 -> 418.58136 | DF23: 48.1256
A24: Power & Fuel Cost | B24: ='Annual Raw'!C13 -> 0 | C24: ='Annual Raw'!D13 -> 0 | D24: ='Annual Raw'!E13 -> 0 | E24: ='Annual Raw'!F13 -> 0 | F24: ='Annual Raw'!G13 -> 0 | G24: ='Annual Raw'!H13 -> 0 | H24: ='Annual Raw'!I13 -> 0 | I24: ='Annual Raw'!J13 -> 0 | ... AA24: ='Annual Raw'!AB13 -> 96.3439 | AB24: =+SUM(CM24:CP24) -> 0 | AC24: =+SUM(CQ24:CT24) -> 0 | AD24: =+SUM(CU24:CX24) -> 0 | AE24: =+SUM(CY24:DB24) -> 0 | AI24: ='QTR Raw'!C15 -> 0 | AJ24: ='QTR Raw'!D15 -> 0 | AK24: ='QTR Raw'!E15 -> 0 | AL24: ='QTR Raw'!F15 -> 0 | AM24: ='QTR Raw'!G15 -> 0 | AN24: ='QTR Raw'!H15 -> 0 | AO24: ='QTR Raw'!I15 -> 0 | AP24: ='QTR Raw'!J15 -> 0 | ... CK24: ='QTR Raw'!BE15 -> 0 | DF24: 96.3439
A25: Selling and Distribution Expenses | B25: ='Annual Raw'!C18 -> 0 | C25: ='Annual Raw'!D18 -> 0 | D25: ='Annual Raw'!E18 -> 0 | E25: ='Annual Raw'!F18 -> 0 | F25: ='Annual Raw'!G18 -> 0 | G25: ='Annual Raw'!H18 -> 0 | H25: ='Annual Raw'!I18 -> 0 | I25: ='Annual Raw'!J18 -> 0 | ... AA25: ='Annual Raw'!AB18 -> 488.5882 | AB25: =+SUM(CM25:CP25) -> 0 | AC25: =+SUM(CQ25:CT25) -> 0 | AD25: =+SUM(CU25:CX25) -> 0 | AE25: =+SUM(CY25:DB25) -> 0 | AI25: ='QTR Raw'!C18 -> 0 | AJ25: ='QTR Raw'!D18 -> 0 | AK25: ='QTR Raw'!E18 -> 0 | AL25: ='QTR Raw'!F18 -> 0 | AM25: ='QTR Raw'!G18 -> 0 | AN25: ='QTR Raw'!H18 -> 0 | AO25: ='QTR Raw'!I18 -> 0 | AP25: ='QTR Raw'!J18 -> 0 | ... CK25: ='QTR Raw'!BE18 -> 0 | DF25: 488.5882
A26: Total Cost | B26: =+SUM(B20:B25) -> 0 | C26: =+SUM(C20:C25) -> 0 | D26: =+SUM(D20:D25) -> 0 | E26: =+SUM(E20:E25) -> 0 | F26: =+SUM(F20:F25) -> 0 | G26: =+SUM(G20:G25) -> 0 | H26: =+SUM(H20:H25) -> 0 | I26: =+SUM(I20:I25) -> 0 | ... AE26: =+SUM(AE20:AE25) -> 1309.653 | AI26: =+SUM(AI20:AI25) -> 0 | AJ26: =+SUM(AJ20:AJ25) -> 0 | AK26: =+SUM(AK20:AK25) -> 0 | AL26: =+SUM(AL20:AL25) -> 0 | AM26: =+SUM(AM20:AM25) -> 0 | AN26: =+SUM(AN20:AN25) -> 0 | AO26: =+SUM(AO20:AO25) -> 0 | AP26: =+SUM(AP20:AP25) -> 0 | ... CK26: =+SUM(CK20:CK25) -> 201.104 | CL26: =CL27*CL10 -> 286.3382 | CM26: =CM27*CM10 -> 239.68926 | CN26: =CN27*CN10 -> 185.98911 | CO26: =CO27*CO10 -> 208.76776 | CP26: =CP27*CP10 -> 325.47578 | CQ26: =CQ27*CQ10 -> 270.50094 | CR26: =CR27*CR10 -> 204.07046 | CS26: =CS27*CS10 -> 229.36865 | ... DB26: =DB27*DB10 -> 446.06155 | DF26: 778.0016
A27: Cost % | B27: =B26/B10 -> #DIV/0! | C27: =C26/C10 -> #DIV/0! | D27: =D26/D10 -> #DIV/0! | E27: =E26/E10 -> #DIV/0! | F27: =F26/F10 -> #DIV/0! | G27: =G26/G10 -> #DIV/0! | H27: =H26/H10 -> #DIV/0! | I27: =I26/I10 -> #DIV/0! | ... AE27: =AE26/AE10 -> 0.73510677 | AI27: =AI26/AI10 -> #DIV/0! | AJ27: =AJ26/AJ10 -> #DIV/0! | AK27: =AK26/AK10 -> #DIV/0! | AL27: =AL26/AL10 -> #DIV/0! | AM27: =AM26/AM10 -> #DIV/0! | AN27: =AN26/AN10 -> #DIV/0! | AO27: =AO26/AO10 -> #DIV/0! | AP27: =AP26/AP10 -> #DIV/0! | ... CK27: =CK26/CK10 -> 0.78999077 | CL27: =AVERAGE(CH27:CK27) -> 0.71859865 | CM27: =AVERAGE(CI27:CL27) -> 0.72105697 | CN27: =AVERAGE(CJ27:CM27) -> 0.74015891 | CO27: =AVERAGE(CK27:CN27) -> 0.74245133 | CP27: =AVERAGE(CL27:CO27) -> 0.73056646 | CQ27: =AVERAGE(CM27:CP27) -> 0.73355842 | CR27: =AVERAGE(CN27:CQ27) -> 0.73668378 | CS27: =AVERAGE(CO27:CR27) -> 0.735815 | ... DB27: =AVERAGE(CX27:DA27) -> 0.7350765 | DF27: 0.7196717
A28: EBITDA | B28: =B16-B26 -> 0 | C28: =C16-C26 -> 0 | D28: =D16-D26 -> 0 | E28: =E16-E26 -> 0 | F28: =F16-F26 -> 0 | G28: =G16-G26 -> 0 | H28: =H16-H26 -> 0 | I28: =I16-I26 -> 0 | ... AE28: =AE16-AE26 -> 436.4515 | AI28: =AI16-AI26 -> 0 | AJ28: =AJ16-AJ26 -> 0 | AK28: =AK16-AK26 -> 0 | AL28: =AL16-AL26 -> 0 | AM28: =AM16-AM26 -> 0 | AN28: =AN16-AN26 -> 0 | AO28: =AO16-AO26 -> 0 | AP28: =AP16-AP26 -> 0 | ... DB28: =DB16-DB26 -> 148.66819 | DF28: 238.7822
A29: EBITDA Margins | B29: =B28/B10 -> #DIV/0! | C29: =C28/C10 -> #DIV/0! | D29: =D28/D10 -> #DIV/0! | E29: =E28/E10 -> #DIV/0! | F29: =F28/F10 -> #DIV/0! | G29: =G28/G10 -> #DIV/0! | H29: =H28/H10 -> #DIV/0! | I29: =I28/I10 -> #DIV/0! | ... AE29: =AE28/AE10 -> 0.24497974 | AI29: =AI28/AI10 -> #DIV/0! | AJ29: =AJ28/AJ10 -> #DIV/0! | AK29: =AK28/AK10 -> #DIV/0! | AL29: =AL28/AL10 -> #DIV/0! | AM29: =AM28/AM10 -> #DIV/0! | AN29: =AN28/AN10 -> #DIV/0! | AO29: =AO28/AO10 -> #DIV/0! | AP29: =AP28/AP10 -> #DIV/0! | ... DB29: =DB28/DB10 -> 0.2449942 | DF29: 0.22087974
A30: EBITDA YOY% | C30: =+IF(B28<0,1-C28/B28,C28/B28-1) -> #DIV/0! | D30: =+IF(C28<0,1-D28/C28,D28/C28-1) -> #DIV/0! | E30: =+IF(D28<0,1-E28/D28,E28/D28-1) -> #DIV/0! | F30: =+IF(E28<0,1-F28/E28,F28/E28-1) -> #DIV/0! | G30: =+IF(F28<0,1-G28/F28,G28/F28-1) -> #DIV/0! | H30: =+IF(G28<0,1-H28/G28,H28/G28-1) -> #DIV/0! | I30: =+IF(H28<0,1-I28/H28,I28/H28-1) -> #DIV/0! | J30: =+IF(I28<0,1-J28/I28,J28/I28-1) -> #DIV/0! | ... AE30: =+IF(AD28<0,1-AE28/AD28,AE28/AD28-1) -> 0.10773508 | AM30: =+IF(AI28<0,1-AM28/AI28,AM28/AI28-1) -> #DIV/0! | AN30: =+IF(AJ28<0,1-AN28/AJ28,AN28/AJ28-1) -> #DIV/0! | AO30: =+IF(AK28<0,1-AO28/AK28,AO28/AK28-1) -> #DIV/0! | AP30: =+IF(AL28<0,1-AP28/AL28,AP28/AL28-1) -> #DIV/0! | AQ30: =+IF(AM28<0,1-AQ28/AM28,AQ28/AM28-1) -> #DIV/0! | AR30: =+IF(AN28<0,1-AR28/AN28,AR28/AN28-1) -> #DIV/0! | AS30: =+IF(AO28<0,1-AS28/AO28,AS28/AO28-1) -> #DIV/0! | AT30: =+IF(AP28<0,1-AT28/AP28,AT28/AP28-1) -> #DIV/0! | ... CL30: =+IF(CH28<0,1-CL28/CH28,CL28/CH28-1) -> 0.13359574 | CM30: =+CM28/CI28-1 -> 0.064623608 | CN30: =+CN28/CJ28-1 -> -0.01310201 | CO30: =+CO28/CK28-1 -> 0.24172025 | CP30: =+CP28/CL28-1 -> 0.098716503 | CQ30: =+CQ28/CM28-1 -> 0.089998832 | CR30: =+CR28/CN28-1 -> 0.097044372 | CS30: =+CS28/CO28-1 -> 0.12778095 | CT30: =+CT28/CP28-1 -> 0.10314407 | ... DB30: =+DB28/CX28-1 -> 0.10753477 | DF30: -0.23992088
A31: EBITDA QOQ% | AJ31: =+IF(AI28<0,1-AJ28/AI28,AJ28/AI28-1) -> #DIV/0! | AK31: =+IF(AJ28<0,1-AK28/AJ28,AK28/AJ28-1) -> #DIV/0! | AL31: =+IF(AK28<0,1-AL28/AK28,AL28/AK28-1) -> #DIV/0! | AM31: =+IF(AL28<0,1-AM28/AL28,AM28/AL28-1) -> #DIV/0! | AN31: =+IF(AM28<0,1-AN28/AM28,AN28/AM28-1) -> #DIV/0! | AO31: =+IF(AN28<0,1-AO28/AN28,AO28/AN28-1) -> #DIV/0! | AP31: =+IF(AO28<0,1-AP28/AO28,AP28/AO28-1) -> #DIV/0! | AQ31: =+IF(AP28<0,1-AQ28/AP28,AQ28/AP28-1) -> #DIV/0! | ... CI31: =+IF(CH28<0,1-CI28/CH28,CI28/CH28-1) -> -0.11553446 | CJ31: =+IF(CI28>1,CJ28/CI28-1,1-CJ28/CI28) -> -0.19839166 | CK31: =+IF(CJ28>1,CK28/CJ28-1,1-CK28/CJ28) -> -0.13107029 | CL31: =+IF(CK28<0,1-CL28/CK28,CL28/CK28-1) -> 0.84005336 | CM31: =+CM28/CL28-1 -> -0.1693486 | CN31: =+CN28/CM28-1 -> -0.25691516 | CO31: =+CO28/CN28-1 -> 0.093291938 | CP31: =+CP28/CO28-1 -> 0.62814209 | CQ31: =+CQ28/CP28-1 -> -0.17593933 | CR31: =+CR28/CQ28-1 -> -0.25211201 | CS31: =+CS28/CR28-1 -> 0.12392338 | CT31: =+CT28/CS28-1 -> 0.59257459 | ... DB31: =+DB28/DA28-1 -> 0.58567584
A32: Depreciation | B32: ='Annual Raw'!C27 -> 0 | C32: ='Annual Raw'!D27 -> 0 | D32: ='Annual Raw'!E27 -> 0 | E32: ='Annual Raw'!F27 -> 0 | F32: ='Annual Raw'!G27 -> 0 | G32: ='Annual Raw'!H27 -> 0 | H32: ='Annual Raw'!I27 -> 0 | I32: ='Annual Raw'!J27 -> 0 | ... AA32: ='Annual Raw'!AB27 -> 92.8887 | AB32: =+SUM(CM32:CP32) -> 88.613347 | AC32: =+SUM(CQ32:CT32) -> 82.417753 | AD32: =+SUM(CU32:CX32) -> 76.655337 | AE32: =+SUM(CY32:DB32) -> 71.295814 | AI32: ='QTR Raw'!C28 -> 0 | AJ32: ='QTR Raw'!D28 -> 0 | AK32: ='QTR Raw'!E28 -> 0 | AL32: ='QTR Raw'!F28 -> 0 | AM32: ='QTR Raw'!G28 -> 0 | AN32: ='QTR Raw'!H28 -> 0 | AO32: ='QTR Raw'!I28 -> 0 | AP32: ='QTR Raw'!J28 -> 0 | ... CK32: ='QTR Raw'!BE28 -> 23.599 | CL32: =CL33*CK134 -> 23.175228 | CM32: =CM33*CL134 -> 22.759065 | CN32: =CN33*CM134 -> 22.350375 | CO32: =CO33*CN134 -> 21.949025 | CP32: =CP33*CO134 -> 21.554881 | CQ32: =CQ33*CP134 -> 21.167816 | CR32: =CR33*CQ134 -> 20.787701 | CS32: =CS33*CR134 -> 20.414411 | ... DB32: =DB33*DA134 -> 17.342453 | DF32: 92.8887
A33: Depreciation % of Net Block | B33: =+B32/B134 -> #DIV/0! | C33: =+C32/C134 -> #DIV/0! | D33: =+D32/D134 -> #DIV/0! | E33: =+E32/E134 -> #DIV/0! | F33: =+F32/F134 -> #DIV/0! | G33: =+G32/G134 -> #DIV/0! | H33: =+H32/H134 -> #DIV/0! | I33: =+I32/I134 -> #DIV/0! | ... AE33: =+AE32/AE134 -> 0.07517305 | AI33: =+AI32/AH134 -> #DIV/0! | AJ33: =+AJ32/AI134 -> #DIV/0! | AK33: =+AK32/AJ134 -> #DIV/0! | AL33: =+AL32/AK134 -> #DIV/0! | AM33: =+AM32/AL134 -> #DIV/0! | AN33: =+AN32/AM134 -> #DIV/0! | AO33: =+AO32/AN134 -> #DIV/0! | AP33: =+AP32/AO134 -> #DIV/0! | ... CK33: =+CK32/CJ134 -> 0.017957219 | CL33: =CK33 -> 0.017957219 | CM33: =CL33 -> 0.017957219 | CN33: =CM33 -> 0.017957219 | CO33: =CN33 -> 0.017957219 | CP33: =CO33 -> 0.017957219 | CQ33: =CP33 -> 0.017957219 | CR33: =CQ33 -> 0.017957219 | CS33: =CR33 -> 0.017957219 | ... DB33: =DA33 -> 0.017957219 | DF33: 0.06715547
A34: EBIT | B34: =B28-B32 -> 0 | C34: =C28-C32 -> 0 | D34: =D28-D32 -> 0 | E34: =E28-E32 -> 0 | F34: =F28-F32 -> 0 | G34: =G28-G32 -> 0 | H34: =H28-H32 -> 0 | I34: =I28-I32 -> 0 | ... AE34: =AE28-AE32 -> 365.15569 | AI34: =AI28-AI32 -> 0 | AJ34: =AJ28-AJ32 -> 0 | AK34: =AK28-AK32 -> 0 | AL34: =AL28-AL32 -> 0 | AM34: =AM28-AM32 -> 0 | AN34: =AN28-AN32 -> 0 | AO34: =AO28-AO32 -> 0 | AP34: =AP28-AP32 -> 0 | ... DB34: =DB28-DB32 -> 131.32574 | DF34: 145.8935
A35: Other Income | B35: ='Annual Raw'!C23 -> 0 | C35: ='Annual Raw'!D23 -> 0 | D35: ='Annual Raw'!E23 -> 0 | E35: ='Annual Raw'!F23 -> 0 | F35: ='Annual Raw'!G23 -> 0 | G35: ='Annual Raw'!H23 -> 0 | H35: ='Annual Raw'!I23 -> 0 | I35: ='Annual Raw'!J23 -> 0 | ... AA35: ='Annual Raw'!AB23 -> 26.9491 | AB35: =+SUM(CM35:CP35) -> 0 | AC35: =+SUM(CQ35:CT35) -> 0 | AD35: =+SUM(CU35:CX35) -> 0 | AE35: =+SUM(CY35:DB35) -> 0 | AI35: ='QTR Raw'!C23 -> 0 | AJ35: ='QTR Raw'!D23 -> 0 | AK35: ='QTR Raw'!E23 -> 0 | AL35: ='QTR Raw'!F23 -> 0 | AM35: ='QTR Raw'!G23 -> 0 | AN35: ='QTR Raw'!H23 -> 0 | AO35: ='QTR Raw'!I23 -> 0 | AP35: ='QTR Raw'!J23 -> 0 | ... CK35: ='QTR Raw'!BE23 -> 6.953 | DF35: 26.9491
A36: Interest | B36: ='Annual Raw'!C25 -> 0 | C36: ='Annual Raw'!D25 -> 0 | D36: ='Annual Raw'!E25 -> 0 | E36: ='Annual Raw'!F25 -> 0 | F36: ='Annual Raw'!G25 -> 0 | G36: ='Annual Raw'!H25 -> 0 | H36: ='Annual Raw'!I25 -> 0 | I36: ='Annual Raw'!J25 -> 0 | ... AA36: ='Annual Raw'!AB25 -> 25.7468 | AB36: =+SUM(CM36:CP36) -> 11.982464 | AC36: =+SUM(CQ36:CT36) -> 67.100296 | AD36: =+SUM(CU36:CX36) -> 116.08886 | AE36: =+SUM(CY36:DB36) -> 160.63756 | AI36: ='QTR Raw'!C25 -> 0 | AJ36: ='QTR Raw'!D25 -> 0 | AK36: ='QTR Raw'!E25 -> 0 | AL36: ='QTR Raw'!F25 -> 0 | AM36: ='QTR Raw'!G25 -> 0 | AN36: ='QTR Raw'!H25 -> 0 | AO36: ='QTR Raw'!I25 -> 0 | AP36: ='QTR Raw'!J25 -> 0 | ... CK36: ='QTR Raw'!BE25 -> 4.42 | CL36: =CL37*CK168 -> -1.8730739 | CM36: =CM37*CL168 -> -16.197838 | CN36: =CN37*CM168 -> -0.71232344 | CO36: =CO37*CN168 -> 14.867014 | CP36: =CP37*CO168 -> 14.025611 | CQ36: =CQ37*CP168 -> -3.5817768 | CR36: =CR37*CQ168 -> 13.124408 | CS36: =CS37*CR168 -> 29.735499 | ... DB36: =DB37*DA168 -> 51.813901 | DF36: 25.7468
A37: Interest % of Debt | B37: =+B36/B128 -> #DIV/0! | C37: =+C36/C128 -> #DIV/0! | D37: =+D36/D128 -> #DIV/0! | E37: =+E36/E128 -> #DIV/0! | F37: =+F36/F128 -> #DIV/0! | G37: =+G36/G128 -> #DIV/0! | H37: =+H36/H128 -> #DIV/0! | I37: =+I36/I128 -> #DIV/0! | ... AE37: =+AE36/AE128 -> 0.76239582 | AI37: =(AI36-AI35)/AH168 -> #DIV/0! | AJ37: =(AJ36-AJ35)/AI168 -> #DIV/0! | AK37: =(AK36-AK35)/AJ168 -> #DIV/0! | AL37: =(AL36-AL35)/AK168 -> #DIV/0! | AM37: =(AM36-AM35)/AL168 -> #DIV/0! | AN37: =(AN36-AN35)/AM168 -> #DIV/0! | AO37: =(AO36-AO35)/AN168 -> #DIV/0! | AP37: =(AP36-AP35)/AO168 -> #DIV/0! | ... CK37: =(CK36-CK35)/CJ168 -> -0.078588936 | CL37: =+CK37 -> -0.078588936 | CM37: =+CL37 -> -0.078588936 | CN37: =+CM37 -> -0.078588936 | CO37: =+CN37 -> -0.078588936 | CP37: =+CO37 -> -0.078588936 | CQ37: =+CP37 -> -0.078588936 | CR37: =+CQ37 -> -0.078588936 | CS37: =+CR37 -> -0.078588936 | ... DB37: =+DA37 -> -0.078588936 | DF37: 0.063569489
A38: PBT | B38: =B34+B35-B36 -> 0 | C38: =C34+C35-C36 -> 0 | D38: =D34+D35-D36 -> 0 | E38: =E34+E35-E36 -> 0 | F38: =F34+F35-F36 -> 0 | G38: =G34+G35-G36 -> 0 | H38: =H34+H35-H36 -> 0 | I38: =I34+I35-I36 -> 0 | ... AE38: =AE34+AE35-AE36 -> 204.51813 | AI38: =AI34+AI35-AI36 -> 0 | AJ38: =AJ34+AJ35-AJ36 -> 0 | AK38: =AK34+AK35-AK36 -> 0 | AL38: =AL34+AL35-AL36 -> 0 | AM38: =AM34+AM35-AM36 -> 0 | AN38: =AN34+AN35-AN36 -> 0 | AO38: =AO34+AO35-AO36 -> 0 | AP38: =AP34+AP35-AP36 -> 0 | ... DB38: =DB34+DB35-DB36 -> 79.511837 | DF38: 147.0958
A39: Tax | B39: ='Annual Raw'!C30 -> 0 | C39: ='Annual Raw'!D30 -> 0 | D39: ='Annual Raw'!E30 -> 0 | E39: ='Annual Raw'!F30 -> 0 | F39: ='Annual Raw'!G30 -> 0 | G39: ='Annual Raw'!H30 -> 0 | H39: ='Annual Raw'!I30 -> 0 | I39: ='Annual Raw'!J30 -> 0 | ... AA39: ='Annual Raw'!AB30 -> 41.6878 | AB39: =+SUM(CM39:CP39) -> 63.017937 | AC39: =+SUM(CQ39:CT39) -> 58.47474 | AD39: =+SUM(CU39:CX39) -> 57.013425 | AE39: =+SUM(CY39:DB39) -> 57.936449 | AI39: ='QTR Raw'!C29 -> 0 | AJ39: ='QTR Raw'!D29 -> 0 | AK39: ='QTR Raw'!E29 -> 0 | AL39: ='QTR Raw'!F29 -> 0 | AM39: ='QTR Raw'!G29 -> 0 | AN39: ='QTR Raw'!H29 -> 0 | AO39: ='QTR Raw'!I29 -> 0 | AP39: ='QTR Raw'!J29 -> 0 | ... CK39: ='QTR Raw'!BE29 -> 9.33 | CL39: =+CL38*CL40 -> 22.463479 | CM39: =+CM38*CM40 -> 21.926528 | CN39: =+CN38*CN40 -> 11.276875 | CO39: =+CO38*CO40 -> 8.6981785 | CP39: =+CP38*CP40 -> 21.116355 | CQ39: =+CQ38*CQ40 -> 20.709226 | CR39: =+CR38*CR40 -> 9.5782729 | CS39: =+CS38*CS40 -> 7.3735607 | ... DB39: =+DB38*DB40 -> 22.524676 | DF39: 41.6878
A40: Tax Rate % | B40: =B39/B38 -> #DIV/0! | C40: =C39/C38 -> #DIV/0! | D40: =D39/D38 -> #DIV/0! | E40: =E39/E38 -> #DIV/0! | F40: =F39/F38 -> #DIV/0! | G40: =G39/G38 -> #DIV/0! | H40: =H39/H38 -> #DIV/0! | I40: =I39/I38 -> #DIV/0! | ... AE40: =AE39/AE38 -> 0.28328271 | AI40: =AI39/AI38 -> #DIV/0! | AJ40: =AJ39/AJ38 -> #DIV/0! | AK40: =AK39/AK38 -> #DIV/0! | AL40: =AL39/AL38 -> #DIV/0! | AM40: =AM39/AM38 -> #DIV/0! | AN40: =AN39/AN38 -> #DIV/0! | AO40: =AO39/AO38 -> #DIV/0! | AP40: =AP39/AP38 -> #DIV/0! | ... CK40: =CK39/CK38 -> 0.27993639 | CL40: =AVERAGE(CH40:CK40) -> 0.28511459 | CM40: =AVERAGE(CI40:CL40) -> 0.28632775 | CN40: =AVERAGE(CJ40:CM40) -> 0.28092627 | CO40: =AVERAGE(CK40:CN40) -> 0.28307625 | CP40: =AVERAGE(CL40:CO40) -> 0.28386121 | CQ40: =AVERAGE(CM40:CP40) -> 0.28354787 | CR40: =AVERAGE(CN40:CQ40) -> 0.2828529 | CS40: =AVERAGE(CO40:CR40) -> 0.28333456 | ... DB40: =AVERAGE(CX40:DA40) -> 0.28328708 | DF40: 0.28340578
A41: PAT | B41: =B38-B39 -> 0 | C41: =C38-C39 -> 0 | D41: =D38-D39 -> 0 | E41: =E38-E39 -> 0 | F41: =F38-F39 -> 0 | G41: =G38-G39 -> 0 | H41: =H38-H39 -> 0 | I41: =I38-I39 -> 0 | ... AE41: =AE38-AE39 -> 146.58168 | AI41: =AI38-AI39 -> 0 | AJ41: =AJ38-AJ39 -> 0 | AK41: =AK38-AK39 -> 0 | AL41: =AL38-AL39 -> 0 | AM41: =AM38-AM39 -> 0 | AN41: =AN38-AN39 -> 0 | AO41: =AO38-AO39 -> 0 | AP41: =AP38-AP39 -> 0 | ... DB41: =DB38-DB39 -> 56.98716 | DF41: 105.408
A42: PAT % | B42: =+B41/B10 -> #DIV/0! | C42: =+C41/C10 -> #DIV/0! | D42: =+D41/D10 -> #DIV/0! | E42: =+E41/E10 -> #DIV/0! | F42: =+F41/F10 -> #DIV/0! | G42: =+G41/G10 -> #DIV/0! | H42: =+H41/H10 -> #DIV/0! | I42: =+I41/I10 -> #DIV/0! | ... AE42: =+AE41/AE10 -> 0.082276132 | AI42: =+AI41/AI10 -> #DIV/0! | AJ42: =+AJ41/AJ10 -> #DIV/0! | AK42: =+AK41/AK10 -> #DIV/0! | AL42: =+AL41/AL10 -> #DIV/0! | AM42: =+AM41/AM10 -> #DIV/0! | AN42: =+AN41/AN10 -> #DIV/0! | AO42: =+AO41/AO10 -> #DIV/0! | AP42: =+AP41/AP10 -> #DIV/0! | ... DB42: =+DB41/DB10 -> 0.093910632 | DF42: 0.09750514
A43: PAT YOY% | C43: =+IF(B41<0,1-C41/B41,C41/B41-1) -> #DIV/0! | D43: =+IF(C41<0,1-D41/C41,D41/C41-1) -> #DIV/0! | E43: =+IF(D41<0,1-E41/D41,E41/D41-1) -> #DIV/0! | F43: =+IF(E41<0,1-F41/E41,F41/E41-1) -> #DIV/0! | G43: =+IF(F41<0,1-G41/F41,G41/F41-1) -> #DIV/0! | H43: =+IF(G41<0,1-H41/G41,H41/G41-1) -> #DIV/0! | I43: =+IF(H41<0,1-I41/H41,I41/H41-1) -> #DIV/0! | J43: =+IF(I41<0,1-J41/I41,J41/I41-1) -> #DIV/0! | ... AE43: =+IF(AD41<0,1-AE41/AD41,AE41/AD41-1) -> 0.016193145 | AM43: =+IF(AI41<0,1-AM41/AI41,AM41/AI41-1) -> #DIV/0! | AN43: =+IF(AJ41<0,1-AN41/AJ41,AN41/AJ41-1) -> #DIV/0! | AO43: =+IF(AK41<0,1-AO41/AK41,AO41/AK41-1) -> #DIV/0! | AP43: =+IF(AL41<0,1-AP41/AL41,AP41/AL41-1) -> #DIV/0! | AQ43: =+IF(AM41<0,1-AQ41/AM41,AQ41/AM41-1) -> #DIV/0! | AR43: =+IF(AN41<0,1-AR41/AN41,AR41/AN41-1) -> #DIV/0! | AS43: =+IF(AO41<0,1-AS41/AO41,AS41/AO41-1) -> #DIV/0! | AT43: =+IF(AP41<0,1-AT41/AP41,AT41/AP41-1) -> #DIV/0! | ... CL43: =+IF(CH41<0,1-CL41/CH41,CL41/CH41-1) -> 0.04798715 | CM43: =+CM41/CI41-1 -> 0.36139639 | CN43: =+CN41/CJ41-1 -> -0.0060300728 | CO43: =+CO41/CK41-1 -> -0.082080268 | CP43: =+CP41/CL41-1 -> -0.054163502 | CQ43: =+CQ41/CM41-1 -> -0.042542687 | CR43: =+CR41/CN41-1 -> -0.15867274 | CS43: =+CS41/CO41-1 -> -0.1533648 | CT43: =+CT41/CP41-1 -> -0.012089523 | ... DB43: =+DB41/CX41-1 -> 0.055562338 | DF43: -0.47902313
A44: PAT QOQ% | AJ44: =+IF(AI41<0,1-AJ41/AI41,AJ41/AI41-1) -> #DIV/0! | AK44: =+IF(AJ41<0,1-AK41/AJ41,AK41/AJ41-1) -> #DIV/0! | AL44: =+IF(AK41<0,1-AL41/AK41,AL41/AK41-1) -> #DIV/0! | AM44: =+IF(AL41<0,1-AM41/AL41,AM41/AL41-1) -> #DIV/0! | AN44: =+IF(AM41<0,1-AN41/AM41,AN41/AM41-1) -> #DIV/0! | AO44: =+IF(AN41<0,1-AO41/AN41,AO41/AN41-1) -> #DIV/0! | AP44: =+IF(AO41<0,1-AP41/AO41,AP41/AO41-1) -> #DIV/0! | AQ44: =+IF(AP41<0,1-AQ41/AP41,AQ41/AP41-1) -> #DIV/0! | ... CL44: =+IF(CK41<0,1-CL41/CK41,CL41/CK41-1) -> 1.346934 | CM44: =+CM41/CL41-1 -> -0.029688424 | CN44: =+CN41/CM41-1 -> -0.47184108 | CO44: =+CO41/CN41-1 -> -0.23681822 | CP44: =+CP41/CO41-1 -> 1.4183115 | CQ44: =+CQ41/CP41-1 -> -0.017766902 | CR44: =+CR41/CQ41-1 -> -0.53590151 | CS44: =+CS41/CR41-1 -> -0.23200329 | CT44: =+CT41/CS41-1 -> 1.8218473 | ... DB44: =+DB41/DA41-1 -> 2.8476827
A45: Minority Interest | B45: ='Annual Raw'!C32 -> 0 | C45: ='Annual Raw'!D32 -> 0 | D45: ='Annual Raw'!E32 -> 0 | E45: ='Annual Raw'!F32 -> 0 | F45: ='Annual Raw'!G32 -> 0 | G45: ='Annual Raw'!H32 -> 0 | H45: ='Annual Raw'!I32 -> 0 | I45: ='Annual Raw'!J32 -> 0 | ... AA45: ='Annual Raw'!AB32 -> 1.4514 | AB45: =+SUM(CM45:CP45) -> -1.44 | AC45: =+SUM(CQ45:CT45) -> -1.44 | AD45: =+SUM(CU45:CX45) -> -1.44 | AE45: =+SUM(CY45:DB45) -> -1.44 | AI45: ='QTR Raw'!C34 -> 0 | AJ45: ='QTR Raw'!D34 -> 0 | AK45: ='QTR Raw'!E34 -> 0 | AL45: ='QTR Raw'!F34 -> 0 | AM45: ='QTR Raw'!G34 -> 0 | AN45: ='QTR Raw'!H34 -> 0 | AO45: ='QTR Raw'!I34 -> 0 | AP45: ='QTR Raw'!J34 -> 0 | ... CK45: ='QTR Raw'!BE34 -> -0.36 | CL45: =+CK45 -> -0.36 | CM45: =+CL45 -> -0.36 | CN45: =+CM45 -> -0.36 | CO45: =+CN45 -> -0.36 | CP45: =+CO45 -> -0.36 | CQ45: =+CP45 -> -0.36 | CR45: =+CQ45 -> -0.36 | CS45: =+CR45 -> -0.36 | ... DB45: =+DA45 -> -0.36 | DF45: 1.4514
A46: Share of Associate | B46: ='Annual Raw'!C33+'Annual Raw'!C28 -> 0 | C46: ='Annual Raw'!D33+'Annual Raw'!D28 -> 0 | D46: ='Annual Raw'!E33+'Annual Raw'!E28 -> 0 | E46: ='Annual Raw'!F33+'Annual Raw'!F28 -> 0 | F46: ='Annual Raw'!G33+'Annual Raw'!G28 -> 0 | G46: ='Annual Raw'!H33+'Annual Raw'!H28 -> 0 | H46: ='Annual Raw'!I33+'Annual Raw'!I28 -> 0 | I46: ='Annual Raw'!J33+'Annual Raw'!J28 -> 0 | ... AA46: ='Annual Raw'!AB33+'Annual Raw'!AB28 -> 0 | AB46: =+SUM(CM46:CP46) -> 0 | AC46: =+SUM(CQ46:CT46) -> 0 | AD46: =+SUM(CU46:CX46) -> 0 | AE46: =+SUM(CY46:DB46) -> 0 | AI46: ='QTR Raw'!C35 -> 0 | AJ46: ='QTR Raw'!D35 -> 0 | AK46: ='QTR Raw'!E35 -> 0 | AL46: ='QTR Raw'!F35 -> 0 | AM46: ='QTR Raw'!G35 -> 0 | AN46: ='QTR Raw'!H35 -> 0 | AO46: ='QTR Raw'!I35 -> 0 | AP46: ='QTR Raw'!J35 -> 0 | ... CK46: ='QTR Raw'!BE35 -> 0 | CL46: =+CK46 -> 0 | CM46: =+CL46 -> 0 | CN46: =+CM46 -> 0 | CO46: =+CN46 -> 0 | CP46: =+CO46 -> 0 | CQ46: =+CP46 -> 0 | CR46: =+CQ46 -> 0 | CS46: =+CR46 -> 0 | ... DB46: =+DA46 -> 0 | DF46: 0
A47: Exceptional Income / Expenses | B47: ='Annual Raw'!C29+'Annual Raw'!C31+'Annual Raw'!C34+'Annual Raw'!C36 -> 0 | C47: ='Annual Raw'!D29+'Annual Raw'!D31+'Annual Raw'!D34+'Annual Raw'!D36 -> 0 | D47: ='Annual Raw'!E29+'Annual Raw'!E31+'Annual Raw'!E34+'Annual Raw'!E36 -> 0 | E47: ='Annual Raw'!F29+'Annual Raw'!F31+'Annual Raw'!F34+'Annual Raw'!F36 -> 0 | F47: ='Annual Raw'!G29+'Annual Raw'!G31+'Annual Raw'!G34+'Annual Raw'!G36 -> 0 | G47: ='Annual Raw'!H29+'Annual Raw'!H31+'Annual Raw'!H34+'Annual Raw'!H36 -> 0 | H47: ='Annual Raw'!I29+'Annual Raw'!I31+'Annual Raw'!I34+'Annual Raw'!I36 -> 0 | I47: ='Annual Raw'!J29+'Annual Raw'!J31+'Annual Raw'!J34+'Annual Raw'!J36 -> 0 | ... AA47: ='Annual Raw'!AB29+'Annual Raw'!AB31+'Annual Raw'!AB34+'Annual Raw'!AB36 -> 0 | AB47: =+SUM(CM47:CP47) -> 0 | AC47: =+SUM(CQ47:CT47) -> 0 | AD47: =+SUM(CU47:CX47) -> 0 | AE47: =+SUM(CY47:DB47) -> 0 | AI47: ='QTR Raw'!C26+'QTR Raw'!C31+'QTR Raw'!C32+'QTR Raw'!C33+'QTR Raw'!C36+'QTR Raw'!C37+'QTR Raw'!C39 -> 0 | AJ47: ='QTR Raw'!D26+'QTR Raw'!D31+'QTR Raw'!D32+'QTR Raw'!D33+'QTR Raw'!D36+'QTR Raw'!D37+'QTR Raw'!D39 -> 0 | AK47: ='QTR Raw'!E26+'QTR Raw'!E31+'QTR Raw'!E32+'QTR Raw'!E33+'QTR Raw'!E36+'QTR Raw'!E37+'QTR Raw'!E39 -> 0 | AL47: ='QTR Raw'!F26+'QTR Raw'!F31+'QTR Raw'!F32+'QTR Raw'!F33+'QTR Raw'!F36+'QTR Raw'!F37+'QTR Raw'!F39 -> 0 | AM47: ='QTR Raw'!G26+'QTR Raw'!G31+'QTR Raw'!G32+'QTR Raw'!G33+'QTR Raw'!G36+'QTR Raw'!G37+'QTR Raw'!G39 -> 0 | AN47: ='QTR Raw'!H26+'QTR Raw'!H31+'QTR Raw'!H32+'QTR Raw'!H33+'QTR Raw'!H36+'QTR Raw'!H37+'QTR Raw'!H39 -> 0 | AO47: ='QTR Raw'!I26+'QTR Raw'!I31+'QTR Raw'!I32+'QTR Raw'!I33+'QTR Raw'!I36+'QTR Raw'!I37+'QTR Raw'!I39 -> 0 | AP47: ='QTR Raw'!J26+'QTR Raw'!J31+'QTR Raw'!J32+'QTR Raw'!J33+'QTR Raw'!J36+'QTR Raw'!J37+'QTR Raw'!J39 -> 0 | ... CK47: ='QTR Raw'!BE26+'QTR Raw'!BE31+'QTR Raw'!BE32+'QTR Raw'!BE33+'QTR Raw'!BE36+'QTR Raw'!BE37+'QTR Raw'!BE39 -> 0 | DF47: 0
A48: Consolidated Net Profit | B48: =B41+B45+B46+B47 -> 0 | C48: =C41+C45+C46+C47 -> 0 | D48: =D41+D45+D46+D47 -> 0 | E48: =E41+E45+E46+E47 -> 0 | F48: =F41+F45+F46+F47 -> 0 | G48: =G41+G45+G46+G47 -> 0 | H48: =H41+H45+H46+H47 -> 0 | I48: =I41+I45+I46+I47 -> 0 | ... AE48: =AE41+AE45+AE46+AE47 -> 145.14168 | AI48: =AI41+AI45+AI46+AI47 -> 0 | AJ48: =AJ41+AJ45+AJ46+AJ47 -> 0 | AK48: =AK41+AK45+AK46+AK47 -> 0 | AL48: =AL41+AL45+AL46+AL47 -> 0 | AM48: =AM41+AM45+AM46+AM47 -> 0 | AN48: =AN41+AN45+AN46+AN47 -> 0 | AO48: =AO41+AO45+AO46+AO47 -> 0 | AP48: =AP41+AP45+AP46+AP47 -> 0 | ... DB48: =DB41+DB45+DB46+DB47 -> 56.62716 | DF48: 106.8594
A49: Profit & Loss- Annual (End)
A51: Ace - PAT | B51: ='Annual Raw'!C35 -> 0 | C51: ='Annual Raw'!D35 -> 0 | D51: ='Annual Raw'!E35 -> 0 | E51: ='Annual Raw'!F35 -> 0 | F51: ='Annual Raw'!G35 -> 0 | G51: ='Annual Raw'!H35 -> 0 | H51: ='Annual Raw'!I35 -> 0 | I51: ='Annual Raw'!J35 -> 0 | ... AA51: ='Annual Raw'!AB35 -> 106.8594 | AB51: =+AB48 -> 157.3793 | AC51: =+AC48 -> 146.45164 | AD51: =+AD48 -> 142.80588 | AE51: =+AE48 -> 145.14168 | AI51: ='QTR Raw'!C42 -> 0 | AJ51: ='QTR Raw'!D42 -> 0 | AK51: ='QTR Raw'!E42 -> 0 | AL51: ='QTR Raw'!F42 -> 0 | AM51: ='QTR Raw'!G42 -> 0 | AN51: ='QTR Raw'!H42 -> 0 | AO51: ='QTR Raw'!I42 -> 0 | AP51: ='QTR Raw'!J42 -> 0 | ... CK51: ='QTR Raw'!BE42 -> 23.638 | DF51: 106.8594
A52: Checksum - PAT | B52: =B51-B48 -> 0 | C52: =C51-C48 -> 0 | D52: =D51-D48 -> 0 | E52: =E51-E48 -> 0 | F52: =F51-F48 -> 0 | G52: =G51-G48 -> 0 | H52: =H51-H48 -> 0 | I52: =I51-I48 -> 0 | ... AE52: =AE51-AE48 -> 0 | AI52: =AI51-AI48 -> 0 | AJ52: =AJ51-AJ48 -> 0 | AK52: =AK51-AK48 -> 0 | AL52: =AL51-AL48 -> 0 | AM52: =AM51-AM48 -> 0 | AN52: =AN51-AN48 -> 0 | AO52: =AO51-AO48 -> 0 | AP52: =AP51-AP48 -> 0 | ... CK52: =CK51-CK48 -> -0.001 | DF52: -1.1368684e-13
A53: Ratios (Start)
A54: ROE (%) | B54: =(B48-B47)/B120 -> #DIV/0! | C54: =(C48-C47)/C120 -> #DIV/0! | D54: =(D48-D47)/D120 -> #DIV/0! | E54: =(E48-E47)/E120 -> #DIV/0! | F54: =(F48-F47)/F120 -> #DIV/0! | G54: =(G48-G47)/G120 -> #DIV/0! | H54: =(H48-H47)/H120 -> #DIV/0! | I54: =(I48-I47)/I120 -> #DIV/0! | ... AE54: =(AE48-AE47)/AE120 -> 0.056364615 | AL54: =(SUM(AI48:AL48)-SUM(AI47:AL47))/AL120 -> #DIV/0! | AM54: =(SUM(AJ48:AM48)-SUM(AJ47:AM47))/AM120 -> #DIV/0! | AN54: =(SUM(AK48:AN48)-SUM(AK47:AN47))/AN120 -> #DIV/0! | AO54: =(SUM(AL48:AO48)-SUM(AL47:AO47))/AO120 -> #DIV/0! | AP54: =(SUM(AM48:AP48)-SUM(AM47:AP47))/AP120 -> #DIV/0! | AQ54: =(SUM(AN48:AQ48)-SUM(AN47:AQ47))/AQ120 -> #DIV/0! | AR54: =(SUM(AO48:AR48)-SUM(AO47:AR47))/AR120 -> #DIV/0! | AS54: =(SUM(AP48:AS48)-SUM(AP47:AS47))/AS120 -> #DIV/0! | ... DB54: =(SUM(CY48:DB48)-SUM(CY47:DB47))/DB120 -> 0.056364615 | DF54: 0.055241919
A55: ROCE (%) | B55: =+B34/B129 -> #DIV/0! | C55: =+C34/C129 -> #DIV/0! | D55: =+D34/D129 -> #DIV/0! | E55: =+E34/E129 -> #DIV/0! | F55: =+F34/F129 -> #DIV/0! | G55: =+G34/G129 -> #DIV/0! | H55: =+H34/H129 -> #DIV/0! | I55: =+I34/I129 -> #DIV/0! | ... AE55: =+AE34/AE129 -> 0.13108429 | AL55: =+SUM(AI34:AL34)/AL129 -> #DIV/0! | AM55: =+SUM(AJ34:AM34)/AM129 -> #DIV/0! | AN55: =+SUM(AK34:AN34)/AN129 -> #DIV/0! | AO55: =+SUM(AL34:AO34)/AO129 -> #DIV/0! | AP55: =+SUM(AM34:AP34)/AP129 -> #DIV/0! | AQ55: =+SUM(AN34:AQ34)/AQ129 -> #DIV/0! | AR55: =+SUM(AO34:AR34)/AR129 -> #DIV/0! | AS55: =+SUM(AP34:AS34)/AS129 -> #DIV/0! | ... DB55: =+SUM(CY34:DB34)/DB129 -> 0.13108429 | DF55: 0.06240203
A56: Ratios (End)
A57: Checksum Of qtr to Annual
A58: Revenue - Checksum Of qtr to Annual | N58: =N10-SUM(AI10:AL10) -> 0 | O58: =O10-SUM(AM10:AP10) -> 0 | P58: =P10-SUM(AQ10:AT10) -> 225.0314 | Q58: =Q10-SUM(AU10:AX10) -> 340.5348 | R58: =R10-SUM(AY10:BB10) -> 287.6457 | S58: =S10-SUM(BC10:BF10) -> 438.8292 | T58: =T10-SUM(BG10:BJ10) -> 565.506 | U58: =U10-SUM(BK10:BN10) -> 608.17 | V58: =V10-SUM(BO10:BR10) -> 740.7643 | W58: =W10-SUM(BS10:BV10) -> 200.7601 | X58: =X10-SUM(BW10:BZ10) -> -0.0011 | Y58: =Y10-SUM(CA10:CD10) -> -0.0005 | Z58: =Z10-SUM(CE10:CH10) -> -0.0001 | AA58: =AA10-SUM(CF10:CI10) -> -39.6343 | AB58: =AB10-SUM(CM10:CP10) -> 0 | AC58: =AC10-SUM(CQ10:CT10) -> 0 | AD58: =AD10-SUM(CU10:CX10) -> 0 | AE58: =AE10-SUM(CY10:DB10) -> 0 | DF58: -39.6343
A59: GP - Checksum Of qtr to Annual | N59: =N16-SUM(AI16:AL16) -> 0 | O59: =O16-SUM(AM16:AP16) -> 0 | P59: =P16-SUM(AQ16:AT16) -> 302.9488 | Q59: =Q16-SUM(AU16:AX16) -> 354.3994 | R59: =R16-SUM(AY16:BB16) -> 258.7673 | S59: =S16-SUM(BC16:BF16) -> 389.3497 | T59: =T16-SUM(BG16:BJ16) -> 469.47 | U59: =U16-SUM(BK16:BN16) -> 607.833 | V59: =V16-SUM(BO16:BR16) -> 731.8704 | W59: =W16-SUM(BS16:BV16) -> 200.7502 | X59: =X16-SUM(BW16:BZ16) -> -0.0015 | Y59: =Y16-SUM(CA16:CD16) -> -0.0007 | Z59: =Z16-SUM(CE16:CH16) -> -0.0001 | AA59: =AA16-SUM(CF16:CI16) -> -67.8672 | AB59: =AB16-SUM(CM16:CP16) -> 0 | AC59: =AC16-SUM(CQ16:CT16) -> 0 | AD59: =AD16-SUM(CU16:CX16) -> 0 | AE59: =AE16-SUM(CY16:DB16) -> 0 | DF59: -67.8672
A60: EBITDA - Checksum Of qtr to Annual | N60: =N28-SUM(AI28:AL28) -> 0 | O60: =O28-SUM(AM28:AP28) -> 0 | P60: =P28-SUM(AQ28:AT28) -> 90.9546 | Q60: =Q28-SUM(AU28:AX28) -> 105.2289 | R60: =R28-SUM(AY28:BB28) -> 69.4993 | S60: =S28-SUM(BC28:BF28) -> 82.7927 | T60: =T28-SUM(BG28:BJ28) -> 72.68 | U60: =U28-SUM(BK28:BN28) -> 147.986 | V60: =V28-SUM(BO28:BR28) -> 262.2263 | W60: =W28-SUM(BS28:BV28) -> 85.7804 | X60: =X28-SUM(BW28:BZ28) -> -0.0019 | Y60: =Y28-SUM(CA28:CD28) -> -0.001 | Z60: =Z28-SUM(CE28:CH28) -> -0.0006 | AA60: =AA28-SUM(CF28:CI28) -> -82.2678 | AB60: =AB28-SUM(CM28:CP28) -> 0 | AC60: =AC28-SUM(CQ28:CT28) -> 0 | AD60: =AD28-SUM(CU28:CX28) -> 0 | AE60: =AE28-SUM(CY28:DB28) -> 0 | DF60: -82.2678
A61: PAT - Checksum Of qtr to Annual | N61: =N48-SUM(AI48:AL48) -> 0 | O61: =O48-SUM(AM48:AP48) -> 0 | P61: =P48-SUM(AQ48:AT48) -> 60.3296 | Q61: =Q48-SUM(AU48:AX48) -> -86.6321 | R61: =R48-SUM(AY48:BB48) -> -73.6238 | S61: =S48-SUM(BC48:BF48) -> -79.2104 | T61: =T48-SUM(BG48:BJ48) -> 39.972 | U61: =U48-SUM(BK48:BN48) -> -36.235 | V61: =V48-SUM(BO48:BR48) -> 66.5866 | W61: =W41-SUM(BS41:BV41) -> 18.2462 | X61: =X41-SUM(BW41:BZ41) -> -0.0008 | Y61: =Y41-SUM(CA41:CD41) -> -0.0013 | Z61: =Z41-SUM(CE41:CH41) -> 0.0006 | AA61: =AA41-SUM(CF41:CI41) -> -92.221 | AB61: =AB41-SUM(CM41:CP41) -> 0 | AC61: =AC41-SUM(CQ41:CT41) -> 0 | AD61: =AD41-SUM(CU41:CX41) -> 4.2632564e-13 | AE61: =AE41-SUM(CY41:DB41) -> 0 | DF61: -92.221
A62: Valuation (Start)
A63: Eq | B63: ='Annual Raw'!C104 -> 0 | C63: ='Annual Raw'!D104 -> 0 | D63: ='Annual Raw'!E104 -> 0 | E63: =+F63 -> 24.692 | F63: =+G63 -> 24.692 | G63: =+H63 -> 24.692 | H63: =+I63 -> 24.692 | I63: =+J63 -> 24.692 | J63: =+K63 -> 24.692 | K63: =+L63 -> 24.692 | L63: =+M63 -> 24.692 | ... AA63: =+AB63 -> 24.692 | AB63: =AA63 -> 24.692 | AC63: =AB63 -> 24.692 | AD63: =AC63 -> 24.692 | AE63: =AD63 -> 24.692 | AI63: =+AJ63 -> 24.686 | AJ63: =+AK63 -> 24.686 | AK63: =+AL63 -> 24.686 | AL63: =+AM63 -> 24.686 | AM63: =+AN63 -> 24.686 | AN63: =+AO63 -> 24.686 | AO63: =+AP63 -> 24.686 | AP63: =+AQ63 -> 24.686 | ... CI63: =+CJ63 -> 24.686 | CJ63: ='QTR Raw'!BD45 -> 24.686 | CK63: ='QTR Raw'!BE45 -> 24.692 | CL63: =+CK63 -> 24.692 | CM63: =+CL63 -> 24.692 | CN63: =+CM63 -> 24.692 | CO63: =+CN63 -> 24.692 | CP63: =+CO63 -> 24.692 | CQ63: =+CP63 -> 24.692 | CR63: =+CQ63 -> 24.692 | CS63: =+CR63 -> 24.692 | ... DB63: =+DA63 -> 24.692 | DF63: 24.692
A64: FV | B64: ='Annual Raw'!C105 -> 0 | C64: ='Annual Raw'!D105 -> 0 | D64: ='Annual Raw'!E105 -> 0 | E64: =+F64 -> 2 | F64: =+G64 -> 2 | G64: =+H64 -> 2 | H64: =+I64 -> 2 | I64: =+J64 -> 2 | J64: =+K64 -> 2 | K64: =+L64 -> 2 | L64: =+M64 -> 2 | ... AA64: =+AB64 -> 2 | AB64: =AA64 -> 2 | AC64: =AB64 -> 2 | AD64: =AC64 -> 2 | AE64: =AD64 -> 2 | AI64: =AJ64 -> 2 | AJ64: =AK64 -> 2 | AK64: =AL64 -> 2 | AL64: =AM64 -> 2 | AM64: =AN64 -> 2 | AN64: =AO64 -> 2 | AO64: =AP64 -> 2 | AP64: =AQ64 -> 2 | ... CI64: =CJ64 -> 2 | CJ64: ='QTR Raw'!BD46 -> 2 | CK64: ='QTR Raw'!BE46 -> 2 | CL64: =+CK64 -> 2 | CM64: =+CL64 -> 2 | CN64: =+CM64 -> 2 | CO64: =+CN64 -> 2 | CP64: =+CO64 -> 2 | CQ64: =+CP64 -> 2 | CR64: =+CQ64 -> 2 | CS64: =+CR64 -> 2 | ... DB64: =+DA64 -> 2 | DF64: 2
A65: No of share | B65: =B63/B64 -> #DIV/0! | C65: =C63/C64 -> #DIV/0! | D65: =D63/D64 -> #DIV/0! | E65: =E63/E64 -> 12.346 | F65: =F63/F64 -> 12.346 | G65: =G63/G64 -> 12.346 | H65: =H63/H64 -> 12.346 | I65: =I63/I64 -> 12.346 | ... AE65: =AE63/AE64 -> 12.346 | AI65: =AI63/AI64 -> 12.343 | AJ65: =AJ63/AJ64 -> 12.343 | AK65: =AK63/AK64 -> 12.343 | AL65: =AL63/AL64 -> 12.343 | AM65: =AM63/AM64 -> 12.343 | AN65: =AN63/AN64 -> 12.343 | AO65: =AO63/AO64 -> 12.343 | AP65: =AP63/AP64 -> 12.343 | ... DB65: =DB63/DB64 -> 12.346 | DF65: 12.346
A66: EPS | B66: =(B48-B47)/B65 -> #DIV/0! | C66: =(C48-C47)/C65 -> #DIV/0! | D66: =(D48-D47)/D65 -> #DIV/0! | E66: =(E48-E47)/E65 -> 0 | F66: =(F48-F47)/F65 -> 0 | G66: =(G48-G47)/G65 -> 0 | H66: =(H48-H47)/H65 -> 0 | I66: =(I48-I47)/I65 -> 0 | ... AE66: =(AE48-AE47)/AE65 -> 11.75617 | AI66: =(AI48-AI47)/AI65 -> 0 | AJ66: =(AJ48-AJ47)/AJ65 -> 0 | AK66: =(AK48-AK47)/AK65 -> 0 | AL66: =(AL48-AL47)/AL65 -> 0 | AM66: =(AM48-AM47)/AM65 -> 0 | AN66: =(AN48-AN47)/AN65 -> 0 | AO66: =(AO48-AO47)/AO65 -> 0 | AP66: =(AP48-AP47)/AP65 -> 0 | ... DB66: =(DB48-DB47)/DB65 -> 4.5866807 | DF66: 16.388417
A67: DPS | B67: ='Annual Raw'!C110 -> 0 | C67: ='Annual Raw'!D110 -> 0 | D67: ='Annual Raw'!E110 -> 0 | E67: ='Annual Raw'!F110 -> 0 | F67: ='Annual Raw'!G110 -> 0 | G67: ='Annual Raw'!H110 -> 0 | H67: ='Annual Raw'!I110 -> 0 | I67: ='Annual Raw'!J110 -> 0 | ... AA67: ='Annual Raw'!AB110 -> 2.5 | DF67: 2.5
A68: DPS % of EPS | B68: =B67/B66 -> #DIV/0! | C68: =C67/C66 -> #DIV/0! | D68: =D67/D66 -> #DIV/0! | E68: =E67/E66 -> #DIV/0! | F68: =F67/F66 -> #DIV/0! | G68: =G67/G66 -> #DIV/0! | H68: =H67/H66 -> #DIV/0! | I68: =I67/I66 -> #DIV/0! | ... AE68: =AE67/AE66 -> 0 | DF68: 0.18305611
A69: EPS TTM | B69: =+B66 -> #DIV/0! | C69: =+C66 -> #DIV/0! | D69: =+D66 -> #DIV/0! | E69: =+E66 -> 0 | F69: =+F66 -> 0 | G69: =+G66 -> 0 | H69: =+H66 -> 0 | I69: =+I66 -> 0 | ... AE69: =+AE66 -> 11.75617 | AL69: =SUM(AI66:AL66) -> 0 | AM69: =SUM(AJ66:AM66) -> 0 | AN69: =SUM(AK66:AN66) -> 0 | AO69: =SUM(AL66:AO66) -> 0 | AP69: =SUM(AM66:AP66) -> 0 | AQ69: =SUM(AN66:AQ66) -> 0 | AR69: =SUM(AO66:AR66) -> 0 | AS69: =SUM(AP66:AS66) -> 0 | ... DB69: =SUM(CY66:DB66) -> 11.75617 | DF69: 16.388417
A70: EPS Growth YoY % | C70: =+C69/B69-1 -> #DIV/0! | D70: =+D69/C69-1 -> #DIV/0! | E70: =+E69/D69-1 -> #DIV/0! | F70: =+F69/E69-1 -> #DIV/0! | G70: =+G69/F69-1 -> #DIV/0! | H70: =+H69/G69-1 -> #DIV/0! | I70: =+I69/H69-1 -> #DIV/0! | J70: =+J69/I69-1 -> #DIV/0! | ... AE70: =+AE69/AD69-1 -> 0.016356431 | AP70: =+IF(AL69<0,1-AP69/AL69,AP69/AL69-1) -> #DIV/0! | AQ70: =+IF(AM69<0,1-AQ69/AM69,AQ69/AM69-1) -> #DIV/0! | AR70: =+IF(AN69<0,1-AR69/AN69,AR69/AN69-1) -> #DIV/0! | AS70: =+IF(AO69<0,1-AS69/AO69,AS69/AO69-1) -> #DIV/0! | AT70: =+IF(AP69<0,1-AT69/AP69,AT69/AP69-1) -> #DIV/0! | AU70: =+IF(AQ69<0,1-AU69/AQ69,AU69/AQ69-1) -> #DIV/0! | AV70: =+IF(AR69<0,1-AV69/AR69,AV69/AR69-1) -> #DIV/0! | AW70: =+IF(AS69<0,1-AW69/AS69,AW69/AS69-1) -> #DIV/0! | ... DB70: =+IF(CX69<0,1-DB69/CX69,DB69/CX69-1) -> 0.016356431 | DF70: -0.36568755
A71: Bloomberg Estimate
A72: Estimate deviation
A73: Promoter Share holding % | B73: ='Annual Raw'!C112 -> 0 | C73: ='Annual Raw'!D112 -> 0 | D73: ='Annual Raw'!E112 -> 0 | E73: ='Annual Raw'!F112 -> 0 | F73: ='Annual Raw'!G112 -> 0 | G73: ='Annual Raw'!H112 -> 0 | H73: ='Annual Raw'!I112 -> 0 | I73: ='Annual Raw'!J112 -> 0 | ... AA73: ='Annual Raw'!AB112 -> 53.43 | AI73: ='QTR Raw'!C49 -> 0 | AJ73: ='QTR Raw'!D49 -> 0 | AK73: ='QTR Raw'!E49 -> 0 | AL73: ='QTR Raw'!F49 -> 0 | AM73: ='QTR Raw'!G49 -> 0 | AN73: ='QTR Raw'!H49 -> 0 | AO73: ='QTR Raw'!I49 -> 0 | AP73: ='QTR Raw'!J49 -> 0 | ... CK73: ='QTR Raw'!BE49 -> 53.43 | DF73: 53.43
A74: Pledge Share % | B74: ='Annual Raw'!C113 -> 0 | C74: ='Annual Raw'!D113 -> 0 | D74: ='Annual Raw'!E113 -> 0 | E74: ='Annual Raw'!F113 -> 0 | F74: ='Annual Raw'!G113 -> 0 | G74: ='Annual Raw'!H113 -> 0 | H74: ='Annual Raw'!I113 -> 0 | I74: ='Annual Raw'!J113 -> 0 | ... AA74: ='Annual Raw'!AB113 -> 17.26 | AI74: ='QTR Raw'!C50 -> 0 | AJ74: ='QTR Raw'!D50 -> 0 | AK74: ='QTR Raw'!E50 -> 0 | AL74: ='QTR Raw'!F50 -> 0 | AM74: ='QTR Raw'!G50 -> 0 | AN74: ='QTR Raw'!H50 -> 0 | AO74: ='QTR Raw'!I50 -> 0 | AP74: ='QTR Raw'!J50 -> 0 | ... CK74: ='QTR Raw'!BE50 -> 9.25 | DF74: 17.26
A76: Share Price
A77: Share Price - Close | B77: ='Annual Raw'!C106 -> 0 | C77: ='Annual Raw'!D106 -> 0 | D77: ='Annual Raw'!E106 -> 0 | E77: ='Annual Raw'!F106 -> 0 | F77: ='Annual Raw'!G106 -> 0 | G77: ='Annual Raw'!H106 -> 0 | H77: ='Annual Raw'!I106 -> 0 | I77: ='Annual Raw'!J106 -> 0 | ... AA77: ='Annual Raw'!AB106 -> 586.75 | AB77: =+CP77 -> 586.75 | AC77: =+CT77 -> 586.75 | AD77: =+CX77 -> 586.75 | AE77: =+DB77 -> 586.75 | AJ77: ='QTR Share Price'!HP21 -> 0 | AK77: ='QTR Share Price'!HQ21 -> 0 | AL77: ='QTR Share Price'!HR21 -> 0 | AM77: ='QTR Share Price'!HS21 -> 0 | AN77: ='QTR Share Price'!HT21 -> 0 | AO77: ='QTR Share Price'!HU21 -> 0 | AP77: ='QTR Share Price'!HV21 -> 0 | AQ77: ='QTR Share Price'!HW21 -> 0 | ... CL77: ='QTR Share Price'!JR21 -> 586.75 | CM77: =+CL77 -> 586.75 | CN77: =+CM77 -> 586.75 | CO77: =+CN77 -> 586.75 | CP77: =+CO77 -> 586.75 | CQ77: =+CP77 -> 586.75 | CR77: =+CQ77 -> 586.75 | CS77: =+CR77 -> 586.75 | CT77: =+CS77 -> 586.75 | ... DB77: =+DA77 -> 586.75 | DF77: 586.75
A78: Share Price - High | B78: ='Annual Raw'!C107 -> 0 | C78: ='Annual Raw'!D107 -> 0 | D78: ='Annual Raw'!E107 -> 0 | E78: ='Annual Raw'!F107 -> 0 | F78: ='Annual Raw'!G107 -> 0 | G78: ='Annual Raw'!H107 -> 0 | H78: ='Annual Raw'!I107 -> 0 | I78: ='Annual Raw'!J107 -> 0 | ... AA78: ='Annual Raw'!AB107 -> 727.8 | AB78: =+MAX(CM78:CP78) -> 687.42912 | AC78: =+MAX(CQ78:CT78) -> 653.93902 | AD78: =+MAX(CU78:CX78) -> 617.48125 | AE78: =+MAX(CY78:DB78) -> 612.13285 | AJ78: ='QTR Share Price'!HP19 -> 0 | AK78: ='QTR Share Price'!HQ19 -> 0 | AL78: ='QTR Share Price'!HR19 -> 0 | AM78: ='QTR Share Price'!HS19 -> 0 | AN78: ='QTR Share Price'!HT19 -> 0 | AO78: ='QTR Share Price'!HU19 -> 0 | AP78: ='QTR Share Price'!HV19 -> 0 | AQ78: ='QTR Share Price'!HW19 -> 0 | ... CL78: ='QTR Share Price'!JR19 -> 628 | CM78: =+CM69*CM86 -> 687.42912 | CN78: =+CN69*CN86 -> 684.91894 | CO78: =+CO69*CO86 -> 676.61115 | CP78: =+CP69*CP86 -> 663.74483 | CQ78: =+CQ69*CQ86 -> 653.93902 | CR78: =+CR69*CR86 -> 634.62264 | CS78: =+CS69*CS86 -> 620.37388 | CT78: =+CT69*CT86 -> 617.65761 | ... DB78: =+DB69*DB86 -> 612.13285 | DF78: 727.8
A79: Share Price - Low | B79: ='Annual Raw'!C108 -> 0 | C79: ='Annual Raw'!D108 -> 0 | D79: ='Annual Raw'!E108 -> 0 | E79: ='Annual Raw'!F108 -> 0 | F79: ='Annual Raw'!G108 -> 0 | G79: ='Annual Raw'!H108 -> 0 | H79: ='Annual Raw'!I108 -> 0 | I79: ='Annual Raw'!J108 -> 0 | ... AA79: ='Annual Raw'!AB108 -> 479.75 | AB79: =+MIN(CM79:CP79) -> 531.10156 | AC79: =+MIN(CQ79:CT79) -> 494.22444 | AD79: =+MIN(CU79:CX79) -> 477.33785 | AE79: =+MIN(CY79:DB79) -> 479.68089 | AJ79: =+'QTR Share Price'!HP20 -> 0 | AK79: =+'QTR Share Price'!HQ20 -> 0 | AL79: =+'QTR Share Price'!HR20 -> 0 | AM79: =+'QTR Share Price'!HS20 -> 0 | AN79: =+'QTR Share Price'!HT20 -> 0 | AO79: =+'QTR Share Price'!HU20 -> 0 | AP79: =+'QTR Share Price'!HV20 -> 0 | AQ79: =+'QTR Share Price'!HW20 -> 0 | ... CL79: =+'QTR Share Price'!JR20 -> 502.5 | CM79: =+CM87*CM69 -> 550.05276 | CN79: =+CN87*CN69 -> 548.04421 | CO79: =+CO87*CO69 -> 541.39666 | CP79: =+CP87*CP69 -> 531.10156 | CQ79: =+CQ87*CQ69 -> 523.25534 | CR79: =+CR87*CR69 -> 507.79916 | CS79: =+CS87*CS69 -> 496.39789 | CT79: =+CT87*CT69 -> 494.22444 | ... DB79: =+DB87*DB69 -> 489.80375 | DF79: 479.75
A81: Upside (%) | AB81: =+AB78/AB77-1 -> 0.17158776 | AC81: =+AC78/AC77-1 -> 0.11451047 | AD81: =+AD78/AD77-1 -> 0.052375378 | AE81: =+AE78/AE77-1 -> 0.043260078 | CM81: =+CM78/CM77-1 -> 0.17158776 | CN81: =+CN78/CN77-1 -> 0.16730965 | CO81: =+CO78/CO77-1 -> 0.15315066 | CP81: =+CP78/CP77-1 -> 0.13122255 | CQ81: =+CQ78/CQ77-1 -> 0.11451047 | CR81: =+CR78/CR77-1 -> 0.081589496 | CS81: =+CS78/CS77-1 -> 0.057305286 | CT81: =+CT78/CT77-1 -> 0.052675939 | ... DB81: =+DB78/DB77-1 -> 0.043260078
A82: Downside (%) | AB82: =+AB79/AB77-1 -> -0.094841829 | AC82: =+AC79/AC77-1 -> -0.15769163 | AD82: =+AD79/AD77-1 -> -0.18647149 | AE82: =+AE79/AE77-1 -> -0.18247825 | CM82: =+CM79/CM77-1 -> -0.06254323 | CN82: =+CN79/CN77-1 -> -0.0659664 | CO82: =+CO79/CO77-1 -> -0.077295849 | CP82: =+CP79/CP77-1 -> -0.094841829 | CQ82: =+CQ79/CQ77-1 -> -0.10821416 | CR82: =+CR79/CR77-1 -> -0.13455618 | CS82: =+CS79/CS77-1 -> -0.15398741 | CT82: =+CT79/CT77-1 -> -0.15769163 | ... DB82: =+DB79/DB77-1 -> -0.16522581
A84: PE
A85: PE - Close | B85: =+B77/B69 -> #DIV/0! | C85: =+C77/C69 -> #DIV/0! | D85: =+D77/D69 -> #DIV/0! | E85: =+E77/E69 -> #DIV/0! | F85: =+F77/F69 -> #DIV/0! | G85: =+G77/G69 -> #DIV/0! | H85: =+H77/H69 -> #DIV/0! | I85: =+I77/I69 -> #DIV/0! | ... AE85: =+AE77/AE69 -> 49.909961 | AL85: =+AL77/AL69 -> #DIV/0! | AM85: =+AM77/AM69 -> #DIV/0! | AN85: =+AN77/AN69 -> #DIV/0! | AO85: =+AO77/AO69 -> #DIV/0! | AP85: =+AP77/AP69 -> #DIV/0! | AQ85: =+AQ77/AQ69 -> #DIV/0! | AR85: =+AR77/AR69 -> #DIV/0! | AS85: =+AS77/AS69 -> #DIV/0! | ... DB85: =+DB77/DB69 -> 49.909961 | DF85: 31.452091
A86: PE - High | B86: =+B78/B69 -> #DIV/0! | C86: =+C78/C69 -> #DIV/0! | D86: =+D78/D69 -> #DIV/0! | E86: =+E78/E69 -> #DIV/0! | F86: =+F78/F69 -> #DIV/0! | G86: =+G78/G69 -> #DIV/0! | H86: =+H78/H69 -> #DIV/0! | I86: =+I78/I69 -> #DIV/0! | ... AE86: =+AE78/AE69 -> 52.06907 | AL86: =+AL78/AL69 -> #DIV/0! | AM86: =+AM78/AM69 -> #DIV/0! | AN86: =+AN78/AN69 -> #DIV/0! | AO86: =+AO78/AO69 -> #DIV/0! | AP86: =+AP78/AP69 -> #DIV/0! | AQ86: =+AQ78/AQ69 -> #DIV/0! | AR86: =+AR78/AR69 -> #DIV/0! | AS86: =+AS78/AS69 -> #DIV/0! | ... CL86: =+CL78/CL69 -> 52.06907 | CM86: =+CL86 -> 52.06907 | CN86: =+CM86 -> 52.06907 | CO86: =+CN86 -> 52.06907 | CP86: =+CO86 -> 52.06907 | CQ86: =+CP86 -> 52.06907 | CR86: =+CQ86 -> 52.06907 | CS86: =+CR86 -> 52.06907 | CT86: =+CS86 -> 52.06907 | ... DB86: =+DA86 -> 52.06907 | DF86: 50.706544
A87: PE - Low | B87: =+B79/B69 -> #DIV/0! | C87: =+C79/C69 -> #DIV/0! | D87: =+D79/D69 -> #DIV/0! | E87: =+E79/E69 -> #DIV/0! | F87: =+F79/F69 -> #DIV/0! | G87: =+G79/G69 -> #DIV/0! | H87: =+H79/H69 -> #DIV/0! | I87: =+I79/I69 -> #DIV/0! | ... AE87: =+AE79/AE69 -> 40.802478 | AL87: =+AL79/AL69 -> #DIV/0! | AM87: =+AM79/AM69 -> #DIV/0! | AN87: =+AN79/AN69 -> #DIV/0! | AO87: =+AO79/AO69 -> #DIV/0! | AP87: =+AP79/AP69 -> #DIV/0! | AQ87: =+AQ79/AQ69 -> #DIV/0! | AR87: =+AR79/AR69 -> #DIV/0! | AS87: =+AS79/AS69 -> #DIV/0! | ... CL87: =+CL79/CL69 -> 41.663547 | CM87: =+CL87 -> 41.663547 | CN87: =+CM87 -> 41.663547 | CO87: =+CN87 -> 41.663547 | CP87: =+CO87 -> 41.663547 | CQ87: =+CP87 -> 41.663547 | CR87: =+CQ87 -> 41.663547 | CS87: =+CR87 -> 41.663547 | CT87: =+CS87 -> 41.663547 | ... DB87: =+DA87 -> 41.663547 | DF87: 24.95665
A89: PE - 1Yr Fwd | B89: =+B78/C69 -> #DIV/0! | C89: =+C78/D69 -> #DIV/0! | D89: =+D78/E69 -> #DIV/0! | E89: =+E78/F69 -> #DIV/0! | F89: =+F78/G69 -> #DIV/0! | G89: =+G78/H69 -> #DIV/0! | H89: =+H78/I69 -> #DIV/0! | I89: =+I78/J69 -> #DIV/0! | ... AD89: =+AD78/AE69 -> 52.524014 | AL89: =+AL78/AP69 -> #DIV/0! | AM89: =+AM78/AQ69 -> #DIV/0! | AN89: =+AN78/AR69 -> #DIV/0! | AO89: =+AO78/AS69 -> #DIV/0! | AP89: =+AP78/AT69 -> #DIV/0! | AQ89: =+AQ78/AU69 -> #DIV/0! | AR89: =+AR78/AV69 -> #DIV/0! | AS89: =+AS78/AW69 -> #DIV/0! | ... CL89: =+CL78/CP69 -> 49.26498 | DF89: 68.908106
A90: Correlation | AO90: =+CORREL(AL69:AO69,AL86:AO86) -> #DIV/0! | AP90: =+CORREL(AM69:AP69,AM86:AP86) -> #DIV/0! | AQ90: =+CORREL(AN69:AQ69,AN86:AQ86) -> #DIV/0! | AR90: =+CORREL(AO69:AR69,AO86:AR86) -> #DIV/0! | AS90: =+CORREL(AP69:AS69,AP86:AS86) -> #DIV/0! | AT90: =+CORREL(AQ69:AT69,AQ86:AT86) -> #DIV/0! | AU90: =+CORREL(AR69:AU69,AR86:AU86) -> #DIV/0! | AV90: =+CORREL(AS69:AV69,AS86:AV86) -> #DIV/0! | ... CL90: =+CORREL(CI69:CL69,CI86:CL86) -> -0.89963813
A92: BVPS | E92: =+E$120/E$65 -> 0 | F92: =+F$120/F$65 -> 0 | G92: =+G$120/G$65 -> 0 | H92: =+H$120/H$65 -> 0 | I92: =+I$120/I$65 -> 0 | J92: =+J$120/J$65 -> 0 | K92: =+K$120/K$65 -> 0 | L92: =+L$120/L$65 -> 0 | ... AE92: =+AE$120/AE$65 -> 208.57359 | AL92: =+AL$120/AL$65 -> 0 | AM92: =+AM$120/AM$65 -> 0 | AN92: =+AN$120/AN$65 -> 0 | AO92: =+AO$120/AO$65 -> 0 | AP92: =+AP$120/AP$65 -> 0 | AQ92: =+AQ$120/AQ$65 -> 0 | AR92: =+AR$120/AR$65 -> 0 | AS92: =+AS$120/AS$65 -> 0 | ... DB92: =+DB$120/DB$65 -> 208.57359 | DF92: 150.98114
A93: PB
A94: PB - Close | E94: =+E77/E$92 -> #DIV/0! | F94: =+F77/F$92 -> #DIV/0! | G94: =+G77/G$92 -> #DIV/0! | H94: =+H77/H$92 -> #DIV/0! | I94: =+I77/I$92 -> #DIV/0! | J94: =+J77/J$92 -> #DIV/0! | K94: =+K77/K$92 -> #DIV/0! | L94: =+L77/L$92 -> #DIV/0! | ... AE94: =+AE77/AE$92 -> 2.8131557 | AL94: =+AL77/AL$92 -> #DIV/0! | AM94: =+AM77/AM$92 -> #DIV/0! | AN94: =+AN77/AN$92 -> #DIV/0! | AO94: =+AO77/AO$92 -> #DIV/0! | AP94: =+AP77/AP$92 -> #DIV/0! | AQ94: =+AQ77/AQ$92 -> #DIV/0! | AR94: =+AR77/AR$92 -> #DIV/0! | AS94: =+AS77/AS$92 -> #DIV/0! | ... DB94: =+DB77/DB$92 -> 2.8131557 | DF94: 3.4140025
A95: PB - High | E95: =+E78/E$92 -> #DIV/0! | F95: =+F78/F$92 -> #DIV/0! | G95: =+G78/G$92 -> #DIV/0! | H95: =+H78/H$92 -> #DIV/0! | I95: =+I78/I$92 -> #DIV/0! | J95: =+J78/J$92 -> #DIV/0! | K95: =+K78/K$92 -> #DIV/0! | L95: =+L78/L$92 -> #DIV/0! | ... AE95: =+AE78/AE$92 -> 2.9348531 | AL95: =+AL78/AL$92 -> #DIV/0! | AM95: =+AM78/AM$92 -> #DIV/0! | AN95: =+AN78/AN$92 -> #DIV/0! | AO95: =+AO78/AO$92 -> #DIV/0! | AP95: =+AP78/AP$92 -> #DIV/0! | AQ95: =+AQ78/AQ$92 -> #DIV/0! | AR95: =+AR78/AR$92 -> #DIV/0! | AS95: =+AS78/AS$92 -> #DIV/0! | ... CL95: =+CL78/CL$92 -> 3.9093436 | CM95: =+CL95 -> 3.9093436 | CN95: =+CM95 -> 3.9093436 | CO95: =+CN95 -> 3.9093436 | CP95: =+CO95 -> 3.9093436 | CQ95: =+CP95 -> 3.9093436 | CR95: =+CQ95 -> 3.9093436 | CS95: =+CR95 -> 3.9093436 | CT95: =+CS95 -> 3.9093436 | ... DB95: =+DA95 -> 3.9093436 | DF95: 5.5039986
A96: PB - Low | E96: =+E79/E$92 -> #DIV/0! | F96: =+F79/F$92 -> #DIV/0! | G96: =+G79/G$92 -> #DIV/0! | H96: =+H79/H$92 -> #DIV/0! | I96: =+I79/I$92 -> #DIV/0! | J96: =+J79/J$92 -> #DIV/0! | K96: =+K79/K$92 -> #DIV/0! | L96: =+L79/L$92 -> #DIV/0! | ... AE96: =+AE79/AE$92 -> 2.299816 | AL96: =+AL79/AL$92 -> #DIV/0! | AM96: =+AM79/AM$92 -> #DIV/0! | AN96: =+AN79/AN$92 -> #DIV/0! | AO96: =+AO79/AO$92 -> #DIV/0! | AP96: =+AP79/AP$92 -> #DIV/0! | AQ96: =+AQ79/AQ$92 -> #DIV/0! | AR96: =+AR79/AR$92 -> #DIV/0! | AS96: =+AS79/AS$92 -> #DIV/0! | ... CL96: =+CL79/CL$92 -> 3.1280974 | CM96: =+CL96 -> 3.1280974 | CN96: =+CM96 -> 3.1280974 | CO96: =+CN96 -> 3.1280974 | CP96: =+CO96 -> 3.1280974 | CQ96: =+CP96 -> 3.1280974 | CR96: =+CQ96 -> 3.1280974 | CS96: =+CR96 -> 3.1280974 | CT96: =+CS96 -> 3.1280974 | ... DB96: =+DA96 -> 3.1280974 | DF96: 2.7089476
A98: Sales Rolling | E98: =+E10 -> 0 | F98: =+F10 -> 0 | G98: =+G10 -> 0 | H98: =+H10 -> 0 | I98: =+I10 -> 0 | J98: =+J10 -> 0 | K98: =+K10 -> 0 | L98: =+L10 -> 0 | ... AE98: =+AE10 -> 1781.582 | AL98: =+SUM(AI8:AL8) -> 0 | AM98: =+SUM(AJ8:AM8) -> 0 | AN98: =+SUM(AK8:AN8) -> 0 | AO98: =+SUM(AL8:AO8) -> 0 | AP98: =+SUM(AM8:AP8) -> 0 | AQ98: =+SUM(AN8:AQ8) -> 0 | AR98: =+SUM(AO8:AR8) -> 0 | AS98: =+SUM(AP8:AS8) -> 0 | ... DB98: =+SUM(CY8:DB8) -> 1781.582 | DF98: 1081.0507
A99: Sales Per Share | E99: =+E98/E65 -> 0 | F99: =+F98/F65 -> 0 | G99: =+G98/G65 -> 0 | H99: =+H98/H65 -> 0 | I99: =+I98/I65 -> 0 | J99: =+J98/J65 -> 0 | K99: =+K98/K65 -> 0 | L99: =+L98/L65 -> 0 | ... AE99: =+AE98/AE65 -> 144.30439 | AL99: =+AL98/AL65 -> 0 | AM99: =+AM98/AM65 -> 0 | AN99: =+AN98/AN65 -> 0 | AO99: =+AO98/AO65 -> 0 | AP99: =+AP98/AP65 -> 0 | AQ99: =+AQ98/AQ65 -> 0 | AR99: =+AR98/AR65 -> 0 | AS99: =+AS98/AS65 -> 0 | ... DB99: =+DB98/DB65 -> 144.30439 | DF99: 84.320258
A101: Price to Sales
A102: Price to Sales - Close | E102: =+E77/E$99 -> #DIV/0! | F102: =+F77/F$99 -> #DIV/0! | G102: =+G77/G$99 -> #DIV/0! | H102: =+H77/H$99 -> #DIV/0! | I102: =+I77/I$99 -> #DIV/0! | J102: =+J77/J$99 -> #DIV/0! | K102: =+K77/K$99 -> #DIV/0! | L102: =+L77/L$99 -> #DIV/0! | ... AE102: =+AE77/AE$99 -> 4.0660578 | AL102: =+AL77/AL99 -> #DIV/0! | AM102: =+AM77/AM99 -> #DIV/0! | AN102: =+AN77/AN99 -> #DIV/0! | AO102: =+AO77/AO99 -> #DIV/0! | AP102: =+AP77/AP99 -> #DIV/0! | AQ102: =+AQ77/AQ99 -> #DIV/0! | AR102: =+AR77/AR99 -> #DIV/0! | AS102: =+AS77/AS99 -> #DIV/0! | ... DB102: =+DB77/DB99 -> 4.0660578 | DF102: 6.1130031
A103: Price to Sales - High | E103: =+E78/E$99 -> #DIV/0! | F103: =+F78/F$99 -> #DIV/0! | G103: =+G78/G$99 -> #DIV/0! | H103: =+H78/H$99 -> #DIV/0! | I103: =+I78/I$99 -> #DIV/0! | J103: =+J78/J$99 -> #DIV/0! | K103: =+K78/K$99 -> #DIV/0! | L103: =+L78/L$99 -> #DIV/0! | ... AE103: =+AE78/AE$99 -> 4.2419558 | AL103: =+AL78/AL99 -> #DIV/0! | AM103: =+AM78/AM99 -> #DIV/0! | AN103: =+AN78/AN99 -> #DIV/0! | AO103: =+AO78/AO99 -> #DIV/0! | AP103: =+AP78/AP99 -> #DIV/0! | AQ103: =+AQ78/AQ99 -> #DIV/0! | AR103: =+AR78/AR99 -> #DIV/0! | AS103: =+AS78/AS99 -> #DIV/0! | ... CL103: =+CL78/CL99 -> 6.5785247 | CM103: =+CL103 -> 6.5785247 | CN103: =+CM103 -> 6.5785247 | CO103: =+CN103 -> 6.5785247 | CP103: =+CO103 -> 6.5785247 | CQ103: =+CP103 -> 6.5785247 | CR103: =+CQ103 -> 6.5785247 | CS103: =+CR103 -> 6.5785247 | CT103: =+CS103 -> 6.5785247 | ... DB103: =+DA103 -> 6.5785247 | DF103: 9.855283
A104: Price to Sales - Low | E104: =+E79/E$99 -> #DIV/0! | F104: =+F79/F$99 -> #DIV/0! | G104: =+G79/G$99 -> #DIV/0! | H104: =+H79/H$99 -> #DIV/0! | I104: =+I79/I$99 -> #DIV/0! | J104: =+J79/J$99 -> #DIV/0! | K104: =+K79/K$99 -> #DIV/0! | L104: =+L79/L$99 -> #DIV/0! | ... AE104: =+AE79/AE$99 -> 3.3240907 | AL104: =+AL79/AL99 -> #DIV/0! | AM104: =+AM79/AM99 -> #DIV/0! | AN104: =+AN79/AN99 -> #DIV/0! | AO104: =+AO79/AO99 -> #DIV/0! | AP104: =+AP79/AP99 -> #DIV/0! | AQ104: =+AQ79/AQ99 -> #DIV/0! | AR104: =+AR79/AR99 -> #DIV/0! | AS104: =+AS79/AS99 -> #DIV/0! | ... CL104: =+CL79/CL99 -> 5.2638673 | CM104: =+CL104 -> 5.2638673 | CN104: =+CM104 -> 5.2638673 | CO104: =+CN104 -> 5.2638673 | CP104: =+CO104 -> 5.2638673 | CQ104: =+CP104 -> 5.2638673 | CR104: =+CQ104 -> 5.2638673 | CS104: =+CR104 -> 5.2638673 | CT104: =+CS104 -> 5.2638673 | ... DB104: =+DA104 -> 5.2638673 | DF104: 4.8505544
A107: Market Cap High | B107: =+B78*B65 -> #DIV/0! | C107: =+C78*C65 -> #DIV/0! | D107: =+D78*D65 -> #DIV/0! | E107: =+E78*E65 -> 0 | F107: =+F78*F65 -> 0 | G107: =+G78*G65 -> 0 | H107: =+H78*H65 -> 0 | I107: =+I78*I65 -> 0 | ... AE107: =+AE78*AE65 -> 7557.3922 | AL107: =+AL78*AL65 -> 0 | AM107: =+AM78*AM65 -> 0 | AN107: =+AN78*AN65 -> 0 | AO107: =+AO78*AO65 -> 0 | AP107: =+AP78*AP65 -> 0 | AQ107: =+AQ78*AQ65 -> 0 | AR107: =+AR78*AR65 -> 0 | AS107: =+AS78*AS65 -> 0 | ... DB107: =+DB78*DB65 -> 7557.3922 | DF107: 10259.526
A108: Market Cap Low | B108: =+B79*B65 -> #DIV/0! | C108: =+C79*C65 -> #DIV/0! | D108: =+D79*D65 -> #DIV/0! | E108: =+E79*E65 -> 0 | F108: =+F79*F65 -> 0 | G108: =+G79*G65 -> 0 | H108: =+H79*H65 -> 0 | I108: =+I79*I65 -> 0 | ... AE108: =+AE79*AE65 -> 5922.1402 | AL108: =+AL79*AL65 -> 0 | AM108: =+AM79*AM65 -> 0 | AN108: =+AN79*AN65 -> 0 | AO108: =+AO79*AO65 -> 0 | AP108: =+AP79*AP65 -> 0 | AQ108: =+AQ79*AQ65 -> 0 | AR108: =+AR79*AR65 -> 0 | AS108: =+AS79*AS65 -> 0 | ... DB108: =+DB79*DB65 -> 6047.1171 | DF108: 5049.514
A109: Net Debt | B109: =+B168 -> 0 | C109: =+C168 -> 0 | D109: =+D168 -> 0 | E109: =+E168 -> 0 | F109: =+F168 -> 0 | G109: =+G168 -> 0 | H109: =+H168 -> 0 | I109: =+I168 -> 0 | ... AE109: =+AE168 -> -326.15237 | AL109: =+AL168 -> 0 | AM109: =+AM168 -> #DIV/0! | AN109: =+AN168 -> 0 | AO109: =+AO168 -> #DIV/0! | AP109: =+AP168 -> 0 | AQ109: =+AQ168 -> #DIV/0! | AR109: =+AR168 -> 0 | AS109: =+AS168 -> #DIV/0! | ... DB109: =+DB168 -> -326.15237 | DF109: 343.9407
A110: EV High | B110: =+B107+B109 -> #DIV/0! | C110: =+C107+C109 -> #DIV/0! | D110: =+D107+D109 -> #DIV/0! | E110: =+E107+E109 -> 0 | F110: =+F107+F109 -> 0 | G110: =+G107+G109 -> 0 | H110: =+H107+H109 -> 0 | I110: =+I107+I109 -> 0 | ... AE110: =+AE107+AE109 -> 7231.2398 | AL110: =+AL107+AL109 -> 0 | AM110: =+AM107+AM109 -> #DIV/0! | AN110: =+AN107+AN109 -> 0 | AO110: =+AO107+AO109 -> #DIV/0! | AP110: =+AP107+AP109 -> 0 | AQ110: =+AQ107+AQ109 -> #DIV/0! | AR110: =+AR107+AR109 -> 0 | AS110: =+AS107+AS109 -> #DIV/0! | ... DB110: =+DB107+DB109 -> 7231.2398 | DF110: 10182.577
A111: EV Low | B111: =+B108+B109 -> #DIV/0! | C111: =+C108+C109 -> #DIV/0! | D111: =+D108+D109 -> #DIV/0! | E111: =+E108+E109 -> 0 | F111: =+F108+F109 -> 0 | G111: =+G108+G109 -> 0 | H111: =+H108+H109 -> 0 | I111: =+I108+I109 -> 0 | ... AE111: =+AE108+AE109 -> 5595.9878 | AL111: =+AL108+AL109 -> 0 | AM111: =+AM108+AM109 -> #DIV/0! | AN111: =+AN108+AN109 -> 0 | AO111: =+AO108+AO109 -> #DIV/0! | AP111: =+AP108+AP109 -> 0 | AQ111: =+AQ108+AQ109 -> #DIV/0! | AR111: =+AR108+AR109 -> 0 | AS111: =+AS108+AS109 -> #DIV/0! | ... DB111: =+DB108+DB109 -> 5720.9648 | DF111: 4972.5646
A112: EBITDA | B112: =+B28 -> 0 | C112: =+C28 -> 0 | D112: =+D28 -> 0 | E112: =+E28 -> 0 | F112: =+F28 -> 0 | G112: =+G28 -> 0 | H112: =+H28 -> 0 | I112: =+I28 -> 0 | ... AE112: =+AE28 -> 436.4515 | AL112: =+SUM(AI28:AL28) -> 0 | AM112: =+SUM(AJ28:AM28) -> 0 | AN112: =+SUM(AK28:AN28) -> 0 | AO112: =+SUM(AL28:AO28) -> 0 | AP112: =+SUM(AM28:AP28) -> 0 | AQ112: =+SUM(AN28:AQ28) -> 0 | AR112: =+SUM(AO28:AR28) -> 0 | AS112: =+SUM(AP28:AS28) -> 0 | ... DB112: =+SUM(CY28:DB28) -> 436.4515 | DF112: 238.7822
A113: EV/EBITDA High | B113: =+B110/B112 -> #DIV/0! | C113: =+C110/C112 -> #DIV/0! | D113: =+D110/D112 -> #DIV/0! | E113: =+E110/E112 -> #DIV/0! | F113: =+F110/F112 -> #DIV/0! | G113: =+G110/G112 -> #DIV/0! | H113: =+H110/H112 -> #DIV/0! | I113: =+I110/I112 -> #DIV/0! | ... AE113: =+AE110/AE112 -> 16.568255 | AL113: =+AL110/AL112 -> #DIV/0! | AM113: =+AM110/AM112 -> #DIV/0! | AN113: =+AN110/AN112 -> #DIV/0! | AO113: =+AO110/AO112 -> #DIV/0! | AP113: =+AP110/AP112 -> #DIV/0! | AQ113: =+AQ110/AQ112 -> #DIV/0! | AR113: =+AR110/AR112 -> #DIV/0! | AS113: =+AS110/AS112 -> #DIV/0! | ... DB113: =+DB110/DB112 -> 16.568255 | DF113: 32.41265
...

Sheet QTR Raw
A1: ='Annual Raw'!A1 -> 293601 | B1: X | C1: 201206 | D1: 201209 | E1: 201212 | F1: 201303 | G1: 201306 | H1: 201309 | I1: 201312 | J1: 201403 | K1: 201406 | L1: 201409 | M1: 201412 | N1: 201503 | O1: 201506 | P1: 201509 | Q1: 201512 | R1: 201603 | S1: 201606 | T1: 201609 | U1: 201612 | V1: 201703 | W1: 201706 | X1: 201709 | Y1: 201712 | Z1: 201803 | AA1: 201806 | AB1: 201809 | AC1: 201812 | AD1: 201903 | AE1: 201906 | AF1: 201909 | AG1: 201912 | AH1: 202003 | AI1: 202006 | AJ1: 202009 | AK1: 202012 | AL1: 202103 | AM1: 202106 | AN1: 202109 | AO1: 202112 | AP1: 202203 | AQ1: 202206 | AR1: 202209 | AS1: 202212 | AT1: 202303 | AU1: 202306 | AV1: 202309 | AW1: 202312 | AX1: 202403 | AY1: 202406 | AZ1: 202409 | BA1: 202412 | BB1: 202503 | BC1: 202506 | BD1: 202509 | BE1: 202512 | BF1: 202603 | BG1: 202606 | BH1: 202609 | BI1: 202612 | BJ1: 202703 | BK1: 202706 | BL1: 202709 | BM1: 202712 | BN1: 202803 | BO1: 202806 | BP1: 202809 | BQ1: 202812 | BR1: 202903 | BS1: 202906 | BT1: 202909 | BU1: 202912 | BV1: 203003
A3: Field Description | B3: Field Name
A4: Company Name | B4: CD_COMPNAME | C4: =_xll.EQNXTDZ(A1,B4,C1) -> Archean Chemical Industries Ltd.
A5: Date End | B5: QTR_DATE_END | C5: =_xll.EQNXTDZ($A$1,$B5,C$1,$B$1) -> 0 | D5: =_xll.EQNXTDZ($A$1,$B5,D$1,$B$1) -> 0 | E5: =_xll.EQNXTDZ($A$1,$B5,E$1,$B$1) -> 0 | F5: =_xll.EQNXTDZ($A$1,$B5,F$1,$B$1) -> 0 | G5: =_xll.EQNXTDZ($A$1,$B5,G$1,$B$1) -> 0 | H5: =_xll.EQNXTDZ($A$1,$B5,H$1,$B$1) -> 0 | I5: =_xll.EQNXTDZ($A$1,$B5,I$1,$B$1) -> 0 | J5: =_xll.EQNXTDZ($A$1,$B5,J$1,$B$1) -> 0 | ... BV5: =_xll.EQNXTDZ($A$1,$B5,BV$1,$B$1) -> 0
A6: Gross Sales | B6: QTR_GROSS_SALE | C6: =_xll.EQNXTDZ($A$1,$B6,C$1,$B$1) -> 0 | D6: =_xll.EQNXTDZ($A$1,$B6,D$1,$B$1) -> 0 | E6: =_xll.EQNXTDZ($A$1,$B6,E$1,$B$1) -> 0 | F6: =_xll.EQNXTDZ($A$1,$B6,F$1,$B$1) -> 0 | G6: =_xll.EQNXTDZ($A$1,$B6,G$1,$B$1) -> 0 | H6: =_xll.EQNXTDZ($A$1,$B6,H$1,$B$1) -> 0 | I6: =_xll.EQNXTDZ($A$1,$B6,I$1,$B$1) -> 0 | J6: =_xll.EQNXTDZ($A$1,$B6,J$1,$B$1) -> 0 | ... BV6: =_xll.EQNXTDZ($A$1,$B6,BV$1,$B$1) -> 0
A7: Less: Excise Duty | B7: QTR_EXCISE_DUTY | C7: =_xll.EQNXTDZ($A$1,$B7,C$1,$B$1) -> 0 | D7: =_xll.EQNXTDZ($A$1,$B7,D$1,$B$1) -> 0 | E7: =_xll.EQNXTDZ($A$1,$B7,E$1,$B$1) -> 0 | F7: =_xll.EQNXTDZ($A$1,$B7,F$1,$B$1) -> 0 | G7: =_xll.EQNXTDZ($A$1,$B7,G$1,$B$1) -> 0 | H7: =_xll.EQNXTDZ($A$1,$B7,H$1,$B$1) -> 0 | I7: =_xll.EQNXTDZ($A$1,$B7,I$1,$B$1) -> 0 | J7: =_xll.EQNXTDZ($A$1,$B7,J$1,$B$1) -> 0 | ... BV7: =_xll.EQNXTDZ($A$1,$B7,BV$1,$B$1) -> 0
A8: Other operating income | B8: QTR_JOB_WORKS | C8: =_xll.EQNXTDZ($A$1,$B8,C$1,$B$1) -> 0 | D8: =_xll.EQNXTDZ($A$1,$B8,D$1,$B$1) -> 0 | E8: =_xll.EQNXTDZ($A$1,$B8,E$1,$B$1) -> 0 | F8: =_xll.EQNXTDZ($A$1,$B8,F$1,$B$1) -> 0 | G8: =_xll.EQNXTDZ($A$1,$B8,G$1,$B$1) -> 0 | H8: =_xll.EQNXTDZ($A$1,$B8,H$1,$B$1) -> 0 | I8: =_xll.EQNXTDZ($A$1,$B8,I$1,$B$1) -> 0 | J8: =_xll.EQNXTDZ($A$1,$B8,J$1,$B$1) -> 0 | ... BV8: =_xll.EQNXTDZ($A$1,$B8,BV$1,$B$1) -> 0
A9: Net Sales & Other Operating Income | B9: QTR_NET_SALES | C9: =_xll.EQNXTDZ($A$1,$B9,C$1,$B$1) -> 0 | D9: =_xll.EQNXTDZ($A$1,$B9,D$1,$B$1) -> 0 | E9: =_xll.EQNXTDZ($A$1,$B9,E$1,$B$1) -> 0 | F9: =_xll.EQNXTDZ($A$1,$B9,F$1,$B$1) -> 0 | G9: =_xll.EQNXTDZ($A$1,$B9,G$1,$B$1) -> 0 | H9: =_xll.EQNXTDZ($A$1,$B9,H$1,$B$1) -> 0 | I9: =_xll.EQNXTDZ($A$1,$B9,I$1,$B$1) -> 0 | J9: =_xll.EQNXTDZ($A$1,$B9,J$1,$B$1) -> 0 | ... BV9: =_xll.EQNXTDZ($A$1,$B9,BV$1,$B$1) -> 0
A10: (Increase) / Decrease In Stocks | B10: QTR_INC_DEC_INVENTORY | C10: =_xll.EQNXTDZ($A$1,$B10,C$1,$B$1) -> 0 | D10: =_xll.EQNXTDZ($A$1,$B10,D$1,$B$1) -> 0 | E10: =_xll.EQNXTDZ($A$1,$B10,E$1,$B$1) -> 0 | F10: =_xll.EQNXTDZ($A$1,$B10,F$1,$B$1) -> 0 | G10: =_xll.EQNXTDZ($A$1,$B10,G$1,$B$1) -> 0 | H10: =_xll.EQNXTDZ($A$1,$B10,H$1,$B$1) -> 0 | I10: =_xll.EQNXTDZ($A$1,$B10,I$1,$B$1) -> 0 | J10: =_xll.EQNXTDZ($A$1,$B10,J$1,$B$1) -> 0 | ... BV10: =_xll.EQNXTDZ($A$1,$B10,BV$1,$B$1) -> 0
A11: Cost of Services & Raw Materials | B11: QTR_RAW_MATERIAL_COST | C11: =_xll.EQNXTDZ($A$1,$B11,C$1,$B$1) -> 0 | D11: =_xll.EQNXTDZ($A$1,$B11,D$1,$B$1) -> 0 | E11: =_xll.EQNXTDZ($A$1,$B11,E$1,$B$1) -> 0 | F11: =_xll.EQNXTDZ($A$1,$B11,F$1,$B$1) -> 0 | G11: =_xll.EQNXTDZ($A$1,$B11,G$1,$B$1) -> 0 | H11: =_xll.EQNXTDZ($A$1,$B11,H$1,$B$1) -> 0 | I11: =_xll.EQNXTDZ($A$1,$B11,I$1,$B$1) -> 0 | J11: =_xll.EQNXTDZ($A$1,$B11,J$1,$B$1) -> 0 | ... BV11: =_xll.EQNXTDZ($A$1,$B11,BV$1,$B$1) -> 0
A12: Purchase of Finished Goods | B12: QTR_PURCHASE_FIN_GOOD | C12: =_xll.EQNXTDZ($A$1,$B12,C$1,$B$1) -> 0 | D12: =_xll.EQNXTDZ($A$1,$B12,D$1,$B$1) -> 0 | E12: =_xll.EQNXTDZ($A$1,$B12,E$1,$B$1) -> 0 | F12: =_xll.EQNXTDZ($A$1,$B12,F$1,$B$1) -> 0 | G12: =_xll.EQNXTDZ($A$1,$B12,G$1,$B$1) -> 0 | H12: =_xll.EQNXTDZ($A$1,$B12,H$1,$B$1) -> 0 | I12: =_xll.EQNXTDZ($A$1,$B12,I$1,$B$1) -> 0 | J12: =_xll.EQNXTDZ($A$1,$B12,J$1,$B$1) -> 0 | ... BV12: =_xll.EQNXTDZ($A$1,$B12,BV$1,$B$1) -> 0
A13: Excise Duty | B13: QTR_EXCISE | C13: =_xll.EQNXTDZ($A$1,$B13,C$1,$B$1) -> 0 | D13: =_xll.EQNXTDZ($A$1,$B13,D$1,$B$1) -> 0 | E13: =_xll.EQNXTDZ($A$1,$B13,E$1,$B$1) -> 0 | F13: =_xll.EQNXTDZ($A$1,$B13,F$1,$B$1) -> 0 | G13: =_xll.EQNXTDZ($A$1,$B13,G$1,$B$1) -> 0 | H13: =_xll.EQNXTDZ($A$1,$B13,H$1,$B$1) -> 0 | I13: =_xll.EQNXTDZ($A$1,$B13,I$1,$B$1) -> 0 | J13: =_xll.EQNXTDZ($A$1,$B13,J$1,$B$1) -> 0 | ... BV13: =_xll.EQNXTDZ($A$1,$B13,BV$1,$B$1) -> 0
A14: Operating & Manufacturing Expenses | B14: QTR_MFG_EXPS | C14: =_xll.EQNXTDZ($A$1,$B14,C$1,$B$1) -> 0 | D14: =_xll.EQNXTDZ($A$1,$B14,D$1,$B$1) -> 0 | E14: =_xll.EQNXTDZ($A$1,$B14,E$1,$B$1) -> 0 | F14: =_xll.EQNXTDZ($A$1,$B14,F$1,$B$1) -> 0 | G14: =_xll.EQNXTDZ($A$1,$B14,G$1,$B$1) -> 0 | H14: =_xll.EQNXTDZ($A$1,$B14,H$1,$B$1) -> 0 | I14: =_xll.EQNXTDZ($A$1,$B14,I$1,$B$1) -> 0 | J14: =_xll.EQNXTDZ($A$1,$B14,J$1,$B$1) -> 0 | ... BV14: =_xll.EQNXTDZ($A$1,$B14,BV$1,$B$1) -> 0
A15: Electricity Power & Fuel Cost | B15: QTR_ELECTRICITY_POWER_FUEL | C15: =_xll.EQNXTDZ($A$1,$B15,C$1,$B$1) -> 0 | D15: =_xll.EQNXTDZ($A$1,$B15,D$1,$B$1) -> 0 | E15: =_xll.EQNXTDZ($A$1,$B15,E$1,$B$1) -> 0 | F15: =_xll.EQNXTDZ($A$1,$B15,F$1,$B$1) -> 0 | G15: =_xll.EQNXTDZ($A$1,$B15,G$1,$B$1) -> 0 | H15: =_xll.EQNXTDZ($A$1,$B15,H$1,$B$1) -> 0 | I15: =_xll.EQNXTDZ($A$1,$B15,I$1,$B$1) -> 0 | J15: =_xll.EQNXTDZ($A$1,$B15,J$1,$B$1) -> 0 | ... BV15: =_xll.EQNXTDZ($A$1,$B15,BV$1,$B$1) -> 0
A16: Employee Cost | B16: QTR_EXPLOYEE_COST | C16: =_xll.EQNXTDZ($A$1,$B16,C$1,$B$1) -> 0 | D16: =_xll.EQNXTDZ($A$1,$B16,D$1,$B$1) -> 0 | E16: =_xll.EQNXTDZ($A$1,$B16,E$1,$B$1) -> 0 | F16: =_xll.EQNXTDZ($A$1,$B16,F$1,$B$1) -> 0 | G16: =_xll.EQNXTDZ($A$1,$B16,G$1,$B$1) -> 0 | H16: =_xll.EQNXTDZ($A$1,$B16,H$1,$B$1) -> 0 | I16: =_xll.EQNXTDZ($A$1,$B16,I$1,$B$1) -> 0 | J16: =_xll.EQNXTDZ($A$1,$B16,J$1,$B$1) -> 0 | ... BV16: =_xll.EQNXTDZ($A$1,$B16,BV$1,$B$1) -> 0
... A42: Consolidated PAT(after extra items) | B42: QTR_CONS_PAT_EXITM | C42: =_xll.EQNXTDZ($A$1,$B42,C$1,$B$1) -> 0 | D42: =_xll.EQNXTDZ($A$1,$B42,D$1,$B$1) -> 0 | E42: =_xll.EQNXTDZ($A$1,$B42,E$1,$B$1) -> 0 | F42: =_xll.EQNXTDZ($A$1,$B42,F$1,$B$1) -> 0 | G42: =_xll.EQNXTDZ($A$1,$B42,G$1,$B$1) -> 0 | H42: =_xll.EQNXTDZ($A$1,$B42,H$1,$B$1) -> 0 | I42: =_xll.EQNXTDZ($A$1,$B42,I$1,$B$1) -> 0 | J42: =_xll.EQNXTDZ($A$1,$B42,J$1,$B$1) -> 0 | ... BV42: =_xll.EQNXTDZ($A$1,$B42,BV$1,$B$1) -> 0
A44: Field Description | B44: Field Name
A45: Equity Capital | B45: QTR_EQUITY_CAP | C45: =_xll.EQNXTDZ($A$1,$B45,C$1,$B$1) -> 0 | D45: =_xll.EQNXTDZ($A$1,$B45,D$1,$B$1) -> 0 | E45: =_xll.EQNXTDZ($A$1,$B45,E$1,$B$1) -> 0 | F45: =_xll.EQNXTDZ($A$1,$B45,F$1,$B$1) -> 0 | G45: =_xll.EQNXTDZ($A$1,$B45,G$1,$B$1) -> 0 | H45: =_xll.EQNXTDZ($A$1,$B45,H$1,$B$1) -> 0 | I45: =_xll.EQNXTDZ($A$1,$B45,I$1,$B$1) -> 0 | J45: =_xll.EQNXTDZ($A$1,$B45,J$1,$B$1) -> 0 | ... BV45: =_xll.EQNXTDZ($A$1,$B45,BV$1,$B$1) -> 0
A46: Face Value | B46: QTR_FV | C46: =_xll.EQNXTDZ($A$1,$B46,C$1,$B$1) -> 0 | D46: =_xll.EQNXTDZ($A$1,$B46,D$1,$B$1) -> 0 | E46: =_xll.EQNXTDZ($A$1,$B46,E$1,$B$1) -> 0 | F46: =_xll.EQNXTDZ($A$1,$B46,F$1,$B$1) -> 0 | G46: =_xll.EQNXTDZ($A$1,$B46,G$1,$B$1) -> 0 | H46: =_xll.EQNXTDZ($A$1,$B46,H$1,$B$1) -> 0 | I46: =_xll.EQNXTDZ($A$1,$B46,I$1,$B$1) -> 0 | J46: =_xll.EQNXTDZ($A$1,$B46,J$1,$B$1) -> 0 | ... BV46: =_xll.EQNXTDZ($A$1,$B46,BV$1,$B$1) -> 0
A47: Month End | B47: BMONTH_MONTHEND | C47: =_xll.EQNXTDZ($A$1,$B47,C$5) -> 0 | D47: =_xll.EQNXTDZ($A$1,$B47,D$5) -> 0 | E47: =_xll.EQNXTDZ($A$1,$B47,E$5) -> 0 | F47: =_xll.EQNXTDZ($A$1,$B47,F$5) -> 0 | G47: =_xll.EQNXTDZ($A$1,$B47,G$5) -> 0 | H47: =_xll.EQNXTDZ($A$1,$B47,H$5) -> 0 | I47: =_xll.EQNXTDZ($A$1,$B47,I$5) -> 0 | J47: =_xll.EQNXTDZ($A$1,$B47,J$5) -> 0 | ... BV47: =_xll.EQNXTDZ($A$1,$B47,BV$5) -> 0
A48: Close | B48: BMONTH_CLOSE | C48: =_xll.EQNXTDZ($A$1,$B48,C$5) -> 0 | D48: =_xll.EQNXTDZ($A$1,$B48,D$5) -> 0 | E48: =_xll.EQNXTDZ($A$1,$B48,E$5) -> 0 | F48: =_xll.EQNXTDZ($A$1,$B48,F$5) -> 0 | G48: =_xll.EQNXTDZ($A$1,$B48,G$5) -> 0 | H48: =_xll.EQNXTDZ($A$1,$B48,H$5) -> 0 | I48: =_xll.EQNXTDZ($A$1,$B48,I$5) -> 0 | J48: =_xll.EQNXTDZ($A$1,$B48,J$5) -> 0 | ... BV48: =_xll.EQNXTDZ($A$1,$B48,BV$5) -> 0
A49: Total of Promoter and Promoter Group | B49: SHP_TPFTOTALPROMOTER | C49: =_xll.EQNXTDZ($A$1,$B49,C$5) -> 0 | D49: =_xll.EQNXTDZ($A$1,$B49,D$5) -> 0 | E49: =_xll.EQNXTDZ($A$1,$B49,E$5) -> 0 | F49: =_xll.EQNXTDZ($A$1,$B49,F$5) -> 0 | G49: =_xll.EQNXTDZ($A$1,$B49,G$5) -> 0 | H49: =_xll.EQNXTDZ($A$1,$B49,H$5) -> 0 | I49: =_xll.EQNXTDZ($A$1,$B49,I$5) -> 0 | J49: =_xll.EQNXTDZ($A$1,$B49,J$5) -> 0 | ... BV49: =_xll.EQNXTDZ($A$1,$B49,BV$5) -> 0
A50: Total of Promoter and Promoter Group Pledged | B50: SHP_PSHFTOTALPROMOTER | C50: =_xll.EQNXTDZ($A$1,$B50,C$5) -> 0 | D50: =_xll.EQNXTDZ($A$1,$B50,D$5) -> 0 | E50: =_xll.EQNXTDZ($A$1,$B50,E$5) -> 0 | F50: =_xll.EQNXTDZ($A$1,$B50,F$5) -> 0 | G50: =_xll.EQNXTDZ($A$1,$B50,G$5) -> 0 | H50: =_xll.EQNXTDZ($A$1,$B50,H$5) -> 0 | I50: =_xll.EQNXTDZ($A$1,$B50,I$5) -> 0 | J50: =_xll.EQNXTDZ($A$1,$B50,J$5) -> 0 | ... BV50: =_xll.EQNXTDZ($A$1,$B50,BV$5) -> 0
A54: Field Description | B54: Field Name | C54: =_xll.EQNXTDZ($A$1,$B54,C$5) -> 0 | D54: =_xll.EQNXTDZ($A$1,$B54,D$5) -> 0 | E54: =_xll.EQNXTDZ($A$1,$B54,E$5) -> 0 | F54: =_xll.EQNXTDZ($A$1,$B54,F$5) -> 0 | G54: =_xll.EQNXTDZ($A$1,$B54,G$5) -> 0 | H54: =_xll.EQNXTDZ($A$1,$B54,H$5) -> 0 | I54: =_xll.EQNXTDZ($A$1,$B54,I$5) -> 0 | J54: =_xll.EQNXTDZ($A$1,$B54,J$5) -> 0 | ... BV54: =_xll.EQNXTDZ($A$1,$B54,BV$5) -> 0
A55: Year End | B55: QTRB_DATE_END | C55: =_xll.EQNXTDZ($A$1,$B55,C$5,$B$1) -> 0 | D55: =_xll.EQNXTDZ($A$1,$B55,D$5,$B$1) -> 0 | E55: =_xll.EQNXTDZ($A$1,$B55,E$5,$B$1) -> 0 | F55: =_xll.EQNXTDZ($A$1,$B55,F$5,$B$1) -> 0 | G55: =_xll.EQNXTDZ($A$1,$B55,G$5,$B$1) -> 0 | H55: =_xll.EQNXTDZ($A$1,$B55,H$5,$B$1) -> 0 | I55: =_xll.EQNXTDZ($A$1,$B55,I$5,$B$1) -> 0 | J55: =_xll.EQNXTDZ($A$1,$B55,J$5,$B$1) -> 0 | ... BV55: =_xll.EQNXTDZ($A$1,$B55,BV$5,$B$1) -> 0
A56: Share Capital | B56: QTRB_SHARE_CAPITAL | C56: =_xll.EQNXTDZ($A$1,$B56,C$5,$B$1) -> 0 | D56: =_xll.EQNXTDZ($A$1,$B56,D$5,$B$1) -> 0 | E56: =_xll.EQNXTDZ($A$1,$B56,E$5,$B$1) -> 0 | F56: =_xll.EQNXTDZ($A$1,$B56,F$5,$B$1) -> 0 | G56: =_xll.EQNXTDZ($A$1,$B56,G$5,$B$1) -> 0 | H56: =_xll.EQNXTDZ($A$1,$B56,H$5,$B$1) -> 0 | I56: =_xll.EQNXTDZ($A$1,$B56,I$5,$B$1) -> 0 | J56: =_xll.EQNXTDZ($A$1,$B56,J$5,$B$1) -> 0 | ... BV56: =_xll.EQNXTDZ($A$1,$B56,BV$5,$B$1) -> 0
A57: Share Warrants & outstandings | B57: QTRB_SHAREWARNDOUT | C57: =_xll.EQNXTDZ($A$1,$B57,C$5,$B$1) -> 0 | D57: =_xll.EQNXTDZ($A$1,$B57,D$5,$B$1) -> 0 | E57: =_xll.EQNXTDZ($A$1,$B57,E$5,$B$1) -> 0 | F57: =_xll.EQNXTDZ($A$1,$B57,F$5,$B$1) -> 0 | G57: =_xll.EQNXTDZ($A$1,$B57,G$5,$B$1) -> 0 | H57: =_xll.EQNXTDZ($A$1,$B57,H$5,$B$1) -> 0 | I57: =_xll.EQNXTDZ($A$1,$B57,I$5,$B$1) -> 0 | J57: =_xll.EQNXTDZ($A$1,$B57,J$5,$B$1) -> 0 | ... BV57: =_xll.EQNXTDZ($A$1,$B57,BV$5,$B$1) -> 0
A58: Reserves & Surplus | B58: QTRB_RESERVE | C58: =_xll.EQNXTDZ($A$1,$B58,C$5,$B$1) -> 0 | D58: =_xll.EQNXTDZ($A$1,$B58,D$5,$B$1) -> 0 | E58: =_xll.EQNXTDZ($A$1,$B58,E$5,$B$1) -> 0 | F58: =_xll.EQNXTDZ($A$1,$B58,F$5,$B$1) -> 0 | G58: =_xll.EQNXTDZ($A$1,$B58,G$5,$B$1) -> 0 | H58: =_xll.EQNXTDZ($A$1,$B58,H$5,$B$1) -> 0 | I58: =_xll.EQNXTDZ($A$1,$B58,I$5,$B$1) -> 0 | J58: =_xll.EQNXTDZ($A$1,$B58,J$5,$B$1) -> 0 | ... BV58: =_xll.EQNXTDZ($A$1,$B58,BV$5,$B$1) -> 0
A59: Shareholder's Funds | B59: QTRB_SHAREHODERS_FUNDS | C59: =_xll.EQNXTDZ($A$1,$B59,C$5,$B$1) -> 0 | D59: =_xll.EQNXTDZ($A$1,$B59,D$5,$B$1) -> 0 | E59: =_xll.EQNXTDZ($A$1,$B59,E$5,$B$1) -> 0 | F59: =_xll.EQNXTDZ($A$1,$B59,F$5,$B$1) -> 0 | G59: =_xll.EQNXTDZ($A$1,$B59,G$5,$B$1) -> 0 | H59: =_xll.EQNXTDZ($A$1,$B59,H$5,$B$1) -> 0 | I59: =_xll.EQNXTDZ($A$1,$B59,I$5,$B$1) -> 0 | J59: =_xll.EQNXTDZ($A$1,$B59,J$5,$B$1) -> 0 | ... BV59: =_xll.EQNXTDZ($A$1,$B59,BV$5,$B$1) -> 0
A60: Minority Interest | B60: QTRB_MINORITY_INTEREST_BS | C60: =_xll.EQNXTDZ($A$1,$B60,C$5,$B$1) -> 0 | D60: =_xll.EQNXTDZ($A$1,$B60,D$5,$B$1) -> 0 | E60: =_xll.EQNXTDZ($A$1,$B60,E$5,$B$1) -> 0 | F60: =_xll.EQNXTDZ($A$1,$B60,F$5,$B$1) -> 0 | G60: =_xll.EQNXTDZ($A$1,$B60,G$5,$B$1) -> 0 | H60: =_xll.EQNXTDZ($A$1,$B60,H$5,$B$1) -> 0 | I60: =_xll.EQNXTDZ($A$1,$B60,I$5,$B$1) -> 0 | J60: =_xll.EQNXTDZ($A$1,$B60,J$5,$B$1) -> 0 | ... BV60: =_xll.EQNXTDZ($A$1,$B60,BV$5,$B$1) -> 0
A61: Long Term Borrowings | B61: QTRB_TOTAL_DEBTS | C61: =_xll.EQNXTDZ($A$1,$B61,C$5,$B$1) -> 0 | D61: =_xll.EQNXTDZ($A$1,$B61,D$5,$B$1) -> 0 | E61: =_xll.EQNXTDZ($A$1,$B61,E$5,$B$1) -> 0 | F61: =_xll.EQNXTDZ($A$1,$B61,F$5,$B$1) -> 0 | G61: =_xll.EQNXTDZ($A$1,$B61,G$5,$B$1) -> 0 | H61: =_xll.EQNXTDZ($A$1,$B61,H$5,$B$1) -> 0 | I61: =_xll.EQNXTDZ($A$1,$B61,I$5,$B$1) -> 0 | J61: =_xll.EQNXTDZ($A$1,$B61,J$5,$B$1) -> 0 | ... BV61: =_xll.EQNXTDZ($A$1,$B61,BV$5,$B$1) -> 0
A62: Secured Loans | B62: QTRB_SECURED_LOANS | C62: =_xll.EQNXTDZ($A$1,$B62,C$5,$B$1) -> 0 | D62: =_xll.EQNXTDZ($A$1,$B62,D$5,$B$1) -> 0 | E62: =_xll.EQNXTDZ($A$1,$B62,E$5,$B$1) -> 0 | F62: =_xll.EQNXTDZ($A$1,$B62,F$5,$B$1) -> 0 | G62: =_xll.EQNXTDZ($A$1,$B62,G$5,$B$1) -> 0 | H62: =_xll.EQNXTDZ($A$1,$B62,H$5,$B$1) -> 0 | I62: =_xll.EQNXTDZ($A$1,$B62,I$5,$B$1) -> 0 | J62: =_xll.EQNXTDZ($A$1,$B62,J$5,$B$1) -> 0 | ... BV62: =_xll.EQNXTDZ($A$1,$B62,BV$5,$B$1) -> 0
A63: Unsecured Loans | B63: QTRB_UNSECURED_LOANS_NF | C63: =_xll.EQNXTDZ($A$1,$B63,C$5,$B$1) -> 0 | D63: =_xll.EQNXTDZ($A$1,$B63,D$5,$B$1) -> 0 | E63: =_xll.EQNXTDZ($A$1,$B63,E$5,$B$1) -> 0 | F63: =_xll.EQNXTDZ($A$1,$B63,F$5,$B$1) -> 0 | G63: =_xll.EQNXTDZ($A$1,$B63,G$5,$B$1) -> 0 | H63: =_xll.EQNXTDZ($A$1,$B63,H$5,$B$1) -> 0 | I63: =_xll.EQNXTDZ($A$1,$B63,I$5,$B$1) -> 0 | J63: =_xll.EQNXTDZ($A$1,$B63,J$5,$B$1) -> 0 | ... BV63: =_xll.EQNXTDZ($A$1,$B63,BV$5,$B$1) -> 0
A64: Other Long Term Liabilities | B64: QTRB_OTHER_LT_LIABILITIES | C64: =_xll.EQNXTDZ($A$1,$B64,C$5,$B$1) -> 0 | D64: =_xll.EQNXTDZ($A$1,$B64,D$5,$B$1) -> 0 | E64: =_xll.EQNXTDZ($A$1,$B64,E$5,$B$1) -> 0 | F64: =_xll.EQNXTDZ($A$1,$B64,F$5,$B$1) -> 0 | G64: =_xll.EQNXTDZ($A$1,$B64,G$5,$B$1) -> 0 | H64: =_xll.EQNXTDZ($A$1,$B64,H$5,$B$1) -> 0 | I64: =_xll.EQNXTDZ($A$1,$B64,I$5,$B$1) -> 0 | J64: =_xll.EQNXTDZ($A$1,$B64,J$5,$B$1) -> 0 | ... BV64: =_xll.EQNXTDZ($A$1,$B64,BV$5,$B$1) -> 0
A65: Long Term Trade Payables | B65: QTRB_LT_TRADE_PAYABLE | C65: =_xll.EQNXTDZ($A$1,$B65,C$5,$B$1) -> 0 | D65: =_xll.EQNXTDZ($A$1,$B65,D$5,$B$1) -> 0 | E65: =_xll.EQNXTDZ($A$1,$B65,E$5,$B$1) -> 0 | F65: =_xll.EQNXTDZ($A$1,$B65,F$5,$B$1) -> 0 | G65: =_xll.EQNXTDZ($A$1,$B65,G$5,$B$1) -> 0 | H65: =_xll.EQNXTDZ($A$1,$B65,H$5,$B$1) -> 0 | I65: =_xll.EQNXTDZ($A$1,$B65,I$5,$B$1) -> 0 | J65: =_xll.EQNXTDZ($A$1,$B65,J$5,$B$1) -> 0 | ... BV65: =_xll.EQNXTDZ($A$1,$B65,BV$5,$B$1) -> 0
A66: Lont Term Provisions | B66: QTRB_LT_PROVISIONS | C66: =_xll.EQNXTDZ($A$1,$B66,C$5,$B$1) -> 0 | D66: =_xll.EQNXTDZ($A$1,$B66,D$5,$B$1) -> 0 | E66: =_xll.EQNXTDZ($A$1,$B66,E$5,$B$1) -> 0 | F66: =_xll.EQNXTDZ($A$1,$B66,F$5,$B$1) -> 0 | G66: =_xll.EQNXTDZ($A$1,$B66,G$5,$B$1) -> 0 | H66: =_xll.EQNXTDZ($A$1,$B66,H$5,$B$1) -> 0 | I66: =_xll.EQNXTDZ($A$1,$B66,I$5,$B$1) -> 0 | J66: =_xll.EQNXTDZ($A$1,$B66,J$5,$B$1) -> 0 | ... BV66: =_xll.EQNXTDZ($A$1,$B66,BV$5,$B$1) -> 0
... A97: Total Assets | B97: QTRB_TOTAL_APPLICATIONS | C97: =_xll.EQNXTDZ($A$1,$B97,C$5,$B$1) -> 0 | D97: =_xll.EQNXTDZ($A$1,$B97,D$5,$B$1) -> 0 | E97: =_xll.EQNXTDZ($A$1,$B97,E$5,$B$1) -> 0 | F97: =_xll.EQNXTDZ($A$1,$B97,F$5,$B$1) -> 0 | G97: =_xll.EQNXTDZ($A$1,$B97,G$5,$B$1) -> 0 | H97: =_xll.EQNXTDZ($A$1,$B97,H$5,$B$1) -> 0 | I97: =_xll.EQNXTDZ($A$1,$B97,I$5,$B$1) -> 0 | J97: =_xll.EQNXTDZ($A$1,$B97,J$5,$B$1) -> 0 | ... BV97: =_xll.EQNXTDZ($A$1,$B97,BV$5,$B$1) -> 0

Sheet Annual Raw
A1: 293601 | B1: X | C1: 200103 | D1: 200203 | E1: 200303 | F1: 200403 | G1: 200503 | H1: 200603 | I1: 200703 | J1: 200803 | K1: 200903 | L1: 201003 | M1: 201103 | N1: 201203 | O1: 201303 | P1: 201403 | Q1: 201503 | R1: 201603 | S1: 201703 | T1: 201803 | U1: 201903 | V1: 202003 | W1: 202103 | X1: 202203 | Y1: 202303 | Z1: 202403 | AA1: 202503 | AB1: 202603 | AC1: 202703 | AD1: 202803 | AE1: 202903 | AF1: 203003
A3: Field Description | B3: Field Name
A4: Company Name | B4: CD_COMPNAME | C4: =_xll.EQNXTDZ(A1,B4,"L") -> Archean Chemical Industries Ltd.
A5: Year End | B5: PL_YEAR_END | C5: =_xll.EQNXTDZ($A$1,$B5,C$1,$B$1) -> 0 | D5: =_xll.EQNXTDZ($A$1,$B5,D$1,$B$1) -> 0 | E5: =_xll.EQNXTDZ($A$1,$B5,E$1,$B$1) -> 0 | F5: =_xll.EQNXTDZ($A$1,$B5,F$1,$B$1) -> 0 | G5: =_xll.EQNXTDZ($A$1,$B5,G$1,$B$1) -> 0 | H5: =_xll.EQNXTDZ($A$1,$B5,H$1,$B$1) -> 0 | I5: =_xll.EQNXTDZ($A$1,$B5,I$1,$B$1) -> 0 | J5: =_xll.EQNXTDZ($A$1,$B5,J$1,$B$1) -> 0 | ... AF5: =_xll.EQNXTDZ($A$1,$B5,AF$1,$B$1) -> 0
A6: Sales Turnover | B6: PL_TOTAL_GROSS_SALES | C6: =_xll.EQNXTDZ($A$1,$B6,C$1,$B$1) -> 0 | D6: =_xll.EQNXTDZ($A$1,$B6,D$1,$B$1) -> 0 | E6: =_xll.EQNXTDZ($A$1,$B6,E$1,$B$1) -> 0 | F6: =_xll.EQNXTDZ($A$1,$B6,F$1,$B$1) -> 0 | G6: =_xll.EQNXTDZ($A$1,$B6,G$1,$B$1) -> 0 | H6: =_xll.EQNXTDZ($A$1,$B6,H$1,$B$1) -> 0 | I6: =_xll.EQNXTDZ($A$1,$B6,I$1,$B$1) -> 0 | J6: =_xll.EQNXTDZ($A$1,$B6,J$1,$B$1) -> 0 | ... AF6: =_xll.EQNXTDZ($A$1,$B6,AF$1,$B$1) -> 0
A7: Less: Inter divisional transfers | B7: PL_INTER_DIV_TRF | C7: =_xll.EQNXTDZ($A$1,$B7,C$1,$B$1) -> 0 | D7: =_xll.EQNXTDZ($A$1,$B7,D$1,$B$1) -> 0 | E7: =_xll.EQNXTDZ($A$1,$B7,E$1,$B$1) -> 0 | F7: =_xll.EQNXTDZ($A$1,$B7,F$1,$B$1) -> 0 | G7: =_xll.EQNXTDZ($A$1,$B7,G$1,$B$1) -> 0 | H7: =_xll.EQNXTDZ($A$1,$B7,H$1,$B$1) -> 0 | I7: =_xll.EQNXTDZ($A$1,$B7,I$1,$B$1) -> 0 | J7: =_xll.EQNXTDZ($A$1,$B7,J$1,$B$1) -> 0 | ... AF7: =_xll.EQNXTDZ($A$1,$B7,AF$1,$B$1) -> 0
A8: Less: Sales Returns | B8: PL_SALES_RETURN | C8: =_xll.EQNXTDZ($A$1,$B8,C$1,$B$1) -> 0 | D8: =_xll.EQNXTDZ($A$1,$B8,D$1,$B$1) -> 0 | E8: =_xll.EQNXTDZ($A$1,$B8,E$1,$B$1) -> 0 | F8: =_xll.EQNXTDZ($A$1,$B8,F$1,$B$1) -> 0 | G8: =_xll.EQNXTDZ($A$1,$B8,G$1,$B$1) -> 0 | H8: =_xll.EQNXTDZ($A$1,$B8,H$1,$B$1) -> 0 | I8: =_xll.EQNXTDZ($A$1,$B8,I$1,$B$1) -> 0 | J8: =_xll.EQNXTDZ($A$1,$B8,J$1,$B$1) -> 0 | ... AF8: =_xll.EQNXTDZ($A$1,$B8,AF$1,$B$1) -> 0
A9: Less: Excise | B9: PL_EXCISE | C9: =_xll.EQNXTDZ($A$1,$B9,C$1,$B$1) -> 0 | D9: =_xll.EQNXTDZ($A$1,$B9,D$1,$B$1) -> 0 | E9: =_xll.EQNXTDZ($A$1,$B9,E$1,$B$1) -> 0 | F9: =_xll.EQNXTDZ($A$1,$B9,F$1,$B$1) -> 0 | G9: =_xll.EQNXTDZ($A$1,$B9,G$1,$B$1) -> 0 | H9: =_xll.EQNXTDZ($A$1,$B9,H$1,$B$1) -> 0 | I9: =_xll.EQNXTDZ($A$1,$B9,I$1,$B$1) -> 0 | J9: =_xll.EQNXTDZ($A$1,$B9,J$1,$B$1) -> 0 | ... AF9: =_xll.EQNXTDZ($A$1,$B9,AF$1,$B$1) -> 0
A10: Net Sales | B10: PL_NET_SALES | C10: =_xll.EQNXTDZ($A$1,$B10,C$1,$B$1) -> 0 | D10: =_xll.EQNXTDZ($A$1,$B10,D$1,$B$1) -> 0 | E10: =_xll.EQNXTDZ($A$1,$B10,E$1,$B$1) -> 0 | F10: =_xll.EQNXTDZ($A$1,$B10,F$1,$B$1) -> 0 | G10: =_xll.EQNXTDZ($A$1,$B10,G$1,$B$1) -> 0 | H10: =_xll.EQNXTDZ($A$1,$B10,H$1,$B$1) -> 0 | I10: =_xll.EQNXTDZ($A$1,$B10,I$1,$B$1) -> 0 | J10: =_xll.EQNXTDZ($A$1,$B10,J$1,$B$1) -> 0 | ... AF10: =_xll.EQNXTDZ($A$1,$B10,AF$1,$B$1) -> 0
A11: Increase/Decrease in Stock | B11: PL_INC_DEC_INVENTORY | C11: =_xll.EQNXTDZ($A$1,$B11,C$1,$B$1) -> 0 | D11: =_xll.EQNXTDZ($A$1,$B11,D$1,$B$1) -> 0 | E11: =_xll.EQNXTDZ($A$1,$B11,E$1,$B$1) -> 0 | F11: =_xll.EQNXTDZ($A$1,$B11,F$1,$B$1) -> 0 | G11: =_xll.EQNXTDZ($A$1,$B11,G$1,$B$1) -> 0 | H11: =_xll.EQNXTDZ($A$1,$B11,H$1,$B$1) -> 0 | I11: =_xll.EQNXTDZ($A$1,$B11,I$1,$B$1) -> 0 | J11: =_xll.EQNXTDZ($A$1,$B11,J$1,$B$1) -> 0 | ... AF11: =_xll.EQNXTDZ($A$1,$B11,AF$1,$B$1) -> 0
A12: Raw Material Consumed | B12: PL_RAW_MATRS_CONSUMED | C12: =_xll.EQNXTDZ($A$1,$B12,C$1,$B$1) -> 0 | D12: =_xll.EQNXTDZ($A$1,$B12,D$1,$B$1) -> 0 | E12: =_xll.EQNXTDZ($A$1,$B12,E$1,$B$1) -> 0 | F12: =_xll.EQNXTDZ($A$1,$B12,F$1,$B$1) -> 0 | G12: =_xll.EQNXTDZ($A$1,$B12,G$1,$B$1) -> 0 | H12: =_xll.EQNXTDZ($A$1,$B12,H$1,$B$1) -> 0 | I12: =_xll.EQNXTDZ($A$1,$B12,I$1,$B$1) -> 0 | J12: =_xll.EQNXTDZ($A$1,$B12,J$1,$B$1) -> 0 | ... AF12: =_xll.EQNXTDZ($A$1,$B12,AF$1,$B$1) -> 0
A13: Power & Fuel Cost | B13: PL_POWER_FUEL | C13: =_xll.EQNXTDZ($A$1,$B13,C$1,$B$1) -> 0 | D13: =_xll.EQNXTDZ($A$1,$B13,D$1,$B$1) -> 0 | E13: =_xll.EQNXTDZ($A$1,$B13,E$1,$B$1) -> 0 | F13: =_xll.EQNXTDZ($A$1,$B13,F$1,$B$1) -> 0 | G13: =_xll.EQNXTDZ($A$1,$B13,G$1,$B$1) -> 0 | H13: =_xll.EQNXTDZ($A$1,$B13,H$1,$B$1) -> 0 | I13: =_xll.EQNXTDZ($A$1,$B13,I$1,$B$1) -> 0 | J13: =_xll.EQNXTDZ($A$1,$B13,J$1,$B$1) -> 0 | ... AF13: =_xll.EQNXTDZ($A$1,$B13,AF$1,$B$1) -> 0
A14: Employee Cost | B14: PL_EMPLOYEES | C14: =_xll.EQNXTDZ($A$1,$B14,C$1,$B$1) -> 0 | D14: =_xll.EQNXTDZ($A$1,$B14,D$1,$B$1) -> 0 | E14: =_xll.EQNXTDZ($A$1,$B14,E$1,$B$1) -> 0 | F14: =_xll.EQNXTDZ($A$1,$B14,F$1,$B$1) -> 0 | G14: =_xll.EQNXTDZ($A$1,$B14,G$1,$B$1) -> 0 | H14: =_xll.EQNXTDZ($A$1,$B14,H$1,$B$1) -> 0 | I14: =_xll.EQNXTDZ($A$1,$B14,I$1,$B$1) -> 0 | J14: =_xll.EQNXTDZ($A$1,$B14,J$1,$B$1) -> 0 | ... AF14: =_xll.EQNXTDZ($A$1,$B14,AF$1,$B$1) -> 0
A15: Operating & Manufacturing Expenses | B15: PL_GEN_OTHER_MFG_EXPS | C15: =_xll.EQNXTDZ($A$1,$B15,C$1,$B$1) -> 0 | D15: =_xll.EQNXTDZ($A$1,$B15,D$1,$B$1) -> 0 | E15: =_xll.EQNXTDZ($A$1,$B15,E$1,$B$1) -> 0 | F15: =_xll.EQNXTDZ($A$1,$B15,F$1,$B$1) -> 0 | G15: =_xll.EQNXTDZ($A$1,$B15,G$1,$B$1) -> 0 | H15: =_xll.EQNXTDZ($A$1,$B15,H$1,$B$1) -> 0 | I15: =_xll.EQNXTDZ($A$1,$B15,I$1,$B$1) -> 0 | J15: =_xll.EQNXTDZ($A$1,$B15,J$1,$B$1) -> 0 | ... AF15: =_xll.EQNXTDZ($A$1,$B15,AF$1,$B$1) -> 0
A16: Cost of Software development | B16: PL_COST_SW | C16: =_xll.EQNXTDZ($A$1,$B16,C$1,$B$1) -> 0 | D16: =_xll.EQNXTDZ($A$1,$B16,D$1,$B$1) -> 0 | E16: =_xll.EQNXTDZ($A$1,$B16,E$1,$B$1) -> 0 | F16: =_xll.EQNXTDZ($A$1,$B16,F$1,$B$1) -> 0 | G16: =_xll.EQNXTDZ($A$1,$B16,G$1,$B$1) -> 0 | H16: =_xll.EQNXTDZ($A$1,$B16,H$1,$B$1) -> 0 | I16: =_xll.EQNXTDZ($A$1,$B16,I$1,$B$1) -> 0 | J16: =_xll.EQNXTDZ($A$1,$B16,J$1,$B$1) -> 0 | ... AF16: =_xll.EQNXTDZ($A$1,$B16,AF$1,$B$1) -> 0
... A36: Profit After Tax from Discontinued Operations | B36: PL_PAT_DIS_OP | C36: =_xll.EQNXTDZ($A$1,$B36,C$1,$B$1) -> 0 | D36: =_xll.EQNXTDZ($A$1,$B36,D$1,$B$1) -> 0 | E36: =_xll.EQNXTDZ($A$1,$B36,E$1,$B$1) -> 0 | F36: =_xll.EQNXTDZ($A$1,$B36,F$1,$B$1) -> 0 | G36: =_xll.EQNXTDZ($A$1,$B36,G$1,$B$1) -> 0 | H36: =_xll.EQNXTDZ($A$1,$B36,H$1,$B$1) -> 0 | I36: =_xll.EQNXTDZ($A$1,$B36,I$1,$B$1) -> 0 | J36: =_xll.EQNXTDZ($A$1,$B36,J$1,$B$1) -> 0 | ... AF36: =_xll.EQNXTDZ($A$1,$B36,AF$1,$B$1) -> 0
A39: Field Description | B39: Field Name
A40: Year End | B40: BS_YEAR_END | C40: =_xll.EQNXTDZ($A$1,$B40,C$1,$B$1) -> 0 | D40: =_xll.EQNXTDZ($A$1,$B40,D$1,$B$1) -> 0 | E40: =_xll.EQNXTDZ($A$1,$B40,E$1,$B$1) -> 0 | F40: =_xll.EQNXTDZ($A$1,$B40,F$1,$B$1) -> 0 | G40: =_xll.EQNXTDZ($A$1,$B40,G$1,$B$1) -> 0 | H40: =_xll.EQNXTDZ($A$1,$B40,H$1,$B$1) -> 0 | I40: =_xll.EQNXTDZ($A$1,$B40,I$1,$B$1) -> 0 | J40: =_xll.EQNXTDZ($A$1,$B40,J$1,$B$1) -> 0 | ... AF40: =_xll.EQNXTDZ($A$1,$B40,AF$1,$B$1) -> 0
A41: Share Capital | B41: BS_SHARE_CAPITAL | C41: =_xll.EQNXTDZ($A$1,$B41,C$1,$B$1) -> 0 | D41: =_xll.EQNXTDZ($A$1,$B41,D$1,$B$1) -> 0 | E41: =_xll.EQNXTDZ($A$1,$B41,E$1,$B$1) -> 0 | F41: =_xll.EQNXTDZ($A$1,$B41,F$1,$B$1) -> 0 | G41: =_xll.EQNXTDZ($A$1,$B41,G$1,$B$1) -> 0 | H41: =_xll.EQNXTDZ($A$1,$B41,H$1,$B$1) -> 0 | I41: =_xll.EQNXTDZ($A$1,$B41,I$1,$B$1) -> 0 | J41: =_xll.EQNXTDZ($A$1,$B41,J$1,$B$1) -> 0 | ... AF41: =_xll.EQNXTDZ($A$1,$B41,AF$1,$B$1) -> 0
A42: Share Warrants & Outstandings | B42: BS_SHAREWROUTST | C42: =_xll.EQNXTDZ($A$1,$B42,C$1,$B$1) -> 0 | D42: =_xll.EQNXTDZ($A$1,$B42,D$1,$B$1) -> 0 | E42: =_xll.EQNXTDZ($A$1,$B42,E$1,$B$1) -> 0 | F42: =_xll.EQNXTDZ($A$1,$B42,F$1,$B$1) -> 0 | G42: =_xll.EQNXTDZ($A$1,$B42,G$1,$B$1) -> 0 | H42: =_xll.EQNXTDZ($A$1,$B42,H$1,$B$1) -> 0 | I42: =_xll.EQNXTDZ($A$1,$B42,I$1,$B$1) -> 0 | J42: =_xll.EQNXTDZ($A$1,$B42,J$1,$B$1) -> 0 | ... AF42: =_xll.EQNXTDZ($A$1,$B42,AF$1,$B$1) -> 0
A43: Total Reserves | B43: BS_RESERVE | C43: =_xll.EQNXTDZ($A$1,$B43,C$1,$B$1) -> 0 | D43: =_xll.EQNXTDZ($A$1,$B43,D$1,$B$1) -> 0 | E43: =_xll.EQNXTDZ($A$1,$B43,E$1,$B$1) -> 0 | F43: =_xll.EQNXTDZ($A$1,$B43,F$1,$B$1) -> 0 | G43: =_xll.EQNXTDZ($A$1,$B43,G$1,$B$1) -> 0 | H43: =_xll.EQNXTDZ($A$1,$B43,H$1,$B$1) -> 0 | I43: =_xll.EQNXTDZ($A$1,$B43,I$1,$B$1) -> 0 | J43: =_xll.EQNXTDZ($A$1,$B43,J$1,$B$1) -> 0 | ... AF43: =_xll.EQNXTDZ($A$1,$B43,AF$1,$B$1) -> 0
A44: Shareholder's Funds | B44: BS_SHAREHODERS_FUNDS | C44: =_xll.EQNXTDZ($A$1,$B44,C$1,$B$1) -> 0 | D44: =_xll.EQNXTDZ($A$1,$B44,D$1,$B$1) -> 0 | E44: =_xll.EQNXTDZ($A$1,$B44,E$1,$B$1) -> 0 | F44: =_xll.EQNXTDZ($A$1,$B44,F$1,$B$1) -> 0 | G44: =_xll.EQNXTDZ($A$1,$B44,G$1,$B$1) -> 0 | H44: =_xll.EQNXTDZ($A$1,$B44,H$1,$B$1) -> 0 | I44: =_xll.EQNXTDZ($A$1,$B44,I$1,$B$1) -> 0 | J44: =_xll.EQNXTDZ($A$1,$B44,J$1,$B$1) -> 0 | ... AF44: =_xll.EQNXTDZ($A$1,$B44,AF$1,$B$1) -> 0
A45: Minority Interest | B45: BS_MINORITY_INTEREST | C45: =_xll.EQNXTDZ($A$1,$B45,C$1,$B$1) -> 0 | D45: =_xll.EQNXTDZ($A$1,$B45,D$1,$B$1) -> 0 | E45: =_xll.EQNXTDZ($A$1,$B45,E$1,$B$1) -> 0 | F45: =_xll.EQNXTDZ($A$1,$B45,F$1,$B$1) -> 0 | G45: =_xll.EQNXTDZ($A$1,$B45,G$1,$B$1) -> 0 | H45: =_xll.EQNXTDZ($A$1,$B45,H$1,$B$1) -> 0 | I45: =_xll.EQNXTDZ($A$1,$B45,I$1,$B$1) -> 0 | J45: =_xll.EQNXTDZ($A$1,$B45,J$1,$B$1) -> 0 | ... AF45: =_xll.EQNXTDZ($A$1,$B45,AF$1,$B$1) -> 0
A46: Long-Term Borrowings | B46: BS_LTRM_BORROWING | C46: =_xll.EQNXTDZ($A$1,$B46,C$1,$B$1) -> 0 | D46: =_xll.EQNXTDZ($A$1,$B46,D$1,$B$1) -> 0 | E46: =_xll.EQNXTDZ($A$1,$B46,E$1,$B$1) -> 0 | F46: =_xll.EQNXTDZ($A$1,$B46,F$1,$B$1) -> 0 | G46: =_xll.EQNXTDZ($A$1,$B46,G$1,$B$1) -> 0 | H46: =_xll.EQNXTDZ($A$1,$B46,H$1,$B$1) -> 0 | I46: =_xll.EQNXTDZ($A$1,$B46,I$1,$B$1) -> 0 | J46: =_xll.EQNXTDZ($A$1,$B46,J$1,$B$1) -> 0 | ... AF46: =_xll.EQNXTDZ($A$1,$B46,AF$1,$B$1) -> 0
A47: Secured Loans | B47: BS_SECURED_LOANS | C47: =_xll.EQNXTDZ($A$1,$B47,C$1,$B$1) -> 0 | D47: =_xll.EQNXTDZ($A$1,$B47,D$1,$B$1) -> 0 | E47: =_xll.EQNXTDZ($A$1,$B47,E$1,$B$1) -> 0 | F47: =_xll.EQNXTDZ($A$1,$B47,F$1,$B$1) -> 0 | G47: =_xll.EQNXTDZ($A$1,$B47,G$1,$B$1) -> 0 | H47: =_xll.EQNXTDZ($A$1,$B47,H$1,$B$1) -> 0 | I47: =_xll.EQNXTDZ($A$1,$B47,I$1,$B$1) -> 0 | J47: =_xll.EQNXTDZ($A$1,$B47,J$1,$B$1) -> 0 | ... AF47: =_xll.EQNXTDZ($A$1,$B47,AF$1,$B$1) -> 0
A48: Unsecured Loans | B48: BS_UNSECURED_LOANS_NF | C48: =_xll.EQNXTDZ($A$1,$B48,C$1,$B$1) -> 0 | D48: =_xll.EQNXTDZ($A$1,$B48,D$1,$B$1) -> 0 | E48: =_xll.EQNXTDZ($A$1,$B48,E$1,$B$1) -> 0 | F48: =_xll.EQNXTDZ($A$1,$B48,F$1,$B$1) -> 0 | G48: =_xll.EQNXTDZ($A$1,$B48,G$1,$B$1) -> 0 | H48: =_xll.EQNXTDZ($A$1,$B48,H$1,$B$1) -> 0 | I48: =_xll.EQNXTDZ($A$1,$B48,I$1,$B$1) -> 0 | J48: =_xll.EQNXTDZ($A$1,$B48,J$1,$B$1) -> 0 | ... AF48: =_xll.EQNXTDZ($A$1,$B48,AF$1,$B$1) -> 0
A49: Deferred Tax Assets / Liabilities | B49: BS_NET_DEF_TAX_NF | C49: =_xll.EQNXTDZ($A$1,$B49,C$1,$B$1) -> 0 | D49: =_xll.EQNXTDZ($A$1,$B49,D$1,$B$1) -> 0 | E49: =_xll.EQNXTDZ($A$1,$B49,E$1,$B$1) -> 0 | F49: =_xll.EQNXTDZ($A$1,$B49,F$1,$B$1) -> 0 | G49: =_xll.EQNXTDZ($A$1,$B49,G$1,$B$1) -> 0 | H49: =_xll.EQNXTDZ($A$1,$B49,H$1,$B$1) -> 0 | I49: =_xll.EQNXTDZ($A$1,$B49,I$1,$B$1) -> 0 | J49: =_xll.EQNXTDZ($A$1,$B49,J$1,$B$1) -> 0 | ... AF49: =_xll.EQNXTDZ($A$1,$B49,AF$1,$B$1) -> 0
A50: Other Long Term Liabilities | B50: BS_OTH_LT_LIAB | C50: =_xll.EQNXTDZ($A$1,$B50,C$1,$B$1) -> 0 | D50: =_xll.EQNXTDZ($A$1,$B50,D$1,$B$1) -> 0 | E50: =_xll.EQNXTDZ($A$1,$B50,E$1,$B$1) -> 0 | F50: =_xll.EQNXTDZ($A$1,$B50,F$1,$B$1) -> 0 | G50: =_xll.EQNXTDZ($A$1,$B50,G$1,$B$1) -> 0 | H50: =_xll.EQNXTDZ($A$1,$B50,H$1,$B$1) -> 0 | I50: =_xll.EQNXTDZ($A$1,$B50,I$1,$B$1) -> 0 | J50: =_xll.EQNXTDZ($A$1,$B50,J$1,$B$1) -> 0 | ... AF50: =_xll.EQNXTDZ($A$1,$B50,AF$1,$B$1) -> 0
A51: Long Term Trade Payables | B51: BS_LT_TRADE_PAYABLES | C51: =_xll.EQNXTDZ($A$1,$B51,C$1,$B$1) -> 0 | D51: =_xll.EQNXTDZ($A$1,$B51,D$1,$B$1) -> 0 | E51: =_xll.EQNXTDZ($A$1,$B51,E$1,$B$1) -> 0 | F51: =_xll.EQNXTDZ($A$1,$B51,F$1,$B$1) -> 0 | G51: =_xll.EQNXTDZ($A$1,$B51,G$1,$B$1) -> 0 | H51: =_xll.EQNXTDZ($A$1,$B51,H$1,$B$1) -> 0 | I51: =_xll.EQNXTDZ($A$1,$B51,I$1,$B$1) -> 0 | J51: =_xll.EQNXTDZ($A$1,$B51,J$1,$B$1) -> 0 | ... AF51: =_xll.EQNXTDZ($A$1,$B51,AF$1,$B$1) -> 0
... A99: Estimated Capital Contracts Remaining | B99: BS_ESTIMATED_CAPITAL_CONTRACT | C99: =_xll.EQNXTDZ($A$1,$B99,C$1,$B$1) -> 0 | D99: =_xll.EQNXTDZ($A$1,$B99,D$1,$B$1) -> 0 | E99: =_xll.EQNXTDZ($A$1,$B99,E$1,$B$1) -> 0 | F99: =_xll.EQNXTDZ($A$1,$B99,F$1,$B$1) -> 0 | G99: =_xll.EQNXTDZ($A$1,$B99,G$1,$B$1) -> 0 | H99: =_xll.EQNXTDZ($A$1,$B99,H$1,$B$1) -> 0 | I99: =_xll.EQNXTDZ($A$1,$B99,I$1,$B$1) -> 0 | J99: =_xll.EQNXTDZ($A$1,$B99,J$1,$B$1) -> 0 | ... AF99: =_xll.EQNXTDZ($A$1,$B99,AF$1,$B$1) -> 0
A103: Field Description | B103: Field Name
A104: Equity Paid Up | B104: BS_EQUITY_PAIDUP | C104: =_xll.EQNXTDZ($A$1,$B104,C$1,$B$1) -> 0 | D104: =_xll.EQNXTDZ($A$1,$B104,D$1,$B$1) -> 0 | E104: =_xll.EQNXTDZ($A$1,$B104,E$1,$B$1) -> 0 | F104: =_xll.EQNXTDZ($A$1,$B104,F$1,$B$1) -> 0 | G104: =_xll.EQNXTDZ($A$1,$B104,G$1,$B$1) -> 0 | H104: =_xll.EQNXTDZ($A$1,$B104,H$1,$B$1) -> 0 | I104: =_xll.EQNXTDZ($A$1,$B104,I$1,$B$1) -> 0 | J104: =_xll.EQNXTDZ($A$1,$B104,J$1,$B$1) -> 0 | ... AF104: =_xll.EQNXTDZ($A$1,$B104,AF$1,$B$1) -> 0
A105: Face Value | B105: BS_FACE_VALUE | C105: =_xll.EQNXTDZ($A$1,$B105,C$1,$B$1) -> 0 | D105: =_xll.EQNXTDZ($A$1,$B105,D$1,$B$1) -> 0 | E105: =_xll.EQNXTDZ($A$1,$B105,E$1,$B$1) -> 0 | F105: =_xll.EQNXTDZ($A$1,$B105,F$1,$B$1) -> 0 | G105: =_xll.EQNXTDZ($A$1,$B105,G$1,$B$1) -> 0 | H105: =_xll.EQNXTDZ($A$1,$B105,H$1,$B$1) -> 0 | I105: =_xll.EQNXTDZ($A$1,$B105,I$1,$B$1) -> 0 | J105: =_xll.EQNXTDZ($A$1,$B105,J$1,$B$1) -> 0 | ... AF105: =_xll.EQNXTDZ($A$1,$B105,AF$1,$B$1) -> 0
A106: Close Price (Unit Curr.) | B106: FH_YEAR_PRICE | C106: =_xll.EQNXTDZ($A$1,$B106,C$1,$B$1) -> 0 | D106: =_xll.EQNXTDZ($A$1,$B106,D$1,$B$1) -> 0 | E106: =_xll.EQNXTDZ($A$1,$B106,E$1,$B$1) -> 0 | F106: =_xll.EQNXTDZ($A$1,$B106,F$1,$B$1) -> 0 | G106: =_xll.EQNXTDZ($A$1,$B106,G$1,$B$1) -> 0 | H106: =_xll.EQNXTDZ($A$1,$B106,H$1,$B$1) -> 0 | I106: =_xll.EQNXTDZ($A$1,$B106,I$1,$B$1) -> 0 | J106: =_xll.EQNXTDZ($A$1,$B106,J$1,$B$1) -> 0 | ... AF106: =_xll.EQNXTDZ($A$1,$B106,AF$1,$B$1) -> 0
A107: High Price (Unit Curr.) | B107: FH_HIGH | C107: =_xll.EQNXTDZ($A$1,$B107,C$1,$B$1) -> 0 | D107: =_xll.EQNXTDZ($A$1,$B107,D$1,$B$1) -> 0 | E107: =_xll.EQNXTDZ($A$1,$B107,E$1,$B$1) -> 0 | F107: =_xll.EQNXTDZ($A$1,$B107,F$1,$B$1) -> 0 | G107: =_xll.EQNXTDZ($A$1,$B107,G$1,$B$1) -> 0 | H107: =_xll.EQNXTDZ($A$1,$B107,H$1,$B$1) -> 0 | I107: =_xll.EQNXTDZ($A$1,$B107,I$1,$B$1) -> 0 | J107: =_xll.EQNXTDZ($A$1,$B107,J$1,$B$1) -> 0 | ... AF107: =_xll.EQNXTDZ($A$1,$B107,AF$1,$B$1) -> 0
A108: Low Price (Unit Curr.) | B108: FH_LOW | C108: =_xll.EQNXTDZ($A$1,$B108,C$1,$B$1) -> 0 | D108: =_xll.EQNXTDZ($A$1,$B108,D$1,$B$1) -> 0 | E108: =_xll.EQNXTDZ($A$1,$B108,E$1,$B$1) -> 0 | F108: =_xll.EQNXTDZ($A$1,$B108,F$1,$B$1) -> 0 | G108: =_xll.EQNXTDZ($A$1,$B108,G$1,$B$1) -> 0 | H108: =_xll.EQNXTDZ($A$1,$B108,H$1,$B$1) -> 0 | I108: =_xll.EQNXTDZ($A$1,$B108,I$1,$B$1) -> 0 | J108: =_xll.EQNXTDZ($A$1,$B108,J$1,$B$1) -> 0 | ... AF108: =_xll.EQNXTDZ($A$1,$B108,AF$1,$B$1) -> 0
A109: Market Capitalization | B109: FH_MCAP | C109: =_xll.EQNXTDZ($A$1,$B109,C$1,$B$1) -> 0 | D109: =_xll.EQNXTDZ($A$1,$B109,D$1,$B$1) -> 0 | E109: =_xll.EQNXTDZ($A$1,$B109,E$1,$B$1) -> 0 | F109: =_xll.EQNXTDZ($A$1,$B109,F$1,$B$1) -> 0 | G109: =_xll.EQNXTDZ($A$1,$B109,G$1,$B$1) -> 0 | H109: =_xll.EQNXTDZ($A$1,$B109,H$1,$B$1) -> 0 | I109: =_xll.EQNXTDZ($A$1,$B109,I$1,$B$1) -> 0 | J109: =_xll.EQNXTDZ($A$1,$B109,J$1,$B$1) -> 0 | ... AF109: =_xll.EQNXTDZ($A$1,$B109,AF$1,$B$1) -> 0
A110: Adj DPS(Rs) | B110: FR_ADJ_DPS | C110: =_xll.EQNXTDZ($A$1,$B110,C$1,$B$1) -> 0 | D110: =_xll.EQNXTDZ($A$1,$B110,D$1,$B$1) -> 0 | E110: =_xll.EQNXTDZ($A$1,$B110,E$1,$B$1) -> 0 | F110: =_xll.EQNXTDZ($A$1,$B110,F$1,$B$1) -> 0 | G110: =_xll.EQNXTDZ($A$1,$B110,G$1,$B$1) -> 0 | H110: =_xll.EQNXTDZ($A$1,$B110,H$1,$B$1) -> 0 | I110: =_xll.EQNXTDZ($A$1,$B110,I$1,$B$1) -> 0 | J110: =_xll.EQNXTDZ($A$1,$B110,J$1,$B$1) -> 0 | ... AF110: =_xll.EQNXTDZ($A$1,$B110,AF$1,$B$1) -> 0
A111: Date End | B111: SHP_DATE_END | C111: =_xll.EQNXTDZ($A$1,$B111,C$5) -> 0 | D111: =_xll.EQNXTDZ($A$1,$B111,D$5) -> 0 | E111: =_xll.EQNXTDZ($A$1,$B111,E$5) -> 0 | F111: =_xll.EQNXTDZ($A$1,$B111,F$5) -> 0 | G111: =_xll.EQNXTDZ($A$1,$B111,G$5) -> 0 | H111: =_xll.EQNXTDZ($A$1,$B111,H$5) -> 0 | I111: =_xll.EQNXTDZ($A$1,$B111,I$5) -> 0 | J111: =_xll.EQNXTDZ($A$1,$B111,J$5) -> 0 | ... AF111: =_xll.EQNXTDZ($A$1,$B111,AF$5) -> 0
A112: Total of Promoter and Promoter Group | B112: SHP_TPFTOTALPROMOTER | C112: =_xll.EQNXTDZ($A$1,$B112,C$5) -> 0 | D112: =_xll.EQNXTDZ($A$1,$B112,D$5) -> 0 | E112: =_xll.EQNXTDZ($A$1,$B112,E$5) -> 0 | F112: =_xll.EQNXTDZ($A$1,$B112,F$5) -> 0 | G112: =_xll.EQNXTDZ($A$1,$B112,G$5) -> 0 | H112: =_xll.EQNXTDZ($A$1,$B112,H$5) -> 0 | I112: =_xll.EQNXTDZ($A$1,$B112,I$5) -> 0 | J112: =_xll.EQNXTDZ($A$1,$B112,J$5) -> 0 | ... AF112: =_xll.EQNXTDZ($A$1,$B112,AF$5) -> 0
A113: Total of Promoter and Promoter Group Pledged | B113: SHP_PSHFTOTALPROMOTER | C113: =_xll.EQNXTDZ($A$1,$B113,C$5) -> 0 | D113: =_xll.EQNXTDZ($A$1,$B113,D$5) -> 0 | E113: =_xll.EQNXTDZ($A$1,$B113,E$5) -> 0 | F113: =_xll.EQNXTDZ($A$1,$B113,F$5) -> 0 | G113: =_xll.EQNXTDZ($A$1,$B113,G$5) -> 0 | H113: =_xll.EQNXTDZ($A$1,$B113,H$5) -> 0 | I113: =_xll.EQNXTDZ($A$1,$B113,I$5) -> 0 | J113: =_xll.EQNXTDZ($A$1,$B113,J$5) -> 0 | ... AF113: =_xll.EQNXTDZ($A$1,$B113,AF$5) -> 0

Sheet QTR Share Price
A1: ='QTR Raw'!A1 -> 293601 | C1: 201206 | D1: 201207 | E1: 201208 | F1: 201209 | G1: 201210 | H1: 201211 | I1: 201212 | J1: 201301 | K1: 201302 | L1: 201303 | M1: 201304 | N1: 201305 | O1: 201306 | P1: 201307 | Q1: 201308 | R1: 201309 | S1: 201310 | T1: 201311 | U1: 201312 | V1: 201401 | W1: 201402 | X1: 201403 | Y1: 201404 | Z1: 201405 | AA1: 201406 | AB1: 201407 | AC1: 201408 | AD1: 201409 | AE1: 201410 | AF1: 201411 | AG1: 201412 | AH1: 201501 | AI1: 201502 | AJ1: 201503 | AK1: 201504 | AL1: 201505 | AM1: 201506 | AN1: 201507 | AO1: 201508 | AP1: 201509 | AQ1: 201510 | AR1: 201511 | AS1: 201512 | AT1: 201601 | AU1: 201602 | AV1: 201603 | AW1: 201604 | AX1: 201605 | AY1: 201606 | AZ1: 201607 | BA1: 201608 | BB1: 201609 | BC1: 201610 | BD1: 201611 | BE1: 201612 | BF1: 201701 | BG1: 201702 | BH1: 201703 | BI1: 201704 | BJ1: 201705 | BK1: 201706 | BL1: 201707 | BM1: 201708 | BN1: 201709 | BO1: 201710 | BP1: 201711 | BQ1: 201712 | BR1: 201801 | BS1: 201802 | BT1: 201803 | BU1: 201804 | BV1: 201805 | BW1: 201806 | BX1: 201807 | BY1: 201808 | BZ1: 201809 | CA1: 201810 | CB1: 201811 | CC1: 201812 | CD1: 201901 | CE1: 201902 | CF1: 201903 | CG1: 201904 | CH1: 201905 | CI1: 201906 | CJ1: 201907 | CK1: 201908 | CL1: 201909 | CM1: 201910 | CN1: 201911 | CO1: 201912 | CP1: 202001 | CQ1: 202002 | CR1: 202003 | CS1: 202004 | CT1: 202005 | CU1: 202006 | CV1: 202007 | CW1: 202008 | CX1: 202009 | CY1: 202010 | CZ1: 202011 | DA1: 202012 | DB1: 202101 | DC1: 202102 | DD1: 202103 | DE1: 202104 | DF1: 202105 | DG1: 202106 | DH1: 202107 | DI1: 202108 | DJ1: 202109 | DK1: 202110 | DL1: 202111 | DM1: 202112 | DN1: 202201 | DO1: 202202 | DP1: 202203 | DQ1: 202204 | DR1: 202205 | DS1: 202206 | DT1: 202207 | DU1: 202208 | DV1: 202209 | DW1: 202210 | DX1: 202211 | DY1: 202212 | DZ1: 202301 | EA1: 202302 | EB1: 202303 | EC1: 202304 | ED1: 202305 | EE1: 202306 | EF1: 202307 | EG1: 202308 | EH1: 202309 | EI1: 202310 | EJ1: 202311 | EK1: 202312 | EL1: 202401 | EM1: 202402 | EN1: 202403 | EO1: 202404 | EP1: 202405 | EQ1: 202406 | ER1: 202407 | ES1: 202408 | ET1: 202409 | EU1: 202410 | EV1: 202411 | EW1: 202412 | EX1: 202501 | EY1: 202502 | EZ1: 202503 | FA1: 202504 | FB1: 202505 | FC1: 202506 | FD1: 202507 | FE1: 202508 | FF1: 202509 | FG1: 202510 | FH1: 202511 | FI1: 202512 | FJ1: 202601 | FK1: 202602 | FL1: 202603 | FM1: 202604 | FN1: 202605 | FO1: 202606 | FP1: 202607 | FQ1: 202608 | FR1: 202609 | FS1: 202610 | FT1: 202611 | FU1: 202612 | FV1: 202701 | FW1: 202702 | FX1: 202703 | FY1: 202704 | FZ1: 202705 | GA1: 202706 | GB1: 202707 | GC1: 202708 | GD1: 202709 | GE1: 202710 | GF1: 202711 | GG1: 202712 | GH1: 202801 | GI1: 202802 | GJ1: 202803 | GK1: 202804 | GL1: 202805 | GM1: 202806 | GN1: 202807 | GO1: 202808 | GP1: 202809 | GQ1: 202810 | GR1: 202811 | GS1: 202812 | GT1: 202901 | GU1: 202902 | GV1: 202903 | GW1: 202904 | GX1: 202905 | GY1: 202906 | GZ1: 202907 | HA1: 202908 | HB1: 202909 | HC1: 202910 | HD1: 202911 | HE1: 202912 | HF1: 203001 | HG1: 203002 | HH1: 203003 | HM1: 201206 | HN1: 201207 | HO1: 201208 | HP1: 201209 | HQ1: 201212 | HR1: 201303 | HS1: 201306 | HT1: 201309 | HU1: 201312 | HV1: 201403 | HW1: 201406 | HX1: 201409 | HY1: 201412 | HZ1: 201503 | IA1: 201506 | IB1: 201509 | IC1: 201512 | ID1: 201603 | IE1: 201606 | IF1: 201609 | IG1: 201612 | IH1: 201703 | II1: 201706 | IJ1: 201709 | IK1: 201712 | IL1: 201803 | IM1: 201806 | IN1: 201809 | IO1: 201812 | IP1: 201903 | IQ1: 201906 | IR1: 201909 | IS1: 201912 | IT1: 202003 | IU1: 202006 | IV1: 202009 | IW1: 202012 | IX1: 202103 | IY1: 202106 | IZ1: 202109 | JA1: 202112 | JB1: 202203 | JC1: 202206 | JD1: 202209 | JE1: 202212 | JF1: 202303 | JG1: 202306 | JH1: 202309 | JI1: 202312 | JJ1: 202403 | JK1: 202406 | JL1: 202409 | JM1: 202412 | JN1: 202503 | JO1: 202506 | JP1: 202509 | JQ1: 202512 | JR1: 202603 | JS1: 202606 | JT1: 202609 | JU1: 202612 | JV1: 202703 | JW1: 202706 | JX1: 202709 | JY1: 202712 | JZ1: 202803 | KA1: 202806 | KB1: 202809 | KC1: 202812 | KD1: 202903 | KE1: 202906 | KF1: 202909 | KG1: 202912 | KH1: 203003
FF2: 45901 | FG2: =+EOMONTH(FF2,1) -> 45961 | FH2: =+EOMONTH(FG2,1) -> 45991 | FI2: =+EOMONTH(FH2,1) -> 46022 | FJ2: =+EOMONTH(FI2,1) -> 46053 | FK2: =+EOMONTH(FJ2,1) -> 46081 | FL2: =+EOMONTH(FK2,1) -> 46112 | FM2: =+EOMONTH(FL2,1) -> 46142 | FN2: =+EOMONTH(FM2,1) -> 46173 | ... HH2: =+EOMONTH(HG2,1) -> 47573
A4: Field Description | B4: Field Name
A5: MonthEnd | B5: NMONTH_MONTHEND | C5: {=_xll.EQNXTDZ($A$1,$B5,C$1)} -> 0 | D5: {=_xll.EQNXTDZ($A$1,$B5,D$1)} -> 0 | E5: {=_xll.EQNXTDZ($A$1,$B5,E$1)} -> 0 | F5: {=_xll.EQNXTDZ($A$1,$B5,F$1)} -> 0 | G5: {=_xll.EQNXTDZ($A$1,$B5,G$1)} -> 0 | H5: {=_xll.EQNXTDZ($A$1,$B5,H$1)} -> 0 | I5: {=_xll.EQNXTDZ($A$1,$B5,I$1)} -> 0 | J5: {=_xll.EQNXTDZ($A$1,$B5,J$1)} -> 0 | ... HH5: {=_xll.EQNXTDZ($A$1,$B5,HH$1)} -> 0
A6: Open | B6: NMONTH_OPEN | C6: {=_xll.EQNXTDZ($A$1,$B6,C$1)} -> 0 | D6: {=_xll.EQNXTDZ($A$1,$B6,D$1)} -> 0 | E6: {=_xll.EQNXTDZ($A$1,$B6,E$1)} -> 0 | F6: {=_xll.EQNXTDZ($A$1,$B6,F$1)} -> 0 | G6: {=_xll.EQNXTDZ($A$1,$B6,G$1)} -> 0 | H6: {=_xll.EQNXTDZ($A$1,$B6,H$1)} -> 0 | I6: {=_xll.EQNXTDZ($A$1,$B6,I$1)} -> 0 | J6: {=_xll.EQNXTDZ($A$1,$B6,J$1)} -> 0 | ... HH6: {=_xll.EQNXTDZ($A$1,$B6,HH$1)} -> 0
A7: High | B7: NMONTH_HIGH | C7: {=_xll.EQNXTDZ($A$1,$B7,C$1)} -> 0 | D7: {=_xll.EQNXTDZ($A$1,$B7,D$1)} -> 0 | E7: {=_xll.EQNXTDZ($A$1,$B7,E$1)} -> 0 | F7: {=_xll.EQNXTDZ($A$1,$B7,F$1)} -> 0 | G7: {=_xll.EQNXTDZ($A$1,$B7,G$1)} -> 0 | H7: {=_xll.EQNXTDZ($A$1,$B7,H$1)} -> 0 | I7: {=_xll.EQNXTDZ($A$1,$B7,I$1)} -> 0 | J7: {=_xll.EQNXTDZ($A$1,$B7,J$1)} -> 0 | ... HH7: {=_xll.EQNXTDZ($A$1,$B7,HH$1)} -> 0 | HP7: =+MAX(D7:F7) -> 0 | HQ7: =+MAX(G7:I7) -> 0 | HR7: =+MAX(J7:L7) -> 0 | HS7: =+MAX(M7:O7) -> 0 | HT7: =+MAX(P7:R7) -> 0 | HU7: =+MAX(S7:U7) -> 0 | HV7: =+MAX(V7:X7) -> 0 | HW7: =+MAX(Y7:AA7) -> 0 | HX7: =+MAX(AB7:AD7) -> 0 | HY7: =+MAX(AE7:AG7) -> 0 | HZ7: =+MAX(AH7:AJ7) -> 0 | IA7: =+MAX(AK7:AM7) -> 0 | IB7: =+MAX(AN7:AP7) -> 0 | IC7: =+MAX(AQ7:AS7) -> 0 | ID7: =+MAX(AT7:AV7) -> 0 | IE7: =+MAX(AW7:AY7) -> 0 | IF7: =+MAX(AZ7:BB7) -> 0 | IG7: =+MAX(BC7:BE7) -> 0 | IH7: =+MAX(BF7:BH7) -> 0 | II7: =+MAX(BI7:BK7) -> 0 | IJ7: =+MAX(BL7:BN7) -> 0 | IK7: =+MAX(BO7:BQ7) -> 0 | IL7: =+MAX(BR7:BT7) -> 0 | IM7: =+MAX(BU7:BW7) -> 0 | IN7: =+MAX(BX7:BZ7) -> 0 | IO7: =+MAX(CA7:CC7) -> 0 | IP7: =+MAX(CD7:CF7) -> 0 | IQ7: =+MAX(CG7:CI7) -> 0 | IR7: =+MAX(CJ7:CL7) -> 0 | IS7: =+MAX(CM7:CO7) -> 0 | IT7: =+MAX(CP7:CR7) -> 0 | IU7: =+MAX(CS7:CU7) -> 0 | IV7: =+MAX(CV7:CX7) -> 0 | IW7: =+MAX(CY7:DA7) -> 0 | IX7: =+MAX(DB7:DD7) -> 0 | IY7: =+MAX(DE7:DG7) -> 0 | IZ7: =+MAX(DH7:DJ7) -> 0 | JA7: =+MAX(DK7:DM7) -> 0 | JB7: =+MAX(DN7:DP7) -> 0 | JC7: =+MAX(DQ7:DS7) -> 0 | JD7: =+MAX(DT7:DV7) -> 0 | JE7: =+MAX(DW7:DY7) -> 554.5 | JF7: =+MAX(DZ7:EB7) -> 731.8 | JG7: =+MAX(EC7:EE7) -> 658 | JH7: =+MAX(EF7:EH7) -> 685 | JI7: =+MAX(EI7:EK7) -> 689 | JJ7: =+MAX(EL7:EN7) -> 837.7 | JK7: =MAX(EO7:EQ7) -> 716.55 | JL7: =MAX(ER7:ET7) -> 832 | JM7: =MAX(EU7:EW7) -> 730 | JN7: =MAX(EX7:EZ7) -> 674.15 | JO7: =MAX(FA7:FC7) -> 670 | JP7: =MAX(FD7:FF7) -> 727.6 | JQ7: =MAX(FG7:FI7) -> 704.25 | JR7: =MAX(FJ7:FL7) -> 622 | JS7: =MAX(FM7:FO7) -> 639.8 | JT7: =MAX(FP7:FR7) -> 0 | JU7: =MAX(FS7:FU7) -> 0 | JV7: =MAX(FV7:FX7) -> 0 | JW7: =MAX(FY7:GA7) -> 0 | JX7: =MAX(GB7:GD7) -> 0 | JY7: =MAX(GE7:GG7) -> 0 | JZ7: =MAX(GH7:GJ7) -> 0 | KA7: =MAX(GK7:GM7) -> 0 | KB7: =MAX(GN7:GP7) -> 0 | KC7: =MAX(GQ7:GS7) -> 0 | KD7: =MAX(GT7:GV7) -> 0 | KE7: =MAX(GW7:GY7) -> 0 | KF7: =MAX(GZ7:HB7) -> 0 | KG7: =MAX(HC7:HE7) -> 0 | KH7: =MAX(HF7:HH7) -> 0
A8: Low | B8: NMONTH_LOW | C8: {=_xll.EQNXTDZ($A$1,$B8,C$1)} -> 0 | D8: {=_xll.EQNXTDZ($A$1,$B8,D$1)} -> 0 | E8: {=_xll.EQNXTDZ($A$1,$B8,E$1)} -> 0 | F8: {=_xll.EQNXTDZ($A$1,$B8,F$1)} -> 0 | G8: {=_xll.EQNXTDZ($A$1,$B8,G$1)} -> 0 | H8: {=_xll.EQNXTDZ($A$1,$B8,H$1)} -> 0 | I8: {=_xll.EQNXTDZ($A$1,$B8,I$1)} -> 0 | J8: {=_xll.EQNXTDZ($A$1,$B8,J$1)} -> 0 | ... HH8: {=_xll.EQNXTDZ($A$1,$B8,HH$1)} -> 0 | HP8: =+MIN(D8:F8) -> 0 | HQ8: =+MIN(G8:I8) -> 0 | HR8: =+MIN(J8:L8) -> 0 | HS8: =+MIN(M8:O8) -> 0 | HT8: =+MIN(P8:R8) -> 0 | HU8: =+MIN(S8:U8) -> 0 | HV8: =+MIN(V8:X8) -> 0 | HW8: =+MIN(Y8:AA8) -> 0 | HX8: =+MIN(AB8:AD8) -> 0 | HY8: =+MIN(AE8:AG8) -> 0 | HZ8: =+MIN(AH8:AJ8) -> 0 | IA8: =+MIN(AK8:AM8) -> 0 | IB8: =+MIN(AN8:AP8) -> 0 | IC8: =+MIN(AQ8:AS8) -> 0 | ID8: =+MIN(AT8:AV8) -> 0 | IE8: =+MIN(AW8:AY8) -> 0 | IF8: =+MIN(AZ8:BB8) -> 0 | IG8: =+MIN(BC8:BE8) -> 0 | IH8: =+MIN(BF8:BH8) -> 0 | II8: =+MIN(BI8:BK8) -> 0 | IJ8: =+MIN(BL8:BN8) -> 0 | IK8: =+MIN(BO8:BQ8) -> 0 | IL8: =+MIN(BR8:BT8) -> 0 | IM8: =+MIN(BU8:BW8) -> 0 | IN8: =+MIN(BX8:BZ8) -> 0 | IO8: =+MIN(CA8:CC8) -> 0 | IP8: =+MIN(CD8:CF8) -> 0 | IQ8: =+MIN(CG8:CI8) -> 0 | IR8: =+MIN(CJ8:CL8) -> 0 | IS8: =+MIN(CM8:CO8) -> 0 | IT8: =+MIN(CP8:CR8) -> 0 | IU8: =+MIN(CS8:CU8) -> 0 | IV8: =+MIN(CV8:CX8) -> 0 | IW8: =+MIN(CY8:DA8) -> 0 | IX8: =+MIN(DB8:DD8) -> 0 | IY8: =+MIN(DE8:DG8) -> 0 | IZ8: =+MIN(DH8:DJ8) -> 0 | JA8: =+MIN(DK8:DM8) -> 0 | JB8: =+MIN(DN8:DP8) -> 0 | JC8: =+MIN(DQ8:DS8) -> 0 | JD8: =+MIN(DT8:DV8) -> 0 | JE8: =+MIN(DW8:DY8) -> 0 | JF8: =+MIN(DZ8:EB8) -> 523 | JG8: =+MIN(EC8:EE8) -> 510 | JH8: =+MIN(EF8:EH8) -> 494.15 | JI8: =+MIN(EI8:EK8) -> 510.05 | JJ8: =+MIN(EL8:EN8) -> 571.3 | JK8: =MIN(EO8:EQ8) -> 581.1 | JL8: =MIN(ER8:ET8) -> 660.05 | JM8: =MIN(EU8:EW8) -> 590.05 | JN8: =MIN(EX8:EZ8) -> 408.35 | JO8: =MIN(FA8:FC8) -> 480 | JP8: =MIN(FD8:FF8) -> 607.5 | JQ8: =MIN(FG8:FI8) -> 483 | JR8: =MIN(FJ8:FL8) -> 502.05 | JS8: =MIN(FM8:FO8) -> 508.5 | JT8: =MIN(FP8:FR8) -> 0 | JU8: =MIN(FS8:FU8) -> 0 | JV8: =MIN(FV8:FX8) -> 0 | JW8: =MIN(FY8:GA8) -> 0 | JX8: =MIN(GB8:GD8) -> 0 | JY8: =MIN(GE8:GG8) -> 0 | JZ8: =MIN(GH8:GJ8) -> 0 | KA8: =MIN(GK8:GM8) -> 0 | KB8: =MIN(GN8:GP8) -> 0 | KC8: =MIN(GQ8:GS8) -> 0 | KD8: =MIN(GT8:GV8) -> 0 | KE8: =MIN(GW8:GY8) -> 0 | KF8: =MIN(GZ8:HB8) -> 0 | KG8: =MIN(HC8:HE8) -> 0 | KH8: =MIN(HF8:HH8) -> 0
A9: Close | B9: NMONTH_CLOSE | C9: {=_xll.EQNXTDZ($A$1,$B9,C$1)} -> 0 | D9: {=_xll.EQNXTDZ($A$1,$B9,D$1)} -> 0 | E9: {=_xll.EQNXTDZ($A$1,$B9,E$1)} -> 0 | F9: {=_xll.EQNXTDZ($A$1,$B9,F$1)} -> 0 | G9: {=_xll.EQNXTDZ($A$1,$B9,G$1)} -> 0 | H9: {=_xll.EQNXTDZ($A$1,$B9,H$1)} -> 0 | I9: {=_xll.EQNXTDZ($A$1,$B9,I$1)} -> 0 | J9: {=_xll.EQNXTDZ($A$1,$B9,J$1)} -> 0 | ... HH9: {=_xll.EQNXTDZ($A$1,$B9,HH$1)} -> 0 | HP9: =+F9 -> 0 | HQ9: =+I9 -> 0 | HR9: =+L9 -> 0 | HS9: =+O9 -> 0 | HT9: =+R9 -> 0 | HU9: =+U9 -> 0 | HV9: =+X9 -> 0 | HW9: =+AA9 -> 0 | HX9: =+AD9 -> 0 | HY9: =+AG9 -> 0 | HZ9: =+AJ9 -> 0 | IA9: =+AM9 -> 0 | IB9: =+AP9 -> 0 | IC9: =+AS9 -> 0 | ID9: =+AV9 -> 0 | IE9: =+AY9 -> 0 | IF9: =+BB9 -> 0 | IG9: =+BE9 -> 0 | IH9: =+BH9 -> 0 | II9: =+BK9 -> 0 | IJ9: =+BN9 -> 0 | IK9: =+BQ9 -> 0 | IL9: =+BT9 -> 0 | IM9: =+BW9 -> 0 | IN9: =+BZ9 -> 0 | IO9: =+CC9 -> 0 | IP9: =+CF9 -> 0 | IQ9: =+CI9 -> 0 | IR9: =+CL9 -> 0 | IS9: =+CO9 -> 0 | IT9: =+CR9 -> 0 | IU9: =+CU9 -> 0 | IV9: =+CX9 -> 0 | IW9: =+DA9 -> 0 | IX9: =+DD9 -> 0 | IY9: =+DG9 -> 0 | IZ9: =+DJ9 -> 0 | JA9: =+DM9 -> 0 | JB9: =+DP9 -> 0 | JC9: =+DS9 -> 0 | JD9: =+DV9 -> 0 | JE9: =+DY9 -> 526.25 | JF9: =+EB9 -> 650.45 | JG9: =+EE9 -> 536.25 | JH9: =+EH9 -> 588.85 | JI9: =+EK9 -> 649.7 | JJ9: =+EN9 -> 669 | JK9: =EQ9 -> 669 | JL9: =ET9 -> 721.8 | JM9: =EW9 -> 669.55 | JN9: =EZ9 -> 517.9 | JO9: =FC9 -> 632.6 | JP9: =FF9 -> 689.3 | JQ9: =FI9 -> 557.15 | JR9: =FL9 -> 587.45 | JS9: =FO9 -> 527.45 | JT9: =FR9 -> 0 | JU9: =FU9 -> 0 | JV9: =FX9 -> 0 | JW9: =GA9 -> 0 | JX9: =GD9 -> 0 | JY9: =GG9 -> 0 | JZ9: =GJ9 -> 0 | KA9: =GM9 -> 0 | KB9: =GP9 -> 0 | KC9: =GS9 -> 0 | KD9: =GV9 -> 0 | KE9: =GY9 -> 0 | KF9: =HB9 -> 0 | KG9: =HE9 -> 0 | KH9: =HH9 -> 0
A11: Field Description | B11: Field Name | C11: {=_xll.EQNXTDZ($A$1,$B11,C$1)} -> 0 | D11: {=_xll.EQNXTDZ($A$1,$B11,D$1)} -> 0 | E11: {=_xll.EQNXTDZ($A$1,$B11,E$1)} -> 0 | F11: {=_xll.EQNXTDZ($A$1,$B11,F$1)} -> 0 | G11: {=_xll.EQNXTDZ($A$1,$B11,G$1)} -> 0 | H11: {=_xll.EQNXTDZ($A$1,$B11,H$1)} -> 0 | I11: {=_xll.EQNXTDZ($A$1,$B11,I$1)} -> 0 | J11: {=_xll.EQNXTDZ($A$1,$B11,J$1)} -> 0 | ... HH11: {=_xll.EQNXTDZ($A$1,$B11,HH$1)} -> 0
A12: Month End | B12: BMONTH_MONTHEND | C12: {=_xll.EQNXTDZ($A$1,$B12,C$1)} -> 0 | D12: {=_xll.EQNXTDZ($A$1,$B12,D$1)} -> 0 | E12: {=_xll.EQNXTDZ($A$1,$B12,E$1)} -> 0 | F12: {=_xll.EQNXTDZ($A$1,$B12,F$1)} -> 0 | G12: {=_xll.EQNXTDZ($A$1,$B12,G$1)} -> 0 | H12: {=_xll.EQNXTDZ($A$1,$B12,H$1)} -> 0 | I12: {=_xll.EQNXTDZ($A$1,$B12,I$1)} -> 0 | J12: {=_xll.EQNXTDZ($A$1,$B12,J$1)} -> 0 | ... HH12: {=_xll.EQNXTDZ($A$1,$B12,HH$1)} -> 0
A13: Open | B13: BMONTH_OPEN | C13: {=_xll.EQNXTDZ($A$1,$B13,C$1)} -> 0 | D13: {=_xll.EQNXTDZ($A$1,$B13,D$1)} -> 0 | E13: {=_xll.EQNXTDZ($A$1,$B13,E$1)} -> 0 | F13: {=_xll.EQNXTDZ($A$1,$B13,F$1)} -> 0 | G13: {=_xll.EQNXTDZ($A$1,$B13,G$1)} -> 0 | H13: {=_xll.EQNXTDZ($A$1,$B13,H$1)} -> 0 | I13: {=_xll.EQNXTDZ($A$1,$B13,I$1)} -> 0 | J13: {=_xll.EQNXTDZ($A$1,$B13,J$1)} -> 0 | ... HH13: {=_xll.EQNXTDZ($A$1,$B13,HH$1)} -> 0
A14: High | B14: BMONTH_HIGH | C14: {=_xll.EQNXTDZ($A$1,$B14,C$1)} -> 0 | D14: {=_xll.EQNXTDZ($A$1,$B14,D$1)} -> 0 | E14: {=_xll.EQNXTDZ($A$1,$B14,E$1)} -> 0 | F14: {=_xll.EQNXTDZ($A$1,$B14,F$1)} -> 0 | G14: {=_xll.EQNXTDZ($A$1,$B14,G$1)} -> 0 | H14: {=_xll.EQNXTDZ($A$1,$B14,H$1)} -> 0 | I14: {=_xll.EQNXTDZ($A$1,$B14,I$1)} -> 0 | J14: {=_xll.EQNXTDZ($A$1,$B14,J$1)} -> 0 | ... HH14: {=_xll.EQNXTDZ($A$1,$B14,HH$1)} -> 0 | HP14: =+MAX(D14:F14) -> 0 | HQ14: =+MAX(G14:I14) -> 0 | HR14: =+MAX(J14:L14) -> 0 | HS14: =+MAX(M14:O14) -> 0 | HT14: =+MAX(P14:R14) -> 0 | HU14: =+MAX(S14:U14) -> 0 | HV14: =+MAX(V14:X14) -> 0 | HW14: =+MAX(Y14:AA14) -> 0 | HX14: =+MAX(AB14:AD14) -> 0 | HY14: =+MAX(AE14:AG14) -> 0 | HZ14: =+MAX(AH14:AJ14) -> 0 | IA14: =+MAX(AK14:AM14) -> 0 | IB14: =+MAX(AN14:AP14) -> 0 | IC14: =+MAX(AQ14:AS14) -> 0 | ID14: =+MAX(AT14:AV14) -> 0 | IE14: =+MAX(AW14:AY14) -> 0 | IF14: =+MAX(AZ14:BB14) -> 0 | IG14: =+MAX(BC14:BE14) -> 0 | IH14: =+MAX(BF14:BH14) -> 0 | II14: =+MAX(BI14:BK14) -> 0 | IJ14: =+MAX(BL14:BN14) -> 0 | IK14: =+MAX(BO14:BQ14) -> 0 | IL14: =+MAX(BR14:BT14) -> 0 | IM14: =+MAX(BU14:BW14) -> 0 | IN14: =+MAX(BX14:BZ14) -> 0 | IO14: =+MAX(CA14:CC14) -> 0 | IP14: =+MAX(CD14:CF14) -> 0 | IQ14: =+MAX(CG14:CI14) -> 0 | IR14: =+MAX(CJ14:CL14) -> 0 | IS14: =+MAX(CM14:CO14) -> 0 | IT14: =+MAX(CP14:CR14) -> 0 | IU14: =+MAX(CS14:CU14) -> 0 | IV14: =+MAX(CV14:CX14) -> 0 | IW14: =+MAX(CY14:DA14) -> 0 | IX14: =+MAX(DB14:DD14) -> 0 | IY14: =+MAX(DE14:DG14) -> 0 | IZ14: =+MAX(DH14:DJ14) -> 0 | JA14: =+MAX(DK14:DM14) -> 0 | JB14: =+MAX(DN14:DP14) -> 0 | JC14: =+MAX(DQ14:DS14) -> 0 | JD14: =+MAX(DT14:DV14) -> 0 | JE14: =+MAX(DW14:DY14) -> 554.45 | JF14: =+MAX(DZ14:EB14) -> 731.75 | JG14: =+MAX(EC14:EE14) -> 654 | JH14: =+MAX(EF14:EH14) -> 685 | JI14: =+MAX(EI14:EK14) -> 687.9 | JJ14: =+MAX(EL14:EN14) -> 838.2 | JK14: =MAX(EO14:EQ14) -> 716.5 | JL14: =MAX(ER14:ET14) -> 831 | JM14: =MAX(EU14:EW14) -> 730.45 | JN14: =MAX(EX14:EZ14) -> 690 | JO14: =MAX(FA14:FC14) -> 669 | JP14: =MAX(FD14:FF14) -> 727.8 | JQ14: =MAX(FG14:FI14) -> 703.85 | JR14: =MAX(FJ14:FL14) -> 628 | JS14: =MAX(FM14:FO14) -> 640.95 | JT14: =MAX(FP14:FR14) -> 0 | JU14: =MAX(FS14:FU14) -> 0 | JV14: =MAX(FV14:FX14) -> 0 | JW14: =MAX(FY14:GA14) -> 0 | JX14: =MAX(GB14:GD14) -> 0 | JY14: =MAX(GE14:GG14) -> 0 | JZ14: =MAX(GH14:GJ14) -> 0 | KA14: =MAX(GK14:GM14) -> 0 | KB14: =MAX(GN14:GP14) -> 0 | KC14: =MAX(GQ14:GS14) -> 0 | KD14: =MAX(GT14:GV14) -> 0 | KE14: =MAX(GW14:GY14) -> 0 | KF14: =MAX(GZ14:HB14) -> 0 | KG14: =MAX(HC14:HE14) -> 0 | KH14: =MAX(HF14:HH14) -> 0
A15: Low | B15: BMONTH_LOW | C15: {=_xll.EQNXTDZ($A$1,$B15,C$1)} -> 0 | D15: {=_xll.EQNXTDZ($A$1,$B15,D$1)} -> 0 | E15: {=_xll.EQNXTDZ($A$1,$B15,E$1)} -> 0 | F15: {=_xll.EQNXTDZ($A$1,$B15,F$1)} -> 0 | G15: {=_xll.EQNXTDZ($A$1,$B15,G$1)} -> 0 | H15: {=_xll.EQNXTDZ($A$1,$B15,H$1)} -> 0 | I15: {=_xll.EQNXTDZ($A$1,$B15,I$1)} -> 0 | J15: {=_xll.EQNXTDZ($A$1,$B15,J$1)} -> 0 | ... HH15: {=_xll.EQNXTDZ($A$1,$B15,HH$1)} -> 0 | HP15: =+MIN(D15:F15) -> 0 | HQ15: =+MIN(G15:I15) -> 0 | HR15: =+MIN(J15:L15) -> 0 | HS15: =+MIN(M15:O15) -> 0 | HT15: =+MIN(P15:R15) -> 0 | HU15: =+MIN(S15:U15) -> 0 | HV15: =+MIN(V15:X15) -> 0 | HW15: =+MIN(Y15:AA15) -> 0 | HX15: =+MIN(AB15:AD15) -> 0 | HY15: =+MIN(AE15:AG15) -> 0 | HZ15: =+MIN(AH15:AJ15) -> 0 | IA15: =+MIN(AK15:AM15) -> 0 | IB15: =+MIN(AN15:AP15) -> 0 | IC15: =+MIN(AQ15:AS15) -> 0 | ID15: =+MIN(AT15:AV15) -> 0 | IE15: =+MIN(AW15:AY15) -> 0 | IF15: =+MIN(AZ15:BB15) -> 0 | IG15: =+MIN(BC15:BE15) -> 0 | IH15: =+MIN(BF15:BH15) -> 0 | II15: =+MIN(BI15:BK15) -> 0 | IJ15: =+MIN(BL15:BN15) -> 0 | IK15: =+MIN(BO15:BQ15) -> 0 | IL15: =+MIN(BR15:BT15) -> 0 | IM15: =+MIN(BU15:BW15) -> 0 | IN15: =+MIN(BX15:BZ15) -> 0 | IO15: =+MIN(CA15:CC15) -> 0 | IP15: =+MIN(CD15:CF15) -> 0 | IQ15: =+MIN(CG15:CI15) -> 0 | IR15: =+MIN(CJ15:CL15) -> 0 | IS15: =+MIN(CM15:CO15) -> 0 | IT15: =+MIN(CP15:CR15) -> 0 | IU15: =+MIN(CS15:CU15) -> 0 | IV15: =+MIN(CV15:CX15) -> 0 | IW15: =+MIN(CY15:DA15) -> 0 | IX15: =+MIN(DB15:DD15) -> 0 | IY15: =+MIN(DE15:DG15) -> 0 | IZ15: =+MIN(DH15:DJ15) -> 0 | JA15: =+MIN(DK15:DM15) -> 0 | JB15: =+MIN(DN15:DP15) -> 0 | JC15: =+MIN(DQ15:DS15) -> 0 | JD15: =+MIN(DT15:DV15) -> 0 | JE15: =+MIN(DW15:DY15) -> 0 | JF15: =+MIN(DZ15:EB15) -> 516.55 | JG15: =+MIN(EC15:EE15) -> 518.9 | JH15: =+MIN(EF15:EH15) -> 495 | JI15: =+MIN(EI15:EK15) -> 510.3 | JJ15: =+MIN(EL15:EN15) -> 571.5 | JK15: =MIN(EO15:EQ15) -> 582.9 | JL15: =MIN(ER15:ET15) -> 665.25 | JM15: =MIN(EU15:EW15) -> 591 | JN15: =MIN(EX15:EZ15) -> 409 | JO15: =MIN(FA15:FC15) -> 479.75 | JP15: =MIN(FD15:FF15) -> 608.7 | JQ15: =MIN(FG15:FI15) -> 483.1 | JR15: =MIN(FJ15:FL15) -> 502.5 | JS15: =MIN(FM15:FO15) -> 509.35 | JT15: =MIN(FP15:FR15) -> 0 | JU15: =MIN(FS15:FU15) -> 0 | JV15: =MIN(FV15:FX15) -> 0 | JW15: =MIN(FY15:GA15) -> 0 | JX15: =MIN(GB15:GD15) -> 0 | JY15: =MIN(GE15:GG15) -> 0 | JZ15: =MIN(GH15:GJ15) -> 0 | KA15: =MIN(GK15:GM15) -> 0 | KB15: =MIN(GN15:GP15) -> 0 | KC15: =MIN(GQ15:GS15) -> 0 | KD15: =MIN(GT15:GV15) -> 0 | KE15: =MIN(GW15:GY15) -> 0 | KF15: =MIN(GZ15:HB15) -> 0 | KG15: =MIN(HC15:HE15) -> 0 | KH15: =MIN(HF15:HH15) -> 0
A16: Close | B16: BMONTH_CLOSE | C16: {=_xll.EQNXTDZ($A$1,$B16,C$1)} -> 0 | D16: {=_xll.EQNXTDZ($A$1,$B16,D$1)} -> 0 | E16: {=_xll.EQNXTDZ($A$1,$B16,E$1)} -> 0 | F16: {=_xll.EQNXTDZ($A$1,$B16,F$1)} -> 0 | G16: {=_xll.EQNXTDZ($A$1,$B16,G$1)} -> 0 | H16: {=_xll.EQNXTDZ($A$1,$B16,H$1)} -> 0 | I16: {=_xll.EQNXTDZ($A$1,$B16,I$1)} -> 0 | J16: {=_xll.EQNXTDZ($A$1,$B16,J$1)} -> 0 | ... HH16: {=_xll.EQNXTDZ($A$1,$B16,HH$1)} -> 0 | HP16: =+F16 -> 0 | HQ16: =+I16 -> 0 | HR16: =+L16 -> 0 | HS16: =+O16 -> 0 | HT16: =+R16 -> 0 | HU16: =+U16 -> 0 | HV16: =+X16 -> 0 | HW16: =+AA16 -> 0 | HX16: =+AD16 -> 0 | HY16: =+AG16 -> 0 | HZ16: =+AJ16 -> 0 | IA16: =+AM16 -> 0 | IB16: =+AP16 -> 0 | IC16: =+AS16 -> 0 | ID16: =+AV16 -> 0 | IE16: =+AY16 -> 0 | IF16: =+BB16 -> 0 | IG16: =+BE16 -> 0 | IH16: =+BH16 -> 0 | II16: =+BK16 -> 0 | IJ16: =+BN16 -> 0 | IK16: =+BQ16 -> 0 | IL16: =+BT16 -> 0 | IM16: =+BW16 -> 0 | IN16: =+BZ16 -> 0 | IO16: =+CC16 -> 0 | IP16: =+CF16 -> 0 | IQ16: =+CI16 -> 0 | IR16: =+CL16 -> 0 | IS16: =+CO16 -> 0 | IT16: =+CR16 -> 0 | IU16: =+CU16 -> 0 | IV16: =+CX16 -> 0 | IW16: =+DA16 -> 0 | IX16: =+DD16 -> 0 | IY16: =+DG16 -> 0 | IZ16: =+DJ16 -> 0 | JA16: =+DM16 -> 0 | JB16: =+DP16 -> 0 | JC16: =+DS16 -> 0 | JD16: =+DV16 -> 0 | JE16: =+DY16 -> 525.55 | JF16: =+EB16 -> 650.7 | JG16: =+EE16 -> 537 | JH16: =+EH16 -> 589.5 | JI16: =+EK16 -> 648.9 | JJ16: =+EN16 -> 670.15 | JK16: =EQ16 -> 668 | JL16: =ET16 -> 721.55 | JM16: =EW16 -> 669.1 | JN16: =EZ16 -> 515.45 | JO16: =FC16 -> 631.6 | JP16: =FF16 -> 691.4 | JQ16: =FI16 -> 556.25 | JR16: =FL16 -> 586.75 | JS16: =FO16 -> 526.8 | JT16: =FR16 -> 0 | JU16: =FU16 -> 0 | JV16: =FX16 -> 0 | JW16: =GA16 -> 0 | JX16: =GD16 -> 0 | JY16: =GG16 -> 0 | JZ16: =GJ16 -> 0 | KA16: =GM16 -> 0 | KB16: =GP16 -> 0 | KC16: =GS16 -> 0 | KD16: =GV16 -> 0 | KE16: =GY16 -> 0 | KF16: =HB16 -> 0 | KG16: =HE16 -> 0 | KH16: =HH16 -> 0
A19: High | HP19: =+IF(HP14=0,HP7,HP14) -> 0 | HQ19: =+IF(HQ14=0,HQ7,HQ14) -> 0 | HR19: =+IF(HR14=0,HR7,HR14) -> 0 | HS19: =+IF(HS14=0,HS7,HS14) -> 0 | HT19: =+IF(HT14=0,HT7,HT14) -> 0 | HU19: =+IF(HU14=0,HU7,HU14) -> 0 | HV19: =+IF(HV14=0,HV7,HV14) -> 0 | HW19: =+IF(HW14=0,HW7,HW14) -> 0 | ... KH19: =+IF(KH14=0,KH7,KH14) -> 0
A20: Low | HP20: =+IF(HP15=0,HP8,HP15) -> 0 | HQ20: =+IF(HQ15=0,HQ8,HQ15) -> 0 | HR20: =+IF(HR15=0,HR8,HR15) -> 0 | HS20: =+IF(HS15=0,HS8,HS15) -> 0 | HT20: =+IF(HT15=0,HT8,HT15) -> 0 | HU20: =+IF(HU15=0,HU8,HU15) -> 0 | HV20: =+IF(HV15=0,HV8,HV15) -> 0 | HW20: =+IF(HW15=0,HW8,HW15) -> 0 | ... KH20: =+IF(KH15=0,KH8,KH15) -> 0
A21: Close | HP21: =+IF(HP16=0,HP9,HP16) -> 0 | HQ21: =+IF(HQ16=0,HQ9,HQ16) -> 0 | HR21: =+IF(HR16=0,HR9,HR16) -> 0 | HS21: =+IF(HS16=0,HS9,HS16) -> 0 | HT21: =+IF(HT16=0,HT9,HT16) -> 0 | HU21: =+IF(HU16=0,HU9,HU16) -> 0 | HV21: =+IF(HV16=0,HV9,HV16) -> 0 | HW21: =+IF(HW16=0,HW9,HW16) -> 0 | ... KH21: =+IF(KH16=0,KH9,KH16) -> 0

Sheet QTR No. of Shares
A1: ='QTR Raw'!A1 -> 293601 | C1: 201206 | D1: 201209 | E1: 201212 | F1: 201303 | G1: 201306 | H1: 201309 | I1: 201312 | J1: 201403 | K1: 201406 | L1: 201409 | M1: 201412 | N1: 201503 | O1: 201506 | P1: 201509 | Q1: 201512 | R1: 201603 | S1: 201606 | T1: 201609 | U1: 201612 | V1: 201703 | W1: 201706 | X1: 201709 | Y1: 201712 | Z1: 201803 | AA1: 201806 | AB1: 201809 | AC1: 201812 | AD1: 201903 | AE1: 201906 | AF1: 201909 | AG1: 201912 | AH1: 202003 | AI1: 202006 | AJ1: 202009 | AK1: 202012 | AL1: 202103 | AM1: 202106 | AN1: 202109 | AO1: 202112 | AP1: 202203 | AQ1: 202206 | AR1: 202209 | AS1: 202212 | AT1: 202303 | AU1: 202306 | AV1: 202309 | AW1: 202312 | AX1: 202403 | AY1: 202406
A4: Field Description | B4: Field Name
A5: Date End | B5: SHP_DATE_END | C5: {=_xll.EQNXTDZ($A$1,$B5,C$1)} -> 0 | D5: {=_xll.EQNXTDZ($A$1,$B5,D$1)} -> 0 | E5: {=_xll.EQNXTDZ($A$1,$B5,E$1)} -> 0 | F5: {=_xll.EQNXTDZ($A$1,$B5,F$1)} -> 0 | G5: {=_xll.EQNXTDZ($A$1,$B5,G$1)} -> 0 | H5: {=_xll.EQNXTDZ($A$1,$B5,H$1)} -> 0 | I5: {=_xll.EQNXTDZ($A$1,$B5,I$1)} -> 0 | J5: {=_xll.EQNXTDZ($A$1,$B5,J$1)} -> 0 | ... AY5: {=_xll.EQNXTDZ($A$1,$B5,AY$1)} -> 202406
A6: Grand Total | B6: SHP_NSGRANDTOTAL | C6: {=_xll.EQNXTDZ($A$1,$B6,C$1)} -> 0 | D6: {=_xll.EQNXTDZ($A$1,$B6,D$1)} -> 0 | E6: {=_xll.EQNXTDZ($A$1,$B6,E$1)} -> 0 | F6: {=_xll.EQNXTDZ($A$1,$B6,F$1)} -> 0 | G6: {=_xll.EQNXTDZ($A$1,$B6,G$1)} -> 0 | H6: {=_xll.EQNXTDZ($A$1,$B6,H$1)} -> 0 | I6: {=_xll.EQNXTDZ($A$1,$B6,I$1)} -> 0 | J6: {=_xll.EQNXTDZ($A$1,$B6,J$1)} -> 0 | ... AY6: {=_xll.EQNXTDZ($A$1,$B6,AY$1)} -> 123396969
B7: In Crs. | C7: =+C6/10^7 -> 0 | D7: =+D6/10^7 -> 0 | E7: =+E6/10^7 -> 0 | F7: =+F6/10^7 -> 0 | G7: =+G6/10^7 -> 0 | H7: =+H6/10^7 -> 0 | I7: =+I6/10^7 -> 0 | J7: =+J6/10^7 -> 0 | ... AY7: =+AY6/10^7 -> 12.339697

Sheet Share price Daily
A1: =_xll.EQNXTH(B1,"[ADJC];[ADJH];[ADJL];[ADJO];[UCLS];[VOLUME]","2015-Jan-01","Y","All traded days","Asc") -> EQNXTH | B1: =+'Annual Raw'!A1 -> 293601 | L1: =_xll.EQNXTH(B1,"[NADJC];[NADJH];[NADJLOW];[NADJOPEN];[NUCLOSE];[NVOLUME]","2015-Jan-01","Y","All traded days","Asc") -> EQNXTH
A2: Archean Chemical Industries Ltd. | L2: Archean Chemical Industries Ltd.
A3: DATE | B3: ADJHIGH | C3: ADJCLOSE | D3: ADJLOW | E3: ADJOPEN | F3: CLOSE | G3: VOLUME | L3: DATE | M3: ADJCLOSE | N3: ADJHIGH | O3: ADJLOW | P3: ADJOPEN | Q3: CLOSE | R3: VOLUME
A4: 44886 | B4: 476.05 | C4: 457.95 | D4: 440.05 | E4: 449 | F4: 457.95 | G4: 1118983 | L4: 44886 | M4: 458.15 | N4: 476 | O4: 440.2 | P4: 450 | Q4: 458.15 | R4: 22187351
A5: 44887 | B5: 478 | C5: 454.85 | D5: 448.8 | E5: 460.45 | F5: 454.85 | G5: 206410 | L5: 44887 | M5: 454.85 | N5: 478 | O5: 450 | P5: 460.8 | Q5: 454.85 | R5: 4464605
A6: 44888 | B6: 471.55 | C6: 464.6 | D6: 455.2 | E6: 455.2 | F6: 464.6 | G6: 201083 | L6: 44888 | M6: 464.7 | N6: 471.65 | O6: 455.6 | P6: 458.9 | Q6: 464.7 | R6: 1736495
A7: 44889 | B7: 510 | C7: 502.4 | D7: 465.2 | E7: 465.2 | F7: 502.4 | G7: 249114 | L7: 44889 | M7: 502.4 | N7: 509 | O7: 465 | P7: 468 | Q7: 502.4 | R7: 4878787
A8: 44890 | B8: 538.35 | C8: 532.75 | D8: 494 | E8: 498.3 | F8: 532.75 | G8: 287290 | L8: 44890 | M8: 534 | N8: 538.8 | O8: 493.2 | P8: 495.95 | Q8: 534 | R8: 3312638
A9: 44893 | B9: 546.5 | C9: 539.3 | D9: 514.65 | E9: 529 | F9: 539.3 | G9: 86813 | L9: 44893 | M9: 539.55 | N9: 547 | O9: 514.35 | P9: 527.95 | Q9: 539.55 | R9: 1577078
A10: 44894 | B10: 554.45 | C10: 538.3 | D10: 534 | E10: 544.65 | F10: 538.3 | G10: 51792 | L10: 44894 | M10: 539.15 | N10: 554.45 | O10: 534 | P10: 542.3 | Q10: 539.15 | R10: 885600
A11: 44895 | B11: 542.7 | C11: 515.2 | D11: 500.1 | E11: 539.65 | F11: 515.2 | G11: 26184 | L11: 44895 | M11: 516.4 | N11: 543.25 | O11: 502.6 | P11: 541 | Q11: 516.4 | R11: 469673
A12: 44896 | B12: 534.95 | C12: 530.85 | D12: 514.95 | E12: 521.85 | F12: 530.85 | G12: 33915 | L12: 44896 | M12: 530.85 | N12: 535 | O12: 514 | P12: 517.9 | Q12: 530.85 | R12: 547914
A13: 44897 | B13: 539 | C13: 522.65 | D13: 517.5 | E13: 530.85 | F13: 522.65 | G13: 19247 | L13: 44897 | M13: 521.95 | N13: 538.8 | O13: 515.35 | P13: 530.85 | Q13: 521.95 | R13: 270405
A14: 44900 | B14: 532.65 | C14: 519.3 | D14: 517.8 | E14: 521.05 | F14: 519.3 | G14: 36228 | L14: 44900 | M14: 519.45 | N14: 533 | O14: 518 | P14: 524.6 | Q14: 519.45 | R14: 410127
A15: 44901 | B15: 522.45 | C15: 505.25 | D15: 502 | E15: 519.35 | F15: 505.25 | G15: 15425 | L15: 44901 | M15: 504.9 | N15: 523.4 | O15: 502 | P15: 522.05 | Q15: 504.9 | R15: 235149
... A2722: 46010 | B2722: 939 | C2722: 932.5 | D2722: 906.25 | E2722: 910.9 | F2722: 932.5 | G2722: 8862 | L2722: 46010 | M2722: 936.6 | N2722: 938.9 | O2722: 905 | P2722: 905 | Q2722: 936.6 | R2722: 296202

Sheet Sheet2
J19: 219.3 | K19: 186.25 | L19: 186.75
J20: 192.9 | K20: 135.5 | L20: 146.9 | N20: 219.3 | O20: 192.9 | P20: 186 | Q20: 178.7 | R20: 207 | S20: 255.15 | T20: 348.25 | U20: 374 | V20: 495.9 | W20: 659.9 | X20: 613.4 | Y20: 607.9 | Z20: 555.95 | AA20: 497.8 | AB20: 459.9 | AC20: 374 | AD20: 362 | AE20: 341.5 | AF20: 384.2 | AG20: 433.8 | AH20: 460 | AI20: 474.4 | AJ20: 414.4 | AK20: 318.7 | AL20: 303.25 | AM20: 332.7 | AN20: 295 | AO20: 247 | AP20: 214.4 | AQ20: 179.5 | AR20: 97.9 | AS20: 119.1 | AT20: 130.65 | AU20: 148.55 | AV20: 153.8 | AW20: 152.9 | AX20: 136 | AY20: 141.15 | AZ20: 128.1 | BA20: 142.5 | BB20: 143.55 | BC20: 124.5 | BD20: 241 | BE20: 450 | BF20: 503.35
J21: 186 | K21: 145.4 | L21: 169.1 | N21: 186.25 | O21: 135.5 | P21: 145.4 | Q21: 108.95 | R21: 137 | S21: 170 | T21: 243.15 | U21: 307.5 | V21: 325.1 | W21: 463 | X21: 467.05 | Y21: 436.5 | Z21: 467 | AA21: 348.2 | AB21: 325 | AC21: 313.1 | AD21: 285 | AE21: 277.85 | AF21: 327 | AG21: 317 | AH21: 370.7 | AI21: 360 | AJ21: 271.15 | AK21: 233.15 | AL21: 218.8 | AM21: 262 | AN21: 223.6 | AO21: 137.6 | AP21: 142 | AQ21: 59.3 | AR21: 58 | AS21: 72.8 | AT21: 80 | AU21: 107.25 | AV21: 106 | AW21: 125.1 | AX21: 112.25 | AY21: 81.45 | AZ21: 88 | BA21: 90.35 | BB21: 106.05 | BC21: 98.55 | BD21: 119.25 | BE21: 210 | BF21: 349
J22: 178.7 | K22: 108.95 | L22: 139.75 | N22: 186.75 | O22: 146.9 | P22: 169.1 | Q22: 139.75 | R22: 202.15 | S22: 249.05 | T22: 346.4 | U22: 349.2 | V22: 469.9 | W22: 584.8 | X22: 536.15 | Y22: 513.35 | Z22: 474 | AA22: 438.55 | AB22: 355.4 | AC22: 334.95 | AD22: 298.8 | AE22: 328.35 | AF22: 343 | AG22: 389.9 | AH22: 443.05 | AI22: 407.5 | AJ22: 290.1 | AK22: 235.75 | AL22: 292.65 | AM22: 276.1 | AN22: 237.05 | AO22: 190.1 | AP22: 147.2 | AQ22: 71.9 | AR22: 75.2 | AS22: 90.1 | AT22: 117.2 | AU22: 116.3 | AV22: 140.5 | AW22: 128.6 | AX22: 133.65 | AY22: 91.65 | AZ22: 97.65 | BA22: 125 | BB22: 115.35 | BC22: 119.25 | BD22: 219.3 | BE22: 442.65 | BF22: 503.35
J23: 207 | K23: 137 | L23: 202.15
J24: 255.15 | K24: 170 | L24: 249.05
J25: 348.25 | K25: 243.15 | L25: 346.4
J26: 374 | K26: 307.5 | L26: 349.2
J27: 495.9 | K27: 325.1 | L27: 469.9
J28: 659.9 | K28: 463 | L28: 584.8
J29: 613.4 | K29: 467.05 | L29: 536.15
J30: 607.9 | K30: 436.5 | L30: 513.35
J31: 555.95 | K31: 467 | L31: 474
J32: 497.8 | K32: 348.2 | L32: 438.55
J33: 459.9 | K33: 325 | L33: 355.4
J34: 374 | K34: 313.1 | L34: 334.95
... J63: 503.35 | K63: 349 | L63: 503.35
