Workbook

Sheet Template
A1: =+'Annual Raw'!C4 -> Balaji Amines Ltd. | B1: 36951 | C1: =EOMONTH(B1,12) -> 37346 | D1: =EOMONTH(C1,12) -> 37711 | E1: =EOMONTH(D1,12) -> 38077 | F1: =EOMONTH(E1,12) -> 38442 | G1: =EOMONTH(F1,12) -> 38807 | H1: =EOMONTH(G1,12) -> 39172 | I1: =EOMONTH(H1,12) -> 39538 | J1: =EOMONTH(I1,12) -> 39903 | ... AE1: =EOMONTH(AD1,12) -> 47573 | AH1: QTR | AI1: 41061 | AJ1: 41153 | AK1: 41244 | AL1: 41334 | AM1: 41426 | AN1: 41518 | AO1: 41609 | AP1: 41699 | AQ1: 41791 | AR1: 41883 | AS1: 41974 | AT1: 42064 | AU1: 42156 | AV1: 42248 | AW1: 42339 | AX1: 42430 | AY1: 42522 | AZ1: 42614 | BA1: 42705 | BB1: 42795 | BC1: 42887 | BD1: 42979 | BE1: 43070 | BF1: 43160 | BG1: 43252 | BH1: 43344 | BI1: 43435 | BJ1: 43525 | BK1: 43617 | BL1: 43709 | BM1: 43800 | BN1: 43891 | BO1: 43983 | BP1: 44075 | BQ1: =EOMONTH(BP1,3) -> 44196 | BR1: =EOMONTH(BQ1,3) -> 44286 | BS1: =EOMONTH(BR1,3) -> 44377 | BT1: =EOMONTH(BS1,3) -> 44469 | BU1: =EOMONTH(BT1,3) -> 44561 | BV1: =EOMONTH(BU1,3) -> 44651 | BW1: =EOMONTH(BV1,3) -> 44742 | BX1: =EOMONTH(BW1,3) -> 44834 | ... DB1: =EOMONTH(DA1,3) -> 47573 | DE1: HISTORICAL ESTIMATES | DF1: 46112
A2: Presentation Data (Start)
A3: Aliphatic amine capacity | W3: 112500 | X3: 112500 | Y3: 112500 | Z3: =Y3+40000 -> 152500 | AA3: =Z3 -> 152500 | AB3: =+SUM(CM3:CP3) -> 152500 | AC3: =+SUM(CQ3:CT3) -> 152500 | AD3: =+SUM(CU3:CX3) -> 152500 | AE3: =+SUM(CY3:DB3) -> 152500 | BS3: =BT3 -> 28125 | BT3: =BU3 -> 28125 | BU3: =BV3 -> 28125 | BV3: =W3/4 -> 28125 | BW3: =BX3 -> 28125 | BX3: =BY3 -> 28125 | BY3: =BZ3 -> 28125 | BZ3: =X3/4 -> 28125 | CA3: =CB3 -> 28125 | CB3: =CC3 -> 28125 | CC3: =CD3 -> 28125 | CD3: =Y3/4 -> 28125 | CE3: =CF3 -> 38125 | CF3: =CG3 -> 38125 | CG3: =CH3 -> 38125 | CH3: =Z3/4 -> 38125 | CI3: =CJ3 -> 38125 | CJ3: =CK3 -> 38125 | CK3: =CL3 -> 38125 | CL3: =AA3/4 -> 38125 | CM3: =CL3 -> 38125 | CN3: =CM3 -> 38125 | CO3: =CN3 -> 38125 | CP3: =CO3 -> 38125 | CQ3: =CP3 -> 38125 | CR3: =CQ3 -> 38125 | CS3: =CR3 -> 38125 | CT3: =CS3 -> 38125 | ... DB3: =DA3 -> 38125
A4: Amine Derivative Cpacity | W4: 61100 | X4: 61100 | Y4: 69000 | Z4: 69000 | AA4: 76000 | AB4: =+SUM(CM4:CP4) -> 76000 | AC4: =+SUM(CQ4:CT4) -> 76000 | AD4: =+SUM(CU4:CX4) -> 76000 | AE4: =+SUM(CY4:DB4) -> 76000 | BS4: =BT4 -> 15275 | BT4: =BU4 -> 15275 | BU4: =BV4 -> 15275 | BV4: =W4/4 -> 15275 | BW4: =BX4 -> 15275 | BX4: =BY4 -> 15275 | BY4: =BZ4 -> 15275 | BZ4: =X4/4 -> 15275 | CA4: =CB4 -> 17250 | CB4: =CC4 -> 17250 | CC4: =CD4 -> 17250 | CD4: =Y4/4 -> 17250 | CE4: =CF4 -> 17250 | CF4: =CG4 -> 17250 | CG4: =CH4 -> 17250 | CH4: =Z4/4 -> 17250 | CI4: =CJ4 -> 19000 | CJ4: =CK4 -> 19000 | CK4: =CL4 -> 19000 | CL4: =AA4/4 -> 19000 | CM4: =CL4 -> 19000 | CN4: =CM4 -> 19000 | CO4: =CN4 -> 19000 | CP4: =CO4 -> 19000 | CQ4: =CP4 -> 19000 | CR4: =CQ4 -> 19000 | CS4: =CR4 -> 19000 | CT4: =CS4 -> 19000 | ... DB4: =DA4 -> 19000
A5: Speciality chemical Capacity | W5: 37500 | X5: =X6-X3-X4 -> 63600 | Y5: =Y6-Y3-Y4 -> 63600 | Z5: =Z6-Z3-Z4 -> 63600 | AA5: =AA6-AA3-AA4 -> 65100 | AB5: =+SUM(CM5:CP5) -> 176850 | AC5: =+SUM(CQ5:CT5) -> 194100 | AD5: =+SUM(CU5:CX5) -> 208100 | AE5: =+SUM(CY5:DB5) -> 208100 | BS5: =BT5 -> 9375 | BT5: =BU5 -> 9375 | BU5: =BV5 -> 9375 | BV5: =W5/4 -> 9375 | BW5: =BX5 -> 15900 | BX5: =BY5 -> 15900 | BY5: =BZ5 -> 15900 | BZ5: =X5/4 -> 15900 | CA5: =CB5 -> 15900 | CB5: =CC5 -> 15900 | CC5: =CD5 -> 15900 | CD5: =Y5/4 -> 15900 | CE5: =CF5 -> 15900 | CF5: =CG5 -> 15900 | CG5: =CH5 -> 15900 | CH5: =Z5/4 -> 15900 | CI5: =CJ5 -> 16275 | CJ5: =CK5 -> 16275 | CK5: =CL5 -> 16275 | CL5: =AA5/4 -> 16275 | CM5: =CM6-CM3-CM4 -> 41275 | CN5: =CN6-CN3-CN4 -> 43525 | CO5: =CO6-CO3-CO4 -> 43525 | CP5: =CP6-CP3-CP4 -> 48525 | CQ5: =CQ6-CQ3-CQ4 -> 48525 | CR5: =CR6-CR3-CR4 -> 48525 | CS5: =CS6-CS3-CS4 -> 48525 | CT5: =CT6-CT3-CT4 -> 48525 | ... DB5: =DB6-DB3-DB4 -> 52025
A6: Capacity | W6: 211100 | X6: 237200 | Y6: 245100 | Z6: 285100 | AA6: 293600 | AB6: =+SUM(CM6:CP6) -> 405350 | AC6: =+SUM(CQ6:CT6) -> 422600 | AD6: =+SUM(CU6:CX6) -> 436600 | AE6: =+SUM(CY6:DB6) -> 436600 | BS6: =BT6 -> 52775 | BT6: =BU6 -> 52775 | BU6: =BV6 -> 52775 | BV6: =W6/4 -> 52775 | BW6: =BX6 -> 59300 | BX6: =BY6 -> 59300 | BY6: =BZ6 -> 59300 | BZ6: =X6/4 -> 59300 | CA6: =CB6 -> 61275 | CB6: =CC6 -> 61275 | CC6: =CD6 -> 61275 | CD6: =Y6/4 -> 61275 | CE6: =CF6 -> 71275 | CF6: =CG6 -> 71275 | CG6: =CH6 -> 71275 | CH6: =Z6/4 -> 71275 | CI6: =CJ6 -> 73400 | CJ6: =CK6 -> 73400 | CK6: =CL6 -> 73400 | CL6: =AA6/4 -> 73400 | CM6: =CL6+25000 -> 98400 | CN6: =CM6+2250 -> 100650 | CO6: =CN6 -> 100650 | CP6: =CO6+5000 -> 105650 | CQ6: =CP6 -> 105650 | CR6: =CQ6 -> 105650 | CS6: =CR6 -> 105650 | CT6: =CS6 -> 105650 | CU6: =CT6+3500 -> 109150 | CV6: =CU6 -> 109150 | CW6: =CV6 -> 109150 | CX6: =CW6 -> 109150 | CY6: =CX6 -> 109150 | CZ6: =CY6 -> 109150 | DA6: =CZ6 -> 109150 | DB6: =DA6 -> 109150
A7: Utilisation | W7: =+W12/W6 -> 0.54641876 | X7: =+X12/X6 -> 0.46587268 | Y7: =+Y12/Y6 -> 0.44602203 | Z7: =+Z12/Z6 -> 0.3661417 | AA7: =+AA12/AA6 -> 0.36434264 | AB7: =+AB12/AB6 -> 0.31206646 | AC7: =+AC12/AC6 -> 0.39358856 | AD7: =+AD12/AD6 -> 0.4579656 | AE7: =+AE12/AE6 -> 0.55487631 | BS7: =BS12/BS6 -> 0.4168072 | BT7: =BT12/BT6 -> 0.44725722 | BU7: =BU12/BU6 -> 0.52276646 | BV7: =BV12/BV6 -> 0.64007579 | BW7: =BW12/BW6 -> 0.46134907 | BX7: =BX12/BX6 -> 0.48052277 | BY7: =BY12/BY6 -> 0.4746543 | BZ7: =BZ12/BZ6 -> 0.44696459 | ... DB7: =DB12/DB6 -> 0.58258961
BS8: =BS12-BS11-BS10-BS9 -> 0 | BT8: =BT12-BT11-BT10-BT9 -> 0 | BU8: =BU12-BU11-BU10-BU9 -> 0 | BV8: =BV12-BV11-BV10-BV9 -> 0 | BW8: =BW12-BW11-BW10-BW9 -> 0 | BX8: =BX12-BX11-BX10-BX9 -> 0 | BY8: =BY12-BY11-BY10-BY9 -> 0
A9: Amines | U9: =SUM(BK9:BN9) -> 18331 | V9: =SUM(BO9:BR9) -> 20049 | W9: =SUM(BS9:BV9) -> 24999 | X9: =SUM(BW9:BZ9) -> 25789 | Y9: =SUM(CA9:CD9) -> 31459 | Z9: =SUM(CE9:CH9) -> 30848 | AA9: =SUM(CI9:CL9) -> 29997 | AB9: =+SUM(CM9:CP9) -> 32096.79 | AC9: =+SUM(CQ9:CT9) -> 34343.565 | AD9: =+SUM(CU9:CX9) -> 36747.615 | AE9: =+SUM(CY9:DB9) -> 39319.948 | BK9: 4280 | BL9: 4631 | BM9: 4500 | BN9: 4920 | BO9: 4153 | BP9: 5094 | BQ9: 4952 | BR9: 5850 | BS9: 5394 | BT9: 5861 | BU9: 6460 | BV9: 7284 | BW9: 6736 | BX9: 6312 | BY9: 6082 | BZ9: 6659 | CA9: 6754 | CB9: 8092 | CC9: 7703 | CD9: 8910 | CE9: 7401 | CF9: 7616 | CG9: 7515 | CH9: 8316 | CI9: 7573 | CJ9: 7685 | CK9: 6993 | CL9: 7746 | CM9: =CI9*(1+CM17) -> 8103.11 | CN9: =CJ9*(1+CN17) -> 8222.95 | CO9: =CK9*(1+CO17) -> 7482.51 | CP9: =CL9*(1+CP17) -> 8288.22 | CQ9: =CM9*(1+CQ17) -> 8670.3277 | CR9: =CN9*(1+CR17) -> 8798.5565 | CS9: =CO9*(1+CS17) -> 8006.2857 | CT9: =CP9*(1+CT17) -> 8868.3954 | ... DB9: =CX9*(1+DB17) -> 10153.426 | DF9: 8800
A10: Amines Derivatives | U10: =SUM(BK10:BN10) -> 36024 | V10: =SUM(BO10:BR10) -> 39545 | W10: =SUM(BS10:BV10) -> 37171 | X10: =SUM(BW10:BZ10) -> 33091 | Y10: =SUM(CA10:CD10) -> 37480 | Z10: =SUM(CE10:CH10) -> 34182 | AA10: =SUM(CI10:CL10) -> 34640 | AB10: =+SUM(CM10:CP10) -> 38104 | AC10: =+SUM(CQ10:CT10) -> 41914.4 | AD10: =+SUM(CU10:CX10) -> 46105.84 | AE10: =+SUM(CY10:DB10) -> 50716.424 | BK10: 8500 | BL10: 9024 | BM10: 9060 | BN10: 9440 | BO10: 8277 | BP10: 9916 | BQ10: 10812 | BR10: 10540 | BS10: 9587 | BT10: 8261 | BU10: 9912 | BV10: 9411 | BW10: 8131 | BX10: 7766 | BY10: 8587 | BZ10: 8607 | CA10: 8288 | CB10: 10236 | CC10: 9280 | CD10: 9676 | CE10: 8299 | CF10: 8685 | CG10: 8809 | CH10: 8389 | CI10: 8108 | CJ10: 8374 | CK10: 9223 | CL10: 8935 | CM10: =CI10*(1+CM18) -> 8918.8 | CN10: =CJ10*(1+CN18) -> 9211.4 | CO10: =CK10*(1+CO18) -> 10145.3 | CP10: =CL10*(1+CP18) -> 9828.5 | CQ10: =CM10*(1+CQ18) -> 9810.68 | CR10: =CN10*(1+CR18) -> 10132.54 | CS10: =CO10*(1+CS18) -> 11159.83 | CT10: =CP10*(1+CT18) -> 10811.35 | ... DB10: =CX10*(1+DB18) -> 13081.734 | DF10: 9400
A11: Specialty Chemicals | U11: =SUM(BK11:BN11) -> 30476 | V11: =+V12-V9-V10 -> 46463 | W11: =+W12-W9-W10 -> 53179 | X11: =SUM(BW11:BZ11) -> 51625 | Y11: =SUM(CA11:CD11) -> 40381 | Z11: =SUM(CE11:CH11) -> 39357 | AA11: =SUM(CI11:CL11) -> 42334 | AB11: =+SUM(CM11:CP11) -> 56295.35 | AC11: =+SUM(CQ11:CT11) -> 90072.56 | AD11: =+SUM(CU11:CX11) -> 117094.33 | AE11: =+SUM(CY11:DB11) -> 152222.63 | BK11: 7370 | BL11: 7720 | BM11: 7600 | BN11: 7786 | BO11: 9824 | BP11: 8140 | BQ11: 12589 | BR11: 12157 | BS11: 7016 | BT11: 9482 | BU11: 11217 | BV11: 17085 | BW11: 12491 | BX11: 14417 | BY11: 13478 | BZ11: 11239 | CA11: 11778 | CB11: 9285 | CC11: 9920 | CD11: 9398 | CE11: 12371 | CF11: 10046 | CG11: 7773 | CH11: 9167 | CI11: 11889 | CJ11: 10107 | CK11: 9678 | CL11: 10660 | CM11: =CI11*(1+CM19) -> 13672.35 | CN11: =CJ11*(1+CN19) -> 14149.8 | CO11: =CK11*(1+CO19) -> 13549.2 | CP11: =CL11*(1+CP19) -> 14924 | CQ11: =CM11*(1+CQ19) -> 21875.76 | CR11: =CN11*(1+CR19) -> 22639.68 | CS11: =CO11*(1+CS19) -> 21678.72 | CT11: =CP11*(1+CT19) -> 23878.4 | ... DB11: =CX11*(1+DB19) -> 40354.496 | DF11: 12300
A12: Volume MT | T12: 79776 | U12: =U9+U10+U11 -> 84831 | V12: 106057 | W12: 115349 | X12: =X9+X10+X11 -> 110505 | Y12: =Y9+Y10+Y11 -> 109320 | Z12: =Z9+Z10+Z11 -> 104387 | AA12: =AA9+AA10+AA11 -> 106971 | AB12: =AB9+AB10+AB11 -> 126496.14 | AC12: =AC9+AC10+AC11 -> 166330.53 | AD12: =AD9+AD10+AD11 -> 199947.78 | AE12: =AE9+AE10+AE11 -> 242259 | BG12: 21678 | BH12: 17426 | BI12: 19128 | BJ12: 21543 | BK12: =BK9+BK10+BK11 -> 20150 | BL12: =BL9+BL10+BL11 -> 21375 | BM12: =BM9+BM10+BM11 -> 21160 | BN12: =BN9+BN10+BN11 -> 22146 | BO12: =BO9+BO10+BO11 -> 22254 | BP12: =BP9+BP10+BP11 -> 23150 | BQ12: =BQ9+BQ10+BQ11 -> 28353 | BR12: =BR9+BR10+BR11 -> 28547 | ... CB12: =CB9+CB10+CB11 -> 27613 | CC12: 26903 | CD12: 27975 | CE12: 28071 | CF12: 26348 | CG12: 24097 | CH12: =CH9+CH10+CH11 -> 25872 | CI12: =CI9+CI10+CI11 -> 27570 | CJ12: =CJ9+CJ10+CJ11 -> 26166 | CK12: =CK9+CK10+CK11 -> 25894 | CL12: =CL9+CL10+CL11 -> 27341 | CM12: =CM9+CM10+CM11 -> 30694.26 | CN12: =CN9+CN10+CN11 -> 31584.15 | CO12: =CO9+CO10+CO11 -> 31177.01 | ... DB12: =DB9+DB10+DB11 -> 63589.655 | DF12: 30500
A13: YOY% | V13: =V12/U12-1 -> 0.25021513 | W13: =W12/V12-1 -> 0.087613265 | X13: =X12/W12-1 -> -0.041994296 | Y13: =Y12/X12-1 -> -0.010723497 | Z13: =Z12/Y12-1 -> -0.045124405 | AA13: =AA12/Z12-1 -> 0.02475404 | AB13: =AB12/AA12-1 -> 0.18252741 | AC13: =AC12/AB12-1 -> 0.31490594 | ... AE13: =AE12/AD12-1 -> 0.21161133 | BK13: =BK12/BG12-1 -> -0.070486207 | BL13: =BL12/BH12-1 -> 0.2266154 | BM13: =BM12/BI12-1 -> 0.1062317 | BN13: =BN12/BJ12-1 -> 0.027990531 | BO13: =BO12/BK12-1 -> 0.10441687 | BP13: =BP12/BL12-1 -> 0.083040936 | BQ13: =BQ12/BM12-1 -> 0.33993384 | BR13: =BR12/BN12-1 -> 0.28903639 | ... DB13: =DB12/CX12-1 -> 0.21299701 | DF13: 0.17888064
A14: Subsidiary Volume | V14: =+V12-94687 -> 11370 | W14: =+W12-98179 -> 17170 | X14: =+X12-89231 -> 21274 | Y14: =+Y12-96596 -> 12724 | Z14: =+Z12-98086 -> 6301 | AA14: =+AA12-98622 -> 8349 | AB14: =+SUM(CM14:CP14) -> 9288 | AC14: =+SUM(CQ14:CT14) -> 15875 | AD14: =+SUM(CU14:CX14) -> 21500 | AE14: =+SUM(CY14:DB14) -> 26000 | CE14: =+CE12+CF12+CG12-74039 -> 4477 | CF14: =+CF12-25041 -> 1307 | CG14: =+CG12-23447 -> 650 | CH14: =+CH12-24047 -> 1825 | CI14: =+CI12+CJ12+CK12-73227 -> 6403 | CJ14: =+CJ12-24523 -> 1643 | CK14: =+CK12-23856 -> 2038 | CL14: =+CL12-25394 -> 1947 | CM14: =+CL14 -> 1947 | CN14: =+CM14 -> 1947 | CO14: =+CN14 -> 1947 | CP14: =+CO14+(3750*40%) -> 3447 | CQ14: =2000+(3750*40%) -> 3500 | CR14: =2000+(3750*50%) -> 3875 | CS14: =2000+(3750*60%) -> 4250 | CT14: =2000+(3750*60%) -> 4250 | CU14: =2000+(3750*80%) -> 5000 | CV14: =2000+(3750*80%) -> 5000 | CW14: =2000+(3750*80%) -> 5000 | CX14: =+CW14+1500 -> 6500 | CY14: =+CX14 -> 6500 | CZ14: =+CY14 -> 6500 | DA14: =+CZ14 -> 6500 | DB14: =+DA14 -> 6500
A16: Growth
A17: Amines vol growth | V17: =V9/U9-1 -> 0.093721019 | W17: =W9/V9-1 -> 0.24689511 | X17: =X9/W9-1 -> 0.031601264 | Y17: =Y9/X9-1 -> 0.21986118 | Z17: =Z9/Y9-1 -> -0.019422105 | AA17: =AA9/Z9-1 -> -0.027586878 | AB17: =AB9/AA9-1 -> 0.07 | AC17: =AC9/AB9-1 -> 0.07 | ... AE17: =AE9/AD9-1 -> 0.07 | BO17: =BO9/BK9-1 -> -0.029672897 | BP17: =BP9/BL9-1 -> 0.099978406 | BQ17: =BQ9/BM9-1 -> 0.10044444 | BR17: =BR9/BN9-1 -> 0.18902439 | BS17: =BS9/BO9-1 -> 0.29882013 | BT17: =BT9/BP9-1 -> 0.1505693 | BU17: =BU9/BQ9-1 -> 0.30452342 | BV17: =BV9/BR9-1 -> 0.24512821 | ... CL17: =CL9/CH9-1 -> -0.068542569 | CM17: 0.07 | CN17: 0.07 | CO17: 0.07 | CP17: 0.07 | CQ17: 0.07 | CR17: 0.07 | CS17: 0.07 | CT17: 0.07 | CU17: 0.07 | CV17: 0.07 | CW17: 0.07 | CX17: 0.07 | CY17: 0.07 | CZ17: 0.07 | DA17: 0.07 | DB17: 0.07
A18: Amines Derivatives vol growth | V18: =V10/U10-1 -> 0.097740395 | W18: =W10/V10-1 -> -0.060032874 | X18: =X10/W10-1 -> -0.10976299 | Y18: =Y10/X10-1 -> 0.13263425 | Z18: =Z10/Y10-1 -> -0.087993597 | AA18: =AA10/Z10-1 -> 0.013398865 | AB18: =AB10/AA10-1 -> 0.1 | AC18: =AC10/AB10-1 -> 0.1 | ... AE18: =AE10/AD10-1 -> 0.1 | BO18: =BO10/BK10-1 -> -0.026235294 | BP18: =BP10/BL10-1 -> 0.098847518 | BQ18: =BQ10/BM10-1 -> 0.19337748 | BR18: =BR10/BN10-1 -> 0.11652542 | BS18: =BS10/BO10-1 -> 0.1582699 | BT18: =BT10/BP10-1 -> -0.16690198 | BU18: =BU10/BQ10-1 -> -0.083240844 | BV18: =BV10/BR10-1 -> -0.10711575 | ... CL18: =CL10/CH10-1 -> 0.065085231 | CM18: 0.1 | CN18: 0.1 | CO18: 0.1 | CP18: 0.1 | CQ18: 0.1 | CR18: 0.1 | CS18: 0.1 | CT18: 0.1 | CU18: 0.1 | CV18: 0.1 | CW18: 0.1 | CX18: 0.1 | CY18: 0.1 | CZ18: 0.1 | DA18: 0.1 | DB18: 0.1
A19: Specialty Chemicals vol growth | V19: =V11/U11-1 -> 0.52457672 | W19: =W11/V11-1 -> 0.14454512 | X19: =X11/W11-1 -> -0.029222061 | Y19: =Y11/X11-1 -> -0.21780145 | Z19: =Z11/Y11-1 -> -0.025358461 | AA19: =AA11/Z11-1 -> 0.075640928 | AB19: =AB11/AA11-1 -> 0.32979048 | AC19: =AC11/AB11-1 -> 0.6 | ... AE19: =AE11/AD11-1 -> 0.3 | BO19: =BO11/BK11-1 -> 0.33297151 | BP19: =BP11/BL11-1 -> 0.054404145 | BQ19: =BQ11/BM11-1 -> 0.65644737 | BR19: =BR11/BN11-1 -> 0.56139224 | BS19: =BS11/BO11-1 -> -0.28583062 | BT19: =BT11/BP11-1 -> 0.16486486 | BU19: =BU11/BQ11-1 -> -0.10898403 | BV19: =BV11/BR11-1 -> 0.40536317 | ... CL19: =CL11/CH11-1 -> 0.1628668 | CM19: 0.15 | CN19: 0.4 | CO19: 0.4 | CP19: 0.4 | CQ19: 0.6 | CR19: 0.6 | CS19: 0.6 | CT19: 0.6 | CU19: 0.3 | CV19: 0.3 | CW19: 0.3 | CX19: 0.3 | CY19: 0.3 | CZ19: 0.3 | DA19: 0.3 | DB19: 0.3
A21: Realisation MT | T21: =T59*10^7/T12 -> 118212.4 | U21: =U59*10^7/U12 -> 110310.13 | V21: =V59*10^7/V12 -> 123655.69 | W21: =W59*10^7/W12 -> 201378.74 | X21: =X59*10^7/X12 -> 213148.33 | Y21: =Y59*10^7/Y12 -> 150156.7 | Z21: =Z59*10^7/Z12 -> 133837.01 | AA21: =AA59*10^7/AA12 -> 120737.84 | ... AE21: =AE59*10^7/AE12 -> 233154.08 | BG21: =BG59*10^7/BG12 -> 119885.14 | BH21: =BH59*10^7/BH12 -> 124148.4 | BI21: =BI59*10^7/BI12 -> 124850.48 | BJ21: =BJ59*10^7/BJ12 -> 105194.73 | BK21: =BK59*10^7/BK12 -> 110658.56 | BL21: =BL59*10^7/BL12 -> 106317.19 | BM21: =BM59*10^7/BM12 -> 107521.27 | BN21: =BN59*10^7/BN12 -> 116511.79 | ... CL21: =CL59*10^7/CL12 -> 144393.4 | CM21: =CI21+(CI21*CM22) -> 149471.22 | CN21: =CJ21+(CJ21*CN22) -> 149673.16 | CO21: =CK21+(CK21*CO22) -> 147136.85 | CP21: =CL21+(CL21*CP22) -> 166052.41 | CQ21: =CM21+(CM21*CQ22) -> 171891.9 | CR21: =CN21+(CN21*CR22) -> 172124.14 | CS21: =CO21+(CO21*CS22) -> 169207.37 | CT21: =CP21+(CP21*CT22) -> 190960.27 | ... DB21: =CX21+(CX21*DB22) -> 252544.96 | DF21: 144516
A22: YOY% | V22: =V21/U21-1 -> 0.12098217 | W22: =W21/V21-1 -> 0.62854411 | X22: =X21/W21-1 -> 0.058445051 | Y22: =Y21/X21-1 -> -0.29552956 | Z22: =Z21/Y21-1 -> -0.10868437 | AA22: =AA21/Z21-1 -> -0.097874085 | AB22: =AB21/AA21-1 -> 0.26950508 | AC22: =AC21/AB21-1 -> 0.15010046 | ... AE22: =AE21/AD21-1 -> 0.15004412 | BK22: =BK21/BG21-1 -> -0.076961802 | BL22: =BL21/BH21-1 -> -0.14362816 | BM22: =BM21/BI21-1 -> -0.13879974 | BN22: =BN21/BJ21-1 -> 0.107582 | BO22: =BO21/BK21-1 -> -0.094816872 | BP22: =BP21/BL21-1 -> 0.14732677 | BQ22: =BQ21/BM21-1 -> 0.2862736 | BR22: =BR21/BN21-1 -> 0.24481747 | ... CL22: =CL21/CH21-1 -> 0.05910109 | CM22: 0.15 | CN22: 0.15 | CO22: 0.15 | CP22: 0.15 | CQ22: 0.15 | CR22: 0.15 | CS22: 0.15 | CT22: 0.15 | CU22: 0.15 | CV22: 0.15 | CW22: 0.15 | CX22: 0.15 | CY22: 0.15 | CZ22: 0.15 | DA22: 0.15 | DB22: 0.15
A24: Unit Matrix per kg
A25: Sales | T25: =T21/1000 -> 118.2124 | U25: =U21/1000 -> 110.31013 | V25: =V21/1000 -> 123.65569 | W25: =W21/1000 -> 201.37874 | X25: =X21/1000 -> 213.14833 | Y25: =Y21/1000 -> 150.1567 | Z25: =Z21/1000 -> 133.83701 | AA25: =AA21/1000 -> 120.73784 | ... AE25: =AE21/1000 -> 233.15408 | BG25: =BG21/1000 -> 119.88514 | BH25: =BH21/1000 -> 124.1484 | BI25: =BI21/1000 -> 124.85048 | BJ25: =BJ21/1000 -> 105.19473 | BK25: =BK21/1000 -> 110.65856 | BL25: =BL21/1000 -> 106.31719 | BM25: =BM21/1000 -> 107.52127 | BN25: =BN21/1000 -> 116.51179 | ... DB25: =DB21/1000 -> 252.54496
A26: Raw Mat | T26: =T25-T27 -> 64.60046 | U26: =U25-U27 -> 60.571087 | V26: =V25-V27 -> 59.426167 | W26: =W25-W27 -> 105.98497 | X26: =X25-X27 -> 112.73594 | Y26: =Y25-Y27 -> 82.619704 | Z26: =Z25-Z27 -> 74.784523 | AA26: =AA25-AA27 -> 66.356648 | ... AE26: =AE25-AE27 -> 128.04362 | BG26: =BG25-BG27 -> 65.14946 | BH26: =BH25-BH27 -> 65.316768 | BI26: =BI25-BI27 -> 72.905688 | BJ26: =BJ25-BJ27 -> 56.097572 | BK26: =BK25-BK27 -> 64.626799 | BL26: =BL25-BL27 -> 58.277427 | BM26: =BM25-BM27 -> 57.562854 | BN26: =BN25-BN27 -> 61.968753 | ... DB26: =DB25-DB27 -> 138.68952
A27: GP | T27: =T65*10^7/T12/1000 -> 53.611944 | U27: =U65*10^7/U12/1000 -> 49.73904 | V27: =V65*10^7/V12/1000 -> 64.229518 | W27: =W65*10^7/W12/1000 -> 95.39377 | X27: =X65*10^7/X12/1000 -> 100.41239 | Y27: =Y65*10^7/Y12/1000 -> 67.536992 | Z27: =Z65*10^7/Z12/1000 -> 59.052487 | AA27: =AA65*10^7/AA12/1000 -> 54.381187 | ... AE27: =AE65*10^7/AE12/1000 -> 105.11046 | BG27: =BG65*10^7/BG12/1000 -> 54.735677 | BH27: =BH65*10^7/BH12/1000 -> 58.831631 | BI27: =BI65*10^7/BI12/1000 -> 51.944793 | BJ27: =BJ65*10^7/BJ12/1000 -> 49.097155 | BK27: =BK65*10^7/BK12/1000 -> 46.031762 | BL27: =BL65*10^7/BL12/1000 -> 48.039766 | BM27: =BM65*10^7/BM12/1000 -> 49.958412 | BN27: =BN65*10^7/BN12/1000 -> 54.543033 | ... DB27: =DB65*10^7/DB12/1000 -> 113.85544
A28: Other Cost | T28: =T27-T29 -> 29.600352 | U28: =U27-U29 -> 28.816871 | V28: =V27-V29 -> 29.537107 | W28: =W27-W29 -> 41.412496 | X28: =X27-X29 -> 45.291453 | Y28: =Y27-Y29 -> 37.923591 | Z28: =Z27-Z29 -> 36.813071 | AA28: =AA27-AA29 -> 31.266409 | ... AE28: =AE27-AE29 -> 55.167502 | BG28: =BG27-BG29 -> 27.670449 | BH28: =BH27-BH29 -> 33.127511 | BI28: =BI27-BI29 -> 29.677959 | BJ28: =BJ27-BJ29 -> 27.117393 | BK28: =BK27-BK29 -> 27.415385 | BL28: =BL27-BL29 -> 27.096608 | BM28: =BM27-BM29 -> 29.714083 | BN28: =BN27-BN29 -> 29.422469 | ... DB28: =DB27-DB29 -> 59.750727
A29: EBIDTA | T29: =T77*10^7/T12/1000 -> 24.011592 | U29: =U77*10^7/U12/1000 -> 20.922168 | V29: =V77*10^7/V12/1000 -> 34.692411 | W29: =W77*10^7/W12/1000 -> 53.981274 | X29: =X77*10^7/X12/1000 -> 55.120936 | Y29: =Y77*10^7/Y12/1000 -> 29.613401 | Z29: =Z77*10^7/Z12/1000 -> 22.239417 | AA29: =AA77*10^7/AA12/1000 -> 23.114779 | ... AE29: =AE77*10^7/AE12/1000 -> 49.942957 | BG29: =BG77*10^7/BG12/1000 -> 27.065227 | BH29: =BH77*10^7/BH12/1000 -> 25.70412 | BI29: =BI77*10^7/BI12/1000 -> 22.266834 | BJ29: =BJ77*10^7/BJ12/1000 -> 21.979761 | BK29: =BK77*10^7/BK12/1000 -> 18.616377 | BL29: =BL77*10^7/BL12/1000 -> 20.943158 | BM29: =BM77*10^7/BM12/1000 -> 20.244329 | BN29: =BN77*10^7/BN12/1000 -> 25.120564 | ... DB29: =DB77*10^7/DB12/1000 -> 54.104711
A32: Standalone Sales | T32: 949.83162 | U32: 919.0541 | V32: 1227.7795 | W32: 1920.6656 | X32: 1726.2831 | Y32: 1337.8444 | Z32: 1273.5923 | AA32: 1291 | CE32: 332.84 | CF32: 319.96 | CG32: 299.23 | CH32: 321.56 | CI32: 319.38 | CJ32: 309.2 | CK32: 301.2 | CL32: 361.77
A33: Standalone GP | T33: 427.63499 | U33: 407.88629 | V33: 605.0869 | W33: 847.6005 | X33: 721.1757 | Y33: 582.3397 | Z33: 567.2438 | AA33: =+AA32-726.56+16.76 -> 581.2 | CE33: 145.96 | CF33: 143.64 | CG33: 135.11 | CH33: 142.53 | CI33: 138.54 | CJ33: 132.67 | CK33: 133.04 | CL33: 171.62
A34: Standalone EBIDTA | T34: 191.55097 | U34: 175.85258 | V34: 321.9886 | W34: 440.9547 | X34: 329.6126 | Y34: 246.5493 | Z34: 226.4104 | AA34: 247.26 | CE34: 58.88 | CF34: 57.83 | CG34: 51.66 | CH34: 58.05 | CI34: 56.47 | CJ34: 50.01 | CK34: 54.7 | CL34: 86.08
A35: Standalone PAT | T35: 118.07628 | U35: 113.75306 | V35: 231.711 | W35: 307.941 | X35: 227.5422 | Y35: 171.3041 | Z35: 156.2127 | AA35: 165.53 | CE35: 40.52 | CF35: 40.4 | CG35: 35.69 | CH35: 39.6 | CI35: 39.8 | CJ35: 31.45 | CK35: 32.42 | CL35: 61.87
A36: Standalone GM | T36: =+T33/T32 -> 0.45022189 | U36: =+U33/U32 -> 0.44381096 | V36: =+V33/V32 -> 0.49283027 | W36: =+W33/W32 -> 0.44130561 | X36: =+X33/X32 -> 0.41776213 | Y36: =+Y33/Y32 -> 0.43528209 | Z36: =+Z33/Z32 -> 0.44538884 | AA36: =+AA33/AA32 -> 0.45019365 | CE36: =+CE33/CE32 -> 0.43852902 | CF36: =+CF33/CF32 -> 0.44893112 | CG36: =+CG33/CG32 -> 0.45152558 | CH36: =+CH33/CH32 -> 0.44324543 | CI36: =+CI33/CI32 -> 0.43377794 | CJ36: =+CJ33/CJ32 -> 0.42907503 | CK36: =+CK33/CK32 -> 0.44169987 | CL36: =+CL33/CL32 -> 0.47438981
A37: Standalone EBIDTA Margins | T37: =+T34/T32 -> 0.20166834 | U37: =+U34/U32 -> 0.19134084 | V37: =+V34/V32 -> 0.26225279 | W37: =+W34/W32 -> 0.22958432 | X37: =+X34/X32 -> 0.19093774 | Y37: =+Y34/Y32 -> 0.18428847 | Z37: =+Z34/Z32 -> 0.17777306 | AA37: =+AA34/AA32 -> 0.19152595 | CE37: =+CE34/CE32 -> 0.17690181 | CF37: =+CF34/CF32 -> 0.18074134 | CG37: =+CG34/CG32 -> 0.17264312 | CH37: =+CH34/CH32 -> 0.18052618 | CI37: =+CI34/CI32 -> 0.17681132 | CJ37: =+CJ34/CJ32 -> 0.16173997 | CK37: =+CK34/CK32 -> 0.18160691 | CL37: =+CL34/CL32 -> 0.23794123
A39: Subsidiary Sales | T39: =+T57-T32 -> -6.780348 | U39: =+U57-U32 -> 16.717735 | V39: =+V57-V32 -> 83.6756 | W39: =+W57-W32 -> 405.589 | X39: =+X57-X32 -> 633.152 | Y39: =+Y57-Y32 -> 304.6916 | Z39: =+Z57-Z32 -> 127.1083 | AA39: =+AA57-AA32 -> 3.111 | AB39: =+SUM(CM39:CP39) -> 222.396 | AC39: =+SUM(CQ39:CT39) -> 617.616 | AD39: =+SUM(CU39:CX39) -> 955.116 | AE39: =+SUM(CY39:DB39) -> 1225.116 | CE39: =+CE57-CE32 -> 51.906 | CF39: =+CF57-CF32 -> 26.923 | CG39: =+CG57-CG32 -> 13.498 | CH39: =+CH57-CH32 -> 31.168 | CI39: =+CI57-CI32 -> 38.961 | CJ39: =+CJ57-CJ32 -> 31.352 | CK39: =+CK57-CK32 -> 30.101 | CL39: =+CL57-CL32 -> 33.016 | CM39: =+(1947*170/10^4) -> 33.099 | CN39: =+(1947*170/10^4) -> 33.099 | CO39: =+(1947*170/10^4) -> 33.099 | CP39: =+(1947*170/10^4)+(CP14-1947)*600/10^4 -> 123.099 | CQ39: =+(1947*170/10^4)+(CQ14-1947)*600/10^4 -> 126.279 | CR39: =+(1947*170/10^4)+(CR14-1947)*600/10^4 -> 148.779 | CS39: =+(1947*170/10^4)+(CS14-1947)*600/10^4 -> 171.279 | CT39: =+(1947*170/10^4)+(CT14-1947)*600/10^4 -> 171.279 | CU39: =+(1947*170/10^4)+(CU14-1947)*600/10^4 -> 216.279 | CV39: =+(1947*170/10^4)+(CV14-1947)*600/10^4 -> 216.279 | CW39: =+(1947*170/10^4)+(CW14-1947)*600/10^4 -> 216.279 | ... DB39: =+(1947*170/10^4)+(DB14-1947)*600/10^4 -> 306.279
A40: Subsidiary GP | T40: =+T65-T33 -> 0.0596589 | U40: =+U65-U33 -> 14.05496 | V40: =+V65-V33 -> 76.1121 | W40: =+W65-W33 -> 252.7571 | X40: =+X65-X33 -> 388.4314 | Y40: =+Y65-Y33 -> 155.9747 | Z40: =+Z65-Z33 -> 49.1874 | AA40: =+AA65-AA33 -> 0.521 | AB40: =+SUM(CM40:CP40) -> 0 | AC40: =+SUM(CQ40:CT40) -> 0 | AD40: =+SUM(CU40:CX40) -> 0 | AE40: =+SUM(CY40:DB40) -> 0 | CE40: =+CE65-CE33 -> 21.741 | CF40: =+CF65-CF33 -> 15.234 | CG40: =+CG65-CG33 -> 0.021 | CH40: =+CH65-CH33 -> 12.194 | CI40: =+CI65-CI33 -> 7.789 | CJ40: =+CJ65-CJ33 -> 22.832 | CK40: =+CK65-CK33 -> 14.502 | CL40: =+CL65-CL33 -> 2.13
A41: Subsidiary EBIDTA | T41: =+T77-T34 -> 0.003908 | U41: =+U77-U34 -> 1.6322637 | V41: =+V77-V34 -> 45.9487 | W41: =+W77-W34 -> 181.7139 | X41: =+X77-X34 -> 279.5013 | Y41: =+Y77-Y34 -> 77.1844 | Z41: =+Z77-Z34 -> 5.7402 | AA41: =+AA77-AA34 -> 0.0011 | AB41: =+SUM(CM41:CP41) -> 48.92712 | AC41: =+SUM(CQ41:CT41) -> 135.87552 | AD41: =+SUM(CU41:CX41) -> 210.12552 | AE41: =+SUM(CY41:DB41) -> 269.52552 | CE41: =+CE77-CE34 -> 7.214 | CF41: =+CF77-CF34 -> 2.858 | CG41: =+CG77-CG34 -> -5.956 | CH41: =+CH77-CH34 -> 1.613 | CI41: =+CI77-CI34 -> -1.775 | CJ41: =+CJ77-CJ34 -> 9.804 | CK41: =+CK77-CK34 -> 1.975 | CL41: =+CL77-CL34 -> 8.169 | CM41: =+CM39*22% -> 7.28178 | CN41: =+CN39*22% -> 7.28178 | CO41: =+CO39*22% -> 7.28178 | CP41: =+CP39*22% -> 27.08178 | CQ41: =+CQ39*22% -> 27.78138 | CR41: =+CR39*22% -> 32.73138 | CS41: =+CS39*22% -> 37.68138 | CT41: =+CT39*22% -> 37.68138 | ... DB41: =+DB39*22% -> 67.38138
A42: Subsidiary Int Dep tax | CE42: =+CE41-CE43 -> 2.175 | CF42: =+CF41-CF43 -> 1.804 | CG42: =+CG41-CG43 -> -1.403 | CH42: =+CH41-CH43 -> 0.773 | CI42: =+CI41-CI43 -> 1.497 | CJ42: =+CJ41-CJ43 -> 4.152 | CK42: =+CK41-CK43 -> 3.637 | CL42: =+CL41-CL43 -> 5.271 | ... DB42: =+DB41-DB43 -> 30.6279
A43: Subsidiary PAT | T43: =+T90-T35 -> -0.9877521 | U43: =+U90-U35 -> -16.282793 | V43: =+V90-V35 -> 11.7846 | W43: =+W90-W35 -> 109.9597 | X43: =+X90-X35 -> 178.1408 | Y43: =+Y90-Y35 -> 60.9989 | Z43: =+Z90-Z35 -> 2.3787 | AA43: =+AA90-AA35 -> -0.0017 | AB43: =+SUM(CM43:CP43) -> 26.68752 | AC43: =+SUM(CQ43:CT43) -> 74.11392 | AD43: =+SUM(CU43:CX43) -> 114.61392 | AE43: =+SUM(CY43:DB43) -> 147.01392 | CE43: =+CE90-CE35 -> 5.039 | CF43: =+CF90-CF35 -> 1.054 | CG43: =+CG90-CG35 -> -4.553 | CH43: =+CH90-CH35 -> 0.84 | CI43: =+CI90-CI35 -> -3.272 | CJ43: =+CJ90-CJ35 -> 5.652 | CK43: =+CK90-CK35 -> -1.662 | CL43: =+CL90-CL35 -> 2.898 | CM43: =+CM39*12% -> 3.97188 | CN43: =+CN39*12% -> 3.97188 | CO43: =+CO39*12% -> 3.97188 | CP43: =+CP39*12% -> 14.77188 | CQ43: =+CQ39*12% -> 15.15348 | CR43: =+CR39*12% -> 17.85348 | CS43: =+CS39*12% -> 20.55348 | CT43: =+CT39*12% -> 20.55348 | ... DB43: =+DB39*12% -> 36.75348
A44: Minority Int | T44: =+T94 -> 0.4444885 | U44: =+U94 -> 7.3272567 | V44: =+V94 -> -5.3031 | W44: =+W94 -> -49.4819 | X44: =+X94 -> -80.163 | Y44: =+Y94 -> -27.4494 | Z44: =+Z94 -> -1.0704 | AA44: =+AA94 -> 0 | AB44: =+SUM(CM44:CP44) -> -12.009384 | AC44: =+SUM(CQ44:CT44) -> -33.351264 | AD44: =+SUM(CU44:CX44) -> -51.576264 | AE44: =+SUM(CY44:DB44) -> -66.156264 | CE44: =+CE94 -> -2.266 | CF44: =+CF94 -> -0.474 | CG44: =+CG94 -> 2.047 | CH44: =+CH94 -> -0.378 | CI44: =+CI94 -> 1.473 | CJ44: =+CJ94 -> -2.543 | CK44: =+CK94 -> 0.676 | CL44: =+CL94 -> -1.562 | CM44: =+CM43*CM45 -> -1.787346 | CN44: =+CN43*CN45 -> -1.787346 | CO44: =+CO43*CO45 -> -1.787346 | CP44: =+CP43*CP45 -> -6.647346 | CQ44: =+CQ43*CQ45 -> -6.819066 | CR44: =+CR43*CR45 -> -8.034066 | CS44: =+CS43*CS45 -> -9.249066 | CT44: =+CT43*CT45 -> -9.249066 | ... DB44: =+DB43*DB45 -> -16.539066
A45: Minority Int % | T45: =+T44/T43 -> -0.45000006 | U45: =+U44/U43 -> -0.45 | V45: =+V44/V43 -> -0.45000255 | W45: =+W44/W43 -> -0.45000032 | X45: =+X44/X43 -> -0.44999798 | Y45: =+Y44/Y43 -> -0.44999828 | Z45: =+Z44/Z43 -> -0.44999369 | AA45: =+AA44/AA43 -> 0 | ... AE45: =+AE44/AE43 -> -0.45 | CE45: =+CE44/CE43 -> -0.4496924 | CF45: =+CF44/CF43 -> -0.44971537 | CG45: =+CG44/CG43 -> -0.44959367 | CH45: =+CH44/CH43 -> -0.45 | CI45: =+CI44/CI43 -> -0.45018337 | CJ45: =+CJ44/CJ43 -> -0.44992923 | CK45: =+CK44/CK43 -> -0.40673887 | CL45: =+CL44/CL43 -> -0.53899241 | CM45: -0.45 | CN45: -0.45 | CO45: -0.45 | CP45: -0.45 | CQ45: -0.45 | CR45: -0.45 | CS45: -0.45 | CT45: -0.45 | CU45: -0.45 | CV45: -0.45 | CW45: -0.45 | CX45: -0.45 | CY45: -0.45 | CZ45: -0.45 | DA45: -0.45 | DB45: -0.45
A46: Subsidiary GM | T46: =+T40/T39 -> -0.0087987962 | U46: =+U40/U39 -> 0.84072158 | V46: =+V40/V39 -> 0.90960925 | W46: =+W40/W39 -> 0.62318529 | X46: =+X40/X39 -> 0.61348839 | Y46: =+Y40/Y39 -> 0.51191008 | Z46: =+Z40/Z39 -> 0.38697237 | AA46: =+AA40/AA39 -> 0.16747027 | ... AE46: =+AE40/AE39 -> 0 | CE46: =+CE40/CE39 -> 0.41885331 | CF46: =+CF40/CF39 -> 0.5658359 | CG46: =+CG40/CG39 -> 0.001555786 | CH46: =+CH40/CH39 -> 0.3912346 | CI46: =+CI40/CI39 -> 0.19991787 | CJ46: =+CJ40/CJ39 -> 0.728247 | CK46: =+CK40/CK39 -> 0.48177801 | CL46: =+CL40/CL39 -> 0.064514175
A47: Subsidiary EBIDTA Margins | T47: =+T41/T39 -> -0.0005763716 | U47: =+U41/U39 -> 0.097636656 | V47: =+V41/V39 -> 0.54912902 | W47: =+W41/W39 -> 0.44802472 | X47: =+X41/X39 -> 0.44144423 | Y47: =+Y41/Y39 -> 0.25331975 | Z47: =+Z41/Z39 -> 0.045159915 | AA47: =+AA41/AA39 -> 0.00035358406 | ... AE47: =+AE41/AE39 -> 0.22 | CE47: =+CE41/CE39 -> 0.13898201 | CF47: =+CF41/CF39 -> 0.10615459 | CG47: =+CG41/CG39 -> -0.44125056 | CH47: =+CH41/CH39 -> 0.051751797 | CI47: =+CI41/CI39 -> -0.045558379 | CJ47: =+CJ41/CJ39 -> 0.31270732 | CK47: =+CK41/CK39 -> 0.065612438 | CL47: =+CL41/CL39 -> 0.24742549 | ... DB47: =+DB41/DB39 -> 0.22
A49: Subsidiary Sales per kg | V49: =+V39*10^7/V14/1000 -> 73.593316 | W49: =+W39*10^7/W14/1000 -> 236.21957 | X49: =+X39*10^7/X14/1000 -> 297.61775 | Y49: =+Y39*10^7/Y14/1000 -> 239.46212 | Z49: =+Z39*10^7/Z14/1000 -> 201.72719 | AA49: =+AA39*10^7/AA14/1000 -> 3.7261948 | AB49: =+AB39*10^7/AB14/1000 -> 239.44444 | AC49: =+AC39*10^7/AC14/1000 -> 389.04945 | ... AE49: =+AE39*10^7/AE14/1000 -> 471.19846 | CE49: =+CE39*10^7/CE14/1000 -> 115.93925 | CF49: =+CF39*10^7/CF14/1000 -> 205.99082 | CG49: =+CG39*10^7/CG14/1000 -> 207.66154 | CH49: =+CH39*10^7/CH14/1000 -> 170.78356 | CI49: =+CI39*10^7/CI14/1000 -> 60.84804 | CJ49: =+CJ39*10^7/CJ14/1000 -> 190.82167 | CK49: =+CK39*10^7/CK14/1000 -> 147.69872 | CL49: =+CL39*10^7/CL14/1000 -> 169.5737 | ... DB49: =+DB39*10^7/DB14/1000 -> 471.19846
A50: Subsidiary GP per kg | V50: =+V40*10^7/V14/1000 -> 66.941161 | W50: =+W40*10^7/W14/1000 -> 147.20856 | X50: =+X40*10^7/X14/1000 -> 182.58503 | Y50: =+Y40*10^7/Y14/1000 -> 122.58307 | Z50: =+Z40*10^7/Z14/1000 -> 78.062847 | AA50: =+AA40*10^7/AA14/1000 -> 0.62402683 | AB50: =+AB40*10^7/AB14/1000 -> 0 | AC50: =+AC40*10^7/AC14/1000 -> 0 | ... AE50: =+AE40*10^7/AE14/1000 -> 0 | CE50: =+CE40*10^7/CE14/1000 -> 48.561537 | CF50: =+CF40*10^7/CF14/1000 -> 116.557 | CG50: =+CG40*10^7/CG14/1000 -> 0.32307692 | CH50: =+CH40*10^7/CH14/1000 -> 66.816438 | CI50: =+CI40*10^7/CI14/1000 -> 12.16461 | CJ50: =+CJ40*10^7/CJ14/1000 -> 138.96531 | CK50: =+CK40*10^7/CK14/1000 -> 71.157998 | CL50: =+CL40*10^7/CL14/1000 -> 10.939908 | ... DB50: =+DB40*10^7/DB14/1000 -> 0
A51: Subsidiary EBIDTA per kg | V51: =+V41*10^7/V14/1000 -> 40.412225 | W51: =+W41*10^7/W14/1000 -> 105.83221 | X51: =+X41*10^7/X14/1000 -> 131.38164 | Y51: =+Y41*10^7/Y14/1000 -> 60.660484 | Z51: =+Z41*10^7/Z14/1000 -> 9.1099825 | AA51: =+AA41*10^7/AA14/1000 -> 0.0013175231 | AB51: =+AB41*10^7/AB14/1000 -> 52.677778 | AC51: =+AC41*10^7/AC14/1000 -> 85.590879 | ... AE51: =+AE41*10^7/AE14/1000 -> 103.66366 | CE51: =+CE41*10^7/CE14/1000 -> 16.113469 | CF51: =+CF41*10^7/CF14/1000 -> 21.866871 | CG51: =+CG41*10^7/CG14/1000 -> -91.630769 | CH51: =+CH41*10^7/CH14/1000 -> 8.8383562 | CI51: =+CI41*10^7/CI14/1000 -> -2.7721381 | CJ51: =+CJ41*10^7/CJ14/1000 -> 59.671333 | CK51: =+CK41*10^7/CK14/1000 -> 9.6908734 | CL51: =+CL41*10^7/CL14/1000 -> 41.956857 | ... DB51: =+DB41*10^7/DB14/1000 -> 103.66366
A55: Presentation Data (End)
A56: Profit & Loss- Annual (Start)
A57: Gross Revenue | B57: ='Annual Raw'!C6 -> 29.322553 | C57: ='Annual Raw'!D6 -> 41.153086 | D57: ='Annual Raw'!E6 -> 50.679308 | E57: ='Annual Raw'!F6 -> 81.990468 | F57: ='Annual Raw'!G6 -> 99.190306 | G57: ='Annual Raw'!H6 -> 145.89401 | H57: ='Annual Raw'!I6 -> 197.29384 | I57: ='Annual Raw'!J6 -> 239.67648 | ... AA57: ='Annual Raw'!AB6 -> 1294.111 | AB57: =+SUM(CM57:CP57) -> 1938.8986 | AC57: =+SUM(CQ57:CT57) -> 2932.1458 | AD57: =+SUM(CU57:CX57) -> 4053.6394 | AE57: =+SUM(CY57:DB57) -> 5648.3674 | AI57: ='QTR Raw'!C6+'QTR Raw'!C8 -> 136.559 | AJ57: ='QTR Raw'!D6+'QTR Raw'!D8 -> 126.011 | AK57: ='QTR Raw'!E6+'QTR Raw'!E8 -> 107.746 | AL57: ='QTR Raw'!F6+'QTR Raw'!F8 -> 141.48 | AM57: ='QTR Raw'!G6+'QTR Raw'!G8 -> 140.1 | AN57: ='QTR Raw'!H6+'QTR Raw'!H8 -> 161.014 | AO57: ='QTR Raw'!I6+'QTR Raw'!I8 -> 137.51 | AP57: ='QTR Raw'!J6+'QTR Raw'!J8 -> 171.5 | ... CL57: ='QTR Raw'!BF6+'QTR Raw'!BF8 -> 394.786 | CM57: =CM12*CM21/10^7 -> 458.79084 | CN57: =CN12*CN21/10^7 -> 472.72997 | CO57: =CO12*CO21/10^7 -> 458.72869 | CP57: =CP12*CP21/10^7 -> 548.64913 | CQ57: =CQ12*CQ21/10^7 -> 693.70015 | CR57: =CR12*CR21/10^7 -> 715.53341 | CS57: =CS12*CS21/10^7 -> 691.12474 | CT57: =CT12*CT21/10^7 -> 831.78754 | ... DB57: =DB12*DB21/10^7 -> 1605.9247 | DF57: 440.77366
A58: Less: Exise Duty | B58: ='Annual Raw'!C7+'Annual Raw'!C8+'Annual Raw'!C9 -> 3.1924889 | C58: ='Annual Raw'!D7+'Annual Raw'!D8+'Annual Raw'!D9 -> 4.57874 | D58: ='Annual Raw'!E7+'Annual Raw'!E8+'Annual Raw'!E9 -> 5.5724934 | E58: ='Annual Raw'!F7+'Annual Raw'!F8+'Annual Raw'!F9 -> 11.084474 | F58: ='Annual Raw'!G7+'Annual Raw'!G8+'Annual Raw'!G9 -> 11.463434 | G58: ='Annual Raw'!H7+'Annual Raw'!H8+'Annual Raw'!H9 -> 17.280035 | H58: ='Annual Raw'!I7+'Annual Raw'!I8+'Annual Raw'!I9 -> 21.788731 | I58: ='Annual Raw'!J7+'Annual Raw'!J8+'Annual Raw'!J9 -> 21.856958 | ... AA58: ='Annual Raw'!AB7+'Annual Raw'!AB8+'Annual Raw'!AB9 -> 2.5663 | AB58: =+SUM(CM58:CP58) -> 0 | AC58: =+SUM(CQ58:CT58) -> 0 | AD58: =+SUM(CU58:CX58) -> 0 | AE58: =+SUM(CY58:DB58) -> 0 | AI58: =+'QTR Raw'!C20+'QTR Raw'!C19+'QTR Raw'!C13+'QTR Raw'!C7 -> 0 | AJ58: =+'QTR Raw'!D20+'QTR Raw'!D19+'QTR Raw'!D13+'QTR Raw'!D7 -> 0 | AK58: =+'QTR Raw'!E20+'QTR Raw'!E19+'QTR Raw'!E13+'QTR Raw'!E7 -> 0 | AL58: =+'QTR Raw'!F20+'QTR Raw'!F19+'QTR Raw'!F13+'QTR Raw'!F7 -> 0 | AM58: =+'QTR Raw'!G20+'QTR Raw'!G19+'QTR Raw'!G13+'QTR Raw'!G7 -> 0 | AN58: =+'QTR Raw'!H20+'QTR Raw'!H19+'QTR Raw'!H13+'QTR Raw'!H7 -> 0 | AO58: =+'QTR Raw'!I20+'QTR Raw'!I19+'QTR Raw'!I13+'QTR Raw'!I7 -> 0 | AP58: =+'QTR Raw'!J20+'QTR Raw'!J19+'QTR Raw'!J13+'QTR Raw'!J7 -> 0 | ... CL58: =+'QTR Raw'!BF20+'QTR Raw'!BF19+'QTR Raw'!BF13+'QTR Raw'!BF7 -> 0 | DF58: 0
A59: Net Revenue | B59: =+B57-B58 -> 26.130064 | C59: =+C57-C58 -> 36.574346 | D59: =+D57-D58 -> 45.106815 | E59: =+E57-E58 -> 70.905994 | F59: =+F57-F58 -> 87.726873 | G59: =+G57-G58 -> 128.61398 | H59: =+H57-H58 -> 175.50511 | I59: =+I57-I58 -> 217.81952 | ... AE59: =+AE57-AE58 -> 5648.3674 | AI59: =+AI57-AI58 -> 136.559 | AJ59: =+AJ57-AJ58 -> 126.011 | AK59: =+AK57-AK58 -> 107.746 | AL59: =+AL57-AL58 -> 141.48 | AM59: =+AM57-AM58 -> 140.1 | AN59: =+AN57-AN58 -> 161.014 | AO59: =+AO57-AO58 -> 137.51 | AP59: =+AP57-AP58 -> 171.5 | ... DB59: =+DB57-DB58 -> 1605.9247 | DF59: 440.77366
A60: Net Revenue YOY% | C60: =C59/B59-1 -> 0.39970366 | D60: =D59/C59-1 -> 0.23329107 | E60: =E59/D59-1 -> 0.57195746 | F60: =F59/E59-1 -> 0.23722788 | G60: =G59/F59-1 -> 0.46607277 | H60: =H59/G59-1 -> 0.36458816 | I60: =I59/H59-1 -> 0.2411007 | J60: =J59/I59-1 -> 0.15548326 | ... AE60: =AE59/AD59-1 -> 0.39340648 | AM60: =+IF(AI59<0,1-AM59/AI59,AM59/AI59-1) -> 0.025930184 | AN60: =+IF(AJ59<0,1-AN59/AJ59,AN59/AJ59-1) -> 0.27777734 | AO60: =+IF(AK59<0,1-AO59/AK59,AO59/AK59-1) -> 0.27624227 | AP60: =+IF(AL59<0,1-AP59/AL59,AP59/AL59-1) -> 0.21218547 | AQ60: =+IF(AM59<0,1-AQ59/AM59,AQ59/AM59-1) -> 0.17394718 | AR60: =+IF(AN59<0,1-AR59/AN59,AR59/AN59-1) -> -0.065609202 | AS60: =+IF(AO59<0,1-AS59/AO59,AS59/AO59-1) -> 0.030295978 | AT60: =+IF(AP59<0,1-AT59/AP59,AT59/AP59-1) -> -0.1354519 | ... DB60: =+IF(CX59<0,1-DB59/CX59,DB59/CX59-1) -> 0.39494656 | DF60: 0.24961348
A61: Net Revenue QOQ% | AJ61: =+IF(AI59<0,1-AJ59/AI59,AJ59/AI59-1) -> -0.077241339 | AK61: =+IF(AJ59<0,1-AK59/AJ59,AK59/AJ59-1) -> -0.14494766 | AL61: =+IF(AK59<0,1-AL59/AK59,AL59/AK59-1) -> 0.31308819 | AM61: =+IF(AL59<0,1-AM59/AL59,AM59/AL59-1) -> -0.0097540288 | AN61: =+IF(AM59<0,1-AN59/AM59,AN59/AM59-1) -> 0.14927909 | AO61: =+IF(AN59<0,1-AO59/AN59,AO59/AN59-1) -> -0.14597488 | AP61: =+IF(AO59<0,1-AP59/AO59,AP59/AO59-1) -> 0.24718202 | AQ61: =+IF(AP59<0,1-AQ59/AP59,AQ59/AP59-1) -> -0.040991254 | ... DB61: =+IF(DA59<0,1-DB59/DA59,DB59/DA59-1) -> 0.21005615 | DF61: 0.33043264
A62: Increase/Decrease in Stock | B62: ='Annual Raw'!C11 -> -0.4594177 | C62: ='Annual Raw'!D11 -> 0.6528199 | D62: ='Annual Raw'!E11 -> 0.0706961 | E62: ='Annual Raw'!F11 -> -2.8792667 | F62: ='Annual Raw'!G11 -> -4.1421282 | G62: ='Annual Raw'!H11 -> -0.9728324 | H62: ='Annual Raw'!I11 -> -8.98609 | I62: ='Annual Raw'!J11 -> 9.3914083 | ... AA62: ='Annual Raw'!AB11 -> -16.7342 | AB62: =+SUM(CM62:CP62) -> 0 | AC62: =+SUM(CQ62:CT62) -> 0 | AD62: =+SUM(CU62:CX62) -> 0 | AE62: =+SUM(CY62:DB62) -> 0 | AI62: ='QTR Raw'!C10 -> 9.242 | AJ62: ='QTR Raw'!D10 -> -4.729 | AK62: ='QTR Raw'!E10 -> 5.027 | AL62: ='QTR Raw'!F10 -> 15.49 | AM62: ='QTR Raw'!G10 -> 2.69 | AN62: ='QTR Raw'!H10 -> -15.333 | AO62: ='QTR Raw'!I10 -> -14.51 | AP62: ='QTR Raw'!J10 -> 4.7 | ... CL62: ='QTR Raw'!BF10 -> -10.213 | DF62: -15.159
A63: Purchase of Finished Goods | B63: 0 | C63: 0 | D63: 0 | E63: 0 | F63: 0 | G63: 0 | H63: 0 | I63: 0 | J63: 0 | K63: 0 | L63: 0 | M63: 0 | N63: 0 | O63: 0 | P63: 0 | Q63: 0 | R63: 0 | S63: 0 | T63: 0 | U63: 0 | V63: 0 | W63: 0 | X63: 0 | Y63: 0 | Z63: 0 | AA63: 0 | AB63: =+SUM(CM63:CP63) -> 0 | AC63: =+SUM(CQ63:CT63) -> 0 | AD63: =+SUM(CU63:CX63) -> 0 | AE63: =+SUM(CY63:DB63) -> 0 | AI63: ='QTR Raw'!C12 -> 0 | AJ63: ='QTR Raw'!D12 -> 0 | AK63: ='QTR Raw'!E12 -> 0 | AL63: ='QTR Raw'!F12 -> 0 | AM63: ='QTR Raw'!G12 -> 0 | AN63: ='QTR Raw'!H12 -> 0 | AO63: ='QTR Raw'!I12 -> 0 | AP63: ='QTR Raw'!J12 -> 0 | ... CL63: ='QTR Raw'!BF12 -> 0 | DF63: 0
A64: Raw Material Consumed | B64: ='Annual Raw'!C12 -> 13.941152 | C64: ='Annual Raw'!D12 -> 16.707095 | D64: ='Annual Raw'!E12 -> 22.226833 | E64: ='Annual Raw'!F12 -> 42.588878 | F64: ='Annual Raw'!G12 -> 56.728602 | G64: ='Annual Raw'!H12 -> 77.304028 | H64: ='Annual Raw'!I12 -> 113.90762 | I64: ='Annual Raw'!J12 -> 125.69363 | ... AA64: ='Annual Raw'!AB12 -> 726.5579 | AB64: =+SUM(CM64:CP64) -> 1071.3174 | AC64: =+SUM(CQ64:CT64) -> 1607.549 | AD64: =+SUM(CU64:CX64) -> 2225.7315 | AE64: =+SUM(CY64:DB64) -> 3101.972 | AI64: ='QTR Raw'!C11 -> 74.989 | AJ64: ='QTR Raw'!D11 -> 78.647 | AK64: ='QTR Raw'!E11 -> 60.731 | AL64: ='QTR Raw'!F11 -> 72.8 | AM64: ='QTR Raw'!G11 -> 87.46 | AN64: ='QTR Raw'!H11 -> 111.359 | AO64: ='QTR Raw'!I11 -> 100.15 | AP64: ='QTR Raw'!J11 -> 104.45 | ... CL64: ='QTR Raw'!BF11 -> 231.249 | CM64: =+CM59-CM65 -> 252.28365 | CN64: =+CN59-CN65 -> 260.92538 | CO64: =+CO59-CO65 -> 254.18036 | CP64: =+CP59-CP65 -> 303.92803 | CQ64: =+CQ59-CQ65 -> 376.31445 | CR64: =+CR59-CR65 -> 393.98754 | CS64: =+CS59-CS65 -> 380.31719 | CT64: =+CT59-CT65 -> 456.92986 | ... DB64: =+DB59-DB65 -> 881.92191 | DF64: 243.64209
A65: Gross Profit | B65: =B59-B62-B64-B63 -> 12.64833 | C65: =C59-C62-C64-C63 -> 19.214432 | D65: =D59-D62-D64-D63 -> 22.809286 | E65: =E59-E62-E64-E63 -> 31.196383 | F65: =F59-F62-F64-F63 -> 35.140399 | G65: =G59-G62-G64-G63 -> 52.282784 | H65: =H59-H62-H64-H63 -> 70.583584 | I65: =I59-I62-I64-I63 -> 82.734483 | ... AE65: =AE59-AE62-AE64-AE63 -> 2546.3955 | AI65: =AI59-AI62-AI64-AI63 -> 52.328 | AJ65: =AJ59-AJ62-AJ64-AJ63 -> 52.093 | AK65: =AK59-AK62-AK64-AK63 -> 41.988 | AL65: =AL59-AL62-AL64-AL63 -> 53.19 | AM65: =AM59-AM62-AM64-AM63 -> 49.95 | AN65: =AN59-AN62-AN64-AN63 -> 64.988 | AO65: =AO59-AO62-AO64-AO63 -> 51.87 | AP65: =AP59-AP62-AP64-AP63 -> 62.35 | ... CL65: =CL59-CL62-CL64-CL63 -> 173.75 | CM65: =+CM66*CM59 -> 206.5072 | CN65: =+CN66*CN59 -> 211.80459 | CO65: =+CO66*CO59 -> 204.54834 | CP65: =+CP66*CP59 -> 244.7211 | CQ65: =+CQ66*CQ59 -> 317.3857 | CR65: =+CR66*CR59 -> 321.54587 | CS65: =+CS66*CS59 -> 310.80755 | CT65: =+CT66*CT59 -> 374.85768 | ... DB65: =+DB66*DB59 -> 724.00281 | DF65: 197.13157
A66: GP% | B66: =B65/B59 -> 0.48405277 | C66: =C65/C59 -> 0.5253527 | D66: =D65/D59 -> 0.50567272 | E66: =E65/E59 -> 0.43996821 | F66: =F65/F59 -> 0.40056596 | G66: =G65/G59 -> 0.40650934 | H66: =H65/H59 -> 0.40217395 | I66: =I65/I59 -> 0.37983044 | ... AE66: =AE65/AE59 -> 0.45081972 | AI66: =AI65/AI59 -> 0.38318968 | AJ66: =AJ65/AJ59 -> 0.41340042 | AK66: =AK65/AK59 -> 0.38969428 | AL66: =AL65/AL59 -> 0.3759542 | AM66: =AM65/AM59 -> 0.35653105 | AN66: =AN65/AN59 -> 0.40361708 | AO66: =AO65/AO59 -> 0.37720893 | AP66: =AP65/AP59 -> 0.36355685 | ... CL66: =CL65/CL59 -> 0.44011186 | CM66: =CL66+1% -> 0.45011186 | CN66: =AVERAGE(CJ66:CM66) -> 0.44804561 | CO66: =AVERAGE(CK66:CN66) -> 0.44590264 | CP66: =AVERAGE(CL66:CO66) -> 0.44604299 | CQ66: =AVERAGE(CM66:CP66)+1% -> 0.45752578 | CR66: =AVERAGE(CN66:CQ66) -> 0.44937926 | CS66: =AVERAGE(CO66:CR66) -> 0.44971267 | CT66: =AVERAGE(CP66:CS66) -> 0.45066517 | CU66: =AVERAGE(CQ66:CT66) -> 0.45182072 | CV66: =AVERAGE(CR66:CU66) -> 0.45039445 | CW66: =AVERAGE(CS66:CV66) -> 0.45064825 | CX66: =AVERAGE(CT66:CW66) -> 0.45088215 | CY66: =AVERAGE(CU66:CX66) -> 0.45093639 | ... DB66: =AVERAGE(CX66:DA66) -> 0.45083235 | DF66: 0.4472399
A67: GP YOY% | C67: =+IF(B65<0,1-C65/B65,C65/B65-1) -> 0.51912798 | D67: =+IF(C65<0,1-D65/C65,D65/C65-1) -> 0.18709135 | E67: =+IF(D65<0,1-E65/D65,E65/D65-1) -> 0.36770539 | F67: =+IF(E65<0,1-F65/E65,F65/E65-1) -> 0.12642541 | G67: =+IF(F65<0,1-G65/F65,G65/F65-1) -> 0.48782557 | H67: =+IF(G65<0,1-H65/G65,H65/G65-1) -> 0.35003493 | I67: =+IF(H65<0,1-I65/H65,I65/H65-1) -> 0.17214908 | J67: =+IF(I65<0,1-J65/I65,J65/I65-1) -> 0.15930563 | ... AE67: =+IF(AD65<0,1-AE65/AD65,AE65/AD65-1) -> 0.39306551 | AM67: =+IF(AI65<0,1-AM65/AI65,AM65/AI65-1) -> -0.045444122 | AN67: =+IF(AJ65<0,1-AN65/AJ65,AN65/AJ65-1) -> 0.24753806 | AO67: =+IF(AK65<0,1-AO65/AK65,AO65/AK65-1) -> 0.23535296 | AP67: =+IF(AL65<0,1-AP65/AL65,AP65/AL65-1) -> 0.17221282 | AQ67: =+IF(AM65<0,1-AQ65/AM65,AQ65/AM65-1) -> 0.26666667 | AR67: =+IF(AN65<0,1-AR65/AN65,AR65/AN65-1) -> 0.0021850188 | AS67: =+IF(AO65<0,1-AS65/AO65,AS65/AO65-1) -> 0.10239059 | AT67: =+IF(AP65<0,1-AT65/AP65,AT65/AP65-1) -> 0.099743384 | ... CL67: =+IF(CH65<0,1-CL65/CH65,CL65/CH65-1) -> 0.12296735 | CM67: =+CM65/CI65-1 -> 0.41125272 | CN67: =+CN65/CJ65-1 -> 0.36206986 | CO67: =+CO65/CK65-1 -> 0.38637362 | CP67: =+CP65/CL65-1 -> 0.40846675 | CQ67: =+CQ65/CM65-1 -> 0.53692318 | CR67: =+CR65/CN65-1 -> 0.51812515 | CS67: =+CS65/CO65-1 -> 0.51948216 | CT67: =+CT65/CP65-1 -> 0.53177506 | ... DB67: =+DB65/CX65-1 -> 0.39479247 | DF67: 0.27408528
A68: GP QOQ% | AJ68: =+IF(AI65<0,1-AJ65/AI65,AJ65/AI65-1) -> -0.0044909035 | AK68: =+IF(AJ65<0,1-AK65/AJ65,AK65/AJ65-1) -> -0.19398 | AL68: =+IF(AK65<0,1-AL65/AK65,AL65/AK65-1) -> 0.26679051 | AM68: =+IF(AL65<0,1-AM65/AL65,AM65/AL65-1) -> -0.060913706 | AN68: =+IF(AM65<0,1-AN65/AM65,AN65/AM65-1) -> 0.30106106 | AO68: =+IF(AN65<0,1-AO65/AN65,AO65/AN65-1) -> -0.20185265 | AP68: =+IF(AO65<0,1-AP65/AO65,AP65/AO65-1) -> 0.20204357 | AQ68: =+IF(AP65<0,1-AQ65/AP65,AQ65/AP65-1) -> 0.014755413 | ... CL68: =+IF(CK65<0,1-CL65/CK65,CL65/CK65-1) -> 0.17763078 | CM68: =+CM65/CL65-1 -> 0.18853065 | CN68: =+CN65/CM65-1 -> 0.025652314 | CO68: =+CO65/CN65-1 -> -0.034259174 | CP68: =+CP65/CO65-1 -> 0.1963974 | CQ68: =+CQ65/CP65-1 -> 0.29692824 | CR68: =+CR65/CQ65-1 -> 0.013107613 | CS68: =+CS65/CR65-1 -> -0.033395926 | CT68: =+CT65/CS65-1 -> 0.20607648 | ... DB68: =+DB65/DA65-1 -> 0.21015498 | DF68: 0.33610478
A69: Employee Cost | B69: ='Annual Raw'!C14 -> 0.8771284 | C69: ='Annual Raw'!D14 -> 0.9991958 | D69: ='Annual Raw'!E14 -> 1.1901778 | E69: ='Annual Raw'!F14 -> 1.6467427 | F69: ='Annual Raw'!G14 -> 2.2550053 | G69: ='Annual Raw'!H14 -> 2.9508445 | H69: ='Annual Raw'!I14 -> 3.4899674 | I69: ='Annual Raw'!J14 -> 4.0490099 | ... AA69: ='Annual Raw'!AB14 -> 77.143 | AB69: =+SUM(CM69:CP69) -> 89.9977 | AC69: =+SUM(CQ69:CT69) -> 96.297539 | AD69: =+SUM(CU69:CX69) -> 103.03837 | AE69: =+SUM(CY69:DB69) -> 110.25105 | AI69: ='QTR Raw'!C16 -> 4.582 | AJ69: ='QTR Raw'!D16 -> 4.299 | AK69: ='QTR Raw'!E16 -> 4.581 | AL69: ='QTR Raw'!F16 -> 4.54 | AM69: ='QTR Raw'!G16 -> 4.52 | AN69: ='QTR Raw'!H16 -> 4.698 | AO69: ='QTR Raw'!I16 -> 5.29 | AP69: ='QTR Raw'!J16 -> 6.27 | ... CL69: ='QTR Raw'!BF16 -> 26.041 | CM69: =CI69*107% -> 21.91146 | CN69: =CJ69*107% -> 20.75693 | CO69: =CK69*107% -> 19.46544 | CP69: =CL69*107% -> 27.86387 | CQ69: =CM69*107% -> 23.445262 | CR69: =CN69*107% -> 22.209915 | CS69: =CO69*107% -> 20.828021 | CT69: =CP69*107% -> 29.814341 | ... DB69: =CX69*107% -> 34.134439 | DF69: 24.48374
A70: General and Administration Expenses | B70: ='Annual Raw'!C17 -> 1.1723648 | C70: ='Annual Raw'!D17 -> 1.5864259 | D70: ='Annual Raw'!E17 -> 2.0068645 | E70: ='Annual Raw'!F17 -> 1.1453089 | F70: ='Annual Raw'!G17 -> 1.5265568 | G70: ='Annual Raw'!H17 -> 2.3651086 | H70: ='Annual Raw'!I17 -> 2.8069501 | I70: ='Annual Raw'!J17 -> 3.0533717 | ... AA70: ='Annual Raw'!AB17 -> 16.9796 | AB70: =+SUM(CM70:CP70) -> 0 | AC70: =+SUM(CQ70:CT70) -> 0 | AD70: =+SUM(CU70:CX70) -> 0 | AE70: =+SUM(CY70:DB70) -> 0 | AI70: ='QTR Raw'!C17 -> 0 | AJ70: ='QTR Raw'!D17 -> 0 | AK70: ='QTR Raw'!E17 -> 0 | AL70: ='QTR Raw'!F17 -> 0 | AM70: ='QTR Raw'!G17 -> 0 | AN70: ='QTR Raw'!H17 -> 0 | AO70: ='QTR Raw'!I17 -> 0 | AP70: ='QTR Raw'!J17 -> 0 | ... CL70: ='QTR Raw'!BF17 -> 0 | DF70: 0
A71: Miscellaneous Expenses | B71: ='Annual Raw'!C19-'Annual Raw'!C20 -> 0.0366861 | C71: ='Annual Raw'!D19-'Annual Raw'!D20 -> 0.2568025 | D71: ='Annual Raw'!E19-'Annual Raw'!E20 -> 0 | E71: ='Annual Raw'!F19-'Annual Raw'!F20 -> 0.038689 | F71: ='Annual Raw'!G19-'Annual Raw'!G20 -> 0.01 | G71: ='Annual Raw'!H19-'Annual Raw'!H20 -> 0.4127311 | H71: ='Annual Raw'!I19-'Annual Raw'!I20 -> 0.2307388 | I71: ='Annual Raw'!J19-'Annual Raw'!J20 -> 0.2307388 | ... AA71: ='Annual Raw'!AB19-'Annual Raw'!AB20 -> 9.5472 | AB71: =+SUM(CM71:CP71) -> 0 | AC71: =+SUM(CQ71:CT71) -> 0 | AD71: =+SUM(CU71:CX71) -> 0 | AE71: =+SUM(CY71:DB71) -> 0 | AI71: =+'QTR Raw'!C21 -> 0 | AJ71: =+'QTR Raw'!D21 -> 0 | AK71: =+'QTR Raw'!E21 -> 0 | AL71: =+'QTR Raw'!F21 -> 0 | AM71: =+'QTR Raw'!G21 -> 0 | AN71: =+'QTR Raw'!H21 -> 0 | AO71: =+'QTR Raw'!I21 -> 0 | AP71: =+'QTR Raw'!J21 -> 0 | ... CL71: =+'QTR Raw'!BF21 -> 0 | DF71: 0
A72: Other Manufacturing Expenses | B72: ='Annual Raw'!C15+'Annual Raw'!C16 -> 1.6168982 | C72: ='Annual Raw'!D15+'Annual Raw'!D16 -> 2.4421327 | D72: ='Annual Raw'!E15+'Annual Raw'!E16 -> 3.6772316 | E72: ='Annual Raw'!F15+'Annual Raw'!F16 -> 4.4617804 | F72: ='Annual Raw'!G15+'Annual Raw'!G16 -> 6.3403451 | G72: ='Annual Raw'!H15+'Annual Raw'!H16 -> 9.6007268 | H72: ='Annual Raw'!I15+'Annual Raw'!I16 -> 13.704348 | I72: ='Annual Raw'!J15+'Annual Raw'!J16 -> 16.88892 | ... AA72: ='Annual Raw'!AB15+'Annual Raw'!AB16 -> 65.0932 | AB72: =+SUM(CM72:CP72) -> 371.63815 | AC72: =+SUM(CQ72:CT72) -> 598.53225 | AD72: =+SUM(CU72:CX72) -> 856.36302 | AE72: =+SUM(CY72:DB72) -> 1226.2313 | AI72: ='QTR Raw'!C14 -> 24.746 | AJ72: ='QTR Raw'!D14 -> 24.727 | AK72: ='QTR Raw'!E14 -> 20.889 | AL72: ='QTR Raw'!F14 -> 31.01 | AM72: ='QTR Raw'!G14 -> 22.73 | AN72: ='QTR Raw'!H14 -> 32.531 | AO72: ='QTR Raw'!I14 -> 27.14 | AP72: ='QTR Raw'!J14 -> 34.95 | ... CL72: ='QTR Raw'!BF14 -> 53.46 | CM72: =CM75-CM69-CM70-CM71-CM73-CM74 -> 89.614531 | CN72: =CN75-CN69-CN70-CN71-CN73-CN74 -> 92.664769 | CO72: =CO75-CO69-CO70-CO71-CO73-CO74 -> 90.476533 | CP72: =CP75-CP69-CP70-CP71-CP73-CP74 -> 98.882314 | CQ72: =CQ75-CQ69-CQ70-CQ71-CQ73-CQ74 -> 141.94978 | CR72: =CR75-CR69-CR70-CR71-CR73-CR74 -> 147.55669 | CS72: =CS75-CS69-CS70-CS71-CS73-CS74 -> 142.68602 | CT72: =CT75-CT69-CT70-CT71-CT73-CT74 -> 166.33976 | ... DB72: =DB75-DB69-DB70-DB71-DB73-DB74 -> 345.81837 | DF72: 94.577156
A73: Power & Fuel Cost | B73: ='Annual Raw'!C13 -> 3.7361172 | C73: ='Annual Raw'!D13 -> 3.9301357 | D73: ='Annual Raw'!E13 -> 4.7636879 | E73: ='Annual Raw'!F13 -> 7.1645533 | F73: ='Annual Raw'!G13 -> 9.0957375 | G73: ='Annual Raw'!H13 -> 11.449297 | H73: ='Annual Raw'!I13 -> 15.132046 | I73: ='Annual Raw'!J13 -> 17.365087 | ... AA73: ='Annual Raw'!AB13 -> 118.685 | AB73: =+SUM(CM73:CP73) -> 0 | AC73: =+SUM(CQ73:CT73) -> 0 | AD73: =+SUM(CU73:CX73) -> 0 | AE73: =+SUM(CY73:DB73) -> 0 | AI73: ='QTR Raw'!C15 -> 0 | AJ73: ='QTR Raw'!D15 -> 0 | AK73: ='QTR Raw'!E15 -> 0 | AL73: ='QTR Raw'!F15 -> 0 | AM73: ='QTR Raw'!G15 -> 0 | AN73: ='QTR Raw'!H15 -> 0 | AO73: ='QTR Raw'!I15 -> 0 | AP73: ='QTR Raw'!J15 -> 0 | ... CL73: ='QTR Raw'!BF15 -> 0 | DF73: 0
A74: Selling and Distribution Expenses | B74: ='Annual Raw'!C18 -> 0.8893245 | C74: ='Annual Raw'!D18 -> 1.1137668 | D74: ='Annual Raw'!E18 -> 1.8791209 | E74: ='Annual Raw'!F18 -> 2.3340399 | F74: ='Annual Raw'!G18 -> 3.2671532 | G74: ='Annual Raw'!H18 -> 6.7559615 | H74: ='Annual Raw'!I18 -> 10.250914 | I74: ='Annual Raw'!J18 -> 11.569645 | ... AA74: ='Annual Raw'!AB18 -> 47.0119 | AB74: =+SUM(CM74:CP74) -> 0 | AC74: =+SUM(CQ74:CT74) -> 0 | AD74: =+SUM(CU74:CX74) -> 0 | AE74: =+SUM(CY74:DB74) -> 0 | AI74: ='QTR Raw'!C18 -> 0 | AJ74: ='QTR Raw'!D18 -> 0 | AK74: ='QTR Raw'!E18 -> 0 | AL74: ='QTR Raw'!F18 -> 0 | AM74: ='QTR Raw'!G18 -> 0 | AN74: ='QTR Raw'!H18 -> 0 | AO74: ='QTR Raw'!I18 -> 0 | AP74: ='QTR Raw'!J18 -> 0 | ... CL74: ='QTR Raw'!BF18 -> 0 | DF74: 0
A75: Total Cost | B75: =+SUM(B69:B74) -> 8.3285192 | C75: =+SUM(C69:C74) -> 10.328459 | D75: =+SUM(D69:D74) -> 13.517083 | E75: =+SUM(E69:E74) -> 16.791114 | F75: =+SUM(F69:F74) -> 22.494798 | G75: =+SUM(G69:G74) -> 33.53467 | H75: =+SUM(H69:H74) -> 45.614964 | I75: =+SUM(I69:I74) -> 53.156772 | ... AE75: =+SUM(AE69:AE74) -> 1336.4824 | AI75: =+SUM(AI69:AI74) -> 29.328 | AJ75: =+SUM(AJ69:AJ74) -> 29.026 | AK75: =+SUM(AK69:AK74) -> 25.47 | AL75: =+SUM(AL69:AL74) -> 35.55 | AM75: =+SUM(AM69:AM74) -> 27.25 | AN75: =+SUM(AN69:AN74) -> 37.229 | AO75: =+SUM(AO69:AO74) -> 32.43 | AP75: =+SUM(AP69:AP74) -> 41.22 | ... CL75: =+SUM(CL69:CL74) -> 79.501 | CM75: =CM76*CM59 -> 111.52599 | CN75: =CN76*CN59 -> 113.4217 | CO75: =CO76*CO59 -> 109.94197 | CP75: =CP76*CP59 -> 126.74618 | CQ75: =CQ76*CQ59 -> 165.39504 | CR75: =CR76*CR59 -> 169.7666 | CS75: =CS76*CS59 -> 163.51404 | CT75: =CT76*CT59 -> 196.1541 | ... DB75: =DB76*DB59 -> 379.95281 | DF75: 119.0609
A76: Cost % | B76: =B75/B59 -> 0.31873321 | C76: =C75/C59 -> 0.28239628 | D76: =D75/D59 -> 0.2996683 | E76: =E75/E59 -> 0.23680811 | F76: =F75/F59 -> 0.25641855 | G76: =G75/G59 -> 0.26073892 | H76: =H75/H59 -> 0.25990675 | I76: =I75/I59 -> 0.24404045 | ... AE76: =AE75/AE59 -> 0.23661393 | AI76: =AI75/AI59 -> 0.21476431 | AJ76: =AJ75/AJ59 -> 0.23034497 | AK76: =AK75/AK59 -> 0.23638929 | AL76: =AL75/AL59 -> 0.25127226 | AM76: =AM75/AM59 -> 0.19450393 | AN76: =AN75/AN59 -> 0.23121592 | AO76: =AO75/AO59 -> 0.23583739 | AP76: =AP75/AP59 -> 0.24034985 | ... CL76: =CL75/CL59 -> 0.20137746 | CM76: =AVERAGE(CI76:CL76)-1% -> 0.24308678 | CN76: =AVERAGE(CJ76:CM76)-1% -> 0.23992915 | CO76: =AVERAGE(CK76:CN76) -> 0.23966666 | CP76: =AVERAGE(CL76:CO76) -> 0.23101501 | CQ76: =AVERAGE(CM76:CP76) -> 0.2384244 | CR76: =AVERAGE(CN76:CQ76) -> 0.23725881 | CS76: =AVERAGE(CO76:CR76) -> 0.23659122 | CT76: =AVERAGE(CP76:CS76) -> 0.23582236 | CU76: =AVERAGE(CQ76:CT76) -> 0.2370242 | CV76: =AVERAGE(CR76:CU76) -> 0.23667414 | ... DB76: =AVERAGE(CX76:DA76) -> 0.23659441 | DF76: 0.27011799
A77: EBITDA | B77: =B65-B75 -> 4.3198107 | C77: =C65-C75 -> 8.8859724 | D77: =D65-D75 -> 9.2922031 | E77: =E65-E75 -> 14.405269 | F77: =F65-F75 -> 12.645601 | G77: =G65-G75 -> 18.748114 | H77: =H65-H75 -> 24.96862 | I77: =I65-I75 -> 29.577711 | ... AE77: =AE65-AE75 -> 1209.9131 | AI77: =AI65-AI75 -> 23 | AJ77: =AJ65-AJ75 -> 23.067 | AK77: =AK65-AK75 -> 16.518 | AL77: =AL65-AL75 -> 17.64 | AM77: =AM65-AM75 -> 22.7 | AN77: =AN65-AN75 -> 27.759 | AO77: =AO65-AO75 -> 19.44 | AP77: =AP65-AP75 -> 21.13 | ... DB77: =DB65-DB75 -> 344.04999 | DF77: 78.070675
A78: EBITDA Margins | B78: =B77/B59 -> 0.16531956 | C78: =C77/C59 -> 0.24295642 | D78: =D77/D59 -> 0.20600442 | E78: =E77/E59 -> 0.2031601 | F78: =F77/F59 -> 0.1441474 | G78: =G77/G59 -> 0.14577042 | H78: =H77/H59 -> 0.14226719 | I78: =I77/I59 -> 0.13578999 | ... AE78: =AE77/AE59 -> 0.2142058 | AI78: =AI77/AI59 -> 0.16842537 | AJ78: =AJ77/AJ59 -> 0.18305545 | AK78: =AK77/AK59 -> 0.153305 | AL78: =AL77/AL59 -> 0.12468193 | AM78: =AM77/AM59 -> 0.16202712 | AN78: =AN77/AN59 -> 0.17240116 | AO78: =AO77/AO59 -> 0.14137154 | AP78: =AP77/AP59 -> 0.123207 | ... DB78: =DB77/DB59 -> 0.21423793 | DF78: 0.17712191
A79: EBITDA YOY% | C79: =+IF(B77<0,1-C77/B77,C77/B77-1) -> 1.0570282 | D79: =+IF(C77<0,1-D77/C77,D77/C77-1) -> 0.045715953 | E79: =+IF(D77<0,1-E77/D77,E77/D77-1) -> 0.55025334 | F79: =+IF(E77<0,1-F77/E77,F77/E77-1) -> -0.12215448 | G79: =+IF(F77<0,1-G77/F77,G77/F77-1) -> 0.48257995 | H79: =+IF(G77<0,1-H77/G77,H77/G77-1) -> 0.3317937 | I79: =+IF(H77<0,1-I77/H77,I77/H77-1) -> 0.18459534 | J79: =+IF(I77<0,1-J77/I77,J77/I77-1) -> 0.24466305 | ... AE79: =+IF(AD77<0,1-AE77/AD77,AE77/AD77-1) -> 0.39309614 | AM79: =+IF(AI77<0,1-AM77/AI77,AM77/AI77-1) -> -0.013043478 | AN79: =+IF(AJ77<0,1-AN77/AJ77,AN77/AJ77-1) -> 0.20340747 | AO79: =+IF(AK77<0,1-AO77/AK77,AO77/AK77-1) -> 0.17689793 | AP79: =+IF(AL77<0,1-AP77/AL77,AP77/AL77-1) -> 0.1978458 | AQ79: =+IF(AM77<0,1-AQ77/AM77,AQ77/AM77-1) -> 0.099559471 | AR79: =+IF(AN77<0,1-AR77/AN77,AR77/AN77-1) -> -0.030440578 | AS79: =+IF(AO77<0,1-AS77/AO77,AS77/AO77-1) -> 0.11028807 | AT79: =+IF(AP77<0,1-AT77/AP77,AT77/AP77-1) -> 0.36781827 | ... CL79: =+IF(CH77<0,1-CL77/CH77,CL77/CH77-1) -> 0.57968925 | CM79: =+CM77/CI77-1 -> 0.73656109 | CN79: =+CN77/CJ77-1 -> 0.64481373 | CO79: =+CO77/CK77-1 -> 0.66927859 | CP79: =+CP77/CL77-1 -> 0.25173651 | CQ79: =+CQ77/CM77-1 -> 0.60021819 | CR79: =+CR77/CN77-1 -> 0.54274053 | CS79: =+CS77/CO77-1 -> 0.55690906 | CT79: =+CT77/CP77-1 -> 0.51475911 | ... DB79: =+DB77/CX77-1 -> 0.39408731 | DF79: 0.30852747
A80: EBITDA QOQ% | AJ80: =+IF(AI77<0,1-AJ77/AI77,AJ77/AI77-1) -> 0.0029130435 | AK80: =+IF(AJ77<0,1-AK77/AJ77,AK77/AJ77-1) -> -0.28391208 | AL80: =+IF(AK77<0,1-AL77/AK77,AL77/AK77-1) -> 0.067925899 | AM80: =+IF(AL77<0,1-AM77/AL77,AM77/AL77-1) -> 0.28684807 | AN80: =+IF(AM77<0,1-AN77/AM77,AN77/AM77-1) -> 0.22286344 | AO80: =+IF(AN77<0,1-AO77/AN77,AO77/AN77-1) -> -0.29968659 | AP80: =+IF(AO77<0,1-AP77/AO77,AP77/AO77-1) -> 0.086934156 | AQ80: =+IF(AP77<0,1-AQ77/AP77,AQ77/AP77-1) -> 0.18125887 | ... CI80: =+IF(CH77<0,1-CI77/CH77,CI77/CH77-1) -> -0.083267687 | CJ80: =+IF(CI77>1,CJ77/CI77-1,1-CJ77/CI77) -> 0.093591736 | CK80: =+IF(CJ77>1,CK77/CJ77-1,1-CK77/CJ77) -> -0.052479353 | CL80: =+IF(CK77>1,CL77/CK77-1,1-CL77/CK77) -> 0.66297309 | CM80: =+CM77/CL77-1 -> 0.007768876 | CN80: =+CN77/CM77-1 -> 0.03581424 | CO80: =+CO77/CN77-1 -> -0.038385988 | CP80: =+CP77/CO77-1 -> 0.24700822 | CQ80: =+CQ77/CP77-1 -> 0.28833032 | CR80: =+CR77/CQ77-1 -> -0.0013908007 | CS80: =+CS77/CR77-1 -> -0.029554528 | CT80: =+CT77/CS77-1 -> 0.21324817 | ... DB80: =+DB77/DA77-1 -> 0.21018908 | DF80: 0.37751521
A81: Depreciation | B81: ='Annual Raw'!C27 -> 1.1695919 | C81: ='Annual Raw'!D27 -> 1.2016112 | D81: ='Annual Raw'!E27 -> 1.5107849 | E81: ='Annual Raw'!F27 -> 2.3293642 | F81: ='Annual Raw'!G27 -> 2.8293367 | G81: ='Annual Raw'!H27 -> 3.2621327 | H81: ='Annual Raw'!I27 -> 3.7871951 | I81: ='Annual Raw'!J27 -> 4.4501646 | ... AA81: ='Annual Raw'!AB27 -> 45.601 | AB81: =+SUM(CM81:CP81) -> 76.06001 | AC81: =+SUM(CQ81:CT81) -> 115.18117 | AD81: =+SUM(CU81:CX81) -> 125.20687 | AE81: =+SUM(CY81:DB81) -> 123.72815 | AI81: ='QTR Raw'!C28 -> 3.143 | AJ81: ='QTR Raw'!D28 -> 3.164 | AK81: ='QTR Raw'!E28 -> 3.172 | AL81: ='QTR Raw'!F28 -> 3.22 | AM81: ='QTR Raw'!G28 -> 3.77 | AN81: ='QTR Raw'!H28 -> 3.786 | AO81: ='QTR Raw'!I28 -> 4.5 | AP81: ='QTR Raw'!J28 -> 4.41 | ... CL81: ='QTR Raw'!BF28 -> 13.953 | CM81: =CM82*CL183 -> 13.943808 | CN81: =CN82*CM183 -> 16.444142 | CO81: =CO82*CN183 -> 19.608091 | CP81: =CP82*CO183 -> 26.063969 | CQ81: =CQ82*CP183 -> 27.17301 | CR81: =CR82*CQ183 -> 28.265415 | CS81: =CS82*CR183 -> 29.341433 | CT81: =CT82*CS183 -> 30.401312 | ... DB81: =DB82*DA183 -> 30.798241 | DF81: 13.982137
A82: Depreciation % of Net Block | B82: =+B81/B183 -> 0.071344236 | C82: =+C81/C183 -> 0.066470032 | D82: =+D81/D183 -> 0.04824732 | E82: =+E81/E183 -> 0.055829052 | F82: =+F81/F183 -> 0.059883687 | G82: =+G81/G183 -> 0.058772255 | H82: =+H81/H183 -> 0.063208407 | I82: =+I81/I183 -> 0.062568662 | ... AE82: =+AE81/AE183 -> 0.060431315 | AI82: =+AI81/AH183 -> #DIV/0! | AJ82: =+AJ81/AI183 -> #DIV/0! | AK82: =+AK81/AJ183 -> 0.016678322 | AL82: =+AL81/AK183 -> 0.016930705 | AM82: =+AM81/AL183 -> 0.016107669 | AN82: =+AN81/AM183 -> 0.016176031 | AO82: =+AO81/AN183 -> 0.019822129 | AP82: =+AP81/AO183 -> 0.019425687 | ... CL82: =+CL81/CK183 -> 0.013438597 | CM82: =CL82 -> 0.013438597 | CN82: =CM82 -> 0.013438597 | CO82: 0.015 | CP82: =CO82 -> 0.015 | CQ82: =CP82 -> 0.015 | CR82: =CQ82 -> 0.015 | CS82: =CR82 -> 0.015 | CT82: =CS82 -> 0.015 | CU82: =CT82 -> 0.015 | CV82: =CU82 -> 0.015 | CW82: =CV82 -> 0.015 | ... DB82: =DA82 -> 0.015 | DF82: 0.01346666
A83: EBIT | B83: =B77-B81 -> 3.1502188 | C83: =C77-C81 -> 7.6843612 | D83: =D77-D81 -> 7.7814182 | E83: =E77-E81 -> 12.075905 | F83: =F77-F81 -> 9.816264 | G83: =G77-G81 -> 15.485981 | H83: =H77-H81 -> 21.181425 | I83: =I77-I81 -> 25.127546 | ... AE83: =AE77-AE81 -> 1086.1849 | AI83: =AI77-AI81 -> 19.857 | AJ83: =AJ77-AJ81 -> 19.903 | AK83: =AK77-AK81 -> 13.346 | AL83: =AL77-AL81 -> 14.42 | AM83: =AM77-AM81 -> 18.93 | AN83: =AN77-AN81 -> 23.973 | AO83: =AO77-AO81 -> 14.94 | AP83: =AP77-AP81 -> 16.72 | ... DB83: =DB77-DB81 -> 313.25175 | DF83: 64.088538
A84: Other Income | B84: ='Annual Raw'!C23 -> 0.3127948 | C84: ='Annual Raw'!D23 -> 0.1246212 | D84: ='Annual Raw'!E23 -> 0.2072782 | E84: ='Annual Raw'!F23 -> 1.0115367 | F84: ='Annual Raw'!G23 -> 0.1706001 | G84: ='Annual Raw'!H23 -> 0.727185 | H84: ='Annual Raw'!I23 -> 0.8592613 | I84: ='Annual Raw'!J23 -> 1.1790966 | ... AA84: ='Annual Raw'!AB23 -> 28.0217 | AB84: =+SUM(CM84:CP84) -> 0 | AC84: =+SUM(CQ84:CT84) -> 0 | AD84: =+SUM(CU84:CX84) -> 0 | AE84: =+SUM(CY84:DB84) -> 0 | AI84: ='QTR Raw'!C23 -> 1.283 | AJ84: ='QTR Raw'!D23 -> 1.543 | AK84: ='QTR Raw'!E23 -> 0.309 | AL84: ='QTR Raw'!F23 -> 0.58 | AM84: ='QTR Raw'!G23 -> 0.81 | AN84: ='QTR Raw'!H23 -> 0.716 | AO84: ='QTR Raw'!I23 -> 0.54 | AP84: ='QTR Raw'!J23 -> 0.54 | ... CL84: ='QTR Raw'!BF23 -> 7.738 | DF84: 28.807
A85: Interest | B85: ='Annual Raw'!C25 -> 2.2854675 | C85: ='Annual Raw'!D25 -> 2.0872357 | D85: ='Annual Raw'!E25 -> 1.6772028 | E85: ='Annual Raw'!F25 -> 2.371387 | F85: ='Annual Raw'!G25 -> 2.7622551 | G85: ='Annual Raw'!H25 -> 4.4185889 | H85: ='Annual Raw'!I25 -> 6.179869 | I85: ='Annual Raw'!J25 -> 7.9178761 | ... AA85: ='Annual Raw'!AB25 -> 2.2778 | AB85: =+SUM(CM85:CP85) -> -18.982495 | AC85: =+SUM(CQ85:CT85) -> 25.469514 | AD85: =+SUM(CU85:CX85) -> 44.102378 | AE85: =+SUM(CY85:DB85) -> 38.621559 | AI85: ='QTR Raw'!C25 -> 6.547 | AJ85: ='QTR Raw'!D25 -> 6.754 | AK85: ='QTR Raw'!E25 -> 6.136 | AL85: ='QTR Raw'!F25 -> 5.96 | AM85: ='QTR Raw'!G25 -> 7.35 | AN85: ='QTR Raw'!H25 -> 7.129 | AO85: ='QTR Raw'!I25 -> 8.7 | AP85: ='QTR Raw'!J25 -> 8.33 | ... CL85: ='QTR Raw'!BF25 -> 2.176 | CM85: =CM86*CL216 -> -3.5452107 | CN85: =CN86*CM216 -> -8.5319352 | CO85: =CO86*CN216 -> -5.7736806 | CP85: =CP86*CO216 -> -1.1316684 | CQ85: =CQ86*CP216 -> 2.4861356 | CR85: =CR86*CQ216 -> 7.565965 | CS85: =CS86*CR216 -> 8.1930658 | CT85: =CT86*CS216 -> 7.2243477 | ... DB85: =DB86*DA216 -> 4.0456889 | DF85: -4.8861064
A86: Interest % of Debt | B86: =+B85/B177 -> 0.14093859 | C86: =+C85/C177 -> 0.15013792 | D86: =+D85/D177 -> 0.067999074 | E86: =+E85/E177 -> 0.068511527 | F86: =+F85/F177 -> 0.06669018 | G86: =+G85/G177 -> 0.0825271 | H86: =+H85/H177 -> 0.093045594 | I86: =+I85/I177 -> 0.094922064 | ... AE86: =+AE85/AE177 -> 0.079976557 | AI86: =(AI85-AI84)/AH216 -> #DIV/0! | AJ86: =(AJ85-AJ84)/AI216 -> #DIV/0! | AK86: =(AK85-AK84)/AJ216 -> 0.030770124 | AL86: =(AL85-AL84)/AK216 -> 0.034203603 | AM86: =(AM85-AM84)/AL216 -> 0.035031335 | AN86: =(AN85-AN84)/AM216 -> 0.036239575 | AO86: =(AO85-AO84)/AN216 -> 0.045995152 | AP86: =(AP85-AP84)/AO216 -> 0.049798154 | ... CL86: =(CL85-CL84)/CK216 -> 0.025606433 | CM86: =+CL86 -> 0.025606433 | CN86: =+CM86 -> 0.025606433 | CO86: =+CN86 -> 0.025606433 | CP86: =+CO86 -> 0.025606433 | CQ86: =+CP86 -> 0.025606433 | CR86: =+CQ86 -> 0.025606433 | CS86: =+CR86 -> 0.025606433 | CT86: =+CS86 -> 0.025606433 | ... DB86: =+DA86 -> 0.025606433 | DF86: 0.022494742
A87: PBT | B87: =B83+B84-B85 -> 1.1775461 | C87: =C83+C84-C85 -> 5.7217467 | D87: =D83+D84-D85 -> 6.3114936 | E87: =E83+E84-E85 -> 10.716054 | F87: =F83+F84-F85 -> 7.224609 | G87: =G83+G84-G85 -> 11.794577 | H87: =H83+H84-H85 -> 15.860817 | I87: =I83+I84-I85 -> 18.388767 | ... AE87: =AE83+AE84-AE85 -> 1047.5634 | AI87: =AI83+AI84-AI85 -> 14.593 | AJ87: =AJ83+AJ84-AJ85 -> 14.692 | AK87: =AK83+AK84-AK85 -> 7.519 | AL87: =AL83+AL84-AL85 -> 9.04 | AM87: =AM83+AM84-AM85 -> 12.39 | AN87: =AN83+AN84-AN85 -> 17.56 | AO87: =AO83+AO84-AO85 -> 6.78 | AP87: =AP83+AP84-AP85 -> 8.93 | ... DB87: =DB83+DB84-DB85 -> 309.20606 | DF87: 68.974644
A88: Tax | B88: ='Annual Raw'!C30 -> 0.089 | C88: ='Annual Raw'!D30 -> 1.927518 | D88: ='Annual Raw'!E30 -> 2.1946857 | E88: ='Annual Raw'!F30 -> 3.6011334 | F88: ='Annual Raw'!G30 -> 2.6415081 | G88: ='Annual Raw'!H30 -> 3.009608 | H88: ='Annual Raw'!I30 -> 5.8238232 | I88: ='Annual Raw'!J30 -> 5.3985952 | ... AA88: ='Annual Raw'!AB30 -> 61.8757 | AB88: =+SUM(CM88:CP88) -> 87.216965 | AC88: =+SUM(CQ88:CT88) -> 122.27908 | AD88: =+SUM(CU88:CX88) -> 174.79931 | AE88: =+SUM(CY88:DB88) -> 261.89084 | AI88: ='QTR Raw'!C29 -> 5.226 | AJ88: ='QTR Raw'!D29 -> 5.801 | AK88: ='QTR Raw'!E29 -> 0.444 | AL88: ='QTR Raw'!F29 -> 3.34 | AM88: ='QTR Raw'!G29 -> 3.88 | AN88: ='QTR Raw'!H29 -> 5.825 | AO88: ='QTR Raw'!I29 -> 2.58 | AP88: ='QTR Raw'!J29 -> -0.16 | ... CL88: ='QTR Raw'!BF29 -> 21.09 | CM88: =+CM87*CM89 -> 21.145653 | CN88: =+CN87*CN89 -> 22.61767 | CO88: =+CO87*CO89 -> 20.192988 | CP88: =+CP87*CP89 -> 23.260653 | CQ88: =+CQ87*CQ89 -> 30.582878 | CR88: =+CR87*CR89 -> 28.986972 | CS88: =+CS87*CS89 -> 27.439751 | CT88: =+CT87*CT89 -> 35.269479 | ... DB88: =+DB87*DB89 -> 77.301516 | DF88: 19.270013
A89: Tax Rate % | B89: =B88/B87 -> 0.075580905 | C89: =C88/C87 -> 0.3368758 | D89: =D88/D87 -> 0.34772842 | E89: =E88/E87 -> 0.33605031 | F89: =F88/F87 -> 0.36562644 | G89: =G88/G87 -> 0.25516879 | H89: =H88/H87 -> 0.36718305 | I89: =I88/I87 -> 0.29358114 | ... AE89: =AE88/AE87 -> 0.25 | AI89: =AI88/AI87 -> 0.35811691 | AJ89: =AJ88/AJ87 -> 0.39484073 | AK89: =AK88/AK87 -> 0.059050406 | AL89: =AL88/AL87 -> 0.36946903 | AM89: =AM88/AM87 -> 0.31315577 | AN89: =AN88/AN87 -> 0.33171982 | AO89: =AO88/AO87 -> 0.38053097 | AP89: =AP88/AP87 -> -0.017917133 | ... CL89: =CL88/CL87 -> 0.24563815 | CM89: 0.25 | CN89: 0.25 | CO89: 0.25 | CP89: 0.25 | CQ89: 0.25 | CR89: 0.25 | CS89: 0.25 | CT89: 0.25 | CU89: 0.25 | CV89: 0.25 | CW89: 0.25 | CX89: 0.25 | CY89: 0.25 | CZ89: 0.25 | DA89: 0.25 | DB89: 0.25 | DF89: 0.27937822
A90: PAT | B90: =B87-B88 -> 1.0885461 | C90: =C87-C88 -> 3.7942287 | D90: =D87-D88 -> 4.1168079 | E90: =E87-E88 -> 7.114921 | F90: =F87-F88 -> 4.5831009 | G90: =G87-G88 -> 8.7849694 | H90: =H87-H88 -> 10.036994 | I90: =I87-I88 -> 12.990172 | ... AE90: =AE87-AE88 -> 785.67252 | AI90: =AI87-AI88 -> 9.367 | AJ90: =AJ87-AJ88 -> 8.891 | AK90: =AK87-AK88 -> 7.075 | AL90: =AL87-AL88 -> 5.7 | AM90: =AM87-AM88 -> 8.51 | AN90: =AN87-AN88 -> 11.735 | AO90: =AO87-AO88 -> 4.2 | AP90: =AP87-AP88 -> 9.09 | ... DB90: =DB87-DB88 -> 231.90455 | DF90: 49.704631
A91: PAT % | B91: =+B90/B59 -> 0.041658761 | C91: =+C90/C59 -> 0.10374016 | D91: =+D90/D59 -> 0.09126798 | E91: =+E90/E59 -> 0.10034301 | F91: =+F90/F59 -> 0.052242839 | G91: =+G90/G59 -> 0.068304934 | H91: =+H90/H59 -> 0.057189183 | I91: =+I90/I59 -> 0.059637317 | ... AE91: =+AE90/AE59 -> 0.13909727 | AI91: =+AI90/AI59 -> 0.068593062 | AJ91: =+AJ90/AJ59 -> 0.070557332 | AK91: =+AK90/AK59 -> 0.065663691 | AL91: =+AL90/AL59 -> 0.04028838 | AM91: =+AM90/AM59 -> 0.060742327 | AN91: =+AN90/AN59 -> 0.072881861 | AO91: =+AO90/AO59 -> 0.030543233 | AP91: =+AP90/AP59 -> 0.053002915 | ... DB91: =+DB90/DB59 -> 0.14440562 | DF91: 0.11276679
A92: PAT YOY% | C92: =+IF(B90<0,1-C90/B90,C90/B90-1) -> 2.485593 | D92: =+IF(C90<0,1-D90/C90,D90/C90-1) -> 0.085018386 | E92: =+IF(D90<0,1-E90/D90,E90/D90-1) -> 0.7282616 | F92: =+IF(E90<0,1-F90/E90,F90/E90-1) -> -0.35584655 | G92: =+IF(F90<0,1-G90/F90,G90/F90-1) -> 0.9168178 | H92: =+IF(G90<0,1-H90/G90,H90/G90-1) -> 0.14251896 | I92: =+IF(H90<0,1-I90/H90,I90/H90-1) -> 0.29422929 | J92: =+IF(I90<0,1-J90/I90,J90/I90-1) -> 0.15953914 | ... AE92: =+IF(AD90<0,1-AE90/AD90,AE90/AD90-1) -> 0.49823722 | AM92: =+IF(AI90<0,1-AM90/AI90,AM90/AI90-1) -> -0.091491406 | AN92: =+IF(AJ90<0,1-AN90/AJ90,AN90/AJ90-1) -> 0.31987403 | AO92: =+IF(AK90<0,1-AO90/AK90,AO90/AK90-1) -> -0.40636042 | AP92: =+IF(AL90<0,1-AP90/AL90,AP90/AL90-1) -> 0.59473684 | AQ92: =+IF(AM90<0,1-AQ90/AM90,AQ90/AM90-1) -> 0.094007051 | AR92: =+IF(AN90<0,1-AR90/AN90,AR90/AN90-1) -> -0.22556455 | AS92: =+IF(AO90<0,1-AS90/AO90,AS90/AO90-1) -> 0.47452381 | AT92: =+IF(AP90<0,1-AT90/AP90,AT90/AP90-1) -> 0.29471947 | ... CL92: =+IF(CH90<0,1-CL90/CH90,CL90/CH90-1) -> 0.60158259 | CM92: =+CM90/CI90-1 -> 0.73666663 | CN92: =+CN90/CJ90-1 -> 0.82882354 | CO92: =+CO90/CK90-1 -> 0.96953526 | CP92: =+CP90/CL90-1 -> 0.077414152 | CQ92: =+CQ90/CM90-1 -> 0.44629624 | CR92: =+CR90/CN90-1 -> 0.28160735 | CS92: =+CS90/CO90-1 -> 0.35887521 | CT92: =+CT90/CP90-1 -> 0.51627208 | ... DB92: =+DB90/CX90-1 -> 0.48407506 | DF92: 0.22909571
A93: PAT QOQ% | AJ93: =+IF(AI90<0,1-AJ90/AI90,AJ90/AI90-1) -> -0.050816697 | AK93: =+IF(AJ90<0,1-AK90/AJ90,AK90/AJ90-1) -> -0.20425149 | AL93: =+IF(AK90<0,1-AL90/AK90,AL90/AK90-1) -> -0.19434629 | AM93: =+IF(AL90<0,1-AM90/AL90,AM90/AL90-1) -> 0.49298246 | AN93: =+IF(AM90<0,1-AN90/AM90,AN90/AM90-1) -> 0.37896592 | AO93: =+IF(AN90<0,1-AO90/AN90,AO90/AN90-1) -> -0.64209629 | AP93: =+IF(AO90<0,1-AP90/AO90,AP90/AO90-1) -> 1.1642857 | AQ93: =+IF(AP90<0,1-AQ90/AP90,AQ90/AP90-1) -> 0.02420242 | ... CL93: =+IF(CK90<0,1-CL90/CK90,CL90/CK90-1) -> 1.1057286 | CM93: =+CM90/CL90-1 -> -0.02055091 | CN93: =+CN90/CM90-1 -> 0.069613244 | CO93: =+CO90/CN90-1 -> -0.10720299 | CP93: =+CP90/CO90-1 -> 0.15191732 | CQ93: =+CQ90/CP90-1 -> 0.31479017 | CR93: =+CR90/CQ90-1 -> -0.052182981 | CS93: =+CS90/CR90-1 -> -0.053376428 | CT93: =+CT90/CS90-1 -> 0.28534251 | ... DB93: =+DB90/DA90-1 -> 0.27230583 | DF93: 0.61599033
A94: Minority Interest | B94: ='Annual Raw'!C32 -> 0 | C94: ='Annual Raw'!D32 -> 0 | D94: ='Annual Raw'!E32 -> 0 | E94: ='Annual Raw'!F32 -> -0.0001866 | F94: ='Annual Raw'!G32 -> 0 | G94: ='Annual Raw'!H32 -> 0 | H94: ='Annual Raw'!I32 -> 0 | I94: ='Annual Raw'!J32 -> 0 | ... AA94: ='Annual Raw'!AB32 -> 0 | AB94: =+SUM(CM94:CP94) -> -12.009384 | AC94: =+SUM(CQ94:CT94) -> -33.351264 | AD94: =+SUM(CU94:CX94) -> -51.576264 | AE94: =+SUM(CY94:DB94) -> -66.156264 | AF94: =900*25% -> 225 | AI94: ='QTR Raw'!C34 -> 0 | AJ94: ='QTR Raw'!D34 -> 0 | AK94: ='QTR Raw'!E34 -> 0 | AL94: ='QTR Raw'!F34 -> 0 | AM94: ='QTR Raw'!G34 -> 0 | AN94: ='QTR Raw'!H34 -> 0 | AO94: ='QTR Raw'!I34 -> 0 | AP94: ='QTR Raw'!J34 -> 0 | ... CL94: ='QTR Raw'!BF34 -> -1.562 | CM94: =+CM44 -> -1.787346 | CN94: =+CN44 -> -1.787346 | CO94: =+CO44 -> -1.787346 | CP94: =+CP44 -> -6.647346 | CQ94: =+CQ44 -> -6.819066 | CR94: =+CR44 -> -8.034066 | CS94: =+CS44 -> -9.249066 | CT94: =+CT44 -> -9.249066 | ... DB94: =+DB44 -> -16.539066 | DF94: 0.676
A95: Share of Associate | B95: ='Annual Raw'!C33+'Annual Raw'!C28 -> 0 | C95: ='Annual Raw'!D33+'Annual Raw'!D28 -> 0 | D95: ='Annual Raw'!E33+'Annual Raw'!E28 -> 0 | E95: ='Annual Raw'!F33+'Annual Raw'!F28 -> 0 | F95: ='Annual Raw'!G33+'Annual Raw'!G28 -> 0 | G95: ='Annual Raw'!H33+'Annual Raw'!H28 -> 0 | H95: ='Annual Raw'!I33+'Annual Raw'!I28 -> 0 | I95: ='Annual Raw'!J33+'Annual Raw'!J28 -> 0 | ... AA95: ='Annual Raw'!AB33+'Annual Raw'!AB28 -> 0 | AB95: =+SUM(CM95:CP95) -> 0 | AC95: =+SUM(CQ95:CT95) -> 0 | AD95: =+SUM(CU95:CX95) -> 0 | AE95: =+SUM(CY95:DB95) -> 0 | AI95: ='QTR Raw'!C35 -> 0 | AJ95: ='QTR Raw'!D35 -> 0 | AK95: ='QTR Raw'!E35 -> 0 | AL95: ='QTR Raw'!F35 -> 0 | AM95: ='QTR Raw'!G35 -> 0 | AN95: ='QTR Raw'!H35 -> 0 | AO95: ='QTR Raw'!I35 -> 0 | AP95: ='QTR Raw'!J35 -> 0 | ... CL95: ='QTR Raw'!BF35 -> 0 | CM95: =+CL95 -> 0 | CN95: =+CM95 -> 0 | CO95: =+CN95 -> 0 | CP95: =+CO95 -> 0 | CQ95: =+CP95 -> 0 | CR95: =+CQ95 -> 0 | CS95: =+CR95 -> 0 | CT95: =+CS95 -> 0 | ... DB95: =+DA95 -> 0 | DF95: 0
A96: Exceptional Income / Expenses | B96: ='Annual Raw'!C29+'Annual Raw'!C31+'Annual Raw'!C34+'Annual Raw'!C36 -> 0 | C96: ='Annual Raw'!D29+'Annual Raw'!D31+'Annual Raw'!D34+'Annual Raw'!D36 -> 0 | D96: ='Annual Raw'!E29+'Annual Raw'!E31+'Annual Raw'!E34+'Annual Raw'!E36 -> 0 | E96: ='Annual Raw'!F29+'Annual Raw'!F31+'Annual Raw'!F34+'Annual Raw'!F36 -> 0 | F96: ='Annual Raw'!G29+'Annual Raw'!G31+'Annual Raw'!G34+'Annual Raw'!G36 -> 0 | G96: ='Annual Raw'!H29+'Annual Raw'!H31+'Annual Raw'!H34+'Annual Raw'!H36 -> 0 | H96: ='Annual Raw'!I29+'Annual Raw'!I31+'Annual Raw'!I34+'Annual Raw'!I36 -> 0 | I96: ='Annual Raw'!J29+'Annual Raw'!J31+'Annual Raw'!J34+'Annual Raw'!J36 -> 0 | ... AA96: ='Annual Raw'!AB29+'Annual Raw'!AB31+'Annual Raw'!AB34+'Annual Raw'!AB36 -> 0 | AB96: =+SUM(CM96:CP96) -> 0 | AC96: =+SUM(CQ96:CT96) -> 0 | AD96: =+SUM(CU96:CX96) -> 0 | AE96: =+SUM(CY96:DB96) -> 0 | AI96: ='QTR Raw'!C26+'QTR Raw'!C31+'QTR Raw'!C32+'QTR Raw'!C33+'QTR Raw'!C36+'QTR Raw'!C37+'QTR Raw'!C39 -> 0 | AJ96: ='QTR Raw'!D26+'QTR Raw'!D31+'QTR Raw'!D32+'QTR Raw'!D33+'QTR Raw'!D36+'QTR Raw'!D37+'QTR Raw'!D39 -> 0 | AK96: ='QTR Raw'!E26+'QTR Raw'!E31+'QTR Raw'!E32+'QTR Raw'!E33+'QTR Raw'!E36+'QTR Raw'!E37+'QTR Raw'!E39 -> 0.118 | AL96: ='QTR Raw'!F26+'QTR Raw'!F31+'QTR Raw'!F32+'QTR Raw'!F33+'QTR Raw'!F36+'QTR Raw'!F37+'QTR Raw'!F39 -> 0 | AM96: ='QTR Raw'!G26+'QTR Raw'!G31+'QTR Raw'!G32+'QTR Raw'!G33+'QTR Raw'!G36+'QTR Raw'!G37+'QTR Raw'!G39 -> 0 | AN96: ='QTR Raw'!H26+'QTR Raw'!H31+'QTR Raw'!H32+'QTR Raw'!H33+'QTR Raw'!H36+'QTR Raw'!H37+'QTR Raw'!H39 -> 0 | AO96: ='QTR Raw'!I26+'QTR Raw'!I31+'QTR Raw'!I32+'QTR Raw'!I33+'QTR Raw'!I36+'QTR Raw'!I37+'QTR Raw'!I39 -> 0 | AP96: ='QTR Raw'!J26+'QTR Raw'!J31+'QTR Raw'!J32+'QTR Raw'!J33+'QTR Raw'!J36+'QTR Raw'!J37+'QTR Raw'!J39 -> 0 | ... CL96: ='QTR Raw'!BF26+'QTR Raw'!BF31+'QTR Raw'!BF32+'QTR Raw'!BF33+'QTR Raw'!BF36+'QTR Raw'!BF37+'QTR Raw'!BF39 -> 0 | DF96: 0
A97: Consolidated Net Profit | B97: =B90+B94+B95+B96 -> 1.0885461 | C97: =C90+C94+C95+C96 -> 3.7942287 | D97: =D90+D94+D95+D96 -> 4.1168079 | E97: =E90+E94+E95+E96 -> 7.1147344 | F97: =F90+F94+F95+F96 -> 4.5831009 | G97: =G90+G94+G95+G96 -> 8.7849694 | H97: =H90+H94+H95+H96 -> 10.036994 | I97: =I90+I94+I95+I96 -> 12.990172 | ... AE97: =AE90+AE94+AE95+AE96 -> 719.51625 | AI97: =AI90+AI94+AI95+AI96 -> 9.367 | AJ97: =AJ90+AJ94+AJ95+AJ96 -> 8.891 | AK97: =AK90+AK94+AK95+AK96 -> 7.193 | AL97: =AL90+AL94+AL95+AL96 -> 5.7 | AM97: =AM90+AM94+AM95+AM96 -> 8.51 | AN97: =AN90+AN94+AN95+AN96 -> 11.735 | AO97: =AO90+AO94+AO95+AO96 -> 4.2 | AP97: =AP90+AP94+AP95+AP96 -> 9.09 | ... DB97: =DB90+DB94+DB95+DB96 -> 215.36548 | DF97: 50.380631
A98: Profit & Loss- Annual (End)
A100: Ace - PAT | B100: ='Annual Raw'!C35 -> 1.0885461 | C100: ='Annual Raw'!D35 -> 3.7942287 | D100: ='Annual Raw'!E35 -> 4.1168079 | E100: ='Annual Raw'!F35 -> 7.1147344 | F100: ='Annual Raw'!G35 -> 4.5831009 | G100: ='Annual Raw'!H35 -> 8.7849694 | H100: ='Annual Raw'!I35 -> 10.036994 | I100: ='Annual Raw'!J35 -> 12.990172 | ... AA100: ='Annual Raw'!AB35 -> 165.5283 | AB100: =+AB97 -> 249.64151 | AC100: =+AC97 -> 333.48598 | AD100: =+AD97 -> 472.82168 | AE100: =+AE97 -> 719.51625 | AI100: ='QTR Raw'!C42 -> 9.367 | AJ100: ='QTR Raw'!D42 -> 8.891 | AK100: ='QTR Raw'!E42 -> 7.193 | AL100: ='QTR Raw'!F42 -> 5.7 | AM100: ='QTR Raw'!G42 -> 8.51 | AN100: ='QTR Raw'!H42 -> 11.735 | AO100: ='QTR Raw'!I42 -> 4.2 | AP100: ='QTR Raw'!J42 -> 9.09 | ... CL100: ='QTR Raw'!BF42 -> 63.208 | DF100: 167.2
A101: Checksum - PAT | B101: =B100-B97 -> 2.4424907e-15 | C101: =C100-C97 -> 0 | D101: =D100-D97 -> 0 | E101: =E100-E97 -> 7.9936058e-15 | F101: =F100-F97 -> -7.1054274e-15 | G101: =G100-G97 -> 0 | H101: =H100-H97 -> 0 | I101: =I100-I97 -> -1.5987212e-14 | ... AE101: =AE100-AE97 -> 0 | AI101: =AI100-AI97 -> 0 | AJ101: =AJ100-AJ97 -> 0 | AK101: =AK100-AK97 -> 7.1054274e-15 | AL101: =AL100-AL97 -> 7.9936058e-15 | AM101: =AM100-AM97 -> 0 | AN101: =AN100-AN97 -> -1.7763568e-14 | AO101: =AO100-AO97 -> 2.3980817e-14 | AP101: =AP100-AP97 -> 0 | ... CL101: =CL100-CL97 -> 0.002 | DF101: 0
A102: Ratios (Start)
A103: ROE (%) | B103: =(B97-B96)/B169 -> 0.096005011 | C103: =(C97-C96)/C169 -> 0.3135501 | D103: =(D97-D96)/D169 -> 0.26770355 | E103: =(E97-E96)/E169 -> 0.33006338 | F103: =(F97-F96)/F169 -> 0.18021539 | G103: =(G97-G96)/G169 -> 0.27025886 | H103: =(H97-H96)/H169 -> 0.22723566 | I103: =(I97-I96)/I169 -> 0.23175674 | ... AE103: =(AE97-AE96)/AE169 -> 0.19177274 | AL103: =(SUM(AI97:AL97)-SUM(AI96:AL96))/AL169 -> 0.17992231 | AM103: =(SUM(AJ97:AM97)-SUM(AJ96:AM96))/AM169 -> 0.16672744 | AN103: =(SUM(AK97:AN97)-SUM(AK96:AN96))/AN169 -> 0.17134643 | AO103: =(SUM(AL97:AO97)-SUM(AL96:AO96))/AO169 -> 0.15309102 | AP103: =(SUM(AM97:AP97)-SUM(AM96:AP96))/AP169 -> 0.16581784 | AQ103: =(SUM(AN97:AQ97)-SUM(AN96:AQ96))/AQ169 -> 0.16230206 | AR103: =(SUM(AO97:AR97)-SUM(AO96:AR96))/AR169 -> 0.14298349 | AS103: =(SUM(AP97:AS97)-SUM(AP96:AS96))/AS169 -> 0.14784494 | ... DB103: =(SUM(CY97:DB97)-SUM(CY96:DB96))/DB169 -> 0.19177274 | DF103: 0.078610614
A104: ROCE (%) | B104: =+B83/B178 -> 0.11432691 | C104: =+C83/C178 -> 0.29551835 | D104: =+D83/D178 -> 0.19432502 | E104: =+E83/E178 -> 0.21499378 | F104: =+F83/F178 -> 0.14683914 | G104: =+G83/G178 -> 0.17997156 | H104: =+H83/H178 -> 0.19153523 | I104: =+I83/I178 -> 0.18017049 | ... AE104: =+AE83/AE178 -> 0.2462951 | AL104: =+SUM(AI83:AL83)/AL178 -> 0.17686686 | AM104: =+SUM(AJ83:AM83)/AM178 -> 0.17063541 | AN104: =+SUM(AK83:AN83)/AN178 -> 0.17585915 | AO104: =+SUM(AL83:AO83)/AO178 -> 0.17796577 | AP104: =+SUM(AM83:AP83)/AP178 -> 0.1743552 | AQ104: =+SUM(AN83:AQ83)/AQ178 -> 0.17322638 | AR104: =+SUM(AO83:AR83)/AR178 -> 0.16965428 | AS104: =+SUM(AP83:AS83)/AS178 -> 0.17104388 | ... DB104: =+SUM(CY83:DB83)/DB178 -> 0.2462951 | DF104: 0.088900646
A105: Ratios (End)
A106: Checksum Of qtr to Annual
A107: Revenue - Checksum Of qtr to Annual | N107: =N59-SUM(AI59:AL59) -> -2.21e-05 | O107: =O59-SUM(AM59:AP59) -> 0.0023 | P107: =P59-SUM(AQ59:AT59) -> 13.908936 | Q107: =Q59-SUM(AU59:AX59) -> -31.90486 | R107: =R59-SUM(AY59:BB59) -> -56.81942 | S107: =S59-SUM(BC59:BF59) -> -14.203377 | T107: =T59-SUM(BG59:BJ59) -> 1.3882717 | U107: =U59-SUM(BK59:BN59) -> -0.0001611 | V107: =V59-SUM(BO59:BR59) -> -0.0009 | W107: =W59-SUM(BS59:BV59) -> 1.2086 | X107: =X59-SUM(BW59:BZ59) -> 0.3226 | Y107: =Y59-SUM(CA59:CD59) -> 0.001 | Z107: =Z59-SUM(CE59:CH59) -> -0.0006 | AA107: =AA59-SUM(CF59:CI59) -> -79.1353 | AB107: =AB59-SUM(CM59:CP59) -> 0 | AC107: =AC59-SUM(CQ59:CT59) -> 0 | AD107: =AD59-SUM(CU59:CX59) -> 0 | AE107: =AE59-SUM(CY59:DB59) -> 0 | DF107: 0
A108: GP - Checksum Of qtr to Annual | N108: =N65-SUM(AI65:AL65) -> -0.005625 | O108: =O65-SUM(AM65:AP65) -> -0.0037 | P108: =P65-SUM(AQ65:AT65) -> 5.0806788 | Q108: =Q65-SUM(AU65:AX65) -> -39.271238 | R108: =R65-SUM(AY65:BB65) -> -58.09707 | S108: =S65-SUM(BC65:BF65) -> -14.204866 | T108: =T65-SUM(BG65:BJ65) -> 1.3886452 | U108: =U65-SUM(BK65:BN65) -> -0.0007525 | V108: =V65-SUM(BO65:BR65) -> -0.001 | W108: =W65-SUM(BS65:BV65) -> 1.2086 | X108: =X65-SUM(BW65:BZ65) -> 0.3231 | Y108: =Y65-SUM(CA65:CD65) -> 0.0014 | Z108: =Z65-SUM(CE65:CH65) -> 0.0012 | AA108: =AA65-SUM(CF65:CI65) -> -13.337 | AB108: =AB65-SUM(CM65:CP65) -> 0 | AC108: =AC65-SUM(CQ65:CT65) -> 0 | AD108: =AD65-SUM(CU65:CX65) -> 0 | AE108: =AE65-SUM(CY65:DB65) -> 0 | CL108: =45*330 -> 14850 | DF108: 0
A109: EBITDA - Checksum Of qtr to Annual | N109: =N77-SUM(AI77:AL77) -> -0.8850603 | O109: =O77-SUM(AM77:AP77) -> -3.6735 | P109: =P77-SUM(AQ77:AT77) -> -0.6009697 | Q109: =Q77-SUM(AU77:AX77) -> -5.6119675 | R109: =R77-SUM(AY77:BB77) -> -5.6733107 | S109: =S77-SUM(BC77:BF77) -> -7.4901648 | T109: =T77-SUM(BG77:BJ77) -> -1.8521268 | U109: =U77-SUM(BK77:BN77) -> -3.2621548 | V109: =V77-SUM(BO77:BR77) -> -5.2887 | W109: =W77-SUM(BS77:BV77) -> -0.2414 | X109: =X77-SUM(BW77:BZ77) -> 0.3079 | Y109: =Y77-SUM(CA77:CD77) -> 0.0027 | Z109: =Z77-SUM(CE77:CH77) -> 0.0016 | AA109: =AA77-SUM(CF77:CI77) -> 26.5111 | AB109: =AB77-SUM(CM77:CP77) -> 0 | AC109: =AC77-SUM(CQ77:CT77) -> 0 | AD109: =AD77-SUM(CU77:CX77) -> 0 | AE109: =AE77-SUM(CY77:DB77) -> 0 | DF109: 0
A110: PAT - Checksum Of qtr to Annual | N110: =N97-SUM(AI97:AL97) -> 0.0178012 | O110: =O97-SUM(AM97:AP97) -> -0.0274 | P110: =P97-SUM(AQ97:AT97) -> -2.0879804 | Q110: =Q97-SUM(AU97:AX97) -> -3.6585793 | R110: =R97-SUM(AY97:BB97) -> -3.2222226 | S110: =S97-SUM(BC97:BF97) -> 0.001004 | T110: =T97-SUM(BG97:BJ97) -> 0.0030158 | U110: =U97-SUM(BK97:BN97) -> 0.0005269 | V110: =V97-SUM(BO97:BR97) -> -0.0005 | W110: =W90-SUM(BS90:BV90) -> 0.0027 | X110: =X90-SUM(BW90:BZ90) -> 0.001 | Y110: =Y90-SUM(CA90:CD90) -> 0.004 | Z110: =Z90-SUM(CE90:CH90) -> 0.0014 | AA110: =AA90-SUM(CF90:CI90) -> 15.9693 | AB110: =AB90-SUM(CM90:CP90) -> 0 | AC110: =AC90-SUM(CQ90:CT90) -> 0 | AD110: =AD90-SUM(CU90:CX90) -> 0 | AE110: =AE90-SUM(CY90:DB90) -> -9.094947e-13 | DF110: 0
A111: Valuation (Start)
...

Sheet data
A1: Plant / Product | B1: Investment | C1: Estimated Annual Revenue Contribution
A2: HCN & Sodium Cyanide | B2: ₹750 Cr | C2: ₹1,100 – ₹1,500 Cr
A3: Methyl Amines (Unit IV) | B3: Part of prior CAPEX | C3: ₹300 – ₹400 Cr
A4: Dimethyl Ether (DME) | B4: Part of prior CAPEX | C4: ₹200 – ₹300 Cr
A5: Specialty Derivatives (NBPT/EDTA) | B5: Integrated | C5: ₹150 – ₹250 Cr
A9: Segments | B9: Amines | C9: Amine Derivatives | D9: Speciality Chemicals | G9: Spec Chem Products | I9: Application
A10: Products | B10: • Mono Methyl Amine (MMA) | C10: Di-Methyl Acetamide (DMAC) | D10: • Morpholine | G10: EDA (Ethyldiamine) | I10: Pesticides, Polymers
B11: • Di-Methyl Amine (DMA) | C11: • Di-Methyl Amine Hydrochloride (DMA HCL) | D11: • Acetonitrile | G11: Piprazine | I11: Pharma, Oilfield
B12: • Tri-Methyl Amine (TMA) | C12: • Tri-Methyl Amine Hydrochloride (TMA HCL) | D12: • Dimethylformamide (DMF) | G12: Diethyltriamine | I12: Coatings, Polymers, Pharma
B13: • Mono-Ethyl Amine (MEA) | C13: • Mono-Methyl Amine Hydrochloride (MMA HCL) | D13: • N-Ethyl-2-Pyrrolidone (NEP) | G13: Mixture of amines | I13: Multiple Industries
B14: • Di-Ethyl Amine (DEA) | C14: • Di-Ethyl Amine Hydrochloride (DEA HCL) | D14: • 2-Pyrrolidone (2-P)
B15: • Tri-Ethyl Amine (TEA) | C15: • Tri-Ethyl Amine Hydrochloride (TEA HCL) | D15: • Gamma Butyrolactone,
B16: • Di-Methyl Amino Ethanol (DMAE) | C16: • Mono-Ethyl Amine Hydrochloride (MEA HCL) | D16: • N-Methyl-Pyrrolidone (NMP)
B17: • Di-Ethyl Amino Ethanol (DEAE) | C17: • Di-Methyl Urea (DMU) | D17: • Pharmapure Povidone (PVP K30 & PVP K25)
C18: • Choline Chloride
A20: End User | B20: Pharma, Agro, Dyestuff intermediates, Agro, Rubber Chemicals, Rocket Fuel | C20: Pharma, Pesticides, Speciality Chem, Animal Poultry feed, Performance chem | D20: Water treatment chemicals, Solvents
A21: Clientele | B21: Jubilant Life science, Dr reddy, Aurobindo, Hetero | C21: Sun Pharma, Venkys, Kores, USV, Wanburry | D21: HP, IOC, Hikal, Mylan, Zydus
A23: 3. Key Raw Materials (The "Cost" Side) | G23: Reporting Segment | H23: FY22 | I23: FY23 | J23: FY24 | K23: FY25 | L23: FY26 (Current)
A24: Since raw materials make up 60-70% of their total cost, tracking these is non-negotiable for margin forecasting. | G24: Aliphatic Amines (Methyl & Ethyl) | H24: 112500 | I24: 112500 | J24: 112500 | K24: 152500 | L24: 152500
A25: Methanol: The single most important raw material for the Methyl Amines and DMF chain. | G25: Amine Derivatives (DMAHCL, etc.) | H25: 31000 | I25: 31000 | J25: 45000 | K25: 45000 | L25: 45000
A26: Note: Methanol prices are often correlated with global Natural Gas prices. | G26: Specialty Chemicals (DMC, Acetonitrile) | H26: 37500 | I26: 45330 | J26: 45330 | K26: 54330 | L26: 54330
A27: Ammonia: The critical nitrogen source for all amines. | G27: Total Nameplate Capacity (MTPA) | H27: 181000 | I27: 188830 | J27: 202830 | K27: 251830 | L27: 251830
A28: Note: Ammonia prices are highly volatile and linked to global Fertilizer demand.
A29: Ethyl Alcohol (Ethanol): The primary input for the Ethyl Amines chain.
A30: Note: In India, this is influenced by Government Sugar/Ethanol policies.

Sheet Concall
A2: DME - unit 4 expected to comission in 1QFY27. applcation in Aerosol and replacement of LPG
A3: N methyl morphine project - capacity of 5000 MT - commisiion in FY27
A4: Balaji speciality - 750 crs project - hydrogen cyanide, sodium cyanide, EDTA, and advanced chemical products
A5: at unit 1 - brownfield project of including DETA, Teta, PIP, AEEA and AEP during first half of FY27 | M5: Capacity - MT | O5: Price
A6: Unit 2 - greenfield in chincholi to mfg HCN, Nacn expected to commission in 4QFY27 | L6: DME | M6: 100000 | O6: 110 | P6: =M6*O6/10^4 -> 1100
A7: Current standalone capacity 293,000 MT. DMF and Methyl amines running at lower utilisatons | L7: NMM | M7: 5000 | O7: 250 | P7: =M7*O7/10^4 -> 125
A8: Expecting vol growth of 25 to 30% from current levels and EBIDTA margins to sustain at 22-23% | L8: Acetonitrile | M8: 9000 | O8: 220 | P8: =M8*O8/10^4 -> 198
A9: if current situation remians we will rach 3000 crs of sales | M9: =SUM(M6:M8) -> 114000 | P9: =SUM(P6:P8) -> 1423
A10: DME - aerosl industry uses 40,000 to 50,000 MT of gases other industry who will use this are baking, bukb and ceramic industry
A11: EDA- 280 to 300 prices currently it also reached 400
A12: Ammoia and methanol - prices are up but availability is not the issue
A13: In DME transport permission is still left which will take 1 months time. After that being a new product can have teething issues. FY27 - 30% utilisation, FY 28 60-80%. Conservative price of 80 rs with 80% utilisation. Have reached to all potential customers bcoz its a gas, have ordered 100 cyclinders of 500 kg each once thos trials are successful we will receive permision
A14: Capex: balaji speciality - total 750 crs of capex - in first phase will spend 350 -400 crs already spent 110 crs rest 280 crs will be spent in this year.
A15: Vol growth for FY27 - 10-15% vol growth on consol basis
A16: Battery chemical product currently offtake has not happened due to mfg pushing their timeline. Its running at 22-25% utilisation and giving to pharma and agrochem
A21: Capacity | N21: 2000 | P21: 1000
A22: Unit 1 | B22: Per Day - MT | C22: MT Pa
A23: EDA | B23: 82 | C23: =+B23*365 -> 29930 | E23: 150 | F23: =+C23*E23/10^4 -> 448.95
A24: Tetra | B24: 10 | C24: =+B24*365 -> 3650
A25: pipra | B25: 10 | C25: =+B25*365 -> 3650 | H25: =1500*13% -> 195
H26: =+H25/2 -> 97.5
A28: Unit 3
A29: MA | B29: 100 | C29: =+B29*365 -> 36500 | E29: 400 | F29: =+C29*E29/10^4*50% -> 730
A30: NMP | B30: 50 | C30: =+B30*365 -> 18250 | F30: =+C30*E30/10^4 -> 0
A31: GBL | B31: 15 | C31: =+B31*365 -> 5475 | F31: =+C31*E31/10^4 -> 0
A32: PVPK 30 | B32: 3 | C32: =+B32*365 -> 1095 | F32: =+C32*E32/10^4 -> 0
A33: DMF | B33: 100 | C33: =+B33*365 -> 36500 | E33: 90 | F33: =+C33*E33/10^4 -> 328.5
A34: DMA HCL | B34: 70 | C34: =+B34*365 -> 25550 | F34: =+C34*E34/10^4 -> 0
A35: ACN | B35: 50 | C35: =+B35*365 -> 18250 | E35: 220 | F35: =+C35*E35/10^4 -> 401.5
A37: Unit 4
A38: DMC | B38: 50 | C38: =+B38*365 -> 18250
A39: MA | B39: 200 | C39: =+B39*365 -> 73000 | E39: 400 | F39: =+C39*E39/10^4*50% -> 1460
A40: N Butyl Amine | B40: 40 | C40: =+B40*365 -> 14600 | F40: =+C40*E40/10^4 -> 0
A41: Ethyl Amine | B41: 130 | C41: =+B41*365 -> 47450 | E41: 80 | F41: =+C41*E41/10^4 -> 379.6
A42: DME | B42: 275 | C42: =+B42*365 -> 100375 | E42: 100 | F42: =+C42*E42/10^4 -> 1003.75
F43: =+C43*E43/10^4 -> 0
A44: Unit 4 New | F44: =+C44*E44/10^4 -> 0
A45: Sodium cyanide | B45: 28 | C45: =+B45*365 -> 10220 | E45: 600 | F45: =+C45*E45/10^4 -> 613.2
A46: EDTA | B46: 14 | C46: =+B46*365 -> 5110 | E46: 600 | F46: =+C46*E46/10^4 -> 306.6
F48: =SUM(F23:F47) -> 5672.1
A50: Speciality Chem - volume and model accordingly with - minority interest

Sheet QTR Raw
A1: ='Annual Raw'!A1 -> 130999 | B1: X | C1: 201206 | D1: 201209 | E1: 201212 | F1: 201303 | G1: 201306 | H1: 201309 | I1: 201312 | J1: 201403 | K1: 201406 | L1: 201409 | M1: 201412 | N1: 201503 | O1: 201506 | P1: 201509 | Q1: 201512 | R1: 201603 | S1: 201606 | T1: 201609 | U1: 201612 | V1: 201703 | W1: 201706 | X1: 201709 | Y1: 201712 | Z1: 201803 | AA1: 201806 | AB1: 201809 | AC1: 201812 | AD1: 201903 | AE1: 201906 | AF1: 201909 | AG1: 201912 | AH1: 202003 | AI1: 202006 | AJ1: 202009 | AK1: 202012 | AL1: 202103 | AM1: 202106 | AN1: 202109 | AO1: 202112 | AP1: 202203 | AQ1: 202206 | AR1: 202209 | AS1: 202212 | AT1: 202303 | AU1: 202306 | AV1: 202309 | AW1: 202312 | AX1: 202403 | AY1: 202406 | AZ1: 202409 | BA1: 202412 | BB1: 202503 | BC1: 202506 | BD1: 202509 | BE1: 202512 | BF1: 202603 | BG1: 202606 | BH1: 202609 | BI1: 202612 | BJ1: 202703 | BK1: 202706 | BL1: 202709 | BM1: 202712 | BN1: 202803 | BO1: 202806 | BP1: 202809 | BQ1: 202812 | BR1: 202903 | BS1: 202906 | BT1: 202909 | BU1: 202912 | BV1: 203003
A3: Field Description | B3: Field Name
A4: Company Name | B4: CD_COMPNAME | C4: =_xll.EQNXTDZ(A1,B4,C1) -> Balaji Amines Ltd.
A5: Date End | B5: QTR_DATE_END | C5: =_xll.EQNXTDZ($A$1,$B5,C$1,$B$1) -> 201206 | D5: =_xll.EQNXTDZ($A$1,$B5,D$1,$B$1) -> 201209 | E5: =_xll.EQNXTDZ($A$1,$B5,E$1,$B$1) -> 201212 | F5: =_xll.EQNXTDZ($A$1,$B5,F$1,$B$1) -> 201303 | G5: =_xll.EQNXTDZ($A$1,$B5,G$1,$B$1) -> 201306 | H5: =_xll.EQNXTDZ($A$1,$B5,H$1,$B$1) -> 201309 | I5: =_xll.EQNXTDZ($A$1,$B5,I$1,$B$1) -> 201312 | J5: =_xll.EQNXTDZ($A$1,$B5,J$1,$B$1) -> 201403 | ... BV5: =_xll.EQNXTDZ($A$1,$B5,BV$1,$B$1) -> 0
A6: Gross Sales | B6: QTR_GROSS_SALE | C6: =_xll.EQNXTDZ($A$1,$B6,C$1,$B$1) -> 136.559 | D6: =_xll.EQNXTDZ($A$1,$B6,D$1,$B$1) -> 126.011 | E6: =_xll.EQNXTDZ($A$1,$B6,E$1,$B$1) -> 107.746 | F6: =_xll.EQNXTDZ($A$1,$B6,F$1,$B$1) -> 141.48 | G6: =_xll.EQNXTDZ($A$1,$B6,G$1,$B$1) -> 140.1 | H6: =_xll.EQNXTDZ($A$1,$B6,H$1,$B$1) -> 161.014 | I6: =_xll.EQNXTDZ($A$1,$B6,I$1,$B$1) -> 137.51 | J6: =_xll.EQNXTDZ($A$1,$B6,J$1,$B$1) -> 171.5 | ... BV6: =_xll.EQNXTDZ($A$1,$B6,BV$1,$B$1) -> 0
A7: Less: Excise Duty | B7: QTR_EXCISE_DUTY | C7: =_xll.EQNXTDZ($A$1,$B7,C$1,$B$1) -> 0 | D7: =_xll.EQNXTDZ($A$1,$B7,D$1,$B$1) -> 0 | E7: =_xll.EQNXTDZ($A$1,$B7,E$1,$B$1) -> 0 | F7: =_xll.EQNXTDZ($A$1,$B7,F$1,$B$1) -> 0 | G7: =_xll.EQNXTDZ($A$1,$B7,G$1,$B$1) -> 0 | H7: =_xll.EQNXTDZ($A$1,$B7,H$1,$B$1) -> 0 | I7: =_xll.EQNXTDZ($A$1,$B7,I$1,$B$1) -> 0 | J7: =_xll.EQNXTDZ($A$1,$B7,J$1,$B$1) -> 0 | ... BV7: =_xll.EQNXTDZ($A$1,$B7,BV$1,$B$1) -> 0
A8: Other operating income | B8: QTR_JOB_WORKS | C8: =_xll.EQNXTDZ($A$1,$B8,C$1,$B$1) -> 0 | D8: =_xll.EQNXTDZ($A$1,$B8,D$1,$B$1) -> 0 | E8: =_xll.EQNXTDZ($A$1,$B8,E$1,$B$1) -> 0 | F8: =_xll.EQNXTDZ($A$1,$B8,F$1,$B$1) -> 0 | G8: =_xll.EQNXTDZ($A$1,$B8,G$1,$B$1) -> 0 | H8: =_xll.EQNXTDZ($A$1,$B8,H$1,$B$1) -> 0 | I8: =_xll.EQNXTDZ($A$1,$B8,I$1,$B$1) -> 0 | J8: =_xll.EQNXTDZ($A$1,$B8,J$1,$B$1) -> 0 | ... BV8: =_xll.EQNXTDZ($A$1,$B8,BV$1,$B$1) -> 0
A9: Net Sales & Other Operating Income | B9: QTR_NET_SALES | C9: =_xll.EQNXTDZ($A$1,$B9,C$1,$B$1) -> 136.559 | D9: =_xll.EQNXTDZ($A$1,$B9,D$1,$B$1) -> 126.011 | E9: =_xll.EQNXTDZ($A$1,$B9,E$1,$B$1) -> 107.746 | F9: =_xll.EQNXTDZ($A$1,$B9,F$1,$B$1) -> 141.48 | G9: =_xll.EQNXTDZ($A$1,$B9,G$1,$B$1) -> 140.1 | H9: =_xll.EQNXTDZ($A$1,$B9,H$1,$B$1) -> 161.014 | I9: =_xll.EQNXTDZ($A$1,$B9,I$1,$B$1) -> 137.51 | J9: =_xll.EQNXTDZ($A$1,$B9,J$1,$B$1) -> 171.5 | ... BV9: =_xll.EQNXTDZ($A$1,$B9,BV$1,$B$1) -> 0
A10: (Increase) / Decrease In Stocks | B10: QTR_INC_DEC_INVENTORY | C10: =_xll.EQNXTDZ($A$1,$B10,C$1,$B$1) -> 9.242 | D10: =_xll.EQNXTDZ($A$1,$B10,D$1,$B$1) -> -4.729 | E10: =_xll.EQNXTDZ($A$1,$B10,E$1,$B$1) -> 5.027 | F10: =_xll.EQNXTDZ($A$1,$B10,F$1,$B$1) -> 15.49 | G10: =_xll.EQNXTDZ($A$1,$B10,G$1,$B$1) -> 2.69 | H10: =_xll.EQNXTDZ($A$1,$B10,H$1,$B$1) -> -15.333 | I10: =_xll.EQNXTDZ($A$1,$B10,I$1,$B$1) -> -14.51 | J10: =_xll.EQNXTDZ($A$1,$B10,J$1,$B$1) -> 4.7 | ... BV10: =_xll.EQNXTDZ($A$1,$B10,BV$1,$B$1) -> 0
A11: Cost of Services & Raw Materials | B11: QTR_RAW_MATERIAL_COST | C11: =_xll.EQNXTDZ($A$1,$B11,C$1,$B$1) -> 74.989 | D11: =_xll.EQNXTDZ($A$1,$B11,D$1,$B$1) -> 78.647 | E11: =_xll.EQNXTDZ($A$1,$B11,E$1,$B$1) -> 60.731 | F11: =_xll.EQNXTDZ($A$1,$B11,F$1,$B$1) -> 72.8 | G11: =_xll.EQNXTDZ($A$1,$B11,G$1,$B$1) -> 87.46 | H11: =_xll.EQNXTDZ($A$1,$B11,H$1,$B$1) -> 111.359 | I11: =_xll.EQNXTDZ($A$1,$B11,I$1,$B$1) -> 100.15 | J11: =_xll.EQNXTDZ($A$1,$B11,J$1,$B$1) -> 104.45 | ... BV11: =_xll.EQNXTDZ($A$1,$B11,BV$1,$B$1) -> 0
A12: Purchase of Finished Goods | B12: QTR_PURCHASE_FIN_GOOD | C12: =_xll.EQNXTDZ($A$1,$B12,C$1,$B$1) -> 0 | D12: =_xll.EQNXTDZ($A$1,$B12,D$1,$B$1) -> 0 | E12: =_xll.EQNXTDZ($A$1,$B12,E$1,$B$1) -> 0 | F12: =_xll.EQNXTDZ($A$1,$B12,F$1,$B$1) -> 0 | G12: =_xll.EQNXTDZ($A$1,$B12,G$1,$B$1) -> 0 | H12: =_xll.EQNXTDZ($A$1,$B12,H$1,$B$1) -> 0 | I12: =_xll.EQNXTDZ($A$1,$B12,I$1,$B$1) -> 0 | J12: =_xll.EQNXTDZ($A$1,$B12,J$1,$B$1) -> 0 | ... BV12: =_xll.EQNXTDZ($A$1,$B12,BV$1,$B$1) -> 0
A13: Excise Duty | B13: QTR_EXCISE | C13: =_xll.EQNXTDZ($A$1,$B13,C$1,$B$1) -> 0 | D13: =_xll.EQNXTDZ($A$1,$B13,D$1,$B$1) -> 0 | E13: =_xll.EQNXTDZ($A$1,$B13,E$1,$B$1) -> 0 | F13: =_xll.EQNXTDZ($A$1,$B13,F$1,$B$1) -> 0 | G13: =_xll.EQNXTDZ($A$1,$B13,G$1,$B$1) -> 0 | H13: =_xll.EQNXTDZ($A$1,$B13,H$1,$B$1) -> 0 | I13: =_xll.EQNXTDZ($A$1,$B13,I$1,$B$1) -> 0 | J13: =_xll.EQNXTDZ($A$1,$B13,J$1,$B$1) -> 0 | ... BV13: =_xll.EQNXTDZ($A$1,$B13,BV$1,$B$1) -> 0
A14: Operating & Manufacturing Expenses | B14: QTR_MFG_EXPS | C14: =_xll.EQNXTDZ($A$1,$B14,C$1,$B$1) -> 24.746 | D14: =_xll.EQNXTDZ($A$1,$B14,D$1,$B$1) -> 24.727 | E14: =_xll.EQNXTDZ($A$1,$B14,E$1,$B$1) -> 20.889 | F14: =_xll.EQNXTDZ($A$1,$B14,F$1,$B$1) -> 31.01 | G14: =_xll.EQNXTDZ($A$1,$B14,G$1,$B$1) -> 22.73 | H14: =_xll.EQNXTDZ($A$1,$B14,H$1,$B$1) -> 32.531 | I14: =_xll.EQNXTDZ($A$1,$B14,I$1,$B$1) -> 27.14 | J14: =_xll.EQNXTDZ($A$1,$B14,J$1,$B$1) -> 34.95 | ... BV14: =_xll.EQNXTDZ($A$1,$B14,BV$1,$B$1) -> 0
A15: Electricity Power & Fuel Cost | B15: QTR_ELECTRICITY_POWER_FUEL | C15: =_xll.EQNXTDZ($A$1,$B15,C$1,$B$1) -> 0 | D15: =_xll.EQNXTDZ($A$1,$B15,D$1,$B$1) -> 0 | E15: =_xll.EQNXTDZ($A$1,$B15,E$1,$B$1) -> 0 | F15: =_xll.EQNXTDZ($A$1,$B15,F$1,$B$1) -> 0 | G15: =_xll.EQNXTDZ($A$1,$B15,G$1,$B$1) -> 0 | H15: =_xll.EQNXTDZ($A$1,$B15,H$1,$B$1) -> 0 | I15: =_xll.EQNXTDZ($A$1,$B15,I$1,$B$1) -> 0 | J15: =_xll.EQNXTDZ($A$1,$B15,J$1,$B$1) -> 0 | ... BV15: =_xll.EQNXTDZ($A$1,$B15,BV$1,$B$1) -> 0
A16: Employee Cost | B16: QTR_EXPLOYEE_COST | C16: =_xll.EQNXTDZ($A$1,$B16,C$1,$B$1) -> 4.582 | D16: =_xll.EQNXTDZ($A$1,$B16,D$1,$B$1) -> 4.299 | E16: =_xll.EQNXTDZ($A$1,$B16,E$1,$B$1) -> 4.581 | F16: =_xll.EQNXTDZ($A$1,$B16,F$1,$B$1) -> 4.54 | G16: =_xll.EQNXTDZ($A$1,$B16,G$1,$B$1) -> 4.52 | H16: =_xll.EQNXTDZ($A$1,$B16,H$1,$B$1) -> 4.698 | I16: =_xll.EQNXTDZ($A$1,$B16,I$1,$B$1) -> 5.29 | J16: =_xll.EQNXTDZ($A$1,$B16,J$1,$B$1) -> 6.27 | ... BV16: =_xll.EQNXTDZ($A$1,$B16,BV$1,$B$1) -> 0
... A42: Consolidated PAT(after extra items) | B42: QTR_CONS_PAT_EXITM | C42: =_xll.EQNXTDZ($A$1,$B42,C$1,$B$1) -> 9.367 | D42: =_xll.EQNXTDZ($A$1,$B42,D$1,$B$1) -> 8.891 | E42: =_xll.EQNXTDZ($A$1,$B42,E$1,$B$1) -> 7.193 | F42: =_xll.EQNXTDZ($A$1,$B42,F$1,$B$1) -> 5.7 | G42: =_xll.EQNXTDZ($A$1,$B42,G$1,$B$1) -> 8.51 | H42: =_xll.EQNXTDZ($A$1,$B42,H$1,$B$1) -> 11.735 | I42: =_xll.EQNXTDZ($A$1,$B42,I$1,$B$1) -> 4.2 | J42: =_xll.EQNXTDZ($A$1,$B42,J$1,$B$1) -> 9.09 | ... BV42: =_xll.EQNXTDZ($A$1,$B42,BV$1,$B$1) -> 0
A44: Field Description | B44: Field Name
A45: Equity Capital | B45: QTR_EQUITY_CAP | C45: =_xll.EQNXTDZ($A$1,$B45,C$1,$B$1) -> 6.48 | D45: =_xll.EQNXTDZ($A$1,$B45,D$1,$B$1) -> 6.48 | E45: =_xll.EQNXTDZ($A$1,$B45,E$1,$B$1) -> 6.48 | F45: =_xll.EQNXTDZ($A$1,$B45,F$1,$B$1) -> 6.48 | G45: =_xll.EQNXTDZ($A$1,$B45,G$1,$B$1) -> 6.48 | H45: =_xll.EQNXTDZ($A$1,$B45,H$1,$B$1) -> 6.48 | I45: =_xll.EQNXTDZ($A$1,$B45,I$1,$B$1) -> 6.48 | J45: =_xll.EQNXTDZ($A$1,$B45,J$1,$B$1) -> 6.48 | ... BV45: =_xll.EQNXTDZ($A$1,$B45,BV$1,$B$1) -> 0
A46: Face Value | B46: QTR_FV | C46: =_xll.EQNXTDZ($A$1,$B46,C$1,$B$1) -> 2 | D46: =_xll.EQNXTDZ($A$1,$B46,D$1,$B$1) -> 2 | E46: =_xll.EQNXTDZ($A$1,$B46,E$1,$B$1) -> 2 | F46: =_xll.EQNXTDZ($A$1,$B46,F$1,$B$1) -> 2 | G46: =_xll.EQNXTDZ($A$1,$B46,G$1,$B$1) -> 2 | H46: =_xll.EQNXTDZ($A$1,$B46,H$1,$B$1) -> 2 | I46: =_xll.EQNXTDZ($A$1,$B46,I$1,$B$1) -> 2 | J46: =_xll.EQNXTDZ($A$1,$B46,J$1,$B$1) -> 2 | ... BV46: =_xll.EQNXTDZ($A$1,$B46,BV$1,$B$1) -> 0
A47: Month End | B47: BMONTH_MONTHEND | C47: =_xll.EQNXTDZ($A$1,$B47,C$5) -> 201206 | D47: =_xll.EQNXTDZ($A$1,$B47,D$5) -> 201209 | E47: =_xll.EQNXTDZ($A$1,$B47,E$5) -> 201212 | F47: =_xll.EQNXTDZ($A$1,$B47,F$5) -> 201303 | G47: =_xll.EQNXTDZ($A$1,$B47,G$5) -> 201306 | H47: =_xll.EQNXTDZ($A$1,$B47,H$5) -> 201309 | I47: =_xll.EQNXTDZ($A$1,$B47,I$5) -> 201312 | J47: =_xll.EQNXTDZ($A$1,$B47,J$5) -> 201403 | ... BV47: =_xll.EQNXTDZ($A$1,$B47,BV$5) -> 0
A48: Close | B48: BMONTH_CLOSE | C48: =_xll.EQNXTDZ($A$1,$B48,C$5) -> 37.9 | D48: =_xll.EQNXTDZ($A$1,$B48,D$5) -> 58.95 | E48: =_xll.EQNXTDZ($A$1,$B48,E$5) -> 54.1 | F48: =_xll.EQNXTDZ($A$1,$B48,F$5) -> 35.2 | G48: =_xll.EQNXTDZ($A$1,$B48,G$5) -> 33.45 | H48: =_xll.EQNXTDZ($A$1,$B48,H$5) -> 32.15 | I48: =_xll.EQNXTDZ($A$1,$B48,I$5) -> 49.8 | J48: =_xll.EQNXTDZ($A$1,$B48,J$5) -> 39.95 | ... BV48: =_xll.EQNXTDZ($A$1,$B48,BV$5) -> 0
A49: Total of Promoter and Promoter Group | B49: SHP_TPFTOTALPROMOTER | C49: =_xll.EQNXTDZ($A$1,$B49,C$5) -> 53.87 | D49: =_xll.EQNXTDZ($A$1,$B49,D$5) -> 53.87 | E49: =_xll.EQNXTDZ($A$1,$B49,E$5) -> 53.87 | F49: =_xll.EQNXTDZ($A$1,$B49,F$5) -> 53.93 | G49: =_xll.EQNXTDZ($A$1,$B49,G$5) -> 53.99 | H49: =_xll.EQNXTDZ($A$1,$B49,H$5) -> 54.24 | I49: =_xll.EQNXTDZ($A$1,$B49,I$5) -> 54.34 | J49: =_xll.EQNXTDZ($A$1,$B49,J$5) -> 54.34 | ... BV49: =_xll.EQNXTDZ($A$1,$B49,BV$5) -> 0
A50: Total of Promoter and Promoter Group Pledged | B50: SHP_PSHFTOTALPROMOTER | C50: =_xll.EQNXTDZ($A$1,$B50,C$5) -> 38.57 | D50: =_xll.EQNXTDZ($A$1,$B50,D$5) -> 38.57 | E50: =_xll.EQNXTDZ($A$1,$B50,E$5) -> 38.57 | F50: =_xll.EQNXTDZ($A$1,$B50,F$5) -> 38.53 | G50: =_xll.EQNXTDZ($A$1,$B50,G$5) -> 38.48 | H50: =_xll.EQNXTDZ($A$1,$B50,H$5) -> 38.3 | I50: =_xll.EQNXTDZ($A$1,$B50,I$5) -> 38.24 | J50: =_xll.EQNXTDZ($A$1,$B50,J$5) -> 38.24 | ... BV50: =_xll.EQNXTDZ($A$1,$B50,BV$5) -> 0
A54: Field Description | B54: Field Name | C54: =_xll.EQNXTDZ($A$1,$B54,C$5) -> 0 | D54: =_xll.EQNXTDZ($A$1,$B54,D$5) -> 0 | E54: =_xll.EQNXTDZ($A$1,$B54,E$5) -> 0 | F54: =_xll.EQNXTDZ($A$1,$B54,F$5) -> 0 | G54: =_xll.EQNXTDZ($A$1,$B54,G$5) -> 0 | H54: =_xll.EQNXTDZ($A$1,$B54,H$5) -> 0 | I54: =_xll.EQNXTDZ($A$1,$B54,I$5) -> 0 | J54: =_xll.EQNXTDZ($A$1,$B54,J$5) -> 0 | ... BV54: =_xll.EQNXTDZ($A$1,$B54,BV$5) -> 0
A55: Year End | B55: QTRB_DATE_END | C55: =_xll.EQNXTDZ($A$1,$B55,C$5,$B$1) -> 0 | D55: =_xll.EQNXTDZ($A$1,$B55,D$5,$B$1) -> 201209 | E55: =_xll.EQNXTDZ($A$1,$B55,E$5,$B$1) -> 0 | F55: =_xll.EQNXTDZ($A$1,$B55,F$5,$B$1) -> 201303 | G55: =_xll.EQNXTDZ($A$1,$B55,G$5,$B$1) -> 0 | H55: =_xll.EQNXTDZ($A$1,$B55,H$5,$B$1) -> 201309 | I55: =_xll.EQNXTDZ($A$1,$B55,I$5,$B$1) -> 0 | J55: =_xll.EQNXTDZ($A$1,$B55,J$5,$B$1) -> 201403 | ... BV55: =_xll.EQNXTDZ($A$1,$B55,BV$5,$B$1) -> 0
A56: Share Capital | B56: QTRB_SHARE_CAPITAL | C56: =_xll.EQNXTDZ($A$1,$B56,C$5,$B$1) -> 0 | D56: =_xll.EQNXTDZ($A$1,$B56,D$5,$B$1) -> 6.48 | E56: =_xll.EQNXTDZ($A$1,$B56,E$5,$B$1) -> 0 | F56: =_xll.EQNXTDZ($A$1,$B56,F$5,$B$1) -> 6.48 | G56: =_xll.EQNXTDZ($A$1,$B56,G$5,$B$1) -> 0 | H56: =_xll.EQNXTDZ($A$1,$B56,H$5,$B$1) -> 6.48 | I56: =_xll.EQNXTDZ($A$1,$B56,I$5,$B$1) -> 0 | J56: =_xll.EQNXTDZ($A$1,$B56,J$5,$B$1) -> 6.48 | ... BV56: =_xll.EQNXTDZ($A$1,$B56,BV$5,$B$1) -> 0
A57: Share Warrants & outstandings | B57: QTRB_SHAREWARNDOUT | C57: =_xll.EQNXTDZ($A$1,$B57,C$5,$B$1) -> 0 | D57: =_xll.EQNXTDZ($A$1,$B57,D$5,$B$1) -> 0 | E57: =_xll.EQNXTDZ($A$1,$B57,E$5,$B$1) -> 0 | F57: =_xll.EQNXTDZ($A$1,$B57,F$5,$B$1) -> 0 | G57: =_xll.EQNXTDZ($A$1,$B57,G$5,$B$1) -> 0 | H57: =_xll.EQNXTDZ($A$1,$B57,H$5,$B$1) -> 0 | I57: =_xll.EQNXTDZ($A$1,$B57,I$5,$B$1) -> 0 | J57: =_xll.EQNXTDZ($A$1,$B57,J$5,$B$1) -> 0 | ... BV57: =_xll.EQNXTDZ($A$1,$B57,BV$5,$B$1) -> 0
A58: Reserves & Surplus | B58: QTRB_RESERVE | C58: =_xll.EQNXTDZ($A$1,$B58,C$5,$B$1) -> 0 | D58: =_xll.EQNXTDZ($A$1,$B58,D$5,$B$1) -> 157.973 | E58: =_xll.EQNXTDZ($A$1,$B58,E$5,$B$1) -> 0 | F58: =_xll.EQNXTDZ($A$1,$B58,F$5,$B$1) -> 166 | G58: =_xll.EQNXTDZ($A$1,$B58,G$5,$B$1) -> 0 | H58: =_xll.EQNXTDZ($A$1,$B58,H$5,$B$1) -> 186.229 | I58: =_xll.EQNXTDZ($A$1,$B58,I$5,$B$1) -> 0 | J58: =_xll.EQNXTDZ($A$1,$B58,J$5,$B$1) -> 195.76 | ... BV58: =_xll.EQNXTDZ($A$1,$B58,BV$5,$B$1) -> 0
A59: Shareholder's Funds | B59: QTRB_SHAREHODERS_FUNDS | C59: =_xll.EQNXTDZ($A$1,$B59,C$5,$B$1) -> 0 | D59: =_xll.EQNXTDZ($A$1,$B59,D$5,$B$1) -> 164.453 | E59: =_xll.EQNXTDZ($A$1,$B59,E$5,$B$1) -> 0 | F59: =_xll.EQNXTDZ($A$1,$B59,F$5,$B$1) -> 172.48 | G59: =_xll.EQNXTDZ($A$1,$B59,G$5,$B$1) -> 0 | H59: =_xll.EQNXTDZ($A$1,$B59,H$5,$B$1) -> 192.709 | I59: =_xll.EQNXTDZ($A$1,$B59,I$5,$B$1) -> 0 | J59: =_xll.EQNXTDZ($A$1,$B59,J$5,$B$1) -> 202.24 | ... BV59: =_xll.EQNXTDZ($A$1,$B59,BV$5,$B$1) -> 0
A60: Minority Interest | B60: QTRB_MINORITY_INTEREST_BS | C60: =_xll.EQNXTDZ($A$1,$B60,C$5,$B$1) -> 0 | D60: =_xll.EQNXTDZ($A$1,$B60,D$5,$B$1) -> 0 | E60: =_xll.EQNXTDZ($A$1,$B60,E$5,$B$1) -> 0 | F60: =_xll.EQNXTDZ($A$1,$B60,F$5,$B$1) -> 0 | G60: =_xll.EQNXTDZ($A$1,$B60,G$5,$B$1) -> 0 | H60: =_xll.EQNXTDZ($A$1,$B60,H$5,$B$1) -> 0 | I60: =_xll.EQNXTDZ($A$1,$B60,I$5,$B$1) -> 0 | J60: =_xll.EQNXTDZ($A$1,$B60,J$5,$B$1) -> 0 | ... BV60: =_xll.EQNXTDZ($A$1,$B60,BV$5,$B$1) -> 0
A61: Long Term Borrowings | B61: QTRB_TOTAL_DEBTS | C61: =_xll.EQNXTDZ($A$1,$B61,C$5,$B$1) -> 0 | D61: =_xll.EQNXTDZ($A$1,$B61,D$5,$B$1) -> 99.499 | E61: =_xll.EQNXTDZ($A$1,$B61,E$5,$B$1) -> 0 | F61: =_xll.EQNXTDZ($A$1,$B61,F$5,$B$1) -> 103.73 | G61: =_xll.EQNXTDZ($A$1,$B61,G$5,$B$1) -> 0 | H61: =_xll.EQNXTDZ($A$1,$B61,H$5,$B$1) -> 101.011 | I61: =_xll.EQNXTDZ($A$1,$B61,I$5,$B$1) -> 0 | J61: =_xll.EQNXTDZ($A$1,$B61,J$5,$B$1) -> 85.95 | ... BV61: =_xll.EQNXTDZ($A$1,$B61,BV$5,$B$1) -> 0
A62: Secured Loans | B62: QTRB_SECURED_LOANS | C62: =_xll.EQNXTDZ($A$1,$B62,C$5,$B$1) -> 0 | D62: =_xll.EQNXTDZ($A$1,$B62,D$5,$B$1) -> 0 | E62: =_xll.EQNXTDZ($A$1,$B62,E$5,$B$1) -> 0 | F62: =_xll.EQNXTDZ($A$1,$B62,F$5,$B$1) -> 0 | G62: =_xll.EQNXTDZ($A$1,$B62,G$5,$B$1) -> 0 | H62: =_xll.EQNXTDZ($A$1,$B62,H$5,$B$1) -> 0 | I62: =_xll.EQNXTDZ($A$1,$B62,I$5,$B$1) -> 0 | J62: =_xll.EQNXTDZ($A$1,$B62,J$5,$B$1) -> 0 | ... BV62: =_xll.EQNXTDZ($A$1,$B62,BV$5,$B$1) -> 0
A63: Unsecured Loans | B63: QTRB_UNSECURED_LOANS_NF | C63: =_xll.EQNXTDZ($A$1,$B63,C$5,$B$1) -> 0 | D63: =_xll.EQNXTDZ($A$1,$B63,D$5,$B$1) -> 99.499 | E63: =_xll.EQNXTDZ($A$1,$B63,E$5,$B$1) -> 0 | F63: =_xll.EQNXTDZ($A$1,$B63,F$5,$B$1) -> 103.73 | G63: =_xll.EQNXTDZ($A$1,$B63,G$5,$B$1) -> 0 | H63: =_xll.EQNXTDZ($A$1,$B63,H$5,$B$1) -> 101.011 | I63: =_xll.EQNXTDZ($A$1,$B63,I$5,$B$1) -> 0 | J63: =_xll.EQNXTDZ($A$1,$B63,J$5,$B$1) -> 85.95 | ... BV63: =_xll.EQNXTDZ($A$1,$B63,BV$5,$B$1) -> 0
A64: Other Long Term Liabilities | B64: QTRB_OTHER_LT_LIABILITIES | C64: =_xll.EQNXTDZ($A$1,$B64,C$5,$B$1) -> 0 | D64: =_xll.EQNXTDZ($A$1,$B64,D$5,$B$1) -> 2.511 | E64: =_xll.EQNXTDZ($A$1,$B64,E$5,$B$1) -> 0 | F64: =_xll.EQNXTDZ($A$1,$B64,F$5,$B$1) -> 5.85 | G64: =_xll.EQNXTDZ($A$1,$B64,G$5,$B$1) -> 0 | H64: =_xll.EQNXTDZ($A$1,$B64,H$5,$B$1) -> 3.548 | I64: =_xll.EQNXTDZ($A$1,$B64,I$5,$B$1) -> 0 | J64: =_xll.EQNXTDZ($A$1,$B64,J$5,$B$1) -> 5.04 | ... BV64: =_xll.EQNXTDZ($A$1,$B64,BV$5,$B$1) -> 0
A65: Long Term Trade Payables | B65: QTRB_LT_TRADE_PAYABLE | C65: =_xll.EQNXTDZ($A$1,$B65,C$5,$B$1) -> 0 | D65: =_xll.EQNXTDZ($A$1,$B65,D$5,$B$1) -> 0 | E65: =_xll.EQNXTDZ($A$1,$B65,E$5,$B$1) -> 0 | F65: =_xll.EQNXTDZ($A$1,$B65,F$5,$B$1) -> 0 | G65: =_xll.EQNXTDZ($A$1,$B65,G$5,$B$1) -> 0 | H65: =_xll.EQNXTDZ($A$1,$B65,H$5,$B$1) -> 0 | I65: =_xll.EQNXTDZ($A$1,$B65,I$5,$B$1) -> 0 | J65: =_xll.EQNXTDZ($A$1,$B65,J$5,$B$1) -> 0 | ... BV65: =_xll.EQNXTDZ($A$1,$B65,BV$5,$B$1) -> 0
A66: Lont Term Provisions | B66: QTRB_LT_PROVISIONS | C66: =_xll.EQNXTDZ($A$1,$B66,C$5,$B$1) -> 0 | D66: =_xll.EQNXTDZ($A$1,$B66,D$5,$B$1) -> 0 | E66: =_xll.EQNXTDZ($A$1,$B66,E$5,$B$1) -> 0 | F66: =_xll.EQNXTDZ($A$1,$B66,F$5,$B$1) -> 0 | G66: =_xll.EQNXTDZ($A$1,$B66,G$5,$B$1) -> 0 | H66: =_xll.EQNXTDZ($A$1,$B66,H$5,$B$1) -> 0 | I66: =_xll.EQNXTDZ($A$1,$B66,I$5,$B$1) -> 0 | J66: =_xll.EQNXTDZ($A$1,$B66,J$5,$B$1) -> 0 | ... BV66: =_xll.EQNXTDZ($A$1,$B66,BV$5,$B$1) -> 0
... A97: Total Assets | B97: QTRB_TOTAL_APPLICATIONS | C97: =_xll.EQNXTDZ($A$1,$B97,C$5,$B$1) -> 0 | D97: =_xll.EQNXTDZ($A$1,$B97,D$5,$B$1) -> 266.463 | E97: =_xll.EQNXTDZ($A$1,$B97,E$5,$B$1) -> 0 | F97: =_xll.EQNXTDZ($A$1,$B97,F$5,$B$1) -> 282.053 | G97: =_xll.EQNXTDZ($A$1,$B97,G$5,$B$1) -> 0 | H97: =_xll.EQNXTDZ($A$1,$B97,H$5,$B$1) -> 297.27 | I97: =_xll.EQNXTDZ($A$1,$B97,I$5,$B$1) -> 0 | J97: =_xll.EQNXTDZ($A$1,$B97,J$5,$B$1) -> 293.23 | ... BV97: =_xll.EQNXTDZ($A$1,$B97,BV$5,$B$1) -> 0

Sheet Annual Raw
A1: 130999 | B1: X | C1: 200103 | D1: 200203 | E1: 200303 | F1: 200403 | G1: 200503 | H1: 200603 | I1: 200703 | J1: 200803 | K1: 200903 | L1: 201003 | M1: 201103 | N1: 201203 | O1: 201303 | P1: 201403 | Q1: 201503 | R1: 201603 | S1: 201703 | T1: 201803 | U1: 201903 | V1: 202003 | W1: 202103 | X1: 202203 | Y1: 202303 | Z1: 202403 | AA1: 202503 | AB1: 202603 | AC1: 202703 | AD1: 202803 | AE1: 202903 | AF1: 203003
A3: Field Description | B3: Field Name
A4: Company Name | B4: CD_COMPNAME | C4: =_xll.EQNXTDZ(A1,B4,"L") -> Balaji Amines Ltd.
A5: Year End | B5: PL_YEAR_END | C5: =_xll.EQNXTDZ($A$1,$B5,C$1,$B$1) -> 200103 | D5: =_xll.EQNXTDZ($A$1,$B5,D$1,$B$1) -> 200203 | E5: =_xll.EQNXTDZ($A$1,$B5,E$1,$B$1) -> 200303 | F5: =_xll.EQNXTDZ($A$1,$B5,F$1,$B$1) -> 200403 | G5: =_xll.EQNXTDZ($A$1,$B5,G$1,$B$1) -> 200503 | H5: =_xll.EQNXTDZ($A$1,$B5,H$1,$B$1) -> 200603 | I5: =_xll.EQNXTDZ($A$1,$B5,I$1,$B$1) -> 200703 | J5: =_xll.EQNXTDZ($A$1,$B5,J$1,$B$1) -> 200803 | ... AF5: =_xll.EQNXTDZ($A$1,$B5,AF$1,$B$1) -> 0
A6: Sales Turnover | B6: PL_TOTAL_GROSS_SALES | C6: =_xll.EQNXTDZ($A$1,$B6,C$1,$B$1) -> 29.322553 | D6: =_xll.EQNXTDZ($A$1,$B6,D$1,$B$1) -> 41.153086 | E6: =_xll.EQNXTDZ($A$1,$B6,E$1,$B$1) -> 50.679308 | F6: =_xll.EQNXTDZ($A$1,$B6,F$1,$B$1) -> 81.990468 | G6: =_xll.EQNXTDZ($A$1,$B6,G$1,$B$1) -> 99.190306 | H6: =_xll.EQNXTDZ($A$1,$B6,H$1,$B$1) -> 145.89401 | I6: =_xll.EQNXTDZ($A$1,$B6,I$1,$B$1) -> 197.29384 | J6: =_xll.EQNXTDZ($A$1,$B6,J$1,$B$1) -> 239.67648 | ... AF6: =_xll.EQNXTDZ($A$1,$B6,AF$1,$B$1) -> 0
A7: Less: Inter divisional transfers | B7: PL_INTER_DIV_TRF | C7: =_xll.EQNXTDZ($A$1,$B7,C$1,$B$1) -> 0 | D7: =_xll.EQNXTDZ($A$1,$B7,D$1,$B$1) -> 0 | E7: =_xll.EQNXTDZ($A$1,$B7,E$1,$B$1) -> 0 | F7: =_xll.EQNXTDZ($A$1,$B7,F$1,$B$1) -> 0 | G7: =_xll.EQNXTDZ($A$1,$B7,G$1,$B$1) -> 0 | H7: =_xll.EQNXTDZ($A$1,$B7,H$1,$B$1) -> 0 | I7: =_xll.EQNXTDZ($A$1,$B7,I$1,$B$1) -> 0 | J7: =_xll.EQNXTDZ($A$1,$B7,J$1,$B$1) -> 0 | ... AF7: =_xll.EQNXTDZ($A$1,$B7,AF$1,$B$1) -> 0
A8: Less: Sales Returns | B8: PL_SALES_RETURN | C8: =_xll.EQNXTDZ($A$1,$B8,C$1,$B$1) -> 0 | D8: =_xll.EQNXTDZ($A$1,$B8,D$1,$B$1) -> 0 | E8: =_xll.EQNXTDZ($A$1,$B8,E$1,$B$1) -> 0 | F8: =_xll.EQNXTDZ($A$1,$B8,F$1,$B$1) -> 0 | G8: =_xll.EQNXTDZ($A$1,$B8,G$1,$B$1) -> 0 | H8: =_xll.EQNXTDZ($A$1,$B8,H$1,$B$1) -> 0 | I8: =_xll.EQNXTDZ($A$1,$B8,I$1,$B$1) -> 0 | J8: =_xll.EQNXTDZ($A$1,$B8,J$1,$B$1) -> 0 | ... AF8: =_xll.EQNXTDZ($A$1,$B8,AF$1,$B$1) -> 0
A9: Less: Excise | B9: PL_EXCISE | C9: =_xll.EQNXTDZ($A$1,$B9,C$1,$B$1) -> 3.1924889 | D9: =_xll.EQNXTDZ($A$1,$B9,D$1,$B$1) -> 4.57874 | E9: =_xll.EQNXTDZ($A$1,$B9,E$1,$B$1) -> 5.5724934 | F9: =_xll.EQNXTDZ($A$1,$B9,F$1,$B$1) -> 11.084474 | G9: =_xll.EQNXTDZ($A$1,$B9,G$1,$B$1) -> 11.463434 | H9: =_xll.EQNXTDZ($A$1,$B9,H$1,$B$1) -> 17.280035 | I9: =_xll.EQNXTDZ($A$1,$B9,I$1,$B$1) -> 21.788731 | J9: =_xll.EQNXTDZ($A$1,$B9,J$1,$B$1) -> 21.856958 | ... AF9: =_xll.EQNXTDZ($A$1,$B9,AF$1,$B$1) -> 0
A10: Net Sales | B10: PL_NET_SALES | C10: =_xll.EQNXTDZ($A$1,$B10,C$1,$B$1) -> 26.130064 | D10: =_xll.EQNXTDZ($A$1,$B10,D$1,$B$1) -> 36.574346 | E10: =_xll.EQNXTDZ($A$1,$B10,E$1,$B$1) -> 45.106815 | F10: =_xll.EQNXTDZ($A$1,$B10,F$1,$B$1) -> 70.905994 | G10: =_xll.EQNXTDZ($A$1,$B10,G$1,$B$1) -> 87.726873 | H10: =_xll.EQNXTDZ($A$1,$B10,H$1,$B$1) -> 128.61398 | I10: =_xll.EQNXTDZ($A$1,$B10,I$1,$B$1) -> 175.50511 | J10: =_xll.EQNXTDZ($A$1,$B10,J$1,$B$1) -> 217.81952 | ... AF10: =_xll.EQNXTDZ($A$1,$B10,AF$1,$B$1) -> 0
A11: Increase/Decrease in Stock | B11: PL_INC_DEC_INVENTORY | C11: =_xll.EQNXTDZ($A$1,$B11,C$1,$B$1) -> -0.4594177 | D11: =_xll.EQNXTDZ($A$1,$B11,D$1,$B$1) -> 0.6528199 | E11: =_xll.EQNXTDZ($A$1,$B11,E$1,$B$1) -> 0.0706961 | F11: =_xll.EQNXTDZ($A$1,$B11,F$1,$B$1) -> -2.8792667 | G11: =_xll.EQNXTDZ($A$1,$B11,G$1,$B$1) -> -4.1421282 | H11: =_xll.EQNXTDZ($A$1,$B11,H$1,$B$1) -> -0.9728324 | I11: =_xll.EQNXTDZ($A$1,$B11,I$1,$B$1) -> -8.98609 | J11: =_xll.EQNXTDZ($A$1,$B11,J$1,$B$1) -> 9.3914083 | ... AF11: =_xll.EQNXTDZ($A$1,$B11,AF$1,$B$1) -> 0
A12: Raw Material Consumed | B12: PL_RAW_MATRS_CONSUMED | C12: =_xll.EQNXTDZ($A$1,$B12,C$1,$B$1) -> 13.941152 | D12: =_xll.EQNXTDZ($A$1,$B12,D$1,$B$1) -> 16.707095 | E12: =_xll.EQNXTDZ($A$1,$B12,E$1,$B$1) -> 22.226833 | F12: =_xll.EQNXTDZ($A$1,$B12,F$1,$B$1) -> 42.588878 | G12: =_xll.EQNXTDZ($A$1,$B12,G$1,$B$1) -> 56.728602 | H12: =_xll.EQNXTDZ($A$1,$B12,H$1,$B$1) -> 77.304028 | I12: =_xll.EQNXTDZ($A$1,$B12,I$1,$B$1) -> 113.90762 | J12: =_xll.EQNXTDZ($A$1,$B12,J$1,$B$1) -> 125.69363 | ... AF12: =_xll.EQNXTDZ($A$1,$B12,AF$1,$B$1) -> 0
A13: Power & Fuel Cost | B13: PL_POWER_FUEL | C13: =_xll.EQNXTDZ($A$1,$B13,C$1,$B$1) -> 3.7361172 | D13: =_xll.EQNXTDZ($A$1,$B13,D$1,$B$1) -> 3.9301357 | E13: =_xll.EQNXTDZ($A$1,$B13,E$1,$B$1) -> 4.7636879 | F13: =_xll.EQNXTDZ($A$1,$B13,F$1,$B$1) -> 7.1645533 | G13: =_xll.EQNXTDZ($A$1,$B13,G$1,$B$1) -> 9.0957375 | H13: =_xll.EQNXTDZ($A$1,$B13,H$1,$B$1) -> 11.449297 | I13: =_xll.EQNXTDZ($A$1,$B13,I$1,$B$1) -> 15.132046 | J13: =_xll.EQNXTDZ($A$1,$B13,J$1,$B$1) -> 17.365087 | ... AF13: =_xll.EQNXTDZ($A$1,$B13,AF$1,$B$1) -> 0
A14: Employee Cost | B14: PL_EMPLOYEES | C14: =_xll.EQNXTDZ($A$1,$B14,C$1,$B$1) -> 0.8771284 | D14: =_xll.EQNXTDZ($A$1,$B14,D$1,$B$1) -> 0.9991958 | E14: =_xll.EQNXTDZ($A$1,$B14,E$1,$B$1) -> 1.1901778 | F14: =_xll.EQNXTDZ($A$1,$B14,F$1,$B$1) -> 1.6467427 | G14: =_xll.EQNXTDZ($A$1,$B14,G$1,$B$1) -> 2.2550053 | H14: =_xll.EQNXTDZ($A$1,$B14,H$1,$B$1) -> 2.9508445 | I14: =_xll.EQNXTDZ($A$1,$B14,I$1,$B$1) -> 3.4899674 | J14: =_xll.EQNXTDZ($A$1,$B14,J$1,$B$1) -> 4.0490099 | ... AF14: =_xll.EQNXTDZ($A$1,$B14,AF$1,$B$1) -> 0
A15: Operating & Manufacturing Expenses | B15: PL_GEN_OTHER_MFG_EXPS | C15: =_xll.EQNXTDZ($A$1,$B15,C$1,$B$1) -> 1.6168982 | D15: =_xll.EQNXTDZ($A$1,$B15,D$1,$B$1) -> 2.4421327 | E15: =_xll.EQNXTDZ($A$1,$B15,E$1,$B$1) -> 3.6772316 | F15: =_xll.EQNXTDZ($A$1,$B15,F$1,$B$1) -> 4.4617804 | G15: =_xll.EQNXTDZ($A$1,$B15,G$1,$B$1) -> 6.3403451 | H15: =_xll.EQNXTDZ($A$1,$B15,H$1,$B$1) -> 9.6007268 | I15: =_xll.EQNXTDZ($A$1,$B15,I$1,$B$1) -> 13.704348 | J15: =_xll.EQNXTDZ($A$1,$B15,J$1,$B$1) -> 16.88892 | ... AF15: =_xll.EQNXTDZ($A$1,$B15,AF$1,$B$1) -> 0
A16: Cost of Software development | B16: PL_COST_SW | C16: =_xll.EQNXTDZ($A$1,$B16,C$1,$B$1) -> 0 | D16: =_xll.EQNXTDZ($A$1,$B16,D$1,$B$1) -> 0 | E16: =_xll.EQNXTDZ($A$1,$B16,E$1,$B$1) -> 0 | F16: =_xll.EQNXTDZ($A$1,$B16,F$1,$B$1) -> 0 | G16: =_xll.EQNXTDZ($A$1,$B16,G$1,$B$1) -> 0 | H16: =_xll.EQNXTDZ($A$1,$B16,H$1,$B$1) -> 0 | I16: =_xll.EQNXTDZ($A$1,$B16,I$1,$B$1) -> 0 | J16: =_xll.EQNXTDZ($A$1,$B16,J$1,$B$1) -> 0 | ... AF16: =_xll.EQNXTDZ($A$1,$B16,AF$1,$B$1) -> 0
... A36: Profit After Tax from Discontinued Operations | B36: PL_PAT_DIS_OP | C36: =_xll.EQNXTDZ($A$1,$B36,C$1,$B$1) -> 0 | D36: =_xll.EQNXTDZ($A$1,$B36,D$1,$B$1) -> 0 | E36: =_xll.EQNXTDZ($A$1,$B36,E$1,$B$1) -> 0 | F36: =_xll.EQNXTDZ($A$1,$B36,F$1,$B$1) -> 0 | G36: =_xll.EQNXTDZ($A$1,$B36,G$1,$B$1) -> 0 | H36: =_xll.EQNXTDZ($A$1,$B36,H$1,$B$1) -> 0 | I36: =_xll.EQNXTDZ($A$1,$B36,I$1,$B$1) -> 0 | J36: =_xll.EQNXTDZ($A$1,$B36,J$1,$B$1) -> 0 | ... AF36: =_xll.EQNXTDZ($A$1,$B36,AF$1,$B$1) -> 0
A39: Field Description | B39: Field Name
A40: Year End | B40: BS_YEAR_END | C40: =_xll.EQNXTDZ($A$1,$B40,C$1,$B$1) -> 200103 | D40: =_xll.EQNXTDZ($A$1,$B40,D$1,$B$1) -> 200203 | E40: =_xll.EQNXTDZ($A$1,$B40,E$1,$B$1) -> 200303 | F40: =_xll.EQNXTDZ($A$1,$B40,F$1,$B$1) -> 200403 | G40: =_xll.EQNXTDZ($A$1,$B40,G$1,$B$1) -> 200503 | H40: =_xll.EQNXTDZ($A$1,$B40,H$1,$B$1) -> 200603 | I40: =_xll.EQNXTDZ($A$1,$B40,I$1,$B$1) -> 200703 | J40: =_xll.EQNXTDZ($A$1,$B40,J$1,$B$1) -> 200803 | ... AF40: =_xll.EQNXTDZ($A$1,$B40,AF$1,$B$1) -> 0
A41: Share Capital | B41: BS_SHARE_CAPITAL | C41: =_xll.EQNXTDZ($A$1,$B41,C$1,$B$1) -> 2.9838 | D41: =_xll.EQNXTDZ($A$1,$B41,D$1,$B$1) -> 2.9838 | E41: =_xll.EQNXTDZ($A$1,$B41,E$1,$B$1) -> 2.9867 | F41: =_xll.EQNXTDZ($A$1,$B41,F$1,$B$1) -> 3.0001 | G41: =_xll.EQNXTDZ($A$1,$B41,G$1,$B$1) -> 3.0001 | H41: =_xll.EQNXTDZ($A$1,$B41,H$1,$B$1) -> 3.0001 | I41: =_xll.EQNXTDZ($A$1,$B41,I$1,$B$1) -> 6.4802 | J41: =_xll.EQNXTDZ($A$1,$B41,J$1,$B$1) -> 6.4802 | ... AF41: =_xll.EQNXTDZ($A$1,$B41,AF$1,$B$1) -> 0
A42: Share Warrants & Outstandings | B42: BS_SHAREWROUTST | C42: =_xll.EQNXTDZ($A$1,$B42,C$1,$B$1) -> 0 | D42: =_xll.EQNXTDZ($A$1,$B42,D$1,$B$1) -> 0 | E42: =_xll.EQNXTDZ($A$1,$B42,E$1,$B$1) -> 0 | F42: =_xll.EQNXTDZ($A$1,$B42,F$1,$B$1) -> 0 | G42: =_xll.EQNXTDZ($A$1,$B42,G$1,$B$1) -> 0.3048 | H42: =_xll.EQNXTDZ($A$1,$B42,H$1,$B$1) -> 0.3048 | I42: =_xll.EQNXTDZ($A$1,$B42,I$1,$B$1) -> 0 | J42: =_xll.EQNXTDZ($A$1,$B42,J$1,$B$1) -> 0 | ... AF42: =_xll.EQNXTDZ($A$1,$B42,AF$1,$B$1) -> 0
A43: Total Reserves | B43: BS_RESERVE | C43: =_xll.EQNXTDZ($A$1,$B43,C$1,$B$1) -> 8.35463 | D43: =_xll.EQNXTDZ($A$1,$B43,D$1,$B$1) -> 9.1170689 | E43: =_xll.EQNXTDZ($A$1,$B43,E$1,$B$1) -> 12.391534 | F43: =_xll.EQNXTDZ($A$1,$B43,F$1,$B$1) -> 18.555561 | G43: =_xll.EQNXTDZ($A$1,$B43,G$1,$B$1) -> 22.12634 | H43: =_xll.EQNXTDZ($A$1,$B43,H$1,$B$1) -> 29.200859 | I43: =_xll.EQNXTDZ($A$1,$B43,I$1,$B$1) -> 37.689778 | J43: =_xll.EQNXTDZ($A$1,$B43,J$1,$B$1) -> 49.57069 | ... AF43: =_xll.EQNXTDZ($A$1,$B43,AF$1,$B$1) -> 0
A44: Shareholder's Funds | B44: BS_SHAREHODERS_FUNDS | C44: =_xll.EQNXTDZ($A$1,$B44,C$1,$B$1) -> 11.33843 | D44: =_xll.EQNXTDZ($A$1,$B44,D$1,$B$1) -> 12.100869 | E44: =_xll.EQNXTDZ($A$1,$B44,E$1,$B$1) -> 15.378234 | F44: =_xll.EQNXTDZ($A$1,$B44,F$1,$B$1) -> 21.555661 | G44: =_xll.EQNXTDZ($A$1,$B44,G$1,$B$1) -> 25.43124 | H44: =_xll.EQNXTDZ($A$1,$B44,H$1,$B$1) -> 32.505759 | I44: =_xll.EQNXTDZ($A$1,$B44,I$1,$B$1) -> 44.169978 | J44: =_xll.EQNXTDZ($A$1,$B44,J$1,$B$1) -> 56.05089 | ... AF44: =_xll.EQNXTDZ($A$1,$B44,AF$1,$B$1) -> 0
A45: Minority Interest | B45: BS_MINORITY_INTEREST | C45: =_xll.EQNXTDZ($A$1,$B45,C$1,$B$1) -> 0 | D45: =_xll.EQNXTDZ($A$1,$B45,D$1,$B$1) -> 0 | E45: =_xll.EQNXTDZ($A$1,$B45,E$1,$B$1) -> 0 | F45: =_xll.EQNXTDZ($A$1,$B45,F$1,$B$1) -> 0 | G45: =_xll.EQNXTDZ($A$1,$B45,G$1,$B$1) -> 0 | H45: =_xll.EQNXTDZ($A$1,$B45,H$1,$B$1) -> 0 | I45: =_xll.EQNXTDZ($A$1,$B45,I$1,$B$1) -> 0 | J45: =_xll.EQNXTDZ($A$1,$B45,J$1,$B$1) -> 0 | ... AF45: =_xll.EQNXTDZ($A$1,$B45,AF$1,$B$1) -> 0
A46: Long-Term Borrowings | B46: BS_LTRM_BORROWING | C46: =_xll.EQNXTDZ($A$1,$B46,C$1,$B$1) -> 0 | D46: =_xll.EQNXTDZ($A$1,$B46,D$1,$B$1) -> 0 | E46: =_xll.EQNXTDZ($A$1,$B46,E$1,$B$1) -> 0 | F46: =_xll.EQNXTDZ($A$1,$B46,F$1,$B$1) -> 0 | G46: =_xll.EQNXTDZ($A$1,$B46,G$1,$B$1) -> 0 | H46: =_xll.EQNXTDZ($A$1,$B46,H$1,$B$1) -> 0 | I46: =_xll.EQNXTDZ($A$1,$B46,I$1,$B$1) -> 0 | J46: =_xll.EQNXTDZ($A$1,$B46,J$1,$B$1) -> 0 | ... AF46: =_xll.EQNXTDZ($A$1,$B46,AF$1,$B$1) -> 0
A47: Secured Loans | B47: BS_SECURED_LOANS | C47: =_xll.EQNXTDZ($A$1,$B47,C$1,$B$1) -> 13.220693 | D47: =_xll.EQNXTDZ($A$1,$B47,D$1,$B$1) -> 11.575736 | E47: =_xll.EQNXTDZ($A$1,$B47,E$1,$B$1) -> 21.37132 | F47: =_xll.EQNXTDZ($A$1,$B47,F$1,$B$1) -> 31.580915 | G47: =_xll.EQNXTDZ($A$1,$B47,G$1,$B$1) -> 36.160241 | H47: =_xll.EQNXTDZ($A$1,$B47,H$1,$B$1) -> 53.541066 | I47: =_xll.EQNXTDZ($A$1,$B47,I$1,$B$1) -> 66.417643 | J47: =_xll.EQNXTDZ($A$1,$B47,J$1,$B$1) -> 83.414495 | ... AF47: =_xll.EQNXTDZ($A$1,$B47,AF$1,$B$1) -> 0
A48: Unsecured Loans | B48: BS_UNSECURED_LOANS_NF | C48: =_xll.EQNXTDZ($A$1,$B48,C$1,$B$1) -> 2.9953581 | D48: =_xll.EQNXTDZ($A$1,$B48,D$1,$B$1) -> 2.3263864 | E48: =_xll.EQNXTDZ($A$1,$B48,E$1,$B$1) -> 3.2937626 | F48: =_xll.EQNXTDZ($A$1,$B48,F$1,$B$1) -> 3.0320484 | G48: =_xll.EQNXTDZ($A$1,$B48,G$1,$B$1) -> 5.2589774 | H48: =_xll.EQNXTDZ($A$1,$B48,H$1,$B$1) -> 0 | I48: =_xll.EQNXTDZ($A$1,$B48,I$1,$B$1) -> 0 | J48: =_xll.EQNXTDZ($A$1,$B48,J$1,$B$1) -> 0 | ... AF48: =_xll.EQNXTDZ($A$1,$B48,AF$1,$B$1) -> 0
A49: Deferred Tax Assets / Liabilities | B49: BS_NET_DEF_TAX_NF | C49: =_xll.EQNXTDZ($A$1,$B49,C$1,$B$1) -> 0 | D49: =_xll.EQNXTDZ($A$1,$B49,D$1,$B$1) -> 3.9040728 | E49: =_xll.EQNXTDZ($A$1,$B49,E$1,$B$1) -> 5.6061584 | F49: =_xll.EQNXTDZ($A$1,$B49,F$1,$B$1) -> 7.8938383 | G49: =_xll.EQNXTDZ($A$1,$B49,G$1,$B$1) -> 8.8953472 | H49: =_xll.EQNXTDZ($A$1,$B49,H$1,$B$1) -> 9.6119544 | I49: =_xll.EQNXTDZ($A$1,$B49,I$1,$B$1) -> 11.778798 | J49: =_xll.EQNXTDZ($A$1,$B49,J$1,$B$1) -> 14.907393 | ... AF49: =_xll.EQNXTDZ($A$1,$B49,AF$1,$B$1) -> 0
A50: Other Long Term Liabilities | B50: BS_OTH_LT_LIAB | C50: =_xll.EQNXTDZ($A$1,$B50,C$1,$B$1) -> 0 | D50: =_xll.EQNXTDZ($A$1,$B50,D$1,$B$1) -> 0 | E50: =_xll.EQNXTDZ($A$1,$B50,E$1,$B$1) -> 0 | F50: =_xll.EQNXTDZ($A$1,$B50,F$1,$B$1) -> 0 | G50: =_xll.EQNXTDZ($A$1,$B50,G$1,$B$1) -> 0 | H50: =_xll.EQNXTDZ($A$1,$B50,H$1,$B$1) -> 0 | I50: =_xll.EQNXTDZ($A$1,$B50,I$1,$B$1) -> 0 | J50: =_xll.EQNXTDZ($A$1,$B50,J$1,$B$1) -> 0 | ... AF50: =_xll.EQNXTDZ($A$1,$B50,AF$1,$B$1) -> 0
A51: Long Term Trade Payables | B51: BS_LT_TRADE_PAYABLES | C51: =_xll.EQNXTDZ($A$1,$B51,C$1,$B$1) -> 0 | D51: =_xll.EQNXTDZ($A$1,$B51,D$1,$B$1) -> 0 | E51: =_xll.EQNXTDZ($A$1,$B51,E$1,$B$1) -> 0 | F51: =_xll.EQNXTDZ($A$1,$B51,F$1,$B$1) -> 0 | G51: =_xll.EQNXTDZ($A$1,$B51,G$1,$B$1) -> 0 | H51: =_xll.EQNXTDZ($A$1,$B51,H$1,$B$1) -> 0 | I51: =_xll.EQNXTDZ($A$1,$B51,I$1,$B$1) -> 0 | J51: =_xll.EQNXTDZ($A$1,$B51,J$1,$B$1) -> 0 | ... AF51: =_xll.EQNXTDZ($A$1,$B51,AF$1,$B$1) -> 0
... A99: Estimated Capital Contracts Remaining | B99: BS_ESTIMATED_CAPITAL_CONTRACT | C99: =_xll.EQNXTDZ($A$1,$B99,C$1,$B$1) -> 0 | D99: =_xll.EQNXTDZ($A$1,$B99,D$1,$B$1) -> 0 | E99: =_xll.EQNXTDZ($A$1,$B99,E$1,$B$1) -> 0 | F99: =_xll.EQNXTDZ($A$1,$B99,F$1,$B$1) -> 0 | G99: =_xll.EQNXTDZ($A$1,$B99,G$1,$B$1) -> 0 | H99: =_xll.EQNXTDZ($A$1,$B99,H$1,$B$1) -> 0 | I99: =_xll.EQNXTDZ($A$1,$B99,I$1,$B$1) -> 0 | J99: =_xll.EQNXTDZ($A$1,$B99,J$1,$B$1) -> 0 | ... AF99: =_xll.EQNXTDZ($A$1,$B99,AF$1,$B$1) -> 0
A103: Field Description | B103: Field Name
A104: Equity Paid Up | B104: BS_EQUITY_PAIDUP | C104: =_xll.EQNXTDZ($A$1,$B104,C$1,$B$1) -> 2.9838 | D104: =_xll.EQNXTDZ($A$1,$B104,D$1,$B$1) -> 2.9838 | E104: =_xll.EQNXTDZ($A$1,$B104,E$1,$B$1) -> 2.9867 | F104: =_xll.EQNXTDZ($A$1,$B104,F$1,$B$1) -> 3.0001 | G104: =_xll.EQNXTDZ($A$1,$B104,G$1,$B$1) -> 3.0001 | H104: =_xll.EQNXTDZ($A$1,$B104,H$1,$B$1) -> 3.0001 | I104: =_xll.EQNXTDZ($A$1,$B104,I$1,$B$1) -> 6.4802 | J104: =_xll.EQNXTDZ($A$1,$B104,J$1,$B$1) -> 6.4802 | ... AF104: =_xll.EQNXTDZ($A$1,$B104,AF$1,$B$1) -> 0
A105: Face Value | B105: BS_FACE_VALUE | C105: =_xll.EQNXTDZ($A$1,$B105,C$1,$B$1) -> 10 | D105: =_xll.EQNXTDZ($A$1,$B105,D$1,$B$1) -> 10 | E105: =_xll.EQNXTDZ($A$1,$B105,E$1,$B$1) -> 10 | F105: =_xll.EQNXTDZ($A$1,$B105,F$1,$B$1) -> 10 | G105: =_xll.EQNXTDZ($A$1,$B105,G$1,$B$1) -> 10 | H105: =_xll.EQNXTDZ($A$1,$B105,H$1,$B$1) -> 10 | I105: =_xll.EQNXTDZ($A$1,$B105,I$1,$B$1) -> 10 | J105: =_xll.EQNXTDZ($A$1,$B105,J$1,$B$1) -> 10 | ... AF105: =_xll.EQNXTDZ($A$1,$B105,AF$1,$B$1) -> 0
A106: Close Price (Unit Curr.) | B106: FH_YEAR_PRICE | C106: =_xll.EQNXTDZ($A$1,$B106,C$1,$B$1) -> 0 | D106: =_xll.EQNXTDZ($A$1,$B106,D$1,$B$1) -> 0 | E106: =_xll.EQNXTDZ($A$1,$B106,E$1,$B$1) -> 2.8 | F106: =_xll.EQNXTDZ($A$1,$B106,F$1,$B$1) -> 11.67 | G106: =_xll.EQNXTDZ($A$1,$B106,G$1,$B$1) -> 33.025 | H106: =_xll.EQNXTDZ($A$1,$B106,H$1,$B$1) -> 21.71 | I106: =_xll.EQNXTDZ($A$1,$B106,I$1,$B$1) -> 26.22 | J106: =_xll.EQNXTDZ($A$1,$B106,J$1,$B$1) -> 22 | ... AF106: =_xll.EQNXTDZ($A$1,$B106,AF$1,$B$1) -> 0
A107: High Price (Unit Curr.) | B107: FH_HIGH | C107: =_xll.EQNXTDZ($A$1,$B107,C$1,$B$1) -> 0 | D107: =_xll.EQNXTDZ($A$1,$B107,D$1,$B$1) -> 0 | E107: =_xll.EQNXTDZ($A$1,$B107,E$1,$B$1) -> 4.975 | F107: =_xll.EQNXTDZ($A$1,$B107,F$1,$B$1) -> 15.49 | G107: =_xll.EQNXTDZ($A$1,$B107,G$1,$B$1) -> 39.1 | H107: =_xll.EQNXTDZ($A$1,$B107,H$1,$B$1) -> 52.49 | I107: =_xll.EQNXTDZ($A$1,$B107,I$1,$B$1) -> 42.5 | J107: =_xll.EQNXTDZ($A$1,$B107,J$1,$B$1) -> 47.4 | ... AF107: =_xll.EQNXTDZ($A$1,$B107,AF$1,$B$1) -> 0
A108: Low Price (Unit Curr.) | B108: FH_LOW | C108: =_xll.EQNXTDZ($A$1,$B108,C$1,$B$1) -> 0 | D108: =_xll.EQNXTDZ($A$1,$B108,D$1,$B$1) -> 0 | E108: =_xll.EQNXTDZ($A$1,$B108,E$1,$B$1) -> 1.8 | F108: =_xll.EQNXTDZ($A$1,$B108,F$1,$B$1) -> 2.41 | G108: =_xll.EQNXTDZ($A$1,$B108,G$1,$B$1) -> 8 | H108: =_xll.EQNXTDZ($A$1,$B108,H$1,$B$1) -> 17 | I108: =_xll.EQNXTDZ($A$1,$B108,I$1,$B$1) -> 15.5 | J108: =_xll.EQNXTDZ($A$1,$B108,J$1,$B$1) -> 18.3 | ... AF108: =_xll.EQNXTDZ($A$1,$B108,AF$1,$B$1) -> 0
A109: Market Capitalization | B109: FH_MCAP | C109: =_xll.EQNXTDZ($A$1,$B109,C$1,$B$1) -> 0 | D109: =_xll.EQNXTDZ($A$1,$B109,D$1,$B$1) -> 0 | E109: =_xll.EQNXTDZ($A$1,$B109,E$1,$B$1) -> 8.36276 | F109: =_xll.EQNXTDZ($A$1,$B109,F$1,$B$1) -> 35.011167 | G109: =_xll.EQNXTDZ($A$1,$B109,G$1,$B$1) -> 99.078303 | H109: =_xll.EQNXTDZ($A$1,$B109,H$1,$B$1) -> 65.132171 | I109: =_xll.EQNXTDZ($A$1,$B109,I$1,$B$1) -> 84.955422 | J109: =_xll.EQNXTDZ($A$1,$B109,J$1,$B$1) -> 71.2822 | ... AF109: =_xll.EQNXTDZ($A$1,$B109,AF$1,$B$1) -> 0
A110: Adj DPS(Rs) | B110: FR_ADJ_DPS | C110: =_xll.EQNXTDZ($A$1,$B110,C$1,$B$1) -> 0.1 | D110: =_xll.EQNXTDZ($A$1,$B110,D$1,$B$1) -> 0.2 | E110: =_xll.EQNXTDZ($A$1,$B110,E$1,$B$1) -> 0.25 | F110: =_xll.EQNXTDZ($A$1,$B110,F$1,$B$1) -> 0.3 | G110: =_xll.EQNXTDZ($A$1,$B110,G$1,$B$1) -> 0.3 | H110: =_xll.EQNXTDZ($A$1,$B110,H$1,$B$1) -> 0.5 | I110: =_xll.EQNXTDZ($A$1,$B110,I$1,$B$1) -> 0.3 | J110: =_xll.EQNXTDZ($A$1,$B110,J$1,$B$1) -> 0.3 | ... AF110: =_xll.EQNXTDZ($A$1,$B110,AF$1,$B$1) -> 0
A111: Date End | B111: SHP_DATE_END | C111: =_xll.EQNXTDZ($A$1,$B111,C$5) -> 200103 | D111: =_xll.EQNXTDZ($A$1,$B111,D$5) -> 0 | E111: =_xll.EQNXTDZ($A$1,$B111,E$5) -> 0 | F111: =_xll.EQNXTDZ($A$1,$B111,F$5) -> 200403 | G111: =_xll.EQNXTDZ($A$1,$B111,G$5) -> 200503 | H111: =_xll.EQNXTDZ($A$1,$B111,H$5) -> 200603 | I111: =_xll.EQNXTDZ($A$1,$B111,I$5) -> 200703 | J111: =_xll.EQNXTDZ($A$1,$B111,J$5) -> 200803 | ... AF111: =_xll.EQNXTDZ($A$1,$B111,AF$5) -> 0
A112: Total of Promoter and Promoter Group | B112: SHP_TPFTOTALPROMOTER | C112: =_xll.EQNXTDZ($A$1,$B112,C$5) -> 44.44 | D112: =_xll.EQNXTDZ($A$1,$B112,D$5) -> 0 | E112: =_xll.EQNXTDZ($A$1,$B112,E$5) -> 0 | F112: =_xll.EQNXTDZ($A$1,$B112,F$5) -> 42.72 | G112: =_xll.EQNXTDZ($A$1,$B112,G$5) -> 49.75 | H112: =_xll.EQNXTDZ($A$1,$B112,H$5) -> 50.5 | I112: =_xll.EQNXTDZ($A$1,$B112,I$5) -> 53.03 | J112: =_xll.EQNXTDZ($A$1,$B112,J$5) -> 53.91 | ... AF112: =_xll.EQNXTDZ($A$1,$B112,AF$5) -> 0
A113: Total of Promoter and Promoter Group Pledged | B113: SHP_PSHFTOTALPROMOTER | C113: =_xll.EQNXTDZ($A$1,$B113,C$5) -> 0 | D113: =_xll.EQNXTDZ($A$1,$B113,D$5) -> 0 | E113: =_xll.EQNXTDZ($A$1,$B113,E$5) -> 0 | F113: =_xll.EQNXTDZ($A$1,$B113,F$5) -> 0 | G113: =_xll.EQNXTDZ($A$1,$B113,G$5) -> 0 | H113: =_xll.EQNXTDZ($A$1,$B113,H$5) -> 0 | I113: =_xll.EQNXTDZ($A$1,$B113,I$5) -> 0 | J113: =_xll.EQNXTDZ($A$1,$B113,J$5) -> 0 | ... AF113: =_xll.EQNXTDZ($A$1,$B113,AF$5) -> 0

Sheet QTR Share Price
A1: ='QTR Raw'!A1 -> 130999 | C1: 201206 | D1: 201207 | E1: 201208 | F1: 201209 | G1: 201210 | H1: 201211 | I1: 201212 | J1: 201301 | K1: 201302 | L1: 201303 | M1: 201304 | N1: 201305 | O1: 201306 | P1: 201307 | Q1: 201308 | R1: 201309 | S1: 201310 | T1: 201311 | U1: 201312 | V1: 201401 | W1: 201402 | X1: 201403 | Y1: 201404 | Z1: 201405 | AA1: 201406 | AB1: 201407 | AC1: 201408 | AD1: 201409 | AE1: 201410 | AF1: 201411 | AG1: 201412 | AH1: 201501 | AI1: 201502 | AJ1: 201503 | AK1: 201504 | AL1: 201505 | AM1: 201506 | AN1: 201507 | AO1: 201508 | AP1: 201509 | AQ1: 201510 | AR1: 201511 | AS1: 201512 | AT1: 201601 | AU1: 201602 | AV1: 201603 | AW1: 201604 | AX1: 201605 | AY1: 201606 | AZ1: 201607 | BA1: 201608 | BB1: 201609 | BC1: 201610 | BD1: 201611 | BE1: 201612 | BF1: 201701 | BG1: 201702 | BH1: 201703 | BI1: 201704 | BJ1: 201705 | BK1: 201706 | BL1: 201707 | BM1: 201708 | BN1: 201709 | BO1: 201710 | BP1: 201711 | BQ1: 201712 | BR1: 201801 | BS1: 201802 | BT1: 201803 | BU1: 201804 | BV1: 201805 | BW1: 201806 | BX1: 201807 | BY1: 201808 | BZ1: 201809 | CA1: 201810 | CB1: 201811 | CC1: 201812 | CD1: 201901 | CE1: 201902 | CF1: 201903 | CG1: 201904 | CH1: 201905 | CI1: 201906 | CJ1: 201907 | CK1: 201908 | CL1: 201909 | CM1: 201910 | CN1: 201911 | CO1: 201912 | CP1: 202001 | CQ1: 202002 | CR1: 202003 | CS1: 202004 | CT1: 202005 | CU1: 202006 | CV1: 202007 | CW1: 202008 | CX1: 202009 | CY1: 202010 | CZ1: 202011 | DA1: 202012 | DB1: 202101 | DC1: 202102 | DD1: 202103 | DE1: 202104 | DF1: 202105 | DG1: 202106 | DH1: 202107 | DI1: 202108 | DJ1: 202109 | DK1: 202110 | DL1: 202111 | DM1: 202112 | DN1: 202201 | DO1: 202202 | DP1: 202203 | DQ1: 202204 | DR1: 202205 | DS1: 202206 | DT1: 202207 | DU1: 202208 | DV1: 202209 | DW1: 202210 | DX1: 202211 | DY1: 202212 | DZ1: 202301 | EA1: 202302 | EB1: 202303 | EC1: 202304 | ED1: 202305 | EE1: 202306 | EF1: 202307 | EG1: 202308 | EH1: 202309 | EI1: 202310 | EJ1: 202311 | EK1: 202312 | EL1: 202401 | EM1: 202402 | EN1: 202403 | EO1: 202404 | EP1: 202405 | EQ1: 202406 | ER1: 202407 | ES1: 202408 | ET1: 202409 | EU1: 202410 | EV1: 202411 | EW1: 202412 | EX1: 202501 | EY1: 202502 | EZ1: 202503 | FA1: 202504 | FB1: 202505 | FC1: 202506 | FD1: 202507 | FE1: 202508 | FF1: 202509 | FG1: 202510 | FH1: 202511 | FI1: 202512 | FJ1: 202601 | FK1: 202602 | FL1: 202603 | FM1: 202604 | FN1: 202605 | FO1: 202606 | FP1: 202607 | FQ1: 202608 | FR1: 202609 | FS1: 202610 | FT1: 202611 | FU1: 202612 | FV1: 202701 | FW1: 202702 | FX1: 202703 | FY1: 202704 | FZ1: 202705 | GA1: 202706 | GB1: 202707 | GC1: 202708 | GD1: 202709 | GE1: 202710 | GF1: 202711 | GG1: 202712 | GH1: 202801 | GI1: 202802 | GJ1: 202803 | GK1: 202804 | GL1: 202805 | GM1: 202806 | GN1: 202807 | GO1: 202808 | GP1: 202809 | GQ1: 202810 | GR1: 202811 | GS1: 202812 | GT1: 202901 | GU1: 202902 | GV1: 202903 | GW1: 202904 | GX1: 202905 | GY1: 202906 | GZ1: 202907 | HA1: 202908 | HB1: 202909 | HC1: 202910 | HD1: 202911 | HE1: 202912 | HF1: 203001 | HG1: 203002 | HH1: 203003 | HM1: 201206 | HN1: 201207 | HO1: 201208 | HP1: 201209 | HQ1: 201212 | HR1: 201303 | HS1: 201306 | HT1: 201309 | HU1: 201312 | HV1: 201403 | HW1: 201406 | HX1: 201409 | HY1: 201412 | HZ1: 201503 | IA1: 201506 | IB1: 201509 | IC1: 201512 | ID1: 201603 | IE1: 201606 | IF1: 201609 | IG1: 201612 | IH1: 201703 | II1: 201706 | IJ1: 201709 | IK1: 201712 | IL1: 201803 | IM1: 201806 | IN1: 201809 | IO1: 201812 | IP1: 201903 | IQ1: 201906 | IR1: 201909 | IS1: 201912 | IT1: 202003 | IU1: 202006 | IV1: 202009 | IW1: 202012 | IX1: 202103 | IY1: 202106 | IZ1: 202109 | JA1: 202112 | JB1: 202203 | JC1: 202206 | JD1: 202209 | JE1: 202212 | JF1: 202303 | JG1: 202306 | JH1: 202309 | JI1: 202312 | JJ1: 202403 | JK1: 202406 | JL1: 202409 | JM1: 202412 | JN1: 202503 | JO1: 202506 | JP1: 202509 | JQ1: 202512 | JR1: 202603 | JS1: 202606 | JT1: 202609 | JU1: 202612 | JV1: 202703 | JW1: 202706 | JX1: 202709 | JY1: 202712 | JZ1: 202803 | KA1: 202806 | KB1: 202809 | KC1: 202812 | KD1: 202903 | KE1: 202906 | KF1: 202909 | KG1: 202912 | KH1: 203003
FF2: 45901 | FG2: =+EOMONTH(FF2,1) -> 45961 | FH2: =+EOMONTH(FG2,1) -> 45991 | FI2: =+EOMONTH(FH2,1) -> 46022 | FJ2: =+EOMONTH(FI2,1) -> 46053 | FK2: =+EOMONTH(FJ2,1) -> 46081 | FL2: =+EOMONTH(FK2,1) -> 46112 | FM2: =+EOMONTH(FL2,1) -> 46142 | FN2: =+EOMONTH(FM2,1) -> 46173 | ... HH2: =+EOMONTH(HG2,1) -> 47573
A4: Field Description | B4: Field Name
A5: MonthEnd | B5: NMONTH_MONTHEND | C5: {=_xll.EQNXTDZ($A$1,$B5,C$1)} -> 201206 | D5: {=_xll.EQNXTDZ($A$1,$B5,D$1)} -> 201207 | E5: {=_xll.EQNXTDZ($A$1,$B5,E$1)} -> 201208 | F5: {=_xll.EQNXTDZ($A$1,$B5,F$1)} -> 201209 | G5: {=_xll.EQNXTDZ($A$1,$B5,G$1)} -> 201210 | H5: {=_xll.EQNXTDZ($A$1,$B5,H$1)} -> 201211 | I5: {=_xll.EQNXTDZ($A$1,$B5,I$1)} -> 201212 | J5: {=_xll.EQNXTDZ($A$1,$B5,J$1)} -> 201301 | ... HH5: {=_xll.EQNXTDZ($A$1,$B5,HH$1)} -> 0
A6: Open | B6: NMONTH_OPEN | C6: {=_xll.EQNXTDZ($A$1,$B6,C$1)} -> 36.5 | D6: {=_xll.EQNXTDZ($A$1,$B6,D$1)} -> 38.95 | E6: {=_xll.EQNXTDZ($A$1,$B6,E$1)} -> 42.35 | F6: {=_xll.EQNXTDZ($A$1,$B6,F$1)} -> 44.5 | G6: {=_xll.EQNXTDZ($A$1,$B6,G$1)} -> 60 | H6: {=_xll.EQNXTDZ($A$1,$B6,H$1)} -> 54 | I6: {=_xll.EQNXTDZ($A$1,$B6,I$1)} -> 54.8 | J6: {=_xll.EQNXTDZ($A$1,$B6,J$1)} -> 55.2 | ... HH6: {=_xll.EQNXTDZ($A$1,$B6,HH$1)} -> 0
A7: High | B7: NMONTH_HIGH | C7: {=_xll.EQNXTDZ($A$1,$B7,C$1)} -> 38.3 | D7: {=_xll.EQNXTDZ($A$1,$B7,D$1)} -> 44 | E7: {=_xll.EQNXTDZ($A$1,$B7,E$1)} -> 48.9 | F7: {=_xll.EQNXTDZ($A$1,$B7,F$1)} -> 60 | G7: {=_xll.EQNXTDZ($A$1,$B7,G$1)} -> 66.85 | H7: {=_xll.EQNXTDZ($A$1,$B7,H$1)} -> 59.1 | I7: {=_xll.EQNXTDZ($A$1,$B7,I$1)} -> 59.7 | J7: {=_xll.EQNXTDZ($A$1,$B7,J$1)} -> 56.75 | ... HH7: {=_xll.EQNXTDZ($A$1,$B7,HH$1)} -> 0 | HP7: =+MAX(D7:F7) -> 60 | HQ7: =+MAX(G7:I7) -> 66.85 | HR7: =+MAX(J7:L7) -> 56.75 | HS7: =+MAX(M7:O7) -> 41.75 | HT7: =+MAX(P7:R7) -> 41 | HU7: =+MAX(S7:U7) -> 54.8 | HV7: =+MAX(V7:X7) -> 54.45 | HW7: =+MAX(Y7:AA7) -> 65.95 | HX7: =+MAX(AB7:AD7) -> 99.25 | HY7: =+MAX(AE7:AG7) -> 87.8 | HZ7: =+MAX(AH7:AJ7) -> 89.55 | IA7: =+MAX(AK7:AM7) -> 129 | IB7: =+MAX(AN7:AP7) -> 164 | IC7: =+MAX(AQ7:AS7) -> 168 | ID7: =+MAX(AT7:AV7) -> 184.8 | IE7: =+MAX(AW7:AY7) -> 282.5 | IF7: =+MAX(AZ7:BB7) -> 328.8 | IG7: =+MAX(BC7:BE7) -> 380.05 | IH7: =+MAX(BF7:BH7) -> 401.8 | II7: =+MAX(BI7:BK7) -> 399.8 | IJ7: =+MAX(BL7:BN7) -> 391.95 | IK7: =+MAX(BO7:BQ7) -> 675 | IL7: =+MAX(BR7:BT7) -> 782 | IM7: =+MAX(BU7:BW7) -> 730 | IN7: =+MAX(BX7:BZ7) -> 603 | IO7: =+MAX(CA7:CC7) -> 518.35 | IP7: =+MAX(CD7:CF7) -> 509.45 | IQ7: =+MAX(CG7:CI7) -> 537.6 | IR7: =+MAX(CJ7:CL7) -> 382 | IS7: =+MAX(CM7:CO7) -> 416.7 | IT7: =+MAX(CP7:CR7) -> 489.2 | IU7: =+MAX(CS7:CU7) -> 543.7 | IV7: =+MAX(CV7:CX7) -> 994.8 | IW7: =+MAX(CY7:DA7) -> 1054.55 | IX7: =+MAX(DB7:DD7) -> 1905.55 | IY7: =+MAX(DE7:DG7) -> 2957.8 | IZ7: =+MAX(DH7:DJ7) -> 5223.55 | JA7: =+MAX(DK7:DM7) -> 4805 | JB7: =+MAX(DN7:DP7) -> 3935 | JC7: =+MAX(DQ7:DS7) -> 3504 | JD7: =+MAX(DT7:DV7) -> 3844 | JE7: =+MAX(DW7:DY7) -> 3265 | JF7: =+MAX(DZ7:EB7) -> 2729.85 | JG7: =+MAX(EC7:EE7) -> 2546.95 | JH7: =+MAX(EF7:EH7) -> 2356.65 | JI7: =+MAX(EI7:EK7) -> 2725 | JJ7: =+MAX(EL7:EN7) -> 2735 | JK7: =MAX(EO7:EQ7) -> 2507 | JL7: =MAX(ER7:ET7) -> 2549.75 | JM7: =MAX(EU7:EW7) -> 2374 | JN7: =MAX(EX7:EZ7) -> 1980 | JO7: =MAX(FA7:FC7) -> 1858 | JP7: =MAX(FD7:FF7) -> 1945 | JQ7: =MAX(FG7:FI7) -> 1457.9 | JR7: =MAX(FJ7:FL7) -> 1333.1 | JS7: =MAX(FM7:FO7) -> 2262.5 | JT7: =MAX(FP7:FR7) -> 0 | JU7: =MAX(FS7:FU7) -> 0 | JV7: =MAX(FV7:FX7) -> 0 | JW7: =MAX(FY7:GA7) -> 0 | JX7: =MAX(GB7:GD7) -> 0 | JY7: =MAX(GE7:GG7) -> 0 | JZ7: =MAX(GH7:GJ7) -> 0 | KA7: =MAX(GK7:GM7) -> 0 | KB7: =MAX(GN7:GP7) -> 0 | KC7: =MAX(GQ7:GS7) -> 0 | KD7: =MAX(GT7:GV7) -> 0 | KE7: =MAX(GW7:GY7) -> 0 | KF7: =MAX(GZ7:HB7) -> 0 | KG7: =MAX(HC7:HE7) -> 0 | KH7: =MAX(HF7:HH7) -> 0
A8: Low | B8: NMONTH_LOW | C8: {=_xll.EQNXTDZ($A$1,$B8,C$1)} -> 35 | D8: {=_xll.EQNXTDZ($A$1,$B8,D$1)} -> 38.5 | E8: {=_xll.EQNXTDZ($A$1,$B8,E$1)} -> 38 | F8: {=_xll.EQNXTDZ($A$1,$B8,F$1)} -> 43.9 | G8: {=_xll.EQNXTDZ($A$1,$B8,G$1)} -> 48.65 | H8: {=_xll.EQNXTDZ($A$1,$B8,H$1)} -> 49.25 | I8: {=_xll.EQNXTDZ($A$1,$B8,I$1)} -> 52 | J8: {=_xll.EQNXTDZ($A$1,$B8,J$1)} -> 45.7 | ... HH8: {=_xll.EQNXTDZ($A$1,$B8,HH$1)} -> 0 | HP8: =+MIN(D8:F8) -> 38 | HQ8: =+MIN(G8:I8) -> 48.65 | HR8: =+MIN(J8:L8) -> 34.1 | HS8: =+MIN(M8:O8) -> 30.6 | HT8: =+MIN(P8:R8) -> 28.05 | HU8: =+MIN(S8:U8) -> 31 | HV8: =+MIN(V8:X8) -> 33.8 | HW8: =+MIN(Y8:AA8) -> 39.75 | HX8: =+MIN(AB8:AD8) -> 60.6 | HY8: =+MIN(AE8:AG8) -> 66.7 | HZ8: =+MIN(AH8:AJ8) -> 68.7 | IA8: =+MIN(AK8:AM8) -> 81 | IB8: =+MIN(AN8:AP8) -> 103.9 | IC8: =+MIN(AQ8:AS8) -> 121 | ID8: =+MIN(AT8:AV8) -> 114 | IE8: =+MIN(AW8:AY8) -> 174 | IF8: =+MIN(AZ8:BB8) -> 249.75 | IG8: =+MIN(BC8:BE8) -> 273.1 | IH8: =+MIN(BF8:BH8) -> 314.8 | II8: =+MIN(BI8:BK8) -> 325 | IJ8: =+MIN(BL8:BN8) -> 294 | IK8: =+MIN(BO8:BQ8) -> 333.3 | IL8: =+MIN(BR8:BT8) -> 550 | IM8: =+MIN(BU8:BW8) -> 506.85 | IN8: =+MIN(BX8:BZ8) -> 456.75 | IO8: =+MIN(CA8:CC8) -> 410 | IP8: =+MIN(CD8:CF8) -> 366.1 | IQ8: =+MIN(CG8:CI8) -> 365.15 | IR8: =+MIN(CJ8:CL8) -> 211.25 | IS8: =+MIN(CM8:CO8) -> 300 | IT8: =+MIN(CP8:CR8) -> 200 | IU8: =+MIN(CS8:CU8) -> 241.3 | IV8: =+MIN(CV8:CX8) -> 495 | IW8: =+MIN(CY8:DA8) -> 795 | IX8: =+MIN(DB8:DD8) -> 927.05 | IY8: =+MIN(DE8:DG8) -> 1725.05 | IZ8: =+MIN(DH8:DJ8) -> 2670 | JA8: =+MIN(DK8:DM8) -> 2885.2 | JB8: =+MIN(DN8:DP8) -> 2692.75 | JC8: =+MIN(DQ8:DS8) -> 2700 | JD8: =+MIN(DT8:DV8) -> 2831.7 | JE8: =+MIN(DW8:DY8) -> 2593.75 | JF8: =+MIN(DZ8:EB8) -> 1932.1 | JG8: =+MIN(EC8:EE8) -> 1880 | JH8: =+MIN(EF8:EH8) -> 2002.25 | JI8: =+MIN(EI8:EK8) -> 2000 | JJ8: =+MIN(EL8:EN8) -> 2009.2 | JK8: =MIN(EO8:EQ8) -> 1960 | JL8: =MIN(ER8:ET8) -> 2089.25 | JM8: =MIN(EU8:EW8) -> 1711.4 | JN8: =MIN(EX8:EZ8) -> 1171 | JO8: =MIN(FA8:FC8) -> 1127.55 | JP8: =MIN(FD8:FF8) -> 1383.5 | JQ8: =MIN(FG8:FI8) -> 1079 | JR8: =MIN(FJ8:FL8) -> 968.1 | JS8: =MIN(FM8:FO8) -> 988.5 | JT8: =MIN(FP8:FR8) -> 0 | JU8: =MIN(FS8:FU8) -> 0 | JV8: =MIN(FV8:FX8) -> 0 | JW8: =MIN(FY8:GA8) -> 0 | JX8: =MIN(GB8:GD8) -> 0 | JY8: =MIN(GE8:GG8) -> 0 | JZ8: =MIN(GH8:GJ8) -> 0 | KA8: =MIN(GK8:GM8) -> 0 | KB8: =MIN(GN8:GP8) -> 0 | KC8: =MIN(GQ8:GS8) -> 0 | KD8: =MIN(GT8:GV8) -> 0 | KE8: =MIN(GW8:GY8) -> 0 | KF8: =MIN(GZ8:HB8) -> 0 | KG8: =MIN(HC8:HE8) -> 0 | KH8: =MIN(HF8:HH8) -> 0
A9: Close | B9: NMONTH_CLOSE | C9: {=_xll.EQNXTDZ($A$1,$B9,C$1)} -> 37.85 | D9: {=_xll.EQNXTDZ($A$1,$B9,D$1)} -> 41.9 | E9: {=_xll.EQNXTDZ($A$1,$B9,E$1)} -> 44.95 | F9: {=_xll.EQNXTDZ($A$1,$B9,F$1)} -> 59.05 | G9: {=_xll.EQNXTDZ($A$1,$B9,G$1)} -> 54.2 | H9: {=_xll.EQNXTDZ($A$1,$B9,H$1)} -> 53.2 | I9: {=_xll.EQNXTDZ($A$1,$B9,I$1)} -> 54.05 | J9: {=_xll.EQNXTDZ($A$1,$B9,J$1)} -> 47.75 | ... HH9: {=_xll.EQNXTDZ($A$1,$B9,HH$1)} -> 0 | HP9: =+F9 -> 59.05 | HQ9: =+I9 -> 54.05 | HR9: =+L9 -> 35 | HS9: =+O9 -> 33.25 | HT9: =+R9 -> 32.45 | HU9: =+U9 -> 49.7 | HV9: =+X9 -> 40.25 | HW9: =+AA9 -> 60.85 | HX9: =+AD9 -> 79 | HY9: =+AG9 -> 70.9 | HZ9: =+AJ9 -> 82 | IA9: =+AM9 -> 115.9 | IB9: =+AP9 -> 126.35 | IC9: =+AS9 -> 163.85 | ID9: =+AV9 -> 178.1 | IE9: =+AY9 -> 277.7 | IF9: =+BB9 -> 297.45 | IG9: =+BE9 -> 321.15 | IH9: =+BH9 -> 378.95 | II9: =+BK9 -> 337.25 | IJ9: =+BN9 -> 339.25 | IK9: =+BQ9 -> 637.35 | IL9: =+BT9 -> 561.05 | IM9: =+BW9 -> 551 | IN9: =+BZ9 -> 469 | IO9: =+CC9 -> 457.45 | IP9: =+CF9 -> 495.7 | IQ9: =+CI9 -> 378.4 | IR9: =+CL9 -> 331.85 | IS9: =+CO9 -> 399.3 | IT9: =+CR9 -> 251.6 | IU9: =+CU9 -> 493.4 | IV9: =+CX9 -> 807.4 | IW9: =+DA9 -> 926.4 | IX9: =+DD9 -> 1759.3 | IY9: =+DG9 -> 2673.8 | IZ9: =+DJ9 -> 4517.4 | JA9: =+DM9 -> 3409.8 | JB9: =+DP9 -> 2905.5 | JC9: =+DS9 -> 2867.3 | JD9: =+DV9 -> 3167.5 | JE9: =+DY9 -> 2708.8 | JF9: =+EB9 -> 1943.3 | JG9: =+EE9 -> 2316.55 | JH9: =+EH9 -> 2174.25 | JI9: =+EK9 -> 2668.5 | JJ9: =+EN9 -> 2045.25 | JK9: =EQ9 -> 2289.55 | JL9: =ET9 -> 2287.05 | JM9: =EW9 -> 1786.7 | JN9: =EZ9 -> 1207.15 | JO9: =FC9 -> 1841.6 | JP9: =FF9 -> 1389.2 | JQ9: =FI9 -> 1121 | JR9: =FL9 -> 977.2 | JS9: =FO9 -> 2076.5 | JT9: =FR9 -> 0 | JU9: =FU9 -> 0 | JV9: =FX9 -> 0 | JW9: =GA9 -> 0 | JX9: =GD9 -> 0 | JY9: =GG9 -> 0 | JZ9: =GJ9 -> 0 | KA9: =GM9 -> 0 | KB9: =GP9 -> 0 | KC9: =GS9 -> 0 | KD9: =GV9 -> 0 | KE9: =GY9 -> 0 | KF9: =HB9 -> 0 | KG9: =HE9 -> 0 | KH9: =HH9 -> 0
A11: Field Description | B11: Field Name | C11: {=_xll.EQNXTDZ($A$1,$B11,C$1)} -> 0 | D11: {=_xll.EQNXTDZ($A$1,$B11,D$1)} -> 0 | E11: {=_xll.EQNXTDZ($A$1,$B11,E$1)} -> 0 | F11: {=_xll.EQNXTDZ($A$1,$B11,F$1)} -> 0 | G11: {=_xll.EQNXTDZ($A$1,$B11,G$1)} -> 0 | H11: {=_xll.EQNXTDZ($A$1,$B11,H$1)} -> 0 | I11: {=_xll.EQNXTDZ($A$1,$B11,I$1)} -> 0 | J11: {=_xll.EQNXTDZ($A$1,$B11,J$1)} -> 0 | ... HH11: {=_xll.EQNXTDZ($A$1,$B11,HH$1)} -> 0
A12: Month End | B12: BMONTH_MONTHEND | C12: {=_xll.EQNXTDZ($A$1,$B12,C$1)} -> 201206 | D12: {=_xll.EQNXTDZ($A$1,$B12,D$1)} -> 201207 | E12: {=_xll.EQNXTDZ($A$1,$B12,E$1)} -> 201208 | F12: {=_xll.EQNXTDZ($A$1,$B12,F$1)} -> 201209 | G12: {=_xll.EQNXTDZ($A$1,$B12,G$1)} -> 201210 | H12: {=_xll.EQNXTDZ($A$1,$B12,H$1)} -> 201211 | I12: {=_xll.EQNXTDZ($A$1,$B12,I$1)} -> 201212 | J12: {=_xll.EQNXTDZ($A$1,$B12,J$1)} -> 201301 | ... HH12: {=_xll.EQNXTDZ($A$1,$B12,HH$1)} -> 0
A13: Open | B13: BMONTH_OPEN | C13: {=_xll.EQNXTDZ($A$1,$B13,C$1)} -> 37 | D13: {=_xll.EQNXTDZ($A$1,$B13,D$1)} -> 38.95 | E13: {=_xll.EQNXTDZ($A$1,$B13,E$1)} -> 41.7 | F13: {=_xll.EQNXTDZ($A$1,$B13,F$1)} -> 45.5 | G13: {=_xll.EQNXTDZ($A$1,$B13,G$1)} -> 59.45 | H13: {=_xll.EQNXTDZ($A$1,$B13,H$1)} -> 54.4 | I13: {=_xll.EQNXTDZ($A$1,$B13,I$1)} -> 55.1 | J13: {=_xll.EQNXTDZ($A$1,$B13,J$1)} -> 55 | ... HH13: {=_xll.EQNXTDZ($A$1,$B13,HH$1)} -> 0
A14: High | B14: BMONTH_HIGH | C14: {=_xll.EQNXTDZ($A$1,$B14,C$1)} -> 38.4 | D14: {=_xll.EQNXTDZ($A$1,$B14,D$1)} -> 43.45 | E14: {=_xll.EQNXTDZ($A$1,$B14,E$1)} -> 49 | F14: {=_xll.EQNXTDZ($A$1,$B14,F$1)} -> 59.65 | G14: {=_xll.EQNXTDZ($A$1,$B14,G$1)} -> 66.7 | H14: {=_xll.EQNXTDZ($A$1,$B14,H$1)} -> 59 | I14: {=_xll.EQNXTDZ($A$1,$B14,I$1)} -> 59 | J14: {=_xll.EQNXTDZ($A$1,$B14,J$1)} -> 56.5 | ... HH14: {=_xll.EQNXTDZ($A$1,$B14,HH$1)} -> 0 | HP14: =+MAX(D14:F14) -> 59.65 | HQ14: =+MAX(G14:I14) -> 66.7 | HR14: =+MAX(J14:L14) -> 56.5 | HS14: =+MAX(M14:O14) -> 41.8 | HT14: =+MAX(P14:R14) -> 41 | HU14: =+MAX(S14:U14) -> 54.8 | HV14: =+MAX(V14:X14) -> 53.9 | HW14: =+MAX(Y14:AA14) -> 65.8 | HX14: =+MAX(AB14:AD14) -> 99 | HY14: =+MAX(AE14:AG14) -> 86.4 | HZ14: =+MAX(AH14:AJ14) -> 89.1 | IA14: =+MAX(AK14:AM14) -> 128.4 | IB14: =+MAX(AN14:AP14) -> 163.6 | IC14: =+MAX(AQ14:AS14) -> 168.4 | ID14: =+MAX(AT14:AV14) -> 184.9 | IE14: =+MAX(AW14:AY14) -> 282.5 | IF14: =+MAX(AZ14:BB14) -> 329 | IG14: =+MAX(BC14:BE14) -> 380 | IH14: =+MAX(BF14:BH14) -> 400 | II14: =+MAX(BI14:BK14) -> 401.1 | IJ14: =+MAX(BL14:BN14) -> 390 | IK14: =+MAX(BO14:BQ14) -> 675 | IL14: =+MAX(BR14:BT14) -> 781 | IM14: =+MAX(BU14:BW14) -> 727.05 | IN14: =+MAX(BX14:BZ14) -> 601.45 | IO14: =+MAX(CA14:CC14) -> 520 | IP14: =+MAX(CD14:CF14) -> 510.75 | IQ14: =+MAX(CG14:CI14) -> 539 | IR14: =+MAX(CJ14:CL14) -> 382.55 | IS14: =+MAX(CM14:CO14) -> 414.8 | IT14: =+MAX(CP14:CR14) -> 486.6 | IU14: =+MAX(CS14:CU14) -> 543.95 | IV14: =+MAX(CV14:CX14) -> 995 | IW14: =+MAX(CY14:DA14) -> 1054 | IX14: =+MAX(DB14:DD14) -> 1905.7 | IY14: =+MAX(DE14:DG14) -> 2959.95 | IZ14: =+MAX(DH14:DJ14) -> 5220 | JA14: =+MAX(DK14:DM14) -> 4799 | JB14: =+MAX(DN14:DP14) -> 3936.95 | JC14: =+MAX(DQ14:DS14) -> 3505 | JD14: =+MAX(DT14:DV14) -> 3841.85 | JE14: =+MAX(DW14:DY14) -> 3267.25 | JF14: =+MAX(DZ14:EB14) -> 2727.65 | JG14: =+MAX(EC14:EE14) -> 2548.7 | JH14: =+MAX(EF14:EH14) -> 2355 | JI14: =+MAX(EI14:EK14) -> 2721.2 | JJ14: =+MAX(EL14:EN14) -> 2736.35 | JK14: =MAX(EO14:EQ14) -> 2508.5 | JL14: =MAX(ER14:ET14) -> 2550.15 | JM14: =MAX(EU14:EW14) -> 2370 | JN14: =MAX(EX14:EZ14) -> 1980 | JO14: =MAX(FA14:FC14) -> 1856.45 | JP14: =MAX(FD14:FF14) -> 1946 | JQ14: =MAX(FG14:FI14) -> 1456 | JR14: =MAX(FJ14:FL14) -> 1333.9 | JS14: =MAX(FM14:FO14) -> 2260 | JT14: =MAX(FP14:FR14) -> 0 | JU14: =MAX(FS14:FU14) -> 0 | JV14: =MAX(FV14:FX14) -> 0 | JW14: =MAX(FY14:GA14) -> 0 | JX14: =MAX(GB14:GD14) -> 0 | JY14: =MAX(GE14:GG14) -> 0 | JZ14: =MAX(GH14:GJ14) -> 0 | KA14: =MAX(GK14:GM14) -> 0 | KB14: =MAX(GN14:GP14) -> 0 | KC14: =MAX(GQ14:GS14) -> 0 | KD14: =MAX(GT14:GV14) -> 0 | KE14: =MAX(GW14:GY14) -> 0 | KF14: =MAX(GZ14:HB14) -> 0 | KG14: =MAX(HC14:HE14) -> 0 | KH14: =MAX(HF14:HH14) -> 0
A15: Low | B15: BMONTH_LOW | C15: {=_xll.EQNXTDZ($A$1,$B15,C$1)} -> 35.7 | D15: {=_xll.EQNXTDZ($A$1,$B15,D$1)} -> 38.1 | E15: {=_xll.EQNXTDZ($A$1,$B15,E$1)} -> 39.9 | F15: {=_xll.EQNXTDZ($A$1,$B15,F$1)} -> 43.65 | G15: {=_xll.EQNXTDZ($A$1,$B15,G$1)} -> 53.55 | H15: {=_xll.EQNXTDZ($A$1,$B15,H$1)} -> 50.05 | I15: {=_xll.EQNXTDZ($A$1,$B15,I$1)} -> 53 | J15: {=_xll.EQNXTDZ($A$1,$B15,J$1)} -> 45.75 | ... HH15: {=_xll.EQNXTDZ($A$1,$B15,HH$1)} -> 0 | HP15: =+MIN(D15:F15) -> 38.1 | HQ15: =+MIN(G15:I15) -> 50.05 | HR15: =+MIN(J15:L15) -> 34.85 | HS15: =+MIN(M15:O15) -> 31.25 | HT15: =+MIN(P15:R15) -> 28.4 | HU15: =+MIN(S15:U15) -> 31.6 | HV15: =+MIN(V15:X15) -> 35.1 | HW15: =+MIN(Y15:AA15) -> 39.5 | HX15: =+MIN(AB15:AD15) -> 61.6 | HY15: =+MIN(AE15:AG15) -> 67 | HZ15: =+MIN(AH15:AJ15) -> 69.1 | IA15: =+MIN(AK15:AM15) -> 80.75 | IB15: =+MIN(AN15:AP15) -> 106 | IC15: =+MIN(AQ15:AS15) -> 119.3 | ID15: =+MIN(AT15:AV15) -> 115 | IE15: =+MIN(AW15:AY15) -> 173.1 | IF15: =+MIN(AZ15:BB15) -> 249.2 | IG15: =+MIN(BC15:BE15) -> 272.95 | IH15: =+MIN(BF15:BH15) -> 310 | II15: =+MIN(BI15:BK15) -> 320 | IJ15: =+MIN(BL15:BN15) -> 271.1 | IK15: =+MIN(BO15:BQ15) -> 337 | IL15: =+MIN(BR15:BT15) -> 547 | IM15: =+MIN(BU15:BW15) -> 506.85 | IN15: =+MIN(BX15:BZ15) -> 457.85 | IO15: =+MIN(CA15:CC15) -> 411.6 | IP15: =+MIN(CD15:CF15) -> 368.5 | IQ15: =+MIN(CG15:CI15) -> 365.1 | IR15: =+MIN(CJ15:CL15) -> 210 | IS15: =+MIN(CM15:CO15) -> 298 | IT15: =+MIN(CP15:CR15) -> 204.1 | IU15: =+MIN(CS15:CU15) -> 241.5 | IV15: =+MIN(CV15:CX15) -> 497.6 | IW15: =+MIN(CY15:DA15) -> 787.1 | IX15: =+MIN(DB15:DD15) -> 928 | IY15: =+MIN(DE15:DG15) -> 1723.95 | IZ15: =+MIN(DH15:DJ15) -> 2672.6 | JA15: =+MIN(DK15:DM15) -> 2880 | JB15: =+MIN(DN15:DP15) -> 2680.05 | JC15: =+MIN(DQ15:DS15) -> 2700 | JD15: =+MIN(DT15:DV15) -> 2838 | JE15: =+MIN(DW15:DY15) -> 2592.1 | JF15: =+MIN(DZ15:EB15) -> 1925.05 | JG15: =+MIN(EC15:EE15) -> 1872.9 | JH15: =+MIN(EF15:EH15) -> 2031 | JI15: =+MIN(EI15:EK15) -> 2002 | JJ15: =+MIN(EL15:EN15) -> 2010 | JK15: =MIN(EO15:EQ15) -> 1965.05 | JL15: =MIN(ER15:ET15) -> 2088.85 | JM15: =MIN(EU15:EW15) -> 1712.2 | JN15: =MIN(EX15:EZ15) -> 1170.75 | JO15: =MIN(FA15:FC15) -> 1112 | JP15: =MIN(FD15:FF15) -> 1386.25 | JQ15: =MIN(FG15:FI15) -> 1079.15 | JR15: =MIN(FJ15:FL15) -> 905.15 | JS15: =MIN(FM15:FO15) -> 990 | JT15: =MIN(FP15:FR15) -> 0 | JU15: =MIN(FS15:FU15) -> 0 | JV15: =MIN(FV15:FX15) -> 0 | JW15: =MIN(FY15:GA15) -> 0 | JX15: =MIN(GB15:GD15) -> 0 | JY15: =MIN(GE15:GG15) -> 0 | JZ15: =MIN(GH15:GJ15) -> 0 | KA15: =MIN(GK15:GM15) -> 0 | KB15: =MIN(GN15:GP15) -> 0 | KC15: =MIN(GQ15:GS15) -> 0 | KD15: =MIN(GT15:GV15) -> 0 | KE15: =MIN(GW15:GY15) -> 0 | KF15: =MIN(GZ15:HB15) -> 0 | KG15: =MIN(HC15:HE15) -> 0 | KH15: =MIN(HF15:HH15) -> 0
A16: Close | B16: BMONTH_CLOSE | C16: {=_xll.EQNXTDZ($A$1,$B16,C$1)} -> 37.9 | D16: {=_xll.EQNXTDZ($A$1,$B16,D$1)} -> 41.7 | E16: {=_xll.EQNXTDZ($A$1,$B16,E$1)} -> 45.1 | F16: {=_xll.EQNXTDZ($A$1,$B16,F$1)} -> 58.95 | G16: {=_xll.EQNXTDZ($A$1,$B16,G$1)} -> 54.15 | H16: {=_xll.EQNXTDZ($A$1,$B16,H$1)} -> 53.4 | I16: {=_xll.EQNXTDZ($A$1,$B16,I$1)} -> 54.1 | J16: {=_xll.EQNXTDZ($A$1,$B16,J$1)} -> 47.15 | ... HH16: {=_xll.EQNXTDZ($A$1,$B16,HH$1)} -> 0 | HP16: =+F16 -> 58.95 | HQ16: =+I16 -> 54.1 | HR16: =+L16 -> 35.2 | HS16: =+O16 -> 33.45 | HT16: =+R16 -> 32.15 | HU16: =+U16 -> 49.8 | HV16: =+X16 -> 39.95 | HW16: =+AA16 -> 60.9 | HX16: =+AD16 -> 78.55 | HY16: =+AG16 -> 70.75 | HZ16: =+AJ16 -> 81.05 | IA16: =+AM16 -> 115.1 | IB16: =+AP16 -> 125.8 | IC16: =+AS16 -> 164.6 | ID16: =+AV16 -> 178.5 | IE16: =+AY16 -> 277.9 | IF16: =+BB16 -> 295.9 | IG16: =+BE16 -> 320.1 | IH16: =+BH16 -> 379.6 | II16: =+BK16 -> 336.3 | IJ16: =+BN16 -> 337.05 | IK16: =+BQ16 -> 636.05 | IL16: =+BT16 -> 562.75 | IM16: =+BW16 -> 549.05 | IN16: =+BZ16 -> 469.5 | IO16: =+CC16 -> 459.35 | IP16: =+CF16 -> 489.1 | IQ16: =+CI16 -> 377.8 | IR16: =+CL16 -> 332.95 | IS16: =+CO16 -> 398.2 | IT16: =+CR16 -> 250.95 | IU16: =+CU16 -> 493.65 | IV16: =+CX16 -> 807.9 | IW16: =+DA16 -> 925.45 | IX16: =+DD16 -> 1762.85 | IY16: =+DG16 -> 2666.85 | IZ16: =+DJ16 -> 4516.1 | JA16: =+DM16 -> 3419.2 | JB16: =+DP16 -> 2902.15 | JC16: =+DS16 -> 2862.95 | JD16: =+DV16 -> 3171.05 | JE16: =+DY16 -> 2707.25 | JF16: =+EB16 -> 1942.65 | JG16: =+EE16 -> 2316.25 | JH16: =+EH16 -> 2173.05 | JI16: =+EK16 -> 2668.4 | JJ16: =+EN16 -> 2043.9 | JK16: =EQ16 -> 2290.65 | JL16: =ET16 -> 2283 | JM16: =EW16 -> 1788 | JN16: =EZ16 -> 1207.25 | JO16: =FC16 -> 1845.4 | JP16: =FF16 -> 1391.35 | JQ16: =FI16 -> 1118.6 | JR16: =FL16 -> 977 | JS16: =FO16 -> 2077.65 | JT16: =FR16 -> 0 | JU16: =FU16 -> 0 | JV16: =FX16 -> 0 | JW16: =GA16 -> 0 | JX16: =GD16 -> 0 | JY16: =GG16 -> 0 | JZ16: =GJ16 -> 0 | KA16: =GM16 -> 0 | KB16: =GP16 -> 0 | KC16: =GS16 -> 0 | KD16: =GV16 -> 0 | KE16: =GY16 -> 0 | KF16: =HB16 -> 0 | KG16: =HE16 -> 0 | KH16: =HH16 -> 0
A19: High | HP19: =+IF(HP14=0,HP7,HP14) -> 59.65 | HQ19: =+IF(HQ14=0,HQ7,HQ14) -> 66.7 | HR19: =+IF(HR14=0,HR7,HR14) -> 56.5 | HS19: =+IF(HS14=0,HS7,HS14) -> 41.8 | HT19: =+IF(HT14=0,HT7,HT14) -> 41 | HU19: =+IF(HU14=0,HU7,HU14) -> 54.8 | HV19: =+IF(HV14=0,HV7,HV14) -> 53.9 | HW19: =+IF(HW14=0,HW7,HW14) -> 65.8 | ... KH19: =+IF(KH14=0,KH7,KH14) -> 0
A20: Low | HP20: =+IF(HP15=0,HP8,HP15) -> 38.1 | HQ20: =+IF(HQ15=0,HQ8,HQ15) -> 50.05 | HR20: =+IF(HR15=0,HR8,HR15) -> 34.85 | HS20: =+IF(HS15=0,HS8,HS15) -> 31.25 | HT20: =+IF(HT15=0,HT8,HT15) -> 28.4 | HU20: =+IF(HU15=0,HU8,HU15) -> 31.6 | HV20: =+IF(HV15=0,HV8,HV15) -> 35.1 | HW20: =+IF(HW15=0,HW8,HW15) -> 39.5 | ... KH20: =+IF(KH15=0,KH8,KH15) -> 0
A21: Close | HP21: =+IF(HP16=0,HP9,HP16) -> 58.95 | HQ21: =+IF(HQ16=0,HQ9,HQ16) -> 54.1 | HR21: =+IF(HR16=0,HR9,HR16) -> 35.2 | HS21: =+IF(HS16=0,HS9,HS16) -> 33.45 | HT21: =+IF(HT16=0,HT9,HT16) -> 32.15 | HU21: =+IF(HU16=0,HU9,HU16) -> 49.8 | HV21: =+IF(HV16=0,HV9,HV16) -> 39.95 | HW21: =+IF(HW16=0,HW9,HW16) -> 60.9 | ... KH21: =+IF(KH16=0,KH9,KH16) -> 0

Sheet QTR No. of Shares
A1: ='QTR Raw'!A1 -> 130999 | C1: 201206 | D1: 201209 | E1: 201212 | F1: 201303 | G1: 201306 | H1: 201309 | I1: 201312 | J1: 201403 | K1: 201406 | L1: 201409 | M1: 201412 | N1: 201503 | O1: 201506 | P1: 201509 | Q1: 201512 | R1: 201603 | S1: 201606 | T1: 201609 | U1: 201612 | V1: 201703 | W1: 201706 | X1: 201709 | Y1: 201712 | Z1: 201803 | AA1: 201806 | AB1: 201809 | AC1: 201812 | AD1: 201903 | AE1: 201906 | AF1: 201909 | AG1: 201912 | AH1: 202003 | AI1: 202006 | AJ1: 202009 | AK1: 202012 | AL1: 202103 | AM1: 202106 | AN1: 202109 | AO1: 202112 | AP1: 202203 | AQ1: 202206 | AR1: 202209 | AS1: 202212 | AT1: 202303 | AU1: 202306 | AV1: 202309 | AW1: 202312 | AX1: 202403 | AY1: 202406
A4: Field Description | B4: Field Name
A5: Date End | B5: SHP_DATE_END | C5: {=_xll.EQNXTDZ($A$1,$B5,C$1)} -> 201206 | D5: {=_xll.EQNXTDZ($A$1,$B5,D$1)} -> 201209 | E5: {=_xll.EQNXTDZ($A$1,$B5,E$1)} -> 201212 | F5: {=_xll.EQNXTDZ($A$1,$B5,F$1)} -> 201303 | G5: {=_xll.EQNXTDZ($A$1,$B5,G$1)} -> 201306 | H5: {=_xll.EQNXTDZ($A$1,$B5,H$1)} -> 201309 | I5: {=_xll.EQNXTDZ($A$1,$B5,I$1)} -> 201312 | J5: {=_xll.EQNXTDZ($A$1,$B5,J$1)} -> 201403 | ... AY5: {=_xll.EQNXTDZ($A$1,$B5,AY$1)} -> 202406
A6: Grand Total | B6: SHP_NSGRANDTOTAL | C6: {=_xll.EQNXTDZ($A$1,$B6,C$1)} -> 32401000 | D6: {=_xll.EQNXTDZ($A$1,$B6,D$1)} -> 32401000 | E6: {=_xll.EQNXTDZ($A$1,$B6,E$1)} -> 32401000 | F6: {=_xll.EQNXTDZ($A$1,$B6,F$1)} -> 32401000 | G6: {=_xll.EQNXTDZ($A$1,$B6,G$1)} -> 32401000 | H6: {=_xll.EQNXTDZ($A$1,$B6,H$1)} -> 32401000 | I6: {=_xll.EQNXTDZ($A$1,$B6,I$1)} -> 32401000 | J6: {=_xll.EQNXTDZ($A$1,$B6,J$1)} -> 32401000 | ... AY6: {=_xll.EQNXTDZ($A$1,$B6,AY$1)} -> 32401000
B7: In Crs. | C7: =+C6/10^7 -> 3.2401 | D7: =+D6/10^7 -> 3.2401 | E7: =+E6/10^7 -> 3.2401 | F7: =+F6/10^7 -> 3.2401 | G7: =+G6/10^7 -> 3.2401 | H7: =+H6/10^7 -> 3.2401 | I7: =+I6/10^7 -> 3.2401 | J7: =+J6/10^7 -> 3.2401 | ... AY7: =+AY6/10^7 -> 3.2401

Sheet Share price Daily
A1: =_xll.EQNXTH(B1,"[ADJC];[ADJH];[ADJL];[ADJO];[UCLS];[VOLUME]","2015-Jan-01","Y","All traded days","Asc") -> EQNXTH | B1: =+'Annual Raw'!A1 -> 130999 | L1: =_xll.EQNXTH(B1,"[NADJC];[NADJH];[NADJLOW];[NADJOPEN];[NUCLOSE];[NVOLUME]","2015-Jan-01","Y","All traded days","Asc") -> EQNXTH
A2: Balaji Amines Ltd. | L2: Balaji Amines Ltd.
A3: DATE | B3: ADJHIGH | C3: ADJCLOSE | D3: ADJLOW | E3: ADJOPEN | F3: CLOSE | G3: VOLUME | L3: DATE | M3: ADJCLOSE | N3: ADJHIGH | O3: ADJLOW | P3: ADJOPEN | Q3: CLOSE | R3: VOLUME
A4: 42005 | B4: 73 | C4: 72.55 | D4: 71 | E4: 71.7 | F4: 72.55 | G4: 10141 | L4: 42005 | M4: 72.35 | N4: 72.85 | O4: 71.1 | P4: 71.55 | Q4: 72.35 | R4: 2550
A5: 42006 | B5: 72.7 | C5: 71.85 | D5: 70.8 | E5: 72 | F5: 71.85 | G5: 5823 | L5: 42006 | M5: 71.6 | N5: 73 | O5: 70 | P5: 71.65 | Q5: 71.6 | R5: 14123
A6: 42009 | B6: 72.1 | C6: 71.3 | D6: 70.1 | E6: 71.95 | F6: 71.3 | G6: 7876 | L6: 42009 | M6: 71.7 | N6: 72.85 | O6: 70.7 | P6: 72.85 | Q6: 71.7 | R6: 3446
A7: 42010 | B7: 71.7 | C7: 69.8 | D7: 69.1 | E7: 70 | F7: 69.8 | G7: 4042 | L7: 42010 | M7: 69.55 | N7: 72.6 | O7: 68.95 | P7: 71 | Q7: 69.55 | R7: 12761
A8: 42011 | B8: 71.25 | C8: 70.7 | D8: 70 | E8: 70 | F8: 70.7 | G8: 4172 | L8: 42011 | M8: 71.45 | N8: 71.75 | O8: 68.7 | P8: 69 | Q8: 71.45 | R8: 12399
A9: 42012 | B9: 72.25 | C9: 71.05 | D9: 71.05 | E9: 71.5 | F9: 71.05 | G9: 10455 | L9: 42012 | M9: 71.9 | N9: 73.1 | O9: 71 | P9: 73.05 | Q9: 71.9 | R9: 2401
A10: 42013 | B10: 72.55 | C10: 71.55 | D10: 71 | E10: 71.2 | F10: 71.55 | G10: 1500 | L10: 42013 | M10: 71.7 | N10: 72.2 | O10: 71 | P10: 72 | Q10: 71.7 | R10: 5802
A11: 42016 | B11: 77.7 | C11: 76.45 | D11: 71.6 | E11: 72 | F11: 76.45 | G11: 7929 | L11: 42016 | M11: 76.85 | N11: 78 | O11: 71.75 | P11: 72.2 | Q11: 76.85 | R11: 18308
A12: 42017 | B12: 80.6 | C12: 78.6 | D12: 77 | E12: 78 | F12: 78.6 | G12: 20322 | L12: 42017 | M12: 78.3 | N12: 80.5 | O12: 76.05 | P12: 76.5 | Q12: 78.3 | R12: 30926
A13: 42018 | B13: 80.15 | C13: 78.3 | D13: 77 | E13: 77.95 | F13: 78.3 | G13: 5094 | L13: 42018 | M13: 79.1 | N13: 80.75 | O13: 77 | P13: 78.35 | Q13: 79.1 | R13: 9640
A14: 42019 | B14: 79.55 | C14: 79.1 | D14: 77.3 | E14: 79.4 | F14: 79.1 | G14: 2438 | L14: 42019 | M14: 78.85 | N14: 80 | O14: 78.05 | P14: 78.5 | Q14: 78.85 | R14: 7003
A15: 42020 | B15: 78.55 | C15: 78.05 | D15: 77.35 | E15: 78.1 | F15: 78.05 | G15: 8255 | L15: 42020 | M15: 77.95 | N15: 79 | O15: 77.25 | P15: 78.65 | Q15: 77.95 | R15: 7679
... A2840: 46189 | B2840: 2107.25 | C2840: 2077.65 | D2840: 2048.5 | E2840: 2107.25 | F2840: 2077.65 | G2840: 14378 | L2840: 46189 | M2840: 2076.5 | N2840: 2102.5 | O2840: 2045.6 | P2840: 2100.1 | Q2840: 2076.5 | R2840: 138544

Sheet Sheet2
J19: 219.3 | K19: 186.25 | L19: 186.75
J20: 192.9 | K20: 135.5 | L20: 146.9 | N20: 219.3 | O20: 192.9 | P20: 186 | Q20: 178.7 | R20: 207 | S20: 255.15 | T20: 348.25 | U20: 374 | V20: 495.9 | W20: 659.9 | X20: 613.4 | Y20: 607.9 | Z20: 555.95 | AA20: 497.8 | AB20: 459.9 | AC20: 374 | AD20: 362 | AE20: 341.5 | AF20: 384.2 | AG20: 433.8 | AH20: 460 | AI20: 474.4 | AJ20: 414.4 | AK20: 318.7 | AL20: 303.25 | AM20: 332.7 | AN20: 295 | AO20: 247 | AP20: 214.4 | AQ20: 179.5 | AR20: 97.9 | AS20: 119.1 | AT20: 130.65 | AU20: 148.55 | AV20: 153.8 | AW20: 152.9 | AX20: 136 | AY20: 141.15 | AZ20: 128.1 | BA20: 142.5 | BB20: 143.55 | BC20: 124.5 | BD20: 241 | BE20: 450 | BF20: 503.35
J21: 186 | K21: 145.4 | L21: 169.1 | N21: 186.25 | O21: 135.5 | P21: 145.4 | Q21: 108.95 | R21: 137 | S21: 170 | T21: 243.15 | U21: 307.5 | V21: 325.1 | W21: 463 | X21: 467.05 | Y21: 436.5 | Z21: 467 | AA21: 348.2 | AB21: 325 | AC21: 313.1 | AD21: 285 | AE21: 277.85 | AF21: 327 | AG21: 317 | AH21: 370.7 | AI21: 360 | AJ21: 271.15 | AK21: 233.15 | AL21: 218.8 | AM21: 262 | AN21: 223.6 | AO21: 137.6 | AP21: 142 | AQ21: 59.3 | AR21: 58 | AS21: 72.8 | AT21: 80 | AU21: 107.25 | AV21: 106 | AW21: 125.1 | AX21: 112.25 | AY21: 81.45 | AZ21: 88 | BA21: 90.35 | BB21: 106.05 | BC21: 98.55 | BD21: 119.25 | BE21: 210 | BF21: 349
J22: 178.7 | K22: 108.95 | L22: 139.75 | N22: 186.75 | O22: 146.9 | P22: 169.1 | Q22: 139.75 | R22: 202.15 | S22: 249.05 | T22: 346.4 | U22: 349.2 | V22: 469.9 | W22: 584.8 | X22: 536.15 | Y22: 513.35 | Z22: 474 | AA22: 438.55 | AB22: 355.4 | AC22: 334.95 | AD22: 298.8 | AE22: 328.35 | AF22: 343 | AG22: 389.9 | AH22: 443.05 | AI22: 407.5 | AJ22: 290.1 | AK22: 235.75 | AL22: 292.65 | AM22: 276.1 | AN22: 237.05 | AO22: 190.1 | AP22: 147.2 | AQ22: 71.9 | AR22: 75.2 | AS22: 90.1 | AT22: 117.2 | AU22: 116.3 | AV22: 140.5 | AW22: 128.6 | AX22: 133.65 | AY22: 91.65 | AZ22: 97.65 | BA22: 125 | BB22: 115.35 | BC22: 119.25 | BD22: 219.3 | BE22: 442.65 | BF22: 503.35
J23: 207 | K23: 137 | L23: 202.15
J24: 255.15 | K24: 170 | L24: 249.05
J25: 348.25 | K25: 243.15 | L25: 346.4
J26: 374 | K26: 307.5 | L26: 349.2
J27: 495.9 | K27: 325.1 | L27: 469.9
J28: 659.9 | K28: 463 | L28: 584.8
J29: 613.4 | K29: 467.05 | L29: 536.15
J30: 607.9 | K30: 436.5 | L30: 513.35
J31: 555.95 | K31: 467 | L31: 474
J32: 497.8 | K32: 348.2 | L32: 438.55
J33: 459.9 | K33: 325 | L33: 355.4
J34: 374 | K34: 313.1 | L34: 334.95
... J63: 503.35 | K63: 349 | L63: 503.35
