Workbook

Sheet Template
A1: =+'Annual Raw'!B2 -> CreditAccess Grameen Ltd. | B1: =+EOMONTH(C1,-12) -> 36981 | C1: =+EOMONTH(D1,-12) -> 37346 | D1: =+EOMONTH(E1,-12) -> 37711 | E1: =+EOMONTH(F1,-12) -> 38077 | F1: =+EOMONTH(G1,-12) -> 38442 | G1: =+EOMONTH(H1,-12) -> 38807 | H1: =+EOMONTH(I1,-12) -> 39172 | I1: =+EOMONTH(J1,-12) -> 39538 | ... N1: =+EOMONTH(O1,-12) -> 41364 | O1: 41699 | P1: 42064 | Q1: 42430 | R1: 42795 | S1: 43160 | T1: 43525 | U1: 43891 | V1: 44256 | W1: 44621 | X1: 44986 | Y1: 45352 | Z1: 45717 | AA1: 46082 | AB1: 46447 | AC1: 46813 | AD1: 47178 | AE1: 47543 | AG1: Quarterly | AH1: 42185 | AI1: =+EOMONTH(AH1,3) -> 42277 | AJ1: =+EOMONTH(AI1,3) -> 42369 | AK1: =+EOMONTH(AJ1,3) -> 42460 | AL1: =+EOMONTH(AK1,3) -> 42551 | AM1: =+EOMONTH(AL1,3) -> 42643 | AN1: =+EOMONTH(AM1,3) -> 42735 | AO1: =+EOMONTH(AN1,3) -> 42825 | AP1: =+EOMONTH(AO1,3) -> 42916 | ... CO1: =+EOMONTH(CN1,3) -> 47573 | CS1: HISTORICAL ESTIMATES | CT1: 46082
A2: Presentation Data (Start)
A4: Average eq | D4: =AVERAGE(C106:D106) -> 0 | E4: =AVERAGE(D106:E106) -> 0 | F4: =AVERAGE(E106:F106) -> 0 | G4: =AVERAGE(F106:G106) -> 0 | H4: =AVERAGE(G106:H106) -> 0 | I4: =AVERAGE(H106:I106) -> 0 | J4: =AVERAGE(I106:J106) -> 10.898666 | K4: =AVERAGE(J106:K106) -> 36.020155 | ... X4: =AVERAGE(W106:X106) -> 4636.925 | Y4: =+AVERAGE(BN4:BQ4) -> 5810.6812 | Z4: =+AVERAGE(BR4:BU4) -> 6901.9788 | AA4: =+AVERAGE(BV4:BY4) -> 7249.03 | AB4: =+AVERAGE(BZ4:CC4) -> 8542.4144 | AC4: =+AVERAGE(CD4:CG4) -> 10367.377 | AD4: =+AVERAGE(CH4:CK4) -> 12646.611 | AE4: =+AVERAGE(CL4:CO4) -> 15282.819 | AH4: =AVERAGE(AG106:AH106) -> 0 | AI4: =AVERAGE(AH106:AI106) -> 0 | AJ4: =AVERAGE(AI106:AJ106) -> 0 | AK4: =AVERAGE(AJ106:AK106) -> 0 | AL4: =AVERAGE(AK106:AL106) -> 0 | AM4: =AVERAGE(AL106:AM106) -> 0 | AN4: =AVERAGE(AM106:AN106) -> 0 | AO4: =AVERAGE(AN106:AO106) -> 0 | ... CO4: =AVERAGE(CN106:CO106) -> 16351.026
A5: Average assets | D5: =AVERAGE(C115:D115) -> 0 | E5: =AVERAGE(D115:E115) -> 0 | F5: =AVERAGE(E115:F115) -> 0 | G5: =AVERAGE(F115:G115) -> 0 | H5: =AVERAGE(G115:H115) -> 0 | I5: =AVERAGE(H115:I115) -> 0 | J5: =AVERAGE(I115:J115) -> 105.52 | K5: =AVERAGE(J115:K115) -> 253.71033 | ... X5: =AVERAGE(W115:X115) -> 19253.4 | Y5: =+AVERAGE(BN5:BQ5) -> 13942.493 | Z5: =+AVERAGE(BR5:BU5) -> 20977.406 | AA5: =+AVERAGE(BV5:BY5) -> 26836.186 | AB5: =+AVERAGE(BZ5:CC5) -> 31306.233 | AC5: =+AVERAGE(CD5:CG5) -> 35988.795 | AD5: =+AVERAGE(CH5:CK5) -> 41482.759 | AE5: =+AVERAGE(CL5:CO5) -> 47736.938 | AH5: =AVERAGE(AG115:AH115) -> 0 | AI5: =AVERAGE(AH115:AI115) -> 0 | AJ5: =AVERAGE(AI115:AJ115) -> 0 | AK5: =AVERAGE(AJ115:AK115) -> 0 | AL5: =AVERAGE(AK115:AL115) -> 0 | AM5: =AVERAGE(AL115:AM115) -> 0 | AN5: =AVERAGE(AM115:AN115) -> 0 | AO5: =AVERAGE(AN115:AO115) -> 0 | ... CO5: =AVERAGE(CN115:CO115) -> 50771.079
A7: Growth (%) | D7: =+D5/C5-1 -> #DIV/0! | E7: =+E5/D5-1 -> #DIV/0! | F7: =+F5/E5-1 -> #DIV/0! | G7: =+G5/F5-1 -> #DIV/0! | H7: =+H5/G5-1 -> #DIV/0! | I7: =+I5/H5-1 -> #DIV/0! | J7: =+J5/I5-1 -> #DIV/0! | K7: =+K5/J5-1 -> 1.4043815 | ... AE7: =+AE5/AD5-1 -> 0.15076574 | AL7: =AL5/AH5-1 -> #DIV/0! | AM7: =AM5/AI5-1 -> #DIV/0! | AN7: =AN5/AJ5-1 -> #DIV/0! | AO7: =AO5/AK5-1 -> #DIV/0! | AP7: =AP5/AL5-1 -> #DIV/0! | AQ7: =AQ5/AM5-1 -> #DIV/0! | AR7: =AR5/AN5-1 -> #DIV/0! | AS7: =AS5/AO5-1 -> #DIV/0! | ... CO7: =CO5/CK5-1 -> 0.14977219
A9: Leverage | D9: =D114/D106 -> #DIV/0! | E9: =E114/E106 -> #DIV/0! | F9: =F114/F106 -> #DIV/0! | G9: =G114/G106 -> #DIV/0! | H9: =H114/H106 -> #DIV/0! | I9: =I114/I106 -> #DIV/0! | J9: =J114/J106 -> 8.6819187 | K9: =K114/K106 -> 4.8989469 | ... AE9: =AE114/AE106 -> 2.1848042 | AH9: =AH114/AH106 -> #DIV/0! | AI9: =AI114/AI106 -> #DIV/0! | AJ9: =AJ114/AJ106 -> #DIV/0! | AK9: =AK114/AK106 -> #DIV/0! | AL9: =AL114/AL106 -> #DIV/0! | AM9: =AM114/AM106 -> #DIV/0! | AN9: =AN114/AN106 -> #DIV/0! | AO9: =AO114/AO106 -> #DIV/0! | ... CO9: =CO114/CO106 -> 2.1848042
A12: Interest Income | D12: =D35/C5 -> #DIV/0! | E12: =E35/D5 -> #DIV/0! | F12: =F35/E5 -> #DIV/0! | G12: =G35/F5 -> #DIV/0! | H12: =H35/G5 -> #DIV/0! | I12: =I35/H5 -> #DIV/0! | J12: =J35/I5 -> #DIV/0! | K12: =K35/J5 -> 0.46160639 | ... AE12: =AE35/AD5 -> 0.28673392 | AI12: =AI35/AH5 -> #DIV/0! | AJ12: =AJ35/AI5 -> #DIV/0! | AK12: =AK35/AJ5 -> #DIV/0! | AL12: =AL35/AK5 -> #DIV/0! | AM12: =AM35/AL5 -> #DIV/0! | AN12: =AN35/AM5 -> #DIV/0! | AO12: =AO35/AN5 -> #DIV/0! | AP12: =AP35/AO5 -> #DIV/0! | ... BX12: =BX35/BW5 -> 0.05737934 | BY12: =+AVERAGE(BU12:BX12)*1.08 -> 0.061221758 | BZ12: =+AVERAGE(BV12:BY12) -> 0.058161849 | CA12: =+AVERAGE(BW12:BZ12)*1.05 -> 0.061708412 | CB12: =+AVERAGE(BX12:CA12)*1.05 -> 0.062598732 | CC12: =+AVERAGE(BY12:CB12)*1.05 -> 0.063968822 | CD12: =+AVERAGE(BZ12:CC12)*1.02 -> 0.062841643 | CE12: =+AVERAGE(CA12:CD12)*1.02 -> 0.06403499 | CF12: =+AVERAGE(CB12:CE12)*1.02 -> 0.064628268 | CG12: =+AVERAGE(CC12:CF12)*1.02 -> 0.065145799 | CH12: =+AVERAGE(CD12:CG12) -> 0.064162675 | CI12: =+AVERAGE(CE12:CH12) -> 0.064492933 | CJ12: =+AVERAGE(CF12:CI12) -> 0.064607419 | CK12: =+AVERAGE(CG12:CJ12) -> 0.064602207 | CL12: =+AVERAGE(CH12:CK12) -> 0.064466308 | CM12: =+AVERAGE(CI12:CL12) -> 0.064542217 | CN12: =+AVERAGE(CJ12:CM12) -> 0.064554538 | CO12: =+AVERAGE(CK12:CN12) -> 0.064541317
A13: Interest Expenses | D13: =D36/C5 -> #DIV/0! | E13: =E36/D5 -> #DIV/0! | F13: =F36/E5 -> #DIV/0! | G13: =G36/F5 -> #DIV/0! | H13: =H36/G5 -> #DIV/0! | I13: =I36/H5 -> #DIV/0! | J13: =J36/I5 -> #DIV/0! | K13: =K36/J5 -> 0.17918624 | ... AE13: =AE36/AD5 -> 0.080821382 | AI13: =AI36/AH5 -> #DIV/0! | AJ13: =AJ36/AI5 -> #DIV/0! | AK13: =AK36/AJ5 -> #DIV/0! | AL13: =AL36/AK5 -> #DIV/0! | AM13: =AM36/AL5 -> #DIV/0! | AN13: =AN36/AM5 -> #DIV/0! | AO13: =AO36/AN5 -> #DIV/0! | AP13: =AP36/AO5 -> #DIV/0! | ... BX13: =BX36/BW5 -> 0.017684145 | BY13: =+AVERAGE(BU13:BX13) -> 0.018345618 | BZ13: =+AVERAGE(BV13:BY13) -> 0.018234348 | CA13: =+AVERAGE(BW13:BZ13) -> 0.018200899 | CB13: =+AVERAGE(BX13:CA13) -> 0.018116252 | CC13: =+AVERAGE(BY13:CB13) -> 0.018224279 | CD13: =+AVERAGE(BZ13:CC13) -> 0.018193945 | CE13: =+AVERAGE(CA13:CD13) -> 0.018183844 | CF13: =+AVERAGE(CB13:CE13) -> 0.01817958 | ... CO13: =+AVERAGE(CK13:CN13) -> 0.018188393
A14: NII | D14: =D12-D13 -> #DIV/0! | E14: =E12-E13 -> #DIV/0! | F14: =F12-F13 -> #DIV/0! | G14: =G12-G13 -> #DIV/0! | H14: =H12-H13 -> #DIV/0! | I14: =I12-I13 -> #DIV/0! | J14: =J12-J13 -> #DIV/0! | K14: =K12-K13 -> 0.28242015 | ... AE14: =AE12-AE13 -> 0.20591254 | AI14: =AI12-AI13 -> #DIV/0! | AJ14: =AJ12-AJ13 -> #DIV/0! | AK14: =AK12-AK13 -> #DIV/0! | AL14: =AL12-AL13 -> #DIV/0! | AM14: =AM12-AM13 -> #DIV/0! | AN14: =AN12-AN13 -> #DIV/0! | AO14: =AO12-AO13 -> #DIV/0! | AP14: =AP12-AP13 -> #DIV/0! | ... CO14: =CO12-CO13 -> 0.046352925
A15: Others income | D15: =D38/C5 -> #DIV/0! | E15: =E38/D5 -> #DIV/0! | F15: =F38/E5 -> #DIV/0! | G15: =G38/F5 -> #DIV/0! | H15: =H38/G5 -> #DIV/0! | I15: =I38/H5 -> #DIV/0! | J15: =J38/I5 -> #DIV/0! | K15: =K38/J5 -> 0.010219392 | ... AE15: =AE38/AD5 -> 0.00015396803 | AI15: =AI38/AH5 -> #DIV/0! | AJ15: =AJ38/AI5 -> #DIV/0! | AK15: =AK38/AJ5 -> #DIV/0! | AL15: =AL38/AK5 -> #DIV/0! | AM15: =AM38/AL5 -> #DIV/0! | AN15: =AN38/AM5 -> #DIV/0! | AO15: =AO38/AN5 -> #DIV/0! | AP15: =AP38/AO5 -> #DIV/0! | ... BX15: =BX38/BW5 -> 3.4649128e-05 | BY15: =BX15 -> 3.4649128e-05 | BZ15: =BY15 -> 3.4649128e-05 | CA15: =BZ15 -> 3.4649128e-05 | CB15: =CA15 -> 3.4649128e-05 | CC15: =CB15 -> 3.4649128e-05 | CD15: =CC15 -> 3.4649128e-05 | CE15: =CD15 -> 3.4649128e-05 | CF15: =CE15 -> 3.4649128e-05 | ... CO15: =CN15 -> 3.4649128e-05
A16: Other non-operating income
A17: Total income | D17: =D14+D15+D16 -> #DIV/0! | E17: =E14+E15+E16 -> #DIV/0! | F17: =F14+F15+F16 -> #DIV/0! | G17: =G14+G15+G16 -> #DIV/0! | H17: =H14+H15+H16 -> #DIV/0! | I17: =I14+I15+I16 -> #DIV/0! | J17: =J14+J15+J16 -> #DIV/0! | K17: =K14+K15+K16 -> 0.29263954 | ... AE17: =AE14+AE15+AE16 -> 0.20606651 | AI17: =AI14+AI15+AI16 -> #DIV/0! | AJ17: =AJ14+AJ15+AJ16 -> #DIV/0! | AK17: =AK14+AK15+AK16 -> #DIV/0! | AL17: =AL14+AL15+AL16 -> #DIV/0! | AM17: =AM14+AM15+AM16 -> #DIV/0! | AN17: =AN14+AN15+AN16 -> #DIV/0! | AO17: =AO14+AO15+AO16 -> #DIV/0! | AP17: =AP14+AP15+AP16 -> #DIV/0! | ... CO17: =CO14+CO15+CO16 -> 0.046387574
A18: TC | D18: =D46/C5 -> #DIV/0! | E18: =E46/D5 -> #DIV/0! | F18: =F46/E5 -> #DIV/0! | G18: =G46/F5 -> #DIV/0! | H18: =H46/G5 -> #DIV/0! | I18: =I46/H5 -> #DIV/0! | J18: =J46/I5 -> #DIV/0! | K18: =K46/J5 -> 0.23044208 | ... AE18: =AE46/AD5 -> 0.055484314 | AI18: =AI46/AH5 -> #DIV/0! | AJ18: =AJ46/AI5 -> #DIV/0! | AK18: =AK46/AJ5 -> #DIV/0! | AL18: =AL46/AK5 -> #DIV/0! | AM18: =AM46/AL5 -> #DIV/0! | AN18: =AN46/AM5 -> #DIV/0! | AO18: =AO46/AN5 -> #DIV/0! | AP18: =AP46/AO5 -> #DIV/0! | ... BX18: =BX46/BW5 -> 0.013531639 | BY18: =BX18 -> 0.013531639 | BZ18: =BY18*0.99 -> 0.013396323 | CA18: =BZ18*0.99 -> 0.01326236 | CB18: =CA18*0.99 -> 0.013129736 | CC18: =CB18*0.99 -> 0.012998439 | CD18: =CC18*0.99 -> 0.012868454 | CE18: =CD18*0.99 -> 0.01273977 | CF18: =CE18*0.99 -> 0.012612372 | CG18: =CF18*0.99 -> 0.012486248 | CH18: =CG18 -> 0.012486248 | CI18: =CH18 -> 0.012486248 | CJ18: =CI18 -> 0.012486248 | CK18: =CJ18 -> 0.012486248 | CL18: =CK18 -> 0.012486248 | CM18: =CL18 -> 0.012486248 | CN18: =CM18 -> 0.012486248 | CO18: =CN18 -> 0.012486248
A19: PPP | D19: =D17-D18 -> #DIV/0! | E19: =E17-E18 -> #DIV/0! | F19: =F17-F18 -> #DIV/0! | G19: =G17-G18 -> #DIV/0! | H19: =H17-H18 -> #DIV/0! | I19: =I17-I18 -> #DIV/0! | J19: =J17-J18 -> #DIV/0! | K19: =K17-K18 -> 0.062197455 | ... AE19: =AE17-AE18 -> 0.15058219 | AI19: =AI17-AI18 -> #DIV/0! | AJ19: =AJ17-AJ18 -> #DIV/0! | AK19: =AK17-AK18 -> #DIV/0! | AL19: =AL17-AL18 -> #DIV/0! | AM19: =AM17-AM18 -> #DIV/0! | AN19: =AN17-AN18 -> #DIV/0! | AO19: =AO17-AO18 -> #DIV/0! | AP19: =AP17-AP18 -> #DIV/0! | ... CO19: =CO17-CO18 -> 0.033901325
A20: Provision | D20: =D49/C5 -> #DIV/0! | E20: =E49/D5 -> #DIV/0! | F20: =F49/E5 -> #DIV/0! | G20: =G49/F5 -> #DIV/0! | H20: =H49/G5 -> #DIV/0! | I20: =I49/H5 -> #DIV/0! | J20: =J49/I5 -> #DIV/0! | K20: =K49/J5 -> 0.044368303 | ... AE20: =AE49/AD5 -> 0.058605364 | AI20: =AI49/AH5 -> #DIV/0! | AJ20: =AJ49/AI5 -> #DIV/0! | AK20: =AK49/AJ5 -> #DIV/0! | AL20: =AL49/AK5 -> #DIV/0! | AM20: =AM49/AL5 -> #DIV/0! | AN20: =AN49/AM5 -> #DIV/0! | AO20: =AO49/AN5 -> #DIV/0! | AP20: =AP49/AO5 -> #DIV/0! | ... BX20: =BX49/BW5 -> 0.013188613 | BY20: =BX20 -> 0.013188613 | BZ20: =BY20 -> 0.013188613 | CA20: =BZ20 -> 0.013188613 | CB20: =CA20 -> 0.013188613 | CC20: =CB20 -> 0.013188613 | CD20: =CC20 -> 0.013188613 | CE20: =CD20 -> 0.013188613 | CF20: =CE20 -> 0.013188613 | ... CO20: =CN20 -> 0.013188613
A21: PBT | D21: =D19-D20 -> #DIV/0! | E21: =E19-E20 -> #DIV/0! | F21: =F19-F20 -> #DIV/0! | G21: =G19-G20 -> #DIV/0! | H21: =H19-H20 -> #DIV/0! | I21: =I19-I20 -> #DIV/0! | J21: =J19-J20 -> #DIV/0! | K21: =K19-K20 -> 0.017829152 | ... AE21: =AE19-AE20 -> 0.091976829 | AI21: =AI19-AI20 -> #DIV/0! | AJ21: =AJ19-AJ20 -> #DIV/0! | AK21: =AK19-AK20 -> #DIV/0! | AL21: =AL19-AL20 -> #DIV/0! | AM21: =AM19-AM20 -> #DIV/0! | AN21: =AN19-AN20 -> #DIV/0! | AO21: =AO19-AO20 -> #DIV/0! | AP21: =AP19-AP20 -> #DIV/0! | ... CO21: =CO19-CO20 -> 0.020712713
A22: Tax | D22: =D51/C5 -> #DIV/0! | E22: =E51/D5 -> #DIV/0! | F22: =F51/E5 -> #DIV/0! | G22: =G51/F5 -> #DIV/0! | H22: =H51/G5 -> #DIV/0! | I22: =I51/H5 -> #DIV/0! | J22: =J51/I5 -> #DIV/0! | K22: =K51/J5 -> 0.0088673788 | ... AE22: =AE51/AD5 -> 0.023913975 | AI22: =AI51/AH5 -> #DIV/0! | AJ22: =AJ51/AI5 -> #DIV/0! | AK22: =AK51/AJ5 -> #DIV/0! | AL22: =AL51/AK5 -> #DIV/0! | AM22: =AM51/AL5 -> #DIV/0! | AN22: =AN51/AM5 -> #DIV/0! | AO22: =AO51/AN5 -> #DIV/0! | AP22: =AP51/AO5 -> #DIV/0! | ... CO22: =CO51/CN5 -> 0.0053853053
A23: PAT | D23: =D21-D22 -> #DIV/0! | E23: =E21-E22 -> #DIV/0! | F23: =F21-F22 -> #DIV/0! | G23: =G21-G22 -> #DIV/0! | H23: =H21-H22 -> #DIV/0! | I23: =I21-I22 -> #DIV/0! | J23: =J21-J22 -> #DIV/0! | K23: =K21-K22 -> 0.0089617732 | ... AE23: =AE21-AE22 -> 0.068062853 | AI23: =AI21-AI22 -> #DIV/0! | AJ23: =AJ21-AJ22 -> #DIV/0! | AK23: =AK21-AK22 -> #DIV/0! | AL23: =AL21-AL22 -> #DIV/0! | AM23: =AM21-AM22 -> #DIV/0! | AN23: =AN21-AN22 -> #DIV/0! | AO23: =AO21-AO22 -> #DIV/0! | AP23: =AP21-AP22 -> #DIV/0! | ... CO23: =CO21-CO22 -> 0.015327407
A26: Loan Book
A27: Opening | S27: =AS27 -> 4075 | T27: =S30 -> 4974.66 | U27: =T30 -> 7159 | V27: =U30 -> 9896 | W27: =V30 -> 13587 | X27: =W30 -> 16599 | Y27: =X30 -> 21031 | Z27: =Y30 -> 26714 | AA27: =Z30 -> 25948 | AR27: =AQ30 -> 3937 | AS27: =AR30 -> 4075 | AT27: =AS30 -> 4974.66 | AU27: =AT30 -> 5498 | AV27: =AU30 -> 5794 | AW27: =AV30 -> 6085 | AX27: =AW30 -> 7159 | AY27: =AX30 -> 7619 | ... BY27: =BX30 -> 26566
A28: Addition | S28: =SUM(AQ28:AS28) -> 4402 | T28: =SUM(AT28:AW28) -> 8221 | U28: =SUM(AX28:BA28) -> 10389 | V28: =SUM(BB28:BE28) -> 9641 | W28: =SUM(BF28:BI28) -> 12833 | X28: =SUM(BJ28:BM28) -> 18539 | Y28: =SUM(BN28:BQ28) -> 23134 | Z28: =SUM(BR28:BU28) -> 20437 | AA28: =SUM(BV28:BY28) -> 24860 | AQ28: 1195 | AR28: 1296 | AS28: 1911 | AT28: 1616 | AU28: 1571 | AV28: 1762 | AW28: 3272 | AX28: 2310 | AY28: 2186 | AZ28: 2977 | BA28: 2916 | BB28: 46 | BC28: 1420 | BD28: 4032 | BE28: 4143 | BF28: 907 | BG28: 3412 | BH28: 3866 | BI28: 4648 | BJ28: 2146 | BK28: 4375 | BL28: 4847 | BM28: 7171 | BN28: 4771 | BO28: 4966 | BP28: 5344 | BQ28: 8053 | BR28: 4476 | BS28: 4404 | BT28: 5085 | BU28: 6472 | BV28: 5458 | BW28: 5322 | BX28: 5767 | BY28: 8313
A29: Repayment | S29: =S27+S28-S30 -> 3502.34 | T29: =T27+T28-T30 -> 6036.66 | U29: =U27+U28-U30 -> 7652 | V29: =V27+V28-V30 -> 5950 | W29: =W27+W28-W30 -> 9821 | X29: =X27+X28-X30 -> 14107 | Y29: =Y27+Y28-Y30 -> 17451 | Z29: =Z27+Z28-Z30 -> 21203 | AA29: =AA27+AA28-AA30 -> 21218 | AQ29: =AQ27+AQ28-AQ30 -> -2742 | AR29: =AR27+AR28-AR30 -> 1158 | AS29: =AS27+AS28-AS30 -> 1011.34 | AT29: =AT27+AT28-AT30 -> 1092.66 | AU29: =AU27+AU28-AU30 -> 1275 | AV29: =AV27+AV28-AV30 -> 1471 | AW29: =AW27+AW28-AW30 -> 2198 | AX29: =AX27+AX28-AX30 -> 1850 | ... BY29: =BY27+BY28-BY30 -> 5289
A30: Closing | S30: =AS30 -> 4974.66 | T30: =AW30 -> 7159 | U30: =BA30 -> 9896 | V30: =BE30 -> 13587 | W30: =BI30 -> 16599 | X30: =BM30 -> 21031 | Y30: =BQ30 -> 26714 | Z30: =BU30 -> 25948 | AA30: =BY30 -> 29590 | AQ30: 3937 | AR30: 4075 | AS30: 4974.66 | AT30: 5498 | AU30: 5794 | AV30: 6085 | AW30: 7159 | AX30: 7619 | AY30: 7905 | AZ30: 8873 | BA30: 9896 | BB30: 11724 | BC30: 11183 | BD30: 12321 | BE30: 13587 | BF30: 12664 | BG30: 13333 | BH30: 14587 | BI30: 16599 | BJ30: 15615 | BK30: 16539 | BL30: 17786 | BM30: 21031 | BN30: 21814 | BO30: 22488 | BP30: 23382 | BQ30: 26714 | BR30: 26304 | BS30: 25133 | BT30: 24810 | BU30: 25948 | BV30: 26055 | BW30: 25904 | BX30: 26566 | BY30: 29590
A33: Presentation Data (End)
A34: Profit & Loss- Annual (Start)
A35: Interest Income | B35: =+'Annual Raw'!C14 -> 0 | C35: =+'Annual Raw'!D14 -> 0 | D35: =+'Annual Raw'!E14 -> 0 | E35: =+'Annual Raw'!F14 -> 0 | F35: =+'Annual Raw'!G14 -> 0 | G35: =+'Annual Raw'!H14 -> 0 | H35: =+'Annual Raw'!I14 -> 0 | I35: =+'Annual Raw'!J14 -> 0 | ... AA35: =+'Annual Raw'!AB14 -> 6058.92 | AB35: =SUM(BZ35:CC35) -> 7450.3332 | AC35: =SUM(CD35:CG35) -> 8915.9888 | AD35: =SUM(CH35:CK35) -> 10322.511 | AE35: =SUM(CL35:CO35) -> 11894.514 | AH35: =+'QTR Raw'!D13 -> 0 | AI35: =+'QTR Raw'!E13 -> 0 | AJ35: =+'QTR Raw'!F13 -> 0 | AK35: =+'QTR Raw'!G13 -> 0 | AL35: =+'QTR Raw'!H13 -> 0 | AM35: =+'QTR Raw'!I13 -> 0 | AN35: =+'QTR Raw'!J13 -> 0 | AO35: =+'QTR Raw'!K13 -> 0 | ... BY35: =+'QTR Raw'!AU13 -> 1597.27 | BZ35: =BZ12*BY5 -> 1679.8189 | CA35: =CA12*BZ5 -> 1872.6136 | CB35: =CB12*CA5 -> 1904.52 | CC35: =CC12*CB5 -> 1993.3806 | CD35: =CD12*CC5 -> 2092.1715 | CE35: =CE12*CD5 -> 2227.0419 | CF35: =CF12*CE5 -> 2259.5634 | CG35: =CG12*CF5 -> 2337.2121 | ... CO35: =CO12*CN5 -> 3074.1222 | CT35: 6058.92
A36: Interest exp | B36: =+'Annual Raw'!C29 -> 0 | C36: =+'Annual Raw'!D29 -> 0 | D36: =+'Annual Raw'!E29 -> 0 | E36: =+'Annual Raw'!F29 -> 0 | F36: =+'Annual Raw'!G29 -> 0 | G36: =+'Annual Raw'!H29 -> 0 | H36: =+'Annual Raw'!I29 -> 0 | I36: =+'Annual Raw'!J29 -> 0 | ... AA36: =+'Annual Raw'!AB29 -> 1905.13 | AB36: =SUM(BZ36:CC36) -> 2198.0423 | AC36: =SUM(CD36:CG36) -> 2526.5267 | AD36: =SUM(CH36:CK36) -> 2912.098 | AE36: =SUM(CL36:CO36) -> 3352.6939 | AH36: =+'QTR Raw'!D14+'QTR Raw'!D33 -> 0 | AI36: =+'QTR Raw'!E14+'QTR Raw'!E33 -> 0 | AJ36: =+'QTR Raw'!F14+'QTR Raw'!F33 -> 0 | AK36: =+'QTR Raw'!G14+'QTR Raw'!G33 -> 0 | AL36: =+'QTR Raw'!H14+'QTR Raw'!H33 -> 0 | AM36: =+'QTR Raw'!I14+'QTR Raw'!I33 -> 0 | AN36: =+'QTR Raw'!J14+'QTR Raw'!J33 -> 0 | AO36: =+'QTR Raw'!K14+'QTR Raw'!K33 -> 0 | ... BY36: =+'QTR Raw'!AU14+'QTR Raw'!AU33 -> 478.05 | BZ36: =BZ13*BY5 -> 526.64079 | CA36: =CA13*BZ5 -> 552.32748 | CB36: =CB13*CA5 -> 551.17356 | CC36: =CC13*CB5 -> 567.90048 | CD36: =CD13*CC5 -> 605.72657 | CE36: =CE13*CD5 -> 632.4071 | CF36: =CF13*CE5 -> 635.60288 | CG36: =CG13*CF5 -> 652.79016 | ... CO36: =CO13*CN5 -> 866.31856 | CT36: 1899.07
A37: NII | B37: =B35-B36 -> 0 | C37: =C35-C36 -> 0 | D37: =D35-D36 -> 0 | E37: =E35-E36 -> 0 | F37: =F35-F36 -> 0 | G37: =G35-G36 -> 0 | H37: =H35-H36 -> 0 | I37: =I35-I36 -> 0 | ... AE37: =AE35-AE36 -> 8541.8202 | AH37: =AH35-AH36 -> 0 | AI37: =AI35-AI36 -> 0 | AJ37: =AJ35-AJ36 -> 0 | AK37: =AK35-AK36 -> 0 | AL37: =AL35-AL36 -> 0 | AM37: =AM35-AM36 -> 0 | AN37: =AN35-AN36 -> 0 | AO37: =AO35-AO36 -> 0 | ... CO37: =CO35-CO36 -> 2207.8036 | CT37: 4159.85
A38: Other Income | B38: =+'Annual Raw'!C27 -> 0 | C38: =+'Annual Raw'!D27 -> 0 | D38: =+'Annual Raw'!E27 -> 0 | E38: =+'Annual Raw'!F27 -> 0 | F38: =+'Annual Raw'!G27 -> 0 | G38: =+'Annual Raw'!H27 -> 0 | H38: =+'Annual Raw'!I27 -> 0 | I38: =+'Annual Raw'!J27 -> 0 | ... AA38: =+'Annual Raw'!AB27 -> 3.62 | AB38: =SUM(BZ38:CC38) -> 4.1860989 | AC38: =SUM(CD38:CG38) -> 4.8131231 | AD38: =SUM(CH38:CK38) -> 5.5477096 | AE38: =SUM(CL38:CO38) -> 6.3870187 | AH38: =+'QTR Raw'!D32 -> 0 | AI38: =+'QTR Raw'!E32 -> 0 | AJ38: =+'QTR Raw'!F32 -> 0 | AK38: =+'QTR Raw'!G32 -> 0 | AL38: =+'QTR Raw'!H32 -> 0 | AM38: =+'QTR Raw'!I32 -> 0 | AN38: =+'QTR Raw'!J32 -> 0 | AO38: =+'QTR Raw'!K32 -> 0 | ... BY38: =+'QTR Raw'!AU32 -> 1.31 | BZ38: =BZ15*BY5 -> 1.0007292 | CA38: =CA15*BZ5 -> 1.0514681 | CB38: =CB15*CA5 -> 1.054174 | CC38: =CC15*CB5 -> 1.0797275 | CD38: =CD15*CC5 -> 1.153565 | CE38: =CE15*CD5 -> 1.2050452 | CF38: =CF15*CE5 -> 1.2114188 | CG38: =CG15*CF5 -> 1.2430941 | ... CO38: =CO15*CN5 -> 1.6503483 | CT38: 3.62
A39: TI | B39: =B37+B38 -> 0 | C39: =C37+C38 -> 0 | D39: =D37+D38 -> 0 | E39: =E37+E38 -> 0 | F39: =F37+F38 -> 0 | G39: =G37+G38 -> 0 | H39: =H37+H38 -> 0 | I39: =I37+I38 -> 0 | ... AE39: =AE37+AE38 -> 8548.2072 | AH39: =AH37+AH38 -> 0 | AI39: =AI37+AI38 -> 0 | AJ39: =AJ37+AJ38 -> 0 | AK39: =AK37+AK38 -> 0 | AL39: =AL37+AL38 -> 0 | AM39: =AM37+AM38 -> 0 | AN39: =AN37+AN38 -> 0 | AO39: =AO37+AO38 -> 0 | ... CO39: =CO37+CO38 -> 2209.454 | CT39: 4163.47
A40: YOY% | C40: =+IF(B39<0,1-C39/B39,C39/B39-1) -> #DIV/0! | D40: =+IF(C39<0,1-D39/C39,D39/C39-1) -> #DIV/0! | E40: =+IF(D39<0,1-E39/D39,E39/D39-1) -> #DIV/0! | F40: =+IF(E39<0,1-F39/E39,F39/E39-1) -> #DIV/0! | G40: =+IF(F39<0,1-G39/F39,G39/F39-1) -> #DIV/0! | H40: =+IF(G39<0,1-H39/G39,H39/G39-1) -> #DIV/0! | I40: =+IF(H39<0,1-I39/H39,I39/H39-1) -> #DIV/0! | J40: =+IF(I39<0,1-J39/I39,J39/I39-1) -> #DIV/0! | ... AE40: =+IF(AD39<0,1-AE39/AD39,AE39/AD39-1) -> 0.15267703 | AL40: =+IF(AH39<0,1-AL39/AH39,AL39/AH39-1) -> #DIV/0! | AM40: =+IF(AI39<0,1-AM39/AI39,AM39/AI39-1) -> #DIV/0! | AN40: =+IF(AJ39<0,1-AN39/AJ39,AN39/AJ39-1) -> #DIV/0! | AO40: =+IF(AK39<0,1-AO39/AK39,AO39/AK39-1) -> #DIV/0! | AP40: =+IF(AL39<0,1-AP39/AL39,AP39/AL39-1) -> #DIV/0! | AQ40: =+IF(AM39<0,1-AQ39/AM39,AQ39/AM39-1) -> #DIV/0! | AR40: =+IF(AN39<0,1-AR39/AN39,AR39/AN39-1) -> #DIV/0! | AS40: =+IF(AO39<0,1-AS39/AO39,AS39/AO39-1) -> #DIV/0! | ... CO40: =+IF(CK39<0,1-CO39/CK39,CO39/CK39-1) -> 0.14957908 | CT40: 0.09531564
A41: Employee Cost | B41: =+'Annual Raw'!C18 -> 0 | C41: =+'Annual Raw'!D18 -> 0 | D41: =+'Annual Raw'!E18 -> 0 | E41: =+'Annual Raw'!F18 -> 0 | F41: =+'Annual Raw'!G18 -> 0 | G41: =+'Annual Raw'!H18 -> 0 | H41: =+'Annual Raw'!I18 -> 0 | I41: =+'Annual Raw'!J18 -> 0 | ... AA41: =+'Annual Raw'!AB18 -> 879.09 | AB41: =SUM(BZ41:CC41) -> 1593.8883 | AC41: =SUM(CD41:CG41) -> 1760.4207 | AD41: =SUM(CH41:CK41) -> 1999.1868 | AE41: =SUM(CL41:CO41) -> 2301.6424 | AH41: =+'QTR Raw'!D20 -> 0 | AI41: =+'QTR Raw'!E20 -> 0 | AJ41: =+'QTR Raw'!F20 -> 0 | AK41: =+'QTR Raw'!G20 -> 0 | AL41: =+'QTR Raw'!H20 -> 0 | AM41: =+'QTR Raw'!I20 -> 0 | AN41: =+'QTR Raw'!J20 -> 0 | AO41: =+'QTR Raw'!K20 -> 0 | ... BY41: =+'QTR Raw'!AU20 -> 211.71 | BZ41: =BZ18*BY5 -> 386.90992 | CA41: =CA18*BZ5 -> 402.46175 | CB41: =CB18*CA5 -> 399.46249 | CC41: =CC18*CB5 -> 405.05412 | CD41: =CD18*CC5 -> 428.42632 | CE41: =CE18*CD5 -> 443.07028 | CF41: =CF18*CE5 -> 440.95958 | CG41: =CG18*CF5 -> 447.96457 | ... CO41: =CO18*CN5 -> 594.72373 | CT41: 879.09
A42: Operating & Establishment Expenses | B42: =+'Annual Raw'!C19+'Annual Raw'!C20+'Annual Raw'!C21+'Annual Raw'!C17+'Annual Raw'!C16+'Annual Raw'!C15-'Annual Raw'!C24 -> 0 | C42: =+'Annual Raw'!D19+'Annual Raw'!D20+'Annual Raw'!D21+'Annual Raw'!D17+'Annual Raw'!D16+'Annual Raw'!D15-'Annual Raw'!D24 -> 0 | D42: =+'Annual Raw'!E19+'Annual Raw'!E20+'Annual Raw'!E21+'Annual Raw'!E17+'Annual Raw'!E16+'Annual Raw'!E15-'Annual Raw'!E24 -> 0 | E42: =+'Annual Raw'!F19+'Annual Raw'!F20+'Annual Raw'!F21+'Annual Raw'!F17+'Annual Raw'!F16+'Annual Raw'!F15-'Annual Raw'!F24 -> 0 | F42: =+'Annual Raw'!G19+'Annual Raw'!G20+'Annual Raw'!G21+'Annual Raw'!G17+'Annual Raw'!G16+'Annual Raw'!G15-'Annual Raw'!G24 -> 0 | G42: =+'Annual Raw'!H19+'Annual Raw'!H20+'Annual Raw'!H21+'Annual Raw'!H17+'Annual Raw'!H16+'Annual Raw'!H15-'Annual Raw'!H24 -> 0 | H42: =+'Annual Raw'!I19+'Annual Raw'!I20+'Annual Raw'!I21+'Annual Raw'!I17+'Annual Raw'!I16+'Annual Raw'!I15-'Annual Raw'!I24 -> 0 | I42: =+'Annual Raw'!J19+'Annual Raw'!J20+'Annual Raw'!J21+'Annual Raw'!J17+'Annual Raw'!J16+'Annual Raw'!J15-'Annual Raw'!J24 -> 0 | ... AA42: =+'Annual Raw'!AB19+'Annual Raw'!AB20+'Annual Raw'!AB21+'Annual Raw'!AB17+'Annual Raw'!AB16+'Annual Raw'!AB15-'Annual Raw'!AB24 -> 373.11 | AB42: =SUM(BZ42:CC42) -> 0 | AC42: =SUM(CD42:CG42) -> 0 | AD42: =SUM(CH42:CK42) -> 0 | AE42: =SUM(CL42:CO42) -> 0 | AH42: =+'QTR Raw'!D15+'QTR Raw'!D21+'QTR Raw'!D17+'QTR Raw'!D18+'QTR Raw'!D19+'QTR Raw'!D16+'QTR Raw'!D25 -> 0 | AI42: =+'QTR Raw'!E15+'QTR Raw'!E21+'QTR Raw'!E17+'QTR Raw'!E18+'QTR Raw'!E19+'QTR Raw'!E16+'QTR Raw'!E25 -> 0 | AJ42: =+'QTR Raw'!F15+'QTR Raw'!F21+'QTR Raw'!F17+'QTR Raw'!F18+'QTR Raw'!F19+'QTR Raw'!F16+'QTR Raw'!F25 -> 0 | AK42: =+'QTR Raw'!G15+'QTR Raw'!G21+'QTR Raw'!G17+'QTR Raw'!G18+'QTR Raw'!G19+'QTR Raw'!G16+'QTR Raw'!G25 -> 0 | AL42: =+'QTR Raw'!H15+'QTR Raw'!H21+'QTR Raw'!H17+'QTR Raw'!H18+'QTR Raw'!H19+'QTR Raw'!H16+'QTR Raw'!H25 -> 0 | AM42: =+'QTR Raw'!I15+'QTR Raw'!I21+'QTR Raw'!I17+'QTR Raw'!I18+'QTR Raw'!I19+'QTR Raw'!I16+'QTR Raw'!I25 -> 0 | AN42: =+'QTR Raw'!J15+'QTR Raw'!J21+'QTR Raw'!J17+'QTR Raw'!J18+'QTR Raw'!J19+'QTR Raw'!J16+'QTR Raw'!J25 -> 0 | AO42: =+'QTR Raw'!K15+'QTR Raw'!K21+'QTR Raw'!K17+'QTR Raw'!K18+'QTR Raw'!K19+'QTR Raw'!K16+'QTR Raw'!K25 -> 0 | ... BY42: =+'QTR Raw'!AU15+'QTR Raw'!AU21+'QTR Raw'!AU17+'QTR Raw'!AU18+'QTR Raw'!AU19+'QTR Raw'!AU16+'QTR Raw'!AU25 -> 112.82 | CT42: 412.69
A43: Depreciation | B43: =+'Annual Raw'!C31 -> 0 | C43: =+'Annual Raw'!D31 -> 0 | D43: =+'Annual Raw'!E31 -> 0 | E43: =+'Annual Raw'!F31 -> 0 | F43: =+'Annual Raw'!G31 -> 0 | G43: =+'Annual Raw'!H31 -> 0 | H43: =+'Annual Raw'!I31 -> 0 | I43: =+'Annual Raw'!J31 -> 0 | ... AA43: =+'Annual Raw'!AB31 -> 63.08 | AB43: =SUM(BZ43:CC43) -> 0 | AC43: =SUM(CD43:CG43) -> 0 | AD43: =SUM(CH43:CK43) -> 0 | AE43: =SUM(CL43:CO43) -> 0 | AH43: =+'QTR Raw'!D37 -> 0 | AI43: =+'QTR Raw'!E37 -> 0 | AJ43: =+'QTR Raw'!F37 -> 0 | AK43: =+'QTR Raw'!G37 -> 0 | AL43: =+'QTR Raw'!H37 -> 0 | AM43: =+'QTR Raw'!I37 -> 0 | AN43: =+'QTR Raw'!J37 -> 0 | AO43: =+'QTR Raw'!K37 -> 0 | ... BY43: =+'QTR Raw'!AU37 -> 15.69 | CT43: 63.09
A44: Advertisement & Sales Promotion | B44: =+'Annual Raw'!C22 -> 0 | C44: =+'Annual Raw'!D22 -> 0 | D44: =+'Annual Raw'!E22 -> 0 | E44: =+'Annual Raw'!F22 -> 0 | F44: =+'Annual Raw'!G22 -> 0 | G44: =+'Annual Raw'!H22 -> 0 | H44: =+'Annual Raw'!I22 -> 0 | I44: =+'Annual Raw'!J22 -> 0 | ... AA44: =+'Annual Raw'!AB22 -> 3.2 | AB44: =SUM(BZ44:CC44) -> 0 | AC44: =SUM(CD44:CG44) -> 0 | AD44: =SUM(CH44:CK44) -> 0 | AE44: =SUM(CL44:CO44) -> 0 | AH44: =+'QTR Raw'!D22 -> 0 | AI44: =+'QTR Raw'!E22 -> 0 | AJ44: =+'QTR Raw'!F22 -> 0 | AK44: =+'QTR Raw'!G22 -> 0 | AL44: =+'QTR Raw'!H22 -> 0 | AM44: =+'QTR Raw'!I22 -> 0 | AN44: =+'QTR Raw'!J22 -> 0 | AO44: =+'QTR Raw'!K22 -> 0 | ... BY44: =+'QTR Raw'!AU22 -> 0 | CT44: 0
A45: Other Expenses | AH45: =+'QTR Raw'!D23+'QTR Raw'!D24+'QTR Raw'!D26 -> 0 | AI45: =+'QTR Raw'!E23+'QTR Raw'!E24+'QTR Raw'!E26 -> 0 | AJ45: =+'QTR Raw'!F23+'QTR Raw'!F24+'QTR Raw'!F26 -> 0 | AK45: =+'QTR Raw'!G23+'QTR Raw'!G24+'QTR Raw'!G26 -> 0 | AL45: =+'QTR Raw'!H23+'QTR Raw'!H24+'QTR Raw'!H26 -> 0 | AM45: =+'QTR Raw'!I23+'QTR Raw'!I24+'QTR Raw'!I26 -> 0 | AN45: =+'QTR Raw'!J23+'QTR Raw'!J24+'QTR Raw'!J26 -> 0 | AO45: =+'QTR Raw'!K23+'QTR Raw'!K24+'QTR Raw'!K26 -> 0 | ... BY45: =+'QTR Raw'!AU23+'QTR Raw'!AU24+'QTR Raw'!AU26 -> 0
A46: TC | B46: =SUM(B41:B45) -> 0 | C46: =SUM(C41:C45) -> 0 | D46: =SUM(D41:D45) -> 0 | E46: =SUM(E41:E45) -> 0 | F46: =SUM(F41:F45) -> 0 | G46: =SUM(G41:G45) -> 0 | H46: =SUM(H41:H45) -> 0 | I46: =SUM(I41:I45) -> 0 | ... AE46: =SUM(AE41:AE45) -> 2301.6424 | AH46: =SUM(AH41:AH45) -> 0 | AI46: =SUM(AI41:AI45) -> 0 | AJ46: =SUM(AJ41:AJ45) -> 0 | AK46: =SUM(AK41:AK45) -> 0 | AL46: =SUM(AL41:AL45) -> 0 | AM46: =SUM(AM41:AM45) -> 0 | AN46: =SUM(AN41:AN45) -> 0 | AO46: =SUM(AO41:AO45) -> 0 | ... CO46: =SUM(CO41:CO45) -> 594.72373 | CT46: 1354.87
A47: PPP | B47: =+B39-B46 -> 0 | C47: =+C39-C46 -> 0 | D47: =+D39-D46 -> 0 | E47: =+E39-E46 -> 0 | F47: =+F39-F46 -> 0 | G47: =+G39-G46 -> 0 | H47: =+H39-H46 -> 0 | I47: =+I39-I46 -> 0 | ... AE47: =+AE39-AE46 -> 6246.5648 | AH47: =+AH39-AH46 -> 0 | AI47: =+AI39-AI46 -> 0 | AJ47: =+AJ39-AJ46 -> 0 | AK47: =+AK39-AK46 -> 0 | AL47: =+AL39-AL46 -> 0 | AM47: =+AM39-AM46 -> 0 | AN47: =+AN39-AN46 -> 0 | AO47: =+AO39-AO46 -> 0 | ... CO47: =+CO39-CO46 -> 1614.7302 | CT47: 2808.6
A48: YOY% | C48: =+IF(B47<0,1-C47/B47,C47/B47-1) -> #DIV/0! | D48: =+IF(C47<0,1-D47/C47,D47/C47-1) -> #DIV/0! | E48: =+IF(D47<0,1-E47/D47,E47/D47-1) -> #DIV/0! | F48: =+IF(E47<0,1-F47/E47,F47/E47-1) -> #DIV/0! | G48: =+IF(F47<0,1-G47/F47,G47/F47-1) -> #DIV/0! | H48: =+IF(G47<0,1-H47/G47,H47/G47-1) -> #DIV/0! | I48: =+IF(H47<0,1-I47/H47,I47/H47-1) -> #DIV/0! | J48: =+IF(I47<0,1-J47/I47,J47/I47-1) -> #DIV/0! | ... AE48: =+IF(AD47<0,1-AE47/AD47,AE47/AD47-1) -> 0.15318921 | AL48: =+IF(AH47<0,1-AL47/AH47,AL47/AH47-1) -> #DIV/0! | AM48: =+IF(AI47<0,1-AM47/AI47,AM47/AI47-1) -> #DIV/0! | AN48: =+IF(AJ47<0,1-AN47/AJ47,AN47/AJ47-1) -> #DIV/0! | AO48: =+IF(AK47<0,1-AO47/AK47,AO47/AK47-1) -> #DIV/0! | AP48: =+IF(AL47<0,1-AP47/AL47,AP47/AL47-1) -> #DIV/0! | AQ48: =+IF(AM47<0,1-AQ47/AM47,AQ47/AM47-1) -> #DIV/0! | AR48: =+IF(AN47<0,1-AR47/AN47,AR47/AN47-1) -> #DIV/0! | AS48: =+IF(AO47<0,1-AS47/AO47,AS47/AO47-1) -> #DIV/0! | ... CO48: =+IF(CK47<0,1-CO47/CK47,CO47/CK47-1) -> 0.14903404 | CT48: 0.053199987
A49: Provisions and Contingencies | B49: =+'Annual Raw'!C23 -> 0 | C49: =+'Annual Raw'!D23 -> 0 | D49: =+'Annual Raw'!E23 -> 0 | E49: =+'Annual Raw'!F23 -> 0 | F49: =+'Annual Raw'!G23 -> 0 | G49: =+'Annual Raw'!H23 -> 0 | H49: =+'Annual Raw'!I23 -> 0 | I49: =+'Annual Raw'!J23 -> 0 | ... AA49: =+'Annual Raw'!AB23 -> 1805.73 | AB49: =SUM(BZ49:CC49) -> 1593.3688 | AC49: =SUM(CD49:CG49) -> 1832.0351 | AD49: =SUM(CH49:CK49) -> 2111.6432 | AE49: =SUM(CL49:CO49) -> 2431.1122 | AH49: =+'QTR Raw'!D36+'QTR Raw'!D27 -> 0 | AI49: =+'QTR Raw'!E36+'QTR Raw'!E27 -> 0 | AJ49: =+'QTR Raw'!F36+'QTR Raw'!F27 -> 0 | AK49: =+'QTR Raw'!G36+'QTR Raw'!G27 -> 0 | AL49: =+'QTR Raw'!H36+'QTR Raw'!H27 -> 0 | AM49: =+'QTR Raw'!I36+'QTR Raw'!I27 -> 0 | AN49: =+'QTR Raw'!J36+'QTR Raw'!J27 -> 0 | AO49: =+'QTR Raw'!K36+'QTR Raw'!K27 -> 0 | ... BY49: =+'QTR Raw'!AU36+'QTR Raw'!AU27 -> 335.31 | BZ49: =BZ20*BY5 -> 380.91088 | CA49: =CA20*BZ5 -> 400.22382 | CB49: =CB20*CA5 -> 401.25378 | CC49: =CC20*CB5 -> 410.98029 | CD49: =CD20*CC5 -> 439.08528 | CE49: =CE20*CD5 -> 458.68038 | CF49: =CF20*CE5 -> 461.10638 | CG49: =CG20*CF5 -> 473.16305 | ... CO49: =CO20*CN5 -> 628.17756 | CT49: 1775.4
A50: PBT | B50: =B47-B49 -> 0 | C50: =C47-C49 -> 0 | D50: =D47-D49 -> 0 | E50: =E47-E49 -> 0 | F50: =F47-F49 -> 0 | G50: =G47-G49 -> 0 | H50: =H47-H49 -> 0 | I50: =I47-I49 -> 0 | ... AE50: =AE47-AE49 -> 3815.4526 | AH50: =AH47-AH49 -> 0 | AI50: =AI47-AI49 -> 0 | AJ50: =AJ47-AJ49 -> 0 | AK50: =AK47-AK49 -> 0 | AL50: =AL47-AL49 -> 0 | AM50: =AM47-AM49 -> 0 | AN50: =AN47-AN49 -> 0 | AO50: =AO47-AO49 -> 0 | ... CO50: =CO47-CO49 -> 986.55267 | CT50: 1033.2
A51: Tax | B51: =+'Annual Raw'!C36 -> 0 | C51: =+'Annual Raw'!D36 -> 0 | D51: =+'Annual Raw'!E36 -> 0 | E51: =+'Annual Raw'!F36 -> 0 | F51: =+'Annual Raw'!G36 -> 0 | G51: =+'Annual Raw'!H36 -> 0 | H51: =+'Annual Raw'!I36 -> 0 | I51: =+'Annual Raw'!J36 -> 0 | ... AA51: =+'Annual Raw'!AB36 -> 255.56 | AB51: =SUM(BZ51:CC51) -> 537.99717 | AC51: =SUM(CD51:CG51) -> 728.47305 | AD51: =SUM(CH51:CK51) -> 859.3339 | AE51: =SUM(CL51:CO51) -> 992.01768 | AH51: =+'QTR Raw'!D38 -> 0 | AI51: =+'QTR Raw'!E38 -> 0 | AJ51: =+'QTR Raw'!F38 -> 0 | AK51: =+'QTR Raw'!G38 -> 0 | AL51: =+'QTR Raw'!H38 -> 0 | AM51: =+'QTR Raw'!I38 -> 0 | AN51: =+'QTR Raw'!J38 -> 0 | AO51: =+'QTR Raw'!K38 -> 0 | ... BY51: =+'QTR Raw'!AU38 -> 105.45 | BZ51: =BZ50*0.26 -> 100.45309 | CA51: =CA50*0.26 -> 134.84954 | CB51: =CB50*0.26 -> 143.95794 | CC51: =CC50*0.26 -> 158.73661 | CD51: =CD50*0.26 -> 161.2226 | CE51: =CE50*0.26 -> 180.46319 | CF51: =CF50*0.26 -> 188.00754 | CG51: =CG50*0.26 -> 198.77972 | ... CO51: =CO50*0.26 -> 256.50369 | CT51: 255.56
A52: PAT | B52: =B50-B51 -> 0 | C52: =C50-C51 -> 0 | D52: =D50-D51 -> 0 | E52: =E50-E51 -> 0 | F52: =F50-F51 -> 0 | G52: =G50-G51 -> 0 | H52: =H50-H51 -> 0 | I52: =I50-I51 -> 0 | ... AE52: =AE50-AE51 -> 2823.4349 | AH52: =AH50-AH51 -> 0 | AI52: =AI50-AI51 -> 0 | AJ52: =AJ50-AJ51 -> 0 | AK52: =AK50-AK51 -> 0 | AL52: =AL50-AL51 -> 0 | AM52: =AM50-AM51 -> 0 | AN52: =AN50-AN51 -> 0 | AO52: =AO50-AO51 -> 0 | ... CO52: =CO50-CO51 -> 730.04897 | CT52: 777.64
A53: Minority Interest | B53: =+'Annual Raw'!C42 -> 0 | C53: =+'Annual Raw'!D42 -> 0 | D53: =+'Annual Raw'!E42 -> 0 | E53: =+'Annual Raw'!F42 -> 0 | F53: =+'Annual Raw'!G42 -> 0 | G53: =+'Annual Raw'!H42 -> 0 | H53: =+'Annual Raw'!I42 -> 0 | I53: =+'Annual Raw'!J42 -> 0 | ... AA53: =+'Annual Raw'!AB42 -> 0 | AB53: =SUM(BZ53:CC53) -> 0 | AC53: =SUM(CD53:CG53) -> 0 | AD53: =SUM(CH53:CK53) -> 0 | AE53: =SUM(CL53:CO53) -> 0 | AH53: =+'QTR Raw'!D39 -> 0 | AI53: =+'QTR Raw'!E39 -> 0 | AJ53: =+'QTR Raw'!F39 -> 0 | AK53: =+'QTR Raw'!G39 -> 0 | AL53: =+'QTR Raw'!H39 -> 0 | AM53: =+'QTR Raw'!I39 -> 0 | AN53: =+'QTR Raw'!J39 -> 0 | AO53: =+'QTR Raw'!K39 -> 0 | ... BY53: =+'QTR Raw'!AU39 -> 0 | BZ53: =+BY53 -> 0 | CA53: =+BZ53 -> 0 | CB53: =+CA53 -> 0 | CC53: =+CB53 -> 0 | CD53: =+CC53 -> 0 | CE53: =+CD53 -> 0 | CF53: =+CE53 -> 0 | CG53: =+CF53 -> 0 | ... CO53: =+CN53 -> 0 | CT53: 0
A54: Share of Associates | B54: =+'Annual Raw'!C43 -> 0 | C54: =+'Annual Raw'!D43 -> 0 | D54: =+'Annual Raw'!E43 -> 0 | E54: =+'Annual Raw'!F43 -> 0 | F54: =+'Annual Raw'!G43 -> 0 | G54: =+'Annual Raw'!H43 -> 0 | H54: =+'Annual Raw'!I43 -> 0 | I54: =+'Annual Raw'!J43 -> 0 | ... AA54: =+'Annual Raw'!AB43 -> 0 | AB54: =SUM(BZ54:CC54) -> 0 | AC54: =SUM(CD54:CG54) -> 0 | AD54: =SUM(CH54:CK54) -> 0 | AE54: =SUM(CL54:CO54) -> 0 | AH54: =+'QTR Raw'!D40 -> 0 | AI54: =+'QTR Raw'!E40 -> 0 | AJ54: =+'QTR Raw'!F40 -> 0 | AK54: =+'QTR Raw'!G40 -> 0 | AL54: =+'QTR Raw'!H40 -> 0 | AM54: =+'QTR Raw'!I40 -> 0 | AN54: =+'QTR Raw'!J40 -> 0 | AO54: =+'QTR Raw'!K40 -> 0 | ... BY54: =+'QTR Raw'!AU40 -> 0 | BZ54: =+BY54 -> 0 | CA54: =+BZ54 -> 0 | CB54: =+CA54 -> 0 | CC54: =+CB54 -> 0 | CD54: =+CC54 -> 0 | CE54: =+CD54 -> 0 | CF54: =+CE54 -> 0 | CG54: =+CF54 -> 0 | ... CO54: =+CN54 -> 0 | CT54: 0
A55: Exceptional Income/Expenses | B55: =+'Annual Raw'!C34+'Annual Raw'!C44+'Annual Raw'!C33+'Annual Raw'!C40 -> 0 | C55: =+'Annual Raw'!D34+'Annual Raw'!D44+'Annual Raw'!D33+'Annual Raw'!D40 -> 0 | D55: =+'Annual Raw'!E34+'Annual Raw'!E44+'Annual Raw'!E33+'Annual Raw'!E40 -> 0 | E55: =+'Annual Raw'!F34+'Annual Raw'!F44+'Annual Raw'!F33+'Annual Raw'!F40 -> 0 | F55: =+'Annual Raw'!G34+'Annual Raw'!G44+'Annual Raw'!G33+'Annual Raw'!G40 -> 0 | G55: =+'Annual Raw'!H34+'Annual Raw'!H44+'Annual Raw'!H33+'Annual Raw'!H40 -> 0 | H55: =+'Annual Raw'!I34+'Annual Raw'!I44+'Annual Raw'!I33+'Annual Raw'!I40 -> 0 | I55: =+'Annual Raw'!J34+'Annual Raw'!J44+'Annual Raw'!J33+'Annual Raw'!J40 -> 0 | ... AA55: =+'Annual Raw'!AB34+'Annual Raw'!AB44+'Annual Raw'!AB33+'Annual Raw'!AB40 -> 0 | AH55: =+'QTR Raw'!D41+'QTR Raw'!D34+'QTR Raw'!D35 -> 0 | AI55: =+'QTR Raw'!E41+'QTR Raw'!E34+'QTR Raw'!E35 -> 0 | AJ55: =+'QTR Raw'!F41+'QTR Raw'!F34+'QTR Raw'!F35 -> 0 | AK55: =+'QTR Raw'!G41+'QTR Raw'!G34+'QTR Raw'!G35 -> 0 | AL55: =+'QTR Raw'!H41+'QTR Raw'!H34+'QTR Raw'!H35 -> 0 | AM55: =+'QTR Raw'!I41+'QTR Raw'!I34+'QTR Raw'!I35 -> 0 | AN55: =+'QTR Raw'!J41+'QTR Raw'!J34+'QTR Raw'!J35 -> 0 | AO55: =+'QTR Raw'!K41+'QTR Raw'!K34+'QTR Raw'!K35 -> 0 | ... BY55: =+'QTR Raw'!AU41+'QTR Raw'!AU34+'QTR Raw'!AU35 -> 0 | CT55: 0
A56: Consolidated Net Profit | B56: =B52+B53+B54+B55 -> 0 | C56: =C52+C53+C54+C55 -> 0 | D56: =D52+D53+D54+D55 -> 0 | E56: =E52+E53+E54+E55 -> 0 | F56: =F52+F53+F54+F55 -> 0 | G56: =G52+G53+G54+G55 -> 0 | H56: =H52+H53+H54+H55 -> 0 | I56: =I52+I53+I54+I55 -> 0 | ... AA56: =AA52+AA53+AA54+AA55 -> 777.64 | AB56: =AB52+AB53+AB54 -> 1531.2227 | AC56: =AC52+AC53+AC54 -> 2073.3464 | AD56: =AD52+AD53+AD54 -> 2445.7965 | AE56: =AE52+AE53+AE54 -> 2823.4349 | AH56: =AH52+AH53+AH54+AH55 -> 0 | AI56: =AI52+AI53+AI54+AI55 -> 0 | AJ56: =AJ52+AJ53+AJ54+AJ55 -> 0 | AK56: =AK52+AK53+AK54+AK55 -> 0 | AL56: =AL52+AL53+AL54+AL55 -> 0 | AM56: =AM52+AM53+AM54+AM55 -> 0 | AN56: =AN52+AN53+AN54+AN55 -> 0 | AO56: =AO52+AO53+AO54+AO55 -> 0 | ... BY56: =BY52+BY53+BY54+BY55 -> 339.55 | BZ56: =BZ52+BZ53+BZ54 -> 285.90494 | CA56: =CA52+CA53+CA54 -> 383.80253 | CB56: =CB52+CB53+CB54 -> 409.72644 | CC56: =CC52+CC53+CC54 -> 451.78881 | CD56: =CD52+CD53+CD54 -> 458.86431 | CE56: =CE52+CE53+CE54 -> 513.626 | CF56: =CF52+CF53+CF54 -> 535.09839 | CG56: =CG52+CG53+CG54 -> 565.75766 | ... CO56: =CO52+CO53+CO54 -> 730.04897 | CT56: 777.64
A57: YOY% | C57: =+IF(B56<0,1-C56/B56,C56/B56-1) -> #DIV/0! | D57: =+IF(C56<0,1-D56/C56,D56/C56-1) -> #DIV/0! | E57: =+IF(D56<0,1-E56/D56,E56/D56-1) -> #DIV/0! | F57: =+IF(E56<0,1-F56/E56,F56/E56-1) -> #DIV/0! | G57: =+IF(F56<0,1-G56/F56,G56/F56-1) -> #DIV/0! | H57: =+IF(G56<0,1-H56/G56,H56/G56-1) -> #DIV/0! | I57: =+IF(H56<0,1-I56/H56,I56/H56-1) -> #DIV/0! | J57: =+IF(I56<0,1-J56/I56,J56/I56-1) -> #DIV/0! | ... AE57: =+IF(AD56<0,1-AE56/AD56,AE56/AD56-1) -> 0.15440306 | AL57: =+IF(AH56<0,1-AL56/AH56,AL56/AH56-1) -> #DIV/0! | AM57: =+IF(AI56<0,1-AM56/AI56,AM56/AI56-1) -> #DIV/0! | AN57: =+IF(AJ56<0,1-AN56/AJ56,AN56/AJ56-1) -> #DIV/0! | AO57: =+IF(AK56<0,1-AO56/AK56,AO56/AK56-1) -> #DIV/0! | AP57: =+IF(AL56<0,1-AP56/AL56,AP56/AL56-1) -> #DIV/0! | AQ57: =+IF(AM56<0,1-AQ56/AM56,AQ56/AM56-1) -> #DIV/0! | AR57: =+IF(AN56<0,1-AR56/AN56,AR56/AN56-1) -> #DIV/0! | AS57: =+IF(AO56<0,1-AS56/AO56,AS56/AO56-1) -> #DIV/0! | ... CO57: =+IF(CK56<0,1-CO56/CK56,CO56/CK56-1) -> 0.14774678 | CT57: 0.46337975
A58: Profit & Loss- Annual (End)
A59: ACE | B59: =+'Annual Raw'!C45 -> 0 | C59: =+'Annual Raw'!D45 -> 0 | D59: =+'Annual Raw'!E45 -> 0 | E59: =+'Annual Raw'!F45 -> 0 | F59: =+'Annual Raw'!G45 -> 0 | G59: =+'Annual Raw'!H45 -> 0 | H59: =+'Annual Raw'!I45 -> 0 | I59: =+'Annual Raw'!J45 -> 0 | ... AA59: =+'Annual Raw'!AB45 -> 777.64 | AH59: =+'QTR Raw'!D45 -> 0 | AI59: =+'QTR Raw'!E45 -> 0 | AJ59: =+'QTR Raw'!F45 -> 0 | AK59: =+'QTR Raw'!G45 -> 0 | AL59: =+'QTR Raw'!H45 -> 0 | AM59: =+'QTR Raw'!I45 -> 0 | AN59: =+'QTR Raw'!J45 -> 0 | AO59: =+'QTR Raw'!K45 -> 0 | ... BY59: =+'QTR Raw'!AU45 -> 339.55 | CT59: 777.64
A60: Checksum - PAT | B60: =+B56-B59 -> 0 | C60: =+C56-C59 -> 0 | D60: =+D56-D59 -> 0 | E60: =+E56-E59 -> 0 | F60: =+F56-F59 -> 0 | G60: =+G56-G59 -> 0 | H60: =+H56-H59 -> 0 | I60: =+I56-I59 -> 0 | ... AA60: =+AA56-AA59 -> 0 | AH60: =+AH56-AH59 -> 0 | AI60: =+AI56-AI59 -> 0 | AJ60: =+AJ56-AJ59 -> 0 | AK60: =+AK56-AK59 -> 0 | AL60: =+AL56-AL59 -> 0 | AM60: =+AM56-AM59 -> 0 | AN60: =+AN56-AN59 -> 0 | AO60: =+AO56-AO59 -> 0 | ... BY60: =+BY56-BY59 -> 0 | CT60: 0
A61: Ratios (Start)
A62: Eq | B62: =+C62 -> 160.2 | C62: =+D62 -> 160.2 | D62: =+E62 -> 160.2 | E62: =+F62 -> 160.2 | F62: =+G62 -> 160.2 | G62: =+H62 -> 160.2 | H62: =+I62 -> 160.2 | I62: =+J62 -> 160.2 | ... AA62: =+AB62 -> 160.2 | AB62: =+CC62 -> 160.2 | AC62: =+CG62 -> 160.2 | AD62: =+CK62 -> 160.2 | AE62: =+CO62 -> 160.2 | AH62: =+AI62 -> 159.88 | AI62: =+AJ62 -> 159.88 | AJ62: =+AK62 -> 159.88 | AK62: =+AL62 -> 159.88 | AL62: =+AM62 -> 159.88 | AM62: =+AN62 -> 159.88 | AN62: =+AO62 -> 159.88 | AO62: =+AP62 -> 159.88 | ... BV62: =+BW62 -> 159.88 | BW62: =+'QTR Raw'!AS50 -> 159.88 | BX62: =+'QTR Raw'!AT50 -> 160.08 | BY62: =+'QTR Raw'!AU50 -> 160.2 | BZ62: =BZ103 -> 160.2 | CA62: =CA103 -> 160.2 | CB62: =CB103 -> 160.2 | CC62: =CC103 -> 160.2 | CD62: =CD103 -> 160.2 | CE62: =CE103 -> 160.2 | CF62: =CF103 -> 160.2 | CG62: =CG103 -> 160.2 | ... CO62: =CO103 -> 160.2 | CT62: 160.2
A63: FV | B63: =+C63 -> 10 | C63: =+D63 -> 10 | D63: =+E63 -> 10 | E63: =+F63 -> 10 | F63: =+G63 -> 10 | G63: =+H63 -> 10 | H63: =+I63 -> 10 | I63: =+J63 -> 10 | ... AA63: =+AB63 -> 10 | AB63: =+CC63 -> 10 | AC63: =+CG63 -> 10 | AD63: =+CK63 -> 10 | AE63: =+CO63 -> 10 | AH63: =+AI63 -> 10 | AI63: =+AJ63 -> 10 | AJ63: =+AK63 -> 10 | AK63: =+AL63 -> 10 | AL63: =+AM63 -> 10 | AM63: =+AN63 -> 10 | AN63: =+AO63 -> 10 | AO63: =+AP63 -> 10 | ... BV63: =+BW63 -> 10 | BW63: =+'QTR Raw'!AS51 -> 10 | BX63: =+'QTR Raw'!AT51 -> 10 | BY63: =+'QTR Raw'!AU51 -> 10 | BZ63: =+BY63 -> 10 | CA63: =+BZ63 -> 10 | CB63: =+CA63 -> 10 | CC63: =+CB63 -> 10 | CD63: =+CC63 -> 10 | CE63: =+CD63 -> 10 | CF63: =+CE63 -> 10 | CG63: =+CF63 -> 10 | ... CO63: =+CN63 -> 10 | CT63: 10
A64: No of share | B64: =B62/B63 -> 16.02 | C64: =C62/C63 -> 16.02 | D64: =D62/D63 -> 16.02 | E64: =E62/E63 -> 16.02 | F64: =F62/F63 -> 16.02 | G64: =G62/G63 -> 16.02 | H64: =H62/H63 -> 16.02 | I64: =I62/I63 -> 16.02 | ... AE64: =AE62/AE63 -> 16.02 | AH64: =AH62/AH63 -> 15.988 | AI64: =AI62/AI63 -> 15.988 | AJ64: =AJ62/AJ63 -> 15.988 | AK64: =AK62/AK63 -> 15.988 | AL64: =AL62/AL63 -> 15.988 | AM64: =AM62/AM63 -> 15.988 | AN64: =AN62/AN63 -> 15.988 | AO64: =AO62/AO63 -> 15.988 | ... CO64: =CO62/CO63 -> 16.02 | CT64: 16.02
A65: EPS | B65: =B56/B64 -> 0 | C65: =C56/C64 -> 0 | D65: =D56/D64 -> 0 | E65: =E56/E64 -> 0 | F65: =F56/F64 -> 0 | G65: =G56/G64 -> 0 | H65: =H56/H64 -> 0 | I65: =I56/I64 -> 0 | ... AE65: =AE56/AE64 -> 176.24438 | AH65: =AH56/AH64 -> 0 | AI65: =AI56/AI64 -> 0 | AJ65: =AJ56/AJ64 -> 0 | AK65: =AK56/AK64 -> 0 | AL65: =AL56/AL64 -> 0 | AM65: =AM56/AM64 -> 0 | AN65: =AN56/AN64 -> 0 | AO65: =AO56/AO64 -> 0 | ... CO65: =CO56/CO64 -> 45.571097 | CT65: 48.541823
A66: EPS TTM | B66: =+B65 -> 0 | C66: =+C65 -> 0 | D66: =+D65 -> 0 | E66: =+E65 -> 0 | F66: =+F65 -> 0 | G66: =+G65 -> 0 | H66: =+H65 -> 0 | I66: =+I65 -> 0 | ... AE66: =+AE65 -> 176.24438 | AO66: =AO65+AN65+AM65+AL65 -> 0 | AP66: =AP65+AO65+AN65+AM65 -> 0 | AQ66: =AQ65+AP65+AO65+AN65 -> 3.8172379 | AR66: =AR65+AQ65+AP65+AO65 -> 7.8427571 | AS66: =AS65+AR65+AQ65+AP65 -> 12.327996 | AT66: =AT65+AS65+AR65+AQ65 -> 16.845134 | AU66: =AU65+AT65+AS65+AR65 -> 17.622592 | AV66: =AV65+AU65+AT65+AS65 -> 19.835502 | ... CO66: =CO65+CN65+CM65+CL65 -> 176.24438 | CT66: 48.541823
A67: Bloomberg Estimate | CC67: 89.8 | CG67: 114.4
A68: Estimate Deviation | CC68: =+CC66/CC67-1 -> 0.064386886 | CG68: =+CG66/CG67-1 -> 0.13131442
A69: BVPS | B69: =B106/B64 -> 0 | C69: =C106/C64 -> 0 | D69: =D106/D64 -> 0 | E69: =E106/E64 -> 0 | F69: =F106/F64 -> 0 | G69: =G106/G64 -> 0 | H69: =H106/H64 -> 0 | I69: =I106/I64 -> 0 | ... AE69: =AE106/AE64 -> 1043.4488 | AH69: =AH106/AH64 -> 0 | AI69: =AI106/AI64 -> 0 | AJ69: =AJ106/AJ64 -> 0 | AK69: =AK106/AK64 -> 0 | AL69: =AL106/AL64 -> 0 | AM69: =AM106/AM64 -> 0 | AN69: =AN106/AN64 -> 0 | AO69: =AO106/AO64 -> 0 | ... CO69: =CO106/CO64 -> 1043.4488 | CT69: 489.52871
A70: ABVPS | C70: =+C69-C74 -> 0 | D70: =+D69-D74 -> 0 | E70: =+E69-E74 -> 0 | F70: =+F69-F74 -> 0 | G70: =+G69-G74 -> 0 | H70: =+H69-H74 -> 0 | I70: =+I69-I74 -> 0 | J70: =+J69-J74 -> 1.3606325 | ... AE70: =+AE69-AE74 -> 1043.4488 | AH70: =+AH69-AH74 -> 0 | AI70: =+AI69-AI74 -> 0 | AJ70: =+AJ69-AJ74 -> 0 | AK70: =+AK69-AK74 -> 0 | AL70: =+AL69-AL74 -> 0 | AM70: =+AM69-AM74 -> 0 | AN70: =+AN69-AN74 -> 0 | AO70: =+AO69-AO74 -> 0 | ... CO70: =+CO69-CO74 -> 1043.4488 | CT70: 489.52871
A72: GNPA | B72: =+'Annual Raw'!C150 -> 0 | C72: =+'Annual Raw'!D150 -> 0 | D72: =+'Annual Raw'!E150 -> 0 | E72: =+'Annual Raw'!F150 -> 0 | F72: =+'Annual Raw'!G150 -> 0 | G72: =+'Annual Raw'!H150 -> 0 | H72: =+'Annual Raw'!I150 -> 0 | I72: =+'Annual Raw'!J150 -> 0 | ... AA72: =+'Annual Raw'!AB150 -> 922.25 | CT72: 922.25
A73: NNPA | B73: =+'Annual Raw'!C151 -> 0 | C73: =+'Annual Raw'!D151 -> 0 | D73: =+'Annual Raw'!E151 -> 0 | E73: =+'Annual Raw'!F151 -> 0 | F73: =+'Annual Raw'!G151 -> 0 | G73: =+'Annual Raw'!H151 -> 0 | H73: =+'Annual Raw'!I151 -> 0 | I73: =+'Annual Raw'!J151 -> 0 | ... AA73: =+'Annual Raw'!AB151 -> 315.58 | BZ73: =+BZ77*BZ120 -> 0 | CA73: =+CA77*CA120 -> 0 | CB73: =+CB77*CB120 -> 0 | CC73: =+CC77*CC120 -> 0 | CD73: =+CD77*CD120 -> 0 | CE73: =+CE77*CE120 -> 0 | CF73: =+CF77*CF120 -> 0 | CG73: =+CG77*CG120 -> 0 | ... CO73: =+CO77*CO120 -> 0 | CT73: 315.58
A74: NNPA Per Share | C74: =+C73/C64 -> 0 | D74: =+D73/D64 -> 0 | E74: =+E73/E64 -> 0 | F74: =+F73/F64 -> 0 | G74: =+G73/G64 -> 0 | H74: =+H73/H64 -> 0 | I74: =+I73/I64 -> 0 | J74: =+J73/J64 -> 0 | ... AA74: =+AA73/AA64 -> 19.699126 | BZ74: =+BZ73/BZ64 -> 0 | CA74: =+CA73/CA64 -> 0 | CB74: =+CB73/CB64 -> 0 | CC74: =+CC73/CC64 -> 0 | CD74: =+CD73/CD64 -> 0 | CE74: =+CE73/CE64 -> 0 | CF74: =+CF73/CF64 -> 0 | CG74: =+CG73/CG64 -> 0 | ... CO74: =+CO73/CO64 -> 0
A76: GNPA % | B76: =+B72/B120 -> #DIV/0! | C76: =+C72/C120 -> #DIV/0! | D76: =+D72/D120 -> #DIV/0! | E76: =+E72/E120 -> #DIV/0! | F76: =+F72/F120 -> #DIV/0! | G76: =+G72/G120 -> #DIV/0! | H76: =+H72/H120 -> #DIV/0! | I76: =+I72/I120 -> #DIV/0! | ... AA76: =+AA72/AA120 -> 0.031640836 | AI76: =+AI72/AI120 -> #DIV/0! | AJ76: =+AJ72/AJ120 -> #DIV/0! | AK76: =+AK72/AK120 -> #DIV/0! | AL76: =+AL72/AL120 -> #DIV/0! | AM76: =+AM72/AM120 -> #DIV/0! | AN76: =+AN72/AN120 -> #DIV/0! | AO76: =+AO72/AO120 -> #DIV/0! | AP76: =+AP72/AP120 -> #DIV/0! | ... BY76: =+BY72/BY120 -> 0 | CT76: 0.031640836
A77: NNPA % | B77: =+B73/B120 -> #DIV/0! | C77: =+C73/C120 -> #DIV/0! | D77: =+D73/D120 -> #DIV/0! | E77: =+E73/E120 -> #DIV/0! | F77: =+F73/F120 -> #DIV/0! | G77: =+G73/G120 -> #DIV/0! | H77: =+H73/H120 -> #DIV/0! | I77: =+I73/I120 -> #DIV/0! | ... AA77: =+AA73/AA120 -> 0.010827015 | AI77: =+AI73/AI120 -> #DIV/0! | AJ77: =+AJ73/AJ120 -> #DIV/0! | AK77: =+AK73/AK120 -> #DIV/0! | AL77: =+AL73/AL120 -> #DIV/0! | AM77: =+AM73/AM120 -> #DIV/0! | AN77: =+AN73/AN120 -> #DIV/0! | AO77: =+AO73/AO120 -> #DIV/0! | AP77: =+AP73/AP120 -> #DIV/0! | ... BY77: =+BY73/BY120 -> 0 | BZ77: =+BY77 -> 0 | CA77: =+BZ77 -> 0 | CB77: =+CA77 -> 0 | CC77: =+CB77 -> 0 | CD77: =+CC77 -> 0 | CE77: =+CD77 -> 0 | CF77: =+CE77 -> 0 | CG77: =+CF77 -> 0 | ... CO77: =+CN77 -> 0 | CT77: 0.010827015
A80: NIIM % | D80: =+D37/D82 -> #DIV/0! | E80: =+E37/E82 -> #DIV/0! | F80: =+F37/F82 -> #DIV/0! | G80: =+G37/G82 -> #DIV/0! | H80: =+H37/H82 -> #DIV/0! | I80: =+I37/I82 -> #DIV/0! | J80: =+J37/J82 -> 0.18146994 | K80: =+K37/K82 -> 0.13950294 | ... AA80: =+AA37/AA82 -> 0.1458613 | AI80: =+AI37/AI82*4 -> #DIV/0! | AJ80: =+AJ37/AJ82*4 -> #DIV/0! | AK80: =+AK37/AK82*4 -> #DIV/0! | AL80: =+AL37/AL82*4 -> #DIV/0! | AM80: =+AM37/AM82*4 -> #DIV/0! | AN80: =+AN37/AN82*4 -> #DIV/0! | AO80: =+AO37/AO82*4 -> #DIV/0! | AP80: =+AP37/AP82*4 -> #DIV/0! | ... CO80: =+CO37/CO82*4 -> 0.1723885 | CT80: 0.1458613
A81: Earning Asset | B81: =+B131+B120+B148 -> 0 | C81: =+C131+C120+C148 -> 0 | D81: =+D131+D120+D148 -> 0 | E81: =+E131+E120+E148 -> 0 | F81: =+F131+F120+F148 -> 0 | G81: =+G131+G120+G148 -> 0 | H81: =+H131+H120+H148 -> 0 | I81: =+I131+I120+I148 -> 0 | ... AA81: =+AA131+AA120+AA148 -> 30222.81 | AI81: =+AI131+AI120+AI148 -> 0 | AJ81: =+AJ131+AJ120+AJ148 -> 0 | AK81: =+AK131+AK120+AK148 -> 0 | AL81: =+AL131+AL120+AL148 -> 0 | AM81: =+AM131+AM120+AM148 -> 0 | AN81: =+AN131+AN120+AN148 -> 0 | AO81: =+AO131+AO120+AO148 -> 0 | AP81: =+AP131+AP120+AP148 -> 0 | ... CO81: =+CO131+CO120+CO148 -> 53694.828 | CT81: 30222.81
A82: Average Earning Asset | D82: =+AVERAGE(C81:D81) -> 0 | E82: =+AVERAGE(D81:E81) -> 0 | F82: =+AVERAGE(E81:F81) -> 0 | G82: =+AVERAGE(F81:G81) -> 0 | H82: =+AVERAGE(G81:H81) -> 0 | I82: =+AVERAGE(H81:I81) -> 0 | J82: =+AVERAGE(I81:J81) -> 93.298277 | K82: =+AVERAGE(J81:K81) -> 213.62255 | ... AA82: =+AVERAGE(Z81:AA81) -> 28477.67 | AI82: =+AVERAGE(AH81:AI81) -> 0 | AJ82: =+AVERAGE(AI81:AJ81) -> 0 | AK82: =+AVERAGE(AJ81:AK81) -> 0 | AL82: =+AVERAGE(AK81:AL81) -> 0 | AM82: =+AVERAGE(AL81:AM81) -> 0 | AN82: =+AVERAGE(AM81:AN81) -> 0 | AO82: =+AVERAGE(AN81:AO81) -> 0 | AP82: =+AVERAGE(AO81:AP81) -> 0 | ... CO82: =+AVERAGE(CN81:CO81) -> 51228.559 | CT82: 28477.67
A83: ROE % | D83: =D56/D106 -> #DIV/0! | E83: =E56/E106 -> #DIV/0! | F83: =F56/F106 -> #DIV/0! | G83: =G56/G106 -> #DIV/0! | H83: =H56/H106 -> #DIV/0! | I83: =I56/I106 -> #DIV/0! | J83: =J56/J106 -> 0.022222963 | K83: =K56/K106 -> 0.018821462 | ... AE83: =AE56/AE106 -> 0.16890562 | CT83: 0.099160318
A85: Ratios (End)
A86: Valuation (Start)
A88: Share Price
A89: Close | B89: =+'Annual Raw'!C59 -> 0 | C89: =+'Annual Raw'!D59 -> 0 | D89: =+'Annual Raw'!E59 -> 0 | E89: =+'Annual Raw'!F59 -> 0 | F89: =+'Annual Raw'!G59 -> 0 | G89: =+'Annual Raw'!H59 -> 0 | H89: =+'Annual Raw'!I59 -> 0 | I89: =+'Annual Raw'!J59 -> 0 | ... AA89: =+'Annual Raw'!AB59 -> 1155.35 | AB89: =+CC89 -> 1181 | AC89: =+CG89 -> 1181 | AD89: =+CK89 -> 1181 | AE89: =+CO89 -> 1181 | AH89: =+'QTR Share Price'!IA21 -> 0 | AI89: =+'QTR Share Price'!IB21 -> 0 | AJ89: =+'QTR Share Price'!IC21 -> 0 | AK89: =+'QTR Share Price'!ID21 -> 0 | AL89: =+'QTR Share Price'!IE21 -> 0 | AM89: =+'QTR Share Price'!IF21 -> 0 | AN89: =+'QTR Share Price'!IG21 -> 0 | AO89: =+'QTR Share Price'!IH21 -> 0 | ... BY89: =+'QTR Share Price'!JR21 -> 1155.35 | BZ89: 1181 | CA89: =+BZ89 -> 1181 | CB89: =+CA89 -> 1181 | CC89: =+CB89 -> 1181 | CD89: =+CC89 -> 1181 | CE89: =+CD89 -> 1181 | CF89: =+CE89 -> 1181 | CG89: =+CF89 -> 1181 | CH89: =+CG89 -> 1181 | ... CO89: =+CN89 -> 1181 | CT89: 1155.35
A90: High | B90: =+'Annual Raw'!C60 -> 0 | C90: =+'Annual Raw'!D60 -> 0 | D90: =+'Annual Raw'!E60 -> 0 | E90: =+'Annual Raw'!F60 -> 0 | F90: =+'Annual Raw'!G60 -> 0 | G90: =+'Annual Raw'!H60 -> 0 | H90: =+'Annual Raw'!I60 -> 0 | I90: =+'Annual Raw'!J60 -> 0 | ... AA90: =+'Annual Raw'!AB60 -> 1496.6 | AB90: =+MAX(BZ90:CC90) -> 1788.8156 | AC90: =+MAX(CD90:CG90) -> 2184.4891 | AD90: =+MAX(CH90:CK90) -> 2651.2402 | AE90: =+MAX(CL90:CO90) -> 3190.0591 | AH90: =+'QTR Share Price'!IA19 -> 0 | AI90: =+'QTR Share Price'!IB19 -> 0 | AJ90: =+'QTR Share Price'!IC19 -> 0 | AK90: =+'QTR Share Price'!ID19 -> 0 | AL90: =+'QTR Share Price'!IE19 -> 0 | AM90: =+'QTR Share Price'!IF19 -> 0 | AN90: =+'QTR Share Price'!IG19 -> 0 | AO90: =+'QTR Share Price'!IH19 -> 0 | ... BY90: =+'QTR Share Price'!JR19 -> 1496.6 | BZ90: =+BZ98*BZ70 -> 1551.1616 | CA90: =+CA98*CA70 -> 1624.4057 | CB90: =+CB98*CB70 -> 1702.5971 | CC90: =+CC98*CC70 -> 1788.8156 | CD90: =+CD98*CD70 -> 1876.3844 | CE90: =+CE98*CE70 -> 1974.4038 | CF90: =+CF98*CF70 -> 2076.521 | CG90: =+CG98*CG70 -> 2184.4891 | ... CO90: =+CO98*CO70 -> 3190.0591 | CT90: 1496.6
A91: Low | B91: =+'Annual Raw'!C61 -> 0 | C91: =+'Annual Raw'!D61 -> 0 | D91: =+'Annual Raw'!E61 -> 0 | E91: =+'Annual Raw'!F61 -> 0 | F91: =+'Annual Raw'!G61 -> 0 | G91: =+'Annual Raw'!H61 -> 0 | H91: =+'Annual Raw'!I61 -> 0 | I91: =+'Annual Raw'!J61 -> 0 | ... AA91: =+'Annual Raw'!AB61 -> 860 | AB91: =+MIN(BZ91:CC91) -> 1153.473 | AC91: =+MIN(CD91:CG91) -> 1395.3148 | AD91: =+MIN(CH91:CK91) -> 1706.2927 | AE91: =+MIN(CL91:CO91) -> 2067.2144 | AH91: =+'QTR Share Price'!IA20 -> 0 | AI91: =+'QTR Share Price'!IB20 -> 0 | AJ91: =+'QTR Share Price'!IC20 -> 0 | AK91: =+'QTR Share Price'!ID20 -> 0 | AL91: =+'QTR Share Price'!IE20 -> 0 | AM91: =+'QTR Share Price'!IF20 -> 0 | AN91: =+'QTR Share Price'!IG20 -> 0 | AO91: =+'QTR Share Price'!IH20 -> 0 | ... BY91: =+'QTR Share Price'!JR20 -> 1112.9 | BZ91: =+BZ99*BZ70 -> 1153.473 | CA91: =+CA99*CA70 -> 1207.9387 | CB91: =+CB99*CB70 -> 1266.0833 | CC91: =+CC99*CC70 -> 1330.197 | CD91: =+CD99*CD70 -> 1395.3148 | CE91: =+CE99*CE70 -> 1468.2039 | CF91: =+CF99*CF70 -> 1544.1402 | CG91: =+CG99*CG70 -> 1624.4273 | ... CO91: =+CO99*CO70 -> 2372.1882 | CT91: 860
A93: Upside (%) | BZ93: =+BZ90/BZ89-1 -> 0.31343061 | CA93: =+CA90/CA89-1 -> 0.37544936 | CB93: =+CB90/CB89-1 -> 0.44165716 | CC93: =+CC90/CC89-1 -> 0.51466183 | CD93: =+CD90/CD89-1 -> 0.58880983 | CE93: =+CE90/CE89-1 -> 0.67180678 | CF93: =+CF90/CF89-1 -> 0.75827347 | CG93: =+CG90/CG89-1 -> 0.84969439 | ... CO93: =+CO90/CO89-1 -> 1.7011508
A94: Downside (%) | BZ94: =+BZ91/BZ89-1 -> -0.023308214 | CA94: =+CA91/CA89-1 -> 0.022810097 | CB94: =+CB91/CB89-1 -> 0.072043466 | CC94: =+CC91/CC89-1 -> 0.12633111 | CD94: =+CD91/CD89-1 -> 0.18146897 | CE94: =+CE91/CE89-1 -> 0.24318707 | CF94: =+CF91/CF89-1 -> 0.30748533 | CG94: =+CG91/CG89-1 -> 0.37546765 | ... CO94: =+CO91/CO89-1 -> 1.0086267
A96: P/ABVPS
A97: Close | B97: =+B89/B70 -> #DIV/0! | C97: =+C89/C70 -> #DIV/0! | D97: =+D89/D70 -> #DIV/0! | E97: =+E89/E70 -> #DIV/0! | F97: =+F89/F70 -> #DIV/0! | G97: =+G89/G70 -> #DIV/0! | H97: =+H89/H70 -> #DIV/0! | I97: =+I89/I70 -> #DIV/0! | ... AE97: =+AE89/AE70 -> 1.1318236 | AH97: =+AH89/AH70 -> #DIV/0! | AI97: =+AI89/AI70 -> #DIV/0! | AJ97: =+AJ89/AJ70 -> #DIV/0! | AK97: =+AK89/AK70 -> #DIV/0! | AL97: =+AL89/AL70 -> #DIV/0! | AM97: =+AM89/AM70 -> #DIV/0! | AN97: =+AN89/AN70 -> #DIV/0! | AO97: =+AO89/AO70 -> #DIV/0! | ... CO97: =+CO89/CO70 -> 1.1318236 | CT97: 2.3601271
A98: High | B98: =B90/B65 -> #DIV/0! | C98: =C90/C65 -> #DIV/0! | D98: =D90/D70 -> #DIV/0! | E98: =E90/E70 -> #DIV/0! | F98: =F90/F70 -> #DIV/0! | G98: =G90/G70 -> #DIV/0! | H98: =H90/H70 -> #DIV/0! | I98: =I90/I70 -> #DIV/0! | J98: =J90/J70 -> 0 | K98: =K90/K70 -> 0 | ... AE98: =AE90/AE70 -> 3.0572262 | AH98: =AH90/AH70 -> #DIV/0! | AI98: =AI90/AI70 -> #DIV/0! | AJ98: =AJ90/AJ70 -> #DIV/0! | AK98: =AK90/AK70 -> #DIV/0! | AL98: =AL90/AL70 -> #DIV/0! | AM98: =AM90/AM70 -> #DIV/0! | AN98: =AN90/AN70 -> #DIV/0! | AO98: =AO90/AO70 -> #DIV/0! | ... BY98: =BY90/BY70 -> 3.0572262 | BZ98: =BY98 -> 3.0572262 | CA98: =BZ98 -> 3.0572262 | CB98: =CA98 -> 3.0572262 | CC98: =CB98 -> 3.0572262 | CD98: =CC98 -> 3.0572262 | CE98: =CD98 -> 3.0572262 | CF98: =CE98 -> 3.0572262 | CG98: =CF98 -> 3.0572262 | ... CO98: =CN98 -> 3.0572262 | CT98: 3.0572262
A99: Low | B99: =B91/B65 -> #DIV/0! | C99: =C91/C65 -> #DIV/0! | D99: =D91/D70 -> #DIV/0! | E99: =E91/E70 -> #DIV/0! | F99: =F91/F70 -> #DIV/0! | G99: =G91/G70 -> #DIV/0! | H99: =H91/H70 -> #DIV/0! | I99: =I91/I70 -> #DIV/0! | J99: =J91/J70 -> 0 | K99: =K91/K70 -> 0 | ... AE99: =AE91/AE70 -> 1.9811364 | AH99: =AH91/AH70 -> #DIV/0! | AI99: =AI91/AI70 -> #DIV/0! | AJ99: =AJ91/AJ70 -> #DIV/0! | AK99: =AK91/AK70 -> #DIV/0! | AL99: =AL91/AL70 -> #DIV/0! | AM99: =AM91/AM70 -> #DIV/0! | AN99: =AN91/AN70 -> #DIV/0! | AO99: =AO91/AO70 -> #DIV/0! | ... BY99: =BY91/BY70 -> 2.2734111 | BZ99: =BY99 -> 2.2734111 | CA99: =BZ99 -> 2.2734111 | CB99: =CA99 -> 2.2734111 | CC99: =CB99 -> 2.2734111 | CD99: =CC99 -> 2.2734111 | CE99: =CD99 -> 2.2734111 | CF99: =CE99 -> 2.2734111 | CG99: =CF99 -> 2.2734111 | ... CO99: =CN99 -> 2.2734111 | CT99: 1.7567917
A101: Valuation (End)
A102: Balance Sheet (Start)
A103: Share Capital | B103: =+'Annual Raw'!C77 -> 0 | C103: =+'Annual Raw'!D77 -> 0 | D103: =+'Annual Raw'!E77 -> 0 | E103: =+'Annual Raw'!F77 -> 0 | F103: =+'Annual Raw'!G77 -> 0 | G103: =+'Annual Raw'!H77 -> 0 | H103: =+'Annual Raw'!I77 -> 0 | I103: =+'Annual Raw'!J77 -> 0 | ... AA103: =+'Annual Raw'!AB77 -> 160.2 | AB103: =CC103 -> 160.2 | AC103: =CG103 -> 160.2 | AD103: =CK103 -> 160.2 | AE103: =CO103 -> 160.2 | AH103: =+'QTR Raw'!D54 -> 0 | AI103: =+'QTR Raw'!E54 -> 0 | AJ103: =+'QTR Raw'!F54 -> 0 | AK103: =+'QTR Raw'!G54 -> 0 | AL103: =+'QTR Raw'!H54 -> 0 | AM103: =+'QTR Raw'!I54 -> 0 | AN103: =+'QTR Raw'!J54 -> 0 | AO103: =+'QTR Raw'!K54 -> 0 | ... BM103: =+'QTR Raw'!AI54 -> 158.91 | BN103: =BM103 -> 158.91 | BO103: =+'QTR Raw'!AK54 -> 159.11 | BP103: =BO103 -> 159.11 | BQ103: =+'QTR Raw'!AM54 -> 159.38 | BR103: =BQ103 -> 159.38 | BS103: =+'QTR Raw'!AO54 -> 159.46 | BT103: =BS103 -> 159.46 | BU103: =+'QTR Raw'!AQ54 -> 159.72 | BV103: =BU103 -> 159.72 | BW103: =+'QTR Raw'!AS54 -> 159.88 | BX103: =BW103 -> 159.88 | BY103: =+'QTR Raw'!AU54 -> 160.2 | BZ103: =BY103 -> 160.2 | CA103: =BZ103 -> 160.2 | CB103: =CA103 -> 160.2 | CC103: =CB103 -> 160.2 | CD103: =CC103 -> 160.2 | CE103: =CD103 -> 160.2 | CF103: =CE103 -> 160.2 | CG103: =CF103 -> 160.2 | ... CO103: =CN103 -> 160.2 | CT103: 160.2
A104: Share Warrants & Outstandings | B104: =+'Annual Raw'!C78 -> 0 | C104: =+'Annual Raw'!D78 -> 0 | D104: =+'Annual Raw'!E78 -> 0 | E104: =+'Annual Raw'!F78 -> 0 | F104: =+'Annual Raw'!G78 -> 0 | G104: =+'Annual Raw'!H78 -> 0 | H104: =+'Annual Raw'!I78 -> 0 | I104: =+'Annual Raw'!J78 -> 0 | ... AA104: =+'Annual Raw'!AB78 -> 66.16 | AH104: =+'QTR Raw'!D55 -> 0 | AI104: =+'QTR Raw'!E55 -> 0 | AJ104: =+'QTR Raw'!F55 -> 0 | AK104: =+'QTR Raw'!G55 -> 0 | AL104: =+'QTR Raw'!H55 -> 0 | AM104: =+'QTR Raw'!I55 -> 0 | AN104: =+'QTR Raw'!J55 -> 0 | AO104: =+'QTR Raw'!K55 -> 0 | ... BW104: =+'QTR Raw'!AS55 -> 0 | BX104: =+BW104 -> 0 | BY104: =+'QTR Raw'!AU55 -> 0 | BZ104: =+BY104 -> 0 | CA104: =+BZ104 -> 0 | CB104: =+CA104 -> 0 | CC104: =+CB104 -> 0 | CD104: =+CC104 -> 0 | CE104: =+CD104 -> 0 | CF104: =+CE104 -> 0 | CG104: =+CF104 -> 0 | ... CO104: =+CN104 -> 0 | CT104: 66.16
A105: Total Reserves | B105: =+'Annual Raw'!C79 -> 0 | C105: =+'Annual Raw'!D79 -> 0 | D105: =+'Annual Raw'!E79 -> 0 | E105: =+'Annual Raw'!F79 -> 0 | F105: =+'Annual Raw'!G79 -> 0 | G105: =+'Annual Raw'!H79 -> 0 | H105: =+'Annual Raw'!I79 -> 0 | I105: =+'Annual Raw'!J79 -> 0 | ... AA105: =+'Annual Raw'!AB79 -> 7615.86 | AB105: =CC105 -> 9213.2727 | AC105: =CG105 -> 11286.619 | AD105: =CK105 -> 13732.416 | AE105: =CO105 -> 16555.85 | AH105: =+'QTR Raw'!D56 -> 0 | AI105: =+'QTR Raw'!E56 -> 0 | AJ105: =+'QTR Raw'!F56 -> 0 | AK105: =+'QTR Raw'!G56 -> 0 | AL105: =+'QTR Raw'!H56 -> 0 | AM105: =+'QTR Raw'!I56 -> 0 | AN105: =+'QTR Raw'!J56 -> 0 | AO105: =+'QTR Raw'!K56 -> 0 | ... BM105: =+'QTR Raw'!AI56 -> 4948.06 | BN105: =BM105+BN56 -> 5296.52 | BO105: =+'QTR Raw'!AK56 -> 5638.63 | BP105: =BO105+BP56 -> 5991.97 | BQ105: =+'QTR Raw'!AM56 -> 6410.6 | BR105: =BQ105+BR56 -> 6808.26 | BS105: =+'QTR Raw'!AO56 -> 6828.95 | BT105: =BS105+BT56 -> 6729.43 | BU105: =+'QTR Raw'!AQ56 -> 6796.25 | BV105: =BU105+BV56 -> 6856.44 | BW105: =+'QTR Raw'!AS56 -> 7004.5 | BX105: =BW105+BX56 -> 7256.59 | BY105: =+'QTR Raw'!AU56 -> 7682.05 | BZ105: =BY105+BZ56 -> 7967.9549 | CA105: =BZ105+CA56 -> 8351.7575 | CB105: =CA105+CB56 -> 8761.4839 | CC105: =CB105+CC56 -> 9213.2727 | CD105: =CC105+CD56 -> 9672.137 | CE105: =CD105+CE56 -> 10185.763 | CF105: =CE105+CF56 -> 10720.861 | CG105: =CF105+CG56 -> 11286.619 | ... CO105: =CN105+CO56 -> 16555.85 | CT105: 7682.05
A106: Shareholder's Funds | B106: =SUM(B103:B105) -> 0 | C106: =SUM(C103:C105) -> 0 | D106: =SUM(D103:D105) -> 0 | E106: =SUM(E103:E105) -> 0 | F106: =SUM(F103:F105) -> 0 | G106: =SUM(G103:G105) -> 0 | H106: =SUM(H103:H105) -> 0 | I106: =SUM(I103:I105) -> 0 | ... AE106: =SUM(AE103:AE105) -> 16716.05 | AH106: =SUM(AH103:AH105) -> 0 | AI106: =SUM(AI103:AI105) -> 0 | AJ106: =SUM(AJ103:AJ105) -> 0 | AK106: =SUM(AK103:AK105) -> 0 | AL106: =SUM(AL103:AL105) -> 0 | AM106: =SUM(AM103:AM105) -> 0 | AN106: =SUM(AN103:AN105) -> 0 | AO106: =SUM(AO103:AO105) -> 0 | ... CO106: =SUM(CO103:CO105) -> 16716.05 | CT106: 7842.25
A108: Minority Interest | B108: =+'Annual Raw'!C81 -> 0 | C108: =+'Annual Raw'!D81 -> 0 | D108: =+'Annual Raw'!E81 -> 0 | E108: =+'Annual Raw'!F81 -> 0 | F108: =+'Annual Raw'!G81 -> 0 | G108: =+'Annual Raw'!H81 -> 0 | H108: =+'Annual Raw'!I81 -> 0 | I108: =+'Annual Raw'!J81 -> 0 | ... AA108: =+'Annual Raw'!AB81 -> 0 | AB108: =CC108 -> 0 | AC108: =CG108 -> 0 | AD108: =CK108 -> 0 | AE108: =CO108 -> 0 | AH108: =+'QTR Raw'!D58 -> 0 | AI108: =+'QTR Raw'!E58 -> 0 | AJ108: =+'QTR Raw'!F58 -> 0 | AK108: =+'QTR Raw'!G58 -> 0 | AL108: =+'QTR Raw'!H58 -> 0 | AM108: =+'QTR Raw'!I58 -> 0 | AN108: =+'QTR Raw'!J58 -> 0 | AO108: =+'QTR Raw'!K58 -> 0 | ... BW108: =+'QTR Raw'!AS58 -> 0 | BX108: =BW108 -> 0 | BY108: =+'QTR Raw'!AU58 -> 0 | BZ108: =BY108 -> 0 | CA108: =BZ108 -> 0 | CB108: =CA108 -> 0 | CC108: =CB108 -> 0 | CD108: =CC108 -> 0 | CE108: =CD108 -> 0 | CF108: =CE108 -> 0 | CG108: =CF108 -> 0 | ... CO108: =CN108 -> 0 | CT108: 0
A110: Secured Loans | B110: =+'Annual Raw'!C83 -> 0 | C110: =+'Annual Raw'!D83 -> 0 | D110: =+'Annual Raw'!E83 -> 0 | E110: =+'Annual Raw'!F83 -> 0 | F110: =+'Annual Raw'!G83 -> 0 | G110: =+'Annual Raw'!H83 -> 0 | H110: =+'Annual Raw'!I83 -> 0 | I110: =+'Annual Raw'!J83 -> 0 | ... AA110: =+'Annual Raw'!AB83 -> 10712.13 | AH110: =+'QTR Raw'!D60 -> 0 | AI110: =+'QTR Raw'!E60 -> 0 | AJ110: =+'QTR Raw'!F60 -> 0 | AK110: =+'QTR Raw'!G60 -> 0 | AL110: =+'QTR Raw'!H60 -> 0 | AM110: =+'QTR Raw'!I60 -> 0 | AN110: =+'QTR Raw'!J60 -> 0 | AO110: =+'QTR Raw'!K60 -> 0 | ... BW110: =+'QTR Raw'!AS60 -> 0 | BY110: =+'QTR Raw'!AU60 -> 0 | CT110: 10712.13
A111: Unsecured Loans | B111: =+'Annual Raw'!C84 -> 0 | C111: =+'Annual Raw'!D84 -> 0 | D111: =+'Annual Raw'!E84 -> 0 | E111: =+'Annual Raw'!F84 -> 0 | F111: =+'Annual Raw'!G84 -> 0 | G111: =+'Annual Raw'!H84 -> 0 | H111: =+'Annual Raw'!I84 -> 0 | I111: =+'Annual Raw'!J84 -> 0 | ... AA111: =+'Annual Raw'!AB84 -> 0 | AH111: =+'QTR Raw'!D61 -> 0 | AI111: =+'QTR Raw'!E61 -> 0 | AJ111: =+'QTR Raw'!F61 -> 0 | AK111: =+'QTR Raw'!G61 -> 0 | AL111: =+'QTR Raw'!H61 -> 0 | AM111: =+'QTR Raw'!I61 -> 0 | AN111: =+'QTR Raw'!J61 -> 0 | AO111: =+'QTR Raw'!K61 -> 0 | ... BW111: =+'QTR Raw'!AS61 -> 0 | BY111: =+'QTR Raw'!AU61 -> 0 | CT111: 0
A112: Current Maturity | B112: =+SUM('Annual Raw'!C95:C98) -> 0 | C112: =+SUM('Annual Raw'!D95:D98) -> 0 | D112: =+SUM('Annual Raw'!E95:E98) -> 0 | E112: =+SUM('Annual Raw'!F95:F98) -> 0 | F112: =+SUM('Annual Raw'!G95:G98) -> 0 | G112: =+SUM('Annual Raw'!H95:H98) -> 0 | H112: =+SUM('Annual Raw'!I95:I98) -> 0 | I112: =+SUM('Annual Raw'!J95:J98) -> 0 | ... AA112: =+SUM('Annual Raw'!AB95:AB98) -> 0 | AH112: =+'QTR Raw'!D89 -> 0 | AI112: =+'QTR Raw'!E89 -> 0 | AJ112: =+'QTR Raw'!F89 -> 0 | AK112: =+'QTR Raw'!G89 -> 0 | AL112: =+'QTR Raw'!H89 -> 0 | AM112: =+'QTR Raw'!I89 -> 0 | AN112: =+'QTR Raw'!J89 -> 0 | AO112: =+'QTR Raw'!K89 -> 0 | ... BW112: =+'QTR Raw'!AS89 -> 0 | BY112: =+'QTR Raw'!AU89 -> 0 | CT112: 0
A113: Short Term Borrowings | B113: =+'Annual Raw'!C99 -> 0 | C113: =+'Annual Raw'!D99 -> 0 | D113: =+'Annual Raw'!E99 -> 0 | E113: =+'Annual Raw'!F99 -> 0 | F113: =+'Annual Raw'!G99 -> 0 | G113: =+'Annual Raw'!H99 -> 0 | H113: =+'Annual Raw'!I99 -> 0 | I113: =+'Annual Raw'!J99 -> 0 | ... AA113: =+'Annual Raw'!AB99 -> 12929 | AB113: =+CC113 -> 25615.855 | AC113: =+CG113 -> 28832.265 | AD113: =+CK113 -> 32449.916 | AE113: =+CO113 -> 36521.297 | AH113: =+'QTR Raw'!D86 -> 0 | AI113: =+'QTR Raw'!E86 -> 0 | AJ113: =+'QTR Raw'!F86 -> 0 | AK113: =+'QTR Raw'!G86 -> 0 | AL113: =+'QTR Raw'!H86 -> 0 | AM113: =+'QTR Raw'!I86 -> 0 | AN113: =+'QTR Raw'!J86 -> 0 | AO113: =+'QTR Raw'!K86 -> 0 | ... BS113: =+'QTR Raw'!AO86 -> 17199.52 | BT113: 19776 | BU113: =+'QTR Raw'!AQ86 -> 18878.73 | BV113: =+'QTR Raw'!AR86 -> 0 | BW113: =+'QTR Raw'!AS86 -> 18890.09 | BX113: 19776 | BY113: =+'QTR Raw'!AU86 -> 22728.88 | BZ113: =+BZ119*BZ162 -> 21993.044 | CA113: =+CA119*CA162 -> 22215.362 | CB113: =+CB119*CB162 -> 22674.501 | CC113: =+CC119*CC162 -> 25615.855 | CD113: =+CD119*CD162 -> 24735.366 | CE113: =+CE119*CE162 -> 25011.258 | CF113: =+CF119*CF162 -> 25514.988 | CG113: =+CG119*CG162 -> 28832.265 | ... CO113: =+CO119*CO162 -> 36521.297 | CT113: 22728.88
A114: Debt | B114: =SUM(B110:B113) -> 0 | C114: =SUM(C110:C113) -> 0 | D114: =SUM(D110:D113) -> 0 | E114: =SUM(E110:E113) -> 0 | F114: =SUM(F110:F113) -> 0 | G114: =SUM(G110:G113) -> 0 | H114: =SUM(H110:H113) -> 0 | I114: =SUM(I110:I113) -> 0 | ... AB114: =SUM(AB110:AB113) -> 25615.855 | AC114: =SUM(AC113:AC113) -> 28832.265 | AD114: =SUM(AD113:AD113) -> 32449.916 | AE114: =SUM(AE113:AE113) -> 36521.297 | AH114: =SUM(AH110:AH113) -> 0 | AI114: =SUM(AI110:AI113) -> 0 | AJ114: =SUM(AJ110:AJ113) -> 0 | AK114: =SUM(AK110:AK113) -> 0 | AL114: =SUM(AL110:AL113) -> 0 | AM114: =SUM(AM110:AM113) -> 0 | AN114: =SUM(AN110:AN113) -> 0 | AO114: =SUM(AO110:AO113) -> 0 | ... BU114: =SUM(BU110:BU113) -> 18878.73 | BV114: =BU114 -> 18878.73 | BW114: =SUM(BW110:BW113) -> 18890.09 | BX114: =SUM(BX110:BX113) -> 19776 | BY114: =SUM(BY110:BY113) -> 22728.88 | BZ114: =SUM(BZ110:BZ113) -> 21993.044 | CA114: =SUM(CA110:CA113) -> 22215.362 | CB114: =SUM(CB110:CB113) -> 22674.501 | CC114: =SUM(CC110:CC113) -> 25615.855 | CD114: =SUM(CD110:CD113) -> 24735.366 | ... CO114: =SUM(CO110:CO113) -> 36521.297 | CT114: 22728.88
A115: Sources of Funds | B115: =B114+B108+B106 -> 0 | C115: =C114+C108+C106 -> 0 | D115: =D114+D108+D106 -> 0 | E115: =E114+E108+E106 -> 0 | F115: =F114+F108+F106 -> 0 | G115: =G114+G108+G106 -> 0 | H115: =H114+H108+H106 -> 0 | I115: =I114+I108+I106 -> 0 | ... AE115: =AE114+AE108+AE106 -> 53237.348 | AH115: =AH114+AH108+AH106 -> 0 | AI115: =AI114+AI108+AI106 -> 0 | AJ115: =AJ114+AJ108+AJ106 -> 0 | AK115: =AK114+AK108+AK106 -> 0 | AL115: =AL114+AL108+AL106 -> 0 | AM115: =AM114+AM108+AM106 -> 0 | AN115: =AN114+AN108+AN106 -> 0 | AO115: =AO114+AO108+AO106 -> 0 | ... CO115: =CO114+CO108+CO106 -> 53237.348 | CT115: 30571.13
A118: Long Term Loans & Advances | B118: =+'Annual Raw'!C116 -> 0 | C118: =+'Annual Raw'!D116 -> 0 | D118: =+'Annual Raw'!E116 -> 0 | E118: =+'Annual Raw'!F116 -> 0 | F118: =+'Annual Raw'!G116 -> 0 | G118: =+'Annual Raw'!H116 -> 0 | H118: =+'Annual Raw'!I116 -> 0 | I118: =+'Annual Raw'!J116 -> 0 | ... AA118: =+'Annual Raw'!AB116 -> 1017.32 | AH118: =+'QTR Raw'!D76 -> 0 | AI118: =+'QTR Raw'!E76 -> 0 | AJ118: =+'QTR Raw'!F76 -> 0 | AK118: =+'QTR Raw'!G76 -> 0 | AL118: =+'QTR Raw'!H76 -> 0 | AM118: =+'QTR Raw'!I76 -> 0 | AN118: =+'QTR Raw'!J76 -> 0 | AO118: =+'QTR Raw'!K76 -> 0 | ... BW118: =+'QTR Raw'!AS76 -> 0 | BY118: =+'QTR Raw'!AU76 -> 0 | CT118: 1017.32
A119: Short Term Loans and Advances | B119: =+'Annual Raw'!C124+'Annual Raw'!C105 -> 0 | C119: =+'Annual Raw'!D124+'Annual Raw'!D105 -> 0 | D119: =+'Annual Raw'!E124+'Annual Raw'!E105 -> 0 | E119: =+'Annual Raw'!F124+'Annual Raw'!F105 -> 0 | F119: =+'Annual Raw'!G124+'Annual Raw'!G105 -> 0 | G119: =+'Annual Raw'!H124+'Annual Raw'!H105 -> 0 | H119: =+'Annual Raw'!I124+'Annual Raw'!I105 -> 0 | I119: =+'Annual Raw'!J124+'Annual Raw'!J105 -> 0 | ... AA119: =+'Annual Raw'!AB124+'Annual Raw'!AB105 -> 28130.14 | AB119: =+CC119 -> 31469.417 | AC119: =+CG119 -> 35420.819 | AD119: =+CK119 -> 39865.151 | AE119: =+CO119 -> 44866.897 | AH119: =+'QTR Raw'!D83 -> 0 | AI119: =+'QTR Raw'!E83 -> 0 | AJ119: =+'QTR Raw'!F83 -> 0 | AK119: =+'QTR Raw'!G83 -> 0 | AL119: =+'QTR Raw'!H83 -> 0 | AM119: =+'QTR Raw'!I83 -> 0 | AN119: =+'QTR Raw'!J83 -> 0 | AO119: =+'QTR Raw'!K83 -> 0 | ... BS119: =+'QTR Raw'!AO83 -> 23530.34 | BT119: 23070 | BU119: =+'QTR Raw'!AQ83 -> 24274.45 | BV119: =BU119 -> 24274.45 | BW119: =+'QTR Raw'!AS83 -> 24116.39 | BX119: 24819 | BY119: =+'QTR Raw'!AU83 -> 27922.73 | BZ119: =+BV119*(1+BZ160) -> 27018.746 | CA119: =+BW119*(1+CA160) -> 27291.866 | CB119: =+BX119*(1+CB160) -> 27855.925 | CC119: =+BY119*(1+CC160) -> 31469.417 | CD119: =+BZ119*(1+CD160) -> 30387.725 | CE119: =+CA119*(1+CE160) -> 30726.661 | CF119: =+CB119*(1+CF160) -> 31345.501 | CG119: =+CC119*(1+CG160) -> 35420.819 | ... CO119: =+CK119*(1+CO160) -> 44866.897 | CT119: 27922.73
A120: Total Advances | B120: =+B118+B119 -> 0 | C120: =+C118+C119 -> 0 | D120: =+D118+D119 -> 0 | E120: =+E118+E119 -> 0 | F120: =+F118+F119 -> 0 | G120: =+G118+G119 -> 0 | H120: =+H118+H119 -> 0 | I120: =+I118+I119 -> 0 | ... AE120: =+AE118+AE119 -> 44866.897 | AH120: =+AH118+AH119 -> 0 | AI120: =+AI118+AI119 -> 0 | AJ120: =+AJ118+AJ119 -> 0 | AK120: =+AK118+AK119 -> 0 | AL120: =+AL118+AL119 -> 0 | AM120: =+AM118+AM119 -> 0 | AN120: =+AN118+AN119 -> 0 | AO120: =+AO118+AO119 -> 0 | ... CO120: =+CO118+CO119 -> 44866.897 | CT120: 27922.73
A122: Gross Block | B122: =+'Annual Raw'!C106 -> 0 | C122: =+'Annual Raw'!D106 -> 0 | D122: =+'Annual Raw'!E106 -> 0 | E122: =+'Annual Raw'!F106 -> 0 | F122: =+'Annual Raw'!G106 -> 0 | G122: =+'Annual Raw'!H106 -> 0 | H122: =+'Annual Raw'!I106 -> 0 | I122: =+'Annual Raw'!J106 -> 0 | ... AA122: =+'Annual Raw'!AB106 -> 901.99 | CT122: 901.99
A123: Less: Accumulated Depreciation | B123: =+'Annual Raw'!C107 -> 0 | C123: =+'Annual Raw'!D107 -> 0 | D123: =+'Annual Raw'!E107 -> 0 | E123: =+'Annual Raw'!F107 -> 0 | F123: =+'Annual Raw'!G107 -> 0 | G123: =+'Annual Raw'!H107 -> 0 | H123: =+'Annual Raw'!I107 -> 0 | I123: =+'Annual Raw'!J107 -> 0 | ... AA123: =+'Annual Raw'!AB107 -> 314.47 | CT123: 314.47
...

Sheet Share price Daily
A1: =_xll.EQNXTH(B1,"[ADJC];[ADJH];[ADJL];[ADJO];[UCLS];[VOLUME]","2015-Jan-01","Y","All traded days","Asc") -> EQNXTH | B1: =+'Annual Raw'!A1 -> 221842 | L1: =_xll.EQNXTH(B1,"[NADJC];[NADJH];[NADJLOW];[NADJOPEN];[NUCLOSE];[NVOLUME]","2015-Jan-01","Y","All traded days","Asc") -> EQNXTH
A2: CreditAccess Grameen Ltd. | L2: CreditAccess Grameen Ltd.
A3: DATE | B3: ADJHIGH | C3: ADJCLOSE | D3: ADJLOW | E3: ADJOPEN | F3: CLOSE | G3: VOLUME | L3: DATE | M3: ADJCLOSE | N3: ADJHIGH | O3: ADJLOW | P3: ADJOPEN | Q3: CLOSE | R3: VOLUME
A4: 43335 | B4: 423.3 | C4: 420.8 | D4: 385 | E4: 385 | F4: 420.8 | G4: 1983509 | L4: 43335 | M4: 422.05 | N4: 426.9 | O4: 385 | P4: 390 | Q4: 422.05 | R4: 11600387
A5: 43336 | B5: 418 | C5: 406.65 | D5: 401.85 | E5: 418 | F5: 406.65 | G5: 189848 | L5: 43336 | M5: 406.8 | N5: 420 | O5: 401.75 | P5: 418 | Q5: 406.8 | R5: 785983
A6: 43339 | B6: 407.7 | C6: 400.1 | D6: 394.9 | E6: 407.7 | F6: 400.1 | G6: 61425 | L6: 43339 | M6: 400.25 | N6: 406 | O6: 395 | P6: 406 | Q6: 400.25 | R6: 411202
A7: 43340 | B7: 408 | C7: 396.2 | D7: 395.05 | E7: 399.8 | F7: 396.2 | G7: 60926 | L7: 43340 | M7: 395.8 | N7: 408 | O7: 395 | P7: 397.1 | Q7: 395.8 | R7: 370390
A8: 43341 | B8: 399.45 | C8: 392.25 | D8: 388.2 | E8: 393.1 | F8: 392.25 | G8: 19157 | L8: 43341 | M8: 392.75 | N8: 400 | O8: 389 | P8: 395.8 | Q8: 392.75 | R8: 212493
A9: 43342 | B9: 395 | C9: 380.6 | D9: 374.05 | E9: 388 | F9: 380.6 | G9: 40436 | L9: 43342 | M9: 380.35 | N9: 392 | O9: 373.1 | P9: 388 | Q9: 380.35 | R9: 296385
A10: 43343 | B10: 387.6 | C10: 384.05 | D10: 375.55 | E10: 380 | F10: 384.05 | G10: 31279 | L10: 43343 | M10: 384.95 | N10: 389 | O10: 375.95 | P10: 380.1 | Q10: 384.95 | R10: 256303
A11: 43346 | B11: 387.25 | C11: 381.3 | D11: 380.7 | E11: 385 | F11: 381.3 | G11: 11575 | L11: 43346 | M11: 381.1 | N11: 387.85 | O11: 380.3 | P11: 386.5 | Q11: 381.1 | R11: 80770
A12: 43347 | B12: 383.8 | C12: 380.1 | D12: 375.1 | E12: 383.8 | F12: 380.1 | G12: 62065 | L12: 43347 | M12: 380.3 | N12: 382 | O12: 375.05 | P12: 378.05 | Q12: 380.3 | R12: 162888
A13: 43348 | B13: 380 | C13: 375.7 | D13: 374.1 | E13: 380 | F13: 375.7 | G13: 20987 | L13: 43348 | M13: 376.1 | N13: 380 | O13: 373.4 | P13: 378 | Q13: 376.1 | R13: 183808
A14: 43349 | B14: 394.5 | C14: 383.95 | D14: 376.55 | E14: 376.55 | F14: 383.95 | G14: 23116 | L14: 43349 | M14: 382.65 | N14: 395 | O14: 375 | P14: 375 | Q14: 382.65 | R14: 106322
A15: 43350 | B15: 388.55 | C15: 383.45 | D15: 380.6 | E15: 385 | F15: 383.45 | G15: 6312 | L15: 43350 | M15: 385.25 | N15: 388.65 | O15: 384 | P15: 385 | Q15: 385.25 | R15: 144584
... A2722: 46010 | B2722: 939 | C2722: 932.5 | D2722: 906.25 | E2722: 910.9 | F2722: 932.5 | G2722: 8862 | L2722: 46010 | M2722: 936.6 | N2722: 938.9 | O2722: 905 | P2722: 905 | Q2722: 936.6 | R2722: 296202

Sheet Annual Raw
A1: 221842 | C1: 200103 | D1: 200203 | E1: 200303 | F1: 200403 | G1: 200503 | H1: 200603 | I1: 200703 | J1: 200803 | K1: 200903 | L1: 201003 | M1: 201103 | N1: 201203 | O1: 201303 | P1: 201403 | Q1: 201503 | R1: 201603 | S1: 201703 | T1: 201803 | U1: 201903 | V1: 202003 | W1: 202103 | X1: 202203 | Y1: 202303 | Z1: 202403 | AA1: 202503 | AB1: 202603 | AC1: 202703 | AD1: 202803 | AE1: 202903 | AF1: 203003
B2: {=_xll.EQNXTDZ($A$1,$B3,C$2)} -> CreditAccess Grameen Ltd.
A3: Company Name | B3: CD_COMPNAME
A4: Field Description | B4: Field Name
A5: No of Months | B5: BPL_NO_MONTHS | C5: {=_xll.EQNXTDZ($A$1,$B5,C$1,$B$1)} -> 0 | D5: {=_xll.EQNXTDZ($A$1,$B5,D$1,$B$1)} -> 0 | E5: {=_xll.EQNXTDZ($A$1,$B5,E$1,$B$1)} -> 0 | F5: {=_xll.EQNXTDZ($A$1,$B5,F$1,$B$1)} -> 0 | G5: {=_xll.EQNXTDZ($A$1,$B5,G$1,$B$1)} -> 0 | H5: {=_xll.EQNXTDZ($A$1,$B5,H$1,$B$1)} -> 0 | I5: {=_xll.EQNXTDZ($A$1,$B5,I$1,$B$1)} -> 0 | J5: {=_xll.EQNXTDZ($A$1,$B5,J$1,$B$1)} -> 0 | ... AF5: {=_xll.EQNXTDZ($A$1,$B5,AF$1,$B$1)} -> 0
A6: Year end date | B6: BPL_YEAR_ENDDATE | C6: {=_xll.EQNXTDZ($A$1,$B6,C$1,$B$1)} -> 0 | D6: {=_xll.EQNXTDZ($A$1,$B6,D$1,$B$1)} -> 0 | E6: {=_xll.EQNXTDZ($A$1,$B6,E$1,$B$1)} -> 0 | F6: {=_xll.EQNXTDZ($A$1,$B6,F$1,$B$1)} -> 0 | G6: {=_xll.EQNXTDZ($A$1,$B6,G$1,$B$1)} -> 0 | H6: {=_xll.EQNXTDZ($A$1,$B6,H$1,$B$1)} -> 0 | I6: {=_xll.EQNXTDZ($A$1,$B6,I$1,$B$1)} -> 0 | J6: {=_xll.EQNXTDZ($A$1,$B6,J$1,$B$1)} -> 0 | ... AF6: {=_xll.EQNXTDZ($A$1,$B6,AF$1,$B$1)} -> 0
A8: Field Description | B8: Field Name
A9: Year End | B9: PL_YEAR_END | C9: {=_xll.EQNXTDZ($A$1,$B9,C$1,$B$1)} -> 0 | D9: {=_xll.EQNXTDZ($A$1,$B9,D$1,$B$1)} -> 0 | E9: {=_xll.EQNXTDZ($A$1,$B9,E$1,$B$1)} -> 0 | F9: {=_xll.EQNXTDZ($A$1,$B9,F$1,$B$1)} -> 0 | G9: {=_xll.EQNXTDZ($A$1,$B9,G$1,$B$1)} -> 0 | H9: {=_xll.EQNXTDZ($A$1,$B9,H$1,$B$1)} -> 0 | I9: {=_xll.EQNXTDZ($A$1,$B9,I$1,$B$1)} -> 0 | J9: {=_xll.EQNXTDZ($A$1,$B9,J$1,$B$1)} -> 0 | ... AF9: {=_xll.EQNXTDZ($A$1,$B9,AF$1,$B$1)} -> 0
A10: Year | B10: PL_YEAR | C10: {=_xll.EQNXTDZ($A$1,$B10,C$1,$B$1)} -> 0 | D10: {=_xll.EQNXTDZ($A$1,$B10,D$1,$B$1)} -> 0 | E10: {=_xll.EQNXTDZ($A$1,$B10,E$1,$B$1)} -> 0 | F10: {=_xll.EQNXTDZ($A$1,$B10,F$1,$B$1)} -> 0 | G10: {=_xll.EQNXTDZ($A$1,$B10,G$1,$B$1)} -> 0 | H10: {=_xll.EQNXTDZ($A$1,$B10,H$1,$B$1)} -> 0 | I10: {=_xll.EQNXTDZ($A$1,$B10,I$1,$B$1)} -> 0 | J10: {=_xll.EQNXTDZ($A$1,$B10,J$1,$B$1)} -> 0 | ... AF10: {=_xll.EQNXTDZ($A$1,$B10,AF$1,$B$1)} -> 0
A11: Year end date | B11: PL_YEAR_ENDDATE | C11: {=_xll.EQNXTDZ($A$1,$B11,C$1,$B$1)} -> 0 | D11: {=_xll.EQNXTDZ($A$1,$B11,D$1,$B$1)} -> 0 | E11: {=_xll.EQNXTDZ($A$1,$B11,E$1,$B$1)} -> 0 | F11: {=_xll.EQNXTDZ($A$1,$B11,F$1,$B$1)} -> 0 | G11: {=_xll.EQNXTDZ($A$1,$B11,G$1,$B$1)} -> 0 | H11: {=_xll.EQNXTDZ($A$1,$B11,H$1,$B$1)} -> 0 | I11: {=_xll.EQNXTDZ($A$1,$B11,I$1,$B$1)} -> 0 | J11: {=_xll.EQNXTDZ($A$1,$B11,J$1,$B$1)} -> 0 | ... AF11: {=_xll.EQNXTDZ($A$1,$B11,AF$1,$B$1)} -> 0
A12: No of Months | B12: PL_NO_MONTHS | C12: {=_xll.EQNXTDZ($A$1,$B12,C$1,$B$1)} -> 0 | D12: {=_xll.EQNXTDZ($A$1,$B12,D$1,$B$1)} -> 0 | E12: {=_xll.EQNXTDZ($A$1,$B12,E$1,$B$1)} -> 0 | F12: {=_xll.EQNXTDZ($A$1,$B12,F$1,$B$1)} -> 0 | G12: {=_xll.EQNXTDZ($A$1,$B12,G$1,$B$1)} -> 0 | H12: {=_xll.EQNXTDZ($A$1,$B12,H$1,$B$1)} -> 0 | I12: {=_xll.EQNXTDZ($A$1,$B12,I$1,$B$1)} -> 0 | J12: {=_xll.EQNXTDZ($A$1,$B12,J$1,$B$1)} -> 0 | ... AF12: {=_xll.EQNXTDZ($A$1,$B12,AF$1,$B$1)} -> 0
A13: Sales Turnover | B13: PL_TOTAL_GROSS_SALES | C13: {=_xll.EQNXTDZ($A$1,$B13,C$1,$B$1)} -> 0 | D13: {=_xll.EQNXTDZ($A$1,$B13,D$1,$B$1)} -> 0 | E13: {=_xll.EQNXTDZ($A$1,$B13,E$1,$B$1)} -> 0 | F13: {=_xll.EQNXTDZ($A$1,$B13,F$1,$B$1)} -> 0 | G13: {=_xll.EQNXTDZ($A$1,$B13,G$1,$B$1)} -> 0 | H13: {=_xll.EQNXTDZ($A$1,$B13,H$1,$B$1)} -> 0 | I13: {=_xll.EQNXTDZ($A$1,$B13,I$1,$B$1)} -> 0 | J13: {=_xll.EQNXTDZ($A$1,$B13,J$1,$B$1)} -> 0 | ... AF13: {=_xll.EQNXTDZ($A$1,$B13,AF$1,$B$1)} -> 0
A14: Net Sales | B14: PL_NET_SALES | C14: {=_xll.EQNXTDZ($A$1,$B14,C$1,$B$1)} -> 0 | D14: {=_xll.EQNXTDZ($A$1,$B14,D$1,$B$1)} -> 0 | E14: {=_xll.EQNXTDZ($A$1,$B14,E$1,$B$1)} -> 0 | F14: {=_xll.EQNXTDZ($A$1,$B14,F$1,$B$1)} -> 0 | G14: {=_xll.EQNXTDZ($A$1,$B14,G$1,$B$1)} -> 0 | H14: {=_xll.EQNXTDZ($A$1,$B14,H$1,$B$1)} -> 0 | I14: {=_xll.EQNXTDZ($A$1,$B14,I$1,$B$1)} -> 0 | J14: {=_xll.EQNXTDZ($A$1,$B14,J$1,$B$1)} -> 0 | ... AF14: {=_xll.EQNXTDZ($A$1,$B14,AF$1,$B$1)} -> 0
A15: Increase/Decrease in Stock | B15: PL_INC_DEC_INVENTORY | C15: {=_xll.EQNXTDZ($A$1,$B15,C$1,$B$1)} -> 0 | D15: {=_xll.EQNXTDZ($A$1,$B15,D$1,$B$1)} -> 0 | E15: {=_xll.EQNXTDZ($A$1,$B15,E$1,$B$1)} -> 0 | F15: {=_xll.EQNXTDZ($A$1,$B15,F$1,$B$1)} -> 0 | G15: {=_xll.EQNXTDZ($A$1,$B15,G$1,$B$1)} -> 0 | H15: {=_xll.EQNXTDZ($A$1,$B15,H$1,$B$1)} -> 0 | I15: {=_xll.EQNXTDZ($A$1,$B15,I$1,$B$1)} -> 0 | J15: {=_xll.EQNXTDZ($A$1,$B15,J$1,$B$1)} -> 0 | ... AF15: {=_xll.EQNXTDZ($A$1,$B15,AF$1,$B$1)} -> 0
A16: Raw Material Consumed | B16: PL_RAW_MATRS_CONSUMED | C16: {=_xll.EQNXTDZ($A$1,$B16,C$1,$B$1)} -> 0 | D16: {=_xll.EQNXTDZ($A$1,$B16,D$1,$B$1)} -> 0 | E16: {=_xll.EQNXTDZ($A$1,$B16,E$1,$B$1)} -> 0 | F16: {=_xll.EQNXTDZ($A$1,$B16,F$1,$B$1)} -> 0 | G16: {=_xll.EQNXTDZ($A$1,$B16,G$1,$B$1)} -> 0 | H16: {=_xll.EQNXTDZ($A$1,$B16,H$1,$B$1)} -> 0 | I16: {=_xll.EQNXTDZ($A$1,$B16,I$1,$B$1)} -> 0 | J16: {=_xll.EQNXTDZ($A$1,$B16,J$1,$B$1)} -> 0 | ... AF16: {=_xll.EQNXTDZ($A$1,$B16,AF$1,$B$1)} -> 0
A17: Power & Fuel Cost | B17: PL_POWER_FUEL | C17: {=_xll.EQNXTDZ($A$1,$B17,C$1,$B$1)} -> 0 | D17: {=_xll.EQNXTDZ($A$1,$B17,D$1,$B$1)} -> 0 | E17: {=_xll.EQNXTDZ($A$1,$B17,E$1,$B$1)} -> 0 | F17: {=_xll.EQNXTDZ($A$1,$B17,F$1,$B$1)} -> 0 | G17: {=_xll.EQNXTDZ($A$1,$B17,G$1,$B$1)} -> 0 | H17: {=_xll.EQNXTDZ($A$1,$B17,H$1,$B$1)} -> 0 | I17: {=_xll.EQNXTDZ($A$1,$B17,I$1,$B$1)} -> 0 | J17: {=_xll.EQNXTDZ($A$1,$B17,J$1,$B$1)} -> 0 | ... AF17: {=_xll.EQNXTDZ($A$1,$B17,AF$1,$B$1)} -> 0
A18: Employee Cost | B18: PL_EMPLOYEES | C18: {=_xll.EQNXTDZ($A$1,$B18,C$1,$B$1)} -> 0 | D18: {=_xll.EQNXTDZ($A$1,$B18,D$1,$B$1)} -> 0 | E18: {=_xll.EQNXTDZ($A$1,$B18,E$1,$B$1)} -> 0 | F18: {=_xll.EQNXTDZ($A$1,$B18,F$1,$B$1)} -> 0 | G18: {=_xll.EQNXTDZ($A$1,$B18,G$1,$B$1)} -> 0 | H18: {=_xll.EQNXTDZ($A$1,$B18,H$1,$B$1)} -> 0 | I18: {=_xll.EQNXTDZ($A$1,$B18,I$1,$B$1)} -> 0 | J18: {=_xll.EQNXTDZ($A$1,$B18,J$1,$B$1)} -> 0 | ... AF18: {=_xll.EQNXTDZ($A$1,$B18,AF$1,$B$1)} -> 0
A19: Operating & Manufacturing Expenses | B19: PL_GEN_OTHER_MFG_EXPS | C19: {=_xll.EQNXTDZ($A$1,$B19,C$1,$B$1)} -> 0 | D19: {=_xll.EQNXTDZ($A$1,$B19,D$1,$B$1)} -> 0 | E19: {=_xll.EQNXTDZ($A$1,$B19,E$1,$B$1)} -> 0 | F19: {=_xll.EQNXTDZ($A$1,$B19,F$1,$B$1)} -> 0 | G19: {=_xll.EQNXTDZ($A$1,$B19,G$1,$B$1)} -> 0 | H19: {=_xll.EQNXTDZ($A$1,$B19,H$1,$B$1)} -> 0 | I19: {=_xll.EQNXTDZ($A$1,$B19,I$1,$B$1)} -> 0 | J19: {=_xll.EQNXTDZ($A$1,$B19,J$1,$B$1)} -> 0 | ... AF19: {=_xll.EQNXTDZ($A$1,$B19,AF$1,$B$1)} -> 0
A20: Cost of Software development | B20: PL_COST_SW | C20: {=_xll.EQNXTDZ($A$1,$B20,C$1,$B$1)} -> 0 | D20: {=_xll.EQNXTDZ($A$1,$B20,D$1,$B$1)} -> 0 | E20: {=_xll.EQNXTDZ($A$1,$B20,E$1,$B$1)} -> 0 | F20: {=_xll.EQNXTDZ($A$1,$B20,F$1,$B$1)} -> 0 | G20: {=_xll.EQNXTDZ($A$1,$B20,G$1,$B$1)} -> 0 | H20: {=_xll.EQNXTDZ($A$1,$B20,H$1,$B$1)} -> 0 | I20: {=_xll.EQNXTDZ($A$1,$B20,I$1,$B$1)} -> 0 | J20: {=_xll.EQNXTDZ($A$1,$B20,J$1,$B$1)} -> 0 | ... AF20: {=_xll.EQNXTDZ($A$1,$B20,AF$1,$B$1)} -> 0
... A49: Consolidated Net Profit | B49: PLC_CONSOLIDATED_NETPROFIT | C49: {=_xll.EQNXTDZ($A$1,$B49,C$1,$B$1)} -> 0 | D49: {=_xll.EQNXTDZ($A$1,$B49,D$1,$B$1)} -> 0 | E49: {=_xll.EQNXTDZ($A$1,$B49,E$1,$B$1)} -> 0 | F49: {=_xll.EQNXTDZ($A$1,$B49,F$1,$B$1)} -> 0 | G49: {=_xll.EQNXTDZ($A$1,$B49,G$1,$B$1)} -> 0 | H49: {=_xll.EQNXTDZ($A$1,$B49,H$1,$B$1)} -> 0 | I49: {=_xll.EQNXTDZ($A$1,$B49,I$1,$B$1)} -> 0 | J49: {=_xll.EQNXTDZ($A$1,$B49,J$1,$B$1)} -> 0 | ... AF49: {=_xll.EQNXTDZ($A$1,$B49,AF$1,$B$1)} -> 0
A51: Field Description | B51: Field Name
A52: Equity Paid Up | B52: FH_EQUITY_PAIDUP | C52: {=_xll.EQNXTDZ($A$1,$B52,C$1,$B$1)} -> 0 | D52: {=_xll.EQNXTDZ($A$1,$B52,D$1,$B$1)} -> 0 | E52: {=_xll.EQNXTDZ($A$1,$B52,E$1,$B$1)} -> 0 | F52: {=_xll.EQNXTDZ($A$1,$B52,F$1,$B$1)} -> 0 | G52: {=_xll.EQNXTDZ($A$1,$B52,G$1,$B$1)} -> 0 | H52: {=_xll.EQNXTDZ($A$1,$B52,H$1,$B$1)} -> 0 | I52: {=_xll.EQNXTDZ($A$1,$B52,I$1,$B$1)} -> 0 | J52: {=_xll.EQNXTDZ($A$1,$B52,J$1,$B$1)} -> 0 | ... AF52: {=_xll.EQNXTDZ($A$1,$B52,AF$1,$B$1)} -> 0
A53: Reserves and Surplus | B53: FH_RESERVE | C53: {=_xll.EQNXTDZ($A$1,$B53,C$1,$B$1)} -> 0 | D53: {=_xll.EQNXTDZ($A$1,$B53,D$1,$B$1)} -> 0 | E53: {=_xll.EQNXTDZ($A$1,$B53,E$1,$B$1)} -> 0 | F53: {=_xll.EQNXTDZ($A$1,$B53,F$1,$B$1)} -> 0 | G53: {=_xll.EQNXTDZ($A$1,$B53,G$1,$B$1)} -> 0 | H53: {=_xll.EQNXTDZ($A$1,$B53,H$1,$B$1)} -> 0 | I53: {=_xll.EQNXTDZ($A$1,$B53,I$1,$B$1)} -> 0 | J53: {=_xll.EQNXTDZ($A$1,$B53,J$1,$B$1)} -> 0 | ... AF53: {=_xll.EQNXTDZ($A$1,$B53,AF$1,$B$1)} -> 0
A54: Net Worth | B54: FH_NET_WORTH | C54: {=_xll.EQNXTDZ($A$1,$B54,C$1,$B$1)} -> 0 | D54: {=_xll.EQNXTDZ($A$1,$B54,D$1,$B$1)} -> 0 | E54: {=_xll.EQNXTDZ($A$1,$B54,E$1,$B$1)} -> 0 | F54: {=_xll.EQNXTDZ($A$1,$B54,F$1,$B$1)} -> 0 | G54: {=_xll.EQNXTDZ($A$1,$B54,G$1,$B$1)} -> 0 | H54: {=_xll.EQNXTDZ($A$1,$B54,H$1,$B$1)} -> 0 | I54: {=_xll.EQNXTDZ($A$1,$B54,I$1,$B$1)} -> 0 | J54: {=_xll.EQNXTDZ($A$1,$B54,J$1,$B$1)} -> 0 | ... AF54: {=_xll.EQNXTDZ($A$1,$B54,AF$1,$B$1)} -> 0
A55: Total Debt | B55: FH_TOTAL_DEBTS | C55: {=_xll.EQNXTDZ($A$1,$B55,C$1,$B$1)} -> 0 | D55: {=_xll.EQNXTDZ($A$1,$B55,D$1,$B$1)} -> 0 | E55: {=_xll.EQNXTDZ($A$1,$B55,E$1,$B$1)} -> 0 | F55: {=_xll.EQNXTDZ($A$1,$B55,F$1,$B$1)} -> 0 | G55: {=_xll.EQNXTDZ($A$1,$B55,G$1,$B$1)} -> 0 | H55: {=_xll.EQNXTDZ($A$1,$B55,H$1,$B$1)} -> 0 | I55: {=_xll.EQNXTDZ($A$1,$B55,I$1,$B$1)} -> 0 | J55: {=_xll.EQNXTDZ($A$1,$B55,J$1,$B$1)} -> 0 | ... AF55: {=_xll.EQNXTDZ($A$1,$B55,AF$1,$B$1)} -> 0
A56: Deposits | B56: FH_DEPOSITS | C56: {=_xll.EQNXTDZ($A$1,$B56,C$1,$B$1)} -> 0 | D56: {=_xll.EQNXTDZ($A$1,$B56,D$1,$B$1)} -> 0 | E56: {=_xll.EQNXTDZ($A$1,$B56,E$1,$B$1)} -> 0 | F56: {=_xll.EQNXTDZ($A$1,$B56,F$1,$B$1)} -> 0 | G56: {=_xll.EQNXTDZ($A$1,$B56,G$1,$B$1)} -> 0 | H56: {=_xll.EQNXTDZ($A$1,$B56,H$1,$B$1)} -> 0 | I56: {=_xll.EQNXTDZ($A$1,$B56,I$1,$B$1)} -> 0 | J56: {=_xll.EQNXTDZ($A$1,$B56,J$1,$B$1)} -> 0 | ... AF56: {=_xll.EQNXTDZ($A$1,$B56,AF$1,$B$1)} -> 0
A57: Borrowings | B57: FH_BORROWINGS | C57: {=_xll.EQNXTDZ($A$1,$B57,C$1,$B$1)} -> 0 | D57: {=_xll.EQNXTDZ($A$1,$B57,D$1,$B$1)} -> 0 | E57: {=_xll.EQNXTDZ($A$1,$B57,E$1,$B$1)} -> 0 | F57: {=_xll.EQNXTDZ($A$1,$B57,F$1,$B$1)} -> 0 | G57: {=_xll.EQNXTDZ($A$1,$B57,G$1,$B$1)} -> 0 | H57: {=_xll.EQNXTDZ($A$1,$B57,H$1,$B$1)} -> 0 | I57: {=_xll.EQNXTDZ($A$1,$B57,I$1,$B$1)} -> 0 | J57: {=_xll.EQNXTDZ($A$1,$B57,J$1,$B$1)} -> 0 | ... AF57: {=_xll.EQNXTDZ($A$1,$B57,AF$1,$B$1)} -> 0
A58: Month End | B58: BMONTH_MONTHEND | C58: {=_xll.EQNXTDZ($A$1,$B58,C$1,$B$1)} -> 0 | D58: {=_xll.EQNXTDZ($A$1,$B58,D$1,$B$1)} -> 0 | E58: {=_xll.EQNXTDZ($A$1,$B58,E$1,$B$1)} -> 0 | F58: {=_xll.EQNXTDZ($A$1,$B58,F$1,$B$1)} -> 0 | G58: {=_xll.EQNXTDZ($A$1,$B58,G$1,$B$1)} -> 0 | H58: {=_xll.EQNXTDZ($A$1,$B58,H$1,$B$1)} -> 0 | I58: {=_xll.EQNXTDZ($A$1,$B58,I$1,$B$1)} -> 0 | J58: {=_xll.EQNXTDZ($A$1,$B58,J$1,$B$1)} -> 0 | ... AF58: {=_xll.EQNXTDZ($A$1,$B58,AF$1,$B$1)} -> 0
A59: Close Price (Unit Curr.) | B59: FH_YEAR_PRICE | C59: {=_xll.EQNXTDZ($A$1,$B59,C$1,$B$1)} -> 0 | D59: {=_xll.EQNXTDZ($A$1,$B59,D$1,$B$1)} -> 0 | E59: {=_xll.EQNXTDZ($A$1,$B59,E$1,$B$1)} -> 0 | F59: {=_xll.EQNXTDZ($A$1,$B59,F$1,$B$1)} -> 0 | G59: {=_xll.EQNXTDZ($A$1,$B59,G$1,$B$1)} -> 0 | H59: {=_xll.EQNXTDZ($A$1,$B59,H$1,$B$1)} -> 0 | I59: {=_xll.EQNXTDZ($A$1,$B59,I$1,$B$1)} -> 0 | J59: {=_xll.EQNXTDZ($A$1,$B59,J$1,$B$1)} -> 0 | ... AF59: {=_xll.EQNXTDZ($A$1,$B59,AF$1,$B$1)} -> 0
A60: High Price (Unit Curr.) | B60: FH_HIGH | C60: {=_xll.EQNXTDZ($A$1,$B60,C$1,$B$1)} -> 0 | D60: {=_xll.EQNXTDZ($A$1,$B60,D$1,$B$1)} -> 0 | E60: {=_xll.EQNXTDZ($A$1,$B60,E$1,$B$1)} -> 0 | F60: {=_xll.EQNXTDZ($A$1,$B60,F$1,$B$1)} -> 0 | G60: {=_xll.EQNXTDZ($A$1,$B60,G$1,$B$1)} -> 0 | H60: {=_xll.EQNXTDZ($A$1,$B60,H$1,$B$1)} -> 0 | I60: {=_xll.EQNXTDZ($A$1,$B60,I$1,$B$1)} -> 0 | J60: {=_xll.EQNXTDZ($A$1,$B60,J$1,$B$1)} -> 0 | ... AF60: {=_xll.EQNXTDZ($A$1,$B60,AF$1,$B$1)} -> 0
A61: Low Price (Unit Curr.) | B61: FH_LOW | C61: {=_xll.EQNXTDZ($A$1,$B61,C$1,$B$1)} -> 0 | D61: {=_xll.EQNXTDZ($A$1,$B61,D$1,$B$1)} -> 0 | E61: {=_xll.EQNXTDZ($A$1,$B61,E$1,$B$1)} -> 0 | F61: {=_xll.EQNXTDZ($A$1,$B61,F$1,$B$1)} -> 0 | G61: {=_xll.EQNXTDZ($A$1,$B61,G$1,$B$1)} -> 0 | H61: {=_xll.EQNXTDZ($A$1,$B61,H$1,$B$1)} -> 0 | I61: {=_xll.EQNXTDZ($A$1,$B61,I$1,$B$1)} -> 0 | J61: {=_xll.EQNXTDZ($A$1,$B61,J$1,$B$1)} -> 0 | ... AF61: {=_xll.EQNXTDZ($A$1,$B61,AF$1,$B$1)} -> 0
A62: Month end date | B62: BMONTH_CLOSEDATE | C62: {=_xll.EQNXTDZ($A$1,$B62,C$1,$B$1)} -> 0 | D62: {=_xll.EQNXTDZ($A$1,$B62,D$1,$B$1)} -> 0 | E62: {=_xll.EQNXTDZ($A$1,$B62,E$1,$B$1)} -> 0 | F62: {=_xll.EQNXTDZ($A$1,$B62,F$1,$B$1)} -> 0 | G62: {=_xll.EQNXTDZ($A$1,$B62,G$1,$B$1)} -> 0 | H62: {=_xll.EQNXTDZ($A$1,$B62,H$1,$B$1)} -> 0 | I62: {=_xll.EQNXTDZ($A$1,$B62,I$1,$B$1)} -> 0 | J62: {=_xll.EQNXTDZ($A$1,$B62,J$1,$B$1)} -> 0 | ... AF62: {=_xll.EQNXTDZ($A$1,$B62,AF$1,$B$1)} -> 0
A63: Volume ('000) | B63: BMONTH_VOLUME | C63: {=_xll.EQNXTDZ($A$1,$B63,C$1,$B$1)} -> 0 | D63: {=_xll.EQNXTDZ($A$1,$B63,D$1,$B$1)} -> 0 | E63: {=_xll.EQNXTDZ($A$1,$B63,E$1,$B$1)} -> 0 | F63: {=_xll.EQNXTDZ($A$1,$B63,F$1,$B$1)} -> 0 | G63: {=_xll.EQNXTDZ($A$1,$B63,G$1,$B$1)} -> 0 | H63: {=_xll.EQNXTDZ($A$1,$B63,H$1,$B$1)} -> 0 | I63: {=_xll.EQNXTDZ($A$1,$B63,I$1,$B$1)} -> 0 | J63: {=_xll.EQNXTDZ($A$1,$B63,J$1,$B$1)} -> 0 | ... AF63: {=_xll.EQNXTDZ($A$1,$B63,AF$1,$B$1)} -> 0
... A68: NIM_Reported (%) | B68: RBI_NIMAR | C68: {=_xll.EQNXTDZ($A$1,$B68,C$1,$B$1)} -> 0 | D68: {=_xll.EQNXTDZ($A$1,$B68,D$1,$B$1)} -> 0 | E68: {=_xll.EQNXTDZ($A$1,$B68,E$1,$B$1)} -> 0 | F68: {=_xll.EQNXTDZ($A$1,$B68,F$1,$B$1)} -> 0 | G68: {=_xll.EQNXTDZ($A$1,$B68,G$1,$B$1)} -> 0 | H68: {=_xll.EQNXTDZ($A$1,$B68,H$1,$B$1)} -> 0 | I68: {=_xll.EQNXTDZ($A$1,$B68,I$1,$B$1)} -> 0 | J68: {=_xll.EQNXTDZ($A$1,$B68,J$1,$B$1)} -> 0 | ... AF68: {=_xll.EQNXTDZ($A$1,$B68,AF$1,$B$1)} -> 0
A70: Assets | C70: =+C85+C104+C106-C107-C108+C110+C111+C113+C114+C115+C116+C117+C119+C120+C121+C122+C123+C124+C125+C105+C112 -> 0 | D70: =+D85+D104+D106-D107-D108+D110+D111+D113+D114+D115+D116+D117+D119+D120+D121+D122+D123+D124+D125+D105+D112 -> 0 | E70: =+E85+E104+E106-E107-E108+E110+E111+E113+E114+E115+E116+E117+E119+E120+E121+E122+E123+E124+E125+E105+E112 -> 0 | F70: =+F85+F104+F106-F107-F108+F110+F111+F113+F114+F115+F116+F117+F119+F120+F121+F122+F123+F124+F125+F105+F112 -> 0 | G70: =+G85+G104+G106-G107-G108+G110+G111+G113+G114+G115+G116+G117+G119+G120+G121+G122+G123+G124+G125+G105+G112 -> 0 | H70: =+H85+H104+H106-H107-H108+H110+H111+H113+H114+H115+H116+H117+H119+H120+H121+H122+H123+H124+H125+H105+H112 -> 0 | I70: =+I85+I104+I106-I107-I108+I110+I111+I113+I114+I115+I116+I117+I119+I120+I121+I122+I123+I124+I125+I105+I112 -> 0 | J70: =+J85+J104+J106-J107-J108+J110+J111+J113+J114+J115+J116+J117+J119+J120+J121+J122+J123+J124+J125+J105+J112 -> 0 | ... AF70: =+AF85+AF104+AF106-AF107-AF108+AF110+AF111+AF113+AF114+AF115+AF116+AF117+AF119+AF120+AF121+AF122+AF123+AF124+AF125+AF105+AF112 -> 0
A71: Liab | C71: =+C77+C78+C79+C81+C82+C83+C84+C86+C87+C88+C89+C90+C91+C93+C94+C99+C100+C101 -> 0 | D71: =+D77+D78+D79+D81+D82+D83+D84+D86+D87+D88+D89+D90+D91+D93+D94+D99+D100+D101 -> 0 | E71: =+E77+E78+E79+E81+E82+E83+E84+E86+E87+E88+E89+E90+E91+E93+E94+E99+E100+E101 -> 0 | F71: =+F77+F78+F79+F81+F82+F83+F84+F86+F87+F88+F89+F90+F91+F93+F94+F99+F100+F101 -> 0 | G71: =+G77+G78+G79+G81+G82+G83+G84+G86+G87+G88+G89+G90+G91+G93+G94+G99+G100+G101 -> 0 | H71: =+H77+H78+H79+H81+H82+H83+H84+H86+H87+H88+H89+H90+H91+H93+H94+H99+H100+H101 -> 0 | I71: =+I77+I78+I79+I81+I82+I83+I84+I86+I87+I88+I89+I90+I91+I93+I94+I99+I100+I101 -> 0 | J71: =+J77+J78+J79+J81+J82+J83+J84+J86+J87+J88+J89+J90+J91+J93+J94+J99+J100+J101 -> 0 | ... AF71: =+AF77+AF78+AF79+AF81+AF82+AF83+AF84+AF86+AF87+AF88+AF89+AF90+AF91+AF93+AF94+AF99+AF100+AF101 -> 0
A72: Field Description | B72: Field Name
A73: Year End | B73: BBS_YEAR_END | C73: {=_xll.EQNXTDZ($A$1,$B73,C$1,$B$1)} -> 0 | D73: {=_xll.EQNXTDZ($A$1,$B73,D$1,$B$1)} -> 0 | E73: {=_xll.EQNXTDZ($A$1,$B73,E$1,$B$1)} -> 0 | F73: {=_xll.EQNXTDZ($A$1,$B73,F$1,$B$1)} -> 0 | G73: {=_xll.EQNXTDZ($A$1,$B73,G$1,$B$1)} -> 0 | H73: {=_xll.EQNXTDZ($A$1,$B73,H$1,$B$1)} -> 0 | I73: {=_xll.EQNXTDZ($A$1,$B73,I$1,$B$1)} -> 0 | J73: {=_xll.EQNXTDZ($A$1,$B73,J$1,$B$1)} -> 0 | ... AF73: {=_xll.EQNXTDZ($A$1,$B73,AF$1,$B$1)} -> 0
A74: Year | B74: BBS_YEAR | C74: {=_xll.EQNXTDZ($A$1,$B74,C$1,$B$1)} -> 0 | D74: {=_xll.EQNXTDZ($A$1,$B74,D$1,$B$1)} -> 0 | E74: {=_xll.EQNXTDZ($A$1,$B74,E$1,$B$1)} -> 0 | F74: {=_xll.EQNXTDZ($A$1,$B74,F$1,$B$1)} -> 0 | G74: {=_xll.EQNXTDZ($A$1,$B74,G$1,$B$1)} -> 0 | H74: {=_xll.EQNXTDZ($A$1,$B74,H$1,$B$1)} -> 0 | I74: {=_xll.EQNXTDZ($A$1,$B74,I$1,$B$1)} -> 0 | J74: {=_xll.EQNXTDZ($A$1,$B74,J$1,$B$1)} -> 0 | ... AF74: {=_xll.EQNXTDZ($A$1,$B74,AF$1,$B$1)} -> 0
A75: No of Months | B75: BBS_NO_MONTHS | C75: {=_xll.EQNXTDZ($A$1,$B75,C$1,$B$1)} -> 0 | D75: {=_xll.EQNXTDZ($A$1,$B75,D$1,$B$1)} -> 0 | E75: {=_xll.EQNXTDZ($A$1,$B75,E$1,$B$1)} -> 0 | F75: {=_xll.EQNXTDZ($A$1,$B75,F$1,$B$1)} -> 0 | G75: {=_xll.EQNXTDZ($A$1,$B75,G$1,$B$1)} -> 0 | H75: {=_xll.EQNXTDZ($A$1,$B75,H$1,$B$1)} -> 0 | I75: {=_xll.EQNXTDZ($A$1,$B75,I$1,$B$1)} -> 0 | J75: {=_xll.EQNXTDZ($A$1,$B75,J$1,$B$1)} -> 0 | ... AF75: {=_xll.EQNXTDZ($A$1,$B75,AF$1,$B$1)} -> 0
A76: Year end date | B76: BBS_YEAR_ENDDATE | C76: {=_xll.EQNXTDZ($A$1,$B76,C$1,$B$1)} -> 0 | D76: {=_xll.EQNXTDZ($A$1,$B76,D$1,$B$1)} -> 0 | E76: {=_xll.EQNXTDZ($A$1,$B76,E$1,$B$1)} -> 0 | F76: {=_xll.EQNXTDZ($A$1,$B76,F$1,$B$1)} -> 0 | G76: {=_xll.EQNXTDZ($A$1,$B76,G$1,$B$1)} -> 0 | H76: {=_xll.EQNXTDZ($A$1,$B76,H$1,$B$1)} -> 0 | I76: {=_xll.EQNXTDZ($A$1,$B76,I$1,$B$1)} -> 0 | J76: {=_xll.EQNXTDZ($A$1,$B76,J$1,$B$1)} -> 0 | ... AF76: {=_xll.EQNXTDZ($A$1,$B76,AF$1,$B$1)} -> 0
A77: Share Capital | B77: BS_SHARE_CAPITAL | C77: {=_xll.EQNXTDZ($A$1,$B77,C$1,$B$1)} -> 0 | D77: {=_xll.EQNXTDZ($A$1,$B77,D$1,$B$1)} -> 0 | E77: {=_xll.EQNXTDZ($A$1,$B77,E$1,$B$1)} -> 0 | F77: {=_xll.EQNXTDZ($A$1,$B77,F$1,$B$1)} -> 0 | G77: {=_xll.EQNXTDZ($A$1,$B77,G$1,$B$1)} -> 0 | H77: {=_xll.EQNXTDZ($A$1,$B77,H$1,$B$1)} -> 0 | I77: {=_xll.EQNXTDZ($A$1,$B77,I$1,$B$1)} -> 0 | J77: {=_xll.EQNXTDZ($A$1,$B77,J$1,$B$1)} -> 0 | ... AF77: {=_xll.EQNXTDZ($A$1,$B77,AF$1,$B$1)} -> 0
A78: Share Warrants & Outstandings | B78: BS_SHAREWROUTST | C78: {=_xll.EQNXTDZ($A$1,$B78,C$1,$B$1)} -> 0 | D78: {=_xll.EQNXTDZ($A$1,$B78,D$1,$B$1)} -> 0 | E78: {=_xll.EQNXTDZ($A$1,$B78,E$1,$B$1)} -> 0 | F78: {=_xll.EQNXTDZ($A$1,$B78,F$1,$B$1)} -> 0 | G78: {=_xll.EQNXTDZ($A$1,$B78,G$1,$B$1)} -> 0 | H78: {=_xll.EQNXTDZ($A$1,$B78,H$1,$B$1)} -> 0 | I78: {=_xll.EQNXTDZ($A$1,$B78,I$1,$B$1)} -> 0 | J78: {=_xll.EQNXTDZ($A$1,$B78,J$1,$B$1)} -> 0 | ... AF78: {=_xll.EQNXTDZ($A$1,$B78,AF$1,$B$1)} -> 0
A79: Total Reserves | B79: BS_RESERVE | C79: {=_xll.EQNXTDZ($A$1,$B79,C$1,$B$1)} -> 0 | D79: {=_xll.EQNXTDZ($A$1,$B79,D$1,$B$1)} -> 0 | E79: {=_xll.EQNXTDZ($A$1,$B79,E$1,$B$1)} -> 0 | F79: {=_xll.EQNXTDZ($A$1,$B79,F$1,$B$1)} -> 0 | G79: {=_xll.EQNXTDZ($A$1,$B79,G$1,$B$1)} -> 0 | H79: {=_xll.EQNXTDZ($A$1,$B79,H$1,$B$1)} -> 0 | I79: {=_xll.EQNXTDZ($A$1,$B79,I$1,$B$1)} -> 0 | J79: {=_xll.EQNXTDZ($A$1,$B79,J$1,$B$1)} -> 0 | ... AF79: {=_xll.EQNXTDZ($A$1,$B79,AF$1,$B$1)} -> 0
A80: Shareholder's Funds | B80: BS_SHAREHODERS_FUNDS | C80: {=_xll.EQNXTDZ($A$1,$B80,C$1,$B$1)} -> 0 | D80: {=_xll.EQNXTDZ($A$1,$B80,D$1,$B$1)} -> 0 | E80: {=_xll.EQNXTDZ($A$1,$B80,E$1,$B$1)} -> 0 | F80: {=_xll.EQNXTDZ($A$1,$B80,F$1,$B$1)} -> 0 | G80: {=_xll.EQNXTDZ($A$1,$B80,G$1,$B$1)} -> 0 | H80: {=_xll.EQNXTDZ($A$1,$B80,H$1,$B$1)} -> 0 | I80: {=_xll.EQNXTDZ($A$1,$B80,I$1,$B$1)} -> 0 | J80: {=_xll.EQNXTDZ($A$1,$B80,J$1,$B$1)} -> 0 | ... AF80: {=_xll.EQNXTDZ($A$1,$B80,AF$1,$B$1)} -> 0
A81: Minority Interest | B81: BS_MINORITY_INTEREST | C81: {=_xll.EQNXTDZ($A$1,$B81,C$1,$B$1)} -> 0 | D81: {=_xll.EQNXTDZ($A$1,$B81,D$1,$B$1)} -> 0 | E81: {=_xll.EQNXTDZ($A$1,$B81,E$1,$B$1)} -> 0 | F81: {=_xll.EQNXTDZ($A$1,$B81,F$1,$B$1)} -> 0 | G81: {=_xll.EQNXTDZ($A$1,$B81,G$1,$B$1)} -> 0 | H81: {=_xll.EQNXTDZ($A$1,$B81,H$1,$B$1)} -> 0 | I81: {=_xll.EQNXTDZ($A$1,$B81,I$1,$B$1)} -> 0 | J81: {=_xll.EQNXTDZ($A$1,$B81,J$1,$B$1)} -> 0 | ... AF81: {=_xll.EQNXTDZ($A$1,$B81,AF$1,$B$1)} -> 0
A82: Long-Term Borrowings | B82: BS_LTRM_BORROWING | C82: {=_xll.EQNXTDZ($A$1,$B82,C$1,$B$1)} -> 0 | D82: {=_xll.EQNXTDZ($A$1,$B82,D$1,$B$1)} -> 0 | E82: {=_xll.EQNXTDZ($A$1,$B82,E$1,$B$1)} -> 0 | F82: {=_xll.EQNXTDZ($A$1,$B82,F$1,$B$1)} -> 0 | G82: {=_xll.EQNXTDZ($A$1,$B82,G$1,$B$1)} -> 0 | H82: {=_xll.EQNXTDZ($A$1,$B82,H$1,$B$1)} -> 0 | I82: {=_xll.EQNXTDZ($A$1,$B82,I$1,$B$1)} -> 0 | J82: {=_xll.EQNXTDZ($A$1,$B82,J$1,$B$1)} -> 0 | ... AF82: {=_xll.EQNXTDZ($A$1,$B82,AF$1,$B$1)} -> 0
A83: Secured Loans | B83: BS_SECURED_LOANS | C83: {=_xll.EQNXTDZ($A$1,$B83,C$1,$B$1)} -> 0 | D83: {=_xll.EQNXTDZ($A$1,$B83,D$1,$B$1)} -> 0 | E83: {=_xll.EQNXTDZ($A$1,$B83,E$1,$B$1)} -> 0 | F83: {=_xll.EQNXTDZ($A$1,$B83,F$1,$B$1)} -> 0 | G83: {=_xll.EQNXTDZ($A$1,$B83,G$1,$B$1)} -> 0 | H83: {=_xll.EQNXTDZ($A$1,$B83,H$1,$B$1)} -> 0 | I83: {=_xll.EQNXTDZ($A$1,$B83,I$1,$B$1)} -> 0 | J83: {=_xll.EQNXTDZ($A$1,$B83,J$1,$B$1)} -> 0 | ... AF83: {=_xll.EQNXTDZ($A$1,$B83,AF$1,$B$1)} -> 0
A84: Unsecured Loans | B84: BS_UNSECURED_LOANS_NF | C84: {=_xll.EQNXTDZ($A$1,$B84,C$1,$B$1)} -> 0 | D84: {=_xll.EQNXTDZ($A$1,$B84,D$1,$B$1)} -> 0 | E84: {=_xll.EQNXTDZ($A$1,$B84,E$1,$B$1)} -> 0 | F84: {=_xll.EQNXTDZ($A$1,$B84,F$1,$B$1)} -> 0 | G84: {=_xll.EQNXTDZ($A$1,$B84,G$1,$B$1)} -> 0 | H84: {=_xll.EQNXTDZ($A$1,$B84,H$1,$B$1)} -> 0 | I84: {=_xll.EQNXTDZ($A$1,$B84,I$1,$B$1)} -> 0 | J84: {=_xll.EQNXTDZ($A$1,$B84,J$1,$B$1)} -> 0 | ... AF84: {=_xll.EQNXTDZ($A$1,$B84,AF$1,$B$1)} -> 0
... A152: NIM(%) | B152: BFR_NETINTERESTINCOME_TOTALFUNDS | C152: {=_xll.EQNXTDZ($A$1,$B152,C$1,$B$1)} -> 0 | D152: {=_xll.EQNXTDZ($A$1,$B152,D$1,$B$1)} -> 0 | E152: {=_xll.EQNXTDZ($A$1,$B152,E$1,$B$1)} -> 0 | F152: {=_xll.EQNXTDZ($A$1,$B152,F$1,$B$1)} -> 0 | G152: {=_xll.EQNXTDZ($A$1,$B152,G$1,$B$1)} -> 0 | H152: {=_xll.EQNXTDZ($A$1,$B152,H$1,$B$1)} -> 0 | I152: {=_xll.EQNXTDZ($A$1,$B152,I$1,$B$1)} -> 0 | J152: {=_xll.EQNXTDZ($A$1,$B152,J$1,$B$1)} -> 0 | ... AF152: {=_xll.EQNXTDZ($A$1,$B152,AF$1,$B$1)} -> 0

Sheet QTR Raw
A1: =+'Annual Raw'!A1 -> 221842 | B1: X | C1: 201503 | D1: 201506 | E1: 201509 | F1: 201512 | G1: 201603 | H1: 201606 | I1: 201609 | J1: 201612 | K1: 201703 | L1: 201706 | M1: 201709 | N1: 201712 | O1: 201803 | P1: 201806 | Q1: 201809 | R1: 201812 | S1: 201903 | T1: 201906 | U1: 201909 | V1: 201912 | W1: 202003 | X1: 202006 | Y1: 202009 | Z1: 202012 | AA1: 202103 | AB1: 202106 | AC1: 202109 | AD1: 202112 | AE1: 202203 | AF1: 202206 | AG1: 202209 | AH1: 202212 | AI1: 202303 | AJ1: 202306 | AK1: 202309 | AL1: 202312 | AM1: 202403 | AN1: 202406 | AO1: 202409 | AP1: 202412 | AQ1: 202503 | AR1: 202506 | AS1: 202509 | AT1: 202512 | AU1: 202603 | AV1: 202606 | AW1: 202609 | AX1: 202612 | AY1: 202703 | AZ1: 202706 | BA1: 202709 | BB1: 202712 | BC1: 202803 | BD1: 202806 | BE1: 202809 | BF1: 202812 | BG1: 202903 | BH1: 202906 | BI1: 202909 | BJ1: 202912 | BK1: 203003
A4: Field Description | B4: Field Name
A5: Date End | B5: BQTR_DATE_END | C5: {=+_xll.EQNXTDZ($A$1,$B5,C$1,$B$1)} -> 0 | D5: {=+_xll.EQNXTDZ($A$1,$B5,D$1,$B$1)} -> 0 | E5: {=+_xll.EQNXTDZ($A$1,$B5,E$1,$B$1)} -> 0 | F5: {=+_xll.EQNXTDZ($A$1,$B5,F$1,$B$1)} -> 0 | G5: {=+_xll.EQNXTDZ($A$1,$B5,G$1,$B$1)} -> 0 | H5: {=+_xll.EQNXTDZ($A$1,$B5,H$1,$B$1)} -> 0 | I5: {=+_xll.EQNXTDZ($A$1,$B5,I$1,$B$1)} -> 0 | J5: {=+_xll.EQNXTDZ($A$1,$B5,J$1,$B$1)} -> 0 | ... BK5: {=+_xll.EQNXTDZ($A$1,$B5,BK$1,$B$1)} -> 0
A6: Field Description | B6: Field Name
A7: Date End | B7: QTR_DATE_END | C7: {=+_xll.EQNXTDZ($A$1,$B7,C$1,$B$1)} -> 0 | D7: {=+_xll.EQNXTDZ($A$1,$B7,D$1,$B$1)} -> 0 | E7: {=+_xll.EQNXTDZ($A$1,$B7,E$1,$B$1)} -> 0 | F7: {=+_xll.EQNXTDZ($A$1,$B7,F$1,$B$1)} -> 0 | G7: {=+_xll.EQNXTDZ($A$1,$B7,G$1,$B$1)} -> 0 | H7: {=+_xll.EQNXTDZ($A$1,$B7,H$1,$B$1)} -> 0 | I7: {=+_xll.EQNXTDZ($A$1,$B7,I$1,$B$1)} -> 0 | J7: {=+_xll.EQNXTDZ($A$1,$B7,J$1,$B$1)} -> 0 | ... BK7: {=+_xll.EQNXTDZ($A$1,$B7,BK$1,$B$1)} -> 0
A8: Gross Sales | B8: QTR_GROSS_SALE | C8: {=+_xll.EQNXTDZ($A$1,$B8,C$1,$B$1)} -> 0 | D8: {=+_xll.EQNXTDZ($A$1,$B8,D$1,$B$1)} -> 0 | E8: {=+_xll.EQNXTDZ($A$1,$B8,E$1,$B$1)} -> 0 | F8: {=+_xll.EQNXTDZ($A$1,$B8,F$1,$B$1)} -> 0 | G8: {=+_xll.EQNXTDZ($A$1,$B8,G$1,$B$1)} -> 0 | H8: {=+_xll.EQNXTDZ($A$1,$B8,H$1,$B$1)} -> 0 | I8: {=+_xll.EQNXTDZ($A$1,$B8,I$1,$B$1)} -> 0 | J8: {=+_xll.EQNXTDZ($A$1,$B8,J$1,$B$1)} -> 0 | ... BK8: {=+_xll.EQNXTDZ($A$1,$B8,BK$1,$B$1)} -> 0
A9: Net Sales | B9: QTR_OTHER_NETSALES | C9: {=+_xll.EQNXTDZ($A$1,$B9,C$1,$B$1)} -> 0 | D9: {=+_xll.EQNXTDZ($A$1,$B9,D$1,$B$1)} -> 0 | E9: {=+_xll.EQNXTDZ($A$1,$B9,E$1,$B$1)} -> 0 | F9: {=+_xll.EQNXTDZ($A$1,$B9,F$1,$B$1)} -> 0 | G9: {=+_xll.EQNXTDZ($A$1,$B9,G$1,$B$1)} -> 0 | H9: {=+_xll.EQNXTDZ($A$1,$B9,H$1,$B$1)} -> 0 | I9: {=+_xll.EQNXTDZ($A$1,$B9,I$1,$B$1)} -> 0 | J9: {=+_xll.EQNXTDZ($A$1,$B9,J$1,$B$1)} -> 0 | ... BK9: {=+_xll.EQNXTDZ($A$1,$B9,BK$1,$B$1)} -> 0
A10: Share of Associates | B10: QTR_SHARE_ASSOCIATE_REVENUE | C10: {=+_xll.EQNXTDZ($A$1,$B10,C$1,$B$1)} -> 0 | D10: {=+_xll.EQNXTDZ($A$1,$B10,D$1,$B$1)} -> 0 | E10: {=+_xll.EQNXTDZ($A$1,$B10,E$1,$B$1)} -> 0 | F10: {=+_xll.EQNXTDZ($A$1,$B10,F$1,$B$1)} -> 0 | G10: {=+_xll.EQNXTDZ($A$1,$B10,G$1,$B$1)} -> 0 | H10: {=+_xll.EQNXTDZ($A$1,$B10,H$1,$B$1)} -> 0 | I10: {=+_xll.EQNXTDZ($A$1,$B10,I$1,$B$1)} -> 0 | J10: {=+_xll.EQNXTDZ($A$1,$B10,J$1,$B$1)} -> 0 | ... BK10: {=+_xll.EQNXTDZ($A$1,$B10,BK$1,$B$1)} -> 0
A11: Other operating income | B11: QTR_JOB_WORKS | C11: {=+_xll.EQNXTDZ($A$1,$B11,C$1,$B$1)} -> 0 | D11: {=+_xll.EQNXTDZ($A$1,$B11,D$1,$B$1)} -> 0 | E11: {=+_xll.EQNXTDZ($A$1,$B11,E$1,$B$1)} -> 0 | F11: {=+_xll.EQNXTDZ($A$1,$B11,F$1,$B$1)} -> 0 | G11: {=+_xll.EQNXTDZ($A$1,$B11,G$1,$B$1)} -> 0 | H11: {=+_xll.EQNXTDZ($A$1,$B11,H$1,$B$1)} -> 0 | I11: {=+_xll.EQNXTDZ($A$1,$B11,I$1,$B$1)} -> 0 | J11: {=+_xll.EQNXTDZ($A$1,$B11,J$1,$B$1)} -> 0 | ... BK11: {=+_xll.EQNXTDZ($A$1,$B11,BK$1,$B$1)} -> 0
A12: Income on Investments | B12: QTR_INC_INV | C12: {=+_xll.EQNXTDZ($A$1,$B12,C$1,$B$1)} -> 0 | D12: {=+_xll.EQNXTDZ($A$1,$B12,D$1,$B$1)} -> 0 | E12: {=+_xll.EQNXTDZ($A$1,$B12,E$1,$B$1)} -> 0 | F12: {=+_xll.EQNXTDZ($A$1,$B12,F$1,$B$1)} -> 0 | G12: {=+_xll.EQNXTDZ($A$1,$B12,G$1,$B$1)} -> 0 | H12: {=+_xll.EQNXTDZ($A$1,$B12,H$1,$B$1)} -> 0 | I12: {=+_xll.EQNXTDZ($A$1,$B12,I$1,$B$1)} -> 0 | J12: {=+_xll.EQNXTDZ($A$1,$B12,J$1,$B$1)} -> 0 | ... BK12: {=+_xll.EQNXTDZ($A$1,$B12,BK$1,$B$1)} -> 0
A13: Net Sales & Other Operating Income | B13: QTR_NET_SALES | C13: {=+_xll.EQNXTDZ($A$1,$B13,C$1,$B$1)} -> 0 | D13: {=+_xll.EQNXTDZ($A$1,$B13,D$1,$B$1)} -> 0 | E13: {=+_xll.EQNXTDZ($A$1,$B13,E$1,$B$1)} -> 0 | F13: {=+_xll.EQNXTDZ($A$1,$B13,F$1,$B$1)} -> 0 | G13: {=+_xll.EQNXTDZ($A$1,$B13,G$1,$B$1)} -> 0 | H13: {=+_xll.EQNXTDZ($A$1,$B13,H$1,$B$1)} -> 0 | I13: {=+_xll.EQNXTDZ($A$1,$B13,I$1,$B$1)} -> 0 | J13: {=+_xll.EQNXTDZ($A$1,$B13,J$1,$B$1)} -> 0 | ... BK13: {=+_xll.EQNXTDZ($A$1,$B13,BK$1,$B$1)} -> 0
A14: Interest Expended | B14: QTR_INTEREST_EX | C14: {=+_xll.EQNXTDZ($A$1,$B14,C$1,$B$1)} -> 0 | D14: {=+_xll.EQNXTDZ($A$1,$B14,D$1,$B$1)} -> 0 | E14: {=+_xll.EQNXTDZ($A$1,$B14,E$1,$B$1)} -> 0 | F14: {=+_xll.EQNXTDZ($A$1,$B14,F$1,$B$1)} -> 0 | G14: {=+_xll.EQNXTDZ($A$1,$B14,G$1,$B$1)} -> 0 | H14: {=+_xll.EQNXTDZ($A$1,$B14,H$1,$B$1)} -> 0 | I14: {=+_xll.EQNXTDZ($A$1,$B14,I$1,$B$1)} -> 0 | J14: {=+_xll.EQNXTDZ($A$1,$B14,J$1,$B$1)} -> 0 | ... BK14: {=+_xll.EQNXTDZ($A$1,$B14,BK$1,$B$1)} -> 0
A15: Operating & Manufacturing Expenses | B15: QTR_MFG_EXPS | C15: {=+_xll.EQNXTDZ($A$1,$B15,C$1,$B$1)} -> 0 | D15: {=+_xll.EQNXTDZ($A$1,$B15,D$1,$B$1)} -> 0 | E15: {=+_xll.EQNXTDZ($A$1,$B15,E$1,$B$1)} -> 0 | F15: {=+_xll.EQNXTDZ($A$1,$B15,F$1,$B$1)} -> 0 | G15: {=+_xll.EQNXTDZ($A$1,$B15,G$1,$B$1)} -> 0 | H15: {=+_xll.EQNXTDZ($A$1,$B15,H$1,$B$1)} -> 0 | I15: {=+_xll.EQNXTDZ($A$1,$B15,I$1,$B$1)} -> 0 | J15: {=+_xll.EQNXTDZ($A$1,$B15,J$1,$B$1)} -> 0 | ... BK15: {=+_xll.EQNXTDZ($A$1,$B15,BK$1,$B$1)} -> 0
A16: (Increase) / Decrease In Stocks | B16: QTR_INC_DEC_INVENTORY | C16: {=+_xll.EQNXTDZ($A$1,$B16,C$1,$B$1)} -> 0 | D16: {=+_xll.EQNXTDZ($A$1,$B16,D$1,$B$1)} -> 0 | E16: {=+_xll.EQNXTDZ($A$1,$B16,E$1,$B$1)} -> 0 | F16: {=+_xll.EQNXTDZ($A$1,$B16,F$1,$B$1)} -> 0 | G16: {=+_xll.EQNXTDZ($A$1,$B16,G$1,$B$1)} -> 0 | H16: {=+_xll.EQNXTDZ($A$1,$B16,H$1,$B$1)} -> 0 | I16: {=+_xll.EQNXTDZ($A$1,$B16,I$1,$B$1)} -> 0 | J16: {=+_xll.EQNXTDZ($A$1,$B16,J$1,$B$1)} -> 0 | ... BK16: {=+_xll.EQNXTDZ($A$1,$B16,BK$1,$B$1)} -> 0
A17: Cost of Services & Raw Materials | B17: QTR_RAW_MATERIAL_COST | C17: {=+_xll.EQNXTDZ($A$1,$B17,C$1,$B$1)} -> 0 | D17: {=+_xll.EQNXTDZ($A$1,$B17,D$1,$B$1)} -> 0 | E17: {=+_xll.EQNXTDZ($A$1,$B17,E$1,$B$1)} -> 0 | F17: {=+_xll.EQNXTDZ($A$1,$B17,F$1,$B$1)} -> 0 | G17: {=+_xll.EQNXTDZ($A$1,$B17,G$1,$B$1)} -> 0 | H17: {=+_xll.EQNXTDZ($A$1,$B17,H$1,$B$1)} -> 0 | I17: {=+_xll.EQNXTDZ($A$1,$B17,I$1,$B$1)} -> 0 | J17: {=+_xll.EQNXTDZ($A$1,$B17,J$1,$B$1)} -> 0 | ... BK17: {=+_xll.EQNXTDZ($A$1,$B17,BK$1,$B$1)} -> 0
A18: Purchase of Finished Goods | B18: QTR_PURCHASE_FIN_GOOD | C18: {=+_xll.EQNXTDZ($A$1,$B18,C$1,$B$1)} -> 0 | D18: {=+_xll.EQNXTDZ($A$1,$B18,D$1,$B$1)} -> 0 | E18: {=+_xll.EQNXTDZ($A$1,$B18,E$1,$B$1)} -> 0 | F18: {=+_xll.EQNXTDZ($A$1,$B18,F$1,$B$1)} -> 0 | G18: {=+_xll.EQNXTDZ($A$1,$B18,G$1,$B$1)} -> 0 | H18: {=+_xll.EQNXTDZ($A$1,$B18,H$1,$B$1)} -> 0 | I18: {=+_xll.EQNXTDZ($A$1,$B18,I$1,$B$1)} -> 0 | J18: {=+_xll.EQNXTDZ($A$1,$B18,J$1,$B$1)} -> 0 | ... BK18: {=+_xll.EQNXTDZ($A$1,$B18,BK$1,$B$1)} -> 0
... A47: Face Value | B47: QTR_FV | C47: {=+_xll.EQNXTDZ($A$1,$B47,C$1,$B$1)} -> 0 | D47: {=+_xll.EQNXTDZ($A$1,$B47,D$1,$B$1)} -> 0 | E47: {=+_xll.EQNXTDZ($A$1,$B47,E$1,$B$1)} -> 0 | F47: {=+_xll.EQNXTDZ($A$1,$B47,F$1,$B$1)} -> 0 | G47: {=+_xll.EQNXTDZ($A$1,$B47,G$1,$B$1)} -> 0 | H47: {=+_xll.EQNXTDZ($A$1,$B47,H$1,$B$1)} -> 0 | I47: {=+_xll.EQNXTDZ($A$1,$B47,I$1,$B$1)} -> 0 | J47: {=+_xll.EQNXTDZ($A$1,$B47,J$1,$B$1)} -> 0 | ... BK47: {=+_xll.EQNXTDZ($A$1,$B47,BK$1,$B$1)} -> 0
A49: Field Description | B49: Field Name
A50: Equity Paid Up | B50: QTR_EQUITY_CAP | C50: {=+_xll.EQNXTDZ($A$1,$B50,C$1,$B$1)} -> 0 | D50: {=+_xll.EQNXTDZ($A$1,$B50,D$1,$B$1)} -> 0 | E50: {=+_xll.EQNXTDZ($A$1,$B50,E$1,$B$1)} -> 0 | F50: {=+_xll.EQNXTDZ($A$1,$B50,F$1,$B$1)} -> 0 | G50: {=+_xll.EQNXTDZ($A$1,$B50,G$1,$B$1)} -> 0 | H50: {=+_xll.EQNXTDZ($A$1,$B50,H$1,$B$1)} -> 0 | I50: {=+_xll.EQNXTDZ($A$1,$B50,I$1,$B$1)} -> 0 | J50: {=+_xll.EQNXTDZ($A$1,$B50,J$1,$B$1)} -> 0 | ... BK50: {=+_xll.EQNXTDZ($A$1,$B50,BK$1,$B$1)} -> 0
A51: Face value | B51: QTR_FV | C51: {=+_xll.EQNXTDZ($A$1,$B51,C$1,$B$1)} -> 0 | D51: {=+_xll.EQNXTDZ($A$1,$B51,D$1,$B$1)} -> 0 | E51: {=+_xll.EQNXTDZ($A$1,$B51,E$1,$B$1)} -> 0 | F51: {=+_xll.EQNXTDZ($A$1,$B51,F$1,$B$1)} -> 0 | G51: {=+_xll.EQNXTDZ($A$1,$B51,G$1,$B$1)} -> 0 | H51: {=+_xll.EQNXTDZ($A$1,$B51,H$1,$B$1)} -> 0 | I51: {=+_xll.EQNXTDZ($A$1,$B51,I$1,$B$1)} -> 0 | J51: {=+_xll.EQNXTDZ($A$1,$B51,J$1,$B$1)} -> 0 | ... BK51: {=+_xll.EQNXTDZ($A$1,$B51,BK$1,$B$1)} -> 0
A54: Share Capital | B54: QTRB_SHARE_CAPITAL | C54: {=+_xll.EQNXTDZ($A$1,$B54,C$1,$B$1)} -> 0 | D54: {=+_xll.EQNXTDZ($A$1,$B54,D$1,$B$1)} -> 0 | E54: {=+_xll.EQNXTDZ($A$1,$B54,E$1,$B$1)} -> 0 | F54: {=+_xll.EQNXTDZ($A$1,$B54,F$1,$B$1)} -> 0 | G54: {=+_xll.EQNXTDZ($A$1,$B54,G$1,$B$1)} -> 0 | H54: {=+_xll.EQNXTDZ($A$1,$B54,H$1,$B$1)} -> 0 | I54: {=+_xll.EQNXTDZ($A$1,$B54,I$1,$B$1)} -> 0 | J54: {=+_xll.EQNXTDZ($A$1,$B54,J$1,$B$1)} -> 0 | ... BK54: {=+_xll.EQNXTDZ($A$1,$B54,BK$1,$B$1)} -> 0
A55: Share Warrants & outstandings | B55: QTRB_SHAREWARNDOUT | C55: {=+_xll.EQNXTDZ($A$1,$B55,C$1,$B$1)} -> 0 | D55: {=+_xll.EQNXTDZ($A$1,$B55,D$1,$B$1)} -> 0 | E55: {=+_xll.EQNXTDZ($A$1,$B55,E$1,$B$1)} -> 0 | F55: {=+_xll.EQNXTDZ($A$1,$B55,F$1,$B$1)} -> 0 | G55: {=+_xll.EQNXTDZ($A$1,$B55,G$1,$B$1)} -> 0 | H55: {=+_xll.EQNXTDZ($A$1,$B55,H$1,$B$1)} -> 0 | I55: {=+_xll.EQNXTDZ($A$1,$B55,I$1,$B$1)} -> 0 | J55: {=+_xll.EQNXTDZ($A$1,$B55,J$1,$B$1)} -> 0 | ... BK55: {=+_xll.EQNXTDZ($A$1,$B55,BK$1,$B$1)} -> 0
A56: Reserves & Surplus | B56: QTRB_RESERVE | C56: {=+_xll.EQNXTDZ($A$1,$B56,C$1,$B$1)} -> 0 | D56: {=+_xll.EQNXTDZ($A$1,$B56,D$1,$B$1)} -> 0 | E56: {=+_xll.EQNXTDZ($A$1,$B56,E$1,$B$1)} -> 0 | F56: {=+_xll.EQNXTDZ($A$1,$B56,F$1,$B$1)} -> 0 | G56: {=+_xll.EQNXTDZ($A$1,$B56,G$1,$B$1)} -> 0 | H56: {=+_xll.EQNXTDZ($A$1,$B56,H$1,$B$1)} -> 0 | I56: {=+_xll.EQNXTDZ($A$1,$B56,I$1,$B$1)} -> 0 | J56: {=+_xll.EQNXTDZ($A$1,$B56,J$1,$B$1)} -> 0 | ... BK56: {=+_xll.EQNXTDZ($A$1,$B56,BK$1,$B$1)} -> 0
A57: Shareholder's Funds | B57: QTRB_SHAREHODERS_FUNDS | C57: {=+_xll.EQNXTDZ($A$1,$B57,C$1,$B$1)} -> 0 | D57: {=+_xll.EQNXTDZ($A$1,$B57,D$1,$B$1)} -> 0 | E57: {=+_xll.EQNXTDZ($A$1,$B57,E$1,$B$1)} -> 0 | F57: {=+_xll.EQNXTDZ($A$1,$B57,F$1,$B$1)} -> 0 | G57: {=+_xll.EQNXTDZ($A$1,$B57,G$1,$B$1)} -> 0 | H57: {=+_xll.EQNXTDZ($A$1,$B57,H$1,$B$1)} -> 0 | I57: {=+_xll.EQNXTDZ($A$1,$B57,I$1,$B$1)} -> 0 | J57: {=+_xll.EQNXTDZ($A$1,$B57,J$1,$B$1)} -> 0 | ... BK57: {=+_xll.EQNXTDZ($A$1,$B57,BK$1,$B$1)} -> 0
A58: Minority Interest | B58: QTRB_MINORITY_INTEREST_BS | C58: {=+_xll.EQNXTDZ($A$1,$B58,C$1,$B$1)} -> 0 | D58: {=+_xll.EQNXTDZ($A$1,$B58,D$1,$B$1)} -> 0 | E58: {=+_xll.EQNXTDZ($A$1,$B58,E$1,$B$1)} -> 0 | F58: {=+_xll.EQNXTDZ($A$1,$B58,F$1,$B$1)} -> 0 | G58: {=+_xll.EQNXTDZ($A$1,$B58,G$1,$B$1)} -> 0 | H58: {=+_xll.EQNXTDZ($A$1,$B58,H$1,$B$1)} -> 0 | I58: {=+_xll.EQNXTDZ($A$1,$B58,I$1,$B$1)} -> 0 | J58: {=+_xll.EQNXTDZ($A$1,$B58,J$1,$B$1)} -> 0 | ... BK58: {=+_xll.EQNXTDZ($A$1,$B58,BK$1,$B$1)} -> 0
A59: Long Term Borrowings | B59: QTRB_TOTAL_DEBTS | C59: {=+_xll.EQNXTDZ($A$1,$B59,C$1,$B$1)} -> 0 | D59: {=+_xll.EQNXTDZ($A$1,$B59,D$1,$B$1)} -> 0 | E59: {=+_xll.EQNXTDZ($A$1,$B59,E$1,$B$1)} -> 0 | F59: {=+_xll.EQNXTDZ($A$1,$B59,F$1,$B$1)} -> 0 | G59: {=+_xll.EQNXTDZ($A$1,$B59,G$1,$B$1)} -> 0 | H59: {=+_xll.EQNXTDZ($A$1,$B59,H$1,$B$1)} -> 0 | I59: {=+_xll.EQNXTDZ($A$1,$B59,I$1,$B$1)} -> 0 | J59: {=+_xll.EQNXTDZ($A$1,$B59,J$1,$B$1)} -> 0 | ... BK59: {=+_xll.EQNXTDZ($A$1,$B59,BK$1,$B$1)} -> 0
A60: Secured Loans | B60: QTRB_SECURED_LOANS | C60: {=+_xll.EQNXTDZ($A$1,$B60,C$1,$B$1)} -> 0 | D60: {=+_xll.EQNXTDZ($A$1,$B60,D$1,$B$1)} -> 0 | E60: {=+_xll.EQNXTDZ($A$1,$B60,E$1,$B$1)} -> 0 | F60: {=+_xll.EQNXTDZ($A$1,$B60,F$1,$B$1)} -> 0 | G60: {=+_xll.EQNXTDZ($A$1,$B60,G$1,$B$1)} -> 0 | H60: {=+_xll.EQNXTDZ($A$1,$B60,H$1,$B$1)} -> 0 | I60: {=+_xll.EQNXTDZ($A$1,$B60,I$1,$B$1)} -> 0 | J60: {=+_xll.EQNXTDZ($A$1,$B60,J$1,$B$1)} -> 0 | ... BK60: {=+_xll.EQNXTDZ($A$1,$B60,BK$1,$B$1)} -> 0
A61: Unsecured Loans | B61: QTRB_UNSECURED_LOANS_NF | C61: {=+_xll.EQNXTDZ($A$1,$B61,C$1,$B$1)} -> 0 | D61: {=+_xll.EQNXTDZ($A$1,$B61,D$1,$B$1)} -> 0 | E61: {=+_xll.EQNXTDZ($A$1,$B61,E$1,$B$1)} -> 0 | F61: {=+_xll.EQNXTDZ($A$1,$B61,F$1,$B$1)} -> 0 | G61: {=+_xll.EQNXTDZ($A$1,$B61,G$1,$B$1)} -> 0 | H61: {=+_xll.EQNXTDZ($A$1,$B61,H$1,$B$1)} -> 0 | I61: {=+_xll.EQNXTDZ($A$1,$B61,I$1,$B$1)} -> 0 | J61: {=+_xll.EQNXTDZ($A$1,$B61,J$1,$B$1)} -> 0 | ... BK61: {=+_xll.EQNXTDZ($A$1,$B61,BK$1,$B$1)} -> 0
A62: Other Long Term Liabilities | B62: QTRB_OTHER_LT_LIABILITIES | C62: {=+_xll.EQNXTDZ($A$1,$B62,C$1,$B$1)} -> 0 | D62: {=+_xll.EQNXTDZ($A$1,$B62,D$1,$B$1)} -> 0 | E62: {=+_xll.EQNXTDZ($A$1,$B62,E$1,$B$1)} -> 0 | F62: {=+_xll.EQNXTDZ($A$1,$B62,F$1,$B$1)} -> 0 | G62: {=+_xll.EQNXTDZ($A$1,$B62,G$1,$B$1)} -> 0 | H62: {=+_xll.EQNXTDZ($A$1,$B62,H$1,$B$1)} -> 0 | I62: {=+_xll.EQNXTDZ($A$1,$B62,I$1,$B$1)} -> 0 | J62: {=+_xll.EQNXTDZ($A$1,$B62,J$1,$B$1)} -> 0 | ... BK62: {=+_xll.EQNXTDZ($A$1,$B62,BK$1,$B$1)} -> 0
A63: Long Term Trade Payables | B63: QTRB_LT_TRADE_PAYABLE | C63: {=+_xll.EQNXTDZ($A$1,$B63,C$1,$B$1)} -> 0 | D63: {=+_xll.EQNXTDZ($A$1,$B63,D$1,$B$1)} -> 0 | E63: {=+_xll.EQNXTDZ($A$1,$B63,E$1,$B$1)} -> 0 | F63: {=+_xll.EQNXTDZ($A$1,$B63,F$1,$B$1)} -> 0 | G63: {=+_xll.EQNXTDZ($A$1,$B63,G$1,$B$1)} -> 0 | H63: {=+_xll.EQNXTDZ($A$1,$B63,H$1,$B$1)} -> 0 | I63: {=+_xll.EQNXTDZ($A$1,$B63,I$1,$B$1)} -> 0 | J63: {=+_xll.EQNXTDZ($A$1,$B63,J$1,$B$1)} -> 0 | ... BK63: {=+_xll.EQNXTDZ($A$1,$B63,BK$1,$B$1)} -> 0
... A97: Book Value | B97: QTRB_BOOKVALUE | C97: {=+_xll.EQNXTDZ($A$1,$B97,C$1,$B$1)} -> 0 | D97: {=+_xll.EQNXTDZ($A$1,$B97,D$1,$B$1)} -> 0 | E97: {=+_xll.EQNXTDZ($A$1,$B97,E$1,$B$1)} -> 0 | F97: {=+_xll.EQNXTDZ($A$1,$B97,F$1,$B$1)} -> 0 | G97: {=+_xll.EQNXTDZ($A$1,$B97,G$1,$B$1)} -> 0 | H97: {=+_xll.EQNXTDZ($A$1,$B97,H$1,$B$1)} -> 0 | I97: {=+_xll.EQNXTDZ($A$1,$B97,I$1,$B$1)} -> 0 | J97: {=+_xll.EQNXTDZ($A$1,$B97,J$1,$B$1)} -> 0 | ... BK97: {=+_xll.EQNXTDZ($A$1,$B97,BK$1,$B$1)} -> 0

Sheet QTR Share Price
A1: =+'Annual Raw'!A1 -> 221842 | C1: 201206 | D1: 201207 | E1: 201208 | F1: 201209 | G1: 201210 | H1: 201211 | I1: 201212 | J1: 201301 | K1: 201302 | L1: 201303 | M1: 201304 | N1: 201305 | O1: 201306 | P1: 201307 | Q1: 201308 | R1: 201309 | S1: 201310 | T1: 201311 | U1: 201312 | V1: 201401 | W1: 201402 | X1: 201403 | Y1: 201404 | Z1: 201405 | AA1: 201406 | AB1: 201407 | AC1: 201408 | AD1: 201409 | AE1: 201410 | AF1: 201411 | AG1: 201412 | AH1: 201501 | AI1: 201502 | AJ1: 201503 | AK1: 201504 | AL1: 201505 | AM1: 201506 | AN1: 201507 | AO1: 201508 | AP1: 201509 | AQ1: 201510 | AR1: 201511 | AS1: 201512 | AT1: 201601 | AU1: 201602 | AV1: 201603 | AW1: 201604 | AX1: 201605 | AY1: 201606 | AZ1: 201607 | BA1: 201608 | BB1: 201609 | BC1: 201610 | BD1: 201611 | BE1: 201612 | BF1: 201701 | BG1: 201702 | BH1: 201703 | BI1: 201704 | BJ1: 201705 | BK1: 201706 | BL1: 201707 | BM1: 201708 | BN1: 201709 | BO1: 201710 | BP1: 201711 | BQ1: 201712 | BR1: 201801 | BS1: 201802 | BT1: 201803 | BU1: 201804 | BV1: 201805 | BW1: 201806 | BX1: 201807 | BY1: 201808 | BZ1: 201809 | CA1: 201810 | CB1: 201811 | CC1: 201812 | CD1: 201901 | CE1: 201902 | CF1: 201903 | CG1: 201904 | CH1: 201905 | CI1: 201906 | CJ1: 201907 | CK1: 201908 | CL1: 201909 | CM1: 201910 | CN1: 201911 | CO1: 201912 | CP1: 202001 | CQ1: 202002 | CR1: 202003 | CS1: 202004 | CT1: 202005 | CU1: 202006 | CV1: 202007 | CW1: 202008 | CX1: 202009 | CY1: 202010 | CZ1: 202011 | DA1: 202012 | DB1: 202101 | DC1: 202102 | DD1: 202103 | DE1: 202104 | DF1: 202105 | DG1: 202106 | DH1: 202107 | DI1: 202108 | DJ1: 202109 | DK1: 202110 | DL1: 202111 | DM1: 202112 | DN1: 202201 | DO1: 202202 | DP1: 202203 | DQ1: 202204 | DR1: 202205 | DS1: 202206 | DT1: 202207 | DU1: 202208 | DV1: 202209 | DW1: 202210 | DX1: 202211 | DY1: 202212 | DZ1: 202301 | EA1: 202302 | EB1: 202303 | EC1: 202304 | ED1: 202305 | EE1: 202306 | EF1: 202307 | EG1: 202308 | EH1: 202309 | EI1: 202310 | EJ1: 202311 | EK1: 202312 | EL1: 202401 | EM1: 202402 | EN1: 202403 | EO1: 202404 | EP1: 202405 | EQ1: 202406 | ER1: 202407 | ES1: 202408 | ET1: 202409 | EU1: 202410 | EV1: 202411 | EW1: 202412 | EX1: 202501 | EY1: 202502 | EZ1: 202503 | FA1: 202504 | FB1: 202505 | FC1: 202506 | FD1: 202507 | FE1: 202508 | FF1: 202509 | FG1: 202510 | FH1: 202511 | FI1: 202512 | FJ1: 202601 | FK1: 202602 | FL1: 202603 | FM1: 202604 | FN1: 202605 | FO1: 202606 | FP1: 202607 | FQ1: 202608 | FR1: 202609 | FS1: 202610 | FT1: 202611 | FU1: 202612 | FV1: 202701 | FW1: 202702 | FX1: 202703 | FY1: 202704 | FZ1: 202705 | GA1: 202706 | GB1: 202707 | GC1: 202708 | GD1: 202709 | GE1: 202710 | GF1: 202711 | GG1: 202712 | GH1: 202801 | GI1: 202802 | GJ1: 202803 | GK1: 202804 | GL1: 202805 | GM1: 202806 | GN1: 202807 | GO1: 202808 | GP1: 202809 | GQ1: 202810 | GR1: 202811 | GS1: 202812 | GT1: 202901 | GU1: 202902 | GV1: 202903 | GW1: 202904 | GX1: 202905 | GY1: 202906 | GZ1: 202907 | HA1: 202908 | HB1: 202909 | HC1: 202910 | HD1: 202911 | HE1: 202912 | HF1: 203001 | HG1: 203002 | HH1: 203003 | HM1: 201206 | HN1: 201207 | HO1: 201208 | HP1: 201209 | HQ1: 201212 | HR1: 201303 | HS1: 201306 | HT1: 201309 | HU1: 201312 | HV1: 201403 | HW1: 201406 | HX1: 201409 | HY1: 201412 | HZ1: 201503 | IA1: 201506 | IB1: 201509 | IC1: 201512 | ID1: 201603 | IE1: 201606 | IF1: 201609 | IG1: 201612 | IH1: 201703 | II1: 201706 | IJ1: 201709 | IK1: 201712 | IL1: 201803 | IM1: 201806 | IN1: 201809 | IO1: 201812 | IP1: 201903 | IQ1: 201906 | IR1: 201909 | IS1: 201912 | IT1: 202003 | IU1: 202006 | IV1: 202009 | IW1: 202012 | IX1: 202103 | IY1: 202106 | IZ1: 202109 | JA1: 202112 | JB1: 202203 | JC1: 202206 | JD1: 202209 | JE1: 202212 | JF1: 202303 | JG1: 202306 | JH1: 202309 | JI1: 202312 | JJ1: 202403 | JK1: 202406 | JL1: 202409 | JM1: 202412 | JN1: 202503 | JO1: 202506 | JP1: 202509 | JQ1: 202512 | JR1: 202603 | JS1: 202606 | JT1: 202609 | JU1: 202612 | JV1: 202703 | JW1: 202706 | JX1: 202709 | JY1: 202712 | JZ1: 202803 | KA1: 202806 | KB1: 202809 | KC1: 202812 | KD1: 202903 | KE1: 202906 | KF1: 202909 | KG1: 202912 | KH1: 203003
A4: Field Description | B4: Field Name
A5: MonthEnd | B5: NMONTH_MONTHEND | C5: {=_xll.EQNXTDZ($A$1,$B5,C$1)} -> 0 | D5: {=_xll.EQNXTDZ($A$1,$B5,D$1)} -> 0 | E5: {=_xll.EQNXTDZ($A$1,$B5,E$1)} -> 0 | F5: {=_xll.EQNXTDZ($A$1,$B5,F$1)} -> 0 | G5: {=_xll.EQNXTDZ($A$1,$B5,G$1)} -> 0 | H5: {=_xll.EQNXTDZ($A$1,$B5,H$1)} -> 0 | I5: {=_xll.EQNXTDZ($A$1,$B5,I$1)} -> 0 | J5: {=_xll.EQNXTDZ($A$1,$B5,J$1)} -> 0 | ... HH5: {=_xll.EQNXTDZ($A$1,$B5,HH$1)} -> 0
A6: Open | B6: NMONTH_OPEN | C6: {=_xll.EQNXTDZ($A$1,$B6,C$1)} -> 0 | D6: {=_xll.EQNXTDZ($A$1,$B6,D$1)} -> 0 | E6: {=_xll.EQNXTDZ($A$1,$B6,E$1)} -> 0 | F6: {=_xll.EQNXTDZ($A$1,$B6,F$1)} -> 0 | G6: {=_xll.EQNXTDZ($A$1,$B6,G$1)} -> 0 | H6: {=_xll.EQNXTDZ($A$1,$B6,H$1)} -> 0 | I6: {=_xll.EQNXTDZ($A$1,$B6,I$1)} -> 0 | J6: {=_xll.EQNXTDZ($A$1,$B6,J$1)} -> 0 | ... HH6: {=_xll.EQNXTDZ($A$1,$B6,HH$1)} -> 0
A7: High | B7: NMONTH_HIGH | C7: {=_xll.EQNXTDZ($A$1,$B7,C$1)} -> 0 | D7: {=_xll.EQNXTDZ($A$1,$B7,D$1)} -> 0 | E7: {=_xll.EQNXTDZ($A$1,$B7,E$1)} -> 0 | F7: {=_xll.EQNXTDZ($A$1,$B7,F$1)} -> 0 | G7: {=_xll.EQNXTDZ($A$1,$B7,G$1)} -> 0 | H7: {=_xll.EQNXTDZ($A$1,$B7,H$1)} -> 0 | I7: {=_xll.EQNXTDZ($A$1,$B7,I$1)} -> 0 | J7: {=_xll.EQNXTDZ($A$1,$B7,J$1)} -> 0 | ... HH7: {=_xll.EQNXTDZ($A$1,$B7,HH$1)} -> 0 | HP7: =+MAX(D7:F7) -> 0 | HQ7: =+MAX(G7:I7) -> 0 | HR7: =+MAX(J7:L7) -> 0 | HS7: =+MAX(M7:O7) -> 0 | HT7: =+MAX(P7:R7) -> 0 | HU7: =+MAX(S7:U7) -> 0 | HV7: =+MAX(V7:X7) -> 0 | HW7: =+MAX(Y7:AA7) -> 0 | HX7: =+MAX(AB7:AD7) -> 0 | HY7: =+MAX(AE7:AG7) -> 0 | HZ7: =+MAX(AH7:AJ7) -> 0 | IA7: =+MAX(AK7:AM7) -> 0 | IB7: =+MAX(AN7:AP7) -> 0 | IC7: =+MAX(AQ7:AS7) -> 0 | ID7: =+MAX(AT7:AV7) -> 0 | IE7: =+MAX(AW7:AY7) -> 0 | IF7: =+MAX(AZ7:BB7) -> 0 | IG7: =+MAX(BC7:BE7) -> 0 | IH7: =+MAX(BF7:BH7) -> 0 | II7: =+MAX(BI7:BK7) -> 0 | IJ7: =+MAX(BL7:BN7) -> 0 | IK7: =+MAX(BO7:BQ7) -> 0 | IL7: =+MAX(BR7:BT7) -> 0 | IM7: =+MAX(BU7:BW7) -> 0 | IN7: =+MAX(BX7:BZ7) -> 426.9 | IO7: =+MAX(CA7:CC7) -> 399.8 | IP7: =+MAX(CD7:CF7) -> 525 | IQ7: =+MAX(CG7:CI7) -> 599 | IR7: =+MAX(CJ7:CL7) -> 689.9 | IS7: =+MAX(CM7:CO7) -> 849 | IT7: =+MAX(CP7:CR7) -> 1000 | IU7: =+MAX(CS7:CU7) -> 582.55 | IV7: =+MAX(CV7:CX7) -> 760 | IW7: =+MAX(CY7:DA7) -> 839.95 | IX7: =+MAX(DB7:DD7) -> 814 | IY7: =+MAX(DE7:DG7) -> 808.4 | IZ7: =+MAX(DH7:DJ7) -> 757.05 | JA7: =+MAX(DK7:DM7) -> 729.65 | JB7: =+MAX(DN7:DP7) -> 877.7 | JC7: =+MAX(DQ7:DS7) -> 1154 | JD7: =+MAX(DT7:DV7) -> 1094.95 | JE7: =+MAX(DW7:DY7) -> 1035 | JF7: =+MAX(DZ7:EB7) -> 1022 | JG7: =+MAX(EC7:EE7) -> 1396.9 | JH7: =+MAX(EF7:EH7) -> 1502 | JI7: =+MAX(EI7:EK7) -> 1796 | JJ7: =+MAX(EL7:EN7) -> 1790.75 | JK7: =MAX(EO7:EQ7) -> 1551.95 | JL7: =MAX(ER7:ET7) -> 1407.95 | JM7: =MAX(EU7:EW7) -> 1207.5 | JN7: =MAX(EX7:EZ7) -> 1119.55 | JO7: =MAX(FA7:FC7) -> 1253.6 | JP7: =MAX(FD7:FF7) -> 1430 | JQ7: =MAX(FG7:FI7) -> 1490.1 | JR7: =MAX(FJ7:FL7) -> 1496.7 | JS7: =MAX(FM7:FO7) -> 1568 | JT7: =MAX(FP7:FR7) -> 0 | JU7: =MAX(FS7:FU7) -> 0 | JV7: =MAX(FV7:FX7) -> 0 | JW7: =MAX(FY7:GA7) -> 0 | JX7: =MAX(GB7:GD7) -> 0 | JY7: =MAX(GE7:GG7) -> 0 | JZ7: =MAX(GH7:GJ7) -> 0 | KA7: =MAX(GK7:GM7) -> 0 | KB7: =MAX(GN7:GP7) -> 0 | KC7: =MAX(GQ7:GS7) -> 0 | KD7: =MAX(GT7:GV7) -> 0 | KE7: =MAX(GW7:GY7) -> 0 | KF7: =MAX(GZ7:HB7) -> 0 | KG7: =MAX(HC7:HE7) -> 0 | KH7: =MAX(HF7:HH7) -> 0
A8: Low | B8: NMONTH_LOW | C8: {=_xll.EQNXTDZ($A$1,$B8,C$1)} -> 0 | D8: {=_xll.EQNXTDZ($A$1,$B8,D$1)} -> 0 | E8: {=_xll.EQNXTDZ($A$1,$B8,E$1)} -> 0 | F8: {=_xll.EQNXTDZ($A$1,$B8,F$1)} -> 0 | G8: {=_xll.EQNXTDZ($A$1,$B8,G$1)} -> 0 | H8: {=_xll.EQNXTDZ($A$1,$B8,H$1)} -> 0 | I8: {=_xll.EQNXTDZ($A$1,$B8,I$1)} -> 0 | J8: {=_xll.EQNXTDZ($A$1,$B8,J$1)} -> 0 | ... HH8: {=_xll.EQNXTDZ($A$1,$B8,HH$1)} -> 0 | HP8: =+MIN(D8:F8) -> 0 | HQ8: =+MIN(G8:I8) -> 0 | HR8: =+MIN(J8:L8) -> 0 | HS8: =+MIN(M8:O8) -> 0 | HT8: =+MIN(P8:R8) -> 0 | HU8: =+MIN(S8:U8) -> 0 | HV8: =+MIN(V8:X8) -> 0 | HW8: =+MIN(Y8:AA8) -> 0 | HX8: =+MIN(AB8:AD8) -> 0 | HY8: =+MIN(AE8:AG8) -> 0 | HZ8: =+MIN(AH8:AJ8) -> 0 | IA8: =+MIN(AK8:AM8) -> 0 | IB8: =+MIN(AN8:AP8) -> 0 | IC8: =+MIN(AQ8:AS8) -> 0 | ID8: =+MIN(AT8:AV8) -> 0 | IE8: =+MIN(AW8:AY8) -> 0 | IF8: =+MIN(AZ8:BB8) -> 0 | IG8: =+MIN(BC8:BE8) -> 0 | IH8: =+MIN(BF8:BH8) -> 0 | II8: =+MIN(BI8:BK8) -> 0 | IJ8: =+MIN(BL8:BN8) -> 0 | IK8: =+MIN(BO8:BQ8) -> 0 | IL8: =+MIN(BR8:BT8) -> 0 | IM8: =+MIN(BU8:BW8) -> 0 | IN8: =+MIN(BX8:BZ8) -> 0 | IO8: =+MIN(CA8:CC8) -> 242.05 | IP8: =+MIN(CD8:CF8) -> 329.9 | IQ8: =+MIN(CG8:CI8) -> 396.2 | IR8: =+MIN(CJ8:CL8) -> 481.1 | IS8: =+MIN(CM8:CO8) -> 602.25 | IT8: =+MIN(CP8:CR8) -> 337.35 | IU8: =+MIN(CS8:CU8) -> 305.2 | IV8: =+MIN(CV8:CX8) -> 498.05 | IW8: =+MIN(CY8:DA8) -> 611.95 | IX8: =+MIN(DB8:DD8) -> 640.05 | IY8: =+MIN(DE8:DG8) -> 542.1 | IZ8: =+MIN(DH8:DJ8) -> 592.95 | JA8: =+MIN(DK8:DM8) -> 494.7 | JB8: =+MIN(DN8:DP8) -> 560.25 | JC8: =+MIN(DQ8:DS8) -> 845.95 | JD8: =+MIN(DT8:DV8) -> 946.45 | JE8: =+MIN(DW8:DY8) -> 845.2 | JF8: =+MIN(DZ8:EB8) -> 834.1 | JG8: =+MIN(EC8:EE8) -> 904 | JH8: =+MIN(EF8:EH8) -> 1240.35 | JI8: =+MIN(EI8:EK8) -> 1290 | JJ8: =+MIN(EL8:EN8) -> 1277.95 | JK8: =MIN(EO8:EQ8) -> 1190.1 | JL8: =MIN(ER8:ET8) -> 1153 | JM8: =MIN(EU8:EW8) -> 810 | JN8: =MIN(EX8:EZ8) -> 750.2 | JO8: =MIN(FA8:FC8) -> 920 | JP8: =MIN(FD8:FF8) -> 1198 | JQ8: =MIN(FG8:FI8) -> 1228.9 | JR8: =MIN(FJ8:FL8) -> 1113 | JS8: =MIN(FM8:FO8) -> 1158.1 | JT8: =MIN(FP8:FR8) -> 0 | JU8: =MIN(FS8:FU8) -> 0 | JV8: =MIN(FV8:FX8) -> 0 | JW8: =MIN(FY8:GA8) -> 0 | JX8: =MIN(GB8:GD8) -> 0 | JY8: =MIN(GE8:GG8) -> 0 | JZ8: =MIN(GH8:GJ8) -> 0 | KA8: =MIN(GK8:GM8) -> 0 | KB8: =MIN(GN8:GP8) -> 0 | KC8: =MIN(GQ8:GS8) -> 0 | KD8: =MIN(GT8:GV8) -> 0 | KE8: =MIN(GW8:GY8) -> 0 | KF8: =MIN(GZ8:HB8) -> 0 | KG8: =MIN(HC8:HE8) -> 0 | KH8: =MIN(HF8:HH8) -> 0
A9: Close | B9: NMONTH_CLOSE | C9: {=_xll.EQNXTDZ($A$1,$B9,C$1)} -> 0 | D9: {=_xll.EQNXTDZ($A$1,$B9,D$1)} -> 0 | E9: {=_xll.EQNXTDZ($A$1,$B9,E$1)} -> 0 | F9: {=_xll.EQNXTDZ($A$1,$B9,F$1)} -> 0 | G9: {=_xll.EQNXTDZ($A$1,$B9,G$1)} -> 0 | H9: {=_xll.EQNXTDZ($A$1,$B9,H$1)} -> 0 | I9: {=_xll.EQNXTDZ($A$1,$B9,I$1)} -> 0 | J9: {=_xll.EQNXTDZ($A$1,$B9,J$1)} -> 0 | ... HH9: {=_xll.EQNXTDZ($A$1,$B9,HH$1)} -> 0 | HP9: =+F9 -> 0 | HQ9: =+I9 -> 0 | HR9: =+L9 -> 0 | HS9: =+O9 -> 0 | HT9: =+R9 -> 0 | HU9: =+U9 -> 0 | HV9: =+X9 -> 0 | HW9: =+AA9 -> 0 | HX9: =+AD9 -> 0 | HY9: =+AG9 -> 0 | HZ9: =+AJ9 -> 0 | IA9: =+AM9 -> 0 | IB9: =+AP9 -> 0 | IC9: =+AS9 -> 0 | ID9: =+AV9 -> 0 | IE9: =+AY9 -> 0 | IF9: =+BB9 -> 0 | IG9: =+BE9 -> 0 | IH9: =+BH9 -> 0 | II9: =+BK9 -> 0 | IJ9: =+BN9 -> 0 | IK9: =+BQ9 -> 0 | IL9: =+BT9 -> 0 | IM9: =+BW9 -> 0 | IN9: =+BZ9 -> 293.4 | IO9: =+CC9 -> 383.25 | IP9: =+CF9 -> 504 | IQ9: =+CI9 -> 519.15 | IR9: =+CL9 -> 657.1 | IS9: =+CO9 -> 767.95 | IT9: =+CR9 -> 337.35 | IU9: =+CU9 -> 522.25 | IV9: =+CX9 -> 742.85 | IW9: =+DA9 -> 755.85 | IX9: =+DD9 -> 670.75 | IY9: =+DG9 -> 750 | IZ9: =+DJ9 -> 636.45 | JA9: =+DM9 -> 597.85 | JB9: =+DP9 -> 849.7 | JC9: =+DS9 -> 1015.8 | JD9: =+DV9 -> 994.1 | JE9: =+DY9 -> 915.3 | JF9: =+EB9 -> 915.2 | JG9: =+EE9 -> 1247.65 | JH9: =+EH9 -> 1315.5 | JI9: =+EK9 -> 1596.55 | JJ9: =+EN9 -> 1441.4 | JK9: =EQ9 -> 1322.1 | JL9: =ET9 -> 1197.6 | JM9: =EW9 -> 886.55 | JN9: =EZ9 -> 951.95 | JO9: =FC9 -> 1209.7 | JP9: =FF9 -> 1353.2 | JQ9: =FI9 -> 1273.6 | JR9: =FL9 -> 1158 | JS9: =FO9 -> 1407.5 | JT9: =FR9 -> 0 | JU9: =FU9 -> 0 | JV9: =FX9 -> 0 | JW9: =GA9 -> 0 | JX9: =GD9 -> 0 | JY9: =GG9 -> 0 | JZ9: =GJ9 -> 0 | KA9: =GM9 -> 0 | KB9: =GP9 -> 0 | KC9: =GS9 -> 0 | KD9: =GV9 -> 0 | KE9: =GY9 -> 0 | KF9: =HB9 -> 0 | KG9: =HE9 -> 0 | KH9: =HH9 -> 0
A11: Field Description | B11: Field Name | C11: {=_xll.EQNXTDZ($A$1,$B11,C$1)} -> 0 | D11: {=_xll.EQNXTDZ($A$1,$B11,D$1)} -> 0 | E11: {=_xll.EQNXTDZ($A$1,$B11,E$1)} -> 0 | F11: {=_xll.EQNXTDZ($A$1,$B11,F$1)} -> 0 | G11: {=_xll.EQNXTDZ($A$1,$B11,G$1)} -> 0 | H11: {=_xll.EQNXTDZ($A$1,$B11,H$1)} -> 0 | I11: {=_xll.EQNXTDZ($A$1,$B11,I$1)} -> 0 | J11: {=_xll.EQNXTDZ($A$1,$B11,J$1)} -> 0 | ... HH11: {=_xll.EQNXTDZ($A$1,$B11,HH$1)} -> 0
A12: Month End | B12: BMONTH_MONTHEND | C12: {=_xll.EQNXTDZ($A$1,$B12,C$1)} -> 0 | D12: {=_xll.EQNXTDZ($A$1,$B12,D$1)} -> 0 | E12: {=_xll.EQNXTDZ($A$1,$B12,E$1)} -> 0 | F12: {=_xll.EQNXTDZ($A$1,$B12,F$1)} -> 0 | G12: {=_xll.EQNXTDZ($A$1,$B12,G$1)} -> 0 | H12: {=_xll.EQNXTDZ($A$1,$B12,H$1)} -> 0 | I12: {=_xll.EQNXTDZ($A$1,$B12,I$1)} -> 0 | J12: {=_xll.EQNXTDZ($A$1,$B12,J$1)} -> 0 | ... HH12: {=_xll.EQNXTDZ($A$1,$B12,HH$1)} -> 0
A13: Open | B13: BMONTH_OPEN | C13: {=_xll.EQNXTDZ($A$1,$B13,C$1)} -> 0 | D13: {=_xll.EQNXTDZ($A$1,$B13,D$1)} -> 0 | E13: {=_xll.EQNXTDZ($A$1,$B13,E$1)} -> 0 | F13: {=_xll.EQNXTDZ($A$1,$B13,F$1)} -> 0 | G13: {=_xll.EQNXTDZ($A$1,$B13,G$1)} -> 0 | H13: {=_xll.EQNXTDZ($A$1,$B13,H$1)} -> 0 | I13: {=_xll.EQNXTDZ($A$1,$B13,I$1)} -> 0 | J13: {=_xll.EQNXTDZ($A$1,$B13,J$1)} -> 0 | ... HH13: {=_xll.EQNXTDZ($A$1,$B13,HH$1)} -> 0
A14: High | B14: BMONTH_HIGH | C14: {=_xll.EQNXTDZ($A$1,$B14,C$1)} -> 0 | D14: {=_xll.EQNXTDZ($A$1,$B14,D$1)} -> 0 | E14: {=_xll.EQNXTDZ($A$1,$B14,E$1)} -> 0 | F14: {=_xll.EQNXTDZ($A$1,$B14,F$1)} -> 0 | G14: {=_xll.EQNXTDZ($A$1,$B14,G$1)} -> 0 | H14: {=_xll.EQNXTDZ($A$1,$B14,H$1)} -> 0 | I14: {=_xll.EQNXTDZ($A$1,$B14,I$1)} -> 0 | J14: {=_xll.EQNXTDZ($A$1,$B14,J$1)} -> 0 | ... HH14: {=_xll.EQNXTDZ($A$1,$B14,HH$1)} -> 0 | HP14: =+MAX(D14:F14) -> 0 | HQ14: =+MAX(G14:I14) -> 0 | HR14: =+MAX(J14:L14) -> 0 | HS14: =+MAX(M14:O14) -> 0 | HT14: =+MAX(P14:R14) -> 0 | HU14: =+MAX(S14:U14) -> 0 | HV14: =+MAX(V14:X14) -> 0 | HW14: =+MAX(Y14:AA14) -> 0 | HX14: =+MAX(AB14:AD14) -> 0 | HY14: =+MAX(AE14:AG14) -> 0 | HZ14: =+MAX(AH14:AJ14) -> 0 | IA14: =+MAX(AK14:AM14) -> 0 | IB14: =+MAX(AN14:AP14) -> 0 | IC14: =+MAX(AQ14:AS14) -> 0 | ID14: =+MAX(AT14:AV14) -> 0 | IE14: =+MAX(AW14:AY14) -> 0 | IF14: =+MAX(AZ14:BB14) -> 0 | IG14: =+MAX(BC14:BE14) -> 0 | IH14: =+MAX(BF14:BH14) -> 0 | II14: =+MAX(BI14:BK14) -> 0 | IJ14: =+MAX(BL14:BN14) -> 0 | IK14: =+MAX(BO14:BQ14) -> 0 | IL14: =+MAX(BR14:BT14) -> 0 | IM14: =+MAX(BU14:BW14) -> 0 | IN14: =+MAX(BX14:BZ14) -> 423.3 | IO14: =+MAX(CA14:CC14) -> 399 | IP14: =+MAX(CD14:CF14) -> 520.95 | IQ14: =+MAX(CG14:CI14) -> 591 | IR14: =+MAX(CJ14:CL14) -> 689 | IS14: =+MAX(CM14:CO14) -> 848.55 | IT14: =+MAX(CP14:CR14) -> 1000.8 | IU14: =+MAX(CS14:CU14) -> 581.5 | IV14: =+MAX(CV14:CX14) -> 759.25 | IW14: =+MAX(CY14:DA14) -> 839 | IX14: =+MAX(DB14:DD14) -> 810 | IY14: =+MAX(DE14:DG14) -> 807.55 | IZ14: =+MAX(DH14:DJ14) -> 757.7 | JA14: =+MAX(DK14:DM14) -> 728.8 | JB14: =+MAX(DN14:DP14) -> 878.25 | JC14: =+MAX(DQ14:DS14) -> 1154.35 | JD14: =+MAX(DT14:DV14) -> 1094.45 | JE14: =+MAX(DW14:DY14) -> 1026.95 | JF14: =+MAX(DZ14:EB14) -> 1020.2 | JG14: =+MAX(EC14:EE14) -> 1397.65 | JH14: =+MAX(EF14:EH14) -> 1502.3 | JI14: =+MAX(EI14:EK14) -> 1794.4 | JJ14: =+MAX(EL14:EN14) -> 1789.75 | JK14: =MAX(EO14:EQ14) -> 1553 | JL14: =MAX(ER14:ET14) -> 1408.95 | JM14: =MAX(EU14:EW14) -> 1218.1 | JN14: =MAX(EX14:EZ14) -> 1118 | JO14: =MAX(FA14:FC14) -> 1253.65 | JP14: =MAX(FD14:FF14) -> 1431 | JQ14: =MAX(FG14:FI14) -> 1489.1 | JR14: =MAX(FJ14:FL14) -> 1496.6 | JS14: =MAX(FM14:FO14) -> 1566 | JT14: =MAX(FP14:FR14) -> 0 | JU14: =MAX(FS14:FU14) -> 0 | JV14: =MAX(FV14:FX14) -> 0 | JW14: =MAX(FY14:GA14) -> 0 | JX14: =MAX(GB14:GD14) -> 0 | JY14: =MAX(GE14:GG14) -> 0 | JZ14: =MAX(GH14:GJ14) -> 0 | KA14: =MAX(GK14:GM14) -> 0 | KB14: =MAX(GN14:GP14) -> 0 | KC14: =MAX(GQ14:GS14) -> 0 | KD14: =MAX(GT14:GV14) -> 0 | KE14: =MAX(GW14:GY14) -> 0 | KF14: =MAX(GZ14:HB14) -> 0 | KG14: =MAX(HC14:HE14) -> 0 | KH14: =MAX(HF14:HH14) -> 0
A15: Low | B15: BMONTH_LOW | C15: {=_xll.EQNXTDZ($A$1,$B15,C$1)} -> 0 | D15: {=_xll.EQNXTDZ($A$1,$B15,D$1)} -> 0 | E15: {=_xll.EQNXTDZ($A$1,$B15,E$1)} -> 0 | F15: {=_xll.EQNXTDZ($A$1,$B15,F$1)} -> 0 | G15: {=_xll.EQNXTDZ($A$1,$B15,G$1)} -> 0 | H15: {=_xll.EQNXTDZ($A$1,$B15,H$1)} -> 0 | I15: {=_xll.EQNXTDZ($A$1,$B15,I$1)} -> 0 | J15: {=_xll.EQNXTDZ($A$1,$B15,J$1)} -> 0 | ... HH15: {=_xll.EQNXTDZ($A$1,$B15,HH$1)} -> 0 | HP15: =+MIN(D15:F15) -> 0 | HQ15: =+MIN(G15:I15) -> 0 | HR15: =+MIN(J15:L15) -> 0 | HS15: =+MIN(M15:O15) -> 0 | HT15: =+MIN(P15:R15) -> 0 | HU15: =+MIN(S15:U15) -> 0 | HV15: =+MIN(V15:X15) -> 0 | HW15: =+MIN(Y15:AA15) -> 0 | HX15: =+MIN(AB15:AD15) -> 0 | HY15: =+MIN(AE15:AG15) -> 0 | HZ15: =+MIN(AH15:AJ15) -> 0 | IA15: =+MIN(AK15:AM15) -> 0 | IB15: =+MIN(AN15:AP15) -> 0 | IC15: =+MIN(AQ15:AS15) -> 0 | ID15: =+MIN(AT15:AV15) -> 0 | IE15: =+MIN(AW15:AY15) -> 0 | IF15: =+MIN(AZ15:BB15) -> 0 | IG15: =+MIN(BC15:BE15) -> 0 | IH15: =+MIN(BF15:BH15) -> 0 | II15: =+MIN(BI15:BK15) -> 0 | IJ15: =+MIN(BL15:BN15) -> 0 | IK15: =+MIN(BO15:BQ15) -> 0 | IL15: =+MIN(BR15:BT15) -> 0 | IM15: =+MIN(BU15:BW15) -> 0 | IN15: =+MIN(BX15:BZ15) -> 0 | IO15: =+MIN(CA15:CC15) -> 245.75 | IP15: =+MIN(CD15:CF15) -> 350.1 | IQ15: =+MIN(CG15:CI15) -> 398.7 | IR15: =+MIN(CJ15:CL15) -> 483 | IS15: =+MIN(CM15:CO15) -> 610 | IT15: =+MIN(CP15:CR15) -> 338.35 | IU15: =+MIN(CS15:CU15) -> 305.75 | IV15: =+MIN(CV15:CX15) -> 500 | IW15: =+MIN(CY15:DA15) -> 605.05 | IX15: =+MIN(DB15:DD15) -> 640 | IY15: =+MIN(DE15:DG15) -> 541 | IZ15: =+MIN(DH15:DJ15) -> 597 | JA15: =+MIN(DK15:DM15) -> 495.3 | JB15: =+MIN(DN15:DP15) -> 560 | JC15: =+MIN(DQ15:DS15) -> 847 | JD15: =+MIN(DT15:DV15) -> 947 | JE15: =+MIN(DW15:DY15) -> 845 | JF15: =+MIN(DZ15:EB15) -> 834.1 | JG15: =+MIN(EC15:EE15) -> 903.2 | JH15: =+MIN(EF15:EH15) -> 1240.35 | JI15: =+MIN(EI15:EK15) -> 1292.95 | JJ15: =+MIN(EL15:EN15) -> 1278 | JK15: =MIN(EO15:EQ15) -> 1193.7 | JL15: =MIN(ER15:ET15) -> 1153.55 | JM15: =MIN(EU15:EW15) -> 810.1 | JN15: =MIN(EX15:EZ15) -> 750.05 | JO15: =MIN(FA15:FC15) -> 860 | JP15: =MIN(FD15:FF15) -> 1197.05 | JQ15: =MIN(FG15:FI15) -> 1231 | JR15: =MIN(FJ15:FL15) -> 1112.9 | JS15: =MIN(FM15:FO15) -> 1157.35 | JT15: =MIN(FP15:FR15) -> 0 | JU15: =MIN(FS15:FU15) -> 0 | JV15: =MIN(FV15:FX15) -> 0 | JW15: =MIN(FY15:GA15) -> 0 | JX15: =MIN(GB15:GD15) -> 0 | JY15: =MIN(GE15:GG15) -> 0 | JZ15: =MIN(GH15:GJ15) -> 0 | KA15: =MIN(GK15:GM15) -> 0 | KB15: =MIN(GN15:GP15) -> 0 | KC15: =MIN(GQ15:GS15) -> 0 | KD15: =MIN(GT15:GV15) -> 0 | KE15: =MIN(GW15:GY15) -> 0 | KF15: =MIN(GZ15:HB15) -> 0 | KG15: =MIN(HC15:HE15) -> 0 | KH15: =MIN(HF15:HH15) -> 0
A16: Close | B16: BMONTH_CLOSE | C16: {=_xll.EQNXTDZ($A$1,$B16,C$1)} -> 0 | D16: {=_xll.EQNXTDZ($A$1,$B16,D$1)} -> 0 | E16: {=_xll.EQNXTDZ($A$1,$B16,E$1)} -> 0 | F16: {=_xll.EQNXTDZ($A$1,$B16,F$1)} -> 0 | G16: {=_xll.EQNXTDZ($A$1,$B16,G$1)} -> 0 | H16: {=_xll.EQNXTDZ($A$1,$B16,H$1)} -> 0 | I16: {=_xll.EQNXTDZ($A$1,$B16,I$1)} -> 0 | J16: {=_xll.EQNXTDZ($A$1,$B16,J$1)} -> 0 | ... HH16: {=_xll.EQNXTDZ($A$1,$B16,HH$1)} -> 0 | HP16: =+F16 -> 0 | HQ16: =+I16 -> 0 | HR16: =+L16 -> 0 | HS16: =+O16 -> 0 | HT16: =+R16 -> 0 | HU16: =+U16 -> 0 | HV16: =+X16 -> 0 | HW16: =+AA16 -> 0 | HX16: =+AD16 -> 0 | HY16: =+AG16 -> 0 | HZ16: =+AJ16 -> 0 | IA16: =+AM16 -> 0 | IB16: =+AP16 -> 0 | IC16: =+AS16 -> 0 | ID16: =+AV16 -> 0 | IE16: =+AY16 -> 0 | IF16: =+BB16 -> 0 | IG16: =+BE16 -> 0 | IH16: =+BH16 -> 0 | II16: =+BK16 -> 0 | IJ16: =+BN16 -> 0 | IK16: =+BQ16 -> 0 | IL16: =+BT16 -> 0 | IM16: =+BW16 -> 0 | IN16: =+BZ16 -> 292.45 | IO16: =+CC16 -> 383.15 | IP16: =+CF16 -> 501.1 | IQ16: =+CI16 -> 519.4 | IR16: =+CL16 -> 657.55 | IS16: =+CO16 -> 767.15 | IT16: =+CR16 -> 338.35 | IU16: =+CU16 -> 520.9 | IV16: =+CX16 -> 743.8 | IW16: =+DA16 -> 756.65 | IX16: =+DD16 -> 670.45 | IY16: =+DG16 -> 749.75 | IZ16: =+DJ16 -> 635.9 | JA16: =+DM16 -> 598.2 | JB16: =+DP16 -> 849.05 | JC16: =+DS16 -> 1016.35 | JD16: =+DV16 -> 995.45 | JE16: =+DY16 -> 914 | JF16: =+EB16 -> 915.1 | JG16: =+EE16 -> 1248.55 | JH16: =+EH16 -> 1316.9 | JI16: =+EK16 -> 1597.55 | JJ16: =+EN16 -> 1439.7 | JK16: =EQ16 -> 1322.35 | JL16: =ET16 -> 1197.1 | JM16: =EW16 -> 887.35 | JN16: =EZ16 -> 952.55 | JO16: =FC16 -> 1210.55 | JP16: =FF16 -> 1354.3 | JQ16: =FI16 -> 1273.85 | JR16: =FL16 -> 1155.35 | JS16: =FO16 -> 1407.3 | JT16: =FR16 -> 0 | JU16: =FU16 -> 0 | JV16: =FX16 -> 0 | JW16: =GA16 -> 0 | JX16: =GD16 -> 0 | JY16: =GG16 -> 0 | JZ16: =GJ16 -> 0 | KA16: =GM16 -> 0 | KB16: =GP16 -> 0 | KC16: =GS16 -> 0 | KD16: =GV16 -> 0 | KE16: =GY16 -> 0 | KF16: =HB16 -> 0 | KG16: =HE16 -> 0 | KH16: =HH16 -> 0
A19: High | HP19: =+IF(HP14=0,HP7,HP14) -> 0 | HQ19: =+IF(HQ14=0,HQ7,HQ14) -> 0 | HR19: =+IF(HR14=0,HR7,HR14) -> 0 | HS19: =+IF(HS14=0,HS7,HS14) -> 0 | HT19: =+IF(HT14=0,HT7,HT14) -> 0 | HU19: =+IF(HU14=0,HU7,HU14) -> 0 | HV19: =+IF(HV14=0,HV7,HV14) -> 0 | HW19: =+IF(HW14=0,HW7,HW14) -> 0 | ... KH19: =+IF(KH14=0,KH7,KH14) -> 0
A20: Low | HP20: =+IF(HP15=0,HP8,HP15) -> 0 | HQ20: =+IF(HQ15=0,HQ8,HQ15) -> 0 | HR20: =+IF(HR15=0,HR8,HR15) -> 0 | HS20: =+IF(HS15=0,HS8,HS15) -> 0 | HT20: =+IF(HT15=0,HT8,HT15) -> 0 | HU20: =+IF(HU15=0,HU8,HU15) -> 0 | HV20: =+IF(HV15=0,HV8,HV15) -> 0 | HW20: =+IF(HW15=0,HW8,HW15) -> 0 | ... KH20: =+IF(KH15=0,KH8,KH15) -> 0
A21: Close | HP21: =+IF(HP16=0,HP9,HP16) -> 0 | HQ21: =+IF(HQ16=0,HQ9,HQ16) -> 0 | HR21: =+IF(HR16=0,HR9,HR16) -> 0 | HS21: =+IF(HS16=0,HS9,HS16) -> 0 | HT21: =+IF(HT16=0,HT9,HT16) -> 0 | HU21: =+IF(HU16=0,HU9,HU16) -> 0 | HV21: =+IF(HV16=0,HV9,HV16) -> 0 | HW21: =+IF(HW16=0,HW9,HW16) -> 0 | ... KH21: =+IF(KH16=0,KH9,KH16) -> 0

Sheet 4_Axis Bank Ltd._Balance Sheet
A1: 132215
A3: =_xll.EQNXTV("Company-Profit And Loss",A1,"Crores/INR/40/Asc/N2",C3,D3,E3,F3,G3,H3) -> EQNXTV | C3: Standalone | D3: Abridged | E3: Actual | F3: 202503 | G3: Reported | H3: Gross Sales
A5: Profit And Loss - Standalone | C5: Axis Bank Ltd. | E5: INR Crores
A6: DESCRIPTION | B6: 34759 | C6: 35490 | D6: 35855 | E6: 36220 | F6: 36586 | G6: 36951 | H6: 37316 | I6: 37681 | J6: 38047 | K6: 38412 | L6: 38777 | M6: 39142 | N6: 39508 | O6: 39873 | P6: 40238 | Q6: 40603 | R6: 40969 | S6: 41334 | T6: 41699 | U6: 42064 | V6: 42430 | W6: 42795 | X6: 43160 | Y6: 43525 | Z6: 43891 | AA6: 44256 | AB6: 44621 | AC6: 44986 | AD6: 45352 | AE6: 45717
A8: No of Months | B8: 12 | C8: 12 | D8: 12 | E8: 12 | F8: 12 | G8: 12 | H8: 12 | I8: 12 | J8: 12 | K8: 12 | L8: 12 | M8: 12 | N8: 12 | O8: 12 | P8: 12 | Q8: 12 | R8: 12 | S8: 12 | T8: 12 | U8: 12 | V8: 12 | W8: 12 | X8: 12 | Y8: 12 | Z8: 12 | AA8: 12 | AB8: 12 | AC8: 12 | AD8: 12 | AE8: 12
A9: I. INCOME
A10: Interest Earned | B10: 29.1719 | C10: 157.6474 | D10: 255.61 | E10: 373.281 | F10: 483.2599 | G10: 889.6314 | H10: 1178.53 | I10: 1464.81 | J10: 1598.543 | K10: 1924.1582 | L10: 2888.7904 | M10: 4461.6552 | N10: 7005.3151 | O10: 10835.486 | P10: 11638.022 | Q10: 15154.806 | R10: 21994.647 | S10: 27182.574 | T10: 30641.155 | U10: 35478.598 | V10: 40988.036 | W10: 44542.158 | X10: 45780.312 | Y10: 54985.771 | Z10: 62635.157 | AA10: 63346.232 | AB10: 67376.83 | AC10: 85163.766 | AD10: 109368.63 | AE10: 122677.04
A11: Other Income | B11: 1.8346 | C11: 24.1029 | D11: 60.8991 | E11: 46.6287 | F11: 91.1659 | G11: 163.0001 | H11: 415.87 | I11: 410.47 | J11: 540.1456 | K11: 415.8196 | L11: 729.6344 | M11: 1010.1113 | N11: 1795.4888 | O11: 2896.8781 | P11: 3945.7819 | Q11: 4632.1338 | R11: 5420.2163 | S11: 6551.1063 | T11: 7405.2247 | U11: 8365.0458 | V11: 9371.4644 | W11: 11691.311 | X11: 10967.086 | Y11: 13130.339 | Z11: 15536.561 | AA11: 12263.599 | AB11: 15220.545 | AC11: 16143.419 | AD11: 22441.955 | AE11: 25257.056
A12: Total Income | B12: 31.0065 | C12: 181.7503 | D12: 316.5091 | E12: 419.9097 | F12: 574.4258 | G12: 1052.6315 | H12: 1594.4 | I12: 1875.28 | J12: 2138.6886 | K12: 2339.9778 | L12: 3618.4248 | M12: 5471.7665 | N12: 8800.8039 | O12: 13732.364 | P12: 15583.803 | Q12: 19786.94 | R12: 27414.864 | S12: 33733.681 | T12: 38046.38 | U12: 43843.643 | V12: 50359.501 | W12: 56233.469 | X12: 56747.399 | Y12: 68116.11 | Z12: 78171.718 | AA12: 75609.831 | AB12: 82597.375 | AC12: 101307.19 | AD12: 131810.59 | AE12: 147934.1
A13: II. EXPENDITURE
A14: Interest Expended | B14: 14.0985 | C14: 122.0736 | D14: 222.1898 | E14: 300.6328 | F14: 392.8564 | G14: 791.3638 | H14: 980 | I14: 1142.41 | J14: 1021.4487 | K14: 1192.9808 | L14: 1810.556 | M14: 2993.3172 | N14: 4419.9617 | O14: 7149.2742 | P14: 6633.5261 | Q14: 8591.823 | R14: 13976.902 | S14: 17516.311 | T14: 18689.522 | U14: 21254.46 | V14: 24155.068 | W14: 26449.042 | X14: 27162.582 | Y14: 33277.597 | Z14: 37428.954 | AA14: 34107.11 | AB14: 34244.613 | AC14: 42218.021 | AD14: 59474.146 | AE14: 68329.221
A15: Operating Expenses | B15: 7.8485 | C15: 26.6971 | D15: 39.7558 | E15: 51.0262 | F15: 65.4009 | G15: 128.7637 | H15: 207.12 | I15: 322.85 | J15: 419.2055 | K15: 581.3789 | L15: 814.0507 | M15: 1214.5984 | N15: 2154.9269 | O15: 2858.2127 | P15: 3709.7223 | Q15: 4779.4281 | R15: 6007.0995 | S15: 6914.2375 | T15: 7900.7739 | U15: 9203.7456 | V15: 10100.819 | W15: 12199.905 | X15: 13990.34 | Y15: 15833.408 | Z15: 17304.624 | AA15: 18375.149 | AB15: 23610.754 | AC15: 39298.538 | AD15: 35213.284 | AE15: 37499.943
A16: Provisions and Contingencies | B16: 3.077 | C16: 17.7587 | D16: 25.2068 | E16: 21.9707 | F16: 37.4932 | G16: 28.0513 | H16: 193.91 | I16: 108.73 | J16: 268.6724 | K16: 51.0104 | L16: 262.3844 | M16: 267.3626 | N16: 579.4163 | O16: 939.3984 | P16: 1388.8417 | Q16: 1279.2779 | R16: 1142.6664 | S16: 1750.0592 | T16: 2107.0376 | U16: 2327.6761 | V16: 3709.9119 | W16: 12116.962 | X16: 15472.906 | Y16: 12031.017 | Z16: 18533.915 | AA16: 14321.721 | AB16: 7359.4491 | AC16: 2884.7777 | AD16: 4063.0948 | AE16: 7758.3504
A17: Profit Before Tax | B17: 5.9825 | C17: 15.2209 | D17: 29.3567 | E17: 46.28 | F17: 78.6753 | G17: 104.4527 | H17: 213.37 | I17: 301.29 | J17: 429.362 | K17: 514.6077 | L17: 731.4337 | M17: 996.4883 | N17: 1646.499 | O17: 2785.4784 | P17: 3851.7133 | Q17: 5136.4106 | R17: 6288.1954 | S17: 7553.0729 | T17: 9349.0466 | U17: 11057.762 | V17: 12393.703 | W17: 5467.5592 | X17: 121.5713 | Y17: 6974.0883 | Z17: 4904.2254 | AA17: 8805.8506 | AB17: 17382.558 | AC17: 16905.849 | AD17: 33060.063 | AE17: 34346.582
A18: Taxes | B18: 3.6733 | C18: 0 | D18: 11.7398 | E18: 15.21 | F18: 27.75 | G18: 18.33 | H18: 79.23 | I18: 109.11 | J18: 151.05 | K18: 180.03 | L18: 246.35 | M18: 337.46 | N18: 575.47 | O18: 970.12 | P18: 1337.18 | Q18: 1747.92 | R18: 2045.99 | S18: 2373.64 | T18: 3131.38 | U18: 3699.94 | V18: 4170.04 | W18: 1788.28 | X18: -154.11 | Y18: 2297.48 | Z18: 3277.01 | AA18: 2217.35 | AB18: 4357.08 | AC18: 7326.17 | AD18: 8198.63 | AE18: 7973.1
A19: Total | B19: 28.6973 | C19: 166.5294 | D19: 298.8922 | E19: 388.8397 | F19: 523.5005 | G19: 966.5088 | H19: 1460.26 | I19: 1683.1 | J19: 1860.3766 | K19: 2005.4001 | L19: 3133.3411 | M19: 4812.7382 | N19: 7729.7749 | O19: 11917.005 | P19: 13069.27 | Q19: 16398.449 | R19: 23172.658 | S19: 28554.248 | T19: 31828.714 | U19: 36485.821 | V19: 42135.838 | W19: 52554.189 | X19: 56471.717 | Y19: 63439.502 | Z19: 76544.503 | AA19: 69021.33 | AB19: 69571.897 | AC19: 91727.507 | AD19: 106949.15 | AE19: 121560.61
A20: III. PROFIT AND LOSS
A21: Profit After Tax | B21: 2.3092 | C21: 15.2209 | D21: 17.6169 | E21: 31.07 | F21: 50.9253 | G21: 86.1227 | H21: 134.14 | I21: 192.18 | J21: 278.312 | K21: 334.5777 | L21: 485.0837 | M21: 659.0283 | N21: 1071.029 | O21: 1815.3584 | P21: 2514.5333 | Q21: 3388.4906 | R21: 4242.2054 | S21: 5179.4329 | T21: 6217.6666 | U21: 7357.8223 | V21: 8223.6628 | W21: 3679.2792 | X21: 275.6813 | Y21: 4676.6083 | Z21: 1627.2154 | AA21: 6588.5006 | AB21: 13025.478 | AC21: 9579.6785 | AD21: 24861.433 | AE21: 26373.482
A22: Extra items | C22: 0 | D22: -1.0307 | L22: 0 | M22: 0 | N22: 0 | O22: 0 | P22: 0 | R22: 0
A23: Profit brought forward | C23: 10.8176 | D23: 20.5338 | E23: 30.7108 | F23: 41.9893 | G23: 52.598 | H23: 74.37 | I23: 78.64 | J23: 122.4667 | K23: 182.1024 | L23: 197.4076 | M23: 731.039 | N23: 1029.074 | O23: 1553.8689 | P23: 2348.0865 | Q23: 3427.4337 | R23: 4969.7707 | S23: 7329.4476 | T23: 10029.262 | U23: 13501.446 | V23: 17623.491 | W23: 23766.456 | X23: 24448.327 | Y23: 23043.052 | Z23: 24322.995 | AA23: 26190.455 | AB23: 29985.281 | AC23: 38100.659 | AD23: 44144.93 | AE23: 60254.056
A24: Adjustments to PAT | C24: -0.2039 | D24: -0.5614 | E24: 0.0124 | F24: 0.1358 | G24: 0.0014 | H24: 2.39 | M24: -31.8028
A25: Total Profit & Loss | B25: 2.3092 | C25: 25.8346 | D25: 37.5893 | E25: 61.7932 | F25: 93.0504 | G25: 138.7221 | H25: 210.9 | I25: 270.82 | J25: 400.7787 | K25: 516.6801 | L25: 682.4913 | M25: 1358.2645 | N25: 2100.103 | O25: 3369.2273 | P25: 4862.6198 | Q25: 6815.9243 | R25: 9211.9761 | S25: 12508.88 | T25: 16246.929 | U25: 20859.268 | V25: 25847.154 | W25: 27445.735 | X25: 24724.009 | Y25: 27719.66 | Z25: 25950.211 | AA25: 32778.955 | AB25: 43010.759 | AC25: 47680.338 | AD25: 69006.363 | AE25: 86627.538
A26: IV. APPROPRIATIONS | B26: 2.3092 | C26: 25.8346 | D26: 36.5586 | E26: 61.7932 | F26: 93.0504 | G26: 138.7221 | H26: 210.9 | I26: 270.82 | J26: 400.7787 | K26: 516.6801 | L26: 682.4913 | M26: 1358.2645 | N26: 2100.103 | O26: 3369.2273 | P26: 4862.6198 | Q26: 6815.9243 | R26: 9211.9761 | S26: 12508.88 | T26: 16246.929 | U26: 20859.268 | V26: 25847.154 | W26: 27445.735 | X26: 24724.009 | Y26: 27719.66 | Z26: 25950.211 | AA26: 32778.955 | AB26: 43010.759 | AC26: 47680.338 | AD26: 69006.363 | AE26: 86627.538
A27: Equity Dividend % | E27: 10 | F27: 12 | G27: 15 | H27: 20 | I27: 22 | J27: 25 | K27: 28 | L27: 35 | M27: 45 | N27: 60 | O27: 100 | P27: 120 | Q27: 140 | R27: 160 | S27: 180 | T27: 200 | U27: 230 | V27: 250 | W27: 250 | Y27: 50 | AB27: 50 | AC27: 50 | AD27: 50 | AE27: 50
A28: Earnings Per Share(Calculated) | B28: 0.20079983 | C28: 1.3235554 | D28: 1.531903 | E28: 2.3555153 | F28: 3.8608085 | G28: 6.5292351 | H28: 6.9933789 | I28: 8.3487554 | J28: 12.017932 | K28: 12.219945 | L28: 17.4058 | M28: 23.4004 | N28: 29.9413 | O28: 50.5664 | P28: 62.0606 | Q28: 82.5362 | R28: 102.6662 | S28: 110.6824 | T28: 132.3345 | U28: 31.0388 | V28: 34.5121 | W28: 15.3621 | X28: 1.0741 | Y28: 18.1853 | Z28: 5.7668 | AA28: 21.5047 | AB28: 42.4318 | AC28: 31.134674 | AD28: 80.5471 | AE28: 85.148
A29: Adjusted EPS | B29: 0.040159965 | C29: 0.26471107 | D29: 0.3063806 | E29: 0.47110305 | F29: 0.77216171 | G29: 1.305847 | H29: 1.3986758 | I29: 1.6697511 | J29: 2.4035865 | K29: 2.443989 | L29: 3.4812 | M29: 4.6801 | N29: 5.9883 | O29: 10.1133 | P29: 12.4121 | Q29: 16.5072 | R29: 20.5332 | S29: 22.1365 | T29: 26.4669 | U29: 31.0388 | V29: 34.5121 | W29: 15.3621 | X29: 1.0741 | Y29: 18.1853 | Z29: 5.7668 | AA29: 21.5047 | AB29: 42.4318 | AC29: 31.1347 | AD29: 80.5471 | AE29: 85.148
A30: EPS - Basic (Reported) | E30: 2.36 | F30: 3.86 | G30: 6.53 | H30: 6.99 | I30: 8.35 | J30: 12.02 | K30: 12.22 | L30: 17.45 | M30: 23.5 | N30: 32.15 | O30: 50.61 | P30: 65.78 | Q30: 82.95 | R30: 102.94 | S30: 119.67 | T30: 26.51 | U30: 31.18 | V30: 34.59 | W30: 15.4 | X30: 1.13 | Y30: 18.2 | Z30: 5.99 | AA30: 22.15 | AB30: 42.48 | AC30: 31.17 | AD30: 80.67 | AE30: 85.28
A31: EPS - Diluted (Reported) | Q31: 81.61 | R31: 102.2 | U31: 30.85 | V31: 34.4 | X31: 1.12 | Y31: 18.09 | Z31: 5.97 | AA31: 22.09 | AB31: 42.35 | AC31: 31.02 | AD31: 80.1 | AE31: 84.77
