Workbook

Sheet Template
A1: =+'Annual Raw'!C4 -> Inox India Ltd. | B1: 36951 | C1: =EOMONTH(B1,12) -> 37346 | D1: =EOMONTH(C1,12) -> 37711 | E1: =EOMONTH(D1,12) -> 38077 | F1: =EOMONTH(E1,12) -> 38442 | G1: =EOMONTH(F1,12) -> 38807 | H1: =EOMONTH(G1,12) -> 39172 | I1: =EOMONTH(H1,12) -> 39538 | J1: =EOMONTH(I1,12) -> 39903 | ... AE1: =EOMONTH(AD1,12) -> 47573 | AH1: QTR | AI1: 41061 | AJ1: 41153 | AK1: 41244 | AL1: 41334 | AM1: 41426 | AN1: 41518 | AO1: 41609 | AP1: 41699 | AQ1: 41791 | AR1: 41883 | AS1: 41974 | AT1: 42064 | AU1: 42156 | AV1: 42248 | AW1: 42339 | AX1: 42430 | AY1: 42522 | AZ1: 42614 | BA1: 42705 | BB1: 42795 | BC1: 42887 | BD1: 42979 | BE1: 43070 | BF1: 43160 | BG1: 43252 | BH1: 43344 | BI1: 43435 | BJ1: 43525 | BK1: 43617 | BL1: 43709 | BM1: 43800 | BN1: 43891 | BO1: 43983 | BP1: 44075 | BQ1: =EOMONTH(BP1,3) -> 44196 | BR1: =EOMONTH(BQ1,3) -> 44286 | BS1: =EOMONTH(BR1,3) -> 44377 | BT1: =EOMONTH(BS1,3) -> 44469 | BU1: =EOMONTH(BT1,3) -> 44561 | BV1: =EOMONTH(BU1,3) -> 44651 | BW1: =EOMONTH(BV1,3) -> 44742 | BX1: =EOMONTH(BW1,3) -> 44834 | ... DB1: =EOMONTH(DA1,3) -> 47573 | DE1: HISTORICAL ESTIMATES | DF1: 46112
A2: Presentation Data (Start)
Z3: =+Z5/Y5-1 -> 0.11957211
A4: Sales Break up
A5: Industrial Gas | W5: 620 | X5: 685 | Y5: =(Y$41+Y$66)*63% -> 733.73152 | Z5: =(Z$41+Z$66)*61% -> 821.46534 | CC5: 214 | CD5: 162 | CE5: 188 | CF5: 188 | CG5: 231 | CH5: 225 | CI5: 165 | CJ5: 212 | CK5: 261 | CL5: 237 | CM5: =+CI5*(1+CM12) -> 186.45 | CN5: =+CJ5*(1+CN12) -> 239.56 | CO5: =+CK5*(1+CO12) -> 294.93 | CP5: =+CL5*(1+CP12) -> 267.81 | CQ5: =+CM5*(1+CQ12) -> 210.6885 | CR5: =+CN5*(1+CR12) -> 270.7028 | CS5: =+CO5*(1+CS12) -> 333.2709 | CT5: =+CP5*(1+CT12) -> 302.6253 | ... DB5: =+CX5*(1+DB12) -> 386.42225 | DF5: 254.25
A6: LNG | W6: 126 | X6: 240 | Y6: =(Y$41+Y$66)*28% -> 326.1029 | Z6: =(Z$41+Z$66)*17% -> 228.93296 | CC6: 73 | CD6: 74 | CE6: 46 | CF6: 62 | CG6: 50 | CH6: 74 | CI6: 102 | CJ6: 93 | CK6: 107 | CL6: 155
A7: Cryo Scientific | W7: 36 | X7: 41 | Y7: =(Y$41+Y$66)*7% -> 81.525724 | Z7: =(Z$41+Z$66)*17% -> 228.93296 | CC7: 6 | CD7: 42 | CE7: 63 | CF7: 57 | CG7: 45 | CH7: 63 | CI7: 67 | CJ7: 49 | CK7: 55 | CL7: 56
A8: Others | W8: 21 | X8: 20 | Y8: =(Y$41+Y$66)*2% -> 23.293064 | Z8: =(Z$41+Z$66)*5% -> 67.333225 | CC8: 6 | CD8: 10 | CE8: 5 | CF8: 13 | CG8: 16 | CH8: 21 | CI8: 18 | CJ8: 15 | CK8: 13 | CL8: 27
A9: Total | W9: =SUM(W5:W8) -> 803 | X9: =SUM(X5:X8) -> 986 | Y9: =SUM(Y5:Y8) -> 1164.6532 | Z9: =SUM(Z5:Z8) -> 1346.6645 | CC9: =SUM(CC5:CC8) -> 299 | CD9: =SUM(CD5:CD8) -> 288 | CE9: =SUM(CE5:CE8) -> 302 | CF9: =SUM(CF5:CF8) -> 320 | CG9: =SUM(CG5:CG8) -> 342 | CH9: =SUM(CH5:CH8) -> 383 | CI9: =SUM(CI5:CI8) -> 352 | CJ9: =SUM(CJ5:CJ8) -> 369 | ... CL9: =SUM(CL5:CL8) -> 475
A10: check sum | W10: =W39+W66-W9 -> 0.713 | X10: =X39+X66-X9 -> 0.0816 | Y10: =Y39+Y66-Y9 -> 0 | Z10: =Z39+Z66-Z9 -> 0 | CC10: =CC39+CC66-CC9 -> -3.575 | CD10: =CD39+CD66-CD9 -> -0.3 | CE10: =CE39+CE66-CE9 -> -0.221 | CF10: =CF39+CF66-CF9 -> 0.003 | CG10: =CG39+CG66-CG9 -> 0.348 | CH10: =CH39+CH66-CH9 -> -0.465 | CI10: =CI39+CI66-CI9 -> 0.293 | CJ10: =CJ39+CJ66-CJ9 -> 0.073 | ... CL10: =CL39+CL66-CL9 -> 0.243
X12: =X5/W5-1 -> 0.10483871 | Y12: =Y5/X5-1 -> 0.071140899 | Z12: =Z5/Y5-1 -> 0.11957211 | CG12: =+CG5/CC5-1 -> 0.079439252 | CH12: =+CH5/CD5-1 -> 0.38888889 | CI12: =+CI5/CE5-1 -> -0.12234043 | CJ12: =+CJ5/CF5-1 -> 0.12765957 | CK12: =+CK5/CG5-1 -> 0.12987013 | CL12: =+CL5/CH5-1 -> 0.053333333 | CM12: 0.13 | CN12: 0.13 | CO12: 0.13 | CP12: 0.13 | CQ12: 0.13 | CR12: 0.13 | CS12: 0.13 | CT12: 0.13 | CU12: 0.13 | CV12: 0.13 | CW12: 0.13 | CX12: 0.13 | CY12: 0.13 | CZ12: 0.13 | DA12: 0.13 | DB12: 0.13 | DF12: 0.13
X13: =X6/W6-1 -> 0.9047619 | Y13: =Y6/X6-1 -> 0.35876207 | Z13: =Z6/Y6-1 -> -0.29797322 | CG13: =+CG6/CC6-1 -> -0.31506849 | CH13: =+CH6/CD6-1 -> 0 | CI13: =+CI6/CE6-1 -> 1.2173913 | CJ13: =+CJ6/CF6-1 -> 0.5 | CK13: =+CK6/CG6-1 -> 1.14 | CL13: =+CL6/CH6-1 -> 1.0945946
X14: =X7/W7-1 -> 0.13888889 | Y14: =Y7/X7-1 -> 0.98843229 | Z14: =Z7/Y7-1 -> 1.8081071 | CG14: =+CG7/CC7-1 -> 6.5 | CH14: =+CH7/CD7-1 -> 0.5 | CI14: =+CI7/CE7-1 -> 0.063492063 | CJ14: =+CJ7/CF7-1 -> -0.14035088 | CK14: =+CK7/CG7-1 -> 0.22222222 | CL14: =+CL7/CH7-1 -> -0.11111111
A16: Exports Crs | Y16: =Y39*Y17 -> 623.33783 | Z16: =SUM(CE16:CH16) -> 705.48 | CC16: 149.5 | CD16: 141.12 | CE16: 163.08 | CF16: 166.4 | CG16: 171 | CH16: 205 | CI16: 198 | CJ16: 211 | CK16: 271 | CL16: 291
A17: exports as % of sales | Y17: 0.55 | Z17: =Z16/Z39 -> 0.54018476 | CC17: =CC16/CC39 -> 0.5142865 | CD17: =CD16/CD39 -> 0.51036683 | CE17: =CE16/CE39 -> 0.55018387 | CF17: =CF16/CF39 -> 0.54279218 | CG17: =CG16/CG39 -> 0.51254844 | CH17: =CH16/CH39 -> 0.55495698 | CI17: =CI16/CI39 -> 0.58299767 | CJ17: =CJ16/CJ39 -> 0.58901693 | ... CL17: =CL16/CL39 -> 0.63171057
A19: OB break up
A20: Industrial Gas | W20: 509 | X20: 502 | Y20: 593 | Z20: =+CH20 -> 631 | CC20: 520 | CD20: 593 | CE20: 557 | CF20: 637 | CG20: 596 | CH20: 631 | CI20: 648 | CJ20: 674 | CK20: 630 | CL20: 738
A21: LNG | W21: 190 | X21: 358 | Y21: 222 | Z21: =+CH21 -> 486 | CC21: 241 | CD21: 222 | CE21: 254 | CF21: 291 | CG21: 485 | CH21: 486 | CI21: 469 | CJ21: 454 | CK21: 446 | CL21: 422
A22: Cryo Scientific | W22: 159 | X22: 143 | Y22: 272 | Z22: =+CH22 -> 234 | CC22: 282 | CD22: 272 | CE22: 294 | CF22: 250 | CG22: =CG24-CG21-CG20 -> 260 | CH22: 234 | CI22: 334 | CJ22: 340 | CK22: 362 | CL22: 329
A23: others | CH23: 5 | CI23: 6 | CJ23: 17 | CK23: 19 | CL23: 25
A24: Total OB - crs | V24: 620 | W24: 858 | X24: 1003 | Y24: 1087 | Z24: 1356 | CB24: 1037 | CC24: 1043 | CD24: =Y24 -> 1087 | CE24: 1105 | CF24: 1178 | CG24: 1341 | CH24: =SUM(CH20:CH23) -> 1356 | CI24: =SUM(CI20:CI23) -> 1457 | CJ24: =SUM(CJ20:CJ23) -> 1485 | CK24: =SUM(CK20:CK23) -> 1457 | CL24: =SUM(CL20:CL23) -> 1514
A26: OP | W26: =V24 -> 620 | X26: =W29 -> 858 | Y26: =X29 -> 1003 | Z26: =Y29 -> 1087 | AA26: =Z29 -> 1356 | AB26: =AA29 -> 1514 | AC26: =AB29 -> 2015.5256 | AD26: =AC29 -> 2614.5712 | AE26: =AD29 -> 3284.9314 | CB26: =CA24 -> 0 | CC26: =CB24 -> 1037 | CD26: =CC24 -> 1043 | CE26: =CD24 -> 1087 | CF26: =CE24 -> 1105 | CG26: =CF24 -> 1178 | CH26: =CG24 -> 1341 | CI26: =CH24 -> 1356 | ... CK26: =CJ24 -> 1485 | CL26: =+CK29 -> 1457 | CM26: =+CL29 -> 1514 | CN26: =+CM29 -> 1699.3502 | CO26: =+CN29 -> 1760.6777 | CP26: =+CO29 -> 1825.2747 | CQ26: =+CP29 -> 2015.5256 | CR26: =+CQ29 -> 2246.9179 | CS26: =+CR29 -> 2312.438 | ... DB26: =+DA29 -> 3658.5795 | DF26: 1457
A27: Additions | W27: =W29+W28-W26 -> 1020.711 | X27: =X29+X28-X26 -> 1110.9003 | Y27: =Y29+Y28-Y26 -> 1217.3415 | Z27: =Z29+Z28-Z26 -> 1574.9976 | AA27: =AA29+AA28-AA26 -> 1745.0629 | AB27: =AB29+AB28-AB26 -> 2333.8586 | AC27: =AC29+AC28-AC26 -> 2915.6112 | AD27: =AD29+AD28-AD26 -> 3427.3299 | AE27: =AE29+AE28-AE26 -> 3986.0479 | CB27: =CB29+CB28-CB26 -> 1294.65 | CC27: =CC29+CC28-CC26 -> 296.694 | CD27: =CD29+CD28-CD26 -> 320.507 | CE27: =CE29+CE28-CE26 -> 314.41 | CF27: =CF29+CF28-CF26 -> 379.563 | CG27: =CG29+CG28-CG26 -> 496.627 | CH27: =CH29+CH28-CH26 -> 384.398 | CI27: =CI29+CI28-CI26 -> 440.624 | ... CL27: =CL29+CL28-CL26 -> 517.654 | CM27: =+CI27*(1+CM32) -> 593.37139 | CN27: =+CJ27*(1+CN32) -> 520.113 | CO27: =+CK27*(1+CO32) -> 539.42009 | CP27: =+CL27*(1+CP32) -> 680.95416 | CQ27: =+CM27*(1+CQ32) -> 763.71076 | CR27: =+CN27*(1+CR32) -> 655.98425 | CS27: =+CO27*(1+CS32) -> 667.65266 | CT27: =+CP27*(1+CT32) -> 828.26358 | ... DB27: =+CX27*(1+DB32) -> 1120.3192 | DF27: 480.4975
A28: Executions | W28: =W39 -> 782.711 | X28: =X39 -> 965.9003 | Y28: =Y39 -> 1133.3415 | Z28: =Z39 -> 1305.9976 | AA28: =AA39 -> 1587.0629 | AB28: =AB39 -> 1832.3331 | AC28: =AC39 -> 2316.5656 | AD28: =AD39 -> 2756.9697 | AE28: =AE39 -> 3366.0586 | CB28: =CB39 -> 257.65 | CC28: =CC39 -> 290.694 | CD28: =CD39 -> 276.507 | CE28: =CE39 -> 296.41 | CF28: =CF39 -> 306.563 | CG28: =CG39 -> 333.627 | CH28: =CH39 -> 369.398 | CI28: =CI39 -> 339.624 | ... CL28: =CL39 -> 460.654 | CM28: =+CM26*CM33 -> 408.02123 | CN28: =+CN26*CN33 -> 458.78547 | CO28: =+CO26*CO33 -> 474.82308 | CP28: =+CP26*CP33 -> 490.70328 | CQ28: =+CQ26*CQ33 -> 532.31843 | CR28: =+CR26*CR33 -> 590.46415 | CS28: =+CS26*CS33 -> 603.60943 | CT28: =+CT26*CT33 -> 590.17359 | ... DB28: =+DB26*DB33 -> 873.97802 | DF28: 422.53
A29: Closing | V29: =V24 -> 620 | W29: =W24 -> 858 | X29: =X24 -> 1003 | Y29: =Y24 -> 1087 | Z29: =Z24 -> 1356 | AA29: =CL29 -> 1514 | AB29: =CP29 -> 2015.5256 | AC29: =CT29 -> 2614.5712 | AD29: =CX29 -> 3284.9314 | AE29: =DB29 -> 3904.9207 | CB29: =CB24 -> 1037 | CC29: =CC24 -> 1043 | CD29: =CD24 -> 1087 | CE29: =CE24 -> 1105 | CF29: =CF24 -> 1178 | CG29: =CG24 -> 1341 | CH29: =CH24 -> 1356 | CI29: =CI24 -> 1457 | ... CL29: =CL24 -> 1514 | CM29: =+CM26+CM27-CM28 -> 1699.3502 | CN29: =+CN26+CN27-CN28 -> 1760.6777 | CO29: =+CO26+CO27-CO28 -> 1825.2747 | CP29: =+CP26+CP27-CP28 -> 2015.5256 | CQ29: =+CQ26+CQ27-CQ28 -> 2246.9179 | CR29: =+CR26+CR27-CR28 -> 2312.438 | CS29: =+CS26+CS27-CS28 -> 2376.4812 | CT29: =+CT26+CT27-CT28 -> 2614.5712 | ... DB29: =+DB26+DB27-DB28 -> 3904.9207 | DF29: 1514.9675
A31: OB Growth | W31: =W29/V29-1 -> 0.38387097 | X31: =X29/W29-1 -> 0.16899767 | Y31: =Y29/X29-1 -> 0.083748754 | Z31: =Z29/Y29-1 -> 0.2474701 | AA31: =AA29/Z29-1 -> 0.11651917 | AB31: =AB29/AA29-1 -> 0.33125864 | AC31: =AC29/AB29-1 -> 0.2972156 | AD31: =AD29/AC29-1 -> 0.25639392 | AE31: =AE29/AD29-1 -> 0.18873737 | CF31: =CF29/CB29-1 -> 0.13596914 | CG31: =CG29/CC29-1 -> 0.28571429 | CH31: =CH29/CD29-1 -> 0.2474701 | CI31: =CI29/CE29-1 -> 0.31855204 | CJ31: =CJ29/CF29-1 -> 0.26061121 | CK31: =CK29/CG29-1 -> 0.08650261 | CL31: =CL29/CH29-1 -> 0.11651917 | CM31: =CM29/CI29-1 -> 0.16633505 | ... DB31: =DB29/CX29-1 -> 0.18873737 | DF31: 0.11723267
A32: Addition Growth | X32: =+X27/W27-1 -> 0.088359291 | Y32: =+Y27/X27-1 -> 0.095815259 | Z32: =+Z27/Y27-1 -> 0.29380096 | AA32: =+AA27/Z27-1 -> 0.10797813 | AB32: =+AB27/AA27-1 -> 0.33740661 | AC32: =+AC27/AB27-1 -> 0.24926642 | AD32: =+AD27/AC27-1 -> 0.1755099 | AE32: =+AE27/AD27-1 -> 0.16301846 | CF32: =+CF27/CB27-1 -> -0.70682192 | CG32: =+CG27/CC27-1 -> 0.67386937 | CH32: =+CH27/CD27-1 -> 0.19934354 | CI32: =+CI27/CE27-1 -> 0.40143125 | CJ32: =+CJ27/CF27-1 -> 0.017549129 | CK32: =+CK27/CG27-1 -> -0.19343693 | CL32: =+CL27/CH27-1 -> 0.34666153 | CM32: =+CL32 -> 0.34666153 | CN32: =+CM32 -> 0.34666153 | CO32: =+CN32 -> 0.34666153 | CP32: =+CO32*0.91 -> 0.315462 | CQ32: =+CP32*0.91 -> 0.28707042 | CR32: =+CQ32*0.91 -> 0.26123408 | CS32: =+CR32*0.91 -> 0.23772301 | CT32: =+CS32*0.91 -> 0.21632794 | CU32: =+CT32*0.91 -> 0.19685843 | CV32: =+CU32*0.91 -> 0.17914117 | CW32: =+CV32*0.91 -> 0.16301846 | CX32: =+CW32 -> 0.16301846 | CY32: =+CX32 -> 0.16301846 | CZ32: =+CY32 -> 0.16301846 | DA32: =+CZ32 -> 0.16301846 | DB32: =+DA32 -> 0.16301846 | DF32: 0.25
A33: Execution % | X33: =+X39/X26 -> 1.1257579 | Y33: =+Y39/Y26 -> 1.1299516 | Z33: =+Z39/Z26 -> 1.2014697 | AA33: =+AA39/AA26 -> 1.1704004 | AB33: =+AB39/AB26 -> 1.2102596 | AC33: =+AC39/AC26 -> 1.1493606 | AD33: =+AD39/AD26 -> 1.0544634 | AE33: =+AE39/AE26 -> 1.0246968 | CC33: =CC28/CB24 -> 0.28032208 | CD33: =CD28/CC24 -> 0.26510738 | CE33: =CE28/CD24 -> 0.27268629 | CF33: =CF28/CE24 -> 0.27743258 | CG33: =CG28/CF24 -> 0.28321477 | CH33: =CH28/CG24 -> 0.27546458 | CI33: =CI28/CH24 -> 0.25046018 | CJ33: =CJ28/CI24 -> 0.2458641 | ... CL33: =CL28/CK24 -> 0.31616609 | CM33: =AVERAGE(CD33:CL33)*0.98 -> 0.26949883 | CN33: =AVERAGE(CE33:CM33)*0.98 -> 0.26997701 | CO33: =AVERAGE(CF33:CN33)*0.98 -> 0.269682 | CP33: =AVERAGE(CG33:CO33)*0.98 -> 0.26883805 | CQ33: =AVERAGE(CM33:CP33)*0.98 -> 0.26410899 | CR33: =AVERAGE(CN33:CQ33)*0.98 -> 0.26278848 | CS33: =AVERAGE(CO33:CR33)*0.98 -> 0.26102729 | CT33: =AVERAGE(CP33:CS33)*0.94 -> 0.24833926 | CU33: =AVERAGE(CQ33:CT33)*0.94 -> 0.24352205 | CV33: =AVERAGE(CR33:CU33)*0.94 -> 0.23868411 | CW33: =AVERAGE(CS33:CV33)*0.94 -> 0.23301959 | CX33: =AVERAGE(CT33:CW33) -> 0.24089125 | CY33: =AVERAGE(CU33:CX33) -> 0.23902925 | CZ33: =AVERAGE(CV33:CY33) -> 0.23790605 | DA33: =AVERAGE(CW33:CZ33) -> 0.23771153 | DB33: =AVERAGE(CX33:DA33) -> 0.23888452 | DF33: 0.29
T35: =T51/T39 -> 0.18735677 | U35: =U51/U39 -> 0.15421549 | V35: =V51/V39 -> 0.13845275 | W35: =W51/W39 -> 0.1531817 | X35: =X51/X39 -> 0.14057848 | Y35: =Y51/Y39 -> 0.123042 | Z35: =Z51/Z39 -> 0.14336481
A37: Presentation Data (End)
A38: Profit & Loss- Annual (Start)
A39: Gross Revenue | B39: ='Annual Raw'!C6 -> 35.032452 | C39: ='Annual Raw'!D6 -> 51.527453 | D39: ='Annual Raw'!E6 -> 48.232658 | E39: ='Annual Raw'!F6 -> 51.989955 | F39: ='Annual Raw'!G6 -> 54.900097 | G39: ='Annual Raw'!H6 -> 87.1955 | H39: ='Annual Raw'!I6 -> 137.65676 | I39: ='Annual Raw'!J6 -> 205.30286 | ... AA39: ='Annual Raw'!AB6 -> 1587.0629 | AB39: =+SUM(CM39:CP39) -> 1832.3331 | AC39: =+SUM(CQ39:CT39) -> 2316.5656 | AD39: =+SUM(CU39:CX39) -> 2756.9697 | AE39: =+SUM(CY39:DB39) -> 3366.0586 | AF39: =2100/AA39-1 -> 0.32319897 | AI39: ='QTR Raw'!C6+'QTR Raw'!C8 -> 0 | AJ39: ='QTR Raw'!D6+'QTR Raw'!D8 -> 0 | AK39: ='QTR Raw'!E6+'QTR Raw'!E8 -> 0 | AL39: ='QTR Raw'!F6+'QTR Raw'!F8 -> 0 | AM39: ='QTR Raw'!G6+'QTR Raw'!G8 -> 0 | AN39: ='QTR Raw'!H6+'QTR Raw'!H8 -> 0 | AO39: ='QTR Raw'!I6+'QTR Raw'!I8 -> 0 | AP39: ='QTR Raw'!J6+'QTR Raw'!J8 -> 0 | ... CL39: ='QTR Raw'!BF6+'QTR Raw'!BF8 -> 460.654 | CM39: =+CM28 -> 408.02123 | CN39: =+CN28 -> 458.78547 | CO39: =+CO28 -> 474.82308 | CP39: =+CP28 -> 490.70328 | CQ39: =+CQ28 -> 532.31843 | CR39: =+CR28 -> 590.46415 | CS39: =+CS28 -> 603.60943 | CT39: =+CT28 -> 590.17359 | ... DB39: =+DB28 -> 873.97802 | DF39: 422.53
A40: Less: Exise Duty | B40: ='Annual Raw'!C7+'Annual Raw'!C8+'Annual Raw'!C9 -> 3.2351323 | C40: ='Annual Raw'!D7+'Annual Raw'!D8+'Annual Raw'!D9 -> 2.5807622 | D40: ='Annual Raw'!E7+'Annual Raw'!E8+'Annual Raw'!E9 -> 1.7177281 | E40: ='Annual Raw'!F7+'Annual Raw'!F8+'Annual Raw'!F9 -> 2.7170725 | F40: ='Annual Raw'!G7+'Annual Raw'!G8+'Annual Raw'!G9 -> 3.4063634 | G40: ='Annual Raw'!H7+'Annual Raw'!H8+'Annual Raw'!H9 -> 5.3058515 | H40: ='Annual Raw'!I7+'Annual Raw'!I8+'Annual Raw'!I9 -> 7.3428139 | I40: ='Annual Raw'!J7+'Annual Raw'!J8+'Annual Raw'!J9 -> 11.593145 | ... AA40: ='Annual Raw'!AB7+'Annual Raw'!AB8+'Annual Raw'!AB9 -> 0 | AB40: =+SUM(CM40:CP40) -> 0 | AC40: =+SUM(CQ40:CT40) -> 0 | AD40: =+SUM(CU40:CX40) -> 0 | AE40: =+SUM(CY40:DB40) -> 0 | AI40: =+'QTR Raw'!C20+'QTR Raw'!C19+'QTR Raw'!C13+'QTR Raw'!C7 -> 0 | AJ40: =+'QTR Raw'!D20+'QTR Raw'!D19+'QTR Raw'!D13+'QTR Raw'!D7 -> 0 | AK40: =+'QTR Raw'!E20+'QTR Raw'!E19+'QTR Raw'!E13+'QTR Raw'!E7 -> 0 | AL40: =+'QTR Raw'!F20+'QTR Raw'!F19+'QTR Raw'!F13+'QTR Raw'!F7 -> 0 | AM40: =+'QTR Raw'!G20+'QTR Raw'!G19+'QTR Raw'!G13+'QTR Raw'!G7 -> 0 | AN40: =+'QTR Raw'!H20+'QTR Raw'!H19+'QTR Raw'!H13+'QTR Raw'!H7 -> 0 | AO40: =+'QTR Raw'!I20+'QTR Raw'!I19+'QTR Raw'!I13+'QTR Raw'!I7 -> 0 | AP40: =+'QTR Raw'!J20+'QTR Raw'!J19+'QTR Raw'!J13+'QTR Raw'!J7 -> 0 | ... CL40: =+'QTR Raw'!BF20+'QTR Raw'!BF19+'QTR Raw'!BF13+'QTR Raw'!BF7 -> 0 | DF40: 0
A41: Net Revenue | B41: =+B39-B40 -> 31.797319 | C41: =+C39-C40 -> 48.946691 | D41: =+D39-D40 -> 46.51493 | E41: =+E39-E40 -> 49.272882 | F41: =+F39-F40 -> 51.493734 | G41: =+G39-G40 -> 81.889648 | H41: =+H39-H40 -> 130.31394 | I41: =+I39-I40 -> 193.70972 | ... AE41: =+AE39-AE40 -> 3366.0586 | AI41: =+AI39-AI40 -> 0 | AJ41: =+AJ39-AJ40 -> 0 | AK41: =+AK39-AK40 -> 0 | AL41: =+AL39-AL40 -> 0 | AM41: =+AM39-AM40 -> 0 | AN41: =+AN39-AN40 -> 0 | AO41: =+AO39-AO40 -> 0 | AP41: =+AP39-AP40 -> 0 | ... DB41: =+DB39-DB40 -> 873.97802 | DF41: 422.53
A42: Net Revenue YOY% | C42: =C41/B41-1 -> 0.53933387 | D42: =D41/C41-1 -> -0.049681814 | E42: =E41/D41-1 -> 0.059291758 | F42: =F41/E41-1 -> 0.045072486 | G42: =G41/F41-1 -> 0.59028377 | H42: =H41/G41-1 -> 0.59133598 | I42: =I41/H41-1 -> 0.48648496 | J42: =J41/I41-1 -> 0.24112377 | ... AE42: =AE41/AD41-1 -> 0.22092695 | AM42: =+IF(AI41<0,1-AM41/AI41,AM41/AI41-1) -> #DIV/0! | AN42: =+IF(AJ41<0,1-AN41/AJ41,AN41/AJ41-1) -> #DIV/0! | AO42: =+IF(AK41<0,1-AO41/AK41,AO41/AK41-1) -> #DIV/0! | AP42: =+IF(AL41<0,1-AP41/AL41,AP41/AL41-1) -> #DIV/0! | AQ42: =+IF(AM41<0,1-AQ41/AM41,AQ41/AM41-1) -> #DIV/0! | AR42: =+IF(AN41<0,1-AR41/AN41,AR41/AN41-1) -> #DIV/0! | AS42: =+IF(AO41<0,1-AS41/AO41,AS41/AO41-1) -> #DIV/0! | AT42: =+IF(AP41<0,1-AT41/AP41,AT41/AP41-1) -> #DIV/0! | ... DB42: =+IF(CX41<0,1-DB41/CX41,DB41/CX41-1) -> 0.18628095 | DF42: 0.14383402
A43: Net Revenue QOQ% | AJ43: =+IF(AI41<0,1-AJ41/AI41,AJ41/AI41-1) -> #DIV/0! | AK43: =+IF(AJ41<0,1-AK41/AJ41,AK41/AJ41-1) -> #DIV/0! | AL43: =+IF(AK41<0,1-AL41/AK41,AL41/AK41-1) -> #DIV/0! | AM43: =+IF(AL41<0,1-AM41/AL41,AM41/AL41-1) -> #DIV/0! | AN43: =+IF(AM41<0,1-AN41/AM41,AN41/AM41-1) -> #DIV/0! | AO43: =+IF(AN41<0,1-AO41/AN41,AO41/AN41-1) -> #DIV/0! | AP43: =+IF(AO41<0,1-AP41/AO41,AP41/AO41-1) -> #DIV/0! | AQ43: =+IF(AP41<0,1-AQ41/AP41,AQ41/AP41-1) -> #DIV/0! | ... CL43: =+IF(CK41<0,1-CL41/CK41,CL41/CK41-1) -> 0.074885489 | CM43: =+CM41/CL41-1 -> -0.11425663 | CN43: =+CN41/CM41-1 -> 0.1244157 | CO43: =+CO41/CN41-1 -> 0.034956652 | CP43: =+CP41/CO41-1 -> 0.033444471 | CQ43: =+CQ41/CP41-1 -> 0.084807143 | CR43: =+CR41/CQ41-1 -> 0.10923108 | CS43: =+CS41/CR41-1 -> 0.022262632 | CT43: =+CT41/CS41-1 -> -0.022259159 | ... DB43: =+DB41/DA41-1 -> 0.017111274 | DF43: -0.014072676
A44: Increase/Decrease in Stock | B44: ='Annual Raw'!C11 -> 0.254252 | C44: ='Annual Raw'!D11 -> 0.3561504 | D44: ='Annual Raw'!E11 -> -0.4957742 | E44: ='Annual Raw'!F11 -> -0.4386168 | F44: ='Annual Raw'!G11 -> -3.880121 | G44: ='Annual Raw'!H11 -> -5.5437663 | H44: ='Annual Raw'!I11 -> -12.068485 | I44: ='Annual Raw'!J11 -> -12.77424 | ... AA44: ='Annual Raw'!AB11 -> 20.1944 | AB44: =+SUM(CM44:CP44) -> 0 | AC44: =+SUM(CQ44:CT44) -> 0 | AD44: =+SUM(CU44:CX44) -> 0 | AE44: =+SUM(CY44:DB44) -> 0 | AI44: ='QTR Raw'!C10 -> 0 | AJ44: ='QTR Raw'!D10 -> 0 | AK44: ='QTR Raw'!E10 -> 0 | AL44: ='QTR Raw'!F10 -> 0 | AM44: ='QTR Raw'!G10 -> 0 | AN44: ='QTR Raw'!H10 -> 0 | AO44: ='QTR Raw'!I10 -> 0 | AP44: ='QTR Raw'!J10 -> 0 | ... CL44: ='QTR Raw'!BF10 -> -9.999 | DF44: 16.335
A45: Purchase of Finished Goods | B45: 0 | C45: 0 | D45: 0 | E45: 0 | F45: 0 | G45: 0 | H45: 0 | I45: 0 | J45: 0 | K45: 0 | L45: 0 | M45: 0 | N45: 0 | O45: 0 | P45: 0 | Q45: 0 | R45: 0 | S45: 0 | T45: 0 | U45: 0 | V45: 0 | W45: 0 | X45: 0 | Y45: 0 | Z45: 0 | AA45: 0 | AB45: =+SUM(CM45:CP45) -> 0 | AC45: =+SUM(CQ45:CT45) -> 0 | AD45: =+SUM(CU45:CX45) -> 0 | AE45: =+SUM(CY45:DB45) -> 0 | AI45: ='QTR Raw'!C12 -> 0 | AJ45: ='QTR Raw'!D12 -> 0 | AK45: ='QTR Raw'!E12 -> 0 | AL45: ='QTR Raw'!F12 -> 0 | AM45: ='QTR Raw'!G12 -> 0 | AN45: ='QTR Raw'!H12 -> 0 | AO45: ='QTR Raw'!I12 -> 0 | AP45: ='QTR Raw'!J12 -> 0 | ... CL45: ='QTR Raw'!BF12 -> 14.477 | DF45: 14.477
A46: Raw Material Consumed | B46: ='Annual Raw'!C12 -> 13.138791 | C46: ='Annual Raw'!D12 -> 28.892685 | D46: ='Annual Raw'!E12 -> 29.077509 | E46: ='Annual Raw'!F12 -> 27.412232 | F46: ='Annual Raw'!G12 -> 30.416405 | G46: ='Annual Raw'!H12 -> 46.127885 | H46: ='Annual Raw'!I12 -> 71.685462 | I46: ='Annual Raw'!J12 -> 106.80836 | ... AA46: ='Annual Raw'!AB12 -> 687.0164 | AB46: =+SUM(CM46:CP46) -> 817.46343 | AC46: =+SUM(CQ46:CT46) -> 1036.6981 | AD46: =+SUM(CU46:CX46) -> 1234.3284 | AE46: =+SUM(CY46:DB46) -> 1507.0965 | AI46: ='QTR Raw'!C11 -> 0 | AJ46: ='QTR Raw'!D11 -> 0 | AK46: ='QTR Raw'!E11 -> 0 | AL46: ='QTR Raw'!F11 -> 0 | AM46: ='QTR Raw'!G11 -> 0 | AN46: ='QTR Raw'!H11 -> 0 | AO46: ='QTR Raw'!I11 -> 0 | AP46: ='QTR Raw'!J11 -> 0 | ... CL46: ='QTR Raw'!BF11 -> 204.133 | CM46: =+CM41-CM47 -> 178.08538 | CN46: =+CN41-CN47 -> 204.79158 | CO46: =+CO41-CO47 -> 215.14392 | CP46: =+CP41-CP47 -> 219.44255 | CQ46: =+CQ41-CQ47 -> 237.29986 | CR46: =+CR41-CR47 -> 264.59682 | CS46: =+CS41-CS47 -> 270.74986 | CT46: =+CT41-CT47 -> 264.05159 | ... DB46: =+DB41-DB47 -> 391.29412 | DF46: 181.42563
A47: Gross Profit | B47: =B41-B44-B46-B45 -> 18.404277 | C47: =C41-C44-C46-C45 -> 19.697855 | D47: =D41-D44-D46-D45 -> 17.933196 | E47: =E41-E44-E46-E45 -> 22.299267 | F47: =F41-F44-F46-F45 -> 24.95745 | G47: =G41-G44-G46-G45 -> 41.30553 | H47: =H41-H44-H46-H45 -> 70.696967 | I47: =I41-I44-I46-I45 -> 99.675595 | ... AE47: =AE41-AE44-AE46-AE45 -> 1858.9621 | AI47: =AI41-AI44-AI46-AI45 -> 0 | AJ47: =AJ41-AJ44-AJ46-AJ45 -> 0 | AK47: =AK41-AK44-AK46-AK45 -> 0 | AL47: =AL41-AL44-AL46-AL45 -> 0 | AM47: =AM41-AM44-AM46-AM45 -> 0 | AN47: =AN41-AN44-AN46-AN45 -> 0 | AO47: =AO41-AO44-AO46-AO45 -> 0 | AP47: =AP41-AP44-AP46-AP45 -> 0 | ... CL47: =CL41-CL44-CL46-CL45 -> 252.043 | CM47: =+CM48*CM41 -> 229.93585 | CN47: =+CN48*CN41 -> 253.99389 | CO47: =+CO48*CO41 -> 259.67916 | CP47: =+CP48*CP41 -> 271.26073 | CQ47: =+CQ48*CQ41 -> 295.01857 | CR47: =+CR48*CR41 -> 325.86733 | CS47: =+CS48*CS41 -> 332.85957 | CT47: =+CT48*CT41 -> 326.12201 | ... DB47: =+DB48*DB41 -> 482.6839 | DF47: 241.10437
A48: GP% | B48: =B47/B41 -> 0.57879963 | C48: =C47/C41 -> 0.40243486 | D48: =D47/D41 -> 0.38553634 | E48: =E47/E41 -> 0.45256672 | F48: =F47/F41 -> 0.48466965 | G48: =G47/G41 -> 0.50440477 | H48: =H47/H41 -> 0.54251268 | I48: =I47/I41 -> 0.51456166 | ... AE48: =AE47/AE41 -> 0.5522667 | AI48: =AI47/AI41 -> #DIV/0! | AJ48: =AJ47/AJ41 -> #DIV/0! | AK48: =AK47/AK41 -> #DIV/0! | AL48: =AL47/AL41 -> #DIV/0! | AM48: =AM47/AM41 -> #DIV/0! | AN48: =AN47/AN41 -> #DIV/0! | AO48: =AO47/AO41 -> #DIV/0! | AP48: =AP47/AP41 -> #DIV/0! | ... CL48: =CL47/CL41 -> 0.54714167 | CM48: =AVERAGE(CI48:CL48) -> 0.56353894 | CN48: =AVERAGE(CJ48:CM48) -> 0.55362234 | CO48: =AVERAGE(CK48:CN48) -> 0.54689667 | CP48: =AVERAGE(CL48:CO48) -> 0.55279991 | CQ48: =AVERAGE(CM48:CP48) -> 0.55421447 | CR48: =AVERAGE(CN48:CQ48) -> 0.55188335 | CS48: =AVERAGE(CO48:CR48) -> 0.5514486 | CT48: =AVERAGE(CP48:CS48) -> 0.55258658 | ... DB48: =AVERAGE(CX48:DA48) -> 0.5522838 | DF48: 0.5706207
A49: GP YOY% | C49: =+IF(B47<0,1-C47/B47,C47/B47-1) -> 0.070286815 | D49: =+IF(C47<0,1-D47/C47,D47/C47-1) -> -0.089586345 | E49: =+IF(D47<0,1-E47/D47,E47/D47-1) -> 0.24346307 | F49: =+IF(E47<0,1-F47/E47,F47/E47-1) -> 0.11920495 | G49: =+IF(F47<0,1-G47/F47,G47/F47-1) -> 0.65503807 | H49: =+IF(G47<0,1-H47/G47,H47/G47-1) -> 0.71156181 | I49: =+IF(H47<0,1-I47/H47,I47/H47-1) -> 0.40989916 | J49: =+IF(I47<0,1-J47/I47,J47/I47-1) -> 0.22015313 | ... AE49: =+IF(AD47<0,1-AE47/AD47,AE47/AD47-1) -> 0.22087987 | AM49: =+IF(AI47<0,1-AM47/AI47,AM47/AI47-1) -> #DIV/0! | AN49: =+IF(AJ47<0,1-AN47/AJ47,AN47/AJ47-1) -> #DIV/0! | AO49: =+IF(AK47<0,1-AO47/AK47,AO47/AK47-1) -> #DIV/0! | AP49: =+IF(AL47<0,1-AP47/AL47,AP47/AL47-1) -> #DIV/0! | AQ49: =+IF(AM47<0,1-AQ47/AM47,AQ47/AM47-1) -> #DIV/0! | AR49: =+IF(AN47<0,1-AR47/AN47,AR47/AN47-1) -> #DIV/0! | AS49: =+IF(AO47<0,1-AS47/AO47,AS47/AO47-1) -> #DIV/0! | AT49: =+IF(AP47<0,1-AT47/AP47,AT47/AP47-1) -> #DIV/0! | ... CL49: =+IF(CH47<0,1-CL47/CH47,CL47/CH47-1) -> 0.18565508 | CM49: =+CM47/CI47-1 -> 0.12238837 | CN49: =+CN47/CJ47-1 -> 0.22137109 | CO49: =+CO47/CK47-1 -> 0.1579431 | CP49: =+CP47/CL47-1 -> 0.076247823 | CQ49: =+CQ47/CM47-1 -> 0.28304731 | CR49: =+CR47/CN47-1 -> 0.2829731 | CS49: =+CS47/CO47-1 -> 0.28181088 | CT49: =+CT47/CP47-1 -> 0.20224556 | ... DB49: =+DB47/CX47-1 -> 0.1861371 | DF49: 0.1341978
A50: GP QOQ% | AJ50: =+IF(AI47<0,1-AJ47/AI47,AJ47/AI47-1) -> #DIV/0! | AK50: =+IF(AJ47<0,1-AK47/AJ47,AK47/AJ47-1) -> #DIV/0! | AL50: =+IF(AK47<0,1-AL47/AK47,AL47/AK47-1) -> #DIV/0! | AM50: =+IF(AL47<0,1-AM47/AL47,AM47/AL47-1) -> #DIV/0! | AN50: =+IF(AM47<0,1-AN47/AM47,AN47/AM47-1) -> #DIV/0! | AO50: =+IF(AN47<0,1-AO47/AN47,AO47/AN47-1) -> #DIV/0! | AP50: =+IF(AO47<0,1-AP47/AO47,AP47/AO47-1) -> #DIV/0! | AQ50: =+IF(AP47<0,1-AQ47/AP47,AQ47/AP47-1) -> #DIV/0! | ... CL50: =+IF(CK47<0,1-CL47/CK47,CL47/CK47-1) -> 0.12389246 | CM50: =+CM47/CL47-1 -> -0.087711824 | CN50: =+CN47/CM47-1 -> 0.10462936 | CO50: =+CO47/CN47-1 -> 0.022383497 | CP50: =+CP47/CO47-1 -> 0.044599531 | CQ50: =+CQ47/CP47-1 -> 0.087583054 | CR50: =+CR47/CQ47-1 -> 0.10456547 | CS50: =+CS47/CR47-1 -> 0.021457338 | CT50: =+CT47/CS47-1 -> -0.020241472 | ... DB50: =+DB47/DA47-1 -> 0.017153064 | DF50: 0.075115673
A51: Other Manufacturing Expenses | B51: ='Annual Raw'!C15+'Annual Raw'!C16 -> 4.0648788 | C51: ='Annual Raw'!D15+'Annual Raw'!D16 -> 4.1775609 | D51: ='Annual Raw'!E15+'Annual Raw'!E16 -> 5.2862596 | E51: ='Annual Raw'!F15+'Annual Raw'!F16 -> 7.8473365 | F51: ='Annual Raw'!G15+'Annual Raw'!G16 -> 7.6527092 | G51: ='Annual Raw'!H15+'Annual Raw'!H16 -> 13.158724 | H51: ='Annual Raw'!I15+'Annual Raw'!I16 -> 21.597667 | I51: ='Annual Raw'!J15+'Annual Raw'!J16 -> 32.498882 | ... AA51: ='Annual Raw'!AB15+'Annual Raw'!AB16 -> 236.765 | AB51: =+SUM(CM51:CP51) -> 465.64146 | AC51: =+SUM(CQ51:CT51) -> 616.795 | AD51: =+SUM(CU51:CX51) -> 753.82964 | AE51: =+SUM(CY51:DB51) -> 947.33323 | AI51: ='QTR Raw'!C14 -> 0 | AJ51: ='QTR Raw'!D14 -> 0 | AK51: ='QTR Raw'!E14 -> 0 | AL51: ='QTR Raw'!F14 -> 0 | AM51: ='QTR Raw'!G14 -> 0 | AN51: ='QTR Raw'!H14 -> 0 | AO51: ='QTR Raw'!I14 -> 0 | AP51: ='QTR Raw'!J14 -> 0 | ... CL51: ='QTR Raw'!BF14 -> 119.212 | CM51: =+CM57-CM56-CM55-CM54-CM53-CM52 -> 105.26291 | CN51: =+CN57-CN56-CN55-CN54-CN53-CN52 -> 119.29823 | CO51: =+CO57-CO56-CO55-CO54-CO53-CO52 -> 115.08479 | CP51: =+CP57-CP56-CP55-CP54-CP53-CP52 -> 125.99553 | CQ51: =+CQ57-CQ56-CQ55-CQ54-CQ53-CQ52 -> 141.98195 | CR51: =+CR57-CR56-CR55-CR54-CR53-CR52 -> 160.78963 | CS51: =+CS57-CS56-CS55-CS54-CS53-CS52 -> 157.82052 | CT51: =+CT57-CT56-CT55-CT54-CT53-CT52 -> 156.2029 | ... DB51: =+DB57-DB56-DB55-DB54-DB53-DB52 -> 245.613 | DF51: 116.44138
A52: Employee Cost | B52: ='Annual Raw'!C14 -> 2.1856685 | C52: ='Annual Raw'!D14 -> 2.3922158 | D52: ='Annual Raw'!E14 -> 2.7783973 | E52: ='Annual Raw'!F14 -> 3.1842187 | F52: ='Annual Raw'!G14 -> 3.5654644 | G52: ='Annual Raw'!H14 -> 4.3553126 | H52: ='Annual Raw'!I14 -> 5.9573332 | I52: ='Annual Raw'!J14 -> 9.0858556 | ... AA52: ='Annual Raw'!AB14 -> 145.9227 | AB52: =+SUM(CM52:CP52) -> 156.13654 | AC52: =+SUM(CQ52:CT52) -> 167.0661 | AD52: =+SUM(CU52:CX52) -> 178.76072 | AE52: =+SUM(CY52:DB52) -> 191.27398 | AI52: ='QTR Raw'!C16 -> 0 | AJ52: ='QTR Raw'!D16 -> 0 | AK52: ='QTR Raw'!E16 -> 0 | AL52: ='QTR Raw'!F16 -> 0 | AM52: ='QTR Raw'!G16 -> 0 | AN52: ='QTR Raw'!H16 -> 0 | AO52: ='QTR Raw'!I16 -> 0 | AP52: ='QTR Raw'!J16 -> 0 | ... CL52: ='QTR Raw'!BF16 -> 38.173 | CM52: =CI52*107% -> 36.25053 | CN52: =CJ52*107% -> 36.12855 | CO52: =CK52*107% -> 42.91235 | CP52: =CL52*107% -> 40.84511 | CQ52: =CM52*107% -> 38.788067 | CR52: =CN52*107% -> 38.657549 | CS52: =CO52*107% -> 45.916215 | CT52: =CP52*107% -> 43.704268 | ... DB52: =CX52*107% -> 50.037016 | DF52: 31.45158
A53: General and Administration Expenses | B53: ='Annual Raw'!C17 -> 2.0371441 | C53: ='Annual Raw'!D17 -> 2.8820853 | D53: ='Annual Raw'!E17 -> 2.1617858 | E53: ='Annual Raw'!F17 -> 1.9958676 | F53: ='Annual Raw'!G17 -> 2.2338539 | G53: ='Annual Raw'!H17 -> 2.2479441 | H53: ='Annual Raw'!I17 -> 3.4993221 | I53: ='Annual Raw'!J17 -> 5.0583309 | ... AA53: ='Annual Raw'!AB17 -> 74.5528 | AB53: =+SUM(CM53:CP53) -> 0 | AC53: =+SUM(CQ53:CT53) -> 0 | AD53: =+SUM(CU53:CX53) -> 0 | AE53: =+SUM(CY53:DB53) -> 0 | AI53: ='QTR Raw'!C17 -> 0 | AJ53: ='QTR Raw'!D17 -> 0 | AK53: ='QTR Raw'!E17 -> 0 | AL53: ='QTR Raw'!F17 -> 0 | AM53: ='QTR Raw'!G17 -> 0 | AN53: ='QTR Raw'!H17 -> 0 | AO53: ='QTR Raw'!I17 -> 0 | AP53: ='QTR Raw'!J17 -> 0 | ... CL53: ='QTR Raw'!BF17 -> 0 | DF53: 0
A54: Selling and Distribution Expenses | B54: ='Annual Raw'!C18 -> 1.9034644 | C54: ='Annual Raw'!D18 -> 0.7818628 | D54: ='Annual Raw'!E18 -> 1.4677134 | E54: ='Annual Raw'!F18 -> 1.882833 | F54: ='Annual Raw'!G18 -> 2.2964553 | G54: ='Annual Raw'!H18 -> 3.0157097 | H54: ='Annual Raw'!I18 -> 5.1719559 | I54: ='Annual Raw'!J18 -> 8.6011471 | ... AA54: ='Annual Raw'!AB18 -> 59.277 | AB54: =+SUM(CM54:CP54) -> 0 | AC54: =+SUM(CQ54:CT54) -> 0 | AD54: =+SUM(CU54:CX54) -> 0 | AE54: =+SUM(CY54:DB54) -> 0 | AI54: ='QTR Raw'!C18 -> 0 | AJ54: ='QTR Raw'!D18 -> 0 | AK54: ='QTR Raw'!E18 -> 0 | AL54: ='QTR Raw'!F18 -> 0 | AM54: ='QTR Raw'!G18 -> 0 | AN54: ='QTR Raw'!H18 -> 0 | AO54: ='QTR Raw'!I18 -> 0 | AP54: ='QTR Raw'!J18 -> 0 | ... CL54: ='QTR Raw'!BF18 -> 0 | DF54: 0
A55: Miscellaneous Expenses | B55: ='Annual Raw'!C19-'Annual Raw'!C20 -> 1.4004614 | C55: ='Annual Raw'!D19-'Annual Raw'!D20 -> 1.2806024 | D55: ='Annual Raw'!E19-'Annual Raw'!E20 -> 0.6977147 | E55: ='Annual Raw'!F19-'Annual Raw'!F20 -> 0.6641621 | F55: ='Annual Raw'!G19-'Annual Raw'!G20 -> 0.7861815 | G55: ='Annual Raw'!H19-'Annual Raw'!H20 -> 0.8971922 | H55: ='Annual Raw'!I19-'Annual Raw'!I20 -> 1.2490533 | I55: ='Annual Raw'!J19-'Annual Raw'!J20 -> 1.8582512 | ... AA55: ='Annual Raw'!AB19-'Annual Raw'!AB20 -> 8.3624 | AB55: =+SUM(CM55:CP55) -> 0 | AC55: =+SUM(CQ55:CT55) -> 0 | AD55: =+SUM(CU55:CX55) -> 0 | AE55: =+SUM(CY55:DB55) -> 0 | AI55: =+'QTR Raw'!C21 -> 0 | AJ55: =+'QTR Raw'!D21 -> 0 | AK55: =+'QTR Raw'!E21 -> 0 | AL55: =+'QTR Raw'!F21 -> 0 | AM55: =+'QTR Raw'!G21 -> 0 | AN55: =+'QTR Raw'!H21 -> 0 | AO55: =+'QTR Raw'!I21 -> 0 | AP55: =+'QTR Raw'!J21 -> 0 | ... CL55: =+'QTR Raw'!BF21 -> 0 | DF55: 0
A56: Power & Fuel Cost | B56: ='Annual Raw'!C13 -> 0.6412955 | C56: ='Annual Raw'!D13 -> 0.6726684 | D56: ='Annual Raw'!E13 -> 0.7121749 | E56: ='Annual Raw'!F13 -> 0.8292202 | F56: ='Annual Raw'!G13 -> 0.8905262 | G56: ='Annual Raw'!H13 -> 0.9735511 | H56: ='Annual Raw'!I13 -> 1.6014805 | I56: ='Annual Raw'!J13 -> 2.232156 | ... AA56: ='Annual Raw'!AB13 -> 14.3574 | AB56: =+SUM(CM56:CP56) -> 0 | AC56: =+SUM(CQ56:CT56) -> 0 | AD56: =+SUM(CU56:CX56) -> 0 | AE56: =+SUM(CY56:DB56) -> 0 | AI56: ='QTR Raw'!C15 -> 0 | AJ56: ='QTR Raw'!D15 -> 0 | AK56: ='QTR Raw'!E15 -> 0 | AL56: ='QTR Raw'!F15 -> 0 | AM56: ='QTR Raw'!G15 -> 0 | AN56: ='QTR Raw'!H15 -> 0 | AO56: ='QTR Raw'!I15 -> 0 | AP56: ='QTR Raw'!J15 -> 0 | ... CL56: ='QTR Raw'!BF15 -> 0 | DF56: 0
A57: Total Cost | B57: =+SUM(B51:B56) -> 12.232913 | C57: =+SUM(C51:C56) -> 12.186996 | D57: =+SUM(D51:D56) -> 13.104046 | E57: =+SUM(E51:E56) -> 16.403638 | F57: =+SUM(F51:F56) -> 17.42519 | G57: =+SUM(G51:G56) -> 24.648434 | H57: =+SUM(H51:H56) -> 39.076812 | I57: =+SUM(I51:I56) -> 59.334623 | ... AE57: =+SUM(AE51:AE56) -> 1138.6072 | AI57: =+SUM(AI51:AI56) -> 0 | AJ57: =+SUM(AJ51:AJ56) -> 0 | AK57: =+SUM(AK51:AK56) -> 0 | AL57: =+SUM(AL51:AL56) -> 0 | AM57: =+SUM(AM51:AM56) -> 0 | AN57: =+SUM(AN51:AN56) -> 0 | AO57: =+SUM(AO51:AO56) -> 0 | AP57: =+SUM(AP51:AP56) -> 0 | ... CL57: =+SUM(CL51:CL56) -> 157.385 | CM57: =CM58*CM41 -> 141.51344 | CN57: =CN58*CN41 -> 155.42678 | CO57: =CO58*CO41 -> 157.99714 | CP57: =CP58*CP41 -> 166.84064 | CQ57: =CQ58*CQ41 -> 180.77001 | CR57: =CR58*CR41 -> 199.44718 | CS57: =CS58*CS41 -> 203.73674 | CT57: =CT58*CT41 -> 199.90717 | ... DB57: =DB58*DB41 -> 295.65002 | DF57: 147.89296
A58: Cost % | B58: =B57/B41 -> 0.38471522 | C58: =C57/C41 -> 0.24898508 | D58: =D57/D41 -> 0.28171698 | E58: =E57/E41 -> 0.33291412 | F58: =F57/F41 -> 0.33839439 | G58: =G57/G41 -> 0.30099572 | H58: =H57/H41 -> 0.2998667 | I58: =I57/I41 -> 0.3063069 | ... AE58: =AE57/AE41 -> 0.33826125 | AI58: =AI57/AI41 -> #DIV/0! | AJ58: =AJ57/AJ41 -> #DIV/0! | AK58: =AK57/AK41 -> #DIV/0! | AL58: =AL57/AL41 -> #DIV/0! | AM58: =AM57/AM41 -> #DIV/0! | AN58: =AN57/AN41 -> #DIV/0! | AO58: =AO57/AO41 -> #DIV/0! | AP58: =AP57/AP41 -> #DIV/0! | ... CL58: =CL57/CL41 -> 0.34165556 | CM58: =AVERAGE(CI58:CL58) -> 0.34682861 | CN58: =AVERAGE(CJ58:CM58) -> 0.33877877 | CO58: =AVERAGE(CK58:CN58) -> 0.3327495 | CP58: =AVERAGE(CL58:CO58) -> 0.34000311 | CQ58: =AVERAGE(CM58:CP58) -> 0.33959 | CR58: =AVERAGE(CN58:CQ58) -> 0.33778034 | CS58: =AVERAGE(CO58:CR58) -> 0.33753074 | CT58: =AVERAGE(CP58:CS58) -> 0.33872605 | ... DB58: =AVERAGE(CX58:DA58) -> 0.33828084 | DF58: 0.35001766
A59: EBITDA | B59: =B47-B57 -> 6.171364 | C59: =C47-C57 -> 7.5108591 | D59: =D47-D57 -> 4.8291502 | E59: =E47-E57 -> 5.8956288 | F59: =F47-F57 -> 7.5322593 | G59: =G47-G57 -> 16.657096 | H59: =H47-H57 -> 31.620155 | I59: =I47-I57 -> 40.340972 | ... AE59: =AE47-AE57 -> 720.35489 | AF59: 525 | AI59: =AI47-AI57 -> 0 | AJ59: =AJ47-AJ57 -> 0 | AK59: =AK47-AK57 -> 0 | AL59: =AL47-AL57 -> 0 | AM59: =AM47-AM57 -> 0 | AN59: =AN47-AN57 -> 0 | AO59: =AO47-AO57 -> 0 | AP59: =AP47-AP57 -> 0 | ... DB59: =DB47-DB57 -> 187.03388 | DF59: 93.211402
A60: EBITDA Margins | B60: =B59/B41 -> 0.19408441 | C60: =C59/C41 -> 0.15344978 | D60: =D59/D41 -> 0.10381936 | E60: =E59/E41 -> 0.11965261 | F60: =F59/F41 -> 0.14627526 | G60: =G59/G41 -> 0.20340905 | H60: =H59/H41 -> 0.24264599 | I60: =I59/I41 -> 0.20825477 | ... AE60: =AE59/AE41 -> 0.21400545 | AI60: =AI59/AI41 -> #DIV/0! | AJ60: =AJ59/AJ41 -> #DIV/0! | AK60: =AK59/AK41 -> #DIV/0! | AL60: =AL59/AL41 -> #DIV/0! | AM60: =AM59/AM41 -> #DIV/0! | AN60: =AN59/AN41 -> #DIV/0! | AO60: =AO59/AO41 -> #DIV/0! | AP60: =AP59/AP41 -> #DIV/0! | ... DB60: =DB59/DB41 -> 0.21400296 | DF60: 0.22060304
A61: EBITDA YOY% | C61: =+IF(B59<0,1-C59/B59,C59/B59-1) -> 0.21705009 | D61: =+IF(C59<0,1-D59/C59,D59/C59-1) -> -0.35704423 | E61: =+IF(D59<0,1-E59/D59,E59/D59-1) -> 0.22084188 | F61: =+IF(E59<0,1-F59/E59,F59/E59-1) -> 0.27760067 | G61: =+IF(F59<0,1-G59/F59,G59/F59-1) -> 1.2114342 | H61: =+IF(G59<0,1-H59/G59,H59/G59-1) -> 0.89829942 | I61: =+IF(H59<0,1-I59/H59,I59/H59-1) -> 0.2757993 | J61: =+IF(I59<0,1-J59/I59,J59/I59-1) -> 0.11148929 | ... AE61: =+IF(AD59<0,1-AE59/AD59,AE59/AD59-1) -> 0.22083511 | AM61: =+IF(AI59<0,1-AM59/AI59,AM59/AI59-1) -> #DIV/0! | AN61: =+IF(AJ59<0,1-AN59/AJ59,AN59/AJ59-1) -> #DIV/0! | AO61: =+IF(AK59<0,1-AO59/AK59,AO59/AK59-1) -> #DIV/0! | AP61: =+IF(AL59<0,1-AP59/AL59,AP59/AL59-1) -> #DIV/0! | AQ61: =+IF(AM59<0,1-AQ59/AM59,AQ59/AM59-1) -> #DIV/0! | AR61: =+IF(AN59<0,1-AR59/AN59,AR59/AN59-1) -> #DIV/0! | AS61: =+IF(AO59<0,1-AS59/AO59,AS59/AO59-1) -> #DIV/0! | AT61: =+IF(AP59<0,1-AT59/AP59,AT59/AP59-1) -> #DIV/0! | ... CL61: =+IF(CH59<0,1-CL59/CH59,CL59/CH59-1) -> 0.15920057 | CM61: =+CM59/CI59-1 -> 0.16137456 | CN61: =+CN59/CJ59-1 -> 0.2643293 | CO61: =+CO59/CK59-1 -> 0.080688914 | CP61: =+CP59/CL59-1 -> 0.10313008 | CQ61: =+CQ59/CM59-1 -> 0.29207692 | CR61: =+CR59/CN59-1 -> 0.2825794 | CS61: =+CS59/CO59-1 -> 0.26986894 | CT61: =+CT59/CP59-1 -> 0.20872183 | ... DB61: =+DB59/CX59-1 -> 0.18634491 | DF61: 0.14148525
A62: EBITDA QOQ% | AJ62: =+IF(AI59<0,1-AJ59/AI59,AJ59/AI59-1) -> #DIV/0! | AK62: =+IF(AJ59<0,1-AK59/AJ59,AK59/AJ59-1) -> #DIV/0! | AL62: =+IF(AK59<0,1-AL59/AK59,AL59/AK59-1) -> #DIV/0! | AM62: =+IF(AL59<0,1-AM59/AL59,AM59/AL59-1) -> #DIV/0! | AN62: =+IF(AM59<0,1-AN59/AM59,AN59/AM59-1) -> #DIV/0! | AO62: =+IF(AN59<0,1-AO59/AN59,AO59/AN59-1) -> #DIV/0! | AP62: =+IF(AO59<0,1-AP59/AO59,AP59/AO59-1) -> #DIV/0! | AQ62: =+IF(AP59<0,1-AQ59/AP59,AQ59/AP59-1) -> #DIV/0! | ... CI62: =+IF(CH59<0,1-CI59/CH59,CI59/CH59-1) -> -0.067623503 | CJ62: =+IF(CI59>1,CJ59/CI59-1,1-CJ59/CI59) -> 0.023957129 | CK62: =+IF(CJ59>1,CK59/CJ59-1,1-CK59/CJ59) -> 0.20690097 | CL62: =+IF(CK59>1,CL59/CK59-1,1-CL59/CK59) -> 0.0060367733 | CM62: =+CM59/CL59-1 -> -0.065874903 | CN62: =+CN59/CM59-1 -> 0.11472995 | CO62: =+CO59/CN59-1 -> 0.031601895 | CP62: =+CP59/CO59-1 -> 0.026927746 | CQ62: =+CQ59/CP59-1 -> 0.094124345 | CR62: =+CR59/CQ59-1 -> 0.10653603 | CS62: =+CS59/CR59-1 -> 0.021378641 | CT62: =+CT59/CS59-1 -> -0.022521185 | ... DB62: =+DB59/DA59-1 -> 0.017136226 | DF62: -0.0093378448
A63: Depreciation | B63: ='Annual Raw'!C27 -> 1.4644648 | C63: ='Annual Raw'!D27 -> 1.2651054 | D63: ='Annual Raw'!E27 -> 0.9957931 | E63: ='Annual Raw'!F27 -> 0.9834665 | F63: ='Annual Raw'!G27 -> 1.0734377 | G63: ='Annual Raw'!H27 -> 1.1749393 | H63: ='Annual Raw'!I27 -> 1.4546299 | I63: ='Annual Raw'!J27 -> 2.560631 | ... AA63: ='Annual Raw'!AB27 -> 33.6155 | AB63: =+SUM(CM63:CP63) -> 44.329671 | AC63: =+SUM(CQ63:CT63) -> 55.0398 | AD63: =+SUM(CU63:CX63) -> 64.758258 | AE63: =+SUM(CY63:DB63) -> 73.576866 | AI63: ='QTR Raw'!C28 -> 0 | AJ63: ='QTR Raw'!D28 -> 0 | AK63: ='QTR Raw'!E28 -> 0 | AL63: ='QTR Raw'!F28 -> 0 | AM63: ='QTR Raw'!G28 -> 0 | AN63: ='QTR Raw'!H28 -> 0 | AO63: ='QTR Raw'!I28 -> 0 | AP63: ='QTR Raw'!J28 -> 0 | ... CL63: ='QTR Raw'!BF28 -> 9.021 | CM63: =CM64*CL165 -> 10.0204 | CN63: =CN64*CM165 -> 10.739853 | CO63: =CO64*CN165 -> 11.442041 | CP63: =CP64*CO165 -> 12.127377 | CQ63: =CQ64*CP165 -> 12.796267 | CR63: =CR64*CQ165 -> 13.449104 | CS63: =CS64*CR165 -> 14.086275 | CT63: =CT64*CS165 -> 14.708154 | ... DB63: =DB64*DA165 -> 19.174958 | DF63: 9.1754341
A64: Depreciation % of Net Block | B64: =+B63/B165 -> 0.12644877 | C64: =+C63/C165 -> 0.11715587 | D64: =+D63/D165 -> 0.097607763 | E64: =+E63/E165 -> 0.098010808 | F64: =+F63/F165 -> 0.10050048 | G64: =+G63/G165 -> 0.10483478 | H64: =+H63/H165 -> 0.047849649 | I64: =+I63/I165 -> 0.050364364 | ... AE64: =+AE63/AE165 -> 0.089744805 | AI64: =+AI63/AH165 -> #DIV/0! | AJ64: =+AJ63/AI165 -> #DIV/0! | AK64: =+AK63/AJ165 -> #DIV/0! | AL64: =+AL63/AK165 -> #DIV/0! | AM64: =+AM63/AL165 -> #DIV/0! | AN64: =+AN63/AM165 -> #DIV/0! | AO64: =+AO63/AN165 -> #DIV/0! | AP64: =+AP63/AO165 -> #DIV/0! | ... CL64: =+CL63/CK165 -> 0.023998085 | CM64: =CL64 -> 0.023998085 | CN64: =CM64 -> 0.023998085 | CO64: =CN64 -> 0.023998085 | CP64: =CO64 -> 0.023998085 | CQ64: =CP64 -> 0.023998085 | CR64: =CQ64 -> 0.023998085 | CS64: =CR64 -> 0.023998085 | CT64: =CS64 -> 0.023998085 | ... DB64: =DA64 -> 0.023998085 | DF64: 0.024408917
A65: EBIT | B65: =B59-B63 -> 4.7068992 | C65: =C59-C63 -> 6.2457537 | D65: =D59-D63 -> 3.8333571 | E65: =E59-E63 -> 4.9121623 | F65: =F59-F63 -> 6.4588216 | G65: =G59-G63 -> 15.482156 | H65: =H59-H63 -> 30.165525 | I65: =I59-I63 -> 37.780341 | ... AE65: =AE59-AE63 -> 646.77802 | AI65: =AI59-AI63 -> 0 | AJ65: =AJ59-AJ63 -> 0 | AK65: =AK59-AK63 -> 0 | AL65: =AL59-AL63 -> 0 | AM65: =AM59-AM63 -> 0 | AN65: =AN59-AN63 -> 0 | AO65: =AO59-AO63 -> 0 | AP65: =AP59-AP63 -> 0 | ... DB65: =DB59-DB63 -> 167.85892 | DF65: 84.035968
A66: Other Income | B66: ='Annual Raw'!C23 -> 1.796321 | C66: ='Annual Raw'!D23 -> 1.5778719 | D66: ='Annual Raw'!E23 -> 2.3277861 | E66: ='Annual Raw'!F23 -> 1.4852618 | F66: ='Annual Raw'!G23 -> 2.0172045 | G66: ='Annual Raw'!H23 -> 1.5512829 | H66: ='Annual Raw'!I23 -> 0.7916434 | I66: ='Annual Raw'!J23 -> 1.742106 | ... AA66: ='Annual Raw'!AB23 -> 47.4177 | AB66: =+SUM(CM66:CP66) -> 0 | AC66: =+SUM(CQ66:CT66) -> 0 | AD66: =+SUM(CU66:CX66) -> 0 | AE66: =+SUM(CY66:DB66) -> 0 | AI66: ='QTR Raw'!C23 -> 0 | AJ66: ='QTR Raw'!D23 -> 0 | AK66: ='QTR Raw'!E23 -> 0 | AL66: ='QTR Raw'!F23 -> 0 | AM66: ='QTR Raw'!G23 -> 0 | AN66: ='QTR Raw'!H23 -> 0 | AO66: ='QTR Raw'!I23 -> 0 | AP66: ='QTR Raw'!J23 -> 0 | ... CL66: ='QTR Raw'!BF23 -> 14.589 | DF66: 44.009
A67: Interest | B67: ='Annual Raw'!C25 -> 0.7251107 | C67: ='Annual Raw'!D25 -> 0.8866333 | D67: ='Annual Raw'!E25 -> 0.6466655 | E67: ='Annual Raw'!F25 -> 0.5841225 | F67: ='Annual Raw'!G25 -> 0.3306739 | G67: ='Annual Raw'!H25 -> 0.3442336 | H67: ='Annual Raw'!I25 -> 0.497821 | I67: ='Annual Raw'!J25 -> 2.4190274 | ... AA67: ='Annual Raw'!AB25 -> 9.2311 | AB67: =+SUM(CM67:CP67) -> -38.659102 | AC67: =+SUM(CQ67:CT67) -> -52.27815 | AD67: =+SUM(CU67:CX67) -> -56.012269 | AE67: =+SUM(CY67:DB67) -> -77.150935 | AI67: ='QTR Raw'!C25 -> 0 | AJ67: ='QTR Raw'!D25 -> 0 | AK67: ='QTR Raw'!E25 -> 0 | AL67: ='QTR Raw'!F25 -> 0 | AM67: ='QTR Raw'!G25 -> 0 | AN67: ='QTR Raw'!H25 -> 0 | AO67: ='QTR Raw'!I25 -> 0 | AP67: ='QTR Raw'!J25 -> 0 | ... CL67: ='QTR Raw'!BF25 -> 3.51 | CM67: =CM68*CL199 -> -7.52505 | CN67: =CN68*CM199 -> -10.149189 | CO67: =CO68*CN199 -> -10.005781 | CP67: =CP68*CO199 -> -10.979082 | CQ67: =CQ68*CP199 -> -12.037567 | CR67: =CR68*CQ199 -> -12.586584 | CS67: =CS68*CR199 -> -12.943243 | CT67: =CT68*CS199 -> -14.710756 | ... DB67: =DB68*DA199 -> -22.000265 | DF67: -3.9601184
A68: Interest % of Debt | B68: =+B67/B159 -> 0.086316534 | C68: =+C67/C159 -> 0.32260803 | D68: =+D67/D159 -> 0.10618681 | E68: =+E67/E159 -> 0.9735375 | F68: =+F67/F159 -> 0.33240938 | G68: =+G67/G159 -> 0.26603797 | H68: =+H67/H159 -> 0.061807493 | I68: =+I67/I159 -> 0.11047575 | ... AE68: =+AE67/AE159 -> -1.1100854 | AI68: =(AI67-AI66)/AH199 -> #DIV/0! | AJ68: =(AJ67-AJ66)/AI199 -> #DIV/0! | AK68: =(AK67-AK66)/AJ199 -> #DIV/0! | AL68: =(AL67-AL66)/AK199 -> #DIV/0! | AM68: =(AM67-AM66)/AL199 -> #DIV/0! | AN68: =(AN67-AN66)/AM199 -> #DIV/0! | AO68: =(AO67-AO66)/AN199 -> #DIV/0! | AP68: =(AP67-AP66)/AO199 -> #DIV/0! | ... CL68: =(CL67-CL66)/CK199 -> 0.053801851 | CM68: 0.03 | CN68: =+CM68 -> 0.03 | CO68: =+CN68 -> 0.03 | CP68: =+CO68 -> 0.03 | CQ68: =+CP68 -> 0.03 | CR68: =+CQ68 -> 0.03 | CS68: =+CR68 -> 0.03 | CT68: =+CS68 -> 0.03 | CU68: 0.022 | CV68: =+CU68 -> 0.022 | CW68: =+CV68 -> 0.022 | CX68: =+CW68 -> 0.022 | CY68: =+CX68 -> 0.022 | CZ68: =+CY68 -> 0.022 | DA68: =+CZ68 -> 0.022 | DB68: =+DA68 -> 0.022 | DF68: 0.019231131
A69: PBT | B69: =B65+B66-B67 -> 5.7781095 | C69: =C65+C66-C67 -> 6.9369923 | D69: =D65+D66-D67 -> 5.5144777 | E69: =E65+E66-E67 -> 5.8133016 | F69: =F65+F66-F67 -> 8.1453522 | G69: =G65+G66-G67 -> 16.689206 | H69: =H65+H66-H67 -> 30.459348 | I69: =I65+I66-I67 -> 37.10342 | ... AE69: =AE65+AE66-AE67 -> 723.92896 | AI69: =AI65+AI66-AI67 -> 0 | AJ69: =AJ65+AJ66-AJ67 -> 0 | AK69: =AK65+AK66-AK67 -> 0 | AL69: =AL65+AL66-AL67 -> 0 | AM69: =AM65+AM66-AM67 -> 0 | AN69: =AN65+AN66-AN67 -> 0 | AO69: =AO65+AO66-AO67 -> 0 | AP69: =AP65+AP66-AP67 -> 0 | ... DB69: =DB65+DB66-DB67 -> 189.85919 | DF69: 87.996086
A70: Tax | B70: ='Annual Raw'!C30 -> 1.66 | C70: ='Annual Raw'!D30 -> 1.82 | D70: ='Annual Raw'!E30 -> 1.8749301 | E70: ='Annual Raw'!F30 -> 2.0196939 | F70: ='Annual Raw'!G30 -> 2.8932112 | G70: ='Annual Raw'!H30 -> 5.8709862 | H70: ='Annual Raw'!I30 -> 10.164441 | I70: ='Annual Raw'!J30 -> 12.301541 | ... AA70: ='Annual Raw'!AB30 -> 84.0184 | AB70: =+SUM(CM70:CP70) -> 91.631705 | AC70: =+SUM(CQ70:CT70) -> 116.46454 | AD70: =+SUM(CU70:CX70) -> 137.22065 | AE70: =+SUM(CY70:DB70) -> 170.88256 | AI70: ='QTR Raw'!C29 -> 0 | AJ70: ='QTR Raw'!D29 -> 0 | AK70: ='QTR Raw'!E29 -> 0 | AL70: ='QTR Raw'!F29 -> 0 | AM70: ='QTR Raw'!G29 -> 0 | AN70: ='QTR Raw'!H29 -> 0 | AO70: ='QTR Raw'!I29 -> 0 | AP70: ='QTR Raw'!J29 -> 0 | ... CL70: ='QTR Raw'!BF29 -> 24.683 | CM70: =+CM69*CM71 -> 20.500295 | CN70: =+CN69*CN71 -> 23.319372 | CO70: =+CO69*CO71 -> 23.392259 | CP70: =+CP69*CP71 -> 24.41978 | CQ70: =+CQ69*CQ71 -> 26.85165 | CR70: =+CR69*CR71 -> 29.644781 | CS70: =+CS69*CS71 -> 30.155719 | CT70: =+CT69*CT71 -> 29.812387 | ... DB70: =+DB69*DB71 -> 44.817443 | DF70: 21.142322
A71: Tax Rate % | B71: =B70/B69 -> 0.2872912 | C71: =C70/C69 -> 0.26236154 | D71: =D70/D69 -> 0.34000139 | E71: =E70/E69 -> 0.34742631 | F71: =F70/F69 -> 0.3551978 | G71: =G70/G69 -> 0.35178344 | H71: =H70/H69 -> 0.33370515 | I71: =I70/I69 -> 0.33154736 | ... AE71: =AE70/AE69 -> 0.2360488 | AI71: =AI70/AI69 -> #DIV/0! | AJ71: =AJ70/AJ69 -> #DIV/0! | AK71: =AK70/AK69 -> #DIV/0! | AL71: =AL70/AL69 -> #DIV/0! | AM71: =AM70/AM69 -> #DIV/0! | AN71: =AN70/AN69 -> #DIV/0! | AO71: =AO70/AO69 -> #DIV/0! | AP71: =AP70/AP69 -> #DIV/0! | ... CL71: =CL70/CL69 -> 0.25521113 | CM71: =AVERAGE(CI71:CL71)*0.98 -> 0.23857786 | CN71: =AVERAGE(CJ71:CM71)*0.98 -> 0.23800997 | CO71: =AVERAGE(CK71:CN71)*0.98 -> 0.23334911 | CP71: =AVERAGE(CL71:CO71)*0.98 -> 0.23646128 | CQ71: =AVERAGE(CM71:CP71) -> 0.23659955 | CR71: =AVERAGE(CN71:CQ71) -> 0.23610498 | CS71: =AVERAGE(CO71:CR71) -> 0.23562873 | CT71: =AVERAGE(CP71:CS71) -> 0.23619863 | CU71: =AVERAGE(CQ71:CT71) -> 0.23613297 | CV71: =AVERAGE(CR71:CU71) -> 0.23601633 | CW71: =AVERAGE(CS71:CV71) -> 0.23599417 | CX71: =AVERAGE(CT71:CW71) -> 0.23608553 | ... DB71: =AVERAGE(CX71:DA71) -> 0.23605623 | DF71: 0.24026435
A72: PAT | B72: =B69-B70 -> 4.1181095 | C72: =C69-C70 -> 5.1169923 | D72: =D69-D70 -> 3.6395476 | E72: =E69-E70 -> 3.7936077 | F72: =F69-F70 -> 5.252141 | G72: =G69-G70 -> 10.81822 | H72: =H69-H70 -> 20.294907 | I72: =I69-I70 -> 24.801879 | ... AE72: =AE69-AE70 -> 553.0464 | AF72: 360 | AI72: =AI69-AI70 -> 0 | AJ72: =AJ69-AJ70 -> 0 | AK72: =AK69-AK70 -> 0 | AL72: =AL69-AL70 -> 0 | AM72: =AM69-AM70 -> 0 | AN72: =AN69-AN70 -> 0 | AO72: =AO69-AO70 -> 0 | AP72: =AP69-AP70 -> 0 | ... DB72: =DB69-DB70 -> 145.04174 | DF72: 66.853764
A73: PAT % | B73: =+B72/B41 -> 0.12951122 | C73: =+C72/C41 -> 0.10454215 | D73: =+D72/D41 -> 0.078244718 | E73: =+E72/E41 -> 0.076991796 | F73: =+F72/F41 -> 0.10199573 | G73: =+G72/G41 -> 0.13210729 | H73: =+H72/H41 -> 0.15573857 | I73: =+I72/I41 -> 0.12803632 | ... AE73: =+AE72/AE41 -> 0.16430088 | AI73: =+AI72/AI41 -> #DIV/0! | AJ73: =+AJ72/AJ41 -> #DIV/0! | AK73: =+AK72/AK41 -> #DIV/0! | AL73: =+AL72/AL41 -> #DIV/0! | AM73: =+AM72/AM41 -> #DIV/0! | AN73: =+AN72/AN41 -> #DIV/0! | AO73: =+AO72/AO41 -> #DIV/0! | AP73: =+AP72/AP41 -> #DIV/0! | ... DB73: =+DB72/DB41 -> 0.16595582 | DF73: 0.15822253
A74: PAT YOY% | C74: =+IF(B72<0,1-C72/B72,C72/B72-1) -> 0.24255858 | D74: =+IF(C72<0,1-D72/C72,D72/C72-1) -> -0.28873303 | E74: =+IF(D72<0,1-E72/D72,E72/D72-1) -> 0.042329464 | F74: =+IF(E72<0,1-F72/E72,F72/E72-1) -> 0.3844713 | G74: =+IF(F72<0,1-G72/F72,G72/F72-1) -> 1.0597733 | H74: =+IF(G72<0,1-H72/G72,H72/G72-1) -> 0.87599323 | I74: =+IF(H72<0,1-I72/H72,I72/H72-1) -> 0.22207405 | J74: =+IF(I72<0,1-J72/I72,J72/I72-1) -> 0.21894938 | ... AE74: =+IF(AD72<0,1-AE72/AD72,AE72/AD72-1) -> 0.24536357 | AM74: =+IF(AI72<0,1-AM72/AI72,AM72/AI72-1) -> #DIV/0! | AN74: =+IF(AJ72<0,1-AN72/AJ72,AN72/AJ72-1) -> #DIV/0! | AO74: =+IF(AK72<0,1-AO72/AK72,AO72/AK72-1) -> #DIV/0! | AP74: =+IF(AL72<0,1-AP72/AL72,AP72/AL72-1) -> #DIV/0! | AQ74: =+IF(AM72<0,1-AQ72/AM72,AQ72/AM72-1) -> #DIV/0! | AR74: =+IF(AN72<0,1-AR72/AN72,AR72/AN72-1) -> #DIV/0! | AS74: =+IF(AO72<0,1-AS72/AO72,AS72/AO72-1) -> #DIV/0! | AT74: =+IF(AP72<0,1-AT72/AP72,AT72/AP72-1) -> #DIV/0! | ... CL74: =+IF(CH72<0,1-CL72/CH72,CL72/CH72-1) -> 0.099505449 | CM74: =+CM72/CI72-1 -> 0.07051669 | CN74: =+CN72/CJ72-1 -> 0.26894443 | CO74: =+CO72/CK72-1 -> 0.11085657 | CP74: =+CP72/CL72-1 -> 0.094665124 | CQ74: =+CQ72/CM72-1 -> 0.32420127 | CR74: =+CR72/CN72-1 -> 0.28471206 | CS74: =+CS72/CO72-1 -> 0.27286443 | CT74: =+CT72/CP72-1 -> 0.22260739 | ... DB74: =+DB72/CX72-1 -> 0.212766 | DF74: 0.020450041
A75: PAT QOQ% | AJ75: =+IF(AI72<0,1-AJ72/AI72,AJ72/AI72-1) -> #DIV/0! | AK75: =+IF(AJ72<0,1-AK72/AJ72,AK72/AJ72-1) -> #DIV/0! | AL75: =+IF(AK72<0,1-AL72/AK72,AL72/AK72-1) -> #DIV/0! | AM75: =+IF(AL72<0,1-AM72/AL72,AM72/AL72-1) -> #DIV/0! | AN75: =+IF(AM72<0,1-AN72/AM72,AN72/AM72-1) -> #DIV/0! | AO75: =+IF(AN72<0,1-AO72/AN72,AO72/AN72-1) -> #DIV/0! | AP75: =+IF(AO72<0,1-AP72/AO72,AP72/AO72-1) -> #DIV/0! | AQ75: =+IF(AP72<0,1-AQ72/AP72,AQ72/AP72-1) -> #DIV/0! | ... CL75: =+IF(CK72<0,1-CL72/CK72,CL72/CK72-1) -> 0.041180042 | CM75: =+CM72/CL72-1 -> -0.091711181 | CN75: =+CN72/CM72-1 -> 0.14107846 | CO75: =+CO72/CN72-1 -> 0.029420177 | CP75: =+CP72/CO72-1 -> 0.026004175 | CQ75: =+CQ72/CP72-1 -> 0.098744431 | CR75: =+CR72/CQ72-1 -> 0.10705019 | CS75: =+CS72/CR72-1 -> 0.019926849 | CT75: =+CT72/CS72-1 -> -0.01450598 | ... DB75: =+DB72/DA72-1 -> 0.027156049 | DF75: -0.033681718
A76: Minority Interest | B76: ='Annual Raw'!C32 -> 0 | C76: ='Annual Raw'!D32 -> 0 | D76: ='Annual Raw'!E32 -> 0 | E76: ='Annual Raw'!F32 -> 0 | F76: ='Annual Raw'!G32 -> 0 | G76: ='Annual Raw'!H32 -> 0 | H76: ='Annual Raw'!I32 -> 0 | I76: ='Annual Raw'!J32 -> 0 | ... AA76: ='Annual Raw'!AB32 -> 0 | AB76: =+SUM(CM76:CP76) -> 0 | AC76: =+SUM(CQ76:CT76) -> 0 | AD76: =+SUM(CU76:CX76) -> 0 | AE76: =+SUM(CY76:DB76) -> 0 | AI76: ='QTR Raw'!C34 -> 0 | AJ76: ='QTR Raw'!D34 -> 0 | AK76: ='QTR Raw'!E34 -> 0 | AL76: ='QTR Raw'!F34 -> 0 | AM76: ='QTR Raw'!G34 -> 0 | AN76: ='QTR Raw'!H34 -> 0 | AO76: ='QTR Raw'!I34 -> 0 | AP76: ='QTR Raw'!J34 -> 0 | ... CL76: ='QTR Raw'!BF34 -> 0 | CM76: =+CL76 -> 0 | CN76: =+CM76 -> 0 | CO76: =+CN76 -> 0 | CP76: =+CO76 -> 0 | CQ76: =+CP76 -> 0 | CR76: =+CQ76 -> 0 | CS76: =+CR76 -> 0 | CT76: =+CS76 -> 0 | ... DB76: =+DA76 -> 0 | DF76: 0
A77: Share of Associate | B77: ='Annual Raw'!C33+'Annual Raw'!C28 -> 0 | C77: ='Annual Raw'!D33+'Annual Raw'!D28 -> 0 | D77: ='Annual Raw'!E33+'Annual Raw'!E28 -> 0 | E77: ='Annual Raw'!F33+'Annual Raw'!F28 -> 0 | F77: ='Annual Raw'!G33+'Annual Raw'!G28 -> 0 | G77: ='Annual Raw'!H33+'Annual Raw'!H28 -> 0 | H77: ='Annual Raw'!I33+'Annual Raw'!I28 -> 0 | I77: ='Annual Raw'!J33+'Annual Raw'!J28 -> 0 | ... AA77: ='Annual Raw'!AB33+'Annual Raw'!AB28 -> 0 | AB77: =+SUM(CM77:CP77) -> 0 | AC77: =+SUM(CQ77:CT77) -> 0 | AD77: =+SUM(CU77:CX77) -> 0 | AE77: =+SUM(CY77:DB77) -> 0 | AI77: ='QTR Raw'!C35 -> 0 | AJ77: ='QTR Raw'!D35 -> 0 | AK77: ='QTR Raw'!E35 -> 0 | AL77: ='QTR Raw'!F35 -> 0 | AM77: ='QTR Raw'!G35 -> 0 | AN77: ='QTR Raw'!H35 -> 0 | AO77: ='QTR Raw'!I35 -> 0 | AP77: ='QTR Raw'!J35 -> 0 | ... CL77: ='QTR Raw'!BF35 -> 0 | CM77: =+CL77 -> 0 | CN77: =+CM77 -> 0 | CO77: =+CN77 -> 0 | CP77: =+CO77 -> 0 | CQ77: =+CP77 -> 0 | CR77: =+CQ77 -> 0 | CS77: =+CR77 -> 0 | CT77: =+CS77 -> 0 | ... DB77: =+DA77 -> 0 | DF77: 0
A78: Exceptional Income / Expenses | B78: ='Annual Raw'!C29+'Annual Raw'!C31+'Annual Raw'!C34+'Annual Raw'!C36 -> 0 | C78: ='Annual Raw'!D29+'Annual Raw'!D31+'Annual Raw'!D34+'Annual Raw'!D36 -> 0 | D78: ='Annual Raw'!E29+'Annual Raw'!E31+'Annual Raw'!E34+'Annual Raw'!E36 -> 0 | E78: ='Annual Raw'!F29+'Annual Raw'!F31+'Annual Raw'!F34+'Annual Raw'!F36 -> 0 | F78: ='Annual Raw'!G29+'Annual Raw'!G31+'Annual Raw'!G34+'Annual Raw'!G36 -> 0 | G78: ='Annual Raw'!H29+'Annual Raw'!H31+'Annual Raw'!H34+'Annual Raw'!H36 -> 0 | H78: ='Annual Raw'!I29+'Annual Raw'!I31+'Annual Raw'!I34+'Annual Raw'!I36 -> 0 | I78: ='Annual Raw'!J29+'Annual Raw'!J31+'Annual Raw'!J34+'Annual Raw'!J36 -> 0 | ... AA78: ='Annual Raw'!AB29+'Annual Raw'!AB31+'Annual Raw'!AB34+'Annual Raw'!AB36 -> -3.2791 | AB78: =+SUM(CM78:CP78) -> 0 | AC78: =+SUM(CQ78:CT78) -> 0 | AD78: =+SUM(CU78:CX78) -> 0 | AE78: =+SUM(CY78:DB78) -> 0 | AI78: ='QTR Raw'!C26+'QTR Raw'!C31+'QTR Raw'!C32+'QTR Raw'!C33+'QTR Raw'!C36+'QTR Raw'!C37+'QTR Raw'!C39 -> 0 | AJ78: ='QTR Raw'!D26+'QTR Raw'!D31+'QTR Raw'!D32+'QTR Raw'!D33+'QTR Raw'!D36+'QTR Raw'!D37+'QTR Raw'!D39 -> 0 | AK78: ='QTR Raw'!E26+'QTR Raw'!E31+'QTR Raw'!E32+'QTR Raw'!E33+'QTR Raw'!E36+'QTR Raw'!E37+'QTR Raw'!E39 -> 0 | AL78: ='QTR Raw'!F26+'QTR Raw'!F31+'QTR Raw'!F32+'QTR Raw'!F33+'QTR Raw'!F36+'QTR Raw'!F37+'QTR Raw'!F39 -> 0 | AM78: ='QTR Raw'!G26+'QTR Raw'!G31+'QTR Raw'!G32+'QTR Raw'!G33+'QTR Raw'!G36+'QTR Raw'!G37+'QTR Raw'!G39 -> 0 | AN78: ='QTR Raw'!H26+'QTR Raw'!H31+'QTR Raw'!H32+'QTR Raw'!H33+'QTR Raw'!H36+'QTR Raw'!H37+'QTR Raw'!H39 -> 0 | AO78: ='QTR Raw'!I26+'QTR Raw'!I31+'QTR Raw'!I32+'QTR Raw'!I33+'QTR Raw'!I36+'QTR Raw'!I37+'QTR Raw'!I39 -> 0 | AP78: ='QTR Raw'!J26+'QTR Raw'!J31+'QTR Raw'!J32+'QTR Raw'!J33+'QTR Raw'!J36+'QTR Raw'!J37+'QTR Raw'!J39 -> 0 | ... CL78: ='QTR Raw'!BF26+'QTR Raw'!BF31+'QTR Raw'!BF32+'QTR Raw'!BF33+'QTR Raw'!BF36+'QTR Raw'!BF37+'QTR Raw'!BF39 -> 3.206 | DF78: -3.28
A79: Consolidated Net Profit | B79: =B72+B76+B77+B78 -> 4.1181095 | C79: =C72+C76+C77+C78 -> 5.1169923 | D79: =D72+D76+D77+D78 -> 3.6395476 | E79: =E72+E76+E77+E78 -> 3.7936077 | F79: =F72+F76+F77+F78 -> 5.252141 | G79: =G72+G76+G77+G78 -> 10.81822 | H79: =H72+H76+H77+H78 -> 20.294907 | I79: =I72+I76+I77+I78 -> 24.801879 | ... AE79: =AE72+AE76+AE77+AE78 -> 553.0464 | AI79: =AI72+AI76+AI77+AI78 -> 0 | AJ79: =AJ72+AJ76+AJ77+AJ78 -> 0 | AK79: =AK72+AK76+AK77+AK78 -> 0 | AL79: =AL72+AL76+AL77+AL78 -> 0 | AM79: =AM72+AM76+AM77+AM78 -> 0 | AN79: =AN72+AN76+AN77+AN78 -> 0 | AO79: =AO72+AO76+AO77+AO78 -> 0 | AP79: =AP72+AP76+AP77+AP78 -> 0 | ... DB79: =DB72+DB76+DB77+DB78 -> 145.04174 | DF79: 66.853764
A80: Profit & Loss- Annual (End)
AF81: =AC79*50 -> 18839.01
A82: Ace - PAT | B82: ='Annual Raw'!C35 -> 4.1181095 | C82: ='Annual Raw'!D35 -> 5.1169923 | D82: ='Annual Raw'!E35 -> 3.6395476 | E82: ='Annual Raw'!F35 -> 3.7936077 | F82: ='Annual Raw'!G35 -> 5.252141 | G82: ='Annual Raw'!H35 -> 10.81822 | H82: ='Annual Raw'!I35 -> 20.294907 | I82: ='Annual Raw'!J35 -> 24.801879 | ... AA82: ='Annual Raw'!AB35 -> 257.8884 | AB82: =+AB79 -> 295.78936 | AC82: =+AC79 -> 376.7802 | AD82: =+AD79 -> 444.08429 | AE82: =+AE79 -> 553.0464 | AI82: ='QTR Raw'!C42 -> 0 | AJ82: ='QTR Raw'!D42 -> 0 | AK82: ='QTR Raw'!E42 -> 0 | AL82: ='QTR Raw'!F42 -> 0 | AM82: ='QTR Raw'!G42 -> 0 | AN82: ='QTR Raw'!H42 -> 0 | AO82: ='QTR Raw'!I42 -> 0 | AP82: ='QTR Raw'!J42 -> 0 | ... CL82: ='QTR Raw'!BF42 -> 75.237 | DF82: 256.932
A83: Checksum - PAT | B83: =B82-B79 -> 0 | C83: =C82-C79 -> 0 | D83: =D82-D79 -> 8.8817842e-15 | E83: =E82-E79 -> 7.1054274e-15 | F83: =F82-F79 -> -7.1054274e-15 | G83: =G82-G79 -> 0 | H83: =H82-H79 -> 0 | I83: =I82-I79 -> 0 | ... AE83: =AE82-AE79 -> 0 | AI83: =AI82-AI79 -> 0 | AJ83: =AJ82-AJ79 -> 0 | AK83: =AK82-AK79 -> 0 | AL83: =AL82-AL79 -> 0 | AM83: =AM82-AM79 -> 0 | AN83: =AN82-AN79 -> 0 | AO83: =AO82-AO79 -> 0 | AP83: =AP82-AP79 -> 0 | ... CL83: =CL82-CL79 -> -0.002 | DF83: 0
A84: Ratios (Start)
A85: ROE (%) | B85: =(B79-B78)/B151 -> 0.24039403 | C85: =(C79-C78)/C151 -> 0.2577397 | D85: =(D79-D78)/D151 -> 0.17612332 | E85: =(E79-E78)/E151 -> 0.16327494 | F85: =(F79-F78)/F151 -> 0.20175879 | G85: =(G79-G78)/G151 -> 0.31469628 | H85: =(H79-H78)/H151 -> 0.40346155 | I85: =(I79-I78)/I151 -> 0.35545509 | ... AE85: =(AE79-AE78)/AE151 -> 0.19841587 | AL85: =(SUM(AI79:AL79)-SUM(AI78:AL78))/AL151 -> #DIV/0! | AM85: =(SUM(AJ79:AM79)-SUM(AJ78:AM78))/AM151 -> #DIV/0! | AN85: =(SUM(AK79:AN79)-SUM(AK78:AN78))/AN151 -> #DIV/0! | AO85: =(SUM(AL79:AO79)-SUM(AL78:AO78))/AO151 -> #DIV/0! | AP85: =(SUM(AM79:AP79)-SUM(AM78:AP78))/AP151 -> #DIV/0! | AQ85: =(SUM(AN79:AQ79)-SUM(AN78:AQ78))/AQ151 -> #DIV/0! | AR85: =(SUM(AO79:AR79)-SUM(AO78:AR78))/AR151 -> #DIV/0! | AS85: =(SUM(AP79:AS79)-SUM(AP78:AS78))/AS151 -> #DIV/0! | ... DB85: =(SUM(CY79:DB79)-SUM(CY78:DB78))/DB151 -> 0.19841587 | DF85: 0.23109128
A86: ROCE (%) | B86: =+B65/B160 -> 0.18435824 | C86: =+C65/C160 -> 0.27634044 | D86: =+D65/D160 -> 0.14327814 | E86: =+E65/E160 -> 0.20609483 | F86: =+F65/F160 -> 0.23898052 | G86: =+G65/G160 -> 0.43403097 | H86: =+H65/H160 -> 0.51691943 | I86: =+I65/I160 -> 0.41212764 | ... AE86: =+AE65/AE160 -> 0.22639874 | AL86: =+SUM(AI65:AL65)/AL160 -> #DIV/0! | AM86: =+SUM(AJ65:AM65)/AM160 -> #DIV/0! | AN86: =+SUM(AK65:AN65)/AN160 -> #DIV/0! | AO86: =+SUM(AL65:AO65)/AO160 -> #DIV/0! | AP86: =+SUM(AM65:AP65)/AP160 -> #DIV/0! | AQ86: =+SUM(AN65:AQ65)/AQ160 -> #DIV/0! | AR86: =+SUM(AO65:AR65)/AR160 -> #DIV/0! | AS86: =+SUM(AP65:AS65)/AS160 -> #DIV/0! | ... DB86: =+SUM(CY65:DB65)/DB160 -> 0.22639874 | DF86: 0.25673261
A87: Ratios (End)
A88: Checksum Of qtr to Annual
A89: Revenue - Checksum Of qtr to Annual | N89: =N41-SUM(AI41:AL41) -> 371.47085 | O89: =O41-SUM(AM41:AP41) -> 308.78476 | P89: =P41-SUM(AQ41:AT41) -> 318.96135 | Q89: =Q41-SUM(AU41:AX41) -> 460.03402 | R89: =R41-SUM(AY41:BB41) -> 432.77876 | S89: =S41-SUM(BC41:BF41) -> 559.46649 | T89: =T41-SUM(BG41:BJ41) -> 643.48971 | U89: =U41-SUM(BK41:BN41) -> 649.05824 | V89: =V41-SUM(BO41:BR41) -> 594.7379 | W89: =W41-SUM(BS41:BV41) -> 782.711 | X89: =X41-SUM(BW41:BZ41) -> 486.8013 | Y89: =Y41-SUM(CA41:CD41) -> 0.0005 | Z89: =Z41-SUM(CE41:CH41) -> -0.0004 | AA89: =AA41-SUM(CF41:CI41) -> 237.8509 | AB89: =AB41-SUM(CM41:CP41) -> 0 | AC89: =AC41-SUM(CQ41:CT41) -> 0 | AD89: =AD41-SUM(CU41:CX41) -> 0 | AE89: =AE41-SUM(CY41:DB41) -> 0 | DF89: 0
A90: GP - Checksum Of qtr to Annual | N90: =N47-SUM(AI47:AL47) -> 186.49379 | O90: =O47-SUM(AM47:AP47) -> 175.78427 | P90: =P47-SUM(AQ47:AT47) -> 170.01335 | Q90: =Q47-SUM(AU47:AX47) -> 247.6023 | R90: =R47-SUM(AY47:BB47) -> 246.64556 | S90: =S47-SUM(BC47:BF47) -> 381.24624 | T90: =T47-SUM(BG47:BJ47) -> 403.23421 | U90: =U47-SUM(BK47:BN47) -> 365.68857 | V90: =V47-SUM(BO47:BR47) -> 346.9846 | W90: =W47-SUM(BS47:BV47) -> 445.004 | X90: =X47-SUM(BW47:BZ47) -> 267.9125 | Y90: =Y47-SUM(CA47:CD47) -> 0.5437 | Z90: =Z47-SUM(CE47:CH47) -> -0.0004 | AA90: =AA47-SUM(CF47:CI47) -> 111.1981 | AB90: =AB47-SUM(CM47:CP47) -> 0 | AC90: =AC47-SUM(CQ47:CT47) -> 0 | AD90: =AD47-SUM(CU47:CX47) -> 0 | AE90: =AE47-SUM(CY47:DB47) -> 0 | DF90: 0
A91: EBITDA - Checksum Of qtr to Annual | N91: =N59-SUM(AI59:AL59) -> 81.459244 | O91: =O59-SUM(AM59:AP59) -> 40.76986 | P91: =P59-SUM(AQ59:AT59) -> 33.146941 | Q91: =Q59-SUM(AU59:AX59) -> -17.810021 | R91: =R59-SUM(AY59:BB59) -> 10.783204 | S91: =S59-SUM(BC59:BF59) -> 36.321285 | T91: =T59-SUM(BG59:BJ59) -> 143.51492 | U91: =U59-SUM(BK59:BN59) -> 132.81059 | V91: =V59-SUM(BO59:BR59) -> 128.8841 | W91: =W59-SUM(BS59:BV59) -> 167.629 | X91: =X59-SUM(BW59:BZ59) -> 112.0509 | Y91: =Y59-SUM(CA59:CD59) -> 0.0013 | Z91: =Z59-SUM(CE59:CH59) -> 0.0001 | AA91: =AA59-SUM(CF59:CI59) -> 49.9928 | AB91: =AB59-SUM(CM59:CP59) -> 0 | AC91: =AC59-SUM(CQ59:CT59) -> 0 | AD91: =AD59-SUM(CU59:CX59) -> 0 | AE91: =AE59-SUM(CY59:DB59) -> 0 | DF91: 0
A92: PAT - Checksum Of qtr to Annual | N92: =N79-SUM(AI79:AL79) -> 44.512796 | O92: =O79-SUM(AM79:AP79) -> 20.454212 | P92: =P79-SUM(AQ79:AT79) -> 15.787643 | Q92: =Q79-SUM(AU79:AX79) -> -64.5732 | R92: =R79-SUM(AY79:BB79) -> -37.530795 | S92: =S79-SUM(BC79:BF79) -> 1.3419823 | T92: =T79-SUM(BG79:BJ79) -> 192.83133 | U92: =U79-SUM(BK79:BN79) -> 98.24924 | V92: =V79-SUM(BO79:BR79) -> 98.0805 | W92: =W72-SUM(BS72:BV72) -> 130.498 | X92: =X72-SUM(BW72:BZ72) -> 83.4371 | Y92: =Y72-SUM(CA72:CD72) -> 0.0003 | Z92: =Z72-SUM(CE72:CH72) -> 0.0011 | AA92: =AA72-SUM(CF72:CI72) -> 33.8325 | AB92: =AB72-SUM(CM72:CP72) -> 0 | AC92: =AC72-SUM(CQ72:CT72) -> 0 | AD92: =AD72-SUM(CU72:CX72) -> 0 | AE92: =AE72-SUM(CY72:DB72) -> 0 | DF92: 0
A93: Valuation (Start)
A94: Eq | B94: ='Annual Raw'!C104 -> 4.338175 | C94: ='Annual Raw'!D104 -> 4.338175 | D94: ='Annual Raw'!E104 -> 4.338175 | E94: =+F94 -> 0 | F94: =+G94 -> 0 | G94: =+H94 -> 0 | H94: =+I94 -> 0 | I94: =+J94 -> 0 | J94: =+K94 -> 0 | K94: =+L94 -> 0 | L94: =+M94 -> 0 | ... AA94: =+AB94 -> 0 | AB94: =AA94 -> 0 | AC94: =AB94 -> 0 | AD94: =AC94 -> 0 | AE94: =AD94 -> 0 | AI94: =+AJ94 -> 18.153 | AJ94: =+AK94 -> 18.153 | AK94: =+AL94 -> 18.153 | AL94: =+AM94 -> 18.153 | AM94: =+AN94 -> 18.153 | AN94: =+AO94 -> 18.153 | AO94: =+AP94 -> 18.153 | AP94: =+AQ94 -> 18.153 | ... CI94: =+CJ94 -> 18.153 | CJ94: ='QTR Raw'!BD45 -> 18.153 | CK94: ='QTR Raw'!BE45 -> 18.153 | CL94: ='QTR Raw'!BF45 -> 18.153 | CM94: =+CL94 -> 18.153 | CN94: =+CM94 -> 18.153 | CO94: =+CN94 -> 18.153 | CP94: =+CO94 -> 18.153 | CQ94: =+CP94 -> 18.153 | CR94: =+CQ94 -> 18.153 | CS94: =+CR94 -> 18.153 | CT94: =+CS94 -> 18.153 | ... DB94: =+DA94 -> 18.153 | DF94: 18.153
A95: FV | B95: ='Annual Raw'!C105 -> 10 | C95: ='Annual Raw'!D105 -> 10 | D95: ='Annual Raw'!E105 -> 10 | E95: =+F95 -> 0 | F95: =+G95 -> 0 | G95: =+H95 -> 0 | H95: =+I95 -> 0 | I95: =+J95 -> 0 | J95: =+K95 -> 0 | K95: =+L95 -> 0 | L95: =+M95 -> 0 | ... AA95: =+AB95 -> 0 | AB95: =AA95 -> 0 | AC95: =AB95 -> 0 | AD95: =AC95 -> 0 | AE95: =AD95 -> 0 | AI95: =AJ95 -> 2 | AJ95: =AK95 -> 2 | AK95: =AL95 -> 2 | AL95: =AM95 -> 2 | AM95: =AN95 -> 2 | AN95: =AO95 -> 2 | AO95: =AP95 -> 2 | AP95: =AQ95 -> 2 | ... CI95: =CJ95 -> 2 | CJ95: ='QTR Raw'!BD46 -> 2 | CK95: ='QTR Raw'!BE46 -> 2 | CL95: ='QTR Raw'!BF46 -> 2 | CM95: =+CL95 -> 2 | CN95: =+CM95 -> 2 | CO95: =+CN95 -> 2 | CP95: =+CO95 -> 2 | CQ95: =+CP95 -> 2 | CR95: =+CQ95 -> 2 | CS95: =+CR95 -> 2 | CT95: =+CS95 -> 2 | ... DB95: =+DA95 -> 2 | DF95: 2
A96: No of share | B96: =B94/B95 -> 0.4338175 | C96: =C94/C95 -> 0.4338175 | D96: =D94/D95 -> 0.4338175 | E96: =E94/E95 -> #DIV/0! | F96: =F94/F95 -> #DIV/0! | G96: =G94/G95 -> #DIV/0! | H96: =H94/H95 -> #DIV/0! | I96: =I94/I95 -> #DIV/0! | ... AE96: =AE94/AE95 -> #DIV/0! | AI96: =AI94/AI95 -> 9.0765 | AJ96: =AJ94/AJ95 -> 9.0765 | AK96: =AK94/AK95 -> 9.0765 | AL96: =AL94/AL95 -> 9.0765 | AM96: =AM94/AM95 -> 9.0765 | AN96: =AN94/AN95 -> 9.0765 | AO96: =AO94/AO95 -> 9.0765 | AP96: =AP94/AP95 -> 9.0765 | ... DB96: =DB94/DB95 -> 9.0765 | DF96: 9.0765
A97: EPS | B97: =(B79-B78)/B96 -> 9.4927233 | C97: =(C79-C78)/C96 -> 11.795265 | D97: =(D79-D78)/D96 -> 8.3895823 | E97: =(E79-E78)/E96 -> #DIV/0! | F97: =(F79-F78)/F96 -> #DIV/0! | G97: =(G79-G78)/G96 -> #DIV/0! | H97: =(H79-H78)/H96 -> #DIV/0! | I97: =(I79-I78)/I96 -> #DIV/0! | ... AE97: =(AE79-AE78)/AE96 -> #DIV/0! | AI97: =(AI79-AI78)/AI96 -> 0 | AJ97: =(AJ79-AJ78)/AJ96 -> 0 | AK97: =(AK79-AK78)/AK96 -> 0 | AL97: =(AL79-AL78)/AL96 -> 0 | AM97: =(AM79-AM78)/AM96 -> 0 | AN97: =(AN79-AN78)/AN96 -> 0 | AO97: =(AO79-AO78)/AO96 -> 0 | AP97: =(AP79-AP78)/AP96 -> 0 | ... DB97: =(DB79-DB78)/DB96 -> 15.97992 | DF97: 7.3655885
A98: DPS | B98: ='Annual Raw'!C110 -> 0.125 | C98: ='Annual Raw'!D110 -> 0.25 | D98: ='Annual Raw'!E110 -> 0.1 | E98: ='Annual Raw'!F110 -> 0.125 | F98: ='Annual Raw'!G110 -> 0.25 | G98: ='Annual Raw'!H110 -> 0.25 | H98: ='Annual Raw'!I110 -> 0.25 | I98: ='Annual Raw'!J110 -> 0.5 | ... AA98: ='Annual Raw'!AB110 -> 2
A99: DPS % of EPS | B99: =B98/B97 -> 0.013167981 | C99: =C98/C97 -> 0.021194946 | D99: =D98/D97 -> 0.011919545 | E99: =E98/E97 -> #DIV/0! | F99: =F98/F97 -> #DIV/0! | G99: =G98/G97 -> #DIV/0! | H99: =H98/H97 -> #DIV/0! | I99: =I98/I97 -> #DIV/0! | ... AE99: =AE98/AE97 -> #DIV/0! | DF99: 0
A100: EPS TTM | B100: =+B97 -> 9.4927233 | C100: =+C97 -> 11.795265 | D100: =+D97 -> 8.3895823 | E100: =+E97 -> #DIV/0! | F100: =+F97 -> #DIV/0! | G100: =+G97 -> #DIV/0! | H100: =+H97 -> #DIV/0! | I100: =+I97 -> #DIV/0! | ... AE100: =+AE97 -> #DIV/0! | AL100: =SUM(AI97:AL97) -> 0 | AM100: =SUM(AJ97:AM97) -> 0 | AN100: =SUM(AK97:AN97) -> 0 | AO100: =SUM(AL97:AO97) -> 0 | AP100: =SUM(AM97:AP97) -> 0 | AQ100: =SUM(AN97:AQ97) -> 0 | AR100: =SUM(AO97:AR97) -> 0 | AS100: =SUM(AP97:AS97) -> 0 | ... DB100: =SUM(CY97:DB97) -> 60.93168 | DF100: 28.203467
A101: EPS Growth YoY % | C101: =+C100/B100-1 -> 0.24255858 | D101: =+D100/C100-1 -> -0.28873303 | E101: =+E100/D100-1 -> #DIV/0! | F101: =+F100/E100-1 -> #DIV/0! | G101: =+G100/F100-1 -> #DIV/0! | H101: =+H100/G100-1 -> #DIV/0! | I101: =+I100/H100-1 -> #DIV/0! | J101: =+J100/I100-1 -> #DIV/0! | ... AE101: =+AE100/AD100-1 -> #DIV/0! | AP101: =+IF(AL100<0,1-AP100/AL100,AP100/AL100-1) -> #DIV/0! | AQ101: =+IF(AM100<0,1-AQ100/AM100,AQ100/AM100-1) -> #DIV/0! | AR101: =+IF(AN100<0,1-AR100/AN100,AR100/AN100-1) -> #DIV/0! | AS101: =+IF(AO100<0,1-AS100/AO100,AS100/AO100-1) -> #DIV/0! | AT101: =+IF(AP100<0,1-AT100/AP100,AT100/AP100-1) -> #DIV/0! | AU101: =+IF(AQ100<0,1-AU100/AQ100,AU100/AQ100-1) -> #DIV/0! | AV101: =+IF(AR100<0,1-AV100/AR100,AV100/AR100-1) -> #DIV/0! | AW101: =+IF(AS100<0,1-AW100/AS100,AW100/AS100-1) -> #DIV/0! | ... DB101: =+IF(CX100<0,1-DB100/CX100,DB100/CX100-1) -> 0.24536357 | DF101: 0.16967291
A102: Bloomberg Estimate | CP102: 35.3 | CT102: 42.4 | CX102: 49.2
A103: Estimate deviation | CP103: =CP100/CP102-1 -> -0.076813535 | CT103: =CT100/CT102-1 -> -0.020952414 | CX103: =CX100/CX102-1 -> -0.0055524207
A104: Promoter Share holding % | B104: ='Annual Raw'!C112 -> 0 | C104: ='Annual Raw'!D112 -> 0 | D104: ='Annual Raw'!E112 -> 0 | E104: ='Annual Raw'!F112 -> 0 | F104: ='Annual Raw'!G112 -> 0 | G104: ='Annual Raw'!H112 -> 0 | H104: ='Annual Raw'!I112 -> 0 | I104: ='Annual Raw'!J112 -> 0 | ... AA104: ='Annual Raw'!AB112 -> 75 | AI104: ='QTR Raw'!C49 -> 0 | AJ104: ='QTR Raw'!D49 -> 0 | AK104: ='QTR Raw'!E49 -> 0 | AL104: ='QTR Raw'!F49 -> 0 | AM104: ='QTR Raw'!G49 -> 0 | AN104: ='QTR Raw'!H49 -> 0 | AO104: ='QTR Raw'!I49 -> 0 | AP104: ='QTR Raw'!J49 -> 0 | ... CL104: ='QTR Raw'!BF49 -> 75
A105: Pledge Share % | B105: ='Annual Raw'!C113 -> 0 | C105: ='Annual Raw'!D113 -> 0 | D105: ='Annual Raw'!E113 -> 0 | E105: ='Annual Raw'!F113 -> 0 | F105: ='Annual Raw'!G113 -> 0 | G105: ='Annual Raw'!H113 -> 0 | H105: ='Annual Raw'!I113 -> 0 | I105: ='Annual Raw'!J113 -> 0 | ... AA105: ='Annual Raw'!AB113 -> 0 | AI105: ='QTR Raw'!C50 -> 0 | AJ105: ='QTR Raw'!D50 -> 0 | AK105: ='QTR Raw'!E50 -> 0 | AL105: ='QTR Raw'!F50 -> 0 | AM105: ='QTR Raw'!G50 -> 0 | AN105: ='QTR Raw'!H50 -> 0 | AO105: ='QTR Raw'!I50 -> 0 | AP105: ='QTR Raw'!J50 -> 0 | ... CL105: ='QTR Raw'!BF50 -> 0
A107: Share Price
A108: Share Price - Close | B108: ='Annual Raw'!C106 -> 0 | C108: ='Annual Raw'!D106 -> 0 | D108: ='Annual Raw'!E106 -> 0 | E108: ='Annual Raw'!F106 -> 0 | F108: ='Annual Raw'!G106 -> 0 | G108: ='Annual Raw'!H106 -> 0 | H108: ='Annual Raw'!I106 -> 0 | I108: ='Annual Raw'!J106 -> 0 | ... AA108: ='Annual Raw'!AB106 -> 1172.75 | AB108: =+CP108 -> 1520 | AC108: =+CT108 -> 1520 | AD108: =+CX108 -> 1520 | AE108: =+DB108 -> 1520 | AJ108: ='QTR Share Price'!HP21 -> 0 | AK108: ='QTR Share Price'!HQ21 -> 0 | AL108: ='QTR Share Price'!HR21 -> 0 | AM108: ='QTR Share Price'!HS21 -> 0 | AN108: ='QTR Share Price'!HT21 -> 0 | AO108: ='QTR Share Price'!HU21 -> 0 | AP108: ='QTR Share Price'!HV21 -> 0 | AQ108: ='QTR Share Price'!HW21 -> 0 | ... CL108: ='QTR Share Price'!JR21 -> 1172.75 | CM108: 1520 | CN108: =+CM108 -> 1520 | CO108: =+CN108 -> 1520 | CP108: =+CO108 -> 1520 | CQ108: =+CP108 -> 1520 | CR108: =+CQ108 -> 1520 | CS108: =+CR108 -> 1520 | CT108: =+CS108 -> 1520 | CU108: =+CT108 -> 1520 | ... DB108: =+DA108 -> 1520 | DF108: 1200
...

Sheet Sheet1
A46: Exports Countrywise break up
A47: North America | B47: 0.32
A48: Export to others | B48: 0.31
A49: Europe | B49: 0.23
A50: South America | B50: 0.14
C56: 2022 | D56: 2023 | E56: 2024 | F56: 2025 | G56: 2026
C57: 20 | D57: 244 | E57: 349 | F57: 607 | G57: 71 | H57: =SUM(C57:G57) -> 1291
C58: 10 | G58: 55

Sheet QTR Raw
A1: ='Annual Raw'!A1 -> 208433 | B1: X | C1: 201206 | D1: 201209 | E1: 201212 | F1: 201303 | G1: 201306 | H1: 201309 | I1: 201312 | J1: 201403 | K1: 201406 | L1: 201409 | M1: 201412 | N1: 201503 | O1: 201506 | P1: 201509 | Q1: 201512 | R1: 201603 | S1: 201606 | T1: 201609 | U1: 201612 | V1: 201703 | W1: 201706 | X1: 201709 | Y1: 201712 | Z1: 201803 | AA1: 201806 | AB1: 201809 | AC1: 201812 | AD1: 201903 | AE1: 201906 | AF1: 201909 | AG1: 201912 | AH1: 202003 | AI1: 202006 | AJ1: 202009 | AK1: 202012 | AL1: 202103 | AM1: 202106 | AN1: 202109 | AO1: 202112 | AP1: 202203 | AQ1: 202206 | AR1: 202209 | AS1: 202212 | AT1: 202303 | AU1: 202306 | AV1: 202309 | AW1: 202312 | AX1: 202403 | AY1: 202406 | AZ1: 202409 | BA1: 202412 | BB1: 202503 | BC1: 202506 | BD1: 202509 | BE1: 202512 | BF1: 202603 | BG1: 202606 | BH1: 202609 | BI1: 202612 | BJ1: 202703 | BK1: 202706 | BL1: 202709 | BM1: 202712 | BN1: 202803 | BO1: 202806 | BP1: 202809 | BQ1: 202812 | BR1: 202903 | BS1: 202906 | BT1: 202909 | BU1: 202912 | BV1: 203003
A3: Field Description | B3: Field Name
A4: Company Name | B4: CD_COMPNAME | C4: =_xll.EQNXTDZ(A1,B4,C1) -> Inox India Ltd.
A5: Date End | B5: QTR_DATE_END | C5: =_xll.EQNXTDZ($A$1,$B5,C$1,$B$1) -> 0 | D5: =_xll.EQNXTDZ($A$1,$B5,D$1,$B$1) -> 0 | E5: =_xll.EQNXTDZ($A$1,$B5,E$1,$B$1) -> 0 | F5: =_xll.EQNXTDZ($A$1,$B5,F$1,$B$1) -> 0 | G5: =_xll.EQNXTDZ($A$1,$B5,G$1,$B$1) -> 0 | H5: =_xll.EQNXTDZ($A$1,$B5,H$1,$B$1) -> 0 | I5: =_xll.EQNXTDZ($A$1,$B5,I$1,$B$1) -> 0 | J5: =_xll.EQNXTDZ($A$1,$B5,J$1,$B$1) -> 0 | ... BV5: =_xll.EQNXTDZ($A$1,$B5,BV$1,$B$1) -> 0
A6: Gross Sales | B6: QTR_GROSS_SALE | C6: =_xll.EQNXTDZ($A$1,$B6,C$1,$B$1) -> 0 | D6: =_xll.EQNXTDZ($A$1,$B6,D$1,$B$1) -> 0 | E6: =_xll.EQNXTDZ($A$1,$B6,E$1,$B$1) -> 0 | F6: =_xll.EQNXTDZ($A$1,$B6,F$1,$B$1) -> 0 | G6: =_xll.EQNXTDZ($A$1,$B6,G$1,$B$1) -> 0 | H6: =_xll.EQNXTDZ($A$1,$B6,H$1,$B$1) -> 0 | I6: =_xll.EQNXTDZ($A$1,$B6,I$1,$B$1) -> 0 | J6: =_xll.EQNXTDZ($A$1,$B6,J$1,$B$1) -> 0 | ... BV6: =_xll.EQNXTDZ($A$1,$B6,BV$1,$B$1) -> 0
A7: Less: Excise Duty | B7: QTR_EXCISE_DUTY | C7: =_xll.EQNXTDZ($A$1,$B7,C$1,$B$1) -> 0 | D7: =_xll.EQNXTDZ($A$1,$B7,D$1,$B$1) -> 0 | E7: =_xll.EQNXTDZ($A$1,$B7,E$1,$B$1) -> 0 | F7: =_xll.EQNXTDZ($A$1,$B7,F$1,$B$1) -> 0 | G7: =_xll.EQNXTDZ($A$1,$B7,G$1,$B$1) -> 0 | H7: =_xll.EQNXTDZ($A$1,$B7,H$1,$B$1) -> 0 | I7: =_xll.EQNXTDZ($A$1,$B7,I$1,$B$1) -> 0 | J7: =_xll.EQNXTDZ($A$1,$B7,J$1,$B$1) -> 0 | ... BV7: =_xll.EQNXTDZ($A$1,$B7,BV$1,$B$1) -> 0
A8: Other operating income | B8: QTR_JOB_WORKS | C8: =_xll.EQNXTDZ($A$1,$B8,C$1,$B$1) -> 0 | D8: =_xll.EQNXTDZ($A$1,$B8,D$1,$B$1) -> 0 | E8: =_xll.EQNXTDZ($A$1,$B8,E$1,$B$1) -> 0 | F8: =_xll.EQNXTDZ($A$1,$B8,F$1,$B$1) -> 0 | G8: =_xll.EQNXTDZ($A$1,$B8,G$1,$B$1) -> 0 | H8: =_xll.EQNXTDZ($A$1,$B8,H$1,$B$1) -> 0 | I8: =_xll.EQNXTDZ($A$1,$B8,I$1,$B$1) -> 0 | J8: =_xll.EQNXTDZ($A$1,$B8,J$1,$B$1) -> 0 | ... BV8: =_xll.EQNXTDZ($A$1,$B8,BV$1,$B$1) -> 0
A9: Net Sales & Other Operating Income | B9: QTR_NET_SALES | C9: =_xll.EQNXTDZ($A$1,$B9,C$1,$B$1) -> 0 | D9: =_xll.EQNXTDZ($A$1,$B9,D$1,$B$1) -> 0 | E9: =_xll.EQNXTDZ($A$1,$B9,E$1,$B$1) -> 0 | F9: =_xll.EQNXTDZ($A$1,$B9,F$1,$B$1) -> 0 | G9: =_xll.EQNXTDZ($A$1,$B9,G$1,$B$1) -> 0 | H9: =_xll.EQNXTDZ($A$1,$B9,H$1,$B$1) -> 0 | I9: =_xll.EQNXTDZ($A$1,$B9,I$1,$B$1) -> 0 | J9: =_xll.EQNXTDZ($A$1,$B9,J$1,$B$1) -> 0 | ... BV9: =_xll.EQNXTDZ($A$1,$B9,BV$1,$B$1) -> 0
A10: (Increase) / Decrease In Stocks | B10: QTR_INC_DEC_INVENTORY | C10: =_xll.EQNXTDZ($A$1,$B10,C$1,$B$1) -> 0 | D10: =_xll.EQNXTDZ($A$1,$B10,D$1,$B$1) -> 0 | E10: =_xll.EQNXTDZ($A$1,$B10,E$1,$B$1) -> 0 | F10: =_xll.EQNXTDZ($A$1,$B10,F$1,$B$1) -> 0 | G10: =_xll.EQNXTDZ($A$1,$B10,G$1,$B$1) -> 0 | H10: =_xll.EQNXTDZ($A$1,$B10,H$1,$B$1) -> 0 | I10: =_xll.EQNXTDZ($A$1,$B10,I$1,$B$1) -> 0 | J10: =_xll.EQNXTDZ($A$1,$B10,J$1,$B$1) -> 0 | ... BV10: =_xll.EQNXTDZ($A$1,$B10,BV$1,$B$1) -> 0
A11: Cost of Services & Raw Materials | B11: QTR_RAW_MATERIAL_COST | C11: =_xll.EQNXTDZ($A$1,$B11,C$1,$B$1) -> 0 | D11: =_xll.EQNXTDZ($A$1,$B11,D$1,$B$1) -> 0 | E11: =_xll.EQNXTDZ($A$1,$B11,E$1,$B$1) -> 0 | F11: =_xll.EQNXTDZ($A$1,$B11,F$1,$B$1) -> 0 | G11: =_xll.EQNXTDZ($A$1,$B11,G$1,$B$1) -> 0 | H11: =_xll.EQNXTDZ($A$1,$B11,H$1,$B$1) -> 0 | I11: =_xll.EQNXTDZ($A$1,$B11,I$1,$B$1) -> 0 | J11: =_xll.EQNXTDZ($A$1,$B11,J$1,$B$1) -> 0 | ... BV11: =_xll.EQNXTDZ($A$1,$B11,BV$1,$B$1) -> 0
A12: Purchase of Finished Goods | B12: QTR_PURCHASE_FIN_GOOD | C12: =_xll.EQNXTDZ($A$1,$B12,C$1,$B$1) -> 0 | D12: =_xll.EQNXTDZ($A$1,$B12,D$1,$B$1) -> 0 | E12: =_xll.EQNXTDZ($A$1,$B12,E$1,$B$1) -> 0 | F12: =_xll.EQNXTDZ($A$1,$B12,F$1,$B$1) -> 0 | G12: =_xll.EQNXTDZ($A$1,$B12,G$1,$B$1) -> 0 | H12: =_xll.EQNXTDZ($A$1,$B12,H$1,$B$1) -> 0 | I12: =_xll.EQNXTDZ($A$1,$B12,I$1,$B$1) -> 0 | J12: =_xll.EQNXTDZ($A$1,$B12,J$1,$B$1) -> 0 | ... BV12: =_xll.EQNXTDZ($A$1,$B12,BV$1,$B$1) -> 0
A13: Excise Duty | B13: QTR_EXCISE | C13: =_xll.EQNXTDZ($A$1,$B13,C$1,$B$1) -> 0 | D13: =_xll.EQNXTDZ($A$1,$B13,D$1,$B$1) -> 0 | E13: =_xll.EQNXTDZ($A$1,$B13,E$1,$B$1) -> 0 | F13: =_xll.EQNXTDZ($A$1,$B13,F$1,$B$1) -> 0 | G13: =_xll.EQNXTDZ($A$1,$B13,G$1,$B$1) -> 0 | H13: =_xll.EQNXTDZ($A$1,$B13,H$1,$B$1) -> 0 | I13: =_xll.EQNXTDZ($A$1,$B13,I$1,$B$1) -> 0 | J13: =_xll.EQNXTDZ($A$1,$B13,J$1,$B$1) -> 0 | ... BV13: =_xll.EQNXTDZ($A$1,$B13,BV$1,$B$1) -> 0
A14: Operating & Manufacturing Expenses | B14: QTR_MFG_EXPS | C14: =_xll.EQNXTDZ($A$1,$B14,C$1,$B$1) -> 0 | D14: =_xll.EQNXTDZ($A$1,$B14,D$1,$B$1) -> 0 | E14: =_xll.EQNXTDZ($A$1,$B14,E$1,$B$1) -> 0 | F14: =_xll.EQNXTDZ($A$1,$B14,F$1,$B$1) -> 0 | G14: =_xll.EQNXTDZ($A$1,$B14,G$1,$B$1) -> 0 | H14: =_xll.EQNXTDZ($A$1,$B14,H$1,$B$1) -> 0 | I14: =_xll.EQNXTDZ($A$1,$B14,I$1,$B$1) -> 0 | J14: =_xll.EQNXTDZ($A$1,$B14,J$1,$B$1) -> 0 | ... BV14: =_xll.EQNXTDZ($A$1,$B14,BV$1,$B$1) -> 0
A15: Electricity Power & Fuel Cost | B15: QTR_ELECTRICITY_POWER_FUEL | C15: =_xll.EQNXTDZ($A$1,$B15,C$1,$B$1) -> 0 | D15: =_xll.EQNXTDZ($A$1,$B15,D$1,$B$1) -> 0 | E15: =_xll.EQNXTDZ($A$1,$B15,E$1,$B$1) -> 0 | F15: =_xll.EQNXTDZ($A$1,$B15,F$1,$B$1) -> 0 | G15: =_xll.EQNXTDZ($A$1,$B15,G$1,$B$1) -> 0 | H15: =_xll.EQNXTDZ($A$1,$B15,H$1,$B$1) -> 0 | I15: =_xll.EQNXTDZ($A$1,$B15,I$1,$B$1) -> 0 | J15: =_xll.EQNXTDZ($A$1,$B15,J$1,$B$1) -> 0 | ... BV15: =_xll.EQNXTDZ($A$1,$B15,BV$1,$B$1) -> 0
A16: Employee Cost | B16: QTR_EXPLOYEE_COST | C16: =_xll.EQNXTDZ($A$1,$B16,C$1,$B$1) -> 0 | D16: =_xll.EQNXTDZ($A$1,$B16,D$1,$B$1) -> 0 | E16: =_xll.EQNXTDZ($A$1,$B16,E$1,$B$1) -> 0 | F16: =_xll.EQNXTDZ($A$1,$B16,F$1,$B$1) -> 0 | G16: =_xll.EQNXTDZ($A$1,$B16,G$1,$B$1) -> 0 | H16: =_xll.EQNXTDZ($A$1,$B16,H$1,$B$1) -> 0 | I16: =_xll.EQNXTDZ($A$1,$B16,I$1,$B$1) -> 0 | J16: =_xll.EQNXTDZ($A$1,$B16,J$1,$B$1) -> 0 | ... BV16: =_xll.EQNXTDZ($A$1,$B16,BV$1,$B$1) -> 0
... A42: Consolidated PAT(after extra items) | B42: QTR_CONS_PAT_EXITM | C42: =_xll.EQNXTDZ($A$1,$B42,C$1,$B$1) -> 0 | D42: =_xll.EQNXTDZ($A$1,$B42,D$1,$B$1) -> 0 | E42: =_xll.EQNXTDZ($A$1,$B42,E$1,$B$1) -> 0 | F42: =_xll.EQNXTDZ($A$1,$B42,F$1,$B$1) -> 0 | G42: =_xll.EQNXTDZ($A$1,$B42,G$1,$B$1) -> 0 | H42: =_xll.EQNXTDZ($A$1,$B42,H$1,$B$1) -> 0 | I42: =_xll.EQNXTDZ($A$1,$B42,I$1,$B$1) -> 0 | J42: =_xll.EQNXTDZ($A$1,$B42,J$1,$B$1) -> 0 | ... BV42: =_xll.EQNXTDZ($A$1,$B42,BV$1,$B$1) -> 0
A44: Field Description | B44: Field Name
A45: Equity Capital | B45: QTR_EQUITY_CAP | C45: =_xll.EQNXTDZ($A$1,$B45,C$1,$B$1) -> 0 | D45: =_xll.EQNXTDZ($A$1,$B45,D$1,$B$1) -> 0 | E45: =_xll.EQNXTDZ($A$1,$B45,E$1,$B$1) -> 0 | F45: =_xll.EQNXTDZ($A$1,$B45,F$1,$B$1) -> 0 | G45: =_xll.EQNXTDZ($A$1,$B45,G$1,$B$1) -> 0 | H45: =_xll.EQNXTDZ($A$1,$B45,H$1,$B$1) -> 0 | I45: =_xll.EQNXTDZ($A$1,$B45,I$1,$B$1) -> 0 | J45: =_xll.EQNXTDZ($A$1,$B45,J$1,$B$1) -> 0 | ... BV45: =_xll.EQNXTDZ($A$1,$B45,BV$1,$B$1) -> 0
A46: Face Value | B46: QTR_FV | C46: =_xll.EQNXTDZ($A$1,$B46,C$1,$B$1) -> 0 | D46: =_xll.EQNXTDZ($A$1,$B46,D$1,$B$1) -> 0 | E46: =_xll.EQNXTDZ($A$1,$B46,E$1,$B$1) -> 0 | F46: =_xll.EQNXTDZ($A$1,$B46,F$1,$B$1) -> 0 | G46: =_xll.EQNXTDZ($A$1,$B46,G$1,$B$1) -> 0 | H46: =_xll.EQNXTDZ($A$1,$B46,H$1,$B$1) -> 0 | I46: =_xll.EQNXTDZ($A$1,$B46,I$1,$B$1) -> 0 | J46: =_xll.EQNXTDZ($A$1,$B46,J$1,$B$1) -> 0 | ... BV46: =_xll.EQNXTDZ($A$1,$B46,BV$1,$B$1) -> 0
A47: Month End | B47: BMONTH_MONTHEND | C47: =_xll.EQNXTDZ($A$1,$B47,C$5) -> 0 | D47: =_xll.EQNXTDZ($A$1,$B47,D$5) -> 0 | E47: =_xll.EQNXTDZ($A$1,$B47,E$5) -> 0 | F47: =_xll.EQNXTDZ($A$1,$B47,F$5) -> 0 | G47: =_xll.EQNXTDZ($A$1,$B47,G$5) -> 0 | H47: =_xll.EQNXTDZ($A$1,$B47,H$5) -> 0 | I47: =_xll.EQNXTDZ($A$1,$B47,I$5) -> 0 | J47: =_xll.EQNXTDZ($A$1,$B47,J$5) -> 0 | ... BV47: =_xll.EQNXTDZ($A$1,$B47,BV$5) -> 0
A48: Close | B48: BMONTH_CLOSE | C48: =_xll.EQNXTDZ($A$1,$B48,C$5) -> 0 | D48: =_xll.EQNXTDZ($A$1,$B48,D$5) -> 0 | E48: =_xll.EQNXTDZ($A$1,$B48,E$5) -> 0 | F48: =_xll.EQNXTDZ($A$1,$B48,F$5) -> 0 | G48: =_xll.EQNXTDZ($A$1,$B48,G$5) -> 0 | H48: =_xll.EQNXTDZ($A$1,$B48,H$5) -> 0 | I48: =_xll.EQNXTDZ($A$1,$B48,I$5) -> 0 | J48: =_xll.EQNXTDZ($A$1,$B48,J$5) -> 0 | ... BV48: =_xll.EQNXTDZ($A$1,$B48,BV$5) -> 0
A49: Total of Promoter and Promoter Group | B49: SHP_TPFTOTALPROMOTER | C49: =_xll.EQNXTDZ($A$1,$B49,C$5) -> 0 | D49: =_xll.EQNXTDZ($A$1,$B49,D$5) -> 0 | E49: =_xll.EQNXTDZ($A$1,$B49,E$5) -> 0 | F49: =_xll.EQNXTDZ($A$1,$B49,F$5) -> 0 | G49: =_xll.EQNXTDZ($A$1,$B49,G$5) -> 0 | H49: =_xll.EQNXTDZ($A$1,$B49,H$5) -> 0 | I49: =_xll.EQNXTDZ($A$1,$B49,I$5) -> 0 | J49: =_xll.EQNXTDZ($A$1,$B49,J$5) -> 0 | ... BV49: =_xll.EQNXTDZ($A$1,$B49,BV$5) -> 0
A50: Total of Promoter and Promoter Group Pledged | B50: SHP_PSHFTOTALPROMOTER | C50: =_xll.EQNXTDZ($A$1,$B50,C$5) -> 0 | D50: =_xll.EQNXTDZ($A$1,$B50,D$5) -> 0 | E50: =_xll.EQNXTDZ($A$1,$B50,E$5) -> 0 | F50: =_xll.EQNXTDZ($A$1,$B50,F$5) -> 0 | G50: =_xll.EQNXTDZ($A$1,$B50,G$5) -> 0 | H50: =_xll.EQNXTDZ($A$1,$B50,H$5) -> 0 | I50: =_xll.EQNXTDZ($A$1,$B50,I$5) -> 0 | J50: =_xll.EQNXTDZ($A$1,$B50,J$5) -> 0 | ... BV50: =_xll.EQNXTDZ($A$1,$B50,BV$5) -> 0
A54: Field Description | B54: Field Name | C54: =_xll.EQNXTDZ($A$1,$B54,C$5) -> 0 | D54: =_xll.EQNXTDZ($A$1,$B54,D$5) -> 0 | E54: =_xll.EQNXTDZ($A$1,$B54,E$5) -> 0 | F54: =_xll.EQNXTDZ($A$1,$B54,F$5) -> 0 | G54: =_xll.EQNXTDZ($A$1,$B54,G$5) -> 0 | H54: =_xll.EQNXTDZ($A$1,$B54,H$5) -> 0 | I54: =_xll.EQNXTDZ($A$1,$B54,I$5) -> 0 | J54: =_xll.EQNXTDZ($A$1,$B54,J$5) -> 0 | ... BV54: =_xll.EQNXTDZ($A$1,$B54,BV$5) -> 0
A55: Year End | B55: QTRB_DATE_END | C55: =_xll.EQNXTDZ($A$1,$B55,C$5,$B$1) -> 0 | D55: =_xll.EQNXTDZ($A$1,$B55,D$5,$B$1) -> 0 | E55: =_xll.EQNXTDZ($A$1,$B55,E$5,$B$1) -> 0 | F55: =_xll.EQNXTDZ($A$1,$B55,F$5,$B$1) -> 0 | G55: =_xll.EQNXTDZ($A$1,$B55,G$5,$B$1) -> 0 | H55: =_xll.EQNXTDZ($A$1,$B55,H$5,$B$1) -> 0 | I55: =_xll.EQNXTDZ($A$1,$B55,I$5,$B$1) -> 0 | J55: =_xll.EQNXTDZ($A$1,$B55,J$5,$B$1) -> 0 | ... BV55: =_xll.EQNXTDZ($A$1,$B55,BV$5,$B$1) -> 0
A56: Share Capital | B56: QTRB_SHARE_CAPITAL | C56: =_xll.EQNXTDZ($A$1,$B56,C$5,$B$1) -> 0 | D56: =_xll.EQNXTDZ($A$1,$B56,D$5,$B$1) -> 0 | E56: =_xll.EQNXTDZ($A$1,$B56,E$5,$B$1) -> 0 | F56: =_xll.EQNXTDZ($A$1,$B56,F$5,$B$1) -> 0 | G56: =_xll.EQNXTDZ($A$1,$B56,G$5,$B$1) -> 0 | H56: =_xll.EQNXTDZ($A$1,$B56,H$5,$B$1) -> 0 | I56: =_xll.EQNXTDZ($A$1,$B56,I$5,$B$1) -> 0 | J56: =_xll.EQNXTDZ($A$1,$B56,J$5,$B$1) -> 0 | ... BV56: =_xll.EQNXTDZ($A$1,$B56,BV$5,$B$1) -> 0
A57: Share Warrants & outstandings | B57: QTRB_SHAREWARNDOUT | C57: =_xll.EQNXTDZ($A$1,$B57,C$5,$B$1) -> 0 | D57: =_xll.EQNXTDZ($A$1,$B57,D$5,$B$1) -> 0 | E57: =_xll.EQNXTDZ($A$1,$B57,E$5,$B$1) -> 0 | F57: =_xll.EQNXTDZ($A$1,$B57,F$5,$B$1) -> 0 | G57: =_xll.EQNXTDZ($A$1,$B57,G$5,$B$1) -> 0 | H57: =_xll.EQNXTDZ($A$1,$B57,H$5,$B$1) -> 0 | I57: =_xll.EQNXTDZ($A$1,$B57,I$5,$B$1) -> 0 | J57: =_xll.EQNXTDZ($A$1,$B57,J$5,$B$1) -> 0 | ... BV57: =_xll.EQNXTDZ($A$1,$B57,BV$5,$B$1) -> 0
A58: Reserves & Surplus | B58: QTRB_RESERVE | C58: =_xll.EQNXTDZ($A$1,$B58,C$5,$B$1) -> 0 | D58: =_xll.EQNXTDZ($A$1,$B58,D$5,$B$1) -> 0 | E58: =_xll.EQNXTDZ($A$1,$B58,E$5,$B$1) -> 0 | F58: =_xll.EQNXTDZ($A$1,$B58,F$5,$B$1) -> 0 | G58: =_xll.EQNXTDZ($A$1,$B58,G$5,$B$1) -> 0 | H58: =_xll.EQNXTDZ($A$1,$B58,H$5,$B$1) -> 0 | I58: =_xll.EQNXTDZ($A$1,$B58,I$5,$B$1) -> 0 | J58: =_xll.EQNXTDZ($A$1,$B58,J$5,$B$1) -> 0 | ... BV58: =_xll.EQNXTDZ($A$1,$B58,BV$5,$B$1) -> 0
A59: Shareholder's Funds | B59: QTRB_SHAREHODERS_FUNDS | C59: =_xll.EQNXTDZ($A$1,$B59,C$5,$B$1) -> 0 | D59: =_xll.EQNXTDZ($A$1,$B59,D$5,$B$1) -> 0 | E59: =_xll.EQNXTDZ($A$1,$B59,E$5,$B$1) -> 0 | F59: =_xll.EQNXTDZ($A$1,$B59,F$5,$B$1) -> 0 | G59: =_xll.EQNXTDZ($A$1,$B59,G$5,$B$1) -> 0 | H59: =_xll.EQNXTDZ($A$1,$B59,H$5,$B$1) -> 0 | I59: =_xll.EQNXTDZ($A$1,$B59,I$5,$B$1) -> 0 | J59: =_xll.EQNXTDZ($A$1,$B59,J$5,$B$1) -> 0 | ... BV59: =_xll.EQNXTDZ($A$1,$B59,BV$5,$B$1) -> 0
A60: Minority Interest | B60: QTRB_MINORITY_INTEREST_BS | C60: =_xll.EQNXTDZ($A$1,$B60,C$5,$B$1) -> 0 | D60: =_xll.EQNXTDZ($A$1,$B60,D$5,$B$1) -> 0 | E60: =_xll.EQNXTDZ($A$1,$B60,E$5,$B$1) -> 0 | F60: =_xll.EQNXTDZ($A$1,$B60,F$5,$B$1) -> 0 | G60: =_xll.EQNXTDZ($A$1,$B60,G$5,$B$1) -> 0 | H60: =_xll.EQNXTDZ($A$1,$B60,H$5,$B$1) -> 0 | I60: =_xll.EQNXTDZ($A$1,$B60,I$5,$B$1) -> 0 | J60: =_xll.EQNXTDZ($A$1,$B60,J$5,$B$1) -> 0 | ... BV60: =_xll.EQNXTDZ($A$1,$B60,BV$5,$B$1) -> 0
A61: Long Term Borrowings | B61: QTRB_TOTAL_DEBTS | C61: =_xll.EQNXTDZ($A$1,$B61,C$5,$B$1) -> 0 | D61: =_xll.EQNXTDZ($A$1,$B61,D$5,$B$1) -> 0 | E61: =_xll.EQNXTDZ($A$1,$B61,E$5,$B$1) -> 0 | F61: =_xll.EQNXTDZ($A$1,$B61,F$5,$B$1) -> 0 | G61: =_xll.EQNXTDZ($A$1,$B61,G$5,$B$1) -> 0 | H61: =_xll.EQNXTDZ($A$1,$B61,H$5,$B$1) -> 0 | I61: =_xll.EQNXTDZ($A$1,$B61,I$5,$B$1) -> 0 | J61: =_xll.EQNXTDZ($A$1,$B61,J$5,$B$1) -> 0 | ... BV61: =_xll.EQNXTDZ($A$1,$B61,BV$5,$B$1) -> 0
A62: Secured Loans | B62: QTRB_SECURED_LOANS | C62: =_xll.EQNXTDZ($A$1,$B62,C$5,$B$1) -> 0 | D62: =_xll.EQNXTDZ($A$1,$B62,D$5,$B$1) -> 0 | E62: =_xll.EQNXTDZ($A$1,$B62,E$5,$B$1) -> 0 | F62: =_xll.EQNXTDZ($A$1,$B62,F$5,$B$1) -> 0 | G62: =_xll.EQNXTDZ($A$1,$B62,G$5,$B$1) -> 0 | H62: =_xll.EQNXTDZ($A$1,$B62,H$5,$B$1) -> 0 | I62: =_xll.EQNXTDZ($A$1,$B62,I$5,$B$1) -> 0 | J62: =_xll.EQNXTDZ($A$1,$B62,J$5,$B$1) -> 0 | ... BV62: =_xll.EQNXTDZ($A$1,$B62,BV$5,$B$1) -> 0
A63: Unsecured Loans | B63: QTRB_UNSECURED_LOANS_NF | C63: =_xll.EQNXTDZ($A$1,$B63,C$5,$B$1) -> 0 | D63: =_xll.EQNXTDZ($A$1,$B63,D$5,$B$1) -> 0 | E63: =_xll.EQNXTDZ($A$1,$B63,E$5,$B$1) -> 0 | F63: =_xll.EQNXTDZ($A$1,$B63,F$5,$B$1) -> 0 | G63: =_xll.EQNXTDZ($A$1,$B63,G$5,$B$1) -> 0 | H63: =_xll.EQNXTDZ($A$1,$B63,H$5,$B$1) -> 0 | I63: =_xll.EQNXTDZ($A$1,$B63,I$5,$B$1) -> 0 | J63: =_xll.EQNXTDZ($A$1,$B63,J$5,$B$1) -> 0 | ... BV63: =_xll.EQNXTDZ($A$1,$B63,BV$5,$B$1) -> 0
A64: Other Long Term Liabilities | B64: QTRB_OTHER_LT_LIABILITIES | C64: =_xll.EQNXTDZ($A$1,$B64,C$5,$B$1) -> 0 | D64: =_xll.EQNXTDZ($A$1,$B64,D$5,$B$1) -> 0 | E64: =_xll.EQNXTDZ($A$1,$B64,E$5,$B$1) -> 0 | F64: =_xll.EQNXTDZ($A$1,$B64,F$5,$B$1) -> 0 | G64: =_xll.EQNXTDZ($A$1,$B64,G$5,$B$1) -> 0 | H64: =_xll.EQNXTDZ($A$1,$B64,H$5,$B$1) -> 0 | I64: =_xll.EQNXTDZ($A$1,$B64,I$5,$B$1) -> 0 | J64: =_xll.EQNXTDZ($A$1,$B64,J$5,$B$1) -> 0 | ... BV64: =_xll.EQNXTDZ($A$1,$B64,BV$5,$B$1) -> 0
A65: Long Term Trade Payables | B65: QTRB_LT_TRADE_PAYABLE | C65: =_xll.EQNXTDZ($A$1,$B65,C$5,$B$1) -> 0 | D65: =_xll.EQNXTDZ($A$1,$B65,D$5,$B$1) -> 0 | E65: =_xll.EQNXTDZ($A$1,$B65,E$5,$B$1) -> 0 | F65: =_xll.EQNXTDZ($A$1,$B65,F$5,$B$1) -> 0 | G65: =_xll.EQNXTDZ($A$1,$B65,G$5,$B$1) -> 0 | H65: =_xll.EQNXTDZ($A$1,$B65,H$5,$B$1) -> 0 | I65: =_xll.EQNXTDZ($A$1,$B65,I$5,$B$1) -> 0 | J65: =_xll.EQNXTDZ($A$1,$B65,J$5,$B$1) -> 0 | ... BV65: =_xll.EQNXTDZ($A$1,$B65,BV$5,$B$1) -> 0
A66: Lont Term Provisions | B66: QTRB_LT_PROVISIONS | C66: =_xll.EQNXTDZ($A$1,$B66,C$5,$B$1) -> 0 | D66: =_xll.EQNXTDZ($A$1,$B66,D$5,$B$1) -> 0 | E66: =_xll.EQNXTDZ($A$1,$B66,E$5,$B$1) -> 0 | F66: =_xll.EQNXTDZ($A$1,$B66,F$5,$B$1) -> 0 | G66: =_xll.EQNXTDZ($A$1,$B66,G$5,$B$1) -> 0 | H66: =_xll.EQNXTDZ($A$1,$B66,H$5,$B$1) -> 0 | I66: =_xll.EQNXTDZ($A$1,$B66,I$5,$B$1) -> 0 | J66: =_xll.EQNXTDZ($A$1,$B66,J$5,$B$1) -> 0 | ... BV66: =_xll.EQNXTDZ($A$1,$B66,BV$5,$B$1) -> 0
... A97: Total Assets | B97: QTRB_TOTAL_APPLICATIONS | C97: =_xll.EQNXTDZ($A$1,$B97,C$5,$B$1) -> 0 | D97: =_xll.EQNXTDZ($A$1,$B97,D$5,$B$1) -> 0 | E97: =_xll.EQNXTDZ($A$1,$B97,E$5,$B$1) -> 0 | F97: =_xll.EQNXTDZ($A$1,$B97,F$5,$B$1) -> 0 | G97: =_xll.EQNXTDZ($A$1,$B97,G$5,$B$1) -> 0 | H97: =_xll.EQNXTDZ($A$1,$B97,H$5,$B$1) -> 0 | I97: =_xll.EQNXTDZ($A$1,$B97,I$5,$B$1) -> 0 | J97: =_xll.EQNXTDZ($A$1,$B97,J$5,$B$1) -> 0 | ... BV97: =_xll.EQNXTDZ($A$1,$B97,BV$5,$B$1) -> 0

Sheet Annual Raw
A1: 208433 | B1: X | C1: 200103 | D1: 200203 | E1: 200303 | F1: 200403 | G1: 200503 | H1: 200603 | I1: 200703 | J1: 200803 | K1: 200903 | L1: 201003 | M1: 201103 | N1: 201203 | O1: 201303 | P1: 201403 | Q1: 201503 | R1: 201603 | S1: 201703 | T1: 201803 | U1: 201903 | V1: 202003 | W1: 202103 | X1: 202203 | Y1: 202303 | Z1: 202403 | AA1: 202503 | AB1: 202603 | AC1: 202703 | AD1: 202803 | AE1: 202903 | AF1: 203003
A3: Field Description | B3: Field Name
A4: Company Name | B4: CD_COMPNAME | C4: =_xll.EQNXTDZ(A1,B4,"L") -> Inox India Ltd.
A5: Year End | B5: PL_YEAR_END | C5: =_xll.EQNXTDZ($A$1,$B5,C$1,$B$1) -> 200103 | D5: =_xll.EQNXTDZ($A$1,$B5,D$1,$B$1) -> 200203 | E5: =_xll.EQNXTDZ($A$1,$B5,E$1,$B$1) -> 200303 | F5: =_xll.EQNXTDZ($A$1,$B5,F$1,$B$1) -> 200403 | G5: =_xll.EQNXTDZ($A$1,$B5,G$1,$B$1) -> 200503 | H5: =_xll.EQNXTDZ($A$1,$B5,H$1,$B$1) -> 200603 | I5: =_xll.EQNXTDZ($A$1,$B5,I$1,$B$1) -> 200703 | J5: =_xll.EQNXTDZ($A$1,$B5,J$1,$B$1) -> 200803 | ... AF5: =_xll.EQNXTDZ($A$1,$B5,AF$1,$B$1) -> 0
A6: Sales Turnover | B6: PL_TOTAL_GROSS_SALES | C6: =_xll.EQNXTDZ($A$1,$B6,C$1,$B$1) -> 35.032452 | D6: =_xll.EQNXTDZ($A$1,$B6,D$1,$B$1) -> 51.527453 | E6: =_xll.EQNXTDZ($A$1,$B6,E$1,$B$1) -> 48.232658 | F6: =_xll.EQNXTDZ($A$1,$B6,F$1,$B$1) -> 51.989955 | G6: =_xll.EQNXTDZ($A$1,$B6,G$1,$B$1) -> 54.900097 | H6: =_xll.EQNXTDZ($A$1,$B6,H$1,$B$1) -> 87.1955 | I6: =_xll.EQNXTDZ($A$1,$B6,I$1,$B$1) -> 137.65676 | J6: =_xll.EQNXTDZ($A$1,$B6,J$1,$B$1) -> 205.30286 | ... AF6: =_xll.EQNXTDZ($A$1,$B6,AF$1,$B$1) -> 0
A7: Less: Inter divisional transfers | B7: PL_INTER_DIV_TRF | C7: =_xll.EQNXTDZ($A$1,$B7,C$1,$B$1) -> 0 | D7: =_xll.EQNXTDZ($A$1,$B7,D$1,$B$1) -> 0 | E7: =_xll.EQNXTDZ($A$1,$B7,E$1,$B$1) -> 0 | F7: =_xll.EQNXTDZ($A$1,$B7,F$1,$B$1) -> 0 | G7: =_xll.EQNXTDZ($A$1,$B7,G$1,$B$1) -> 0 | H7: =_xll.EQNXTDZ($A$1,$B7,H$1,$B$1) -> 0 | I7: =_xll.EQNXTDZ($A$1,$B7,I$1,$B$1) -> 0 | J7: =_xll.EQNXTDZ($A$1,$B7,J$1,$B$1) -> 0 | ... AF7: =_xll.EQNXTDZ($A$1,$B7,AF$1,$B$1) -> 0
A8: Less: Sales Returns | B8: PL_SALES_RETURN | C8: =_xll.EQNXTDZ($A$1,$B8,C$1,$B$1) -> 0 | D8: =_xll.EQNXTDZ($A$1,$B8,D$1,$B$1) -> 0 | E8: =_xll.EQNXTDZ($A$1,$B8,E$1,$B$1) -> 0 | F8: =_xll.EQNXTDZ($A$1,$B8,F$1,$B$1) -> 0 | G8: =_xll.EQNXTDZ($A$1,$B8,G$1,$B$1) -> 0 | H8: =_xll.EQNXTDZ($A$1,$B8,H$1,$B$1) -> 0 | I8: =_xll.EQNXTDZ($A$1,$B8,I$1,$B$1) -> 0 | J8: =_xll.EQNXTDZ($A$1,$B8,J$1,$B$1) -> 0 | ... AF8: =_xll.EQNXTDZ($A$1,$B8,AF$1,$B$1) -> 0
A9: Less: Excise | B9: PL_EXCISE | C9: =_xll.EQNXTDZ($A$1,$B9,C$1,$B$1) -> 3.2351323 | D9: =_xll.EQNXTDZ($A$1,$B9,D$1,$B$1) -> 2.5807622 | E9: =_xll.EQNXTDZ($A$1,$B9,E$1,$B$1) -> 1.7177281 | F9: =_xll.EQNXTDZ($A$1,$B9,F$1,$B$1) -> 2.7170725 | G9: =_xll.EQNXTDZ($A$1,$B9,G$1,$B$1) -> 3.4063634 | H9: =_xll.EQNXTDZ($A$1,$B9,H$1,$B$1) -> 5.3058515 | I9: =_xll.EQNXTDZ($A$1,$B9,I$1,$B$1) -> 7.3428139 | J9: =_xll.EQNXTDZ($A$1,$B9,J$1,$B$1) -> 11.593145 | ... AF9: =_xll.EQNXTDZ($A$1,$B9,AF$1,$B$1) -> 0
A10: Net Sales | B10: PL_NET_SALES | C10: =_xll.EQNXTDZ($A$1,$B10,C$1,$B$1) -> 31.797319 | D10: =_xll.EQNXTDZ($A$1,$B10,D$1,$B$1) -> 48.946691 | E10: =_xll.EQNXTDZ($A$1,$B10,E$1,$B$1) -> 46.51493 | F10: =_xll.EQNXTDZ($A$1,$B10,F$1,$B$1) -> 49.272882 | G10: =_xll.EQNXTDZ($A$1,$B10,G$1,$B$1) -> 51.493733 | H10: =_xll.EQNXTDZ($A$1,$B10,H$1,$B$1) -> 81.889649 | I10: =_xll.EQNXTDZ($A$1,$B10,I$1,$B$1) -> 130.31394 | J10: =_xll.EQNXTDZ($A$1,$B10,J$1,$B$1) -> 193.70972 | ... AF10: =_xll.EQNXTDZ($A$1,$B10,AF$1,$B$1) -> 0
A11: Increase/Decrease in Stock | B11: PL_INC_DEC_INVENTORY | C11: =_xll.EQNXTDZ($A$1,$B11,C$1,$B$1) -> 0.254252 | D11: =_xll.EQNXTDZ($A$1,$B11,D$1,$B$1) -> 0.3561504 | E11: =_xll.EQNXTDZ($A$1,$B11,E$1,$B$1) -> -0.4957742 | F11: =_xll.EQNXTDZ($A$1,$B11,F$1,$B$1) -> -0.4386168 | G11: =_xll.EQNXTDZ($A$1,$B11,G$1,$B$1) -> -3.880121 | H11: =_xll.EQNXTDZ($A$1,$B11,H$1,$B$1) -> -5.5437663 | I11: =_xll.EQNXTDZ($A$1,$B11,I$1,$B$1) -> -12.068485 | J11: =_xll.EQNXTDZ($A$1,$B11,J$1,$B$1) -> -12.77424 | ... AF11: =_xll.EQNXTDZ($A$1,$B11,AF$1,$B$1) -> 0
A12: Raw Material Consumed | B12: PL_RAW_MATRS_CONSUMED | C12: =_xll.EQNXTDZ($A$1,$B12,C$1,$B$1) -> 13.138791 | D12: =_xll.EQNXTDZ($A$1,$B12,D$1,$B$1) -> 28.892685 | E12: =_xll.EQNXTDZ($A$1,$B12,E$1,$B$1) -> 29.077509 | F12: =_xll.EQNXTDZ($A$1,$B12,F$1,$B$1) -> 27.412232 | G12: =_xll.EQNXTDZ($A$1,$B12,G$1,$B$1) -> 30.416405 | H12: =_xll.EQNXTDZ($A$1,$B12,H$1,$B$1) -> 46.127885 | I12: =_xll.EQNXTDZ($A$1,$B12,I$1,$B$1) -> 71.685462 | J12: =_xll.EQNXTDZ($A$1,$B12,J$1,$B$1) -> 106.80836 | ... AF12: =_xll.EQNXTDZ($A$1,$B12,AF$1,$B$1) -> 0
A13: Power & Fuel Cost | B13: PL_POWER_FUEL | C13: =_xll.EQNXTDZ($A$1,$B13,C$1,$B$1) -> 0.6412955 | D13: =_xll.EQNXTDZ($A$1,$B13,D$1,$B$1) -> 0.6726684 | E13: =_xll.EQNXTDZ($A$1,$B13,E$1,$B$1) -> 0.7121749 | F13: =_xll.EQNXTDZ($A$1,$B13,F$1,$B$1) -> 0.8292202 | G13: =_xll.EQNXTDZ($A$1,$B13,G$1,$B$1) -> 0.8905262 | H13: =_xll.EQNXTDZ($A$1,$B13,H$1,$B$1) -> 0.9735511 | I13: =_xll.EQNXTDZ($A$1,$B13,I$1,$B$1) -> 1.6014805 | J13: =_xll.EQNXTDZ($A$1,$B13,J$1,$B$1) -> 2.232156 | ... AF13: =_xll.EQNXTDZ($A$1,$B13,AF$1,$B$1) -> 0
A14: Employee Cost | B14: PL_EMPLOYEES | C14: =_xll.EQNXTDZ($A$1,$B14,C$1,$B$1) -> 2.1856685 | D14: =_xll.EQNXTDZ($A$1,$B14,D$1,$B$1) -> 2.3922158 | E14: =_xll.EQNXTDZ($A$1,$B14,E$1,$B$1) -> 2.7783973 | F14: =_xll.EQNXTDZ($A$1,$B14,F$1,$B$1) -> 3.1842187 | G14: =_xll.EQNXTDZ($A$1,$B14,G$1,$B$1) -> 3.5654644 | H14: =_xll.EQNXTDZ($A$1,$B14,H$1,$B$1) -> 4.3553126 | I14: =_xll.EQNXTDZ($A$1,$B14,I$1,$B$1) -> 5.9573332 | J14: =_xll.EQNXTDZ($A$1,$B14,J$1,$B$1) -> 9.0858556 | ... AF14: =_xll.EQNXTDZ($A$1,$B14,AF$1,$B$1) -> 0
A15: Operating & Manufacturing Expenses | B15: PL_GEN_OTHER_MFG_EXPS | C15: =_xll.EQNXTDZ($A$1,$B15,C$1,$B$1) -> 4.0648788 | D15: =_xll.EQNXTDZ($A$1,$B15,D$1,$B$1) -> 4.1775609 | E15: =_xll.EQNXTDZ($A$1,$B15,E$1,$B$1) -> 5.2862596 | F15: =_xll.EQNXTDZ($A$1,$B15,F$1,$B$1) -> 7.8473365 | G15: =_xll.EQNXTDZ($A$1,$B15,G$1,$B$1) -> 7.6527092 | H15: =_xll.EQNXTDZ($A$1,$B15,H$1,$B$1) -> 13.158724 | I15: =_xll.EQNXTDZ($A$1,$B15,I$1,$B$1) -> 21.597667 | J15: =_xll.EQNXTDZ($A$1,$B15,J$1,$B$1) -> 32.498882 | ... AF15: =_xll.EQNXTDZ($A$1,$B15,AF$1,$B$1) -> 0
A16: Cost of Software development | B16: PL_COST_SW | C16: =_xll.EQNXTDZ($A$1,$B16,C$1,$B$1) -> 0 | D16: =_xll.EQNXTDZ($A$1,$B16,D$1,$B$1) -> 0 | E16: =_xll.EQNXTDZ($A$1,$B16,E$1,$B$1) -> 0 | F16: =_xll.EQNXTDZ($A$1,$B16,F$1,$B$1) -> 0 | G16: =_xll.EQNXTDZ($A$1,$B16,G$1,$B$1) -> 0 | H16: =_xll.EQNXTDZ($A$1,$B16,H$1,$B$1) -> 0 | I16: =_xll.EQNXTDZ($A$1,$B16,I$1,$B$1) -> 0 | J16: =_xll.EQNXTDZ($A$1,$B16,J$1,$B$1) -> 0 | ... AF16: =_xll.EQNXTDZ($A$1,$B16,AF$1,$B$1) -> 0
... A36: Profit After Tax from Discontinued Operations | B36: PL_PAT_DIS_OP | C36: =_xll.EQNXTDZ($A$1,$B36,C$1,$B$1) -> 0 | D36: =_xll.EQNXTDZ($A$1,$B36,D$1,$B$1) -> 0 | E36: =_xll.EQNXTDZ($A$1,$B36,E$1,$B$1) -> 0 | F36: =_xll.EQNXTDZ($A$1,$B36,F$1,$B$1) -> 0 | G36: =_xll.EQNXTDZ($A$1,$B36,G$1,$B$1) -> 0 | H36: =_xll.EQNXTDZ($A$1,$B36,H$1,$B$1) -> 0 | I36: =_xll.EQNXTDZ($A$1,$B36,I$1,$B$1) -> 0 | J36: =_xll.EQNXTDZ($A$1,$B36,J$1,$B$1) -> 0 | ... AF36: =_xll.EQNXTDZ($A$1,$B36,AF$1,$B$1) -> 0
A39: Field Description | B39: Field Name
A40: Year End | B40: BS_YEAR_END | C40: =_xll.EQNXTDZ($A$1,$B40,C$1,$B$1) -> 200103 | D40: =_xll.EQNXTDZ($A$1,$B40,D$1,$B$1) -> 200203 | E40: =_xll.EQNXTDZ($A$1,$B40,E$1,$B$1) -> 200303 | F40: =_xll.EQNXTDZ($A$1,$B40,F$1,$B$1) -> 200403 | G40: =_xll.EQNXTDZ($A$1,$B40,G$1,$B$1) -> 200503 | H40: =_xll.EQNXTDZ($A$1,$B40,H$1,$B$1) -> 200603 | I40: =_xll.EQNXTDZ($A$1,$B40,I$1,$B$1) -> 200703 | J40: =_xll.EQNXTDZ($A$1,$B40,J$1,$B$1) -> 200803 | ... AF40: =_xll.EQNXTDZ($A$1,$B40,AF$1,$B$1) -> 0
A41: Share Capital | B41: BS_SHARE_CAPITAL | C41: =_xll.EQNXTDZ($A$1,$B41,C$1,$B$1) -> 4.338175 | D41: =_xll.EQNXTDZ($A$1,$B41,D$1,$B$1) -> 4.338175 | E41: =_xll.EQNXTDZ($A$1,$B41,E$1,$B$1) -> 4.338175 | F41: =_xll.EQNXTDZ($A$1,$B41,F$1,$B$1) -> 4.338175 | G41: =_xll.EQNXTDZ($A$1,$B41,G$1,$B$1) -> 4.338175 | H41: =_xll.EQNXTDZ($A$1,$B41,H$1,$B$1) -> 4.338175 | I41: =_xll.EQNXTDZ($A$1,$B41,I$1,$B$1) -> 9.07635 | J41: =_xll.EQNXTDZ($A$1,$B41,J$1,$B$1) -> 9.07635 | ... AF41: =_xll.EQNXTDZ($A$1,$B41,AF$1,$B$1) -> 0
A42: Share Warrants & Outstandings | B42: BS_SHAREWROUTST | C42: =_xll.EQNXTDZ($A$1,$B42,C$1,$B$1) -> 0 | D42: =_xll.EQNXTDZ($A$1,$B42,D$1,$B$1) -> 0 | E42: =_xll.EQNXTDZ($A$1,$B42,E$1,$B$1) -> 0 | F42: =_xll.EQNXTDZ($A$1,$B42,F$1,$B$1) -> 0 | G42: =_xll.EQNXTDZ($A$1,$B42,G$1,$B$1) -> 0 | H42: =_xll.EQNXTDZ($A$1,$B42,H$1,$B$1) -> 0 | I42: =_xll.EQNXTDZ($A$1,$B42,I$1,$B$1) -> 0 | J42: =_xll.EQNXTDZ($A$1,$B42,J$1,$B$1) -> 0 | ... AF42: =_xll.EQNXTDZ($A$1,$B42,AF$1,$B$1) -> 0
A43: Total Reserves | B43: BS_RESERVE | C43: =_xll.EQNXTDZ($A$1,$B43,C$1,$B$1) -> 12.79249 | D43: =_xll.EQNXTDZ($A$1,$B43,D$1,$B$1) -> 15.515159 | E43: =_xll.EQNXTDZ($A$1,$B43,E$1,$B$1) -> 16.326594 | F43: =_xll.EQNXTDZ($A$1,$B43,F$1,$B$1) -> 18.896301 | G43: =_xll.EQNXTDZ($A$1,$B43,G$1,$B$1) -> 21.693607 | H43: =_xll.EQNXTDZ($A$1,$B43,H$1,$B$1) -> 30.038525 | I43: =_xll.EQNXTDZ($A$1,$B43,I$1,$B$1) -> 41.22561 | J43: =_xll.EQNXTDZ($A$1,$B43,J$1,$B$1) -> 60.698651 | ... AF43: =_xll.EQNXTDZ($A$1,$B43,AF$1,$B$1) -> 0
A44: Shareholder's Funds | B44: BS_SHAREHODERS_FUNDS | C44: =_xll.EQNXTDZ($A$1,$B44,C$1,$B$1) -> 17.130665 | D44: =_xll.EQNXTDZ($A$1,$B44,D$1,$B$1) -> 19.853334 | E44: =_xll.EQNXTDZ($A$1,$B44,E$1,$B$1) -> 20.664769 | F44: =_xll.EQNXTDZ($A$1,$B44,F$1,$B$1) -> 23.234476 | G44: =_xll.EQNXTDZ($A$1,$B44,G$1,$B$1) -> 26.031782 | H44: =_xll.EQNXTDZ($A$1,$B44,H$1,$B$1) -> 34.3767 | I44: =_xll.EQNXTDZ($A$1,$B44,I$1,$B$1) -> 50.30196 | J44: =_xll.EQNXTDZ($A$1,$B44,J$1,$B$1) -> 69.775001 | ... AF44: =_xll.EQNXTDZ($A$1,$B44,AF$1,$B$1) -> 0
A45: Minority Interest | B45: BS_MINORITY_INTEREST | C45: =_xll.EQNXTDZ($A$1,$B45,C$1,$B$1) -> 0 | D45: =_xll.EQNXTDZ($A$1,$B45,D$1,$B$1) -> 0 | E45: =_xll.EQNXTDZ($A$1,$B45,E$1,$B$1) -> 0 | F45: =_xll.EQNXTDZ($A$1,$B45,F$1,$B$1) -> 0 | G45: =_xll.EQNXTDZ($A$1,$B45,G$1,$B$1) -> 0 | H45: =_xll.EQNXTDZ($A$1,$B45,H$1,$B$1) -> 0 | I45: =_xll.EQNXTDZ($A$1,$B45,I$1,$B$1) -> 0 | J45: =_xll.EQNXTDZ($A$1,$B45,J$1,$B$1) -> 0 | ... AF45: =_xll.EQNXTDZ($A$1,$B45,AF$1,$B$1) -> 0
A46: Long-Term Borrowings | B46: BS_LTRM_BORROWING | C46: =_xll.EQNXTDZ($A$1,$B46,C$1,$B$1) -> 0 | D46: =_xll.EQNXTDZ($A$1,$B46,D$1,$B$1) -> 0 | E46: =_xll.EQNXTDZ($A$1,$B46,E$1,$B$1) -> 0 | F46: =_xll.EQNXTDZ($A$1,$B46,F$1,$B$1) -> 0 | G46: =_xll.EQNXTDZ($A$1,$B46,G$1,$B$1) -> 0 | H46: =_xll.EQNXTDZ($A$1,$B46,H$1,$B$1) -> 0 | I46: =_xll.EQNXTDZ($A$1,$B46,I$1,$B$1) -> 0 | J46: =_xll.EQNXTDZ($A$1,$B46,J$1,$B$1) -> 0 | ... AF46: =_xll.EQNXTDZ($A$1,$B46,AF$1,$B$1) -> 0
A47: Secured Loans | B47: BS_SECURED_LOANS | C47: =_xll.EQNXTDZ($A$1,$B47,C$1,$B$1) -> 6.9256003 | D47: =_xll.EQNXTDZ($A$1,$B47,D$1,$B$1) -> 1.7983299 | E47: =_xll.EQNXTDZ($A$1,$B47,E$1,$B$1) -> 5.3148854 | F47: =_xll.EQNXTDZ($A$1,$B47,F$1,$B$1) -> 0 | G47: =_xll.EQNXTDZ($A$1,$B47,G$1,$B$1) -> 0.9197791 | H47: =_xll.EQNXTDZ($A$1,$B47,H$1,$B$1) -> 1.2939266 | I47: =_xll.EQNXTDZ($A$1,$B47,I$1,$B$1) -> 8.0543794 | J47: =_xll.EQNXTDZ($A$1,$B47,J$1,$B$1) -> 11.896456 | ... AF47: =_xll.EQNXTDZ($A$1,$B47,AF$1,$B$1) -> 0
A48: Unsecured Loans | B48: BS_UNSECURED_LOANS_NF | C48: =_xll.EQNXTDZ($A$1,$B48,C$1,$B$1) -> 1.475 | D48: =_xll.EQNXTDZ($A$1,$B48,D$1,$B$1) -> 0.95 | E48: =_xll.EQNXTDZ($A$1,$B48,E$1,$B$1) -> 0.775 | F48: =_xll.EQNXTDZ($A$1,$B48,F$1,$B$1) -> 0.6 | G48: =_xll.EQNXTDZ($A$1,$B48,G$1,$B$1) -> 0.075 | H48: =_xll.EQNXTDZ($A$1,$B48,H$1,$B$1) -> 0 | I48: =_xll.EQNXTDZ($A$1,$B48,I$1,$B$1) -> 0 | J48: =_xll.EQNXTDZ($A$1,$B48,J$1,$B$1) -> 10 | ... AF48: =_xll.EQNXTDZ($A$1,$B48,AF$1,$B$1) -> 0
A49: Deferred Tax Assets / Liabilities | B49: BS_NET_DEF_TAX_NF | C49: =_xll.EQNXTDZ($A$1,$B49,C$1,$B$1) -> 0 | D49: =_xll.EQNXTDZ($A$1,$B49,D$1,$B$1) -> 0 | E49: =_xll.EQNXTDZ($A$1,$B49,E$1,$B$1) -> 1.8425793 | F49: =_xll.EQNXTDZ($A$1,$B49,F$1,$B$1) -> 1.8222732 | G49: =_xll.EQNXTDZ($A$1,$B49,G$1,$B$1) -> 1.7154844 | H49: =_xll.EQNXTDZ($A$1,$B49,H$1,$B$1) -> 1.7564706 | I49: =_xll.EQNXTDZ($A$1,$B49,I$1,$B$1) -> 3.9844117 | J49: =_xll.EQNXTDZ($A$1,$B49,J$1,$B$1) -> 6.2079525 | ... AF49: =_xll.EQNXTDZ($A$1,$B49,AF$1,$B$1) -> 0
A50: Other Long Term Liabilities | B50: BS_OTH_LT_LIAB | C50: =_xll.EQNXTDZ($A$1,$B50,C$1,$B$1) -> 0 | D50: =_xll.EQNXTDZ($A$1,$B50,D$1,$B$1) -> 0 | E50: =_xll.EQNXTDZ($A$1,$B50,E$1,$B$1) -> 0 | F50: =_xll.EQNXTDZ($A$1,$B50,F$1,$B$1) -> 0 | G50: =_xll.EQNXTDZ($A$1,$B50,G$1,$B$1) -> 0 | H50: =_xll.EQNXTDZ($A$1,$B50,H$1,$B$1) -> 0 | I50: =_xll.EQNXTDZ($A$1,$B50,I$1,$B$1) -> 0 | J50: =_xll.EQNXTDZ($A$1,$B50,J$1,$B$1) -> 0 | ... AF50: =_xll.EQNXTDZ($A$1,$B50,AF$1,$B$1) -> 0
A51: Long Term Trade Payables | B51: BS_LT_TRADE_PAYABLES | C51: =_xll.EQNXTDZ($A$1,$B51,C$1,$B$1) -> 0 | D51: =_xll.EQNXTDZ($A$1,$B51,D$1,$B$1) -> 0 | E51: =_xll.EQNXTDZ($A$1,$B51,E$1,$B$1) -> 0 | F51: =_xll.EQNXTDZ($A$1,$B51,F$1,$B$1) -> 0 | G51: =_xll.EQNXTDZ($A$1,$B51,G$1,$B$1) -> 0 | H51: =_xll.EQNXTDZ($A$1,$B51,H$1,$B$1) -> 0 | I51: =_xll.EQNXTDZ($A$1,$B51,I$1,$B$1) -> 0 | J51: =_xll.EQNXTDZ($A$1,$B51,J$1,$B$1) -> 0 | ... AF51: =_xll.EQNXTDZ($A$1,$B51,AF$1,$B$1) -> 0
... A99: Estimated Capital Contracts Remaining | B99: BS_ESTIMATED_CAPITAL_CONTRACT | C99: =_xll.EQNXTDZ($A$1,$B99,C$1,$B$1) -> 0 | D99: =_xll.EQNXTDZ($A$1,$B99,D$1,$B$1) -> 0 | E99: =_xll.EQNXTDZ($A$1,$B99,E$1,$B$1) -> 0 | F99: =_xll.EQNXTDZ($A$1,$B99,F$1,$B$1) -> 0 | G99: =_xll.EQNXTDZ($A$1,$B99,G$1,$B$1) -> 0 | H99: =_xll.EQNXTDZ($A$1,$B99,H$1,$B$1) -> 0 | I99: =_xll.EQNXTDZ($A$1,$B99,I$1,$B$1) -> 0 | J99: =_xll.EQNXTDZ($A$1,$B99,J$1,$B$1) -> 0 | ... AF99: =_xll.EQNXTDZ($A$1,$B99,AF$1,$B$1) -> 0
A103: Field Description | B103: Field Name
A104: Equity Paid Up | B104: BS_EQUITY_PAIDUP | C104: =_xll.EQNXTDZ($A$1,$B104,C$1,$B$1) -> 4.338175 | D104: =_xll.EQNXTDZ($A$1,$B104,D$1,$B$1) -> 4.338175 | E104: =_xll.EQNXTDZ($A$1,$B104,E$1,$B$1) -> 4.338175 | F104: =_xll.EQNXTDZ($A$1,$B104,F$1,$B$1) -> 4.338175 | G104: =_xll.EQNXTDZ($A$1,$B104,G$1,$B$1) -> 4.338175 | H104: =_xll.EQNXTDZ($A$1,$B104,H$1,$B$1) -> 4.338175 | I104: =_xll.EQNXTDZ($A$1,$B104,I$1,$B$1) -> 9.07635 | J104: =_xll.EQNXTDZ($A$1,$B104,J$1,$B$1) -> 9.07635 | ... AF104: =_xll.EQNXTDZ($A$1,$B104,AF$1,$B$1) -> 0
A105: Face Value | B105: BS_FACE_VALUE | C105: =_xll.EQNXTDZ($A$1,$B105,C$1,$B$1) -> 10 | D105: =_xll.EQNXTDZ($A$1,$B105,D$1,$B$1) -> 10 | E105: =_xll.EQNXTDZ($A$1,$B105,E$1,$B$1) -> 10 | F105: =_xll.EQNXTDZ($A$1,$B105,F$1,$B$1) -> 10 | G105: =_xll.EQNXTDZ($A$1,$B105,G$1,$B$1) -> 10 | H105: =_xll.EQNXTDZ($A$1,$B105,H$1,$B$1) -> 10 | I105: =_xll.EQNXTDZ($A$1,$B105,I$1,$B$1) -> 10 | J105: =_xll.EQNXTDZ($A$1,$B105,J$1,$B$1) -> 10 | ... AF105: =_xll.EQNXTDZ($A$1,$B105,AF$1,$B$1) -> 0
A106: Close Price (Unit Curr.) | B106: FH_YEAR_PRICE | C106: =_xll.EQNXTDZ($A$1,$B106,C$1,$B$1) -> 0 | D106: =_xll.EQNXTDZ($A$1,$B106,D$1,$B$1) -> 0 | E106: =_xll.EQNXTDZ($A$1,$B106,E$1,$B$1) -> 0 | F106: =_xll.EQNXTDZ($A$1,$B106,F$1,$B$1) -> 0 | G106: =_xll.EQNXTDZ($A$1,$B106,G$1,$B$1) -> 0 | H106: =_xll.EQNXTDZ($A$1,$B106,H$1,$B$1) -> 0 | I106: =_xll.EQNXTDZ($A$1,$B106,I$1,$B$1) -> 0 | J106: =_xll.EQNXTDZ($A$1,$B106,J$1,$B$1) -> 0 | ... AF106: =_xll.EQNXTDZ($A$1,$B106,AF$1,$B$1) -> 0
A107: High Price (Unit Curr.) | B107: FH_HIGH | C107: =_xll.EQNXTDZ($A$1,$B107,C$1,$B$1) -> 0 | D107: =_xll.EQNXTDZ($A$1,$B107,D$1,$B$1) -> 0 | E107: =_xll.EQNXTDZ($A$1,$B107,E$1,$B$1) -> 0 | F107: =_xll.EQNXTDZ($A$1,$B107,F$1,$B$1) -> 0 | G107: =_xll.EQNXTDZ($A$1,$B107,G$1,$B$1) -> 0 | H107: =_xll.EQNXTDZ($A$1,$B107,H$1,$B$1) -> 0 | I107: =_xll.EQNXTDZ($A$1,$B107,I$1,$B$1) -> 0 | J107: =_xll.EQNXTDZ($A$1,$B107,J$1,$B$1) -> 0 | ... AF107: =_xll.EQNXTDZ($A$1,$B107,AF$1,$B$1) -> 0
A108: Low Price (Unit Curr.) | B108: FH_LOW | C108: =_xll.EQNXTDZ($A$1,$B108,C$1,$B$1) -> 0 | D108: =_xll.EQNXTDZ($A$1,$B108,D$1,$B$1) -> 0 | E108: =_xll.EQNXTDZ($A$1,$B108,E$1,$B$1) -> 0 | F108: =_xll.EQNXTDZ($A$1,$B108,F$1,$B$1) -> 0 | G108: =_xll.EQNXTDZ($A$1,$B108,G$1,$B$1) -> 0 | H108: =_xll.EQNXTDZ($A$1,$B108,H$1,$B$1) -> 0 | I108: =_xll.EQNXTDZ($A$1,$B108,I$1,$B$1) -> 0 | J108: =_xll.EQNXTDZ($A$1,$B108,J$1,$B$1) -> 0 | ... AF108: =_xll.EQNXTDZ($A$1,$B108,AF$1,$B$1) -> 0
A109: Market Capitalization | B109: FH_MCAP | C109: =_xll.EQNXTDZ($A$1,$B109,C$1,$B$1) -> 0 | D109: =_xll.EQNXTDZ($A$1,$B109,D$1,$B$1) -> 0 | E109: =_xll.EQNXTDZ($A$1,$B109,E$1,$B$1) -> 0 | F109: =_xll.EQNXTDZ($A$1,$B109,F$1,$B$1) -> 0 | G109: =_xll.EQNXTDZ($A$1,$B109,G$1,$B$1) -> 0 | H109: =_xll.EQNXTDZ($A$1,$B109,H$1,$B$1) -> 0 | I109: =_xll.EQNXTDZ($A$1,$B109,I$1,$B$1) -> 0 | J109: =_xll.EQNXTDZ($A$1,$B109,J$1,$B$1) -> 0 | ... AF109: =_xll.EQNXTDZ($A$1,$B109,AF$1,$B$1) -> 0
A110: Adj DPS(Rs) | B110: FR_ADJ_DPS | C110: =_xll.EQNXTDZ($A$1,$B110,C$1,$B$1) -> 0.125 | D110: =_xll.EQNXTDZ($A$1,$B110,D$1,$B$1) -> 0.25 | E110: =_xll.EQNXTDZ($A$1,$B110,E$1,$B$1) -> 0.1 | F110: =_xll.EQNXTDZ($A$1,$B110,F$1,$B$1) -> 0.125 | G110: =_xll.EQNXTDZ($A$1,$B110,G$1,$B$1) -> 0.25 | H110: =_xll.EQNXTDZ($A$1,$B110,H$1,$B$1) -> 0.25 | I110: =_xll.EQNXTDZ($A$1,$B110,I$1,$B$1) -> 0.25 | J110: =_xll.EQNXTDZ($A$1,$B110,J$1,$B$1) -> 0.5 | ... AF110: =_xll.EQNXTDZ($A$1,$B110,AF$1,$B$1) -> 0
A111: Date End | B111: SHP_DATE_END | C111: =_xll.EQNXTDZ($A$1,$B111,C$5) -> 0 | D111: =_xll.EQNXTDZ($A$1,$B111,D$5) -> 0 | E111: =_xll.EQNXTDZ($A$1,$B111,E$5) -> 0 | F111: =_xll.EQNXTDZ($A$1,$B111,F$5) -> 0 | G111: =_xll.EQNXTDZ($A$1,$B111,G$5) -> 0 | H111: =_xll.EQNXTDZ($A$1,$B111,H$5) -> 0 | I111: =_xll.EQNXTDZ($A$1,$B111,I$5) -> 0 | J111: =_xll.EQNXTDZ($A$1,$B111,J$5) -> 0 | ... AF111: =_xll.EQNXTDZ($A$1,$B111,AF$5) -> 0
A112: Total of Promoter and Promoter Group | B112: SHP_TPFTOTALPROMOTER | C112: =_xll.EQNXTDZ($A$1,$B112,C$5) -> 0 | D112: =_xll.EQNXTDZ($A$1,$B112,D$5) -> 0 | E112: =_xll.EQNXTDZ($A$1,$B112,E$5) -> 0 | F112: =_xll.EQNXTDZ($A$1,$B112,F$5) -> 0 | G112: =_xll.EQNXTDZ($A$1,$B112,G$5) -> 0 | H112: =_xll.EQNXTDZ($A$1,$B112,H$5) -> 0 | I112: =_xll.EQNXTDZ($A$1,$B112,I$5) -> 0 | J112: =_xll.EQNXTDZ($A$1,$B112,J$5) -> 0 | ... AF112: =_xll.EQNXTDZ($A$1,$B112,AF$5) -> 0
A113: Total of Promoter and Promoter Group Pledged | B113: SHP_PSHFTOTALPROMOTER | C113: =_xll.EQNXTDZ($A$1,$B113,C$5) -> 0 | D113: =_xll.EQNXTDZ($A$1,$B113,D$5) -> 0 | E113: =_xll.EQNXTDZ($A$1,$B113,E$5) -> 0 | F113: =_xll.EQNXTDZ($A$1,$B113,F$5) -> 0 | G113: =_xll.EQNXTDZ($A$1,$B113,G$5) -> 0 | H113: =_xll.EQNXTDZ($A$1,$B113,H$5) -> 0 | I113: =_xll.EQNXTDZ($A$1,$B113,I$5) -> 0 | J113: =_xll.EQNXTDZ($A$1,$B113,J$5) -> 0 | ... AF113: =_xll.EQNXTDZ($A$1,$B113,AF$5) -> 0

Sheet QTR Share Price
A1: ='QTR Raw'!A1 -> 208433 | C1: 201206 | D1: 201207 | E1: 201208 | F1: 201209 | G1: 201210 | H1: 201211 | I1: 201212 | J1: 201301 | K1: 201302 | L1: 201303 | M1: 201304 | N1: 201305 | O1: 201306 | P1: 201307 | Q1: 201308 | R1: 201309 | S1: 201310 | T1: 201311 | U1: 201312 | V1: 201401 | W1: 201402 | X1: 201403 | Y1: 201404 | Z1: 201405 | AA1: 201406 | AB1: 201407 | AC1: 201408 | AD1: 201409 | AE1: 201410 | AF1: 201411 | AG1: 201412 | AH1: 201501 | AI1: 201502 | AJ1: 201503 | AK1: 201504 | AL1: 201505 | AM1: 201506 | AN1: 201507 | AO1: 201508 | AP1: 201509 | AQ1: 201510 | AR1: 201511 | AS1: 201512 | AT1: 201601 | AU1: 201602 | AV1: 201603 | AW1: 201604 | AX1: 201605 | AY1: 201606 | AZ1: 201607 | BA1: 201608 | BB1: 201609 | BC1: 201610 | BD1: 201611 | BE1: 201612 | BF1: 201701 | BG1: 201702 | BH1: 201703 | BI1: 201704 | BJ1: 201705 | BK1: 201706 | BL1: 201707 | BM1: 201708 | BN1: 201709 | BO1: 201710 | BP1: 201711 | BQ1: 201712 | BR1: 201801 | BS1: 201802 | BT1: 201803 | BU1: 201804 | BV1: 201805 | BW1: 201806 | BX1: 201807 | BY1: 201808 | BZ1: 201809 | CA1: 201810 | CB1: 201811 | CC1: 201812 | CD1: 201901 | CE1: 201902 | CF1: 201903 | CG1: 201904 | CH1: 201905 | CI1: 201906 | CJ1: 201907 | CK1: 201908 | CL1: 201909 | CM1: 201910 | CN1: 201911 | CO1: 201912 | CP1: 202001 | CQ1: 202002 | CR1: 202003 | CS1: 202004 | CT1: 202005 | CU1: 202006 | CV1: 202007 | CW1: 202008 | CX1: 202009 | CY1: 202010 | CZ1: 202011 | DA1: 202012 | DB1: 202101 | DC1: 202102 | DD1: 202103 | DE1: 202104 | DF1: 202105 | DG1: 202106 | DH1: 202107 | DI1: 202108 | DJ1: 202109 | DK1: 202110 | DL1: 202111 | DM1: 202112 | DN1: 202201 | DO1: 202202 | DP1: 202203 | DQ1: 202204 | DR1: 202205 | DS1: 202206 | DT1: 202207 | DU1: 202208 | DV1: 202209 | DW1: 202210 | DX1: 202211 | DY1: 202212 | DZ1: 202301 | EA1: 202302 | EB1: 202303 | EC1: 202304 | ED1: 202305 | EE1: 202306 | EF1: 202307 | EG1: 202308 | EH1: 202309 | EI1: 202310 | EJ1: 202311 | EK1: 202312 | EL1: 202401 | EM1: 202402 | EN1: 202403 | EO1: 202404 | EP1: 202405 | EQ1: 202406 | ER1: 202407 | ES1: 202408 | ET1: 202409 | EU1: 202410 | EV1: 202411 | EW1: 202412 | EX1: 202501 | EY1: 202502 | EZ1: 202503 | FA1: 202504 | FB1: 202505 | FC1: 202506 | FD1: 202507 | FE1: 202508 | FF1: 202509 | FG1: 202510 | FH1: 202511 | FI1: 202512 | FJ1: 202601 | FK1: 202602 | FL1: 202603 | FM1: 202604 | FN1: 202605 | FO1: 202606 | FP1: 202607 | FQ1: 202608 | FR1: 202609 | FS1: 202610 | FT1: 202611 | FU1: 202612 | FV1: 202701 | FW1: 202702 | FX1: 202703 | FY1: 202704 | FZ1: 202705 | GA1: 202706 | GB1: 202707 | GC1: 202708 | GD1: 202709 | GE1: 202710 | GF1: 202711 | GG1: 202712 | GH1: 202801 | GI1: 202802 | GJ1: 202803 | GK1: 202804 | GL1: 202805 | GM1: 202806 | GN1: 202807 | GO1: 202808 | GP1: 202809 | GQ1: 202810 | GR1: 202811 | GS1: 202812 | GT1: 202901 | GU1: 202902 | GV1: 202903 | GW1: 202904 | GX1: 202905 | GY1: 202906 | GZ1: 202907 | HA1: 202908 | HB1: 202909 | HC1: 202910 | HD1: 202911 | HE1: 202912 | HF1: 203001 | HG1: 203002 | HH1: 203003 | HM1: 201206 | HN1: 201207 | HO1: 201208 | HP1: 201209 | HQ1: 201212 | HR1: 201303 | HS1: 201306 | HT1: 201309 | HU1: 201312 | HV1: 201403 | HW1: 201406 | HX1: 201409 | HY1: 201412 | HZ1: 201503 | IA1: 201506 | IB1: 201509 | IC1: 201512 | ID1: 201603 | IE1: 201606 | IF1: 201609 | IG1: 201612 | IH1: 201703 | II1: 201706 | IJ1: 201709 | IK1: 201712 | IL1: 201803 | IM1: 201806 | IN1: 201809 | IO1: 201812 | IP1: 201903 | IQ1: 201906 | IR1: 201909 | IS1: 201912 | IT1: 202003 | IU1: 202006 | IV1: 202009 | IW1: 202012 | IX1: 202103 | IY1: 202106 | IZ1: 202109 | JA1: 202112 | JB1: 202203 | JC1: 202206 | JD1: 202209 | JE1: 202212 | JF1: 202303 | JG1: 202306 | JH1: 202309 | JI1: 202312 | JJ1: 202403 | JK1: 202406 | JL1: 202409 | JM1: 202412 | JN1: 202503 | JO1: 202506 | JP1: 202509 | JQ1: 202512 | JR1: 202603 | JS1: 202606 | JT1: 202609 | JU1: 202612 | JV1: 202703 | JW1: 202706 | JX1: 202709 | JY1: 202712 | JZ1: 202803 | KA1: 202806 | KB1: 202809 | KC1: 202812 | KD1: 202903 | KE1: 202906 | KF1: 202909 | KG1: 202912 | KH1: 203003
FF2: 45901 | FG2: =+EOMONTH(FF2,1) -> 45961 | FH2: =+EOMONTH(FG2,1) -> 45991 | FI2: =+EOMONTH(FH2,1) -> 46022 | FJ2: =+EOMONTH(FI2,1) -> 46053 | FK2: =+EOMONTH(FJ2,1) -> 46081 | FL2: =+EOMONTH(FK2,1) -> 46112 | FM2: =+EOMONTH(FL2,1) -> 46142 | FN2: =+EOMONTH(FM2,1) -> 46173 | ... HH2: =+EOMONTH(HG2,1) -> 47573
A4: Field Description | B4: Field Name
A5: MonthEnd | B5: NMONTH_MONTHEND | C5: {=_xll.EQNXTDZ($A$1,$B5,C$1)} -> 0 | D5: {=_xll.EQNXTDZ($A$1,$B5,D$1)} -> 0 | E5: {=_xll.EQNXTDZ($A$1,$B5,E$1)} -> 0 | F5: {=_xll.EQNXTDZ($A$1,$B5,F$1)} -> 0 | G5: {=_xll.EQNXTDZ($A$1,$B5,G$1)} -> 0 | H5: {=_xll.EQNXTDZ($A$1,$B5,H$1)} -> 0 | I5: {=_xll.EQNXTDZ($A$1,$B5,I$1)} -> 0 | J5: {=_xll.EQNXTDZ($A$1,$B5,J$1)} -> 0 | ... HH5: {=_xll.EQNXTDZ($A$1,$B5,HH$1)} -> 0
A6: Open | B6: NMONTH_OPEN | C6: {=_xll.EQNXTDZ($A$1,$B6,C$1)} -> 0 | D6: {=_xll.EQNXTDZ($A$1,$B6,D$1)} -> 0 | E6: {=_xll.EQNXTDZ($A$1,$B6,E$1)} -> 0 | F6: {=_xll.EQNXTDZ($A$1,$B6,F$1)} -> 0 | G6: {=_xll.EQNXTDZ($A$1,$B6,G$1)} -> 0 | H6: {=_xll.EQNXTDZ($A$1,$B6,H$1)} -> 0 | I6: {=_xll.EQNXTDZ($A$1,$B6,I$1)} -> 0 | J6: {=_xll.EQNXTDZ($A$1,$B6,J$1)} -> 0 | ... HH6: {=_xll.EQNXTDZ($A$1,$B6,HH$1)} -> 0
A7: High | B7: NMONTH_HIGH | C7: {=_xll.EQNXTDZ($A$1,$B7,C$1)} -> 0 | D7: {=_xll.EQNXTDZ($A$1,$B7,D$1)} -> 0 | E7: {=_xll.EQNXTDZ($A$1,$B7,E$1)} -> 0 | F7: {=_xll.EQNXTDZ($A$1,$B7,F$1)} -> 0 | G7: {=_xll.EQNXTDZ($A$1,$B7,G$1)} -> 0 | H7: {=_xll.EQNXTDZ($A$1,$B7,H$1)} -> 0 | I7: {=_xll.EQNXTDZ($A$1,$B7,I$1)} -> 0 | J7: {=_xll.EQNXTDZ($A$1,$B7,J$1)} -> 0 | ... HH7: {=_xll.EQNXTDZ($A$1,$B7,HH$1)} -> 0 | HP7: =+MAX(D7:F7) -> 0 | HQ7: =+MAX(G7:I7) -> 0 | HR7: =+MAX(J7:L7) -> 0 | HS7: =+MAX(M7:O7) -> 0 | HT7: =+MAX(P7:R7) -> 0 | HU7: =+MAX(S7:U7) -> 0 | HV7: =+MAX(V7:X7) -> 0 | HW7: =+MAX(Y7:AA7) -> 0 | HX7: =+MAX(AB7:AD7) -> 0 | HY7: =+MAX(AE7:AG7) -> 0 | HZ7: =+MAX(AH7:AJ7) -> 0 | IA7: =+MAX(AK7:AM7) -> 0 | IB7: =+MAX(AN7:AP7) -> 0 | IC7: =+MAX(AQ7:AS7) -> 0 | ID7: =+MAX(AT7:AV7) -> 0 | IE7: =+MAX(AW7:AY7) -> 0 | IF7: =+MAX(AZ7:BB7) -> 0 | IG7: =+MAX(BC7:BE7) -> 0 | IH7: =+MAX(BF7:BH7) -> 0 | II7: =+MAX(BI7:BK7) -> 0 | IJ7: =+MAX(BL7:BN7) -> 0 | IK7: =+MAX(BO7:BQ7) -> 0 | IL7: =+MAX(BR7:BT7) -> 0 | IM7: =+MAX(BU7:BW7) -> 0 | IN7: =+MAX(BX7:BZ7) -> 0 | IO7: =+MAX(CA7:CC7) -> 0 | IP7: =+MAX(CD7:CF7) -> 0 | IQ7: =+MAX(CG7:CI7) -> 0 | IR7: =+MAX(CJ7:CL7) -> 0 | IS7: =+MAX(CM7:CO7) -> 0 | IT7: =+MAX(CP7:CR7) -> 0 | IU7: =+MAX(CS7:CU7) -> 0 | IV7: =+MAX(CV7:CX7) -> 0 | IW7: =+MAX(CY7:DA7) -> 0 | IX7: =+MAX(DB7:DD7) -> 0 | IY7: =+MAX(DE7:DG7) -> 0 | IZ7: =+MAX(DH7:DJ7) -> 0 | JA7: =+MAX(DK7:DM7) -> 0 | JB7: =+MAX(DN7:DP7) -> 0 | JC7: =+MAX(DQ7:DS7) -> 0 | JD7: =+MAX(DT7:DV7) -> 0 | JE7: =+MAX(DW7:DY7) -> 0 | JF7: =+MAX(DZ7:EB7) -> 0 | JG7: =+MAX(EC7:EE7) -> 0 | JH7: =+MAX(EF7:EH7) -> 0 | JI7: =+MAX(EI7:EK7) -> 990 | JJ7: =+MAX(EL7:EN7) -> 1323 | JK7: =MAX(EO7:EQ7) -> 1473 | JL7: =MAX(ER7:ET7) -> 1506.9 | JM7: =MAX(EU7:EW7) -> 1247 | JN7: =MAX(EX7:EZ7) -> 1113.3 | JO7: =MAX(FA7:FC7) -> 1263 | JP7: =MAX(FD7:FF7) -> 1288 | JQ7: =MAX(FG7:FI7) -> 1260 | JR7: =MAX(FJ7:FL7) -> 1262 | JS7: =MAX(FM7:FO7) -> 1980 | JT7: =MAX(FP7:FR7) -> 0 | JU7: =MAX(FS7:FU7) -> 0 | JV7: =MAX(FV7:FX7) -> 0 | JW7: =MAX(FY7:GA7) -> 0 | JX7: =MAX(GB7:GD7) -> 0 | JY7: =MAX(GE7:GG7) -> 0 | JZ7: =MAX(GH7:GJ7) -> 0 | KA7: =MAX(GK7:GM7) -> 0 | KB7: =MAX(GN7:GP7) -> 0 | KC7: =MAX(GQ7:GS7) -> 0 | KD7: =MAX(GT7:GV7) -> 0 | KE7: =MAX(GW7:GY7) -> 0 | KF7: =MAX(GZ7:HB7) -> 0 | KG7: =MAX(HC7:HE7) -> 0 | KH7: =MAX(HF7:HH7) -> 0
A8: Low | B8: NMONTH_LOW | C8: {=_xll.EQNXTDZ($A$1,$B8,C$1)} -> 0 | D8: {=_xll.EQNXTDZ($A$1,$B8,D$1)} -> 0 | E8: {=_xll.EQNXTDZ($A$1,$B8,E$1)} -> 0 | F8: {=_xll.EQNXTDZ($A$1,$B8,F$1)} -> 0 | G8: {=_xll.EQNXTDZ($A$1,$B8,G$1)} -> 0 | H8: {=_xll.EQNXTDZ($A$1,$B8,H$1)} -> 0 | I8: {=_xll.EQNXTDZ($A$1,$B8,I$1)} -> 0 | J8: {=_xll.EQNXTDZ($A$1,$B8,J$1)} -> 0 | ... HH8: {=_xll.EQNXTDZ($A$1,$B8,HH$1)} -> 0 | HP8: =+MIN(D8:F8) -> 0 | HQ8: =+MIN(G8:I8) -> 0 | HR8: =+MIN(J8:L8) -> 0 | HS8: =+MIN(M8:O8) -> 0 | HT8: =+MIN(P8:R8) -> 0 | HU8: =+MIN(S8:U8) -> 0 | HV8: =+MIN(V8:X8) -> 0 | HW8: =+MIN(Y8:AA8) -> 0 | HX8: =+MIN(AB8:AD8) -> 0 | HY8: =+MIN(AE8:AG8) -> 0 | HZ8: =+MIN(AH8:AJ8) -> 0 | IA8: =+MIN(AK8:AM8) -> 0 | IB8: =+MIN(AN8:AP8) -> 0 | IC8: =+MIN(AQ8:AS8) -> 0 | ID8: =+MIN(AT8:AV8) -> 0 | IE8: =+MIN(AW8:AY8) -> 0 | IF8: =+MIN(AZ8:BB8) -> 0 | IG8: =+MIN(BC8:BE8) -> 0 | IH8: =+MIN(BF8:BH8) -> 0 | II8: =+MIN(BI8:BK8) -> 0 | IJ8: =+MIN(BL8:BN8) -> 0 | IK8: =+MIN(BO8:BQ8) -> 0 | IL8: =+MIN(BR8:BT8) -> 0 | IM8: =+MIN(BU8:BW8) -> 0 | IN8: =+MIN(BX8:BZ8) -> 0 | IO8: =+MIN(CA8:CC8) -> 0 | IP8: =+MIN(CD8:CF8) -> 0 | IQ8: =+MIN(CG8:CI8) -> 0 | IR8: =+MIN(CJ8:CL8) -> 0 | IS8: =+MIN(CM8:CO8) -> 0 | IT8: =+MIN(CP8:CR8) -> 0 | IU8: =+MIN(CS8:CU8) -> 0 | IV8: =+MIN(CV8:CX8) -> 0 | IW8: =+MIN(CY8:DA8) -> 0 | IX8: =+MIN(DB8:DD8) -> 0 | IY8: =+MIN(DE8:DG8) -> 0 | IZ8: =+MIN(DH8:DJ8) -> 0 | JA8: =+MIN(DK8:DM8) -> 0 | JB8: =+MIN(DN8:DP8) -> 0 | JC8: =+MIN(DQ8:DS8) -> 0 | JD8: =+MIN(DT8:DV8) -> 0 | JE8: =+MIN(DW8:DY8) -> 0 | JF8: =+MIN(DZ8:EB8) -> 0 | JG8: =+MIN(EC8:EE8) -> 0 | JH8: =+MIN(EF8:EH8) -> 0 | JI8: =+MIN(EI8:EK8) -> 0 | JJ8: =+MIN(EL8:EN8) -> 801.55 | JK8: =MIN(EO8:EQ8) -> 1111.15 | JL8: =MIN(ER8:ET8) -> 1079.55 | JM8: =MIN(EU8:EW8) -> 1063.25 | JN8: =MIN(EX8:EZ8) -> 884.2 | JO8: =MIN(FA8:FC8) -> 892.25 | JP8: =MIN(FD8:FF8) -> 1065 | JQ8: =MIN(FG8:FI8) -> 1083.1 | JR8: =MIN(FJ8:FL8) -> 1068.2 | JS8: =MIN(FM8:FO8) -> 1190.2 | JT8: =MIN(FP8:FR8) -> 0 | JU8: =MIN(FS8:FU8) -> 0 | JV8: =MIN(FV8:FX8) -> 0 | JW8: =MIN(FY8:GA8) -> 0 | JX8: =MIN(GB8:GD8) -> 0 | JY8: =MIN(GE8:GG8) -> 0 | JZ8: =MIN(GH8:GJ8) -> 0 | KA8: =MIN(GK8:GM8) -> 0 | KB8: =MIN(GN8:GP8) -> 0 | KC8: =MIN(GQ8:GS8) -> 0 | KD8: =MIN(GT8:GV8) -> 0 | KE8: =MIN(GW8:GY8) -> 0 | KF8: =MIN(GZ8:HB8) -> 0 | KG8: =MIN(HC8:HE8) -> 0 | KH8: =MIN(HF8:HH8) -> 0
A9: Close | B9: NMONTH_CLOSE | C9: {=_xll.EQNXTDZ($A$1,$B9,C$1)} -> 0 | D9: {=_xll.EQNXTDZ($A$1,$B9,D$1)} -> 0 | E9: {=_xll.EQNXTDZ($A$1,$B9,E$1)} -> 0 | F9: {=_xll.EQNXTDZ($A$1,$B9,F$1)} -> 0 | G9: {=_xll.EQNXTDZ($A$1,$B9,G$1)} -> 0 | H9: {=_xll.EQNXTDZ($A$1,$B9,H$1)} -> 0 | I9: {=_xll.EQNXTDZ($A$1,$B9,I$1)} -> 0 | J9: {=_xll.EQNXTDZ($A$1,$B9,J$1)} -> 0 | ... HH9: {=_xll.EQNXTDZ($A$1,$B9,HH$1)} -> 0 | HP9: =+F9 -> 0 | HQ9: =+I9 -> 0 | HR9: =+L9 -> 0 | HS9: =+O9 -> 0 | HT9: =+R9 -> 0 | HU9: =+U9 -> 0 | HV9: =+X9 -> 0 | HW9: =+AA9 -> 0 | HX9: =+AD9 -> 0 | HY9: =+AG9 -> 0 | HZ9: =+AJ9 -> 0 | IA9: =+AM9 -> 0 | IB9: =+AP9 -> 0 | IC9: =+AS9 -> 0 | ID9: =+AV9 -> 0 | IE9: =+AY9 -> 0 | IF9: =+BB9 -> 0 | IG9: =+BE9 -> 0 | IH9: =+BH9 -> 0 | II9: =+BK9 -> 0 | IJ9: =+BN9 -> 0 | IK9: =+BQ9 -> 0 | IL9: =+BT9 -> 0 | IM9: =+BW9 -> 0 | IN9: =+BZ9 -> 0 | IO9: =+CC9 -> 0 | IP9: =+CF9 -> 0 | IQ9: =+CI9 -> 0 | IR9: =+CL9 -> 0 | IS9: =+CO9 -> 0 | IT9: =+CR9 -> 0 | IU9: =+CU9 -> 0 | IV9: =+CX9 -> 0 | IW9: =+DA9 -> 0 | IX9: =+DD9 -> 0 | IY9: =+DG9 -> 0 | IZ9: =+DJ9 -> 0 | JA9: =+DM9 -> 0 | JB9: =+DP9 -> 0 | JC9: =+DS9 -> 0 | JD9: =+DV9 -> 0 | JE9: =+DY9 -> 0 | JF9: =+EB9 -> 0 | JG9: =+EE9 -> 0 | JH9: =+EH9 -> 0 | JI9: =+EK9 -> 882.6 | JJ9: =+EN9 -> 1222.65 | JK9: =EQ9 -> 1315.5 | JL9: =ET9 -> 1168.1 | JM9: =EW9 -> 1106.85 | JN9: =EZ9 -> 1000.55 | JO9: =FC9 -> 1230 | JP9: =FF9 -> 1178.1 | JQ9: =FI9 -> 1134.1 | JR9: =FL9 -> 1175 | JS9: =FO9 -> 1839.6 | JT9: =FR9 -> 0 | JU9: =FU9 -> 0 | JV9: =FX9 -> 0 | JW9: =GA9 -> 0 | JX9: =GD9 -> 0 | JY9: =GG9 -> 0 | JZ9: =GJ9 -> 0 | KA9: =GM9 -> 0 | KB9: =GP9 -> 0 | KC9: =GS9 -> 0 | KD9: =GV9 -> 0 | KE9: =GY9 -> 0 | KF9: =HB9 -> 0 | KG9: =HE9 -> 0 | KH9: =HH9 -> 0
A11: Field Description | B11: Field Name | C11: {=_xll.EQNXTDZ($A$1,$B11,C$1)} -> 0 | D11: {=_xll.EQNXTDZ($A$1,$B11,D$1)} -> 0 | E11: {=_xll.EQNXTDZ($A$1,$B11,E$1)} -> 0 | F11: {=_xll.EQNXTDZ($A$1,$B11,F$1)} -> 0 | G11: {=_xll.EQNXTDZ($A$1,$B11,G$1)} -> 0 | H11: {=_xll.EQNXTDZ($A$1,$B11,H$1)} -> 0 | I11: {=_xll.EQNXTDZ($A$1,$B11,I$1)} -> 0 | J11: {=_xll.EQNXTDZ($A$1,$B11,J$1)} -> 0 | ... HH11: {=_xll.EQNXTDZ($A$1,$B11,HH$1)} -> 0
A12: Month End | B12: BMONTH_MONTHEND | C12: {=_xll.EQNXTDZ($A$1,$B12,C$1)} -> 0 | D12: {=_xll.EQNXTDZ($A$1,$B12,D$1)} -> 0 | E12: {=_xll.EQNXTDZ($A$1,$B12,E$1)} -> 0 | F12: {=_xll.EQNXTDZ($A$1,$B12,F$1)} -> 0 | G12: {=_xll.EQNXTDZ($A$1,$B12,G$1)} -> 0 | H12: {=_xll.EQNXTDZ($A$1,$B12,H$1)} -> 0 | I12: {=_xll.EQNXTDZ($A$1,$B12,I$1)} -> 0 | J12: {=_xll.EQNXTDZ($A$1,$B12,J$1)} -> 0 | ... HH12: {=_xll.EQNXTDZ($A$1,$B12,HH$1)} -> 0
A13: Open | B13: BMONTH_OPEN | C13: {=_xll.EQNXTDZ($A$1,$B13,C$1)} -> 0 | D13: {=_xll.EQNXTDZ($A$1,$B13,D$1)} -> 0 | E13: {=_xll.EQNXTDZ($A$1,$B13,E$1)} -> 0 | F13: {=_xll.EQNXTDZ($A$1,$B13,F$1)} -> 0 | G13: {=_xll.EQNXTDZ($A$1,$B13,G$1)} -> 0 | H13: {=_xll.EQNXTDZ($A$1,$B13,H$1)} -> 0 | I13: {=_xll.EQNXTDZ($A$1,$B13,I$1)} -> 0 | J13: {=_xll.EQNXTDZ($A$1,$B13,J$1)} -> 0 | ... HH13: {=_xll.EQNXTDZ($A$1,$B13,HH$1)} -> 0
A14: High | B14: BMONTH_HIGH | C14: {=_xll.EQNXTDZ($A$1,$B14,C$1)} -> 0 | D14: {=_xll.EQNXTDZ($A$1,$B14,D$1)} -> 0 | E14: {=_xll.EQNXTDZ($A$1,$B14,E$1)} -> 0 | F14: {=_xll.EQNXTDZ($A$1,$B14,F$1)} -> 0 | G14: {=_xll.EQNXTDZ($A$1,$B14,G$1)} -> 0 | H14: {=_xll.EQNXTDZ($A$1,$B14,H$1)} -> 0 | I14: {=_xll.EQNXTDZ($A$1,$B14,I$1)} -> 0 | J14: {=_xll.EQNXTDZ($A$1,$B14,J$1)} -> 0 | ... HH14: {=_xll.EQNXTDZ($A$1,$B14,HH$1)} -> 0 | HP14: =+MAX(D14:F14) -> 0 | HQ14: =+MAX(G14:I14) -> 0 | HR14: =+MAX(J14:L14) -> 0 | HS14: =+MAX(M14:O14) -> 0 | HT14: =+MAX(P14:R14) -> 0 | HU14: =+MAX(S14:U14) -> 0 | HV14: =+MAX(V14:X14) -> 0 | HW14: =+MAX(Y14:AA14) -> 0 | HX14: =+MAX(AB14:AD14) -> 0 | HY14: =+MAX(AE14:AG14) -> 0 | HZ14: =+MAX(AH14:AJ14) -> 0 | IA14: =+MAX(AK14:AM14) -> 0 | IB14: =+MAX(AN14:AP14) -> 0 | IC14: =+MAX(AQ14:AS14) -> 0 | ID14: =+MAX(AT14:AV14) -> 0 | IE14: =+MAX(AW14:AY14) -> 0 | IF14: =+MAX(AZ14:BB14) -> 0 | IG14: =+MAX(BC14:BE14) -> 0 | IH14: =+MAX(BF14:BH14) -> 0 | II14: =+MAX(BI14:BK14) -> 0 | IJ14: =+MAX(BL14:BN14) -> 0 | IK14: =+MAX(BO14:BQ14) -> 0 | IL14: =+MAX(BR14:BT14) -> 0 | IM14: =+MAX(BU14:BW14) -> 0 | IN14: =+MAX(BX14:BZ14) -> 0 | IO14: =+MAX(CA14:CC14) -> 0 | IP14: =+MAX(CD14:CF14) -> 0 | IQ14: =+MAX(CG14:CI14) -> 0 | IR14: =+MAX(CJ14:CL14) -> 0 | IS14: =+MAX(CM14:CO14) -> 0 | IT14: =+MAX(CP14:CR14) -> 0 | IU14: =+MAX(CS14:CU14) -> 0 | IV14: =+MAX(CV14:CX14) -> 0 | IW14: =+MAX(CY14:DA14) -> 0 | IX14: =+MAX(DB14:DD14) -> 0 | IY14: =+MAX(DE14:DG14) -> 0 | IZ14: =+MAX(DH14:DJ14) -> 0 | JA14: =+MAX(DK14:DM14) -> 0 | JB14: =+MAX(DN14:DP14) -> 0 | JC14: =+MAX(DQ14:DS14) -> 0 | JD14: =+MAX(DT14:DV14) -> 0 | JE14: =+MAX(DW14:DY14) -> 0 | JF14: =+MAX(DZ14:EB14) -> 0 | JG14: =+MAX(EC14:EE14) -> 0 | JH14: =+MAX(EF14:EH14) -> 0 | JI14: =+MAX(EI14:EK14) -> 990 | JJ14: =+MAX(EL14:EN14) -> 1323 | JK14: =MAX(EO14:EQ14) -> 1471.95 | JL14: =MAX(ER14:ET14) -> 1507.2 | JM14: =MAX(EU14:EW14) -> 1246.15 | JN14: =MAX(EX14:EZ14) -> 1116.85 | JO14: =MAX(FA14:FC14) -> 1273.95 | JP14: =MAX(FD14:FF14) -> 1289 | JQ14: =MAX(FG14:FI14) -> 1259 | JR14: =MAX(FJ14:FL14) -> 1261.25 | JS14: =MAX(FM14:FO14) -> 1979 | JT14: =MAX(FP14:FR14) -> 0 | JU14: =MAX(FS14:FU14) -> 0 | JV14: =MAX(FV14:FX14) -> 0 | JW14: =MAX(FY14:GA14) -> 0 | JX14: =MAX(GB14:GD14) -> 0 | JY14: =MAX(GE14:GG14) -> 0 | JZ14: =MAX(GH14:GJ14) -> 0 | KA14: =MAX(GK14:GM14) -> 0 | KB14: =MAX(GN14:GP14) -> 0 | KC14: =MAX(GQ14:GS14) -> 0 | KD14: =MAX(GT14:GV14) -> 0 | KE14: =MAX(GW14:GY14) -> 0 | KF14: =MAX(GZ14:HB14) -> 0 | KG14: =MAX(HC14:HE14) -> 0 | KH14: =MAX(HF14:HH14) -> 0
A15: Low | B15: BMONTH_LOW | C15: {=_xll.EQNXTDZ($A$1,$B15,C$1)} -> 0 | D15: {=_xll.EQNXTDZ($A$1,$B15,D$1)} -> 0 | E15: {=_xll.EQNXTDZ($A$1,$B15,E$1)} -> 0 | F15: {=_xll.EQNXTDZ($A$1,$B15,F$1)} -> 0 | G15: {=_xll.EQNXTDZ($A$1,$B15,G$1)} -> 0 | H15: {=_xll.EQNXTDZ($A$1,$B15,H$1)} -> 0 | I15: {=_xll.EQNXTDZ($A$1,$B15,I$1)} -> 0 | J15: {=_xll.EQNXTDZ($A$1,$B15,J$1)} -> 0 | ... HH15: {=_xll.EQNXTDZ($A$1,$B15,HH$1)} -> 0 | HP15: =+MIN(D15:F15) -> 0 | HQ15: =+MIN(G15:I15) -> 0 | HR15: =+MIN(J15:L15) -> 0 | HS15: =+MIN(M15:O15) -> 0 | HT15: =+MIN(P15:R15) -> 0 | HU15: =+MIN(S15:U15) -> 0 | HV15: =+MIN(V15:X15) -> 0 | HW15: =+MIN(Y15:AA15) -> 0 | HX15: =+MIN(AB15:AD15) -> 0 | HY15: =+MIN(AE15:AG15) -> 0 | HZ15: =+MIN(AH15:AJ15) -> 0 | IA15: =+MIN(AK15:AM15) -> 0 | IB15: =+MIN(AN15:AP15) -> 0 | IC15: =+MIN(AQ15:AS15) -> 0 | ID15: =+MIN(AT15:AV15) -> 0 | IE15: =+MIN(AW15:AY15) -> 0 | IF15: =+MIN(AZ15:BB15) -> 0 | IG15: =+MIN(BC15:BE15) -> 0 | IH15: =+MIN(BF15:BH15) -> 0 | II15: =+MIN(BI15:BK15) -> 0 | IJ15: =+MIN(BL15:BN15) -> 0 | IK15: =+MIN(BO15:BQ15) -> 0 | IL15: =+MIN(BR15:BT15) -> 0 | IM15: =+MIN(BU15:BW15) -> 0 | IN15: =+MIN(BX15:BZ15) -> 0 | IO15: =+MIN(CA15:CC15) -> 0 | IP15: =+MIN(CD15:CF15) -> 0 | IQ15: =+MIN(CG15:CI15) -> 0 | IR15: =+MIN(CJ15:CL15) -> 0 | IS15: =+MIN(CM15:CO15) -> 0 | IT15: =+MIN(CP15:CR15) -> 0 | IU15: =+MIN(CS15:CU15) -> 0 | IV15: =+MIN(CV15:CX15) -> 0 | IW15: =+MIN(CY15:DA15) -> 0 | IX15: =+MIN(DB15:DD15) -> 0 | IY15: =+MIN(DE15:DG15) -> 0 | IZ15: =+MIN(DH15:DJ15) -> 0 | JA15: =+MIN(DK15:DM15) -> 0 | JB15: =+MIN(DN15:DP15) -> 0 | JC15: =+MIN(DQ15:DS15) -> 0 | JD15: =+MIN(DT15:DV15) -> 0 | JE15: =+MIN(DW15:DY15) -> 0 | JF15: =+MIN(DZ15:EB15) -> 0 | JG15: =+MIN(EC15:EE15) -> 0 | JH15: =+MIN(EF15:EH15) -> 0 | JI15: =+MIN(EI15:EK15) -> 0 | JJ15: =+MIN(EL15:EN15) -> 802.2 | JK15: =MIN(EO15:EQ15) -> 1111 | JL15: =MIN(ER15:ET15) -> 1080.7 | JM15: =MIN(EU15:EW15) -> 1059.05 | JN15: =MIN(EX15:EZ15) -> 884.65 | JO15: =MIN(FA15:FC15) -> 890.65 | JP15: =MIN(FD15:FF15) -> 1063.85 | JQ15: =MIN(FG15:FI15) -> 1077.85 | JR15: =MIN(FJ15:FL15) -> 1030.85 | JS15: =MIN(FM15:FO15) -> 1194.55 | JT15: =MIN(FP15:FR15) -> 0 | JU15: =MIN(FS15:FU15) -> 0 | JV15: =MIN(FV15:FX15) -> 0 | JW15: =MIN(FY15:GA15) -> 0 | JX15: =MIN(GB15:GD15) -> 0 | JY15: =MIN(GE15:GG15) -> 0 | JZ15: =MIN(GH15:GJ15) -> 0 | KA15: =MIN(GK15:GM15) -> 0 | KB15: =MIN(GN15:GP15) -> 0 | KC15: =MIN(GQ15:GS15) -> 0 | KD15: =MIN(GT15:GV15) -> 0 | KE15: =MIN(GW15:GY15) -> 0 | KF15: =MIN(GZ15:HB15) -> 0 | KG15: =MIN(HC15:HE15) -> 0 | KH15: =MIN(HF15:HH15) -> 0
A16: Close | B16: BMONTH_CLOSE | C16: {=_xll.EQNXTDZ($A$1,$B16,C$1)} -> 0 | D16: {=_xll.EQNXTDZ($A$1,$B16,D$1)} -> 0 | E16: {=_xll.EQNXTDZ($A$1,$B16,E$1)} -> 0 | F16: {=_xll.EQNXTDZ($A$1,$B16,F$1)} -> 0 | G16: {=_xll.EQNXTDZ($A$1,$B16,G$1)} -> 0 | H16: {=_xll.EQNXTDZ($A$1,$B16,H$1)} -> 0 | I16: {=_xll.EQNXTDZ($A$1,$B16,I$1)} -> 0 | J16: {=_xll.EQNXTDZ($A$1,$B16,J$1)} -> 0 | ... HH16: {=_xll.EQNXTDZ($A$1,$B16,HH$1)} -> 0 | HP16: =+F16 -> 0 | HQ16: =+I16 -> 0 | HR16: =+L16 -> 0 | HS16: =+O16 -> 0 | HT16: =+R16 -> 0 | HU16: =+U16 -> 0 | HV16: =+X16 -> 0 | HW16: =+AA16 -> 0 | HX16: =+AD16 -> 0 | HY16: =+AG16 -> 0 | HZ16: =+AJ16 -> 0 | IA16: =+AM16 -> 0 | IB16: =+AP16 -> 0 | IC16: =+AS16 -> 0 | ID16: =+AV16 -> 0 | IE16: =+AY16 -> 0 | IF16: =+BB16 -> 0 | IG16: =+BE16 -> 0 | IH16: =+BH16 -> 0 | II16: =+BK16 -> 0 | IJ16: =+BN16 -> 0 | IK16: =+BQ16 -> 0 | IL16: =+BT16 -> 0 | IM16: =+BW16 -> 0 | IN16: =+BZ16 -> 0 | IO16: =+CC16 -> 0 | IP16: =+CF16 -> 0 | IQ16: =+CI16 -> 0 | IR16: =+CL16 -> 0 | IS16: =+CO16 -> 0 | IT16: =+CR16 -> 0 | IU16: =+CU16 -> 0 | IV16: =+CX16 -> 0 | IW16: =+DA16 -> 0 | IX16: =+DD16 -> 0 | IY16: =+DG16 -> 0 | IZ16: =+DJ16 -> 0 | JA16: =+DM16 -> 0 | JB16: =+DP16 -> 0 | JC16: =+DS16 -> 0 | JD16: =+DV16 -> 0 | JE16: =+DY16 -> 0 | JF16: =+EB16 -> 0 | JG16: =+EE16 -> 0 | JH16: =+EH16 -> 0 | JI16: =+EK16 -> 883.35 | JJ16: =+EN16 -> 1220 | JK16: =EQ16 -> 1314.75 | JL16: =ET16 -> 1169.2 | JM16: =EW16 -> 1107.35 | JN16: =EZ16 -> 999.65 | JO16: =FC16 -> 1229.75 | JP16: =FF16 -> 1178.2 | JQ16: =FI16 -> 1134.8 | JR16: =FL16 -> 1172.75 | JS16: =FO16 -> 1840.3 | JT16: =FR16 -> 0 | JU16: =FU16 -> 0 | JV16: =FX16 -> 0 | JW16: =GA16 -> 0 | JX16: =GD16 -> 0 | JY16: =GG16 -> 0 | JZ16: =GJ16 -> 0 | KA16: =GM16 -> 0 | KB16: =GP16 -> 0 | KC16: =GS16 -> 0 | KD16: =GV16 -> 0 | KE16: =GY16 -> 0 | KF16: =HB16 -> 0 | KG16: =HE16 -> 0 | KH16: =HH16 -> 0
A19: High | HP19: =+IF(HP14=0,HP7,HP14) -> 0 | HQ19: =+IF(HQ14=0,HQ7,HQ14) -> 0 | HR19: =+IF(HR14=0,HR7,HR14) -> 0 | HS19: =+IF(HS14=0,HS7,HS14) -> 0 | HT19: =+IF(HT14=0,HT7,HT14) -> 0 | HU19: =+IF(HU14=0,HU7,HU14) -> 0 | HV19: =+IF(HV14=0,HV7,HV14) -> 0 | HW19: =+IF(HW14=0,HW7,HW14) -> 0 | ... KH19: =+IF(KH14=0,KH7,KH14) -> 0
A20: Low | HP20: =+IF(HP15=0,HP8,HP15) -> 0 | HQ20: =+IF(HQ15=0,HQ8,HQ15) -> 0 | HR20: =+IF(HR15=0,HR8,HR15) -> 0 | HS20: =+IF(HS15=0,HS8,HS15) -> 0 | HT20: =+IF(HT15=0,HT8,HT15) -> 0 | HU20: =+IF(HU15=0,HU8,HU15) -> 0 | HV20: =+IF(HV15=0,HV8,HV15) -> 0 | HW20: =+IF(HW15=0,HW8,HW15) -> 0 | ... KH20: =+IF(KH15=0,KH8,KH15) -> 0
A21: Close | HP21: =+IF(HP16=0,HP9,HP16) -> 0 | HQ21: =+IF(HQ16=0,HQ9,HQ16) -> 0 | HR21: =+IF(HR16=0,HR9,HR16) -> 0 | HS21: =+IF(HS16=0,HS9,HS16) -> 0 | HT21: =+IF(HT16=0,HT9,HT16) -> 0 | HU21: =+IF(HU16=0,HU9,HU16) -> 0 | HV21: =+IF(HV16=0,HV9,HV16) -> 0 | HW21: =+IF(HW16=0,HW9,HW16) -> 0 | ... KH21: =+IF(KH16=0,KH9,KH16) -> 0

Sheet QTR No. of Shares
A1: ='QTR Raw'!A1 -> 208433 | C1: 201206 | D1: 201209 | E1: 201212 | F1: 201303 | G1: 201306 | H1: 201309 | I1: 201312 | J1: 201403 | K1: 201406 | L1: 201409 | M1: 201412 | N1: 201503 | O1: 201506 | P1: 201509 | Q1: 201512 | R1: 201603 | S1: 201606 | T1: 201609 | U1: 201612 | V1: 201703 | W1: 201706 | X1: 201709 | Y1: 201712 | Z1: 201803 | AA1: 201806 | AB1: 201809 | AC1: 201812 | AD1: 201903 | AE1: 201906 | AF1: 201909 | AG1: 201912 | AH1: 202003 | AI1: 202006 | AJ1: 202009 | AK1: 202012 | AL1: 202103 | AM1: 202106 | AN1: 202109 | AO1: 202112 | AP1: 202203 | AQ1: 202206 | AR1: 202209 | AS1: 202212 | AT1: 202303 | AU1: 202306 | AV1: 202309 | AW1: 202312 | AX1: 202403 | AY1: 202406
A4: Field Description | B4: Field Name
A5: Date End | B5: SHP_DATE_END | C5: {=_xll.EQNXTDZ($A$1,$B5,C$1)} -> 0 | D5: {=_xll.EQNXTDZ($A$1,$B5,D$1)} -> 0 | E5: {=_xll.EQNXTDZ($A$1,$B5,E$1)} -> 0 | F5: {=_xll.EQNXTDZ($A$1,$B5,F$1)} -> 0 | G5: {=_xll.EQNXTDZ($A$1,$B5,G$1)} -> 0 | H5: {=_xll.EQNXTDZ($A$1,$B5,H$1)} -> 201309 | I5: {=_xll.EQNXTDZ($A$1,$B5,I$1)} -> 0 | J5: {=_xll.EQNXTDZ($A$1,$B5,J$1)} -> 0 | ... AY5: {=_xll.EQNXTDZ($A$1,$B5,AY$1)} -> 202406
A6: Grand Total | B6: SHP_NSGRANDTOTAL | C6: {=_xll.EQNXTDZ($A$1,$B6,C$1)} -> 0 | D6: {=_xll.EQNXTDZ($A$1,$B6,D$1)} -> 0 | E6: {=_xll.EQNXTDZ($A$1,$B6,E$1)} -> 0 | F6: {=_xll.EQNXTDZ($A$1,$B6,F$1)} -> 0 | G6: {=_xll.EQNXTDZ($A$1,$B6,G$1)} -> 0 | H6: {=_xll.EQNXTDZ($A$1,$B6,H$1)} -> 9076350 | I6: {=_xll.EQNXTDZ($A$1,$B6,I$1)} -> 0 | J6: {=_xll.EQNXTDZ($A$1,$B6,J$1)} -> 0 | ... AY6: {=_xll.EQNXTDZ($A$1,$B6,AY$1)} -> 90763500
B7: In Crs. | C7: =+C6/10^7 -> 0 | D7: =+D6/10^7 -> 0 | E7: =+E6/10^7 -> 0 | F7: =+F6/10^7 -> 0 | G7: =+G6/10^7 -> 0 | H7: =+H6/10^7 -> 0.907635 | I7: =+I6/10^7 -> 0 | J7: =+J6/10^7 -> 0 | ... AY7: =+AY6/10^7 -> 9.07635

Sheet Share price Daily
A1: =_xll.EQNXTH(B1,"[ADJC];[ADJH];[ADJL];[ADJO];[UCLS];[VOLUME]","2015-Jan-01","Y","All traded days","Asc") -> EQNXTH | B1: =+'Annual Raw'!A1 -> 208433 | L1: =_xll.EQNXTH(B1,"[NADJC];[NADJH];[NADJLOW];[NADJOPEN];[NUCLOSE];[NVOLUME]","2015-Jan-01","Y","All traded days","Asc") -> EQNXTH
A2: Inox India Ltd. | L2: Inox India Ltd.
A3: DATE | B3: ADJHIGH | C3: ADJCLOSE | D3: ADJLOW | E3: ADJOPEN | F3: CLOSE | G3: VOLUME | L3: DATE | M3: ADJCLOSE | N3: ADJHIGH | O3: ADJLOW | P3: ADJOPEN | Q3: CLOSE | R3: VOLUME
A4: 45281 | B4: 990 | C4: 939.9 | D4: 855.2 | E4: 933.15 | F4: 939.9 | G4: 1645249 | L4: 45281 | M4: 939.95 | N4: 990 | O4: 855.1 | P4: 949.65 | Q4: 939.95 | R4: 27195021
A5: 45282 | B5: 959.65 | C5: 910.35 | D5: 906.25 | E5: 944 | F5: 910.35 | G5: 214859 | L5: 45282 | M5: 910.65 | N5: 959.9 | O5: 906.6 | P5: 945 | Q5: 910.65 | R5: 4189118
A6: 45286 | B6: 937.25 | C6: 929 | D6: 876.7 | E6: 910.8 | F6: 929 | G6: 173268 | L6: 45286 | M6: 928.85 | N6: 937.65 | O6: 876.6 | P6: 911.1 | Q6: 928.85 | R6: 3494031
A7: 45287 | B7: 944 | C7: 896.1 | D7: 893 | E7: 925.95 | F7: 896.1 | G7: 183908 | L7: 45287 | M7: 896.15 | N7: 944.35 | O7: 892.5 | P7: 926 | Q7: 896.15 | R7: 1537537
A8: 45288 | B8: 907.7 | C8: 888.55 | D8: 883.05 | E8: 902.15 | F8: 888.55 | G8: 61832 | L8: 45288 | M8: 889.3 | N8: 907 | O8: 886 | P8: 905 | Q8: 889.3 | R8: 831020
A9: 45289 | B9: 904.35 | C9: 883.35 | D9: 877 | E9: 888.85 | F9: 883.35 | G9: 45145 | L9: 45289 | M9: 882.6 | N9: 904.25 | O9: 877.05 | P9: 890 | Q9: 882.6 | R9: 974188
A10: 45292 | B10: 894.95 | C10: 878.15 | D10: 876.1 | E10: 883.2 | F10: 878.15 | G10: 58287 | L10: 45292 | M10: 878.4 | N10: 894.9 | O10: 876.1 | P10: 884.9 | Q10: 878.4 | R10: 395867
A11: 45293 | B11: 894 | C11: 875.9 | D11: 872 | E11: 878.35 | F11: 875.9 | G11: 25393 | L11: 45293 | M11: 875.55 | N11: 894.5 | O11: 871.65 | P11: 880 | Q11: 875.55 | R11: 510793
A12: 45294 | B12: 885 | C12: 876.05 | D12: 867.4 | E12: 872.15 | F12: 876.05 | G12: 75423 | L12: 45294 | M12: 874.9 | N12: 886 | O12: 865.05 | P12: 873.05 | Q12: 874.9 | R12: 500473
A13: 45295 | B13: 912.4 | C13: 902.3 | D13: 876.1 | E13: 876.1 | F13: 902.3 | G13: 117393 | L13: 45295 | M13: 902.3 | N13: 912.85 | O13: 877 | P13: 877 | Q13: 902.3 | R13: 1123117
A14: 45296 | B14: 908.4 | C14: 889.2 | D14: 882.8 | E14: 905.1 | F14: 889.2 | G14: 59806 | L14: 45296 | M14: 888.55 | N14: 908.5 | O14: 883 | P14: 906.7 | Q14: 888.55 | R14: 440642
A15: 45299 | B15: 893.15 | C15: 877.05 | D15: 872.9 | E15: 886.3 | F15: 877.05 | G15: 53792 | L15: 45299 | M15: 876.45 | N15: 893.25 | O15: 873.25 | P15: 888.55 | Q15: 876.45 | R15: 359093
... A2722: 46010 | B2722: 939 | C2722: 932.5 | D2722: 906.25 | E2722: 910.9 | F2722: 932.5 | G2722: 8862 | L2722: 46010 | M2722: 936.6 | N2722: 938.9 | O2722: 905 | P2722: 905 | Q2722: 936.6 | R2722: 296202

Sheet Sheet2
J19: 219.3 | K19: 186.25 | L19: 186.75
J20: 192.9 | K20: 135.5 | L20: 146.9 | N20: 219.3 | O20: 192.9 | P20: 186 | Q20: 178.7 | R20: 207 | S20: 255.15 | T20: 348.25 | U20: 374 | V20: 495.9 | W20: 659.9 | X20: 613.4 | Y20: 607.9 | Z20: 555.95 | AA20: 497.8 | AB20: 459.9 | AC20: 374 | AD20: 362 | AE20: 341.5 | AF20: 384.2 | AG20: 433.8 | AH20: 460 | AI20: 474.4 | AJ20: 414.4 | AK20: 318.7 | AL20: 303.25 | AM20: 332.7 | AN20: 295 | AO20: 247 | AP20: 214.4 | AQ20: 179.5 | AR20: 97.9 | AS20: 119.1 | AT20: 130.65 | AU20: 148.55 | AV20: 153.8 | AW20: 152.9 | AX20: 136 | AY20: 141.15 | AZ20: 128.1 | BA20: 142.5 | BB20: 143.55 | BC20: 124.5 | BD20: 241 | BE20: 450 | BF20: 503.35
J21: 186 | K21: 145.4 | L21: 169.1 | N21: 186.25 | O21: 135.5 | P21: 145.4 | Q21: 108.95 | R21: 137 | S21: 170 | T21: 243.15 | U21: 307.5 | V21: 325.1 | W21: 463 | X21: 467.05 | Y21: 436.5 | Z21: 467 | AA21: 348.2 | AB21: 325 | AC21: 313.1 | AD21: 285 | AE21: 277.85 | AF21: 327 | AG21: 317 | AH21: 370.7 | AI21: 360 | AJ21: 271.15 | AK21: 233.15 | AL21: 218.8 | AM21: 262 | AN21: 223.6 | AO21: 137.6 | AP21: 142 | AQ21: 59.3 | AR21: 58 | AS21: 72.8 | AT21: 80 | AU21: 107.25 | AV21: 106 | AW21: 125.1 | AX21: 112.25 | AY21: 81.45 | AZ21: 88 | BA21: 90.35 | BB21: 106.05 | BC21: 98.55 | BD21: 119.25 | BE21: 210 | BF21: 349
J22: 178.7 | K22: 108.95 | L22: 139.75 | N22: 186.75 | O22: 146.9 | P22: 169.1 | Q22: 139.75 | R22: 202.15 | S22: 249.05 | T22: 346.4 | U22: 349.2 | V22: 469.9 | W22: 584.8 | X22: 536.15 | Y22: 513.35 | Z22: 474 | AA22: 438.55 | AB22: 355.4 | AC22: 334.95 | AD22: 298.8 | AE22: 328.35 | AF22: 343 | AG22: 389.9 | AH22: 443.05 | AI22: 407.5 | AJ22: 290.1 | AK22: 235.75 | AL22: 292.65 | AM22: 276.1 | AN22: 237.05 | AO22: 190.1 | AP22: 147.2 | AQ22: 71.9 | AR22: 75.2 | AS22: 90.1 | AT22: 117.2 | AU22: 116.3 | AV22: 140.5 | AW22: 128.6 | AX22: 133.65 | AY22: 91.65 | AZ22: 97.65 | BA22: 125 | BB22: 115.35 | BC22: 119.25 | BD22: 219.3 | BE22: 442.65 | BF22: 503.35
J23: 207 | K23: 137 | L23: 202.15
J24: 255.15 | K24: 170 | L24: 249.05
J25: 348.25 | K25: 243.15 | L25: 346.4
J26: 374 | K26: 307.5 | L26: 349.2
J27: 495.9 | K27: 325.1 | L27: 469.9
J28: 659.9 | K28: 463 | L28: 584.8
J29: 613.4 | K29: 467.05 | L29: 536.15
J30: 607.9 | K30: 436.5 | L30: 513.35
J31: 555.95 | K31: 467 | L31: 474
J32: 497.8 | K32: 348.2 | L32: 438.55
J33: 459.9 | K33: 325 | L33: 355.4
J34: 374 | K34: 313.1 | L34: 334.95
... J63: 503.35 | K63: 349 | L63: 503.35
