Workbook

Sheet Template
A1: =+'Annual Raw'!C4 -> Jindal Saw Ltd. | B1: 36951 | C1: =EOMONTH(B1,12) -> 37346 | D1: =EOMONTH(C1,12) -> 37711 | E1: =EOMONTH(D1,12) -> 38077 | F1: =EOMONTH(E1,12) -> 38442 | G1: =EOMONTH(F1,12) -> 38807 | H1: =EOMONTH(G1,12) -> 39172 | I1: =EOMONTH(H1,12) -> 39538 | J1: =EOMONTH(I1,12) -> 39903 | ... AE1: =EOMONTH(AD1,12) -> 47573 | AH1: QTR | AI1: 41061 | AJ1: 41153 | AK1: 41244 | AL1: 41334 | AM1: 41426 | AN1: 41518 | AO1: 41609 | AP1: 41699 | AQ1: 41791 | AR1: 41883 | AS1: 41974 | AT1: 42064 | AU1: 42156 | AV1: 42248 | AW1: 42339 | AX1: 42430 | AY1: 42522 | AZ1: 42614 | BA1: 42705 | BB1: 42795 | BC1: 42887 | BD1: 42979 | BE1: 43070 | BF1: 43160 | BG1: 43252 | BH1: 43344 | BI1: 43435 | BJ1: 43525 | BK1: 43617 | BL1: 43709 | BM1: 43800 | BN1: 43891 | BO1: 43983 | BP1: 44075 | BQ1: =EOMONTH(BP1,3) -> 44196 | BR1: =EOMONTH(BQ1,3) -> 44286 | BS1: =EOMONTH(BR1,3) -> 44377 | BT1: =EOMONTH(BS1,3) -> 44469 | BU1: =EOMONTH(BT1,3) -> 44561 | BV1: =EOMONTH(BU1,3) -> 44651 | BW1: =EOMONTH(BV1,3) -> 44742 | BX1: =EOMONTH(BW1,3) -> 44834 | ... DB1: =EOMONTH(DA1,3) -> 47573 | DE1: HISTORICAL ESTIMATES | DF1: 46112
A2: Presentation Data (Start)
A4: Current Capacity - MT pipes | W4: 1800000 | X4: =W4 -> 1800000 | Y4: 2350000 | Z4: =Y4 -> 2350000 | AA4: 2700000 | CE4: =CF4 -> 587500 | CF4: =CG4 -> 587500 | CG4: =CH4 -> 587500 | CH4: =Z4/4 -> 587500 | CI4: =AA4/4 -> 675000 | CJ4: =CI4 -> 675000 | CK4: =CJ4 -> 675000 | CL4: =CK4 -> 675000 | CM4: =+CL4 -> 675000 | CN4: =+CM4 -> 675000 | CO4: =+CN4 -> 675000 | CP4: =+CO4 -> 675000 | CQ4: =+CP4 -> 675000 | CR4: =+CQ4 -> 675000 | DF4: 675000
A6: Total Vol with Abu Dhabi | Q6: =+Q7+Q10 -> 2158700 | R6: =+R7+R10 -> 2240000 | S6: =+S7+S10 -> 2471860 | T6: =+T7+T10 -> 2666194 | U6: =+U7+U10 -> 2569827 | V6: =+V7+V10 -> 2355422 | W6: =+W7+W10 -> 2540977 | X6: =+X7+X10 -> 2823000 | ... Z6: =+Z7+Z10 -> 3546300
A7: Sales Vol - MT | Q7: =Q8+Q9 -> 2158700 | R7: =R8+R9 -> 2240000 | S7: =S8+S9 -> 2471860 | T7: =T8+T9 -> 2666194 | U7: =U8+U9 -> 2569827 | V7: =V8+V9 -> 2355422 | W7: =W8+W9 -> 2540977 | X7: =SUM(BW7:BZ7) -> 2823000 | Y7: =SUM(CA7:CD7) -> 3460600 | Z7: =SUM(CE7:CH7) -> 3347000 | AA7: =SUM(CI7:CL7) -> 2830000 | AB7: =+SUM(CM7:CP7) -> 0 | AC7: =+SUM(CQ7:CT7) -> 0 | AD7: =+SUM(CU7:CX7) -> 0 | AE7: =+SUM(CY7:DB7) -> 0 | BK7: 641405 | BL7: 625800 | BM7: 720900 | BN7: 596200 | BO7: 394906 | BP7: 620800 | BQ7: 615800 | BR7: 744894 | BS7: =257800+366200 -> 624000 | BT7: 616000 | BU7: 659500 | BV7: 686700 | BW7: =233200+295200 -> 528400 | BX7: 657800 | BY7: 820362 | BZ7: 816438 | CA7: 805000 | CB7: 885000 | CC7: 893600 | CD7: =478000+399000 -> 877000 | CE7: =400000+413000 -> 813000 | CF7: =432000+396000 -> 828000 | CG7: =432000+443000 -> 875000 | CH7: =434000+397000 -> 831000 | CI7: =326000+222000 -> 548000 | CJ7: =293000+356000 -> 649000 | CK7: =370000+491000 -> 861000 | CL7: =CL8+CL9 -> 772000
A8: Pipes- MT Standalone | Q8: 958700 | R8: 1040000 | S8: 1171860 | T8: 1266194 | U8: 1237931 | V8: 1090656 | W8: 1023567 | X8: 1285619 | Y8: 1716000 | Z8: 1698000 | AA8: =SUM(CI8:CL8) -> 1387000 | AB8: =+SUM(CM8:CP8) -> 1525700 | AC8: =+SUM(CQ8:CT8) -> 1678270 | AD8: =+SUM(CU8:CX8) -> 1846097 | AE8: =+SUM(CY8:DB8) -> 2030706.7 | BK8: =+BK7-BK9 -> 321405 | BL8: =+BL7-BL9 -> 305800 | BM8: =+BM7-BM9 -> 400900 | BN8: =+BN7-BN9 -> 276200 | BO8: =+BO7-BO9 -> 214906 | BP8: =+BP7-BP9 -> 254600 | BQ8: =+BQ7-BQ9 -> 249600 | BR8: =+BR7-BR9 -> 378694 | BS8: 257800 | BT8: 295000 | BU8: 310000 | BV8: 350000 | BW8: 233200 | BX8: 280000 | BY8: 330000 | BZ8: 410000 | CA8: 340000 | CB8: 375000 | CC8: 390000 | CD8: 478000 | CE8: 400000 | CF8: =+Z8-CE8-CG8-CH8 -> 432000 | CG8: 432000 | CH8: 434000 | CI8: 326000 | CJ8: 293000 | CK8: 370000 | CL8: 398000 | CM8: =+CI8*1.1 -> 358600 | CN8: =+CJ8*1.1 -> 322300 | CO8: =+CK8*1.1 -> 407000 | CP8: =+CL8*1.1 -> 437800 | CQ8: =+CM8*1.1 -> 394460 | CR8: =+CN8*1.1 -> 354530 | CS8: =+CO8*1.1 -> 447700 | CT8: =+CP8*1.1 -> 481580 | ... DB8: =+CX8*1.1 -> 582711.8 | DF8: 347200
A9: Pellets | Q9: 1200000 | R9: 1200000 | S9: 1300000 | T9: 1400000 | U9: 1331896 | V9: 1264766 | W9: 1517410 | X9: =+X7-X8 -> 1537381 | Y9: =+Y7-Y8 -> 1744600 | Z9: =+Z7-Z8 -> 1649000 | AA9: =SUM(CI9:CL9) -> 1443000 | AB9: =+SUM(CM9:CP9) -> 0 | AC9: =+SUM(CQ9:CT9) -> 0 | AD9: =+SUM(CU9:CX9) -> 0 | AE9: =+SUM(CY9:DB9) -> 0 | BK9: 320000 | BL9: 320000 | BM9: 320000 | BN9: 320000 | BO9: 180000 | BP9: =+BQ9 -> 366200 | BQ9: =+BR9 -> 366200 | BR9: =+BS9 -> 366200 | BS9: =+BS7-BS8 -> 366200 | BT9: =+BT7-BT8 -> 321000 | BU9: =+BU7-BU8 -> 349500 | BV9: =+BV7-BV8 -> 336700 | BW9: =+BW7-BW8 -> 295200 | BX9: =+BX7-BX8 -> 377800 | BY9: =+BY7-BY8 -> 490362 | BZ9: =+BZ7-BZ8 -> 406438 | ... CK9: =+CK7-CK8 -> 491000 | CL9: 374000
A10: Pipes Abu Dhabi | Y10: 191000 | Z10: 199300 | AA10: =SUM(CI10:CL10) -> 209000 | AB10: =+SUM(CM10:CP10) -> 208000 | AC10: =+SUM(CQ10:CT10) -> 208000 | AD10: =+SUM(CU10:CX10) -> 208000 | AE10: =+SUM(CY10:DB10) -> 208000 | BY10: 37362 | BZ10: 39638 | CA10: 43000 | CB10: 59000 | CC10: 63000 | CD10: 26000 | CE10: 36800 | CF10: 61000 | CG10: 57000 | CH10: =+Z10-CE10-CF10-CG10 -> 44500 | CI10: 51000 | CJ10: 58000 | CK10: 52000 | CL10: 48000 | CM10: 52000 | CN10: =+CM10 -> 52000 | CO10: =+CN10 -> 52000 | CP10: =+CO10 -> 52000 | CQ10: =+CP10 -> 52000 | CR10: =+CQ10 -> 52000 | CS10: =+CR10 -> 52000 | CT10: =+CS10 -> 52000 | CU10: =+CT10 -> 52000 | ... DB10: =+DA10 -> 52000 | DF10: 41600
A11: Vol Growth pipes only | R11: =(R10+R8)/(Q8+Q10)-1 -> 0.084802336 | S11: =(S10+S8)/(R8+R10)-1 -> 0.12678846 | T11: =(T10+T8)/(S8+S10)-1 -> 0.080499377 | U11: =(U10+U8)/(T8+T10)-1 -> -0.022321224 | V11: =(V10+V8)/(U8+U10)-1 -> -0.11896867 | W11: =(W10+W8)/(V8+V10)-1 -> -0.061512521 | X11: =(X10+X8)/(W8+W10)-1 -> 0.25601841 | Y11: =(Y10+Y8)/(X8+X10)-1 -> 0.48333215 | ... AE11: =(AE10+AE8)/(AD8+AD10)-1 -> 0.089873896 | BQ11: =(BQ10+BQ8)/(BM8+BM10)-1 -> -0.37740085 | BR11: =(BR10+BR8)/(BN8+BN10)-1 -> 0.37108617 | BS11: =(BS10+BS8)/(BO8+BO10)-1 -> 0.19959424 | BT11: =(BT10+BT8)/(BP8+BP10)-1 -> 0.15868028 | BU11: =(BU10+BU8)/(BQ8+BQ10)-1 -> 0.24198718 | BV11: =(BV10+BV8)/(BR8+BR10)-1 -> -0.075770939 | BW11: =(BW10+BW8)/(BS8+BS10)-1 -> -0.095422808 | BX11: =(BX10+BX8)/(BT8+BT10)-1 -> -0.050847458 | ... DB11: =(DB10+DB8)/(CX8+CX10)-1 -> 0.091061268 | DF11: -0.18746082
A13: Orderbook Crs | Y13: =CD13 -> 12657.5 | Z13: =CH13 -> 11271 | CB13: =1.44*83*100 -> 11952 | CC13: =1.49*83*100 -> 12367 | CD13: =+((1509+16)/10)*83 -> 12657.5 | CE13: =165*83 -> 13695 | CF13: =162*83 -> 13446 | CG13: =148*83 -> 12284 | CH13: =132.6*85 -> 11271 | CI13: =130.5*85 -> 11092.5 | CJ13: =145.2*88 -> 12777.6 | CK13: =148.1*90 -> 13329
A14: OB MT - Pipes | Y14: =CD14 -> 1376000 | Z14: =CH14 -> 1301000 | CD14: 1376000 | CE14: 1524000 | CF14: 1469000 | CG14: 1394000 | CH14: 1301000 | CI14: 1560000 | CJ14: 1925000 | CK14: 1964000 | CL14: 1900000
A15: DI Pipes | Z15: =CH15 -> 625000 | CG15: 680000 | CH15: 625000 | CK15: 700000
A17: Unit Matrix
A18: Sales | Q18: =+Q27*10^7/(Q$8+Q$10)/1000 -> 82.824723 | R18: =+R27*10^7/(R$8+R$10)/1000 -> 70.606387 | S18: =+S27*10^7/(S$8+S$10)/1000 -> 73.083214 | T18: =+T27*10^7/(T$8+T$10)/1000 -> 95.696249 | U18: =+U27*10^7/(U$8+U$10)/1000 -> 93.923141 | V18: =+V27*10^7/(V$8+V$10)/1000 -> 97.772678 | W18: =+W27*10^7/(W$8+W$10)/1000 -> 129.92233 | X18: =+X27*10^7/(X$8+X$10)/1000 -> 138.98417 | ... AE18: =+AE27*10^7/(AE$8+AE$10)/1000 -> 107.88969 | BO18: =+BO27*10^7/(BO$8+BO$10)/1000 -> 76.349195 | BP18: =+BP27*10^7/(BP$8+BP$10)/1000 -> 93.256874 | BQ18: =+BQ27*10^7/(BQ$8+BQ$10)/1000 -> 114.77083 | BR18: =+BR27*10^7/(BR$8+BR$10)/1000 -> 99.918404 | BS18: =+BS27*10^7/(BS$8+BS$10)/1000 -> 111.89294 | BT18: =+BT27*10^7/(BT$8+BT$10)/1000 -> 100.77559 | BU18: =+BU27*10^7/(BU$8+BU$10)/1000 -> 111.96903 | BV18: =+BV27*10^7/(BV$8+BV$10)/1000 -> 113.42571 | ... CL18: =+CL27*10^7/(CL$8+CL$10)/1000 -> 103.88969 | CM18: =+CL18+2 -> 105.88969 | CN18: =+CM18+2 -> 107.88969 | CO18: =+CN18 -> 107.88969 | CP18: =+CO18 -> 107.88969 | CQ18: =+CP18 -> 107.88969 | CR18: =+CQ18 -> 107.88969 | CS18: =+CR18 -> 107.88969 | CT18: =+CS18 -> 107.88969 | CU18: =+CT18 -> 107.88969 | CV18: =+CU18 -> 107.88969 | ... DB18: =+DA18 -> 107.88969 | DF18: 117.14242
A19: Raw Mat | Q19: =+Q18-Q20 -> 47.259395 | R19: =+R18-R20 -> 39.269639 | S19: =+S18-S20 -> 42.308059 | T19: =+T18-T20 -> 58.963831 | U19: =+U18-U20 -> 56.018023 | V19: =+V18-V20 -> 55.265002 | W19: =+W18-W20 -> 77.203042 | X19: =+X18-X20 -> 87.058821 | ... AE19: =+AE18-AE20 -> 59.174664 | BO19: =+BO18-BO20 -> 41.875518 | BP19: =+BP18-BP20 -> 50.765515 | BQ19: =+BQ18-BQ20 -> 63.191907 | BR19: =+BR18-BR20 -> 59.621489 | BS19: =+BS18-BS20 -> 59.408456 | BT19: =+BT18-BT20 -> 56.470169 | BU19: =+BU18-BU20 -> 71.886774 | BV19: =+BV18-BV20 -> 70.781143 | ... CL19: =+CL18-CL20 -> 59.174664 | CM19: =+CL19 -> 59.174664 | CN19: =+CM19 -> 59.174664 | CO19: =+CN19 -> 59.174664 | CP19: =+CO19 -> 59.174664 | CQ19: =+CP19 -> 59.174664 | CR19: =+CQ19 -> 59.174664 | CS19: =+CR19 -> 59.174664 | CT19: =+CS19 -> 59.174664 | ... DB19: =+DA19 -> 59.174664 | DF19: 69.001185
A20: GP | Q20: =+Q35*10^7/(Q$8+Q$10)/1000 -> 35.565328 | R20: =+R35*10^7/(R$8+R$10)/1000 -> 31.336747 | S20: =+S35*10^7/(S$8+S$10)/1000 -> 30.775155 | T20: =+T35*10^7/(T$8+T$10)/1000 -> 36.732418 | U20: =+U35*10^7/(U$8+U$10)/1000 -> 37.905118 | V20: =+V35*10^7/(V$8+V$10)/1000 -> 42.507676 | W20: =+W35*10^7/(W$8+W$10)/1000 -> 52.71929 | X20: =+X35*10^7/(X$8+X$10)/1000 -> 51.925348 | ... AE20: =+AE35*10^7/(AE$8+AE$10)/1000 -> 48.715022 | BO20: =+BO35*10^7/(BO$8+BO$10)/1000 -> 34.473677 | BP20: =+BP35*10^7/(BP$8+BP$10)/1000 -> 42.491359 | BQ20: =+BQ35*10^7/(BQ$8+BQ$10)/1000 -> 51.578926 | BR20: =+BR35*10^7/(BR$8+BR$10)/1000 -> 40.296915 | BS20: =+BS35*10^7/(BS$8+BS$10)/1000 -> 52.484484 | BT20: =+BT35*10^7/(BT$8+BT$10)/1000 -> 44.305424 | BU20: =+BU35*10^7/(BU$8+BU$10)/1000 -> 40.082258 | BV20: =+BV35*10^7/(BV$8+BV$10)/1000 -> 42.644571 | ... CL20: =+CL35*10^7/(CL$8+CL$10)/1000 -> 44.715022 | CM20: =+CM18-CM19 -> 46.715022 | CN20: =+CN18-CN19 -> 48.715022 | CO20: =+CO18-CO19 -> 48.715022 | CP20: =+CP18-CP19 -> 48.715022 | CQ20: =+CQ18-CQ19 -> 48.715022 | CR20: =+CR18-CR19 -> 48.715022 | CS20: =+CS18-CS19 -> 48.715022 | CT20: =+CT18-CT19 -> 48.715022 | ... DB20: =+DB18-DB19 -> 48.715022 | DF20: 48.141232
A21: Other Cost | Q21: =+Q20-Q22 -> 28.572117 | R21: =+R20-R22 -> 24.387977 | S21: =+S20-S22 -> 22.276204 | T21: =+T20-T22 -> 25.423293 | U21: =+U20-U22 -> 26.079158 | V21: =+V20-V22 -> 31.643294 | W21: =+W20-W22 -> 39.477432 | X21: =+X20-X22 -> 39.447232 | ... AE21: =+AE20-AE22 -> 33.93296 | BO21: =+BO20-BO22 -> 25.937852 | BP21: =+BP20-BP22 -> 31.638256 | BQ21: =+BQ20-BQ22 -> 39.225962 | BR21: =+BR20-BR22 -> 27.754335 | BS21: =+BS20-BS22 -> 36.244375 | BT21: =+BT20-BT22 -> 31.487119 | BU21: =+BU20-BU22 -> 33.481935 | BV21: =+BV20-BV22 -> 31.198571 | ... CL21: =+CL20-CL22 -> 33.93296 | CM21: =+CL21 -> 33.93296 | CN21: =+CM21 -> 33.93296 | CO21: =+CN21 -> 33.93296 | CP21: =+CO21 -> 33.93296 | CQ21: =+CP21 -> 33.93296 | CR21: =+CQ21 -> 33.93296 | CS21: =+CR21 -> 33.93296 | CT21: =+CS21 -> 33.93296 | ... DB21: =+DA21 -> 33.93296 | DF21: 33.623934
A22: EBIDTA | Q22: =+Q47*10^7/(Q$8+Q$10)/1000 -> 6.9932106 | R22: =+R47*10^7/(R$8+R$10)/1000 -> 6.9487702 | S22: =+S47*10^7/(S$8+S$10)/1000 -> 8.4989504 | T22: =+T47*10^7/(T$8+T$10)/1000 -> 11.309125 | U22: =+U47*10^7/(U$8+U$10)/1000 -> 11.82596 | V22: =+V47*10^7/(V$8+V$10)/1000 -> 10.864383 | W22: =+W47*10^7/(W$8+W$10)/1000 -> 13.241857 | X22: =+X47*10^7/(X$8+X$10)/1000 -> 12.478116 | ... AE22: =+AE47*10^7/(AE$8+AE$10)/1000 -> 14.782063 | BO22: =+BO47*10^7/(BO$8+BO$10)/1000 -> 8.535825 | BP22: =+BP47*10^7/(BP$8+BP$10)/1000 -> 10.853103 | BQ22: =+BQ47*10^7/(BQ$8+BQ$10)/1000 -> 12.352965 | BR22: =+BR47*10^7/(BR$8+BR$10)/1000 -> 12.542581 | BS22: =+BS47*10^7/(BS$8+BS$10)/1000 -> 16.240109 | BT22: =+BT47*10^7/(BT$8+BT$10)/1000 -> 12.818305 | BU22: =+BU47*10^7/(BU$8+BU$10)/1000 -> 6.6003226 | BV22: =+BV47*10^7/(BV$8+BV$10)/1000 -> 11.446 | ... CL22: =+CL47*10^7/(CL$8+CL$10)/1000 -> 10.782063 | CM22: =+CM20-CM21 -> 12.782063 | CN22: =+CN20-CN21 -> 14.782063 | CO22: =+CO20-CO21 -> 14.782063 | CP22: =+CP20-CP21 -> 14.782063 | CQ22: =+CQ20-CQ21 -> 14.782063 | CR22: =+CR20-CR21 -> 14.782063 | CS22: =+CS20-CS21 -> 14.782063 | CT22: =+CT20-CT21 -> 14.782063 | ... DB22: =+DB20-DB21 -> 14.782063 | DF22: 14.517299
A25: Presentation Data (End)
A26: Profit & Loss- Annual (Start)
A27: Gross Revenue | B27: ='Annual Raw'!C6 -> 0 | C27: ='Annual Raw'!D6 -> 0 | D27: ='Annual Raw'!E6 -> 0 | E27: ='Annual Raw'!F6 -> 0 | F27: ='Annual Raw'!G6 -> 0 | G27: ='Annual Raw'!H6 -> 0 | H27: ='Annual Raw'!I6 -> 0 | I27: ='Annual Raw'!J6 -> 0 | ... AA27: ='Annual Raw'!AB6 -> 17895.165 | AB27: =+SUM(CM27:CP27) -> 18622.715 | AC27: =+SUM(CQ27:CT27) -> 20350.908 | AD27: =+SUM(CU27:CX27) -> 22161.588 | AE27: =+SUM(CY27:DB27) -> 24153.336 | AI27: ='QTR Raw'!C6+'QTR Raw'!C8 -> 1290.43 | AJ27: ='QTR Raw'!D6+'QTR Raw'!D8 -> 1636.93 | AK27: ='QTR Raw'!E6+'QTR Raw'!E8 -> 1722.73 | AL27: ='QTR Raw'!F6+'QTR Raw'!F8 -> 980.07 | AM27: ='QTR Raw'!G6+'QTR Raw'!G8 -> 1207.01 | AN27: ='QTR Raw'!H6+'QTR Raw'!H8 -> 1229.39 | AO27: ='QTR Raw'!I6+'QTR Raw'!I8 -> 1709.61 | AP27: ='QTR Raw'!J6+'QTR Raw'!J8 -> 1363.58 | ... CL27: ='QTR Raw'!BF6+'QTR Raw'!BF8 -> 4633.48 | CM27: =+(CM$8+CM$10)*CM18/10^4 -> 4347.8305 | CN27: =+(CN$8+CN$10)*CN18/10^4 -> 4038.311 | CO27: =+(CO$8+CO$10)*CO18/10^4 -> 4952.1366 | CP27: =+(CP$8+CP$10)*CP18/10^4 -> 5284.4368 | CQ27: =+(CQ$8+CQ$10)*CQ18/10^4 -> 4816.8429 | CR27: =+(CR$8+CR$10)*CR18/10^4 -> 4386.0394 | CS27: =+(CS$8+CS$10)*CS18/10^4 -> 5391.2476 | CT27: =+(CT$8+CT$10)*CT18/10^4 -> 5756.7779 | ... DB27: =+(DB$8+DB$10)*DB18/10^4 -> 6847.8857 | DF27: 17895.165
A28: Less: Exise Duty | B28: ='Annual Raw'!C7+'Annual Raw'!C8+'Annual Raw'!C9 -> 0 | C28: ='Annual Raw'!D7+'Annual Raw'!D8+'Annual Raw'!D9 -> 0 | D28: ='Annual Raw'!E7+'Annual Raw'!E8+'Annual Raw'!E9 -> 0 | E28: ='Annual Raw'!F7+'Annual Raw'!F8+'Annual Raw'!F9 -> 0 | F28: ='Annual Raw'!G7+'Annual Raw'!G8+'Annual Raw'!G9 -> 0 | G28: ='Annual Raw'!H7+'Annual Raw'!H8+'Annual Raw'!H9 -> 0 | H28: ='Annual Raw'!I7+'Annual Raw'!I8+'Annual Raw'!I9 -> 0 | I28: ='Annual Raw'!J7+'Annual Raw'!J8+'Annual Raw'!J9 -> 0 | ... AA28: ='Annual Raw'!AB7+'Annual Raw'!AB8+'Annual Raw'!AB9 -> 0 | AB28: =+SUM(CM28:CP28) -> 0 | AC28: =+SUM(CQ28:CT28) -> 0 | AD28: =+SUM(CU28:CX28) -> 0 | AE28: =+SUM(CY28:DB28) -> 0 | AI28: =+'QTR Raw'!C20+'QTR Raw'!C19+'QTR Raw'!C13+'QTR Raw'!C7 -> 0 | AJ28: =+'QTR Raw'!D20+'QTR Raw'!D19+'QTR Raw'!D13+'QTR Raw'!D7 -> 0 | AK28: =+'QTR Raw'!E20+'QTR Raw'!E19+'QTR Raw'!E13+'QTR Raw'!E7 -> 0 | AL28: =+'QTR Raw'!F20+'QTR Raw'!F19+'QTR Raw'!F13+'QTR Raw'!F7 -> 0 | AM28: =+'QTR Raw'!G20+'QTR Raw'!G19+'QTR Raw'!G13+'QTR Raw'!G7 -> 0 | AN28: =+'QTR Raw'!H20+'QTR Raw'!H19+'QTR Raw'!H13+'QTR Raw'!H7 -> 0 | AO28: =+'QTR Raw'!I20+'QTR Raw'!I19+'QTR Raw'!I13+'QTR Raw'!I7 -> 0 | AP28: =+'QTR Raw'!J20+'QTR Raw'!J19+'QTR Raw'!J13+'QTR Raw'!J7 -> 0 | ... CL28: =+'QTR Raw'!BF20+'QTR Raw'!BF19+'QTR Raw'!BF13+'QTR Raw'!BF7 -> 0 | DF28: 0
A29: Net Revenue | B29: =+B27-B28 -> 0 | C29: =+C27-C28 -> 0 | D29: =+D27-D28 -> 0 | E29: =+E27-E28 -> 0 | F29: =+F27-F28 -> 0 | G29: =+G27-G28 -> 0 | H29: =+H27-H28 -> 0 | I29: =+I27-I28 -> 0 | ... AE29: =+AE27-AE28 -> 24153.336 | AI29: =+AI27-AI28 -> 1290.43 | AJ29: =+AJ27-AJ28 -> 1636.93 | AK29: =+AK27-AK28 -> 1722.73 | AL29: =+AL27-AL28 -> 980.07 | AM29: =+AM27-AM28 -> 1207.01 | AN29: =+AN27-AN28 -> 1229.39 | AO29: =+AO27-AO28 -> 1709.61 | AP29: =+AP27-AP28 -> 1363.58 | ... DB29: =+DB27-DB28 -> 6847.8857 | DF29: 17895.165
A30: Net Revenue YOY% | C30: =C29/B29-1 -> #DIV/0! | D30: =D29/C29-1 -> #DIV/0! | E30: =E29/D29-1 -> #DIV/0! | F30: =F29/E29-1 -> #DIV/0! | G30: =G29/F29-1 -> #DIV/0! | H30: =H29/G29-1 -> #DIV/0! | I30: =I29/H29-1 -> #DIV/0! | J30: =J29/I29-1 -> #DIV/0! | ... AE30: =AE29/AD29-1 -> 0.089873896 | AM30: =+IF(AI29<0,1-AM29/AI29,AM29/AI29-1) -> -0.064645118 | AN30: =+IF(AJ29<0,1-AN29/AJ29,AN29/AJ29-1) -> -0.24896605 | AO30: =+IF(AK29<0,1-AO29/AK29,AO29/AK29-1) -> -0.0076158191 | AP30: =+IF(AL29<0,1-AP29/AL29,AP29/AL29-1) -> 0.39130878 | AQ30: =+IF(AM29<0,1-AQ29/AM29,AQ29/AM29-1) -> -0.048002916 | AR30: =+IF(AN29<0,1-AR29/AN29,AR29/AN29-1) -> 0.29443057 | AS30: =+IF(AO29<0,1-AS29/AO29,AS29/AO29-1) -> 0.039669866 | AT30: =+IF(AP29<0,1-AT29/AP29,AT29/AP29-1) -> 0.5283445 | ... DB30: =+IF(CX29<0,1-DB29/CX29,DB29/CX29-1) -> 0.091061268 | DF30: -0.14084903
A31: Net Revenue QOQ% | AJ31: =+IF(AI29<0,1-AJ29/AI29,AJ29/AI29-1) -> 0.26851515 | AK31: =+IF(AJ29<0,1-AK29/AJ29,AK29/AJ29-1) -> 0.052415192 | AL31: =+IF(AK29<0,1-AL29/AK29,AL29/AK29-1) -> -0.43109483 | AM31: =+IF(AL29<0,1-AM29/AL29,AM29/AL29-1) -> 0.23155489 | AN31: =+IF(AM29<0,1-AN29/AM29,AN29/AM29-1) -> 0.018541686 | AO31: =+IF(AN29<0,1-AO29/AN29,AO29/AN29-1) -> 0.39061648 | AP31: =+IF(AO29<0,1-AP29/AO29,AP29/AO29-1) -> -0.20240289 | AQ31: =+IF(AP29<0,1-AQ29/AP29,AQ29/AP29-1) -> -0.15731384 | ... CL31: =+IF(CK29<0,1-CL29/CK29,CL29/CK29-1) -> -0.062695589 | CM31: =+CM29/CL29-1 -> -0.061649017 | CN31: =+CN29/CM29-1 -> -0.071189426 | CO31: =+CO29/CN29-1 -> 0.22628907 | CP31: =+CP29/CO29-1 -> 0.067102397 | CQ31: =+CQ29/CP29-1 -> -0.088485096 | CR31: =+CR29/CQ29-1 -> -0.089436904 | CS31: =+CS29/CR29-1 -> 0.22918358 | CT31: =+CT29/CS29-1 -> 0.06780068 | ... DB31: =+DB29/DA29-1 -> 0.069047711
A32: Increase/Decrease in Stock | B32: ='Annual Raw'!C11 -> 0 | C32: ='Annual Raw'!D11 -> 0 | D32: ='Annual Raw'!E11 -> 0 | E32: ='Annual Raw'!F11 -> 0 | F32: ='Annual Raw'!G11 -> 0 | G32: ='Annual Raw'!H11 -> 0 | H32: ='Annual Raw'!I11 -> 0 | I32: ='Annual Raw'!J11 -> 0 | ... AA32: ='Annual Raw'!AB11 -> -587.217 | AB32: =+SUM(CM32:CP32) -> 0 | AC32: =+SUM(CQ32:CT32) -> 0 | AD32: =+SUM(CU32:CX32) -> 0 | AE32: =+SUM(CY32:DB32) -> 0 | AI32: ='QTR Raw'!C10 -> -191.53 | AJ32: ='QTR Raw'!D10 -> 112.79 | AK32: ='QTR Raw'!E10 -> 366.5 | AL32: ='QTR Raw'!F10 -> -56.95 | AM32: ='QTR Raw'!G10 -> 28.77 | AN32: ='QTR Raw'!H10 -> -70.38 | AO32: ='QTR Raw'!I10 -> 190.88 | AP32: ='QTR Raw'!J10 -> 93.36 | ... CL32: ='QTR Raw'!BF10 -> -23.16 | DF32: -587.217
A33: Purchase of Finished Goods | B33: 0 | C33: 0 | D33: 0 | E33: 0 | F33: 0 | G33: 0 | H33: 0 | I33: 0 | J33: 0 | K33: 0 | L33: 0 | M33: 0 | N33: 0 | O33: 0 | P33: 0 | Q33: 0 | R33: 0 | S33: 0 | T33: 0 | U33: 0 | V33: 0 | W33: 0 | X33: 0 | Y33: 0 | Z33: 0 | AA33: 0 | AB33: =+SUM(CM33:CP33) -> 0 | AC33: =+SUM(CQ33:CT33) -> 0 | AD33: =+SUM(CU33:CX33) -> 0 | AE33: =+SUM(CY33:DB33) -> 0 | AI33: ='QTR Raw'!C12 -> 0 | AJ33: ='QTR Raw'!D12 -> 0 | AK33: ='QTR Raw'!E12 -> 0 | AL33: ='QTR Raw'!F12 -> 21.38 | AM33: ='QTR Raw'!G12 -> 0 | AN33: ='QTR Raw'!H12 -> 0 | AO33: ='QTR Raw'!I12 -> 0 | AP33: ='QTR Raw'!J12 -> 4.48 | ... CL33: ='QTR Raw'!BF12 -> 0.98 | DF33: 0
A34: Raw Material Consumed | B34: ='Annual Raw'!C12 -> 0 | C34: ='Annual Raw'!D12 -> 0 | D34: ='Annual Raw'!E12 -> 0 | E34: ='Annual Raw'!F12 -> 0 | F34: ='Annual Raw'!G12 -> 0 | G34: ='Annual Raw'!H12 -> 0 | H34: ='Annual Raw'!I12 -> 0 | I34: ='Annual Raw'!J12 -> 0 | ... AA34: ='Annual Raw'!AB12 -> 10640.055 | AB34: =+SUM(CM34:CP34) -> 10259.111 | AC34: =+SUM(CQ34:CT34) -> 11161.939 | AD34: =+SUM(CU34:CX34) -> 12155.05 | AE34: =+SUM(CY34:DB34) -> 13247.472 | AI34: ='QTR Raw'!C11 -> 1035.26 | AJ34: ='QTR Raw'!D11 -> 984.68 | AK34: ='QTR Raw'!E11 -> 892.56 | AL34: ='QTR Raw'!F11 -> 660.83 | AM34: ='QTR Raw'!G11 -> 759.39 | AN34: ='QTR Raw'!H11 -> 840.83 | AO34: ='QTR Raw'!I11 -> 916.31 | AP34: ='QTR Raw'!J11 -> 619.51 | ... CL34: ='QTR Raw'!BF11 -> 2661.37 | CM34: =+CM29-CM35 -> 2429.7117 | CN34: =+CN29-CN35 -> 2214.9077 | CO34: =+CO29-CO35 -> 2716.1171 | CP34: =+CP29-CP35 -> 2898.375 | CQ34: =+CQ29-CQ35 -> 2641.912 | CR34: =+CR29-CR35 -> 2405.6276 | CS34: =+CS29-CS35 -> 2956.9579 | CT34: =+CT29-CT35 -> 3157.4417 | ... DB34: =+DB29-DB35 -> 3755.8857 | DF34: 10640.055
A35: Gross Profit | B35: =B29-B32-B34-B33 -> 0 | C35: =C29-C32-C34-C33 -> 0 | D35: =D29-D32-D34-D33 -> 0 | E35: =E29-E32-E34-E33 -> 0 | F35: =F29-F32-F34-F33 -> 0 | G35: =G29-G32-G34-G33 -> 0 | H35: =H29-H32-H34-H33 -> 0 | I35: =I29-I32-I34-I33 -> 0 | ... AE35: =AE29-AE32-AE34-AE33 -> 10905.865 | AI35: =AI29-AI32-AI34-AI33 -> 446.7 | AJ35: =AJ29-AJ32-AJ34-AJ33 -> 539.46 | AK35: =AK29-AK32-AK34-AK33 -> 463.67 | AL35: =AL29-AL32-AL34-AL33 -> 354.81 | AM35: =AM29-AM32-AM34-AM33 -> 418.85 | AN35: =AN29-AN32-AN34-AN33 -> 458.94 | AO35: =AO29-AO32-AO34-AO33 -> 602.42 | AP35: =AP29-AP32-AP34-AP33 -> 646.23 | ... CL35: =CL29-CL32-CL34-CL33 -> 1994.29 | CM35: =+(CM$8+CM$10)*CM20/10^4 -> 1918.1188 | CN35: =+(CN$8+CN$10)*CN20/10^4 -> 1823.4033 | CO35: =+(CO$8+CO$10)*CO20/10^4 -> 2236.0195 | CP35: =+(CP$8+CP$10)*CP20/10^4 -> 2386.0618 | CQ35: =+(CQ$8+CQ$10)*CQ20/10^4 -> 2174.9309 | CR35: =+(CR$8+CR$10)*CR20/10^4 -> 1980.4118 | CS35: =+(CS$8+CS$10)*CS20/10^4 -> 2434.2897 | CT35: =+(CT$8+CT$10)*CT20/10^4 -> 2599.3362 | ... DB35: =+(DB$8+DB$10)*DB20/10^4 -> 3092 | DF35: 7842.3271
A36: GP% | B36: =B35/B29 -> #DIV/0! | C36: =C35/C29 -> #DIV/0! | D36: =D35/D29 -> #DIV/0! | E36: =E35/E29 -> #DIV/0! | F36: =F35/F29 -> #DIV/0! | G36: =G35/G29 -> #DIV/0! | H36: =H35/H29 -> #DIV/0! | I36: =I35/I29 -> #DIV/0! | ... AE36: =AE35/AE29 -> 0.45152622 | AI36: =AI35/AI29 -> 0.34616368 | AJ36: =AJ35/AJ29 -> 0.32955594 | AK36: =AK35/AK29 -> 0.26914839 | AL36: =AL35/AL29 -> 0.36202516 | AM36: =AM35/AM29 -> 0.34701452 | AN36: =AN35/AN29 -> 0.37330709 | AO36: =AO35/AO29 -> 0.35237276 | AP36: =AP35/AP29 -> 0.47392159 | ... DB36: =DB35/DB29 -> 0.45152622 | DF36: 0.4382372
A37: GP YOY% | C37: =+IF(B35<0,1-C35/B35,C35/B35-1) -> #DIV/0! | D37: =+IF(C35<0,1-D35/C35,D35/C35-1) -> #DIV/0! | E37: =+IF(D35<0,1-E35/D35,E35/D35-1) -> #DIV/0! | F37: =+IF(E35<0,1-F35/E35,F35/E35-1) -> #DIV/0! | G37: =+IF(F35<0,1-G35/F35,G35/F35-1) -> #DIV/0! | H37: =+IF(G35<0,1-H35/G35,H35/G35-1) -> #DIV/0! | I37: =+IF(H35<0,1-I35/H35,I35/H35-1) -> #DIV/0! | J37: =+IF(I35<0,1-J35/I35,J35/I35-1) -> #DIV/0! | ... AE37: =+IF(AD35<0,1-AE35/AD35,AE35/AD35-1) -> 0.089873896 | AM37: =+IF(AI35<0,1-AM35/AI35,AM35/AI35-1) -> -0.062346094 | AN37: =+IF(AJ35<0,1-AN35/AJ35,AN35/AJ35-1) -> -0.14926037 | AO37: =+IF(AK35<0,1-AO35/AK35,AO35/AK35-1) -> 0.299243 | AP37: =+IF(AL35<0,1-AP35/AL35,AP35/AL35-1) -> 0.821341 | AQ37: =+IF(AM35<0,1-AQ35/AM35,AQ35/AM35-1) -> 0.28976961 | AR37: =+IF(AN35<0,1-AR35/AN35,AR35/AN35-1) -> 0.59027324 | AS37: =+IF(AO35<0,1-AS35/AO35,AS35/AO35-1) -> 0.35186415 | AT37: =+IF(AP35<0,1-AT35/AP35,AT35/AP35-1) -> 0.38456896 | ... CL37: =+IF(CH35<0,1-CL35/CH35,CL35/CH35-1) -> -0.048861566 | CM37: =+CM35/CI35-1 -> -0.013018894 | CN37: =+CN35/CJ35-1 -> -0.026516206 | CO37: =+CO35/CK35-1 -> 0.10064164 | CP37: =+CP35/CL35-1 -> 0.19644675 | CQ37: =+CQ35/CM35-1 -> 0.13388747 | CR37: =+CR35/CN35-1 -> 0.0861074 | CS37: =+CS35/CO35-1 -> 0.088671024 | CT37: =+CT35/CP35-1 -> 0.089383422 | ... DB37: =+DB35/CX35-1 -> 0.091061268 | DF37: -0.12705973
A38: GP QOQ% | AJ38: =+IF(AI35<0,1-AJ35/AI35,AJ35/AI35-1) -> 0.20765615 | AK38: =+IF(AJ35<0,1-AK35/AJ35,AK35/AJ35-1) -> -0.14049234 | AL38: =+IF(AK35<0,1-AL35/AK35,AL35/AK35-1) -> -0.23477905 | AM38: =+IF(AL35<0,1-AM35/AL35,AM35/AL35-1) -> 0.18049097 | AN38: =+IF(AM35<0,1-AN35/AM35,AN35/AM35-1) -> 0.095714456 | AO38: =+IF(AN35<0,1-AO35/AN35,AO35/AN35-1) -> 0.31263346 | AP38: =+IF(AO35<0,1-AP35/AO35,AP35/AO35-1) -> 0.072723349 | AQ38: =+IF(AP35<0,1-AQ35/AP35,AQ35/AP35-1) -> -0.16404376 | ... CL38: =+IF(CK35<0,1-CL35/CK35,CL35/CK35-1) -> -0.018345508 | CM38: =+CM35/CL35-1 -> -0.038194635 | CN38: =+CN35/CM35-1 -> -0.049379387 | CO38: =+CO35/CN35-1 -> 0.22628907 | CP38: =+CP35/CO35-1 -> 0.067102397 | CQ38: =+CQ35/CP35-1 -> -0.088485096 | CR38: =+CR35/CQ35-1 -> -0.089436904 | CS38: =+CS35/CR35-1 -> 0.22918358 | CT38: =+CT35/CS35-1 -> 0.06780068 | ... DB38: =+DB35/DA35-1 -> 0.069047711
A39: Employee Cost | B39: ='Annual Raw'!C14 -> 0 | C39: ='Annual Raw'!D14 -> 0 | D39: ='Annual Raw'!E14 -> 0 | E39: ='Annual Raw'!F14 -> 0 | F39: ='Annual Raw'!G14 -> 0 | G39: ='Annual Raw'!H14 -> 0 | H39: ='Annual Raw'!I14 -> 0 | I39: ='Annual Raw'!J14 -> 0 | ... AA39: ='Annual Raw'!AB14 -> 1629.7263 | AB39: =+SUM(CM39:CP39) -> 1743.8111 | AC39: =+SUM(CQ39:CT39) -> 1865.8779 | AD39: =+SUM(CU39:CX39) -> 1996.4893 | AE39: =+SUM(CY39:DB39) -> 2136.2436 | AI39: ='QTR Raw'!C16 -> 61.88 | AJ39: ='QTR Raw'!D16 -> 62.85 | AK39: ='QTR Raw'!E16 -> 64.17 | AL39: ='QTR Raw'!F16 -> 63.36 | AM39: ='QTR Raw'!G16 -> 68.02 | AN39: ='QTR Raw'!H16 -> 76.7 | AO39: ='QTR Raw'!I16 -> 78.73 | AP39: ='QTR Raw'!J16 -> 76.75 | ... CL39: ='QTR Raw'!BF16 -> 398.79 | CM39: =CI39*107% -> 436.0571 | CN39: =CJ39*107% -> 445.5266 | CO39: =CK39*107% -> 435.5221 | CP39: =CL39*107% -> 426.7053 | CQ39: =CM39*107% -> 466.5811 | CR39: =CN39*107% -> 476.71346 | CS39: =CO39*107% -> 466.00865 | CT39: =CP39*107% -> 456.57467 | ... DB39: =CX39*107% -> 522.73234 | DF39: 1629.7263
A40: General and Administration Expenses | B40: ='Annual Raw'!C17 -> 0 | C40: ='Annual Raw'!D17 -> 0 | D40: ='Annual Raw'!E17 -> 0 | E40: ='Annual Raw'!F17 -> 0 | F40: ='Annual Raw'!G17 -> 0 | G40: ='Annual Raw'!H17 -> 0 | H40: ='Annual Raw'!I17 -> 0 | I40: ='Annual Raw'!J17 -> 0 | ... AA40: ='Annual Raw'!AB17 -> 246.2315 | AB40: =+SUM(CM40:CP40) -> 0 | AC40: =+SUM(CQ40:CT40) -> 0 | AD40: =+SUM(CU40:CX40) -> 0 | AE40: =+SUM(CY40:DB40) -> 0 | AI40: ='QTR Raw'!C17 -> 0 | AJ40: ='QTR Raw'!D17 -> 0 | AK40: ='QTR Raw'!E17 -> 0 | AL40: ='QTR Raw'!F17 -> 0 | AM40: ='QTR Raw'!G17 -> 0 | AN40: ='QTR Raw'!H17 -> 0 | AO40: ='QTR Raw'!I17 -> 0 | AP40: ='QTR Raw'!J17 -> 0 | ... CL40: ='QTR Raw'!BF17 -> 0 | DF40: 246.2315
A41: Miscellaneous Expenses | B41: ='Annual Raw'!C19-'Annual Raw'!C20 -> 0 | C41: ='Annual Raw'!D19-'Annual Raw'!D20 -> 0 | D41: ='Annual Raw'!E19-'Annual Raw'!E20 -> 0 | E41: ='Annual Raw'!F19-'Annual Raw'!F20 -> 0 | F41: ='Annual Raw'!G19-'Annual Raw'!G20 -> 0 | G41: ='Annual Raw'!H19-'Annual Raw'!H20 -> 0 | H41: ='Annual Raw'!I19-'Annual Raw'!I20 -> 0 | I41: ='Annual Raw'!J19-'Annual Raw'!J20 -> 0 | ... AA41: ='Annual Raw'!AB19-'Annual Raw'!AB20 -> 275.1806 | AB41: =+SUM(CM41:CP41) -> 0 | AC41: =+SUM(CQ41:CT41) -> 0 | AD41: =+SUM(CU41:CX41) -> 0 | AE41: =+SUM(CY41:DB41) -> 0 | AI41: =+'QTR Raw'!C21 -> 0 | AJ41: =+'QTR Raw'!D21 -> 0 | AK41: =+'QTR Raw'!E21 -> 0 | AL41: =+'QTR Raw'!F21 -> 0 | AM41: =+'QTR Raw'!G21 -> 0 | AN41: =+'QTR Raw'!H21 -> 0 | AO41: =+'QTR Raw'!I21 -> 0 | AP41: =+'QTR Raw'!J21 -> 0 | ... CL41: =+'QTR Raw'!BF21 -> 0 | DF41: 275.1806
A42: Other Manufacturing Expenses | B42: ='Annual Raw'!C15+'Annual Raw'!C16 -> 0 | C42: ='Annual Raw'!D15+'Annual Raw'!D16 -> 0 | D42: ='Annual Raw'!E15+'Annual Raw'!E16 -> 0 | E42: ='Annual Raw'!F15+'Annual Raw'!F16 -> 0 | F42: ='Annual Raw'!G15+'Annual Raw'!G16 -> 0 | G42: ='Annual Raw'!H15+'Annual Raw'!H16 -> 0 | H42: ='Annual Raw'!I15+'Annual Raw'!I16 -> 0 | I42: ='Annual Raw'!J15+'Annual Raw'!J16 -> 0 | ... AA42: ='Annual Raw'!AB15+'Annual Raw'!AB16 -> 1395.5755 | AB42: =+SUM(CM42:CP42) -> 4139.1461 | AC42: =+SUM(CQ42:CT42) -> 4534.7945 | AD42: =+SUM(CU42:CX42) -> 4973.6697 | AE42: =+SUM(CY42:DB42) -> 5460.3508 | AI42: ='QTR Raw'!C14 -> 224.58 | AJ42: ='QTR Raw'!D14 -> 278.76 | AK42: ='QTR Raw'!E14 -> 240.94 | AL42: ='QTR Raw'!F14 -> 188.49 | AM42: ='QTR Raw'!G14 -> 208.47 | AN42: ='QTR Raw'!H14 -> 234.04 | AO42: ='QTR Raw'!I14 -> 357.96 | AP42: ='QTR Raw'!J14 -> 406.77 | ... CL42: ='QTR Raw'!BF14 -> 1114.62 | CM42: =CM45-CM39-CM40-CM41-CM43-CM44 -> 957.23022 | CN42: =CN45-CN39-CN40-CN41-CN43-CN44 -> 824.58408 | CO42: =CO45-CO39-CO40-CO41-CO43-CO44 -> 1122.0007 | CP42: =CP45-CP39-CP40-CP41-CP43-CP44 -> 1235.3311 | CQ42: =CQ45-CQ39-CQ40-CQ41-CQ43-CQ44 -> 1048.3898 | CR42: =CR45-CR39-CR40-CR41-CR43-CR44 -> 902.76315 | CS42: =CS45-CS39-CS40-CS41-CS43-CS44 -> 1229.6213 | CT42: =CT45-CT39-CT40-CT41-CT43-CT44 -> 1354.0202 | ... DB42: =DB45-DB39-DB40-DB41-DB43-DB44 -> 1631.0326 | DF42: 1395.5755
A43: Power & Fuel Cost | B43: ='Annual Raw'!C13 -> 0 | C43: ='Annual Raw'!D13 -> 0 | D43: ='Annual Raw'!E13 -> 0 | E43: ='Annual Raw'!F13 -> 0 | F43: ='Annual Raw'!G13 -> 0 | G43: ='Annual Raw'!H13 -> 0 | H43: ='Annual Raw'!I13 -> 0 | I43: ='Annual Raw'!J13 -> 0 | ... AA43: ='Annual Raw'!AB13 -> 724.0416 | AB43: =+SUM(CM43:CP43) -> 0 | AC43: =+SUM(CQ43:CT43) -> 0 | AD43: =+SUM(CU43:CX43) -> 0 | AE43: =+SUM(CY43:DB43) -> 0 | AI43: ='QTR Raw'!C15 -> 0 | AJ43: ='QTR Raw'!D15 -> 0 | AK43: ='QTR Raw'!E15 -> 0 | AL43: ='QTR Raw'!F15 -> 0 | AM43: ='QTR Raw'!G15 -> 0 | AN43: ='QTR Raw'!H15 -> 0 | AO43: ='QTR Raw'!I15 -> 0 | AP43: ='QTR Raw'!J15 -> 0 | ... CL43: ='QTR Raw'!BF15 -> 0 | DF43: 724.0416
A44: Selling and Distribution Expenses | B44: ='Annual Raw'!C18 -> 0 | C44: ='Annual Raw'!D18 -> 0 | D44: ='Annual Raw'!E18 -> 0 | E44: ='Annual Raw'!F18 -> 0 | F44: ='Annual Raw'!G18 -> 0 | G44: ='Annual Raw'!H18 -> 0 | H44: ='Annual Raw'!I18 -> 0 | I44: ='Annual Raw'!J18 -> 0 | ... AA44: ='Annual Raw'!AB18 -> 1409.8388 | AB44: =+SUM(CM44:CP44) -> 0 | AC44: =+SUM(CQ44:CT44) -> 0 | AD44: =+SUM(CU44:CX44) -> 0 | AE44: =+SUM(CY44:DB44) -> 0 | AI44: ='QTR Raw'!C18 -> 0 | AJ44: ='QTR Raw'!D18 -> 0 | AK44: ='QTR Raw'!E18 -> 0 | AL44: ='QTR Raw'!F18 -> 0 | AM44: ='QTR Raw'!G18 -> 0 | AN44: ='QTR Raw'!H18 -> 0 | AO44: ='QTR Raw'!I18 -> 0 | AP44: ='QTR Raw'!J18 -> 0 | ... CL44: ='QTR Raw'!BF18 -> 0 | DF44: 1409.8388
A45: Total Cost | B45: =+SUM(B39:B44) -> 0 | C45: =+SUM(C39:C44) -> 0 | D45: =+SUM(D39:D44) -> 0 | E45: =+SUM(E39:E44) -> 0 | F45: =+SUM(F39:F44) -> 0 | G45: =+SUM(G39:G44) -> 0 | H45: =+SUM(H39:H44) -> 0 | I45: =+SUM(I39:I44) -> 0 | ... AE45: =+SUM(AE39:AE44) -> 7596.5944 | AI45: =+SUM(AI39:AI44) -> 286.46 | AJ45: =+SUM(AJ39:AJ44) -> 341.61 | AK45: =+SUM(AK39:AK44) -> 305.11 | AL45: =+SUM(AL39:AL44) -> 251.85 | AM45: =+SUM(AM39:AM44) -> 276.49 | AN45: =+SUM(AN39:AN44) -> 310.74 | AO45: =+SUM(AO39:AO44) -> 436.69 | AP45: =+SUM(AP39:AP44) -> 483.52 | ... CL45: =+SUM(CL39:CL44) -> 1513.41 | CM45: =+CM35-CM47 -> 1393.2873 | CN45: =+CN35-CN47 -> 1270.1107 | CO45: =+CO35-CO47 -> 1557.5228 | CP45: =+CP35-CP47 -> 1662.0364 | CQ45: =+CQ35-CQ47 -> 1514.9709 | CR45: =+CR35-CR47 -> 1379.4766 | CS45: =+CS35-CS47 -> 1695.63 | CT45: =+CT35-CT47 -> 1810.5949 | ... DB45: =+DB35-DB47 -> 2153.765 | DF45: 5680.5943
A46: Cost % | B46: =B45/B29 -> #DIV/0! | C46: =C45/C29 -> #DIV/0! | D46: =D45/D29 -> #DIV/0! | E46: =E45/E29 -> #DIV/0! | F46: =F45/F29 -> #DIV/0! | G46: =G45/G29 -> #DIV/0! | H46: =H45/H29 -> #DIV/0! | I46: =I45/I29 -> #DIV/0! | ... AE46: =AE45/AE29 -> 0.31451532 | AI46: =AI45/AI29 -> 0.22198802 | AJ46: =AJ45/AJ29 -> 0.20868944 | AK46: =AK45/AK29 -> 0.17710843 | AL46: =AL45/AL29 -> 0.25697144 | AM46: =AM45/AM29 -> 0.22907018 | AN46: =AN45/AN29 -> 0.2527595 | AO46: =AO45/AO29 -> 0.25543253 | AP46: =AP45/AP29 -> 0.35459599 | ... DB46: =DB45/DB29 -> 0.31451532 | DF46: 0.31743738
A47: EBITDA | B47: =B35-B45 -> 0 | C47: =C35-C45 -> 0 | D47: =D35-D45 -> 0 | E47: =E35-E45 -> 0 | F47: =F35-F45 -> 0 | G47: =G35-G45 -> 0 | H47: =H35-H45 -> 0 | I47: =I35-I45 -> 0 | ... AE47: =AE35-AE45 -> 3309.2703 | AI47: =AI35-AI45 -> 160.24 | AJ47: =AJ35-AJ45 -> 197.85 | AK47: =AK35-AK45 -> 158.56 | AL47: =AL35-AL45 -> 102.96 | AM47: =AM35-AM45 -> 142.36 | AN47: =AN35-AN45 -> 148.2 | AO47: =AO35-AO45 -> 165.73 | AP47: =AP35-AP45 -> 162.71 | ... CL47: =CL35-CL45 -> 480.88 | CM47: =+(CM$8+CM$10)*CM22/10^4 -> 524.8315 | CN47: =+(CN$8+CN$10)*CN22/10^4 -> 553.29261 | CO47: =+(CO$8+CO$10)*CO22/10^4 -> 678.49668 | CP47: =+(CP$8+CP$10)*CP22/10^4 -> 724.02543 | CQ47: =+(CQ$8+CQ$10)*CQ22/10^4 -> 659.95997 | CR47: =+(CR$8+CR$10)*CR22/10^4 -> 600.9352 | CS47: =+(CS$8+CS$10)*CS22/10^4 -> 738.65968 | CT47: =+(CT$8+CT$10)*CT22/10^4 -> 788.74131 | ... DB47: =+(DB$8+DB$10)*DB22/10^4 -> 938.23497 | DF47: 2161.7328
A48: EBITDA Margins | B48: =B47/B29 -> #DIV/0! | C48: =C47/C29 -> #DIV/0! | D48: =D47/D29 -> #DIV/0! | E48: =E47/E29 -> #DIV/0! | F48: =F47/F29 -> #DIV/0! | G48: =G47/G29 -> #DIV/0! | H48: =H47/H29 -> #DIV/0! | I48: =I47/I29 -> #DIV/0! | ... AE48: =AE47/AE29 -> 0.1370109 | AI48: =AI47/AI29 -> 0.12417566 | AJ48: =AJ47/AJ29 -> 0.1208665 | AK48: =AK47/AK29 -> 0.09203996 | AL48: =AL47/AL29 -> 0.10505372 | AM48: =AM47/AM29 -> 0.11794434 | AN48: =AN47/AN29 -> 0.12054759 | AO48: =AO47/AO29 -> 0.096940238 | AP48: =AP47/AP29 -> 0.1193256 | ... DB48: =DB47/DB29 -> 0.1370109 | DF48: 0.12079982
A49: EBITDA YOY% | C49: =+IF(B47<0,1-C47/B47,C47/B47-1) -> #DIV/0! | D49: =+IF(C47<0,1-D47/C47,D47/C47-1) -> #DIV/0! | E49: =+IF(D47<0,1-E47/D47,E47/D47-1) -> #DIV/0! | F49: =+IF(E47<0,1-F47/E47,F47/E47-1) -> #DIV/0! | G49: =+IF(F47<0,1-G47/F47,G47/F47-1) -> #DIV/0! | H49: =+IF(G47<0,1-H47/G47,H47/G47-1) -> #DIV/0! | I49: =+IF(H47<0,1-I47/H47,I47/H47-1) -> #DIV/0! | J49: =+IF(I47<0,1-J47/I47,J47/I47-1) -> #DIV/0! | ... AE49: =+IF(AD47<0,1-AE47/AD47,AE47/AD47-1) -> 0.089873896 | AM49: =+IF(AI47<0,1-AM47/AI47,AM47/AI47-1) -> -0.11158263 | AN49: =+IF(AJ47<0,1-AN47/AJ47,AN47/AJ47-1) -> -0.25094769 | AO49: =+IF(AK47<0,1-AO47/AK47,AO47/AK47-1) -> 0.045219475 | AP49: =+IF(AL47<0,1-AP47/AL47,AP47/AL47-1) -> 0.58032246 | AQ49: =+IF(AM47<0,1-AQ47/AM47,AQ47/AM47-1) -> 0.13683619 | AR49: =+IF(AN47<0,1-AR47/AN47,AR47/AN47-1) -> 0.41302294 | AS49: =+IF(AO47<0,1-AS47/AO47,AS47/AO47-1) -> 0.43908767 | AT49: =+IF(AP47<0,1-AT47/AP47,AT47/AP47-1) -> 0.40065147 | ... CL49: =+IF(CH47<0,1-CL47/CH47,CL47/CH47-1) -> -0.34677244 | CM49: =+CM47/CI47-1 -> -0.21679799 | CN49: =+CN47/CJ47-1 -> 0.22648654 | CO49: =+CO47/CK47-1 -> 0.10751462 | CP49: =+CP47/CL47-1 -> 0.50562601 | CQ49: =+CQ47/CM47-1 -> 0.25747021 | CR49: =+CR47/CN47-1 -> 0.0861074 | CS49: =+CS47/CO47-1 -> 0.088671024 | CT49: =+CT47/CP47-1 -> 0.089383422 | ... DB49: =+DB47/CX47-1 -> 0.091061268 | DF49: -0.3524081
A50: EBITDA QOQ% | AJ50: =+IF(AI47<0,1-AJ47/AI47,AJ47/AI47-1) -> 0.23471043 | AK50: =+IF(AJ47<0,1-AK47/AJ47,AK47/AJ47-1) -> -0.19858479 | AL50: =+IF(AK47<0,1-AL47/AK47,AL47/AK47-1) -> -0.3506559 | AM50: =+IF(AL47<0,1-AM47/AL47,AM47/AL47-1) -> 0.38267288 | AN50: =+IF(AM47<0,1-AN47/AM47,AN47/AM47-1) -> 0.041022759 | AO50: =+IF(AN47<0,1-AO47/AN47,AO47/AN47-1) -> 0.1182861 | AP50: =+IF(AO47<0,1-AP47/AO47,AP47/AO47-1) -> -0.01822241 | AQ50: =+IF(AP47<0,1-AQ47/AP47,AQ47/AP47-1) -> -0.0053469363 | ... CI50: =+IF(CH47<0,1-CI47/CH47,CI47/CH47-1) -> -0.089722343 | CJ50: =+IF(CI47>1,CJ47/CI47-1,1-CJ47/CI47) -> -0.32679709 | CK50: =+IF(CJ47>1,CK47/CJ47-1,1-CK47/CJ47) -> 0.35802004 | CL50: =+IF(CK47>1,CL47/CK47-1,1-CL47/CK47) -> -0.2150564 | CM50: =+CM47/CL47-1 -> 0.091398057 | CN50: =+CN47/CM47-1 -> 0.054229047 | CO50: =+CO47/CN47-1 -> 0.22628907 | CP50: =+CP47/CO47-1 -> 0.067102397 | CQ50: =+CQ47/CP47-1 -> -0.088485096 | CR50: =+CR47/CQ47-1 -> -0.089436904 | CS50: =+CS47/CR47-1 -> 0.22918358 | CT50: =+CT47/CS47-1 -> 0.06780068 | ... DB50: =+DB47/DA47-1 -> 0.069047711
A51: Depreciation | B51: ='Annual Raw'!C27 -> 0 | C51: ='Annual Raw'!D27 -> 0 | D51: ='Annual Raw'!E27 -> 0 | E51: ='Annual Raw'!F27 -> 0 | F51: ='Annual Raw'!G27 -> 0 | G51: ='Annual Raw'!H27 -> 0 | H51: ='Annual Raw'!I27 -> 0 | I51: ='Annual Raw'!J27 -> 0 | ... AA51: ='Annual Raw'!AB27 -> 630.4911 | AB51: =+SUM(CM51:CP51) -> 723.69311 | AC51: =+SUM(CQ51:CT51) -> 757.58318 | AD51: =+SUM(CU51:CX51) -> 789.06192 | AE51: =+SUM(CY51:DB51) -> 818.30089 | AI51: ='QTR Raw'!C28 -> 38.71 | AJ51: ='QTR Raw'!D28 -> 41.56 | AK51: ='QTR Raw'!E28 -> 38.63 | AL51: ='QTR Raw'!F28 -> 36.05 | AM51: ='QTR Raw'!G28 -> 45.39 | AN51: ='QTR Raw'!H28 -> 51.26 | AO51: ='QTR Raw'!I28 -> 53.86 | AP51: ='QTR Raw'!J28 -> 62.24 | ... CL51: ='QTR Raw'!BF28 -> 166.74 | CM51: =CM52*CL153 -> 177.6074 | CN51: =CN52*CM153 -> 179.84513 | CO51: =CO52*CN153 -> 182.04196 | CP51: =CP52*CO153 -> 184.19862 | CQ51: =CQ52*CP153 -> 186.31585 | CR51: =CR52*CQ153 -> 188.39437 | CS51: =CS52*CR153 -> 190.43488 | CT51: =CT52*CS153 -> 192.43809 | ... DB51: =DB52*DA153 -> 207.19999 | DF51: 630.4911
A52: Depreciation % of Net Block | B52: =+B51/B153 -> #DIV/0! | C52: =+C51/C153 -> #DIV/0! | D52: =+D51/D153 -> #DIV/0! | E52: =+E51/E153 -> #DIV/0! | F52: =+F51/F153 -> #DIV/0! | G52: =+G51/G153 -> #DIV/0! | H52: =+H51/H153 -> #DIV/0! | I52: =+I51/I153 -> #DIV/0! | ... AE52: =+AE51/AE153 -> 0.071620195 | AI52: =+AI51/AH153 -> #DIV/0! | AJ52: =+AJ51/AI153 -> #DIV/0! | AK52: =+AK51/AJ153 -> 0.012109035 | AL52: =+AL51/AK153 -> 0.011300303 | AM52: =+AM51/AL153 -> 0.0082480784 | AN52: =+AN51/AM153 -> 0.0093147499 | AO52: =+AO51/AN153 -> 0.014400338 | AP52: =+AP51/AO153 -> 0.016640866 | ... CL52: =+CL51/CK153 -> 0.018283276 | CM52: =CL52 -> 0.018283276 | CN52: =CM52 -> 0.018283276 | CO52: =CN52 -> 0.018283276 | CP52: =CO52 -> 0.018283276 | CQ52: =CP52 -> 0.018283276 | CR52: =CQ52 -> 0.018283276 | CS52: =CR52 -> 0.018283276 | CT52: =CS52 -> 0.018283276 | ... DB52: =DA52 -> 0.018283276 | DF52: 0.060931857
A53: EBIT | B53: =B47-B51 -> 0 | C53: =C47-C51 -> 0 | D53: =D47-D51 -> 0 | E53: =E47-E51 -> 0 | F53: =F47-F51 -> 0 | G53: =G47-G51 -> 0 | H53: =H47-H51 -> 0 | I53: =I47-I51 -> 0 | ... AE53: =AE47-AE51 -> 2490.9694 | AI53: =AI47-AI51 -> 121.53 | AJ53: =AJ47-AJ51 -> 156.29 | AK53: =AK47-AK51 -> 119.93 | AL53: =AL47-AL51 -> 66.91 | AM53: =AM47-AM51 -> 96.97 | AN53: =AN47-AN51 -> 96.94 | AO53: =AO47-AO51 -> 111.87 | AP53: =AP47-AP51 -> 100.47 | ... DB53: =DB47-DB51 -> 731.03498 | DF53: 1531.2417
A54: Other Income | B54: ='Annual Raw'!C23 -> 0 | C54: ='Annual Raw'!D23 -> 0 | D54: ='Annual Raw'!E23 -> 0 | E54: ='Annual Raw'!F23 -> 0 | F54: ='Annual Raw'!G23 -> 0 | G54: ='Annual Raw'!H23 -> 0 | H54: ='Annual Raw'!I23 -> 0 | I54: ='Annual Raw'!J23 -> 0 | ... AA54: ='Annual Raw'!AB23 -> 144.6897 | AB54: =+SUM(CM54:CP54) -> 0 | AC54: =+SUM(CQ54:CT54) -> 0 | AD54: =+SUM(CU54:CX54) -> 0 | AE54: =+SUM(CY54:DB54) -> 0 | AI54: ='QTR Raw'!C23 -> 18.37 | AJ54: ='QTR Raw'!D23 -> 22.54 | AK54: ='QTR Raw'!E23 -> 22.54 | AL54: ='QTR Raw'!F23 -> 18.96 | AM54: ='QTR Raw'!G23 -> 18.76 | AN54: ='QTR Raw'!H23 -> 20.75 | AO54: ='QTR Raw'!I23 -> 14.52 | AP54: ='QTR Raw'!J23 -> 30.62 | ... CL54: ='QTR Raw'!BF23 -> 23.37 | DF54: 144.6897
A55: Interest | B55: ='Annual Raw'!C25 -> 0 | C55: ='Annual Raw'!D25 -> 0 | D55: ='Annual Raw'!E25 -> 0 | E55: ='Annual Raw'!F25 -> 0 | F55: ='Annual Raw'!G25 -> 0 | G55: ='Annual Raw'!H25 -> 0 | H55: ='Annual Raw'!I25 -> 0 | I55: ='Annual Raw'!J25 -> 0 | ... AA55: ='Annual Raw'!AB25 -> 619.5593 | AB55: =+SUM(CM55:CP55) -> 347.5038 | AC55: =+SUM(CQ55:CT55) -> 286.41597 | AD55: =+SUM(CU55:CX55) -> 217.6339 | AE55: =+SUM(CY55:DB55) -> 119.6371 | AI55: ='QTR Raw'!C25 -> 32.33 | AJ55: ='QTR Raw'!D25 -> 37.67 | AK55: ='QTR Raw'!E25 -> 41.79 | AL55: ='QTR Raw'!F25 -> 38.29 | AM55: ='QTR Raw'!G25 -> 42.98 | AN55: ='QTR Raw'!H25 -> 54.7 | AO55: ='QTR Raw'!I25 -> 69.16 | AP55: ='QTR Raw'!J25 -> 59.35 | ... CL55: ='QTR Raw'!BF25 -> 162.7 | CM55: =CM56*CL187 -> 121.96555 | CN55: =CN56*CM187 -> 76.477583 | CO55: =CO56*CN187 -> 59.911989 | CP55: =CP56*CO187 -> 89.148679 | CQ55: =CQ56*CP187 -> 94.388252 | CR55: =CR56*CQ187 -> 69.03449 | CS55: =CS56*CR187 -> 46.036341 | CT55: =CT56*CS187 -> 76.956885 | ... DB55: =DB56*DA187 -> 31.960793 | DF55: 619.5593
A56: Interest % of Debt | B56: =+B55/B147 -> #DIV/0! | C56: =+C55/C147 -> #DIV/0! | D56: =+D55/D147 -> #DIV/0! | E56: =+E55/E147 -> #DIV/0! | F56: =+F55/F147 -> #DIV/0! | G56: =+G55/G147 -> #DIV/0! | H56: =+H55/H147 -> #DIV/0! | I56: =+I55/I147 -> #DIV/0! | ... AE56: =+AE55/AE147 -> 0.049030595 | AI56: =(AI55-AI54)/AH187 -> #DIV/0! | AJ56: =(AJ55-AJ54)/AI187 -> #DIV/0! | AK56: =(AK55-AK54)/AJ187 -> 0.0064222326 | AL56: =(AL55-AL54)/AK187 -> 0.0062155023 | AM56: =(AM55-AM54)/AL187 -> 0.0053663616 | AN56: =(AN55-AN54)/AM187 -> 0.0066351563 | AO56: =(AO55-AO54)/AN187 -> 0.015172341 | AP56: =(AP55-AP54)/AO187 -> 0.0062661959 | ... CL56: =(CL55-CL54)/CK187 -> 0.025057091 | CM56: 0.035 | CN56: =+CM56 -> 0.035 | CO56: =+CN56 -> 0.035 | CP56: =+CO56 -> 0.035 | CQ56: =+CP56 -> 0.035 | CR56: =+CQ56 -> 0.035 | CS56: =+CR56 -> 0.035 | CT56: =+CS56 -> 0.035 | CU56: =+CT56 -> 0.035 | ... DB56: =+DA56 -> 0.035 | DF56: 0.15335439
A57: PBT | B57: =B53+B54-B55 -> 0 | C57: =C53+C54-C55 -> 0 | D57: =D53+D54-D55 -> 0 | E57: =E53+E54-E55 -> 0 | F57: =F53+F54-F55 -> 0 | G57: =G53+G54-G55 -> 0 | H57: =H53+H54-H55 -> 0 | I57: =I53+I54-I55 -> 0 | ... AE57: =AE53+AE54-AE55 -> 2371.3323 | AI57: =AI53+AI54-AI55 -> 107.57 | AJ57: =AJ53+AJ54-AJ55 -> 141.16 | AK57: =AK53+AK54-AK55 -> 100.68 | AL57: =AL53+AL54-AL55 -> 47.58 | AM57: =AM53+AM54-AM55 -> 72.75 | AN57: =AN53+AN54-AN55 -> 62.99 | AO57: =AO53+AO54-AO55 -> 57.23 | AP57: =AP53+AP54-AP55 -> 71.74 | ... DB57: =DB53+DB54-DB55 -> 699.07418 | DF57: 1056.3721
A58: Tax | B58: ='Annual Raw'!C30 -> 0 | C58: ='Annual Raw'!D30 -> 0 | D58: ='Annual Raw'!E30 -> 0 | E58: ='Annual Raw'!F30 -> 0 | F58: ='Annual Raw'!G30 -> 0 | G58: ='Annual Raw'!H30 -> 0 | H58: ='Annual Raw'!I30 -> 0 | I58: ='Annual Raw'!J30 -> 0 | ... AA58: ='Annual Raw'!AB30 -> 150.3795 | AB58: =+SUM(CM58:CP58) -> 352.36233 | AC58: =+SUM(CQ58:CT58) -> 436.07425 | AD58: =+SUM(CU58:CX58) -> 507.42082 | AE58: =+SUM(CY58:DB58) -> 592.83308 | AI58: ='QTR Raw'!C29 -> 15.74 | AJ58: ='QTR Raw'!D29 -> 22.31 | AK58: ='QTR Raw'!E29 -> 24.77 | AL58: ='QTR Raw'!F29 -> 9.69 | AM58: ='QTR Raw'!G29 -> 5.44 | AN58: ='QTR Raw'!H29 -> 7.95 | AO58: ='QTR Raw'!I29 -> 9.99 | AP58: ='QTR Raw'!J29 -> 23.14 | ... CG58: ='QTR Raw'!BA29 -> 165.88 | CH58: =CH57*0.25 -> 116.415 | CI58: =CI57*0.25 -> 90.9775 | CJ58: ='QTR Raw'!BD29 -> 44.01 | CK58: ='QTR Raw'!BE29 -> 99.57 | CL58: ='QTR Raw'!BF29 -> 47.97 | CM58: =+CM57*CM59 -> 56.314638 | CN58: =+CN57*CN59 -> 74.242473 | CO58: =+CO57*CO59 -> 109.13568 | CP58: =+CP57*CP59 -> 112.66953 | CQ58: =+CQ57*CQ59 -> 94.813969 | CR58: =+CR57*CR59 -> 85.876586 | CS58: =+CS57*CS59 -> 125.54711 | CT58: =+CT57*CT59 -> 129.83658 | ... DB58: =+DB57*DB59 -> 174.76855 | DF58: 150.3795
A59: Tax Rate % | B59: =B58/B57 -> #DIV/0! | C59: =C58/C57 -> #DIV/0! | D59: =D58/D57 -> #DIV/0! | E59: =E58/E57 -> #DIV/0! | F59: =F58/F57 -> #DIV/0! | G59: =G58/G57 -> #DIV/0! | H59: =H58/H57 -> #DIV/0! | I59: =I58/I57 -> #DIV/0! | ... AE59: =AE58/AE57 -> 0.25 | AI59: =AI58/AI57 -> 0.14632332 | AJ59: =AJ58/AJ57 -> 0.15804761 | AK59: =AK58/AK57 -> 0.24602702 | AL59: =AL58/AL57 -> 0.203657 | AM59: =AM58/AM57 -> 0.074776632 | AN59: =AN58/AN57 -> 0.12621051 | AO59: =AO58/AO57 -> 0.1745588 | AP59: =AP58/AP57 -> 0.32255367 | ... CL59: =CL58/CL57 -> 0.27441222 | CM59: 0.25 | CN59: 0.25 | CO59: 0.25 | CP59: 0.25 | CQ59: 0.25 | CR59: 0.25 | CS59: 0.25 | CT59: 0.25 | CU59: 0.25 | CV59: 0.25 | CW59: 0.25 | CX59: 0.25 | CY59: 0.25 | CZ59: 0.25 | DA59: 0.25 | DB59: 0.25 | DF59: 0.14235467
A60: PAT | B60: =B57-B58 -> 0 | C60: =C57-C58 -> 0 | D60: =D57-D58 -> 0 | E60: =E57-E58 -> 0 | F60: =F57-F58 -> 0 | G60: =G57-G58 -> 0 | H60: =H57-H58 -> 0 | I60: =I57-I58 -> 0 | ... AE60: =AE57-AE58 -> 1778.4992 | AI60: =AI57-AI58 -> 91.83 | AJ60: =AJ57-AJ58 -> 118.85 | AK60: =AK57-AK58 -> 75.91 | AL60: =AL57-AL58 -> 37.89 | AM60: =AM57-AM58 -> 67.31 | AN60: =AN57-AN58 -> 55.04 | AO60: =AO57-AO58 -> 47.24 | AP60: =AP57-AP58 -> 48.6 | ... DB60: =DB57-DB58 -> 524.30564 | DF60: 905.9926
A61: PAT % | B61: =+B60/B29 -> #DIV/0! | C61: =+C60/C29 -> #DIV/0! | D61: =+D60/D29 -> #DIV/0! | E61: =+E60/E29 -> #DIV/0! | F61: =+F60/F29 -> #DIV/0! | G61: =+G60/G29 -> #DIV/0! | H61: =+H60/H29 -> #DIV/0! | I61: =+I60/I29 -> #DIV/0! | ... AE61: =+AE60/AE29 -> 0.073633688 | AI61: =+AI60/AI29 -> 0.071162326 | AJ61: =+AJ60/AJ29 -> 0.072605426 | AK61: =+AK60/AK29 -> 0.044063782 | AL61: =+AL60/AL29 -> 0.038660504 | AM61: =+AM60/AM29 -> 0.055765901 | AN61: =+AN60/AN29 -> 0.044770171 | AO61: =+AO60/AO29 -> 0.027632033 | AP61: =+AP60/AP29 -> 0.035641473 | ... DB61: =+DB60/DB29 -> 0.076564601 | DF61: 0.050627786
A62: PAT YOY% | C62: =+IF(B60<0,1-C60/B60,C60/B60-1) -> #DIV/0! | D62: =+IF(C60<0,1-D60/C60,D60/C60-1) -> #DIV/0! | E62: =+IF(D60<0,1-E60/D60,E60/D60-1) -> #DIV/0! | F62: =+IF(E60<0,1-F60/E60,F60/E60-1) -> #DIV/0! | G62: =+IF(F60<0,1-G60/F60,G60/F60-1) -> #DIV/0! | H62: =+IF(G60<0,1-H60/G60,H60/G60-1) -> #DIV/0! | I62: =+IF(H60<0,1-I60/H60,I60/H60-1) -> #DIV/0! | J62: =+IF(I60<0,1-J60/I60,J60/I60-1) -> #DIV/0! | ... AE62: =+IF(AD60<0,1-AE60/AD60,AE60/AD60-1) -> 0.16832628 | AM62: =+IF(AI60<0,1-AM60/AI60,AM60/AI60-1) -> -0.26701514 | AN62: =+IF(AJ60<0,1-AN60/AJ60,AN60/AJ60-1) -> -0.53689525 | AO62: =+IF(AK60<0,1-AO60/AK60,AO60/AK60-1) -> -0.3776841 | AP62: =+IF(AL60<0,1-AP60/AL60,AP60/AL60-1) -> 0.28266033 | AQ62: =+IF(AM60<0,1-AQ60/AM60,AQ60/AM60-1) -> -0.34095974 | AR62: =+IF(AN60<0,1-AR60/AN60,AR60/AN60-1) -> 0.44585756 | AS62: =+IF(AO60<0,1-AS60/AO60,AS60/AO60-1) -> 1.1570703 | AT62: =+IF(AP60<0,1-AT60/AP60,AT60/AP60-1) -> 0.98312757 | ... CL62: =+IF(CH60<0,1-CL60/CH60,CL60/CH60-1) -> -0.63681656 | CM62: =+CM60/CI60-1 -> -0.38100478 | CN62: =+CN60/CJ60-1 -> 0.72483094 | CO62: =+CO60/CK60-1 -> 0.33662809 | CP62: =+CP60/CL60-1 -> 1.6648423 | CQ62: =+CQ60/CM60-1 -> 0.68364697 | CR62: =+CR60/CN60-1 -> 0.15670427 | CS62: =+CS60/CO60-1 -> 0.15037639 | CT62: =+CT60/CP60-1 -> 0.15236637 | ... DB62: =+DB60/CX60-1 -> 0.16211695 | DF62: -0.36722321
A63: PAT QOQ% | AJ63: =+IF(AI60<0,1-AJ60/AI60,AJ60/AI60-1) -> 0.29423936 | AK63: =+IF(AJ60<0,1-AK60/AJ60,AK60/AJ60-1) -> -0.36129575 | AL63: =+IF(AK60<0,1-AL60/AK60,AL60/AK60-1) -> -0.50085628 | AM63: =+IF(AL60<0,1-AM60/AL60,AM60/AL60-1) -> 0.77645817 | AN63: =+IF(AM60<0,1-AN60/AM60,AN60/AM60-1) -> -0.18229089 | AO63: =+IF(AN60<0,1-AO60/AN60,AO60/AN60-1) -> -0.14171512 | AP63: =+IF(AO60<0,1-AP60/AO60,AP60/AO60-1) -> 0.028789162 | AQ63: =+IF(AP60<0,1-AQ60/AP60,AQ60/AP60-1) -> -0.087242798 | ... CL63: =+IF(CK60<0,1-CL60/CK60,CL60/CK60-1) -> -0.48218004 | CM63: =+CM60/CL60-1 -> 0.33194508 | CN63: =+CN60/CM60-1 -> 0.31835125 | CO63: =+CO60/CN60-1 -> 0.46998987 | CP63: =+CP60/CO60-1 -> 0.032380343 | CQ63: =+CQ60/CP60-1 -> -0.15847731 | CR63: =+CR60/CQ60-1 -> -0.094262308 | CS63: =+CS60/CR60-1 -> 0.46194813 | CT63: =+CT60/CS60-1 -> 0.034166209 | ... DB63: =+DB60/DA60-1 -> 0.036248097
A64: Minority Interest | B64: ='Annual Raw'!C32 -> 0 | C64: ='Annual Raw'!D32 -> 0 | D64: ='Annual Raw'!E32 -> 0 | E64: ='Annual Raw'!F32 -> 0 | F64: ='Annual Raw'!G32 -> 0 | G64: ='Annual Raw'!H32 -> 0 | H64: ='Annual Raw'!I32 -> 0 | I64: ='Annual Raw'!J32 -> 0 | ... AA64: ='Annual Raw'!AB32 -> 48.0266 | AB64: =+SUM(CM64:CP64) -> 63 | AC64: =+SUM(CQ64:CT64) -> 63 | AD64: =+SUM(CU64:CX64) -> 63 | AE64: =+SUM(CY64:DB64) -> 63 | AI64: ='QTR Raw'!C34 -> 0 | AJ64: ='QTR Raw'!D34 -> 0 | AK64: ='QTR Raw'!E34 -> 0 | AL64: ='QTR Raw'!F34 -> 0 | AM64: ='QTR Raw'!G34 -> 0 | AN64: ='QTR Raw'!H34 -> 0 | AO64: ='QTR Raw'!I34 -> 0 | AP64: ='QTR Raw'!J34 -> 0 | ... CL64: ='QTR Raw'!BF34 -> 15.75 | CM64: =+CL64 -> 15.75 | CN64: =+CM64 -> 15.75 | CO64: =+CN64 -> 15.75 | CP64: =+CO64 -> 15.75 | CQ64: =+CP64 -> 15.75 | CR64: =+CQ64 -> 15.75 | CS64: =+CR64 -> 15.75 | CT64: =+CS64 -> 15.75 | ... DB64: =+DA64 -> 15.75 | DF64: 48.0266
A65: Share of Associate | B65: ='Annual Raw'!C33+'Annual Raw'!C28 -> 0 | C65: ='Annual Raw'!D33+'Annual Raw'!D28 -> 0 | D65: ='Annual Raw'!E33+'Annual Raw'!E28 -> 0 | E65: ='Annual Raw'!F33+'Annual Raw'!F28 -> 0 | F65: ='Annual Raw'!G33+'Annual Raw'!G28 -> 0 | G65: ='Annual Raw'!H33+'Annual Raw'!H28 -> 0 | H65: ='Annual Raw'!I33+'Annual Raw'!I28 -> 0 | I65: ='Annual Raw'!J33+'Annual Raw'!J28 -> 0 | ... AA65: ='Annual Raw'!AB33+'Annual Raw'!AB28 -> 19.3331 | AB65: =+SUM(CM65:CP65) -> -12.64 | AC65: =+SUM(CQ65:CT65) -> -12.64 | AD65: =+SUM(CU65:CX65) -> -12.64 | AE65: =+SUM(CY65:DB65) -> -12.64 | AI65: ='QTR Raw'!C35 -> 0 | AJ65: ='QTR Raw'!D35 -> 0 | AK65: ='QTR Raw'!E35 -> 0 | AL65: ='QTR Raw'!F35 -> 0 | AM65: ='QTR Raw'!G35 -> 0 | AN65: ='QTR Raw'!H35 -> 0 | AO65: ='QTR Raw'!I35 -> 0 | AP65: ='QTR Raw'!J35 -> 0 | ... CL65: ='QTR Raw'!BF35 -> -3.16 | CM65: =+CL65 -> -3.16 | CN65: =+CM65 -> -3.16 | CO65: =+CN65 -> -3.16 | CP65: =+CO65 -> -3.16 | CQ65: =+CP65 -> -3.16 | CR65: =+CQ65 -> -3.16 | CS65: =+CR65 -> -3.16 | CT65: =+CS65 -> -3.16 | ... DB65: =+DA65 -> -3.16 | DF65: 19.3331
A66: Exceptional Income / Expenses | B66: ='Annual Raw'!C29+'Annual Raw'!C31+'Annual Raw'!C34+'Annual Raw'!C36 -> 0 | C66: ='Annual Raw'!D29+'Annual Raw'!D31+'Annual Raw'!D34+'Annual Raw'!D36 -> 0 | D66: ='Annual Raw'!E29+'Annual Raw'!E31+'Annual Raw'!E34+'Annual Raw'!E36 -> 0 | E66: ='Annual Raw'!F29+'Annual Raw'!F31+'Annual Raw'!F34+'Annual Raw'!F36 -> 0 | F66: ='Annual Raw'!G29+'Annual Raw'!G31+'Annual Raw'!G34+'Annual Raw'!G36 -> 0 | G66: ='Annual Raw'!H29+'Annual Raw'!H31+'Annual Raw'!H34+'Annual Raw'!H36 -> 0 | H66: ='Annual Raw'!I29+'Annual Raw'!I31+'Annual Raw'!I34+'Annual Raw'!I36 -> 0 | I66: ='Annual Raw'!J29+'Annual Raw'!J31+'Annual Raw'!J34+'Annual Raw'!J36 -> 0 | ... AA66: ='Annual Raw'!AB29+'Annual Raw'!AB31+'Annual Raw'!AB34+'Annual Raw'!AB36 -> 0 | AB66: =+SUM(CM66:CP66) -> 0 | AC66: =+SUM(CQ66:CT66) -> 0 | AD66: =+SUM(CU66:CX66) -> 0 | AE66: =+SUM(CY66:DB66) -> 0 | AI66: ='QTR Raw'!C26+'QTR Raw'!C31+'QTR Raw'!C32+'QTR Raw'!C33+'QTR Raw'!C36+'QTR Raw'!C37+'QTR Raw'!C39 -> -56.64 | AJ66: ='QTR Raw'!D26+'QTR Raw'!D31+'QTR Raw'!D32+'QTR Raw'!D33+'QTR Raw'!D36+'QTR Raw'!D37+'QTR Raw'!D39 -> -57.74 | AK66: ='QTR Raw'!E26+'QTR Raw'!E31+'QTR Raw'!E32+'QTR Raw'!E33+'QTR Raw'!E36+'QTR Raw'!E37+'QTR Raw'!E39 -> -15.88 | AL66: ='QTR Raw'!F26+'QTR Raw'!F31+'QTR Raw'!F32+'QTR Raw'!F33+'QTR Raw'!F36+'QTR Raw'!F37+'QTR Raw'!F39 -> -0.81 | AM66: ='QTR Raw'!G26+'QTR Raw'!G31+'QTR Raw'!G32+'QTR Raw'!G33+'QTR Raw'!G36+'QTR Raw'!G37+'QTR Raw'!G39 -> -52.1 | AN66: ='QTR Raw'!H26+'QTR Raw'!H31+'QTR Raw'!H32+'QTR Raw'!H33+'QTR Raw'!H36+'QTR Raw'!H37+'QTR Raw'!H39 -> -33.08 | AO66: ='QTR Raw'!I26+'QTR Raw'!I31+'QTR Raw'!I32+'QTR Raw'!I33+'QTR Raw'!I36+'QTR Raw'!I37+'QTR Raw'!I39 -> 2.8 | AP66: ='QTR Raw'!J26+'QTR Raw'!J31+'QTR Raw'!J32+'QTR Raw'!J33+'QTR Raw'!J36+'QTR Raw'!J37+'QTR Raw'!J39 -> 8.46 | ... CG66: ='QTR Raw'!BA26+'QTR Raw'!BA31+'QTR Raw'!BA32+'QTR Raw'!BA33+'QTR Raw'!BA36+'QTR Raw'!BA37+'QTR Raw'!BA39 -> 0 | CH66: -269.18 | CI66: 132.15 | CJ66: ='QTR Raw'!BD26+'QTR Raw'!BD31+'QTR Raw'!BD32+'QTR Raw'!BD33+'QTR Raw'!BD36+'QTR Raw'!BD37+'QTR Raw'!BD39 -> 0 | CK66: ='QTR Raw'!BE26+'QTR Raw'!BE31+'QTR Raw'!BE32+'QTR Raw'!BE33+'QTR Raw'!BE36+'QTR Raw'!BE37+'QTR Raw'!BE39 -> 0 | CL66: ='QTR Raw'!BF26+'QTR Raw'!BF31+'QTR Raw'!BF32+'QTR Raw'!BF33+'QTR Raw'!BF36+'QTR Raw'!BF37+'QTR Raw'!BF39 -> 0 | DF66: 0
A67: Consolidated Net Profit | B67: =B60+B64+B65+B66 -> 0 | C67: =C60+C64+C65+C66 -> 0 | D67: =D60+D64+D65+D66 -> 0 | E67: =E60+E64+E65+E66 -> 0 | F67: =F60+F64+F65+F66 -> 0 | G67: =G60+G64+G65+G66 -> 0 | H67: =H60+H64+H65+H66 -> 0 | I67: =I60+I64+I65+I66 -> 0 | ... AE67: =AE60+AE64+AE65+AE66 -> 1828.8592 | AI67: =AI60+AI64+AI65+AI66 -> 35.19 | AJ67: =AJ60+AJ64+AJ65+AJ66 -> 61.11 | AK67: =AK60+AK64+AK65+AK66 -> 60.03 | AL67: =AL60+AL64+AL65+AL66 -> 37.08 | AM67: =AM60+AM64+AM65+AM66 -> 15.21 | AN67: =AN60+AN64+AN65+AN66 -> 21.96 | AO67: =AO60+AO64+AO65+AO66 -> 50.04 | AP67: =AP60+AP64+AP65+AP66 -> 57.06 | ... DB67: =DB60+DB64+DB65+DB66 -> 536.89564 | DF67: 973.3523
A68: Profit & Loss- Annual (End)
A70: Ace - PAT | B70: ='Annual Raw'!C35 -> 0 | C70: ='Annual Raw'!D35 -> 0 | D70: ='Annual Raw'!E35 -> 0 | E70: ='Annual Raw'!F35 -> 0 | F70: ='Annual Raw'!G35 -> 0 | G70: ='Annual Raw'!H35 -> 0 | H70: ='Annual Raw'!I35 -> 0 | I70: ='Annual Raw'!J35 -> 0 | ... AA70: ='Annual Raw'!AB35 -> 973.3523 | AB70: =+AB67 -> 1107.447 | AC70: =+AC67 -> 1358.5828 | AD70: =+AD67 -> 1572.6224 | AE70: =+AE67 -> 1828.8592 | AI70: ='QTR Raw'!C42 -> 35.19 | AJ70: ='QTR Raw'!D42 -> 61.11 | AK70: ='QTR Raw'!E42 -> 60.03 | AL70: ='QTR Raw'!F42 -> 37.08 | AM70: ='QTR Raw'!G42 -> 15.21 | AN70: ='QTR Raw'!H42 -> 21.96 | AO70: ='QTR Raw'!I42 -> 50.04 | AP70: ='QTR Raw'!J42 -> 57.06 | ... CL70: ='QTR Raw'!BF42 -> 139.43 | DF70: 973.3523
A71: Checksum - PAT | B71: =B70-B67 -> 0 | C71: =C70-C67 -> 0 | D71: =D70-D67 -> 0 | E71: =E70-E67 -> 0 | F71: =F70-F67 -> 0 | G71: =G70-G67 -> 0 | H71: =H70-H67 -> 0 | I71: =I70-I67 -> 0 | ... AE71: =AE70-AE67 -> 0 | AI71: =AI70-AI67 -> 2.1316282e-13 | AJ71: =AJ70-AJ67 -> -1.3500312e-13 | AK71: =AK70-AK67 -> -6.3948846e-14 | AL71: =AL70-AL67 -> 7.8159701e-14 | AM71: =AM70-AM67 -> -2.8421709e-14 | AN71: =AN70-AN67 -> 6.3948846e-14 | AO71: =AO70-AO67 -> -7.1054274e-14 | AP71: =AP70-AP67 -> -2.6290081e-13 | ... CL71: =CL70-CL67 -> 3.4106051e-13 | DF71: 0
A72: Ratios (Start)
A73: ROE (%) | B73: =(B67-B66)/B139 -> #DIV/0! | C73: =(C67-C66)/C139 -> #DIV/0! | D73: =(D67-D66)/D139 -> #DIV/0! | E73: =(E67-E66)/E139 -> #DIV/0! | F73: =(F67-F66)/F139 -> #DIV/0! | G73: =(G67-G66)/G139 -> #DIV/0! | H73: =(H67-H66)/H139 -> #DIV/0! | I73: =(I67-I66)/I139 -> #DIV/0! | ... AE73: =(AE67-AE66)/AE139 -> 0.099169498 | AL73: =(SUM(AI67:AL67)-SUM(AI66:AL66))/AL139 -> 0.088474679 | AM73: =(SUM(AJ67:AM67)-SUM(AJ66:AM66))/AM139 -> 0.081451109 | AN73: =(SUM(AK67:AN67)-SUM(AK66:AN66))/AN139 -> 0.062713782 | AO73: =(SUM(AL67:AO67)-SUM(AL66:AO66))/AO139 -> 0.054377339 | AP73: =(SUM(AM67:AP67)-SUM(AM66:AP66))/AP139 -> 0.061145394 | AQ73: =(SUM(AN67:AQ67)-SUM(AN66:AQ66))/AQ139 -> 0.053884878 | AR73: =(SUM(AO67:AR67)-SUM(AO66:AR66))/AR139 -> 0.054880927 | AS73: =(SUM(AP67:AS67)-SUM(AP66:AS66))/AS139 -> 0.067486518 | ... DB73: =(SUM(CY67:DB67)-SUM(CY66:DB66))/DB139 -> 0.099169498 | DF73: 0.07740841
A74: ROCE (%) | B74: =+B53/B148 -> #DIV/0! | C74: =+C53/C148 -> #DIV/0! | D74: =+D53/D148 -> #DIV/0! | E74: =+E53/E148 -> #DIV/0! | F74: =+F53/F148 -> #DIV/0! | G74: =+G53/G148 -> #DIV/0! | H74: =+H53/H148 -> #DIV/0! | I74: =+I53/I148 -> #DIV/0! | ... AE74: =+AE53/AE148 -> 0.12097798 | AL74: =+SUM(AI53:AL53)/AL148 -> 0.052732283 | AM74: =+SUM(AJ53:AM53)/AM148 -> 0.04985901 | AN74: =+SUM(AK53:AN53)/AN148 -> 0.051312011 | AO74: =+SUM(AL53:AO53)/AO148 -> 0.049889362 | AP74: =+SUM(AM53:AP53)/AP148 -> 0.042758162 | AQ74: =+SUM(AN53:AQ53)/AQ148 -> 0.042805522 | AR74: =+SUM(AO53:AR53)/AR148 -> 0.060716301 | AS74: =+SUM(AP53:AS53)/AS148 -> 0.068705388 | ... DB74: =+SUM(CY53:DB53)/DB148 -> 0.12097798 | DF74: 0.093810179
A75: Ratios (End)
A76: Checksum Of qtr to Annual
A77: Revenue - Checksum Of qtr to Annual | N77: =N29-SUM(AI29:AL29) -> 1134.5678 | O77: =O29-SUM(AM29:AP29) -> 1146.2574 | P77: =P29-SUM(AQ29:AT29) -> 1605.9501 | Q77: =Q29-SUM(AU29:AX29) -> 1457.3186 | R77: =R29-SUM(AY29:BB29) -> 1379.4814 | S77: =S29-SUM(BC29:BF29) -> 1216.6899 | T77: =T29-SUM(BG29:BJ29) -> 0.0016 | U77: =U29-SUM(BK29:BN29) -> -0.0032 | V77: =V29-SUM(BO29:BR29) -> -0.0042 | W77: =W29-SUM(BS29:BV29) -> 0.0011 | X77: =X29-SUM(BW29:BZ29) -> 0.2189 | Y77: =Y29-SUM(CA29:CD29) -> 9.9999997e-05 | Z77: =Z29-SUM(CE29:CH29) -> 0.0048 | AA77: =AA29-SUM(CF29:CI29) -> -2079.3248 | AB77: =AB29-SUM(CM29:CP29) -> 0 | AC77: =AC29-SUM(CQ29:CT29) -> 0 | AD77: =AD29-SUM(CU29:CX29) -> 0 | AE77: =AE29-SUM(CY29:DB29) -> 0 | DF77: -2079.3248
A78: GP - Checksum Of qtr to Annual | N78: =N35-SUM(AI35:AL35) -> 700.2726 | O78: =O35-SUM(AM35:AP35) -> 810.0456 | P78: =P35-SUM(AQ35:AT35) -> 980.7163 | Q78: =Q35-SUM(AU35:AX35) -> 675.188 | R78: =R35-SUM(AY35:BB35) -> 576.5517 | S78: =S35-SUM(BC35:BF35) -> 596.3273 | T78: =T35-SUM(BG35:BJ35) -> 0.0067 | U78: =U35-SUM(BK35:BN35) -> 0.0021 | V78: =V35-SUM(BO35:BR35) -> 0.0052 | W78: =W35-SUM(BS35:BV35) -> 1.0025 | X78: =X35-SUM(BW35:BZ35) -> 0.1514 | Y78: =Y35-SUM(CA35:CD35) -> 0.0001 | Z78: =Z35-SUM(CE35:CH35) -> 0.0072 | AA78: =AA35-SUM(CF35:CI35) -> -875.1229 | AB78: =AB35-SUM(CM35:CP35) -> 0 | AC78: =AC35-SUM(CQ35:CT35) -> 0 | AD78: =AD35-SUM(CU35:CX35) -> 0 | AE78: =AE35-SUM(CY35:DB35) -> 0 | DF78: -875.1229
A79: EBITDA - Checksum Of qtr to Annual | N79: =N47-SUM(AI47:AL47) -> -15.9315 | O79: =O47-SUM(AM47:AP47) -> 21.0115 | P79: =P47-SUM(AQ47:AT47) -> -29.3267 | Q79: =Q47-SUM(AU47:AX47) -> -280.0109 | R79: =R47-SUM(AY47:BB47) -> -233.2379 | S79: =S47-SUM(BC47:BF47) -> -51.152 | T79: =T47-SUM(BG47:BJ47) -> -43.0954 | U79: =U47-SUM(BK47:BN47) -> -48.4077 | V79: =V47-SUM(BO47:BR47) -> -58.1396 | W79: =W47-SUM(BS47:BV47) -> -46.6372 | X79: =X47-SUM(BW47:BZ47) -> -60.6997 | Y79: =Y47-SUM(CA47:CD47) -> -144.2679 | Z79: =Z47-SUM(CE47:CH47) -> -91.1403 | AA79: =AA47-SUM(CF47:CI47) -> -1098.0672 | AB79: =AB47-SUM(CM47:CP47) -> 0 | AC79: =AC47-SUM(CQ47:CT47) -> 0 | AD79: =AD47-SUM(CU47:CX47) -> 0 | AE79: =AE47-SUM(CY47:DB47) -> 0 | DF79: -1098.0672
A80: PAT - Checksum Of qtr to Annual | N80: =N67-SUM(AI67:AL67) -> -212.2767 | O80: =O67-SUM(AM67:AP67) -> -229.8122 | P80: =P67-SUM(AQ67:AT67) -> -302.2846 | Q80: =Q67-SUM(AU67:AX67) -> -261.4942 | R80: =R67-SUM(AY67:BB67) -> -193.9295 | S80: =S67-SUM(BC67:BF67) -> -207.2929 | T80: =T67-SUM(BG67:BJ67) -> -0.0005 | U80: =U67-SUM(BK67:BN67) -> 0.0111 | V80: =V67-SUM(BO67:BR67) -> 0.0006 | W80: =W60-SUM(BS60:BV60) -> 0.0098 | X80: =X60-SUM(BW60:BZ60) -> 5.7167 | Y80: =Y60-SUM(CA60:CD60) -> 0.0157 | Z80: =Z60-SUM(CE60:CH60) -> -269.1722 | AA80: =AA60-SUM(CF60:CI60) -> -656.6849 | AB80: =AB60-SUM(CM60:CP60) -> 0 | AC80: =AC60-SUM(CQ60:CT60) -> 0 | AD80: =AD60-SUM(CU60:CX60) -> -2.5011104e-12 | AE80: =AE60-SUM(CY60:DB60) -> 0 | DF80: -656.6849
A81: Valuation (Start)
A82: Eq | B82: ='Annual Raw'!C104 -> 0 | C82: ='Annual Raw'!D104 -> 0 | D82: ='Annual Raw'!E104 -> 0 | E82: =+F82 -> 63.95 | F82: =+G82 -> 63.95 | G82: =+H82 -> 63.95 | H82: =+I82 -> 63.95 | I82: =+J82 -> 63.95 | J82: =+K82 -> 63.95 | K82: =+L82 -> 63.95 | L82: =+M82 -> 63.95 | ... AA82: =+AB82 -> 63.95 | AB82: =AA82 -> 63.95 | AC82: =AB82 -> 63.95 | AD82: =AC82 -> 63.95 | AE82: =AD82 -> 63.95 | AI82: =+AJ82 -> 63.95 | AJ82: =+AK82 -> 63.95 | AK82: =+AL82 -> 63.95 | AL82: =+AM82 -> 63.95 | AM82: =+AN82 -> 63.95 | AN82: =+AO82 -> 63.95 | AO82: =+AP82 -> 63.95 | AP82: =+AQ82 -> 63.95 | ... CI82: =+CJ82 -> 63.95 | CJ82: ='QTR Raw'!BD45 -> 63.95 | CK82: ='QTR Raw'!BE45 -> 63.95 | CL82: ='QTR Raw'!BF45 -> 63.95 | CM82: =+CL82 -> 63.95 | CN82: =+CM82 -> 63.95 | CO82: =+CN82 -> 63.95 | CP82: =+CO82 -> 63.95 | CQ82: =+CP82 -> 63.95 | CR82: =+CQ82 -> 63.95 | CS82: =+CR82 -> 63.95 | CT82: =+CS82 -> 63.95 | ... DB82: =+DA82 -> 63.95 | DF82: 63.95
A83: FV | B83: ='Annual Raw'!C105 -> 0 | C83: ='Annual Raw'!D105 -> 0 | D83: ='Annual Raw'!E105 -> 0 | E83: =+F83 -> 1 | F83: =+G83 -> 1 | G83: =+H83 -> 1 | H83: =+I83 -> 1 | I83: =+J83 -> 1 | J83: =+K83 -> 1 | K83: =+L83 -> 1 | L83: =+M83 -> 1 | ... AA83: =+AB83 -> 1 | AB83: =AA83 -> 1 | AC83: =AB83 -> 1 | AD83: =AC83 -> 1 | AE83: =AD83 -> 1 | AI83: =AJ83 -> 1 | AJ83: =AK83 -> 1 | AK83: =AL83 -> 1 | AL83: =AM83 -> 1 | AM83: =AN83 -> 1 | AN83: =AO83 -> 1 | AO83: =AP83 -> 1 | AP83: =AQ83 -> 1 | ... CI83: =CJ83 -> 1 | CJ83: ='QTR Raw'!BD46 -> 1 | CK83: ='QTR Raw'!BE46 -> 1 | CL83: ='QTR Raw'!BF46 -> 1 | CM83: =+CL83 -> 1 | CN83: =+CM83 -> 1 | CO83: =+CN83 -> 1 | CP83: =+CO83 -> 1 | CQ83: =+CP83 -> 1 | CR83: =+CQ83 -> 1 | CS83: =+CR83 -> 1 | CT83: =+CS83 -> 1 | ... DB83: =+DA83 -> 1 | DF83: 1
A84: No of share | B84: =B82/B83 -> #DIV/0! | C84: =C82/C83 -> #DIV/0! | D84: =D82/D83 -> #DIV/0! | E84: =E82/E83 -> 63.95 | F84: =F82/F83 -> 63.95 | G84: =G82/G83 -> 63.95 | H84: =H82/H83 -> 63.95 | I84: =I82/I83 -> 63.95 | ... AE84: =AE82/AE83 -> 63.95 | AI84: =AI82/AI83 -> 63.95 | AJ84: =AJ82/AJ83 -> 63.95 | AK84: =AK82/AK83 -> 63.95 | AL84: =AL82/AL83 -> 63.95 | AM84: =AM82/AM83 -> 63.95 | AN84: =AN82/AN83 -> 63.95 | AO84: =AO82/AO83 -> 63.95 | AP84: =AP82/AP83 -> 63.95 | ... DB84: =DB82/DB83 -> 63.95 | DF84: 63.95
A85: EPS | B85: =(B67-B66)/B84 -> #DIV/0! | C85: =(C67-C66)/C84 -> #DIV/0! | D85: =(D67-D66)/D84 -> #DIV/0! | E85: =(E67-E66)/E84 -> 0 | F85: =(F67-F66)/F84 -> 0 | G85: =(G67-G66)/G84 -> 0 | H85: =(H67-H66)/H84 -> 0 | I85: =(I67-I66)/I84 -> 0 | ... AE85: =(AE67-AE66)/AE84 -> 28.598268 | AI85: =(AI67-AI66)/AI84 -> 1.4359656 | AJ85: =(AJ67-AJ66)/AJ84 -> 1.8584832 | AK85: =(AK67-AK66)/AK84 -> 1.1870211 | AL85: =(AL67-AL66)/AL84 -> 0.59249414 | AM85: =(AM67-AM66)/AM84 -> 1.052541 | AN85: =(AN67-AN66)/AN84 -> 0.8606724 | AO85: =(AO67-AO66)/AO84 -> 0.73870211 | AP85: =(AP67-AP66)/AP84 -> 0.75996873 | ... DB85: =(DB67-DB66)/DB84 -> 8.3955534 | DF85: 27.183212
A86: DPS | B86: ='Annual Raw'!C110 -> 0 | C86: ='Annual Raw'!D110 -> 0 | D86: ='Annual Raw'!E110 -> 0 | E86: ='Annual Raw'!F110 -> 0 | F86: ='Annual Raw'!G110 -> 0 | G86: ='Annual Raw'!H110 -> 0 | H86: ='Annual Raw'!I110 -> 0 | I86: ='Annual Raw'!J110 -> 0 | ... AA86: ='Annual Raw'!AB110 -> 2 | DF86: 2
A87: DPS % of EPS | B87: =B86/B85 -> #DIV/0! | C87: =C86/C85 -> #DIV/0! | D87: =D86/D85 -> #DIV/0! | E87: =E86/E85 -> #DIV/0! | F87: =F86/F85 -> #DIV/0! | G87: =G86/G85 -> #DIV/0! | H87: =H86/H85 -> #DIV/0! | I87: =I86/I85 -> #DIV/0! | ... AE87: =AE86/AE85 -> 0 | DF87: 0.073574823
A88: EPS TTM | B88: =+B85 -> #DIV/0! | C88: =+C85 -> #DIV/0! | D88: =+D85 -> #DIV/0! | E88: =+E85 -> 0 | F88: =+F85 -> 0 | G88: =+G85 -> 0 | H88: =+H85 -> 0 | I88: =+I85 -> 0 | ... AE88: =+AE85 -> 28.598268 | AL88: =SUM(AI85:AL85) -> 5.073964 | AM88: =SUM(AJ85:AM85) -> 4.6905395 | AN88: =SUM(AK85:AN85) -> 3.6927287 | AO88: =SUM(AL85:AO85) -> 3.2444097 | AP88: =SUM(AM85:AP85) -> 3.4118843 | AQ88: =SUM(AN85:AQ85) -> 3.0530102 | AR88: =SUM(AO85:AR85) -> 3.4367475 | AS88: =SUM(AP85:AS85) -> 4.2914777 | ... DB88: =SUM(CY85:DB85) -> 28.598268 | DF88: 27.183212
A89: EPS Growth YoY % | C89: =+C88/B88-1 -> #DIV/0! | D89: =+D88/C88-1 -> #DIV/0! | E89: =+E88/D88-1 -> #DIV/0! | F89: =+F88/E88-1 -> #DIV/0! | G89: =+G88/F88-1 -> #DIV/0! | H89: =+H88/G88-1 -> #DIV/0! | I89: =+I88/H88-1 -> #DIV/0! | J89: =+J88/I88-1 -> #DIV/0! | ... AE89: =+AE88/AD88-1 -> 0.16293598 | AP89: =+IF(AL88<0,1-AP88/AL88,AP88/AL88-1) -> -0.32757027 | AQ89: =+IF(AM88<0,1-AQ88/AM88,AQ88/AM88-1) -> -0.34911322 | AR89: =+IF(AN88<0,1-AR88/AN88,AR88/AN88-1) -> -0.069320347 | AS89: =+IF(AO88<0,1-AS88/AO88,AS88/AO88-1) -> 0.3227299 | AT89: =+IF(AP88<0,1-AT88/AP88,AT88/AP88-1) -> 0.47678629 | AU89: =+IF(AQ88<0,1-AU88/AQ88,AU88/AQ88-1) -> 0.92102028 | AV89: =+IF(AR88<0,1-AV88/AR88,AV88/AR88-1) -> 0.67526618 | AW89: =+IF(AS88<0,1-AW88/AS88,AW88/AS88-1) -> 0.12516397 | ... DB89: =+IF(CX88<0,1-DB88/CX88,DB88/CX88-1) -> 0.16293598 | DF89: 0.036572813
A90: Bloomberg Estimate
A91: Estimate deviation
A92: Promoter Share holding % | B92: ='Annual Raw'!C112 -> 0 | C92: ='Annual Raw'!D112 -> 0 | D92: ='Annual Raw'!E112 -> 0 | E92: ='Annual Raw'!F112 -> 0 | F92: ='Annual Raw'!G112 -> 0 | G92: ='Annual Raw'!H112 -> 0 | H92: ='Annual Raw'!I112 -> 0 | I92: ='Annual Raw'!J112 -> 0 | ... AA92: ='Annual Raw'!AB112 -> 63.25 | AI92: ='QTR Raw'!C49 -> 46 | AJ92: ='QTR Raw'!D49 -> 45.99 | AK92: ='QTR Raw'!E49 -> 46 | AL92: ='QTR Raw'!F49 -> 46 | AM92: ='QTR Raw'!G49 -> 46 | AN92: ='QTR Raw'!H49 -> 46.27 | AO92: ='QTR Raw'!I49 -> 46.27 | AP92: ='QTR Raw'!J49 -> 46.27 | ... CL92: ='QTR Raw'!BF49 -> 63.25 | DF92: 63.25
A93: Pledge Share % | B93: ='Annual Raw'!C113 -> 0 | C93: ='Annual Raw'!D113 -> 0 | D93: ='Annual Raw'!E113 -> 0 | E93: ='Annual Raw'!F113 -> 0 | F93: ='Annual Raw'!G113 -> 0 | G93: ='Annual Raw'!H113 -> 0 | H93: ='Annual Raw'!I113 -> 0 | I93: ='Annual Raw'!J113 -> 0 | ... AA93: ='Annual Raw'!AB113 -> 0 | AI93: ='QTR Raw'!C50 -> 0 | AJ93: ='QTR Raw'!D50 -> 0 | AK93: ='QTR Raw'!E50 -> 0 | AL93: ='QTR Raw'!F50 -> 0 | AM93: ='QTR Raw'!G50 -> 0 | AN93: ='QTR Raw'!H50 -> 0 | AO93: ='QTR Raw'!I50 -> 0 | AP93: ='QTR Raw'!J50 -> 0 | ... CL93: ='QTR Raw'!BF50 -> 0 | DF93: 0
A95: Share Price
A96: Share Price - Close | B96: ='Annual Raw'!C106 -> 0 | C96: ='Annual Raw'!D106 -> 0 | D96: ='Annual Raw'!E106 -> 0 | E96: ='Annual Raw'!F106 -> 0 | F96: ='Annual Raw'!G106 -> 0 | G96: ='Annual Raw'!H106 -> 0 | H96: ='Annual Raw'!I106 -> 0 | I96: ='Annual Raw'!J106 -> 0 | ... AA96: ='Annual Raw'!AB106 -> 183.25 | AB96: =+CP96 -> 245 | AC96: =+CT96 -> 245 | AD96: =+CX96 -> 245 | AE96: =+DB96 -> 245 | AJ96: ='QTR Share Price'!HP21 -> 59.25 | AK96: ='QTR Share Price'!HQ21 -> 64.3 | AL96: ='QTR Share Price'!HR21 -> 41.05 | AM96: ='QTR Share Price'!HS21 -> 28.65 | AN96: ='QTR Share Price'!HT21 -> 22.175 | AO96: ='QTR Share Price'!HU21 -> 24.525 | AP96: ='QTR Share Price'!HV21 -> 28.3 | AQ96: ='QTR Share Price'!HW21 -> 41.675 | ... CL96: ='QTR Share Price'!JR21 -> 183.25 | CM96: 245 | CN96: =+CM96 -> 245 | CO96: =+CN96 -> 245 | CP96: =+CO96 -> 245 | CQ96: =+CP96 -> 245 | CR96: =+CQ96 -> 245 | CS96: =+CR96 -> 245 | CT96: =+CS96 -> 245 | CU96: =+CT96 -> 245 | ... DB96: =+DA96 -> 245 | DF96: 183.25
A97: Share Price - High | B97: ='Annual Raw'!C107 -> 0 | C97: ='Annual Raw'!D107 -> 0 | D97: ='Annual Raw'!E107 -> 0 | E97: ='Annual Raw'!F107 -> 0 | F97: ='Annual Raw'!G107 -> 0 | G97: ='Annual Raw'!H107 -> 0 | H97: ='Annual Raw'!I107 -> 0 | I97: ='Annual Raw'!J107 -> 0 | ... AA97: ='Annual Raw'!AB107 -> 277.4 | AB97: =+MAX(CM97:CP97) -> 277.97995 | AC97: =+MAX(CQ97:CT97) -> 341.01747 | AD97: =+MAX(CU97:CX97) -> 394.74351 | AE97: =+MAX(CY97:DB97) -> 459.06143 | AJ97: ='QTR Share Price'!HP19 -> 69.325 | AK97: ='QTR Share Price'!HQ19 -> 68.75 | AL97: ='QTR Share Price'!HR19 -> 68.4 | AM97: ='QTR Share Price'!HS19 -> 46.45 | AN97: ='QTR Share Price'!HT19 -> 31.875 | AO97: ='QTR Share Price'!HU19 -> 27.075 | AP97: ='QTR Share Price'!HV19 -> 31.65 | AQ97: ='QTR Share Price'!HW19 -> 47.95 | ... CL97: ='QTR Share Price'!JR19 -> 211.15 | CM97: =+CM88*CM105 -> 183.44892 | CN97: =+CN88*CN105 -> 204.39002 | CO97: =+CO88*CO105 -> 224.97458 | CP97: =+CP88*CP105 -> 277.97995 | CQ97: =+CQ88*CQ105 -> 306.97107 | CR97: =+CR88*CR105 -> 315.7319 | CS97: =+CS88*CS105 -> 328.09018 | CT97: =+CT88*CT105 -> 341.01747 | ... DB97: =+DB88*DB105 -> 459.06143 | DF97: 277.4
A98: Share Price - Low | B98: ='Annual Raw'!C108 -> 0 | C98: ='Annual Raw'!D108 -> 0 | D98: ='Annual Raw'!E108 -> 0 | E98: ='Annual Raw'!F108 -> 0 | F98: ='Annual Raw'!G108 -> 0 | G98: ='Annual Raw'!H108 -> 0 | H98: ='Annual Raw'!I108 -> 0 | I98: ='Annual Raw'!J108 -> 0 | ... AA98: ='Annual Raw'!AB108 -> 153.2 | AB98: =+MIN(CM98:CP98) -> 133.8834 | AC98: =+MIN(CQ98:CT98) -> 224.03146 | AD98: =+MIN(CU98:CX98) -> 257.55633 | AE98: =+MIN(CY98:DB98) -> 298.56431 | AJ98: =+'QTR Share Price'!HP20 -> 55.525 | AK98: =+'QTR Share Price'!HQ20 -> 50.85 | AL98: =+'QTR Share Price'!HR20 -> 39 | AM98: =+'QTR Share Price'!HS20 -> 24.35 | AN98: =+'QTR Share Price'!HT20 -> 18.95 | AO98: =+'QTR Share Price'!HU20 -> 21.35 | AP98: =+'QTR Share Price'!HV20 -> 23.125 | AQ98: =+'QTR Share Price'!HW20 -> 26.55 | ... CL98: =+'QTR Share Price'!JR20 -> 154.1 | CM98: =+CM106*CM88 -> 133.8834 | CN98: =+CN106*CN88 -> 149.16648 | CO98: =+CO106*CO88 -> 164.18936 | CP98: =+CP106*CP88 -> 202.87336 | CQ98: =+CQ106*CQ88 -> 224.03146 | CR98: =+CR106*CR88 -> 230.42522 | CS98: =+CS106*CS88 -> 239.44446 | CT98: =+CT106*CT88 -> 248.87896 | ... DB98: =+DB106*DB88 -> 335.02897 | DF98: 153.2
A100: Upside (%) | AB100: =+AB97/AB96-1 -> 0.13461205 | AC100: =+AC97/AC96-1 -> 0.39190804 | AD100: =+AD97/AD96-1 -> 0.61119801 | AE100: =+AE97/AE96-1 -> 0.87372014 | CM100: =+CM97/CM96-1 -> -0.25122889 | CN100: =+CN97/CN96-1 -> -0.16575504 | CO100: =+CO97/CO96-1 -> -0.0817364 | CP100: =+CP97/CP96-1 -> 0.13461205 | CQ100: =+CQ97/CQ96-1 -> 0.25294315 | CR100: =+CR97/CR96-1 -> 0.28870162 | CS100: =+CS97/CS96-1 -> 0.3391436 | CT100: =+CT97/CT96-1 -> 0.39190804 | ... DB100: =+DB97/DB96-1 -> 0.87372014
A101: Downside (%) | AB101: =+AB98/AB96-1 -> -0.45353716 | AC101: =+AC98/AC96-1 -> -0.08558589 | AD101: =+AD98/AD96-1 -> 0.051250314 | AE101: =+AE98/AE96-1 -> 0.21862983 | CM101: =+CM98/CM96-1 -> -0.45353716 | CN101: =+CN98/CN96-1 -> -0.39115724 | CO101: =+CO98/CO96-1 -> -0.32983935 | CP101: =+CP98/CP96-1 -> -0.17194545 | CQ101: =+CQ98/CQ96-1 -> -0.08558589 | CR101: =+CR98/CR96-1 -> -0.059488895 | CS101: =+CS98/CS96-1 -> -0.022675686 | CT101: =+CT98/CT96-1 -> 0.015832484 | ... DB101: =+DB98/DB96-1 -> 0.36746518
A103: PE
A104: PE - Close | B104: =+B96/B88 -> #DIV/0! | C104: =+C96/C88 -> #DIV/0! | D104: =+D96/D88 -> #DIV/0! | E104: =+E96/E88 -> #DIV/0! | F104: =+F96/F88 -> #DIV/0! | G104: =+G96/G88 -> #DIV/0! | H104: =+H96/H88 -> #DIV/0! | I104: =+I96/I88 -> #DIV/0! | ... AE104: =+AE96/AE88 -> 8.5669524 | AL104: =+AL96/AL88 -> 8.0903214 | AM104: =+AM96/AM88 -> 6.1080394 | AN104: =+AN96/AN88 -> 6.0050445 | AO104: =+AO96/AO88 -> 7.5591563 | AP104: =+AP96/AP88 -> 8.2945369 | AQ104: =+AQ96/AQ88 -> 13.650462 | AR104: =+AR96/AR88 -> 11.740752 | AS104: =+AS96/AS88 -> 10.882033 | ... DB104: =+DB96/DB88 -> 8.5669524 | DF104: 9.9362798
A105: PE - High | B105: =+B97/B88 -> #DIV/0! | C105: =+C97/C88 -> #DIV/0! | D105: =+D97/D88 -> #DIV/0! | E105: =+E97/E88 -> #DIV/0! | F105: =+F97/F88 -> #DIV/0! | G105: =+G97/G88 -> #DIV/0! | H105: =+H97/H88 -> #DIV/0! | I105: =+I97/I88 -> #DIV/0! | ... AE105: =+AE97/AE88 -> 16.052071 | AL105: =+AL97/AL88 -> 13.480584 | AM105: =+AM97/AM88 -> 9.9029121 | AN105: =+AN97/AN88 -> 8.6318283 | AO105: =+AO97/AO88 -> 8.3451236 | AP105: =+AP97/AP88 -> 9.276399 | AQ105: =+AQ97/AQ88 -> 15.705811 | AR105: =+AR97/AR88 -> 14.308587 | AS105: =+AS97/AS88 -> 13.491856 | ... CL105: =+CL97/CL88 -> 16.052071 | CM105: =+CL105 -> 16.052071 | CN105: =+CM105 -> 16.052071 | CO105: =+CN105 -> 16.052071 | CP105: =+CO105 -> 16.052071 | CQ105: =+CP105 -> 16.052071 | CR105: =+CQ105 -> 16.052071 | CS105: =+CR105 -> 16.052071 | CT105: =+CS105 -> 16.052071 | ... DB105: =+DA105 -> 16.052071 | DF105: 14.120848
A106: PE - Low | B106: =+B98/B88 -> #DIV/0! | C106: =+C98/C88 -> #DIV/0! | D106: =+D98/D88 -> #DIV/0! | E106: =+E98/E88 -> #DIV/0! | F106: =+F98/F88 -> #DIV/0! | G106: =+G98/G88 -> #DIV/0! | H106: =+H98/H88 -> #DIV/0! | I106: =+I98/I88 -> #DIV/0! | ... AE106: =+AE98/AE88 -> 10.439944 | AL106: =+AL98/AL88 -> 7.6862981 | AM106: =+AM98/AM88 -> 5.1913005 | AN106: =+AN98/AN88 -> 5.1317065 | AO106: =+AO98/AO88 -> 6.5805499 | AP106: =+AP98/AP88 -> 6.7777797 | AQ106: =+AQ98/AQ88 -> 8.6963353 | AR106: =+AR98/AR88 -> 10.431375 | AS106: =+AS98/AS88 -> 8.6799938 | ... CL106: =+CL98/CL88 -> 11.715009 | CM106: =+CL106 -> 11.715009 | CN106: =+CM106 -> 11.715009 | CO106: =+CN106 -> 11.715009 | CP106: =+CO106 -> 11.715009 | CQ106: =+CP106 -> 11.715009 | CR106: =+CQ106 -> 11.715009 | CS106: =+CR106 -> 11.715009 | CT106: =+CS106 -> 11.715009 | ... DB106: =+DA106 -> 11.715009 | DF106: 8.0067801
A108: PE - 1Yr Fwd | B108: =+B97/C88 -> #DIV/0! | C108: =+C97/D88 -> #DIV/0! | D108: =+D97/E88 -> #DIV/0! | E108: =+E97/F88 -> #DIV/0! | F108: =+F97/G88 -> #DIV/0! | G108: =+G97/H88 -> #DIV/0! | H108: =+H97/I88 -> #DIV/0! | I108: =+I97/J88 -> #DIV/0! | ... AD108: =+AD97/AE88 -> 13.803057 | AL108: =+AL97/AP88 -> 20.047573 | AM108: =+AM97/AQ88 -> 15.214492 | AN108: =+AN97/AR88 -> 9.2747577 | AO108: =+AO97/AS88 -> 6.3090156 | AP108: =+AP97/AT88 -> 6.2814769 | AQ108: =+AQ97/AU88 -> 8.1757652 | AR108: =+AR97/AV88 -> 8.5410827 | AS108: =+AS97/AW88 -> 11.991013 | ... CL108: =+CL97/CP88 -> 12.192947 | DF108: 29.181092
A109: Correlation | AO109: =+CORREL(AL88:AO88,AL105:AO105) -> 0.87629917 | AP109: =+CORREL(AM88:AP88,AM105:AP105) -> 0.81939529 | AQ109: =+CORREL(AN88:AQ88,AN105:AQ105) -> -0.71466072 | AR109: =+CORREL(AO88:AR88,AO105:AR105) -> -0.36388457 | AS109: =+CORREL(AP88:AS88,AP105:AS105) -> -0.14036354 | AT109: =+CORREL(AQ88:AT88,AQ105:AT105) -> -0.95233583 | AU109: =+CORREL(AR88:AU88,AR105:AU105) -> -0.96810887 | AV109: =+CORREL(AS88:AV88,AS105:AV105) -> -0.99262535 | ... CL109: =+CORREL(CI88:CL88,CI105:CL105) -> -0.90919986
A111: BVPS | E111: =+E$139/E$84 -> 0 | F111: =+F$139/F$84 -> 0 | G111: =+G$139/G$84 -> 0 | H111: =+H$139/H$84 -> 0 | I111: =+I$139/I$84 -> 0 | J111: =+J$139/J$84 -> 0 | K111: =+K$139/K$84 -> 57.655192 | L111: =+L$139/L$84 -> 63.634432 | ... AE111: =+AE$139/AE$84 -> 288.37766 | AL111: =+AL$139/AL$84 -> 57.349335 | AM111: =+AM$139/AM$84 -> 57.587177 | AN111: =+AN$139/AN$84 -> 58.882252 | AO111: =+AO$139/AO$84 -> 59.664738 | AP111: =+AP$139/AP$84 -> 55.799531 | AQ111: =+AQ$139/AQ$84 -> 56.658014 | AR111: =+AR$139/AR$84 -> 62.621892 | AS111: =+AS$139/AS$84 -> 63.590149 | ... DB111: =+DB$139/DB$84 -> 288.37766 | DF111: 178.43564
A112: PB
...

Sheet Notes
J5: Rajeev Goyal - VP Finance Mar 19, 2026
J6: Feed back from ground is good
J7: MP, rajasthan, and UP - by mar end to release 8000 crs
J8: Thrust on jal jeevan mission - some things are seeing
J9: positivity on the EPC sector
J10: 620,000 MT order from Saudi company - jobwork - 18-24 months
J11: stuck money -
J12: 450 crs jal jeevan mission money has not come
J14: 2 expansion - KSA - local demand
J15: 1 in Abu Dhabi - adnoc demand local
J16: all at starting point
J18: 20 lakh MT - can do in full swing in pipe
J20: Pellet - don’t take this vol. compare company of pipe volumes only

Sheet QTR Raw
A1: ='Annual Raw'!A1 -> 100378 | B1: X | C1: 201206 | D1: 201209 | E1: 201212 | F1: 201303 | G1: 201306 | H1: 201309 | I1: 201312 | J1: 201403 | K1: 201406 | L1: 201409 | M1: 201412 | N1: 201503 | O1: 201506 | P1: 201509 | Q1: 201512 | R1: 201603 | S1: 201606 | T1: 201609 | U1: 201612 | V1: 201703 | W1: 201706 | X1: 201709 | Y1: 201712 | Z1: 201803 | AA1: 201806 | AB1: 201809 | AC1: 201812 | AD1: 201903 | AE1: 201906 | AF1: 201909 | AG1: 201912 | AH1: 202003 | AI1: 202006 | AJ1: 202009 | AK1: 202012 | AL1: 202103 | AM1: 202106 | AN1: 202109 | AO1: 202112 | AP1: 202203 | AQ1: 202206 | AR1: 202209 | AS1: 202212 | AT1: 202303 | AU1: 202306 | AV1: 202309 | AW1: 202312 | AX1: 202403 | AY1: 202406 | AZ1: 202409 | BA1: 202412 | BB1: 202503 | BC1: 202506 | BD1: 202509 | BE1: 202512 | BF1: 202603 | BG1: 202606 | BH1: 202609 | BI1: 202612 | BJ1: 202703 | BK1: 202706 | BL1: 202709 | BM1: 202712 | BN1: 202803 | BO1: 202806 | BP1: 202809 | BQ1: 202812 | BR1: 202903 | BS1: 202906 | BT1: 202909 | BU1: 202912 | BV1: 203003
A3: Field Description | B3: Field Name
A4: Company Name | B4: CD_COMPNAME | C4: =_xll.EQNXTDZ(A1,B4,C1) -> Jindal Saw Ltd.
A5: Date End | B5: QTR_DATE_END | C5: =_xll.EQNXTDZ($A$1,$B5,C$1,$B$1) -> 201206 | D5: =_xll.EQNXTDZ($A$1,$B5,D$1,$B$1) -> 201209 | E5: =_xll.EQNXTDZ($A$1,$B5,E$1,$B$1) -> 201212 | F5: =_xll.EQNXTDZ($A$1,$B5,F$1,$B$1) -> 201303 | G5: =_xll.EQNXTDZ($A$1,$B5,G$1,$B$1) -> 201306 | H5: =_xll.EQNXTDZ($A$1,$B5,H$1,$B$1) -> 201309 | I5: =_xll.EQNXTDZ($A$1,$B5,I$1,$B$1) -> 201312 | J5: =_xll.EQNXTDZ($A$1,$B5,J$1,$B$1) -> 201403 | ... BV5: =_xll.EQNXTDZ($A$1,$B5,BV$1,$B$1) -> 0
A6: Gross Sales | B6: QTR_GROSS_SALE | C6: =_xll.EQNXTDZ($A$1,$B6,C$1,$B$1) -> 1290.06 | D6: =_xll.EQNXTDZ($A$1,$B6,D$1,$B$1) -> 1635.21 | E6: =_xll.EQNXTDZ($A$1,$B6,E$1,$B$1) -> 1722.01 | F6: =_xll.EQNXTDZ($A$1,$B6,F$1,$B$1) -> 979.04 | G6: =_xll.EQNXTDZ($A$1,$B6,G$1,$B$1) -> 1206.7 | H6: =_xll.EQNXTDZ($A$1,$B6,H$1,$B$1) -> 1223.71 | I6: =_xll.EQNXTDZ($A$1,$B6,I$1,$B$1) -> 1709.45 | J6: =_xll.EQNXTDZ($A$1,$B6,J$1,$B$1) -> 1363.13 | ... BV6: =_xll.EQNXTDZ($A$1,$B6,BV$1,$B$1) -> 0
A7: Less: Excise Duty | B7: QTR_EXCISE_DUTY | C7: =_xll.EQNXTDZ($A$1,$B7,C$1,$B$1) -> 0 | D7: =_xll.EQNXTDZ($A$1,$B7,D$1,$B$1) -> 0 | E7: =_xll.EQNXTDZ($A$1,$B7,E$1,$B$1) -> 0 | F7: =_xll.EQNXTDZ($A$1,$B7,F$1,$B$1) -> 0 | G7: =_xll.EQNXTDZ($A$1,$B7,G$1,$B$1) -> 0 | H7: =_xll.EQNXTDZ($A$1,$B7,H$1,$B$1) -> 0 | I7: =_xll.EQNXTDZ($A$1,$B7,I$1,$B$1) -> 0 | J7: =_xll.EQNXTDZ($A$1,$B7,J$1,$B$1) -> 0 | ... BV7: =_xll.EQNXTDZ($A$1,$B7,BV$1,$B$1) -> 0
A8: Other operating income | B8: QTR_JOB_WORKS | C8: =_xll.EQNXTDZ($A$1,$B8,C$1,$B$1) -> 0.37 | D8: =_xll.EQNXTDZ($A$1,$B8,D$1,$B$1) -> 1.72 | E8: =_xll.EQNXTDZ($A$1,$B8,E$1,$B$1) -> 0.72 | F8: =_xll.EQNXTDZ($A$1,$B8,F$1,$B$1) -> 1.03 | G8: =_xll.EQNXTDZ($A$1,$B8,G$1,$B$1) -> 0.31 | H8: =_xll.EQNXTDZ($A$1,$B8,H$1,$B$1) -> 5.68 | I8: =_xll.EQNXTDZ($A$1,$B8,I$1,$B$1) -> 0.16 | J8: =_xll.EQNXTDZ($A$1,$B8,J$1,$B$1) -> 0.45 | ... BV8: =_xll.EQNXTDZ($A$1,$B8,BV$1,$B$1) -> 0
A9: Net Sales & Other Operating Income | B9: QTR_NET_SALES | C9: =_xll.EQNXTDZ($A$1,$B9,C$1,$B$1) -> 1290.43 | D9: =_xll.EQNXTDZ($A$1,$B9,D$1,$B$1) -> 1636.93 | E9: =_xll.EQNXTDZ($A$1,$B9,E$1,$B$1) -> 1722.73 | F9: =_xll.EQNXTDZ($A$1,$B9,F$1,$B$1) -> 980.07 | G9: =_xll.EQNXTDZ($A$1,$B9,G$1,$B$1) -> 1207.01 | H9: =_xll.EQNXTDZ($A$1,$B9,H$1,$B$1) -> 1229.39 | I9: =_xll.EQNXTDZ($A$1,$B9,I$1,$B$1) -> 1709.61 | J9: =_xll.EQNXTDZ($A$1,$B9,J$1,$B$1) -> 1363.58 | ... BV9: =_xll.EQNXTDZ($A$1,$B9,BV$1,$B$1) -> 0
A10: (Increase) / Decrease In Stocks | B10: QTR_INC_DEC_INVENTORY | C10: =_xll.EQNXTDZ($A$1,$B10,C$1,$B$1) -> -191.53 | D10: =_xll.EQNXTDZ($A$1,$B10,D$1,$B$1) -> 112.79 | E10: =_xll.EQNXTDZ($A$1,$B10,E$1,$B$1) -> 366.5 | F10: =_xll.EQNXTDZ($A$1,$B10,F$1,$B$1) -> -56.95 | G10: =_xll.EQNXTDZ($A$1,$B10,G$1,$B$1) -> 28.77 | H10: =_xll.EQNXTDZ($A$1,$B10,H$1,$B$1) -> -70.38 | I10: =_xll.EQNXTDZ($A$1,$B10,I$1,$B$1) -> 190.88 | J10: =_xll.EQNXTDZ($A$1,$B10,J$1,$B$1) -> 93.36 | ... BV10: =_xll.EQNXTDZ($A$1,$B10,BV$1,$B$1) -> 0
A11: Cost of Services & Raw Materials | B11: QTR_RAW_MATERIAL_COST | C11: =_xll.EQNXTDZ($A$1,$B11,C$1,$B$1) -> 1035.26 | D11: =_xll.EQNXTDZ($A$1,$B11,D$1,$B$1) -> 984.68 | E11: =_xll.EQNXTDZ($A$1,$B11,E$1,$B$1) -> 892.56 | F11: =_xll.EQNXTDZ($A$1,$B11,F$1,$B$1) -> 660.83 | G11: =_xll.EQNXTDZ($A$1,$B11,G$1,$B$1) -> 759.39 | H11: =_xll.EQNXTDZ($A$1,$B11,H$1,$B$1) -> 840.83 | I11: =_xll.EQNXTDZ($A$1,$B11,I$1,$B$1) -> 916.31 | J11: =_xll.EQNXTDZ($A$1,$B11,J$1,$B$1) -> 619.51 | ... BV11: =_xll.EQNXTDZ($A$1,$B11,BV$1,$B$1) -> 0
A12: Purchase of Finished Goods | B12: QTR_PURCHASE_FIN_GOOD | C12: =_xll.EQNXTDZ($A$1,$B12,C$1,$B$1) -> 0 | D12: =_xll.EQNXTDZ($A$1,$B12,D$1,$B$1) -> 0 | E12: =_xll.EQNXTDZ($A$1,$B12,E$1,$B$1) -> 0 | F12: =_xll.EQNXTDZ($A$1,$B12,F$1,$B$1) -> 21.38 | G12: =_xll.EQNXTDZ($A$1,$B12,G$1,$B$1) -> 0 | H12: =_xll.EQNXTDZ($A$1,$B12,H$1,$B$1) -> 0 | I12: =_xll.EQNXTDZ($A$1,$B12,I$1,$B$1) -> 0 | J12: =_xll.EQNXTDZ($A$1,$B12,J$1,$B$1) -> 4.48 | ... BV12: =_xll.EQNXTDZ($A$1,$B12,BV$1,$B$1) -> 0
A13: Excise Duty | B13: QTR_EXCISE | C13: =_xll.EQNXTDZ($A$1,$B13,C$1,$B$1) -> 0 | D13: =_xll.EQNXTDZ($A$1,$B13,D$1,$B$1) -> 0 | E13: =_xll.EQNXTDZ($A$1,$B13,E$1,$B$1) -> 0 | F13: =_xll.EQNXTDZ($A$1,$B13,F$1,$B$1) -> 0 | G13: =_xll.EQNXTDZ($A$1,$B13,G$1,$B$1) -> 0 | H13: =_xll.EQNXTDZ($A$1,$B13,H$1,$B$1) -> 0 | I13: =_xll.EQNXTDZ($A$1,$B13,I$1,$B$1) -> 0 | J13: =_xll.EQNXTDZ($A$1,$B13,J$1,$B$1) -> 0 | ... BV13: =_xll.EQNXTDZ($A$1,$B13,BV$1,$B$1) -> 0
A14: Operating & Manufacturing Expenses | B14: QTR_MFG_EXPS | C14: =_xll.EQNXTDZ($A$1,$B14,C$1,$B$1) -> 224.58 | D14: =_xll.EQNXTDZ($A$1,$B14,D$1,$B$1) -> 278.76 | E14: =_xll.EQNXTDZ($A$1,$B14,E$1,$B$1) -> 240.94 | F14: =_xll.EQNXTDZ($A$1,$B14,F$1,$B$1) -> 188.49 | G14: =_xll.EQNXTDZ($A$1,$B14,G$1,$B$1) -> 208.47 | H14: =_xll.EQNXTDZ($A$1,$B14,H$1,$B$1) -> 234.04 | I14: =_xll.EQNXTDZ($A$1,$B14,I$1,$B$1) -> 357.96 | J14: =_xll.EQNXTDZ($A$1,$B14,J$1,$B$1) -> 406.77 | ... BV14: =_xll.EQNXTDZ($A$1,$B14,BV$1,$B$1) -> 0
A15: Electricity Power & Fuel Cost | B15: QTR_ELECTRICITY_POWER_FUEL | C15: =_xll.EQNXTDZ($A$1,$B15,C$1,$B$1) -> 0 | D15: =_xll.EQNXTDZ($A$1,$B15,D$1,$B$1) -> 0 | E15: =_xll.EQNXTDZ($A$1,$B15,E$1,$B$1) -> 0 | F15: =_xll.EQNXTDZ($A$1,$B15,F$1,$B$1) -> 0 | G15: =_xll.EQNXTDZ($A$1,$B15,G$1,$B$1) -> 0 | H15: =_xll.EQNXTDZ($A$1,$B15,H$1,$B$1) -> 0 | I15: =_xll.EQNXTDZ($A$1,$B15,I$1,$B$1) -> 0 | J15: =_xll.EQNXTDZ($A$1,$B15,J$1,$B$1) -> 0 | ... BV15: =_xll.EQNXTDZ($A$1,$B15,BV$1,$B$1) -> 0
A16: Employee Cost | B16: QTR_EXPLOYEE_COST | C16: =_xll.EQNXTDZ($A$1,$B16,C$1,$B$1) -> 61.88 | D16: =_xll.EQNXTDZ($A$1,$B16,D$1,$B$1) -> 62.85 | E16: =_xll.EQNXTDZ($A$1,$B16,E$1,$B$1) -> 64.17 | F16: =_xll.EQNXTDZ($A$1,$B16,F$1,$B$1) -> 63.36 | G16: =_xll.EQNXTDZ($A$1,$B16,G$1,$B$1) -> 68.02 | H16: =_xll.EQNXTDZ($A$1,$B16,H$1,$B$1) -> 76.7 | I16: =_xll.EQNXTDZ($A$1,$B16,I$1,$B$1) -> 78.73 | J16: =_xll.EQNXTDZ($A$1,$B16,J$1,$B$1) -> 76.75 | ... BV16: =_xll.EQNXTDZ($A$1,$B16,BV$1,$B$1) -> 0
... A42: Consolidated PAT(after extra items) | B42: QTR_CONS_PAT_EXITM | C42: =_xll.EQNXTDZ($A$1,$B42,C$1,$B$1) -> 35.19 | D42: =_xll.EQNXTDZ($A$1,$B42,D$1,$B$1) -> 61.11 | E42: =_xll.EQNXTDZ($A$1,$B42,E$1,$B$1) -> 60.03 | F42: =_xll.EQNXTDZ($A$1,$B42,F$1,$B$1) -> 37.08 | G42: =_xll.EQNXTDZ($A$1,$B42,G$1,$B$1) -> 15.21 | H42: =_xll.EQNXTDZ($A$1,$B42,H$1,$B$1) -> 21.96 | I42: =_xll.EQNXTDZ($A$1,$B42,I$1,$B$1) -> 50.04 | J42: =_xll.EQNXTDZ($A$1,$B42,J$1,$B$1) -> 57.06 | ... BV42: =_xll.EQNXTDZ($A$1,$B42,BV$1,$B$1) -> 0
A44: Field Description | B44: Field Name
A45: Equity Capital | B45: QTR_EQUITY_CAP | C45: =_xll.EQNXTDZ($A$1,$B45,C$1,$B$1) -> 55.25 | D45: =_xll.EQNXTDZ($A$1,$B45,D$1,$B$1) -> 55.25 | E45: =_xll.EQNXTDZ($A$1,$B45,E$1,$B$1) -> 55.25 | F45: =_xll.EQNXTDZ($A$1,$B45,F$1,$B$1) -> 55.25 | G45: =_xll.EQNXTDZ($A$1,$B45,G$1,$B$1) -> 55.25 | H45: =_xll.EQNXTDZ($A$1,$B45,H$1,$B$1) -> 55.25 | I45: =_xll.EQNXTDZ($A$1,$B45,I$1,$B$1) -> 55.25 | J45: =_xll.EQNXTDZ($A$1,$B45,J$1,$B$1) -> 55.25 | ... BV45: =_xll.EQNXTDZ($A$1,$B45,BV$1,$B$1) -> 0
A46: Face Value | B46: QTR_FV | C46: =_xll.EQNXTDZ($A$1,$B46,C$1,$B$1) -> 2 | D46: =_xll.EQNXTDZ($A$1,$B46,D$1,$B$1) -> 2 | E46: =_xll.EQNXTDZ($A$1,$B46,E$1,$B$1) -> 2 | F46: =_xll.EQNXTDZ($A$1,$B46,F$1,$B$1) -> 2 | G46: =_xll.EQNXTDZ($A$1,$B46,G$1,$B$1) -> 2 | H46: =_xll.EQNXTDZ($A$1,$B46,H$1,$B$1) -> 2 | I46: =_xll.EQNXTDZ($A$1,$B46,I$1,$B$1) -> 2 | J46: =_xll.EQNXTDZ($A$1,$B46,J$1,$B$1) -> 2 | ... BV46: =_xll.EQNXTDZ($A$1,$B46,BV$1,$B$1) -> 0
A47: Month End | B47: BMONTH_MONTHEND | C47: =_xll.EQNXTDZ($A$1,$B47,C$5) -> 201206 | D47: =_xll.EQNXTDZ($A$1,$B47,D$5) -> 201209 | E47: =_xll.EQNXTDZ($A$1,$B47,E$5) -> 201212 | F47: =_xll.EQNXTDZ($A$1,$B47,F$5) -> 201303 | G47: =_xll.EQNXTDZ($A$1,$B47,G$5) -> 201306 | H47: =_xll.EQNXTDZ($A$1,$B47,H$5) -> 201309 | I47: =_xll.EQNXTDZ($A$1,$B47,I$5) -> 201312 | J47: =_xll.EQNXTDZ($A$1,$B47,J$5) -> 201403 | ... BV47: =_xll.EQNXTDZ($A$1,$B47,BV$5) -> 0
A48: Close | B48: BMONTH_CLOSE | C48: =_xll.EQNXTDZ($A$1,$B48,C$5) -> 66.175 | D48: =_xll.EQNXTDZ($A$1,$B48,D$5) -> 59.25 | E48: =_xll.EQNXTDZ($A$1,$B48,E$5) -> 64.3 | F48: =_xll.EQNXTDZ($A$1,$B48,F$5) -> 41.05 | G48: =_xll.EQNXTDZ($A$1,$B48,G$5) -> 28.65 | H48: =_xll.EQNXTDZ($A$1,$B48,H$5) -> 22.175 | I48: =_xll.EQNXTDZ($A$1,$B48,I$5) -> 24.525 | J48: =_xll.EQNXTDZ($A$1,$B48,J$5) -> 28.3 | ... BV48: =_xll.EQNXTDZ($A$1,$B48,BV$5) -> 0
A49: Total of Promoter and Promoter Group | B49: SHP_TPFTOTALPROMOTER | C49: =_xll.EQNXTDZ($A$1,$B49,C$5) -> 46 | D49: =_xll.EQNXTDZ($A$1,$B49,D$5) -> 45.99 | E49: =_xll.EQNXTDZ($A$1,$B49,E$5) -> 46 | F49: =_xll.EQNXTDZ($A$1,$B49,F$5) -> 46 | G49: =_xll.EQNXTDZ($A$1,$B49,G$5) -> 46 | H49: =_xll.EQNXTDZ($A$1,$B49,H$5) -> 46.27 | I49: =_xll.EQNXTDZ($A$1,$B49,I$5) -> 46.27 | J49: =_xll.EQNXTDZ($A$1,$B49,J$5) -> 46.27 | ... BV49: =_xll.EQNXTDZ($A$1,$B49,BV$5) -> 0
A50: Total of Promoter and Promoter Group Pledged | B50: SHP_PSHFTOTALPROMOTER | C50: =_xll.EQNXTDZ($A$1,$B50,C$5) -> 0 | D50: =_xll.EQNXTDZ($A$1,$B50,D$5) -> 0 | E50: =_xll.EQNXTDZ($A$1,$B50,E$5) -> 0 | F50: =_xll.EQNXTDZ($A$1,$B50,F$5) -> 0 | G50: =_xll.EQNXTDZ($A$1,$B50,G$5) -> 0 | H50: =_xll.EQNXTDZ($A$1,$B50,H$5) -> 0 | I50: =_xll.EQNXTDZ($A$1,$B50,I$5) -> 0 | J50: =_xll.EQNXTDZ($A$1,$B50,J$5) -> 0 | ... BV50: =_xll.EQNXTDZ($A$1,$B50,BV$5) -> 0
A54: Field Description | B54: Field Name | C54: =_xll.EQNXTDZ($A$1,$B54,C$5) -> 0 | D54: =_xll.EQNXTDZ($A$1,$B54,D$5) -> 0 | E54: =_xll.EQNXTDZ($A$1,$B54,E$5) -> 0 | F54: =_xll.EQNXTDZ($A$1,$B54,F$5) -> 0 | G54: =_xll.EQNXTDZ($A$1,$B54,G$5) -> 0 | H54: =_xll.EQNXTDZ($A$1,$B54,H$5) -> 0 | I54: =_xll.EQNXTDZ($A$1,$B54,I$5) -> 0 | J54: =_xll.EQNXTDZ($A$1,$B54,J$5) -> 0 | ... BV54: =_xll.EQNXTDZ($A$1,$B54,BV$5) -> 0
A55: Year End | B55: QTRB_DATE_END | C55: =_xll.EQNXTDZ($A$1,$B55,C$5,$B$1) -> 0 | D55: =_xll.EQNXTDZ($A$1,$B55,D$5,$B$1) -> 201209 | E55: =_xll.EQNXTDZ($A$1,$B55,E$5,$B$1) -> 0 | F55: =_xll.EQNXTDZ($A$1,$B55,F$5,$B$1) -> 201303 | G55: =_xll.EQNXTDZ($A$1,$B55,G$5,$B$1) -> 0 | H55: =_xll.EQNXTDZ($A$1,$B55,H$5,$B$1) -> 201309 | I55: =_xll.EQNXTDZ($A$1,$B55,I$5,$B$1) -> 0 | J55: =_xll.EQNXTDZ($A$1,$B55,J$5,$B$1) -> 201403 | ... BV55: =_xll.EQNXTDZ($A$1,$B55,BV$5,$B$1) -> 0
A56: Share Capital | B56: QTRB_SHARE_CAPITAL | C56: =_xll.EQNXTDZ($A$1,$B56,C$5,$B$1) -> 0 | D56: =_xll.EQNXTDZ($A$1,$B56,D$5,$B$1) -> 55.25 | E56: =_xll.EQNXTDZ($A$1,$B56,E$5,$B$1) -> 0 | F56: =_xll.EQNXTDZ($A$1,$B56,F$5,$B$1) -> 55.25 | G56: =_xll.EQNXTDZ($A$1,$B56,G$5,$B$1) -> 0 | H56: =_xll.EQNXTDZ($A$1,$B56,H$5,$B$1) -> 55.25 | I56: =_xll.EQNXTDZ($A$1,$B56,I$5,$B$1) -> 0 | J56: =_xll.EQNXTDZ($A$1,$B56,J$5,$B$1) -> 55.25 | ... BV56: =_xll.EQNXTDZ($A$1,$B56,BV$5,$B$1) -> 0
A57: Share Warrants & outstandings | B57: QTRB_SHAREWARNDOUT | C57: =_xll.EQNXTDZ($A$1,$B57,C$5,$B$1) -> 0 | D57: =_xll.EQNXTDZ($A$1,$B57,D$5,$B$1) -> 0 | E57: =_xll.EQNXTDZ($A$1,$B57,E$5,$B$1) -> 0 | F57: =_xll.EQNXTDZ($A$1,$B57,F$5,$B$1) -> 0 | G57: =_xll.EQNXTDZ($A$1,$B57,G$5,$B$1) -> 0 | H57: =_xll.EQNXTDZ($A$1,$B57,H$5,$B$1) -> 0 | I57: =_xll.EQNXTDZ($A$1,$B57,I$5,$B$1) -> 0 | J57: =_xll.EQNXTDZ($A$1,$B57,J$5,$B$1) -> 0 | ... BV57: =_xll.EQNXTDZ($A$1,$B57,BV$5,$B$1) -> 0
A58: Reserves & Surplus | B58: QTRB_RESERVE | C58: =_xll.EQNXTDZ($A$1,$B58,C$5,$B$1) -> 0 | D58: =_xll.EQNXTDZ($A$1,$B58,D$5,$B$1) -> 3602.35 | E58: =_xll.EQNXTDZ($A$1,$B58,E$5,$B$1) -> 0 | F58: =_xll.EQNXTDZ($A$1,$B58,F$5,$B$1) -> 3612.24 | G58: =_xll.EQNXTDZ($A$1,$B58,G$5,$B$1) -> 0 | H58: =_xll.EQNXTDZ($A$1,$B58,H$5,$B$1) -> 3710.27 | I58: =_xll.EQNXTDZ($A$1,$B58,I$5,$B$1) -> 0 | J58: =_xll.EQNXTDZ($A$1,$B58,J$5,$B$1) -> 3513.13 | ... BV58: =_xll.EQNXTDZ($A$1,$B58,BV$5,$B$1) -> 0
A59: Shareholder's Funds | B59: QTRB_SHAREHODERS_FUNDS | C59: =_xll.EQNXTDZ($A$1,$B59,C$5,$B$1) -> 0 | D59: =_xll.EQNXTDZ($A$1,$B59,D$5,$B$1) -> 3657.6 | E59: =_xll.EQNXTDZ($A$1,$B59,E$5,$B$1) -> 0 | F59: =_xll.EQNXTDZ($A$1,$B59,F$5,$B$1) -> 3667.49 | G59: =_xll.EQNXTDZ($A$1,$B59,G$5,$B$1) -> 0 | H59: =_xll.EQNXTDZ($A$1,$B59,H$5,$B$1) -> 3765.52 | I59: =_xll.EQNXTDZ($A$1,$B59,I$5,$B$1) -> 0 | J59: =_xll.EQNXTDZ($A$1,$B59,J$5,$B$1) -> 3568.38 | ... BV59: =_xll.EQNXTDZ($A$1,$B59,BV$5,$B$1) -> 0
A60: Minority Interest | B60: QTRB_MINORITY_INTEREST_BS | C60: =_xll.EQNXTDZ($A$1,$B60,C$5,$B$1) -> 0 | D60: =_xll.EQNXTDZ($A$1,$B60,D$5,$B$1) -> 0 | E60: =_xll.EQNXTDZ($A$1,$B60,E$5,$B$1) -> 0 | F60: =_xll.EQNXTDZ($A$1,$B60,F$5,$B$1) -> 197.98 | G60: =_xll.EQNXTDZ($A$1,$B60,G$5,$B$1) -> 0 | H60: =_xll.EQNXTDZ($A$1,$B60,H$5,$B$1) -> 0 | I60: =_xll.EQNXTDZ($A$1,$B60,I$5,$B$1) -> 0 | J60: =_xll.EQNXTDZ($A$1,$B60,J$5,$B$1) -> 157.83 | ... BV60: =_xll.EQNXTDZ($A$1,$B60,BV$5,$B$1) -> 0
A61: Long Term Borrowings | B61: QTRB_TOTAL_DEBTS | C61: =_xll.EQNXTDZ($A$1,$B61,C$5,$B$1) -> 0 | D61: =_xll.EQNXTDZ($A$1,$B61,D$5,$B$1) -> 1166.93 | E61: =_xll.EQNXTDZ($A$1,$B61,E$5,$B$1) -> 0 | F61: =_xll.EQNXTDZ($A$1,$B61,F$5,$B$1) -> 2843.79 | G61: =_xll.EQNXTDZ($A$1,$B61,G$5,$B$1) -> 0 | H61: =_xll.EQNXTDZ($A$1,$B61,H$5,$B$1) -> 1612.35 | I61: =_xll.EQNXTDZ($A$1,$B61,I$5,$B$1) -> 0 | J61: =_xll.EQNXTDZ($A$1,$B61,J$5,$B$1) -> 3492.7 | ... BV61: =_xll.EQNXTDZ($A$1,$B61,BV$5,$B$1) -> 0
A62: Secured Loans | B62: QTRB_SECURED_LOANS | C62: =_xll.EQNXTDZ($A$1,$B62,C$5,$B$1) -> 0 | D62: =_xll.EQNXTDZ($A$1,$B62,D$5,$B$1) -> 0 | E62: =_xll.EQNXTDZ($A$1,$B62,E$5,$B$1) -> 0 | F62: =_xll.EQNXTDZ($A$1,$B62,F$5,$B$1) -> 0 | G62: =_xll.EQNXTDZ($A$1,$B62,G$5,$B$1) -> 0 | H62: =_xll.EQNXTDZ($A$1,$B62,H$5,$B$1) -> 0 | I62: =_xll.EQNXTDZ($A$1,$B62,I$5,$B$1) -> 0 | J62: =_xll.EQNXTDZ($A$1,$B62,J$5,$B$1) -> 0 | ... BV62: =_xll.EQNXTDZ($A$1,$B62,BV$5,$B$1) -> 0
A63: Unsecured Loans | B63: QTRB_UNSECURED_LOANS_NF | C63: =_xll.EQNXTDZ($A$1,$B63,C$5,$B$1) -> 0 | D63: =_xll.EQNXTDZ($A$1,$B63,D$5,$B$1) -> 1166.93 | E63: =_xll.EQNXTDZ($A$1,$B63,E$5,$B$1) -> 0 | F63: =_xll.EQNXTDZ($A$1,$B63,F$5,$B$1) -> 2843.79 | G63: =_xll.EQNXTDZ($A$1,$B63,G$5,$B$1) -> 0 | H63: =_xll.EQNXTDZ($A$1,$B63,H$5,$B$1) -> 1612.35 | I63: =_xll.EQNXTDZ($A$1,$B63,I$5,$B$1) -> 0 | J63: =_xll.EQNXTDZ($A$1,$B63,J$5,$B$1) -> 3492.7 | ... BV63: =_xll.EQNXTDZ($A$1,$B63,BV$5,$B$1) -> 0
A64: Other Long Term Liabilities | B64: QTRB_OTHER_LT_LIABILITIES | C64: =_xll.EQNXTDZ($A$1,$B64,C$5,$B$1) -> 0 | D64: =_xll.EQNXTDZ($A$1,$B64,D$5,$B$1) -> 0.08 | E64: =_xll.EQNXTDZ($A$1,$B64,E$5,$B$1) -> 0 | F64: =_xll.EQNXTDZ($A$1,$B64,F$5,$B$1) -> 101.96 | G64: =_xll.EQNXTDZ($A$1,$B64,G$5,$B$1) -> 0 | H64: =_xll.EQNXTDZ($A$1,$B64,H$5,$B$1) -> 0 | I64: =_xll.EQNXTDZ($A$1,$B64,I$5,$B$1) -> 0 | J64: =_xll.EQNXTDZ($A$1,$B64,J$5,$B$1) -> 187.99 | ... BV64: =_xll.EQNXTDZ($A$1,$B64,BV$5,$B$1) -> 0
A65: Long Term Trade Payables | B65: QTRB_LT_TRADE_PAYABLE | C65: =_xll.EQNXTDZ($A$1,$B65,C$5,$B$1) -> 0 | D65: =_xll.EQNXTDZ($A$1,$B65,D$5,$B$1) -> 0 | E65: =_xll.EQNXTDZ($A$1,$B65,E$5,$B$1) -> 0 | F65: =_xll.EQNXTDZ($A$1,$B65,F$5,$B$1) -> 0 | G65: =_xll.EQNXTDZ($A$1,$B65,G$5,$B$1) -> 0 | H65: =_xll.EQNXTDZ($A$1,$B65,H$5,$B$1) -> 0 | I65: =_xll.EQNXTDZ($A$1,$B65,I$5,$B$1) -> 0 | J65: =_xll.EQNXTDZ($A$1,$B65,J$5,$B$1) -> 0 | ... BV65: =_xll.EQNXTDZ($A$1,$B65,BV$5,$B$1) -> 0
A66: Lont Term Provisions | B66: QTRB_LT_PROVISIONS | C66: =_xll.EQNXTDZ($A$1,$B66,C$5,$B$1) -> 0 | D66: =_xll.EQNXTDZ($A$1,$B66,D$5,$B$1) -> 28.88 | E66: =_xll.EQNXTDZ($A$1,$B66,E$5,$B$1) -> 0 | F66: =_xll.EQNXTDZ($A$1,$B66,F$5,$B$1) -> 34.48 | G66: =_xll.EQNXTDZ($A$1,$B66,G$5,$B$1) -> 0 | H66: =_xll.EQNXTDZ($A$1,$B66,H$5,$B$1) -> 29.87 | I66: =_xll.EQNXTDZ($A$1,$B66,I$5,$B$1) -> 0 | J66: =_xll.EQNXTDZ($A$1,$B66,J$5,$B$1) -> 36.63 | ... BV66: =_xll.EQNXTDZ($A$1,$B66,BV$5,$B$1) -> 0
... A97: Total Assets | B97: QTRB_TOTAL_APPLICATIONS | C97: =_xll.EQNXTDZ($A$1,$B97,C$5,$B$1) -> 0 | D97: =_xll.EQNXTDZ($A$1,$B97,D$5,$B$1) -> 4853.49 | E97: =_xll.EQNXTDZ($A$1,$B97,E$5,$B$1) -> 0 | F97: =_xll.EQNXTDZ($A$1,$B97,F$5,$B$1) -> 6845.7 | G97: =_xll.EQNXTDZ($A$1,$B97,G$5,$B$1) -> 0 | H97: =_xll.EQNXTDZ($A$1,$B97,H$5,$B$1) -> 5407.74 | I97: =_xll.EQNXTDZ($A$1,$B97,I$5,$B$1) -> 0 | J97: =_xll.EQNXTDZ($A$1,$B97,J$5,$B$1) -> 7443.53 | ... BV97: =_xll.EQNXTDZ($A$1,$B97,BV$5,$B$1) -> 0

Sheet Annual Raw
A1: 100378 | B1: X | C1: 200103 | D1: 200203 | E1: 200303 | F1: 200403 | G1: 200503 | H1: 200603 | I1: 200703 | J1: 200803 | K1: 200903 | L1: 201003 | M1: 201103 | N1: 201203 | O1: 201303 | P1: 201403 | Q1: 201503 | R1: 201603 | S1: 201703 | T1: 201803 | U1: 201903 | V1: 202003 | W1: 202103 | X1: 202203 | Y1: 202303 | Z1: 202403 | AA1: 202503 | AB1: 202603 | AC1: 202703 | AD1: 202803 | AE1: 202903 | AF1: 203003
A3: Field Description | B3: Field Name
A4: Company Name | B4: CD_COMPNAME | C4: =_xll.EQNXTDZ(A1,B4,"L") -> Jindal Saw Ltd.
A5: Year End | B5: PL_YEAR_END | C5: =_xll.EQNXTDZ($A$1,$B5,C$1,$B$1) -> 0 | D5: =_xll.EQNXTDZ($A$1,$B5,D$1,$B$1) -> 0 | E5: =_xll.EQNXTDZ($A$1,$B5,E$1,$B$1) -> 0 | F5: =_xll.EQNXTDZ($A$1,$B5,F$1,$B$1) -> 0 | G5: =_xll.EQNXTDZ($A$1,$B5,G$1,$B$1) -> 0 | H5: =_xll.EQNXTDZ($A$1,$B5,H$1,$B$1) -> 0 | I5: =_xll.EQNXTDZ($A$1,$B5,I$1,$B$1) -> 0 | J5: =_xll.EQNXTDZ($A$1,$B5,J$1,$B$1) -> 0 | ... AF5: =_xll.EQNXTDZ($A$1,$B5,AF$1,$B$1) -> 0
A6: Sales Turnover | B6: PL_TOTAL_GROSS_SALES | C6: =_xll.EQNXTDZ($A$1,$B6,C$1,$B$1) -> 0 | D6: =_xll.EQNXTDZ($A$1,$B6,D$1,$B$1) -> 0 | E6: =_xll.EQNXTDZ($A$1,$B6,E$1,$B$1) -> 0 | F6: =_xll.EQNXTDZ($A$1,$B6,F$1,$B$1) -> 0 | G6: =_xll.EQNXTDZ($A$1,$B6,G$1,$B$1) -> 0 | H6: =_xll.EQNXTDZ($A$1,$B6,H$1,$B$1) -> 0 | I6: =_xll.EQNXTDZ($A$1,$B6,I$1,$B$1) -> 0 | J6: =_xll.EQNXTDZ($A$1,$B6,J$1,$B$1) -> 0 | ... AF6: =_xll.EQNXTDZ($A$1,$B6,AF$1,$B$1) -> 0
A7: Less: Inter divisional transfers | B7: PL_INTER_DIV_TRF | C7: =_xll.EQNXTDZ($A$1,$B7,C$1,$B$1) -> 0 | D7: =_xll.EQNXTDZ($A$1,$B7,D$1,$B$1) -> 0 | E7: =_xll.EQNXTDZ($A$1,$B7,E$1,$B$1) -> 0 | F7: =_xll.EQNXTDZ($A$1,$B7,F$1,$B$1) -> 0 | G7: =_xll.EQNXTDZ($A$1,$B7,G$1,$B$1) -> 0 | H7: =_xll.EQNXTDZ($A$1,$B7,H$1,$B$1) -> 0 | I7: =_xll.EQNXTDZ($A$1,$B7,I$1,$B$1) -> 0 | J7: =_xll.EQNXTDZ($A$1,$B7,J$1,$B$1) -> 0 | ... AF7: =_xll.EQNXTDZ($A$1,$B7,AF$1,$B$1) -> 0
A8: Less: Sales Returns | B8: PL_SALES_RETURN | C8: =_xll.EQNXTDZ($A$1,$B8,C$1,$B$1) -> 0 | D8: =_xll.EQNXTDZ($A$1,$B8,D$1,$B$1) -> 0 | E8: =_xll.EQNXTDZ($A$1,$B8,E$1,$B$1) -> 0 | F8: =_xll.EQNXTDZ($A$1,$B8,F$1,$B$1) -> 0 | G8: =_xll.EQNXTDZ($A$1,$B8,G$1,$B$1) -> 0 | H8: =_xll.EQNXTDZ($A$1,$B8,H$1,$B$1) -> 0 | I8: =_xll.EQNXTDZ($A$1,$B8,I$1,$B$1) -> 0 | J8: =_xll.EQNXTDZ($A$1,$B8,J$1,$B$1) -> 0 | ... AF8: =_xll.EQNXTDZ($A$1,$B8,AF$1,$B$1) -> 0
A9: Less: Excise | B9: PL_EXCISE | C9: =_xll.EQNXTDZ($A$1,$B9,C$1,$B$1) -> 0 | D9: =_xll.EQNXTDZ($A$1,$B9,D$1,$B$1) -> 0 | E9: =_xll.EQNXTDZ($A$1,$B9,E$1,$B$1) -> 0 | F9: =_xll.EQNXTDZ($A$1,$B9,F$1,$B$1) -> 0 | G9: =_xll.EQNXTDZ($A$1,$B9,G$1,$B$1) -> 0 | H9: =_xll.EQNXTDZ($A$1,$B9,H$1,$B$1) -> 0 | I9: =_xll.EQNXTDZ($A$1,$B9,I$1,$B$1) -> 0 | J9: =_xll.EQNXTDZ($A$1,$B9,J$1,$B$1) -> 0 | ... AF9: =_xll.EQNXTDZ($A$1,$B9,AF$1,$B$1) -> 0
A10: Net Sales | B10: PL_NET_SALES | C10: =_xll.EQNXTDZ($A$1,$B10,C$1,$B$1) -> 0 | D10: =_xll.EQNXTDZ($A$1,$B10,D$1,$B$1) -> 0 | E10: =_xll.EQNXTDZ($A$1,$B10,E$1,$B$1) -> 0 | F10: =_xll.EQNXTDZ($A$1,$B10,F$1,$B$1) -> 0 | G10: =_xll.EQNXTDZ($A$1,$B10,G$1,$B$1) -> 0 | H10: =_xll.EQNXTDZ($A$1,$B10,H$1,$B$1) -> 0 | I10: =_xll.EQNXTDZ($A$1,$B10,I$1,$B$1) -> 0 | J10: =_xll.EQNXTDZ($A$1,$B10,J$1,$B$1) -> 0 | ... AF10: =_xll.EQNXTDZ($A$1,$B10,AF$1,$B$1) -> 0
A11: Increase/Decrease in Stock | B11: PL_INC_DEC_INVENTORY | C11: =_xll.EQNXTDZ($A$1,$B11,C$1,$B$1) -> 0 | D11: =_xll.EQNXTDZ($A$1,$B11,D$1,$B$1) -> 0 | E11: =_xll.EQNXTDZ($A$1,$B11,E$1,$B$1) -> 0 | F11: =_xll.EQNXTDZ($A$1,$B11,F$1,$B$1) -> 0 | G11: =_xll.EQNXTDZ($A$1,$B11,G$1,$B$1) -> 0 | H11: =_xll.EQNXTDZ($A$1,$B11,H$1,$B$1) -> 0 | I11: =_xll.EQNXTDZ($A$1,$B11,I$1,$B$1) -> 0 | J11: =_xll.EQNXTDZ($A$1,$B11,J$1,$B$1) -> 0 | ... AF11: =_xll.EQNXTDZ($A$1,$B11,AF$1,$B$1) -> 0
A12: Raw Material Consumed | B12: PL_RAW_MATRS_CONSUMED | C12: =_xll.EQNXTDZ($A$1,$B12,C$1,$B$1) -> 0 | D12: =_xll.EQNXTDZ($A$1,$B12,D$1,$B$1) -> 0 | E12: =_xll.EQNXTDZ($A$1,$B12,E$1,$B$1) -> 0 | F12: =_xll.EQNXTDZ($A$1,$B12,F$1,$B$1) -> 0 | G12: =_xll.EQNXTDZ($A$1,$B12,G$1,$B$1) -> 0 | H12: =_xll.EQNXTDZ($A$1,$B12,H$1,$B$1) -> 0 | I12: =_xll.EQNXTDZ($A$1,$B12,I$1,$B$1) -> 0 | J12: =_xll.EQNXTDZ($A$1,$B12,J$1,$B$1) -> 0 | ... AF12: =_xll.EQNXTDZ($A$1,$B12,AF$1,$B$1) -> 0
A13: Power & Fuel Cost | B13: PL_POWER_FUEL | C13: =_xll.EQNXTDZ($A$1,$B13,C$1,$B$1) -> 0 | D13: =_xll.EQNXTDZ($A$1,$B13,D$1,$B$1) -> 0 | E13: =_xll.EQNXTDZ($A$1,$B13,E$1,$B$1) -> 0 | F13: =_xll.EQNXTDZ($A$1,$B13,F$1,$B$1) -> 0 | G13: =_xll.EQNXTDZ($A$1,$B13,G$1,$B$1) -> 0 | H13: =_xll.EQNXTDZ($A$1,$B13,H$1,$B$1) -> 0 | I13: =_xll.EQNXTDZ($A$1,$B13,I$1,$B$1) -> 0 | J13: =_xll.EQNXTDZ($A$1,$B13,J$1,$B$1) -> 0 | ... AF13: =_xll.EQNXTDZ($A$1,$B13,AF$1,$B$1) -> 0
A14: Employee Cost | B14: PL_EMPLOYEES | C14: =_xll.EQNXTDZ($A$1,$B14,C$1,$B$1) -> 0 | D14: =_xll.EQNXTDZ($A$1,$B14,D$1,$B$1) -> 0 | E14: =_xll.EQNXTDZ($A$1,$B14,E$1,$B$1) -> 0 | F14: =_xll.EQNXTDZ($A$1,$B14,F$1,$B$1) -> 0 | G14: =_xll.EQNXTDZ($A$1,$B14,G$1,$B$1) -> 0 | H14: =_xll.EQNXTDZ($A$1,$B14,H$1,$B$1) -> 0 | I14: =_xll.EQNXTDZ($A$1,$B14,I$1,$B$1) -> 0 | J14: =_xll.EQNXTDZ($A$1,$B14,J$1,$B$1) -> 0 | ... AF14: =_xll.EQNXTDZ($A$1,$B14,AF$1,$B$1) -> 0
A15: Operating & Manufacturing Expenses | B15: PL_GEN_OTHER_MFG_EXPS | C15: =_xll.EQNXTDZ($A$1,$B15,C$1,$B$1) -> 0 | D15: =_xll.EQNXTDZ($A$1,$B15,D$1,$B$1) -> 0 | E15: =_xll.EQNXTDZ($A$1,$B15,E$1,$B$1) -> 0 | F15: =_xll.EQNXTDZ($A$1,$B15,F$1,$B$1) -> 0 | G15: =_xll.EQNXTDZ($A$1,$B15,G$1,$B$1) -> 0 | H15: =_xll.EQNXTDZ($A$1,$B15,H$1,$B$1) -> 0 | I15: =_xll.EQNXTDZ($A$1,$B15,I$1,$B$1) -> 0 | J15: =_xll.EQNXTDZ($A$1,$B15,J$1,$B$1) -> 0 | ... AF15: =_xll.EQNXTDZ($A$1,$B15,AF$1,$B$1) -> 0
A16: Cost of Software development | B16: PL_COST_SW | C16: =_xll.EQNXTDZ($A$1,$B16,C$1,$B$1) -> 0 | D16: =_xll.EQNXTDZ($A$1,$B16,D$1,$B$1) -> 0 | E16: =_xll.EQNXTDZ($A$1,$B16,E$1,$B$1) -> 0 | F16: =_xll.EQNXTDZ($A$1,$B16,F$1,$B$1) -> 0 | G16: =_xll.EQNXTDZ($A$1,$B16,G$1,$B$1) -> 0 | H16: =_xll.EQNXTDZ($A$1,$B16,H$1,$B$1) -> 0 | I16: =_xll.EQNXTDZ($A$1,$B16,I$1,$B$1) -> 0 | J16: =_xll.EQNXTDZ($A$1,$B16,J$1,$B$1) -> 0 | ... AF16: =_xll.EQNXTDZ($A$1,$B16,AF$1,$B$1) -> 0
... A36: Profit After Tax from Discontinued Operations | B36: PL_PAT_DIS_OP | C36: =_xll.EQNXTDZ($A$1,$B36,C$1,$B$1) -> 0 | D36: =_xll.EQNXTDZ($A$1,$B36,D$1,$B$1) -> 0 | E36: =_xll.EQNXTDZ($A$1,$B36,E$1,$B$1) -> 0 | F36: =_xll.EQNXTDZ($A$1,$B36,F$1,$B$1) -> 0 | G36: =_xll.EQNXTDZ($A$1,$B36,G$1,$B$1) -> 0 | H36: =_xll.EQNXTDZ($A$1,$B36,H$1,$B$1) -> 0 | I36: =_xll.EQNXTDZ($A$1,$B36,I$1,$B$1) -> 0 | J36: =_xll.EQNXTDZ($A$1,$B36,J$1,$B$1) -> 0 | ... AF36: =_xll.EQNXTDZ($A$1,$B36,AF$1,$B$1) -> 0
A39: Field Description | B39: Field Name
A40: Year End | B40: BS_YEAR_END | C40: =_xll.EQNXTDZ($A$1,$B40,C$1,$B$1) -> 0 | D40: =_xll.EQNXTDZ($A$1,$B40,D$1,$B$1) -> 0 | E40: =_xll.EQNXTDZ($A$1,$B40,E$1,$B$1) -> 0 | F40: =_xll.EQNXTDZ($A$1,$B40,F$1,$B$1) -> 0 | G40: =_xll.EQNXTDZ($A$1,$B40,G$1,$B$1) -> 0 | H40: =_xll.EQNXTDZ($A$1,$B40,H$1,$B$1) -> 0 | I40: =_xll.EQNXTDZ($A$1,$B40,I$1,$B$1) -> 0 | J40: =_xll.EQNXTDZ($A$1,$B40,J$1,$B$1) -> 0 | ... AF40: =_xll.EQNXTDZ($A$1,$B40,AF$1,$B$1) -> 0
A41: Share Capital | B41: BS_SHARE_CAPITAL | C41: =_xll.EQNXTDZ($A$1,$B41,C$1,$B$1) -> 0 | D41: =_xll.EQNXTDZ($A$1,$B41,D$1,$B$1) -> 0 | E41: =_xll.EQNXTDZ($A$1,$B41,E$1,$B$1) -> 0 | F41: =_xll.EQNXTDZ($A$1,$B41,F$1,$B$1) -> 0 | G41: =_xll.EQNXTDZ($A$1,$B41,G$1,$B$1) -> 0 | H41: =_xll.EQNXTDZ($A$1,$B41,H$1,$B$1) -> 0 | I41: =_xll.EQNXTDZ($A$1,$B41,I$1,$B$1) -> 0 | J41: =_xll.EQNXTDZ($A$1,$B41,J$1,$B$1) -> 0 | ... AF41: =_xll.EQNXTDZ($A$1,$B41,AF$1,$B$1) -> 0
A42: Share Warrants & Outstandings | B42: BS_SHAREWROUTST | C42: =_xll.EQNXTDZ($A$1,$B42,C$1,$B$1) -> 0 | D42: =_xll.EQNXTDZ($A$1,$B42,D$1,$B$1) -> 0 | E42: =_xll.EQNXTDZ($A$1,$B42,E$1,$B$1) -> 0 | F42: =_xll.EQNXTDZ($A$1,$B42,F$1,$B$1) -> 0 | G42: =_xll.EQNXTDZ($A$1,$B42,G$1,$B$1) -> 0 | H42: =_xll.EQNXTDZ($A$1,$B42,H$1,$B$1) -> 0 | I42: =_xll.EQNXTDZ($A$1,$B42,I$1,$B$1) -> 0 | J42: =_xll.EQNXTDZ($A$1,$B42,J$1,$B$1) -> 0 | ... AF42: =_xll.EQNXTDZ($A$1,$B42,AF$1,$B$1) -> 0
A43: Total Reserves | B43: BS_RESERVE | C43: =_xll.EQNXTDZ($A$1,$B43,C$1,$B$1) -> 0 | D43: =_xll.EQNXTDZ($A$1,$B43,D$1,$B$1) -> 0 | E43: =_xll.EQNXTDZ($A$1,$B43,E$1,$B$1) -> 0 | F43: =_xll.EQNXTDZ($A$1,$B43,F$1,$B$1) -> 0 | G43: =_xll.EQNXTDZ($A$1,$B43,G$1,$B$1) -> 0 | H43: =_xll.EQNXTDZ($A$1,$B43,H$1,$B$1) -> 0 | I43: =_xll.EQNXTDZ($A$1,$B43,I$1,$B$1) -> 0 | J43: =_xll.EQNXTDZ($A$1,$B43,J$1,$B$1) -> 0 | ... AF43: =_xll.EQNXTDZ($A$1,$B43,AF$1,$B$1) -> 0
A44: Shareholder's Funds | B44: BS_SHAREHODERS_FUNDS | C44: =_xll.EQNXTDZ($A$1,$B44,C$1,$B$1) -> 0 | D44: =_xll.EQNXTDZ($A$1,$B44,D$1,$B$1) -> 0 | E44: =_xll.EQNXTDZ($A$1,$B44,E$1,$B$1) -> 0 | F44: =_xll.EQNXTDZ($A$1,$B44,F$1,$B$1) -> 0 | G44: =_xll.EQNXTDZ($A$1,$B44,G$1,$B$1) -> 0 | H44: =_xll.EQNXTDZ($A$1,$B44,H$1,$B$1) -> 0 | I44: =_xll.EQNXTDZ($A$1,$B44,I$1,$B$1) -> 0 | J44: =_xll.EQNXTDZ($A$1,$B44,J$1,$B$1) -> 0 | ... AF44: =_xll.EQNXTDZ($A$1,$B44,AF$1,$B$1) -> 0
A45: Minority Interest | B45: BS_MINORITY_INTEREST | C45: =_xll.EQNXTDZ($A$1,$B45,C$1,$B$1) -> 0 | D45: =_xll.EQNXTDZ($A$1,$B45,D$1,$B$1) -> 0 | E45: =_xll.EQNXTDZ($A$1,$B45,E$1,$B$1) -> 0 | F45: =_xll.EQNXTDZ($A$1,$B45,F$1,$B$1) -> 0 | G45: =_xll.EQNXTDZ($A$1,$B45,G$1,$B$1) -> 0 | H45: =_xll.EQNXTDZ($A$1,$B45,H$1,$B$1) -> 0 | I45: =_xll.EQNXTDZ($A$1,$B45,I$1,$B$1) -> 0 | J45: =_xll.EQNXTDZ($A$1,$B45,J$1,$B$1) -> 0 | ... AF45: =_xll.EQNXTDZ($A$1,$B45,AF$1,$B$1) -> 0
A46: Long-Term Borrowings | B46: BS_LTRM_BORROWING | C46: =_xll.EQNXTDZ($A$1,$B46,C$1,$B$1) -> 0 | D46: =_xll.EQNXTDZ($A$1,$B46,D$1,$B$1) -> 0 | E46: =_xll.EQNXTDZ($A$1,$B46,E$1,$B$1) -> 0 | F46: =_xll.EQNXTDZ($A$1,$B46,F$1,$B$1) -> 0 | G46: =_xll.EQNXTDZ($A$1,$B46,G$1,$B$1) -> 0 | H46: =_xll.EQNXTDZ($A$1,$B46,H$1,$B$1) -> 0 | I46: =_xll.EQNXTDZ($A$1,$B46,I$1,$B$1) -> 0 | J46: =_xll.EQNXTDZ($A$1,$B46,J$1,$B$1) -> 0 | ... AF46: =_xll.EQNXTDZ($A$1,$B46,AF$1,$B$1) -> 0
A47: Secured Loans | B47: BS_SECURED_LOANS | C47: =_xll.EQNXTDZ($A$1,$B47,C$1,$B$1) -> 0 | D47: =_xll.EQNXTDZ($A$1,$B47,D$1,$B$1) -> 0 | E47: =_xll.EQNXTDZ($A$1,$B47,E$1,$B$1) -> 0 | F47: =_xll.EQNXTDZ($A$1,$B47,F$1,$B$1) -> 0 | G47: =_xll.EQNXTDZ($A$1,$B47,G$1,$B$1) -> 0 | H47: =_xll.EQNXTDZ($A$1,$B47,H$1,$B$1) -> 0 | I47: =_xll.EQNXTDZ($A$1,$B47,I$1,$B$1) -> 0 | J47: =_xll.EQNXTDZ($A$1,$B47,J$1,$B$1) -> 0 | ... AF47: =_xll.EQNXTDZ($A$1,$B47,AF$1,$B$1) -> 0
A48: Unsecured Loans | B48: BS_UNSECURED_LOANS_NF | C48: =_xll.EQNXTDZ($A$1,$B48,C$1,$B$1) -> 0 | D48: =_xll.EQNXTDZ($A$1,$B48,D$1,$B$1) -> 0 | E48: =_xll.EQNXTDZ($A$1,$B48,E$1,$B$1) -> 0 | F48: =_xll.EQNXTDZ($A$1,$B48,F$1,$B$1) -> 0 | G48: =_xll.EQNXTDZ($A$1,$B48,G$1,$B$1) -> 0 | H48: =_xll.EQNXTDZ($A$1,$B48,H$1,$B$1) -> 0 | I48: =_xll.EQNXTDZ($A$1,$B48,I$1,$B$1) -> 0 | J48: =_xll.EQNXTDZ($A$1,$B48,J$1,$B$1) -> 0 | ... AF48: =_xll.EQNXTDZ($A$1,$B48,AF$1,$B$1) -> 0
A49: Deferred Tax Assets / Liabilities | B49: BS_NET_DEF_TAX_NF | C49: =_xll.EQNXTDZ($A$1,$B49,C$1,$B$1) -> 0 | D49: =_xll.EQNXTDZ($A$1,$B49,D$1,$B$1) -> 0 | E49: =_xll.EQNXTDZ($A$1,$B49,E$1,$B$1) -> 0 | F49: =_xll.EQNXTDZ($A$1,$B49,F$1,$B$1) -> 0 | G49: =_xll.EQNXTDZ($A$1,$B49,G$1,$B$1) -> 0 | H49: =_xll.EQNXTDZ($A$1,$B49,H$1,$B$1) -> 0 | I49: =_xll.EQNXTDZ($A$1,$B49,I$1,$B$1) -> 0 | J49: =_xll.EQNXTDZ($A$1,$B49,J$1,$B$1) -> 0 | ... AF49: =_xll.EQNXTDZ($A$1,$B49,AF$1,$B$1) -> 0
A50: Other Long Term Liabilities | B50: BS_OTH_LT_LIAB | C50: =_xll.EQNXTDZ($A$1,$B50,C$1,$B$1) -> 0 | D50: =_xll.EQNXTDZ($A$1,$B50,D$1,$B$1) -> 0 | E50: =_xll.EQNXTDZ($A$1,$B50,E$1,$B$1) -> 0 | F50: =_xll.EQNXTDZ($A$1,$B50,F$1,$B$1) -> 0 | G50: =_xll.EQNXTDZ($A$1,$B50,G$1,$B$1) -> 0 | H50: =_xll.EQNXTDZ($A$1,$B50,H$1,$B$1) -> 0 | I50: =_xll.EQNXTDZ($A$1,$B50,I$1,$B$1) -> 0 | J50: =_xll.EQNXTDZ($A$1,$B50,J$1,$B$1) -> 0 | ... AF50: =_xll.EQNXTDZ($A$1,$B50,AF$1,$B$1) -> 0
A51: Long Term Trade Payables | B51: BS_LT_TRADE_PAYABLES | C51: =_xll.EQNXTDZ($A$1,$B51,C$1,$B$1) -> 0 | D51: =_xll.EQNXTDZ($A$1,$B51,D$1,$B$1) -> 0 | E51: =_xll.EQNXTDZ($A$1,$B51,E$1,$B$1) -> 0 | F51: =_xll.EQNXTDZ($A$1,$B51,F$1,$B$1) -> 0 | G51: =_xll.EQNXTDZ($A$1,$B51,G$1,$B$1) -> 0 | H51: =_xll.EQNXTDZ($A$1,$B51,H$1,$B$1) -> 0 | I51: =_xll.EQNXTDZ($A$1,$B51,I$1,$B$1) -> 0 | J51: =_xll.EQNXTDZ($A$1,$B51,J$1,$B$1) -> 0 | ... AF51: =_xll.EQNXTDZ($A$1,$B51,AF$1,$B$1) -> 0
... A99: Estimated Capital Contracts Remaining | B99: BS_ESTIMATED_CAPITAL_CONTRACT | C99: =_xll.EQNXTDZ($A$1,$B99,C$1,$B$1) -> 0 | D99: =_xll.EQNXTDZ($A$1,$B99,D$1,$B$1) -> 0 | E99: =_xll.EQNXTDZ($A$1,$B99,E$1,$B$1) -> 0 | F99: =_xll.EQNXTDZ($A$1,$B99,F$1,$B$1) -> 0 | G99: =_xll.EQNXTDZ($A$1,$B99,G$1,$B$1) -> 0 | H99: =_xll.EQNXTDZ($A$1,$B99,H$1,$B$1) -> 0 | I99: =_xll.EQNXTDZ($A$1,$B99,I$1,$B$1) -> 0 | J99: =_xll.EQNXTDZ($A$1,$B99,J$1,$B$1) -> 0 | ... AF99: =_xll.EQNXTDZ($A$1,$B99,AF$1,$B$1) -> 0
A103: Field Description | B103: Field Name
A104: Equity Paid Up | B104: BS_EQUITY_PAIDUP | C104: =_xll.EQNXTDZ($A$1,$B104,C$1,$B$1) -> 0 | D104: =_xll.EQNXTDZ($A$1,$B104,D$1,$B$1) -> 0 | E104: =_xll.EQNXTDZ($A$1,$B104,E$1,$B$1) -> 0 | F104: =_xll.EQNXTDZ($A$1,$B104,F$1,$B$1) -> 0 | G104: =_xll.EQNXTDZ($A$1,$B104,G$1,$B$1) -> 0 | H104: =_xll.EQNXTDZ($A$1,$B104,H$1,$B$1) -> 0 | I104: =_xll.EQNXTDZ($A$1,$B104,I$1,$B$1) -> 0 | J104: =_xll.EQNXTDZ($A$1,$B104,J$1,$B$1) -> 0 | ... AF104: =_xll.EQNXTDZ($A$1,$B104,AF$1,$B$1) -> 0
A105: Face Value | B105: BS_FACE_VALUE | C105: =_xll.EQNXTDZ($A$1,$B105,C$1,$B$1) -> 0 | D105: =_xll.EQNXTDZ($A$1,$B105,D$1,$B$1) -> 0 | E105: =_xll.EQNXTDZ($A$1,$B105,E$1,$B$1) -> 0 | F105: =_xll.EQNXTDZ($A$1,$B105,F$1,$B$1) -> 0 | G105: =_xll.EQNXTDZ($A$1,$B105,G$1,$B$1) -> 0 | H105: =_xll.EQNXTDZ($A$1,$B105,H$1,$B$1) -> 0 | I105: =_xll.EQNXTDZ($A$1,$B105,I$1,$B$1) -> 0 | J105: =_xll.EQNXTDZ($A$1,$B105,J$1,$B$1) -> 0 | ... AF105: =_xll.EQNXTDZ($A$1,$B105,AF$1,$B$1) -> 0
A106: Close Price (Unit Curr.) | B106: FH_YEAR_PRICE | C106: =_xll.EQNXTDZ($A$1,$B106,C$1,$B$1) -> 0 | D106: =_xll.EQNXTDZ($A$1,$B106,D$1,$B$1) -> 0 | E106: =_xll.EQNXTDZ($A$1,$B106,E$1,$B$1) -> 0 | F106: =_xll.EQNXTDZ($A$1,$B106,F$1,$B$1) -> 0 | G106: =_xll.EQNXTDZ($A$1,$B106,G$1,$B$1) -> 0 | H106: =_xll.EQNXTDZ($A$1,$B106,H$1,$B$1) -> 0 | I106: =_xll.EQNXTDZ($A$1,$B106,I$1,$B$1) -> 0 | J106: =_xll.EQNXTDZ($A$1,$B106,J$1,$B$1) -> 0 | ... AF106: =_xll.EQNXTDZ($A$1,$B106,AF$1,$B$1) -> 0
A107: High Price (Unit Curr.) | B107: FH_HIGH | C107: =_xll.EQNXTDZ($A$1,$B107,C$1,$B$1) -> 0 | D107: =_xll.EQNXTDZ($A$1,$B107,D$1,$B$1) -> 0 | E107: =_xll.EQNXTDZ($A$1,$B107,E$1,$B$1) -> 0 | F107: =_xll.EQNXTDZ($A$1,$B107,F$1,$B$1) -> 0 | G107: =_xll.EQNXTDZ($A$1,$B107,G$1,$B$1) -> 0 | H107: =_xll.EQNXTDZ($A$1,$B107,H$1,$B$1) -> 0 | I107: =_xll.EQNXTDZ($A$1,$B107,I$1,$B$1) -> 0 | J107: =_xll.EQNXTDZ($A$1,$B107,J$1,$B$1) -> 0 | ... AF107: =_xll.EQNXTDZ($A$1,$B107,AF$1,$B$1) -> 0
A108: Low Price (Unit Curr.) | B108: FH_LOW | C108: =_xll.EQNXTDZ($A$1,$B108,C$1,$B$1) -> 0 | D108: =_xll.EQNXTDZ($A$1,$B108,D$1,$B$1) -> 0 | E108: =_xll.EQNXTDZ($A$1,$B108,E$1,$B$1) -> 0 | F108: =_xll.EQNXTDZ($A$1,$B108,F$1,$B$1) -> 0 | G108: =_xll.EQNXTDZ($A$1,$B108,G$1,$B$1) -> 0 | H108: =_xll.EQNXTDZ($A$1,$B108,H$1,$B$1) -> 0 | I108: =_xll.EQNXTDZ($A$1,$B108,I$1,$B$1) -> 0 | J108: =_xll.EQNXTDZ($A$1,$B108,J$1,$B$1) -> 0 | ... AF108: =_xll.EQNXTDZ($A$1,$B108,AF$1,$B$1) -> 0
A109: Market Capitalization | B109: FH_MCAP | C109: =_xll.EQNXTDZ($A$1,$B109,C$1,$B$1) -> 0 | D109: =_xll.EQNXTDZ($A$1,$B109,D$1,$B$1) -> 0 | E109: =_xll.EQNXTDZ($A$1,$B109,E$1,$B$1) -> 0 | F109: =_xll.EQNXTDZ($A$1,$B109,F$1,$B$1) -> 0 | G109: =_xll.EQNXTDZ($A$1,$B109,G$1,$B$1) -> 0 | H109: =_xll.EQNXTDZ($A$1,$B109,H$1,$B$1) -> 0 | I109: =_xll.EQNXTDZ($A$1,$B109,I$1,$B$1) -> 0 | J109: =_xll.EQNXTDZ($A$1,$B109,J$1,$B$1) -> 0 | ... AF109: =_xll.EQNXTDZ($A$1,$B109,AF$1,$B$1) -> 0
A110: Adj DPS(Rs) | B110: FR_ADJ_DPS | C110: =_xll.EQNXTDZ($A$1,$B110,C$1,$B$1) -> 0 | D110: =_xll.EQNXTDZ($A$1,$B110,D$1,$B$1) -> 0 | E110: =_xll.EQNXTDZ($A$1,$B110,E$1,$B$1) -> 0 | F110: =_xll.EQNXTDZ($A$1,$B110,F$1,$B$1) -> 0 | G110: =_xll.EQNXTDZ($A$1,$B110,G$1,$B$1) -> 0 | H110: =_xll.EQNXTDZ($A$1,$B110,H$1,$B$1) -> 0 | I110: =_xll.EQNXTDZ($A$1,$B110,I$1,$B$1) -> 0 | J110: =_xll.EQNXTDZ($A$1,$B110,J$1,$B$1) -> 0 | ... AF110: =_xll.EQNXTDZ($A$1,$B110,AF$1,$B$1) -> 0
A111: Date End | B111: SHP_DATE_END | C111: =_xll.EQNXTDZ($A$1,$B111,C$5) -> 0 | D111: =_xll.EQNXTDZ($A$1,$B111,D$5) -> 0 | E111: =_xll.EQNXTDZ($A$1,$B111,E$5) -> 0 | F111: =_xll.EQNXTDZ($A$1,$B111,F$5) -> 0 | G111: =_xll.EQNXTDZ($A$1,$B111,G$5) -> 0 | H111: =_xll.EQNXTDZ($A$1,$B111,H$5) -> 0 | I111: =_xll.EQNXTDZ($A$1,$B111,I$5) -> 0 | J111: =_xll.EQNXTDZ($A$1,$B111,J$5) -> 0 | ... AF111: =_xll.EQNXTDZ($A$1,$B111,AF$5) -> 0
A112: Total of Promoter and Promoter Group | B112: SHP_TPFTOTALPROMOTER | C112: =_xll.EQNXTDZ($A$1,$B112,C$5) -> 0 | D112: =_xll.EQNXTDZ($A$1,$B112,D$5) -> 0 | E112: =_xll.EQNXTDZ($A$1,$B112,E$5) -> 0 | F112: =_xll.EQNXTDZ($A$1,$B112,F$5) -> 0 | G112: =_xll.EQNXTDZ($A$1,$B112,G$5) -> 0 | H112: =_xll.EQNXTDZ($A$1,$B112,H$5) -> 0 | I112: =_xll.EQNXTDZ($A$1,$B112,I$5) -> 0 | J112: =_xll.EQNXTDZ($A$1,$B112,J$5) -> 0 | ... AF112: =_xll.EQNXTDZ($A$1,$B112,AF$5) -> 0
A113: Total of Promoter and Promoter Group Pledged | B113: SHP_PSHFTOTALPROMOTER | C113: =_xll.EQNXTDZ($A$1,$B113,C$5) -> 0 | D113: =_xll.EQNXTDZ($A$1,$B113,D$5) -> 0 | E113: =_xll.EQNXTDZ($A$1,$B113,E$5) -> 0 | F113: =_xll.EQNXTDZ($A$1,$B113,F$5) -> 0 | G113: =_xll.EQNXTDZ($A$1,$B113,G$5) -> 0 | H113: =_xll.EQNXTDZ($A$1,$B113,H$5) -> 0 | I113: =_xll.EQNXTDZ($A$1,$B113,I$5) -> 0 | J113: =_xll.EQNXTDZ($A$1,$B113,J$5) -> 0 | ... AF113: =_xll.EQNXTDZ($A$1,$B113,AF$5) -> 0

Sheet QTR Share Price
A1: ='QTR Raw'!A1 -> 100378 | C1: 201206 | D1: 201207 | E1: 201208 | F1: 201209 | G1: 201210 | H1: 201211 | I1: 201212 | J1: 201301 | K1: 201302 | L1: 201303 | M1: 201304 | N1: 201305 | O1: 201306 | P1: 201307 | Q1: 201308 | R1: 201309 | S1: 201310 | T1: 201311 | U1: 201312 | V1: 201401 | W1: 201402 | X1: 201403 | Y1: 201404 | Z1: 201405 | AA1: 201406 | AB1: 201407 | AC1: 201408 | AD1: 201409 | AE1: 201410 | AF1: 201411 | AG1: 201412 | AH1: 201501 | AI1: 201502 | AJ1: 201503 | AK1: 201504 | AL1: 201505 | AM1: 201506 | AN1: 201507 | AO1: 201508 | AP1: 201509 | AQ1: 201510 | AR1: 201511 | AS1: 201512 | AT1: 201601 | AU1: 201602 | AV1: 201603 | AW1: 201604 | AX1: 201605 | AY1: 201606 | AZ1: 201607 | BA1: 201608 | BB1: 201609 | BC1: 201610 | BD1: 201611 | BE1: 201612 | BF1: 201701 | BG1: 201702 | BH1: 201703 | BI1: 201704 | BJ1: 201705 | BK1: 201706 | BL1: 201707 | BM1: 201708 | BN1: 201709 | BO1: 201710 | BP1: 201711 | BQ1: 201712 | BR1: 201801 | BS1: 201802 | BT1: 201803 | BU1: 201804 | BV1: 201805 | BW1: 201806 | BX1: 201807 | BY1: 201808 | BZ1: 201809 | CA1: 201810 | CB1: 201811 | CC1: 201812 | CD1: 201901 | CE1: 201902 | CF1: 201903 | CG1: 201904 | CH1: 201905 | CI1: 201906 | CJ1: 201907 | CK1: 201908 | CL1: 201909 | CM1: 201910 | CN1: 201911 | CO1: 201912 | CP1: 202001 | CQ1: 202002 | CR1: 202003 | CS1: 202004 | CT1: 202005 | CU1: 202006 | CV1: 202007 | CW1: 202008 | CX1: 202009 | CY1: 202010 | CZ1: 202011 | DA1: 202012 | DB1: 202101 | DC1: 202102 | DD1: 202103 | DE1: 202104 | DF1: 202105 | DG1: 202106 | DH1: 202107 | DI1: 202108 | DJ1: 202109 | DK1: 202110 | DL1: 202111 | DM1: 202112 | DN1: 202201 | DO1: 202202 | DP1: 202203 | DQ1: 202204 | DR1: 202205 | DS1: 202206 | DT1: 202207 | DU1: 202208 | DV1: 202209 | DW1: 202210 | DX1: 202211 | DY1: 202212 | DZ1: 202301 | EA1: 202302 | EB1: 202303 | EC1: 202304 | ED1: 202305 | EE1: 202306 | EF1: 202307 | EG1: 202308 | EH1: 202309 | EI1: 202310 | EJ1: 202311 | EK1: 202312 | EL1: 202401 | EM1: 202402 | EN1: 202403 | EO1: 202404 | EP1: 202405 | EQ1: 202406 | ER1: 202407 | ES1: 202408 | ET1: 202409 | EU1: 202410 | EV1: 202411 | EW1: 202412 | EX1: 202501 | EY1: 202502 | EZ1: 202503 | FA1: 202504 | FB1: 202505 | FC1: 202506 | FD1: 202507 | FE1: 202508 | FF1: 202509 | FG1: 202510 | FH1: 202511 | FI1: 202512 | FJ1: 202601 | FK1: 202602 | FL1: 202603 | FM1: 202604 | FN1: 202605 | FO1: 202606 | FP1: 202607 | FQ1: 202608 | FR1: 202609 | FS1: 202610 | FT1: 202611 | FU1: 202612 | FV1: 202701 | FW1: 202702 | FX1: 202703 | FY1: 202704 | FZ1: 202705 | GA1: 202706 | GB1: 202707 | GC1: 202708 | GD1: 202709 | GE1: 202710 | GF1: 202711 | GG1: 202712 | GH1: 202801 | GI1: 202802 | GJ1: 202803 | GK1: 202804 | GL1: 202805 | GM1: 202806 | GN1: 202807 | GO1: 202808 | GP1: 202809 | GQ1: 202810 | GR1: 202811 | GS1: 202812 | GT1: 202901 | GU1: 202902 | GV1: 202903 | GW1: 202904 | GX1: 202905 | GY1: 202906 | GZ1: 202907 | HA1: 202908 | HB1: 202909 | HC1: 202910 | HD1: 202911 | HE1: 202912 | HF1: 203001 | HG1: 203002 | HH1: 203003 | HM1: 201206 | HN1: 201207 | HO1: 201208 | HP1: 201209 | HQ1: 201212 | HR1: 201303 | HS1: 201306 | HT1: 201309 | HU1: 201312 | HV1: 201403 | HW1: 201406 | HX1: 201409 | HY1: 201412 | HZ1: 201503 | IA1: 201506 | IB1: 201509 | IC1: 201512 | ID1: 201603 | IE1: 201606 | IF1: 201609 | IG1: 201612 | IH1: 201703 | II1: 201706 | IJ1: 201709 | IK1: 201712 | IL1: 201803 | IM1: 201806 | IN1: 201809 | IO1: 201812 | IP1: 201903 | IQ1: 201906 | IR1: 201909 | IS1: 201912 | IT1: 202003 | IU1: 202006 | IV1: 202009 | IW1: 202012 | IX1: 202103 | IY1: 202106 | IZ1: 202109 | JA1: 202112 | JB1: 202203 | JC1: 202206 | JD1: 202209 | JE1: 202212 | JF1: 202303 | JG1: 202306 | JH1: 202309 | JI1: 202312 | JJ1: 202403 | JK1: 202406 | JL1: 202409 | JM1: 202412 | JN1: 202503 | JO1: 202506 | JP1: 202509 | JQ1: 202512 | JR1: 202603 | JS1: 202606 | JT1: 202609 | JU1: 202612 | JV1: 202703 | JW1: 202706 | JX1: 202709 | JY1: 202712 | JZ1: 202803 | KA1: 202806 | KB1: 202809 | KC1: 202812 | KD1: 202903 | KE1: 202906 | KF1: 202909 | KG1: 202912 | KH1: 203003
FF2: 45901 | FG2: =+EOMONTH(FF2,1) -> 45961 | FH2: =+EOMONTH(FG2,1) -> 45991 | FI2: =+EOMONTH(FH2,1) -> 46022 | FJ2: =+EOMONTH(FI2,1) -> 46053 | FK2: =+EOMONTH(FJ2,1) -> 46081 | FL2: =+EOMONTH(FK2,1) -> 46112 | FM2: =+EOMONTH(FL2,1) -> 46142 | FN2: =+EOMONTH(FM2,1) -> 46173 | ... HH2: =+EOMONTH(HG2,1) -> 47573
A4: Field Description | B4: Field Name
A5: MonthEnd | B5: NMONTH_MONTHEND | C5: {=_xll.EQNXTDZ($A$1,$B5,C$1)} -> 201206 | D5: {=_xll.EQNXTDZ($A$1,$B5,D$1)} -> 201207 | E5: {=_xll.EQNXTDZ($A$1,$B5,E$1)} -> 201208 | F5: {=_xll.EQNXTDZ($A$1,$B5,F$1)} -> 201209 | G5: {=_xll.EQNXTDZ($A$1,$B5,G$1)} -> 201210 | H5: {=_xll.EQNXTDZ($A$1,$B5,H$1)} -> 201211 | I5: {=_xll.EQNXTDZ($A$1,$B5,I$1)} -> 201212 | J5: {=_xll.EQNXTDZ($A$1,$B5,J$1)} -> 201301 | ... HH5: {=_xll.EQNXTDZ($A$1,$B5,HH$1)} -> 0
A6: Open | B6: NMONTH_OPEN | C6: {=_xll.EQNXTDZ($A$1,$B6,C$1)} -> 61.725 | D6: {=_xll.EQNXTDZ($A$1,$B6,D$1)} -> 67.425 | E6: {=_xll.EQNXTDZ($A$1,$B6,E$1)} -> 57.5 | F6: {=_xll.EQNXTDZ($A$1,$B6,F$1)} -> 58.65 | G6: {=_xll.EQNXTDZ($A$1,$B6,G$1)} -> 59.925 | H6: {=_xll.EQNXTDZ($A$1,$B6,H$1)} -> 57.075 | I6: {=_xll.EQNXTDZ($A$1,$B6,I$1)} -> 66.5 | J6: {=_xll.EQNXTDZ($A$1,$B6,J$1)} -> 65.125 | ... HH6: {=_xll.EQNXTDZ($A$1,$B6,HH$1)} -> 0
A7: High | B7: NMONTH_HIGH | C7: {=_xll.EQNXTDZ($A$1,$B7,C$1)} -> 66.7 | D7: {=_xll.EQNXTDZ($A$1,$B7,D$1)} -> 69.225 | E7: {=_xll.EQNXTDZ($A$1,$B7,E$1)} -> 61.5 | F7: {=_xll.EQNXTDZ($A$1,$B7,F$1)} -> 61.75 | G7: {=_xll.EQNXTDZ($A$1,$B7,G$1)} -> 60.75 | H7: {=_xll.EQNXTDZ($A$1,$B7,H$1)} -> 68.95 | I7: {=_xll.EQNXTDZ($A$1,$B7,I$1)} -> 66.825 | J7: {=_xll.EQNXTDZ($A$1,$B7,J$1)} -> 68.35 | ... HH7: {=_xll.EQNXTDZ($A$1,$B7,HH$1)} -> 0 | HP7: =+MAX(D7:F7) -> 69.225 | HQ7: =+MAX(G7:I7) -> 68.95 | HR7: =+MAX(J7:L7) -> 68.35 | HS7: =+MAX(M7:O7) -> 46.425 | HT7: =+MAX(P7:R7) -> 31.95 | HU7: =+MAX(S7:U7) -> 27.05 | HV7: =+MAX(V7:X7) -> 31.725 | HW7: =+MAX(Y7:AA7) -> 47.925 | HX7: =+MAX(AB7:AD7) -> 49.15 | HY7: =+MAX(AE7:AG7) -> 57.825 | HZ7: =+MAX(AH7:AJ7) -> 48.6 | IA7: =+MAX(AK7:AM7) -> 37.325 | IB7: =+MAX(AN7:AP7) -> 42.7 | IC7: =+MAX(AQ7:AS7) -> 36.75 | ID7: =+MAX(AT7:AV7) -> 32.85 | IE7: =+MAX(AW7:AY7) -> 27.775 | IF7: =+MAX(AZ7:BB7) -> 29.9 | IG7: =+MAX(BC7:BE7) -> 33.8 | IH7: =+MAX(BF7:BH7) -> 43.75 | II7: =+MAX(BI7:BK7) -> 46.1 | IJ7: =+MAX(BL7:BN7) -> 61.5 | IK7: =+MAX(BO7:BQ7) -> 71.85 | IL7: =+MAX(BR7:BT7) -> 91.125 | IM7: =+MAX(BU7:BW7) -> 68.75 | IN7: =+MAX(BX7:BZ7) -> 50.95 | IO7: =+MAX(CA7:CC7) -> 45.375 | IP7: =+MAX(CD7:CF7) -> 48.6 | IQ7: =+MAX(CG7:CI7) -> 46.4 | IR7: =+MAX(CJ7:CL7) -> 44.25 | IS7: =+MAX(CM7:CO7) -> 46.45 | IT7: =+MAX(CP7:CR7) -> 51.3 | IU7: =+MAX(CS7:CU7) -> 31.95 | IV7: =+MAX(CV7:CX7) -> 37.375 | IW7: =+MAX(CY7:DA7) -> 40.95 | IX7: =+MAX(DB7:DD7) -> 43.825 | IY7: =+MAX(DE7:DG7) -> 59.85 | IZ7: =+MAX(DH7:DJ7) -> 73.8 | JA7: =+MAX(DK7:DM7) -> 64 | JB7: =+MAX(DN7:DP7) -> 59.7 | JC7: =+MAX(DQ7:DS7) -> 50.75 | JD7: =+MAX(DT7:DV7) -> 46.4 | JE7: =+MAX(DW7:DY7) -> 53.9 | JF7: =+MAX(DZ7:EB7) -> 89.775 | JG7: =+MAX(EC7:EE7) -> 132.2 | JH7: =+MAX(EF7:EH7) -> 195.5 | JI7: =+MAX(EI7:EK7) -> 257.5 | JJ7: =+MAX(EL7:EN7) -> 279.225 | JK7: =MAX(EO7:EQ7) -> 299 | JL7: =MAX(ER7:ET7) -> 379.95 | JM7: =MAX(EU7:EW7) -> 383.85 | JN7: =MAX(EX7:EZ7) -> 289.3 | JO7: =MAX(FA7:FC7) -> 277.95 | JP7: =MAX(FD7:FF7) -> 244.91 | JQ7: =MAX(FG7:FI7) -> 213.6 | JR7: =MAX(FJ7:FL7) -> 211 | JS7: =MAX(FM7:FO7) -> 267.5 | JT7: =MAX(FP7:FR7) -> 0 | JU7: =MAX(FS7:FU7) -> 0 | JV7: =MAX(FV7:FX7) -> 0 | JW7: =MAX(FY7:GA7) -> 0 | JX7: =MAX(GB7:GD7) -> 0 | JY7: =MAX(GE7:GG7) -> 0 | JZ7: =MAX(GH7:GJ7) -> 0 | KA7: =MAX(GK7:GM7) -> 0 | KB7: =MAX(GN7:GP7) -> 0 | KC7: =MAX(GQ7:GS7) -> 0 | KD7: =MAX(GT7:GV7) -> 0 | KE7: =MAX(GW7:GY7) -> 0 | KF7: =MAX(GZ7:HB7) -> 0 | KG7: =MAX(HC7:HE7) -> 0 | KH7: =MAX(HF7:HH7) -> 0
A8: Low | B8: NMONTH_LOW | C8: {=_xll.EQNXTDZ($A$1,$B8,C$1)} -> 60.175 | D8: {=_xll.EQNXTDZ($A$1,$B8,D$1)} -> 59.25 | E8: {=_xll.EQNXTDZ($A$1,$B8,E$1)} -> 56.875 | F8: {=_xll.EQNXTDZ($A$1,$B8,F$1)} -> 55.575 | G8: {=_xll.EQNXTDZ($A$1,$B8,G$1)} -> 54.5 | H8: {=_xll.EQNXTDZ($A$1,$B8,H$1)} -> 56.6 | I8: {=_xll.EQNXTDZ($A$1,$B8,I$1)} -> 60 | J8: {=_xll.EQNXTDZ($A$1,$B8,J$1)} -> 52.55 | ... HH8: {=_xll.EQNXTDZ($A$1,$B8,HH$1)} -> 0 | HP8: =+MIN(D8:F8) -> 55.575 | HQ8: =+MIN(G8:I8) -> 54.5 | HR8: =+MIN(J8:L8) -> 38.5 | HS8: =+MIN(M8:O8) -> 24.25 | HT8: =+MIN(P8:R8) -> 18.775 | HU8: =+MIN(S8:U8) -> 21.075 | HV8: =+MIN(V8:X8) -> 23.025 | HW8: =+MIN(Y8:AA8) -> 26 | HX8: =+MIN(AB8:AD8) -> 35.75 | HY8: =+MIN(AE8:AG8) -> 37 | HZ8: =+MIN(AH8:AJ8) -> 28.1 | IA8: =+MIN(AK8:AM8) -> 25.5 | IB8: =+MIN(AN8:AP8) -> 29.125 | IC8: =+MIN(AQ8:AS8) -> 29.875 | ID8: =+MIN(AT8:AV8) -> 17.825 | IE8: =+MIN(AW8:AY8) -> 19.125 | IF8: =+MIN(AZ8:BB8) -> 22.375 | IG8: =+MIN(BC8:BE8) -> 23.75 | IH8: =+MIN(BF8:BH8) -> 27.625 | II8: =+MIN(BI8:BK8) -> 36.225 | IJ8: =+MIN(BL8:BN8) -> 41.125 | IK8: =+MIN(BO8:BQ8) -> 54.5 | IL8: =+MIN(BR8:BT8) -> 56.775 | IM8: =+MIN(BU8:BW8) -> 35.275 | IN8: =+MIN(BX8:BZ8) -> 35 | IO8: =+MIN(CA8:CC8) -> 33.7 | IP8: =+MIN(CD8:CF8) -> 37.05 | IQ8: =+MIN(CG8:CI8) -> 36.4 | IR8: =+MIN(CJ8:CL8) -> 31.5 | IS8: =+MIN(CM8:CO8) -> 35.05 | IT8: =+MIN(CP8:CR8) -> 19.925 | IU8: =+MIN(CS8:CU8) -> 21.9 | IV8: =+MIN(CV8:CX8) -> 27.15 | IW8: =+MIN(CY8:DA8) -> 29 | IX8: =+MIN(DB8:DD8) -> 34.925 | IY8: =+MIN(DE8:DG8) -> 35.3 | IZ8: =+MIN(DH8:DJ8) -> 55.225 | JA8: =+MIN(DK8:DM8) -> 46.75 | JB8: =+MIN(DN8:DP8) -> 40 | JC8: =+MIN(DQ8:DS8) -> 37.525 | JD8: =+MIN(DT8:DV8) -> 38.425 | JE8: =+MIN(DW8:DY8) -> 38.725 | JF8: =+MIN(DZ8:EB8) -> 51.875 | JG8: =+MIN(EC8:EE8) -> 73.175 | JH8: =+MIN(EF8:EH8) -> 128.525 | JI8: =+MIN(EI8:EK8) -> 164.275 | JJ8: =+MIN(EL8:EN8) -> 189.975 | JK8: =MIN(EO8:EQ8) -> 219.425 | JL8: =MIN(ER8:ET8) -> 263.425 | JM8: =MIN(EU8:EW8) -> 287.5 | JN8: =MIN(EX8:EZ8) -> 217.65 | JO8: =MIN(FA8:FC8) -> 199.62 | JP8: =MIN(FD8:FF8) -> 196.02 | JQ8: =MIN(FG8:FI8) -> 153 | JR8: =MIN(FJ8:FL8) -> 154 | JS8: =MIN(FM8:FO8) -> 184.45 | JT8: =MIN(FP8:FR8) -> 0 | JU8: =MIN(FS8:FU8) -> 0 | JV8: =MIN(FV8:FX8) -> 0 | JW8: =MIN(FY8:GA8) -> 0 | JX8: =MIN(GB8:GD8) -> 0 | JY8: =MIN(GE8:GG8) -> 0 | JZ8: =MIN(GH8:GJ8) -> 0 | KA8: =MIN(GK8:GM8) -> 0 | KB8: =MIN(GN8:GP8) -> 0 | KC8: =MIN(GQ8:GS8) -> 0 | KD8: =MIN(GT8:GV8) -> 0 | KE8: =MIN(GW8:GY8) -> 0 | KF8: =MIN(GZ8:HB8) -> 0 | KG8: =MIN(HC8:HE8) -> 0 | KH8: =MIN(HF8:HH8) -> 0
A9: Close | B9: NMONTH_CLOSE | C9: {=_xll.EQNXTDZ($A$1,$B9,C$1)} -> 66.25 | D9: {=_xll.EQNXTDZ($A$1,$B9,D$1)} -> 59.925 | E9: {=_xll.EQNXTDZ($A$1,$B9,E$1)} -> 58.95 | F9: {=_xll.EQNXTDZ($A$1,$B9,F$1)} -> 59.4 | G9: {=_xll.EQNXTDZ($A$1,$B9,G$1)} -> 57.025 | H9: {=_xll.EQNXTDZ($A$1,$B9,H$1)} -> 65.95 | I9: {=_xll.EQNXTDZ($A$1,$B9,I$1)} -> 64.275 | J9: {=_xll.EQNXTDZ($A$1,$B9,J$1)} -> 54.275 | ... HH9: {=_xll.EQNXTDZ($A$1,$B9,HH$1)} -> 0 | HP9: =+F9 -> 59.4 | HQ9: =+I9 -> 64.275 | HR9: =+L9 -> 41.05 | HS9: =+O9 -> 28.75 | HT9: =+R9 -> 22.325 | HU9: =+U9 -> 24.55 | HV9: =+X9 -> 28.275 | HW9: =+AA9 -> 41.675 | HX9: =+AD9 -> 40.225 | HY9: =+AG9 -> 46.65 | HZ9: =+AJ9 -> 32.875 | IA9: =+AM9 -> 29.3 | IB9: =+AP9 -> 31.925 | IC9: =+AS9 -> 31.325 | ID9: =+AV9 -> 19.35 | IE9: =+AY9 -> 26.6 | IF9: =+BB9 -> 27.425 | IG9: =+BE9 -> 27.675 | IH9: =+BH9 -> 41.7 | II9: =+BK9 -> 42 | IJ9: =+BN9 -> 56.2 | IK9: =+BQ9 -> 69.925 | IL9: =+BT9 -> 59.375 | IM9: =+BW9 -> 39.725 | IN9: =+BZ9 -> 36.675 | IO9: =+CC9 -> 42.425 | IP9: =+CF9 -> 43.2 | IQ9: =+CI9 -> 41.625 | IR9: =+CL9 -> 42.875 | IS9: =+CO9 -> 36.525 | IT9: =+CR9 -> 22.9 | IU9: =+CU9 -> 28.95 | IV9: =+CX9 -> 31.45 | IW9: =+DA9 -> 37.925 | IX9: =+DD9 -> 37.075 | IY9: =+DG9 -> 58.5 | IZ9: =+DJ9 -> 57.025 | JA9: =+DM9 -> 49.425 | JB9: =+DP9 -> 45.05 | JC9: =+DS9 -> 39.4 | JD9: =+DV9 -> 41.25 | JE9: =+DY9 -> 51.775 | JF9: =+EB9 -> 72.95 | JG9: =+EE9 -> 127.95 | JH9: =+EH9 -> 173.3 | JI9: =+EK9 -> 206.025 | JJ9: =+EN9 -> 216.35 | JK9: =EQ9 -> 271.925 | JL9: =ET9 -> 371.65 | JM9: =EW9 -> 291.4 | JN9: =EZ9 -> 270.09 | JO9: =FC9 -> 240.78 | JP9: =FF9 -> 202.82 | JQ9: =FI9 -> 167.94 | JR9: =FL9 -> 183.12 | JS9: =FO9 -> 247.91 | JT9: =FR9 -> 0 | JU9: =FU9 -> 0 | JV9: =FX9 -> 0 | JW9: =GA9 -> 0 | JX9: =GD9 -> 0 | JY9: =GG9 -> 0 | JZ9: =GJ9 -> 0 | KA9: =GM9 -> 0 | KB9: =GP9 -> 0 | KC9: =GS9 -> 0 | KD9: =GV9 -> 0 | KE9: =GY9 -> 0 | KF9: =HB9 -> 0 | KG9: =HE9 -> 0 | KH9: =HH9 -> 0
A11: Field Description | B11: Field Name | C11: {=_xll.EQNXTDZ($A$1,$B11,C$1)} -> 0 | D11: {=_xll.EQNXTDZ($A$1,$B11,D$1)} -> 0 | E11: {=_xll.EQNXTDZ($A$1,$B11,E$1)} -> 0 | F11: {=_xll.EQNXTDZ($A$1,$B11,F$1)} -> 0 | G11: {=_xll.EQNXTDZ($A$1,$B11,G$1)} -> 0 | H11: {=_xll.EQNXTDZ($A$1,$B11,H$1)} -> 0 | I11: {=_xll.EQNXTDZ($A$1,$B11,I$1)} -> 0 | J11: {=_xll.EQNXTDZ($A$1,$B11,J$1)} -> 0 | ... HH11: {=_xll.EQNXTDZ($A$1,$B11,HH$1)} -> 0
A12: Month End | B12: BMONTH_MONTHEND | C12: {=_xll.EQNXTDZ($A$1,$B12,C$1)} -> 201206 | D12: {=_xll.EQNXTDZ($A$1,$B12,D$1)} -> 201207 | E12: {=_xll.EQNXTDZ($A$1,$B12,E$1)} -> 201208 | F12: {=_xll.EQNXTDZ($A$1,$B12,F$1)} -> 201209 | G12: {=_xll.EQNXTDZ($A$1,$B12,G$1)} -> 201210 | H12: {=_xll.EQNXTDZ($A$1,$B12,H$1)} -> 201211 | I12: {=_xll.EQNXTDZ($A$1,$B12,I$1)} -> 201212 | J12: {=_xll.EQNXTDZ($A$1,$B12,J$1)} -> 201301 | ... HH12: {=_xll.EQNXTDZ($A$1,$B12,HH$1)} -> 0
A13: Open | B13: BMONTH_OPEN | C13: {=_xll.EQNXTDZ($A$1,$B13,C$1)} -> 62.2 | D13: {=_xll.EQNXTDZ($A$1,$B13,D$1)} -> 68 | E13: {=_xll.EQNXTDZ($A$1,$B13,E$1)} -> 59.1 | F13: {=_xll.EQNXTDZ($A$1,$B13,F$1)} -> 59.25 | G13: {=_xll.EQNXTDZ($A$1,$B13,G$1)} -> 59.75 | H13: {=_xll.EQNXTDZ($A$1,$B13,H$1)} -> 56.675 | I13: {=_xll.EQNXTDZ($A$1,$B13,I$1)} -> 66.75 | J13: {=_xll.EQNXTDZ($A$1,$B13,J$1)} -> 65 | ... HH13: {=_xll.EQNXTDZ($A$1,$B13,HH$1)} -> 0
A14: High | B14: BMONTH_HIGH | C14: {=_xll.EQNXTDZ($A$1,$B14,C$1)} -> 66.875 | D14: {=_xll.EQNXTDZ($A$1,$B14,D$1)} -> 69.325 | E14: {=_xll.EQNXTDZ($A$1,$B14,E$1)} -> 61.35 | F14: {=_xll.EQNXTDZ($A$1,$B14,F$1)} -> 61.825 | G14: {=_xll.EQNXTDZ($A$1,$B14,G$1)} -> 60.75 | H14: {=_xll.EQNXTDZ($A$1,$B14,H$1)} -> 68.75 | I14: {=_xll.EQNXTDZ($A$1,$B14,I$1)} -> 66.775 | J14: {=_xll.EQNXTDZ($A$1,$B14,J$1)} -> 68.4 | ... HH14: {=_xll.EQNXTDZ($A$1,$B14,HH$1)} -> 0 | HP14: =+MAX(D14:F14) -> 69.325 | HQ14: =+MAX(G14:I14) -> 68.75 | HR14: =+MAX(J14:L14) -> 68.4 | HS14: =+MAX(M14:O14) -> 46.45 | HT14: =+MAX(P14:R14) -> 31.875 | HU14: =+MAX(S14:U14) -> 27.075 | HV14: =+MAX(V14:X14) -> 31.65 | HW14: =+MAX(Y14:AA14) -> 47.95 | HX14: =+MAX(AB14:AD14) -> 49.175 | HY14: =+MAX(AE14:AG14) -> 57.9 | HZ14: =+MAX(AH14:AJ14) -> 48.6 | IA14: =+MAX(AK14:AM14) -> 37.3 | IB14: =+MAX(AN14:AP14) -> 42.7 | IC14: =+MAX(AQ14:AS14) -> 36.825 | ID14: =+MAX(AT14:AV14) -> 32.825 | IE14: =+MAX(AW14:AY14) -> 27.8 | IF14: =+MAX(AZ14:BB14) -> 29.9 | IG14: =+MAX(BC14:BE14) -> 33.8 | IH14: =+MAX(BF14:BH14) -> 43.725 | II14: =+MAX(BI14:BK14) -> 46.175 | IJ14: =+MAX(BL14:BN14) -> 61.45 | IK14: =+MAX(BO14:BQ14) -> 71.9 | IL14: =+MAX(BR14:BT14) -> 91 | IM14: =+MAX(BU14:BW14) -> 68.35 | IN14: =+MAX(BX14:BZ14) -> 51 | IO14: =+MAX(CA14:CC14) -> 45.275 | IP14: =+MAX(CD14:CF14) -> 48.625 | IQ14: =+MAX(CG14:CI14) -> 46.35 | IR14: =+MAX(CJ14:CL14) -> 44.25 | IS14: =+MAX(CM14:CO14) -> 46.45 | IT14: =+MAX(CP14:CR14) -> 51.35 | IU14: =+MAX(CS14:CU14) -> 31.9 | IV14: =+MAX(CV14:CX14) -> 37.45 | IW14: =+MAX(CY14:DA14) -> 40.95 | IX14: =+MAX(DB14:DD14) -> 43.8 | IY14: =+MAX(DE14:DG14) -> 59.85 | IZ14: =+MAX(DH14:DJ14) -> 73.825 | JA14: =+MAX(DK14:DM14) -> 63.975 | JB14: =+MAX(DN14:DP14) -> 59.675 | JC14: =+MAX(DQ14:DS14) -> 51.1 | JD14: =+MAX(DT14:DV14) -> 46.55 | JE14: =+MAX(DW14:DY14) -> 53.9 | JF14: =+MAX(DZ14:EB14) -> 89.825 | JG14: =+MAX(EC14:EE14) -> 132.2 | JH14: =+MAX(EF14:EH14) -> 195.475 | JI14: =+MAX(EI14:EK14) -> 257.475 | JJ14: =+MAX(EL14:EN14) -> 279.15 | JK14: =MAX(EO14:EQ14) -> 299.025 | JL14: =MAX(ER14:ET14) -> 380 | JM14: =MAX(EU14:EW14) -> 383.85 | JN14: =MAX(EX14:EZ14) -> 288.35 | JO14: =MAX(FA14:FC14) -> 277.4 | JP14: =MAX(FD14:FF14) -> 244.9 | JQ14: =MAX(FG14:FI14) -> 213.5 | JR14: =MAX(FJ14:FL14) -> 211.15 | JS14: =MAX(FM14:FO14) -> 267.5 | JT14: =MAX(FP14:FR14) -> 0 | JU14: =MAX(FS14:FU14) -> 0 | JV14: =MAX(FV14:FX14) -> 0 | JW14: =MAX(FY14:GA14) -> 0 | JX14: =MAX(GB14:GD14) -> 0 | JY14: =MAX(GE14:GG14) -> 0 | JZ14: =MAX(GH14:GJ14) -> 0 | KA14: =MAX(GK14:GM14) -> 0 | KB14: =MAX(GN14:GP14) -> 0 | KC14: =MAX(GQ14:GS14) -> 0 | KD14: =MAX(GT14:GV14) -> 0 | KE14: =MAX(GW14:GY14) -> 0 | KF14: =MAX(GZ14:HB14) -> 0 | KG14: =MAX(HC14:HE14) -> 0 | KH14: =MAX(HF14:HH14) -> 0
A15: Low | B15: BMONTH_LOW | C15: {=_xll.EQNXTDZ($A$1,$B15,C$1)} -> 60.375 | D15: {=_xll.EQNXTDZ($A$1,$B15,D$1)} -> 59.275 | E15: {=_xll.EQNXTDZ($A$1,$B15,E$1)} -> 56.8 | F15: {=_xll.EQNXTDZ($A$1,$B15,F$1)} -> 55.525 | G15: {=_xll.EQNXTDZ($A$1,$B15,G$1)} -> 50.85 | H15: {=_xll.EQNXTDZ($A$1,$B15,H$1)} -> 56.675 | I15: {=_xll.EQNXTDZ($A$1,$B15,I$1)} -> 60.125 | J15: {=_xll.EQNXTDZ($A$1,$B15,J$1)} -> 53.175 | ... HH15: {=_xll.EQNXTDZ($A$1,$B15,HH$1)} -> 0 | HP15: =+MIN(D15:F15) -> 55.525 | HQ15: =+MIN(G15:I15) -> 50.85 | HR15: =+MIN(J15:L15) -> 39 | HS15: =+MIN(M15:O15) -> 24.35 | HT15: =+MIN(P15:R15) -> 18.95 | HU15: =+MIN(S15:U15) -> 21.35 | HV15: =+MIN(V15:X15) -> 23.125 | HW15: =+MIN(Y15:AA15) -> 26.55 | HX15: =+MIN(AB15:AD15) -> 35.85 | HY15: =+MIN(AE15:AG15) -> 37.25 | HZ15: =+MIN(AH15:AJ15) -> 28.125 | IA15: =+MIN(AK15:AM15) -> 25.55 | IB15: =+MIN(AN15:AP15) -> 29.25 | IC15: =+MIN(AQ15:AS15) -> 29.875 | ID15: =+MIN(AT15:AV15) -> 17.825 | IE15: =+MIN(AW15:AY15) -> 19.25 | IF15: =+MIN(AZ15:BB15) -> 22.525 | IG15: =+MIN(BC15:BE15) -> 23.275 | IH15: =+MIN(BF15:BH15) -> 27.65 | II15: =+MIN(BI15:BK15) -> 36.15 | IJ15: =+MIN(BL15:BN15) -> 41.1 | IK15: =+MIN(BO15:BQ15) -> 54.35 | IL15: =+MIN(BR15:BT15) -> 56.8 | IM15: =+MIN(BU15:BW15) -> 34.125 | IN15: =+MIN(BX15:BZ15) -> 35 | IO15: =+MIN(CA15:CC15) -> 33.8 | IP15: =+MIN(CD15:CF15) -> 37.05 | IQ15: =+MIN(CG15:CI15) -> 36.15 | IR15: =+MIN(CJ15:CL15) -> 31.55 | IS15: =+MIN(CM15:CO15) -> 35.075 | IT15: =+MIN(CP15:CR15) -> 20 | IU15: =+MIN(CS15:CU15) -> 21.9 | IV15: =+MIN(CV15:CX15) -> 27.175 | IW15: =+MIN(CY15:DA15) -> 29.1 | IX15: =+MIN(DB15:DD15) -> 34.375 | IY15: =+MIN(DE15:DG15) -> 35.325 | IZ15: =+MIN(DH15:DJ15) -> 55.15 | JA15: =+MIN(DK15:DM15) -> 46.75 | JB15: =+MIN(DN15:DP15) -> 40.125 | JC15: =+MIN(DQ15:DS15) -> 37.55 | JD15: =+MIN(DT15:DV15) -> 38.45 | JE15: =+MIN(DW15:DY15) -> 38.7 | JF15: =+MIN(DZ15:EB15) -> 51.9 | JG15: =+MIN(EC15:EE15) -> 72.575 | JH15: =+MIN(EF15:EH15) -> 128.6 | JI15: =+MIN(EI15:EK15) -> 164.875 | JJ15: =+MIN(EL15:EN15) -> 189.4 | JK15: =MIN(EO15:EQ15) -> 220.025 | JL15: =MIN(ER15:ET15) -> 263 | JM15: =MIN(EU15:EW15) -> 280.15 | JN15: =MIN(EX15:EZ15) -> 217.65 | JO15: =MIN(FA15:FC15) -> 199.75 | JP15: =MIN(FD15:FF15) -> 196.1 | JQ15: =MIN(FG15:FI15) -> 153.2 | JR15: =MIN(FJ15:FL15) -> 154.1 | JS15: =MIN(FM15:FO15) -> 184.4 | JT15: =MIN(FP15:FR15) -> 0 | JU15: =MIN(FS15:FU15) -> 0 | JV15: =MIN(FV15:FX15) -> 0 | JW15: =MIN(FY15:GA15) -> 0 | JX15: =MIN(GB15:GD15) -> 0 | JY15: =MIN(GE15:GG15) -> 0 | JZ15: =MIN(GH15:GJ15) -> 0 | KA15: =MIN(GK15:GM15) -> 0 | KB15: =MIN(GN15:GP15) -> 0 | KC15: =MIN(GQ15:GS15) -> 0 | KD15: =MIN(GT15:GV15) -> 0 | KE15: =MIN(GW15:GY15) -> 0 | KF15: =MIN(GZ15:HB15) -> 0 | KG15: =MIN(HC15:HE15) -> 0 | KH15: =MIN(HF15:HH15) -> 0
A16: Close | B16: BMONTH_CLOSE | C16: {=_xll.EQNXTDZ($A$1,$B16,C$1)} -> 66.175 | D16: {=_xll.EQNXTDZ($A$1,$B16,D$1)} -> 59.925 | E16: {=_xll.EQNXTDZ($A$1,$B16,E$1)} -> 59.275 | F16: {=_xll.EQNXTDZ($A$1,$B16,F$1)} -> 59.25 | G16: {=_xll.EQNXTDZ($A$1,$B16,G$1)} -> 57 | H16: {=_xll.EQNXTDZ($A$1,$B16,H$1)} -> 65.825 | I16: {=_xll.EQNXTDZ($A$1,$B16,I$1)} -> 64.3 | J16: {=_xll.EQNXTDZ($A$1,$B16,J$1)} -> 54.5 | ... HH16: {=_xll.EQNXTDZ($A$1,$B16,HH$1)} -> 0 | HP16: =+F16 -> 59.25 | HQ16: =+I16 -> 64.3 | HR16: =+L16 -> 41.05 | HS16: =+O16 -> 28.65 | HT16: =+R16 -> 22.175 | HU16: =+U16 -> 24.525 | HV16: =+X16 -> 28.3 | HW16: =+AA16 -> 41.675 | HX16: =+AD16 -> 40.35 | HY16: =+AG16 -> 46.7 | HZ16: =+AJ16 -> 32.85 | IA16: =+AM16 -> 29.3 | IB16: =+AP16 -> 31.85 | IC16: =+AS16 -> 31.25 | ID16: =+AV16 -> 19.275 | IE16: =+AY16 -> 26.65 | IF16: =+BB16 -> 27.35 | IG16: =+BE16 -> 27.6 | IH16: =+BH16 -> 41.7 | II16: =+BK16 -> 41.975 | IJ16: =+BN16 -> 56.3 | IK16: =+BQ16 -> 70 | IL16: =+BT16 -> 59.5 | IM16: =+BW16 -> 39.7 | IN16: =+BZ16 -> 36.4 | IO16: =+CC16 -> 42.35 | IP16: =+CF16 -> 43.275 | IQ16: =+CI16 -> 41.625 | IR16: =+CL16 -> 42.8 | IS16: =+CO16 -> 36.55 | IT16: =+CR16 -> 22.9 | IU16: =+CU16 -> 28.95 | IV16: =+CX16 -> 31.475 | IW16: =+DA16 -> 37.925 | IX16: =+DD16 -> 37.075 | IY16: =+DG16 -> 58.475 | IZ16: =+DJ16 -> 57.025 | JA16: =+DM16 -> 49.45 | JB16: =+DP16 -> 45.025 | JC16: =+DS16 -> 39.375 | JD16: =+DV16 -> 41.275 | JE16: =+DY16 -> 51.8 | JF16: =+EB16 -> 72.775 | JG16: =+EE16 -> 127.775 | JH16: =+EH16 -> 173.25 | JI16: =+EK16 -> 206 | JJ16: =+EN16 -> 216.05 | JK16: =EQ16 -> 271.725 | JL16: =ET16 -> 371.75 | JM16: =EW16 -> 291.25 | JN16: =EZ16 -> 270.1 | JO16: =FC16 -> 240.75 | JP16: =FF16 -> 202.6 | JQ16: =FI16 -> 168 | JR16: =FL16 -> 183.25 | JS16: =FO16 -> 247.8 | JT16: =FR16 -> 0 | JU16: =FU16 -> 0 | JV16: =FX16 -> 0 | JW16: =GA16 -> 0 | JX16: =GD16 -> 0 | JY16: =GG16 -> 0 | JZ16: =GJ16 -> 0 | KA16: =GM16 -> 0 | KB16: =GP16 -> 0 | KC16: =GS16 -> 0 | KD16: =GV16 -> 0 | KE16: =GY16 -> 0 | KF16: =HB16 -> 0 | KG16: =HE16 -> 0 | KH16: =HH16 -> 0
A19: High | HP19: =+IF(HP14=0,HP7,HP14) -> 69.325 | HQ19: =+IF(HQ14=0,HQ7,HQ14) -> 68.75 | HR19: =+IF(HR14=0,HR7,HR14) -> 68.4 | HS19: =+IF(HS14=0,HS7,HS14) -> 46.45 | HT19: =+IF(HT14=0,HT7,HT14) -> 31.875 | HU19: =+IF(HU14=0,HU7,HU14) -> 27.075 | HV19: =+IF(HV14=0,HV7,HV14) -> 31.65 | HW19: =+IF(HW14=0,HW7,HW14) -> 47.95 | ... KH19: =+IF(KH14=0,KH7,KH14) -> 0
A20: Low | HP20: =+IF(HP15=0,HP8,HP15) -> 55.525 | HQ20: =+IF(HQ15=0,HQ8,HQ15) -> 50.85 | HR20: =+IF(HR15=0,HR8,HR15) -> 39 | HS20: =+IF(HS15=0,HS8,HS15) -> 24.35 | HT20: =+IF(HT15=0,HT8,HT15) -> 18.95 | HU20: =+IF(HU15=0,HU8,HU15) -> 21.35 | HV20: =+IF(HV15=0,HV8,HV15) -> 23.125 | HW20: =+IF(HW15=0,HW8,HW15) -> 26.55 | ... KH20: =+IF(KH15=0,KH8,KH15) -> 0
A21: Close | HP21: =+IF(HP16=0,HP9,HP16) -> 59.25 | HQ21: =+IF(HQ16=0,HQ9,HQ16) -> 64.3 | HR21: =+IF(HR16=0,HR9,HR16) -> 41.05 | HS21: =+IF(HS16=0,HS9,HS16) -> 28.65 | HT21: =+IF(HT16=0,HT9,HT16) -> 22.175 | HU21: =+IF(HU16=0,HU9,HU16) -> 24.525 | HV21: =+IF(HV16=0,HV9,HV16) -> 28.3 | HW21: =+IF(HW16=0,HW9,HW16) -> 41.675 | ... KH21: =+IF(KH16=0,KH9,KH16) -> 0

Sheet QTR No. of Shares
A1: ='QTR Raw'!A1 -> 100378 | C1: 201206 | D1: 201209 | E1: 201212 | F1: 201303 | G1: 201306 | H1: 201309 | I1: 201312 | J1: 201403 | K1: 201406 | L1: 201409 | M1: 201412 | N1: 201503 | O1: 201506 | P1: 201509 | Q1: 201512 | R1: 201603 | S1: 201606 | T1: 201609 | U1: 201612 | V1: 201703 | W1: 201706 | X1: 201709 | Y1: 201712 | Z1: 201803 | AA1: 201806 | AB1: 201809 | AC1: 201812 | AD1: 201903 | AE1: 201906 | AF1: 201909 | AG1: 201912 | AH1: 202003 | AI1: 202006 | AJ1: 202009 | AK1: 202012 | AL1: 202103 | AM1: 202106 | AN1: 202109 | AO1: 202112 | AP1: 202203 | AQ1: 202206 | AR1: 202209 | AS1: 202212 | AT1: 202303 | AU1: 202306 | AV1: 202309 | AW1: 202312 | AX1: 202403 | AY1: 202406
A4: Field Description | B4: Field Name
A5: Date End | B5: SHP_DATE_END | C5: {=_xll.EQNXTDZ($A$1,$B5,C$1)} -> 201206 | D5: {=_xll.EQNXTDZ($A$1,$B5,D$1)} -> 201209 | E5: {=_xll.EQNXTDZ($A$1,$B5,E$1)} -> 201212 | F5: {=_xll.EQNXTDZ($A$1,$B5,F$1)} -> 201303 | G5: {=_xll.EQNXTDZ($A$1,$B5,G$1)} -> 201306 | H5: {=_xll.EQNXTDZ($A$1,$B5,H$1)} -> 201309 | I5: {=_xll.EQNXTDZ($A$1,$B5,I$1)} -> 201312 | J5: {=_xll.EQNXTDZ($A$1,$B5,J$1)} -> 201403 | ... AY5: {=_xll.EQNXTDZ($A$1,$B5,AY$1)} -> 202406
A6: Grand Total | B6: SHP_NSGRANDTOTAL | C6: {=_xll.EQNXTDZ($A$1,$B6,C$1)} -> 276223521 | D6: {=_xll.EQNXTDZ($A$1,$B6,D$1)} -> 276227521 | E6: {=_xll.EQNXTDZ($A$1,$B6,E$1)} -> 276223521 | F6: {=_xll.EQNXTDZ($A$1,$B6,F$1)} -> 276223521 | G6: {=_xll.EQNXTDZ($A$1,$B6,G$1)} -> 276223521 | H6: {=_xll.EQNXTDZ($A$1,$B6,H$1)} -> 276223521 | I6: {=_xll.EQNXTDZ($A$1,$B6,I$1)} -> 276223521 | J6: {=_xll.EQNXTDZ($A$1,$B6,J$1)} -> 276223521 | ... AY6: {=_xll.EQNXTDZ($A$1,$B6,AY$1)} -> 319754117
B7: In Crs. | C7: =+C6/10^7 -> 27.622352 | D7: =+D6/10^7 -> 27.622752 | E7: =+E6/10^7 -> 27.622352 | F7: =+F6/10^7 -> 27.622352 | G7: =+G6/10^7 -> 27.622352 | H7: =+H6/10^7 -> 27.622352 | I7: =+I6/10^7 -> 27.622352 | J7: =+J6/10^7 -> 27.622352 | ... AY7: =+AY6/10^7 -> 31.975412

Sheet Share price Daily
A1: =_xll.EQNXTH(B1,"[ADJC];[ADJH];[ADJL];[ADJO];[UCLS];[VOLUME]","2015-Jan-01","Y","All traded days","Asc") -> EQNXTH | B1: =+'Annual Raw'!A1 -> 100378 | L1: =_xll.EQNXTH(B1,"[NADJC];[NADJH];[NADJLOW];[NADJOPEN];[NUCLOSE];[NVOLUME]","2015-Jan-01","Y","All traded days","Asc") -> EQNXTH
A2: Jindal Saw Ltd. | L2: Jindal Saw Ltd.
A3: DATE | B3: ADJHIGH | C3: ADJCLOSE | D3: ADJLOW | E3: ADJOPEN | F3: CLOSE | G3: VOLUME | L3: DATE | M3: ADJCLOSE | N3: ADJHIGH | O3: ADJLOW | P3: ADJOPEN | Q3: CLOSE | R3: VOLUME
A4: 42005 | B4: 47.925 | C4: 47.125 | D4: 45.85 | E4: 46.675 | F4: 94.25 | G4: 426831 | L4: 42005 | M4: 47 | N4: 47.925 | O4: 45.775 | P4: 46.5 | Q4: 94 | R4: 1780714
A5: 42006 | B5: 48.425 | C5: 47.55 | D5: 46.65 | E5: 46.65 | F5: 95.1 | G5: 661400 | L5: 42006 | M5: 47.55 | N5: 48.4 | O5: 47.05 | P5: 47.35 | Q5: 95.1 | R5: 1857096
A6: 42009 | B6: 48.6 | C6: 46.575 | D6: 46.4 | E6: 47.75 | F6: 93.15 | G6: 478076 | L6: 42009 | M6: 46.475 | N6: 48.6 | O6: 46.3 | P6: 47.5 | Q6: 92.95 | R6: 2489709
A7: 42010 | B7: 46.225 | C7: 44.5 | D7: 44.275 | E7: 46.225 | F7: 89 | G7: 424046 | L7: 42010 | M7: 44.35 | N7: 46.225 | O7: 44.1 | P7: 46.225 | Q7: 88.7 | R7: 1287116
A8: 42011 | B8: 45.325 | C8: 43.325 | D8: 43.1 | E8: 45.325 | F8: 86.65 | G8: 469501 | L8: 42011 | M8: 43.3 | N8: 44.775 | O8: 43.025 | P8: 44.725 | Q8: 86.6 | R8: 1109173
A9: 42012 | B9: 45.25 | C9: 44.6 | D9: 43.625 | E9: 43.625 | F9: 89.2 | G9: 510437 | L9: 42012 | M9: 44.675 | N9: 45.2 | O9: 43.675 | P9: 43.75 | Q9: 89.35 | R9: 1274220
A10: 42013 | B10: 45.9 | C10: 44.375 | D10: 43.725 | E10: 44.875 | F10: 88.75 | G10: 495601 | L10: 42013 | M10: 44.425 | N10: 45.875 | O10: 43.625 | P10: 45.05 | Q10: 88.85 | R10: 1738097
A11: 42016 | B11: 45.075 | C11: 44.275 | D11: 44.05 | E11: 44.6 | F11: 88.55 | G11: 331060 | L11: 42016 | M11: 44.3 | N11: 45 | O11: 43.95 | P11: 44.65 | Q11: 88.6 | R11: 1014250
A12: 42017 | B12: 44.75 | C12: 43.175 | D12: 43 | E12: 44.5 | F12: 86.35 | G12: 300521 | L12: 42017 | M12: 43.175 | N12: 44.725 | O12: 43.025 | P12: 44.35 | Q12: 86.35 | R12: 683656
A13: 42018 | B13: 43.425 | C13: 41.475 | D13: 41.175 | E13: 43.425 | F13: 82.95 | G13: 455501 | L13: 42018 | M13: 41.45 | N13: 43.425 | O13: 41.125 | P13: 43.1 | Q13: 82.9 | R13: 941180
A14: 42019 | B14: 42.55 | C14: 41.575 | D14: 41.25 | E14: 41.75 | F14: 83.15 | G14: 323199 | L14: 42019 | M14: 41.625 | N14: 42.475 | O14: 41.3 | P14: 42.05 | Q14: 83.25 | R14: 914616
A15: 42020 | B15: 43.35 | C15: 42.1 | D15: 41.375 | E15: 41.5 | F15: 84.2 | G15: 581785 | L15: 42020 | M15: 42.1 | N15: 43.4 | O15: 41.35 | P15: 41.55 | Q15: 84.2 | R15: 1455966
... A2841: 46190 | B2841: 259.2 | C2841: 258.15 | D2841: 244.65 | E2841: 248.8 | F2841: 258.15 | G2841: 139681 | L2841: 46190 | M2841: 258.48 | N2841: 259.45 | O2841: 244.51 | P2841: 249.45 | Q2841: 258.48 | R2841: 2835731

Sheet Sheet2
J19: 219.3 | K19: 186.25 | L19: 186.75
J20: 192.9 | K20: 135.5 | L20: 146.9 | N20: 219.3 | O20: 192.9 | P20: 186 | Q20: 178.7 | R20: 207 | S20: 255.15 | T20: 348.25 | U20: 374 | V20: 495.9 | W20: 659.9 | X20: 613.4 | Y20: 607.9 | Z20: 555.95 | AA20: 497.8 | AB20: 459.9 | AC20: 374 | AD20: 362 | AE20: 341.5 | AF20: 384.2 | AG20: 433.8 | AH20: 460 | AI20: 474.4 | AJ20: 414.4 | AK20: 318.7 | AL20: 303.25 | AM20: 332.7 | AN20: 295 | AO20: 247 | AP20: 214.4 | AQ20: 179.5 | AR20: 97.9 | AS20: 119.1 | AT20: 130.65 | AU20: 148.55 | AV20: 153.8 | AW20: 152.9 | AX20: 136 | AY20: 141.15 | AZ20: 128.1 | BA20: 142.5 | BB20: 143.55 | BC20: 124.5 | BD20: 241 | BE20: 450 | BF20: 503.35
J21: 186 | K21: 145.4 | L21: 169.1 | N21: 186.25 | O21: 135.5 | P21: 145.4 | Q21: 108.95 | R21: 137 | S21: 170 | T21: 243.15 | U21: 307.5 | V21: 325.1 | W21: 463 | X21: 467.05 | Y21: 436.5 | Z21: 467 | AA21: 348.2 | AB21: 325 | AC21: 313.1 | AD21: 285 | AE21: 277.85 | AF21: 327 | AG21: 317 | AH21: 370.7 | AI21: 360 | AJ21: 271.15 | AK21: 233.15 | AL21: 218.8 | AM21: 262 | AN21: 223.6 | AO21: 137.6 | AP21: 142 | AQ21: 59.3 | AR21: 58 | AS21: 72.8 | AT21: 80 | AU21: 107.25 | AV21: 106 | AW21: 125.1 | AX21: 112.25 | AY21: 81.45 | AZ21: 88 | BA21: 90.35 | BB21: 106.05 | BC21: 98.55 | BD21: 119.25 | BE21: 210 | BF21: 349
J22: 178.7 | K22: 108.95 | L22: 139.75 | N22: 186.75 | O22: 146.9 | P22: 169.1 | Q22: 139.75 | R22: 202.15 | S22: 249.05 | T22: 346.4 | U22: 349.2 | V22: 469.9 | W22: 584.8 | X22: 536.15 | Y22: 513.35 | Z22: 474 | AA22: 438.55 | AB22: 355.4 | AC22: 334.95 | AD22: 298.8 | AE22: 328.35 | AF22: 343 | AG22: 389.9 | AH22: 443.05 | AI22: 407.5 | AJ22: 290.1 | AK22: 235.75 | AL22: 292.65 | AM22: 276.1 | AN22: 237.05 | AO22: 190.1 | AP22: 147.2 | AQ22: 71.9 | AR22: 75.2 | AS22: 90.1 | AT22: 117.2 | AU22: 116.3 | AV22: 140.5 | AW22: 128.6 | AX22: 133.65 | AY22: 91.65 | AZ22: 97.65 | BA22: 125 | BB22: 115.35 | BC22: 119.25 | BD22: 219.3 | BE22: 442.65 | BF22: 503.35
J23: 207 | K23: 137 | L23: 202.15
J24: 255.15 | K24: 170 | L24: 249.05
J25: 348.25 | K25: 243.15 | L25: 346.4
J26: 374 | K26: 307.5 | L26: 349.2
J27: 495.9 | K27: 325.1 | L27: 469.9
J28: 659.9 | K28: 463 | L28: 584.8
J29: 613.4 | K29: 467.05 | L29: 536.15
J30: 607.9 | K30: 436.5 | L30: 513.35
J31: 555.95 | K31: 467 | L31: 474
J32: 497.8 | K32: 348.2 | L32: 438.55
J33: 459.9 | K33: 325 | L33: 355.4
J34: 374 | K34: 313.1 | L34: 334.95
... J63: 503.35 | K63: 349 | L63: 503.35
