Workbook

Sheet Template
A1: =+'Annual Raw'!C4 -> John Cockerill India Ltd | B1: 36951 | C1: =EOMONTH(B1,12) -> 37346 | D1: 37591 | E1: =EOMONTH(D1,12) -> 37986 | F1: =EOMONTH(E1,12) -> 38352 | G1: =EOMONTH(F1,12) -> 38717 | H1: =EOMONTH(G1,12) -> 39082 | I1: =EOMONTH(H1,12) -> 39447 | J1: =EOMONTH(I1,12) -> 39813 | K1: =EOMONTH(J1,12) -> 40178 | L1: =EOMONTH(K1,12) -> 40543 | ... AE1: =EOMONTH(AD1,12) -> 47483 | AH1: QTR | AI1: 41061 | AJ1: 41153 | AK1: 41244 | AL1: 41334 | AM1: 41426 | AN1: 41518 | AO1: 41609 | AP1: 41699 | AQ1: 41791 | AR1: 41883 | AS1: 41974 | AT1: 42064 | AU1: 42156 | AV1: 42248 | AW1: 42339 | AX1: 42430 | AY1: 42522 | AZ1: 42614 | BA1: 42705 | BB1: 42795 | BC1: 42887 | BD1: 42979 | BE1: 43070 | BF1: 43160 | BG1: 43252 | BH1: 43344 | BI1: 43435 | BJ1: 43525 | BK1: 43617 | BL1: 43709 | BM1: 43800 | BN1: 43891 | BO1: 43983 | BP1: 44075 | BQ1: =EOMONTH(BP1,3) -> 44196 | BR1: =EOMONTH(BQ1,3) -> 44286 | BS1: =EOMONTH(BR1,3) -> 44377 | BT1: =EOMONTH(BS1,3) -> 44469 | BU1: =EOMONTH(BT1,3) -> 44561 | BV1: =EOMONTH(BU1,3) -> 44651 | BW1: =EOMONTH(BV1,3) -> 44742 | BX1: =EOMONTH(BW1,3) -> 44834 | ... DA1: =EOMONTH(CZ1,3) -> 47483 | DC1: historical estimates | DD1: 46022
A2: Presentation Data (Start)
A4: Order Book
A5: Opening | T5: =S8 -> 0 | U5: =T8 -> 0 | V5: =U8 -> 0 | W5: =V8 -> 0 | X5: =W8 -> 0 | Y5: =X8 -> 0 | Z5: =Y8 -> 1000 | AA5: =Z8 -> 680.8 | ... AE5: =AD8 -> 9133.5717 | CH5: =CG8 -> 680.8 | CI5: =CH8 -> 683 | CJ5: =CI8 -> 680 | CK5: =CJ8 -> 1129.1 | CL5: =CK8 -> 1186.9 | CM5: =CL8 -> 3300 | CN5: =CM8 -> 5073 | CO5: =CN8 -> 5271.7308 | ... DA5: =CZ8 -> 11866.42
A6: Addition | T6: =T8+T7-T5 -> 0 | U6: =U8+U7-U5 -> 0 | V6: =V8+V7-V5 -> 0 | W6: =W8+W7-W5 -> 0 | X6: =X8+X7-X5 -> 0 | Y6: =Y8+Y7-Y5 -> 1666.6143 | Z6: =Z8+Z7-Z5 -> 69.526 | AA6: =AA8+AA7-AA5 -> 863.6948 | ... AE6: =AE8+AE7-AE5 -> 6022.8067 | CH6: =CH8+CH7-CH5 -> 223.1 | CI6: =CI8+CI7-CI5 -> 79.118 | CJ6: =CJ8+CJ7-CJ5 -> 546.084 | CK6: =CK8+CK7-CK5 -> 286.2109 | CL6: =CL8+CL7-CL5 -> 2457.617 | CM6: =300+470+1300 -> 2070 | CN6: =CJ6*(1+CN12) -> 655.3008 | CO6: =CK6*(1+CO12) -> 343.45308 | CP6: 500 | CQ6: =CM6*(1+CQ12) -> 2484 | CR6: =CN6*(1+CR12) -> 786.36096 | CS6: =CO6*(1+CS12) -> 412.1437 | CT6: =CP6*(1+CT12) -> 600 | CU6: =CQ6*(1+CU12) -> 2980.8 | CV6: =CR6*(1+CV12) -> 943.63315 | CW6: =CS6*(1+CW12) -> 494.57244 | CX6: =CT6*(1+CX12) -> 720 | ... DA6: =CW6*(1+DA12) -> 593.48692
A7: Executed | T7: =T27 -> 0 | U7: =U27 -> 0 | V7: =V27 -> 0 | W7: =W27 -> 0 | X7: =X27 -> 0 | Y7: =Y27 -> 666.6143 | Z7: =Z27 -> 388.726 | AA7: =AA27 -> 357.5948 | ... AE7: =AE27 -> 3764.4492 | CG7: =CG27 -> 72.339 | CH7: =CH27 -> 220.9 | CI7: =CI27 -> 82.118 | CJ7: =CJ27 -> 96.984 | CK7: =CK27 -> 228.4109 | CL7: =CL27 -> 344.517 | CM7: =CM5*CM13 -> 297 | CN7: =CN5*CN13 -> 456.57 | CO7: =CO5*CO13 -> 474.45577 | CP7: =CP5*CP13 -> 462.66553 | CQ7: =CQ5*CQ13 -> 466.02563 | CR7: =CR5*CR13 -> 647.64333 | CS7: =CS5*CS13 -> 660.12791 | CT7: =CT5*CT13 -> 637.80933 | ... DA7: =DA5*DA13 -> 1067.9778
A8: Closing | Y8: 1000 | Z8: =CG8 -> 680.8 | AA8: =CK8 -> 1186.9 | AB8: =CO8 -> 5140.7281 | AC8: =CS8 -> 7086.7704 | AD8: =CW8 -> 9133.5717 | AE8: =DA8 -> 11391.929 | CG8: 680.8 | CH8: 683 | CI8: 680 | CJ8: 1129.1 | CK8: 1186.9 | CL8: 3300 | CM8: =CM5+CM6-CM7 -> 5073 | CN8: =CN5+CN6-CN7 -> 5271.7308 | CO8: =CO5+CO6-CO7 -> 5140.7281 | CP8: =CP5+CP6-CP7 -> 5178.0626 | CQ8: =CQ5+CQ6-CQ7 -> 7196.0369 | CR8: =CR5+CR6-CR7 -> 7334.7546 | CS8: =CS5+CS6-CS7 -> 7086.7704 | CT8: =CT5+CT6-CT7 -> 7048.961 | ... DA8: =DA5+DA6-DA7 -> 11391.929
A9: OB to Mkt cap | Y9: =+(Y96*Y84)/Y8 -> #DIV/0! | Z9: =+(Z96*Z84)/Z8 -> #DIV/0! | AA9: =+(AA96*AA84)/AA8 -> #DIV/0! | CG9: =+(CG96*CG84)/CG8 -> 3.0351147 | CH9: =+(CH96*CH84)/CH8 -> 2.0793101 | CI9: =+(CI96*CI84)/CI8 -> 2.4923103 | CJ9: =+(CJ96*CJ84)/CJ8 -> 2.5922641 | CK9: =+(CK96*CK84)/CK8 -> 2.1921034 | CL9: =+(CL96*CL84)/CL8 -> 0.61084556 | CM9: =+(CM96*CM84)/CM8 -> 0.79237004 | CN9: =+(CN96*CN84)/CN8 -> 0.76249971
CM10: =+CM8*2.5 -> 12682.5
A11: OB YoY growth % | Z11: =Z8/Y8-1 -> -0.3192 | AA11: =AA8/Z8-1 -> 0.74339013 | AB11: =AB8/AA8-1 -> 3.3312226 | AC11: =AC8/AB8-1 -> 0.37855382 | AD11: =AD8/AC8-1 -> 0.28882004 | AE11: =AE8/AD8-1 -> 0.24725897 | CK11: =CK8/CG8-1 -> 0.74339013
A12: Addition YoY Growth % | Z12: =Z6/Y6-1 -> -0.95828309 | AA12: =AA6/Z6-1 -> 11.422616 | AB12: =AB6/AA6-1 -> 5.3985228 | AC12: =AC6/AB6-1 -> -0.24317337 | AD12: =AD6/AC6-1 -> 0.2 | AE12: =AE6/AD6-1 -> 0.2 | CL12: =CL6/CH6-1 -> 10.015764 | CM12: =CM6/CI6-1 -> 25.163452 | CN12: 0.2 | CO12: =CN12 -> 0.2 | CP12: =+CP6/CL6-1 -> -0.79655089 | CQ12: 0.2 | CR12: 0.2 | CS12: 0.2 | CT12: 0.2 | CU12: 0.2 | CV12: 0.2 | CW12: 0.2 | CX12: 0.2 | CY12: 0.2 | CZ12: 0.2 | DA12: 0.2
A13: Execution % | Z13: =Z7/Z5 -> 0.388726 | AA13: =AA7/AA5 -> 0.52525676 | AB13: =AB7/AB5 -> 1.324916 | AC13: =AC7/AC5 -> 0.43504779 | AD13: =AD7/AD5 -> 0.4194018 | AE13: =AE7/AE5 -> 0.41215521 | CH13: =CH7/CH5 -> 0.32447121 | CI13: =CI7/CI5 -> 0.12023133 | CJ13: =CJ7/CJ5 -> 0.14262353 | CK13: =CK7/CK5 -> 0.20229466 | CL13: =CL7/CL5 -> 0.29026624 | CM13: 0.09 | CN13: 0.09 | CO13: 0.09 | CP13: 0.09 | CQ13: 0.09 | CR13: 0.09 | CS13: 0.09 | CT13: 0.09 | CU13: 0.09 | CV13: 0.09 | CW13: 0.09 | CX13: 0.09 | CY13: 0.09 | CZ13: 0.09 | DA13: 0.09
A15: Standalone sales | AA15: 357.5948 | CH15: 76.4243 | CK15: 102.0693 | CL15: 200.0443
A16: Standalone EBIDTA | AA16: =22.763+3.0328+6.1507-9.0317 -> 22.9148 | CH16: =-1.02+1.5086+0.4225-1.3543 -> -0.4432 | CK16: =9.5493+1.5585+1.6721-2.6706 -> 10.1093 | CL16: =7.5045+5.1412+1.5615-2.8007 -> 11.4065
A17: Standalone PAT | AA17: 10.3139 | CH17: 0.7461 | CK17: 0.4211 | CL17: =7.0068 -> 7.0068
A19: Subsidiary sales | AA19: =AA27-AA15 -> 0 | CH19: =CH27-CH15 -> 144.4757 | CK19: =CK27-CK15 -> 126.3416 | CL19: =CL27-CL15 -> 144.4727
A20: Subsidiary EBIDTA | AA20: =AA47-AA16 -> -0.4746 | CH20: =CH47-CH16 -> -1.0478 | CK20: =CK47-CK16 -> -29.7676 | CL20: =CL47-CL16 -> -6.4945
A21: Subsidiary PAT | AA21: =AA67-AA17 -> 0 | CH21: =CH67-CH17 -> -3.6601 | CK21: =CK67-CK17 -> -9.3434 | CL21: =CL67-CL17 -> 0.3542
A23: Other Exp | AA23: =+AA41/AA29 -> 0.11922265 | CI23: =+CI41/CI29 -> 0.74894664 | CJ23: =+CJ41/CJ29 -> 0.76354863 | CK23: =+CK41/CK29 -> 0.33480495 | CL23: =+CL41/CL29 -> 0.33005628 | CM23: =+CL23 -> 0.33005628 | CN23: =+CM23-0.5% -> 0.32505628 | CO23: =+CN23-0.5% -> 0.32005628 | CP23: =+CO23-0.5% -> 0.31505628 | CQ23: =+CP23-0.5% -> 0.31005628 | CR23: =+CQ23-0.5% -> 0.30505628 | CS23: =+CR23-0.5% -> 0.30005628 | CT23: =+CS23-0.5% -> 0.29505628 | CU23: =+CT23-0.5% -> 0.29005628 | ... DA23: =+CZ23-0.5% -> 0.26005628
A25: Presentation Data (End)
A26: Profit & Loss- Annual (Start)
A27: Gross Revenue | B27: ='Annual Raw'!C6 -> 94.467588 | C27: ='Annual Raw'!D6 -> 127.52504 | D27: ='Annual Raw'!E6 -> 0 | E27: ='Annual Raw'!F6 -> 0 | F27: ='Annual Raw'!G6 -> 0 | G27: ='Annual Raw'!H6 -> 0 | H27: ='Annual Raw'!I6 -> 0 | I27: ='Annual Raw'!J6 -> 0 | ... AA27: ='Annual Raw'!AB6 -> 357.5948 | AB27: =+SUM(CL27:CO27) -> 1572.5428 | AC27: =+SUM(CP27:CS27) -> 2236.4624 | AD27: =+SUM(CT27:CW27) -> 2972.2043 | AE27: =+SUM(CX27:DA27) -> 3764.4492 | AI27: ='QTR Raw'!C6+'QTR Raw'!C8 -> 92.71 | AJ27: ='QTR Raw'!D6+'QTR Raw'!D8 -> 110.46 | AK27: ='QTR Raw'!E6+'QTR Raw'!E8 -> 194.452 | AL27: ='QTR Raw'!F6+'QTR Raw'!F8 -> 135.274 | AM27: ='QTR Raw'!G6+'QTR Raw'!G8 -> 101.785 | AN27: ='QTR Raw'!H6+'QTR Raw'!H8 -> 122.009 | AO27: ='QTR Raw'!I6+'QTR Raw'!I8 -> 126.378 | AP27: ='QTR Raw'!J6+'QTR Raw'!J8 -> 92.661 | ... CJ27: ='QTR Raw'!BD6+'QTR Raw'!BD8 -> 96.984 | CK27: 228.4109 | CL27: ='QTR Raw'!BF6+'QTR Raw'!BF8 -> 344.517 | CM27: =CM7 -> 297 | CN27: =CN7 -> 456.57 | CO27: =CO7 -> 474.45577 | CP27: =CP7 -> 462.66553 | CQ27: =CQ7 -> 466.02563 | CR27: =CR7 -> 647.64333 | CS27: =CS7 -> 660.12791 | CT27: =CT7 -> 637.80933 | ... DA27: =DA7 -> 1067.9778 | DD27: 53.536827 | DE27: 279.9248
A28: Less: Exise Duty | B28: ='Annual Raw'!C7+'Annual Raw'!C8+'Annual Raw'!C9 -> 9.8270536 | C28: ='Annual Raw'!D7+'Annual Raw'!D8+'Annual Raw'!D9 -> 4.5848681 | D28: ='Annual Raw'!E7+'Annual Raw'!E8+'Annual Raw'!E9 -> 0 | E28: ='Annual Raw'!F7+'Annual Raw'!F8+'Annual Raw'!F9 -> 0 | F28: ='Annual Raw'!G7+'Annual Raw'!G8+'Annual Raw'!G9 -> 0 | G28: ='Annual Raw'!H7+'Annual Raw'!H8+'Annual Raw'!H9 -> 0 | H28: ='Annual Raw'!I7+'Annual Raw'!I8+'Annual Raw'!I9 -> 0 | I28: ='Annual Raw'!J7+'Annual Raw'!J8+'Annual Raw'!J9 -> 0 | ... AA28: ='Annual Raw'!AB7+'Annual Raw'!AB8+'Annual Raw'!AB9 -> 0 | AB28: =+SUM(CL28:CO28) -> 0 | AC28: =+SUM(CP28:CS28) -> 0 | AD28: =+SUM(CT28:CW28) -> 0 | AE28: =+SUM(CX28:DA28) -> 0 | AI28: ='QTR Raw'!C21+'QTR Raw'!C20+'QTR Raw'!C19+'QTR Raw'!C13+'QTR Raw'!C7 -> 0 | AJ28: ='QTR Raw'!D21+'QTR Raw'!D20+'QTR Raw'!D19+'QTR Raw'!D13+'QTR Raw'!D7 -> 0 | AK28: ='QTR Raw'!E21+'QTR Raw'!E20+'QTR Raw'!E19+'QTR Raw'!E13+'QTR Raw'!E7 -> 0 | AL28: ='QTR Raw'!F21+'QTR Raw'!F20+'QTR Raw'!F19+'QTR Raw'!F13+'QTR Raw'!F7 -> 2.818 | AM28: ='QTR Raw'!G21+'QTR Raw'!G20+'QTR Raw'!G19+'QTR Raw'!G13+'QTR Raw'!G7 -> 0 | AN28: ='QTR Raw'!H21+'QTR Raw'!H20+'QTR Raw'!H19+'QTR Raw'!H13+'QTR Raw'!H7 -> 0 | AO28: ='QTR Raw'!I21+'QTR Raw'!I20+'QTR Raw'!I19+'QTR Raw'!I13+'QTR Raw'!I7 -> 0 | AP28: ='QTR Raw'!J21+'QTR Raw'!J20+'QTR Raw'!J19+'QTR Raw'!J13+'QTR Raw'!J7 -> 12.888 | ... CL28: ='QTR Raw'!BF21+'QTR Raw'!BF20+'QTR Raw'!BF19+'QTR Raw'!BF13+'QTR Raw'!BF7 -> 0 | DD28: 0
A29: Net Revenue | B29: =+B27-B28 -> 84.640534 | C29: =+C27-C28 -> 122.94017 | D29: =+D27-D28 -> 0 | E29: =+E27-E28 -> 0 | F29: =+F27-F28 -> 0 | G29: =+G27-G28 -> 0 | H29: =+H27-H28 -> 0 | I29: =+I27-I28 -> 0 | ... AE29: =+AE27-AE28 -> 3764.4492 | AI29: =+AI27-AI28 -> 92.71 | AJ29: =+AJ27-AJ28 -> 110.46 | AK29: =+AK27-AK28 -> 194.452 | AL29: =+AL27-AL28 -> 132.456 | AM29: =+AM27-AM28 -> 101.785 | AN29: =+AN27-AN28 -> 122.009 | AO29: =+AO27-AO28 -> 126.378 | AP29: =+AP27-AP28 -> 79.773 | ... DA29: =+DA27-DA28 -> 1067.9778 | DD29: 53.536827 | DE29: 279.9248
A30: Net Revenue YOY% | C30: =C29/B29-1 -> 0.45249761 | D30: =D29/C29-1 -> -1 | E30: =E29/D29-1 -> #DIV/0! | F30: =F29/E29-1 -> #DIV/0! | G30: =G29/F29-1 -> #DIV/0! | H30: =H29/G29-1 -> #DIV/0! | I30: =I29/H29-1 -> #DIV/0! | J30: =J29/I29-1 -> #DIV/0! | ... AE30: =AE29/AD29-1 -> 0.2665513 | AM30: =+IF(AI29<0,1-AM29/AI29,AM29/AI29-1) -> 0.097885881 | AN30: =+IF(AJ29<0,1-AN29/AJ29,AN29/AJ29-1) -> 0.10455368 | AO30: =+IF(AK29<0,1-AO29/AK29,AO29/AK29-1) -> -0.35008125 | AP30: =+IF(AL29<0,1-AP29/AL29,AP29/AL29-1) -> -0.39773963 | AQ30: =+IF(AM29<0,1-AQ29/AM29,AQ29/AM29-1) -> -0.48803851 | AR30: =+IF(AN29<0,1-AR29/AN29,AR29/AN29-1) -> -0.56157333 | AS30: =+IF(AO29<0,1-AS29/AO29,AS29/AO29-1) -> -0.56761462 | AT30: =+IF(AP29<0,1-AT29/AP29,AT29/AP29-1) -> -0.25929826 | ... DA30: =+IF(CW29<0,1-DA29/CW29,DA29/CW29-1) -> 0.24996449 | DD30: -0.25991752 | DE30: 0.26720144
A31: Net Revenue QOQ% | AJ31: =+IF(AI29<0,1-AJ29/AI29,AJ29/AI29-1) -> 0.19145723 | AK31: =+IF(AJ29<0,1-AK29/AJ29,AK29/AJ29-1) -> 0.76038385 | AL31: =+IF(AK29<0,1-AL29/AK29,AL29/AK29-1) -> -0.31882418 | AM31: =+IF(AL29<0,1-AM29/AL29,AM29/AL29-1) -> -0.23155614 | AN31: =+IF(AM29<0,1-AN29/AM29,AN29/AM29-1) -> 0.19869332 | AO31: =+IF(AN29<0,1-AO29/AN29,AO29/AN29-1) -> 0.035808834 | AP31: =+IF(AO29<0,1-AP29/AO29,AP29/AO29-1) -> -0.36877463 | AQ31: =+IF(AP29<0,1-AQ29/AP29,AQ29/AP29-1) -> -0.34677146 | ... CL31: =+IF(CK29<0,1-CL29/CK29,CL29/CK29-1) -> 0.50832119 | CM31: =+CM29/CL29-1 -> -0.13792353 | CN31: =+CN29/CM29-1 -> 0.53727273 | CO31: =+CO29/CN29-1 -> 0.039174216 | CP31: =+CP29/CO29-1 -> -0.024850034 | CQ31: =+CQ29/CP29-1 -> 0.0072624868 | CR31: =+CR29/CQ29-1 -> 0.3897161 | CS31: =+CS29/CR29-1 -> 0.019276949 | CT31: =+CT29/CS29-1 -> -0.033809477 | ... DA31: =+DA29/CZ29-1 -> 0.0059979139 | DD31: -0.4479829 | DE31: 1.7425055
A32: Increase/Decrease in Stock | B32: ='Annual Raw'!C11 -> -2.4551 | C32: ='Annual Raw'!D11 -> 10.9082 | D32: ='Annual Raw'!E11 -> 0 | E32: ='Annual Raw'!F11 -> 0 | F32: ='Annual Raw'!G11 -> 0 | G32: ='Annual Raw'!H11 -> 0 | H32: ='Annual Raw'!I11 -> 0 | I32: ='Annual Raw'!J11 -> 0 | ... AA32: ='Annual Raw'!AB11 -> 1.8645 | AB32: =+SUM(CL32:CO32) -> -0.659 | AC32: =+SUM(CP32:CS32) -> 0 | AD32: =+SUM(CT32:CW32) -> 0 | AE32: =+SUM(CX32:DA32) -> 0 | AI32: ='QTR Raw'!C10 -> -0.416 | AJ32: ='QTR Raw'!D10 -> 1.175 | AK32: ='QTR Raw'!E10 -> -0.81 | AL32: ='QTR Raw'!F10 -> -1.338 | AM32: ='QTR Raw'!G10 -> 1.701 | AN32: ='QTR Raw'!H10 -> -0.053 | AO32: ='QTR Raw'!I10 -> 0.205 | AP32: ='QTR Raw'!J10 -> -1.586 | ... CJ32: ='QTR Raw'!BD10 -> -0.678 | CK32: 16.5718 | CL32: ='QTR Raw'!BF10 -> -0.659 | DD32: 37.3584
A33: Purchase of Finished Goods | B33: 0 | C33: 0 | D33: 0 | E33: 0 | F33: 0 | G33: 0 | H33: 0 | I33: 0 | J33: 0 | K33: 0 | L33: 0 | M33: 0 | N33: 0 | O33: 0 | P33: 0 | Q33: 0 | R33: 0 | S33: 0 | T33: 0 | U33: 0 | V33: 0 | W33: 0 | X33: 0 | Y33: 0 | Z33: 0 | AA33: 0 | AB33: =+SUM(CL33:CO33) -> 0 | AC33: =+SUM(CP33:CS33) -> 0 | AD33: =+SUM(CT33:CW33) -> 0 | AE33: =+SUM(CX33:DA33) -> 0 | AI33: ='QTR Raw'!C12 -> 15.591 | AJ33: ='QTR Raw'!D12 -> 32.846 | AK33: ='QTR Raw'!E12 -> 68.75 | AL33: ='QTR Raw'!F12 -> 24.29 | AM33: ='QTR Raw'!G12 -> 32.826 | AN33: ='QTR Raw'!H12 -> 55.692 | AO33: ='QTR Raw'!I12 -> 50.49 | AP33: ='QTR Raw'!J12 -> 26.933 | ... CL33: ='QTR Raw'!BF12 -> 0 | DD33: 0
A34: Raw Material Consumed | B34: ='Annual Raw'!C12 -> 64.55574 | C34: ='Annual Raw'!D12 -> 64.487941 | D34: ='Annual Raw'!E12 -> 0 | E34: ='Annual Raw'!F12 -> 0 | F34: ='Annual Raw'!G12 -> 0 | G34: ='Annual Raw'!H12 -> 0 | H34: ='Annual Raw'!I12 -> 0 | I34: ='Annual Raw'!J12 -> 0 | ... AA34: ='Annual Raw'!AB12 -> 159.9097 | AB34: =+SUM(CL34:CO34) -> 705.00472 | AC34: =+SUM(CP34:CS34) -> 1001.7169 | AD34: =+SUM(CT34:CW34) -> 1331.2575 | AE34: =+SUM(CX34:DA34) -> 1686.1059 | AI34: ='QTR Raw'!C11 -> 35.855 | AJ34: ='QTR Raw'!D11 -> 47.087 | AK34: ='QTR Raw'!E11 -> 78.065 | AL34: ='QTR Raw'!F11 -> 78.283 | AM34: ='QTR Raw'!G11 -> 44.369 | AN34: ='QTR Raw'!H11 -> 35.775 | AO34: ='QTR Raw'!I11 -> 36.873 | AP34: ='QTR Raw'!J11 -> 33.207 | ... CJ34: ='QTR Raw'!BD11 -> 0 | CK34: 104.3428 | CL34: ='QTR Raw'!BF11 -> 154.969 | CM34: =+CM29-CM35 -> 133.02702 | CN34: =+CN29-CN35 -> 204.49881 | CO34: =+CO29-CO35 -> 212.50989 | CP34: =+CP29-CP35 -> 207.22901 | CQ34: =+CQ29-CQ35 -> 208.73401 | CR34: =+CR29-CR35 -> 290.08102 | CS34: =+CS29-CS35 -> 295.67289 | CT34: =+CT29-CT35 -> 285.67635 | ... DA34: =+DA29-DA35 -> 478.34985 | DD34: -0.12722574 | DE34: 31.90592
A35: Gross Profit | B35: =B29-B32-B34-B33 -> 22.539894 | C35: =C29-C32-C34-C33 -> 47.544033 | D35: =D29-D32-D34-D33 -> 0 | E35: =E29-E32-E34-E33 -> 0 | F35: =F29-F32-F34-F33 -> 0 | G35: =G29-G32-G34-G33 -> 0 | H35: =H29-H32-H34-H33 -> 0 | I35: =I29-I32-I34-I33 -> 0 | ... AE35: =AE29-AE32-AE34-AE33 -> 2078.3432 | AI35: =AI29-AI32-AI34-AI33 -> 41.68 | AJ35: =AJ29-AJ32-AJ34-AJ33 -> 29.352 | AK35: =AK29-AK32-AK34-AK33 -> 48.447 | AL35: =AL29-AL32-AL34-AL33 -> 31.221 | AM35: =AM29-AM32-AM34-AM33 -> 22.889 | AN35: =AN29-AN32-AN34-AN33 -> 30.595 | AO35: =AO29-AO32-AO34-AO33 -> 38.81 | AP35: =AP29-AP32-AP34-AP33 -> 21.219 | ... CL35: =CL29-CL32-CL34-CL33 -> 190.207 | CM35: =+CM36*CM29 -> 163.97298 | CN35: =+CN36*CN29 -> 252.07119 | CO35: =+CO36*CO29 -> 261.94588 | CP35: =+CP36*CP29 -> 255.43652 | CQ35: =+CQ36*CQ29 -> 257.29162 | CR35: =+CR36*CR29 -> 357.56231 | CS35: =+CS36*CS29 -> 364.45502 | CT35: =+CT36*CT29 -> 352.13299 | ... DA35: =+DA36*DA29 -> 589.62796 | DD35: 53.664053 | DE35: 248.01888
A36: GP% | B36: =B35/B29 -> 0.26630142 | C36: =C35/C29 -> 0.38672495 | D36: =D35/D29 -> #DIV/0! | E36: =E35/E29 -> #DIV/0! | F36: =F35/F29 -> #DIV/0! | G36: =G35/G29 -> #DIV/0! | H36: =H35/H29 -> #DIV/0! | I36: =I35/I29 -> #DIV/0! | ... AE36: =AE35/AE29 -> 0.55209757 | AI36: =AI35/AI29 -> 0.44957394 | AJ36: =AJ35/AJ29 -> 0.26572515 | AK36: =AK35/AK29 -> 0.24914632 | AL36: =AL35/AL29 -> 0.23570846 | AM36: =AM35/AM29 -> 0.22487596 | AN36: =AN35/AN29 -> 0.25076019 | AO36: =AO35/AO29 -> 0.30709459 | AP36: =AP35/AP29 -> 0.26599225 | ... CL36: =CL35/CL29 -> 0.55209757 | CM36: =+CL36 -> 0.55209757 | CN36: =+CM36 -> 0.55209757 | CO36: =+CN36 -> 0.55209757 | CP36: =+CO36 -> 0.55209757 | CQ36: =+CP36 -> 0.55209757 | CR36: =+CQ36 -> 0.55209757 | CS36: =+CR36 -> 0.55209757 | CT36: =+CS36 -> 0.55209757 | ... DA36: =+CZ36 -> 0.55209757 | DD36: 1.0023764 | DE36: 0.88601967
A37: GP YOY% | C37: =+IF(B35<0,1-C35/B35,C35/B35-1) -> 1.1093281 | D37: =+IF(C35<0,1-D35/C35,D35/C35-1) -> -1 | E37: =+IF(D35<0,1-E35/D35,E35/D35-1) -> #DIV/0! | F37: =+IF(E35<0,1-F35/E35,F35/E35-1) -> #DIV/0! | G37: =+IF(F35<0,1-G35/F35,G35/F35-1) -> #DIV/0! | H37: =+IF(G35<0,1-H35/G35,H35/G35-1) -> #DIV/0! | I37: =+IF(H35<0,1-I35/H35,I35/H35-1) -> #DIV/0! | J37: =+IF(I35<0,1-J35/I35,J35/I35-1) -> #DIV/0! | ... AE37: =+IF(AD35<0,1-AE35/AD35,AE35/AD35-1) -> 0.2665513 | AM37: =+IF(AI35<0,1-AM35/AI35,AM35/AI35-1) -> -0.45083973 | AN37: =+IF(AJ35<0,1-AN35/AJ35,AN35/AJ35-1) -> 0.042348051 | AO37: =+IF(AK35<0,1-AO35/AK35,AO35/AK35-1) -> -0.19891841 | AP37: =+IF(AL35<0,1-AP35/AL35,AP35/AL35-1) -> -0.3203613 | AQ37: =+IF(AM35<0,1-AQ35/AM35,AQ35/AM35-1) -> -0.2848093 | AR37: =+IF(AN35<0,1-AR35/AN35,AR35/AN35-1) -> -0.46635071 | AS37: =+IF(AO35<0,1-AS35/AO35,AS35/AO35-1) -> -0.58098428 | AT37: =+IF(AP35<0,1-AT35/AP35,AT35/AP35-1) -> 0.14661388 | ... CL37: =+IF(CH35<0,1-CL35/CH35,CL35/CH35-1) -> 0.57137428 | CM37: =+CM35/CI35-1 -> 1.0011103 | CN37: =+CN35/CJ35-1 -> 1.581057 | CO37: =+CO35/CK35-1 -> 1.4367897 | CP37: =+CP35/CL35-1 -> 0.34293962 | CQ37: =+CQ35/CM35-1 -> 0.56910987 | CR37: =+CR35/CN35-1 -> 0.41849733 | CS37: =+CS35/CO35-1 -> 0.39133709 | CT37: =+CT35/CP35-1 -> 0.37855382 | ... DA37: =+DA35/CW35-1 -> 0.24996449 | DD37: -0.27552479 | DE37: 1.0489808
A38: GP QOQ% | AJ38: =+IF(AI35<0,1-AJ35/AI35,AJ35/AI35-1) -> -0.29577735 | AK38: =+IF(AJ35<0,1-AK35/AJ35,AK35/AJ35-1) -> 0.65055192 | AL38: =+IF(AK35<0,1-AL35/AK35,AL35/AK35-1) -> -0.35556381 | AM38: =+IF(AL35<0,1-AM35/AL35,AM35/AL35-1) -> -0.26687166 | AN38: =+IF(AM35<0,1-AN35/AM35,AN35/AM35-1) -> 0.33666827 | AO38: =+IF(AN35<0,1-AO35/AN35,AO35/AN35-1) -> 0.26850793 | AP38: =+IF(AO35<0,1-AP35/AO35,AP35/AO35-1) -> -0.45325947 | AQ38: =+IF(AP35<0,1-AQ35/AP35,AQ35/AP35-1) -> -0.22852161 | ... CL38: =+IF(CK35<0,1-CL35/CK35,CL35/CK35-1) -> 0.76942834 | CM38: =+CM35/CL35-1 -> -0.13792353 | CN38: =+CN35/CM35-1 -> 0.53727273 | CO38: =+CO35/CN35-1 -> 0.039174216 | CP38: =+CP35/CO35-1 -> -0.024850034 | CQ38: =+CQ35/CP35-1 -> 0.0072624868 | CR38: =+CR35/CQ35-1 -> 0.3897161 | CS38: =+CS35/CR35-1 -> 0.019276949 | CT38: =+CT35/CS35-1 -> -0.033809477 | ... DA38: =+DA35/CZ35-1 -> 0.0059979139 | DD38: -0.45051246 | DE38: 1.4512881
A39: Power & Fuel Cost | B39: ='Annual Raw'!C13 -> 0.3935483 | C39: ='Annual Raw'!D13 -> 0.49143431 | D39: ='Annual Raw'!E13 -> 0 | E39: ='Annual Raw'!F13 -> 0 | F39: ='Annual Raw'!G13 -> 0 | G39: ='Annual Raw'!H13 -> 0 | H39: ='Annual Raw'!I13 -> 0 | I39: ='Annual Raw'!J13 -> 0 | ... AA39: ='Annual Raw'!AB13 -> 1.7533 | AB39: =+SUM(CL39:CO39) -> 0 | AC39: =+SUM(CP39:CS39) -> 0 | AD39: =+SUM(CT39:CW39) -> 0 | AE39: =+SUM(CX39:DA39) -> 0 | AI39: ='QTR Raw'!C15 -> 0 | AJ39: ='QTR Raw'!D15 -> 0 | AK39: ='QTR Raw'!E15 -> 0 | AL39: ='QTR Raw'!F15 -> 0 | AM39: ='QTR Raw'!G15 -> 0 | AN39: ='QTR Raw'!H15 -> 0 | AO39: ='QTR Raw'!I15 -> 0 | AP39: ='QTR Raw'!J15 -> 0 | ... CL39: ='QTR Raw'!BF15 -> 0 | DD39: 0
A40: Selling and Distribution Expenses | B40: =('Annual Raw'!C18) -> 0.49196158 | C40: =('Annual Raw'!D18) -> 5.5031474 | D40: =('Annual Raw'!E18) -> 0 | E40: =('Annual Raw'!F18) -> 0 | F40: =('Annual Raw'!G18) -> 0 | G40: =('Annual Raw'!H18) -> 0 | H40: =('Annual Raw'!I18) -> 0 | I40: =('Annual Raw'!J18) -> 0 | ... AA40: =('Annual Raw'!AB18) -> 4.8797 | AB40: =+SUM(CL40:CO40) -> 0 | AC40: =+SUM(CP40:CS40) -> 0 | AD40: =+SUM(CT40:CW40) -> 0 | AE40: =+SUM(CX40:DA40) -> 0 | AI40: ='QTR Raw'!C18 -> 0 | AJ40: ='QTR Raw'!D18 -> 0 | AK40: ='QTR Raw'!E18 -> 0 | AL40: ='QTR Raw'!F18 -> 0 | AM40: ='QTR Raw'!G18 -> 0 | AN40: ='QTR Raw'!H18 -> 0 | AO40: ='QTR Raw'!I18 -> 0 | AP40: ='QTR Raw'!J18 -> 0 | ... CL40: ='QTR Raw'!BF18 -> 0 | DD40: 0
A41: Other Manufacturing Expenses | B41: ='Annual Raw'!C15+'Annual Raw'!C16 -> 13.841807 | C41: ='Annual Raw'!D15+'Annual Raw'!D16 -> 12.645187 | D41: ='Annual Raw'!E15+'Annual Raw'!E16 -> 0 | E41: ='Annual Raw'!F15+'Annual Raw'!F16 -> 0 | F41: ='Annual Raw'!G15+'Annual Raw'!G16 -> 0 | G41: ='Annual Raw'!H15+'Annual Raw'!H16 -> 0 | H41: ='Annual Raw'!I15+'Annual Raw'!I16 -> 0 | I41: ='Annual Raw'!J15+'Annual Raw'!J16 -> 0 | ... AA41: ='Annual Raw'!AB15+'Annual Raw'!AB16 -> 42.6334 | AB41: =+SUM(CL41:CO41) -> 512.00021 | AC41: =+SUM(CP41:CS41) -> 685.90305 | AD41: =+SUM(CT41:CW41) -> 852.52359 | AE41: =+SUM(CX41:DA41) -> 1004.7354 | AI41: ='QTR Raw'!C14 -> 24.914 | AJ41: ='QTR Raw'!D14 -> 22.731 | AK41: ='QTR Raw'!E14 -> 33.6 | AL41: ='QTR Raw'!F14 -> 27.844 | AM41: ='QTR Raw'!G14 -> 29.033 | AN41: ='QTR Raw'!H14 -> 31.506 | AO41: ='QTR Raw'!I14 -> 15.745 | AP41: ='QTR Raw'!J14 -> 20.862 | ... CJ41: ='QTR Raw'!BD14 -> 74.052 | CK41: 76.4731 | CL41: ='QTR Raw'!BF14 -> 113.71 | CM41: =+CM23*CM29 -> 98.026716 | CN41: =+CN23*CN29 -> 148.41095 | CO41: =+CO23*CO29 -> 151.85255 | CP41: =+CP23*CP29 -> 145.76568 | CQ41: =+CQ23*CQ29 -> 144.49417 | CR41: =+CR23*CR29 -> 197.56766 | CS41: =+CS23*CS29 -> 198.07553 | CT41: =+CT23*CT29 -> 188.18965 | ... DA41: =+DA23*DA29 -> 277.73434 | DD41: 39.683199 | DE41: 166.64904
A42: Employee Cost | B42: ='Annual Raw'!C14 -> 4.8360056 | C42: ='Annual Raw'!D14 -> 4.8083723 | D42: ='Annual Raw'!E14 -> 0 | E42: ='Annual Raw'!F14 -> 0 | F42: ='Annual Raw'!G14 -> 0 | G42: ='Annual Raw'!H14 -> 0 | H42: ='Annual Raw'!I14 -> 0 | I42: ='Annual Raw'!J14 -> 0 | ... AA42: ='Annual Raw'!AB14 -> 63.3485 | AB42: =+SUM(CL42:CO42) -> 286.34 | AC42: =+SUM(CP42:CS42) -> 314.974 | AD42: =+SUM(CT42:CW42) -> 346.4714 | AE42: =+SUM(CX42:DA42) -> 381.11854 | AI42: ='QTR Raw'!C16 -> 9.925 | AJ42: ='QTR Raw'!D16 -> 12.134 | AK42: ='QTR Raw'!E16 -> 12.361 | AL42: ='QTR Raw'!F16 -> 8.983 | AM42: ='QTR Raw'!G16 -> 11.883 | AN42: ='QTR Raw'!H16 -> 11.589 | AO42: ='QTR Raw'!I16 -> 10.835 | AP42: ='QTR Raw'!J16 -> 8.541 | ... CJ42: ='QTR Raw'!BD16 -> 12.292 | CK42: 50.6815 | CL42: ='QTR Raw'!BF16 -> 71.585 | CM42: =+CL42 -> 71.585 | CN42: =+CM42 -> 71.585 | CO42: =+CN42 -> 71.585 | CP42: =CL42*110% -> 78.7435 | CQ42: =CM42*110% -> 78.7435 | CR42: =CN42*110% -> 78.7435 | CS42: =CO42*110% -> 78.7435 | CT42: =CP42*110% -> 86.61785 | CU42: =CQ42*110% -> 86.61785 | CV42: =CR42*110% -> 86.61785 | CW42: =CS42*110% -> 86.61785 | ... DA42: =CW42*110% -> 95.279635 | DD42: 12.27076 | DE42: 65.0988
A43: General and Administration Expenses | B43: ='Annual Raw'!C17 -> 6.2128015 | C43: ='Annual Raw'!D17 -> 7.9917853 | D43: ='Annual Raw'!E17 -> 0 | E43: ='Annual Raw'!F17 -> 0 | F43: ='Annual Raw'!G17 -> 0 | G43: ='Annual Raw'!H17 -> 0 | H43: ='Annual Raw'!I17 -> 0 | I43: ='Annual Raw'!J17 -> 0 | ... AA43: ='Annual Raw'!AB17 -> 31.7816 | AB43: =+SUM(CL43:CO43) -> 0 | AC43: =+SUM(CP43:CS43) -> 0 | AD43: =+SUM(CT43:CW43) -> 0 | AE43: =+SUM(CX43:DA43) -> 0 | AI43: ='QTR Raw'!C17 -> 0 | AJ43: ='QTR Raw'!D17 -> 0 | AK43: ='QTR Raw'!E17 -> 0 | AL43: ='QTR Raw'!F17 -> 0 | AM43: ='QTR Raw'!G17 -> 0 | AN43: ='QTR Raw'!H17 -> 0 | AO43: ='QTR Raw'!I17 -> 0 | AP43: ='QTR Raw'!J17 -> 0 | ... CL43: ='QTR Raw'!BF17 -> 0 | DD43: 0
A44: Miscellaneous Expenses | B44: ='Annual Raw'!C19-'Annual Raw'!C20 -> 0.15594419 | C44: ='Annual Raw'!D19-'Annual Raw'!D20 -> 1.0731105 | D44: ='Annual Raw'!E19-'Annual Raw'!E20 -> 0 | E44: ='Annual Raw'!F19-'Annual Raw'!F20 -> 0 | F44: ='Annual Raw'!G19-'Annual Raw'!G20 -> 0 | G44: ='Annual Raw'!H19-'Annual Raw'!H20 -> 0 | H44: ='Annual Raw'!I19-'Annual Raw'!I20 -> 0 | I44: ='Annual Raw'!J19-'Annual Raw'!J20 -> 0 | ... AA44: ='Annual Raw'!AB19-'Annual Raw'!AB20 -> 28.9839 | AB44: =+SUM(CL44:CO44) -> 0 | AC44: =+SUM(CP44:CS44) -> 0 | AD44: =+SUM(CT44:CW44) -> 0 | AE44: =+SUM(CX44:DA44) -> 0 | DD44: 0
A45: Total Cost | B45: =+SUM(B39:B44) -> 25.932068 | C45: =+SUM(C39:C44) -> 32.513037 | D45: =+SUM(D39:D44) -> 0 | E45: =+SUM(E39:E44) -> 0 | F45: =+SUM(F39:F44) -> 0 | G45: =+SUM(G39:G44) -> 0 | H45: =+SUM(H39:H44) -> 0 | I45: =+SUM(I39:I44) -> 0 | ... AE45: =+SUM(AE39:AE44) -> 1385.854 | AI45: =+SUM(AI39:AI44) -> 34.839 | AJ45: =+SUM(AJ39:AJ44) -> 34.865 | AK45: =+SUM(AK39:AK44) -> 45.961 | AL45: =+SUM(AL39:AL44) -> 36.827 | AM45: =+SUM(AM39:AM44) -> 40.916 | AN45: =+SUM(AN39:AN44) -> 43.095 | AO45: =+SUM(AO39:AO44) -> 26.58 | AP45: =+SUM(AP39:AP44) -> 29.403 | ... DA45: =+SUM(DA39:DA44) -> 373.01397 | DD45: 51.953959 | DE45: 231.74784
A46: Cost % | B46: =B45/B29 -> 0.30637884 | C46: =C45/C29 -> 0.26446226 | D46: =D45/D29 -> #DIV/0! | E46: =E45/E29 -> #DIV/0! | F46: =F45/F29 -> #DIV/0! | G46: =G45/G29 -> #DIV/0! | H46: =H45/H29 -> #DIV/0! | I46: =I45/I29 -> #DIV/0! | ... AE46: =AE45/AE29 -> 0.36814256 | AI46: =AI45/AI29 -> 0.3757847 | AJ46: =AJ45/AJ29 -> 0.31563462 | AK46: =AK45/AK29 -> 0.23636167 | AL46: =AL45/AL29 -> 0.27803195 | AM46: =AM45/AM29 -> 0.40198458 | AN46: =AN45/AN29 -> 0.35321165 | AO46: =AO45/AO29 -> 0.21032142 | AP46: =AP45/AP29 -> 0.36858336 | ... DA46: =DA45/DA29 -> 0.34927128 | DD46: 0.97043404 | DE46: 0.82789323
A47: EBITDA | B47: =B35-B45 -> -3.3921744 | C47: =C35-C45 -> 15.030996 | D47: =D35-D45 -> 0 | E47: =E35-E45 -> 0 | F47: =F35-F45 -> 0 | G47: =G35-G45 -> 0 | H47: =H35-H45 -> 0 | I47: =I35-I45 -> 0 | ... AE47: =AE35-AE45 -> 692.48929 | AI47: =AI35-AI45 -> 6.841 | AJ47: =AJ35-AJ45 -> -5.513 | AK47: =AK35-AK45 -> 2.486 | AL47: =AL35-AL45 -> -5.606 | AM47: =AM35-AM45 -> -18.027 | AN47: =AN35-AN45 -> -12.5 | AO47: =AO35-AO45 -> 12.23 | AP47: =AP35-AP45 -> -8.184 | ... DA47: =DA35-DA45 -> 216.61399 | DD47: 1.7100932 | DE47: 16.271034
A48: EBITDA Margins | B48: =B47/B29 -> -0.040077421 | C48: =C47/C29 -> 0.12226268 | D48: =D47/D29 -> #DIV/0! | E48: =E47/E29 -> #DIV/0! | F48: =F47/F29 -> #DIV/0! | G48: =G47/G29 -> #DIV/0! | H48: =H47/H29 -> #DIV/0! | I48: =I47/I29 -> #DIV/0! | ... AE48: =AE47/AE29 -> 0.18395501 | AI48: =AI47/AI29 -> 0.073789235 | AJ48: =AJ47/AJ29 -> -0.049909469 | AK48: =AK47/AK29 -> 0.012784646 | AL48: =AL47/AL29 -> -0.042323489 | AM48: =AM47/AM29 -> -0.17710861 | AN48: =AN47/AN29 -> -0.10245146 | AO48: =AO47/AO29 -> 0.096773173 | AP48: =AP47/AP29 -> -0.1025911 | ... DA48: =DA47/DA29 -> 0.2028263 | DD48: 0.031942371 | DE48: 0.058126447
A49: EBITDA YOY% | C49: =+IF(B47<0,1-C47/B47,C47/B47-1) -> 5.4310799 | D49: =+IF(C47<0,1-D47/C47,D47/C47-1) -> -1 | E49: =+IF(D47<0,1-E47/D47,E47/D47-1) -> #DIV/0! | F49: =+IF(E47<0,1-F47/E47,F47/E47-1) -> #DIV/0! | G49: =+IF(F47<0,1-G47/F47,G47/F47-1) -> #DIV/0! | H49: =+IF(G47<0,1-H47/G47,H47/G47-1) -> #DIV/0! | I49: =+IF(H47<0,1-I47/H47,I47/H47-1) -> #DIV/0! | J49: =+IF(I47<0,1-J47/I47,J47/I47-1) -> #DIV/0! | ... AE49: =+IF(AD47<0,1-AE47/AD47,AE47/AD47-1) -> 0.56688881 | AM49: =+IF(AI47<0,1-AM47/AI47,AM47/AI47-1) -> -3.6351411 | AN49: =+IF(AJ47<0,1-AN47/AJ47,AN47/AJ47-1) -> -1.267368 | AO49: =+IF(AK47<0,1-AO47/AK47,AO47/AK47-1) -> 3.9195495 | AP49: =+IF(AL47<0,1-AP47/AL47,AP47/AL47-1) -> -0.45986443 | AQ49: =+IF(AM47<0,1-AQ47/AM47,AQ47/AM47-1) -> 0.76485272 | AR49: =+IF(AN47<0,1-AR47/AN47,AR47/AN47-1) -> 0.65944 | AS49: =+IF(AO47<0,1-AS47/AO47,AS47/AO47-1) -> -1.2501226 | AT49: =+IF(AP47<0,1-AT47/AP47,AT47/AP47-1) -> 1.3814761 | ... DA49: =+IF(CW47<0,1-DA47/CW47,DA47/CW47-1) -> 0.48552957 | DD49: 4.5626942 | DE49: 11.912833
A50: EBITDA QOQ% | AJ50: =+IF(AI47<0,1-AJ47/AI47,AJ47/AI47-1) -> -1.8058763 | AK50: =+IF(AJ47<0,1-AK47/AJ47,AK47/AJ47-1) -> 1.4509342 | AL50: =+IF(AK47<0,1-AL47/AK47,AL47/AK47-1) -> -3.2550282 | AM50: =+IF(AL47<0,1-AM47/AL47,AM47/AL47-1) -> -2.2156618 | AN50: =+IF(AM47<0,1-AN47/AM47,AN47/AM47-1) -> 0.30659566 | AO50: =+IF(AN47<0,1-AO47/AN47,AO47/AN47-1) -> 1.9784 | AP50: =+IF(AO47<0,1-AP47/AO47,AP47/AO47-1) -> -1.6691742 | AQ50: =+IF(AP47<0,1-AQ47/AP47,AQ47/AP47-1) -> 0.48203812 | ... CI50: =+IF(CH47<0,1-CI47/CH47,CI47/CH47-1) -> 2.295104 | CJ50: =+IF(CI47>1,CJ47/CI47-1,1-CJ47/CI47) -> 4.8612118 | CK50: =+IF(CJ47>1,CK47/CJ47-1,1-CK47/CJ47) -> -2.7369058 | CL50: =+IF(CK47>1,CL47/CK47-1,1-CL47/CK47) -> 1.249869 | CM50: =+IF(CL47>1,CM47/CL47-1,1-CM47/CL47) -> -2.1479512 | CN50: =+IF(CM47>1,CN47/CM47-1,1-CN47/CM47) -> 6.6883746 | CO50: =+IF(CN47>1,CO47/CN47-1,1-CO47/CN47) -> 0.2005624 | CP50: =+IF(CO47>1,CP47/CO47-1,1-CP47/CO47) -> -0.19686637 | CQ50: =+IF(CP47>1,CQ47/CP47-1,1-CQ47/CP47) -> 0.10109539 | ... DA50: =+IF(CZ47>1,DA47/CZ47-1,1-DA47/CZ47) -> 0.034221692 | DD50: -0.848905 | DE50: 0.6095592
A51: Depreciation | B51: ='Annual Raw'!C27 -> 3.1754977 | C51: ='Annual Raw'!D27 -> 2.6181707 | D51: ='Annual Raw'!E27 -> 0 | E51: ='Annual Raw'!F27 -> 0 | F51: ='Annual Raw'!G27 -> 0 | G51: ='Annual Raw'!H27 -> 0 | H51: ='Annual Raw'!I27 -> 0 | I51: ='Annual Raw'!J27 -> 0 | ... AA51: ='Annual Raw'!AB27 -> 6.1507 | AB51: =+SUM(CL51:CO51) -> 13.108 | AC51: =+SUM(CP51:CS51) -> 13.108 | AD51: =+SUM(CT51:CW51) -> 13.108 | AE51: =+SUM(CX51:DA51) -> 13.108 | AI51: ='QTR Raw'!C28 -> 1.03 | AJ51: ='QTR Raw'!D28 -> 1.102 | AK51: ='QTR Raw'!E28 -> 1.157 | AL51: ='QTR Raw'!F28 -> 1.315 | AM51: ='QTR Raw'!G28 -> 2.081 | AN51: ='QTR Raw'!H28 -> 2.136 | AO51: ='QTR Raw'!I28 -> 2.239 | AP51: ='QTR Raw'!J28 -> 1.925 | ... CJ51: ='QTR Raw'!BD28 -> 1.55 | CK51: 3.5851 | CL51: ='QTR Raw'!BF28 -> 3.277 | CM51: =CM52*CL153 -> 3.277 | CN51: =CN52*CM153 -> 3.277 | CO51: =CO52*CN153 -> 3.277 | CP51: =CP52*CO153 -> 3.277 | CQ51: =CQ52*CP153 -> 3.277 | CR51: =CR52*CQ153 -> 3.277 | CS51: =CS52*CR153 -> 3.277 | CT51: =CT52*CS153 -> 3.277 | ... DA51: =DA52*CZ153 -> 3.277 | DD51: 1.55 | DE51: 1.7234591
A52: Depreciation % of Net Block | B52: =+B51/B153 -> 0.13861311 | C52: =+C51/C153 -> 0.11175025 | D52: =+D51/D153 -> #DIV/0! | E52: =+E51/E153 -> #DIV/0! | F52: =+F51/F153 -> #DIV/0! | G52: =+G51/G153 -> #DIV/0! | H52: =+H51/H153 -> #DIV/0! | I52: =+I51/I153 -> #DIV/0! | ... AE52: =+AE51/AE153 -> 0.25776764 | AI52: =+AI51/AH153 -> #DIV/0! | AJ52: =+AJ51/AI153 -> #DIV/0! | AK52: =+AK51/AJ153 -> #DIV/0! | AL52: =+AL51/AK153 -> #DIV/0! | AM52: =+AM51/AL153 -> #DIV/0! | AN52: =+AN51/AM153 -> #DIV/0! | AO52: =+AO51/AN153 -> #DIV/0! | AP52: =+AP51/AO153 -> #DIV/0! | ... CE52: =+CE51/CD153 -> 0.031705175 | CF52: =+CF51/CE150 -> 0.030077189 | CG52: =+CG51/CF153 -> 0.033086956 | CH52: =+CH51/CG153 -> 0.046912435 | CI52: =+CI51/CH153 -> 0.029052755 | CJ52: =+CJ51/CI153 -> 0.033717642 | CK52: =+CK51/CJ153 -> 0.077987818 | CL52: =+CL51/CK153 -> 0.06444191 | CM52: =CL52 -> 0.06444191 | CN52: =CM52 -> 0.06444191 | CO52: =CN52 -> 0.06444191 | CP52: =CO52 -> 0.06444191 | CQ52: =CP52 -> 0.06444191 | CR52: =CQ52 -> 0.06444191 | CS52: =CR52 -> 0.06444191 | CT52: =CS52 -> 0.06444191 | ... DA52: =CZ52 -> 0.06444191 | DD52: 0.033717642 | DE52: 0.033891668
A53: EBIT | B53: =B47-B51 -> -6.5676721 | C53: =C47-C51 -> 12.412825 | D53: =D47-D51 -> 0 | E53: =E47-E51 -> 0 | F53: =F47-F51 -> 0 | G53: =G47-G51 -> 0 | H53: =H47-H51 -> 0 | I53: =I47-I51 -> 0 | ... AE53: =AE47-AE51 -> 679.38129 | AI53: =AI47-AI51 -> 5.811 | AJ53: =AJ47-AJ51 -> -6.615 | AK53: =AK47-AK51 -> 1.329 | AL53: =AL47-AL51 -> -6.921 | AM53: =AM47-AM51 -> -20.108 | AN53: =AN47-AN51 -> -14.636 | AO53: =AO47-AO51 -> 9.991 | AP53: =AP47-AP51 -> -10.109 | ... DA53: =DA47-DA51 -> 213.33699 | DD53: 0.1600932 | DE53: 14.547575
A54: Other Income | B54: ='Annual Raw'!C23 -> 6.8892502 | C54: ='Annual Raw'!D23 -> 0.27437178 | D54: ='Annual Raw'!E23 -> 0 | E54: ='Annual Raw'!F23 -> 0 | F54: ='Annual Raw'!G23 -> 0 | G54: ='Annual Raw'!H23 -> 0 | H54: ='Annual Raw'!I23 -> 0 | I54: ='Annual Raw'!J23 -> 0 | ... AA54: ='Annual Raw'!AB23 -> 9.5063 | AB54: =+SUM(CL54:CO54) -> 9.376 | AC54: =+SUM(CP54:CS54) -> 0 | AD54: =+SUM(CT54:CW54) -> 0 | AE54: =+SUM(CX54:DA54) -> 0 | AI54: ='QTR Raw'!C23 -> 1.402 | AJ54: ='QTR Raw'!D23 -> 2.111 | AK54: ='QTR Raw'!E23 -> 1.636 | AL54: ='QTR Raw'!F23 -> 2.469 | AM54: ='QTR Raw'!G23 -> 1.164 | AN54: ='QTR Raw'!H23 -> 2.159 | AO54: ='QTR Raw'!I23 -> 4.606 | AP54: ='QTR Raw'!J23 -> 7.602 | ... CJ54: ='QTR Raw'!BD23 -> 2.437 | CK54: 27.9883 | CL54: ='QTR Raw'!BF23 -> 9.376 | DD54: 66.8445
A55: Interest | B55: ='Annual Raw'!C25 -> 5.0028747 | C55: ='Annual Raw'!D25 -> 6.4226669 | D55: ='Annual Raw'!E25 -> 0 | E55: ='Annual Raw'!F25 -> 0 | F55: ='Annual Raw'!G25 -> 0 | G55: ='Annual Raw'!H25 -> 0 | H55: ='Annual Raw'!I25 -> 0 | I55: ='Annual Raw'!J25 -> 0 | ... AA55: ='Annual Raw'!AB25 -> 3.0328 | AB55: =+SUM(CL55:CO55) -> -0.82450312 | AC55: =+SUM(CP55:CS55) -> -17.228693 | AD55: =+SUM(CT55:CW55) -> -29.333541 | AE55: =+SUM(CX55:DA55) -> -48.92105 | AI55: ='QTR Raw'!C25 -> 0.573 | AJ55: ='QTR Raw'!D25 -> 1.019 | AK55: ='QTR Raw'!E25 -> 0.451 | AL55: ='QTR Raw'!F25 -> 1.105 | AM55: ='QTR Raw'!G25 -> 1.947 | AN55: ='QTR Raw'!H25 -> 1.766 | AO55: ='QTR Raw'!I25 -> 1.642 | AP55: ='QTR Raw'!J25 -> 1.347 | ... CJ55: ='QTR Raw'!BD25 -> 0.288 | CK55: 5.6602 | CL55: ='QTR Raw'!BF25 -> 7.039 | CM55: =CM56*CL187 -> -1.9302976 | CN55: =CN56*CM187 -> -2.5836904 | CO55: =CO56*CN187 -> -3.3495152 | CP55: =CP56*CO187 -> -3.7066853 | CQ55: =CQ56*CP187 -> -3.9106937 | CR55: =CR56*CQ187 -> -4.1901299 | CS55: =CS56*CR187 -> -5.4211842 | CT55: =CT56*CS187 -> -6.1568484 | ... DA55: =DA56*CZ187 -> -14.887955 | DD55: -1.9053625 | DE55: -2.0618059
A56: Interest % of Debt | B56: =+B55/B147 -> 0.16003087 | C56: =+C55/C147 -> 0.1913503 | D56: =+D55/D147 -> #DIV/0! | E56: =+E55/E147 -> #DIV/0! | F56: =+F55/F147 -> #DIV/0! | G56: =+G55/G147 -> #DIV/0! | H56: =+H55/H147 -> #DIV/0! | I56: =+I55/I147 -> #DIV/0! | ... AE56: =+AE55/AE147 -> #DIV/0! | AI56: =(AI55-AI54)/AH187 -> #DIV/0! | AJ56: =(AJ55-AJ54)/AI187 -> #DIV/0! | AK56: =(AK55-AK54)/AJ187 -> -0.31880549 | AL56: =(AL55-AL54)/AK187 -> #DIV/0! | AM56: =(AM55-AM54)/AL187 -> 0.22781495 | AN56: =(AN55-AN54)/AM187 -> #DIV/0! | AO56: =(AO55-AO54)/AN187 -> -0.16014696 | AP56: =(AP55-AP54)/AO187 -> #DIV/0! | ... CL56: =(CL55-CL54)/CK187 -> 0.010317744 | CM56: =+CL56 -> 0.010317744 | CN56: =+CM56 -> 0.010317744 | CO56: =+CN56 -> 0.010317744 | CP56: =+CO56 -> 0.010317744 | CQ56: =+CP56 -> 0.010317744 | CR56: =+CQ56 -> 0.010317744 | CS56: =+CR56 -> 0.010317744 | CT56: =+CS56 -> 0.010317744 | ... DA56: =+CZ56 -> 0.010317744 | DD56: 0.017361448 | DE56: 0.0091027753
A57: PBT | B57: =B53+B54-B55 -> -4.6812965 | C57: =C53+C54-C55 -> 6.2645299 | D57: =D53+D54-D55 -> 0 | E57: =E53+E54-E55 -> 0 | F57: =F53+F54-F55 -> 0 | G57: =G53+G54-G55 -> 0 | H57: =H53+H54-H55 -> 0 | I57: =I53+I54-I55 -> 0 | ... AE57: =AE53+AE54-AE55 -> 728.30234 | AI57: =AI53+AI54-AI55 -> 6.64 | AJ57: =AJ53+AJ54-AJ55 -> -5.523 | AK57: =AK53+AK54-AK55 -> 2.514 | AL57: =AL53+AL54-AL55 -> -5.557 | AM57: =AM53+AM54-AM55 -> -20.891 | AN57: =AN53+AN54-AN55 -> -14.243 | AO57: =AO53+AO54-AO55 -> 12.955 | AP57: =AP53+AP54-AP55 -> -3.854 | ... DA57: =DA53+DA54-DA55 -> 228.22494 | DD57: 2.0654557 | DE57: 16.609381
A58: Tax | B58: ='Annual Raw'!C30 -> 0 | C58: ='Annual Raw'!D30 -> 0.25 | D58: ='Annual Raw'!E30 -> 0 | E58: ='Annual Raw'!F30 -> 0 | F58: ='Annual Raw'!G30 -> 0 | G58: ='Annual Raw'!H30 -> 0 | H58: ='Annual Raw'!I30 -> 0 | I58: ='Annual Raw'!J30 -> 0 | ... AA58: ='Annual Raw'!AB30 -> 1.0405 | AB58: =+SUM(CL58:CO58) -> 14.747335 | AC58: =+SUM(CP58:CS58) -> 59.497278 | AD58: =+SUM(CT58:CW58) -> 114.54433 | AE58: =+SUM(CX58:DA58) -> 182.07558 | AI58: ='QTR Raw'!C29 -> 2.175 | AJ58: ='QTR Raw'!D29 -> -1.806 | AK58: ='QTR Raw'!E29 -> 0.819 | AL58: ='QTR Raw'!F29 -> -2.12 | AM58: ='QTR Raw'!G29 -> -7.133 | AN58: ='QTR Raw'!H29 -> 4.265 | AO58: ='QTR Raw'!I29 -> 1.424 | AP58: ='QTR Raw'!J29 -> -2.278 | ... CJ58: ='QTR Raw'!BD29 -> 2.997 | CK58: -3.402 | CL58: ='QTR Raw'!BF29 -> -0.997 | CM58: =+CM57*CM59 -> -1.7463596 | CN58: =+CN57*CN59 -> 7.8454833 | CO58: =+CO57*CO59 -> 9.6452114 | CP58: =+CP57*CP59 -> 7.8392551 | CQ58: =+CQ57*CQ59 -> 8.67191 | CR58: =+CR57*CR59 -> 20.541069 | CS58: =+CS57*CS59 -> 22.445044 | CT58: =+CT57*CT59 -> 20.051333 | ... DA58: =+DA57*DA59 -> 57.056235 | DD58: 0.49840794 | DE58: -0.26030484
A59: Tax Rate % | B59: =B58/B57 -> 0 | C59: =C58/C57 -> 0.039907224 | D59: =D58/D57 -> #DIV/0! | E59: =E58/E57 -> #DIV/0! | F59: =F58/F57 -> #DIV/0! | G59: =G58/G57 -> #DIV/0! | H59: =H58/H57 -> #DIV/0! | I59: =I58/I57 -> #DIV/0! | ... AE59: =AE58/AE57 -> 0.25 | AI59: =AI58/AI57 -> 0.32756024 | AJ59: =AJ58/AJ57 -> 0.3269962 | AK59: =AK58/AK57 -> 0.32577566 | AL59: =AL58/AL57 -> 0.38150081 | AM59: =AM58/AM57 -> 0.3414389 | AN59: =AN58/AN57 -> -0.29944534 | AO59: =AO58/AO57 -> 0.10991895 | AP59: =AP58/AP57 -> 0.59107421 | ... CL59: =CL58/CL57 -> -0.25100705 | CM59: 0.25 | CN59: 0.25 | CO59: 0.25 | CP59: 0.25 | CQ59: 0.25 | CR59: 0.25 | CS59: 0.25 | CT59: 0.25 | CU59: 0.25 | CV59: 0.25 | CW59: 0.25 | CX59: 0.25 | CY59: 0.25 | CZ59: 0.25 | DA59: 0.25 | DD59: 0.24130653 | DE59: -0.015672158
A60: PAT | B60: =B57-B58 -> -4.6812965 | C60: =C57-C58 -> 6.0145299 | D60: =D57-D58 -> 0 | E60: =E57-E58 -> 0 | F60: =F57-F58 -> 0 | G60: =G57-G58 -> 0 | H60: =H57-H58 -> 0 | I60: =I57-I58 -> 0 | ... AE60: =AE57-AE58 -> 546.22675 | AI60: =AI57-AI58 -> 4.465 | AJ60: =AJ57-AJ58 -> -3.717 | AK60: =AK57-AK58 -> 1.695 | AL60: =AL57-AL58 -> -3.437 | AM60: =AM57-AM58 -> -13.758 | AN60: =AN57-AN58 -> -18.508 | AO60: =AO57-AO58 -> 11.531 | AP60: =AP57-AP58 -> -1.576 | ... DA60: =DA57-DA58 -> 171.16871 | DD60: 1.5670477 | DE60: 16.869686
A61: PAT % | B61: =+B60/B29 -> -0.055307975 | C61: =+C60/C29 -> 0.048922412 | D61: =+D60/D29 -> #DIV/0! | E61: =+E60/E29 -> #DIV/0! | F61: =+F60/F29 -> #DIV/0! | G61: =+G60/G29 -> #DIV/0! | H61: =+H60/H29 -> #DIV/0! | I61: =+I60/I29 -> #DIV/0! | ... AE61: =+AE60/AE29 -> 0.14510138 | AI61: =+AI60/AI29 -> 0.048160932 | AJ61: =+AJ60/AJ29 -> -0.03365019 | AK61: =+AK60/AK29 -> 0.0087168041 | AL61: =+AL60/AL29 -> -0.025948239 | AM61: =+AM60/AM29 -> -0.13516726 | AN61: =+AN60/AN29 -> -0.15169373 | AO61: =+AO60/AO29 -> 0.091242147 | AP61: =+AP60/AP29 -> -0.019756058 | ... DA61: =+DA60/DA29 -> 0.16027365 | DD61: 0.029270463 | DE61: 0.060265063
A62: PAT YOY% | C62: =+IF(B60<0,1-C60/B60,C60/B60-1) -> 2.2848 | D62: =+IF(C60<0,1-D60/C60,D60/C60-1) -> -1 | E62: =+IF(D60<0,1-E60/D60,E60/D60-1) -> #DIV/0! | F62: =+IF(E60<0,1-F60/E60,F60/E60-1) -> #DIV/0! | G62: =+IF(F60<0,1-G60/F60,G60/F60-1) -> #DIV/0! | H62: =+IF(G60<0,1-H60/G60,H60/G60-1) -> #DIV/0! | I62: =+IF(H60<0,1-I60/H60,I60/H60-1) -> #DIV/0! | J62: =+IF(I60<0,1-J60/I60,J60/I60-1) -> #DIV/0! | ... AE62: =+IF(AD60<0,1-AE60/AD60,AE60/AD60-1) -> 0.58956438 | AM62: =+IF(AI60<0,1-AM60/AI60,AM60/AI60-1) -> -4.081299 | AN62: =+IF(AJ60<0,1-AN60/AJ60,AN60/AJ60-1) -> -3.9792844 | AO62: =+IF(AK60<0,1-AO60/AK60,AO60/AK60-1) -> 5.8029499 | AP62: =+IF(AL60<0,1-AP60/AL60,AP60/AL60-1) -> 0.54146058 | AQ62: =+IF(AM60<0,1-AQ60/AM60,AQ60/AM60-1) -> 0.80840238 | AR62: =+IF(AN60<0,1-AR60/AN60,AR60/AN60-1) -> 1.0472228 | AS62: =+IF(AO60<0,1-AS60/AO60,AS60/AO60-1) -> -0.98967999 | AT62: =+IF(AP60<0,1-AT60/AP60,AT60/AP60-1) -> 4.5234772 | ... CL62: =+IF(CH60<0,1-CL60/CH60,CL60/CH60-1) -> 2.7052162 | CM62: =+CM60/CI60-1 -> -4.0495221 | CN62: =+CN60/CJ60-1 -> 1.6386155 | CO62: =+CO60/CK60-1 -> 10.636158 | CP62: =+CP60/CL60-1 -> 3.732897 | CQ62: =+CQ60/CM60-1 -> -5.9657069 | CR62: =+CR60/CN60-1 -> 1.6182031 | CS62: =+CS60/CO60-1 -> 1.3270661 | CT62: =+CT60/CP60-1 -> 1.5578111 | ... DA62: =+DA60/CW60-1 -> 0.50469246 | DD62: 2.063126 | DE62: 6.7891852
A63: PAT QOQ% | AJ63: =+IF(AI60<0,1-AJ60/AI60,AJ60/AI60-1) -> -1.8324748 | AK63: =+IF(AJ60<0,1-AK60/AJ60,AK60/AJ60-1) -> 1.4560129 | AL63: =+IF(AK60<0,1-AL60/AK60,AL60/AK60-1) -> -3.0277286 | AM63: =+IF(AL60<0,1-AM60/AL60,AM60/AL60-1) -> -3.0029095 | AN63: =+IF(AM60<0,1-AN60/AM60,AN60/AM60-1) -> -0.34525367 | AO63: =+IF(AN60<0,1-AO60/AN60,AO60/AN60-1) -> 1.6230279 | AP63: =+IF(AO60<0,1-AP60/AO60,AP60/AO60-1) -> -1.136675 | AQ63: =+IF(AP60<0,1-AQ60/AP60,AQ60/AP60-1) -> -0.67258883 | ... CL63: =+IF(CK60<0,1-CL60/CK60,CL60/CK60-1) -> 0.99823059 | CM63: =+CM60/CL60-1 -> -2.0543528 | CN63: =+CN60/CM60-1 -> -5.4924786 | CO63: =+CO60/CN60-1 -> 0.22939672 | CP63: =+CP60/CO60-1 -> -0.18723865 | CQ63: =+CQ60/CP60-1 -> 0.10621607 | CR63: =+CR60/CQ60-1 -> 1.3686902 | CS63: =+CS60/CR60-1 -> 0.092691166 | CT63: =+CT60/CS60-1 -> -0.10664763 | ... DA63: =+DA60/CZ60-1 -> 0.044265022 | DD63: -0.824322 | DE63: 0.42600893
A64: Minority Interest | B64: ='Annual Raw'!C32 -> 0 | C64: ='Annual Raw'!D32 -> 0 | D64: ='Annual Raw'!E32 -> 0 | E64: ='Annual Raw'!F32 -> 0 | F64: ='Annual Raw'!G32 -> 0 | G64: ='Annual Raw'!H32 -> 0 | H64: ='Annual Raw'!I32 -> 0 | I64: ='Annual Raw'!J32 -> 0 | ... AA64: ='Annual Raw'!AB32 -> 0 | AB64: =+SUM(CL64:CO64) -> 0 | AC64: =+SUM(CP64:CS64) -> 0 | AD64: =+SUM(CT64:CW64) -> 0 | AE64: =+SUM(CX64:DA64) -> 0 | AI64: ='QTR Raw'!C34 -> 0 | AJ64: ='QTR Raw'!D34 -> 0 | AK64: ='QTR Raw'!E34 -> 0 | AL64: ='QTR Raw'!F34 -> 0 | AM64: ='QTR Raw'!G34 -> 0 | AN64: ='QTR Raw'!H34 -> 0 | AO64: ='QTR Raw'!I34 -> 0 | AP64: ='QTR Raw'!J34 -> 0 | ... CL64: ='QTR Raw'!BF34 -> 0 | CM64: =+CL64 -> 0 | CN64: =+CM64 -> 0 | CO64: =+CN64 -> 0 | CP64: =+CO64 -> 0 | CQ64: =+CP64 -> 0 | CR64: =+CQ64 -> 0 | CS64: =+CR64 -> 0 | CT64: =+CS64 -> 0 | ... DA64: =+CZ64 -> 0 | DD64: 0 | DE64: 0
A65: Share of Associate | B65: ='Annual Raw'!C33+'Annual Raw'!C28 -> 0 | C65: ='Annual Raw'!D33+'Annual Raw'!D28 -> 0 | D65: ='Annual Raw'!E33+'Annual Raw'!E28 -> 0 | E65: ='Annual Raw'!F33+'Annual Raw'!F28 -> 0 | F65: ='Annual Raw'!G33+'Annual Raw'!G28 -> 0 | G65: ='Annual Raw'!H33+'Annual Raw'!H28 -> 0 | H65: ='Annual Raw'!I33+'Annual Raw'!I28 -> 0 | I65: ='Annual Raw'!J33+'Annual Raw'!J28 -> 0 | ... AA65: ='Annual Raw'!AB33+'Annual Raw'!AB28 -> 0 | AB65: =+SUM(CL65:CO65) -> 0 | AC65: =+SUM(CP65:CS65) -> 0 | AD65: =+SUM(CT65:CW65) -> 0 | AE65: =+SUM(CX65:DA65) -> 0 | AI65: ='QTR Raw'!C35 -> 0 | AJ65: ='QTR Raw'!D35 -> 0 | AK65: ='QTR Raw'!E35 -> 0 | AL65: ='QTR Raw'!F35 -> 0 | AM65: ='QTR Raw'!G35 -> 0 | AN65: ='QTR Raw'!H35 -> 0 | AO65: ='QTR Raw'!I35 -> 0 | AP65: ='QTR Raw'!J35 -> 0 | ... CL65: ='QTR Raw'!BF35 -> 0 | CM65: =+CL65 -> 0 | CN65: =+CM65 -> 0 | CO65: =+CN65 -> 0 | CP65: =+CO65 -> 0 | CQ65: =+CP65 -> 0 | CR65: =+CQ65 -> 0 | CS65: =+CR65 -> 0 | CT65: =+CS65 -> 0 | ... DA65: =+CZ65 -> 0 | DD65: 0 | DE65: 0
A66: Exceptional Income / Expenses | B66: ='Annual Raw'!C29+'Annual Raw'!C31+'Annual Raw'!C34+'Annual Raw'!C36 -> 0 | C66: ='Annual Raw'!D29+'Annual Raw'!D31+'Annual Raw'!D34+'Annual Raw'!D36 -> 0 | D66: ='Annual Raw'!E29+'Annual Raw'!E31+'Annual Raw'!E34+'Annual Raw'!E36 -> 0 | E66: ='Annual Raw'!F29+'Annual Raw'!F31+'Annual Raw'!F34+'Annual Raw'!F36 -> 0 | F66: ='Annual Raw'!G29+'Annual Raw'!G31+'Annual Raw'!G34+'Annual Raw'!G36 -> 0 | G66: ='Annual Raw'!H29+'Annual Raw'!H31+'Annual Raw'!H34+'Annual Raw'!H36 -> 0 | H66: ='Annual Raw'!I29+'Annual Raw'!I31+'Annual Raw'!I34+'Annual Raw'!I36 -> 0 | I66: ='Annual Raw'!J29+'Annual Raw'!J31+'Annual Raw'!J34+'Annual Raw'!J36 -> 0 | ... AA66: ='Annual Raw'!AB29+'Annual Raw'!AB31+'Annual Raw'!AB34+'Annual Raw'!AB36 -> -11.4086 | AB66: =+SUM(CL66:CO66) -> 2.392 | AC66: =+SUM(CP66:CS66) -> 0 | AD66: =+SUM(CT66:CW66) -> 0 | AE66: =+SUM(CX66:DA66) -> 0 | AI66: ='QTR Raw'!C26+'QTR Raw'!C31+'QTR Raw'!C32+'QTR Raw'!C33+'QTR Raw'!C36+'QTR Raw'!C37+'QTR Raw'!C39 -> 0 | AJ66: ='QTR Raw'!D26+'QTR Raw'!D31+'QTR Raw'!D32+'QTR Raw'!D33+'QTR Raw'!D36+'QTR Raw'!D37+'QTR Raw'!D39 -> 0 | AK66: ='QTR Raw'!E26+'QTR Raw'!E31+'QTR Raw'!E32+'QTR Raw'!E33+'QTR Raw'!E36+'QTR Raw'!E37+'QTR Raw'!E39 -> 0 | AL66: ='QTR Raw'!F26+'QTR Raw'!F31+'QTR Raw'!F32+'QTR Raw'!F33+'QTR Raw'!F36+'QTR Raw'!F37+'QTR Raw'!F39 -> 0 | AM66: ='QTR Raw'!G26+'QTR Raw'!G31+'QTR Raw'!G32+'QTR Raw'!G33+'QTR Raw'!G36+'QTR Raw'!G37+'QTR Raw'!G39 -> 0 | AN66: ='QTR Raw'!H26+'QTR Raw'!H31+'QTR Raw'!H32+'QTR Raw'!H33+'QTR Raw'!H36+'QTR Raw'!H37+'QTR Raw'!H39 -> 0 | AO66: ='QTR Raw'!I26+'QTR Raw'!I31+'QTR Raw'!I32+'QTR Raw'!I33+'QTR Raw'!I36+'QTR Raw'!I37+'QTR Raw'!I39 -> 0 | AP66: ='QTR Raw'!J26+'QTR Raw'!J31+'QTR Raw'!J32+'QTR Raw'!J33+'QTR Raw'!J36+'QTR Raw'!J37+'QTR Raw'!J39 -> 0 | ... CL66: ='QTR Raw'!BF26+'QTR Raw'!BF31+'QTR Raw'!BF32+'QTR Raw'!BF33+'QTR Raw'!BF36+'QTR Raw'!BF37+'QTR Raw'!BF39 -> 2.392 | DD66: -11.409
A67: Consolidated Net Profit | B67: =B60+B64+B65+B66 -> -4.6812965 | C67: =C60+C64+C65+C66 -> 6.0145299 | D67: =D60+D64+D65+D66 -> 0 | E67: =E60+E64+E65+E66 -> 0 | F67: =F60+F64+F65+F66 -> 0 | G67: =G60+G64+G65+G66 -> 0 | H67: =H60+H64+H65+H66 -> 0 | I67: =I60+I64+I65+I66 -> 0 | ... AE67: =AE60+AE64+AE65+AE66 -> 546.22675 | AI67: =AI60+AI64+AI65+AI66 -> 4.465 | AJ67: =AJ60+AJ64+AJ65+AJ66 -> -3.717 | AK67: =AK60+AK64+AK65+AK66 -> 1.695 | AL67: =AL60+AL64+AL65+AL66 -> -3.437 | AM67: =AM60+AM64+AM65+AM66 -> -13.758 | AN67: =AN60+AN64+AN65+AN66 -> -18.508 | AO67: =AO60+AO64+AO65+AO66 -> 11.531 | AP67: =AP60+AP64+AP65+AP66 -> -1.576 | ... DA67: =DA60+DA64+DA65+DA66 -> 171.16871 | DD67: 1.5670477 | DE67: 16.869686
A68: Profit & Loss- Annual (End)
A69: Rat
A70: Ace - PAT | B70: ='Annual Raw'!C35 -> -4.6812965 | C70: ='Annual Raw'!D35 -> 6.0145299 | D70: ='Annual Raw'!E35 -> 0 | E70: ='Annual Raw'!F35 -> 0 | F70: ='Annual Raw'!G35 -> 0 | G70: ='Annual Raw'!H35 -> 0 | H70: ='Annual Raw'!I35 -> 0 | I70: ='Annual Raw'!J35 -> 0 | ... AA70: ='Annual Raw'!AB35 -> 10.3139 | AB70: =+AB67 -> 54.594005 | AC70: =+AC67 -> 178.49183 | AD70: =+AD67 -> 343.63299 | AE70: =+AE67 -> 546.22675 | AI70: ='QTR Raw'!C42 -> 4.466 | AJ70: ='QTR Raw'!D42 -> -3.717 | AK70: ='QTR Raw'!E42 -> 1.695 | AL70: ='QTR Raw'!F42 -> -3.437 | AM70: ='QTR Raw'!G42 -> -13.758 | AN70: ='QTR Raw'!H42 -> -18.51 | AO70: ='QTR Raw'!I42 -> 11.531 | AP70: ='QTR Raw'!J42 -> -1.576 | ... CJ70: ='QTR Raw'!BD42 -> 8.919 | CK70: -8.9219 | CL70: ='QTR Raw'!BF42 -> 7.361 | DD70: -29.1759
A71: Checksum - PAT | B71: =B70-B67 -> 0 | C71: =C70-C67 -> -1.4210855e-14 | D71: =D70-D67 -> 0 | E71: =E70-E67 -> 0 | F71: =F70-F67 -> 0 | G71: =G70-G67 -> 0 | H71: =H70-H67 -> 0 | I71: =I70-I67 -> 0 | ... AE71: =AE70-AE67 -> 0 | AI71: =AI70-AI67 -> 0.001 | AJ71: =AJ70-AJ67 -> -9.3258734e-15 | AK71: =AK70-AK67 -> -4.2188475e-15 | AL71: =AL70-AL67 -> 1.6431301e-14 | AM71: =AM70-AM67 -> 0 | AN71: =AN70-AN67 -> -0.002 | AO71: =AO70-AO67 -> 0 | AP71: =AP70-AP67 -> 1.9095836e-14 | ... CL71: =CL70-CL67 -> 0 | DD71: 0
A72: Ratios (Start)
A73: ROE (%) | B73: =(B67-B66)/B139 -> -0.1027573 | C73: =(C67-C66)/C139 -> 0.11978513 | D73: =(D67-D66)/D139 -> #DIV/0! | E73: =(E67-E66)/E139 -> #DIV/0! | F73: =(F67-F66)/F139 -> #DIV/0! | G73: =(G67-G66)/G139 -> #DIV/0! | H73: =(H67-H66)/H139 -> #DIV/0! | I73: =(I67-I66)/I139 -> #DIV/0! | ... AE73: =(AE67-AE66)/AE139 -> 0.40974497 | AL73: =(SUM(AI67:AL67)-SUM(AI66:AL66))/AL139 -> 0.2892057 | AM73: =(SUM(AJ67:AM67)-SUM(AJ66:AM66))/AM139 -> #DIV/0! | AN73: =(SUM(AK67:AN67)-SUM(AK66:AN66))/AN139 -> 1.8374757 | AO73: =(SUM(AL67:AO67)-SUM(AL66:AO66))/AO139 -> #DIV/0! | AP73: =(SUM(AM67:AP67)-SUM(AM66:AP66))/AP139 -> 14.156726 | AQ73: =(SUM(AN67:AQ67)-SUM(AN66:AQ66))/AQ139 -> #DIV/0! | AR73: =(SUM(AO67:AR67)-SUM(AO66:AR66))/AR139 -> 1.9428504 | AS73: =(SUM(AP67:AS67)-SUM(AP66:AS66))/AS139 -> #DIV/0! | ... DA73: =(SUM(CX67:DA67)-SUM(CX66:DA66))/DA139 -> 0.40974497 | DD73: -0.084546311 | DE73: 0.17328332
A74: ROCE (%) | B74: =+B53/B148 -> -0.085495679 | C74: =+C53/C148 -> 0.14816691 | D74: =+D53/D148 -> #DIV/0! | E74: =+E53/E148 -> #DIV/0! | F74: =+F53/F148 -> #DIV/0! | G74: =+G53/G148 -> #DIV/0! | H74: =+H53/H148 -> #DIV/0! | I74: =+I53/I148 -> #DIV/0! | ... AE74: =+AE53/AE148 -> 0.50962913 | AL74: =+SUM(AI53:AL53)/AL148 -> 1.8609252 | AM74: =+SUM(AJ53:AM53)/AM148 -> #DIV/0! | AN74: =+SUM(AK53:AN53)/AN148 -> 2.1793819 | AO74: =+SUM(AL53:AO53)/AO148 -> #DIV/0! | AP74: =+SUM(AM53:AP53)/AP148 -> 22.120558 | AQ74: =+SUM(AN53:AQ53)/AQ148 -> #DIV/0! | AR74: =+SUM(AO53:AR53)/AR148 -> -2.7782784 | AS74: =+SUM(AP53:AS53)/AS148 -> #DIV/0! | ... DA74: =+SUM(CX53:DA53)/DA148 -> 0.50962913 | DD74: -0.23667723 | DE74: 0.14652674
A75: Ratios (End)
A76: Checksum Of qtr to Annual
A77: Revenue - Checksum Of qtr to Annual | N77: =N29-SUM(AI29:AL29) -> -530.078 | R77: =R29-SUM(AX29:BA29) -> -175.265 | S77: =S29-SUM(BB29:BE29) -> -271.302 | T77: =T29-SUM(BF29:BI29) -> -448.877 | U77: =U29-SUM(BJ29:BM29) -> -432.296 | V77: =V29-SUM(BN29:BQ29) -> -198.278 | W77: =W29-SUM(BR29:BU29) -> -381.35 | X77: =X29-SUM(BV29:BY29) -> -354.366 | Y77: =Y29-SUM(BZ29:CC29) -> -192.6067 | Z77: =Z29-SUM(CD29:CG29) -> -0.001 | AA77: =AA29-SUM(CE29:CH29) -> -104.9682 | AB77: =AB29-SUM(CL29:CO29) -> 0 | AC77: =AC29-SUM(CP29:CS29) -> 0 | AD77: =AD29-SUM(CT29:CW29) -> 0 | AE77: =AE29-SUM(CX29:DA29) -> 0 | DD77: 333.6035
A78: GP - Checksum Of qtr to Annual | N78: =N35-SUM(AI35:AL35) -> -150.7 | R78: =R35-SUM(AX35:BA35) -> -88.682 | S78: =S35-SUM(BB35:BE35) -> -99.612 | T78: =T35-SUM(BF35:BI35) -> -144.327 | U78: =U35-SUM(BJ35:BM35) -> -180.979 | V78: =V35-SUM(BN35:BQ35) -> -81.093 | W78: =W35-SUM(BR35:BU35) -> -106.104 | X78: =X35-SUM(BV35:BY35) -> -148.547 | Y78: =Y35-SUM(BZ35:CC35) -> -688.0973 | Z78: =Z35-SUM(CD35:CG35) -> -246.1437 | AA78: =AA35-SUM(CE35:CH35) -> -168.6184 | AB78: =AB35-SUM(CL35:CO35) -> 0 | AC78: =AC35-SUM(CP35:CS35) -> 0 | AD78: =AD35-SUM(CT35:CW35) -> 0 | AE78: =AE35-SUM(CX35:DA35) -> 0 | DD78: 81.7705
A79: EBITDA - Checksum Of qtr to Annual | N79: =N47-SUM(AI47:AL47) -> 1.792 | R79: =R47-SUM(AX47:BA47) -> 1.975 | S79: =S47-SUM(BB47:BE47) -> -8.496 | T79: =T47-SUM(BF47:BI47) -> -24.064 | U79: =U47-SUM(BJ47:BM47) -> -24.755 | V79: =V47-SUM(BN47:BQ47) -> 18.402 | W79: =W47-SUM(BR47:BU47) -> -1.566 | X79: =X47-SUM(BV47:BY47) -> 3.754 | Y79: =Y47-SUM(BZ47:CC47) -> -11.3495 | Z79: =Z47-SUM(CD47:CG47) -> -0.002 | AA79: =AA47-SUM(CE47:CH47) -> 32.4762 | AB79: =AB47-SUM(CL47:CO47) -> 1.4210855e-13 | AC79: =AC47-SUM(CP47:CS47) -> 0 | AD79: =AD47-SUM(CT47:CW47) -> 4.5474735e-13 | AE79: =AE47-SUM(CX47:DA47) -> 0 | DD79: -30.7551
A80: PAT - Checksum Of qtr to Annual | N80: =N67-SUM(AI67:AL67) -> 0.994 | R80: =R60-SUM(AX60:BA60) -> 2.432 | S80: =S60-SUM(BB60:BE60) -> -12.297 | T80: =T60-SUM(BF60:BI60) -> -28.622 | U80: =U60-SUM(BJ60:BM60) -> -24.697 | V80: =V60-SUM(BN60:BQ60) -> 15.574 | W80: =W60-SUM(BR60:BU60) -> 1.865 | X80: =X60-SUM(BV60:BY60) -> -0.639 | Y80: =Y60-SUM(BZ60:CC60) -> -9.7938 | Z80: =Z60-SUM(CD60:CG60) -> -0.0031 | AA80: =AA60-SUM(CE60:CH60) -> 33.6345 | AB80: =AB60-SUM(CL60:CO60) -> 1.4210855e-13 | AC80: =AC60-SUM(CP60:CS60) -> 0 | AD80: =AD60-SUM(CT60:CW60) -> 0 | AE80: =AE60-SUM(CX60:DA60) -> 0 | DD80: -27.9776
A81: Valuation (Start)
A82: Eq | B82: ='Annual Raw'!C104 -> 4.937813 | C82: ='Annual Raw'!D104 -> 4.937813 | D82: ='Annual Raw'!E104 -> 0 | E82: =+F82 -> 0 | F82: =+G82 -> 0 | G82: =+H82 -> 0 | H82: =+I82 -> 0 | I82: =+J82 -> 0 | J82: =+K82 -> 0 | K82: =+L82 -> 0 | L82: =+M82 -> 0 | ... AA82: =+AB82 -> 0 | AB82: =AA82 -> 0 | AC82: =AB82 -> 0 | AD82: =AC82 -> 0 | AE82: =AD82 -> 0 | AI82: =+AJ82 -> 4.938 | AJ82: =+AK82 -> 4.938 | AK82: =+AL82 -> 4.938 | AL82: =+AM82 -> 4.938 | AM82: =+AN82 -> 4.938 | AN82: =+AO82 -> 4.938 | AO82: =+AP82 -> 4.938 | AP82: =+AQ82 -> 4.938 | ... CI82: =+CJ82 -> 4.938 | CJ82: ='QTR Raw'!BD45 -> 4.938 | CK82: ='QTR Raw'!BE45 -> 4.938 | CL82: ='QTR Raw'!BF45 -> 4.938 | CM82: 5.28907 | CN82: =+CM82 -> 5.28907 | CO82: =+CN82 -> 5.28907 | CP82: =+CO82 -> 5.28907 | CQ82: =+CP82 -> 5.28907 | CR82: =+CQ82 -> 5.28907 | CS82: =+CR82 -> 5.28907 | CT82: =+CS82 -> 5.28907 | CU82: =+CT82 -> 5.28907 | ... DA82: =+CZ82 -> 5.28907 | DD82: 4.938 | DE82: 4.938
A83: FV | B83: ='Annual Raw'!C105 -> 10 | C83: ='Annual Raw'!D105 -> 10 | D83: ='Annual Raw'!E105 -> 0 | E83: =+F83 -> 0 | F83: =+G83 -> 0 | G83: =+H83 -> 0 | H83: =+I83 -> 0 | I83: =+J83 -> 0 | J83: =+K83 -> 0 | K83: =+L83 -> 0 | L83: =+M83 -> 0 | ... AA83: =+AB83 -> 0 | AB83: =AA83 -> 0 | AC83: =AB83 -> 0 | AD83: =AC83 -> 0 | AE83: =AD83 -> 0 | AI83: =AJ83 -> 10 | AJ83: =AK83 -> 10 | AK83: =AL83 -> 10 | AL83: =AM83 -> 10 | AM83: =AN83 -> 10 | AN83: =AO83 -> 10 | AO83: =AP83 -> 10 | AP83: =AQ83 -> 10 | ... CI83: =CJ83 -> 10 | CJ83: ='QTR Raw'!BD46 -> 10 | CK83: ='QTR Raw'!BE46 -> 10 | CL83: ='QTR Raw'!BF46 -> 10 | CM83: =+CL83 -> 10 | CN83: =+CM83 -> 10 | CO83: =+CN83 -> 10 | CP83: =+CO83 -> 10 | CQ83: =+CP83 -> 10 | CR83: =+CQ83 -> 10 | CS83: =+CR83 -> 10 | CT83: =+CS83 -> 10 | ... DA83: =+CZ83 -> 10 | DD83: 10 | DE83: 10
A84: No of share | B84: =B82/B83 -> 0.4937813 | C84: =C82/C83 -> 0.4937813 | D84: =D82/D83 -> #DIV/0! | E84: =E82/E83 -> #DIV/0! | F84: =F82/F83 -> #DIV/0! | G84: =G82/G83 -> #DIV/0! | H84: =H82/H83 -> #DIV/0! | I84: =I82/I83 -> #DIV/0! | ... AE84: =AE82/AE83 -> #DIV/0! | AI84: =AI82/AI83 -> 0.4938 | AJ84: =AJ82/AJ83 -> 0.4938 | AK84: =AK82/AK83 -> 0.4938 | AL84: =AL82/AL83 -> 0.4938 | AM84: =AM82/AM83 -> 0.4938 | AN84: =AN82/AN83 -> 0.4938 | AO84: =AO82/AO83 -> 0.4938 | AP84: =AP82/AP83 -> 0.4938 | ... DA84: =DA82/DA83 -> 0.528907 | DD84: 0.4938 | DE84: 0.4938
A85: EPS | B85: =(B67-B66)/B84 -> -9.4805059 | C85: =(C67-C66)/C84 -> 12.180554 | D85: =(D67-D66)/D84 -> #DIV/0! | E85: =(E67-E66)/E84 -> #DIV/0! | F85: =(F67-F66)/F84 -> #DIV/0! | G85: =(G67-G66)/G84 -> #DIV/0! | H85: =(H67-H66)/H84 -> #DIV/0! | I85: =(I67-I66)/I84 -> #DIV/0! | ... AE85: =(AE67-AE66)/AE84 -> #DIV/0! | AI85: =(AI67-AI66)/AI84 -> 9.0421223 | AJ85: =(AJ67-AJ66)/AJ84 -> -7.527339 | AK85: =(AK67-AK66)/AK84 -> 3.4325638 | AL85: =(AL67-AL66)/AL84 -> -6.9603078 | AM85: =(AM67-AM66)/AM84 -> -27.861482 | AN85: =(AN67-AN66)/AN84 -> -37.480761 | AO85: =(AO67-AO66)/AO84 -> 23.351559 | AP85: =(AP67-AP66)/AP84 -> -3.1915755 | ... DA85: =(DA67-DA66)/DA84 -> 323.62723 | DD85: -35.979951 | DE85: 34.162992
A86: DPS | B86: ='Annual Raw'!C110 -> 0 | C86: ='Annual Raw'!D110 -> 2.5 | D86: ='Annual Raw'!E110 -> 0 | E86: ='Annual Raw'!F110 -> 0 | F86: ='Annual Raw'!G110 -> 0 | G86: ='Annual Raw'!H110 -> 0 | H86: ='Annual Raw'!I110 -> 0 | I86: ='Annual Raw'!J110 -> 0 | ... AA86: ='Annual Raw'!AB110 -> 7
A87: DPS % of EPS | B87: =B86/B85 -> 0 | C87: =C86/C85 -> 0.20524518 | D87: =D86/D85 -> #DIV/0! | E87: =E86/E85 -> #DIV/0! | F87: =F86/F85 -> #DIV/0! | G87: =G86/G85 -> #DIV/0! | H87: =H86/H85 -> #DIV/0! | I87: =I86/I85 -> #DIV/0! | ... AE87: =AE86/AE85 -> #DIV/0! | DD87: 0
A88: EPS TTM | B88: =+B85 -> -9.4805059 | C88: =+C85 -> 12.180554 | D88: =+D85 -> #DIV/0! | E88: =+E85 -> #DIV/0! | F88: =+F85 -> #DIV/0! | G88: =+G85 -> #DIV/0! | H88: =+H85 -> #DIV/0! | I88: =+I85 -> #DIV/0! | ... AE88: =+AE85 -> #DIV/0! | AL88: =SUM(AI85:AL85) -> -2.0129607 | AM88: =SUM(AJ85:AM85) -> -38.916565 | AN88: =SUM(AK85:AN85) -> -68.869988 | AO88: =SUM(AL85:AO85) -> -48.950992 | AP88: =SUM(AM85:AP85) -> -45.18226 | AQ88: =SUM(AN85:AQ85) -> -22.658971 | AR88: =SUM(AO85:AR85) -> 16.591738 | AS88: =SUM(AP85:AS85) -> -6.5188335 | ... DA88: =SUM(CX85:DA85) -> 1032.7463 | DD88: -35.979951 | DE88: 79.663195
A89: EPS Growth YoY % | C89: =+C88/B88-1 -> -2.2848 | D89: =+D88/C88-1 -> #DIV/0! | E89: =+E88/D88-1 -> #DIV/0! | F89: =+F88/E88-1 -> #DIV/0! | G89: =+G88/F88-1 -> #DIV/0! | H89: =+H88/G88-1 -> #DIV/0! | I89: =+I88/H88-1 -> #DIV/0! | J89: =+J88/I88-1 -> #DIV/0! | ... AE89: =+AE88/AD88-1 -> #DIV/0! | AP89: =+IF(AL88<0,1-AP88/AL88,AP88/AL88-1) -> -21.445674 | AQ89: =+IF(AM88<0,1-AQ88/AM88,AQ88/AM88-1) -> 0.41775511 | AR89: =+IF(AN88<0,1-AR88/AN88,AR88/AN88-1) -> 1.2409139 | AS89: =+IF(AO88<0,1-AS88/AO88,AS88/AO88-1) -> 0.86682939 | AT89: =+IF(AP88<0,1-AT88/AP88,AT88/AP88-1) -> 1.1752499 | AU89: =+IF(AQ88<0,1-AU88/AQ88,AU88/AQ88-1) -> 1.6686925 | AV89: =+IF(AR88<0,1-AV88/AR88,AV88/AR88-1) -> -0.5354571 | AW89: =+IF(AS88<0,1-AW88/AS88,AW88/AS88-1) -> 3.4799627 | ... DA89: =+IF(CW88<0,1-DA88/CW88,DA88/CW88-1) -> 0.58956438 | DD89: 2.3011092 | DE89: 4.3023578
A90: Bloomberg Estimate
A91: Estimate deviation
A92: Promoter Share holding % | B92: ='Annual Raw'!C112 -> 0 | C92: ='Annual Raw'!D112 -> 54.91 | D92: ='Annual Raw'!E112 -> 0 | E92: ='Annual Raw'!F112 -> 0 | F92: ='Annual Raw'!G112 -> 0 | G92: ='Annual Raw'!H112 -> 0 | H92: ='Annual Raw'!I112 -> 0 | I92: ='Annual Raw'!J112 -> 0 | ... AA92: ='Annual Raw'!AB112 -> 70.44 | AI92: ='QTR Raw'!C49 -> 75 | AJ92: ='QTR Raw'!D49 -> 75 | AK92: ='QTR Raw'!E49 -> 75 | AL92: ='QTR Raw'!F49 -> 75 | AM92: ='QTR Raw'!G49 -> 75 | AN92: ='QTR Raw'!H49 -> 75 | AO92: ='QTR Raw'!I49 -> 75 | AP92: ='QTR Raw'!J49 -> 75 | ... CL92: ='QTR Raw'!BF49 -> 70.44
A93: Pledge Share % | B93: ='Annual Raw'!C113 -> 0 | C93: ='Annual Raw'!D113 -> 0 | D93: ='Annual Raw'!E113 -> 0 | E93: ='Annual Raw'!F113 -> 0 | F93: ='Annual Raw'!G113 -> 0 | G93: ='Annual Raw'!H113 -> 0 | H93: ='Annual Raw'!I113 -> 0 | I93: ='Annual Raw'!J113 -> 0 | ... AA93: ='Annual Raw'!AB113 -> 0 | AI93: ='QTR Raw'!C50 -> 0 | AJ93: ='QTR Raw'!D50 -> 0 | AK93: ='QTR Raw'!E50 -> 0 | AL93: ='QTR Raw'!F50 -> 0 | AM93: ='QTR Raw'!G50 -> 0 | AN93: ='QTR Raw'!H50 -> 0 | AO93: ='QTR Raw'!I50 -> 0 | AP93: ='QTR Raw'!J50 -> 0 | ... CL93: ='QTR Raw'!BF50 -> 0
A95: Share Price
A96: Share Price - Close | B96: ='Annual Raw'!C106 -> 16.5 | C96: ='Annual Raw'!D106 -> 15.85 | D96: ='Annual Raw'!E106 -> 0 | E96: ='Annual Raw'!F106 -> 0 | F96: ='Annual Raw'!G106 -> 0 | G96: ='Annual Raw'!H106 -> 0 | H96: ='Annual Raw'!I106 -> 0 | I96: ='Annual Raw'!J106 -> 0 | ... AA96: ='Annual Raw'!AB106 -> 5268.95 | AB96: =+CO96 -> 7600 | AC96: =+CS96 -> 7600 | AD96: =+CW96 -> 7600 | AE96: =+DA96 -> 7600 | AJ96: ='QTR Share Price'!HP21 -> 705.5 | AK96: ='QTR Share Price'!HQ21 -> 660 | AL96: ='QTR Share Price'!HR21 -> 372.95 | AM96: ='QTR Share Price'!HS21 -> 330 | AN96: ='QTR Share Price'!HT21 -> 263 | AO96: ='QTR Share Price'!HU21 -> 314.4 | AP96: ='QTR Share Price'!HV21 -> 445 | AQ96: ='QTR Share Price'!HW21 -> 512.6 | ... CL96: ='QTR Share Price'!JR21 -> 4082.2 | CM96: 7600 | CN96: =+CM96 -> 7600 | CO96: =+CN96 -> 7600 | CP96: =+CO96 -> 7600 | CQ96: =+CP96 -> 7600 | CR96: =+CQ96 -> 7600 | CS96: =+CR96 -> 7600 | CT96: =+CS96 -> 7600 | CU96: =+CT96 -> 7600 | ... DA96: =+CZ96 -> 7600 | DD96: 5268.95 | DE96: 5268.95
A97: Share Price - High | B97: ='Annual Raw'!C107 -> 46 | C97: ='Annual Raw'!D107 -> 28.95 | D97: ='Annual Raw'!E107 -> 0 | E97: ='Annual Raw'!F107 -> 0 | F97: ='Annual Raw'!G107 -> 0 | G97: ='Annual Raw'!H107 -> 0 | H97: ='Annual Raw'!I107 -> 0 | I97: ='Annual Raw'!J107 -> 0 | ... AA97: ='Annual Raw'!AB107 -> 6660 | AB97: =+MAX(CL97:CO97) -> 5961.9494 | AC97: =+MAX(CP97:CS97) -> 20248.38 | AD97: =+MAX(CT97:CW97) -> 38982.239 | AE97: =+MAX(CX97:DA97) -> 61964.779 | AJ97: ='QTR Share Price'!HP19 -> 824.4 | AK97: ='QTR Share Price'!HQ19 -> 832 | AL97: ='QTR Share Price'!HR19 -> 668 | AM97: ='QTR Share Price'!HS19 -> 424.9 | AN97: ='QTR Share Price'!HT19 -> 337 | AO97: ='QTR Share Price'!HU19 -> 320 | AP97: ='QTR Share Price'!HV19 -> 466.5 | AQ97: ='QTR Share Price'!HW19 -> 598 | ... CL97: ='QTR Share Price'!JR19 -> 5940 | CM97: =+CM88*CM105 -> 1395.4281 | CN97: =+CN88*CN105 -> 2981.5985 | CO97: =+CO88*CO105 -> 5961.9494 | CP97: =+CP88*CP105 -> 8026.0731 | CQ97: =+CQ88*CQ105 -> 11571.665 | CR97: =+CR88*CR105 -> 15892.284 | CS97: =+CS88*CS105 -> 20248.38 | CT97: =+CT88*CT105 -> 24404.449 | ... DA97: =+DA88*DA105 -> 61964.779 | DD97: 6660 | DE97: 13398.23
A98: Share Price - Low | B98: ='Annual Raw'!C108 -> 13.85 | C98: ='Annual Raw'!D108 -> 10.75 | D98: ='Annual Raw'!E108 -> 0 | E98: ='Annual Raw'!F108 -> 0 | F98: ='Annual Raw'!G108 -> 0 | G98: ='Annual Raw'!H108 -> 0 | H98: ='Annual Raw'!I108 -> 0 | I98: ='Annual Raw'!J108 -> 0 | ... AA98: ='Annual Raw'!AB108 -> 2383 | AB98: =+MIN(CL98:CO98) -> 930.28537 | AC98: =+MIN(CP98:CS98) -> 5350.7154 | AD98: =+MIN(CT98:CW98) -> 16269.633 | AE98: =+MIN(CX98:DA98) -> 29352.325 | AJ98: =+'QTR Share Price'!HP20 -> 651 | AK98: =+'QTR Share Price'!HQ20 -> 640 | AL98: =+'QTR Share Price'!HR20 -> 361.1 | AM98: =+'QTR Share Price'!HS20 -> 318.25 | AN98: =+'QTR Share Price'!HT20 -> 207.2 | AO98: =+'QTR Share Price'!HU20 -> 231 | AP98: =+'QTR Share Price'!HV20 -> 305.5 | AQ98: =+'QTR Share Price'!HW20 -> 451 | ... CL98: =+'QTR Share Price'!JR20 -> 4041.05 | CM98: =+CM106*CM88 -> 930.28537 | CN98: =+CN106*CN88 -> 1987.7323 | CO98: =+CO106*CO88 -> 3974.6329 | CP98: =+CP106*CP88 -> 5350.7154 | CQ98: =+CQ106*CQ88 -> 7714.4435 | CR98: =+CR106*CR88 -> 10594.856 | CS98: =+CS106*CS88 -> 13498.92 | CT98: =+CT106*CT88 -> 16269.633 | ... DA98: =+DA106*DA88 -> 41309.852 | DD98: 2383 | DE98: 3983.1597
A100: Upside (%) | AB100: =+AB97/AB96-1 -> -0.21553298 | AC100: =+AC97/AC96-1 -> 1.6642605 | AD100: =+AD97/AD96-1 -> 4.129242 | AE100: =+AE97/AE96-1 -> 7.1532603 | CM100: =+CM97/CM96-1 -> -0.81639105 | CN100: =+CN97/CN96-1 -> -0.60768441 | CO100: =+CO97/CO96-1 -> -0.21553298 | CP100: =+CP97/CP96-1 -> 0.056062251 | CQ100: =+CQ97/CQ96-1 -> 0.52258754 | CR100: =+CR97/CR96-1 -> 1.09109 | CS100: =+CS97/CS96-1 -> 1.6642605 | CT100: =+CT97/CT96-1 -> 2.2111118 | ... DA100: =+DA97/DA96-1 -> 7.1532603 | DD100: 0.26400896 | DE100: 1.5428652
A101: Downside (%) | AB101: =+AB98/AB96-1 -> -0.87759403 | AC101: =+AC98/AC96-1 -> -0.2959585 | AD101: =+AD98/AD96-1 -> 1.1407412 | AE101: =+AE98/AE96-1 -> 2.862148 | CM101: =+CM98/CM96-1 -> -0.87759403 | CN101: =+CN98/CN96-1 -> -0.73845627 | CO101: =+CO98/CO96-1 -> -0.47702198 | CP101: =+CP98/CP96-1 -> -0.2959585 | CQ101: =+CQ98/CQ96-1 -> 0.01505836 | CR101: =+CR98/CR96-1 -> 0.39405998 | CS101: =+CS98/CS96-1 -> 0.7761737 | CT101: =+CT98/CT96-1 -> 1.1407412 | ... DA101: =+DA98/DA96-1 -> 4.4355069 | DD101: -0.54772773 | DE101: -0.24403159
A103: PE
A104: PE - Close | B104: =+B96/B88 -> -1.7404134 | C104: =+C96/C88 -> 1.3012544 | D104: =+D96/D88 -> #DIV/0! | E104: =+E96/E88 -> #DIV/0! | F104: =+F96/F88 -> #DIV/0! | G104: =+G96/G88 -> #DIV/0! | H104: =+H96/H88 -> #DIV/0! | I104: =+I96/I88 -> #DIV/0! | ... AE104: =+AE96/AE88 -> #DIV/0! | AL104: =+AL96/AL88 -> -185.27436 | AM104: =+AM96/AM88 -> -8.4796795 | AN104: =+AN96/AN88 -> -3.8187897 | AO104: =+AO96/AO88 -> -6.4227503 | AP104: =+AP96/AP88 -> -9.8489983 | AQ104: =+AQ96/AQ88 -> -22.622386 | AR104: =+AR96/AR88 -> 27.784914 | AS104: =+AS96/AS88 -> -77.467847 | ... DA104: =+DA96/DA88 -> 7.3590193 | DD104: -146.44128 | DE104: 66.14033
A105: PE - High | B105: =+B97/B88 -> -4.8520617 | C105: =+C97/C88 -> 2.3767392 | D105: =+D97/D88 -> #DIV/0! | E105: =+E97/E88 -> #DIV/0! | F105: =+F97/F88 -> #DIV/0! | G105: =+G97/G88 -> #DIV/0! | H105: =+H97/H88 -> #DIV/0! | I105: =+I97/I88 -> #DIV/0! | ... AE105: =+AE97/AE88 -> #DIV/0! | AL105: =+AL97/AL88 -> -331.8495 | AM105: =+AM97/AM88 -> -10.91823 | AN105: =+AN97/AN88 -> -4.8932781 | AO105: =+AO97/AO88 -> -6.5371504 | AP105: =+AP97/AP88 -> -10.324849 | AQ105: =+AQ97/AQ88 -> -26.391313 | AR105: =+AR97/AR88 -> 35.761776 | AS105: =+AS97/AS88 -> -91.573131 | ... CL105: =+CL97/CL88 -> 162.11013 | CM105: 60 | CN105: =+CM105 -> 60 | CO105: =+CN105 -> 60 | CP105: =+CO105 -> 60 | CQ105: =+CP105 -> 60 | CR105: =+CQ105 -> 60 | CS105: =+CR105 -> 60 | CT105: =+CS105 -> 60 | CU105: =+CT105 -> 60 | ... DA105: =+CZ105 -> 60 | DD105: -185.10308 | DE105: 168.18595
A106: PE - Low | B106: =+B98/B88 -> -1.4608925 | C106: =+C98/C88 -> 0.88255426 | D106: =+D98/D88 -> #DIV/0! | E106: =+E98/E88 -> #DIV/0! | F106: =+F98/F88 -> #DIV/0! | G106: =+G98/G88 -> #DIV/0! | H106: =+H98/H88 -> #DIV/0! | I106: =+I98/I88 -> #DIV/0! | ... AE106: =+AE98/AE88 -> #DIV/0! | AL106: =+AL98/AL88 -> -179.38751 | AM106: =+AM98/AM88 -> -8.1777515 | AN106: =+AN98/AN88 -> -3.0085674 | AO106: =+AO98/AO88 -> -4.7190055 | AP106: =+AP98/AP88 -> -6.7615033 | AQ106: =+AQ98/AQ88 -> -19.903816 | AR106: =+AR98/AR88 -> 24.111399 | AS106: =+AS98/AS88 -> -64.428705 | ... CL106: =+CL98/CL88 -> 110.28538 | CM106: 40 | CN106: =+CM106 -> 40 | CO106: =+CN106 -> 40 | CP106: =+CO106 -> 40 | CQ106: =+CP106 -> 40 | CR106: =+CQ106 -> 40 | CS106: =+CR106 -> 40 | CT106: =+CS106 -> 40 | CU106: =+CT106 -> 40 | ... DA106: =+CZ106 -> 40 | DD106: -66.231329 | DE106: 50
A108: PE - 1Yr Fwd | B108: =+B97/C88 -> 3.7765113 | C108: =+C97/D88 -> #DIV/0! | D108: =+D97/E88 -> #DIV/0! | E108: =+E97/F88 -> #DIV/0! | F108: =+F97/G88 -> #DIV/0! | G108: =+G97/H88 -> #DIV/0! | H108: =+H97/I88 -> #DIV/0! | I108: =+I97/J88 -> #DIV/0! | ... AD108: =+AD97/AE88 -> #DIV/0! | AL108: =+AL97/AP88 -> -14.784564 | AM108: =+AM97/AQ88 -> -18.751955 | AN108: =+AN97/AR88 -> 20.311315 | AO108: =+AO97/AS88 -> -49.088537 | AP108: =+AP97/AT88 -> 58.915013 | AQ108: =+AQ97/AU88 -> 39.467041 | AR108: =+AR97/AV88 -> 76.982719 | AS108: =+AS97/AW88 -> 36.925205 | ... CL108: =+CL97/CP88 -> 44.405277 | DD108: 62.999649
A109: Correlation | AO109: =+CORREL(AL88:AO88,AL105:AO105) -> -0.90216255 | AP109: =+CORREL(AM88:AP88,AM105:AP105) -> -0.89030298 | AQ109: =+CORREL(AN88:AQ88,AN105:AQ105) -> -0.91817274 | AR109: =+CORREL(AO88:AR88,AO105:AR105) -> 0.74764165 | AS109: =+CORREL(AP88:AS88,AP105:AS105) -> 0.22294203 | AT109: =+CORREL(AQ88:AT88,AQ105:AT105) -> 0.633815 | AU109: =+CORREL(AR88:AU88,AR105:AU105) -> 0.8347426 | AV109: =+CORREL(AS88:AV88,AS105:AV105) -> 0.82719425 | ... CL109: =+CORREL(CI88:CL88,CI105:CL105) -> 0.61309128
...

Sheet Acquisition
C2: crs
A3: Transactions | B3: 30 Mln Euros | C3: =3*105 -> 315 | D3: Germany (Europe) and China
I7: 58028 | J7: price
I8: 35185 | J8: no of shares | K8: metals shares 1.9746 crs share swap | O8: =+I8*10 -> 351850
I9: =+I7*I8/10^7 -> 204.17152 | O9: =+O8/10^7 -> 0.035185
O10: =+O9*10 -> 0.35185
H13: =+J13/K13 -> 0.49367269 | I13: Pre share | J13: 0.3472 | K13: 0.7033 | M13: 0.3824 | N13: 0.723 | P13: =+M13/N13 -> 0.52890733
M14: =+M13-J13 -> 0.0352 | O14: =+M14*10^7 -> 352000
B15: in crs | M15: =200/M14 -> 5681.8182
A16: JCMI Belgium | B16: 2025
A17: Sales | B17: =3.44*106 -> 364.64 | M17: =7.3*100 -> 730
A18: PAT | B18: =-0.47*105 -> -49.35
A19: Networth | B19: =2.1*105 -> 220.5
A22: JCMI USA | B22: 2025
A23: Sales | B23: =2.4*90 -> 216
A24: PAT | B24: =0.09*90 -> 8.1
A25: Networth | B25: =-0.46*90 -> -41.4 | J25: =J27*500 -> 3750000
J26: 30000 | K26: =J26*20% -> 6000
J27: 7500 | K27: 7500
J28: =J26*J27 -> 225000000 | K28: =K26*K27 -> 45000000
J29: =J28/10^7 -> 22.5 | K29: =K28/10^7 -> 4.5

Sheet OB Data
A2: Date | B2: Order size | C2: Order details
A3: 46127 | B3: 300 | C3: JSW Steel Coated Products Limited Design, Engineering, Supply of Continuous Galvanizing Line (CGL#3) and associated equipment Technical Scope for Continuous Galvanizing Line (CGL) as per list agreed in Technical Scope of supply. Time period: May 2028
A4: 46157 | B4: 470 | C4: Order from JSW Steel Coated Products Limited to Design, Manufacturing, Supply, Supervision of Erection & Commissioning of Pickling Line, 2 Stand cold Rolling Mill, Galvanising line (Cold Rolling Complex) as per list agreed in Technical Scope of supply. Time period: June 2028
A5: 46175 | B5: 1300 | C5: Order from JSW Vijayanagar Metallics Limited to Design, Engineering, Supply, Supervision of Erection & Commissioning of Two Annealing & Coating Line (ACL 1 & ACL 2) and one Annealing & Pickling Line (APL) for CRNO Project. Time period: 36 month

Sheet QTR Raw
A1: ='Annual Raw'!A1 -> 100147 | B1: X | C1: 201206 | D1: 201209 | E1: 201212 | F1: 201303 | G1: 201306 | H1: 201309 | I1: 201312 | J1: 201403 | K1: 201406 | L1: 201409 | M1: 201412 | N1: 201503 | O1: 201506 | P1: 201509 | Q1: 201512 | R1: 201603 | S1: 201606 | T1: 201609 | U1: 201612 | V1: 201703 | W1: 201706 | X1: 201709 | Y1: 201712 | Z1: 201803 | AA1: 201806 | AB1: 201809 | AC1: 201812 | AD1: 201903 | AE1: 201906 | AF1: 201909 | AG1: 201912 | AH1: 202003 | AI1: 202006 | AJ1: 202009 | AK1: 202012 | AL1: 202103 | AM1: 202106 | AN1: 202109 | AO1: 202112 | AP1: 202203 | AQ1: 202206 | AR1: 202209 | AS1: 202212 | AT1: 202303 | AU1: 202306 | AV1: 202309 | AW1: 202312 | AX1: 202403 | AY1: 202406 | AZ1: 202409 | BA1: 202412 | BB1: 202503 | BC1: 202506 | BD1: 202509 | BE1: 202512 | BF1: 202603 | BG1: 202606 | BH1: 202609 | BI1: 202612 | BJ1: 202703 | BK1: 202706 | BL1: 202709 | BM1: 202712 | BN1: 202803 | BO1: 202806 | BP1: 202809 | BQ1: 202812 | BR1: 202903 | BS1: 202906 | BT1: 202909 | BU1: 202912
A3: Field Description | B3: Field Name
A4: Company Name | B4: CD_COMPNAME | C4: =_xll.EQNXTDZ(A1,B4,C1) -> John Cockerill India Ltd
A5: Date End | B5: QTR_DATE_END | C5: =_xll.EQNXTDZ($A$1,$B5,C$1,$B$1) -> 201206 | D5: =_xll.EQNXTDZ($A$1,$B5,D$1,$B$1) -> 201209 | E5: =_xll.EQNXTDZ($A$1,$B5,E$1,$B$1) -> 201212 | F5: =_xll.EQNXTDZ($A$1,$B5,F$1,$B$1) -> 201303 | G5: =_xll.EQNXTDZ($A$1,$B5,G$1,$B$1) -> 201306 | H5: =_xll.EQNXTDZ($A$1,$B5,H$1,$B$1) -> 201309 | I5: =_xll.EQNXTDZ($A$1,$B5,I$1,$B$1) -> 201312 | J5: =_xll.EQNXTDZ($A$1,$B5,J$1,$B$1) -> 201403 | ... BU5: =_xll.EQNXTDZ($A$1,$B5,BU$1,$B$1) -> 0
A6: Gross Sales | B6: QTR_GROSS_SALE | C6: =_xll.EQNXTDZ($A$1,$B6,C$1,$B$1) -> 92.428 | D6: =_xll.EQNXTDZ($A$1,$B6,D$1,$B$1) -> 110.081 | E6: =_xll.EQNXTDZ($A$1,$B6,E$1,$B$1) -> 194.165 | F6: =_xll.EQNXTDZ($A$1,$B6,F$1,$B$1) -> 133.297 | G6: =_xll.EQNXTDZ($A$1,$B6,G$1,$B$1) -> 101.481 | H6: =_xll.EQNXTDZ($A$1,$B6,H$1,$B$1) -> 121.6 | I6: =_xll.EQNXTDZ($A$1,$B6,I$1,$B$1) -> 125.846 | J6: =_xll.EQNXTDZ($A$1,$B6,J$1,$B$1) -> 92.323 | ... BU6: =_xll.EQNXTDZ($A$1,$B6,BU$1,$B$1) -> 0
A7: Less: Excise Duty | B7: QTR_EXCISE_DUTY | C7: =_xll.EQNXTDZ($A$1,$B7,C$1,$B$1) -> 0 | D7: =_xll.EQNXTDZ($A$1,$B7,D$1,$B$1) -> 0 | E7: =_xll.EQNXTDZ($A$1,$B7,E$1,$B$1) -> 0 | F7: =_xll.EQNXTDZ($A$1,$B7,F$1,$B$1) -> 0 | G7: =_xll.EQNXTDZ($A$1,$B7,G$1,$B$1) -> 0 | H7: =_xll.EQNXTDZ($A$1,$B7,H$1,$B$1) -> 0 | I7: =_xll.EQNXTDZ($A$1,$B7,I$1,$B$1) -> 0 | J7: =_xll.EQNXTDZ($A$1,$B7,J$1,$B$1) -> 0 | ... BU7: =_xll.EQNXTDZ($A$1,$B7,BU$1,$B$1) -> 0
A8: Other operating income | B8: QTR_JOB_WORKS | C8: =_xll.EQNXTDZ($A$1,$B8,C$1,$B$1) -> 0.282 | D8: =_xll.EQNXTDZ($A$1,$B8,D$1,$B$1) -> 0.379 | E8: =_xll.EQNXTDZ($A$1,$B8,E$1,$B$1) -> 0.287 | F8: =_xll.EQNXTDZ($A$1,$B8,F$1,$B$1) -> 1.977 | G8: =_xll.EQNXTDZ($A$1,$B8,G$1,$B$1) -> 0.304 | H8: =_xll.EQNXTDZ($A$1,$B8,H$1,$B$1) -> 0.409 | I8: =_xll.EQNXTDZ($A$1,$B8,I$1,$B$1) -> 0.532 | J8: =_xll.EQNXTDZ($A$1,$B8,J$1,$B$1) -> 0.338 | ... BU8: =_xll.EQNXTDZ($A$1,$B8,BU$1,$B$1) -> 0
A9: Net Sales & Other Operating Income | B9: QTR_NET_SALES | C9: =_xll.EQNXTDZ($A$1,$B9,C$1,$B$1) -> 92.709 | D9: =_xll.EQNXTDZ($A$1,$B9,D$1,$B$1) -> 110.46 | E9: =_xll.EQNXTDZ($A$1,$B9,E$1,$B$1) -> 194.452 | F9: =_xll.EQNXTDZ($A$1,$B9,F$1,$B$1) -> 135.274 | G9: =_xll.EQNXTDZ($A$1,$B9,G$1,$B$1) -> 101.785 | H9: =_xll.EQNXTDZ($A$1,$B9,H$1,$B$1) -> 122.009 | I9: =_xll.EQNXTDZ($A$1,$B9,I$1,$B$1) -> 126.378 | J9: =_xll.EQNXTDZ($A$1,$B9,J$1,$B$1) -> 92.661 | ... BU9: =_xll.EQNXTDZ($A$1,$B9,BU$1,$B$1) -> 0
A10: (Increase) / Decrease In Stocks | B10: QTR_INC_DEC_INVENTORY | C10: =_xll.EQNXTDZ($A$1,$B10,C$1,$B$1) -> -0.416 | D10: =_xll.EQNXTDZ($A$1,$B10,D$1,$B$1) -> 1.175 | E10: =_xll.EQNXTDZ($A$1,$B10,E$1,$B$1) -> -0.81 | F10: =_xll.EQNXTDZ($A$1,$B10,F$1,$B$1) -> -1.338 | G10: =_xll.EQNXTDZ($A$1,$B10,G$1,$B$1) -> 1.701 | H10: =_xll.EQNXTDZ($A$1,$B10,H$1,$B$1) -> -0.053 | I10: =_xll.EQNXTDZ($A$1,$B10,I$1,$B$1) -> 0.205 | J10: =_xll.EQNXTDZ($A$1,$B10,J$1,$B$1) -> -1.586 | ... BU10: =_xll.EQNXTDZ($A$1,$B10,BU$1,$B$1) -> 0
A11: Cost of Services & Raw Materials | B11: QTR_RAW_MATERIAL_COST | C11: =_xll.EQNXTDZ($A$1,$B11,C$1,$B$1) -> 35.855 | D11: =_xll.EQNXTDZ($A$1,$B11,D$1,$B$1) -> 47.087 | E11: =_xll.EQNXTDZ($A$1,$B11,E$1,$B$1) -> 78.065 | F11: =_xll.EQNXTDZ($A$1,$B11,F$1,$B$1) -> 78.283 | G11: =_xll.EQNXTDZ($A$1,$B11,G$1,$B$1) -> 44.369 | H11: =_xll.EQNXTDZ($A$1,$B11,H$1,$B$1) -> 35.775 | I11: =_xll.EQNXTDZ($A$1,$B11,I$1,$B$1) -> 36.873 | J11: =_xll.EQNXTDZ($A$1,$B11,J$1,$B$1) -> 33.207 | ... BU11: =_xll.EQNXTDZ($A$1,$B11,BU$1,$B$1) -> 0
A12: Purchase of Finished Goods | B12: QTR_PURCHASE_FIN_GOOD | C12: =_xll.EQNXTDZ($A$1,$B12,C$1,$B$1) -> 15.591 | D12: =_xll.EQNXTDZ($A$1,$B12,D$1,$B$1) -> 32.846 | E12: =_xll.EQNXTDZ($A$1,$B12,E$1,$B$1) -> 68.75 | F12: =_xll.EQNXTDZ($A$1,$B12,F$1,$B$1) -> 24.29 | G12: =_xll.EQNXTDZ($A$1,$B12,G$1,$B$1) -> 32.826 | H12: =_xll.EQNXTDZ($A$1,$B12,H$1,$B$1) -> 55.692 | I12: =_xll.EQNXTDZ($A$1,$B12,I$1,$B$1) -> 50.49 | J12: =_xll.EQNXTDZ($A$1,$B12,J$1,$B$1) -> 26.933 | ... BU12: =_xll.EQNXTDZ($A$1,$B12,BU$1,$B$1) -> 0
A13: Excise Duty | B13: QTR_EXCISE | C13: =_xll.EQNXTDZ($A$1,$B13,C$1,$B$1) -> 0 | D13: =_xll.EQNXTDZ($A$1,$B13,D$1,$B$1) -> 0 | E13: =_xll.EQNXTDZ($A$1,$B13,E$1,$B$1) -> 0 | F13: =_xll.EQNXTDZ($A$1,$B13,F$1,$B$1) -> 0 | G13: =_xll.EQNXTDZ($A$1,$B13,G$1,$B$1) -> 0 | H13: =_xll.EQNXTDZ($A$1,$B13,H$1,$B$1) -> 0 | I13: =_xll.EQNXTDZ($A$1,$B13,I$1,$B$1) -> 0 | J13: =_xll.EQNXTDZ($A$1,$B13,J$1,$B$1) -> 0 | ... BU13: =_xll.EQNXTDZ($A$1,$B13,BU$1,$B$1) -> 0
A14: Operating & Manufacturing Expenses | B14: QTR_MFG_EXPS | C14: =_xll.EQNXTDZ($A$1,$B14,C$1,$B$1) -> 24.914 | D14: =_xll.EQNXTDZ($A$1,$B14,D$1,$B$1) -> 22.731 | E14: =_xll.EQNXTDZ($A$1,$B14,E$1,$B$1) -> 33.6 | F14: =_xll.EQNXTDZ($A$1,$B14,F$1,$B$1) -> 27.844 | G14: =_xll.EQNXTDZ($A$1,$B14,G$1,$B$1) -> 29.033 | H14: =_xll.EQNXTDZ($A$1,$B14,H$1,$B$1) -> 31.506 | I14: =_xll.EQNXTDZ($A$1,$B14,I$1,$B$1) -> 15.745 | J14: =_xll.EQNXTDZ($A$1,$B14,J$1,$B$1) -> 20.862 | ... BU14: =_xll.EQNXTDZ($A$1,$B14,BU$1,$B$1) -> 0
A15: Electricity Power & Fuel Cost | B15: QTR_ELECTRICITY_POWER_FUEL | C15: =_xll.EQNXTDZ($A$1,$B15,C$1,$B$1) -> 0 | D15: =_xll.EQNXTDZ($A$1,$B15,D$1,$B$1) -> 0 | E15: =_xll.EQNXTDZ($A$1,$B15,E$1,$B$1) -> 0 | F15: =_xll.EQNXTDZ($A$1,$B15,F$1,$B$1) -> 0 | G15: =_xll.EQNXTDZ($A$1,$B15,G$1,$B$1) -> 0 | H15: =_xll.EQNXTDZ($A$1,$B15,H$1,$B$1) -> 0 | I15: =_xll.EQNXTDZ($A$1,$B15,I$1,$B$1) -> 0 | J15: =_xll.EQNXTDZ($A$1,$B15,J$1,$B$1) -> 0 | ... BU15: =_xll.EQNXTDZ($A$1,$B15,BU$1,$B$1) -> 0
A16: Employee Cost | B16: QTR_EXPLOYEE_COST | C16: =_xll.EQNXTDZ($A$1,$B16,C$1,$B$1) -> 9.925 | D16: =_xll.EQNXTDZ($A$1,$B16,D$1,$B$1) -> 12.134 | E16: =_xll.EQNXTDZ($A$1,$B16,E$1,$B$1) -> 12.361 | F16: =_xll.EQNXTDZ($A$1,$B16,F$1,$B$1) -> 8.983 | G16: =_xll.EQNXTDZ($A$1,$B16,G$1,$B$1) -> 11.883 | H16: =_xll.EQNXTDZ($A$1,$B16,H$1,$B$1) -> 11.589 | I16: =_xll.EQNXTDZ($A$1,$B16,I$1,$B$1) -> 10.835 | J16: =_xll.EQNXTDZ($A$1,$B16,J$1,$B$1) -> 8.541 | ... BU16: =_xll.EQNXTDZ($A$1,$B16,BU$1,$B$1) -> 0
... A42: Consolidated PAT(after extra items) | B42: QTR_CONS_PAT_EXITM | C42: =_xll.EQNXTDZ($A$1,$B42,C$1,$B$1) -> 4.466 | D42: =_xll.EQNXTDZ($A$1,$B42,D$1,$B$1) -> -3.717 | E42: =_xll.EQNXTDZ($A$1,$B42,E$1,$B$1) -> 1.695 | F42: =_xll.EQNXTDZ($A$1,$B42,F$1,$B$1) -> -3.437 | G42: =_xll.EQNXTDZ($A$1,$B42,G$1,$B$1) -> -13.758 | H42: =_xll.EQNXTDZ($A$1,$B42,H$1,$B$1) -> -18.51 | I42: =_xll.EQNXTDZ($A$1,$B42,I$1,$B$1) -> 11.531 | J42: =_xll.EQNXTDZ($A$1,$B42,J$1,$B$1) -> -1.576 | ... BU42: =_xll.EQNXTDZ($A$1,$B42,BU$1,$B$1) -> 0
A44: Field Description | B44: Field Name
A45: Equity Capital | B45: QTR_EQUITY_CAP | C45: =_xll.EQNXTDZ($A$1,$B45,C$1,$B$1) -> 4.938 | D45: =_xll.EQNXTDZ($A$1,$B45,D$1,$B$1) -> 4.938 | E45: =_xll.EQNXTDZ($A$1,$B45,E$1,$B$1) -> 4.938 | F45: =_xll.EQNXTDZ($A$1,$B45,F$1,$B$1) -> 4.938 | G45: =_xll.EQNXTDZ($A$1,$B45,G$1,$B$1) -> 4.938 | H45: =_xll.EQNXTDZ($A$1,$B45,H$1,$B$1) -> 4.938 | I45: =_xll.EQNXTDZ($A$1,$B45,I$1,$B$1) -> 4.938 | J45: =_xll.EQNXTDZ($A$1,$B45,J$1,$B$1) -> 4.938 | ... BU45: =_xll.EQNXTDZ($A$1,$B45,BU$1,$B$1) -> 0
A46: Face Value | B46: QTR_FV | C46: =_xll.EQNXTDZ($A$1,$B46,C$1,$B$1) -> 10 | D46: =_xll.EQNXTDZ($A$1,$B46,D$1,$B$1) -> 10 | E46: =_xll.EQNXTDZ($A$1,$B46,E$1,$B$1) -> 10 | F46: =_xll.EQNXTDZ($A$1,$B46,F$1,$B$1) -> 10 | G46: =_xll.EQNXTDZ($A$1,$B46,G$1,$B$1) -> 10 | H46: =_xll.EQNXTDZ($A$1,$B46,H$1,$B$1) -> 10 | I46: =_xll.EQNXTDZ($A$1,$B46,I$1,$B$1) -> 10 | J46: =_xll.EQNXTDZ($A$1,$B46,J$1,$B$1) -> 10 | ... BU46: =_xll.EQNXTDZ($A$1,$B46,BU$1,$B$1) -> 0
A47: Month End | B47: BMONTH_MONTHEND | C47: =_xll.EQNXTDZ($A$1,$B47,C$5) -> 201206 | D47: =_xll.EQNXTDZ($A$1,$B47,D$5) -> 201209 | E47: =_xll.EQNXTDZ($A$1,$B47,E$5) -> 201212 | F47: =_xll.EQNXTDZ($A$1,$B47,F$5) -> 201303 | G47: =_xll.EQNXTDZ($A$1,$B47,G$5) -> 201306 | H47: =_xll.EQNXTDZ($A$1,$B47,H$5) -> 201309 | I47: =_xll.EQNXTDZ($A$1,$B47,I$5) -> 201312 | J47: =_xll.EQNXTDZ($A$1,$B47,J$5) -> 201403 | ... BU47: =_xll.EQNXTDZ($A$1,$B47,BU$5) -> 0
A48: Close | B48: BMONTH_CLOSE | C48: =_xll.EQNXTDZ($A$1,$B48,C$5) -> 763.65 | D48: =_xll.EQNXTDZ($A$1,$B48,D$5) -> 705.5 | E48: =_xll.EQNXTDZ($A$1,$B48,E$5) -> 660 | F48: =_xll.EQNXTDZ($A$1,$B48,F$5) -> 372.95 | G48: =_xll.EQNXTDZ($A$1,$B48,G$5) -> 330 | H48: =_xll.EQNXTDZ($A$1,$B48,H$5) -> 263 | I48: =_xll.EQNXTDZ($A$1,$B48,I$5) -> 314.4 | J48: =_xll.EQNXTDZ($A$1,$B48,J$5) -> 445 | ... BU48: =_xll.EQNXTDZ($A$1,$B48,BU$5) -> 0
A49: Total of Promoter and Promoter Group | B49: SHP_TPFTOTALPROMOTER | C49: =_xll.EQNXTDZ($A$1,$B49,C$5) -> 75 | D49: =_xll.EQNXTDZ($A$1,$B49,D$5) -> 75 | E49: =_xll.EQNXTDZ($A$1,$B49,E$5) -> 75 | F49: =_xll.EQNXTDZ($A$1,$B49,F$5) -> 75 | G49: =_xll.EQNXTDZ($A$1,$B49,G$5) -> 75 | H49: =_xll.EQNXTDZ($A$1,$B49,H$5) -> 75 | I49: =_xll.EQNXTDZ($A$1,$B49,I$5) -> 75 | J49: =_xll.EQNXTDZ($A$1,$B49,J$5) -> 75 | ... BU49: =_xll.EQNXTDZ($A$1,$B49,BU$5) -> 0
A50: Total of Promoter and Promoter Group Pledged | B50: SHP_PSHFTOTALPROMOTER | C50: =_xll.EQNXTDZ($A$1,$B50,C$5) -> 0 | D50: =_xll.EQNXTDZ($A$1,$B50,D$5) -> 0 | E50: =_xll.EQNXTDZ($A$1,$B50,E$5) -> 0 | F50: =_xll.EQNXTDZ($A$1,$B50,F$5) -> 0 | G50: =_xll.EQNXTDZ($A$1,$B50,G$5) -> 0 | H50: =_xll.EQNXTDZ($A$1,$B50,H$5) -> 0 | I50: =_xll.EQNXTDZ($A$1,$B50,I$5) -> 0 | J50: =_xll.EQNXTDZ($A$1,$B50,J$5) -> 0 | ... BU50: =_xll.EQNXTDZ($A$1,$B50,BU$5) -> 0
A54: Field Description | B54: Field Name | C54: =_xll.EQNXTDZ($A$1,$B54,C$5) -> 0 | D54: =_xll.EQNXTDZ($A$1,$B54,D$5) -> 0 | E54: =_xll.EQNXTDZ($A$1,$B54,E$5) -> 0 | F54: =_xll.EQNXTDZ($A$1,$B54,F$5) -> 0 | G54: =_xll.EQNXTDZ($A$1,$B54,G$5) -> 0 | H54: =_xll.EQNXTDZ($A$1,$B54,H$5) -> 0 | I54: =_xll.EQNXTDZ($A$1,$B54,I$5) -> 0 | J54: =_xll.EQNXTDZ($A$1,$B54,J$5) -> 0 | ... BU54: =_xll.EQNXTDZ($A$1,$B54,BU$5) -> 0
A55: Year End | B55: QTRB_DATE_END | C55: =_xll.EQNXTDZ($A$1,$B55,C$5,$B$1) -> 0 | D55: =_xll.EQNXTDZ($A$1,$B55,D$5,$B$1) -> 201209 | E55: =_xll.EQNXTDZ($A$1,$B55,E$5,$B$1) -> 0 | F55: =_xll.EQNXTDZ($A$1,$B55,F$5,$B$1) -> 201303 | G55: =_xll.EQNXTDZ($A$1,$B55,G$5,$B$1) -> 0 | H55: =_xll.EQNXTDZ($A$1,$B55,H$5,$B$1) -> 201309 | I55: =_xll.EQNXTDZ($A$1,$B55,I$5,$B$1) -> 0 | J55: =_xll.EQNXTDZ($A$1,$B55,J$5,$B$1) -> 201403 | ... BU55: =_xll.EQNXTDZ($A$1,$B55,BU$5,$B$1) -> 0
A56: Share Capital | B56: QTRB_SHARE_CAPITAL | C56: =_xll.EQNXTDZ($A$1,$B56,C$5,$B$1) -> 0 | D56: =_xll.EQNXTDZ($A$1,$B56,D$5,$B$1) -> 4.938 | E56: =_xll.EQNXTDZ($A$1,$B56,E$5,$B$1) -> 0 | F56: =_xll.EQNXTDZ($A$1,$B56,F$5,$B$1) -> 4.938 | G56: =_xll.EQNXTDZ($A$1,$B56,G$5,$B$1) -> 0 | H56: =_xll.EQNXTDZ($A$1,$B56,H$5,$B$1) -> 4.938 | I56: =_xll.EQNXTDZ($A$1,$B56,I$5,$B$1) -> 0 | J56: =_xll.EQNXTDZ($A$1,$B56,J$5,$B$1) -> 4.938 | ... BU56: =_xll.EQNXTDZ($A$1,$B56,BU$5,$B$1) -> 0
A57: Share Warrants & outstandings | B57: QTRB_SHAREWARNDOUT | C57: =_xll.EQNXTDZ($A$1,$B57,C$5,$B$1) -> 0 | D57: =_xll.EQNXTDZ($A$1,$B57,D$5,$B$1) -> 0 | E57: =_xll.EQNXTDZ($A$1,$B57,E$5,$B$1) -> 0 | F57: =_xll.EQNXTDZ($A$1,$B57,F$5,$B$1) -> 0 | G57: =_xll.EQNXTDZ($A$1,$B57,G$5,$B$1) -> 0 | H57: =_xll.EQNXTDZ($A$1,$B57,H$5,$B$1) -> 0 | I57: =_xll.EQNXTDZ($A$1,$B57,I$5,$B$1) -> 0 | J57: =_xll.EQNXTDZ($A$1,$B57,J$5,$B$1) -> 0 | ... BU57: =_xll.EQNXTDZ($A$1,$B57,BU$5,$B$1) -> 0
A58: Reserves & Surplus | B58: QTRB_RESERVE | C58: =_xll.EQNXTDZ($A$1,$B58,C$5,$B$1) -> 0 | D58: =_xll.EQNXTDZ($A$1,$B58,D$5,$B$1) -> 147.412 | E58: =_xll.EQNXTDZ($A$1,$B58,E$5,$B$1) -> 0 | F58: =_xll.EQNXTDZ($A$1,$B58,F$5,$B$1) -> 145.669 | G58: =_xll.EQNXTDZ($A$1,$B58,G$5,$B$1) -> 0 | H58: =_xll.EQNXTDZ($A$1,$B58,H$5,$B$1) -> 113.402 | I58: =_xll.EQNXTDZ($A$1,$B58,I$5,$B$1) -> 0 | J58: =_xll.EQNXTDZ($A$1,$B58,J$5,$B$1) -> 123.357 | ... BU58: =_xll.EQNXTDZ($A$1,$B58,BU$5,$B$1) -> 0
A59: Shareholder's Funds | B59: QTRB_SHAREHODERS_FUNDS | C59: =_xll.EQNXTDZ($A$1,$B59,C$5,$B$1) -> 0 | D59: =_xll.EQNXTDZ($A$1,$B59,D$5,$B$1) -> 152.35 | E59: =_xll.EQNXTDZ($A$1,$B59,E$5,$B$1) -> 0 | F59: =_xll.EQNXTDZ($A$1,$B59,F$5,$B$1) -> 150.607 | G59: =_xll.EQNXTDZ($A$1,$B59,G$5,$B$1) -> 0 | H59: =_xll.EQNXTDZ($A$1,$B59,H$5,$B$1) -> 118.34 | I59: =_xll.EQNXTDZ($A$1,$B59,I$5,$B$1) -> 0 | J59: =_xll.EQNXTDZ($A$1,$B59,J$5,$B$1) -> 128.295 | ... BU59: =_xll.EQNXTDZ($A$1,$B59,BU$5,$B$1) -> 0
A60: Minority Interest | B60: QTRB_MINORITY_INTEREST_BS | C60: =_xll.EQNXTDZ($A$1,$B60,C$5,$B$1) -> 0 | D60: =_xll.EQNXTDZ($A$1,$B60,D$5,$B$1) -> 0 | E60: =_xll.EQNXTDZ($A$1,$B60,E$5,$B$1) -> 0 | F60: =_xll.EQNXTDZ($A$1,$B60,F$5,$B$1) -> 0 | G60: =_xll.EQNXTDZ($A$1,$B60,G$5,$B$1) -> 0 | H60: =_xll.EQNXTDZ($A$1,$B60,H$5,$B$1) -> 0 | I60: =_xll.EQNXTDZ($A$1,$B60,I$5,$B$1) -> 0 | J60: =_xll.EQNXTDZ($A$1,$B60,J$5,$B$1) -> 0 | ... BU60: =_xll.EQNXTDZ($A$1,$B60,BU$5,$B$1) -> 0
A61: Long Term Borrowings | B61: QTRB_TOTAL_DEBTS | C61: =_xll.EQNXTDZ($A$1,$B61,C$5,$B$1) -> 0 | D61: =_xll.EQNXTDZ($A$1,$B61,D$5,$B$1) -> 15.686 | E61: =_xll.EQNXTDZ($A$1,$B61,E$5,$B$1) -> 0 | F61: =_xll.EQNXTDZ($A$1,$B61,F$5,$B$1) -> 23.086 | G61: =_xll.EQNXTDZ($A$1,$B61,G$5,$B$1) -> 0 | H61: =_xll.EQNXTDZ($A$1,$B61,H$5,$B$1) -> 20.2 | I61: =_xll.EQNXTDZ($A$1,$B61,I$5,$B$1) -> 0 | J61: =_xll.EQNXTDZ($A$1,$B61,J$5,$B$1) -> 17.314 | ... BU61: =_xll.EQNXTDZ($A$1,$B61,BU$5,$B$1) -> 0
A62: Secured Loans | B62: QTRB_SECURED_LOANS | C62: =_xll.EQNXTDZ($A$1,$B62,C$5,$B$1) -> 0 | D62: =_xll.EQNXTDZ($A$1,$B62,D$5,$B$1) -> 0 | E62: =_xll.EQNXTDZ($A$1,$B62,E$5,$B$1) -> 0 | F62: =_xll.EQNXTDZ($A$1,$B62,F$5,$B$1) -> 0 | G62: =_xll.EQNXTDZ($A$1,$B62,G$5,$B$1) -> 0 | H62: =_xll.EQNXTDZ($A$1,$B62,H$5,$B$1) -> 0 | I62: =_xll.EQNXTDZ($A$1,$B62,I$5,$B$1) -> 0 | J62: =_xll.EQNXTDZ($A$1,$B62,J$5,$B$1) -> 0 | ... BU62: =_xll.EQNXTDZ($A$1,$B62,BU$5,$B$1) -> 0
A63: Unsecured Loans | B63: QTRB_UNSECURED_LOANS_NF | C63: =_xll.EQNXTDZ($A$1,$B63,C$5,$B$1) -> 0 | D63: =_xll.EQNXTDZ($A$1,$B63,D$5,$B$1) -> 15.686 | E63: =_xll.EQNXTDZ($A$1,$B63,E$5,$B$1) -> 0 | F63: =_xll.EQNXTDZ($A$1,$B63,F$5,$B$1) -> 23.086 | G63: =_xll.EQNXTDZ($A$1,$B63,G$5,$B$1) -> 0 | H63: =_xll.EQNXTDZ($A$1,$B63,H$5,$B$1) -> 20.2 | I63: =_xll.EQNXTDZ($A$1,$B63,I$5,$B$1) -> 0 | J63: =_xll.EQNXTDZ($A$1,$B63,J$5,$B$1) -> 17.314 | ... BU63: =_xll.EQNXTDZ($A$1,$B63,BU$5,$B$1) -> 0
A64: Other Long Term Liabilities | B64: QTRB_OTHER_LT_LIABILITIES | C64: =_xll.EQNXTDZ($A$1,$B64,C$5,$B$1) -> 0 | D64: =_xll.EQNXTDZ($A$1,$B64,D$5,$B$1) -> 22.798 | E64: =_xll.EQNXTDZ($A$1,$B64,E$5,$B$1) -> 0 | F64: =_xll.EQNXTDZ($A$1,$B64,F$5,$B$1) -> 8.99 | G64: =_xll.EQNXTDZ($A$1,$B64,G$5,$B$1) -> 0 | H64: =_xll.EQNXTDZ($A$1,$B64,H$5,$B$1) -> 13.422 | I64: =_xll.EQNXTDZ($A$1,$B64,I$5,$B$1) -> 0 | J64: =_xll.EQNXTDZ($A$1,$B64,J$5,$B$1) -> 10.543 | ... BU64: =_xll.EQNXTDZ($A$1,$B64,BU$5,$B$1) -> 0
A65: Long Term Trade Payables | B65: QTRB_LT_TRADE_PAYABLE | C65: =_xll.EQNXTDZ($A$1,$B65,C$5,$B$1) -> 0 | D65: =_xll.EQNXTDZ($A$1,$B65,D$5,$B$1) -> 0 | E65: =_xll.EQNXTDZ($A$1,$B65,E$5,$B$1) -> 0 | F65: =_xll.EQNXTDZ($A$1,$B65,F$5,$B$1) -> 0 | G65: =_xll.EQNXTDZ($A$1,$B65,G$5,$B$1) -> 0 | H65: =_xll.EQNXTDZ($A$1,$B65,H$5,$B$1) -> 0 | I65: =_xll.EQNXTDZ($A$1,$B65,I$5,$B$1) -> 0 | J65: =_xll.EQNXTDZ($A$1,$B65,J$5,$B$1) -> 0 | ... BU65: =_xll.EQNXTDZ($A$1,$B65,BU$5,$B$1) -> 0
A66: Lont Term Provisions | B66: QTRB_LT_PROVISIONS | C66: =_xll.EQNXTDZ($A$1,$B66,C$5,$B$1) -> 0 | D66: =_xll.EQNXTDZ($A$1,$B66,D$5,$B$1) -> 8.953 | E66: =_xll.EQNXTDZ($A$1,$B66,E$5,$B$1) -> 0 | F66: =_xll.EQNXTDZ($A$1,$B66,F$5,$B$1) -> 11.671 | G66: =_xll.EQNXTDZ($A$1,$B66,G$5,$B$1) -> 0 | H66: =_xll.EQNXTDZ($A$1,$B66,H$5,$B$1) -> 11.381 | I66: =_xll.EQNXTDZ($A$1,$B66,I$5,$B$1) -> 0 | J66: =_xll.EQNXTDZ($A$1,$B66,J$5,$B$1) -> 6.806 | ... BU66: =_xll.EQNXTDZ($A$1,$B66,BU$5,$B$1) -> 0
... A97: Total Assets | B97: QTRB_TOTAL_APPLICATIONS | C97: =_xll.EQNXTDZ($A$1,$B97,C$5,$B$1) -> 0 | D97: =_xll.EQNXTDZ($A$1,$B97,D$5,$B$1) -> 199.787 | E97: =_xll.EQNXTDZ($A$1,$B97,E$5,$B$1) -> 0 | F97: =_xll.EQNXTDZ($A$1,$B97,F$5,$B$1) -> 194.354 | G97: =_xll.EQNXTDZ($A$1,$B97,G$5,$B$1) -> 0 | H97: =_xll.EQNXTDZ($A$1,$B97,H$5,$B$1) -> 163.343 | I97: =_xll.EQNXTDZ($A$1,$B97,I$5,$B$1) -> 0 | J97: =_xll.EQNXTDZ($A$1,$B97,J$5,$B$1) -> 162.958 | ... BU97: =_xll.EQNXTDZ($A$1,$B97,BU$5,$B$1) -> 0

Sheet Annual Raw
A1: 100147 | B1: X | C1: 200003 | D1: 200103 | E1: 200212 | F1: 200312 | G1: 200412 | H1: 200512 | I1: 200612 | J1: 200712 | K1: 200812 | L1: 200912 | M1: 201012 | N1: 201112 | O1: 201212 | P1: 201312 | Q1: 201412 | R1: 201512 | S1: 201612 | T1: 201712 | U1: 201812 | V1: 201912 | W1: 202012 | X1: 202112 | Y1: 202212 | Z1: 202312 | AA1: 202412 | AB1: 202512 | AC1: 202612 | AD1: 202712 | AE1: 202812 | AF1: 202912 | AG1: 203012
A3: Field Description | B3: Field Name
A4: Company Name | B4: CD_COMPNAME | C4: =_xll.EQNXTDZ(A1,B4,"L") -> John Cockerill India Ltd
A5: Year End | B5: PL_YEAR_END | C5: =_xll.EQNXTDZ($A$1,$B5,C$1,$B$1) -> 200003 | D5: =_xll.EQNXTDZ($A$1,$B5,D$1,$B$1) -> 200103 | E5: =_xll.EQNXTDZ($A$1,$B5,E$1,$B$1) -> 0 | F5: =_xll.EQNXTDZ($A$1,$B5,F$1,$B$1) -> 0 | G5: =_xll.EQNXTDZ($A$1,$B5,G$1,$B$1) -> 0 | H5: =_xll.EQNXTDZ($A$1,$B5,H$1,$B$1) -> 0 | I5: =_xll.EQNXTDZ($A$1,$B5,I$1,$B$1) -> 0 | J5: =_xll.EQNXTDZ($A$1,$B5,J$1,$B$1) -> 0 | ... AG5: =_xll.EQNXTDZ($A$1,$B5,AG$1,$B$1) -> 0
A6: Sales Turnover | B6: PL_TOTAL_GROSS_SALES | C6: =_xll.EQNXTDZ($A$1,$B6,C$1,$B$1) -> 94.467588 | D6: =_xll.EQNXTDZ($A$1,$B6,D$1,$B$1) -> 127.52504 | E6: =_xll.EQNXTDZ($A$1,$B6,E$1,$B$1) -> 0 | F6: =_xll.EQNXTDZ($A$1,$B6,F$1,$B$1) -> 0 | G6: =_xll.EQNXTDZ($A$1,$B6,G$1,$B$1) -> 0 | H6: =_xll.EQNXTDZ($A$1,$B6,H$1,$B$1) -> 0 | I6: =_xll.EQNXTDZ($A$1,$B6,I$1,$B$1) -> 0 | J6: =_xll.EQNXTDZ($A$1,$B6,J$1,$B$1) -> 0 | ... AG6: =_xll.EQNXTDZ($A$1,$B6,AG$1,$B$1) -> 0
A7: Less: Inter divisional transfers | B7: PL_INTER_DIV_TRF | C7: =_xll.EQNXTDZ($A$1,$B7,C$1,$B$1) -> 0 | D7: =_xll.EQNXTDZ($A$1,$B7,D$1,$B$1) -> 0 | E7: =_xll.EQNXTDZ($A$1,$B7,E$1,$B$1) -> 0 | F7: =_xll.EQNXTDZ($A$1,$B7,F$1,$B$1) -> 0 | G7: =_xll.EQNXTDZ($A$1,$B7,G$1,$B$1) -> 0 | H7: =_xll.EQNXTDZ($A$1,$B7,H$1,$B$1) -> 0 | I7: =_xll.EQNXTDZ($A$1,$B7,I$1,$B$1) -> 0 | J7: =_xll.EQNXTDZ($A$1,$B7,J$1,$B$1) -> 0 | ... AG7: =_xll.EQNXTDZ($A$1,$B7,AG$1,$B$1) -> 0
A8: Less: Sales Returns | B8: PL_SALES_RETURN | C8: =_xll.EQNXTDZ($A$1,$B8,C$1,$B$1) -> 0 | D8: =_xll.EQNXTDZ($A$1,$B8,D$1,$B$1) -> 0 | E8: =_xll.EQNXTDZ($A$1,$B8,E$1,$B$1) -> 0 | F8: =_xll.EQNXTDZ($A$1,$B8,F$1,$B$1) -> 0 | G8: =_xll.EQNXTDZ($A$1,$B8,G$1,$B$1) -> 0 | H8: =_xll.EQNXTDZ($A$1,$B8,H$1,$B$1) -> 0 | I8: =_xll.EQNXTDZ($A$1,$B8,I$1,$B$1) -> 0 | J8: =_xll.EQNXTDZ($A$1,$B8,J$1,$B$1) -> 0 | ... AG8: =_xll.EQNXTDZ($A$1,$B8,AG$1,$B$1) -> 0
A9: Less: Excise | B9: PL_EXCISE | C9: =_xll.EQNXTDZ($A$1,$B9,C$1,$B$1) -> 9.8270536 | D9: =_xll.EQNXTDZ($A$1,$B9,D$1,$B$1) -> 4.5848681 | E9: =_xll.EQNXTDZ($A$1,$B9,E$1,$B$1) -> 0 | F9: =_xll.EQNXTDZ($A$1,$B9,F$1,$B$1) -> 0 | G9: =_xll.EQNXTDZ($A$1,$B9,G$1,$B$1) -> 0 | H9: =_xll.EQNXTDZ($A$1,$B9,H$1,$B$1) -> 0 | I9: =_xll.EQNXTDZ($A$1,$B9,I$1,$B$1) -> 0 | J9: =_xll.EQNXTDZ($A$1,$B9,J$1,$B$1) -> 0 | ... AG9: =_xll.EQNXTDZ($A$1,$B9,AG$1,$B$1) -> 0
A10: Net Sales | B10: PL_NET_SALES | C10: =_xll.EQNXTDZ($A$1,$B10,C$1,$B$1) -> 84.640534 | D10: =_xll.EQNXTDZ($A$1,$B10,D$1,$B$1) -> 122.94017 | E10: =_xll.EQNXTDZ($A$1,$B10,E$1,$B$1) -> 0 | F10: =_xll.EQNXTDZ($A$1,$B10,F$1,$B$1) -> 0 | G10: =_xll.EQNXTDZ($A$1,$B10,G$1,$B$1) -> 0 | H10: =_xll.EQNXTDZ($A$1,$B10,H$1,$B$1) -> 0 | I10: =_xll.EQNXTDZ($A$1,$B10,I$1,$B$1) -> 0 | J10: =_xll.EQNXTDZ($A$1,$B10,J$1,$B$1) -> 0 | ... AG10: =_xll.EQNXTDZ($A$1,$B10,AG$1,$B$1) -> 0
A11: Increase/Decrease in Stock | B11: PL_INC_DEC_INVENTORY | C11: =_xll.EQNXTDZ($A$1,$B11,C$1,$B$1) -> -2.4551 | D11: =_xll.EQNXTDZ($A$1,$B11,D$1,$B$1) -> 10.9082 | E11: =_xll.EQNXTDZ($A$1,$B11,E$1,$B$1) -> 0 | F11: =_xll.EQNXTDZ($A$1,$B11,F$1,$B$1) -> 0 | G11: =_xll.EQNXTDZ($A$1,$B11,G$1,$B$1) -> 0 | H11: =_xll.EQNXTDZ($A$1,$B11,H$1,$B$1) -> 0 | I11: =_xll.EQNXTDZ($A$1,$B11,I$1,$B$1) -> 0 | J11: =_xll.EQNXTDZ($A$1,$B11,J$1,$B$1) -> 0 | ... AG11: =_xll.EQNXTDZ($A$1,$B11,AG$1,$B$1) -> 0
A12: Raw Material Consumed | B12: PL_RAW_MATRS_CONSUMED | C12: =_xll.EQNXTDZ($A$1,$B12,C$1,$B$1) -> 64.55574 | D12: =_xll.EQNXTDZ($A$1,$B12,D$1,$B$1) -> 64.487941 | E12: =_xll.EQNXTDZ($A$1,$B12,E$1,$B$1) -> 0 | F12: =_xll.EQNXTDZ($A$1,$B12,F$1,$B$1) -> 0 | G12: =_xll.EQNXTDZ($A$1,$B12,G$1,$B$1) -> 0 | H12: =_xll.EQNXTDZ($A$1,$B12,H$1,$B$1) -> 0 | I12: =_xll.EQNXTDZ($A$1,$B12,I$1,$B$1) -> 0 | J12: =_xll.EQNXTDZ($A$1,$B12,J$1,$B$1) -> 0 | ... AG12: =_xll.EQNXTDZ($A$1,$B12,AG$1,$B$1) -> 0
A13: Power & Fuel Cost | B13: PL_POWER_FUEL | C13: =_xll.EQNXTDZ($A$1,$B13,C$1,$B$1) -> 0.3935483 | D13: =_xll.EQNXTDZ($A$1,$B13,D$1,$B$1) -> 0.49143431 | E13: =_xll.EQNXTDZ($A$1,$B13,E$1,$B$1) -> 0 | F13: =_xll.EQNXTDZ($A$1,$B13,F$1,$B$1) -> 0 | G13: =_xll.EQNXTDZ($A$1,$B13,G$1,$B$1) -> 0 | H13: =_xll.EQNXTDZ($A$1,$B13,H$1,$B$1) -> 0 | I13: =_xll.EQNXTDZ($A$1,$B13,I$1,$B$1) -> 0 | J13: =_xll.EQNXTDZ($A$1,$B13,J$1,$B$1) -> 0 | ... AG13: =_xll.EQNXTDZ($A$1,$B13,AG$1,$B$1) -> 0
A14: Employee Cost | B14: PL_EMPLOYEES | C14: =_xll.EQNXTDZ($A$1,$B14,C$1,$B$1) -> 4.8360056 | D14: =_xll.EQNXTDZ($A$1,$B14,D$1,$B$1) -> 4.8083723 | E14: =_xll.EQNXTDZ($A$1,$B14,E$1,$B$1) -> 0 | F14: =_xll.EQNXTDZ($A$1,$B14,F$1,$B$1) -> 0 | G14: =_xll.EQNXTDZ($A$1,$B14,G$1,$B$1) -> 0 | H14: =_xll.EQNXTDZ($A$1,$B14,H$1,$B$1) -> 0 | I14: =_xll.EQNXTDZ($A$1,$B14,I$1,$B$1) -> 0 | J14: =_xll.EQNXTDZ($A$1,$B14,J$1,$B$1) -> 0 | ... AG14: =_xll.EQNXTDZ($A$1,$B14,AG$1,$B$1) -> 0
A15: Operating & Manufacturing Expenses | B15: PL_GEN_OTHER_MFG_EXPS | C15: =_xll.EQNXTDZ($A$1,$B15,C$1,$B$1) -> 13.841807 | D15: =_xll.EQNXTDZ($A$1,$B15,D$1,$B$1) -> 12.645187 | E15: =_xll.EQNXTDZ($A$1,$B15,E$1,$B$1) -> 0 | F15: =_xll.EQNXTDZ($A$1,$B15,F$1,$B$1) -> 0 | G15: =_xll.EQNXTDZ($A$1,$B15,G$1,$B$1) -> 0 | H15: =_xll.EQNXTDZ($A$1,$B15,H$1,$B$1) -> 0 | I15: =_xll.EQNXTDZ($A$1,$B15,I$1,$B$1) -> 0 | J15: =_xll.EQNXTDZ($A$1,$B15,J$1,$B$1) -> 0 | ... AG15: =_xll.EQNXTDZ($A$1,$B15,AG$1,$B$1) -> 0
A16: Cost of Software development | B16: PL_COST_SW | C16: =_xll.EQNXTDZ($A$1,$B16,C$1,$B$1) -> 0 | D16: =_xll.EQNXTDZ($A$1,$B16,D$1,$B$1) -> 0 | E16: =_xll.EQNXTDZ($A$1,$B16,E$1,$B$1) -> 0 | F16: =_xll.EQNXTDZ($A$1,$B16,F$1,$B$1) -> 0 | G16: =_xll.EQNXTDZ($A$1,$B16,G$1,$B$1) -> 0 | H16: =_xll.EQNXTDZ($A$1,$B16,H$1,$B$1) -> 0 | I16: =_xll.EQNXTDZ($A$1,$B16,I$1,$B$1) -> 0 | J16: =_xll.EQNXTDZ($A$1,$B16,J$1,$B$1) -> 0 | ... AG16: =_xll.EQNXTDZ($A$1,$B16,AG$1,$B$1) -> 0
... A36: Profit After Tax from Discontinued Operations | B36: PL_PAT_DIS_OP | C36: =_xll.EQNXTDZ($A$1,$B36,C$1,$B$1) -> 0 | D36: =_xll.EQNXTDZ($A$1,$B36,D$1,$B$1) -> 0 | E36: =_xll.EQNXTDZ($A$1,$B36,E$1,$B$1) -> 0 | F36: =_xll.EQNXTDZ($A$1,$B36,F$1,$B$1) -> 0 | G36: =_xll.EQNXTDZ($A$1,$B36,G$1,$B$1) -> 0 | H36: =_xll.EQNXTDZ($A$1,$B36,H$1,$B$1) -> 0 | I36: =_xll.EQNXTDZ($A$1,$B36,I$1,$B$1) -> 0 | J36: =_xll.EQNXTDZ($A$1,$B36,J$1,$B$1) -> 0 | ... AG36: =_xll.EQNXTDZ($A$1,$B36,AG$1,$B$1) -> 0
A39: Field Description | B39: Field Name
A40: Year End | B40: BS_YEAR_END | C40: =_xll.EQNXTDZ($A$1,$B40,C$1,$B$1) -> 200003 | D40: =_xll.EQNXTDZ($A$1,$B40,D$1,$B$1) -> 200103 | E40: =_xll.EQNXTDZ($A$1,$B40,E$1,$B$1) -> 0 | F40: =_xll.EQNXTDZ($A$1,$B40,F$1,$B$1) -> 0 | G40: =_xll.EQNXTDZ($A$1,$B40,G$1,$B$1) -> 0 | H40: =_xll.EQNXTDZ($A$1,$B40,H$1,$B$1) -> 0 | I40: =_xll.EQNXTDZ($A$1,$B40,I$1,$B$1) -> 0 | J40: =_xll.EQNXTDZ($A$1,$B40,J$1,$B$1) -> 0 | ... AG40: =_xll.EQNXTDZ($A$1,$B40,AG$1,$B$1) -> 0
A41: Share Capital | B41: BS_SHARE_CAPITAL | C41: =_xll.EQNXTDZ($A$1,$B41,C$1,$B$1) -> 4.937813 | D41: =_xll.EQNXTDZ($A$1,$B41,D$1,$B$1) -> 4.937813 | E41: =_xll.EQNXTDZ($A$1,$B41,E$1,$B$1) -> 0 | F41: =_xll.EQNXTDZ($A$1,$B41,F$1,$B$1) -> 0 | G41: =_xll.EQNXTDZ($A$1,$B41,G$1,$B$1) -> 0 | H41: =_xll.EQNXTDZ($A$1,$B41,H$1,$B$1) -> 0 | I41: =_xll.EQNXTDZ($A$1,$B41,I$1,$B$1) -> 0 | J41: =_xll.EQNXTDZ($A$1,$B41,J$1,$B$1) -> 0 | ... AG41: =_xll.EQNXTDZ($A$1,$B41,AG$1,$B$1) -> 0
A42: Share Warrants & Outstandings | B42: BS_SHAREWROUTST | C42: =_xll.EQNXTDZ($A$1,$B42,C$1,$B$1) -> 0 | D42: =_xll.EQNXTDZ($A$1,$B42,D$1,$B$1) -> 0 | E42: =_xll.EQNXTDZ($A$1,$B42,E$1,$B$1) -> 0 | F42: =_xll.EQNXTDZ($A$1,$B42,F$1,$B$1) -> 0 | G42: =_xll.EQNXTDZ($A$1,$B42,G$1,$B$1) -> 0 | H42: =_xll.EQNXTDZ($A$1,$B42,H$1,$B$1) -> 0 | I42: =_xll.EQNXTDZ($A$1,$B42,I$1,$B$1) -> 0 | J42: =_xll.EQNXTDZ($A$1,$B42,J$1,$B$1) -> 0 | ... AG42: =_xll.EQNXTDZ($A$1,$B42,AG$1,$B$1) -> 0
A43: Total Reserves | B43: BS_RESERVE | C43: =_xll.EQNXTDZ($A$1,$B43,C$1,$B$1) -> 40.619013 | D43: =_xll.EQNXTDZ($A$1,$B43,D$1,$B$1) -> 45.273175 | E43: =_xll.EQNXTDZ($A$1,$B43,E$1,$B$1) -> 0 | F43: =_xll.EQNXTDZ($A$1,$B43,F$1,$B$1) -> 0 | G43: =_xll.EQNXTDZ($A$1,$B43,G$1,$B$1) -> 0 | H43: =_xll.EQNXTDZ($A$1,$B43,H$1,$B$1) -> 0 | I43: =_xll.EQNXTDZ($A$1,$B43,I$1,$B$1) -> 0 | J43: =_xll.EQNXTDZ($A$1,$B43,J$1,$B$1) -> 0 | ... AG43: =_xll.EQNXTDZ($A$1,$B43,AG$1,$B$1) -> 0
A44: Shareholder's Funds | B44: BS_SHAREHODERS_FUNDS | C44: =_xll.EQNXTDZ($A$1,$B44,C$1,$B$1) -> 45.556826 | D44: =_xll.EQNXTDZ($A$1,$B44,D$1,$B$1) -> 50.210988 | E44: =_xll.EQNXTDZ($A$1,$B44,E$1,$B$1) -> 0 | F44: =_xll.EQNXTDZ($A$1,$B44,F$1,$B$1) -> 0 | G44: =_xll.EQNXTDZ($A$1,$B44,G$1,$B$1) -> 0 | H44: =_xll.EQNXTDZ($A$1,$B44,H$1,$B$1) -> 0 | I44: =_xll.EQNXTDZ($A$1,$B44,I$1,$B$1) -> 0 | J44: =_xll.EQNXTDZ($A$1,$B44,J$1,$B$1) -> 0 | ... AG44: =_xll.EQNXTDZ($A$1,$B44,AG$1,$B$1) -> 0
A45: Minority Interest | B45: BS_MINORITY_INTEREST | C45: =_xll.EQNXTDZ($A$1,$B45,C$1,$B$1) -> 0 | D45: =_xll.EQNXTDZ($A$1,$B45,D$1,$B$1) -> 0 | E45: =_xll.EQNXTDZ($A$1,$B45,E$1,$B$1) -> 0 | F45: =_xll.EQNXTDZ($A$1,$B45,F$1,$B$1) -> 0 | G45: =_xll.EQNXTDZ($A$1,$B45,G$1,$B$1) -> 0 | H45: =_xll.EQNXTDZ($A$1,$B45,H$1,$B$1) -> 0 | I45: =_xll.EQNXTDZ($A$1,$B45,I$1,$B$1) -> 0 | J45: =_xll.EQNXTDZ($A$1,$B45,J$1,$B$1) -> 0 | ... AG45: =_xll.EQNXTDZ($A$1,$B45,AG$1,$B$1) -> 0
A46: Long-Term Borrowings | B46: BS_LTRM_BORROWING | C46: =_xll.EQNXTDZ($A$1,$B46,C$1,$B$1) -> 0 | D46: =_xll.EQNXTDZ($A$1,$B46,D$1,$B$1) -> 0 | E46: =_xll.EQNXTDZ($A$1,$B46,E$1,$B$1) -> 0 | F46: =_xll.EQNXTDZ($A$1,$B46,F$1,$B$1) -> 0 | G46: =_xll.EQNXTDZ($A$1,$B46,G$1,$B$1) -> 0 | H46: =_xll.EQNXTDZ($A$1,$B46,H$1,$B$1) -> 0 | I46: =_xll.EQNXTDZ($A$1,$B46,I$1,$B$1) -> 0 | J46: =_xll.EQNXTDZ($A$1,$B46,J$1,$B$1) -> 0 | ... AG46: =_xll.EQNXTDZ($A$1,$B46,AG$1,$B$1) -> 0
A47: Secured Loans | B47: BS_SECURED_LOANS | C47: =_xll.EQNXTDZ($A$1,$B47,C$1,$B$1) -> 26.601813 | D47: =_xll.EQNXTDZ($A$1,$B47,D$1,$B$1) -> 29.762912 | E47: =_xll.EQNXTDZ($A$1,$B47,E$1,$B$1) -> 0 | F47: =_xll.EQNXTDZ($A$1,$B47,F$1,$B$1) -> 0 | G47: =_xll.EQNXTDZ($A$1,$B47,G$1,$B$1) -> 0 | H47: =_xll.EQNXTDZ($A$1,$B47,H$1,$B$1) -> 0 | I47: =_xll.EQNXTDZ($A$1,$B47,I$1,$B$1) -> 0 | J47: =_xll.EQNXTDZ($A$1,$B47,J$1,$B$1) -> 0 | ... AG47: =_xll.EQNXTDZ($A$1,$B47,AG$1,$B$1) -> 0
A48: Unsecured Loans | B48: BS_UNSECURED_LOANS_NF | C48: =_xll.EQNXTDZ($A$1,$B48,C$1,$B$1) -> 4.660122 | D48: =_xll.EQNXTDZ($A$1,$B48,D$1,$B$1) -> 3.8020562 | E48: =_xll.EQNXTDZ($A$1,$B48,E$1,$B$1) -> 0 | F48: =_xll.EQNXTDZ($A$1,$B48,F$1,$B$1) -> 0 | G48: =_xll.EQNXTDZ($A$1,$B48,G$1,$B$1) -> 0 | H48: =_xll.EQNXTDZ($A$1,$B48,H$1,$B$1) -> 0 | I48: =_xll.EQNXTDZ($A$1,$B48,I$1,$B$1) -> 0 | J48: =_xll.EQNXTDZ($A$1,$B48,J$1,$B$1) -> 0 | ... AG48: =_xll.EQNXTDZ($A$1,$B48,AG$1,$B$1) -> 0
A49: Deferred Tax Assets / Liabilities | B49: BS_NET_DEF_TAX_NF | C49: =_xll.EQNXTDZ($A$1,$B49,C$1,$B$1) -> 0 | D49: =_xll.EQNXTDZ($A$1,$B49,D$1,$B$1) -> 0 | E49: =_xll.EQNXTDZ($A$1,$B49,E$1,$B$1) -> 0 | F49: =_xll.EQNXTDZ($A$1,$B49,F$1,$B$1) -> 0 | G49: =_xll.EQNXTDZ($A$1,$B49,G$1,$B$1) -> 0 | H49: =_xll.EQNXTDZ($A$1,$B49,H$1,$B$1) -> 0 | I49: =_xll.EQNXTDZ($A$1,$B49,I$1,$B$1) -> 0 | J49: =_xll.EQNXTDZ($A$1,$B49,J$1,$B$1) -> 0 | ... AG49: =_xll.EQNXTDZ($A$1,$B49,AG$1,$B$1) -> 0
A50: Other Long Term Liabilities | B50: BS_OTH_LT_LIAB | C50: =_xll.EQNXTDZ($A$1,$B50,C$1,$B$1) -> 0 | D50: =_xll.EQNXTDZ($A$1,$B50,D$1,$B$1) -> 0 | E50: =_xll.EQNXTDZ($A$1,$B50,E$1,$B$1) -> 0 | F50: =_xll.EQNXTDZ($A$1,$B50,F$1,$B$1) -> 0 | G50: =_xll.EQNXTDZ($A$1,$B50,G$1,$B$1) -> 0 | H50: =_xll.EQNXTDZ($A$1,$B50,H$1,$B$1) -> 0 | I50: =_xll.EQNXTDZ($A$1,$B50,I$1,$B$1) -> 0 | J50: =_xll.EQNXTDZ($A$1,$B50,J$1,$B$1) -> 0 | ... AG50: =_xll.EQNXTDZ($A$1,$B50,AG$1,$B$1) -> 0
A51: Long Term Trade Payables | B51: BS_LT_TRADE_PAYABLES | C51: =_xll.EQNXTDZ($A$1,$B51,C$1,$B$1) -> 0 | D51: =_xll.EQNXTDZ($A$1,$B51,D$1,$B$1) -> 0 | E51: =_xll.EQNXTDZ($A$1,$B51,E$1,$B$1) -> 0 | F51: =_xll.EQNXTDZ($A$1,$B51,F$1,$B$1) -> 0 | G51: =_xll.EQNXTDZ($A$1,$B51,G$1,$B$1) -> 0 | H51: =_xll.EQNXTDZ($A$1,$B51,H$1,$B$1) -> 0 | I51: =_xll.EQNXTDZ($A$1,$B51,I$1,$B$1) -> 0 | J51: =_xll.EQNXTDZ($A$1,$B51,J$1,$B$1) -> 0 | ... AG51: =_xll.EQNXTDZ($A$1,$B51,AG$1,$B$1) -> 0
... A99: Estimated Capital Contracts Remaining | B99: BS_ESTIMATED_CAPITAL_CONTRACT | C99: =_xll.EQNXTDZ($A$1,$B99,C$1,$B$1) -> 0 | D99: =_xll.EQNXTDZ($A$1,$B99,D$1,$B$1) -> 0 | E99: =_xll.EQNXTDZ($A$1,$B99,E$1,$B$1) -> 0 | F99: =_xll.EQNXTDZ($A$1,$B99,F$1,$B$1) -> 0 | G99: =_xll.EQNXTDZ($A$1,$B99,G$1,$B$1) -> 0 | H99: =_xll.EQNXTDZ($A$1,$B99,H$1,$B$1) -> 0 | I99: =_xll.EQNXTDZ($A$1,$B99,I$1,$B$1) -> 0 | J99: =_xll.EQNXTDZ($A$1,$B99,J$1,$B$1) -> 0 | ... AG99: =_xll.EQNXTDZ($A$1,$B99,AG$1,$B$1) -> 0
A103: Field Description | B103: Field Name
A104: Equity Paid Up | B104: BS_EQUITY_PAIDUP | C104: =_xll.EQNXTDZ($A$1,$B104,C$1,$B$1) -> 4.937813 | D104: =_xll.EQNXTDZ($A$1,$B104,D$1,$B$1) -> 4.937813 | E104: =_xll.EQNXTDZ($A$1,$B104,E$1,$B$1) -> 0 | F104: =_xll.EQNXTDZ($A$1,$B104,F$1,$B$1) -> 0 | G104: =_xll.EQNXTDZ($A$1,$B104,G$1,$B$1) -> 0 | H104: =_xll.EQNXTDZ($A$1,$B104,H$1,$B$1) -> 0 | I104: =_xll.EQNXTDZ($A$1,$B104,I$1,$B$1) -> 0 | J104: =_xll.EQNXTDZ($A$1,$B104,J$1,$B$1) -> 0 | ... AG104: =_xll.EQNXTDZ($A$1,$B104,AG$1,$B$1) -> 0
A105: Face Value | B105: BS_FACE_VALUE | C105: =_xll.EQNXTDZ($A$1,$B105,C$1,$B$1) -> 10 | D105: =_xll.EQNXTDZ($A$1,$B105,D$1,$B$1) -> 10 | E105: =_xll.EQNXTDZ($A$1,$B105,E$1,$B$1) -> 0 | F105: =_xll.EQNXTDZ($A$1,$B105,F$1,$B$1) -> 0 | G105: =_xll.EQNXTDZ($A$1,$B105,G$1,$B$1) -> 0 | H105: =_xll.EQNXTDZ($A$1,$B105,H$1,$B$1) -> 0 | I105: =_xll.EQNXTDZ($A$1,$B105,I$1,$B$1) -> 0 | J105: =_xll.EQNXTDZ($A$1,$B105,J$1,$B$1) -> 0 | ... AG105: =_xll.EQNXTDZ($A$1,$B105,AG$1,$B$1) -> 0
A106: Close Price (Unit Curr.) | B106: FH_YEAR_PRICE | C106: =_xll.EQNXTDZ($A$1,$B106,C$1,$B$1) -> 16.5 | D106: =_xll.EQNXTDZ($A$1,$B106,D$1,$B$1) -> 15.85 | E106: =_xll.EQNXTDZ($A$1,$B106,E$1,$B$1) -> 0 | F106: =_xll.EQNXTDZ($A$1,$B106,F$1,$B$1) -> 0 | G106: =_xll.EQNXTDZ($A$1,$B106,G$1,$B$1) -> 0 | H106: =_xll.EQNXTDZ($A$1,$B106,H$1,$B$1) -> 0 | I106: =_xll.EQNXTDZ($A$1,$B106,I$1,$B$1) -> 0 | J106: =_xll.EQNXTDZ($A$1,$B106,J$1,$B$1) -> 0 | ... AG106: =_xll.EQNXTDZ($A$1,$B106,AG$1,$B$1) -> 0
A107: High Price (Unit Curr.) | B107: FH_HIGH | C107: =_xll.EQNXTDZ($A$1,$B107,C$1,$B$1) -> 46 | D107: =_xll.EQNXTDZ($A$1,$B107,D$1,$B$1) -> 28.95 | E107: =_xll.EQNXTDZ($A$1,$B107,E$1,$B$1) -> 0 | F107: =_xll.EQNXTDZ($A$1,$B107,F$1,$B$1) -> 0 | G107: =_xll.EQNXTDZ($A$1,$B107,G$1,$B$1) -> 0 | H107: =_xll.EQNXTDZ($A$1,$B107,H$1,$B$1) -> 0 | I107: =_xll.EQNXTDZ($A$1,$B107,I$1,$B$1) -> 0 | J107: =_xll.EQNXTDZ($A$1,$B107,J$1,$B$1) -> 0 | ... AG107: =_xll.EQNXTDZ($A$1,$B107,AG$1,$B$1) -> 0
A108: Low Price (Unit Curr.) | B108: FH_LOW | C108: =_xll.EQNXTDZ($A$1,$B108,C$1,$B$1) -> 13.85 | D108: =_xll.EQNXTDZ($A$1,$B108,D$1,$B$1) -> 10.75 | E108: =_xll.EQNXTDZ($A$1,$B108,E$1,$B$1) -> 0 | F108: =_xll.EQNXTDZ($A$1,$B108,F$1,$B$1) -> 0 | G108: =_xll.EQNXTDZ($A$1,$B108,G$1,$B$1) -> 0 | H108: =_xll.EQNXTDZ($A$1,$B108,H$1,$B$1) -> 0 | I108: =_xll.EQNXTDZ($A$1,$B108,I$1,$B$1) -> 0 | J108: =_xll.EQNXTDZ($A$1,$B108,J$1,$B$1) -> 0 | ... AG108: =_xll.EQNXTDZ($A$1,$B108,AG$1,$B$1) -> 0
A109: Market Capitalization | B109: FH_MCAP | C109: =_xll.EQNXTDZ($A$1,$B109,C$1,$B$1) -> 8.1473915 | D109: =_xll.EQNXTDZ($A$1,$B109,D$1,$B$1) -> 7.8264336 | E109: =_xll.EQNXTDZ($A$1,$B109,E$1,$B$1) -> 0 | F109: =_xll.EQNXTDZ($A$1,$B109,F$1,$B$1) -> 0 | G109: =_xll.EQNXTDZ($A$1,$B109,G$1,$B$1) -> 0 | H109: =_xll.EQNXTDZ($A$1,$B109,H$1,$B$1) -> 0 | I109: =_xll.EQNXTDZ($A$1,$B109,I$1,$B$1) -> 0 | J109: =_xll.EQNXTDZ($A$1,$B109,J$1,$B$1) -> 0 | ... AG109: =_xll.EQNXTDZ($A$1,$B109,AG$1,$B$1) -> 0
A110: Adj DPS(Rs) | B110: FR_ADJ_DPS | C110: =_xll.EQNXTDZ($A$1,$B110,C$1,$B$1) -> 0 | D110: =_xll.EQNXTDZ($A$1,$B110,D$1,$B$1) -> 2.5 | E110: =_xll.EQNXTDZ($A$1,$B110,E$1,$B$1) -> 0 | F110: =_xll.EQNXTDZ($A$1,$B110,F$1,$B$1) -> 0 | G110: =_xll.EQNXTDZ($A$1,$B110,G$1,$B$1) -> 0 | H110: =_xll.EQNXTDZ($A$1,$B110,H$1,$B$1) -> 0 | I110: =_xll.EQNXTDZ($A$1,$B110,I$1,$B$1) -> 0 | J110: =_xll.EQNXTDZ($A$1,$B110,J$1,$B$1) -> 0 | ... AG110: =_xll.EQNXTDZ($A$1,$B110,AG$1,$B$1) -> 0
A111: Date End | B111: SHP_DATE_END | C111: =_xll.EQNXTDZ($A$1,$B111,C$5) -> 0 | D111: =_xll.EQNXTDZ($A$1,$B111,D$5) -> 200103 | E111: =_xll.EQNXTDZ($A$1,$B111,E$5) -> 0 | F111: =_xll.EQNXTDZ($A$1,$B111,F$5) -> 0 | G111: =_xll.EQNXTDZ($A$1,$B111,G$5) -> 0 | H111: =_xll.EQNXTDZ($A$1,$B111,H$5) -> 0 | I111: =_xll.EQNXTDZ($A$1,$B111,I$5) -> 0 | J111: =_xll.EQNXTDZ($A$1,$B111,J$5) -> 0 | ... AG111: =_xll.EQNXTDZ($A$1,$B111,AG$5) -> 0
A112: Total of Promoter and Promoter Group | B112: SHP_TPFTOTALPROMOTER | C112: =_xll.EQNXTDZ($A$1,$B112,C$5) -> 0 | D112: =_xll.EQNXTDZ($A$1,$B112,D$5) -> 54.91 | E112: =_xll.EQNXTDZ($A$1,$B112,E$5) -> 0 | F112: =_xll.EQNXTDZ($A$1,$B112,F$5) -> 0 | G112: =_xll.EQNXTDZ($A$1,$B112,G$5) -> 0 | H112: =_xll.EQNXTDZ($A$1,$B112,H$5) -> 0 | I112: =_xll.EQNXTDZ($A$1,$B112,I$5) -> 0 | J112: =_xll.EQNXTDZ($A$1,$B112,J$5) -> 0 | ... AG112: =_xll.EQNXTDZ($A$1,$B112,AG$5) -> 0
A113: Total of Promoter and Promoter Group Pledged | B113: SHP_PSHFTOTALPROMOTER | C113: =_xll.EQNXTDZ($A$1,$B113,C$5) -> 0 | D113: =_xll.EQNXTDZ($A$1,$B113,D$5) -> 0 | E113: =_xll.EQNXTDZ($A$1,$B113,E$5) -> 0 | F113: =_xll.EQNXTDZ($A$1,$B113,F$5) -> 0 | G113: =_xll.EQNXTDZ($A$1,$B113,G$5) -> 0 | H113: =_xll.EQNXTDZ($A$1,$B113,H$5) -> 0 | I113: =_xll.EQNXTDZ($A$1,$B113,I$5) -> 0 | J113: =_xll.EQNXTDZ($A$1,$B113,J$5) -> 0 | ... AG113: =_xll.EQNXTDZ($A$1,$B113,AG$5) -> 0

Sheet QTR Share Price
A1: ='QTR Raw'!A1 -> 100147 | C1: 201206 | D1: 201207 | E1: 201208 | F1: 201209 | G1: 201210 | H1: 201211 | I1: 201212 | J1: 201301 | K1: 201302 | L1: 201303 | M1: 201304 | N1: 201305 | O1: 201306 | P1: 201307 | Q1: 201308 | R1: 201309 | S1: 201310 | T1: 201311 | U1: 201312 | V1: 201401 | W1: 201402 | X1: 201403 | Y1: 201404 | Z1: 201405 | AA1: 201406 | AB1: 201407 | AC1: 201408 | AD1: 201409 | AE1: 201410 | AF1: 201411 | AG1: 201412 | AH1: 201501 | AI1: 201502 | AJ1: 201503 | AK1: 201504 | AL1: 201505 | AM1: 201506 | AN1: 201507 | AO1: 201508 | AP1: 201509 | AQ1: 201510 | AR1: 201511 | AS1: 201512 | AT1: 201601 | AU1: 201602 | AV1: 201603 | AW1: 201604 | AX1: 201605 | AY1: 201606 | AZ1: 201607 | BA1: 201608 | BB1: 201609 | BC1: 201610 | BD1: 201611 | BE1: 201612 | BF1: 201701 | BG1: 201702 | BH1: 201703 | BI1: 201704 | BJ1: 201705 | BK1: 201706 | BL1: 201707 | BM1: 201708 | BN1: 201709 | BO1: 201710 | BP1: 201711 | BQ1: 201712 | BR1: 201801 | BS1: 201802 | BT1: 201803 | BU1: 201804 | BV1: 201805 | BW1: 201806 | BX1: 201807 | BY1: 201808 | BZ1: 201809 | CA1: 201810 | CB1: 201811 | CC1: 201812 | CD1: 201901 | CE1: 201902 | CF1: 201903 | CG1: 201904 | CH1: 201905 | CI1: 201906 | CJ1: 201907 | CK1: 201908 | CL1: 201909 | CM1: 201910 | CN1: 201911 | CO1: 201912 | CP1: 202001 | CQ1: 202002 | CR1: 202003 | CS1: 202004 | CT1: 202005 | CU1: 202006 | CV1: 202007 | CW1: 202008 | CX1: 202009 | CY1: 202010 | CZ1: 202011 | DA1: 202012 | DB1: 202101 | DC1: 202102 | DD1: 202103 | DE1: 202104 | DF1: 202105 | DG1: 202106 | DH1: 202107 | DI1: 202108 | DJ1: 202109 | DK1: 202110 | DL1: 202111 | DM1: 202112 | DN1: 202201 | DO1: 202202 | DP1: 202203 | DQ1: 202204 | DR1: 202205 | DS1: 202206 | DT1: 202207 | DU1: 202208 | DV1: 202209 | DW1: 202210 | DX1: 202211 | DY1: 202212 | DZ1: 202301 | EA1: 202302 | EB1: 202303 | EC1: 202304 | ED1: 202305 | EE1: 202306 | EF1: 202307 | EG1: 202308 | EH1: 202309 | EI1: 202310 | EJ1: 202311 | EK1: 202312 | EL1: 202401 | EM1: 202402 | EN1: 202403 | EO1: 202404 | EP1: 202405 | EQ1: 202406 | ER1: 202407 | ES1: 202408 | ET1: 202409 | EU1: 202410 | EV1: 202411 | EW1: 202412 | EX1: 202501 | EY1: 202502 | EZ1: 202503 | FA1: 202504 | FB1: 202505 | FC1: 202506 | FD1: 202507 | FE1: 202508 | FF1: 202509 | FG1: 202510 | FH1: 202511 | FI1: 202512 | FJ1: 202601 | FK1: 202602 | FL1: 202603 | FM1: 202604 | FN1: 202605 | FO1: 202606 | FP1: 202607 | FQ1: 202608 | FR1: 202609 | FS1: 202610 | FT1: 202611 | FU1: 202612 | FV1: 202701 | FW1: 202702 | FX1: 202703 | FY1: 202704 | FZ1: 202705 | GA1: 202706 | GB1: 202707 | GC1: 202708 | GD1: 202709 | GE1: 202710 | GF1: 202711 | GG1: 202712 | GH1: 202801 | GI1: 202802 | GJ1: 202803 | GK1: 202804 | GL1: 202805 | GM1: 202806 | GN1: 202807 | GO1: 202808 | GP1: 202809 | GQ1: 202810 | GR1: 202811 | GS1: 202812 | GT1: 202901 | GU1: 202902 | GV1: 202903 | GW1: 202904 | GX1: 202905 | GY1: 202906 | GZ1: 202907 | HA1: 202908 | HB1: 202909 | HC1: 202910 | HD1: 202911 | HE1: 202912 | HF1: 203001 | HG1: 203002 | HH1: 203003 | HM1: 201206 | HN1: 201207 | HO1: 201208 | HP1: 201209 | HQ1: 201212 | HR1: 201303 | HS1: 201306 | HT1: 201309 | HU1: 201312 | HV1: 201403 | HW1: 201406 | HX1: 201409 | HY1: 201412 | HZ1: 201503 | IA1: 201506 | IB1: 201509 | IC1: 201512 | ID1: 201603 | IE1: 201606 | IF1: 201609 | IG1: 201612 | IH1: 201703 | II1: 201706 | IJ1: 201709 | IK1: 201712 | IL1: 201803 | IM1: 201806 | IN1: 201809 | IO1: 201812 | IP1: 201903 | IQ1: 201906 | IR1: 201909 | IS1: 201912 | IT1: 202003 | IU1: 202006 | IV1: 202009 | IW1: 202012 | IX1: 202103 | IY1: 202106 | IZ1: 202109 | JA1: 202112 | JB1: 202203 | JC1: 202206 | JD1: 202209 | JE1: 202212 | JF1: 202303 | JG1: 202306 | JH1: 202309 | JI1: 202312 | JJ1: 202403 | JK1: 202406 | JL1: 202409 | JM1: 202412 | JN1: 202503 | JO1: 202506 | JP1: 202509 | JQ1: 202512 | JR1: 202603 | JS1: 202606 | JT1: 202609 | JU1: 202612 | JV1: 202703 | JW1: 202706 | JX1: 202709 | JY1: 202712 | JZ1: 202803 | KA1: 202806 | KB1: 202809 | KC1: 202812 | KD1: 202903 | KE1: 202906 | KF1: 202909 | KG1: 202912 | KH1: 203003
A4: Field Description | B4: Field Name
A5: MonthEnd | B5: NMONTH_MONTHEND | C5: {=_xll.EQNXTDZ($A$1,$B5,C$1)} -> 0 | D5: {=_xll.EQNXTDZ($A$1,$B5,D$1)} -> 0 | E5: {=_xll.EQNXTDZ($A$1,$B5,E$1)} -> 0 | F5: {=_xll.EQNXTDZ($A$1,$B5,F$1)} -> 0 | G5: {=_xll.EQNXTDZ($A$1,$B5,G$1)} -> 0 | H5: {=_xll.EQNXTDZ($A$1,$B5,H$1)} -> 0 | I5: {=_xll.EQNXTDZ($A$1,$B5,I$1)} -> 0 | J5: {=_xll.EQNXTDZ($A$1,$B5,J$1)} -> 0 | ... HH5: {=_xll.EQNXTDZ($A$1,$B5,HH$1)} -> 0
A6: Open | B6: NMONTH_OPEN | C6: {=_xll.EQNXTDZ($A$1,$B6,C$1)} -> 0 | D6: {=_xll.EQNXTDZ($A$1,$B6,D$1)} -> 0 | E6: {=_xll.EQNXTDZ($A$1,$B6,E$1)} -> 0 | F6: {=_xll.EQNXTDZ($A$1,$B6,F$1)} -> 0 | G6: {=_xll.EQNXTDZ($A$1,$B6,G$1)} -> 0 | H6: {=_xll.EQNXTDZ($A$1,$B6,H$1)} -> 0 | I6: {=_xll.EQNXTDZ($A$1,$B6,I$1)} -> 0 | J6: {=_xll.EQNXTDZ($A$1,$B6,J$1)} -> 0 | ... HH6: {=_xll.EQNXTDZ($A$1,$B6,HH$1)} -> 0
A7: High | B7: NMONTH_HIGH | C7: {=_xll.EQNXTDZ($A$1,$B7,C$1)} -> 0 | D7: {=_xll.EQNXTDZ($A$1,$B7,D$1)} -> 0 | E7: {=_xll.EQNXTDZ($A$1,$B7,E$1)} -> 0 | F7: {=_xll.EQNXTDZ($A$1,$B7,F$1)} -> 0 | G7: {=_xll.EQNXTDZ($A$1,$B7,G$1)} -> 0 | H7: {=_xll.EQNXTDZ($A$1,$B7,H$1)} -> 0 | I7: {=_xll.EQNXTDZ($A$1,$B7,I$1)} -> 0 | J7: {=_xll.EQNXTDZ($A$1,$B7,J$1)} -> 0 | ... HH7: {=_xll.EQNXTDZ($A$1,$B7,HH$1)} -> 0 | HP7: =+MAX(D7:F7) -> 0 | HQ7: =+MAX(G7:I7) -> 0 | HR7: =+MAX(J7:L7) -> 0 | HS7: =+MAX(M7:O7) -> 0 | HT7: =+MAX(P7:R7) -> 0 | HU7: =+MAX(S7:U7) -> 0 | HV7: =+MAX(V7:X7) -> 0 | HW7: =+MAX(Y7:AA7) -> 0 | HX7: =+MAX(AB7:AD7) -> 0 | HY7: =+MAX(AE7:AG7) -> 0 | HZ7: =+MAX(AH7:AJ7) -> 0 | IA7: =+MAX(AK7:AM7) -> 0 | IB7: =+MAX(AN7:AP7) -> 0 | IC7: =+MAX(AQ7:AS7) -> 0 | ID7: =+MAX(AT7:AV7) -> 0 | IE7: =+MAX(AW7:AY7) -> 0 | IF7: =+MAX(AZ7:BB7) -> 0 | IG7: =+MAX(BC7:BE7) -> 0 | IH7: =+MAX(BF7:BH7) -> 0 | II7: =+MAX(BI7:BK7) -> 0 | IJ7: =+MAX(BL7:BN7) -> 0 | IK7: =+MAX(BO7:BQ7) -> 0 | IL7: =+MAX(BR7:BT7) -> 0 | IM7: =+MAX(BU7:BW7) -> 0 | IN7: =+MAX(BX7:BZ7) -> 0 | IO7: =+MAX(CA7:CC7) -> 0 | IP7: =+MAX(CD7:CF7) -> 0 | IQ7: =+MAX(CG7:CI7) -> 0 | IR7: =+MAX(CJ7:CL7) -> 0 | IS7: =+MAX(CM7:CO7) -> 0 | IT7: =+MAX(CP7:CR7) -> 0 | IU7: =+MAX(CS7:CU7) -> 0 | IV7: =+MAX(CV7:CX7) -> 0 | IW7: =+MAX(CY7:DA7) -> 0 | IX7: =+MAX(DB7:DD7) -> 0 | IY7: =+MAX(DE7:DG7) -> 0 | IZ7: =+MAX(DH7:DJ7) -> 0 | JA7: =+MAX(DK7:DM7) -> 0 | JB7: =+MAX(DN7:DP7) -> 0 | JC7: =+MAX(DQ7:DS7) -> 0 | JD7: =+MAX(DT7:DV7) -> 0 | JE7: =+MAX(DW7:DY7) -> 0 | JF7: =+MAX(DZ7:EB7) -> 0 | JG7: =+MAX(EC7:EE7) -> 0 | JH7: =+MAX(EF7:EH7) -> 0 | JI7: =+MAX(EI7:EK7) -> 0 | JJ7: =+MAX(EL7:EN7) -> 0 | JK7: =MAX(EO7:EQ7) -> 0 | JL7: =MAX(ER7:ET7) -> 0 | JM7: =MAX(EU7:EW7) -> 0 | JN7: =MAX(EX7:EZ7) -> 0 | JO7: =MAX(FA7:FC7) -> 0 | JP7: =MAX(FD7:FF7) -> 0 | JQ7: =MAX(FG7:FI7) -> 0 | JR7: =MAX(FJ7:FL7) -> 0 | JS7: =MAX(FM7:FO7) -> 10871.5 | JT7: =MAX(FP7:FR7) -> 0 | JU7: =MAX(FS7:FU7) -> 0 | JV7: =MAX(FV7:FX7) -> 0 | JW7: =MAX(FY7:GA7) -> 0 | JX7: =MAX(GB7:GD7) -> 0 | JY7: =MAX(GE7:GG7) -> 0 | JZ7: =MAX(GH7:GJ7) -> 0 | KA7: =MAX(GK7:GM7) -> 0 | KB7: =MAX(GN7:GP7) -> 0 | KC7: =MAX(GQ7:GS7) -> 0 | KD7: =MAX(GT7:GV7) -> 0 | KE7: =MAX(GW7:GY7) -> 0 | KF7: =MAX(GZ7:HB7) -> 0 | KG7: =MAX(HC7:HE7) -> 0 | KH7: =MAX(HF7:HH7) -> 0
A8: Low | B8: NMONTH_LOW | C8: {=_xll.EQNXTDZ($A$1,$B8,C$1)} -> 0 | D8: {=_xll.EQNXTDZ($A$1,$B8,D$1)} -> 0 | E8: {=_xll.EQNXTDZ($A$1,$B8,E$1)} -> 0 | F8: {=_xll.EQNXTDZ($A$1,$B8,F$1)} -> 0 | G8: {=_xll.EQNXTDZ($A$1,$B8,G$1)} -> 0 | H8: {=_xll.EQNXTDZ($A$1,$B8,H$1)} -> 0 | I8: {=_xll.EQNXTDZ($A$1,$B8,I$1)} -> 0 | J8: {=_xll.EQNXTDZ($A$1,$B8,J$1)} -> 0 | ... HH8: {=_xll.EQNXTDZ($A$1,$B8,HH$1)} -> 0 | HP8: =+MIN(D8:F8) -> 0 | HQ8: =+MIN(G8:I8) -> 0 | HR8: =+MIN(J8:L8) -> 0 | HS8: =+MIN(M8:O8) -> 0 | HT8: =+MIN(P8:R8) -> 0 | HU8: =+MIN(S8:U8) -> 0 | HV8: =+MIN(V8:X8) -> 0 | HW8: =+MIN(Y8:AA8) -> 0 | HX8: =+MIN(AB8:AD8) -> 0 | HY8: =+MIN(AE8:AG8) -> 0 | HZ8: =+MIN(AH8:AJ8) -> 0 | IA8: =+MIN(AK8:AM8) -> 0 | IB8: =+MIN(AN8:AP8) -> 0 | IC8: =+MIN(AQ8:AS8) -> 0 | ID8: =+MIN(AT8:AV8) -> 0 | IE8: =+MIN(AW8:AY8) -> 0 | IF8: =+MIN(AZ8:BB8) -> 0 | IG8: =+MIN(BC8:BE8) -> 0 | IH8: =+MIN(BF8:BH8) -> 0 | II8: =+MIN(BI8:BK8) -> 0 | IJ8: =+MIN(BL8:BN8) -> 0 | IK8: =+MIN(BO8:BQ8) -> 0 | IL8: =+MIN(BR8:BT8) -> 0 | IM8: =+MIN(BU8:BW8) -> 0 | IN8: =+MIN(BX8:BZ8) -> 0 | IO8: =+MIN(CA8:CC8) -> 0 | IP8: =+MIN(CD8:CF8) -> 0 | IQ8: =+MIN(CG8:CI8) -> 0 | IR8: =+MIN(CJ8:CL8) -> 0 | IS8: =+MIN(CM8:CO8) -> 0 | IT8: =+MIN(CP8:CR8) -> 0 | IU8: =+MIN(CS8:CU8) -> 0 | IV8: =+MIN(CV8:CX8) -> 0 | IW8: =+MIN(CY8:DA8) -> 0 | IX8: =+MIN(DB8:DD8) -> 0 | IY8: =+MIN(DE8:DG8) -> 0 | IZ8: =+MIN(DH8:DJ8) -> 0 | JA8: =+MIN(DK8:DM8) -> 0 | JB8: =+MIN(DN8:DP8) -> 0 | JC8: =+MIN(DQ8:DS8) -> 0 | JD8: =+MIN(DT8:DV8) -> 0 | JE8: =+MIN(DW8:DY8) -> 0 | JF8: =+MIN(DZ8:EB8) -> 0 | JG8: =+MIN(EC8:EE8) -> 0 | JH8: =+MIN(EF8:EH8) -> 0 | JI8: =+MIN(EI8:EK8) -> 0 | JJ8: =+MIN(EL8:EN8) -> 0 | JK8: =MIN(EO8:EQ8) -> 0 | JL8: =MIN(ER8:ET8) -> 0 | JM8: =MIN(EU8:EW8) -> 0 | JN8: =MIN(EX8:EZ8) -> 0 | JO8: =MIN(FA8:FC8) -> 0 | JP8: =MIN(FD8:FF8) -> 0 | JQ8: =MIN(FG8:FI8) -> 0 | JR8: =MIN(FJ8:FL8) -> 0 | JS8: =MIN(FM8:FO8) -> 5015.25 | JT8: =MIN(FP8:FR8) -> 0 | JU8: =MIN(FS8:FU8) -> 0 | JV8: =MIN(FV8:FX8) -> 0 | JW8: =MIN(FY8:GA8) -> 0 | JX8: =MIN(GB8:GD8) -> 0 | JY8: =MIN(GE8:GG8) -> 0 | JZ8: =MIN(GH8:GJ8) -> 0 | KA8: =MIN(GK8:GM8) -> 0 | KB8: =MIN(GN8:GP8) -> 0 | KC8: =MIN(GQ8:GS8) -> 0 | KD8: =MIN(GT8:GV8) -> 0 | KE8: =MIN(GW8:GY8) -> 0 | KF8: =MIN(GZ8:HB8) -> 0 | KG8: =MIN(HC8:HE8) -> 0 | KH8: =MIN(HF8:HH8) -> 0
A9: Close | B9: NMONTH_CLOSE | C9: {=_xll.EQNXTDZ($A$1,$B9,C$1)} -> 0 | D9: {=_xll.EQNXTDZ($A$1,$B9,D$1)} -> 0 | E9: {=_xll.EQNXTDZ($A$1,$B9,E$1)} -> 0 | F9: {=_xll.EQNXTDZ($A$1,$B9,F$1)} -> 0 | G9: {=_xll.EQNXTDZ($A$1,$B9,G$1)} -> 0 | H9: {=_xll.EQNXTDZ($A$1,$B9,H$1)} -> 0 | I9: {=_xll.EQNXTDZ($A$1,$B9,I$1)} -> 0 | J9: {=_xll.EQNXTDZ($A$1,$B9,J$1)} -> 0 | ... HH9: {=_xll.EQNXTDZ($A$1,$B9,HH$1)} -> 0 | HP9: =+F9 -> 0 | HQ9: =+I9 -> 0 | HR9: =+L9 -> 0 | HS9: =+O9 -> 0 | HT9: =+R9 -> 0 | HU9: =+U9 -> 0 | HV9: =+X9 -> 0 | HW9: =+AA9 -> 0 | HX9: =+AD9 -> 0 | HY9: =+AG9 -> 0 | HZ9: =+AJ9 -> 0 | IA9: =+AM9 -> 0 | IB9: =+AP9 -> 0 | IC9: =+AS9 -> 0 | ID9: =+AV9 -> 0 | IE9: =+AY9 -> 0 | IF9: =+BB9 -> 0 | IG9: =+BE9 -> 0 | IH9: =+BH9 -> 0 | II9: =+BK9 -> 0 | IJ9: =+BN9 -> 0 | IK9: =+BQ9 -> 0 | IL9: =+BT9 -> 0 | IM9: =+BW9 -> 0 | IN9: =+BZ9 -> 0 | IO9: =+CC9 -> 0 | IP9: =+CF9 -> 0 | IQ9: =+CI9 -> 0 | IR9: =+CL9 -> 0 | IS9: =+CO9 -> 0 | IT9: =+CR9 -> 0 | IU9: =+CU9 -> 0 | IV9: =+CX9 -> 0 | IW9: =+DA9 -> 0 | IX9: =+DD9 -> 0 | IY9: =+DG9 -> 0 | IZ9: =+DJ9 -> 0 | JA9: =+DM9 -> 0 | JB9: =+DP9 -> 0 | JC9: =+DS9 -> 0 | JD9: =+DV9 -> 0 | JE9: =+DY9 -> 0 | JF9: =+EB9 -> 0 | JG9: =+EE9 -> 0 | JH9: =+EH9 -> 0 | JI9: =+EK9 -> 0 | JJ9: =+EN9 -> 0 | JK9: =EQ9 -> 0 | JL9: =ET9 -> 0 | JM9: =EW9 -> 0 | JN9: =EZ9 -> 0 | JO9: =FC9 -> 0 | JP9: =FF9 -> 0 | JQ9: =FI9 -> 0 | JR9: =FL9 -> 0 | JS9: =FO9 -> 9283.5 | JT9: =FR9 -> 0 | JU9: =FU9 -> 0 | JV9: =FX9 -> 0 | JW9: =GA9 -> 0 | JX9: =GD9 -> 0 | JY9: =GG9 -> 0 | JZ9: =GJ9 -> 0 | KA9: =GM9 -> 0 | KB9: =GP9 -> 0 | KC9: =GS9 -> 0 | KD9: =GV9 -> 0 | KE9: =GY9 -> 0 | KF9: =HB9 -> 0 | KG9: =HE9 -> 0 | KH9: =HH9 -> 0
A11: Field Description | B11: Field Name | C11: {=_xll.EQNXTDZ($A$1,$B11,C$1)} -> 0 | D11: {=_xll.EQNXTDZ($A$1,$B11,D$1)} -> 0 | E11: {=_xll.EQNXTDZ($A$1,$B11,E$1)} -> 0 | F11: {=_xll.EQNXTDZ($A$1,$B11,F$1)} -> 0 | G11: {=_xll.EQNXTDZ($A$1,$B11,G$1)} -> 0 | H11: {=_xll.EQNXTDZ($A$1,$B11,H$1)} -> 0 | I11: {=_xll.EQNXTDZ($A$1,$B11,I$1)} -> 0 | J11: {=_xll.EQNXTDZ($A$1,$B11,J$1)} -> 0 | ... HH11: {=_xll.EQNXTDZ($A$1,$B11,HH$1)} -> 0
A12: Month End | B12: BMONTH_MONTHEND | C12: {=_xll.EQNXTDZ($A$1,$B12,C$1)} -> 201206 | D12: {=_xll.EQNXTDZ($A$1,$B12,D$1)} -> 201207 | E12: {=_xll.EQNXTDZ($A$1,$B12,E$1)} -> 201208 | F12: {=_xll.EQNXTDZ($A$1,$B12,F$1)} -> 201209 | G12: {=_xll.EQNXTDZ($A$1,$B12,G$1)} -> 201210 | H12: {=_xll.EQNXTDZ($A$1,$B12,H$1)} -> 201211 | I12: {=_xll.EQNXTDZ($A$1,$B12,I$1)} -> 201212 | J12: {=_xll.EQNXTDZ($A$1,$B12,J$1)} -> 201301 | ... HH12: {=_xll.EQNXTDZ($A$1,$B12,HH$1)} -> 0
A13: Open | B13: BMONTH_OPEN | C13: {=_xll.EQNXTDZ($A$1,$B13,C$1)} -> 642.05 | D13: {=_xll.EQNXTDZ($A$1,$B13,D$1)} -> 797.9 | E13: {=_xll.EQNXTDZ($A$1,$B13,E$1)} -> 763 | F13: {=_xll.EQNXTDZ($A$1,$B13,F$1)} -> 691 | G13: {=_xll.EQNXTDZ($A$1,$B13,G$1)} -> 703 | H13: {=_xll.EQNXTDZ($A$1,$B13,H$1)} -> 739 | I13: {=_xll.EQNXTDZ($A$1,$B13,I$1)} -> 654 | J13: {=_xll.EQNXTDZ($A$1,$B13,J$1)} -> 650.1 | ... HH13: {=_xll.EQNXTDZ($A$1,$B13,HH$1)} -> 0
A14: High | B14: BMONTH_HIGH | C14: {=_xll.EQNXTDZ($A$1,$B14,C$1)} -> 880 | D14: {=_xll.EQNXTDZ($A$1,$B14,D$1)} -> 807.85 | E14: {=_xll.EQNXTDZ($A$1,$B14,E$1)} -> 775 | F14: {=_xll.EQNXTDZ($A$1,$B14,F$1)} -> 824.4 | G14: {=_xll.EQNXTDZ($A$1,$B14,G$1)} -> 832 | H14: {=_xll.EQNXTDZ($A$1,$B14,H$1)} -> 764.4 | I14: {=_xll.EQNXTDZ($A$1,$B14,I$1)} -> 734.9 | J14: {=_xll.EQNXTDZ($A$1,$B14,J$1)} -> 668 | ... HH14: {=_xll.EQNXTDZ($A$1,$B14,HH$1)} -> 0 | HP14: =+MAX(D14:F14) -> 824.4 | HQ14: =+MAX(G14:I14) -> 832 | HR14: =+MAX(J14:L14) -> 668 | HS14: =+MAX(M14:O14) -> 424.9 | HT14: =+MAX(P14:R14) -> 337 | HU14: =+MAX(S14:U14) -> 320 | HV14: =+MAX(V14:X14) -> 466.5 | HW14: =+MAX(Y14:AA14) -> 598 | HX14: =+MAX(AB14:AD14) -> 593.35 | HY14: =+MAX(AE14:AG14) -> 596.95 | HZ14: =+MAX(AH14:AJ14) -> 544 | IA14: =+MAX(AK14:AM14) -> 557 | IB14: =+MAX(AN14:AP14) -> 549 | IC14: =+MAX(AQ14:AS14) -> 456 | ID14: =+MAX(AT14:AV14) -> 484.9 | IE14: =+MAX(AW14:AY14) -> 557 | IF14: =+MAX(AZ14:BB14) -> 430 | IG14: =+MAX(BC14:BE14) -> 508 | IH14: =+MAX(BF14:BH14) -> 699 | II14: =+MAX(BI14:BK14) -> 601 | IJ14: =+MAX(BL14:BN14) -> 999 | IK14: =+MAX(BO14:BQ14) -> 1360 | IL14: =+MAX(BR14:BT14) -> 1389 | IM14: =+MAX(BU14:BW14) -> 1049 | IN14: =+MAX(BX14:BZ14) -> 849 | IO14: =+MAX(CA14:CC14) -> 1035 | IP14: =+MAX(CD14:CF14) -> 1439.75 | IQ14: =+MAX(CG14:CI14) -> 1369.95 | IR14: =+MAX(CJ14:CL14) -> 1158.95 | IS14: =+MAX(CM14:CO14) -> 995 | IT14: =+MAX(CP14:CR14) -> 1050 | IU14: =+MAX(CS14:CU14) -> 600 | IV14: =+MAX(CV14:CX14) -> 877 | IW14: =+MAX(CY14:DA14) -> 880 | IX14: =+MAX(DB14:DD14) -> 862 | IY14: =+MAX(DE14:DG14) -> 990 | IZ14: =+MAX(DH14:DJ14) -> 1160 | JA14: =+MAX(DK14:DM14) -> 1472.95 | JB14: =+MAX(DN14:DP14) -> 1750 | JC14: =+MAX(DQ14:DS14) -> 1835 | JD14: =+MAX(DT14:DV14) -> 1438 | JE14: =+MAX(DW14:DY14) -> 1375.9 | JF14: =+MAX(DZ14:EB14) -> 1615 | JG14: =+MAX(EC14:EE14) -> 3009 | JH14: =+MAX(EF14:EH14) -> 3030 | JI14: =+MAX(EI14:EK14) -> 3290 | JJ14: =+MAX(EL14:EN14) -> 3659 | JK14: =MAX(EO14:EQ14) -> 6443 | JL14: =MAX(ER14:ET14) -> 6399 | JM14: =MAX(EU14:EW14) -> 6100 | JN14: =MAX(EX14:EZ14) -> 4376 | JO14: =MAX(FA14:FC14) -> 3990 | JP14: =MAX(FD14:FF14) -> 6385.85 | JQ14: =MAX(FG14:FI14) -> 6660 | JR14: =MAX(FJ14:FL14) -> 5940 | JS14: =MAX(FM14:FO14) -> 10846.15 | JT14: =MAX(FP14:FR14) -> 0 | JU14: =MAX(FS14:FU14) -> 0 | JV14: =MAX(FV14:FX14) -> 0 | JW14: =MAX(FY14:GA14) -> 0 | JX14: =MAX(GB14:GD14) -> 0 | JY14: =MAX(GE14:GG14) -> 0 | JZ14: =MAX(GH14:GJ14) -> 0 | KA14: =MAX(GK14:GM14) -> 0 | KB14: =MAX(GN14:GP14) -> 0 | KC14: =MAX(GQ14:GS14) -> 0 | KD14: =MAX(GT14:GV14) -> 0 | KE14: =MAX(GW14:GY14) -> 0 | KF14: =MAX(GZ14:HB14) -> 0 | KG14: =MAX(HC14:HE14) -> 0 | KH14: =MAX(HF14:HH14) -> 0
A15: Low | B15: BMONTH_LOW | C15: {=_xll.EQNXTDZ($A$1,$B15,C$1)} -> 626 | D15: {=_xll.EQNXTDZ($A$1,$B15,D$1)} -> 702 | E15: {=_xll.EQNXTDZ($A$1,$B15,E$1)} -> 680 | F15: {=_xll.EQNXTDZ($A$1,$B15,F$1)} -> 651 | G15: {=_xll.EQNXTDZ($A$1,$B15,G$1)} -> 680 | H15: {=_xll.EQNXTDZ($A$1,$B15,H$1)} -> 644 | I15: {=_xll.EQNXTDZ($A$1,$B15,I$1)} -> 640 | J15: {=_xll.EQNXTDZ($A$1,$B15,J$1)} -> 602 | ... HH15: {=_xll.EQNXTDZ($A$1,$B15,HH$1)} -> 0 | HP15: =+MIN(D15:F15) -> 651 | HQ15: =+MIN(G15:I15) -> 640 | HR15: =+MIN(J15:L15) -> 361.1 | HS15: =+MIN(M15:O15) -> 318.25 | HT15: =+MIN(P15:R15) -> 207.2 | HU15: =+MIN(S15:U15) -> 231 | HV15: =+MIN(V15:X15) -> 305.5 | HW15: =+MIN(Y15:AA15) -> 451 | HX15: =+MIN(AB15:AD15) -> 400.05 | HY15: =+MIN(AE15:AG15) -> 420 | HZ15: =+MIN(AH15:AJ15) -> 340.2 | IA15: =+MIN(AK15:AM15) -> 340 | IB15: =+MIN(AN15:AP15) -> 385 | IC15: =+MIN(AQ15:AS15) -> 340 | ID15: =+MIN(AT15:AV15) -> 345.2 | IE15: =+MIN(AW15:AY15) -> 370 | IF15: =+MIN(AZ15:BB15) -> 352 | IG15: =+MIN(BC15:BE15) -> 354 | IH15: =+MIN(BF15:BH15) -> 408.5 | II15: =+MIN(BI15:BK15) -> 470.1 | IJ15: =+MIN(BL15:BN15) -> 484.6 | IK15: =+MIN(BO15:BQ15) -> 770 | IL15: =+MIN(BR15:BT15) -> 830 | IM15: =+MIN(BU15:BW15) -> 751 | IN15: =+MIN(BX15:BZ15) -> 650 | IO15: =+MIN(CA15:CC15) -> 627.1 | IP15: =+MIN(CD15:CF15) -> 970 | IQ15: =+MIN(CG15:CI15) -> 992.05 | IR15: =+MIN(CJ15:CL15) -> 740.05 | IS15: =+MIN(CM15:CO15) -> 740 | IT15: =+MIN(CP15:CR15) -> 340 | IU15: =+MIN(CS15:CU15) -> 402 | IV15: =+MIN(CV15:CX15) -> 480 | IW15: =+MIN(CY15:DA15) -> 700 | IX15: =+MIN(DB15:DD15) -> 750 | IY15: =+MIN(DE15:DG15) -> 765 | IZ15: =+MIN(DH15:DJ15) -> 852.05 | JA15: =+MIN(DK15:DM15) -> 862.85 | JB15: =+MIN(DN15:DP15) -> 1045.05 | JC15: =+MIN(DQ15:DS15) -> 1000 | JD15: =+MIN(DT15:DV15) -> 1043.05 | JE15: =+MIN(DW15:DY15) -> 1132.4 | JF15: =+MIN(DZ15:EB15) -> 1266.05 | JG15: =+MIN(EC15:EE15) -> 1420 | JH15: =+MIN(EF15:EH15) -> 2374 | JI15: =+MIN(EI15:EK15) -> 2660 | JJ15: =+MIN(EL15:EN15) -> 2910 | JK15: =MIN(EO15:EQ15) -> 3126.1 | JL15: =MIN(ER15:ET15) -> 4551 | JM15: =MIN(EU15:EW15) -> 4105 | JN15: =MIN(EX15:EZ15) -> 2383 | JO15: =MIN(FA15:FC15) -> 2619.9 | JP15: =MIN(FD15:FF15) -> 3402.1 | JQ15: =MIN(FG15:FI15) -> 4525 | JR15: =MIN(FJ15:FL15) -> 4041.05 | JS15: =MIN(FM15:FO15) -> 4152 | JT15: =MIN(FP15:FR15) -> 0 | JU15: =MIN(FS15:FU15) -> 0 | JV15: =MIN(FV15:FX15) -> 0 | JW15: =MIN(FY15:GA15) -> 0 | JX15: =MIN(GB15:GD15) -> 0 | JY15: =MIN(GE15:GG15) -> 0 | JZ15: =MIN(GH15:GJ15) -> 0 | KA15: =MIN(GK15:GM15) -> 0 | KB15: =MIN(GN15:GP15) -> 0 | KC15: =MIN(GQ15:GS15) -> 0 | KD15: =MIN(GT15:GV15) -> 0 | KE15: =MIN(GW15:GY15) -> 0 | KF15: =MIN(GZ15:HB15) -> 0 | KG15: =MIN(HC15:HE15) -> 0 | KH15: =MIN(HF15:HH15) -> 0
A16: Close | B16: BMONTH_CLOSE | C16: {=_xll.EQNXTDZ($A$1,$B16,C$1)} -> 763.65 | D16: {=_xll.EQNXTDZ($A$1,$B16,D$1)} -> 715 | E16: {=_xll.EQNXTDZ($A$1,$B16,E$1)} -> 688.05 | F16: {=_xll.EQNXTDZ($A$1,$B16,F$1)} -> 705.5 | G16: {=_xll.EQNXTDZ($A$1,$B16,G$1)} -> 748.45 | H16: {=_xll.EQNXTDZ($A$1,$B16,H$1)} -> 666 | I16: {=_xll.EQNXTDZ($A$1,$B16,I$1)} -> 660 | J16: {=_xll.EQNXTDZ($A$1,$B16,J$1)} -> 612.7 | ... HH16: {=_xll.EQNXTDZ($A$1,$B16,HH$1)} -> 0 | HP16: =+F16 -> 705.5 | HQ16: =+I16 -> 660 | HR16: =+L16 -> 372.95 | HS16: =+O16 -> 330 | HT16: =+R16 -> 263 | HU16: =+U16 -> 314.4 | HV16: =+X16 -> 445 | HW16: =+AA16 -> 512.6 | HX16: =+AD16 -> 461 | HY16: =+AG16 -> 505 | HZ16: =+AJ16 -> 398 | IA16: =+AM16 -> 380 | IB16: =+AP16 -> 407.2 | IC16: =+AS16 -> 387.5 | ID16: =+AV16 -> 408.1 | IE16: =+AY16 -> 400 | IF16: =+BB16 -> 376 | IG16: =+BE16 -> 434.05 | IH16: =+BH16 -> 585.3 | II16: =+BK16 -> 498 | IJ16: =+BN16 -> 899.85 | IK16: =+BQ16 -> 1274.1 | IL16: =+BT16 -> 872.55 | IM16: =+BW16 -> 777.15 | IN16: =+BZ16 -> 670 | IO16: =+CC16 -> 987.65 | IP16: =+CF16 -> 1338.8 | IQ16: =+CI16 -> 1099.65 | IR16: =+CL16 -> 939.95 | IS16: =+CO16 -> 938.35 | IT16: =+CR16 -> 417.25 | IU16: =+CU16 -> 481.15 | IV16: =+CX16 -> 798.05 | IW16: =+DA16 -> 787.5 | IX16: =+DD16 -> 833.1 | IY16: =+DG16 -> 925.05 | IZ16: =+DJ16 -> 926.9 | JA16: =+DM16 -> 1029.75 | JB16: =+DP16 -> 1556.9 | JC16: =+DS16 -> 1158.95 | JD16: =+DV16 -> 1260.05 | JE16: =+DY16 -> 1309.15 | JF16: =+EB16 -> 1451.95 | JG16: =+EE16 -> 2947.45 | JH16: =+EH16 -> 2879 | JI16: =+EK16 -> 3066.75 | JJ16: =+EN16 -> 3296.45 | JK16: =EQ16 -> 5998.15 | JL16: =ET16 -> 5744.6 | JM16: =EW16 -> 4184.5 | JN16: =EZ16 -> 2876 | JO16: =FC16 -> 3432.1 | JP16: =FF16 -> 5927.35 | JQ16: =FI16 -> 5268.95 | JR16: =FL16 -> 4082.2 | JS16: =FO16 -> 9296.55 | JT16: =FR16 -> 0 | JU16: =FU16 -> 0 | JV16: =FX16 -> 0 | JW16: =GA16 -> 0 | JX16: =GD16 -> 0 | JY16: =GG16 -> 0 | JZ16: =GJ16 -> 0 | KA16: =GM16 -> 0 | KB16: =GP16 -> 0 | KC16: =GS16 -> 0 | KD16: =GV16 -> 0 | KE16: =GY16 -> 0 | KF16: =HB16 -> 0 | KG16: =HE16 -> 0 | KH16: =HH16 -> 0
A19: High | HP19: =+IF(HP14=0,HP7,HP14) -> 824.4 | HQ19: =+IF(HQ14=0,HQ7,HQ14) -> 832 | HR19: =+IF(HR14=0,HR7,HR14) -> 668 | HS19: =+IF(HS14=0,HS7,HS14) -> 424.9 | HT19: =+IF(HT14=0,HT7,HT14) -> 337 | HU19: =+IF(HU14=0,HU7,HU14) -> 320 | HV19: =+IF(HV14=0,HV7,HV14) -> 466.5 | HW19: =+IF(HW14=0,HW7,HW14) -> 598 | ... KH19: =+IF(KH14=0,KH7,KH14) -> 0
A20: Low | HP20: =+IF(HP15=0,HP8,HP15) -> 651 | HQ20: =+IF(HQ15=0,HQ8,HQ15) -> 640 | HR20: =+IF(HR15=0,HR8,HR15) -> 361.1 | HS20: =+IF(HS15=0,HS8,HS15) -> 318.25 | HT20: =+IF(HT15=0,HT8,HT15) -> 207.2 | HU20: =+IF(HU15=0,HU8,HU15) -> 231 | HV20: =+IF(HV15=0,HV8,HV15) -> 305.5 | HW20: =+IF(HW15=0,HW8,HW15) -> 451 | ... KH20: =+IF(KH15=0,KH8,KH15) -> 0
A21: Close | HP21: =+IF(HP16=0,HP9,HP16) -> 705.5 | HQ21: =+IF(HQ16=0,HQ9,HQ16) -> 660 | HR21: =+IF(HR16=0,HR9,HR16) -> 372.95 | HS21: =+IF(HS16=0,HS9,HS16) -> 330 | HT21: =+IF(HT16=0,HT9,HT16) -> 263 | HU21: =+IF(HU16=0,HU9,HU16) -> 314.4 | HV21: =+IF(HV16=0,HV9,HV16) -> 445 | HW21: =+IF(HW16=0,HW9,HW16) -> 512.6 | ... KH21: =+IF(KH16=0,KH9,KH16) -> 0

Sheet QTR No. of Shares
A1: ='QTR Raw'!A1 -> 100147 | C1: 201206 | D1: 201209 | E1: 201212 | F1: 201303 | G1: 201306 | H1: 201309 | I1: 201312 | J1: 201403 | K1: 201406 | L1: 201409 | M1: 201412 | N1: 201503 | O1: 201506 | P1: 201509 | Q1: 201512 | R1: 201603 | S1: 201606 | T1: 201609 | U1: 201612 | V1: 201703 | W1: 201706 | X1: 201709 | Y1: 201712 | Z1: 201803 | AA1: 201806 | AB1: 201809 | AC1: 201812 | AD1: 201903 | AE1: 201906 | AF1: 201909 | AG1: 201912 | AH1: 202003 | AI1: 202006 | AJ1: 202009 | AK1: 202012 | AL1: 202103 | AM1: 202106 | AN1: 202109 | AO1: 202112 | AP1: 202203 | AQ1: 202206 | AR1: 202209 | AS1: 202212 | AT1: 202303 | AU1: 202306 | AV1: 202309 | AW1: 202312 | AX1: 202403 | AY1: 202406
A4: Field Description | B4: Field Name
A5: Date End | B5: SHP_DATE_END | C5: {=_xll.EQNXTDZ($A$1,$B5,C$1)} -> 201206 | D5: {=_xll.EQNXTDZ($A$1,$B5,D$1)} -> 201209 | E5: {=_xll.EQNXTDZ($A$1,$B5,E$1)} -> 201212 | F5: {=_xll.EQNXTDZ($A$1,$B5,F$1)} -> 201303 | G5: {=_xll.EQNXTDZ($A$1,$B5,G$1)} -> 201306 | H5: {=_xll.EQNXTDZ($A$1,$B5,H$1)} -> 201309 | I5: {=_xll.EQNXTDZ($A$1,$B5,I$1)} -> 201312 | J5: {=_xll.EQNXTDZ($A$1,$B5,J$1)} -> 201403 | ... AY5: {=_xll.EQNXTDZ($A$1,$B5,AY$1)} -> 202406
A6: Grand Total | B6: SHP_NSGRANDTOTAL | C6: {=_xll.EQNXTDZ($A$1,$B6,C$1)} -> 4937813 | D6: {=_xll.EQNXTDZ($A$1,$B6,D$1)} -> 4937813 | E6: {=_xll.EQNXTDZ($A$1,$B6,E$1)} -> 4937813 | F6: {=_xll.EQNXTDZ($A$1,$B6,F$1)} -> 4937815 | G6: {=_xll.EQNXTDZ($A$1,$B6,G$1)} -> 4937813 | H6: {=_xll.EQNXTDZ($A$1,$B6,H$1)} -> 4937813 | I6: {=_xll.EQNXTDZ($A$1,$B6,I$1)} -> 4937813 | J6: {=_xll.EQNXTDZ($A$1,$B6,J$1)} -> 4937813 | ... AY6: {=_xll.EQNXTDZ($A$1,$B6,AY$1)} -> 4937813
B7: In Crs. | C7: =+C6/10^7 -> 0.4937813 | D7: =+D6/10^7 -> 0.4937813 | E7: =+E6/10^7 -> 0.4937813 | F7: =+F6/10^7 -> 0.4937815 | G7: =+G6/10^7 -> 0.4937813 | H7: =+H6/10^7 -> 0.4937813 | I7: =+I6/10^7 -> 0.4937813 | J7: =+J6/10^7 -> 0.4937813 | ... AY7: =+AY6/10^7 -> 0.4937813

Sheet Share price Daily
A1: =_xll.EQNXTH(B1,"[ADJC];[ADJH];[ADJL];[ADJO];[UCLS];[VOLUME]","2015-Jan-01","Y","All traded days","Asc") -> EQNXTH | B1: =+'Annual Raw'!A1 -> 100147 | L1: =_xll.EQNXTH(B1,"[NADJC];[NADJH];[NADJLOW];[NADJOPEN];[NUCLOSE];[NVOLUME]","2015-Jan-01","Y","All traded days","Asc") -> EQNXTH
A2: John Cockerill India Ltd | L2: John Cockerill India Ltd
A3: DATE | B3: ADJHIGH | C3: ADJCLOSE | D3: ADJLOW | E3: ADJOPEN | F3: CLOSE | G3: VOLUME | L3: DATE | M3: ADJCLOSE | N3: ADJHIGH | O3: ADJLOW | P3: ADJOPEN | Q3: CLOSE | R3: VOLUME
A4: 42005 | B4: 525 | C4: 523.1 | D4: 502.05 | E4: 507 | F4: 523.1 | G4: 1023 | L4: 46133 | M4: 5212.65 | N4: 5286.75 | O4: 5161 | P4: 5204.6 | Q4: 5212.65 | R4: 862
A5: 42006 | B5: 529 | C5: 522.1 | D5: 498 | E5: 498 | F5: 522.1 | G5: 885 | L5: 46134 | M5: 5277.35 | N5: 5293 | O5: 5207 | P5: 5224.95 | Q5: 5277.35 | R5: 2861
A6: 42009 | B6: 516.5 | C6: 504.05 | D6: 501.2 | E6: 510.05 | F6: 504.05 | G6: 1722 | L6: 46135 | M6: 5213.95 | N6: 5292.95 | O6: 5108.15 | P6: 5292.95 | Q6: 5213.95 | R6: 1792
A7: 42010 | B7: 500 | C7: 485.95 | D7: 480 | E7: 480 | F7: 485.95 | G7: 271 | L7: 46136 | M7: 5136.7 | N7: 5238.05 | O7: 5015.25 | P7: 5160 | Q7: 5136.7 | R7: 1213
A8: 42011 | B8: 527 | C8: 489.7 | D8: 475 | E8: 527 | F8: 489.7 | G8: 909 | L8: 46139 | M8: 5173.45 | N8: 5265 | O8: 5100 | P8: 5265 | Q8: 5173.45 | R8: 1202
A9: 42012 | B9: 513 | C9: 505 | D9: 498 | E9: 513 | F9: 505 | G9: 288 | L9: 46140 | M9: 5156.5 | N9: 5255 | O9: 5149.9 | P9: 5250.85 | Q9: 5156.5 | R9: 1836
A10: 42013 | B10: 529 | C10: 508.45 | D10: 506.05 | E10: 519.9 | F10: 508.45 | G10: 798 | L10: 46141 | M10: 5174.4 | N10: 5265 | O10: 5141.05 | P10: 5240.35 | Q10: 5174.4 | R10: 1236
A11: 42016 | B11: 528.9 | C11: 525.9 | D11: 503.25 | E11: 515 | F11: 525.9 | G11: 1396 | L11: 46142 | M11: 5115.5 | N11: 5205.95 | O11: 5100 | P11: 5205 | Q11: 5115.5 | R11: 1649
A12: 42017 | B12: 531.9 | C12: 522.5 | D12: 514 | E12: 529 | F12: 522.5 | G12: 2552 | L12: 46146 | M12: 5086.5 | N12: 5169.5 | O12: 5061.5 | P12: 5116 | Q12: 5086.5 | R12: 2327
A13: 42018 | B13: 538.8 | C13: 513.8 | D13: 509.75 | E13: 538.8 | F13: 513.8 | G13: 301 | L13: 46147 | M13: 5193.5 | N13: 5229 | O13: 5060 | P13: 5060 | Q13: 5193.5 | R13: 1557
A14: 42019 | B14: 530 | C14: 529.9 | D14: 515 | E14: 515 | F14: 529.9 | G14: 347 | L14: 46148 | M14: 5191 | N14: 5295 | O14: 5102 | P14: 5250 | Q14: 5191 | R14: 3085
A15: 42020 | B15: 530 | C15: 516.65 | D15: 504 | E15: 504 | F15: 516.65 | G15: 336 | L15: 46149 | M15: 5579.5 | N15: 5635.5 | O15: 5150 | P15: 5189 | Q15: 5579.5 | R15: 12923
... A43: 42065 | B43: 412 | C43: 412 | D43: 405.1 | E43: 405.1 | F43: 412 | G43: 147 | L43: 46190 | M43: 9239.5 | N43: 9497 | O43: 9150.5 | P43: 9380 | Q43: 9239.5 | R43: 15554
A44: 42066 | B44: 424.5 | C44: 412.1 | D44: 406 | E44: 406 | F44: 412.1 | G44: 247
A45: 42067 | B45: 439 | C45: 409.4 | D45: 401.2 | E45: 401.2 | F45: 409.4 | G45: 709
A46: 42068 | B46: 410 | C46: 408.1 | D46: 406 | E46: 406 | F46: 408.1 | G46: 331
A47: 42072 | B47: 419.6 | C47: 412.7 | D47: 400.1 | E47: 404 | F47: 412.7 | G47: 717
A48: 42073 | B48: 420 | C48: 413.1 | D48: 402.4 | E48: 402.4 | F48: 413.1 | G48: 310
A49: 42074 | B49: 434 | C49: 410 | D49: 402 | E49: 434 | F49: 410 | G49: 48
A50: 42075 | B50: 411 | C50: 407 | D50: 404.4 | E50: 404.4 | F50: 407 | G50: 213
A51: 42076 | B51: 488.4 | C51: 474.7 | D51: 405.6 | E51: 429 | F51: 474.7 | G51: 3129
A52: 42079 | B52: 500 | C52: 471.2 | D52: 437 | E52: 472.9 | F52: 471.2 | G52: 53294
A53: 42080 | B53: 484.7 | C53: 444.1 | D53: 441.9 | E53: 484.7 | F53: 444.1 | G53: 1228
A54: 42081 | B54: 450 | C54: 447.7 | D54: 437.1 | E54: 450 | F54: 447.7 | G54: 1577
A55: 42082 | B55: 461.5 | C55: 419.7 | D55: 418 | E55: 421 | F55: 419.7 | G55: 1623
... A193: 42290 | B193: 410 | C193: 408 | D193: 408 | E193: 409.5 | F193: 408 | G193: 735
A194: 42291 | B194: 408 | C194: 408 | D194: 402 | E194: 406.1 | F194: 408 | G194: 305 | L194: 42284 | M194: 439.85 | N194: 444 | O194: 434 | P194: 435.05 | Q194: 439.85 | R194: 4065
A195: 42292 | B195: 425 | C195: 403.7 | D195: 402.1 | E195: 408 | F195: 403.7 | G195: 1689 | L195: 42285 | M195: 445.7 | N195: 448 | O195: 435.1 | P195: 435.1 | Q195: 445.7 | R195: 6627
A196: 42293 | B196: 409 | C196: 407.5 | D196: 405 | E196: 405 | F196: 407.5 | G196: 246 | L196: 42286 | M196: 460.15 | N196: 489.2 | O196: 441 | P196: 441 | Q196: 460.15 | R196: 43708
A197: 42296 | B197: 423.9 | C197: 419.9 | D197: 404 | E197: 423.9 | F197: 419.9 | G197: 286 | L197: 42289 | M197: 473.4 | N197: 487 | O197: 461 | P197: 461.35 | Q197: 473.4 | R197: 13443
A198: 42298 | B198: 420 | C198: 420 | D198: 415 | E198: 415 | F198: 420 | G198: 65 | L198: 42290 | M198: 489 | N198: 505 | O198: 475.2 | P198: 477.85 | Q198: 489 | R198: 30295
A199: 42300 | B199: 420 | C199: 413.7 | D199: 410 | E199: 410 | F199: 413.7 | G199: 784 | L199: 42291 | M199: 487.25 | N199: 497 | O199: 482.05 | P199: 497 | Q199: 487.25 | R199: 4166
A200: 42303 | B200: 415 | C200: 406.1 | D200: 405 | E200: 405.1 | F200: 406.1 | G200: 76 | L200: 42292 | M200: 483.15 | N200: 494.9 | O200: 482 | P200: 490 | Q200: 483.15 | R200: 3539
A201: 42304 | B201: 411 | C201: 411 | D201: 405 | E201: 405.1 | F201: 411 | G201: 843 | L201: 42293 | M201: 477.6 | N201: 490.45 | O201: 473.4 | P201: 490.45 | Q201: 477.6 | R201: 4174
A202: 42305 | B202: 440 | C202: 420.5 | D202: 400 | E202: 401.1 | F202: 420.5 | G202: 344 | L202: 42296 | M202: 474.35 | N202: 481.25 | O202: 470.05 | P202: 470.05 | Q202: 474.35 | R202: 4446
A203: 42306 | B203: 449 | C203: 428.6 | D203: 423 | E203: 440 | F203: 428.6 | G203: 970 | L203: 42297 | M203: 474.8 | N203: 484 | O203: 474 | P203: 478 | Q203: 474.8 | R203: 3527
A204: 42307 | B204: 436.5 | C204: 421.2 | D204: 405 | E204: 436.4 | F204: 421.2 | G204: 1660 | L204: 42298 | M204: 479.9 | N204: 486.8 | O204: 471.95 | P204: 478 | Q204: 479.9 | R204: 5919
A205: 42310 | B205: 403.1 | C205: 377.8 | D205: 365 | E205: 402 | F205: 377.8 | G205: 1705 | L205: 42300 | M205: 472.9 | N205: 488.5 | O205: 470.05 | P205: 481.55 | Q205: 472.9 | R205: 4793
... A2821: 46185 | B2821: 10200 | C2821: 10029.05 | D2821: 9646.3 | E2821: 9800.05 | F2821: 10029.05 | G2821: 5441 | L2821: 46161 | M2821: 1181.6 | N2821: 1248 | O2821: 1090 | P2821: 1090 | Q2821: 1181.6 | R2821: 3465855
A2822: 46188 | B2822: 10500 | C2822: 9333.85 | D2822: 9157.15 | E2822: 10500 | F2822: 9333.85 | G2822: 5484
A2823: 46189 | B2823: 9517.35 | C2823: 9296.55 | D2823: 9200 | E2823: 9394.95 | F2823: 9296.55 | G2823: 1920
A2824: 46190 | B2824: 9480 | C2824: 9254.7 | D2824: 9160 | E2824: 9386.45 | F2824: 9254.7 | G2824: 1992

Sheet Sheet2
J19: 219.3 | K19: 186.25 | L19: 186.75
J20: 192.9 | K20: 135.5 | L20: 146.9 | N20: 219.3 | O20: 192.9 | P20: 186 | Q20: 178.7 | R20: 207 | S20: 255.15 | T20: 348.25 | U20: 374 | V20: 495.9 | W20: 659.9 | X20: 613.4 | Y20: 607.9 | Z20: 555.95 | AA20: 497.8 | AB20: 459.9 | AC20: 374 | AD20: 362 | AE20: 341.5 | AF20: 384.2 | AG20: 433.8 | AH20: 460 | AI20: 474.4 | AJ20: 414.4 | AK20: 318.7 | AL20: 303.25 | AM20: 332.7 | AN20: 295 | AO20: 247 | AP20: 214.4 | AQ20: 179.5 | AR20: 97.9 | AS20: 119.1 | AT20: 130.65 | AU20: 148.55 | AV20: 153.8 | AW20: 152.9 | AX20: 136 | AY20: 141.15 | AZ20: 128.1 | BA20: 142.5 | BB20: 143.55 | BC20: 124.5 | BD20: 241 | BE20: 450 | BF20: 503.35
J21: 186 | K21: 145.4 | L21: 169.1 | N21: 186.25 | O21: 135.5 | P21: 145.4 | Q21: 108.95 | R21: 137 | S21: 170 | T21: 243.15 | U21: 307.5 | V21: 325.1 | W21: 463 | X21: 467.05 | Y21: 436.5 | Z21: 467 | AA21: 348.2 | AB21: 325 | AC21: 313.1 | AD21: 285 | AE21: 277.85 | AF21: 327 | AG21: 317 | AH21: 370.7 | AI21: 360 | AJ21: 271.15 | AK21: 233.15 | AL21: 218.8 | AM21: 262 | AN21: 223.6 | AO21: 137.6 | AP21: 142 | AQ21: 59.3 | AR21: 58 | AS21: 72.8 | AT21: 80 | AU21: 107.25 | AV21: 106 | AW21: 125.1 | AX21: 112.25 | AY21: 81.45 | AZ21: 88 | BA21: 90.35 | BB21: 106.05 | BC21: 98.55 | BD21: 119.25 | BE21: 210 | BF21: 349
J22: 178.7 | K22: 108.95 | L22: 139.75 | N22: 186.75 | O22: 146.9 | P22: 169.1 | Q22: 139.75 | R22: 202.15 | S22: 249.05 | T22: 346.4 | U22: 349.2 | V22: 469.9 | W22: 584.8 | X22: 536.15 | Y22: 513.35 | Z22: 474 | AA22: 438.55 | AB22: 355.4 | AC22: 334.95 | AD22: 298.8 | AE22: 328.35 | AF22: 343 | AG22: 389.9 | AH22: 443.05 | AI22: 407.5 | AJ22: 290.1 | AK22: 235.75 | AL22: 292.65 | AM22: 276.1 | AN22: 237.05 | AO22: 190.1 | AP22: 147.2 | AQ22: 71.9 | AR22: 75.2 | AS22: 90.1 | AT22: 117.2 | AU22: 116.3 | AV22: 140.5 | AW22: 128.6 | AX22: 133.65 | AY22: 91.65 | AZ22: 97.65 | BA22: 125 | BB22: 115.35 | BC22: 119.25 | BD22: 219.3 | BE22: 442.65 | BF22: 503.35
J23: 207 | K23: 137 | L23: 202.15
J24: 255.15 | K24: 170 | L24: 249.05
J25: 348.25 | K25: 243.15 | L25: 346.4
J26: 374 | K26: 307.5 | L26: 349.2
J27: 495.9 | K27: 325.1 | L27: 469.9
J28: 659.9 | K28: 463 | L28: 584.8
J29: 613.4 | K29: 467.05 | L29: 536.15
J30: 607.9 | K30: 436.5 | L30: 513.35
J31: 555.95 | K31: 467 | L31: 474
J32: 497.8 | K32: 348.2 | L32: 438.55
J33: 459.9 | K33: 325 | L33: 355.4
J34: 374 | K34: 313.1 | L34: 334.95
... J63: 503.35 | K63: 349 | L63: 503.35
