Workbook

Sheet Template
A1: =+'Annual Raw'!C4 -> KSB Ltd. | B1: 36951 | C1: =EOMONTH(B1,12) -> 37346 | D1: 37591 | E1: =EOMONTH(D1,12) -> 37986 | F1: =EOMONTH(E1,12) -> 38352 | G1: =EOMONTH(F1,12) -> 38717 | H1: =EOMONTH(G1,12) -> 39082 | I1: =EOMONTH(H1,12) -> 39447 | J1: =EOMONTH(I1,12) -> 39813 | K1: =EOMONTH(J1,12) -> 40178 | L1: =EOMONTH(K1,12) -> 40543 | ... AE1: =EOMONTH(AD1,12) -> 47483 | AH1: QTR | AI1: 41061 | AJ1: 41153 | AK1: 41244 | AL1: 41334 | AM1: 41426 | AN1: 41518 | AO1: 41609 | AP1: 41699 | AQ1: 41791 | AR1: 41883 | AS1: 41974 | AT1: 42064 | AU1: 42156 | AV1: 42248 | AW1: 42339 | AX1: 42430 | AY1: 42522 | AZ1: 42614 | BA1: 42705 | BB1: 42795 | BC1: 42887 | BD1: 42979 | BE1: 43070 | BF1: 43160 | BG1: 43252 | BH1: 43344 | BI1: 43435 | BJ1: 43525 | BK1: 43617 | BL1: 43709 | BM1: 43800 | BN1: 43891 | BO1: 43983 | BP1: 44075 | BQ1: =EOMONTH(BP1,3) -> 44196 | BR1: =EOMONTH(BQ1,3) -> 44286 | BS1: =EOMONTH(BR1,3) -> 44377 | BT1: =EOMONTH(BS1,3) -> 44469 | BU1: =EOMONTH(BT1,3) -> 44561 | BV1: =EOMONTH(BU1,3) -> 44651 | BW1: =EOMONTH(BV1,3) -> 44742 | BX1: =EOMONTH(BW1,3) -> 44834 | ... DA1: =EOMONTH(CZ1,3) -> 47483 | DD1: HISTORICAL ESTIMATES | DE1: 46022
A2: Presentation Data (Start)
A4: REVENUE FROM OPERATIONS
A5: Pumps | U5: 1087.8 | V5: 1008 | W5: 1262 | X5: 1521.9 | Y5: 1896.8 | Z5: 2108.1 | AA5: =SUM(CH5:CK5) -> 2215 | BK5: 247.6 | BL5: 315.5 | BM5: 281.5 | BN5: 216.7 | BO5: 189.2 | BP5: 301.6 | BQ5: 300.5 | BR5: 317.7 | BS5: 262.3 | BT5: 305.4 | BU5: 376.6 | BV5: 349.6 | BW5: 381.4 | BX5: 351.4 | BY5: 439.5 | BZ5: 412.9 | CA5: 501.8 | CB5: 473.8 | CC5: 508.3 | CD5: 450 | CE5: 540.6 | CF5: 515.3 | CG5: 602.2 | CH5: 473.8 | CI5: 551.2 | CJ5: 533.1 | CK5: 656.9 | CL5: 499.5
A6: Valves | U6: 208.1 | V6: 201 | W6: 237 | X6: 302.3 | Y6: 353.6 | Z6: 428.8 | AA6: =SUM(CH6:CK6) -> 485.1 | BK6: 55.5 | BL6: 50.5 | BM6: 55.8 | BN6: 40.7 | BO6: 29.9 | BP6: 60.8 | BQ6: 69.6 | BR6: 64.1 | BS6: 41.3 | BT6: 63.1 | BU6: 68.5 | BV6: 68.5 | BW6: 67.4 | BX6: 80.5 | BY6: 85.9 | BZ6: 77.3 | CA6: 90.3 | CB6: 90.9 | CC6: 95.1 | CD6: 95 | CE6: 106.4 | CF6: 102.2 | CG6: 125.2 | CH6: 122.4 | CI6: 116.3 | CJ6: 117.9 | CK6: 128.5 | CL6: 102.5
A7: Less Inter Segment Revenue | U7: 1.992 | V7: 0.885 | W7: 1.709 | X7: 2.24 | Y7: 3.162 | Z7: 3.814 | AA7: =SUM(CH7:CK7) -> 4.4 | BK7: 1.3 | BL7: 0.2 | BM7: 0.3 | BN7: 0.4 | BO7: 0.2 | BP7: 0.1 | BQ7: 0.2 | BR7: 0.2 | BS7: 0.6 | BT7: 0.4 | BU7: 0.5 | BV7: 0.4 | BW7: 0.4 | BX7: 0.6 | BY7: 0.8 | BZ7: 0.6 | CA7: 0.8 | CB7: 1 | CC7: 0.8 | CD7: 0.8 | CE7: 1 | CF7: 1 | CG7: 1 | CH7: 0.8 | CI7: 0.8 | CJ7: 1.4 | CK7: 1.4 | CL7: 0.7
A8: Net Revenue/Inc. From Ops. | U8: =+U5+U6-U7 -> 1293.908 | V8: =+V5+V6-V7 -> 1208.115 | W8: =+W5+W6-W7 -> 1497.291 | X8: =+X5+X6-X7 -> 1821.96 | Y8: =+Y5+Y6-Y7 -> 2247.238 | Z8: =+Z5+Z6-Z7 -> 2533.086 | AA8: =+AA5+AA6-AA7 -> 2695.7 | BK8: =SUM(BK5:BK6)-BK7 -> 301.8 | BL8: =SUM(BL5:BL6)-BL7 -> 365.8 | BM8: =SUM(BM5:BM6)-BM7 -> 337 | BN8: =SUM(BN5:BN6)-BN7 -> 257 | BO8: =SUM(BO5:BO6)-BO7 -> 218.9 | BP8: =SUM(BP5:BP6)-BP7 -> 362.3 | BQ8: =SUM(BQ5:BQ6)-BQ7 -> 369.9 | BR8: =SUM(BR5:BR6)-BR7 -> 381.6 | ... CL8: =SUM(CL5:CL6)-CL7 -> 601.3
A9: Checskum | U9: =+U46-U8 -> 0 | V9: =+V46-V8 -> 0 | W9: =+W46-W8 -> 0 | X9: =+X46-X8 -> 0 | Y9: =+Y46-Y8 -> 0 | Z9: =+Z46-Z8 -> 0 | AA9: =+AA46-AA8 -> 0.028 | BK9: =+BK46-BK8 -> 0 | BL9: =+BL46-BL8 -> 0 | BM9: =+BM46-BM8 -> 0 | BN9: =+BN46-BN8 -> 0 | BO9: =+BO46-BO8 -> 0 | BP9: =+BP46-BP8 -> 0 | BQ9: =+BQ46-BQ8 -> 0 | BR9: =+BR46-BR8 -> 0 | ... CL9: =+CL46-CL8 -> 0
A11: Growth (%)
A12: Pumps | V12: =+V5/U5-1 -> -0.073359073 | W12: =+W5/V5-1 -> 0.25198413 | X12: =+X5/W5-1 -> 0.20594295 | Y12: =+Y5/X5-1 -> 0.24633682 | Z12: =+Z5/Y5-1 -> 0.11139814 | AA12: =+AA5/Z5-1 -> 0.050709169 | BO12: =+BO5/BK5-1 -> -0.2358643 | BP12: =+BP5/BL5-1 -> -0.044057052 | BQ12: =+BQ5/BM5-1 -> 0.06749556 | BR12: =+BR5/BN5-1 -> 0.46608214 | BS12: =+BS5/BO5-1 -> 0.38636364 | BT12: =+BT5/BP5-1 -> 0.012599469 | BU12: =+BU5/BQ5-1 -> 0.25324459 | BV12: =+BV5/BR5-1 -> 0.10040919 | ... CL12: =+CL5/CH5-1 -> 0.054242296
A13: Valves | V13: =+V6/U6-1 -> -0.034118212 | W13: =+W6/V6-1 -> 0.17910448 | X13: =+X6/W6-1 -> 0.27552743 | Y13: =+Y6/X6-1 -> 0.16969897 | Z13: =+Z6/Y6-1 -> 0.21266968 | AA13: =+AA6/Z6-1 -> 0.13129664 | BO13: =+BO6/BK6-1 -> -0.46126126 | BP13: =+BP6/BL6-1 -> 0.2039604 | BQ13: =+BQ6/BM6-1 -> 0.24731183 | BR13: =+BR6/BN6-1 -> 0.57493857 | BS13: =+BS6/BO6-1 -> 0.3812709 | BT13: =+BT6/BP6-1 -> 0.037828947 | BU13: =+BU6/BQ6-1 -> -0.015804598 | BV13: =+BV6/BR6-1 -> 0.068642746 | ... CL13: =+CL6/CH6-1 -> -0.1625817
A15: PROFIT / LOSS BEFORE INTEREST & TAX
A16: Pumps | U16: 124.6 | V16: 127.8 | W16: 162.8 | X16: 197.2 | Y16: 214.8 | Z16: 231.3 | AA16: =SUM(CH16:CK16) -> 284.7 | BK16: 22.1 | BL16: 30 | BM16: 50 | BN16: 16.9 | BO16: 9.3 | BP16: 46.6 | BQ16: 55 | BR16: 46.8 | BS16: 31.3 | BT16: 40.3 | BU16: 44.4 | BV16: 43.1 | BW16: 54 | BX16: 40.8 | BY16: 59.3 | BZ16: 41.3 | CA16: 64.4 | CB16: 52.4 | CC16: 56.7 | CD16: 36.2 | CE16: 66.3 | CF16: 63.2 | CG16: 65.6 | CH16: 41.5 | CI16: 64 | CJ16: 70.7 | CK16: 108.5 | CL16: 39.3
A17: Valves | U17: 14.1 | V17: 16 | W17: 17.2 | X17: 27 | Y17: 45.1 | Z17: 64.8 | AA17: =SUM(CH17:CK17) -> 69.7 | BK17: 3.4 | BL17: 2.9 | BM17: 5.5 | BN17: 2.3 | BO17: -0.5 | BP17: 7.5 | BQ17: 6.7 | BR17: 7.1 | BS17: 0.6 | BT17: 4.5 | BU17: 5 | BV17: 5.9 | BW17: 3.7 | BX17: 7.8 | BY17: 9.6 | BZ17: 9.5 | CA17: 11.7 | CB17: 10.5 | CC17: 13.4 | CD17: 15.5 | CE17: 15.3 | CF17: 11.7 | CG17: 22.3 | CH17: 19.4 | CI17: 17.8 | CJ17: 14.8 | CK17: 17.7 | CL17: 8.4
A18: Less :Finance Cost | U18: 5.3 | V18: 3.4 | W18: 5 | X18: 6.1 | Y18: 5.3 | Z18: 2.7 | AA18: =SUM(CH18:CK18) -> 3 | BK18: 1 | BL18: 1.2 | BM18: 2.2 | BN18: 0.8 | BO18: 0.9 | BP18: 1 | BQ18: 0.7 | BR18: 0.9 | BS18: 1 | BT18: 1.2 | BU18: 1.9 | BV18: 0.9 | BW18: 1.4 | BX18: 1.3 | BY18: 2.5 | BZ18: 0.8 | CA18: 0.9 | CB18: 2 | CC18: 1.6 | CD18: 0.9 | CE18: 0.8 | CF18: 0.6 | CG18: 0.4 | CH18: 0.8 | CI18: 0.7 | CJ18: 0.7 | CK18: 0.8 | CL18: 0.6
A19: Other Un-Allocable Expenditure Net Off + share of asscicate | U19: -7.6 | V19: -16.6 | W19: -26 | X19: -27.2 | Y19: -25.7 | Z19: -37.3 | AA19: =SUM(CH19:CK19) -> -9.1 | BK19: -15.3 | BL19: -2 | BM19: 11 | BN19: -2.3 | BO19: -2.5 | BP19: -4.7 | BQ19: -7.1 | BR19: -6.4 | BS19: -6.2 | BT19: -7.2 | BU19: -6.2 | BV19: -6.6 | BW19: -7.7 | BX19: -6.1 | BY19: -6.8 | BZ19: -5.2 | CA19: -7.9 | CB19: =-3.6-2.7 -> -6.3 | CC19: -6.3 | CD19: -8.9 | CE19: -9.1 | CF19: =-5.6-3.2 -> -8.8 | CG19: -10.5 | CH19: -8.9 | CI19: -11.1 | CJ19: -6.3 | CK19: 17.2 | CL19: -6.2
A20: Total Profit Before Tax | U20: =SUM(U16:U17)-U18-U19 -> 141 | V20: =SUM(V16:V17)-V18-V19 -> 157 | W20: =SUM(W16:W17)-W18-W19 -> 201 | X20: =SUM(X16:X17)-X18-X19 -> 245.3 | Y20: =SUM(Y16:Y17)-Y18-Y19 -> 280.3 | Z20: =SUM(Z16:Z17)-Z18-Z19 -> 330.7 | AA20: =SUM(AA16:AA17)-AA18-AA19 -> 360.5 | BK20: =SUM(BK16:BK17)-BK18-BK19 -> 39.8 | BL20: =SUM(BL16:BL17)-BL18-BL19 -> 33.7 | BM20: =SUM(BM16:BM17)-BM18-BM19 -> 42.3 | BN20: =SUM(BN16:BN17)-BN18-BN19 -> 20.7 | BO20: =SUM(BO16:BO17)-BO18-BO19 -> 10.4 | BP20: =SUM(BP16:BP17)-BP18-BP19 -> 57.8 | BQ20: =SUM(BQ16:BQ17)-BQ18-BQ19 -> 68.1 | BR20: =SUM(BR16:BR17)-BR18-BR19 -> 59.4 | ... CL20: =SUM(CL16:CL17)-CL18-CL19 -> 53.3
A21: Checksum | U21: =+U20-(U74+U83+U82) -> 0.511 | V21: =+V20-(V74+V83+V82) -> 0.043 | W21: =+W20-(W74+W83+W82) -> -0.007 | X21: =+X20-(X74+X83+X82) -> 0.031 | Y21: =+Y20-(Y74+Y83+Y82) -> -0.049 | Z21: =+Z20-(Z74+Z83+Z82) -> 0.05 | AA21: =+AA20-(AA74+AA83+AA82) -> 0.038 | BK21: =+BK20-(BK74+BK83+BK82) -> 0.1 | BL21: =+BL20-(BL74+BL83+BL82) -> -0.4 | BM21: =+BM20-(BM74+BM83+BM82) -> 0.8 | BN21: =+BN20-(BN74+BN83+BN82) -> 0 | BO21: =+BO20-(BO74+BO83+BO82) -> 0.1 | BP21: =+BP20-(BP74+BP83+BP82) -> -0.1 | BQ21: =+BQ20-(BQ74+BQ83+BQ82) -> 0 | BR21: =+BR20-(BR74+BR83+BR82) -> 0 | ... CL21: =+CL20-(CL74+CL83+CL82) -> 0
A23: PBIT Margins (%)
A24: Pumps | U24: =+U16/U5 -> 0.11454311 | V24: =+V16/V5 -> 0.12678571 | W24: =+W16/W5 -> 0.12900158 | X24: =+X16/X5 -> 0.12957487 | Y24: =+Y16/Y5 -> 0.11324336 | Z24: =+Z16/Z5 -> 0.10971965 | AA24: =+AA16/AA5 -> 0.12853273 | BK24: =+BK16/BK5 -> 0.089256866 | BL24: =+BL16/BL5 -> 0.095087163 | BM24: =+BM16/BM5 -> 0.17761989 | BN24: =+BN16/BN5 -> 0.077988002 | BO24: =+BO16/BO5 -> 0.049154334 | BP24: =+BP16/BP5 -> 0.15450928 | BQ24: =+BQ16/BQ5 -> 0.18302829 | BR24: =+BR16/BR5 -> 0.14730878 | ... CL24: =+CL16/CL5 -> 0.078678679
A25: Valves | U25: =+U17/U6 -> 0.067755887 | V25: =+V17/V6 -> 0.07960199 | W25: =+W17/W6 -> 0.07257384 | X25: =+X17/X6 -> 0.08931525 | Y25: =+Y17/Y6 -> 0.12754525 | Z25: =+Z17/Z6 -> 0.1511194 | AA25: =+AA17/AA6 -> 0.14368172 | BK25: =+BK17/BK6 -> 0.061261261 | BL25: =+BL17/BL6 -> 0.057425743 | BM25: =+BM17/BM6 -> 0.098566308 | BN25: =+BN17/BN6 -> 0.056511057 | BO25: =+BO17/BO6 -> -0.016722408 | BP25: =+BP17/BP6 -> 0.12335526 | BQ25: =+BQ17/BQ6 -> 0.096264368 | BR25: =+BR17/BR6 -> 0.11076443 | ... CL25: =+CL17/CL6 -> 0.08195122
A28: Orderbook
A29: Nuclear | X29: =+BY29 -> 700 | Y29: 968.7 | Z29: 1282.8 | AA29: 1282.8 | BW29: 600 | BX29: 650 | BY29: 700 | BZ29: 750 | CA29: 750 | CB29: 1020 | CC29: 920 | CD29: 915 | CE29: 915 | CF29: 920 | CG29: 920 | CH29: 1310 | CI29: 1313 | CJ29: 1314 | CK29: 1315
A30: Legacy Business | X30: =+BY30 -> 1050 | Y30: 1175.5 | Z30: 967.5 | AA30: 967.5 | BW30: 850 | BX30: 950 | BY30: 1050 | BZ30: 1050 | CA30: 1200 | CB30: 1180 | CC30: 1180 | CD30: 1235 | CE30: 1265 | CF30: 1330 | CG30: 1380 | CH30: 1140 | CI30: 1384 | CJ30: 1325 | CK30: 1385
A31: Total OB | X31: =+BY31 -> 1750 | Y31: =SUM(Y29:Y30) -> 2144.2 | Z31: =SUM(Z29:Z30) -> 2250.3 | AA31: =+CK31 -> 2700 | BW31: =SUM(BW29:BW30) -> 1450 | BX31: =SUM(BX29:BX30) -> 1600 | BY31: =SUM(BY29:BY30) -> 1750 | BZ31: =SUM(BZ29:BZ30) -> 1800 | CA31: =SUM(CA29:CA30) -> 1950 | CB31: =SUM(CB29:CB30) -> 2200 | CC31: =SUM(CC29:CC30) -> 2100 | CD31: =SUM(CD29:CD30) -> 2150 | ... CK31: =SUM(CK29:CK30) -> 2700
A33: Opening | Y33: =+X31 -> 1750 | Z33: =+Y31 -> 2144.2 | AA33: =+Z31 -> 2250.3 | AB33: =+AA36 -> 2700 | AC33: =+AB36 -> 2951.7281 | AD33: =+AC36 -> 3241.8579 | AE33: =+AD36 -> 3564.6517 | BX33: =+BW36 -> 1450 | BY33: =+BX36 -> 1600 | BZ33: =+BY36 -> 1750 | CA33: =+BZ36 -> 1800 | CB33: =+CA36 -> 1950 | CC33: =+CB36 -> 2200 | CD33: =+CC36 -> 2100 | CE33: =+CD36 -> 2150 | ... DA33: =+CZ36 -> 3817.7555
A34: Additions | Y34: =+Y36+Y35-Y33 -> 2641.438 | Z34: =+Z36+Z35-Z33 -> 2639.186 | AA34: =+AA36+AA35-AA33 -> 3145.428 | AB34: =+AB36+AB35-AB33 -> 3307.6222 | AC34: =+AC36+AC35-AC33 -> 3745.797 | AD34: =+AD36+AD35-AD33 -> 4120.3767 | AE34: =+AE36+AE35-AE33 -> 4532.4144 | BX34: =+BX36+BX35-BX33 -> 581.3 | BY34: =+BY36+BY35-BY33 -> 674.6 | BZ34: =+BZ36+BZ35-BZ33 -> 539.6 | CA34: =+CA36+CA35-CA33 -> 741.3 | CB34: =+CB36+CB35-CB33 -> 813.7 | CC34: =+CC36+CC35-CC33 -> 502.6 | CD34: =+CD36+CD35-CD33 -> 594.2 | CE34: =+CE36+CE35-CE33 -> 676 | ... CK34: =+CK36+CK35-CK33 -> 845 | CL34: =+CH34*(1+CL38) -> 819.94 | CM34: =+CI34*(1+CM38) -> 1005.07 | CN34: =+CJ34*(1+CN38) -> 650.76 | CO34: =+CK34*(1+CO38) -> 929.5 | CP34: =+CL34*(1+CP38) -> 901.934 | CQ34: =+CM34*(1+CQ38) -> 1105.577 | CR34: =+CN34*(1+CR38) -> 715.836 | CS34: =+CO34*(1+CS38) -> 1022.45 | ... DA34: =+CW34*(1+DA38) -> 1237.1645
A35: Execution | Y35: =+Y46 -> 2247.238 | Z35: =+Z46 -> 2533.086 | AA35: =+AA46 -> 2695.728 | AB35: =+AB44 -> 3055.894 | AC35: =+AC44 -> 3455.6673 | AD35: =+AD44 -> 3797.5828 | AE35: =+AE44 -> 4176.3334 | BX35: =+BX46 -> 431.3 | BY35: =+BY46 -> 524.6 | BZ35: =+BZ46 -> 489.6 | CA35: =+CA46 -> 591.3 | CB35: =+CB46 -> 563.7 | CC35: =+CC46 -> 602.6 | CD35: =+CD46 -> 544.2 | CE35: =+CE46 -> 646 | ... CK35: =+CK46 -> 784 | CL35: =+CL33*CL39 -> 698.94783 | CM35: =+CM33*CM39 -> 767.6553 | CN35: =+CN33*CN39 -> 832.26117 | CO35: =+CO33*CO39 -> 854.67756 | CP35: =+CP33*CP39 -> 764.11258 | CQ35: =+CQ33*CQ39 -> 840.73579 | CR35: =+CR33*CR39 -> 912.80503 | CS35: =+CS33*CS39 -> 938.01389 | ... DA35: =+DA33*DA39 -> 1134.1873
A36: Closing | X36: =+X31 -> 1750 | Y36: =+Y31 -> 2144.2 | Z36: =+Z31 -> 2250.3 | AA36: =+AA31 -> 2700 | AB36: =+CO36 -> 2951.7281 | AC36: =+CS36 -> 3241.8579 | AD36: =+CW36 -> 3564.6517 | AE36: =+DA36 -> 3920.7327 | BW36: =+BW31 -> 1450 | BX36: =+BX31 -> 1600 | BY36: =+BY31 -> 1750 | BZ36: =+BZ31 -> 1800 | CA36: =+CA31 -> 1950 | CB36: =+CB31 -> 2200 | CC36: =+CC31 -> 2100 | CD36: =+CD31 -> 2150 | ... CK36: =+CK31 -> 2700 | CL36: =+CL33+CL34-CL35 -> 2820.9922 | CM36: =+CM33+CM34-CM35 -> 3058.4069 | CN36: =+CN33+CN34-CN35 -> 2876.9057 | CO36: =+CO33+CO34-CO35 -> 2951.7281 | CP36: =+CP33+CP34-CP35 -> 3089.5496 | CQ36: =+CQ33+CQ34-CQ35 -> 3354.3908 | CR36: =+CR33+CR34-CR35 -> 3157.4217 | CS36: =+CS33+CS34-CS35 -> 3241.8579 | ... DA36: =+DA33+DA34-DA35 -> 3920.7327
A37: OB Growth | Y37: =+Y36/X36-1 -> 0.22525714 | Z37: =+Z36/Y36-1 -> 0.049482324 | AA37: =+AA36/Z36-1 -> 0.19984002 | AB37: =+AB36/AA36-1 -> 0.093232648 | AC37: =+AC36/AB36-1 -> 0.098291472 | AD37: =+AD36/AC36-1 -> 0.099570641 | AE37: =+AE36/AD36-1 -> 0.099892226 | CA37: =+CA36/BW36-1 -> 0.34482759 | CB37: =+CB36/BX36-1 -> 0.375 | CC37: =+CC36/BY36-1 -> 0.2 | CD37: =+CD36/BZ36-1 -> 0.19444444 | CE37: =+CE36/CA36-1 -> 0.11794872 | CF37: =+CF36/CB36-1 -> 0.022727273 | CG37: =+CG36/CC36-1 -> 0.095238095 | CH37: =+CH36/CD36-1 -> 0.13953488 | ... DA37: =+DA36/CW36-1 -> 0.099892226
A38: Additions Growth | Z38: =+Z34/Y34-1 -> -0.00085256591 | AA38: =+AA34/Z34-1 -> 0.19181748 | AB38: =+AB34/AA34-1 -> 0.051565057 | AC38: =+AC34/AB34-1 -> 0.13247427 | AD38: =+AD34/AC34-1 -> 0.1 | AE38: =+AE34/AD34-1 -> 0.1 | CB38: =+CB34/BX34-1 -> 0.39979357 | CC38: =+CC34/BY34-1 -> -0.25496591 | CD38: =+CD34/BZ34-1 -> 0.10118606 | CE38: =+CE34/CA34-1 -> -0.088088493 | CF38: =+CF34/CB34-1 -> -0.15632297 | CG38: =+CG34/CC34-1 -> 0.54476721 | CH38: =+CH34/CD34-1 -> 0.25445978 | CI38: =+CI34/CE34-1 -> 0.35162722 | ... CK38: =+CK34/CG34-1 -> 0.088356517 | CL38: 0.1 | CM38: 0.1 | CN38: 0.1 | CO38: 0.1 | CP38: 0.1 | CQ38: 0.1 | CR38: 0.1 | CS38: 0.1 | CT38: 0.1 | CU38: 0.1 | CV38: 0.1 | CW38: 0.1 | CX38: 0.1 | CY38: 0.1 | CZ38: 0.1 | DA38: 0.1
A39: Execution % | Y39: =+Y35/Y33 -> 1.284136 | Z39: =+Z35/Z33 -> 1.1813665 | AA39: =+AA35/AA33 -> 1.1979416 | AB39: =+AB35/AB33 -> 1.1318126 | AC39: =+AC35/AC33 -> 1.1707268 | AD39: =+AD35/AD33 -> 1.1714218 | AE39: =+AE35/AE33 -> 1.1715965 | BX39: =+BX35/BX33 -> 0.29744828 | BY39: =+BY35/BY33 -> 0.327875 | BZ39: =+BZ35/BZ33 -> 0.27977143 | CA39: =+CA35/CA33 -> 0.3285 | CB39: =+CB35/CB33 -> 0.28907692 | CC39: =+CC35/CC33 -> 0.27390909 | CD39: =+CD35/CD33 -> 0.25914286 | CE39: =+CE35/CE33 -> 0.30046512 | ... CK39: =+CK35/CK33 -> 0.29708223 | CL39: =+CH39 -> 0.25886957 | CM39: =+CI39 -> 0.27212245 | CN39: =+CM39 -> 0.27212245 | CO39: =+CK39 -> 0.29708223 | CP39: =+CL39 -> 0.25886957 | CQ39: =+CM39 -> 0.27212245 | CR39: =+CN39 -> 0.27212245 | CS39: =+CO39 -> 0.29708223 | CT39: =+CP39 -> 0.25886957 | CU39: =+CQ39 -> 0.27212245 | CV39: =+CR39 -> 0.27212245 | ... DA39: =+CW39 -> 0.29708223
A42: Presentation Data (End)
A43: Profit & Loss- Annual (Start)
A44: Gross Revenue | B44: ='Annual Raw'!C6 -> 183.5706 | C44: ='Annual Raw'!D6 -> 208.06 | D44: ='Annual Raw'!E6 -> 246.6743 | E44: ='Annual Raw'!F6 -> 262.837 | F44: ='Annual Raw'!G6 -> 332.4444 | G44: ='Annual Raw'!H6 -> 397.7657 | H44: ='Annual Raw'!I6 -> 453.1451 | I44: ='Annual Raw'!J6 -> 513.1169 | ... AA44: ='Annual Raw'!AB6 -> 2753.025 | AB44: =+SUM(CL44:CO44) -> 3055.894 | AC44: =+SUM(CP44:CS44) -> 3455.6673 | AD44: =+SUM(CT44:CW44) -> 3797.5828 | AE44: =+SUM(CX44:DA44) -> 4176.3334 | AI44: ='QTR Raw'!C6+'QTR Raw'!C8 -> 187.38 | AJ44: ='QTR Raw'!D6+'QTR Raw'!D8 -> 169.74 | AK44: ='QTR Raw'!E6+'QTR Raw'!E8 -> 194.58 | AL44: ='QTR Raw'!F6+'QTR Raw'!F8 -> 163.79 | AM44: ='QTR Raw'!G6+'QTR Raw'!G8 -> 195.22 | AN44: ='QTR Raw'!H6+'QTR Raw'!H8 -> 190.24 | AO44: ='QTR Raw'!I6+'QTR Raw'!I8 -> 182.09 | AP44: ='QTR Raw'!J6+'QTR Raw'!J8 -> 173.37 | ... CL44: ='QTR Raw'!BF6+'QTR Raw'!BF8 -> 601.3 | CM44: =+CM35 -> 767.6553 | CN44: =+CN35 -> 832.26117 | CO44: =+CO35 -> 854.67756 | CP44: =+CP35 -> 764.11258 | CQ44: =+CQ35 -> 840.73579 | CR44: =+CR35 -> 912.80503 | CS44: =+CS35 -> 938.01389 | CT44: =+CT35 -> 839.21833 | ... DA44: =+DA35 -> 1134.1873 | DE44: 2695.7
A45: Less: Exise Duty | B45: ='Annual Raw'!C7+'Annual Raw'!C8+'Annual Raw'!C9 -> 0 | C45: ='Annual Raw'!D7+'Annual Raw'!D8+'Annual Raw'!D9 -> 0 | D45: ='Annual Raw'!E7+'Annual Raw'!E8+'Annual Raw'!E9 -> 16.1455 | E45: ='Annual Raw'!F7+'Annual Raw'!F8+'Annual Raw'!F9 -> 19.9915 | F45: ='Annual Raw'!G7+'Annual Raw'!G8+'Annual Raw'!G9 -> 27.8799 | G45: ='Annual Raw'!H7+'Annual Raw'!H8+'Annual Raw'!H9 -> 37.8643 | H45: ='Annual Raw'!I7+'Annual Raw'!I8+'Annual Raw'!I9 -> 45.6415 | I45: ='Annual Raw'!J7+'Annual Raw'!J8+'Annual Raw'!J9 -> 46.6397 | ... AA45: ='Annual Raw'!AB7+'Annual Raw'!AB8+'Annual Raw'!AB9 -> 57.297 | AB45: =+SUM(CL45:CO45) -> 0 | AC45: =+SUM(CP45:CS45) -> 0 | AD45: =+SUM(CT45:CW45) -> 0 | AE45: =+SUM(CX45:DA45) -> 0 | AI45: ='QTR Raw'!C21+'QTR Raw'!C20+'QTR Raw'!C19+'QTR Raw'!C13+'QTR Raw'!C7 -> 0 | AJ45: ='QTR Raw'!D21+'QTR Raw'!D20+'QTR Raw'!D19+'QTR Raw'!D13+'QTR Raw'!D7 -> 0 | AK45: ='QTR Raw'!E21+'QTR Raw'!E20+'QTR Raw'!E19+'QTR Raw'!E13+'QTR Raw'!E7 -> 0 | AL45: ='QTR Raw'!F21+'QTR Raw'!F20+'QTR Raw'!F19+'QTR Raw'!F13+'QTR Raw'!F7 -> 0 | AM45: ='QTR Raw'!G21+'QTR Raw'!G20+'QTR Raw'!G19+'QTR Raw'!G13+'QTR Raw'!G7 -> 0 | AN45: ='QTR Raw'!H21+'QTR Raw'!H20+'QTR Raw'!H19+'QTR Raw'!H13+'QTR Raw'!H7 -> 0 | AO45: ='QTR Raw'!I21+'QTR Raw'!I20+'QTR Raw'!I19+'QTR Raw'!I13+'QTR Raw'!I7 -> 0 | AP45: ='QTR Raw'!J21+'QTR Raw'!J20+'QTR Raw'!J19+'QTR Raw'!J13+'QTR Raw'!J7 -> 0 | ... CL45: ='QTR Raw'!BF21+'QTR Raw'!BF20+'QTR Raw'!BF19+'QTR Raw'!BF13+'QTR Raw'!BF7 -> 0 | DE45: 0
A46: Net Revenue | B46: =+B44-B45 -> 183.5706 | C46: =+C44-C45 -> 208.06 | D46: =+D44-D45 -> 230.5288 | E46: =+E44-E45 -> 242.8455 | F46: =+F44-F45 -> 304.5645 | G46: =+G44-G45 -> 359.9014 | H46: =+H44-H45 -> 407.5036 | I46: =+I44-I45 -> 466.4772 | ... AE46: =+AE44-AE45 -> 4176.3334 | AI46: =+AI44-AI45 -> 187.38 | AJ46: =+AJ44-AJ45 -> 169.74 | AK46: =+AK44-AK45 -> 194.58 | AL46: =+AL44-AL45 -> 163.79 | AM46: =+AM44-AM45 -> 195.22 | AN46: =+AN44-AN45 -> 190.24 | AO46: =+AO44-AO45 -> 182.09 | AP46: =+AP44-AP45 -> 173.37 | ... DA46: =+DA44-DA45 -> 1134.1873 | DE46: 2695.7
A47: Net Revenue YOY% | C47: =C46/B46-1 -> 0.13340589 | D47: =D46/C46-1 -> 0.10799193 | E47: =E46/D46-1 -> 0.053428032 | F47: =F46/E46-1 -> 0.25414924 | G47: =G46/F46-1 -> 0.18169189 | H47: =H46/G46-1 -> 0.13226456 | I47: =I46/H46-1 -> 0.14471921 | J47: =J46/I46-1 -> 0.28216213 | ... AE47: =AE46/AD46-1 -> 0.099734635 | AM47: =+IF(AI46<0,1-AM46/AI46,AM46/AI46-1) -> 0.041840111 | AN47: =+IF(AJ46<0,1-AN46/AJ46,AN46/AJ46-1) -> 0.12077295 | AO47: =+IF(AK46<0,1-AO46/AK46,AO46/AK46-1) -> -0.064189536 | AP47: =+IF(AL46<0,1-AP46/AL46,AP46/AL46-1) -> 0.058489529 | AQ47: =+IF(AM46<0,1-AQ46/AM46,AQ46/AM46-1) -> 0.021155619 | AR47: =+IF(AN46<0,1-AR46/AN46,AR46/AN46-1) -> 0.045468881 | AS47: =+IF(AO46<0,1-AS46/AO46,AS46/AO46-1) -> 0.26360591 | AT47: =+IF(AP46<0,1-AT46/AP46,AT46/AP46-1) -> 0.091711369 | ... DA47: =+IF(CW46<0,1-DA46/CW46,DA46/CW46-1) -> 0.099842548 | DE47: 0.064196004
A48: Net Revenue QOQ% | AJ48: =+IF(AI46<0,1-AJ46/AI46,AJ46/AI46-1) -> -0.09414025 | AK48: =+IF(AJ46<0,1-AK46/AJ46,AK46/AJ46-1) -> 0.14634146 | AL48: =+IF(AK46<0,1-AL46/AK46,AL46/AK46-1) -> -0.15823826 | AM48: =+IF(AL46<0,1-AM46/AL46,AM46/AL46-1) -> 0.19189206 | AN48: =+IF(AM46<0,1-AN46/AM46,AN46/AM46-1) -> -0.025509681 | AO48: =+IF(AN46<0,1-AO46/AN46,AO46/AN46-1) -> -0.042840622 | AP48: =+IF(AO46<0,1-AP46/AO46,AP46/AO46-1) -> -0.047888407 | AQ48: =+IF(AP46<0,1-AQ46/AP46,AQ46/AP46-1) -> 0.14985292 | ... CL48: =+IF(CK46<0,1-CL46/CK46,CL46/CK46-1) -> -0.23303571 | CM48: =+CM46/CL46-1 -> 0.2766594 | CN48: =+CN46/CM46-1 -> 0.08416 | CO48: =+CO46/CN46-1 -> 0.02693432 | CP48: =+CP46/CO46-1 -> -0.10596391 | CQ48: =+CQ46/CP46-1 -> 0.10027739 | CR48: =+CR46/CQ46-1 -> 0.085721624 | CS48: =+CS46/CR46-1 -> 0.02761691 | CT48: =+CT46/CS46-1 -> -0.10532419 | ... DA48: =+DA46/CZ46-1 -> 0.027831982
A49: Increase/Decrease in Stock | B49: ='Annual Raw'!C11 -> -4.9865 | C49: ='Annual Raw'!D11 -> -2.3004 | D49: ='Annual Raw'!E11 -> -0.2105 | E49: ='Annual Raw'!F11 -> -5.7236 | F49: ='Annual Raw'!G11 -> -2.9785 | G49: ='Annual Raw'!H11 -> -5.5271 | H49: ='Annual Raw'!I11 -> -1.3516 | I49: ='Annual Raw'!J11 -> -24.511 | ... AA49: ='Annual Raw'!AB11 -> -93.224 | AB49: =+SUM(CL49:CO49) -> -100.1 | AC49: =+SUM(CP49:CS49) -> 0 | AD49: =+SUM(CT49:CW49) -> 0 | AE49: =+SUM(CX49:DA49) -> 0 | AI49: ='QTR Raw'!C10 -> 8.28 | AJ49: ='QTR Raw'!D10 -> -7.8 | AK49: ='QTR Raw'!E10 -> 8.8 | AL49: ='QTR Raw'!F10 -> -21.35 | AM49: ='QTR Raw'!G10 -> 11.93 | AN49: ='QTR Raw'!H10 -> 6 | AO49: ='QTR Raw'!I10 -> 7.68 | AP49: ='QTR Raw'!J10 -> -17.34 | ... CL49: ='QTR Raw'!BF10 -> -100.1 | DE49: -93.2
A50: Purchase of Finished Goods | B50: 0 | C50: 0 | D50: 0 | E50: 0 | F50: 0 | G50: 0 | H50: 0 | I50: 0 | J50: 0 | K50: 0 | L50: 0 | M50: 0 | N50: 0 | O50: 0 | P50: 0 | Q50: 0 | R50: 0 | S50: 0 | T50: 0 | U50: 0 | V50: 0 | W50: 0 | X50: 0 | Y50: 0 | Z50: 0 | AA50: 0 | AB50: =+SUM(CL50:CO50) -> 68.7 | AC50: =+SUM(CP50:CS50) -> 0 | AD50: =+SUM(CT50:CW50) -> 0 | AE50: =+SUM(CX50:DA50) -> 0 | AI50: ='QTR Raw'!C12 -> 1.88 | AJ50: ='QTR Raw'!D12 -> 2.26 | AK50: ='QTR Raw'!E12 -> 4.23 | AL50: ='QTR Raw'!F12 -> 1.71 | AM50: ='QTR Raw'!G12 -> 0.31 | AN50: ='QTR Raw'!H12 -> 2.52 | AO50: ='QTR Raw'!I12 -> 7.51 | AP50: ='QTR Raw'!J12 -> 8.42 | ... CL50: ='QTR Raw'!BF12 -> 68.7 | DE50: 274.9
A51: Raw Material Consumed | B51: ='Annual Raw'!C12 -> 89.8881 | C51: ='Annual Raw'!D12 -> 99.2511 | D51: ='Annual Raw'!E12 -> 101.805 | E51: ='Annual Raw'!F12 -> 106.0585 | F51: ='Annual Raw'!G12 -> 137.6404 | G51: ='Annual Raw'!H12 -> 165.4362 | H51: ='Annual Raw'!I12 -> 175.7443 | I51: ='Annual Raw'!J12 -> 250.9755 | ... AA51: ='Annual Raw'!AB12 -> 1549.488 | AB51: =+SUM(CL51:CO51) -> 1681.7451 | AC51: =+SUM(CP51:CS51) -> 1865.1445 | AD51: =+SUM(CT51:CW51) -> 2049.4907 | AE51: =+SUM(CX51:DA51) -> 2253.8828 | AI51: ='QTR Raw'!C11 -> 91.95 | AJ51: ='QTR Raw'!D11 -> 87.13 | AK51: ='QTR Raw'!E11 -> 82.97 | AL51: ='QTR Raw'!F11 -> 91.88 | AM51: ='QTR Raw'!G11 -> 85.09 | AN51: ='QTR Raw'!H11 -> 77.48 | AO51: ='QTR Raw'!I11 -> 73.57 | AP51: ='QTR Raw'!J11 -> 86.74 | ... CL51: ='QTR Raw'!BF11 -> 358.1 | CM51: =+CM46-CM52 -> 414.74246 | CN51: =+CN46-CN52 -> 447.08785 | CO51: =+CO46-CO52 -> 461.81483 | CP51: =+CP46-CP52 -> 412.8365 | CQ51: =+CQ46-CQ52 -> 453.5956 | CR51: =+CR46-CR52 -> 492.3075 | CS51: =+CS46-CS52 -> 506.40493 | CT51: =+CT46-CT52 -> 452.9699 | ... DA51: =+DA46-DA52 -> 612.10728 | DE51: 1274.6
A52: Gross Profit | B52: =B46-B49-B51-B50 -> 98.669 | C52: =C46-C49-C51-C50 -> 111.1093 | D52: =D46-D49-D51-D50 -> 128.9343 | E52: =E46-E49-E51-E50 -> 142.5106 | F52: =F46-F49-F51-F50 -> 169.9026 | G52: =G46-G49-G51-G50 -> 199.9923 | H52: =H46-H49-H51-H50 -> 233.1109 | I52: =I46-I49-I51-I50 -> 240.0127 | ... AE52: =AE46-AE49-AE51-AE50 -> 1922.4506 | AI52: =AI46-AI49-AI51-AI50 -> 85.27 | AJ52: =AJ46-AJ49-AJ51-AJ50 -> 88.15 | AK52: =AK46-AK49-AK51-AK50 -> 98.58 | AL52: =AL46-AL49-AL51-AL50 -> 91.55 | AM52: =AM46-AM49-AM51-AM50 -> 97.89 | AN52: =AN46-AN49-AN51-AN50 -> 104.24 | AO52: =AO46-AO49-AO51-AO50 -> 93.33 | AP52: =AP46-AP49-AP51-AP50 -> 95.55 | ... CL52: =CL46-CL49-CL51-CL50 -> 274.6 | CM52: =+CM53*CM46 -> 352.91284 | CN52: =+CN53*CN46 -> 385.17332 | CO52: =+CO53*CO46 -> 392.86272 | CP52: =+CP53*CP46 -> 351.27608 | CQ52: =+CQ53*CQ46 -> 387.14019 | CR52: =+CR53*CR46 -> 420.49753 | CS52: =+CS53*CS46 -> 431.60895 | CT52: =+CT53*CT46 -> 386.24844 | ... DA52: =+DA53*DA46 -> 522.08004 | DE52: 1239.4
A53: GP% | B53: =B52/B46 -> 0.53749892 | C53: =C52/C46 -> 0.53402528 | D53: =D52/D46 -> 0.55929801 | E53: =E52/E46 -> 0.58683649 | F53: =F52/F46 -> 0.55785425 | G53: =G52/G46 -> 0.55568636 | H53: =H52/H46 -> 0.57204623 | I53: =I52/I46 -> 0.51452182 | ... AE53: =AE52/AE46 -> 0.4603202 | AI53: =AI52/AI46 -> 0.45506457 | AJ53: =AJ52/AJ46 -> 0.51932367 | AK53: =AK52/AK46 -> 0.50662966 | AL53: =AL52/AL46 -> 0.55894743 | AM53: =AM52/AM46 -> 0.50143428 | AN53: =AN52/AN46 -> 0.54793944 | AO53: =AO52/AO46 -> 0.51254874 | AP53: =AP52/AP46 -> 0.55113341 | ... CL53: =CL52/CL46 -> 0.4566772 | CM53: =AVERAGE(CI53:CL53) -> 0.45972827 | CN53: =AVERAGE(CJ53:CM53) -> 0.46280342 | CO53: =AVERAGE(CK53:CN53) -> 0.45966192 | CP53: =AVERAGE(CL53:CO53) -> 0.4597177 | CQ53: =AVERAGE(CM53:CP53) -> 0.46047783 | CR53: =AVERAGE(CN53:CQ53) -> 0.46066522 | CS53: =AVERAGE(CO53:CR53) -> 0.46013067 | CT53: =AVERAGE(CP53:CS53) -> 0.46024785 | ... DA53: =AVERAGE(CW53:CZ53) -> 0.46031201 | DE53: 0.45976926
A54: GP YOY% | C54: =+IF(B52<0,1-C52/B52,C52/B52-1) -> 0.12608114 | D54: =+IF(C52<0,1-D52/C52,D52/C52-1) -> 0.16042761 | E54: =+IF(D52<0,1-E52/D52,E52/D52-1) -> 0.10529626 | F54: =+IF(E52<0,1-F52/E52,F52/E52-1) -> 0.19221026 | G54: =+IF(F52<0,1-G52/F52,G52/F52-1) -> 0.1770997 | H54: =+IF(G52<0,1-H52/G52,H52/G52-1) -> 0.16559938 | I54: =+IF(H52<0,1-I52/H52,I52/H52-1) -> 0.029607367 | J54: =+IF(I52<0,1-J52/I52,J52/I52-1) -> 0.29682513 | ... AE54: =+IF(AD52<0,1-AE52/AD52,AE52/AD52-1) -> 0.099742137 | AM54: =+IF(AI52<0,1-AM52/AI52,AM52/AI52-1) -> 0.14800047 | AN54: =+IF(AJ52<0,1-AN52/AJ52,AN52/AJ52-1) -> 0.18252978 | AO54: =+IF(AK52<0,1-AO52/AK52,AO52/AK52-1) -> -0.053256239 | AP54: =+IF(AL52<0,1-AP52/AL52,AP52/AL52-1) -> 0.043691972 | AQ54: =+IF(AM52<0,1-AQ52/AM52,AQ52/AM52-1) -> 0.11768311 | AR54: =+IF(AN52<0,1-AR52/AN52,AR52/AN52-1) -> 0.048733691 | AS54: =+IF(AO52<0,1-AS52/AO52,AS52/AO52-1) -> 0.16243437 | AT54: =+IF(AP52<0,1-AT52/AP52,AT52/AP52-1) -> -0.0047095761 | ... CL54: =+IF(CH52<0,1-CL52/CH52,CL52/CH52-1) -> 0.0091877986 | CM54: =+CM52/CI52-1 -> 0.18308025 | CN54: =+CN52/CJ52-1 -> 0.24732292 | CO54: =+CO52/CK52-1 -> 0.090679411 | CP54: =+CP52/CL52-1 -> 0.27922826 | CQ54: =+CQ52/CM52-1 -> 0.096985286 | CR54: =+CR52/CN52-1 -> 0.091709907 | CS54: =+CS52/CO52-1 -> 0.098625365 | CT54: =+CT52/CP52-1 -> 0.099558034 | ... DA54: =+DA52/CW52-1 -> 0.099922051 | DE54: 0.1156298
A55: GP QOQ% | AJ55: =+IF(AI52<0,1-AJ52/AI52,AJ52/AI52-1) -> 0.033775067 | AK55: =+IF(AJ52<0,1-AK52/AJ52,AK52/AJ52-1) -> 0.11832104 | AL55: =+IF(AK52<0,1-AL52/AK52,AL52/AK52-1) -> -0.071312639 | AM55: =+IF(AL52<0,1-AM52/AL52,AM52/AL52-1) -> 0.069251775 | AN55: =+IF(AM52<0,1-AN52/AM52,AN52/AM52-1) -> 0.06486873 | AO55: =+IF(AN52<0,1-AO52/AN52,AO52/AN52-1) -> -0.10466232 | AP55: =+IF(AO52<0,1-AP52/AO52,AP52/AO52-1) -> 0.023786564 | AQ55: =+IF(AP52<0,1-AQ52/AP52,AQ52/AP52-1) -> 0.14505495 | ... CL55: =+IF(CK52<0,1-CL52/CK52,CL52/CK52-1) -> -0.23764575 | CM55: =+CM52/CL52-1 -> 0.28518878 | CN55: =+CN52/CM52-1 -> 0.091412033 | CO55: =+CO52/CN52-1 -> 0.019963492 | CP55: =+CP52/CO52-1 -> -0.10585541 | CQ55: =+CQ52/CP52-1 -> 0.10209665 | CR55: =+CR52/CQ52-1 -> 0.086163456 | CS55: =+CS52/CR52-1 -> 0.026424472 | CT55: =+CT52/CS52-1 -> -0.10509633 | ... DA55: =+DA52/CZ52-1 -> 0.027812322
A56: Power & Fuel Cost | B56: ='Annual Raw'!C13 -> 4.914 | C56: ='Annual Raw'!D13 -> 5.2112 | D56: ='Annual Raw'!E13 -> 7.6916 | E56: ='Annual Raw'!F13 -> 7.4721 | F56: ='Annual Raw'!G13 -> 8.3325 | G56: ='Annual Raw'!H13 -> 8.5092 | H56: ='Annual Raw'!I13 -> 8.9057 | I56: ='Annual Raw'!J13 -> 9.8512 | ... AA56: ='Annual Raw'!AB13 -> 22.019 | AB56: =+SUM(CL56:CO56) -> 0 | AC56: =+SUM(CP56:CS56) -> 0 | AD56: =+SUM(CT56:CW56) -> 0 | AE56: =+SUM(CX56:DA56) -> 0 | AI56: ='QTR Raw'!C15 -> 0 | AJ56: ='QTR Raw'!D15 -> 0 | AK56: ='QTR Raw'!E15 -> 0 | AL56: ='QTR Raw'!F15 -> 0 | AM56: ='QTR Raw'!G15 -> 0 | AN56: ='QTR Raw'!H15 -> 0 | AO56: ='QTR Raw'!I15 -> 0 | AP56: ='QTR Raw'!J15 -> 0 | ... CL56: ='QTR Raw'!BF15 -> 0 | DE56: 0
A57: Selling and Distribution Expenses | B57: =('Annual Raw'!C18) -> 8.4801 | C57: =('Annual Raw'!D18) -> 9.1987 | D57: =('Annual Raw'!E18) -> 10.3013 | E57: =('Annual Raw'!F18) -> 10.9365 | F57: =('Annual Raw'!G18) -> 12.7087 | G57: =('Annual Raw'!H18) -> 13.8252 | H57: =('Annual Raw'!I18) -> 11.4522 | I57: =('Annual Raw'!J18) -> 13.272 | ... AA57: =('Annual Raw'!AB18) -> 72.796 | AB57: =+SUM(CL57:CO57) -> 0 | AC57: =+SUM(CP57:CS57) -> 0 | AD57: =+SUM(CT57:CW57) -> 0 | AE57: =+SUM(CX57:DA57) -> 0 | AI57: ='QTR Raw'!C18 -> 0 | AJ57: ='QTR Raw'!D18 -> 0 | AK57: ='QTR Raw'!E18 -> 0 | AL57: ='QTR Raw'!F18 -> 0 | AM57: ='QTR Raw'!G18 -> 0 | AN57: ='QTR Raw'!H18 -> 0 | AO57: ='QTR Raw'!I18 -> 0 | AP57: ='QTR Raw'!J18 -> 0 | ... CL57: ='QTR Raw'!BF18 -> 0 | DE57: 0
A58: Other Manufacturing Expenses | B58: ='Annual Raw'!C15+'Annual Raw'!C16 -> 14.9782 | C58: ='Annual Raw'!D15+'Annual Raw'!D16 -> 15.8263 | D58: ='Annual Raw'!E15+'Annual Raw'!E16 -> 19.4585 | E58: ='Annual Raw'!F15+'Annual Raw'!F16 -> 20.8578 | F58: ='Annual Raw'!G15+'Annual Raw'!G16 -> 26.2982 | G58: ='Annual Raw'!H15+'Annual Raw'!H16 -> 31.3784 | H58: ='Annual Raw'!I15+'Annual Raw'!I16 -> 36.23 | I58: ='Annual Raw'!J15+'Annual Raw'!J16 -> 40.3246 | ... AA58: ='Annual Raw'!AB15+'Annual Raw'!AB16 -> 250.946 | AB58: =+SUM(CL58:CO58) -> 613.9001 | AC58: =+SUM(CP58:CS58) -> 722.40762 | AD58: =+SUM(CT58:CW58) -> 805.82535 | AE58: =+SUM(CX58:DA58) -> 899.34372 | AI58: ='QTR Raw'!C14 -> 34.83 | AJ58: ='QTR Raw'!D14 -> 40.74 | AK58: ='QTR Raw'!E14 -> 44.25 | AL58: ='QTR Raw'!F14 -> 41.57 | AM58: ='QTR Raw'!G14 -> 42.57 | AN58: ='QTR Raw'!H14 -> 46.26 | AO58: ='QTR Raw'!I14 -> 45.98 | AP58: ='QTR Raw'!J14 -> 39.34 | ... CL58: ='QTR Raw'!BF14 -> 127.8 | CM58: =CM62-CM59 -> 145.78191 | CN58: =CN62-CN59 -> 186.29961 | CO58: =CO62-CO59 -> 154.01858 | CP58: =CP62-CP59 -> 181.6778 | CQ58: =CQ62-CQ59 -> 161.98995 | CR58: =CR62-CR59 -> 207.02527 | CS58: =CS62-CS59 -> 171.71461 | CT58: =CT62-CT59 -> 202.44128 | ... DA58: =DA62-DA59 -> 214.31909 | DE58: 501.6
A59: Employee Cost | B59: ='Annual Raw'!C14 -> 37.5406 | C59: ='Annual Raw'!D14 -> 31.7845 | D59: ='Annual Raw'!E14 -> 38.63 | E59: ='Annual Raw'!F14 -> 45.9854 | F59: ='Annual Raw'!G14 -> 45.3776 | G59: ='Annual Raw'!H14 -> 48.9709 | H59: ='Annual Raw'!I14 -> 53.2348 | I59: ='Annual Raw'!J14 -> 62.1157 | ... AA59: ='Annual Raw'!AB14 -> 364.228 | AB59: =+SUM(CL59:CO59) -> 386.505 | AC59: =+SUM(CP59:CS59) -> 413.56035 | AD59: =+SUM(CT59:CW59) -> 442.50957 | AE59: =+SUM(CX59:DA59) -> 473.48524 | AI59: ='QTR Raw'!C16 -> 25.72 | AJ59: ='QTR Raw'!D16 -> 24.68 | AK59: ='QTR Raw'!E16 -> 24.42 | AL59: ='QTR Raw'!F16 -> 28.26 | AM59: ='QTR Raw'!G16 -> 28.39 | AN59: ='QTR Raw'!H16 -> 27.78 | AO59: ='QTR Raw'!I16 -> 25.63 | AP59: ='QTR Raw'!J16 -> 31.08 | ... CL59: ='QTR Raw'!BF16 -> 96 | CM59: =CI59*107% -> 92.448 | CN59: =CJ59*107% -> 100.687 | CO59: =CK59*107% -> 97.37 | CP59: =CL59*107% -> 102.72 | CQ59: =CM59*107% -> 98.91936 | CR59: =CN59*107% -> 107.73509 | CS59: =CO59*107% -> 104.1859 | CT59: =CP59*107% -> 109.9104 | ... DA59: =CW59*107% -> 119.28244 | DE59: 364.3
A60: General and Administration Expenses | B60: ='Annual Raw'!C17 -> 27.7506 | C60: ='Annual Raw'!D17 -> 27.9812 | D60: ='Annual Raw'!E17 -> 25.7383 | E60: ='Annual Raw'!F17 -> 27.4429 | F60: ='Annual Raw'!G17 -> 28.3811 | G60: ='Annual Raw'!H17 -> 32.8914 | H60: ='Annual Raw'!I17 -> 40.0555 | I60: ='Annual Raw'!J17 -> 47.5918 | ... AA60: ='Annual Raw'!AB17 -> 67.275 | AB60: =+SUM(CL60:CO60) -> 0 | AC60: =+SUM(CP60:CS60) -> 0 | AD60: =+SUM(CT60:CW60) -> 0 | AE60: =+SUM(CX60:DA60) -> 0 | AI60: ='QTR Raw'!C17 -> 0 | AJ60: ='QTR Raw'!D17 -> 0 | AK60: ='QTR Raw'!E17 -> 0 | AL60: ='QTR Raw'!F17 -> 0 | AM60: ='QTR Raw'!G17 -> 0 | AN60: ='QTR Raw'!H17 -> 0 | AO60: ='QTR Raw'!I17 -> 0 | AP60: ='QTR Raw'!J17 -> 0 | ... CL60: ='QTR Raw'!BF17 -> 0 | DE60: 0
A61: Miscellaneous Expenses | B61: ='Annual Raw'!C19-'Annual Raw'!C20 -> -0.671 | C61: ='Annual Raw'!D19-'Annual Raw'!D20 -> -0.5747 | D61: ='Annual Raw'!E19-'Annual Raw'!E20 -> 0.1213 | E61: ='Annual Raw'!F19-'Annual Raw'!F20 -> -0.0864 | F61: ='Annual Raw'!G19-'Annual Raw'!G20 -> -0.7596 | G61: ='Annual Raw'!H19-'Annual Raw'!H20 -> -0.6543 | H61: ='Annual Raw'!I19-'Annual Raw'!I20 -> -0.2453 | I61: ='Annual Raw'!J19-'Annual Raw'!J20 -> -1.3273 | ... AA61: ='Annual Raw'!AB19-'Annual Raw'!AB20 -> 88.605 | AB61: =+SUM(CL61:CO61) -> 0 | AC61: =+SUM(CP61:CS61) -> 0 | AD61: =+SUM(CT61:CW61) -> 0 | AE61: =+SUM(CX61:DA61) -> 0 | DE61: 0
A62: Total Cost | B62: =+SUM(B56:B61) -> 92.9925 | C62: =+SUM(C56:C61) -> 89.4272 | D62: =+SUM(D56:D61) -> 101.941 | E62: =+SUM(E56:E61) -> 112.6083 | F62: =+SUM(F56:F61) -> 120.3385 | G62: =+SUM(G56:G61) -> 134.9208 | H62: =+SUM(H56:H61) -> 149.6329 | I62: =+SUM(I56:I61) -> 171.828 | ... AE62: =+SUM(AE56:AE61) -> 1372.829 | AI62: =+SUM(AI56:AI61) -> 60.55 | AJ62: =+SUM(AJ56:AJ61) -> 65.42 | AK62: =+SUM(AK56:AK61) -> 68.67 | AL62: =+SUM(AL56:AL61) -> 69.83 | AM62: =+SUM(AM56:AM61) -> 70.96 | AN62: =+SUM(AN56:AN61) -> 74.04 | AO62: =+SUM(AO56:AO61) -> 71.61 | AP62: =+SUM(AP56:AP61) -> 70.42 | ... CL62: =+SUM(CL56:CL61) -> 223.8 | CM62: =CM63*CM46 -> 238.22991 | CN62: =CN63*CN46 -> 286.98661 | CO62: =CO63*CO46 -> 251.38858 | CP62: =CP63*CP46 -> 284.3978 | CQ62: =CQ63*CQ46 -> 260.90931 | CR62: =CR63*CR46 -> 314.76036 | CS62: =CS63*CS46 -> 275.90051 | CT62: =CT63*CT46 -> 312.35168 | ... DA62: =DA63*DA46 -> 333.60153 | DE62: 865.9
A63: Cost % | B63: =B62/B46 -> 0.50657622 | C63: =C62/C46 -> 0.42981448 | D63: =D62/D46 -> 0.44220505 | E63: =E62/E46 -> 0.46370347 | F63: =F62/F46 -> 0.39511663 | G63: =G62/G46 -> 0.37488268 | H63: =H62/H46 -> 0.36719406 | I63: =I62/I46 -> 0.36835241 | ... AE63: =AE62/AE46 -> 0.32871633 | AI63: =AI62/AI46 -> 0.32314014 | AJ63: =AJ62/AJ46 -> 0.38541298 | AK63: =AK62/AK46 -> 0.35291397 | AL63: =AL62/AL46 -> 0.4263386 | AM63: =AM62/AM46 -> 0.36348735 | AN63: =AN62/AN46 -> 0.3891926 | AO63: =AO62/AO46 -> 0.39326707 | AP63: =AP62/AP46 -> 0.40618331 | ... CL63: =CL62/CL46 -> 0.37219358 | CM63: =+CI63 -> 0.31033448 | CN63: =+CJ63 -> 0.34482759 | CO63: =+CK63 -> 0.29413265 | CP63: =+CL63 -> 0.37219358 | CQ63: =+CM63 -> 0.31033448 | CR63: =+CN63 -> 0.34482759 | CS63: =+CO63 -> 0.29413265 | CT63: =+CP63 -> 0.37219358 | ... DA63: =+CW63 -> 0.29413265 | DE63: 0.32121527
A64: EBITDA | B64: =B52-B62 -> 5.6765 | C64: =C52-C62 -> 21.6821 | D64: =D52-D62 -> 26.9933 | E64: =E52-E62 -> 29.9023 | F64: =F52-F62 -> 49.5641 | G64: =G52-G62 -> 65.0715 | H64: =H52-H62 -> 83.478 | I64: =I52-I62 -> 68.1847 | ... AE64: =AE52-AE62 -> 549.62165 | AI64: =AI52-AI62 -> 24.72 | AJ64: =AJ52-AJ62 -> 22.73 | AK64: =AK52-AK62 -> 29.91 | AL64: =AL52-AL62 -> 21.72 | AM64: =AM52-AM62 -> 26.93 | AN64: =AN52-AN62 -> 30.2 | AO64: =AO52-AO62 -> 21.72 | AP64: =AP52-AP62 -> 25.13 | ... DA64: =DA52-DA62 -> 188.47852 | DE64: 373.5
A65: EBITDA Margins | B65: =B64/B46 -> 0.030922708 | C65: =C64/C46 -> 0.1042108 | D65: =D64/D46 -> 0.11709296 | E65: =E64/E46 -> 0.12313302 | F65: =F64/F46 -> 0.16273761 | G65: =G64/G46 -> 0.18080369 | H65: =H64/H46 -> 0.20485218 | I65: =I64/I46 -> 0.14616942 | ... AE65: =AE64/AE46 -> 0.13160387 | AI65: =AI64/AI46 -> 0.13192443 | AJ65: =AJ64/AJ46 -> 0.13391069 | AK65: =AK64/AK46 -> 0.1537157 | AL65: =AL64/AL46 -> 0.13260883 | AM65: =AM64/AM46 -> 0.13794693 | AN65: =AN64/AN46 -> 0.15874685 | AO65: =AO64/AO46 -> 0.11928167 | AP65: =AP64/AP46 -> 0.14495011 | ... DA65: =DA64/DA46 -> 0.16617935 | DE65: 0.13855399
A66: EBITDA YOY% | C66: =+IF(B64<0,1-C64/B64,C64/B64-1) -> 2.8196248 | D66: =+IF(C64<0,1-D64/C64,D64/C64-1) -> 0.24495782 | E66: =+IF(D64<0,1-E64/D64,E64/D64-1) -> 0.10776748 | F66: =+IF(E64<0,1-F64/E64,F64/E64-1) -> 0.6575347 | G66: =+IF(F64<0,1-G64/F64,G64/F64-1) -> 0.31287565 | H66: =+IF(G64<0,1-H64/G64,H64/G64-1) -> 0.28286577 | I66: =+IF(H64<0,1-I64/H64,I64/H64-1) -> -0.18320156 | J66: =+IF(I64<0,1-J64/I64,J64/I64-1) -> 0.5433433 | ... AE66: =+IF(AD64<0,1-AE64/AD64,AE64/AD64-1) -> 0.099777244 | AM66: =+IF(AI64<0,1-AM64/AI64,AM64/AI64-1) -> 0.089401294 | AN66: =+IF(AJ64<0,1-AN64/AJ64,AN64/AJ64-1) -> 0.32864056 | AO66: =+IF(AK64<0,1-AO64/AK64,AO64/AK64-1) -> -0.27382146 | AP66: =+IF(AL64<0,1-AP64/AL64,AP64/AL64-1) -> 0.15699816 | AQ66: =+IF(AM64<0,1-AQ64/AM64,AQ64/AM64-1) -> 0.089491274 | AR66: =+IF(AN64<0,1-AR64/AN64,AR64/AN64-1) -> -0.10496689 | AS66: =+IF(AO64<0,1-AS64/AO64,AS64/AO64-1) -> -0.18047882 | AT66: =+IF(AP64<0,1-AT64/AP64,AT64/AP64-1) -> -0.51571827 | ... CL66: =+IF(CH64<0,1-CL64/CH64,CL64/CH64-1) -> -0.24963072 | CM66: =+CM64/CI64-1 -> 0.25473664 | CN66: =+CN64/CJ64-1 -> 0.15786214 | CO66: =+CO64/CK64-1 -> 0.091621499 | CP66: =+CP64/CL64-1 -> 0.31650161 | CQ66: =+CQ64/CM64-1 -> 0.10069463 | CR66: =+CR64/CN64-1 -> 0.076899037 | CS66: =+CS64/CO64-1 -> 0.1006141 | CT66: =+CT64/CP64-1 -> 0.10494405 | ... DA66: =+DA64/CW64-1 -> 0.1000628 | DE66: 0.10655519
A67: EBITDA QOQ% | AJ67: =+IF(AI64<0,1-AJ64/AI64,AJ64/AI64-1) -> -0.080501618 | AK67: =+IF(AJ64<0,1-AK64/AJ64,AK64/AJ64-1) -> 0.31588209 | AL67: =+IF(AK64<0,1-AL64/AK64,AL64/AK64-1) -> -0.27382146 | AM67: =+IF(AL64<0,1-AM64/AL64,AM64/AL64-1) -> 0.23987109 | AN67: =+IF(AM64<0,1-AN64/AM64,AN64/AM64-1) -> 0.12142592 | AO67: =+IF(AN64<0,1-AO64/AN64,AO64/AN64-1) -> -0.2807947 | AP67: =+IF(AO64<0,1-AP64/AO64,AP64/AO64-1) -> 0.15699816 | AQ67: =+IF(AP64<0,1-AQ64/AP64,AQ64/AP64-1) -> 0.16752885 | ... CI67: =+IF(CH64<0,1-CI64/CH64,CI64/CH64-1) -> 0.35007386 | CJ67: =+IF(CI64>1,CJ64/CI64-1,1-CJ64/CI64) -> -0.072210066 | CK67: =+IF(CJ64>1,CK64/CJ64-1,1-CK64/CJ64) -> 0.52830189 | CL67: =+IF(CK64>1,CL64/CK64-1,1-CL64/CK64) -> -0.60802469 | CM67: =+CM64/CL64-1 -> 1.257538 | CN67: =+CN64/CM64-1 -> -0.14384198 | CO67: =+CO64/CN64-1 -> 0.4408686 | CP67: =+CP64/CO64-1 -> -0.52727559 | CQ67: =+CQ64/CP64-1 -> 0.88747198 | CR67: =+CR64/CQ64-1 -> -0.162351 | CS67: =+CS64/CR64-1 -> 0.47259887 | CT67: =+CT64/CS64-1 -> -0.52541584 | ... DA67: =+DA64/CZ64-1 -> 0.47891319
A68: Depreciation | B68: ='Annual Raw'!C27 -> 3.6691 | C68: ='Annual Raw'!D27 -> 8.422 | D68: ='Annual Raw'!E27 -> 9.1091 | E68: ='Annual Raw'!F27 -> 9.6188 | F68: ='Annual Raw'!G27 -> 9.3591 | G68: ='Annual Raw'!H27 -> 9.9595 | H68: ='Annual Raw'!I27 -> 8.8257 | I68: ='Annual Raw'!J27 -> 10.9879 | ... AA68: ='Annual Raw'!AB27 -> 58.336 | AB68: =+SUM(CL68:CO68) -> 59.010218 | AC68: =+SUM(CP68:CS68) -> 64.06131 | AD68: =+SUM(CT68:CW68) -> 69.449141 | AE68: =+SUM(CX68:DA68) -> 74.836972 | AI68: ='QTR Raw'!C28 -> 5.78 | AJ68: ='QTR Raw'!D28 -> 5.89 | AK68: ='QTR Raw'!E28 -> 6.21 | AL68: ='QTR Raw'!F28 -> 6.2 | AM68: ='QTR Raw'!G28 -> 6.58 | AN68: ='QTR Raw'!H28 -> 6.76 | AO68: ='QTR Raw'!I28 -> 6.99 | AP68: ='QTR Raw'!J28 -> 6.71 | ... CL68: ='QTR Raw'!BF28 -> 14.5 | CM68: =CM69*CL170 -> 14.5 | CN68: =CN69*CM170 -> 14.836739 | CO68: =CO69*CN170 -> 15.173479 | CP68: =CP69*CO170 -> 15.510218 | CQ68: =CQ69*CP170 -> 15.846958 | CR68: =CR69*CQ170 -> 16.183697 | CS68: =CS69*CR170 -> 16.520437 | CT68: =CT69*CS170 -> 16.857176 | ... DA68: =DA69*CZ170 -> 19.214352 | DE68: 58.3
A69: Depreciation % of Net Block | B69: =+B68/B170 -> 0.074082824 | C69: =+C68/C170 -> 0.15887598 | D69: =+D68/D170 -> 0.17183123 | E69: =+E68/E170 -> 0.19907322 | F69: =+F68/F170 -> 0.20466981 | G69: =+G68/G170 -> 0.21317104 | H69: =+H68/H170 -> 0.1665195 | I69: =+I68/I170 -> 0.14600328 | ... AE69: =+AE68/AE170 -> 0.12889592 | AI69: =+AI68/AH170 -> #DIV/0! | AJ69: =+AJ68/AI170 -> 0.03523781 | AK69: =+AK68/AJ170 -> 0.037152258 | AL69: =+AL68/AK170 -> #DIV/0! | AM69: =+AM68/AL170 -> #DIV/0! | AN69: =+AN68/AM170 -> 0.03541121 | AO69: =+AO68/AN170 -> 0.036616029 | AP69: =+AP68/AO170 -> 0.03541084 | ... CE69: =+CE68/CD170 -> 0.033799238 | CF69: =+CF68/CE167 -> 0.034465409 | CG69: =+CG68/CF170 -> 0.036226415 | CH69: =+CH68/CG170 -> 0.031701576 | CI69: =+CI68/CH170 -> 0.031929645 | CJ69: =+CJ68/CI170 -> 0.035992218 | CK69: =+CK68/CJ170 -> 0.037937743 | CL69: =+CL68/CK170 -> 0.033673943 | CM69: =CL69 -> 0.033673943 | CN69: =CM69 -> 0.033673943 | CO69: =CN69 -> 0.033673943 | CP69: =CO69 -> 0.033673943 | CQ69: =CP69 -> 0.033673943 | CR69: =CQ69 -> 0.033673943 | CS69: =CR69 -> 0.033673943 | CT69: =CS69 -> 0.033673943 | ... DA69: =CZ69 -> 0.033673943 | DE69: 0.13539248
A70: EBIT | B70: =B64-B68 -> 2.0074 | C70: =C64-C68 -> 13.2601 | D70: =D64-D68 -> 17.8842 | E70: =E64-E68 -> 20.2835 | F70: =F64-F68 -> 40.205 | G70: =G64-G68 -> 55.112 | H70: =H64-H68 -> 74.6523 | I70: =I64-I68 -> 57.1968 | ... AE70: =AE64-AE68 -> 474.78468 | AI70: =AI64-AI68 -> 18.94 | AJ70: =AJ64-AJ68 -> 16.84 | AK70: =AK64-AK68 -> 23.7 | AL70: =AL64-AL68 -> 15.52 | AM70: =AM64-AM68 -> 20.35 | AN70: =AN64-AN68 -> 23.44 | AO70: =AO64-AO68 -> 14.73 | AP70: =AP64-AP68 -> 18.42 | ... DA70: =DA64-DA68 -> 169.26416 | DE70: 315.2
A71: Other Income | B71: ='Annual Raw'!C23 -> 23.41 | C71: ='Annual Raw'!D23 -> 3.9933 | D71: ='Annual Raw'!E23 -> 2.8567 | E71: ='Annual Raw'!F23 -> 6.6992 | F71: ='Annual Raw'!G23 -> 6.5572 | G71: ='Annual Raw'!H23 -> 5.1677 | H71: ='Annual Raw'!I23 -> 5.8851 | I71: ='Annual Raw'!J23 -> 9.0131 | ... AA71: ='Annual Raw'!AB23 -> 59.141 | AB71: =+SUM(CL71:CO71) -> 14.4 | AC71: =+SUM(CP71:CS71) -> 0 | AD71: =+SUM(CT71:CW71) -> 0 | AE71: =+SUM(CX71:DA71) -> 0 | AI71: ='QTR Raw'!C23 -> 6.56 | AJ71: ='QTR Raw'!D23 -> 2.88 | AK71: ='QTR Raw'!E23 -> 3.27 | AL71: ='QTR Raw'!F23 -> 6.49 | AM71: ='QTR Raw'!G23 -> 3.8 | AN71: ='QTR Raw'!H23 -> 3.51 | AO71: ='QTR Raw'!I23 -> 2.36 | AP71: ='QTR Raw'!J23 -> 4.57 | ... CL71: ='QTR Raw'!BF23 -> 14.4 | DE71: 59.2
A72: Interest | B72: ='Annual Raw'!C25 -> 3.8016 | C72: ='Annual Raw'!D25 -> 4.3718 | D72: ='Annual Raw'!E25 -> 2.2933 | E72: ='Annual Raw'!F25 -> 1.5704 | F72: ='Annual Raw'!G25 -> 0.7525 | G72: ='Annual Raw'!H25 -> 0.5393 | H72: ='Annual Raw'!I25 -> 0.9645 | I72: ='Annual Raw'!J25 -> 0.6501 | ... AA72: ='Annual Raw'!AB25 -> 3.028 | AB72: =+SUM(CL72:CO72) -> -42.910752 | AC72: =+SUM(CP72:CS72) -> -72.708736 | AD72: =+SUM(CT72:CW72) -> -85.746547 | AE72: =+SUM(CX72:DA72) -> -114.47122 | AI72: ='QTR Raw'!C25 -> 1.51 | AJ72: ='QTR Raw'!D25 -> 0.76 | AK72: ='QTR Raw'!E25 -> 1.23 | AL72: ='QTR Raw'!F25 -> 0.68 | AM72: ='QTR Raw'!G25 -> 1.03 | AN72: ='QTR Raw'!H25 -> 0.58 | AO72: ='QTR Raw'!I25 -> 0.3 | AP72: ='QTR Raw'!J25 -> 0.18 | ... CL72: ='QTR Raw'!BF25 -> 0.6 | CM72: =CM73*CL204 -> -18.183161 | CN72: =CN73*CM204 -> -12.635884 | CO72: =CO73*CN204 -> -12.691708 | CP72: =CP73*CO204 -> -14.95584 | CQ72: =CQ73*CP204 -> -18.907362 | CR72: =CR73*CQ204 -> -19.359166 | CS72: =CS73*CR204 -> -19.486368 | CT72: =CT73*CS204 -> -18.426023 | ... DA72: =DA73*CZ204 -> -30.166514 | DE72: 3
A73: Interest % of Debt | B73: =+B72/B164 -> 0.091487979 | C73: =+C72/C164 -> 0.094081949 | D73: =+D72/D164 -> 0.080733512 | E73: =+E72/E164 -> 0.12320148 | F73: =+F72/F164 -> 0.097995807 | G73: =+G72/G164 -> 0.047716374 | H73: =+H72/H164 -> 0.088075757 | I73: =+I72/I164 -> 0.025887712 | ... AE73: =+AE72/AE164 -> #DIV/0! | AI73: =(AI72-AI71)/AH204 -> #DIV/0! | AJ73: =(AJ72-AJ71)/AI204 -> 0.054012739 | AK73: =(AK72-AK71)/AJ204 -> 0.023856923 | AL73: =(AL72-AL71)/AK204 -> #DIV/0! | AM73: =(AM72-AM71)/AL204 -> 0.17745035 | AN73: =(AN72-AN71)/AM204 -> 0.036533666 | AO73: =(AO72-AO71)/AN204 -> 0.019812672 | AP73: =(AP72-AP71)/AO204 -> 0.027983172 | ... CL73: =(CL72-CL71)/CK204 -> 0.048694425 | CM73: 0.03 | CN73: =+CM73 -> 0.03 | CO73: =+CN73 -> 0.03 | CP73: =+CO73 -> 0.03 | CQ73: =+CP73 -> 0.03 | CR73: =+CQ73 -> 0.03 | CS73: =+CR73 -> 0.03 | CT73: 0.025 | CU73: =+CT73 -> 0.025 | CV73: =+CU73 -> 0.025 | CW73: =+CV73 -> 0.025 | CX73: =+CW73 -> 0.025 | CY73: =+CX73 -> 0.025 | CZ73: =+CY73 -> 0.025 | DA73: =+CZ73 -> 0.025
A74: PBT | B74: =B70+B71-B72 -> 21.6158 | C74: =C70+C71-C72 -> 12.8816 | D74: =D70+D71-D72 -> 18.4476 | E74: =E70+E71-E72 -> 25.4123 | F74: =F70+F71-F72 -> 46.0097 | G74: =G70+G71-G72 -> 59.7404 | H74: =H70+H71-H72 -> 79.5729 | I74: =I70+I71-I72 -> 65.5598 | ... AE74: =AE70+AE71-AE72 -> 589.2559 | AI74: =AI70+AI71-AI72 -> 23.99 | AJ74: =AJ70+AJ71-AJ72 -> 18.96 | AK74: =AK70+AK71-AK72 -> 25.74 | AL74: =AL70+AL71-AL72 -> 21.33 | AM74: =AM70+AM71-AM72 -> 23.12 | AN74: =AN70+AN71-AN72 -> 26.37 | AO74: =AO70+AO71-AO72 -> 16.79 | AP74: =AP70+AP71-AP72 -> 22.81 | ... DA74: =DA70+DA71-DA72 -> 199.43068 | DE74: 371.4
A75: Tax | B75: ='Annual Raw'!C30 -> 6.75 | C75: ='Annual Raw'!D30 -> 4.6 | D75: ='Annual Raw'!E30 -> 6.6433 | E75: ='Annual Raw'!F30 -> 7.7071 | F75: ='Annual Raw'!G30 -> 15.9847 | G75: ='Annual Raw'!H30 -> 21.5975 | H75: ='Annual Raw'!I30 -> 27.4247 | I75: ='Annual Raw'!J30 -> 22.1329 | ... AA75: ='Annual Raw'!AB30 -> 89.968 | AB75: =+SUM(CL75:CO75) -> 101.83608 | AC75: =+SUM(CP75:CS75) -> 115.80055 | AD75: =+SUM(CT75:CW75) -> 129.01366 | AE75: =+SUM(CX75:DA75) -> 147.31398 | AI75: ='QTR Raw'!C29 -> 6.53 | AJ75: ='QTR Raw'!D29 -> 6.04 | AK75: ='QTR Raw'!E29 -> 6.2 | AL75: ='QTR Raw'!F29 -> 5.72 | AM75: ='QTR Raw'!G29 -> 7.66 | AN75: ='QTR Raw'!H29 -> 8.47 | AO75: ='QTR Raw'!I29 -> 6 | AP75: ='QTR Raw'!J29 -> 7.68 | ... CL75: ='QTR Raw'!BF29 -> 13.5 | CM75: =+CM74*CM76 -> 29.591522 | CN75: =+CN74*CN76 -> 23.996463 | CO75: =+CO74*CO76 -> 34.748094 | CP75: =+CP74*CP76 -> 16.580976 | CQ75: =+CQ74*CQ76 -> 32.322822 | CR75: =+CR74*CR76 -> 27.22816 | CS75: =+CS74*CS76 -> 39.668593 | CT75: =+CT74*CT76 -> 18.866402 | ... DA75: =+DA74*DA76 -> 49.857669 | DE75: 90
A76: Tax Rate % | B76: =B75/B74 -> 0.31227158 | C76: =C75/C74 -> 0.3570985 | D76: =D75/D74 -> 0.36011731 | E76: =E75/E74 -> 0.30328227 | F76: =F75/F74 -> 0.34742022 | G76: =G75/G74 -> 0.36152252 | H76: =H75/H74 -> 0.34464874 | I76: =I75/I74 -> 0.33759865 | ... AE76: =AE75/AE74 -> 0.25 | AI76: =AI75/AI74 -> 0.27219675 | AJ76: =AJ75/AJ74 -> 0.3185654 | AK76: =AK75/AK74 -> 0.24087024 | AL76: =AL75/AL74 -> 0.2681669 | AM76: =AM75/AM74 -> 0.33131488 | AN76: =AN75/AN74 -> 0.32119833 | AO76: =AO75/AO74 -> 0.35735557 | AP76: =AP75/AP74 -> 0.33669443 | ... CL76: =CL75/CL74 -> 0.26946108 | CM76: 0.25 | CN76: 0.25 | CO76: 0.25 | CP76: 0.25 | CQ76: 0.25 | CR76: 0.25 | CS76: 0.25 | CT76: 0.25 | CU76: 0.25 | CV76: 0.25 | CW76: 0.25 | CX76: 0.25 | CY76: 0.25 | CZ76: 0.25 | DA76: 0.25 | DE76: 0.24232633
A77: PAT | B77: =B74-B75 -> 14.8658 | C77: =C74-C75 -> 8.2816 | D77: =D74-D75 -> 11.8043 | E77: =E74-E75 -> 17.7052 | F77: =F74-F75 -> 30.025 | G77: =G74-G75 -> 38.1429 | H77: =H74-H75 -> 52.1482 | I77: =I74-I75 -> 43.4269 | ... AE77: =AE74-AE75 -> 441.94193 | AI77: =AI74-AI75 -> 17.46 | AJ77: =AJ74-AJ75 -> 12.92 | AK77: =AK74-AK75 -> 19.54 | AL77: =AL74-AL75 -> 15.61 | AM77: =AM74-AM75 -> 15.46 | AN77: =AN74-AN75 -> 17.9 | AO77: =AO74-AO75 -> 10.79 | AP77: =AP74-AP75 -> 15.13 | ... DA77: =DA74-DA75 -> 149.57301 | DE77: 281.4
A78: PAT % | B78: =+B77/B46 -> 0.080981377 | C78: =+C77/C46 -> 0.039803903 | D78: =+D77/D46 -> 0.051205316 | E78: =+E77/E46 -> 0.07290726 | F78: =+F77/F46 -> 0.098583387 | G78: =+G77/G46 -> 0.10598153 | H78: =+H77/H46 -> 0.12796991 | I78: =+I77/I46 -> 0.09309544 | ... AE78: =+AE77/AE46 -> 0.10582056 | AI78: =+AI77/AI46 -> 0.093179635 | AJ78: =+AJ77/AJ46 -> 0.076116413 | AK78: =+AK77/AK46 -> 0.10042142 | AL78: =+AL77/AL46 -> 0.095304964 | AM78: =+AM77/AM46 -> 0.079192706 | AN78: =+AN77/AN46 -> 0.094091674 | AO78: =+AO77/AO46 -> 0.059256412 | AP78: =+AP77/AP46 -> 0.087270001 | ... DA78: =+DA77/DA46 -> 0.13187681 | DE78: 0.10438847
A79: PAT YOY% | C79: =+IF(B77<0,1-C77/B77,C77/B77-1) -> -0.44290923 | D79: =+IF(C77<0,1-D77/C77,D77/C77-1) -> 0.42536466 | E79: =+IF(D77<0,1-E77/D77,E77/D77-1) -> 0.49989411 | F79: =+IF(E77<0,1-F77/E77,F77/E77-1) -> 0.69582947 | G79: =+IF(F77<0,1-G77/F77,G77/F77-1) -> 0.27037136 | H79: =+IF(G77<0,1-H77/G77,H77/G77-1) -> 0.36717974 | I79: =+IF(H77<0,1-I77/H77,I77/H77-1) -> -0.16724067 | J79: =+IF(I77<0,1-J77/I77,J77/I77-1) -> 0.48812372 | ... AE79: =+IF(AD77<0,1-AE77/AD77,AE77/AD77-1) -> 0.14184786 | AM79: =+IF(AI77<0,1-AM77/AI77,AM77/AI77-1) -> -0.11454754 | AN79: =+IF(AJ77<0,1-AN77/AJ77,AN77/AJ77-1) -> 0.38544892 | AO79: =+IF(AK77<0,1-AO77/AK77,AO77/AK77-1) -> -0.44779939 | AP79: =+IF(AL77<0,1-AP77/AL77,AP77/AL77-1) -> -0.03074952 | AQ79: =+IF(AM77<0,1-AQ77/AM77,AQ77/AM77-1) -> 0.45213454 | AR79: =+IF(AN77<0,1-AR77/AN77,AR77/AN77-1) -> -0.0016759777 | AS79: =+IF(AO77<0,1-AS77/AO77,AS77/AO77-1) -> -0.075996293 | AT79: =+IF(AP77<0,1-AT77/AP77,AT77/AP77-1) -> -0.5763384 | ... CL79: =+IF(CH77<0,1-CL77/CH77,CL77/CH77-1) -> -0.23908524 | CM79: =+CM77/CI77-1 -> 0.33095303 | CN79: =+CN77/CJ77-1 -> 0.12133006 | CO79: =+CO77/CK77-1 -> 0.018010562 | CP79: =+CP77/CL77-1 -> 0.35909639 | CQ79: =+CQ77/CM77-1 -> 0.092300071 | CR79: =+CR77/CN77-1 -> 0.13467388 | CS79: =+CS77/CO77-1 -> 0.14160487 | CT79: =+CT77/CP77-1 -> 0.13783421 | ... DA79: =+DA77/CW77-1 -> 0.1321313 | DE79: 0.2022096
A80: PAT QOQ% | AJ80: =+IF(AI77<0,1-AJ77/AI77,AJ77/AI77-1) -> -0.26002291 | AK80: =+IF(AJ77<0,1-AK77/AJ77,AK77/AJ77-1) -> 0.5123839 | AL80: =+IF(AK77<0,1-AL77/AK77,AL77/AK77-1) -> -0.2011259 | AM80: =+IF(AL77<0,1-AM77/AL77,AM77/AL77-1) -> -0.0096092249 | AN80: =+IF(AM77<0,1-AN77/AM77,AN77/AM77-1) -> 0.15782665 | AO80: =+IF(AN77<0,1-AO77/AN77,AO77/AN77-1) -> -0.3972067 | AP80: =+IF(AO77<0,1-AP77/AO77,AP77/AO77-1) -> 0.40222428 | AQ80: =+IF(AP77<0,1-AQ77/AP77,AQ77/AP77-1) -> 0.48380701 | ... CL80: =+IF(CK77<0,1-CL77/CK77,CL77/CK77-1) -> -0.64257813 | CM80: =+CM77/CL77-1 -> 1.4255346 | CN80: =+CN77/CM77-1 -> -0.18907641 | CO80: =+CO77/CN77-1 -> 0.44805063 | CP80: =+CP77/CO77-1 -> -0.52282344 | CQ80: =+CQ77/CP77-1 -> 0.949392 | CR80: =+CR77/CQ77-1 -> -0.15761809 | CS80: =+CS77/CR77-1 -> 0.45689583 | CT80: =+CT77/CS77-1 -> -0.52439953 | ... DA80: =+DA77/CZ77-1 -> 0.44041978
A81: Minority Interest | B81: ='Annual Raw'!C32 -> 0 | C81: ='Annual Raw'!D32 -> 0 | D81: ='Annual Raw'!E32 -> -0.0136 | E81: ='Annual Raw'!F32 -> 0 | F81: ='Annual Raw'!G32 -> 0 | G81: ='Annual Raw'!H32 -> 0 | H81: ='Annual Raw'!I32 -> 0 | I81: ='Annual Raw'!J32 -> 0 | ... AA81: ='Annual Raw'!AB32 -> 0 | AB81: =+SUM(CL81:CO81) -> 0 | AC81: =+SUM(CP81:CS81) -> 0 | AD81: =+SUM(CT81:CW81) -> 0 | AE81: =+SUM(CX81:DA81) -> 0 | AI81: ='QTR Raw'!C34 -> 0 | AJ81: ='QTR Raw'!D34 -> 0 | AK81: ='QTR Raw'!E34 -> 0 | AL81: ='QTR Raw'!F34 -> 0 | AM81: ='QTR Raw'!G34 -> 0 | AN81: ='QTR Raw'!H34 -> 0 | AO81: ='QTR Raw'!I34 -> 0 | AP81: ='QTR Raw'!J34 -> 0 | ... CL81: ='QTR Raw'!BF34 -> 0 | CM81: =+CL81 -> 0 | CN81: =+CM81 -> 0 | CO81: =+CN81 -> 0 | CP81: =+CO81 -> 0 | CQ81: =+CP81 -> 0 | CR81: =+CQ81 -> 0 | CS81: =+CR81 -> 0 | CT81: =+CS81 -> 0 | ... DA81: =+CZ81 -> 0 | DE81: 0
A82: Share of Associate | B82: ='Annual Raw'!C33+'Annual Raw'!C28 -> 0 | C82: ='Annual Raw'!D33+'Annual Raw'!D28 -> 0 | D82: ='Annual Raw'!E33+'Annual Raw'!E28 -> 0 | E82: ='Annual Raw'!F33+'Annual Raw'!F28 -> 2.5015 | F82: ='Annual Raw'!G33+'Annual Raw'!G28 -> 0 | G82: ='Annual Raw'!H33+'Annual Raw'!H28 -> 1.3345 | H82: ='Annual Raw'!I33+'Annual Raw'!I28 -> 3.5284 | I82: ='Annual Raw'!J33+'Annual Raw'!J28 -> 6.4486 | ... AA82: ='Annual Raw'!AB33+'Annual Raw'!AB28 -> 14.638 | AB82: =+SUM(CL82:CO82) -> 12.8 | AC82: =+SUM(CP82:CS82) -> 12.8 | AD82: =+SUM(CT82:CW82) -> 12.8 | AE82: =+SUM(CX82:DA82) -> 12.8 | AI82: ='QTR Raw'!C35 -> 0 | AJ82: ='QTR Raw'!D35 -> 0 | AK82: ='QTR Raw'!E35 -> 0 | AL82: ='QTR Raw'!F35 -> 0 | AM82: ='QTR Raw'!G35 -> 0 | AN82: ='QTR Raw'!H35 -> 0 | AO82: ='QTR Raw'!I35 -> 0 | AP82: ='QTR Raw'!J35 -> 0 | ... CL82: ='QTR Raw'!BF35 -> 3.2 | CM82: =+CL82 -> 3.2 | CN82: =+CM82 -> 3.2 | CO82: =+CN82 -> 3.2 | CP82: =+CO82 -> 3.2 | CQ82: =+CP82 -> 3.2 | CR82: =+CQ82 -> 3.2 | CS82: =+CR82 -> 3.2 | CT82: =+CS82 -> 3.2 | ... DA82: =+CZ82 -> 3.2 | DE82: 14.6
A83: Exceptional Income / Expenses | B83: ='Annual Raw'!C29+'Annual Raw'!C31+'Annual Raw'!C34+'Annual Raw'!C36 -> 0 | C83: ='Annual Raw'!D29+'Annual Raw'!D31+'Annual Raw'!D34+'Annual Raw'!D36 -> 0 | D83: ='Annual Raw'!E29+'Annual Raw'!E31+'Annual Raw'!E34+'Annual Raw'!E36 -> 0 | E83: ='Annual Raw'!F29+'Annual Raw'!F31+'Annual Raw'!F34+'Annual Raw'!F36 -> 0 | F83: ='Annual Raw'!G29+'Annual Raw'!G31+'Annual Raw'!G34+'Annual Raw'!G36 -> 0 | G83: ='Annual Raw'!H29+'Annual Raw'!H31+'Annual Raw'!H34+'Annual Raw'!H36 -> 0 | H83: ='Annual Raw'!I29+'Annual Raw'!I31+'Annual Raw'!I34+'Annual Raw'!I36 -> 0 | I83: ='Annual Raw'!J29+'Annual Raw'!J31+'Annual Raw'!J34+'Annual Raw'!J36 -> 0 | ... AA83: ='Annual Raw'!AB29+'Annual Raw'!AB31+'Annual Raw'!AB34+'Annual Raw'!AB36 -> -25.548 | AB83: =+SUM(CL83:CO83) -> 0 | AC83: =+SUM(CP83:CS83) -> 0 | AD83: =+SUM(CT83:CW83) -> 0 | AE83: =+SUM(CX83:DA83) -> 0 | AI83: ='QTR Raw'!C26+'QTR Raw'!C31+'QTR Raw'!C32+'QTR Raw'!C33+'QTR Raw'!C36+'QTR Raw'!C37+'QTR Raw'!C39 -> 0 | AJ83: ='QTR Raw'!D26+'QTR Raw'!D31+'QTR Raw'!D32+'QTR Raw'!D33+'QTR Raw'!D36+'QTR Raw'!D37+'QTR Raw'!D39 -> 0 | AK83: ='QTR Raw'!E26+'QTR Raw'!E31+'QTR Raw'!E32+'QTR Raw'!E33+'QTR Raw'!E36+'QTR Raw'!E37+'QTR Raw'!E39 -> 0 | AL83: ='QTR Raw'!F26+'QTR Raw'!F31+'QTR Raw'!F32+'QTR Raw'!F33+'QTR Raw'!F36+'QTR Raw'!F37+'QTR Raw'!F39 -> 0 | AM83: ='QTR Raw'!G26+'QTR Raw'!G31+'QTR Raw'!G32+'QTR Raw'!G33+'QTR Raw'!G36+'QTR Raw'!G37+'QTR Raw'!G39 -> 0 | AN83: ='QTR Raw'!H26+'QTR Raw'!H31+'QTR Raw'!H32+'QTR Raw'!H33+'QTR Raw'!H36+'QTR Raw'!H37+'QTR Raw'!H39 -> 0 | AO83: ='QTR Raw'!I26+'QTR Raw'!I31+'QTR Raw'!I32+'QTR Raw'!I33+'QTR Raw'!I36+'QTR Raw'!I37+'QTR Raw'!I39 -> 0 | AP83: ='QTR Raw'!J26+'QTR Raw'!J31+'QTR Raw'!J32+'QTR Raw'!J33+'QTR Raw'!J36+'QTR Raw'!J37+'QTR Raw'!J39 -> 0 | ... CL83: ='QTR Raw'!BF26+'QTR Raw'!BF31+'QTR Raw'!BF32+'QTR Raw'!BF33+'QTR Raw'!BF36+'QTR Raw'!BF37+'QTR Raw'!BF39 -> 0 | DE83: -25.5
A84: Consolidated Net Profit | B84: =B77+B81+B82+B83 -> 14.8658 | C84: =C77+C81+C82+C83 -> 8.2816 | D84: =D77+D81+D82+D83 -> 11.7907 | E84: =E77+E81+E82+E83 -> 20.2067 | F84: =F77+F81+F82+F83 -> 30.025 | G84: =G77+G81+G82+G83 -> 39.4774 | H84: =H77+H81+H82+H83 -> 55.6766 | I84: =I77+I81+I82+I83 -> 49.8755 | ... AE84: =AE77+AE81+AE82+AE83 -> 454.74193 | AI84: =AI77+AI81+AI82+AI83 -> 17.46 | AJ84: =AJ77+AJ81+AJ82+AJ83 -> 12.92 | AK84: =AK77+AK81+AK82+AK83 -> 19.54 | AL84: =AL77+AL81+AL82+AL83 -> 15.61 | AM84: =AM77+AM81+AM82+AM83 -> 15.46 | AN84: =AN77+AN81+AN82+AN83 -> 17.9 | AO84: =AO77+AO81+AO82+AO83 -> 10.79 | AP84: =AP77+AP81+AP82+AP83 -> 15.13 | ... DA84: =DA77+DA81+DA82+DA83 -> 152.77301 | DE84: 270.5
A85: Profit & Loss- Annual (End)
A86: Rat
A87: Ace - PAT | B87: ='Annual Raw'!C35 -> 14.8658 | C87: ='Annual Raw'!D35 -> 8.2816 | D87: ='Annual Raw'!E35 -> 11.7907 | E87: ='Annual Raw'!F35 -> 20.2067 | F87: ='Annual Raw'!G35 -> 30.025 | G87: ='Annual Raw'!H35 -> 39.4774 | H87: ='Annual Raw'!I35 -> 55.6766 | I87: ='Annual Raw'!J35 -> 49.8755 | ... AA87: ='Annual Raw'!AB35 -> 270.494 | AB87: =+AB84 -> 314.40824 | AC87: =+AC84 -> 360.20165 | AD87: =+AD84 -> 399.84099 | AE87: =+AE84 -> 454.74193 | AI87: ='QTR Raw'!C42 -> 17.46 | AJ87: ='QTR Raw'!D42 -> 12.92 | AK87: ='QTR Raw'!E42 -> 19.54 | AL87: ='QTR Raw'!F42 -> 15.61 | AM87: ='QTR Raw'!G42 -> 15.46 | AN87: ='QTR Raw'!H42 -> 17.9 | AO87: ='QTR Raw'!I42 -> 10.79 | AP87: ='QTR Raw'!J42 -> 15.13 | ... CL87: ='QTR Raw'!BF42 -> 39.8 | DE87: 270.5
A88: Checksum - PAT | B88: =B87-B84 -> -3.1974423e-14 | C88: =C87-C84 -> 0 | D88: =D87-D84 -> 1.9539925e-14 | E88: =E87-E84 -> 0 | F88: =F87-F84 -> 3.907985e-14 | G88: =G87-G84 -> 0 | H88: =H87-H84 -> 0 | I88: =I87-I84 -> 0 | ... AE88: =AE87-AE84 -> 0 | AI88: =AI87-AI84 -> 0 | AJ88: =AJ87-AJ84 -> -1.5987212e-14 | AK88: =AK87-AK84 -> 0 | AL88: =AL87-AL84 -> 0 | AM88: =AM87-AM84 -> 2.1316282e-14 | AN88: =AN87-AN84 -> 0 | AO88: =AO87-AO84 -> 0 | AP88: =AP87-AP84 -> 0 | ... CL88: =CL87-CL84 -> 0 | DE88: 0
A89: Ratios (Start)
A90: ROE (%) | B90: =(B84-B83)/B156 -> 0.16183193 | C90: =(C84-C83)/C156 -> 0.088025059 | D90: =(D84-D83)/D156 -> 0.11842904 | E90: =(E84-E83)/E156 -> 0.17890062 | F90: =(F84-F83)/F156 -> 0.22480937 | G90: =(G84-G83)/G156 -> 0.23699916 | H90: =(H84-H83)/H156 -> 0.26506229 | I90: =(I84-I83)/I156 -> 0.19972505 | ... AE90: =(AE84-AE83)/AE156 -> 0.14175279 | AL90: =(SUM(AI84:AL84)-SUM(AI83:AL83))/AL156 -> 4.19795 | AM90: =(SUM(AJ84:AM84)-SUM(AJ83:AM83))/AM156 -> 0.13902749 | AN90: =(SUM(AK84:AN84)-SUM(AK83:AN83))/AN156 -> 0.1442741 | AO90: =(SUM(AL84:AO84)-SUM(AL83:AO83))/AO156 -> 0.11677121 | AP90: =(SUM(AM84:AP84)-SUM(AM83:AP83))/AP156 -> 0.11250712 | AQ90: =(SUM(AN84:AQ84)-SUM(AN83:AQ83))/AQ156 -> 0.13232035 | AR90: =(SUM(AO84:AR84)-SUM(AO83:AR83))/AR156 -> 0.12770388 | AS90: =(SUM(AP84:AS84)-SUM(AP83:AS83))/AS156 -> 0.11740215 | ... DA90: =(SUM(CX84:DA84)-SUM(CX83:DA83))/DA156 -> 0.14175279 | DE90: 0.17631642
A91: ROCE (%) | B91: =+B70/B165 -> 0.015046566 | C91: =+C70/C165 -> 0.09434416 | D91: =+D70/D165 -> 0.13934919 | E91: =+E70/E165 -> 0.16136962 | F91: =+F70/F165 -> 0.28466438 | G91: =+G70/G165 -> 0.30983713 | H91: =+H70/H165 -> 0.33779046 | I91: =+I70/I165 -> 0.20811467 | ... AE91: =+AE70/AE165 -> 0.14800054 | AL91: =+SUM(AI70:AL70)/AL165 -> 4.8046124 | AM91: =+SUM(AJ70:AM70)/AM165 -> 0.15628643 | AN91: =+SUM(AK70:AN70)/AN165 -> 0.16378919 | AO91: =+SUM(AL70:AO70)/AO165 -> 0.14378095 | AP91: =+SUM(AM70:AP70)/AP165 -> 0.1451479 | AQ91: =+SUM(AN70:AQ70)/AQ165 -> 0.15276491 | AR91: =+SUM(AO70:AR70)/AR165 -> 0.14147334 | AS91: =+SUM(AP70:AS70)/AS165 -> 0.12336445 | ... DA91: =+SUM(CX70:DA70)/DA165 -> 0.14800054 | DE91: 0.18775316
A92: Ratios (End)
A93: Checksum Of qtr to Annual
A94: Revenue - Checksum Of qtr to Annual | N94: =N46-SUM(AI46:AL46) -> -0.108 | R94: =R46-SUM(AX46:BA46) -> 0.886 | S94: =S46-SUM(BB46:BE46) -> 0.037 | T94: =T46-SUM(BF46:BI46) -> -0.034 | U94: =U46-SUM(BJ46:BM46) -> 0.008 | V94: =V46-SUM(BN46:BQ46) -> 0.015 | W94: =W46-SUM(BR46:BU46) -> -0.009 | X94: =X46-SUM(BV46:BY46) -> -0.04 | Y94: =Y46-SUM(BZ46:CC46) -> 0.038 | Z94: =Z46-SUM(CD46:CG46) -> -0.014 | AA94: =AA46-SUM(CE46:CH46) -> 111.428 | AB94: =AB46-SUM(CL46:CO46) -> 0 | AC94: =AC46-SUM(CP46:CS46) -> 0 | AD94: =AD46-SUM(CT46:CW46) -> 0 | AE94: =AE46-SUM(CX46:DA46) -> 0 | DE94: 0
A95: GP - Checksum Of qtr to Annual | N95: =N52-SUM(AI52:AL52) -> -6.32 | R95: =R52-SUM(AX52:BA52) -> 0.998 | S95: =S52-SUM(BB52:BE52) -> 1.564 | T95: =T52-SUM(BF52:BI52) -> -0.003 | U95: =U52-SUM(BJ52:BM52) -> 0.002 | V95: =V52-SUM(BN52:BQ52) -> 0.097 | W95: =W52-SUM(BR52:BU52) -> -0.034 | X95: =X52-SUM(BV52:BY52) -> -0.041 | Y95: =Y52-SUM(BZ52:CC52) -> 0.028 | Z95: =Z52-SUM(CD52:CG52) -> -0.058 | AA95: =AA52-SUM(CE52:CH52) -> 86.364 | AB95: =AB52-SUM(CL52:CO52) -> 0 | AC95: =AC52-SUM(CP52:CS52) -> 0 | AD95: =AD52-SUM(CT52:CW52) -> 0 | AE95: =AE52-SUM(CX52:DA52) -> 0 | DE95: 0
A96: EBITDA - Checksum Of qtr to Annual | N96: =N64-SUM(AI64:AL64) -> -6.474 | R96: =R64-SUM(AX64:BA64) -> 0.8 | S96: =S64-SUM(BB64:BE64) -> -0.105 | T96: =T64-SUM(BF64:BI64) -> -0.06 | U96: =U64-SUM(BJ64:BM64) -> 1.434 | V96: =V64-SUM(BN64:BQ64) -> -0.009 | W96: =W64-SUM(BR64:BU64) -> 0.067 | X96: =X64-SUM(BV64:BY64) -> -0.051 | Y96: =Y64-SUM(BZ64:CC64) -> -0.03 | Z96: =Z64-SUM(CD64:CG64) -> 0.034 | AA96: =AA64-SUM(CE64:CH64) -> 29.295 | AB96: =AB64-SUM(CL64:CO64) -> 0 | AC96: =AC64-SUM(CP64:CS64) -> 0 | AD96: =AD64-SUM(CT64:CW64) -> 0 | AE96: =AE64-SUM(CX64:DA64) -> 0 | DE96: -5.1159077e-13
A97: PAT - Checksum Of qtr to Annual | N97: =N84-SUM(AI84:AL84) -> -1.951 | R97: =R77-SUM(AX77:BA77) -> -1.397 | S97: =S77-SUM(BB77:BE77) -> -1.893 | T97: =T77-SUM(BF77:BI77) -> -0.01 | U97: =U77-SUM(BJ77:BM77) -> -0.024 | V97: =V77-SUM(BN77:BQ77) -> -0.018 | W97: =W77-SUM(BR77:BU77) -> -0.031 | X97: =X77-SUM(BV77:BY77) -> 0.018 | Y97: =Y77-SUM(BZ77:CC77) -> 0.023 | Z97: =Z77-SUM(CD77:CG77) -> -0.031 | AA97: =AA77-SUM(CE77:CH77) -> 41.704 | AB97: =AB77-SUM(CL77:CO77) -> 0 | AC97: =AC77-SUM(CP77:CS77) -> 0 | AD97: =AD77-SUM(CT77:CW77) -> 0 | AE97: =AE77-SUM(CX77:DA77) -> 0 | DE97: -5.1159077e-13
A98: Valuation (Start)
A99: Eq | B99: ='Annual Raw'!C104 -> 17.403 | C99: ='Annual Raw'!D104 -> 17.403 | D99: ='Annual Raw'!E104 -> 17.4039 | E99: =+F99 -> 34.8 | F99: =+G99 -> 34.8 | G99: =+H99 -> 34.8 | H99: =+I99 -> 34.8 | I99: =+J99 -> 34.8 | J99: =+K99 -> 34.8 | K99: =+L99 -> 34.8 | L99: =+M99 -> 34.8 | ... AA99: =+AB99 -> 34.8 | AB99: =AA99 -> 34.8 | AC99: =AB99 -> 34.8 | AD99: =AC99 -> 34.8 | AE99: =AD99 -> 34.8 | AI99: =+AJ99 -> 34.8 | AJ99: =+AK99 -> 34.8 | AK99: =+AL99 -> 34.8 | AL99: =+AM99 -> 34.8 | AM99: =+AN99 -> 34.8 | AN99: =+AO99 -> 34.8 | AO99: =+AP99 -> 34.8 | AP99: =+AQ99 -> 34.8 | ... CI99: =+CJ99 -> 34.8 | CJ99: ='QTR Raw'!BD45 -> 34.8 | CK99: ='QTR Raw'!BE45 -> 34.8 | CL99: ='QTR Raw'!BF45 -> 34.8 | CM99: =+CL99 -> 34.8 | CN99: =+CM99 -> 34.8 | CO99: =+CN99 -> 34.8 | CP99: =+CO99 -> 34.8 | CQ99: =+CP99 -> 34.8 | CR99: =+CQ99 -> 34.8 | CS99: =+CR99 -> 34.8 | CT99: =+CS99 -> 34.8 | ... DA99: =+CZ99 -> 34.8 | DE99: 34.8
A100: FV | B100: ='Annual Raw'!C105 -> 10 | C100: ='Annual Raw'!D105 -> 10 | D100: ='Annual Raw'!E105 -> 10 | E100: =+F100 -> 1 | F100: =+G100 -> 1 | G100: =+H100 -> 1 | H100: =+I100 -> 1 | I100: =+J100 -> 1 | J100: =+K100 -> 1 | K100: =+L100 -> 1 | L100: =+M100 -> 1 | ... AA100: =+AB100 -> 1 | AB100: =AA100 -> 1 | AC100: =AB100 -> 1 | AD100: =AC100 -> 1 | AE100: =AD100 -> 1 | AI100: =AJ100 -> 2 | AJ100: =AK100 -> 2 | AK100: =AL100 -> 2 | AL100: =AM100 -> 2 | AM100: =AN100 -> 2 | AN100: =AO100 -> 2 | AO100: =AP100 -> 2 | AP100: =AQ100 -> 2 | ... CI100: =CJ100 -> 2 | CJ100: ='QTR Raw'!BD46 -> 2 | CK100: ='QTR Raw'!BE46 -> 2 | CL100: ='QTR Raw'!BF46 -> 2 | CM100: =+CL100 -> 2 | CN100: =+CM100 -> 2 | CO100: =+CN100 -> 2 | CP100: =+CO100 -> 2 | CQ100: =+CP100 -> 2 | CR100: =+CQ100 -> 2 | CS100: =+CR100 -> 2 | CT100: =+CS100 -> 2 | ... DA100: =+CZ100 -> 2 | DE100: 1
A101: No of share | B101: =B99/B100 -> 1.7403 | C101: =C99/C100 -> 1.7403 | D101: =D99/D100 -> 1.74039 | E101: =E99/E100 -> 34.8 | F101: =F99/F100 -> 34.8 | G101: =G99/G100 -> 34.8 | H101: =H99/H100 -> 34.8 | I101: =I99/I100 -> 34.8 | ... AE101: =AE99/AE100 -> 34.8 | AI101: =AI99/AI100 -> 17.4 | AJ101: =AJ99/AJ100 -> 17.4 | AK101: =AK99/AK100 -> 17.4 | AL101: =AL99/AL100 -> 17.4 | AM101: =AM99/AM100 -> 17.4 | AN101: =AN99/AN100 -> 17.4 | AO101: =AO99/AO100 -> 17.4 | AP101: =AP99/AP100 -> 17.4 | ... DA101: =DA99/DA100 -> 17.4 | DE101: 34.8
A102: EPS | B102: =(B84-B83)/B101 -> 8.5420904 | C102: =(C84-C83)/C101 -> 4.7587198 | D102: =(D84-D83)/D101 -> 6.7747459 | E102: =(E84-E83)/E101 -> 0.5806523 | F102: =(F84-F83)/F101 -> 0.86278736 | G102: =(G84-G83)/G101 -> 1.134408 | H102: =(H84-H83)/H101 -> 1.5999023 | I102: =(I84-I83)/I101 -> 1.433204 | ... AE102: =(AE84-AE83)/AE101 -> 13.067297 | AI102: =(AI84-AI83)/AI101 -> 1.0034483 | AJ102: =(AJ84-AJ83)/AJ101 -> 0.74252874 | AK102: =(AK84-AK83)/AK101 -> 1.1229885 | AL102: =(AL84-AL83)/AL101 -> 0.89712644 | AM102: =(AM84-AM83)/AM101 -> 0.88850575 | AN102: =(AN84-AN83)/AN101 -> 1.0287356 | AO102: =(AO84-AO83)/AO101 -> 0.62011494 | AP102: =(AP84-AP83)/AP101 -> 0.86954023 | ... DA102: =(DA84-DA83)/DA101 -> 8.7800579 | DE102: 8.5057471
A103: DPS | B103: ='Annual Raw'!C110 -> 0.3 | C103: ='Annual Raw'!D110 -> 0.3 | D103: ='Annual Raw'!E110 -> 0.3 | E103: ='Annual Raw'!F110 -> 0.35 | F103: ='Annual Raw'!G110 -> 0.4 | G103: ='Annual Raw'!H110 -> 0.45 | H103: ='Annual Raw'!I110 -> 0.55 | I103: ='Annual Raw'!J110 -> 0.55 | ... AA103: ='Annual Raw'!AB110 -> 4.4 | DE103: 4.4
A104: DPS % of EPS | B104: =B103/B102 -> 0.035120209 | C104: =C103/C102 -> 0.063042166 | D104: =D103/D102 -> 0.044282104 | E104: =E103/E102 -> 0.60277037 | F104: =F103/F102 -> 0.46361366 | G104: =G103/G102 -> 0.39668266 | H104: =H103/H102 -> 0.34377099 | I104: =I103/I102 -> 0.38375555 | ... AE104: =AE103/AE102 -> 0 | DE104: 0
A105: EPS TTM | B105: =+B102 -> 8.5420904 | C105: =+C102 -> 4.7587198 | D105: =+D102 -> 6.7747459 | E105: =+E102 -> 0.5806523 | F105: =+F102 -> 0.86278736 | G105: =+G102 -> 1.134408 | H105: =+H102 -> 1.5999023 | I105: =+I102 -> 1.433204 | ... AE105: =+AE102 -> 13.067297 | AL105: =SUM(AI102:AL102) -> 3.766092 | AM105: =SUM(AJ102:AM102) -> 3.6511494 | AN105: =SUM(AK102:AN102) -> 3.9373563 | AO105: =SUM(AL102:AO102) -> 3.4344828 | AP105: =SUM(AM102:AP102) -> 3.4068966 | AQ105: =SUM(AN102:AQ102) -> 3.8086207 | AR105: =SUM(AO102:AR102) -> 3.8068966 | AS105: =SUM(AP102:AS102) -> 3.7597701 | ... DA105: =SUM(CX102:DA102) -> 26.134594 | DE105: 8.5057471
A106: EPS Growth YoY % | C106: =+C105/B105-1 -> -0.44290923 | D106: =+D105/C105-1 -> 0.42364884 | E106: =+E105/D105-1 -> -0.91429165 | F106: =+F105/E105-1 -> 0.48589329 | G106: =+G105/F105-1 -> 0.31481765 | H106: =+H105/G105-1 -> 0.41034111 | I106: =+I105/H105-1 -> -0.10419278 | J106: =+J105/I105-1 -> 0.41671562 | ... AE106: =+AE105/AD105-1 -> 0.13730692 | AP106: =+IF(AL105<0,1-AP105/AL105,AP105/AL105-1) -> -0.095376164 | AQ106: =+IF(AM105<0,1-AQ105/AM105,AQ105/AM105-1) -> 0.04312923 | AR106: =+IF(AN105<0,1-AR105/AN105,AR105/AN105-1) -> -0.033133849 | AS106: =+IF(AO105<0,1-AS105/AO105,AS105/AO105-1) -> 0.094712182 | AT106: =+IF(AP105<0,1-AT105/AP105,AT105/AP105-1) -> -0.043522267 | AU106: =+IF(AQ105<0,1-AU105/AQ105,AU105/AQ105-1) -> -0.14787989 | AV106: =+IF(AR105<0,1-AV105/AR105,AV105/AR105-1) -> -0.16289251 | AW106: =+IF(AS105<0,1-AW105/AS105,AW105/AS105-1) -> 0.067410578 | ... DA106: =+IF(CW105<0,1-DA105/CW105,DA105/CW105-1) -> 0.13730692 | DE106: 0.19608041
A107: Bloomberg Estimate
A108: Estimate deviation
A109: Promoter Share holding % | B109: ='Annual Raw'!C112 -> 0 | C109: ='Annual Raw'!D112 -> 65.38 | D109: ='Annual Raw'!E112 -> 66.55 | E109: ='Annual Raw'!F112 -> 66.49 | F109: ='Annual Raw'!G112 -> 66.49 | G109: ='Annual Raw'!H112 -> 66.49 | H109: ='Annual Raw'!I112 -> 66.49 | I109: ='Annual Raw'!J112 -> 66.49 | ... AA109: ='Annual Raw'!AB112 -> 69.8 | AI109: ='QTR Raw'!C49 -> 66.8 | AJ109: ='QTR Raw'!D49 -> 66.8 | AK109: ='QTR Raw'!E49 -> 66.8 | AL109: ='QTR Raw'!F49 -> 66.8 | AM109: ='QTR Raw'!G49 -> 66.8 | AN109: ='QTR Raw'!H49 -> 66.8 | AO109: ='QTR Raw'!I49 -> 66.42 | AP109: ='QTR Raw'!J49 -> 66.42 | ... CL109: ='QTR Raw'!BF49 -> 69.8 | DE109: 69.8
...

Sheet Sheet1
A2: Calendar Year | B2: Quarter | C2: Nuclear (NPCIL) | D2: Non-Nuclear | E2: Total Order Book
A3: 2022 | B3: Q2 (Jun) | C3: ~600 | D3: ~850 | E3: 1450
B4: Q3 (Sep) | C4: ~650 | D4: ~950 | E4: 1600
B5: Q4 (Dec) | C5: ~700 | D5: 1050 | E5: 1750
A6: 2023 | B6: Q1 (Mar) | C6: ~750 | D6: ~1,050 | E6: 1800
B7: Q2 (Jun) | C7: ~750 | D7: 1200 | E7: 1950
B8: Q3 (Sep) | C8: 1020 | D8: 1180 | E8: 2200
B9: Q4 (Dec) | C9: 920 | D9: 1180 | E9: 2100
A10: 2024 | B10: Q1 (Mar) | C10: ~915 | D10: 1235 | E10: 2150
B11: Q2 (Jun) | C11: ~915 | D11: ~1,265 | E11: 2180
B12: Q3 (Sep) | C12: ~920 | D12: ~1,330 | E12: 2250
B13: Q4 (Dec) | C13: ~920 | D13: ~1,380 | E13: 2300
A14: 2025 | B14: Q1 (Mar) | C14: ~1,310 | D14: ~1,140 | E14: 2450
B15: Q2 (Jun) | C15: ~1,313 | D15: ~1,384 | E15: 2697
B16: Q3 (Sep) | C16: 1314 | D16: 1325 | E16: 2639
B17: Q4 (Dec) | C17: ~1,315 | D17: ~1,385 | E17: 2700
B19: 2022 | E19: 2023 | I19: 2024 | M19: 2025
B20: Q2 (Jun) | C20: Q3 (Sep) | D20: Q4 (Dec) | E20: Q1 (Mar) | F20: Q2 (Jun) | G20: Q3 (Sep) | H20: Q4 (Dec) | I20: Q1 (Mar) | J20: Q2 (Jun) | K20: Q3 (Sep) | L20: Q4 (Dec) | M20: Q1 (Mar) | N20: Q2 (Jun) | O20: Q3 (Sep) | P20: Q4 (Dec)
A21: Nuclear (NPCIL) | B21: ~600 | C21: ~650 | D21: ~700 | E21: ~750 | F21: ~750 | G21: 1020 | H21: 920 | I21: ~915 | J21: ~915 | K21: ~920 | L21: ~920 | M21: ~1,310 | N21: ~1,313 | O21: 1314 | P21: ~1,315
A22: Non-Nuclear | B22: ~850 | C22: ~950 | D22: 1050 | E22: ~1,050 | F22: 1200 | G22: 1180 | H22: 1180 | I22: 1235 | J22: ~1,265 | K22: ~1,330 | L22: ~1,380 | M22: ~1,140 | N22: ~1,384 | O22: 1325 | P22: ~1,385
B23: 1450 | C23: 1600 | D23: 1750 | E23: 1800 | F23: 1950 | G23: 2200 | H23: 2100 | I23: 2150 | J23: 2180 | K23: 2250 | L23: 2300 | M23: 2450 | N23: 2697 | O23: 2639 | P23: 2700
B25: 600 | C25: 650 | D25: 700 | E25: 750 | F25: 750 | G25: 1020 | H25: 920 | I25: 915 | J25: 915 | K25: 920 | L25: 920 | M25: 1310 | N25: 1313 | O25: 1314 | P25: 1315
B26: 850 | C26: 950 | D26: 1050 | E26: 1050 | F26: 1200 | G26: 1180 | H26: 1180 | I26: 1235 | J26: 1265 | K26: 1330 | L26: 1380 | M26: 1140 | N26: 1384 | O26: 1325 | P26: 1385

Sheet QTR Raw
A1: ='Annual Raw'!A1 -> 100249 | B1: X | C1: 201206 | D1: 201209 | E1: 201212 | F1: 201303 | G1: 201306 | H1: 201309 | I1: 201312 | J1: 201403 | K1: 201406 | L1: 201409 | M1: 201412 | N1: 201503 | O1: 201506 | P1: 201509 | Q1: 201512 | R1: 201603 | S1: 201606 | T1: 201609 | U1: 201612 | V1: 201703 | W1: 201706 | X1: 201709 | Y1: 201712 | Z1: 201803 | AA1: 201806 | AB1: 201809 | AC1: 201812 | AD1: 201903 | AE1: 201906 | AF1: 201909 | AG1: 201912 | AH1: 202003 | AI1: 202006 | AJ1: 202009 | AK1: 202012 | AL1: 202103 | AM1: 202106 | AN1: 202109 | AO1: 202112 | AP1: 202203 | AQ1: 202206 | AR1: 202209 | AS1: 202212 | AT1: 202303 | AU1: 202306 | AV1: 202309 | AW1: 202312 | AX1: 202403 | AY1: 202406 | AZ1: 202409 | BA1: 202412 | BB1: 202503 | BC1: 202506 | BD1: 202509 | BE1: 202512 | BF1: 202603 | BG1: 202606 | BH1: 202609 | BI1: 202612 | BJ1: 202703 | BK1: 202706 | BL1: 202709 | BM1: 202712 | BN1: 202803 | BO1: 202806 | BP1: 202809 | BQ1: 202812 | BR1: 202903 | BS1: 202906 | BT1: 202909 | BU1: 202912
A3: Field Description | B3: Field Name
A4: Company Name | B4: CD_COMPNAME | C4: =_xll.EQNXTDZ(A1,B4,C1) -> KSB Ltd.
A5: Date End | B5: QTR_DATE_END | C5: =_xll.EQNXTDZ($A$1,$B5,C$1,$B$1) -> 201206 | D5: =_xll.EQNXTDZ($A$1,$B5,D$1,$B$1) -> 201209 | E5: =_xll.EQNXTDZ($A$1,$B5,E$1,$B$1) -> 201212 | F5: =_xll.EQNXTDZ($A$1,$B5,F$1,$B$1) -> 201303 | G5: =_xll.EQNXTDZ($A$1,$B5,G$1,$B$1) -> 201306 | H5: =_xll.EQNXTDZ($A$1,$B5,H$1,$B$1) -> 201309 | I5: =_xll.EQNXTDZ($A$1,$B5,I$1,$B$1) -> 201312 | J5: =_xll.EQNXTDZ($A$1,$B5,J$1,$B$1) -> 201403 | ... BU5: =_xll.EQNXTDZ($A$1,$B5,BU$1,$B$1) -> 0
A6: Gross Sales | B6: QTR_GROSS_SALE | C6: =_xll.EQNXTDZ($A$1,$B6,C$1,$B$1) -> 186.66 | D6: =_xll.EQNXTDZ($A$1,$B6,D$1,$B$1) -> 168.72 | E6: =_xll.EQNXTDZ($A$1,$B6,E$1,$B$1) -> 193.77 | F6: =_xll.EQNXTDZ($A$1,$B6,F$1,$B$1) -> 162.87 | G6: =_xll.EQNXTDZ($A$1,$B6,G$1,$B$1) -> 194.1 | H6: =_xll.EQNXTDZ($A$1,$B6,H$1,$B$1) -> 188.16 | I6: =_xll.EQNXTDZ($A$1,$B6,I$1,$B$1) -> 179.49 | J6: =_xll.EQNXTDZ($A$1,$B6,J$1,$B$1) -> 171.63 | ... BU6: =_xll.EQNXTDZ($A$1,$B6,BU$1,$B$1) -> 0
A7: Less: Excise Duty | B7: QTR_EXCISE_DUTY | C7: =_xll.EQNXTDZ($A$1,$B7,C$1,$B$1) -> 0 | D7: =_xll.EQNXTDZ($A$1,$B7,D$1,$B$1) -> 0 | E7: =_xll.EQNXTDZ($A$1,$B7,E$1,$B$1) -> 0 | F7: =_xll.EQNXTDZ($A$1,$B7,F$1,$B$1) -> 0 | G7: =_xll.EQNXTDZ($A$1,$B7,G$1,$B$1) -> 0 | H7: =_xll.EQNXTDZ($A$1,$B7,H$1,$B$1) -> 0 | I7: =_xll.EQNXTDZ($A$1,$B7,I$1,$B$1) -> 0 | J7: =_xll.EQNXTDZ($A$1,$B7,J$1,$B$1) -> 0 | ... BU7: =_xll.EQNXTDZ($A$1,$B7,BU$1,$B$1) -> 0
A8: Other operating income | B8: QTR_JOB_WORKS | C8: =_xll.EQNXTDZ($A$1,$B8,C$1,$B$1) -> 0.72 | D8: =_xll.EQNXTDZ($A$1,$B8,D$1,$B$1) -> 1.02 | E8: =_xll.EQNXTDZ($A$1,$B8,E$1,$B$1) -> 0.81 | F8: =_xll.EQNXTDZ($A$1,$B8,F$1,$B$1) -> 0.92 | G8: =_xll.EQNXTDZ($A$1,$B8,G$1,$B$1) -> 1.12 | H8: =_xll.EQNXTDZ($A$1,$B8,H$1,$B$1) -> 2.08 | I8: =_xll.EQNXTDZ($A$1,$B8,I$1,$B$1) -> 2.6 | J8: =_xll.EQNXTDZ($A$1,$B8,J$1,$B$1) -> 1.74 | ... BU8: =_xll.EQNXTDZ($A$1,$B8,BU$1,$B$1) -> 0
A9: Net Sales & Other Operating Income | B9: QTR_NET_SALES | C9: =_xll.EQNXTDZ($A$1,$B9,C$1,$B$1) -> 187.38 | D9: =_xll.EQNXTDZ($A$1,$B9,D$1,$B$1) -> 169.74 | E9: =_xll.EQNXTDZ($A$1,$B9,E$1,$B$1) -> 194.58 | F9: =_xll.EQNXTDZ($A$1,$B9,F$1,$B$1) -> 163.79 | G9: =_xll.EQNXTDZ($A$1,$B9,G$1,$B$1) -> 195.22 | H9: =_xll.EQNXTDZ($A$1,$B9,H$1,$B$1) -> 190.24 | I9: =_xll.EQNXTDZ($A$1,$B9,I$1,$B$1) -> 182.09 | J9: =_xll.EQNXTDZ($A$1,$B9,J$1,$B$1) -> 173.37 | ... BU9: =_xll.EQNXTDZ($A$1,$B9,BU$1,$B$1) -> 0
A10: (Increase) / Decrease In Stocks | B10: QTR_INC_DEC_INVENTORY | C10: =_xll.EQNXTDZ($A$1,$B10,C$1,$B$1) -> 8.28 | D10: =_xll.EQNXTDZ($A$1,$B10,D$1,$B$1) -> -7.8 | E10: =_xll.EQNXTDZ($A$1,$B10,E$1,$B$1) -> 8.8 | F10: =_xll.EQNXTDZ($A$1,$B10,F$1,$B$1) -> -21.35 | G10: =_xll.EQNXTDZ($A$1,$B10,G$1,$B$1) -> 11.93 | H10: =_xll.EQNXTDZ($A$1,$B10,H$1,$B$1) -> 6 | I10: =_xll.EQNXTDZ($A$1,$B10,I$1,$B$1) -> 7.68 | J10: =_xll.EQNXTDZ($A$1,$B10,J$1,$B$1) -> -17.34 | ... BU10: =_xll.EQNXTDZ($A$1,$B10,BU$1,$B$1) -> 0
A11: Cost of Services & Raw Materials | B11: QTR_RAW_MATERIAL_COST | C11: =_xll.EQNXTDZ($A$1,$B11,C$1,$B$1) -> 91.95 | D11: =_xll.EQNXTDZ($A$1,$B11,D$1,$B$1) -> 87.13 | E11: =_xll.EQNXTDZ($A$1,$B11,E$1,$B$1) -> 82.97 | F11: =_xll.EQNXTDZ($A$1,$B11,F$1,$B$1) -> 91.88 | G11: =_xll.EQNXTDZ($A$1,$B11,G$1,$B$1) -> 85.09 | H11: =_xll.EQNXTDZ($A$1,$B11,H$1,$B$1) -> 77.48 | I11: =_xll.EQNXTDZ($A$1,$B11,I$1,$B$1) -> 73.57 | J11: =_xll.EQNXTDZ($A$1,$B11,J$1,$B$1) -> 86.74 | ... BU11: =_xll.EQNXTDZ($A$1,$B11,BU$1,$B$1) -> 0
A12: Purchase of Finished Goods | B12: QTR_PURCHASE_FIN_GOOD | C12: =_xll.EQNXTDZ($A$1,$B12,C$1,$B$1) -> 1.88 | D12: =_xll.EQNXTDZ($A$1,$B12,D$1,$B$1) -> 2.26 | E12: =_xll.EQNXTDZ($A$1,$B12,E$1,$B$1) -> 4.23 | F12: =_xll.EQNXTDZ($A$1,$B12,F$1,$B$1) -> 1.71 | G12: =_xll.EQNXTDZ($A$1,$B12,G$1,$B$1) -> 0.31 | H12: =_xll.EQNXTDZ($A$1,$B12,H$1,$B$1) -> 2.52 | I12: =_xll.EQNXTDZ($A$1,$B12,I$1,$B$1) -> 7.51 | J12: =_xll.EQNXTDZ($A$1,$B12,J$1,$B$1) -> 8.42 | ... BU12: =_xll.EQNXTDZ($A$1,$B12,BU$1,$B$1) -> 0
A13: Excise Duty | B13: QTR_EXCISE | C13: =_xll.EQNXTDZ($A$1,$B13,C$1,$B$1) -> 0 | D13: =_xll.EQNXTDZ($A$1,$B13,D$1,$B$1) -> 0 | E13: =_xll.EQNXTDZ($A$1,$B13,E$1,$B$1) -> 0 | F13: =_xll.EQNXTDZ($A$1,$B13,F$1,$B$1) -> 0 | G13: =_xll.EQNXTDZ($A$1,$B13,G$1,$B$1) -> 0 | H13: =_xll.EQNXTDZ($A$1,$B13,H$1,$B$1) -> 0 | I13: =_xll.EQNXTDZ($A$1,$B13,I$1,$B$1) -> 0 | J13: =_xll.EQNXTDZ($A$1,$B13,J$1,$B$1) -> 0 | ... BU13: =_xll.EQNXTDZ($A$1,$B13,BU$1,$B$1) -> 0
A14: Operating & Manufacturing Expenses | B14: QTR_MFG_EXPS | C14: =_xll.EQNXTDZ($A$1,$B14,C$1,$B$1) -> 34.83 | D14: =_xll.EQNXTDZ($A$1,$B14,D$1,$B$1) -> 40.74 | E14: =_xll.EQNXTDZ($A$1,$B14,E$1,$B$1) -> 44.25 | F14: =_xll.EQNXTDZ($A$1,$B14,F$1,$B$1) -> 41.57 | G14: =_xll.EQNXTDZ($A$1,$B14,G$1,$B$1) -> 42.57 | H14: =_xll.EQNXTDZ($A$1,$B14,H$1,$B$1) -> 46.26 | I14: =_xll.EQNXTDZ($A$1,$B14,I$1,$B$1) -> 45.98 | J14: =_xll.EQNXTDZ($A$1,$B14,J$1,$B$1) -> 39.34 | ... BU14: =_xll.EQNXTDZ($A$1,$B14,BU$1,$B$1) -> 0
A15: Electricity Power & Fuel Cost | B15: QTR_ELECTRICITY_POWER_FUEL | C15: =_xll.EQNXTDZ($A$1,$B15,C$1,$B$1) -> 0 | D15: =_xll.EQNXTDZ($A$1,$B15,D$1,$B$1) -> 0 | E15: =_xll.EQNXTDZ($A$1,$B15,E$1,$B$1) -> 0 | F15: =_xll.EQNXTDZ($A$1,$B15,F$1,$B$1) -> 0 | G15: =_xll.EQNXTDZ($A$1,$B15,G$1,$B$1) -> 0 | H15: =_xll.EQNXTDZ($A$1,$B15,H$1,$B$1) -> 0 | I15: =_xll.EQNXTDZ($A$1,$B15,I$1,$B$1) -> 0 | J15: =_xll.EQNXTDZ($A$1,$B15,J$1,$B$1) -> 0 | ... BU15: =_xll.EQNXTDZ($A$1,$B15,BU$1,$B$1) -> 0
A16: Employee Cost | B16: QTR_EXPLOYEE_COST | C16: =_xll.EQNXTDZ($A$1,$B16,C$1,$B$1) -> 25.72 | D16: =_xll.EQNXTDZ($A$1,$B16,D$1,$B$1) -> 24.68 | E16: =_xll.EQNXTDZ($A$1,$B16,E$1,$B$1) -> 24.42 | F16: =_xll.EQNXTDZ($A$1,$B16,F$1,$B$1) -> 28.26 | G16: =_xll.EQNXTDZ($A$1,$B16,G$1,$B$1) -> 28.39 | H16: =_xll.EQNXTDZ($A$1,$B16,H$1,$B$1) -> 27.78 | I16: =_xll.EQNXTDZ($A$1,$B16,I$1,$B$1) -> 25.63 | J16: =_xll.EQNXTDZ($A$1,$B16,J$1,$B$1) -> 31.08 | ... BU16: =_xll.EQNXTDZ($A$1,$B16,BU$1,$B$1) -> 0
... A42: Consolidated PAT(after extra items) | B42: QTR_CONS_PAT_EXITM | C42: =_xll.EQNXTDZ($A$1,$B42,C$1,$B$1) -> 17.46 | D42: =_xll.EQNXTDZ($A$1,$B42,D$1,$B$1) -> 12.92 | E42: =_xll.EQNXTDZ($A$1,$B42,E$1,$B$1) -> 19.54 | F42: =_xll.EQNXTDZ($A$1,$B42,F$1,$B$1) -> 15.61 | G42: =_xll.EQNXTDZ($A$1,$B42,G$1,$B$1) -> 15.46 | H42: =_xll.EQNXTDZ($A$1,$B42,H$1,$B$1) -> 17.9 | I42: =_xll.EQNXTDZ($A$1,$B42,I$1,$B$1) -> 10.79 | J42: =_xll.EQNXTDZ($A$1,$B42,J$1,$B$1) -> 15.13 | ... BU42: =_xll.EQNXTDZ($A$1,$B42,BU$1,$B$1) -> 0
A44: Field Description | B44: Field Name
A45: Equity Capital | B45: QTR_EQUITY_CAP | C45: =_xll.EQNXTDZ($A$1,$B45,C$1,$B$1) -> 34.81 | D45: =_xll.EQNXTDZ($A$1,$B45,D$1,$B$1) -> 34.81 | E45: =_xll.EQNXTDZ($A$1,$B45,E$1,$B$1) -> 34.81 | F45: =_xll.EQNXTDZ($A$1,$B45,F$1,$B$1) -> 34.81 | G45: =_xll.EQNXTDZ($A$1,$B45,G$1,$B$1) -> 34.81 | H45: =_xll.EQNXTDZ($A$1,$B45,H$1,$B$1) -> 34.81 | I45: =_xll.EQNXTDZ($A$1,$B45,I$1,$B$1) -> 34.81 | J45: =_xll.EQNXTDZ($A$1,$B45,J$1,$B$1) -> 34.81 | ... BU45: =_xll.EQNXTDZ($A$1,$B45,BU$1,$B$1) -> 0
A46: Face Value | B46: QTR_FV | C46: =_xll.EQNXTDZ($A$1,$B46,C$1,$B$1) -> 10 | D46: =_xll.EQNXTDZ($A$1,$B46,D$1,$B$1) -> 10 | E46: =_xll.EQNXTDZ($A$1,$B46,E$1,$B$1) -> 10 | F46: =_xll.EQNXTDZ($A$1,$B46,F$1,$B$1) -> 10 | G46: =_xll.EQNXTDZ($A$1,$B46,G$1,$B$1) -> 10 | H46: =_xll.EQNXTDZ($A$1,$B46,H$1,$B$1) -> 10 | I46: =_xll.EQNXTDZ($A$1,$B46,I$1,$B$1) -> 10 | J46: =_xll.EQNXTDZ($A$1,$B46,J$1,$B$1) -> 10 | ... BU46: =_xll.EQNXTDZ($A$1,$B46,BU$1,$B$1) -> 0
A47: Month End | B47: BMONTH_MONTHEND | C47: =_xll.EQNXTDZ($A$1,$B47,C$5) -> 201206 | D47: =_xll.EQNXTDZ($A$1,$B47,D$5) -> 201209 | E47: =_xll.EQNXTDZ($A$1,$B47,E$5) -> 201212 | F47: =_xll.EQNXTDZ($A$1,$B47,F$5) -> 201303 | G47: =_xll.EQNXTDZ($A$1,$B47,G$5) -> 201306 | H47: =_xll.EQNXTDZ($A$1,$B47,H$5) -> 201309 | I47: =_xll.EQNXTDZ($A$1,$B47,I$5) -> 201312 | J47: =_xll.EQNXTDZ($A$1,$B47,J$5) -> 201403 | ... BU47: =_xll.EQNXTDZ($A$1,$B47,BU$5) -> 0
A48: Close | B48: BMONTH_CLOSE | C48: =_xll.EQNXTDZ($A$1,$B48,C$5) -> 36.88 | D48: =_xll.EQNXTDZ($A$1,$B48,D$5) -> 41.19 | E48: =_xll.EQNXTDZ($A$1,$B48,E$5) -> 44.32 | F48: =_xll.EQNXTDZ($A$1,$B48,F$5) -> 40.66 | G48: =_xll.EQNXTDZ($A$1,$B48,G$5) -> 41.64 | H48: =_xll.EQNXTDZ($A$1,$B48,H$5) -> 42.91 | I48: =_xll.EQNXTDZ($A$1,$B48,I$5) -> 53.6 | J48: =_xll.EQNXTDZ($A$1,$B48,J$5) -> 64.96 | ... BU48: =_xll.EQNXTDZ($A$1,$B48,BU$5) -> 0
A49: Total of Promoter and Promoter Group | B49: SHP_TPFTOTALPROMOTER | C49: =_xll.EQNXTDZ($A$1,$B49,C$5) -> 66.8 | D49: =_xll.EQNXTDZ($A$1,$B49,D$5) -> 66.8 | E49: =_xll.EQNXTDZ($A$1,$B49,E$5) -> 66.8 | F49: =_xll.EQNXTDZ($A$1,$B49,F$5) -> 66.8 | G49: =_xll.EQNXTDZ($A$1,$B49,G$5) -> 66.8 | H49: =_xll.EQNXTDZ($A$1,$B49,H$5) -> 66.8 | I49: =_xll.EQNXTDZ($A$1,$B49,I$5) -> 66.42 | J49: =_xll.EQNXTDZ($A$1,$B49,J$5) -> 66.42 | ... BU49: =_xll.EQNXTDZ($A$1,$B49,BU$5) -> 0
A50: Total of Promoter and Promoter Group Pledged | B50: SHP_PSHFTOTALPROMOTER | C50: =_xll.EQNXTDZ($A$1,$B50,C$5) -> 0 | D50: =_xll.EQNXTDZ($A$1,$B50,D$5) -> 0 | E50: =_xll.EQNXTDZ($A$1,$B50,E$5) -> 0 | F50: =_xll.EQNXTDZ($A$1,$B50,F$5) -> 0 | G50: =_xll.EQNXTDZ($A$1,$B50,G$5) -> 0 | H50: =_xll.EQNXTDZ($A$1,$B50,H$5) -> 0 | I50: =_xll.EQNXTDZ($A$1,$B50,I$5) -> 0 | J50: =_xll.EQNXTDZ($A$1,$B50,J$5) -> 0 | ... BU50: =_xll.EQNXTDZ($A$1,$B50,BU$5) -> 0
A54: Field Description | B54: Field Name | C54: =_xll.EQNXTDZ($A$1,$B54,C$5) -> 0 | D54: =_xll.EQNXTDZ($A$1,$B54,D$5) -> 0 | E54: =_xll.EQNXTDZ($A$1,$B54,E$5) -> 0 | F54: =_xll.EQNXTDZ($A$1,$B54,F$5) -> 0 | G54: =_xll.EQNXTDZ($A$1,$B54,G$5) -> 0 | H54: =_xll.EQNXTDZ($A$1,$B54,H$5) -> 0 | I54: =_xll.EQNXTDZ($A$1,$B54,I$5) -> 0 | J54: =_xll.EQNXTDZ($A$1,$B54,J$5) -> 0 | ... BU54: =_xll.EQNXTDZ($A$1,$B54,BU$5) -> 0
A55: Year End | B55: QTRB_DATE_END | C55: =_xll.EQNXTDZ($A$1,$B55,C$5,$B$1) -> 201206 | D55: =_xll.EQNXTDZ($A$1,$B55,D$5,$B$1) -> 0 | E55: =_xll.EQNXTDZ($A$1,$B55,E$5,$B$1) -> 0 | F55: =_xll.EQNXTDZ($A$1,$B55,F$5,$B$1) -> 0 | G55: =_xll.EQNXTDZ($A$1,$B55,G$5,$B$1) -> 201306 | H55: =_xll.EQNXTDZ($A$1,$B55,H$5,$B$1) -> 0 | I55: =_xll.EQNXTDZ($A$1,$B55,I$5,$B$1) -> 201312 | J55: =_xll.EQNXTDZ($A$1,$B55,J$5,$B$1) -> 0 | ... BU55: =_xll.EQNXTDZ($A$1,$B55,BU$5,$B$1) -> 0
A56: Share Capital | B56: QTRB_SHARE_CAPITAL | C56: =_xll.EQNXTDZ($A$1,$B56,C$5,$B$1) -> 34.81 | D56: =_xll.EQNXTDZ($A$1,$B56,D$5,$B$1) -> 0 | E56: =_xll.EQNXTDZ($A$1,$B56,E$5,$B$1) -> 0 | F56: =_xll.EQNXTDZ($A$1,$B56,F$5,$B$1) -> 0 | G56: =_xll.EQNXTDZ($A$1,$B56,G$5,$B$1) -> 34.81 | H56: =_xll.EQNXTDZ($A$1,$B56,H$5,$B$1) -> 0 | I56: =_xll.EQNXTDZ($A$1,$B56,I$5,$B$1) -> 34.81 | J56: =_xll.EQNXTDZ($A$1,$B56,J$5,$B$1) -> 0 | ... BU56: =_xll.EQNXTDZ($A$1,$B56,BU$5,$B$1) -> 0
A57: Share Warrants & outstandings | B57: QTRB_SHAREWARNDOUT | C57: =_xll.EQNXTDZ($A$1,$B57,C$5,$B$1) -> 0 | D57: =_xll.EQNXTDZ($A$1,$B57,D$5,$B$1) -> 0 | E57: =_xll.EQNXTDZ($A$1,$B57,E$5,$B$1) -> 0 | F57: =_xll.EQNXTDZ($A$1,$B57,F$5,$B$1) -> 0 | G57: =_xll.EQNXTDZ($A$1,$B57,G$5,$B$1) -> 0 | H57: =_xll.EQNXTDZ($A$1,$B57,H$5,$B$1) -> 0 | I57: =_xll.EQNXTDZ($A$1,$B57,I$5,$B$1) -> 0 | J57: =_xll.EQNXTDZ($A$1,$B57,J$5,$B$1) -> 0 | ... BU57: =_xll.EQNXTDZ($A$1,$B57,BU$5,$B$1) -> 0
A58: Reserves & Surplus | B58: QTRB_RESERVE | C58: =_xll.EQNXTDZ($A$1,$B58,C$5,$B$1) -> 380.87 | D58: =_xll.EQNXTDZ($A$1,$B58,D$5,$B$1) -> 0 | E58: =_xll.EQNXTDZ($A$1,$B58,E$5,$B$1) -> 0 | F58: =_xll.EQNXTDZ($A$1,$B58,F$5,$B$1) -> 0 | G58: =_xll.EQNXTDZ($A$1,$B58,G$5,$B$1) -> 422.15 | H58: =_xll.EQNXTDZ($A$1,$B58,H$5,$B$1) -> 0 | I58: =_xll.EQNXTDZ($A$1,$B58,I$5,$B$1) -> 476.96 | J58: =_xll.EQNXTDZ($A$1,$B58,J$5,$B$1) -> 0 | ... BU58: =_xll.EQNXTDZ($A$1,$B58,BU$5,$B$1) -> 0
A59: Shareholder's Funds | B59: QTRB_SHAREHODERS_FUNDS | C59: =_xll.EQNXTDZ($A$1,$B59,C$5,$B$1) -> 415.68 | D59: =_xll.EQNXTDZ($A$1,$B59,D$5,$B$1) -> 0 | E59: =_xll.EQNXTDZ($A$1,$B59,E$5,$B$1) -> 0 | F59: =_xll.EQNXTDZ($A$1,$B59,F$5,$B$1) -> 0 | G59: =_xll.EQNXTDZ($A$1,$B59,G$5,$B$1) -> 456.96 | H59: =_xll.EQNXTDZ($A$1,$B59,H$5,$B$1) -> 0 | I59: =_xll.EQNXTDZ($A$1,$B59,I$5,$B$1) -> 511.77 | J59: =_xll.EQNXTDZ($A$1,$B59,J$5,$B$1) -> 0 | ... BU59: =_xll.EQNXTDZ($A$1,$B59,BU$5,$B$1) -> 0
A60: Minority Interest | B60: QTRB_MINORITY_INTEREST_BS | C60: =_xll.EQNXTDZ($A$1,$B60,C$5,$B$1) -> 0 | D60: =_xll.EQNXTDZ($A$1,$B60,D$5,$B$1) -> 0 | E60: =_xll.EQNXTDZ($A$1,$B60,E$5,$B$1) -> 0 | F60: =_xll.EQNXTDZ($A$1,$B60,F$5,$B$1) -> 0 | G60: =_xll.EQNXTDZ($A$1,$B60,G$5,$B$1) -> 0 | H60: =_xll.EQNXTDZ($A$1,$B60,H$5,$B$1) -> 0 | I60: =_xll.EQNXTDZ($A$1,$B60,I$5,$B$1) -> 0 | J60: =_xll.EQNXTDZ($A$1,$B60,J$5,$B$1) -> 0 | ... BU60: =_xll.EQNXTDZ($A$1,$B60,BU$5,$B$1) -> 0
A61: Long Term Borrowings | B61: QTRB_TOTAL_DEBTS | C61: =_xll.EQNXTDZ($A$1,$B61,C$5,$B$1) -> 0.01 | D61: =_xll.EQNXTDZ($A$1,$B61,D$5,$B$1) -> 0 | E61: =_xll.EQNXTDZ($A$1,$B61,E$5,$B$1) -> 0 | F61: =_xll.EQNXTDZ($A$1,$B61,F$5,$B$1) -> 0 | G61: =_xll.EQNXTDZ($A$1,$B61,G$5,$B$1) -> 0 | H61: =_xll.EQNXTDZ($A$1,$B61,H$5,$B$1) -> 0 | I61: =_xll.EQNXTDZ($A$1,$B61,I$5,$B$1) -> 0 | J61: =_xll.EQNXTDZ($A$1,$B61,J$5,$B$1) -> 0 | ... BU61: =_xll.EQNXTDZ($A$1,$B61,BU$5,$B$1) -> 0
A62: Secured Loans | B62: QTRB_SECURED_LOANS | C62: =_xll.EQNXTDZ($A$1,$B62,C$5,$B$1) -> 0 | D62: =_xll.EQNXTDZ($A$1,$B62,D$5,$B$1) -> 0 | E62: =_xll.EQNXTDZ($A$1,$B62,E$5,$B$1) -> 0 | F62: =_xll.EQNXTDZ($A$1,$B62,F$5,$B$1) -> 0 | G62: =_xll.EQNXTDZ($A$1,$B62,G$5,$B$1) -> 0 | H62: =_xll.EQNXTDZ($A$1,$B62,H$5,$B$1) -> 0 | I62: =_xll.EQNXTDZ($A$1,$B62,I$5,$B$1) -> 0 | J62: =_xll.EQNXTDZ($A$1,$B62,J$5,$B$1) -> 0 | ... BU62: =_xll.EQNXTDZ($A$1,$B62,BU$5,$B$1) -> 0
A63: Unsecured Loans | B63: QTRB_UNSECURED_LOANS_NF | C63: =_xll.EQNXTDZ($A$1,$B63,C$5,$B$1) -> 0.01 | D63: =_xll.EQNXTDZ($A$1,$B63,D$5,$B$1) -> 0 | E63: =_xll.EQNXTDZ($A$1,$B63,E$5,$B$1) -> 0 | F63: =_xll.EQNXTDZ($A$1,$B63,F$5,$B$1) -> 0 | G63: =_xll.EQNXTDZ($A$1,$B63,G$5,$B$1) -> 0 | H63: =_xll.EQNXTDZ($A$1,$B63,H$5,$B$1) -> 0 | I63: =_xll.EQNXTDZ($A$1,$B63,I$5,$B$1) -> 0 | J63: =_xll.EQNXTDZ($A$1,$B63,J$5,$B$1) -> 0 | ... BU63: =_xll.EQNXTDZ($A$1,$B63,BU$5,$B$1) -> 0
A64: Other Long Term Liabilities | B64: QTRB_OTHER_LT_LIABILITIES | C64: =_xll.EQNXTDZ($A$1,$B64,C$5,$B$1) -> 5.4 | D64: =_xll.EQNXTDZ($A$1,$B64,D$5,$B$1) -> 0 | E64: =_xll.EQNXTDZ($A$1,$B64,E$5,$B$1) -> 0 | F64: =_xll.EQNXTDZ($A$1,$B64,F$5,$B$1) -> 0 | G64: =_xll.EQNXTDZ($A$1,$B64,G$5,$B$1) -> 5.79 | H64: =_xll.EQNXTDZ($A$1,$B64,H$5,$B$1) -> 0 | I64: =_xll.EQNXTDZ($A$1,$B64,I$5,$B$1) -> 6.04 | J64: =_xll.EQNXTDZ($A$1,$B64,J$5,$B$1) -> 0 | ... BU64: =_xll.EQNXTDZ($A$1,$B64,BU$5,$B$1) -> 0
A65: Long Term Trade Payables | B65: QTRB_LT_TRADE_PAYABLE | C65: =_xll.EQNXTDZ($A$1,$B65,C$5,$B$1) -> 0 | D65: =_xll.EQNXTDZ($A$1,$B65,D$5,$B$1) -> 0 | E65: =_xll.EQNXTDZ($A$1,$B65,E$5,$B$1) -> 0 | F65: =_xll.EQNXTDZ($A$1,$B65,F$5,$B$1) -> 0 | G65: =_xll.EQNXTDZ($A$1,$B65,G$5,$B$1) -> 0 | H65: =_xll.EQNXTDZ($A$1,$B65,H$5,$B$1) -> 0 | I65: =_xll.EQNXTDZ($A$1,$B65,I$5,$B$1) -> 0 | J65: =_xll.EQNXTDZ($A$1,$B65,J$5,$B$1) -> 0 | ... BU65: =_xll.EQNXTDZ($A$1,$B65,BU$5,$B$1) -> 0
A66: Lont Term Provisions | B66: QTRB_LT_PROVISIONS | C66: =_xll.EQNXTDZ($A$1,$B66,C$5,$B$1) -> 22.05 | D66: =_xll.EQNXTDZ($A$1,$B66,D$5,$B$1) -> 0 | E66: =_xll.EQNXTDZ($A$1,$B66,E$5,$B$1) -> 0 | F66: =_xll.EQNXTDZ($A$1,$B66,F$5,$B$1) -> 0 | G66: =_xll.EQNXTDZ($A$1,$B66,G$5,$B$1) -> 22.96 | H66: =_xll.EQNXTDZ($A$1,$B66,H$5,$B$1) -> 0 | I66: =_xll.EQNXTDZ($A$1,$B66,I$5,$B$1) -> 23.27 | J66: =_xll.EQNXTDZ($A$1,$B66,J$5,$B$1) -> 0 | ... BU66: =_xll.EQNXTDZ($A$1,$B66,BU$5,$B$1) -> 0
... A97: Total Assets | B97: QTRB_TOTAL_APPLICATIONS | C97: =_xll.EQNXTDZ($A$1,$B97,C$5,$B$1) -> 443.14 | D97: =_xll.EQNXTDZ($A$1,$B97,D$5,$B$1) -> 0 | E97: =_xll.EQNXTDZ($A$1,$B97,E$5,$B$1) -> 0 | F97: =_xll.EQNXTDZ($A$1,$B97,F$5,$B$1) -> 0 | G97: =_xll.EQNXTDZ($A$1,$B97,G$5,$B$1) -> 485.71 | H97: =_xll.EQNXTDZ($A$1,$B97,H$5,$B$1) -> 0 | I97: =_xll.EQNXTDZ($A$1,$B97,I$5,$B$1) -> 541.08 | J97: =_xll.EQNXTDZ($A$1,$B97,J$5,$B$1) -> 0 | ... BU97: =_xll.EQNXTDZ($A$1,$B97,BU$5,$B$1) -> 0

Sheet Annual Raw
A1: 100249 | B1: X | C1: 200003 | D1: 200103 | E1: 200212 | F1: 200312 | G1: 200412 | H1: 200512 | I1: 200612 | J1: 200712 | K1: 200812 | L1: 200912 | M1: 201012 | N1: 201112 | O1: 201212 | P1: 201312 | Q1: 201412 | R1: 201512 | S1: 201612 | T1: 201712 | U1: 201812 | V1: 201912 | W1: 202012 | X1: 202112 | Y1: 202212 | Z1: 202312 | AA1: 202412 | AB1: 202512 | AC1: 202612 | AD1: 202712 | AE1: 202812 | AF1: 202912 | AG1: 203012
A3: Field Description | B3: Field Name
A4: Company Name | B4: CD_COMPNAME | C4: =_xll.EQNXTDZ(A1,B4,"L") -> KSB Ltd.
A5: Year End | B5: PL_YEAR_END | C5: =_xll.EQNXTDZ($A$1,$B5,C$1,$B$1) -> 200003 | D5: =_xll.EQNXTDZ($A$1,$B5,D$1,$B$1) -> 200103 | E5: =_xll.EQNXTDZ($A$1,$B5,E$1,$B$1) -> 200212 | F5: =_xll.EQNXTDZ($A$1,$B5,F$1,$B$1) -> 200312 | G5: =_xll.EQNXTDZ($A$1,$B5,G$1,$B$1) -> 200412 | H5: =_xll.EQNXTDZ($A$1,$B5,H$1,$B$1) -> 200512 | I5: =_xll.EQNXTDZ($A$1,$B5,I$1,$B$1) -> 200612 | J5: =_xll.EQNXTDZ($A$1,$B5,J$1,$B$1) -> 200712 | ... AG5: =_xll.EQNXTDZ($A$1,$B5,AG$1,$B$1) -> 0
A6: Sales Turnover | B6: PL_TOTAL_GROSS_SALES | C6: =_xll.EQNXTDZ($A$1,$B6,C$1,$B$1) -> 183.5706 | D6: =_xll.EQNXTDZ($A$1,$B6,D$1,$B$1) -> 208.06 | E6: =_xll.EQNXTDZ($A$1,$B6,E$1,$B$1) -> 246.6743 | F6: =_xll.EQNXTDZ($A$1,$B6,F$1,$B$1) -> 262.837 | G6: =_xll.EQNXTDZ($A$1,$B6,G$1,$B$1) -> 332.4444 | H6: =_xll.EQNXTDZ($A$1,$B6,H$1,$B$1) -> 397.7657 | I6: =_xll.EQNXTDZ($A$1,$B6,I$1,$B$1) -> 453.1451 | J6: =_xll.EQNXTDZ($A$1,$B6,J$1,$B$1) -> 513.1169 | ... AG6: =_xll.EQNXTDZ($A$1,$B6,AG$1,$B$1) -> 0
A7: Less: Inter divisional transfers | B7: PL_INTER_DIV_TRF | C7: =_xll.EQNXTDZ($A$1,$B7,C$1,$B$1) -> 0 | D7: =_xll.EQNXTDZ($A$1,$B7,D$1,$B$1) -> 0 | E7: =_xll.EQNXTDZ($A$1,$B7,E$1,$B$1) -> 0 | F7: =_xll.EQNXTDZ($A$1,$B7,F$1,$B$1) -> 0 | G7: =_xll.EQNXTDZ($A$1,$B7,G$1,$B$1) -> 0 | H7: =_xll.EQNXTDZ($A$1,$B7,H$1,$B$1) -> 0 | I7: =_xll.EQNXTDZ($A$1,$B7,I$1,$B$1) -> 0 | J7: =_xll.EQNXTDZ($A$1,$B7,J$1,$B$1) -> 0 | ... AG7: =_xll.EQNXTDZ($A$1,$B7,AG$1,$B$1) -> 0
A8: Less: Sales Returns | B8: PL_SALES_RETURN | C8: =_xll.EQNXTDZ($A$1,$B8,C$1,$B$1) -> 0 | D8: =_xll.EQNXTDZ($A$1,$B8,D$1,$B$1) -> 0 | E8: =_xll.EQNXTDZ($A$1,$B8,E$1,$B$1) -> 0 | F8: =_xll.EQNXTDZ($A$1,$B8,F$1,$B$1) -> 0 | G8: =_xll.EQNXTDZ($A$1,$B8,G$1,$B$1) -> 0 | H8: =_xll.EQNXTDZ($A$1,$B8,H$1,$B$1) -> 0 | I8: =_xll.EQNXTDZ($A$1,$B8,I$1,$B$1) -> 0 | J8: =_xll.EQNXTDZ($A$1,$B8,J$1,$B$1) -> 0 | ... AG8: =_xll.EQNXTDZ($A$1,$B8,AG$1,$B$1) -> 0
A9: Less: Excise | B9: PL_EXCISE | C9: =_xll.EQNXTDZ($A$1,$B9,C$1,$B$1) -> 0 | D9: =_xll.EQNXTDZ($A$1,$B9,D$1,$B$1) -> 0 | E9: =_xll.EQNXTDZ($A$1,$B9,E$1,$B$1) -> 16.1455 | F9: =_xll.EQNXTDZ($A$1,$B9,F$1,$B$1) -> 19.9915 | G9: =_xll.EQNXTDZ($A$1,$B9,G$1,$B$1) -> 27.8799 | H9: =_xll.EQNXTDZ($A$1,$B9,H$1,$B$1) -> 37.8643 | I9: =_xll.EQNXTDZ($A$1,$B9,I$1,$B$1) -> 45.6415 | J9: =_xll.EQNXTDZ($A$1,$B9,J$1,$B$1) -> 46.6397 | ... AG9: =_xll.EQNXTDZ($A$1,$B9,AG$1,$B$1) -> 0
A10: Net Sales | B10: PL_NET_SALES | C10: =_xll.EQNXTDZ($A$1,$B10,C$1,$B$1) -> 183.5706 | D10: =_xll.EQNXTDZ($A$1,$B10,D$1,$B$1) -> 208.06 | E10: =_xll.EQNXTDZ($A$1,$B10,E$1,$B$1) -> 230.5288 | F10: =_xll.EQNXTDZ($A$1,$B10,F$1,$B$1) -> 242.8455 | G10: =_xll.EQNXTDZ($A$1,$B10,G$1,$B$1) -> 304.5645 | H10: =_xll.EQNXTDZ($A$1,$B10,H$1,$B$1) -> 359.9014 | I10: =_xll.EQNXTDZ($A$1,$B10,I$1,$B$1) -> 407.5036 | J10: =_xll.EQNXTDZ($A$1,$B10,J$1,$B$1) -> 466.4772 | ... AG10: =_xll.EQNXTDZ($A$1,$B10,AG$1,$B$1) -> 0
A11: Increase/Decrease in Stock | B11: PL_INC_DEC_INVENTORY | C11: =_xll.EQNXTDZ($A$1,$B11,C$1,$B$1) -> -4.9865 | D11: =_xll.EQNXTDZ($A$1,$B11,D$1,$B$1) -> -2.3004 | E11: =_xll.EQNXTDZ($A$1,$B11,E$1,$B$1) -> -0.2105 | F11: =_xll.EQNXTDZ($A$1,$B11,F$1,$B$1) -> -5.7236 | G11: =_xll.EQNXTDZ($A$1,$B11,G$1,$B$1) -> -2.9785 | H11: =_xll.EQNXTDZ($A$1,$B11,H$1,$B$1) -> -5.5271 | I11: =_xll.EQNXTDZ($A$1,$B11,I$1,$B$1) -> -1.3516 | J11: =_xll.EQNXTDZ($A$1,$B11,J$1,$B$1) -> -24.511 | ... AG11: =_xll.EQNXTDZ($A$1,$B11,AG$1,$B$1) -> 0
A12: Raw Material Consumed | B12: PL_RAW_MATRS_CONSUMED | C12: =_xll.EQNXTDZ($A$1,$B12,C$1,$B$1) -> 89.8881 | D12: =_xll.EQNXTDZ($A$1,$B12,D$1,$B$1) -> 99.2511 | E12: =_xll.EQNXTDZ($A$1,$B12,E$1,$B$1) -> 101.805 | F12: =_xll.EQNXTDZ($A$1,$B12,F$1,$B$1) -> 106.0585 | G12: =_xll.EQNXTDZ($A$1,$B12,G$1,$B$1) -> 137.6404 | H12: =_xll.EQNXTDZ($A$1,$B12,H$1,$B$1) -> 165.4362 | I12: =_xll.EQNXTDZ($A$1,$B12,I$1,$B$1) -> 175.7443 | J12: =_xll.EQNXTDZ($A$1,$B12,J$1,$B$1) -> 250.9755 | ... AG12: =_xll.EQNXTDZ($A$1,$B12,AG$1,$B$1) -> 0
A13: Power & Fuel Cost | B13: PL_POWER_FUEL | C13: =_xll.EQNXTDZ($A$1,$B13,C$1,$B$1) -> 4.914 | D13: =_xll.EQNXTDZ($A$1,$B13,D$1,$B$1) -> 5.2112 | E13: =_xll.EQNXTDZ($A$1,$B13,E$1,$B$1) -> 7.6916 | F13: =_xll.EQNXTDZ($A$1,$B13,F$1,$B$1) -> 7.4721 | G13: =_xll.EQNXTDZ($A$1,$B13,G$1,$B$1) -> 8.3325 | H13: =_xll.EQNXTDZ($A$1,$B13,H$1,$B$1) -> 8.5092 | I13: =_xll.EQNXTDZ($A$1,$B13,I$1,$B$1) -> 8.9057 | J13: =_xll.EQNXTDZ($A$1,$B13,J$1,$B$1) -> 9.8512 | ... AG13: =_xll.EQNXTDZ($A$1,$B13,AG$1,$B$1) -> 0
A14: Employee Cost | B14: PL_EMPLOYEES | C14: =_xll.EQNXTDZ($A$1,$B14,C$1,$B$1) -> 37.5406 | D14: =_xll.EQNXTDZ($A$1,$B14,D$1,$B$1) -> 31.7845 | E14: =_xll.EQNXTDZ($A$1,$B14,E$1,$B$1) -> 38.63 | F14: =_xll.EQNXTDZ($A$1,$B14,F$1,$B$1) -> 45.9854 | G14: =_xll.EQNXTDZ($A$1,$B14,G$1,$B$1) -> 45.3776 | H14: =_xll.EQNXTDZ($A$1,$B14,H$1,$B$1) -> 48.9709 | I14: =_xll.EQNXTDZ($A$1,$B14,I$1,$B$1) -> 53.2348 | J14: =_xll.EQNXTDZ($A$1,$B14,J$1,$B$1) -> 62.1157 | ... AG14: =_xll.EQNXTDZ($A$1,$B14,AG$1,$B$1) -> 0
A15: Operating & Manufacturing Expenses | B15: PL_GEN_OTHER_MFG_EXPS | C15: =_xll.EQNXTDZ($A$1,$B15,C$1,$B$1) -> 14.9782 | D15: =_xll.EQNXTDZ($A$1,$B15,D$1,$B$1) -> 15.8263 | E15: =_xll.EQNXTDZ($A$1,$B15,E$1,$B$1) -> 19.4585 | F15: =_xll.EQNXTDZ($A$1,$B15,F$1,$B$1) -> 20.8578 | G15: =_xll.EQNXTDZ($A$1,$B15,G$1,$B$1) -> 26.2982 | H15: =_xll.EQNXTDZ($A$1,$B15,H$1,$B$1) -> 31.3784 | I15: =_xll.EQNXTDZ($A$1,$B15,I$1,$B$1) -> 36.23 | J15: =_xll.EQNXTDZ($A$1,$B15,J$1,$B$1) -> 40.3246 | ... AG15: =_xll.EQNXTDZ($A$1,$B15,AG$1,$B$1) -> 0
A16: Cost of Software development | B16: PL_COST_SW | C16: =_xll.EQNXTDZ($A$1,$B16,C$1,$B$1) -> 0 | D16: =_xll.EQNXTDZ($A$1,$B16,D$1,$B$1) -> 0 | E16: =_xll.EQNXTDZ($A$1,$B16,E$1,$B$1) -> 0 | F16: =_xll.EQNXTDZ($A$1,$B16,F$1,$B$1) -> 0 | G16: =_xll.EQNXTDZ($A$1,$B16,G$1,$B$1) -> 0 | H16: =_xll.EQNXTDZ($A$1,$B16,H$1,$B$1) -> 0 | I16: =_xll.EQNXTDZ($A$1,$B16,I$1,$B$1) -> 0 | J16: =_xll.EQNXTDZ($A$1,$B16,J$1,$B$1) -> 0 | ... AG16: =_xll.EQNXTDZ($A$1,$B16,AG$1,$B$1) -> 0
... A36: Profit After Tax from Discontinued Operations | B36: PL_PAT_DIS_OP | C36: =_xll.EQNXTDZ($A$1,$B36,C$1,$B$1) -> 0 | D36: =_xll.EQNXTDZ($A$1,$B36,D$1,$B$1) -> 0 | E36: =_xll.EQNXTDZ($A$1,$B36,E$1,$B$1) -> 0 | F36: =_xll.EQNXTDZ($A$1,$B36,F$1,$B$1) -> 0 | G36: =_xll.EQNXTDZ($A$1,$B36,G$1,$B$1) -> 0 | H36: =_xll.EQNXTDZ($A$1,$B36,H$1,$B$1) -> 0 | I36: =_xll.EQNXTDZ($A$1,$B36,I$1,$B$1) -> 0 | J36: =_xll.EQNXTDZ($A$1,$B36,J$1,$B$1) -> 0 | ... AG36: =_xll.EQNXTDZ($A$1,$B36,AG$1,$B$1) -> 0
A39: Field Description | B39: Field Name
A40: Year End | B40: BS_YEAR_END | C40: =_xll.EQNXTDZ($A$1,$B40,C$1,$B$1) -> 200003 | D40: =_xll.EQNXTDZ($A$1,$B40,D$1,$B$1) -> 200103 | E40: =_xll.EQNXTDZ($A$1,$B40,E$1,$B$1) -> 200212 | F40: =_xll.EQNXTDZ($A$1,$B40,F$1,$B$1) -> 200312 | G40: =_xll.EQNXTDZ($A$1,$B40,G$1,$B$1) -> 200412 | H40: =_xll.EQNXTDZ($A$1,$B40,H$1,$B$1) -> 200512 | I40: =_xll.EQNXTDZ($A$1,$B40,I$1,$B$1) -> 200612 | J40: =_xll.EQNXTDZ($A$1,$B40,J$1,$B$1) -> 200712 | ... AG40: =_xll.EQNXTDZ($A$1,$B40,AG$1,$B$1) -> 0
A41: Share Capital | B41: BS_SHARE_CAPITAL | C41: =_xll.EQNXTDZ($A$1,$B41,C$1,$B$1) -> 17.403 | D41: =_xll.EQNXTDZ($A$1,$B41,D$1,$B$1) -> 17.403 | E41: =_xll.EQNXTDZ($A$1,$B41,E$1,$B$1) -> 17.4039 | F41: =_xll.EQNXTDZ($A$1,$B41,F$1,$B$1) -> 17.4039 | G41: =_xll.EQNXTDZ($A$1,$B41,G$1,$B$1) -> 17.4039 | H41: =_xll.EQNXTDZ($A$1,$B41,H$1,$B$1) -> 17.4039 | I41: =_xll.EQNXTDZ($A$1,$B41,I$1,$B$1) -> 17.4039 | J41: =_xll.EQNXTDZ($A$1,$B41,J$1,$B$1) -> 17.4039 | ... AG41: =_xll.EQNXTDZ($A$1,$B41,AG$1,$B$1) -> 0
A42: Share Warrants & Outstandings | B42: BS_SHAREWROUTST | C42: =_xll.EQNXTDZ($A$1,$B42,C$1,$B$1) -> 0 | D42: =_xll.EQNXTDZ($A$1,$B42,D$1,$B$1) -> 0 | E42: =_xll.EQNXTDZ($A$1,$B42,E$1,$B$1) -> 0 | F42: =_xll.EQNXTDZ($A$1,$B42,F$1,$B$1) -> 0 | G42: =_xll.EQNXTDZ($A$1,$B42,G$1,$B$1) -> 0 | H42: =_xll.EQNXTDZ($A$1,$B42,H$1,$B$1) -> 0 | I42: =_xll.EQNXTDZ($A$1,$B42,I$1,$B$1) -> 0 | J42: =_xll.EQNXTDZ($A$1,$B42,J$1,$B$1) -> 0 | ... AG42: =_xll.EQNXTDZ($A$1,$B42,AG$1,$B$1) -> 0
A43: Total Reserves | B43: BS_RESERVE | C43: =_xll.EQNXTDZ($A$1,$B43,C$1,$B$1) -> 74.4565 | D43: =_xll.EQNXTDZ($A$1,$B43,D$1,$B$1) -> 76.6793 | E43: =_xll.EQNXTDZ($A$1,$B43,E$1,$B$1) -> 82.1553 | F43: =_xll.EQNXTDZ($A$1,$B43,F$1,$B$1) -> 95.5454 | G43: =_xll.EQNXTDZ($A$1,$B43,G$1,$B$1) -> 116.1537 | H43: =_xll.EQNXTDZ($A$1,$B43,H$1,$B$1) -> 149.168 | I43: =_xll.EQNXTDZ($A$1,$B43,I$1,$B$1) -> 192.6471 | J43: =_xll.EQNXTDZ($A$1,$B43,J$1,$B$1) -> 232.3169 | ... AG43: =_xll.EQNXTDZ($A$1,$B43,AG$1,$B$1) -> 0
A44: Shareholder's Funds | B44: BS_SHAREHODERS_FUNDS | C44: =_xll.EQNXTDZ($A$1,$B44,C$1,$B$1) -> 91.8595 | D44: =_xll.EQNXTDZ($A$1,$B44,D$1,$B$1) -> 94.0823 | E44: =_xll.EQNXTDZ($A$1,$B44,E$1,$B$1) -> 99.5592 | F44: =_xll.EQNXTDZ($A$1,$B44,F$1,$B$1) -> 112.9493 | G44: =_xll.EQNXTDZ($A$1,$B44,G$1,$B$1) -> 133.5576 | H44: =_xll.EQNXTDZ($A$1,$B44,H$1,$B$1) -> 166.5719 | I44: =_xll.EQNXTDZ($A$1,$B44,I$1,$B$1) -> 210.051 | J44: =_xll.EQNXTDZ($A$1,$B44,J$1,$B$1) -> 249.7208 | ... AG44: =_xll.EQNXTDZ($A$1,$B44,AG$1,$B$1) -> 0
A45: Minority Interest | B45: BS_MINORITY_INTEREST | C45: =_xll.EQNXTDZ($A$1,$B45,C$1,$B$1) -> 0 | D45: =_xll.EQNXTDZ($A$1,$B45,D$1,$B$1) -> 0 | E45: =_xll.EQNXTDZ($A$1,$B45,E$1,$B$1) -> 0.3759 | F45: =_xll.EQNXTDZ($A$1,$B45,F$1,$B$1) -> 0 | G45: =_xll.EQNXTDZ($A$1,$B45,G$1,$B$1) -> 0 | H45: =_xll.EQNXTDZ($A$1,$B45,H$1,$B$1) -> 0 | I45: =_xll.EQNXTDZ($A$1,$B45,I$1,$B$1) -> 0 | J45: =_xll.EQNXTDZ($A$1,$B45,J$1,$B$1) -> 0 | ... AG45: =_xll.EQNXTDZ($A$1,$B45,AG$1,$B$1) -> 0
A46: Long-Term Borrowings | B46: BS_LTRM_BORROWING | C46: =_xll.EQNXTDZ($A$1,$B46,C$1,$B$1) -> 0 | D46: =_xll.EQNXTDZ($A$1,$B46,D$1,$B$1) -> 0 | E46: =_xll.EQNXTDZ($A$1,$B46,E$1,$B$1) -> 0 | F46: =_xll.EQNXTDZ($A$1,$B46,F$1,$B$1) -> 0 | G46: =_xll.EQNXTDZ($A$1,$B46,G$1,$B$1) -> 0 | H46: =_xll.EQNXTDZ($A$1,$B46,H$1,$B$1) -> 0 | I46: =_xll.EQNXTDZ($A$1,$B46,I$1,$B$1) -> 0 | J46: =_xll.EQNXTDZ($A$1,$B46,J$1,$B$1) -> 0 | ... AG46: =_xll.EQNXTDZ($A$1,$B46,AG$1,$B$1) -> 0
A47: Secured Loans | B47: BS_SECURED_LOANS | C47: =_xll.EQNXTDZ($A$1,$B47,C$1,$B$1) -> 20.6329 | D47: =_xll.EQNXTDZ($A$1,$B47,D$1,$B$1) -> 19.8949 | E47: =_xll.EQNXTDZ($A$1,$B47,E$1,$B$1) -> 10.8991 | F47: =_xll.EQNXTDZ($A$1,$B47,F$1,$B$1) -> 6.545 | G47: =_xll.EQNXTDZ($A$1,$B47,G$1,$B$1) -> 4.5416 | H47: =_xll.EQNXTDZ($A$1,$B47,H$1,$B$1) -> 9.8549 | I47: =_xll.EQNXTDZ($A$1,$B47,I$1,$B$1) -> 10.0336 | J47: =_xll.EQNXTDZ($A$1,$B47,J$1,$B$1) -> 24.215 | ... AG47: =_xll.EQNXTDZ($A$1,$B47,AG$1,$B$1) -> 0
A48: Unsecured Loans | B48: BS_UNSECURED_LOANS_NF | C48: =_xll.EQNXTDZ($A$1,$B48,C$1,$B$1) -> 20.9201 | D48: =_xll.EQNXTDZ($A$1,$B48,D$1,$B$1) -> 26.5731 | E48: =_xll.EQNXTDZ($A$1,$B48,E$1,$B$1) -> 17.5067 | F48: =_xll.EQNXTDZ($A$1,$B48,F$1,$B$1) -> 6.2016 | G48: =_xll.EQNXTDZ($A$1,$B48,G$1,$B$1) -> 3.1373 | H48: =_xll.EQNXTDZ($A$1,$B48,H$1,$B$1) -> 1.4473 | I48: =_xll.EQNXTDZ($A$1,$B48,I$1,$B$1) -> 0.9172 | J48: =_xll.EQNXTDZ($A$1,$B48,J$1,$B$1) -> 0.8973 | ... AG48: =_xll.EQNXTDZ($A$1,$B48,AG$1,$B$1) -> 0
A49: Deferred Tax Assets / Liabilities | B49: BS_NET_DEF_TAX_NF | C49: =_xll.EQNXTDZ($A$1,$B49,C$1,$B$1) -> 0 | D49: =_xll.EQNXTDZ($A$1,$B49,D$1,$B$1) -> 0 | E49: =_xll.EQNXTDZ($A$1,$B49,E$1,$B$1) -> 5.1152 | F49: =_xll.EQNXTDZ($A$1,$B49,F$1,$B$1) -> 2.4358 | G49: =_xll.EQNXTDZ($A$1,$B49,G$1,$B$1) -> 1.0205 | H49: =_xll.EQNXTDZ($A$1,$B49,H$1,$B$1) -> 0 | I49: =_xll.EQNXTDZ($A$1,$B49,I$1,$B$1) -> -0.0003 | J49: =_xll.EQNXTDZ($A$1,$B49,J$1,$B$1) -> -1.0473 | ... AG49: =_xll.EQNXTDZ($A$1,$B49,AG$1,$B$1) -> 0
A50: Other Long Term Liabilities | B50: BS_OTH_LT_LIAB | C50: =_xll.EQNXTDZ($A$1,$B50,C$1,$B$1) -> 0 | D50: =_xll.EQNXTDZ($A$1,$B50,D$1,$B$1) -> 0 | E50: =_xll.EQNXTDZ($A$1,$B50,E$1,$B$1) -> 0 | F50: =_xll.EQNXTDZ($A$1,$B50,F$1,$B$1) -> 0 | G50: =_xll.EQNXTDZ($A$1,$B50,G$1,$B$1) -> 0 | H50: =_xll.EQNXTDZ($A$1,$B50,H$1,$B$1) -> 0 | I50: =_xll.EQNXTDZ($A$1,$B50,I$1,$B$1) -> 0 | J50: =_xll.EQNXTDZ($A$1,$B50,J$1,$B$1) -> 0 | ... AG50: =_xll.EQNXTDZ($A$1,$B50,AG$1,$B$1) -> 0
A51: Long Term Trade Payables | B51: BS_LT_TRADE_PAYABLES | C51: =_xll.EQNXTDZ($A$1,$B51,C$1,$B$1) -> 0 | D51: =_xll.EQNXTDZ($A$1,$B51,D$1,$B$1) -> 0 | E51: =_xll.EQNXTDZ($A$1,$B51,E$1,$B$1) -> 0 | F51: =_xll.EQNXTDZ($A$1,$B51,F$1,$B$1) -> 0 | G51: =_xll.EQNXTDZ($A$1,$B51,G$1,$B$1) -> 0 | H51: =_xll.EQNXTDZ($A$1,$B51,H$1,$B$1) -> 0 | I51: =_xll.EQNXTDZ($A$1,$B51,I$1,$B$1) -> 0 | J51: =_xll.EQNXTDZ($A$1,$B51,J$1,$B$1) -> 0 | ... AG51: =_xll.EQNXTDZ($A$1,$B51,AG$1,$B$1) -> 0
... A99: Estimated Capital Contracts Remaining | B99: BS_ESTIMATED_CAPITAL_CONTRACT | C99: =_xll.EQNXTDZ($A$1,$B99,C$1,$B$1) -> 0 | D99: =_xll.EQNXTDZ($A$1,$B99,D$1,$B$1) -> 0 | E99: =_xll.EQNXTDZ($A$1,$B99,E$1,$B$1) -> 0 | F99: =_xll.EQNXTDZ($A$1,$B99,F$1,$B$1) -> 0 | G99: =_xll.EQNXTDZ($A$1,$B99,G$1,$B$1) -> 0 | H99: =_xll.EQNXTDZ($A$1,$B99,H$1,$B$1) -> 0 | I99: =_xll.EQNXTDZ($A$1,$B99,I$1,$B$1) -> 0 | J99: =_xll.EQNXTDZ($A$1,$B99,J$1,$B$1) -> 0 | ... AG99: =_xll.EQNXTDZ($A$1,$B99,AG$1,$B$1) -> 0
A103: Field Description | B103: Field Name
A104: Equity Paid Up | B104: BS_EQUITY_PAIDUP | C104: =_xll.EQNXTDZ($A$1,$B104,C$1,$B$1) -> 17.403 | D104: =_xll.EQNXTDZ($A$1,$B104,D$1,$B$1) -> 17.403 | E104: =_xll.EQNXTDZ($A$1,$B104,E$1,$B$1) -> 17.4039 | F104: =_xll.EQNXTDZ($A$1,$B104,F$1,$B$1) -> 17.4039 | G104: =_xll.EQNXTDZ($A$1,$B104,G$1,$B$1) -> 17.4039 | H104: =_xll.EQNXTDZ($A$1,$B104,H$1,$B$1) -> 17.4039 | I104: =_xll.EQNXTDZ($A$1,$B104,I$1,$B$1) -> 17.4039 | J104: =_xll.EQNXTDZ($A$1,$B104,J$1,$B$1) -> 17.4039 | ... AG104: =_xll.EQNXTDZ($A$1,$B104,AG$1,$B$1) -> 0
A105: Face Value | B105: BS_FACE_VALUE | C105: =_xll.EQNXTDZ($A$1,$B105,C$1,$B$1) -> 10 | D105: =_xll.EQNXTDZ($A$1,$B105,D$1,$B$1) -> 10 | E105: =_xll.EQNXTDZ($A$1,$B105,E$1,$B$1) -> 10 | F105: =_xll.EQNXTDZ($A$1,$B105,F$1,$B$1) -> 10 | G105: =_xll.EQNXTDZ($A$1,$B105,G$1,$B$1) -> 10 | H105: =_xll.EQNXTDZ($A$1,$B105,H$1,$B$1) -> 10 | I105: =_xll.EQNXTDZ($A$1,$B105,I$1,$B$1) -> 10 | J105: =_xll.EQNXTDZ($A$1,$B105,J$1,$B$1) -> 10 | ... AG105: =_xll.EQNXTDZ($A$1,$B105,AG$1,$B$1) -> 0
A106: Close Price (Unit Curr.) | B106: FH_YEAR_PRICE | C106: =_xll.EQNXTDZ($A$1,$B106,C$1,$B$1) -> 9.6 | D106: =_xll.EQNXTDZ($A$1,$B106,D$1,$B$1) -> 5.375 | E106: =_xll.EQNXTDZ($A$1,$B106,E$1,$B$1) -> 5.995 | F106: =_xll.EQNXTDZ($A$1,$B106,F$1,$B$1) -> 12.575 | G106: =_xll.EQNXTDZ($A$1,$B106,G$1,$B$1) -> 24.33 | H106: =_xll.EQNXTDZ($A$1,$B106,H$1,$B$1) -> 41.88 | I106: =_xll.EQNXTDZ($A$1,$B106,I$1,$B$1) -> 67.635 | J106: =_xll.EQNXTDZ($A$1,$B106,J$1,$B$1) -> 46.53 | ... AG106: =_xll.EQNXTDZ($A$1,$B106,AG$1,$B$1) -> 0
A107: High Price (Unit Curr.) | B107: FH_HIGH | C107: =_xll.EQNXTDZ($A$1,$B107,C$1,$B$1) -> 25.4 | D107: =_xll.EQNXTDZ($A$1,$B107,D$1,$B$1) -> 10.365 | E107: =_xll.EQNXTDZ($A$1,$B107,E$1,$B$1) -> 9.5 | F107: =_xll.EQNXTDZ($A$1,$B107,F$1,$B$1) -> 16.2 | G107: =_xll.EQNXTDZ($A$1,$B107,G$1,$B$1) -> 24.485 | H107: =_xll.EQNXTDZ($A$1,$B107,H$1,$B$1) -> 45.5 | I107: =_xll.EQNXTDZ($A$1,$B107,I$1,$B$1) -> 68.04 | J107: =_xll.EQNXTDZ($A$1,$B107,J$1,$B$1) -> 67.9 | ... AG107: =_xll.EQNXTDZ($A$1,$B107,AG$1,$B$1) -> 0
A108: Low Price (Unit Curr.) | B108: FH_LOW | C108: =_xll.EQNXTDZ($A$1,$B108,C$1,$B$1) -> 9.5 | D108: =_xll.EQNXTDZ($A$1,$B108,D$1,$B$1) -> 4.9 | E108: =_xll.EQNXTDZ($A$1,$B108,E$1,$B$1) -> 4.44 | F108: =_xll.EQNXTDZ($A$1,$B108,F$1,$B$1) -> 5.75 | G108: =_xll.EQNXTDZ($A$1,$B108,G$1,$B$1) -> 7.7 | H108: =_xll.EQNXTDZ($A$1,$B108,H$1,$B$1) -> 20.125 | I108: =_xll.EQNXTDZ($A$1,$B108,I$1,$B$1) -> 36 | J108: =_xll.EQNXTDZ($A$1,$B108,J$1,$B$1) -> 41.525 | ... AG108: =_xll.EQNXTDZ($A$1,$B108,AG$1,$B$1) -> 0
A109: Market Capitalization | B109: FH_MCAP | C109: =_xll.EQNXTDZ($A$1,$B109,C$1,$B$1) -> 167.0688 | D109: =_xll.EQNXTDZ($A$1,$B109,D$1,$B$1) -> 93.541125 | E109: =_xll.EQNXTDZ($A$1,$B109,E$1,$B$1) -> 104.33638 | F109: =_xll.EQNXTDZ($A$1,$B109,F$1,$B$1) -> 218.85404 | G109: =_xll.EQNXTDZ($A$1,$B109,G$1,$B$1) -> 423.43689 | H109: =_xll.EQNXTDZ($A$1,$B109,H$1,$B$1) -> 728.87533 | I109: =_xll.EQNXTDZ($A$1,$B109,I$1,$B$1) -> 1177.1128 | J109: =_xll.EQNXTDZ($A$1,$B109,J$1,$B$1) -> 809.80347 | ... AG109: =_xll.EQNXTDZ($A$1,$B109,AG$1,$B$1) -> 0
A110: Adj DPS(Rs) | B110: FR_ADJ_DPS | C110: =_xll.EQNXTDZ($A$1,$B110,C$1,$B$1) -> 0.3 | D110: =_xll.EQNXTDZ($A$1,$B110,D$1,$B$1) -> 0.3 | E110: =_xll.EQNXTDZ($A$1,$B110,E$1,$B$1) -> 0.3 | F110: =_xll.EQNXTDZ($A$1,$B110,F$1,$B$1) -> 0.35 | G110: =_xll.EQNXTDZ($A$1,$B110,G$1,$B$1) -> 0.4 | H110: =_xll.EQNXTDZ($A$1,$B110,H$1,$B$1) -> 0.45 | I110: =_xll.EQNXTDZ($A$1,$B110,I$1,$B$1) -> 0.55 | J110: =_xll.EQNXTDZ($A$1,$B110,J$1,$B$1) -> 0.55 | ... AG110: =_xll.EQNXTDZ($A$1,$B110,AG$1,$B$1) -> 0
A111: Date End | B111: SHP_DATE_END | C111: =_xll.EQNXTDZ($A$1,$B111,C$5) -> 0 | D111: =_xll.EQNXTDZ($A$1,$B111,D$5) -> 200103 | E111: =_xll.EQNXTDZ($A$1,$B111,E$5) -> 200212 | F111: =_xll.EQNXTDZ($A$1,$B111,F$5) -> 200312 | G111: =_xll.EQNXTDZ($A$1,$B111,G$5) -> 200412 | H111: =_xll.EQNXTDZ($A$1,$B111,H$5) -> 200512 | I111: =_xll.EQNXTDZ($A$1,$B111,I$5) -> 200612 | J111: =_xll.EQNXTDZ($A$1,$B111,J$5) -> 200712 | ... AG111: =_xll.EQNXTDZ($A$1,$B111,AG$5) -> 0
A112: Total of Promoter and Promoter Group | B112: SHP_TPFTOTALPROMOTER | C112: =_xll.EQNXTDZ($A$1,$B112,C$5) -> 0 | D112: =_xll.EQNXTDZ($A$1,$B112,D$5) -> 65.38 | E112: =_xll.EQNXTDZ($A$1,$B112,E$5) -> 66.55 | F112: =_xll.EQNXTDZ($A$1,$B112,F$5) -> 66.49 | G112: =_xll.EQNXTDZ($A$1,$B112,G$5) -> 66.49 | H112: =_xll.EQNXTDZ($A$1,$B112,H$5) -> 66.49 | I112: =_xll.EQNXTDZ($A$1,$B112,I$5) -> 66.49 | J112: =_xll.EQNXTDZ($A$1,$B112,J$5) -> 66.49 | ... AG112: =_xll.EQNXTDZ($A$1,$B112,AG$5) -> 0
A113: Total of Promoter and Promoter Group Pledged | B113: SHP_PSHFTOTALPROMOTER | C113: =_xll.EQNXTDZ($A$1,$B113,C$5) -> 0 | D113: =_xll.EQNXTDZ($A$1,$B113,D$5) -> 0 | E113: =_xll.EQNXTDZ($A$1,$B113,E$5) -> 0 | F113: =_xll.EQNXTDZ($A$1,$B113,F$5) -> 0 | G113: =_xll.EQNXTDZ($A$1,$B113,G$5) -> 0 | H113: =_xll.EQNXTDZ($A$1,$B113,H$5) -> 0 | I113: =_xll.EQNXTDZ($A$1,$B113,I$5) -> 0 | J113: =_xll.EQNXTDZ($A$1,$B113,J$5) -> 0 | ... AG113: =_xll.EQNXTDZ($A$1,$B113,AG$5) -> 0

Sheet QTR Share Price
A1: ='QTR Raw'!A1 -> 100249 | C1: 201206 | D1: 201207 | E1: 201208 | F1: 201209 | G1: 201210 | H1: 201211 | I1: 201212 | J1: 201301 | K1: 201302 | L1: 201303 | M1: 201304 | N1: 201305 | O1: 201306 | P1: 201307 | Q1: 201308 | R1: 201309 | S1: 201310 | T1: 201311 | U1: 201312 | V1: 201401 | W1: 201402 | X1: 201403 | Y1: 201404 | Z1: 201405 | AA1: 201406 | AB1: 201407 | AC1: 201408 | AD1: 201409 | AE1: 201410 | AF1: 201411 | AG1: 201412 | AH1: 201501 | AI1: 201502 | AJ1: 201503 | AK1: 201504 | AL1: 201505 | AM1: 201506 | AN1: 201507 | AO1: 201508 | AP1: 201509 | AQ1: 201510 | AR1: 201511 | AS1: 201512 | AT1: 201601 | AU1: 201602 | AV1: 201603 | AW1: 201604 | AX1: 201605 | AY1: 201606 | AZ1: 201607 | BA1: 201608 | BB1: 201609 | BC1: 201610 | BD1: 201611 | BE1: 201612 | BF1: 201701 | BG1: 201702 | BH1: 201703 | BI1: 201704 | BJ1: 201705 | BK1: 201706 | BL1: 201707 | BM1: 201708 | BN1: 201709 | BO1: 201710 | BP1: 201711 | BQ1: 201712 | BR1: 201801 | BS1: 201802 | BT1: 201803 | BU1: 201804 | BV1: 201805 | BW1: 201806 | BX1: 201807 | BY1: 201808 | BZ1: 201809 | CA1: 201810 | CB1: 201811 | CC1: 201812 | CD1: 201901 | CE1: 201902 | CF1: 201903 | CG1: 201904 | CH1: 201905 | CI1: 201906 | CJ1: 201907 | CK1: 201908 | CL1: 201909 | CM1: 201910 | CN1: 201911 | CO1: 201912 | CP1: 202001 | CQ1: 202002 | CR1: 202003 | CS1: 202004 | CT1: 202005 | CU1: 202006 | CV1: 202007 | CW1: 202008 | CX1: 202009 | CY1: 202010 | CZ1: 202011 | DA1: 202012 | DB1: 202101 | DC1: 202102 | DD1: 202103 | DE1: 202104 | DF1: 202105 | DG1: 202106 | DH1: 202107 | DI1: 202108 | DJ1: 202109 | DK1: 202110 | DL1: 202111 | DM1: 202112 | DN1: 202201 | DO1: 202202 | DP1: 202203 | DQ1: 202204 | DR1: 202205 | DS1: 202206 | DT1: 202207 | DU1: 202208 | DV1: 202209 | DW1: 202210 | DX1: 202211 | DY1: 202212 | DZ1: 202301 | EA1: 202302 | EB1: 202303 | EC1: 202304 | ED1: 202305 | EE1: 202306 | EF1: 202307 | EG1: 202308 | EH1: 202309 | EI1: 202310 | EJ1: 202311 | EK1: 202312 | EL1: 202401 | EM1: 202402 | EN1: 202403 | EO1: 202404 | EP1: 202405 | EQ1: 202406 | ER1: 202407 | ES1: 202408 | ET1: 202409 | EU1: 202410 | EV1: 202411 | EW1: 202412 | EX1: 202501 | EY1: 202502 | EZ1: 202503 | FA1: 202504 | FB1: 202505 | FC1: 202506 | FD1: 202507 | FE1: 202508 | FF1: 202509 | FG1: 202510 | FH1: 202511 | FI1: 202512 | FJ1: 202601 | FK1: 202602 | FL1: 202603 | FM1: 202604 | FN1: 202605 | FO1: 202606 | FP1: 202607 | FQ1: 202608 | FR1: 202609 | FS1: 202610 | FT1: 202611 | FU1: 202612 | FV1: 202701 | FW1: 202702 | FX1: 202703 | FY1: 202704 | FZ1: 202705 | GA1: 202706 | GB1: 202707 | GC1: 202708 | GD1: 202709 | GE1: 202710 | GF1: 202711 | GG1: 202712 | GH1: 202801 | GI1: 202802 | GJ1: 202803 | GK1: 202804 | GL1: 202805 | GM1: 202806 | GN1: 202807 | GO1: 202808 | GP1: 202809 | GQ1: 202810 | GR1: 202811 | GS1: 202812 | GT1: 202901 | GU1: 202902 | GV1: 202903 | GW1: 202904 | GX1: 202905 | GY1: 202906 | GZ1: 202907 | HA1: 202908 | HB1: 202909 | HC1: 202910 | HD1: 202911 | HE1: 202912 | HF1: 203001 | HG1: 203002 | HH1: 203003 | HM1: 201206 | HN1: 201207 | HO1: 201208 | HP1: 201209 | HQ1: 201212 | HR1: 201303 | HS1: 201306 | HT1: 201309 | HU1: 201312 | HV1: 201403 | HW1: 201406 | HX1: 201409 | HY1: 201412 | HZ1: 201503 | IA1: 201506 | IB1: 201509 | IC1: 201512 | ID1: 201603 | IE1: 201606 | IF1: 201609 | IG1: 201612 | IH1: 201703 | II1: 201706 | IJ1: 201709 | IK1: 201712 | IL1: 201803 | IM1: 201806 | IN1: 201809 | IO1: 201812 | IP1: 201903 | IQ1: 201906 | IR1: 201909 | IS1: 201912 | IT1: 202003 | IU1: 202006 | IV1: 202009 | IW1: 202012 | IX1: 202103 | IY1: 202106 | IZ1: 202109 | JA1: 202112 | JB1: 202203 | JC1: 202206 | JD1: 202209 | JE1: 202212 | JF1: 202303 | JG1: 202306 | JH1: 202309 | JI1: 202312 | JJ1: 202403 | JK1: 202406 | JL1: 202409 | JM1: 202412 | JN1: 202503 | JO1: 202506 | JP1: 202509 | JQ1: 202512 | JR1: 202603 | JS1: 202606 | JT1: 202609 | JU1: 202612 | JV1: 202703 | JW1: 202706 | JX1: 202709 | JY1: 202712 | JZ1: 202803 | KA1: 202806 | KB1: 202809 | KC1: 202812 | KD1: 202903 | KE1: 202906 | KF1: 202909 | KG1: 202912 | KH1: 203003
A4: Field Description | B4: Field Name
A5: MonthEnd | B5: NMONTH_MONTHEND | C5: {=_xll.EQNXTDZ($A$1,$B5,C$1)} -> 201206 | D5: {=_xll.EQNXTDZ($A$1,$B5,D$1)} -> 201207 | E5: {=_xll.EQNXTDZ($A$1,$B5,E$1)} -> 201208 | F5: {=_xll.EQNXTDZ($A$1,$B5,F$1)} -> 201209 | G5: {=_xll.EQNXTDZ($A$1,$B5,G$1)} -> 201210 | H5: {=_xll.EQNXTDZ($A$1,$B5,H$1)} -> 201211 | I5: {=_xll.EQNXTDZ($A$1,$B5,I$1)} -> 201212 | J5: {=_xll.EQNXTDZ($A$1,$B5,J$1)} -> 201301 | ... HH5: {=_xll.EQNXTDZ($A$1,$B5,HH$1)} -> 0
A6: Open | B6: NMONTH_OPEN | C6: {=_xll.EQNXTDZ($A$1,$B6,C$1)} -> 36.08 | D6: {=_xll.EQNXTDZ($A$1,$B6,D$1)} -> 37 | E6: {=_xll.EQNXTDZ($A$1,$B6,E$1)} -> 41.99 | F6: {=_xll.EQNXTDZ($A$1,$B6,F$1)} -> 41.2 | G6: {=_xll.EQNXTDZ($A$1,$B6,G$1)} -> 41.23 | H6: {=_xll.EQNXTDZ($A$1,$B6,H$1)} -> 44.2 | I6: {=_xll.EQNXTDZ($A$1,$B6,I$1)} -> 47.12 | J6: {=_xll.EQNXTDZ($A$1,$B6,J$1)} -> 45.12 | ... HH6: {=_xll.EQNXTDZ($A$1,$B6,HH$1)} -> 0
A7: High | B7: NMONTH_HIGH | C7: {=_xll.EQNXTDZ($A$1,$B7,C$1)} -> 39.57 | D7: {=_xll.EQNXTDZ($A$1,$B7,D$1)} -> 45 | E7: {=_xll.EQNXTDZ($A$1,$B7,E$1)} -> 44.73 | F7: {=_xll.EQNXTDZ($A$1,$B7,F$1)} -> 43.17 | G7: {=_xll.EQNXTDZ($A$1,$B7,G$1)} -> 48.29 | H7: {=_xll.EQNXTDZ($A$1,$B7,H$1)} -> 47.6 | I7: {=_xll.EQNXTDZ($A$1,$B7,I$1)} -> 47.96 | J7: {=_xll.EQNXTDZ($A$1,$B7,J$1)} -> 45.79 | ... HH7: {=_xll.EQNXTDZ($A$1,$B7,HH$1)} -> 0 | HP7: =+MAX(D7:F7) -> 45 | HQ7: =+MAX(G7:I7) -> 48.29 | HR7: =+MAX(J7:L7) -> 45.79 | HS7: =+MAX(M7:O7) -> 46.8 | HT7: =+MAX(P7:R7) -> 46 | HU7: =+MAX(S7:U7) -> 55.37 | HV7: =+MAX(V7:X7) -> 72.73 | HW7: =+MAX(Y7:AA7) -> 114.96 | HX7: =+MAX(AB7:AD7) -> 119.6 | HY7: =+MAX(AE7:AG7) -> 136.4 | HZ7: =+MAX(AH7:AJ7) -> 156 | IA7: =+MAX(AK7:AM7) -> 149.78 | IB7: =+MAX(AN7:AP7) -> 129.71 | IC7: =+MAX(AQ7:AS7) -> 125.31 | ID7: =+MAX(AT7:AV7) -> 136 | IE7: =+MAX(AW7:AY7) -> 149.8 | IF7: =+MAX(AZ7:BB7) -> 154.8 | IG7: =+MAX(BC7:BE7) -> 127.9 | IH7: =+MAX(BF7:BH7) -> 147.8 | II7: =+MAX(BI7:BK7) -> 160.99 | IJ7: =+MAX(BL7:BN7) -> 167.77 | IK7: =+MAX(BO7:BQ7) -> 185.7 | IL7: =+MAX(BR7:BT7) -> 187.6 | IM7: =+MAX(BU7:BW7) -> 181.83 | IN7: =+MAX(BX7:BZ7) -> 175 | IO7: =+MAX(CA7:CC7) -> 165 | IP7: =+MAX(CD7:CF7) -> 157.96 | IQ7: =+MAX(CG7:CI7) -> 147.8 | IR7: =+MAX(CJ7:CL7) -> 147.79 | IS7: =+MAX(CM7:CO7) -> 147.6 | IT7: =+MAX(CP7:CR7) -> 152.8 | IU7: =+MAX(CS7:CU7) -> 111.6 | IV7: =+MAX(CV7:CX7) -> 118.1 | IW7: =+MAX(CY7:DA7) -> 131 | IX7: =+MAX(DB7:DD7) -> 181.58 | IY7: =+MAX(DE7:DG7) -> 221 | IZ7: =+MAX(DH7:DJ7) -> 275 | JA7: =+MAX(DK7:DM7) -> 282.2 | JB7: =+MAX(DN7:DP7) -> 266.15 | JC7: =+MAX(DQ7:DS7) -> 304.63 | JD7: =+MAX(DT7:DV7) -> 421.79 | JE7: =+MAX(DW7:DY7) -> 434.8 | JF7: =+MAX(DZ7:EB7) -> 427.98 | JG7: =+MAX(EC7:EE7) -> 471.4 | JH7: =+MAX(EF7:EH7) -> 645.54 | JI7: =+MAX(EI7:EK7) -> 710 | JJ7: =+MAX(EL7:EN7) -> 843.13 | JK7: =MAX(EO7:EQ7) -> 1038 | JL7: =MAX(ER7:ET7) -> 1060 | JM7: =MAX(EU7:EW7) -> 958 | JN7: =MAX(EX7:EZ7) -> 796.95 | JO7: =MAX(FA7:FC7) -> 908 | JP7: =MAX(FD7:FF7) -> 912 | JQ7: =MAX(FG7:FI7) -> 828.45 | JR7: =MAX(FJ7:FL7) -> 837.05 | JS7: =MAX(FM7:FO7) -> 1028.3 | JT7: =MAX(FP7:FR7) -> 0 | JU7: =MAX(FS7:FU7) -> 0 | JV7: =MAX(FV7:FX7) -> 0 | JW7: =MAX(FY7:GA7) -> 0 | JX7: =MAX(GB7:GD7) -> 0 | JY7: =MAX(GE7:GG7) -> 0 | JZ7: =MAX(GH7:GJ7) -> 0 | KA7: =MAX(GK7:GM7) -> 0 | KB7: =MAX(GN7:GP7) -> 0 | KC7: =MAX(GQ7:GS7) -> 0 | KD7: =MAX(GT7:GV7) -> 0 | KE7: =MAX(GW7:GY7) -> 0 | KF7: =MAX(GZ7:HB7) -> 0 | KG7: =MAX(HC7:HE7) -> 0 | KH7: =MAX(HF7:HH7) -> 0
A8: Low | B8: NMONTH_LOW | C8: {=_xll.EQNXTDZ($A$1,$B8,C$1)} -> 35.26 | D8: {=_xll.EQNXTDZ($A$1,$B8,D$1)} -> 35.96 | E8: {=_xll.EQNXTDZ($A$1,$B8,E$1)} -> 39.8 | F8: {=_xll.EQNXTDZ($A$1,$B8,F$1)} -> 40.5 | G8: {=_xll.EQNXTDZ($A$1,$B8,G$1)} -> 41.03 | H8: {=_xll.EQNXTDZ($A$1,$B8,H$1)} -> 44.02 | I8: {=_xll.EQNXTDZ($A$1,$B8,I$1)} -> 43.61 | J8: {=_xll.EQNXTDZ($A$1,$B8,J$1)} -> 37.04 | ... HH8: {=_xll.EQNXTDZ($A$1,$B8,HH$1)} -> 0 | HP8: =+MIN(D8:F8) -> 35.96 | HQ8: =+MIN(G8:I8) -> 41.03 | HR8: =+MIN(J8:L8) -> 35.42 | HS8: =+MIN(M8:O8) -> 38.6 | HT8: =+MIN(P8:R8) -> 38 | HU8: =+MIN(S8:U8) -> 41.22 | HV8: =+MIN(V8:X8) -> 46.84 | HW8: =+MIN(Y8:AA8) -> 63.31 | HX8: =+MIN(AB8:AD8) -> 100.08 | HY8: =+MIN(AE8:AG8) -> 100.07 | HZ8: =+MIN(AH8:AJ8) -> 118.05 | IA8: =+MIN(AK8:AM8) -> 109.1 | IB8: =+MIN(AN8:AP8) -> 108 | IC8: =+MIN(AQ8:AS8) -> 110.2 | ID8: =+MIN(AT8:AV8) -> 100.6 | IE8: =+MIN(AW8:AY8) -> 117.4 | IF8: =+MIN(AZ8:BB8) -> 108.42 | IG8: =+MIN(BC8:BE8) -> 108.6 | IH8: =+MIN(BF8:BH8) -> 119.6 | II8: =+MIN(BI8:BK8) -> 131.11 | IJ8: =+MIN(BL8:BN8) -> 132.04 | IK8: =+MIN(BO8:BQ8) -> 144.2 | IL8: =+MIN(BR8:BT8) -> 151 | IM8: =+MIN(BU8:BW8) -> 151.22 | IN8: =+MIN(BX8:BZ8) -> 135.32 | IO8: =+MIN(CA8:CC8) -> 134.8 | IP8: =+MIN(CD8:CF8) -> 127.72 | IQ8: =+MIN(CG8:CI8) -> 129.73 | IR8: =+MIN(CJ8:CL8) -> 107.8 | IS8: =+MIN(CM8:CO8) -> 125 | IT8: =+MIN(CP8:CR8) -> 77.2 | IU8: =+MIN(CS8:CU8) -> 80.01 | IV8: =+MIN(CV8:CX8) -> 90.39 | IW8: =+MIN(CY8:DA8) -> 85.5 | IX8: =+MIN(DB8:DD8) -> 124.9 | IY8: =+MIN(DE8:DG8) -> 164.24 | IZ8: =+MIN(DH8:DJ8) -> 200.27 | JA8: =+MIN(DK8:DM8) -> 235.11 | JB8: =+MIN(DN8:DP8) -> 192 | JC8: =+MIN(DQ8:DS8) -> 239.66 | JD8: =+MIN(DT8:DV8) -> 282.3 | JE8: =+MIN(DW8:DY8) -> 350.2 | JF8: =+MIN(DZ8:EB8) -> 343.4 | JG8: =+MIN(EC8:EE8) -> 415 | JH8: =+MIN(EF8:EH8) -> 402.67 | JI8: =+MIN(EI8:EK8) -> 558.94 | JJ8: =+MIN(EL8:EN8) -> 634.4 | JK8: =MIN(EO8:EQ8) -> 767 | JL8: =MIN(ER8:ET8) -> 856.5 | JM8: =MIN(EU8:EW8) -> 715.5 | JN8: =MIN(EX8:EZ8) -> 582.25 | JO8: =MIN(FA8:FC8) -> 647.8 | JP8: =MIN(FD8:FF8) -> 766.8 | JQ8: =MIN(FG8:FI8) -> 701.1 | JR8: =MIN(FJ8:FL8) -> 666.65 | JS8: =MIN(FM8:FO8) -> 750 | JT8: =MIN(FP8:FR8) -> 0 | JU8: =MIN(FS8:FU8) -> 0 | JV8: =MIN(FV8:FX8) -> 0 | JW8: =MIN(FY8:GA8) -> 0 | JX8: =MIN(GB8:GD8) -> 0 | JY8: =MIN(GE8:GG8) -> 0 | JZ8: =MIN(GH8:GJ8) -> 0 | KA8: =MIN(GK8:GM8) -> 0 | KB8: =MIN(GN8:GP8) -> 0 | KC8: =MIN(GQ8:GS8) -> 0 | KD8: =MIN(GT8:GV8) -> 0 | KE8: =MIN(GW8:GY8) -> 0 | KF8: =MIN(GZ8:HB8) -> 0 | KG8: =MIN(HC8:HE8) -> 0 | KH8: =MIN(HF8:HH8) -> 0
A9: Close | B9: NMONTH_CLOSE | C9: {=_xll.EQNXTDZ($A$1,$B9,C$1)} -> 37.07 | D9: {=_xll.EQNXTDZ($A$1,$B9,D$1)} -> 41.23 | E9: {=_xll.EQNXTDZ($A$1,$B9,E$1)} -> 40.9 | F9: {=_xll.EQNXTDZ($A$1,$B9,F$1)} -> 41.18 | G9: {=_xll.EQNXTDZ($A$1,$B9,G$1)} -> 45.81 | H9: {=_xll.EQNXTDZ($A$1,$B9,H$1)} -> 45.6 | I9: {=_xll.EQNXTDZ($A$1,$B9,I$1)} -> 44.62 | J9: {=_xll.EQNXTDZ($A$1,$B9,J$1)} -> 37.55 | ... HH9: {=_xll.EQNXTDZ($A$1,$B9,HH$1)} -> 0 | HP9: =+F9 -> 41.18 | HQ9: =+I9 -> 44.62 | HR9: =+L9 -> 40.8 | HS9: =+O9 -> 41.63 | HT9: =+R9 -> 43.2 | HU9: =+U9 -> 53.85 | HV9: =+X9 -> 65.16 | HW9: =+AA9 -> 109.02 | HX9: =+AD9 -> 107.88 | HY9: =+AG9 -> 132.18 | HZ9: =+AJ9 -> 149.58 | IA9: =+AM9 -> 123.93 | IB9: =+AP9 -> 118.32 | IC9: =+AS9 -> 124.45 | ID9: =+AV9 -> 126.69 | IE9: =+AY9 -> 149.04 | IF9: =+BB9 -> 118.57 | IG9: =+BE9 -> 126.23 | IH9: =+BH9 -> 145.29 | II9: =+BK9 -> 153.22 | IJ9: =+BN9 -> 147.12 | IK9: =+BQ9 -> 181.07 | IL9: =+BT9 -> 159.53 | IM9: =+BW9 -> 156.31 | IN9: =+BZ9 -> 146.63 | IO9: =+CC9 -> 154.94 | IP9: =+CF9 -> 137.45 | IQ9: =+CI9 -> 143.39 | IR9: =+CL9 -> 138.69 | IS9: =+CO9 -> 134.96 | IT9: =+CR9 -> 85.01 | IU9: =+CU9 -> 93.43 | IV9: =+CX9 -> 95.81 | IW9: =+DA9 -> 128.88 | IX9: =+DD9 -> 179.25 | IY9: =+DG9 -> 202.35 | IZ9: =+DJ9 -> 244.24 | JA9: =+DM9 -> 244.05 | JB9: =+DP9 -> 263.89 | JC9: =+DS9 -> 296.75 | JD9: =+DV9 -> 399.61 | JE9: =+DY9 -> 386.76 | JF9: =+EB9 -> 418.96 | JG9: =+EE9 -> 431.56 | JH9: =+EH9 -> 597.93 | JI9: =+EK9 -> 693.35 | JJ9: =+EN9 -> 771.18 | JK9: =EQ9 -> 939.34 | JL9: =ET9 -> 899.3 | JM9: =EW9 -> 768.3 | JN9: =EZ9 -> 713.8 | JO9: =FC9 -> 818.05 | JP9: =FF9 -> 821.6 | JQ9: =FI9 -> 754.75 | JR9: =FL9 -> 796.85 | JS9: =FO9 -> 865.45 | JT9: =FR9 -> 0 | JU9: =FU9 -> 0 | JV9: =FX9 -> 0 | JW9: =GA9 -> 0 | JX9: =GD9 -> 0 | JY9: =GG9 -> 0 | JZ9: =GJ9 -> 0 | KA9: =GM9 -> 0 | KB9: =GP9 -> 0 | KC9: =GS9 -> 0 | KD9: =GV9 -> 0 | KE9: =GY9 -> 0 | KF9: =HB9 -> 0 | KG9: =HE9 -> 0 | KH9: =HH9 -> 0
A11: Field Description | B11: Field Name | C11: {=_xll.EQNXTDZ($A$1,$B11,C$1)} -> 0 | D11: {=_xll.EQNXTDZ($A$1,$B11,D$1)} -> 0 | E11: {=_xll.EQNXTDZ($A$1,$B11,E$1)} -> 0 | F11: {=_xll.EQNXTDZ($A$1,$B11,F$1)} -> 0 | G11: {=_xll.EQNXTDZ($A$1,$B11,G$1)} -> 0 | H11: {=_xll.EQNXTDZ($A$1,$B11,H$1)} -> 0 | I11: {=_xll.EQNXTDZ($A$1,$B11,I$1)} -> 0 | J11: {=_xll.EQNXTDZ($A$1,$B11,J$1)} -> 0 | ... HH11: {=_xll.EQNXTDZ($A$1,$B11,HH$1)} -> 0
A12: Month End | B12: BMONTH_MONTHEND | C12: {=_xll.EQNXTDZ($A$1,$B12,C$1)} -> 201206 | D12: {=_xll.EQNXTDZ($A$1,$B12,D$1)} -> 201207 | E12: {=_xll.EQNXTDZ($A$1,$B12,E$1)} -> 201208 | F12: {=_xll.EQNXTDZ($A$1,$B12,F$1)} -> 201209 | G12: {=_xll.EQNXTDZ($A$1,$B12,G$1)} -> 201210 | H12: {=_xll.EQNXTDZ($A$1,$B12,H$1)} -> 201211 | I12: {=_xll.EQNXTDZ($A$1,$B12,I$1)} -> 201212 | J12: {=_xll.EQNXTDZ($A$1,$B12,J$1)} -> 201301 | ... HH12: {=_xll.EQNXTDZ($A$1,$B12,HH$1)} -> 0
A13: Open | B13: BMONTH_OPEN | C13: {=_xll.EQNXTDZ($A$1,$B13,C$1)} -> 36.49 | D13: {=_xll.EQNXTDZ($A$1,$B13,D$1)} -> 37.1 | E13: {=_xll.EQNXTDZ($A$1,$B13,E$1)} -> 42.25 | F13: {=_xll.EQNXTDZ($A$1,$B13,F$1)} -> 41.58 | G13: {=_xll.EQNXTDZ($A$1,$B13,G$1)} -> 41.4 | H13: {=_xll.EQNXTDZ($A$1,$B13,H$1)} -> 45.5 | I13: {=_xll.EQNXTDZ($A$1,$B13,I$1)} -> 45.6 | J13: {=_xll.EQNXTDZ($A$1,$B13,J$1)} -> 45.59 | ... HH13: {=_xll.EQNXTDZ($A$1,$B13,HH$1)} -> 0
A14: High | B14: BMONTH_HIGH | C14: {=_xll.EQNXTDZ($A$1,$B14,C$1)} -> 39.18 | D14: {=_xll.EQNXTDZ($A$1,$B14,D$1)} -> 44.4 | E14: {=_xll.EQNXTDZ($A$1,$B14,E$1)} -> 44.4 | F14: {=_xll.EQNXTDZ($A$1,$B14,F$1)} -> 42.58 | G14: {=_xll.EQNXTDZ($A$1,$B14,G$1)} -> 48.19 | H14: {=_xll.EQNXTDZ($A$1,$B14,H$1)} -> 47.29 | I14: {=_xll.EQNXTDZ($A$1,$B14,I$1)} -> 47.3 | J14: {=_xll.EQNXTDZ($A$1,$B14,J$1)} -> 46.72 | ... HH14: {=_xll.EQNXTDZ($A$1,$B14,HH$1)} -> 0 | HP14: =+MAX(D14:F14) -> 44.4 | HQ14: =+MAX(G14:I14) -> 48.19 | HR14: =+MAX(J14:L14) -> 46.72 | HS14: =+MAX(M14:O14) -> 46.4 | HT14: =+MAX(P14:R14) -> 44.2 | HU14: =+MAX(S14:U14) -> 54.8 | HV14: =+MAX(V14:X14) -> 72.8 | HW14: =+MAX(Y14:AA14) -> 114.7 | HX14: =+MAX(AB14:AD14) -> 118.36 | HY14: =+MAX(AE14:AG14) -> 136 | HZ14: =+MAX(AH14:AJ14) -> 165 | IA14: =+MAX(AK14:AM14) -> 148.8 | IB14: =+MAX(AN14:AP14) -> 139 | IC14: =+MAX(AQ14:AS14) -> 124.95 | ID14: =+MAX(AT14:AV14) -> 135.4 | IE14: =+MAX(AW14:AY14) -> 148.89 | IF14: =+MAX(AZ14:BB14) -> 153.59 | IG14: =+MAX(BC14:BE14) -> 127 | IH14: =+MAX(BF14:BH14) -> 146.6 | II14: =+MAX(BI14:BK14) -> 160.6 | IJ14: =+MAX(BL14:BN14) -> 167.9 | IK14: =+MAX(BO14:BQ14) -> 186.2 | IL14: =+MAX(BR14:BT14) -> 187.2 | IM14: =+MAX(BU14:BW14) -> 181.59 | IN14: =+MAX(BX14:BZ14) -> 177 | IO14: =+MAX(CA14:CC14) -> 163.8 | IP14: =+MAX(CD14:CF14) -> 156 | IQ14: =+MAX(CG14:CI14) -> 147.98 | IR14: =+MAX(CJ14:CL14) -> 148 | IS14: =+MAX(CM14:CO14) -> 148 | IT14: =+MAX(CP14:CR14) -> 152.89 | IU14: =+MAX(CS14:CU14) -> 110.69 | IV14: =+MAX(CV14:CX14) -> 115.08 | IW14: =+MAX(CY14:DA14) -> 130.8 | IX14: =+MAX(DB14:DD14) -> 181.87 | IY14: =+MAX(DE14:DG14) -> 222 | IZ14: =+MAX(DH14:DJ14) -> 275 | JA14: =+MAX(DK14:DM14) -> 281.82 | JB14: =+MAX(DN14:DP14) -> 265.01 | JC14: =+MAX(DQ14:DS14) -> 304.31 | JD14: =+MAX(DT14:DV14) -> 419.57 | JE14: =+MAX(DW14:DY14) -> 434.2 | JF14: =+MAX(DZ14:EB14) -> 427.12 | JG14: =+MAX(EC14:EE14) -> 471.37 | JH14: =+MAX(EF14:EH14) -> 644 | JI14: =+MAX(EI14:EK14) -> 709.8 | JJ14: =+MAX(EL14:EN14) -> 842.24 | JK14: =MAX(EO14:EQ14) -> 1037 | JL14: =MAX(ER14:ET14) -> 1057.54 | JM14: =MAX(EU14:EW14) -> 960 | JN14: =MAX(EX14:EZ14) -> 799.55 | JO14: =MAX(FA14:FC14) -> 907.3 | JP14: =MAX(FD14:FF14) -> 917.9 | JQ14: =MAX(FG14:FI14) -> 826.3 | JR14: =MAX(FJ14:FL14) -> 835.15 | JS14: =MAX(FM14:FO14) -> 1028 | JT14: =MAX(FP14:FR14) -> 0 | JU14: =MAX(FS14:FU14) -> 0 | JV14: =MAX(FV14:FX14) -> 0 | JW14: =MAX(FY14:GA14) -> 0 | JX14: =MAX(GB14:GD14) -> 0 | JY14: =MAX(GE14:GG14) -> 0 | JZ14: =MAX(GH14:GJ14) -> 0 | KA14: =MAX(GK14:GM14) -> 0 | KB14: =MAX(GN14:GP14) -> 0 | KC14: =MAX(GQ14:GS14) -> 0 | KD14: =MAX(GT14:GV14) -> 0 | KE14: =MAX(GW14:GY14) -> 0 | KF14: =MAX(GZ14:HB14) -> 0 | KG14: =MAX(HC14:HE14) -> 0 | KH14: =MAX(HF14:HH14) -> 0
A15: Low | B15: BMONTH_LOW | C15: {=_xll.EQNXTDZ($A$1,$B15,C$1)} -> 35.45 | D15: {=_xll.EQNXTDZ($A$1,$B15,D$1)} -> 36 | E15: {=_xll.EQNXTDZ($A$1,$B15,E$1)} -> 39.8 | F15: {=_xll.EQNXTDZ($A$1,$B15,F$1)} -> 40.6 | G15: {=_xll.EQNXTDZ($A$1,$B15,G$1)} -> 40.87 | H15: {=_xll.EQNXTDZ($A$1,$B15,H$1)} -> 44.4 | I15: {=_xll.EQNXTDZ($A$1,$B15,I$1)} -> 43.26 | J15: {=_xll.EQNXTDZ($A$1,$B15,J$1)} -> 37.21 | ... HH15: {=_xll.EQNXTDZ($A$1,$B15,HH$1)} -> 0 | HP15: =+MIN(D15:F15) -> 36 | HQ15: =+MIN(G15:I15) -> 40.87 | HR15: =+MIN(J15:L15) -> 35.47 | HS15: =+MIN(M15:O15) -> 38.98 | HT15: =+MIN(P15:R15) -> 38.31 | HU15: =+MIN(S15:U15) -> 41.6 | HV15: =+MIN(V15:X15) -> 45.2 | HW15: =+MIN(Y15:AA15) -> 63 | HX15: =+MIN(AB15:AD15) -> 100 | HY15: =+MIN(AE15:AG15) -> 100 | HZ15: =+MIN(AH15:AJ15) -> 117.29 | IA15: =+MIN(AK15:AM15) -> 109.65 | IB15: =+MIN(AN15:AP15) -> 108.5 | IC15: =+MIN(AQ15:AS15) -> 111.3 | ID15: =+MIN(AT15:AV15) -> 99.8 | IE15: =+MIN(AW15:AY15) -> 117.3 | IF15: =+MIN(AZ15:BB15) -> 118.14 | IG15: =+MIN(BC15:BE15) -> 109.98 | IH15: =+MIN(BF15:BH15) -> 120 | II15: =+MIN(BI15:BK15) -> 131.12 | IJ15: =+MIN(BL15:BN15) -> 131.81 | IK15: =+MIN(BO15:BQ15) -> 143.2 | IL15: =+MIN(BR15:BT15) -> 150.03 | IM15: =+MIN(BU15:BW15) -> 151.81 | IN15: =+MIN(BX15:BZ15) -> 135 | IO15: =+MIN(CA15:CC15) -> 131.2 | IP15: =+MIN(CD15:CF15) -> 120.26 | IQ15: =+MIN(CG15:CI15) -> 128 | IR15: =+MIN(CJ15:CL15) -> 107.13 | IS15: =+MIN(CM15:CO15) -> 125.57 | IT15: =+MIN(CP15:CR15) -> 77.28 | IU15: =+MIN(CS15:CU15) -> 80 | IV15: =+MIN(CV15:CX15) -> 90.46 | IW15: =+MIN(CY15:DA15) -> 85.09 | IX15: =+MIN(DB15:DD15) -> 124.6 | IY15: =+MIN(DE15:DG15) -> 163.12 | IZ15: =+MIN(DH15:DJ15) -> 200.66 | JA15: =+MIN(DK15:DM15) -> 236 | JB15: =+MIN(DN15:DP15) -> 191.93 | JC15: =+MIN(DQ15:DS15) -> 236.73 | JD15: =+MIN(DT15:DV15) -> 282.74 | JE15: =+MIN(DW15:DY15) -> 350.29 | JF15: =+MIN(DZ15:EB15) -> 341.24 | JG15: =+MIN(EC15:EE15) -> 411.46 | JH15: =+MIN(EF15:EH15) -> 402.93 | JI15: =+MIN(EI15:EK15) -> 560 | JJ15: =+MIN(EL15:EN15) -> 635 | JK15: =MIN(EO15:EQ15) -> 768.62 | JL15: =MIN(ER15:ET15) -> 856.15 | JM15: =MIN(EU15:EW15) -> 716.5 | JN15: =MIN(EX15:EZ15) -> 585 | JO15: =MIN(FA15:FC15) -> 648 | JP15: =MIN(FD15:FF15) -> 770 | JQ15: =MIN(FG15:FI15) -> 702 | JR15: =MIN(FJ15:FL15) -> 668.65 | JS15: =MIN(FM15:FO15) -> 749.6 | JT15: =MIN(FP15:FR15) -> 0 | JU15: =MIN(FS15:FU15) -> 0 | JV15: =MIN(FV15:FX15) -> 0 | JW15: =MIN(FY15:GA15) -> 0 | JX15: =MIN(GB15:GD15) -> 0 | JY15: =MIN(GE15:GG15) -> 0 | JZ15: =MIN(GH15:GJ15) -> 0 | KA15: =MIN(GK15:GM15) -> 0 | KB15: =MIN(GN15:GP15) -> 0 | KC15: =MIN(GQ15:GS15) -> 0 | KD15: =MIN(GT15:GV15) -> 0 | KE15: =MIN(GW15:GY15) -> 0 | KF15: =MIN(GZ15:HB15) -> 0 | KG15: =MIN(HC15:HE15) -> 0 | KH15: =MIN(HF15:HH15) -> 0
A16: Close | B16: BMONTH_CLOSE | C16: {=_xll.EQNXTDZ($A$1,$B16,C$1)} -> 36.88 | D16: {=_xll.EQNXTDZ($A$1,$B16,D$1)} -> 41.19 | E16: {=_xll.EQNXTDZ($A$1,$B16,E$1)} -> 41.17 | F16: {=_xll.EQNXTDZ($A$1,$B16,F$1)} -> 41.19 | G16: {=_xll.EQNXTDZ($A$1,$B16,G$1)} -> 45.57 | H16: {=_xll.EQNXTDZ($A$1,$B16,H$1)} -> 45.75 | I16: {=_xll.EQNXTDZ($A$1,$B16,I$1)} -> 44.32 | J16: {=_xll.EQNXTDZ($A$1,$B16,J$1)} -> 37.35 | ... HH16: {=_xll.EQNXTDZ($A$1,$B16,HH$1)} -> 0 | HP16: =+F16 -> 41.19 | HQ16: =+I16 -> 44.32 | HR16: =+L16 -> 40.66 | HS16: =+O16 -> 41.64 | HT16: =+R16 -> 42.91 | HU16: =+U16 -> 53.6 | HV16: =+X16 -> 64.96 | HW16: =+AA16 -> 109.35 | HX16: =+AD16 -> 108.84 | HY16: =+AG16 -> 132.69 | HZ16: =+AJ16 -> 147.95 | IA16: =+AM16 -> 123.3 | IB16: =+AP16 -> 117.85 | IC16: =+AS16 -> 123.55 | ID16: =+AV16 -> 126.3 | IE16: =+AY16 -> 147.47 | IF16: =+BB16 -> 118.96 | IG16: =+BE16 -> 125.79 | IH16: =+BH16 -> 144.78 | II16: =+BK16 -> 151.91 | IJ16: =+BN16 -> 146.47 | IK16: =+BQ16 -> 177.3 | IL16: =+BT16 -> 158.09 | IM16: =+BW16 -> 155.43 | IN16: =+BZ16 -> 144.58 | IO16: =+CC16 -> 155.85 | IP16: =+CF16 -> 137.56 | IQ16: =+CI16 -> 143.32 | IR16: =+CL16 -> 139.08 | IS16: =+CO16 -> 135 | IT16: =+CR16 -> 84.84 | IU16: =+CU16 -> 93.35 | IV16: =+CX16 -> 95.57 | IW16: =+DA16 -> 129.36 | IX16: =+DD16 -> 179.07 | IY16: =+DG16 -> 202.22 | IZ16: =+DJ16 -> 244.3 | JA16: =+DM16 -> 243.08 | JB16: =+DP16 -> 262.92 | JC16: =+DS16 -> 296.71 | JD16: =+DV16 -> 401.25 | JE16: =+DY16 -> 387.38 | JF16: =+EB16 -> 418.32 | JG16: =+EE16 -> 431.17 | JH16: =+EH16 -> 599.16 | JI16: =+EK16 -> 692.83 | JJ16: =+EN16 -> 770.92 | JK16: =EQ16 -> 934.99 | JL16: =ET16 -> 898.9 | JM16: =EW16 -> 767.4 | JN16: =EZ16 -> 712.7 | JO16: =FC16 -> 817.9 | JP16: =FF16 -> 821.45 | JQ16: =FI16 -> 754.25 | JR16: =FL16 -> 792.25 | JS16: =FO16 -> 864.15 | JT16: =FR16 -> 0 | JU16: =FU16 -> 0 | JV16: =FX16 -> 0 | JW16: =GA16 -> 0 | JX16: =GD16 -> 0 | JY16: =GG16 -> 0 | JZ16: =GJ16 -> 0 | KA16: =GM16 -> 0 | KB16: =GP16 -> 0 | KC16: =GS16 -> 0 | KD16: =GV16 -> 0 | KE16: =GY16 -> 0 | KF16: =HB16 -> 0 | KG16: =HE16 -> 0 | KH16: =HH16 -> 0
A19: High | HP19: =+IF(HP14=0,HP7,HP14) -> 44.4 | HQ19: =+IF(HQ14=0,HQ7,HQ14) -> 48.19 | HR19: =+IF(HR14=0,HR7,HR14) -> 46.72 | HS19: =+IF(HS14=0,HS7,HS14) -> 46.4 | HT19: =+IF(HT14=0,HT7,HT14) -> 44.2 | HU19: =+IF(HU14=0,HU7,HU14) -> 54.8 | HV19: =+IF(HV14=0,HV7,HV14) -> 72.8 | HW19: =+IF(HW14=0,HW7,HW14) -> 114.7 | ... KH19: =+IF(KH14=0,KH7,KH14) -> 0
A20: Low | HP20: =+IF(HP15=0,HP8,HP15) -> 36 | HQ20: =+IF(HQ15=0,HQ8,HQ15) -> 40.87 | HR20: =+IF(HR15=0,HR8,HR15) -> 35.47 | HS20: =+IF(HS15=0,HS8,HS15) -> 38.98 | HT20: =+IF(HT15=0,HT8,HT15) -> 38.31 | HU20: =+IF(HU15=0,HU8,HU15) -> 41.6 | HV20: =+IF(HV15=0,HV8,HV15) -> 45.2 | HW20: =+IF(HW15=0,HW8,HW15) -> 63 | ... KH20: =+IF(KH15=0,KH8,KH15) -> 0
A21: Close | HP21: =+IF(HP16=0,HP9,HP16) -> 41.19 | HQ21: =+IF(HQ16=0,HQ9,HQ16) -> 44.32 | HR21: =+IF(HR16=0,HR9,HR16) -> 40.66 | HS21: =+IF(HS16=0,HS9,HS16) -> 41.64 | HT21: =+IF(HT16=0,HT9,HT16) -> 42.91 | HU21: =+IF(HU16=0,HU9,HU16) -> 53.6 | HV21: =+IF(HV16=0,HV9,HV16) -> 64.96 | HW21: =+IF(HW16=0,HW9,HW16) -> 109.35 | ... KH21: =+IF(KH16=0,KH9,KH16) -> 0

Sheet QTR No. of Shares
A1: ='QTR Raw'!A1 -> 100249 | C1: 201206 | D1: 201209 | E1: 201212 | F1: 201303 | G1: 201306 | H1: 201309 | I1: 201312 | J1: 201403 | K1: 201406 | L1: 201409 | M1: 201412 | N1: 201503 | O1: 201506 | P1: 201509 | Q1: 201512 | R1: 201603 | S1: 201606 | T1: 201609 | U1: 201612 | V1: 201703 | W1: 201706 | X1: 201709 | Y1: 201712 | Z1: 201803 | AA1: 201806 | AB1: 201809 | AC1: 201812 | AD1: 201903 | AE1: 201906 | AF1: 201909 | AG1: 201912 | AH1: 202003 | AI1: 202006 | AJ1: 202009 | AK1: 202012 | AL1: 202103 | AM1: 202106 | AN1: 202109 | AO1: 202112 | AP1: 202203 | AQ1: 202206 | AR1: 202209 | AS1: 202212 | AT1: 202303 | AU1: 202306 | AV1: 202309 | AW1: 202312 | AX1: 202403 | AY1: 202406
A4: Field Description | B4: Field Name
A5: Date End | B5: SHP_DATE_END | C5: {=_xll.EQNXTDZ($A$1,$B5,C$1)} -> 201206 | D5: {=_xll.EQNXTDZ($A$1,$B5,D$1)} -> 201209 | E5: {=_xll.EQNXTDZ($A$1,$B5,E$1)} -> 201212 | F5: {=_xll.EQNXTDZ($A$1,$B5,F$1)} -> 201303 | G5: {=_xll.EQNXTDZ($A$1,$B5,G$1)} -> 201306 | H5: {=_xll.EQNXTDZ($A$1,$B5,H$1)} -> 201309 | I5: {=_xll.EQNXTDZ($A$1,$B5,I$1)} -> 201312 | J5: {=_xll.EQNXTDZ($A$1,$B5,J$1)} -> 201403 | ... AY5: {=_xll.EQNXTDZ($A$1,$B5,AY$1)} -> 202406
A6: Grand Total | B6: SHP_NSGRANDTOTAL | C6: {=_xll.EQNXTDZ($A$1,$B6,C$1)} -> 34807844 | D6: {=_xll.EQNXTDZ($A$1,$B6,D$1)} -> 34807844 | E6: {=_xll.EQNXTDZ($A$1,$B6,E$1)} -> 34807844 | F6: {=_xll.EQNXTDZ($A$1,$B6,F$1)} -> 34807844 | G6: {=_xll.EQNXTDZ($A$1,$B6,G$1)} -> 34807844 | H6: {=_xll.EQNXTDZ($A$1,$B6,H$1)} -> 34807844 | I6: {=_xll.EQNXTDZ($A$1,$B6,I$1)} -> 34807844 | J6: {=_xll.EQNXTDZ($A$1,$B6,J$1)} -> 34807844 | ... AY6: {=_xll.EQNXTDZ($A$1,$B6,AY$1)} -> 34807844
B7: In Crs. | C7: =+C6/10^7 -> 3.4807844 | D7: =+D6/10^7 -> 3.4807844 | E7: =+E6/10^7 -> 3.4807844 | F7: =+F6/10^7 -> 3.4807844 | G7: =+G6/10^7 -> 3.4807844 | H7: =+H6/10^7 -> 3.4807844 | I7: =+I6/10^7 -> 3.4807844 | J7: =+J6/10^7 -> 3.4807844 | ... AY7: =+AY6/10^7 -> 3.4807844

Sheet Share price Daily
A1: =_xll.EQNXTH(B1,"[ADJC];[ADJH];[ADJL];[ADJO];[UCLS];[VOLUME]","2015-Jan-01","Y","All traded days","Asc") -> EQNXTH | B1: =+'Annual Raw'!A1 -> 100249 | L1: =_xll.EQNXTH(B1,"[NADJC];[NADJH];[NADJLOW];[NADJOPEN];[NUCLOSE];[NVOLUME]","2015-Jan-01","Y","All traded days","Asc") -> EQNXTH
A2: KSB Ltd. | L2: KSB Ltd.
A3: DATE | B3: ADJHIGH | C3: ADJCLOSE | D3: ADJLOW | E3: ADJOPEN | F3: CLOSE | G3: VOLUME | L3: DATE | M3: ADJCLOSE | N3: ADJHIGH | O3: ADJLOW | P3: ADJOPEN | Q3: CLOSE | R3: VOLUME
A4: 42005 | B4: 132 | C4: 128.84 | D4: 127.93 | E4: 129.6 | F4: 644.2 | G4: 3577 | L4: 42005 | M4: 128.86 | N4: 131.9 | O4: 127.6 | P4: 130 | Q4: 644.3 | R4: 101562
A5: 42006 | B5: 131.36 | C5: 128.94 | D5: 128.27 | E5: 130.22 | F5: 644.7 | G5: 4701 | L5: 42006 | M5: 128.39 | N5: 131.4 | O5: 127.66 | P5: 129.69 | Q5: 641.95 | R5: 14041
A6: 42009 | B6: 130.18 | C6: 126.83 | D6: 125.6 | E6: 129.5 | F6: 634.15 | G6: 3158 | L6: 42009 | M6: 125.8 | N6: 129.96 | O6: 124.76 | P6: 128.79 | Q6: 629 | R6: 6438
A7: 42010 | B7: 124.99 | C7: 121.86 | D7: 121.6 | E7: 123.81 | F7: 609.3 | G7: 1907 | L7: 42010 | M7: 121.78 | N7: 126.3 | O7: 121.1 | P7: 125.03 | Q7: 608.9 | R7: 5631
A8: 42011 | B8: 122.34 | C8: 120.43 | D8: 117.29 | E8: 120.4 | F8: 602.15 | G8: 2592 | L8: 42011 | M8: 120.58 | N8: 122.51 | O8: 118.3 | P8: 121.79 | Q8: 602.9 | R8: 5215
A9: 42012 | B9: 130 | C9: 125.05 | D9: 121.2 | E9: 122.22 | F9: 625.25 | G9: 6313 | L9: 42012 | M9: 125.06 | N9: 130.62 | O9: 120.58 | P9: 121.58 | Q9: 625.3 | R9: 20181
A10: 42013 | B10: 127.4 | C10: 125.56 | D10: 125 | E10: 127 | F10: 627.8 | G10: 1906 | L10: 42013 | M10: 125.23 | N10: 127.6 | O10: 124.25 | P10: 125.6 | Q10: 626.15 | R10: 5387
A11: 42016 | B11: 127.3 | C11: 125.1 | D11: 124.2 | E11: 126.67 | F11: 625.5 | G11: 1531 | L11: 42016 | M11: 124.96 | N11: 127.41 | O11: 124 | P11: 126 | Q11: 624.8 | R11: 4255
A12: 42017 | B12: 124.47 | C12: 122.87 | D12: 122.2 | E12: 124.47 | F12: 614.35 | G12: 2327 | L12: 42017 | M12: 122.33 | N12: 125 | O12: 121.21 | P12: 124.96 | Q12: 611.65 | R12: 9267
A13: 42018 | B13: 125.67 | C13: 121.56 | D13: 118.73 | E13: 125.24 | F13: 607.8 | G13: 3795 | L13: 42018 | M13: 121.15 | N13: 125 | O13: 118.05 | P13: 125 | Q13: 605.75 | R13: 15866
A14: 42019 | B14: 125.14 | C14: 123.02 | D14: 120.91 | E14: 121.98 | F14: 615.1 | G14: 4290 | L14: 42019 | M14: 123.11 | N14: 125.2 | O14: 121 | P14: 122 | Q14: 615.55 | R14: 16923
A15: 42020 | B15: 124.72 | C15: 123.94 | D15: 122.01 | E15: 123.41 | F15: 619.7 | G15: 1053 | L15: 42020 | M15: 123.91 | N15: 124.88 | O15: 121.73 | P15: 121.73 | Q15: 619.55 | R15: 3014
... A2834: 46190 | B2834: 874.4 | C2834: 870.1 | D2834: 860 | E2834: 869.75 | F2834: 870.1 | G2834: 7830 | L2834: 46182 | M2834: 818.75 | N2834: 821.1 | O2834: 795.4 | P2834: 804.65 | Q2834: 818.75 | R2834: 236072
L2835: 46183 | M2835: 819.9 | N2835: 833 | O2835: 808.05 | P2835: 820.5 | Q2835: 819.9 | R2835: 206489
L2836: 46184 | M2836: 807.3 | N2836: 818.45 | O2836: 800.2 | P2836: 816 | Q2836: 807.3 | R2836: 101299
L2837: 46185 | M2837: 834.8 | N2837: 844.8 | O2837: 810.4 | P2837: 813.1 | Q2837: 834.8 | R2837: 233451
L2838: 46188 | M2838: 855.3 | N2838: 870.4 | O2838: 841.55 | P2838: 844.8 | Q2838: 855.3 | R2838: 374055
L2839: 46189 | M2839: 865.45 | N2839: 868.1 | O2839: 855 | P2839: 855 | Q2839: 865.45 | R2839: 130451
L2840: 46190 | M2840: 870.25 | N2840: 875 | O2840: 860.05 | P2840: 865.5 | Q2840: 870.25 | R2840: 86818

Sheet Sheet2
J19: 219.3 | K19: 186.25 | L19: 186.75
J20: 192.9 | K20: 135.5 | L20: 146.9 | N20: 219.3 | O20: 192.9 | P20: 186 | Q20: 178.7 | R20: 207 | S20: 255.15 | T20: 348.25 | U20: 374 | V20: 495.9 | W20: 659.9 | X20: 613.4 | Y20: 607.9 | Z20: 555.95 | AA20: 497.8 | AB20: 459.9 | AC20: 374 | AD20: 362 | AE20: 341.5 | AF20: 384.2 | AG20: 433.8 | AH20: 460 | AI20: 474.4 | AJ20: 414.4 | AK20: 318.7 | AL20: 303.25 | AM20: 332.7 | AN20: 295 | AO20: 247 | AP20: 214.4 | AQ20: 179.5 | AR20: 97.9 | AS20: 119.1 | AT20: 130.65 | AU20: 148.55 | AV20: 153.8 | AW20: 152.9 | AX20: 136 | AY20: 141.15 | AZ20: 128.1 | BA20: 142.5 | BB20: 143.55 | BC20: 124.5 | BD20: 241 | BE20: 450 | BF20: 503.35
J21: 186 | K21: 145.4 | L21: 169.1 | N21: 186.25 | O21: 135.5 | P21: 145.4 | Q21: 108.95 | R21: 137 | S21: 170 | T21: 243.15 | U21: 307.5 | V21: 325.1 | W21: 463 | X21: 467.05 | Y21: 436.5 | Z21: 467 | AA21: 348.2 | AB21: 325 | AC21: 313.1 | AD21: 285 | AE21: 277.85 | AF21: 327 | AG21: 317 | AH21: 370.7 | AI21: 360 | AJ21: 271.15 | AK21: 233.15 | AL21: 218.8 | AM21: 262 | AN21: 223.6 | AO21: 137.6 | AP21: 142 | AQ21: 59.3 | AR21: 58 | AS21: 72.8 | AT21: 80 | AU21: 107.25 | AV21: 106 | AW21: 125.1 | AX21: 112.25 | AY21: 81.45 | AZ21: 88 | BA21: 90.35 | BB21: 106.05 | BC21: 98.55 | BD21: 119.25 | BE21: 210 | BF21: 349
J22: 178.7 | K22: 108.95 | L22: 139.75 | N22: 186.75 | O22: 146.9 | P22: 169.1 | Q22: 139.75 | R22: 202.15 | S22: 249.05 | T22: 346.4 | U22: 349.2 | V22: 469.9 | W22: 584.8 | X22: 536.15 | Y22: 513.35 | Z22: 474 | AA22: 438.55 | AB22: 355.4 | AC22: 334.95 | AD22: 298.8 | AE22: 328.35 | AF22: 343 | AG22: 389.9 | AH22: 443.05 | AI22: 407.5 | AJ22: 290.1 | AK22: 235.75 | AL22: 292.65 | AM22: 276.1 | AN22: 237.05 | AO22: 190.1 | AP22: 147.2 | AQ22: 71.9 | AR22: 75.2 | AS22: 90.1 | AT22: 117.2 | AU22: 116.3 | AV22: 140.5 | AW22: 128.6 | AX22: 133.65 | AY22: 91.65 | AZ22: 97.65 | BA22: 125 | BB22: 115.35 | BC22: 119.25 | BD22: 219.3 | BE22: 442.65 | BF22: 503.35
J23: 207 | K23: 137 | L23: 202.15
J24: 255.15 | K24: 170 | L24: 249.05
J25: 348.25 | K25: 243.15 | L25: 346.4
J26: 374 | K26: 307.5 | L26: 349.2
J27: 495.9 | K27: 325.1 | L27: 469.9
J28: 659.9 | K28: 463 | L28: 584.8
J29: 613.4 | K29: 467.05 | L29: 536.15
J30: 607.9 | K30: 436.5 | L30: 513.35
J31: 555.95 | K31: 467 | L31: 474
J32: 497.8 | K32: 348.2 | L32: 438.55
J33: 459.9 | K33: 325 | L33: 355.4
J34: 374 | K34: 313.1 | L34: 334.95
... J63: 503.35 | K63: 349 | L63: 503.35
