Workbook

Sheet Template
A1: =+'Annual Raw'!C4 -> Larsen & Toubro Ltd. | B1: 36951 | C1: =EOMONTH(B1,12) -> 37346 | D1: =EOMONTH(C1,12) -> 37711 | E1: =EOMONTH(D1,12) -> 38077 | F1: =EOMONTH(E1,12) -> 38442 | G1: =EOMONTH(F1,12) -> 38807 | H1: =EOMONTH(G1,12) -> 39172 | I1: =EOMONTH(H1,12) -> 39538 | J1: =EOMONTH(I1,12) -> 39903 | ... AE1: =EOMONTH(AD1,12) -> 47573 | AH1: QTR | AI1: 41061 | AJ1: 41153 | AK1: 41244 | AL1: 41334 | AM1: 41426 | AN1: 41518 | AO1: 41609 | AP1: 41699 | AQ1: 41791 | AR1: 41883 | AS1: 41974 | AT1: 42064 | AU1: 42156 | AV1: 42248 | AW1: 42339 | AX1: 42430 | AY1: 42522 | AZ1: 42614 | BA1: 42705 | BB1: 42795 | BC1: 42887 | BD1: 42979 | BE1: 43070 | BF1: 43160 | BG1: 43252 | BH1: 43344 | BI1: 43435 | BJ1: 43525 | BK1: 43617 | BL1: 43709 | BM1: 43800 | BN1: 43891 | BO1: 43983 | BP1: 44075 | BQ1: =EOMONTH(BP1,3) -> 44196 | BR1: =EOMONTH(BQ1,3) -> 44286 | BS1: =EOMONTH(BR1,3) -> 44377 | BT1: =EOMONTH(BS1,3) -> 44469 | BU1: =EOMONTH(BT1,3) -> 44561 | BV1: =EOMONTH(BU1,3) -> 44651 | BW1: =EOMONTH(BV1,3) -> 44742 | BX1: =EOMONTH(BW1,3) -> 44834 | ... DB1: =EOMONTH(DA1,3) -> 47573 | DE1: HISTORICAL ESTIMATES | DF1: 46112
A2: Presentation Data (Start)
A4: Order Book-Segment Wise
A5: Infrastructure Projects Segment (orderbook) | CG5: =+CG7+CG14+CG21 -> 98787
A6: Infrastructure Projects Segment- Opening | T6: 0 | U6: 221810.4 | V6: 224886 | W6: 245550 | X6: 261048 | Y6: 283645 | Z6: =+Y9 -> 311665 | AA6: =+Z9 -> 357073 | AB6: =+AA9 -> 422562 | AC6: =+AB9 -> 481360.92 | AD6: =+AC9 -> 536492.48 | AE6: =+AD9 -> 590139 | BK6: =+BJ9 -> 221810.4 | BL6: =+BK9 -> 218736 | BM6: =+BL9 -> 215272 | BN6: =+BM9 -> 223599 | BO6: =+BN9 -> 224886 | BP6: =+BO9 -> 219672 | BQ6: =+BP9 -> 221186 | BR6: =+BQ9 -> 245014 | ... DB6: =+DA9 -> 655126.42 | DF6: 424937
A7: Infrastructure Projects Segment- Addition | T7: 0 | U7: 64498 | V7: 82094 | W7: 87902 | X7: 109314 | Y7: 140571 | Z7: =+SUM(CE7:CH7) -> 175305 | AA7: =SUM(CI7:CL7) -> 199399 | AB7: =+SUM(CM7:CP7) -> 214498.19 | AC7: =+SUM(CQ7:CT7) -> 230740.75 | AD7: =+SUM(CU7:CX7) -> 248213.25 | AE7: =+SUM(CY7:DB7) -> 267008.83 | BK7: =+BK9+BK8-BK6 -> 10519.6 | BL7: =+BL9+BL8-BL6 -> 12766 | BM7: =+BM9+BM8-BM6 -> 25353 | BN7: =+BN9+BN8-BN6 -> 26379 | BO7: =+BO9+BO8-BO6 -> 1179 | BP7: =+BP9+BP8-BP6 -> 14483 | BQ7: =+BQ9+BQ8-BQ6 -> 39656 | BR7: =+BR9+BR8-BR6 -> 26776 | ... CL7: =+CL9+CL8-CL6 -> 37319 | CM7: =+CI7+(CI7*CM10) -> 45259.991 | CN7: =+CJ7+(CJ7*CN10) -> 60321.196 | CO7: =+CK7+(CK7*CO10) -> 68772.08 | CP7: =+CL7+(CL7*CP10) -> 40144.926 | CQ7: =+CM7+(CM7*CQ10) -> 48687.236 | CR7: =+CN7+(CN7*CR10) -> 64888.928 | CS7: =+CO7+(CO7*CS10) -> 73979.743 | CT7: =+CP7+(CP7*CT10) -> 43184.84 | ... DB7: =+CX7+(CX7*DB10) -> 49972.68 | DF7: 41630.4
A8: Infrastructure Projects Segment- Execution % | T8: 0 | U8: 58348 | V8: 61430 | W8: 72404 | X8: 86717 | Y8: 112551 | Z8: =+SUM(CE8:CH8) -> 129897 | AA8: =SUM(CI8:CL8) -> 133910 | AB8: =+SUM(CM8:CP8) -> 155699.27 | AC8: =+SUM(CQ8:CT8) -> 175609.19 | AD8: =+SUM(CU8:CX8) -> 194566.73 | AE8: =+SUM(CY8:DB8) -> 213245.06 | AF8: =24*80 -> 1920 | AG8: tr | BK8: =+BK37 -> 13594 | BL8: =+BL37 -> 16230 | BM8: =+BM37 -> 17026 | BN8: =+BN37 -> 25092 | BO8: =+BO37 -> 6393 | BP8: =+BP37 -> 12969 | BQ8: =+BQ37 -> 15828 | BR8: =+BR37 -> 26240 | ... CL8: =+CL37 -> 39694 | CM8: =+CM6*CM11 -> 34031.18 | CN8: =+CN6*CN11 -> 37195.287 | CO8: =+CO6*CO11 -> 39011.552 | CP8: =+CP6*CP11 -> 45461.249 | CQ8: =+CQ6*CQ11 -> 38766.572 | CR8: =+CR6*CR11 -> 42124.82 | CS8: =+CS6*CS11 -> 43889.224 | CT8: =+CT6*CT11 -> 50828.577 | ... DB8: =+DB6*DB11 -> 61196.338 | DF8: 36281.12
A9: Infrastructure Projects Segment- Closing | T9: 221810.4 | U9: 224886 | V9: 245550 | W9: 261048 | X9: 283645 | Y9: 311665 | Z9: =+Z6+Z7-Z8 -> 357073 | AA9: =+AA6+AA7-AA8 -> 422562 | AB9: =+AB6+AB7-AB8 -> 481360.92 | AC9: =+AC6+AC7-AC8 -> 536492.48 | AD9: =+AD6+AD7-AD8 -> 590139 | AE9: =+AE6+AE7-AE8 -> 643902.76 | AF9: 1.1 | AG9: tr | AY9: 190476 | AZ9: 186332 | BA9: 193950 | BB9: 193362 | BC9: 197175 | BD9: 190550 | BE9: 200318 | BF9: 195483.3 | BG9: 210567.5 | BH9: 218211.2 | BI9: 219248 | BJ9: 221810.4 | BK9: 218736 | BL9: 215272 | BM9: 223599 | BN9: 224886 | BO9: 219672 | BP9: 221186 | BQ9: 245014 | BR9: 245550 | BS9: 246012 | BT9: 244570 | BU9: 248492 | BV9: 261048 | BW9: 265282 | BX9: 268128 | BY9: 278352 | BZ9: 283645 | CA9: 301198 | CB9: 301969 | CC9: 317693 | CD9: 311665 | CE9: 323994 | CF9: 342954 | CG9: 361282 | CH9: 357073 | CI9: 370390 | CJ9: 394706 | CK9: 424937 | CL9: 422562 | CM9: =+CM6+CM7-CM8 -> 433790.81 | CN9: =+CN6+CN7-CN8 -> 456916.72 | CO9: =+CO6+CO7-CO8 -> 486677.25 | CP9: =+CP6+CP7-CP8 -> 481360.92 | CQ9: =+CQ6+CQ7-CQ8 -> 491281.59 | CR9: =+CR6+CR7-CR8 -> 514045.7 | CS9: =+CS6+CS7-CS8 -> 544136.22 | CT9: =+CT6+CT7-CT8 -> 536492.48 | ... DB9: =+DB6+DB7-DB8 -> 643902.76 | DF9: 430286.28
A10: Infrastructure Projects Segment- Inflow growth YoY% | U10: =+U7/T7-1 -> #DIV/0! | V10: =+V7/U7-1 -> 0.27281466 | W10: =+W7/V7-1 -> 0.070748167 | X10: =+X7/W7-1 -> 0.24358945 | Y10: =+Y7/X7-1 -> 0.28593776 | Z10: =+Z7/Y7-1 -> 0.24709222 | AA10: =+AA7/Z7-1 -> 0.13744046 | AB10: =+AB7/AA7-1 -> 0.07572351 | ... AE10: =+AE7/AD7-1 -> 0.07572351 | AF10: =+AF9*20% -> 0.22 | AG10: bn | BP10: =+BP7/BL7-1 -> 0.13449789 | BQ10: =+BQ7/BM7-1 -> 0.56415414 | BR10: =+BR7/BN7-1 -> 0.01504985 | BS10: =+BS7/BO7-1 -> 8.2205259 | BT10: =+BT7/BP7-1 -> -0.13823103 | BU10: =+BU7/BQ7-1 -> -0.43849607 | BV10: =+BV7/BR7-1 -> 0.57913803 | BW10: =+BW7/BS7-1 -> 0.6939564 | ... CL10: =+CL7/CH7-1 -> 0.07572351 | CM10: =+CL10 -> 0.07572351 | CN10: =+CM10 -> 0.07572351 | CO10: =+CN10 -> 0.07572351 | CP10: =+CO10 -> 0.07572351 | CQ10: =+CP10 -> 0.07572351 | CR10: =+CQ10 -> 0.07572351 | CS10: =+CR10 -> 0.07572351 | CT10: =+CS10 -> 0.07572351 | ... DB10: =+DA10 -> 0.07572351 | DF10: 0.2
A11: Infrastructure Projects Segment- Execution % | U11: =+U8/U6 -> 0.26305349 | V11: =+V8/V6 -> 0.27316062 | W11: =+W8/W6 -> 0.29486459 | X11: =+X8/X6 -> 0.33218795 | Y11: =+Y8/Y6 -> 0.39680234 | Z11: =+Z8/Z6 -> 0.41678405 | AA11: =+AA8/AA6 -> 0.37502135 | AB11: =+AB8/AB6 -> 0.3684649 | ... AE11: =+AE8/AE6 -> 0.36134718 | BP11: =+BP8/BP6 -> 0.05903802 | BQ11: =+BQ8/BQ6 -> 0.071559683 | BR11: =+BR8/BR6 -> 0.10709592 | BS11: =+BS8/BS6 -> 0.042390552 | BT11: =+BT8/BT6 -> 0.0565948 | BU11: =+BU8/BU6 -> 0.0750092 | BV11: =+BV8/BV6 -> 0.11962961 | BW11: =+BW8/BW6 -> 0.054323343 | ... CL11: =+CL8/CL6 -> 0.093411494 | CM11: =+CI11 -> 0.080535353 | CN11: =+CJ11 -> 0.085744756 | CO11: =+CK11 -> 0.085380004 | CP11: =+CL11 -> 0.093411494 | CQ11: =+CM11 -> 0.080535353 | CR11: =+CN11 -> 0.085744756 | CS11: =+CO11 -> 0.085380004 | CT11: =+CP11 -> 0.093411494 | ... DB11: =+CX11 -> 0.093411494 | DF11: 0.09
A12: Energy Projects Segment (orderbook)
A13: Energy Projects Segment- Opening | T13: 0 | U13: 46944 | V13: 60780 | W13: 58932 | X13: 64368 | Y13: 71910 | Z13: =+Y16 -> 118189 | AA13: =+Z16 -> 165754 | AB13: =+AA16 -> 258472 | AC13: =+AB16 -> 308318.27 | AD13: =+AC16 -> 328729.74 | AE13: =+AD16 -> 329515.3 | BL13: =+BK16 -> 53214 | BM13: =+BL16 -> 66704 | BN13: =+BM16 -> 64323 | BO13: =+BN16 -> 60780 | BP13: =+BO16 -> 57969 | BQ13: =+BP16 -> 53802 | BR13: =+BQ16 -> 59598 | BS13: =+BR16 -> 58932 | ... DB13: =+DA16 -> 325589.32 | DF13: 247861
A14: Energy Projects Segment- Addition | T14: 0 | U14: 22956 | V14: 18251 | W14: 29029 | X14: 32450 | Y14: 75818 | Z14: =+SUM(CE14:CH14) -> 88229 | AA14: =SUM(CI14:CL14) -> 147590 | AB14: =+SUM(CM14:CP14) -> 124788.23 | AC14: =+SUM(CQ14:CT14) -> 105509.19 | AD14: =+SUM(CU14:CX14) -> 89208.649 | AE14: =+SUM(CY14:DB14) -> 75426.445 | BL14: =+BL16+BL15-BL13 -> 18276 | BM14: =+BM16+BM15-BM13 -> 2700 | BN14: =+BN16+BN15-BN13 -> 1980 | BO14: =+BO16+BO15-BO13 -> 625 | BP14: =+BP16+BP15-BP13 -> 564 | BQ14: =+BQ16+BQ15-BQ13 -> 11100 | BR14: =+BR16+BR15-BR13 -> 5962 | BS14: =+BS16+BS15-BS13 -> 1046 | ... CL14: =+CL16+CL15-CL13 -> 27205 | CM14: =+CI14+(CI14*CM17) -> 28000.621 | CN14: =+CJ14+(CJ14*CN17) -> 34815.399 | CO14: =+CK14+(CK14*CO17) -> 38970.216 | CP14: =+CL14+(CL14*CP17) -> 23001.99 | CQ14: =+CM14+(CM14*CQ17) -> 23674.692 | CR14: =+CN14+(CN14*CR17) -> 29436.628 | CS14: =+CO14+(CO14*CS17) -> 32949.55 | CT14: =+CP14+(CP14*CT17) -> 19448.32 | ... DB14: =+CX14+(CX14*DB17) -> 13903.221 | DF14: 37323.8
A15: Energy Projects Segment- Execution % | T15: 0 | U15: 15390 | V15: 20099 | W15: 23593 | X15: 24908 | Y15: 29539 | Z15: =+SUM(CE15:CH15) -> 40664 | AA15: =SUM(CI15:CL15) -> 54872 | AB15: =+SUM(CM15:CP15) -> 74941.955 | AC15: =+SUM(CQ15:CT15) -> 85097.72 | AD15: =+SUM(CU15:CX15) -> 88423.093 | AE15: =+SUM(CY15:DB15) -> 87247.019 | BL15: =+BL38 -> 4786 | BM15: =+BM38 -> 5081 | BN15: =+BN38 -> 5523 | BO15: =+BO38 -> 3436 | BP15: =+BP38 -> 4731 | BQ15: =+BQ38 -> 5304 | BR15: =+BR38 -> 6628 | BS15: =+BS38 -> 4949 | ... CL15: =+CL38 -> 16594 | CM15: =+CM13*CM18 -> 17304.394 | CN15: =+CN13*CN18 -> 18020.494 | CO15: =+CO13*CO18 -> 19144.893 | CP15: =+CP13*CP18 -> 20472.174 | CQ15: =+CQ13*CQ18 -> 20641.543 | CR15: =+CR13*CR18 -> 20844.608 | CS15: =+CS13*CS18 -> 21419.834 | CT15: =+CT13*CT18 -> 22191.735 | ... DB15: =+DB13*DB18 -> 21797.819 | DF15: 14705.54
A16: Energy Projects Segment- Closing | T16: 46944 | U16: 60780 | V16: 58932 | W16: 64368 | X16: 71910 | Y16: 118189 | Z16: =+Z13+Z14-Z15 -> 165754 | AA16: =+AA13+AA14-AA15 -> 258472 | AB16: =+AB13+AB14-AB15 -> 308318.27 | AC16: =+AC13+AC14-AC15 -> 328729.74 | AD16: =+AD13+AD14-AD15 -> 329515.3 | AE16: =+AE13+AE14-AE15 -> 317694.72 | AY16: 38610 | AZ16: 37770 | BA16: 36204 | BB16: 39195 | BC16: 36806 | BD16: 36050 | BE16: 40605 | BF16: 36044.7 | BG16: 36407.8 | BH16: 36837.2 | BI16: 40044 | BJ16: 46944 | BK16: 53214 | BL16: 66704 | BM16: 64323 | BN16: 60780 | BO16: 57969 | BP16: 53802 | BQ16: 59598 | BR16: 58932 | BS16: 55029 | BT16: 62795 | BU16: 64676 | BV16: 64368 | BW16: 65412 | BX16: 70756 | BY16: 73454 | BZ16: 71910 | CA16: 74268 | CB16: 108168 | CC16: 112777 | CD16: 118189 | CE16: 117816 | CF16: 117144 | CG16: 145827 | CH16: 165754 | CI16: 186401 | CJ16: 214496 | CK16: 247861 | CL16: 258472 | CM16: =+CM13+CM14-CM15 -> 269168.23 | CN16: =+CN13+CN14-CN15 -> 285963.13 | CO16: =+CO13+CO14-CO15 -> 305788.46 | CP16: =+CP13+CP14-CP15 -> 308318.27 | CQ16: =+CQ13+CQ14-CQ15 -> 311351.42 | CR16: =+CR13+CR14-CR15 -> 319943.44 | CS16: =+CS13+CS14-CS15 -> 331473.16 | CT16: =+CT13+CT14-CT15 -> 328729.74 | ... DB16: =+DB13+DB14-DB15 -> 317694.72 | DF16: 270479.27
A17: Energy Projects Segment- Inflow growth YoY% | U17: =+U14/T14-1 -> #DIV/0! | V17: =+V14/U14-1 -> -0.20495731 | W17: =+W14/V14-1 -> 0.59054298 | X17: =+X14/W14-1 -> 0.11784767 | Y17: =+Y14/X14-1 -> 1.3364561 | Z17: =+Z14/Y14-1 -> 0.16369464 | AA17: =+AA14/Z14-1 -> 0.67280599 | AB17: =+AB14/AA14-1 -> -0.15449403 | ... AE17: =+AE14/AD14-1 -> -0.15449403 | BP17: =+BP14/BL14-1 -> -0.96913986 | BQ17: =+BQ14/BM14-1 -> 3.1111111 | BR17: =+BR14/BN14-1 -> 2.0111111 | BS17: =+BS14/BO14-1 -> 0.6736 | BT17: =+BT14/BP14-1 -> 23.374113 | BU17: =+BU14/BQ14-1 -> -0.29486486 | BV17: =+BV14/BR14-1 -> 0.074974841 | BW17: =+BW14/BS14-1 -> 4.8479924 | ... CL17: =+CL14/CH14-1 -> -0.15449403 | CM17: =+CL17 -> -0.15449403 | CN17: =+CM17 -> -0.15449403 | CO17: =+CN17 -> -0.15449403 | CP17: =+CO17 -> -0.15449403 | CQ17: =+CP17 -> -0.15449403 | CR17: =+CQ17 -> -0.15449403 | CS17: =+CR17 -> -0.15449403 | CT17: =+CS17 -> -0.15449403 | ... DB17: =+DA17 -> -0.15449403 | DF17: 0.16
A18: Energy Projects Segment- Execution % | U18: =+U15/U13 -> 0.32783742 | V18: =+V15/V13 -> 0.33068444 | W18: =+W15/W13 -> 0.40034277 | X18: =+X15/X13 -> 0.38696247 | Y18: =+Y15/Y13 -> 0.41077736 | Z18: =+Z15/Z13 -> 0.34405909 | AA18: =+AA15/AA13 -> 0.3310448 | AB18: =+AB15/AB13 -> 0.28994226 | ... AE18: =+AE15/AE13 -> 0.2647738 | BP18: =+BP15/BP13 -> 0.081612586 | BQ18: =+BQ15/BQ13 -> 0.098583696 | BR18: =+BR15/BR13 -> 0.11121179 | BS18: =+BS15/BS13 -> 0.083978144 | BT18: =+BT15/BT13 -> 0.10868815 | BU18: =+BU15/BU13 -> 0.094689068 | BV18: =+BV15/BV13 -> 0.10385614 | BW18: =+BW15/BW13 -> 0.078812453 | ... CL18: =+CL15/CL13 -> 0.066948814 | CM18: =+CL18 -> 0.066948814 | CN18: =+CM18 -> 0.066948814 | CO18: =+CN18 -> 0.066948814 | CP18: =+CO18 -> 0.066948814 | CQ18: =+CP18 -> 0.066948814 | CR18: =+CQ18 -> 0.066948814 | CS18: =+CR18 -> 0.066948814 | CT18: =+CS18 -> 0.066948814 | ... DB18: =+DA18 -> 0.066948814 | DF18: 0.06
A19: Hi-Tech Manufacturing Segment (orderbook)
A20: Hi-Tech Manufacturing Segment- Opening | T20: 0 | U20: 18777.6 | V20: 12156 | W20: 9822 | X20: 21456 | Y20: 27965 | Z20: =+Y23 -> 31975 | AA20: =+Z23 -> 40388 | AB20: =+AA23 -> 35312 | AC20: =+AB23 -> 29557.791 | AD20: =+AC23 -> 24128.405 | AE20: =+AD23 -> 19586.428 | BL20: =+BK23 -> 15288 | BM20: =+BL23 -> 15160 | BN20: =+BM23 -> 12252 | BO20: =+BN23 -> 12156 | BP20: =+BO23 -> 12204 | BQ20: =+BP23 -> 11956 | BR20: =+BQ23 -> 13244 | BS20: =+BR23 -> 9822 | ... DB20: =+DA23 -> 17404.697 | DF20: 37865
A21: Hi-Tech Manufacturing Segment- Addition | T21: 0 | U21: 1602 | V21: 3773 | W21: 17575 | X21: 13044 | Y21: 12205 | Z21: =+SUM(CE21:CH21) -> 18108 | AA21: =SUM(CI21:CL21) -> 9033 | AB21: =+SUM(CM21:CP21) -> 9033 | AC21: =+SUM(CQ21:CT21) -> 9033 | AD21: =+SUM(CU21:CX21) -> 9033 | AE21: =+SUM(CY21:DB21) -> 9033 | BL21: =+BL23+BL22-BL20 -> 1447 | BM21: =+BM23+BM22-BM20 -> -1182 | BN21: =+BN23+BN22-BN20 -> 1337 | BO21: =+BO23+BO22-BO20 -> 899 | BP21: =+BP23+BP22-BP20 -> 1118 | BQ21: =+BQ23+BQ22-BQ20 -> 3043 | BR21: =+BR23+BR22-BR20 -> -1287 | BS21: =+BS23+BS22-BS20 -> 1126 | ... CL21: =+CL23+CL22-CL20 -> 2308 | CM21: =+CI21+(CI21*CM24) -> 2001 | CN21: =+CJ21+(CJ21*CN24) -> 2656 | CO21: =+CK21+(CK21*CO24) -> 2068 | CP21: =+CL21+(CL21*CP24) -> 2308 | CQ21: =+CM21+(CM21*CQ24) -> 2001 | CR21: =+CN21+(CN21*CR24) -> 2656 | CS21: =+CO21+(CO21*CS24) -> 2068 | CT21: =+CP21+(CP21*CT24) -> 2308 | ... DB21: =+CX21+(CX21*DB24) -> 2308 | DF21: 474.93
A22: Hi-Tech Manufacturing Segment- Executiom | T22: 0 | U22: 4734 | V22: 6107 | W22: 5941 | X22: 6535 | Y22: 8195 | Z22: =+SUM(CE22:CH22) -> 9695 | AA22: =SUM(CI22:CL22) -> 14109 | AB22: =+SUM(CM22:CP22) -> 14787.209 | AC22: =+SUM(CQ22:CT22) -> 14462.387 | AD22: =+SUM(CU22:CX22) -> 13574.976 | AE22: =+SUM(CY22:DB22) -> 12533.472 | BL22: =+BL39 -> 1575 | BM22: =+BM39 -> 1726 | BN22: =+BN39 -> 1433 | BO22: =+BO39 -> 851 | BP22: =+BP39 -> 1366 | BQ22: =+BQ39 -> 1755 | BR22: =+BR39 -> 2135 | BS22: =+BS39 -> 1237 | ... CL22: =+CL39 -> 4861 | CM22: =+CM20*CM25 -> 3527.6678 | CN22: =+CN20*CN25 -> 3051.6018 | CO22: =+CO20*CO25 -> 3460.2442 | CP22: =+CP20*CP25 -> 4747.6952 | CQ22: =+CQ20*CQ25 -> 3543.9783 | CR22: =+CR20*CR25 -> 3090.6858 | CS22: =+CS20*CS25 -> 3409.7859 | CT22: =+CT20*CT25 -> 4417.9365 | ... DB22: =+DB20*DB25 -> 3626.7408 | DF22: 3797.81
A23: Hi-Tech Manufacturing Segment- Closing | T23: 18777.6 | U23: 12156 | V23: 9822 | W23: 21456 | X23: 27965 | Y23: 31975 | Z23: =+Z20+Z21-Z22 -> 40388 | AA23: =+AA20+AA21-AA22 -> 35312 | AB23: =+AB20+AB21-AB22 -> 29557.791 | AC23: =+AC20+AC21-AC22 -> 24128.405 | AD23: =+AD20+AD21-AD22 -> 19586.428 | AE23: =+AE20+AE21-AE22 -> 16085.956 | AY23: 10296 | AZ23: 10072 | BA23: 10344 | BB23: 15678 | BC23: 13145 | BD23: 15450 | BE23: 16242 | BF23: 16575.3 | BG23: 18747.3 | BH23: 20246.4 | BI23: 19028 | BJ23: 18777.6 | BK23: 15288 | BL23: 15160 | BM23: 12252 | BN23: 12156 | BO23: 12204 | BP23: 11956 | BQ23: 13244 | BR23: 9822 | BS23: 9711 | BT23: 9915 | BU23: 13616 | BV23: 21456 | BW23: 18170 | BX23: 18620 | BY23: 19330 | BZ23: 27965 | CA23: 24756 | CB23: 27042 | CC23: 25758 | CD23: 31975 | CE23: 34363 | CF23: 35611 | CG23: 41769 | CH23: 40388 | CI23: 39162 | CJ23: 39064 | CK23: 37865 | CL23: 35312 | CM23: =+CM20+CM21-CM22 -> 33785.332 | CN23: =+CN20+CN21-CN22 -> 33389.73 | CO23: =+CO20+CO21-CO22 -> 31997.486 | CP23: =+CP20+CP21-CP22 -> 29557.791 | CQ23: =+CQ20+CQ21-CQ22 -> 28014.813 | CR23: =+CR20+CR21-CR22 -> 27580.127 | CS23: =+CS20+CS21-CS22 -> 26238.341 | CT23: =+CT20+CT21-CT22 -> 24128.405 | ... DB23: =+DB20+DB21-DB22 -> 16085.956 | DF23: 34542.12
A24: Hi-Tech Manufacturing Segment- Inflow growth YoY% | U24: =+U21/T21-1 -> #DIV/0! | V24: =+V21/U21-1 -> 1.355181 | W24: =+W21/V21-1 -> 3.658097 | X24: =+X21/W21-1 -> -0.25780939 | Y24: =+Y21/X21-1 -> -0.064320761 | Z24: =+Z21/Y21-1 -> 0.48365424 | AA24: =+AA21/Z21-1 -> -0.50115971 | AB24: =+AB21/AA21-1 -> 0 | ... AE24: =+AE21/AD21-1 -> 0 | BP24: =+BP21/BL21-1 -> -0.22736697 | BQ24: =+BQ21/BM21-1 -> -3.5744501 | BR24: =+BR21/BN21-1 -> -1.9626028 | BS24: =+BS21/BO21-1 -> 0.25250278 | BT24: =+BT21/BP21-1 -> 0.49642218 | BU24: =+BU21/BQ21-1 -> 0.70029576 | BV24: =+BV21/BR21-1 -> -8.4607615 | BW24: =+BW21/BS21-1 -> -2.7886323 | ... CL24: =+CL21/CH21-1 -> 0.16979219 | CM24: 0 | CN24: 0 | CO24: 0 | CP24: 0 | CQ24: 0 | CR24: 0 | CS24: 0 | CT24: 0 | CU24: 0 | CV24: 0 | CW24: 0 | CX24: 0 | CY24: 0 | CZ24: 0 | DA24: 0 | DB24: 0 | DF24: -0.76
A25: Hi-Tech Manufacturing Segment- Execution % | U25: =+U22/U20 -> 0.2521089 | V25: =+V22/V20 -> 0.50238565 | W25: =+W22/W20 -> 0.60486663 | X25: =+X22/X20 -> 0.30457681 | Y25: =+Y22/Y20 -> 0.29304488 | Z25: =+Z22/Z20 -> 0.30320563 | AA25: =+AA22/AA20 -> 0.34933644 | AB25: =+AB22/AB20 -> 0.41875875 | ... AE25: =+AE22/AE20 -> 0.63990596 | BP25: =+BP22/BP20 -> 0.11193051 | BQ25: =+BQ22/BQ20 -> 0.14678822 | BR25: =+BR22/BR20 -> 0.16120507 | BS25: =+BS22/BS20 -> 0.12594176 | BT25: =+BT22/BT20 -> 0.15127175 | BU25: =+BU22/BU20 -> 0.14856278 | BV25: =+BV22/BV20 -> 0.12940658 | BW25: =+BW22/BW20 -> 0.059284116 | ... CL25: =+CL22/CL20 -> 0.12837713 | CM25: =+CI25+2% -> 0.09989997 | CN25: =+CJ25+2% -> 0.090323273 | CO25: =+CK25+2% -> 0.10363199 | CP25: =+CL25+2% -> 0.14837713 | CQ25: =+CM25+2% -> 0.11989997 | CR25: =+CN25+2% -> 0.11032327 | CS25: =+CO25+2% -> 0.12363199 | CT25: =+CP25+2% -> 0.16837713 | ... DB25: =+CX25+2% -> 0.20837713 | DF25: 0.1
A26: Other Segments- (Orderbook) | T26: 5868 | U26: 6078 | V26: 13096 | W26: 10728 | X26: 15980 | Y26: 13981 | Z26: =+CH26 -> 15921 | AA26: =+CL26 -> 23981 | AB26: =+CP26 -> 23981 | AC26: =+CT26 -> 23981 | AD26: =+CX26 -> 23981 | AE26: =+DB26 -> 23981 | AY26: 18018 | AZ26: 17626 | BA26: 18102 | BB26: 13065 | BC26: 15774 | BD26: 15450 | BE26: 13535 | BF26: 14996.7 | BG26: 5977.4 | BH26: 5624 | BI26: 5680 | BJ26: 5868 | BK26: 6762 | BL26: 6064 | BM26: 6126 | BN26: 6078 | BO26: 15255 | BP26: 11956 | BQ26: 13244 | BR26: 13096 | BS26: 12948 | BT26: 13220 | BU26: 13616 | BV26: 10728 | BW26: 14536 | BX26: 14896 | BY26: 15464 | BZ26: 15980 | CA26: 12378 | CB26: 13521 | CC26: 13580 | CD26: 13981 | CE26: 14727 | CF26: 14684 | CG26: 15345 | CH26: 15921 | CI26: 16808 | CJ26: 18774 | CK26: 22498 | CL26: 23981 | CM26: =+CL26 -> 23981 | CN26: =+CM26 -> 23981 | CO26: =+CN26 -> 23981 | CP26: =+CO26 -> 23981 | CQ26: =+CP26 -> 23981 | CR26: =+CQ26 -> 23981 | CS26: =+CR26 -> 23981 | CT26: =+CS26 -> 23981 | ... DB26: =+DA26 -> 23981 | DF26: 22498
A28: Total Order Book -Opening | BZ28: =+BY31 -> 386600 | CA28: =+BZ31 -> 399500 | CB28: =+CA31 -> 412600 | CC28: =+CB31 -> 450700 | CD28: =+CC31 -> 469808 | CE28: =+CD31 -> 475810 | CF28: =+CE31 -> 490900 | CG28: =+CF31 -> 510393 | ... DB28: =+DA31 -> 1022101.4
A29: Total Order Book -Addition | BZ29: =+BZ31+BZ30-BZ28 -> 71235 | CA29: =+CA31+CA30-CA28 -> 60982 | CB29: =+CB31+CB30-CB28 -> 89124 | CC29: =+CC31+CC30-CC28 -> 74236 | CD29: =+CD31+CD30-CD28 -> 73081 | CE29: =+CE31+CE30-CE28 -> 70209 | CF29: =+CF31+CF30-CF28 -> 81044 | CG29: =+CG31+CG30-CG28 -> 118498 | ... DB29: =+DB31+DB30-DB28 -> 127139.69
A30: Total Order Book -Execution | BZ30: =+BZ45 -> 58335 | CA30: =+CA45 -> 47882 | CB30: =+CB45 -> 51024 | CC30: =+CC45 -> 55128 | CD30: =+CD45 -> 67079 | CE30: =+CE45 -> 55119 | CF30: =+CF45 -> 61551 | CG30: =+CG45 -> 64668 | ... DB30: =+DB45 -> 147576.69
A31: Total Order Book-Closing | T31: =+T9+T16+T23+T26 -> 293400 | U31: =+U9+U16+U23+U26 -> 303900 | V31: =+V9+V16+V23+V26 -> 327400 | W31: =+W9+W16+W23+W26 -> 357600 | X31: =+X9+X16+X23+X26 -> 399500 | Y31: =+Y9+Y16+Y23+Y26 -> 475810 | Z31: =+Z9+Z16+Z23+Z26 -> 579136 | AA31: =+AA9+AA16+AA23+AA26 -> 740327 | ... AE31: =+AE9+AE16+AE23+AE26 -> 1001664.4 | AY31: =+AY9+AY16+AY23+AY26 -> 257400 | AZ31: =+AZ9+AZ16+AZ23+AZ26 -> 251800 | BA31: =+BA9+BA16+BA23+BA26 -> 258600 | BB31: =+BB9+BB16+BB23+BB26 -> 261300 | BC31: =+BC9+BC16+BC23+BC26 -> 262900 | BD31: =+BD9+BD16+BD23+BD26 -> 257500 | BE31: =+BE9+BE16+BE23+BE26 -> 270700 | BF31: =+BF9+BF16+BF23+BF26 -> 263100 | ... DB31: =+DB9+DB16+DB23+DB26 -> 1001664.4 | DF31: 757806
A32: Total Inflow Growth YoY% | CA32: =+CA29/BW29-1 -> #DIV/0! | CB32: =+CB29/BX29-1 -> #DIV/0! | CC32: =+CC29/BY29-1 -> #DIV/0! | CD32: =+CD29/BZ29-1 -> 0.025914228 | CE32: =+CE29/CA29-1 -> 0.15130694 | CF32: =+CF29/CB29-1 -> -0.090660204 | CG32: =+CG29/CC29-1 -> 0.59623363 | CH32: =+CH29/CD29-1 -> 0.22201393 | ... DB32: =+DB29/CX29-1 -> 0.1483027
A33: Total Order Book Growth YoY % | U33: =+U31/T31-1 -> 0.035787321 | V33: =+V31/U31-1 -> 0.077328068 | W33: =+W31/V31-1 -> 0.092241906 | X33: =+X31/W31-1 -> 0.11717002 | Y33: =+Y31/X31-1 -> 0.19101377 | Z33: =+Z31/Y31-1 -> 0.21715811 | AA33: =+AA31/Z31-1 -> 0.27833013 | AB33: =+AB31/AA31-1 -> 0.13898046 | ... AE33: =+AE31/AD31-1 -> 0.039910557 | BC33: =+BC31/AY31-1 -> 0.021367521 | BD33: =+BD31/AZ31-1 -> 0.022637014 | BE33: =+BE31/BA31-1 -> 0.04679041 | BF33: =+BF31/BB31-1 -> 0.0068886338 | BG33: =+BG31/BC31-1 -> 0.033472803 | BH33: =+BH31/BD31-1 -> 0.090946796 | BI33: =+BI31/BE31-1 -> 0.04913188 | BJ33: =+BJ31/BF31-1 -> 0.11516534 | ... DB33: =+DB31/CX31-1 -> 0.039910557 | DF33: 0.31
A35: Segment Revenue
A36: Projects & Manufacturing- Revenue | T36: =+SUM(T37:T40) -> 0 | U36: =+SUM(U37:U40) -> 104644 | V36: =+SUM(V37:V40) -> 93490 | W36: =+SUM(W37:W40) -> 107916 | X36: =+SUM(X37:X40) -> 124204 | Y36: =+SUM(Y37:Y40) -> 157910 | Z36: =+SUM(Z37:Z40) -> 187322 | AA36: =+SUM(AA37:AA40) -> 209984 | ... AE36: =+SUM(AE37:AE40) -> 319785.56 | BK36: =+SUM(BK37:BK40) -> 21176 | BL36: =+SUM(BL37:BL40) -> 24555 | BM36: =+SUM(BM37:BM40) -> 25365 | BN36: =+SUM(BN37:BN40) -> 33548 | BO36: =+SUM(BO37:BO40) -> 11394 | BP36: =+SUM(BP37:BP40) -> 20387 | BQ36: =+SUM(BQ37:BQ40) -> 24876 | BR36: =+SUM(BR37:BR40) -> 36833 | ... DB36: =+SUM(DB37:DB40) -> 88310.897 | DF36: 57378
A37: Infrastructure Projects Segment- Revenue | U37: 71942 | V37: 61430 | W37: 72404 | X37: 86717 | Y37: 112551 | Z37: =+SUM(CE37:CH37) -> 129897 | AA37: =SUM(CI37:CL37) -> 133910 | AB37: =+SUM(CM37:CP37) -> 155699.27 | AC37: =+SUM(CQ37:CT37) -> 175609.19 | AD37: =+SUM(CU37:CX37) -> 194566.73 | AE37: =+SUM(CY37:DB37) -> 213245.06 | BK37: 13594 | BL37: 16230 | BM37: 17026 | BN37: 25092 | BO37: 6393 | BP37: 12969 | BQ37: 15828 | BR37: 26240 | BS37: 10409 | BT37: 13923 | BU37: 18345 | BV37: 29727 | BW37: 14181 | BX37: 19370 | BY37: 21944 | BZ37: 31222 | CA37: 22058 | CB37: 24613 | CC37: 27845 | CD37: 38035 | CE37: 26908 | CF37: 31954 | CG37: 32134 | CH37: 38901 | CI37: 28757 | CJ37: 31759 | CK37: 33700 | CL37: 39694 | CM37: =+CM8 -> 34031.18 | CN37: =+CN8 -> 37195.287 | CO37: =+CO8 -> 39011.552 | CP37: =+CP8 -> 45461.249 | CQ37: =+CQ8 -> 38766.572 | CR37: =+CR8 -> 42124.82 | CS37: =+CS8 -> 43889.224 | CT37: =+CT8 -> 50828.577 | ... DB37: =+DB8 -> 61196.338 | DF37: 36281
A38: Energy Projects Segment- Revenue | U38: 19714 | V38: 20099 | W38: 23593 | X38: 24908 | Y38: 29539 | Z38: =+SUM(CE38:CH38) -> 40664 | AA38: =SUM(CI38:CL38) -> 54872 | AB38: =+SUM(CM38:CP38) -> 74941.955 | AC38: =+SUM(CQ38:CT38) -> 85097.72 | AD38: =+SUM(CU38:CX38) -> 88423.093 | AE38: =+SUM(CY38:DB38) -> 87247.019 | BK38: 4324 | BL38: 4786 | BM38: 5081 | BN38: 5523 | BO38: 3436 | BP38: 4731 | BQ38: 5304 | BR38: 6628 | BS38: 4949 | BT38: 5981 | BU38: 5946 | BV38: 6717 | BW38: 5073 | BX38: 5586 | BY38: 6333 | BZ38: 7916 | CA38: 6682 | CB38: 6788 | CC38: 7864 | CD38: 8205 | CE38: 8495 | CF38: 8869 | CG38: 11051 | CH38: 12249 | CI38: 12470 | CJ38: 13082 | CK38: 12726 | CL38: 16594 | CM38: =+CM15 -> 17304.394 | CN38: =+CN15 -> 18020.494 | CO38: =+CO15 -> 19144.893 | CP38: =+CP15 -> 20472.174 | CQ38: =+CQ15 -> 20641.543 | CR38: =+CR15 -> 20844.608 | CS38: =+CS15 -> 21419.834 | CT38: =+CT15 -> 22191.735 | ... DB38: =+DB15 -> 21797.819 | DF38: 14706
A39: Hi-Tech Manufacturing Segment- Revenue | U39: 6543 | V39: 6107 | W39: 5941 | X39: 6535 | Y39: 8195 | Z39: =+SUM(CE39:CH39) -> 9695 | AA39: =SUM(CI39:CL39) -> 14109 | AB39: =+SUM(CM39:CP39) -> 14787.209 | AC39: =+SUM(CQ39:CT39) -> 14462.387 | AD39: =+SUM(CU39:CX39) -> 13574.976 | AE39: =+SUM(CY39:DB39) -> 12533.472 | BK39: 1809 | BL39: 1575 | BM39: 1726 | BN39: 1433 | BO39: 851 | BP39: 1366 | BQ39: 1755 | BR39: 2135 | BS39: 1237 | BT39: 1469 | BU39: 1473 | BV39: 1762 | BW39: 1272 | BX39: 1456 | BY39: 1673 | BZ39: 2134 | CA39: 1781 | CB39: 1886 | CC39: 2066 | CD39: 2462 | CE39: 1845 | CF39: 2063 | CG39: 2433 | CH39: 3354 | CI39: 3227 | CJ39: 2754 | CK39: 3267 | CL39: 4861 | CM39: =+CM22 -> 3527.6678 | CN39: =+CN22 -> 3051.6018 | CO39: =+CO22 -> 3460.2442 | CP39: =+CP22 -> 4747.6952 | CQ39: =+CQ22 -> 3543.9783 | CR39: =+CR22 -> 3090.6858 | CS39: =+CS22 -> 3409.7859 | CT39: =+CT22 -> 4417.9365 | ... DB39: =+DB22 -> 3626.7408 | DF39: 3798
A40: Other Segment- Revenue | U40: 6445 | V40: 5854 | W40: 5978 | X40: 6044 | Y40: 7625 | Z40: =+SUM(CE40:CH40) -> 7066 | AA40: =SUM(CI40:CL40) -> 7093 | AB40: =+SUM(CM40:CP40) -> 6760 | AC40: =+SUM(CQ40:CT40) -> 6760 | AD40: =+SUM(CU40:CX40) -> 6760 | AE40: =+SUM(CY40:DB40) -> 6760 | BK40: 1449 | BL40: 1964 | BM40: 1532 | BN40: 1500 | BO40: 714 | BP40: 1321 | BQ40: 1989 | BR40: 1830 | BS40: 1320 | BT40: 1379 | BU40: 1455 | BV40: 1824 | BW40: 1467 | BX40: 1418 | BY40: 1361 | BZ40: 1798 | CA40: 2196 | CB40: 1622 | CC40: 1530 | CD40: 2277 | CE40: 1375 | CF40: 1648 | CG40: 1674 | CH40: 2369 | CI40: 1393 | CJ40: 1416 | CK40: 2594 | CL40: 1690 | CM40: =+CL40 -> 1690 | CN40: =+CM40 -> 1690 | CO40: =+CN40 -> 1690 | CP40: =+CO40 -> 1690 | CQ40: =+CP40 -> 1690 | CR40: =+CQ40 -> 1690 | CS40: =+CR40 -> 1690 | CT40: =+CS40 -> 1690 | ... DB40: =+DA40 -> 1690 | DF40: 2594
A41: Services & Concessions- Revenue | V41: =+SUM(V42:V44) -> 42489 | W41: =+SUM(W42:W44) -> 48604 | X41: =+SUM(X42:X44) -> 59136 | Y41: =+SUM(Y42:Y44) -> 63203 | Z41: =+SUM(Z42:Z44) -> 68409 | AA41: =+SUM(AA42:AA44) -> 75890 | AB41: =+SUM(AB42:AB44) -> 0 | AC41: =+SUM(AC42:AC44) -> 0 | ... AE41: =+SUM(AE42:AE44) -> 0 | BK41: =+SUM(BK42:BK44) -> 8460 | BL41: =+SUM(BL42:BL44) -> 10774 | BM41: =+SUM(BM42:BM44) -> 10878 | BN41: =+SUM(BN42:BN44) -> 10690 | BO41: =+SUM(BO42:BO44) -> 9866 | BP41: =+SUM(BP42:BP44) -> 10649 | BQ41: =+SUM(BQ42:BQ44) -> 10720 | BR41: =+SUM(BR42:BR44) -> 11254 | ... CL41: =+SUM(CL42:CL44) -> 19922 | CM41: =+CM45-CM36 -> 16313.084 | CN41: =+CN45-CN36 -> 17647.575 | CO41: =+CO45-CO36 -> 18917.38 | CP41: =+CP45-CP36 -> 23821.467 | CQ41: =+CQ45-CQ36 -> 19133.72 | CR41: =+CR45-CR36 -> 21579.38 | CS41: =+CS45-CS36 -> 24434.005 | CT41: =+CT45-CT36 -> 31891.091 | ... DB41: =+DB45-DB36 -> 59265.793 | DF41: 33262
A42: IT & Technology Services Segment- Revenue | U42: 22135 | V42: 25463 | W42: 32267 | X42: 41538 | Y42: 44473 | Z42: =+SUM(CE42:CH42) -> 47845 | AA42: =SUM(CI42:CL42) -> 53497 | AB42: =+SUM(CM42:CP42) -> 0 | AC42: =+SUM(CQ42:CT42) -> 0 | AD42: =+SUM(CU42:CX42) -> 0 | AE42: =+SUM(CY42:DB42) -> 0 | BK42: 3820 | BL42: 5876 | BM42: 6090 | BN42: 6349 | BO42: 6028 | BP42: 6167 | BQ42: 6505 | BR42: 6763 | BS42: 7232 | BT42: 7876 | BU42: 8398 | BV42: 8761 | BW42: 9556 | BX42: 10437 | BY42: 10625 | BZ42: 10920 | CA42: 10851 | CB42: 11182 | CC42: 11196 | CD42: 11244 | CE42: 11505 | CF42: 11798 | CG42: 12061 | CH42: 12481 | CI42: 12619 | CJ42: 13274 | CK42: 13526 | CL42: 14078
A43: Financial Services Segment- Revenue | U43: 13822 | V43: 13404 | W43: 11969 | X43: 12574 | Y43: 13109 | Z43: =+SUM(CE43:CH43) -> 15194 | AA43: =SUM(CI43:CL43) -> 17283 | AB43: =+SUM(CM43:CP43) -> 0 | AC43: =+SUM(CQ43:CT43) -> 0 | AD43: =+SUM(CU43:CX43) -> 0 | AE43: =+SUM(CY43:DB43) -> 0 | BK43: 3462 | BL43: 3445 | BM43: 3550 | BN43: 3365 | BO43: 3284 | BP43: 3342 | BQ43: 3401 | BR43: 3377 | BS43: 3061 | BT43: 2975 | BU43: 2970 | BV43: 2963 | BW43: 2958 | BX43: 3152 | BY43: 3348 | BZ43: 3116 | CA43: 3020 | CB43: 3084 | CC43: 3407 | CD43: 3598 | CE43: 3664 | CF43: 3837 | CG43: 3881 | CH43: 3812 | CI43: 3971 | CJ43: 4166 | CK43: 4477 | CL43: 4669
A44: Developmental Projects Segment- Revenue | U44: 4845 | V44: 3622 | W44: 4368 | X44: 5024 | Y44: 5621 | Z44: =+SUM(CE44:CH44) -> 5370 | AA44: =SUM(CI44:CL44) -> 5110 | AB44: =+SUM(CM44:CP44) -> 0 | AC44: =+SUM(CQ44:CT44) -> 0 | AD44: =+SUM(CU44:CX44) -> 0 | AE44: =+SUM(CY44:DB44) -> 0 | BK44: 1178 | BL44: 1453 | BM44: 1238 | BN44: 976 | BO44: 554 | BP44: 1140 | BQ44: 814 | BR44: 1114 | BS44: 1126 | BT44: 1170 | BU44: 976 | BV44: 1096 | BW44: 1346 | BX44: 1344 | BY44: 1105 | BZ44: 1229 | CA44: 1294 | CB44: 1849 | CC44: 1220 | CD44: 1258 | CE44: 1327 | CF44: 1382 | CG44: 1434 | CH44: 1227 | CI44: 1242 | CJ44: 1533 | CK44: 1160 | CL44: 1175
A45: Total- Revenue | U45: =+U36+U41 -> 104644 | V45: =+V36+V41 -> 135979 | W45: =+W36+W41 -> 156520 | X45: =+X36+X41 -> 183340 | Y45: =+Y36+Y41 -> 221113 | Z45: =+Z36+Z41 -> 255731 | AA45: =SUM(CI45:CL45) -> 285874 | AB45: =+SUM(CM45:CP45) -> 328887.94 | AC45: =+SUM(CQ45:CT45) -> 378967.49 | AD45: =+SUM(CU45:CX45) -> 436857.5 | AE45: =+SUM(CY45:DB45) -> 503636.04 | BK45: =+BK36+BK41 -> 29636 | BL45: =+BL36+BL41 -> 35329 | BM45: =+BM36+BM41 -> 36243 | BN45: =+BN36+BN41 -> 44238 | BO45: =+BO36+BO41 -> 21260 | BP45: =+BP36+BP41 -> 31036 | BQ45: =+BQ36+BQ41 -> 35596 | BR45: =+BR36+BR41 -> 48087 | ... CL45: =+CL36+CL41 -> 82761 | CM45: =+CM164 -> 72866.325 | CN45: =+CN164 -> 77604.957 | CO45: =+CO164 -> 82224.068 | CP45: =+CP164 -> 96192.586 | CQ45: =+CQ164 -> 83775.813 | CR45: =+CR164 -> 89329.494 | CS45: =+CS164 -> 94842.849 | CT45: =+CT164 -> 111019.34 | ... DB45: =+DB164 -> 147576.69 | DF45: 90640
A46: Checksum- Revenue | U46: =+U45-U164 -> -40808.36 | V46: =+V45-V164 -> -0.03 | W46: =+W45-W164 -> -1.23 | X46: =+X45-X164 -> -0.7 | Y46: =+Y45-Y164 -> 0.09 | Z46: =+Z45-Z164 -> -3.45 | AA46: =+AA45-AA164 -> -0.36 | AB46: =+AB45-AB164 -> 0 | ... AE46: =+AE45-AE164 -> 0 | BK46: =+BK45-BK164 -> 0.05 | BL46: =+BL45-BL164 -> 0.55 | BM46: =+BM45-BM164 -> 0.32 | BN46: =+BN45-BN164 -> -7.28 | BO46: =+BO45-BO164 -> 0.03 | BP46: =+BP45-BP164 -> 1.26 | BQ46: =+BQ45-BQ164 -> -0.42 | BR46: =+BR45-BR164 -> -0.9 | ... DB46: =+DB45-DB164 -> 0 | DF46: -
A48: Segment EBITDA
A49: Projects & Manufacturing- EBITDA | U49: =+SUM(U50:U53) -> 10479 | V49: =+SUM(V50:V53) -> 9610 | W49: =+SUM(W50:W53) -> 10043 | X49: =+SUM(X50:X53) -> 10708 | Y49: =+SUM(Y50:Y53) -> 12884 | Z49: =+SUM(Z50:Z53) -> 15545 | AA49: =+SUM(AA50:AA53) -> 17460 | AB49: =+SUM(AB50:AB53) -> 21456.436 | ... AE49: =+SUM(AE50:AE53) -> 26178.208 | BK49: =+SUM(BK50:BK53) -> 1790 | BL49: =+SUM(BL50:BL53) -> 2409 | BM49: =+SUM(BM50:BM53) -> 2265 | BN49: =+SUM(BN50:BN53) -> 4015 | BO49: =+SUM(BO50:BO53) -> 742 | BP49: =+SUM(BP50:BP53) -> 1644 | BQ49: =+SUM(BQ50:BQ53) -> 2540 | BR49: =+SUM(BR50:BR53) -> 4684 | ... DB49: =+SUM(DB50:DB53) -> 7232.1776 | DF49: 4869.31
A50: Infrastructure Projects Segment- EBITDA | U50: 5873 | V50: 5227 | W50: 5921 | X50: 6064 | Y50: 6983 | Z50: =+SUM(CE50:CH50) -> 8362 | AA50: =SUM(CI50:CL50) -> 9175 | AB50: =+SUM(CM50:CP50) -> 11557.165 | AC50: =+SUM(CQ50:CT50) -> 13106.362 | AD50: =+SUM(CU50:CX50) -> 14541.297 | AE50: =+SUM(CY50:DB50) -> 15941.857 | BK50: 873 | BL50: 1166 | BM50: 1044 | BN50: 2790 | BO50: 400 | BP50: 825 | BQ50: 982 | BR50: 3020 | BS50: 736 | BT50: 1152 | BU50: 1298 | BV50: 2735 | BW50: 919 | BX50: 1287 | BY50: 1527 | BZ50: 2331 | CA50: 1117 | CB50: 1332 | CC50: 1522 | CD50: 3012 | CE50: 1553 | CF50: 1926 | CG50: 1774 | CH50: 3109 | CI50: 1628 | CJ50: 1994 | CK50: 2054 | CL50: 3499 | CM50: =+CM64*CM37 -> 2454.4695 | CN50: =+CN64*CN37 -> 2733.9316 | CO50: =+CO64*CO37 -> 2874.4212 | CP50: =+CP64*CP37 -> 3494.3432 | CQ50: =+CQ64*CQ37 -> 2870.3907 | CR50: =+CR64*CR37 -> 3139.2524 | CS50: =+CS64*CS37 -> 3281.9381 | CT50: =+CT64*CT37 -> 3814.7806 | ... DB50: =+DB64*DB37 -> 4575.3419 | DF50: 2360.7
A51: Energy Projects Segment- EBITDA | U51: 2172 | V51: 1868 | W51: 1843 | X51: 2276 | Y51: 2947 | Z51: =+SUM(CE51:CH51) -> 3440 | AA51: =SUM(CI51:CL51) -> 3707 | AB51: =+SUM(CM51:CP51) -> 4868.4722 | AC51: =+SUM(CQ51:CT51) -> 5528.2236 | AD51: =+SUM(CU51:CX51) -> 5744.2506 | AE51: =+SUM(CY51:DB51) -> 5667.849 | BK51: 303 | BL51: 557 | BM51: 554 | BN51: 758 | BO51: 167 | BP51: 364 | BQ51: 557 | BR51: 780 | BS51: 371 | BT51: 392 | BU51: 492 | BV51: 588 | BW51: 432 | BX51: 472 | BY51: 548 | BZ51: 824 | CA51: 608 | CB51: 646 | CC51: 760 | CD51: 933 | CE51: 741 | CF51: 789 | CG51: 912 | CH51: 998 | CI51: 915 | CJ51: 959 | CK51: 755 | CL51: 1078 | CM51: =+CM65*CM38 -> 1124.1495 | CN51: =+CN65*CN38 -> 1170.6696 | CO51: =+CO65*CO38 -> 1243.7142 | CP51: =+CP65*CP38 -> 1329.9388 | CQ51: =+CQ65*CQ38 -> 1340.9415 | CR51: =+CR65*CR38 -> 1354.1333 | CS51: =+CS65*CS38 -> 1391.5018 | CT51: =+CT65*CT38 -> 1441.647 | ... DB51: =+DB65*DB38 -> 1416.0569 | DF51: 882.33
A52: Hi-Tech Manufacturing Segment- EBITDA | U52: 1297 | V52: 1288 | W52: 1167 | X52: 1174 | Y52: 1336 | Z52: =+SUM(CE52:CH52) -> 1682 | AA52: =SUM(CI52:CL52) -> 2356 | AB52: =+SUM(CM52:CP52) -> 2957.4418 | AC52: =+SUM(CQ52:CT52) -> 2892.4773 | AD52: =+SUM(CU52:CX52) -> 2714.9952 | AE52: =+SUM(CY52:DB52) -> 2506.6945 | BK52: 326 | BL52: 326 | BM52: 381 | BN52: 264 | BO52: 127 | BP52: 217 | BQ52: 318 | BR52: 626 | BS52: 238 | BT52: 214 | BU52: 293 | BV52: 422 | BW52: 192 | BX52: 270 | BY52: 293 | BZ52: 419 | CA52: 299 | CB52: 281 | CC52: 344 | CD52: 412 | CE52: 321 | CF52: 265 | CG52: 443 | CH52: 653 | CI52: 486 | CJ52: 404 | CK52: 597 | CL52: 869 | CM52: =+CM66*CM39 -> 705.53355 | CN52: =+CN66*CN39 -> 610.32035 | CO52: =+CO66*CO39 -> 692.04883 | CP52: =+CP66*CP39 -> 949.53903 | CQ52: =+CQ66*CQ39 -> 708.79566 | CR52: =+CR66*CR39 -> 618.13717 | CS52: =+CS66*CS39 -> 681.95719 | CT52: =+CT66*CT39 -> 883.58731 | ... DB52: =+DB66*DB39 -> 725.34815 | DF52: 759.56
A53: Other Segment- EBITDA | U53: 1137 | V53: 1227 | W53: 1112 | X53: 1194 | Y53: 1618 | Z53: =+SUM(CE53:CH53) -> 2061 | AA53: =SUM(CI53:CL53) -> 2222 | AB53: =+SUM(CM53:CP53) -> 2073.3566 | AC53: =+SUM(CQ53:CT53) -> 2064.2081 | AD53: =+SUM(CU53:CX53) -> 2062.1916 | AE53: =+SUM(CY53:DB53) -> 2061.8077 | BK53: 288 | BL53: 360 | BM53: 286 | BN53: 203 | BO53: 48 | BP53: 238 | BQ53: 683 | BR53: 258 | BS53: 225 | BT53: 296 | BU53: 214 | BV53: 377 | BW53: 273 | BX53: 248 | BY53: 294 | BZ53: 379 | CA53: 408 | CB53: 324 | CC53: 373 | CD53: 513 | CE53: 321 | CF53: 413 | CG53: 459 | CH53: 868 | CI53: 458 | CJ53: 443 | CK53: 852 | CL53: 469 | CM53: =+CM67*CM40 -> 527.1131 | CN53: =+CN67*CN40 -> 519.97895 | CO53: =+CO67*CO40 -> 517.79325 | CP53: =+CP67*CP40 -> 508.47132 | CQ53: =+CQ67*CQ40 -> 518.33916 | CR53: =+CR67*CR40 -> 516.14567 | CS53: =+CS67*CS40 -> 515.18735 | CT53: =+CT67*CT40 -> 514.53588 | ... DB53: =+DB67*DB40 -> 515.43064 | DF53: 866.71
A54: Services & Concessions- EBITDA | U54: =+SUM(U55:U57) -> 7941 | V54: =+SUM(V55:V57) -> 7551 | W54: =+SUM(W55:W57) -> 9210 | X54: =+SUM(X55:X57) -> 11580 | Y54: =+SUM(Y55:Y57) -> 13539 | Z54: =+SUM(Z55:Z57) -> 14005 | AA54: =+SUM(AA55:AA57) -> 15532 | AB54: =+SUM(AB55:AB57) -> 15556.673 | ... AE54: =+SUM(AE55:AE57) -> 30529.314 | BK54: =+SUM(BK55:BK57) -> 1768 | BL54: =+SUM(BL55:BL57) -> 2069 | BM54: =+SUM(BM55:BM57) -> 2247 | BN54: =+SUM(BN55:BN57) -> 1857 | BO54: =+SUM(BO55:BO57) -> 1178 | BP54: =+SUM(BP55:BP57) -> 1841 | BQ54: =+SUM(BQ55:BQ57) -> 2030 | BR54: =+SUM(BR55:BR57) -> 2502 | ... DB54: =+SUM(DB55:DB57) -> 9422.6214 | DF54: -217.66
A55: IT & Technology Services Segment- EBITDA | U55: 4645 | V55: 5985 | W55: 7535 | X55: 8492 | Y55: 9061 | Z55: =+SUM(CE55:CH55) -> 9315 | AA55: =SUM(CI55:CL55) -> 10421 | AB55: =+SUM(CM55:CP55) -> 15556.673 | AC55: =+SUM(CQ55:CT55) -> 18929.106 | AD55: =+SUM(CU55:CX55) -> 24019.254 | AE55: =+SUM(CY55:DB55) -> 30529.314 | BK55: 888 | BL55: 1148 | BM55: 1278 | BN55: 1331 | BO55: 1246 | BP55: 1428 | BQ55: 1656 | BR55: 1655 | BS55: 1648 | BT55: 1823 | BU55: 1986 | BV55: 2078 | BW55: 2090 | BX55: 2238 | BY55: 2013 | BZ55: 2151 | CA55: 2236 | CB55: 2257 | CC55: 2319 | CD55: 2249 | CE55: 2300 | CF55: 2482 | CG55: 2256 | CH55: 2277 | CI55: 2462 | CJ55: 2676 | CK55: 2665 | CL55: 2618 | CM55: =+CM59-CM49+CM60 -> 3619.2892 | CN55: =+CN59-CN49+CN60 -> 3820.5156 | CO55: =+CO59-CO49+CO60 -> 3898.8167 | CP55: =+CP59-CP49+CP60 -> 4218.0516 | CQ55: =+CQ59-CQ49+CQ60 -> 4017.8666 | CR55: =+CR59-CR49+CR60 -> 4398.5336 | CS55: =+CS59-CS49+CS60 -> 4735.0072 | CT55: =+CT59-CT49+CT60 -> 5777.6991 | ... DB55: =+DB59-DB49+DB60 -> 9422.6214 | DF55: -217.66
A56: Financial Services Segment- EBITDA | U56: 2757 | V56: 1372 | W56: 1575 | X56: 2373 | Y56: 3144 | Z56: =+SUM(CE56:CH56) -> 3631 | AA56: =SUM(CI56:CL56) -> 4242 | AB56: =+SUM(CM56:CP56) -> 0 | AC56: =+SUM(CQ56:CT56) -> 0 | AD56: =+SUM(CU56:CX56) -> 0 | AE56: =+SUM(CY56:DB56) -> 0 | BK56: 762 | BL56: 774 | BM56: 755 | BN56: 466 | BO56: -107 | BP56: 353 | BQ56: 373 | BR56: 753 | BS56: 257 | BT56: 350 | BU56: 459 | BV56: 509 | BW56: 384 | BX56: 641 | BY56: 660 | BZ56: 688 | CA56: 744 | CB56: 825 | CC56: 853 | CD56: 722 | CE56: 951 | CF56: 973 | CG56: 860 | CH56: 847 | CI56: 984 | CJ56: 1040 | CK56: 1078 | CL56: 1140
A57: Developmental Projects Segment- EBITDA | U57: 539 | V57: 194 | W57: 100 | X57: 715 | Y57: 1334 | Z57: =+SUM(CE57:CH57) -> 1059 | AA57: =SUM(CI57:CL57) -> 869 | AB57: =+SUM(CM57:CP57) -> 0 | AC57: =+SUM(CQ57:CT57) -> 0 | AD57: =+SUM(CU57:CX57) -> 0 | AE57: =+SUM(CY57:DB57) -> 0 | BK57: 118 | BL57: 147 | BM57: 214 | BN57: 60 | BO57: 39 | BP57: 60 | BQ57: 1 | BR57: 94 | BS57: -5 | BT57: 48 | BU57: 31 | BV57: 26 | BW57: 60 | BX57: 69 | BY57: 75 | BZ57: 511 | CA57: 204 | CB57: 715 | CC57: 198 | CD57: 217 | CE57: 225 | CF57: 203 | CG57: 227 | CH57: 404 | CI57: 221 | CJ57: 167 | CK57: 239 | CL57: 242
A58: Corporate EBITDA | U58: 931 | V58: 1862 | W58: 1114 | X58: 1394 | Y58: 1229 | Z58: =+SUM(CE58:CH58) -> 1010 | AA58: =SUM(CI58:CL58) -> 1921 | AB58: =+SUM(CM58:CP58) -> 0 | AC58: =+SUM(CQ58:CT58) -> 0 | AD58: =+SUM(CU58:CX58) -> 0 | AE58: =+SUM(CY58:DB58) -> 0 | BL58: 284 | BM58: 367 | BN58: 280 | BO58: 477 | BP58: 408 | BQ58: 275 | BR58: 702 | BS58: 300 | BT58: 211 | BU58: 305 | BV58: 298 | BW58: 298 | BX58: 408 | BY58: 418 | BZ58: 270 | CA58: 398 | CB58: 385 | CC58: 228 | CD58: 218 | CE58: 124 | CF58: 413 | CG58: 291 | CH58: 182 | CI58: 520 | CJ58: 507 | CK58: 618 | CL58: 276
A59: Total | U59: =+U49+U54+U58 -> 19351 | V59: =+V49+V54+V58 -> 19023 | W59: =+W49+W54+W58 -> 20367 | X59: =+X49+X54+X58 -> 23682 | Y59: =+Y49+Y54+Y58 -> 27652 | Z59: =+Z49+Z54+Z58 -> 30560 | AA59: =+AA49+AA54+AA58 -> 34913 | AB59: =+AB49+AB54+AB58 -> 37013.109 | ... AE59: =+AE49+AE54+AE58 -> 56707.522 | BK59: =+BK49+BK54+BK58 -> 3558 | BL59: =+BL49+BL54+BL58 -> 4762 | BM59: =+BM49+BM54+BM58 -> 4879 | BN59: =+BN49+BN54+BN58 -> 6152 | BO59: =+BO49+BO54+BO58 -> 2397 | BP59: =+BP49+BP54+BP58 -> 3893 | BQ59: =+BQ49+BQ54+BQ58 -> 4845 | BR59: =+BR49+BR54+BR58 -> 7888 | ... CL59: =+CL49+CL54+CL58 -> 10191 | CM59: =+CM190 -> 8658.5748 | CN59: =+CN190 -> 9083.4361 | CO59: =+CO190 -> 9454.8142 | CP59: =+CP190 -> 10728.364 | CQ59: =+CQ190 -> 9684.3535 | CR59: =+CR190 -> 10254.222 | CS59: =+CS190 -> 10833.612 | CT59: =+CT190 -> 12660.27 | ... DB59: =+DB190 -> 16882.819 | DF59: 4984
A60: Checksum- EBITDA | U60: =+U59-U190 -> -4850.12 | V60: =+V59-V190 -> -4108.07 | W60: =+W59-W190 -> -3497.8 | X60: =+X59-X190 -> -2586.98 | Y60: =+Y59-Y190 -> -1523.72 | Z60: =+Z59-Z190 -> -2176.97 | AA60: =+AA59-AA190 -> -2486.46 | AB60: =+AB59-AB190 -> -912.08 | ... AE60: =+AE59-AE190 -> -912.08 | BK60: =+BK59-BK190 -> -1588.97 | BL60: =+BL59-BL190 -> -1283.14 | BM60: =+BM59-BM190 -> -1243.07 | BN60: =+BN59-BN190 -> -904.67 | BO60: =+BO59-BO190 -> -1327.36 | BP60: =+BP59-BP190 -> -1426.51 | BQ60: =+BQ59-BQ190 -> -1220.84 | BR60: =+BR59-BR190 -> -317.43 | ... CL60: =+CL59-CL190 -> -228.02 | CM60: =+CL60 -> -228.02 | CN60: =+CM60 -> -228.02 | CO60: =+CN60 -> -228.02 | CP60: =+CO60 -> -228.02 | CQ60: =+CP60 -> -228.02 | CR60: =+CQ60 -> -228.02 | CS60: =+CR60 -> -228.02 | CT60: =+CS60 -> -228.02 | ... DB60: =+DA60 -> -228.02 | DF60: -332
A62: Segment EBITDA Margin %
A63: Projects & Manufacturing (EBITDA Margin %) | U63: =+U49/U36 -> 0.10013952 | V63: =+V49/V36 -> 0.10279174 | W63: =+W49/W36 -> 0.093063123 | X63: =+X49/X36 -> 0.086213004 | Y63: =+Y49/Y36 -> 0.08159078 | Z63: =+Z49/Z36 -> 0.082985448 | AA63: =+AA49/AA36 -> 0.083149192 | AB63: =+AB49/AB36 -> 0.085080969 | ... AE63: =+AE49/AE36 -> 0.081861759 | BK63: =+BK49/BK36 -> 0.084529656 | BL63: =+BL49/BL36 -> 0.098106292 | BM63: =+BM49/BM36 -> 0.089296274 | BN63: =+BN49/BN36 -> 0.11967927 | BO63: =+BO49/BO36 -> 0.065121994 | BP63: =+BP49/BP36 -> 0.080639623 | BQ63: =+BQ49/BQ36 -> 0.10210645 | BR63: =+BR49/BR36 -> 0.12716857 | ... DB63: =+DB49/DB36 -> 0.08189451 | DF63: 0.085
A64: Infrastructure Projects Segment (EBITDA Margin %) | U64: =+U50/U37 -> 0.081635206 | V64: =+V50/V37 -> 0.085088719 | W64: =+W50/W37 -> 0.08177725 | X64: =+X50/X37 -> 0.069928618 | Y64: =+Y50/Y37 -> 0.062042985 | Z64: =+Z50/Z37 -> 0.064374081 | AA64: =+AA50/AA37 -> 0.068516168 | AB64: =+AB50/AB37 -> 0.074227488 | ... AE64: =+AE50/AE37 -> 0.074758387 | BK64: =+BK50/BK37 -> 0.064219509 | BL64: =+BL50/BL37 -> 0.071842267 | BM64: =+BM50/BM37 -> 0.061317984 | BN64: =+BN50/BN37 -> 0.11119082 | BO64: =+BO50/BO37 -> 0.062568434 | BP64: =+BP50/BP37 -> 0.063613232 | BQ64: =+BQ50/BQ37 -> 0.062041951 | BR64: =+BR50/BR37 -> 0.11509146 | ... CL64: =+CL50/CL37 -> 0.088149342 | CM64: =+AVERAGE(CI64:CL64)+0.5% -> 0.072124138 | CN64: =+AVERAGE(CJ64:CM64)+0.25% -> 0.073502097 | CO64: =+AVERAGE(CK64:CN64) -> 0.073681283 | CP64: =+AVERAGE(CL64:CO64) -> 0.076864215 | CQ64: =+AVERAGE(CM64:CP64) -> 0.074042933 | CR64: =+AVERAGE(CN64:CQ64) -> 0.074522632 | CS64: =+AVERAGE(CO64:CR64) -> 0.074777766 | CT64: =+AVERAGE(CP64:CS64) -> 0.075051887 | CU64: =+AVERAGE(CQ64:CT64) -> 0.074598805 | CV64: =+AVERAGE(CR64:CU64) -> 0.074737772 | ... DB64: =+AVERAGE(CX64:DA64) -> 0.074764963 | DF64: 0.065
A65: Energy Projects Segment (EBITDA Margin %) | U65: =+U51/U38 -> 0.11017551 | V65: =+V51/V38 -> 0.092939947 | W65: =+W51/W38 -> 0.07811639 | X65: =+X51/X38 -> 0.091376265 | Y65: =+Y51/Y38 -> 0.099766411 | Z65: =+Z51/Z38 -> 0.084595711 | AA65: =+AA51/AA38 -> 0.067557224 | AB65: =+AB51/AB38 -> 0.06496324 | ... AE65: =+AE51/AE38 -> 0.06496324 | BK65: =+BK51/BK38 -> 0.070074006 | BL65: =+BL51/BL38 -> 0.11638111 | BM65: =+BM51/BM38 -> 0.10903365 | BN65: =+BN51/BN38 -> 0.13724425 | BO65: =+BO51/BO38 -> 0.048603027 | BP65: =+BP51/BP38 -> 0.076939336 | BQ65: =+BQ51/BQ38 -> 0.10501508 | BR65: =+BR51/BR38 -> 0.11768256 | ... CL65: =+CL51/CL38 -> 0.06496324 | CM65: =+CL65 -> 0.06496324 | CN65: =+CM65 -> 0.06496324 | CO65: =+CN65 -> 0.06496324 | CP65: =+CO65 -> 0.06496324 | CQ65: =+CP65 -> 0.06496324 | CR65: =+CQ65 -> 0.06496324 | CS65: =+CR65 -> 0.06496324 | CT65: =+CS65 -> 0.06496324 | ... DB65: =+DA65 -> 0.06496324 | DF65: 0.06
A66: Hi-Tech Manufacturing Segment (EBITDA Margin %) | U66: =+U52/U39 -> 0.19822711 | V66: =+V52/V39 -> 0.21090552 | W66: =+W52/W39 -> 0.19643158 | X66: =+X52/X39 -> 0.17964805 | Y66: =+Y52/Y39 -> 0.16302624 | Z66: =+Z52/Z39 -> 0.17349149 | AA66: =+AA52/AA39 -> 0.16698561 | AB66: =+AB52/AB39 -> 0.2 | ... AE66: =+AE52/AE39 -> 0.2 | BK66: =+BK52/BK39 -> 0.18021006 | BL66: =+BL52/BL39 -> 0.20698413 | BM66: =+BM52/BM39 -> 0.2207416 | BN66: =+BN52/BN39 -> 0.18422889 | BO66: =+BO52/BO39 -> 0.14923619 | BP66: =+BP52/BP39 -> 0.15885798 | BQ66: =+BQ52/BQ39 -> 0.18119658 | BR66: =+BR52/BR39 -> 0.29320843 | ... CL66: =+CL52/CL39 -> 0.1787698 | CM66: 0.2 | CN66: 0.2 | CO66: 0.2 | CP66: 0.2 | CQ66: 0.2 | CR66: 0.2 | CS66: 0.2 | CT66: 0.2 | CU66: 0.2 | CV66: 0.2 | CW66: 0.2 | CX66: 0.2 | CY66: 0.2 | CZ66: 0.2 | DA66: 0.2 | DB66: 0.2 | DF66: 0.2
A67: Other Segment (EBITDA Margin %) | U67: =+U53/U40 -> 0.17641583 | V67: =+V53/V40 -> 0.20960027 | W67: =+W53/W40 -> 0.18601539 | X67: =+X53/X40 -> 0.19755129 | Y67: =+Y53/Y40 -> 0.21219672 | Z67: =+Z53/Z40 -> 0.29167846 | AA67: =+AA53/AA40 -> 0.3132666 | AB67: =+AB53/AB40 -> 0.30670956 | ... AE67: =+AE53/AE40 -> 0.30500114 | BK67: =+BK53/BK40 -> 0.19875776 | BL67: =+BL53/BL40 -> 0.18329939 | BM67: =+BM53/BM40 -> 0.18668407 | BN67: =+BN53/BN40 -> 0.13533333 | BO67: =+BO53/BO40 -> 0.067226891 | BP67: =+BP53/BP40 -> 0.18016654 | BQ67: =+BQ53/BQ40 -> 0.34338864 | BR67: =+BR53/BR40 -> 0.14098361 | ... CL67: =+CL53/CL40 -> 0.27751479 | CM67: =+AVERAGE(CI67:CL67) -> 0.31190124 | CN67: =+AVERAGE(CJ67:CM67) -> 0.30767985 | CO67: =+AVERAGE(CK67:CN67) -> 0.30638654 | CP67: =+AVERAGE(CL67:CO67) -> 0.30087061 | CQ67: =+AVERAGE(CM67:CP67) -> 0.30670956 | CR67: =+AVERAGE(CN67:CQ67) -> 0.30541164 | CS67: =+AVERAGE(CO67:CR67) -> 0.30484459 | CT67: =+AVERAGE(CP67:CS67) -> 0.3044591 | ... DB67: =+AVERAGE(CX67:DA67) -> 0.30498854 | DF67: 0.334
A69: Depreciation
A70: Projects & Manufacturing- Depreciation | U70: 2924 | V70: 2134 | W70: 1206 | X70: 1406 | Y70: 1815 | Z70: =+SUM(CE70:CH70) -> 2083 | AA70: =SUM(CI70:CL70) -> 2147 | AB70: =+SUM(CM70:CP70) -> 2496 | AC70: =+SUM(CQ70:CT70) -> 2816 | AD70: =+SUM(CU70:CX70) -> 3136 | AE70: =+SUM(CY70:DB70) -> 3456 | BS70: 294 | BT70: 296 | BU70: 301 | BV70: 315 | BW70: 351 | BX70: 344 | BY70: 343 | BZ70: 368 | CA70: 388 | CB70: 428 | CC70: 458 | CD70: 541 | CE70: 509 | CF70: 529 | CG70: 523 | CH70: 522 | CI70: 519 | CJ70: 522 | CK70: 532 | CL70: 574 | CM70: =+CL70+20 -> 594 | CN70: =+CM70+20 -> 614 | CO70: =+CN70+20 -> 634 | CP70: =+CO70+20 -> 654 | CQ70: =+CP70+20 -> 674 | CR70: =+CQ70+20 -> 694 | CS70: =+CR70+20 -> 714 | CT70: =+CS70+20 -> 734 | ... DB70: =+DA70+20 -> 894 | DF70: 552
A71: IT & Technology Services Segment- Depreciation | U71: 1932 | V71: 2508 | W71: 1203 | X71: 1277 | Y71: 1403 | Z71: =+SUM(CE71:CH71) -> 1633 | AA71: =SUM(CI71:CL71) -> 1786 | AB71: =+SUM(CM71:CP71) -> -287.33579 | AC71: =+SUM(CQ71:CT71) -> -446.36309 | AD71: =+SUM(CU71:CX71) -> -623.85511 | AE71: =+SUM(CY71:DB71) -> -817.69382 | BS71: 289 | BT71: 295 | BU71: 302 | BV71: 317 | BW71: 316 | BX71: 333 | BY71: 316 | BZ71: 312 | CA71: 319 | CB71: 356 | CC71: 348 | CD71: 380 | CE71: 389 | CF71: 402 | CG71: 422 | CH71: 420 | CI71: 416 | CJ71: 465 | CK71: 449 | CL71: 456 | CM71: =+CM75-CM70-CM73-CM74 -> -58.0221 | CN71: =+CN75-CN70-CN73-CN74 -> -67.011437 | CO71: =+CO75-CO70-CO73-CO74 -> -76.331094 | CP71: =+CP75-CP70-CP73-CP74 -> -85.971161 | CQ71: =+CQ75-CQ70-CQ73-CQ74 -> -95.922026 | CR71: =+CR75-CR70-CR73-CR74 -> -106.17437 | CS71: =+CS75-CS70-CS73-CS74 -> -116.71913 | CT71: =+CT75-CT70-CT73-CT74 -> -127.54756 | ... DB71: =+DB75-DB70-DB73-DB74 -> -223.41718 | DF71: 533.77
A72: Financial Services Segment- Depreciation | U72: 1060 | V72: 586 | W72: 104 | X72: 113 | Y72: 115 | Z72: =+SUM(CE72:CH72) -> 138 | AA72: =SUM(CI72:CL72) -> 210 | AB72: =+SUM(CM72:CP72) -> 0 | AC72: =+SUM(CQ72:CT72) -> 0 | AD72: =+SUM(CU72:CX72) -> 0 | AE72: =+SUM(CY72:DB72) -> 0 | BS72: 23 | BT72: 28 | BU72: 25 | BV72: 28 | BW72: 28 | BX72: 27 | BY72: 29 | BZ72: 29 | CA72: 30 | CB72: 28 | CC72: 29 | CD72: 28 | CE72: 28 | CF72: 33 | CG72: 36 | CH72: 41 | CI72: 41 | CJ72: 51 | CK72: 58 | CL72: 60
A73: Developmental Projects Segment- Depreciation | U73: 696 | V73: 1808 | W73: 330 | X73: 324 | Y73: 319 | Z73: =+SUM(CE73:CH73) -> 313 | AA73: =SUM(CI73:CL73) -> 320 | AB73: =+SUM(CM73:CP73) -> 0 | AC73: =+SUM(CQ73:CT73) -> 0 | AD73: =+SUM(CU73:CX73) -> 0 | AE73: =+SUM(CY73:DB73) -> 0 | BS73: 86 | BT73: 83 | BU73: 79 | BV73: 82 | BW73: 81 | BX73: 81 | BY73: 81 | BZ73: 81 | CA73: 81 | CB73: 81 | CC73: 79 | CD73: 78 | CE73: 78 | CF73: 78 | CG73: 78 | CH73: 79 | CI73: 78 | CJ73: 80 | CK73: 81 | CL73: 81
A74: Corporate- Depreciation | U74: 1911 | V74: 3793 | W74: 104 | X74: 385 | Y74: 30 | Z74: =+SUM(CE74:CH74) -> -46 | AA74: =SUM(CI74:CL74) -> -98 | AB74: =+SUM(CM74:CP74) -> -12 | AC74: =+SUM(CQ74:CT74) -> -12 | AD74: =+SUM(CU74:CX74) -> -12 | AE74: =+SUM(CY74:DB74) -> -12 | BS74: 26 | BT74: 26 | BU74: 26 | BV74: 26 | BW74: 187 | BX74: 75 | BY74: 59 | BZ74: 64 | CA74: 13 | CB74: 17 | CC74: 5 | CD74: -5 | CE74: -6 | CF74: -19 | CG74: -12 | CH74: -9 | CI74: -21 | CJ74: -27 | CK74: -47 | CL74: -3 | CM74: =+CL74 -> -3 | CN74: =+CM74 -> -3 | CO74: =+CN74 -> -3 | CP74: =+CO74 -> -3 | CQ74: =+CP74 -> -3 | CR74: =+CQ74 -> -3 | CS74: =+CR74 -> -3 | CT74: =+CS74 -> -3 | ... DB74: =+DA74 -> -3 | DF74: -47
A75: Total Deprecation | U75: =+SUM(U70:U74) -> 8523 | V75: =+SUM(V70:V74) -> 10829 | W75: =+SUM(W70:W74) -> 2947 | X75: =+SUM(X70:X74) -> 3505 | Y75: =+SUM(Y70:Y74) -> 3682 | Z75: =+SUM(Z70:Z74) -> 4121 | AA75: =SUM(CI75:CL75) -> 4365 | AB75: =+SUM(CM75:CP75) -> 2196.6642 | AC75: =+SUM(CQ75:CT75) -> 2357.6369 | AD75: =+SUM(CU75:CX75) -> 2500.1449 | AE75: =+SUM(CY75:DB75) -> 2626.3062 | BS75: =+SUM(BS70:BS74) -> 718 | BT75: =+SUM(BT70:BT74) -> 728 | BU75: =+SUM(BU70:BU74) -> 733 | BV75: =+SUM(BV70:BV74) -> 768 | BW75: =+SUM(BW70:BW74) -> 963 | BX75: =+SUM(BX70:BX74) -> 860 | BY75: =+SUM(BY70:BY74) -> 828 | BZ75: =+SUM(BZ70:BZ74) -> 854 | ... CL75: =+SUM(CL70:CL74) -> 1168 | CM75: =+CM194 -> 532.9779 | CN75: =+CN194 -> 543.98856 | CO75: =+CO194 -> 554.66891 | CP75: =+CP194 -> 565.02884 | CQ75: =+CQ194 -> 575.07797 | CR75: =+CR194 -> 584.82563 | CS75: =+CS194 -> 594.28087 | CT75: =+CT194 -> 603.45244 | ... DB75: =+DB194 -> 667.58282 | DF75: 1038.77
A76: Checksum- Depreciation | U76: =+U75-U194 -> 6060.73 | V76: =+V75-V194 -> 7924.79 | W76: =+W75-W194 -> -0.95 | X76: =+X75-X194 -> 2.75 | Y76: =+Y75-Y194 -> -0.33 | Z76: =+Z75-Z194 -> -0.18 | AA76: =+AA75-AA194 -> 0.25 | AB76: =+AB75-AB194 -> 0 | ... AE76: =+AE75-AE194 -> 0 | BS76: =+BS75-BS194 -> 0.62 | BT76: =+BT75-BT194 -> -0.75 | BU76: =+BU75-BU194 -> 0.54 | BV76: =+BV75-BV194 -> -1.36 | BW76: =+BW75-BW194 -> -0.4 | BX76: =+BX75-BX194 -> -0.17 | BY76: =+BY75-BY194 -> 2.82 | BZ76: =+BZ75-BZ194 -> 0.5 | ... DB76: =+DB75-DB194 -> 0 | DF76: -
A78: Segment Finance Cost & Tax Expense
A79: Projects & Manufacturing- SFC & TE | W79: 768 | X79: 435 | Y79: 507 | Z79: =+SUM(CE79:CH79) -> 639 | AA79: =SUM(CI79:CL79) -> 858 | AB79: =+SUM(CM79:CP79) -> 836 | AC79: =+SUM(CQ79:CT79) -> 1156 | AD79: =+SUM(CU79:CX79) -> 1476 | AE79: =+SUM(CY79:DB79) -> 1796 | BS79: 188 | BT79: 177 | BU79: 200 | BV79: 203 | BW79: 68 | BX79: 83 | BY79: 127 | BZ79: 157 | CA79: 104 | CB79: 120 | CC79: 112 | CD79: 171 | CE79: 145 | CF79: 66 | CG79: 55 | CH79: 373 | CI79: 190 | CJ79: 266 | CK79: 243 | CL79: 159 | CM79: =+CL79+20 -> 179 | CN79: =+CM79+20 -> 199 | CO79: =+CN79+20 -> 219 | CP79: =+CO79+20 -> 239 | CQ79: =+CP79+20 -> 259 | CR79: =+CQ79+20 -> 279 | CS79: =+CR79+20 -> 299 | CT79: =+CS79+20 -> 319 | ... DB79: =+DA79+20 -> 479 | DF79: 263
A80: IT & Technology Services Segment- SFC & TE | W80: 1744 | X80: 1980 | Y80: 2195 | Z80: =+SUM(CE80:CH80) -> 2390 | AA80: =SUM(CI80:CL80) -> 2736 | AB80: =+SUM(CM80:CP80) -> 4508 | AC80: =+SUM(CQ80:CT80) -> 4188 | AD80: =+SUM(CU80:CX80) -> 3868 | AE80: =+SUM(CY80:DB80) -> 3548 | BS80: 385 | BT80: 415 | BU80: 462 | BV80: 482 | BW80: 495 | BX80: 510 | BY80: 491 | BZ80: 484 | CA80: 551 | CB80: 526 | CC80: 565 | CD80: 553 | CE80: 585 | CF80: 626 | CG80: 586 | CH80: 593 | CI80: 672 | CJ80: 694 | CK80: 692 | CL80: 678 | CM80: =+CM84-CM79-CM83 -> 1157 | CN80: =+CN84-CN79-CN83 -> 1137 | CO80: =+CO84-CO79-CO83 -> 1117 | CP80: =+CP84-CP79-CP83 -> 1097 | CQ80: =+CQ84-CQ79-CQ83 -> 1077 | CR80: =+CR84-CR79-CR83 -> 1057 | CS80: =+CS84-CS79-CS83 -> 1037 | CT80: =+CT84-CT79-CT83 -> 1017 | ... DB80: =+DB84-DB79-DB83 -> 857 | DF80: 1171
A81: Financial Services Segment- SFC & TE | W81: 426 | X81: 872 | Y81: 712 | Z81: =+SUM(CE81:CH81) -> 848 | AA81: =SUM(CI81:CL81) -> 1027 | AB81: =+SUM(CM81:CP81) -> 0 | AC81: =+SUM(CQ81:CT81) -> 0 | AD81: =+SUM(CU81:CX81) -> 0 | AE81: =+SUM(CY81:DB81) -> 0 | BS81: 61 | BT81: 99 | BU81: 126 | BV81: 140 | BW81: 97 | BX81: 205 | BY81: 327 | BZ81: 243 | CA81: 183 | CB81: 203 | CC81: 185 | CD81: 141 | CE81: 237 | CF81: 243 | CG81: 198 | CH81: 170 | CI81: 242 | CJ81: 254 | CK81: 261 | CL81: 270
A82: Developmental Projects Segment- SFC & TE | W82: 1478 | X82: 1274 | Y82: 1173 | Z82: =+SUM(CE82:CH82) -> 939 | AA82: =SUM(CI82:CL82) -> 946 | AB82: =+SUM(CM82:CP82) -> 0 | AC82: =+SUM(CQ82:CT82) -> 0 | AD82: =+SUM(CU82:CX82) -> 0 | AE82: =+SUM(CY82:DB82) -> 0 | BS82: 370 | BT82: 380 | BU82: 437 | BV82: 291 | BW82: 302 | BX82: 315 | BY82: 325 | BZ82: 332 | CA82: 357 | CB82: 295 | CC82: 277 | CD82: 244 | CE82: 237 | CF82: 241 | CG82: 234 | CH82: 227 | CI82: 243 | CJ82: 236 | CK82: 238 | CL82: 229
A83: Corporate- SFC & TE | W83: 2928 | X83: 3138 | Y83: 3907 | Z83: =+SUM(CE83:CH83) -> 4411 | AA83: =SUM(CI83:CL83) -> 4527 | AB83: =+SUM(CM83:CP83) -> 5672 | AC83: =+SUM(CQ83:CT83) -> 5672 | AD83: =+SUM(CU83:CX83) -> 5672 | AE83: =+SUM(CY83:DB83) -> 5672 | BS83: 543 | BT83: 593 | BU83: 647 | BV83: 1145 | BW83: 433 | BX83: 846 | BY83: 802 | BZ83: 1057 | CA83: 873 | CB83: 855 | CC83: 943 | CD83: 1236 | CE83: 894 | CF83: 1152 | CG83: 1101 | CH83: 1264 | CI83: 969 | CJ83: 961 | CK83: 1179 | CL83: 1418 | CM83: =+CL83 -> 1418 | CN83: =+CM83 -> 1418 | CO83: =+CN83 -> 1418 | CP83: =+CO83 -> 1418 | CQ83: =+CP83 -> 1418 | CR83: =+CQ83 -> 1418 | CS83: =+CR83 -> 1418 | CT83: =+CS83 -> 1418 | ... DB83: =+DA83 -> 1418 | DF83: 1179
A84: Total Finance Cost & tax Expenses | W84: =+SUM(W79:W83) -> 7344 | X84: =+SUM(X79:X83) -> 7699 | Y84: =+SUM(Y79:Y83) -> 8494 | Z84: =+SUM(Z79:Z83) -> 9227 | AA84: =SUM(CI84:CL84) -> 10094 | AB84: =+SUM(CM84:CP84) -> 11016 | AC84: =+SUM(CQ84:CT84) -> 11016 | AD84: =+SUM(CU84:CX84) -> 11016 | AE84: =+SUM(CY84:DB84) -> 11016 | BS84: =+SUM(BS79:BS83) -> 1547 | BT84: =+SUM(BT79:BT83) -> 1664 | BU84: =+SUM(BU79:BU83) -> 1872 | BV84: =+SUM(BV79:BV83) -> 2261 | BW84: =+SUM(BW79:BW83) -> 1395 | BX84: =+SUM(BX79:BX83) -> 1959 | BY84: =+SUM(BY79:BY83) -> 2072 | BZ84: =+SUM(BZ79:BZ83) -> 2273 | ... CL84: =+SUM(CL79:CL83) -> 2754 | CM84: =+CL84 -> 2754 | CN84: =+CM84 -> 2754 | CO84: =+CN84 -> 2754 | CP84: =+CO84 -> 2754 | CQ84: =+CP84 -> 2754 | CR84: =+CQ84 -> 2754 | CS84: =+CR84 -> 2754 | CT84: =+CS84 -> 2754 | ... DB84: =+DA84 -> 2754 | DF84: 2613
A86: Segment Non Controlling Interest
A87: Projects & Manufacturing- NCI | W87: 2 | X87: -38 | Y87: 15 | Z87: =+SUM(CE87:CH87) -> 25 | AA87: =SUM(CI87:CL87) -> 53 | AB87: =+SUM(CM87:CP87) -> 132 | AC87: =+SUM(CQ87:CT87) -> 132 | AD87: =+SUM(CU87:CX87) -> 132 | AE87: =+SUM(CY87:DB87) -> 132 | BS87: 0 | BT87: -3 | BU87: -2 | BV87: 7 | BW87: -2 | BX87: -7 | BY87: -2 | BZ87: -27 | CA87: -2 | CB87: 0 | CC87: -2 | CD87: 19 | CE87: 0 | CF87: 4 | CG87: 1 | CH87: 20 | CI87: 2 | CJ87: 15 | CK87: 3 | CL87: 33 | CM87: =+CL87 -> 33 | CN87: =+CM87 -> 33 | CO87: =+CN87 -> 33 | CP87: =+CO87 -> 33 | CQ87: =+CP87 -> 33 | CR87: =+CQ87 -> 33 | CS87: =+CR87 -> 33 | CT87: =+CS87 -> 33 | ... DB87: =+DA87 -> 33 | DF87: 3
A88: IT & Technology Services Segment- NCI | W88: 1389 | X88: 1621 | Y88: 1719 | Z88: =+SUM(CE88:CH88) -> 1719 | AA88: =SUM(CI88:CL88) -> 1820 | AB88: =+SUM(CM88:CP88) -> 2020 | AC88: =+SUM(CQ88:CT88) -> 2020 | AD88: =+SUM(CU88:CX88) -> 2020 | AE88: =+SUM(CY88:DB88) -> 2020 | BS88: 295 | BT88: 335 | BU88: 369 | BV88: 390 | BW88: 397 | BX88: 429 | BY88: 380 | BZ88: 415 | CA88: 430 | CB88: 431 | CC88: 440 | CD88: 418 | CE88: 426 | CF88: 468 | CG88: 406 | CH88: 419 | CI88: 464 | CJ88: 492 | CK88: 359 | CL88: 505 | CM88: =+CL88 -> 505 | CN88: =+CM88 -> 505 | CO88: =+CN88 -> 505 | CP88: =+CO88 -> 505 | CQ88: =+CP88 -> 505 | CR88: =+CQ88 -> 505 | CS88: =+CR88 -> 505 | CT88: =+CS88 -> 505 | ... DB88: =+DA88 -> 505 | DF88: 359
A89: Financial Services Segment- NCI | W89: 365 | X89: 450 | Y89: 781 | Z89: =+SUM(CE89:CH89) -> 903 | AA89: =SUM(CI89:CL89) -> 1008 | AB89: =+SUM(CM89:CP89) -> 1100 | AC89: =+SUM(CQ89:CT89) -> 1100 | AD89: =+SUM(CU89:CX89) -> 1100 | AE89: =+SUM(CY89:DB89) -> 1100 | BS89: 62 | BT89: 80 | BU89: 100 | BV89: 123 | BW89: 87 | BX89: 137 | BY89: 141 | BZ89: 85 | CA89: 179 | CB89: 199 | CC89: 216 | CD89: 187 | CE89: 234 | CF89: 235 | CG89: 210 | CH89: 224 | CI89: 236 | CJ89: 248 | CK89: 249 | CL89: 275 | CM89: =+CL89 -> 275 | CN89: =+CM89 -> 275 | CO89: =+CN89 -> 275 | CP89: =+CO89 -> 275 | CQ89: =+CP89 -> 275 | CR89: =+CQ89 -> 275 | CS89: =+CR89 -> 275 | CT89: =+CS89 -> 275 | ... DB89: =+DA89 -> 275 | DF89: 249
A90: Developmental Projects Segment- NCI | W90: 0 | X90: 0 | Y90: 0 | Z90: =+SUM(CE90:CH90) -> 0 | AA90: =SUM(CI90:CL90) -> 0 | AB90: =+SUM(CM90:CP90) -> 0 | AC90: =+SUM(CQ90:CT90) -> 0 | AD90: =+SUM(CU90:CX90) -> 0 | AE90: =+SUM(CY90:DB90) -> 0 | BS90: 0 | BT90: 0 | BU90: 0 | BV90: 0 | BW90: 0 | BX90: 0 | BY90: 0 | BZ90: 0 | CA90: 0 | CB90: 0 | CC90: 0 | CD90: 0 | CE90: 0 | CF90: 0 | CG90: 0 | CH90: 0 | CI90: 0 | CJ90: 0 | CK90: 0 | CL90: 0 | CM90: =+CL90 -> 0 | CN90: =+CM90 -> 0 | CO90: =+CN90 -> 0 | CP90: =+CO90 -> 0 | CQ90: =+CP90 -> 0 | CR90: =+CQ90 -> 0 | CS90: =+CR90 -> 0 | CT90: =+CS90 -> 0 | ... DB90: =+DA90 -> 0 | DF90: -
A91: Corporate- NCI | W91: -8 | X91: 29 | Y91: -30 | Z91: =+SUM(CE91:CH91) -> -11 | AA91: =SUM(CI91:CL91) -> -13 | AB91: =+SUM(CM91:CP91) -> -24 | AC91: =+SUM(CQ91:CT91) -> -24 | AD91: =+SUM(CU91:CX91) -> -24 | AE91: =+SUM(CY91:DB91) -> -24 | BS91: 0 | BT91: 0 | BU91: -5 | BV91: -3 | BW91: 45 | BX91: -3 | BY91: -12 | BZ91: -1 | CA91: -5 | CB91: -8 | CC91: -9 | CD91: -8 | CE91: -1 | CF91: -3 | CG91: -2 | CH91: -5 | CI91: -2 | CJ91: -3 | CK91: -2 | CL91: -6 | CM91: =+CL91 -> -6 | CN91: =+CM91 -> -6 | CO91: =+CN91 -> -6 | CP91: =+CO91 -> -6 | CQ91: =+CP91 -> -6 | CR91: =+CQ91 -> -6 | CS91: =+CR91 -> -6 | CT91: =+CS91 -> -6 | ... DB91: =+DA91 -> -6 | DF91: -2
A92: Total- NCI | W92: =+SUM(W87:W91) -> 1748 | X92: =+SUM(X87:X91) -> 2062 | Y92: =+SUM(Y87:Y91) -> 2485 | Z92: =+SUM(Z87:Z91) -> 2636 | AA92: =+SUM(AA87:AA91) -> 2868 | AB92: =+SUM(AB87:AB91) -> 3228 | AC92: =+SUM(AC87:AC91) -> 3228 | AD92: =+SUM(AD87:AD91) -> 3228 | AE92: =+SUM(AE87:AE91) -> 3228 | BS92: =+SUM(BS87:BS91) -> 357 | BT92: =+SUM(BT87:BT91) -> 412 | BU92: =+SUM(BU87:BU91) -> 462 | BV92: =+SUM(BV87:BV91) -> 517 | BW92: =+SUM(BW87:BW91) -> 527 | BX92: =+SUM(BX87:BX91) -> 556 | BY92: =+SUM(BY87:BY91) -> 507 | BZ92: =+SUM(BZ87:BZ91) -> 472 | ... DB92: =+SUM(DB87:DB91) -> 807 | DF92: 609
A95: Segment Share in profit/loss of JV/Associates - Cr
A96: Projects & Manufacturing- JV & Associate share | W96: -108 | X96: 18 | Y96: 21 | Z96: =+SUM(CE96:CH96) -> 15 | AA96: =SUM(CI96:CL96) -> 161 | AB96: =+SUM(CM96:CP96) -> 688 | AC96: =+SUM(CQ96:CT96) -> 688 | AD96: =+SUM(CU96:CX96) -> 688 | AE96: =+SUM(CY96:DB96) -> 688 | BS96: -20 | BT96: -27 | BU96: -22 | BV96: -39 | BW96: 44 | BX96: 2 | BY96: -16 | BZ96: -12 | CA96: 21 | CB96: 10 | CC96: 1 | CD96: -11 | CE96: -5 | CF96: 14 | CG96: 27 | CH96: -21 | CI96: -5 | CJ96: 0 | CK96: -6 | CL96: 172 | CM96: =+CL96 -> 172 | CN96: =+CM96 -> 172 | CO96: =+CN96 -> 172 | CP96: =+CO96 -> 172 | CQ96: =+CP96 -> 172 | CR96: =+CQ96 -> 172 | CS96: =+CR96 -> 172 | CT96: =+CS96 -> 172 | ... DB96: =+DA96 -> 172 | DF96: -6
A97: IT & Technology Services Segment- JV & Associate share | W97: -93 | X97: 0 | Y97: 0 | Z97: =+SUM(CE97:CH97) -> 2 | AA97: =SUM(CI97:CL97) -> 44 | AB97: =+SUM(CM97:CP97) -> 48 | AC97: =+SUM(CQ97:CT97) -> 48 | AD97: =+SUM(CU97:CX97) -> 48 | AE97: =+SUM(CY97:DB97) -> 48 | BS97: 0 | BT97: 0 | BU97: 0 | BV97: -93 | BW97: 0 | BX97: 0 | BY97: 0 | BZ97: 0 | CA97: 0 | CB97: 0 | CC97: 0 | CD97: 0 | CE97: 0 | CF97: 0 | CG97: 0 | CH97: 2 | CI97: 12 | CJ97: 9 | CK97: 11 | CL97: 12 | CM97: =+CL97 -> 12 | CN97: =+CM97 -> 12 | CO97: =+CN97 -> 12 | CP97: =+CO97 -> 12 | CQ97: =+CP97 -> 12 | CR97: =+CQ97 -> 12 | CS97: =+CR97 -> 12 | CT97: =+CS97 -> 12 | ... DB97: =+DA97 -> 12 | DF97: 11
A98: Financial Services Segment- JV & Associate share | W98: 0 | X98: 0 | Y98: 0 | Z98: =+SUM(CE98:CH98) -> 0 | AA98: =SUM(CI98:CL98) -> 0 | AB98: =+SUM(CM98:CP98) -> 0 | AC98: =+SUM(CQ98:CT98) -> 0 | AD98: =+SUM(CU98:CX98) -> 0 | AE98: =+SUM(CY98:DB98) -> 0 | BS98: 0 | BT98: 0 | BU98: 0 | BV98: 0 | BW98: 0 | BX98: 0 | BY98: 0 | BZ98: 0 | CA98: 0 | CB98: 0 | CC98: 0 | CD98: 0 | CE98: 0 | CF98: 0 | CG98: 0 | CH98: 0 | CI98: 0 | CJ98: 0 | CK98: 0 | CL98: 0 | CM98: =+CL98 -> 0 | CN98: =+CM98 -> 0 | CO98: =+CN98 -> 0 | CP98: =+CO98 -> 0 | CQ98: =+CP98 -> 0 | CR98: =+CQ98 -> 0 | CS98: =+CR98 -> 0 | CT98: =+CS98 -> 0 | ... DB98: =+DA98 -> 0 | DF98: -
A99: Developmental Projects Segment- JV & Associate share | W99: 72 | X99: 75 | Y99: 1 | Z99: =+SUM(CE99:CH99) -> -1 | AA99: =SUM(CI99:CL99) -> 0 | AB99: =+SUM(CM99:CP99) -> 0 | AC99: =+SUM(CQ99:CT99) -> 0 | AD99: =+SUM(CU99:CX99) -> 0 | AE99: =+SUM(CY99:DB99) -> 0 | BS99: 45 | BT99: 26 | BU99: 1 | BV99: 0 | BW99: 20 | BX99: 32 | BY99: 23 | BZ99: 0 | CA99: 0 | CB99: 0 | CC99: 0 | CD99: 1 | CE99: 0 | CF99: 0 | CG99: 0 | CH99: -1 | CI99: 0 | CJ99: 0 | CK99: 0 | CL99: 0 | CM99: =+CL99 -> 0 | CN99: =+CM99 -> 0 | CO99: =+CN99 -> 0 | CP99: =+CO99 -> 0 | CQ99: =+CP99 -> 0 | CR99: =+CQ99 -> 0 | CS99: =+CR99 -> 0 | CT99: =+CS99 -> 0 | ... DB99: =+DA99 -> 0 | DF99: -
A100: Corporate- JV & Associate share | W100: 0 | X100: 0 | Y100: 0 | Z100: =+SUM(CE100:CH100) -> 0 | AA100: =SUM(CI100:CL100) -> 0 | AB100: =+SUM(CM100:CP100) -> 0 | AC100: =+SUM(CQ100:CT100) -> 0 | AD100: =+SUM(CU100:CX100) -> 0 | AE100: =+SUM(CY100:DB100) -> 0 | BS100: 0 | BT100: 0 | BU100: 0 | BV100: 0 | BW100: 0 | BX100: 0 | BY100: 0 | BZ100: 0 | CA100: 0 | CB100: 0 | CC100: 0 | CD100: 0 | CE100: 0 | CF100: 0 | CG100: 0 | CH100: 0 | CI100: 0 | CJ100: 0 | CK100: 0 | CL100: 0 | CM100: =+CL100 -> 0 | CN100: =+CM100 -> 0 | CO100: =+CN100 -> 0 | CP100: =+CO100 -> 0 | CQ100: =+CP100 -> 0 | CR100: =+CQ100 -> 0 | CS100: =+CR100 -> 0 | CT100: =+CS100 -> 0 | ... DB100: =+DA100 -> 0 | DF100: -
A101: Total - JV & Associate share | W101: =+SUM(W96:W100) -> -129 | X101: =+SUM(X96:X100) -> 93 | Y101: =+SUM(Y96:Y100) -> 22 | Z101: =+SUM(Z96:Z100) -> 16 | AA101: =+SUM(AA96:AA100) -> 205 | AB101: =+SUM(AB96:AB100) -> 736 | AC101: =+SUM(AC96:AC100) -> 736 | AD101: =+SUM(AD96:AD100) -> 736 | AE101: =+SUM(AE96:AE100) -> 736 | BS101: =+SUM(BS96:BS100) -> 25 | BT101: =+SUM(BT96:BT100) -> -1 | BU101: =+SUM(BU96:BU100) -> -21 | BV101: =+SUM(BV96:BV100) -> -132 | BW101: =+SUM(BW96:BW100) -> 64 | BX101: =+SUM(BX96:BX100) -> 34 | BY101: =+SUM(BY96:BY100) -> 7 | BZ101: =+SUM(BZ96:BZ100) -> -12 | ... DB101: =+SUM(DB96:DB100) -> 184 | DF101: 5
A103: Segment Exceptional Items (Net of Tax)
A104: Projects & Manufacturing-SEI | W104: 0 | X104: 0 | Y104: 0 | Z104: =+SUM(CE104:CH104) -> 0 | AA104: =SUM(CI104:CL104) -> 0 | AB104: =+SUM(CM104:CP104) -> 0 | AC104: =+SUM(CQ104:CT104) -> 0 | AD104: =+SUM(CU104:CX104) -> 0 | AE104: =+SUM(CY104:DB104) -> 0 | BS104: 0 | BT104: 0 | BU104: 0 | BV104: 0 | BW104: 0 | BX104: 0 | BY104: 0 | BZ104: 0 | CA104: 0 | CB104: 0 | CC104: 0 | CD104: 0 | CE104: 0 | CF104: 0 | CG104: 0 | CH104: 0 | CI104: 0 | CJ104: 0 | CK104: =+CJ104 -> 0 | CL104: =+CK104 -> 0 | CM104: =+CL104 -> 0 | CN104: =+CM104 -> 0 | CO104: =+CN104 -> 0 | CP104: =+CO104 -> 0 | CQ104: =+CP104 -> 0 | CR104: =+CQ104 -> 0 | ... DB104: =+DA104 -> 0 | DF104: -
A105: IT & Technology Services Segment-SEI | CK105: 468 | CL105: -47 | CM105: 0 | CN105: =+CM105 -> 0 | CO105: =+CN105 -> 0 | CP105: =+CO105 -> 0 | CQ105: =+CP105 -> 0 | CR105: =+CQ105 -> 0 | CS105: =+CR105 -> 0 | CT105: =+CS105 -> 0 | CU105: =+CT105 -> 0 | ... DB105: =+DA105 -> 0 | DF105: -
A106: Financial Services Segment-SEI | W106: 0 | X106: 0 | Y106: 0 | Z106: =+SUM(CE106:CH106) -> 0 | AA106: =SUM(CI106:CL106) -> 21 | AB106: =+SUM(CM106:CP106) -> 0 | AC106: =+SUM(CQ106:CT106) -> 0 | AD106: =+SUM(CU106:CX106) -> 0 | AE106: =+SUM(CY106:DB106) -> 0 | BS106: 0 | BT106: 0 | BU106: 0 | BV106: 0 | BW106: 0 | BX106: 0 | BY106: 0 | BZ106: 0 | CA106: 0 | CB106: 0 | CC106: 0 | CD106: 0 | CE106: 0 | CF106: 0 | CG106: 0 | CH106: 0 | CI106: 0 | CJ106: 0 | CK106: 21 | CL106: 0 | CM106: =+CL106 -> 0 | CN106: =+CM106 -> 0 | CO106: =+CN106 -> 0 | CP106: =+CO106 -> 0 | CQ106: =+CP106 -> 0 | CR106: =+CQ106 -> 0 | CS106: =+CR106 -> 0 | CT106: =+CS106 -> 0 | ... DB106: =+DA106 -> 0 | DF106: -
A107: Developmental Projects Segment-SEI | W107: 0 | X107: 0 | Y107: 0 | Z107: =+SUM(CE107:CH107) -> 0 | AA107: =SUM(CI107:CL107) -> 0 | AB107: =+SUM(CM107:CP107) -> 0 | AC107: =+SUM(CQ107:CT107) -> 0 | AD107: =+SUM(CU107:CX107) -> 0 | AE107: =+SUM(CY107:DB107) -> 0 | BS107: 0 | BT107: 0 | BU107: 0 | BV107: 0 | BW107: 0 | BX107: 0 | BY107: 0 | BZ107: 0 | CA107: 0 | CB107: 0 | CC107: 0 | CD107: 0 | CE107: 0 | CF107: 0 | CG107: 0 | CH107: 0 | CI107: 0 | CJ107: 0 | CK107: 0 | CL107: 0 | CM107: =+CL107 -> 0 | CN107: =+CM107 -> 0 | CO107: =+CN107 -> 0 | CP107: =+CO107 -> 0 | CQ107: =+CP107 -> 0 | CR107: =+CQ107 -> 0 | CS107: =+CR107 -> 0 | CT107: =+CS107 -> 0 | ... DB107: =+DA107 -> 0 | DF107: -
A108: Corporate-SEI | W108: -97 | X108: -136 | Y108: -94 | Z108: =+SUM(CE108:CH108) -> -475 | AA108: =SUM(CI108:CL108) -> 850 | AB108: =+SUM(CM108:CP108) -> 0 | AC108: =+SUM(CQ108:CT108) -> 0 | AD108: =+SUM(CU108:CX108) -> 0 | AE108: =+SUM(CY108:DB108) -> 0 | BS108: 0 | BT108: -97 | BU108: 0 | BV108: 0 | BW108: 0 | BX108: 0 | BY108: -136 | BZ108: 0 | CA108: 0 | CB108: 0 | CC108: 0 | CD108: -94 | CE108: 0 | CF108: 0 | CG108: 0 | CH108: -475 | CI108: 0 | CJ108: 0 | CK108: 854 | CL108: -4 | CM108: 0 | CN108: =+CM108 -> 0 | CO108: =+CN108 -> 0 | CP108: =+CO108 -> 0 | CQ108: =+CP108 -> 0 | CR108: =+CQ108 -> 0 | CS108: =+CR108 -> 0 | CT108: =+CS108 -> 0 | CU108: =+CT108 -> 0 | ... DB108: =+DA108 -> 0 | DF108: -
A109: Total -SEI | W109: =+SUM(W103:W108) -> -97 | X109: =+SUM(X103:X108) -> -136 | Y109: =+SUM(Y103:Y108) -> -94 | Z109: =+SUM(Z103:Z108) -> -475 | AA109: =+SUM(AA103:AA108) -> 871 | AB109: =+SUM(AB103:AB108) -> 0 | AC109: =+SUM(AC103:AC108) -> 0 | AD109: =+SUM(AD103:AD108) -> 0 | AE109: =+SUM(AE103:AE108) -> 0 | BS109: =+SUM(BS104:BS108) -> 0 | BT109: =+SUM(BT104:BT108) -> -97 | BU109: =+SUM(BU104:BU108) -> 0 | BV109: =+SUM(BV104:BV108) -> 0 | BW109: =+SUM(BW104:BW108) -> 0 | BX109: =+SUM(BX104:BX108) -> 0 | BY109: =+SUM(BY104:BY108) -> -136 | BZ109: =+SUM(BZ104:BZ108) -> 0 | ... DB109: =+SUM(DB104:DB108) -> 0 | DF109: -
A111: Segment PAT - Cr
A112: Projects & Manufacturing- PAT | W112: =+W49-W70-W79-W87-W96-W104 -> 8175 | X112: =+X49-X70-X79-X87-X96-X104 -> 8887 | Y112: =+Y49-Y70-Y79-Y87-Y96-Y104 -> 10526 | Z112: =+SUM(CE112:CH112) -> 12783 | AA112: =SUM(CI112:CL112) -> 14241 | AB112: =+SUM(CM112:CP112) -> 17304.436 | AC112: =+SUM(CQ112:CT112) -> 18799.271 | AD112: =+SUM(CU112:CX112) -> 19630.734 | AE112: =+SUM(CY112:DB112) -> 20106.208 | BS112: =+BS49-BS70-BS79-BS87-BS96-BS104 -> 1108 | BT112: =+BT49-BT70-BT79-BT87-BT96-BT104 -> 1611 | BU112: =+BU49-BU70-BU79-BU87-BU96-BU104 -> 1820 | BV112: =+BV49-BV70-BV79-BV87-BV96-BV104 -> 3636 | BW112: =+BW49-BW70-BW79-BW87-BW96-BW104 -> 1355 | BX112: =+BX49-BX70-BX79-BX87-BX96-BX104 -> 1855 | BY112: =+BY49-BY70-BY79-BY87-BY96-BY104 -> 2210 | BZ112: =+BZ49-BZ70-BZ79-BZ87-BZ96-BZ104 -> 3467 | ... DB112: =+DB49-DB70-DB79-DB87-DB96-DB104 -> 5654.1776 | DF112: 4057.31
...

Sheet QTR Raw
A1: ='Annual Raw'!A1 -> 100510 | B1: X | C1: 201206 | D1: 201209 | E1: 201212 | F1: 201303 | G1: 201306 | H1: 201309 | I1: 201312 | J1: 201403 | K1: 201406 | L1: 201409 | M1: 201412 | N1: 201503 | O1: 201506 | P1: 201509 | Q1: 201512 | R1: 201603 | S1: 201606 | T1: 201609 | U1: 201612 | V1: 201703 | W1: 201706 | X1: 201709 | Y1: 201712 | Z1: 201803 | AA1: 201806 | AB1: 201809 | AC1: 201812 | AD1: 201903 | AE1: 201906 | AF1: 201909 | AG1: 201912 | AH1: 202003 | AI1: 202006 | AJ1: 202009 | AK1: 202012 | AL1: 202103 | AM1: 202106 | AN1: 202109 | AO1: 202112 | AP1: 202203 | AQ1: 202206 | AR1: 202209 | AS1: 202212 | AT1: 202303 | AU1: 202306 | AV1: 202309 | AW1: 202312 | AX1: 202403 | AY1: 202406 | AZ1: 202409 | BA1: 202412 | BB1: 202503 | BC1: 202506 | BD1: 202509 | BE1: 202512 | BF1: 202603 | BG1: 202606 | BH1: 202609 | BI1: 202612 | BJ1: 202703 | BK1: 202706 | BL1: 202709 | BM1: 202712 | BN1: 202803 | BO1: 202806 | BP1: 202809 | BQ1: 202812 | BR1: 202903 | BS1: 202906 | BT1: 202909 | BU1: 202912 | BV1: 203003
A3: Field Description | B3: Field Name
A4: Company Name | B4: CD_COMPNAME | C4: =_xll.EQNXTDZ(A1,B4,C1) -> Larsen & Toubro Ltd.
A5: Date End | B5: QTR_DATE_END | C5: =_xll.EQNXTDZ($A$1,$B5,C$1,$B$1) -> 201206 | D5: =_xll.EQNXTDZ($A$1,$B5,D$1,$B$1) -> 201209 | E5: =_xll.EQNXTDZ($A$1,$B5,E$1,$B$1) -> 201212 | F5: =_xll.EQNXTDZ($A$1,$B5,F$1,$B$1) -> 201303 | G5: =_xll.EQNXTDZ($A$1,$B5,G$1,$B$1) -> 201306 | H5: =_xll.EQNXTDZ($A$1,$B5,H$1,$B$1) -> 201309 | I5: =_xll.EQNXTDZ($A$1,$B5,I$1,$B$1) -> 201312 | J5: =_xll.EQNXTDZ($A$1,$B5,J$1,$B$1) -> 201403 | ... BV5: =_xll.EQNXTDZ($A$1,$B5,BV$1,$B$1) -> 0
A6: Gross Sales | B6: QTR_GROSS_SALE | C6: =_xll.EQNXTDZ($A$1,$B6,C$1,$B$1) -> 12078.33 | D6: =_xll.EQNXTDZ($A$1,$B6,D$1,$B$1) -> 13327.53 | E6: =_xll.EQNXTDZ($A$1,$B6,E$1,$B$1) -> 13016.04 | F6: =_xll.EQNXTDZ($A$1,$B6,F$1,$B$1) -> 18266.05 | G6: =_xll.EQNXTDZ($A$1,$B6,G$1,$B$1) -> 17419.56 | H6: =_xll.EQNXTDZ($A$1,$B6,H$1,$B$1) -> 19313.62 | I6: =_xll.EQNXTDZ($A$1,$B6,I$1,$B$1) -> 21928.54 | J6: =_xll.EQNXTDZ($A$1,$B6,J$1,$B$1) -> 27227.32 | ... BV6: =_xll.EQNXTDZ($A$1,$B6,BV$1,$B$1) -> 0
A7: Less: Excise Duty | B7: QTR_EXCISE_DUTY | C7: =_xll.EQNXTDZ($A$1,$B7,C$1,$B$1) -> 122.98 | D7: =_xll.EQNXTDZ($A$1,$B7,D$1,$B$1) -> 132.3 | E7: =_xll.EQNXTDZ($A$1,$B7,E$1,$B$1) -> 146.7 | F7: =_xll.EQNXTDZ($A$1,$B7,F$1,$B$1) -> 190.45 | G7: =_xll.EQNXTDZ($A$1,$B7,G$1,$B$1) -> 178.42 | H7: =_xll.EQNXTDZ($A$1,$B7,H$1,$B$1) -> 182.85 | I7: =_xll.EQNXTDZ($A$1,$B7,I$1,$B$1) -> 196.19 | J7: =_xll.EQNXTDZ($A$1,$B7,J$1,$B$1) -> 203.18 | ... BV7: =_xll.EQNXTDZ($A$1,$B7,BV$1,$B$1) -> 0
A8: Other operating income | B8: QTR_JOB_WORKS | C8: =_xll.EQNXTDZ($A$1,$B8,C$1,$B$1) -> 0 | D8: =_xll.EQNXTDZ($A$1,$B8,D$1,$B$1) -> 0 | E8: =_xll.EQNXTDZ($A$1,$B8,E$1,$B$1) -> 0 | F8: =_xll.EQNXTDZ($A$1,$B8,F$1,$B$1) -> 0 | G8: =_xll.EQNXTDZ($A$1,$B8,G$1,$B$1) -> 0 | H8: =_xll.EQNXTDZ($A$1,$B8,H$1,$B$1) -> 0 | I8: =_xll.EQNXTDZ($A$1,$B8,I$1,$B$1) -> 0 | J8: =_xll.EQNXTDZ($A$1,$B8,J$1,$B$1) -> 0 | ... BV8: =_xll.EQNXTDZ($A$1,$B8,BV$1,$B$1) -> 0
A9: Net Sales & Other Operating Income | B9: QTR_NET_SALES | C9: =_xll.EQNXTDZ($A$1,$B9,C$1,$B$1) -> 11955.35 | D9: =_xll.EQNXTDZ($A$1,$B9,D$1,$B$1) -> 13195.23 | E9: =_xll.EQNXTDZ($A$1,$B9,E$1,$B$1) -> 12869.34 | F9: =_xll.EQNXTDZ($A$1,$B9,F$1,$B$1) -> 18075.6 | G9: =_xll.EQNXTDZ($A$1,$B9,G$1,$B$1) -> 17241.14 | H9: =_xll.EQNXTDZ($A$1,$B9,H$1,$B$1) -> 19130.77 | I9: =_xll.EQNXTDZ($A$1,$B9,I$1,$B$1) -> 21732.35 | J9: =_xll.EQNXTDZ($A$1,$B9,J$1,$B$1) -> 27024.14 | ... BV9: =_xll.EQNXTDZ($A$1,$B9,BV$1,$B$1) -> 0
A10: (Increase) / Decrease In Stocks | B10: QTR_INC_DEC_INVENTORY | C10: =_xll.EQNXTDZ($A$1,$B10,C$1,$B$1) -> -511.51 | D10: =_xll.EQNXTDZ($A$1,$B10,D$1,$B$1) -> -881.21 | E10: =_xll.EQNXTDZ($A$1,$B10,E$1,$B$1) -> -542.87 | F10: =_xll.EQNXTDZ($A$1,$B10,F$1,$B$1) -> 831.73 | G10: =_xll.EQNXTDZ($A$1,$B10,G$1,$B$1) -> -1875.53 | H10: =_xll.EQNXTDZ($A$1,$B10,H$1,$B$1) -> -339.64 | I10: =_xll.EQNXTDZ($A$1,$B10,I$1,$B$1) -> -69.38 | J10: =_xll.EQNXTDZ($A$1,$B10,J$1,$B$1) -> 1735.38 | ... BV10: =_xll.EQNXTDZ($A$1,$B10,BV$1,$B$1) -> 0
A11: Cost of Services & Raw Materials | B11: QTR_RAW_MATERIAL_COST | C11: =_xll.EQNXTDZ($A$1,$B11,C$1,$B$1) -> 3720.05 | D11: =_xll.EQNXTDZ($A$1,$B11,D$1,$B$1) -> 3191.01 | E11: =_xll.EQNXTDZ($A$1,$B11,E$1,$B$1) -> 2031.46 | F11: =_xll.EQNXTDZ($A$1,$B11,F$1,$B$1) -> 2643.42 | G11: =_xll.EQNXTDZ($A$1,$B11,G$1,$B$1) -> 3148.88 | H11: =_xll.EQNXTDZ($A$1,$B11,H$1,$B$1) -> 3223.99 | I11: =_xll.EQNXTDZ($A$1,$B11,I$1,$B$1) -> 2851.44 | J11: =_xll.EQNXTDZ($A$1,$B11,J$1,$B$1) -> 2936.93 | ... BV11: =_xll.EQNXTDZ($A$1,$B11,BV$1,$B$1) -> 0
A12: Purchase of Finished Goods | B12: QTR_PURCHASE_FIN_GOOD | C12: =_xll.EQNXTDZ($A$1,$B12,C$1,$B$1) -> 501.66 | D12: =_xll.EQNXTDZ($A$1,$B12,D$1,$B$1) -> 437.12 | E12: =_xll.EQNXTDZ($A$1,$B12,E$1,$B$1) -> 516.58 | F12: =_xll.EQNXTDZ($A$1,$B12,F$1,$B$1) -> 607.86 | G12: =_xll.EQNXTDZ($A$1,$B12,G$1,$B$1) -> 407.75 | H12: =_xll.EQNXTDZ($A$1,$B12,H$1,$B$1) -> 471.08 | I12: =_xll.EQNXTDZ($A$1,$B12,I$1,$B$1) -> 405.67 | J12: =_xll.EQNXTDZ($A$1,$B12,J$1,$B$1) -> 509.02 | ... BV12: =_xll.EQNXTDZ($A$1,$B12,BV$1,$B$1) -> 0
A13: Excise Duty | B13: QTR_EXCISE | C13: =_xll.EQNXTDZ($A$1,$B13,C$1,$B$1) -> 0 | D13: =_xll.EQNXTDZ($A$1,$B13,D$1,$B$1) -> 0 | E13: =_xll.EQNXTDZ($A$1,$B13,E$1,$B$1) -> 0 | F13: =_xll.EQNXTDZ($A$1,$B13,F$1,$B$1) -> 0 | G13: =_xll.EQNXTDZ($A$1,$B13,G$1,$B$1) -> 0 | H13: =_xll.EQNXTDZ($A$1,$B13,H$1,$B$1) -> 0 | I13: =_xll.EQNXTDZ($A$1,$B13,I$1,$B$1) -> 0 | J13: =_xll.EQNXTDZ($A$1,$B13,J$1,$B$1) -> 0 | ... BV13: =_xll.EQNXTDZ($A$1,$B13,BV$1,$B$1) -> 0
A14: Operating & Manufacturing Expenses | B14: QTR_MFG_EXPS | C14: =_xll.EQNXTDZ($A$1,$B14,C$1,$B$1) -> 5642.42 | D14: =_xll.EQNXTDZ($A$1,$B14,D$1,$B$1) -> 7217.02 | E14: =_xll.EQNXTDZ($A$1,$B14,E$1,$B$1) -> 8272.34 | F14: =_xll.EQNXTDZ($A$1,$B14,F$1,$B$1) -> 10180.35 | G14: =_xll.EQNXTDZ($A$1,$B14,G$1,$B$1) -> 10973.39 | H14: =_xll.EQNXTDZ($A$1,$B14,H$1,$B$1) -> 9970 | I14: =_xll.EQNXTDZ($A$1,$B14,I$1,$B$1) -> 12876.68 | J14: =_xll.EQNXTDZ($A$1,$B14,J$1,$B$1) -> 15365 | ... BV14: =_xll.EQNXTDZ($A$1,$B14,BV$1,$B$1) -> 0
A15: Electricity Power & Fuel Cost | B15: QTR_ELECTRICITY_POWER_FUEL | C15: =_xll.EQNXTDZ($A$1,$B15,C$1,$B$1) -> 0 | D15: =_xll.EQNXTDZ($A$1,$B15,D$1,$B$1) -> 0 | E15: =_xll.EQNXTDZ($A$1,$B15,E$1,$B$1) -> 0 | F15: =_xll.EQNXTDZ($A$1,$B15,F$1,$B$1) -> 0 | G15: =_xll.EQNXTDZ($A$1,$B15,G$1,$B$1) -> 0 | H15: =_xll.EQNXTDZ($A$1,$B15,H$1,$B$1) -> 0 | I15: =_xll.EQNXTDZ($A$1,$B15,I$1,$B$1) -> 0 | J15: =_xll.EQNXTDZ($A$1,$B15,J$1,$B$1) -> 0 | ... BV15: =_xll.EQNXTDZ($A$1,$B15,BV$1,$B$1) -> 0
A16: Employee Cost | B16: QTR_EXPLOYEE_COST | C16: =_xll.EQNXTDZ($A$1,$B16,C$1,$B$1) -> 947.19 | D16: =_xll.EQNXTDZ($A$1,$B16,D$1,$B$1) -> 1298.51 | E16: =_xll.EQNXTDZ($A$1,$B16,E$1,$B$1) -> 926.75 | F16: =_xll.EQNXTDZ($A$1,$B16,F$1,$B$1) -> 979.16 | G16: =_xll.EQNXTDZ($A$1,$B16,G$1,$B$1) -> 1565.14 | H16: =_xll.EQNXTDZ($A$1,$B16,H$1,$B$1) -> 2003.52 | I16: =_xll.EQNXTDZ($A$1,$B16,I$1,$B$1) -> 1708.34 | J16: =_xll.EQNXTDZ($A$1,$B16,J$1,$B$1) -> 1858.07 | ... BV16: =_xll.EQNXTDZ($A$1,$B16,BV$1,$B$1) -> 0
... A42: Consolidated PAT(after extra items) | B42: QTR_CONS_PAT_EXITM | C42: =_xll.EQNXTDZ($A$1,$B42,C$1,$B$1) -> 863.65 | D42: =_xll.EQNXTDZ($A$1,$B42,D$1,$B$1) -> 1137.31 | E42: =_xll.EQNXTDZ($A$1,$B42,E$1,$B$1) -> 1013.23 | F42: =_xll.EQNXTDZ($A$1,$B42,F$1,$B$1) -> 1787.94 | G42: =_xll.EQNXTDZ($A$1,$B42,G$1,$B$1) -> 458.59 | H42: =_xll.EQNXTDZ($A$1,$B42,H$1,$B$1) -> 806.35 | I42: =_xll.EQNXTDZ($A$1,$B42,I$1,$B$1) -> 796.66 | J42: =_xll.EQNXTDZ($A$1,$B42,J$1,$B$1) -> 2840.4 | ... BV42: =_xll.EQNXTDZ($A$1,$B42,BV$1,$B$1) -> 0
A44: Field Description | B44: Field Name
A45: Equity Capital | B45: QTR_EQUITY_CAP | C45: =_xll.EQNXTDZ($A$1,$B45,C$1,$B$1) -> 122.56 | D45: =_xll.EQNXTDZ($A$1,$B45,D$1,$B$1) -> 122.76 | E45: =_xll.EQNXTDZ($A$1,$B45,E$1,$B$1) -> 122.98 | F45: =_xll.EQNXTDZ($A$1,$B45,F$1,$B$1) -> 123.08 | G45: =_xll.EQNXTDZ($A$1,$B45,G$1,$B$1) -> 123.25 | H45: =_xll.EQNXTDZ($A$1,$B45,H$1,$B$1) -> 185.05 | I45: =_xll.EQNXTDZ($A$1,$B45,I$1,$B$1) -> 185.21 | J45: =_xll.EQNXTDZ($A$1,$B45,J$1,$B$1) -> 185.38 | ... BV45: =_xll.EQNXTDZ($A$1,$B45,BV$1,$B$1) -> 0
A46: Face Value | B46: QTR_FV | C46: =_xll.EQNXTDZ($A$1,$B46,C$1,$B$1) -> 2 | D46: =_xll.EQNXTDZ($A$1,$B46,D$1,$B$1) -> 2 | E46: =_xll.EQNXTDZ($A$1,$B46,E$1,$B$1) -> 2 | F46: =_xll.EQNXTDZ($A$1,$B46,F$1,$B$1) -> 2 | G46: =_xll.EQNXTDZ($A$1,$B46,G$1,$B$1) -> 2 | H46: =_xll.EQNXTDZ($A$1,$B46,H$1,$B$1) -> 2 | I46: =_xll.EQNXTDZ($A$1,$B46,I$1,$B$1) -> 2 | J46: =_xll.EQNXTDZ($A$1,$B46,J$1,$B$1) -> 2 | ... BV46: =_xll.EQNXTDZ($A$1,$B46,BV$1,$B$1) -> 0
A47: Month End | B47: BMONTH_MONTHEND | C47: =_xll.EQNXTDZ($A$1,$B47,C$5) -> 201206 | D47: =_xll.EQNXTDZ($A$1,$B47,D$5) -> 201209 | E47: =_xll.EQNXTDZ($A$1,$B47,E$5) -> 201212 | F47: =_xll.EQNXTDZ($A$1,$B47,F$5) -> 201303 | G47: =_xll.EQNXTDZ($A$1,$B47,G$5) -> 201306 | H47: =_xll.EQNXTDZ($A$1,$B47,H$5) -> 201309 | I47: =_xll.EQNXTDZ($A$1,$B47,I$5) -> 201312 | J47: =_xll.EQNXTDZ($A$1,$B47,J$5) -> 201403 | ... BV47: =_xll.EQNXTDZ($A$1,$B47,BV$5) -> 0
A48: Close | B48: BMONTH_CLOSE | C48: =_xll.EQNXTDZ($A$1,$B48,C$5) -> 621.04444 | D48: =_xll.EQNXTDZ($A$1,$B48,D$5) -> 709.66667 | E48: =_xll.EQNXTDZ($A$1,$B48,E$5) -> 713.71111 | F48: =_xll.EQNXTDZ($A$1,$B48,F$5) -> 606.62222 | G48: =_xll.EQNXTDZ($A$1,$B48,G$5) -> 624.06667 | H48: =_xll.EQNXTDZ($A$1,$B48,H$5) -> 525.73333 | I48: =_xll.EQNXTDZ($A$1,$B48,I$5) -> 713.26667 | J48: =_xll.EQNXTDZ($A$1,$B48,J$5) -> 848.43333 | ... BV48: =_xll.EQNXTDZ($A$1,$B48,BV$5) -> 0
A49: Total of Promoter and Promoter Group | B49: SHP_TPFTOTALPROMOTER | C49: =_xll.EQNXTDZ($A$1,$B49,C$5) -> 0 | D49: =_xll.EQNXTDZ($A$1,$B49,D$5) -> 0 | E49: =_xll.EQNXTDZ($A$1,$B49,E$5) -> 0 | F49: =_xll.EQNXTDZ($A$1,$B49,F$5) -> 0 | G49: =_xll.EQNXTDZ($A$1,$B49,G$5) -> 0 | H49: =_xll.EQNXTDZ($A$1,$B49,H$5) -> 0 | I49: =_xll.EQNXTDZ($A$1,$B49,I$5) -> 0 | J49: =_xll.EQNXTDZ($A$1,$B49,J$5) -> 0 | ... BV49: =_xll.EQNXTDZ($A$1,$B49,BV$5) -> 0
A50: Total of Promoter and Promoter Group Pledged | B50: SHP_PSHFTOTALPROMOTER | C50: =_xll.EQNXTDZ($A$1,$B50,C$5) -> 0 | D50: =_xll.EQNXTDZ($A$1,$B50,D$5) -> 0 | E50: =_xll.EQNXTDZ($A$1,$B50,E$5) -> 0 | F50: =_xll.EQNXTDZ($A$1,$B50,F$5) -> 0 | G50: =_xll.EQNXTDZ($A$1,$B50,G$5) -> 0 | H50: =_xll.EQNXTDZ($A$1,$B50,H$5) -> 0 | I50: =_xll.EQNXTDZ($A$1,$B50,I$5) -> 0 | J50: =_xll.EQNXTDZ($A$1,$B50,J$5) -> 0 | ... BV50: =_xll.EQNXTDZ($A$1,$B50,BV$5) -> 0
A54: Field Description | B54: Field Name | C54: =_xll.EQNXTDZ($A$1,$B54,C$5) -> 0 | D54: =_xll.EQNXTDZ($A$1,$B54,D$5) -> 0 | E54: =_xll.EQNXTDZ($A$1,$B54,E$5) -> 0 | F54: =_xll.EQNXTDZ($A$1,$B54,F$5) -> 0 | G54: =_xll.EQNXTDZ($A$1,$B54,G$5) -> 0 | H54: =_xll.EQNXTDZ($A$1,$B54,H$5) -> 0 | I54: =_xll.EQNXTDZ($A$1,$B54,I$5) -> 0 | J54: =_xll.EQNXTDZ($A$1,$B54,J$5) -> 0 | ... BV54: =_xll.EQNXTDZ($A$1,$B54,BV$5) -> 0
A55: Year End | B55: QTRB_DATE_END | C55: =_xll.EQNXTDZ($A$1,$B55,C$5,$B$1) -> 0 | D55: =_xll.EQNXTDZ($A$1,$B55,D$5,$B$1) -> 201209 | E55: =_xll.EQNXTDZ($A$1,$B55,E$5,$B$1) -> 0 | F55: =_xll.EQNXTDZ($A$1,$B55,F$5,$B$1) -> 201303 | G55: =_xll.EQNXTDZ($A$1,$B55,G$5,$B$1) -> 0 | H55: =_xll.EQNXTDZ($A$1,$B55,H$5,$B$1) -> 201309 | I55: =_xll.EQNXTDZ($A$1,$B55,I$5,$B$1) -> 0 | J55: =_xll.EQNXTDZ($A$1,$B55,J$5,$B$1) -> 201403 | ... BV55: =_xll.EQNXTDZ($A$1,$B55,BV$5,$B$1) -> 0
A56: Share Capital | B56: QTRB_SHARE_CAPITAL | C56: =_xll.EQNXTDZ($A$1,$B56,C$5,$B$1) -> 0 | D56: =_xll.EQNXTDZ($A$1,$B56,D$5,$B$1) -> 122.76 | E56: =_xll.EQNXTDZ($A$1,$B56,E$5,$B$1) -> 0 | F56: =_xll.EQNXTDZ($A$1,$B56,F$5,$B$1) -> 123.08 | G56: =_xll.EQNXTDZ($A$1,$B56,G$5,$B$1) -> 0 | H56: =_xll.EQNXTDZ($A$1,$B56,H$5,$B$1) -> 185.05 | I56: =_xll.EQNXTDZ($A$1,$B56,I$5,$B$1) -> 0 | J56: =_xll.EQNXTDZ($A$1,$B56,J$5,$B$1) -> 185.38 | ... BV56: =_xll.EQNXTDZ($A$1,$B56,BV$5,$B$1) -> 0
A57: Share Warrants & outstandings | B57: QTRB_SHAREWARNDOUT | C57: =_xll.EQNXTDZ($A$1,$B57,C$5,$B$1) -> 0 | D57: =_xll.EQNXTDZ($A$1,$B57,D$5,$B$1) -> 0 | E57: =_xll.EQNXTDZ($A$1,$B57,E$5,$B$1) -> 0 | F57: =_xll.EQNXTDZ($A$1,$B57,F$5,$B$1) -> 0 | G57: =_xll.EQNXTDZ($A$1,$B57,G$5,$B$1) -> 0 | H57: =_xll.EQNXTDZ($A$1,$B57,H$5,$B$1) -> 0 | I57: =_xll.EQNXTDZ($A$1,$B57,I$5,$B$1) -> 0 | J57: =_xll.EQNXTDZ($A$1,$B57,J$5,$B$1) -> 0 | ... BV57: =_xll.EQNXTDZ($A$1,$B57,BV$5,$B$1) -> 0
A58: Reserves & Surplus | B58: QTRB_RESERVE | C58: =_xll.EQNXTDZ($A$1,$B58,C$5,$B$1) -> 0 | D58: =_xll.EQNXTDZ($A$1,$B58,D$5,$B$1) -> 27269.48 | E58: =_xll.EQNXTDZ($A$1,$B58,E$5,$B$1) -> 0 | F58: =_xll.EQNXTDZ($A$1,$B58,F$5,$B$1) -> 33736.61 | G58: =_xll.EQNXTDZ($A$1,$B58,G$5,$B$1) -> 0 | H58: =_xll.EQNXTDZ($A$1,$B58,H$5,$B$1) -> 34783.8 | I58: =_xll.EQNXTDZ($A$1,$B58,I$5,$B$1) -> 0 | J58: =_xll.EQNXTDZ($A$1,$B58,J$5,$B$1) -> 37526.23 | ... BV58: =_xll.EQNXTDZ($A$1,$B58,BV$5,$B$1) -> 0
A59: Shareholder's Funds | B59: QTRB_SHAREHODERS_FUNDS | C59: =_xll.EQNXTDZ($A$1,$B59,C$5,$B$1) -> 0 | D59: =_xll.EQNXTDZ($A$1,$B59,D$5,$B$1) -> 27392.24 | E59: =_xll.EQNXTDZ($A$1,$B59,E$5,$B$1) -> 0 | F59: =_xll.EQNXTDZ($A$1,$B59,F$5,$B$1) -> 33859.69 | G59: =_xll.EQNXTDZ($A$1,$B59,G$5,$B$1) -> 0 | H59: =_xll.EQNXTDZ($A$1,$B59,H$5,$B$1) -> 34968.85 | I59: =_xll.EQNXTDZ($A$1,$B59,I$5,$B$1) -> 0 | J59: =_xll.EQNXTDZ($A$1,$B59,J$5,$B$1) -> 37711.61 | ... BV59: =_xll.EQNXTDZ($A$1,$B59,BV$5,$B$1) -> 0
A60: Minority Interest | B60: QTRB_MINORITY_INTEREST_BS | C60: =_xll.EQNXTDZ($A$1,$B60,C$5,$B$1) -> 0 | D60: =_xll.EQNXTDZ($A$1,$B60,D$5,$B$1) -> 0 | E60: =_xll.EQNXTDZ($A$1,$B60,E$5,$B$1) -> 0 | F60: =_xll.EQNXTDZ($A$1,$B60,F$5,$B$1) -> 2652.87 | G60: =_xll.EQNXTDZ($A$1,$B60,G$5,$B$1) -> 0 | H60: =_xll.EQNXTDZ($A$1,$B60,H$5,$B$1) -> 2645.02 | I60: =_xll.EQNXTDZ($A$1,$B60,I$5,$B$1) -> 0 | J60: =_xll.EQNXTDZ($A$1,$B60,J$5,$B$1) -> 3179.18 | ... BV60: =_xll.EQNXTDZ($A$1,$B60,BV$5,$B$1) -> 0
A61: Long Term Borrowings | B61: QTRB_TOTAL_DEBTS | C61: =_xll.EQNXTDZ($A$1,$B61,C$5,$B$1) -> 0 | D61: =_xll.EQNXTDZ($A$1,$B61,D$5,$B$1) -> 5749.96 | E61: =_xll.EQNXTDZ($A$1,$B61,E$5,$B$1) -> 0 | F61: =_xll.EQNXTDZ($A$1,$B61,F$5,$B$1) -> 47392.14 | G61: =_xll.EQNXTDZ($A$1,$B61,G$5,$B$1) -> 0 | H61: =_xll.EQNXTDZ($A$1,$B61,H$5,$B$1) -> 53702.39 | I61: =_xll.EQNXTDZ($A$1,$B61,I$5,$B$1) -> 0 | J61: =_xll.EQNXTDZ($A$1,$B61,J$5,$B$1) -> 55444.89 | ... BV61: =_xll.EQNXTDZ($A$1,$B61,BV$5,$B$1) -> 0
A62: Secured Loans | B62: QTRB_SECURED_LOANS | C62: =_xll.EQNXTDZ($A$1,$B62,C$5,$B$1) -> 0 | D62: =_xll.EQNXTDZ($A$1,$B62,D$5,$B$1) -> 0 | E62: =_xll.EQNXTDZ($A$1,$B62,E$5,$B$1) -> 0 | F62: =_xll.EQNXTDZ($A$1,$B62,F$5,$B$1) -> 0 | G62: =_xll.EQNXTDZ($A$1,$B62,G$5,$B$1) -> 0 | H62: =_xll.EQNXTDZ($A$1,$B62,H$5,$B$1) -> 0 | I62: =_xll.EQNXTDZ($A$1,$B62,I$5,$B$1) -> 0 | J62: =_xll.EQNXTDZ($A$1,$B62,J$5,$B$1) -> 0 | ... BV62: =_xll.EQNXTDZ($A$1,$B62,BV$5,$B$1) -> 0
A63: Unsecured Loans | B63: QTRB_UNSECURED_LOANS_NF | C63: =_xll.EQNXTDZ($A$1,$B63,C$5,$B$1) -> 0 | D63: =_xll.EQNXTDZ($A$1,$B63,D$5,$B$1) -> 5749.96 | E63: =_xll.EQNXTDZ($A$1,$B63,E$5,$B$1) -> 0 | F63: =_xll.EQNXTDZ($A$1,$B63,F$5,$B$1) -> 47392.14 | G63: =_xll.EQNXTDZ($A$1,$B63,G$5,$B$1) -> 0 | H63: =_xll.EQNXTDZ($A$1,$B63,H$5,$B$1) -> 53702.39 | I63: =_xll.EQNXTDZ($A$1,$B63,I$5,$B$1) -> 0 | J63: =_xll.EQNXTDZ($A$1,$B63,J$5,$B$1) -> 55444.89 | ... BV63: =_xll.EQNXTDZ($A$1,$B63,BV$5,$B$1) -> 0
A64: Other Long Term Liabilities | B64: QTRB_OTHER_LT_LIABILITIES | C64: =_xll.EQNXTDZ($A$1,$B64,C$5,$B$1) -> 0 | D64: =_xll.EQNXTDZ($A$1,$B64,D$5,$B$1) -> 632.87 | E64: =_xll.EQNXTDZ($A$1,$B64,E$5,$B$1) -> 0 | F64: =_xll.EQNXTDZ($A$1,$B64,F$5,$B$1) -> 4642.3 | G64: =_xll.EQNXTDZ($A$1,$B64,G$5,$B$1) -> 0 | H64: =_xll.EQNXTDZ($A$1,$B64,H$5,$B$1) -> 4416.61 | I64: =_xll.EQNXTDZ($A$1,$B64,I$5,$B$1) -> 0 | J64: =_xll.EQNXTDZ($A$1,$B64,J$5,$B$1) -> 3990.86 | ... BV64: =_xll.EQNXTDZ($A$1,$B64,BV$5,$B$1) -> 0
A65: Long Term Trade Payables | B65: QTRB_LT_TRADE_PAYABLE | C65: =_xll.EQNXTDZ($A$1,$B65,C$5,$B$1) -> 0 | D65: =_xll.EQNXTDZ($A$1,$B65,D$5,$B$1) -> 0 | E65: =_xll.EQNXTDZ($A$1,$B65,E$5,$B$1) -> 0 | F65: =_xll.EQNXTDZ($A$1,$B65,F$5,$B$1) -> 0 | G65: =_xll.EQNXTDZ($A$1,$B65,G$5,$B$1) -> 0 | H65: =_xll.EQNXTDZ($A$1,$B65,H$5,$B$1) -> 0 | I65: =_xll.EQNXTDZ($A$1,$B65,I$5,$B$1) -> 0 | J65: =_xll.EQNXTDZ($A$1,$B65,J$5,$B$1) -> 0 | ... BV65: =_xll.EQNXTDZ($A$1,$B65,BV$5,$B$1) -> 0
A66: Lont Term Provisions | B66: QTRB_LT_PROVISIONS | C66: =_xll.EQNXTDZ($A$1,$B66,C$5,$B$1) -> 0 | D66: =_xll.EQNXTDZ($A$1,$B66,D$5,$B$1) -> 286.73 | E66: =_xll.EQNXTDZ($A$1,$B66,E$5,$B$1) -> 0 | F66: =_xll.EQNXTDZ($A$1,$B66,F$5,$B$1) -> 346.67 | G66: =_xll.EQNXTDZ($A$1,$B66,G$5,$B$1) -> 0 | H66: =_xll.EQNXTDZ($A$1,$B66,H$5,$B$1) -> 312 | I66: =_xll.EQNXTDZ($A$1,$B66,I$5,$B$1) -> 0 | J66: =_xll.EQNXTDZ($A$1,$B66,J$5,$B$1) -> 374.24 | ... BV66: =_xll.EQNXTDZ($A$1,$B66,BV$5,$B$1) -> 0
... A97: Total Assets | B97: QTRB_TOTAL_APPLICATIONS | C97: =_xll.EQNXTDZ($A$1,$B97,C$5,$B$1) -> 0 | D97: =_xll.EQNXTDZ($A$1,$B97,D$5,$B$1) -> 34061.8 | E97: =_xll.EQNXTDZ($A$1,$B97,E$5,$B$1) -> 0 | F97: =_xll.EQNXTDZ($A$1,$B97,F$5,$B$1) -> 88893.67 | G97: =_xll.EQNXTDZ($A$1,$B97,G$5,$B$1) -> 0 | H97: =_xll.EQNXTDZ($A$1,$B97,H$5,$B$1) -> 96044.87 | I97: =_xll.EQNXTDZ($A$1,$B97,I$5,$B$1) -> 0 | J97: =_xll.EQNXTDZ($A$1,$B97,J$5,$B$1) -> 100700.78 | ... BV97: =_xll.EQNXTDZ($A$1,$B97,BV$5,$B$1) -> 0

Sheet Annual Raw
A1: 100510 | B1: X | C1: 200103 | D1: 200203 | E1: 200303 | F1: 200403 | G1: 200503 | H1: 200603 | I1: 200703 | J1: 200803 | K1: 200903 | L1: 201003 | M1: 201103 | N1: 201203 | O1: 201303 | P1: 201403 | Q1: 201503 | R1: 201603 | S1: 201703 | T1: 201803 | U1: 201903 | V1: 202003 | W1: 202103 | X1: 202203 | Y1: 202303 | Z1: 202403 | AA1: 202503 | AB1: 202603 | AC1: 202703 | AD1: 202803 | AE1: 202903 | AF1: 203003
A3: Field Description | B3: Field Name
A4: Company Name | B4: CD_COMPNAME | C4: =_xll.EQNXTDZ(A1,B4,"L") -> Larsen & Toubro Ltd.
A5: Year End | B5: PL_YEAR_END | C5: =_xll.EQNXTDZ($A$1,$B5,C$1,$B$1) -> 200103 | D5: =_xll.EQNXTDZ($A$1,$B5,D$1,$B$1) -> 200203 | E5: =_xll.EQNXTDZ($A$1,$B5,E$1,$B$1) -> 200303 | F5: =_xll.EQNXTDZ($A$1,$B5,F$1,$B$1) -> 200403 | G5: =_xll.EQNXTDZ($A$1,$B5,G$1,$B$1) -> 200503 | H5: =_xll.EQNXTDZ($A$1,$B5,H$1,$B$1) -> 200603 | I5: =_xll.EQNXTDZ($A$1,$B5,I$1,$B$1) -> 200703 | J5: =_xll.EQNXTDZ($A$1,$B5,J$1,$B$1) -> 200803 | ... AF5: =_xll.EQNXTDZ($A$1,$B5,AF$1,$B$1) -> 0
A6: Sales Turnover | B6: PL_TOTAL_GROSS_SALES | C6: =_xll.EQNXTDZ($A$1,$B6,C$1,$B$1) -> 7825.43 | D6: =_xll.EQNXTDZ($A$1,$B6,D$1,$B$1) -> 9170.02 | E6: =_xll.EQNXTDZ($A$1,$B6,E$1,$B$1) -> 10813.13 | F6: =_xll.EQNXTDZ($A$1,$B6,F$1,$B$1) -> 11232.34 | G6: =_xll.EQNXTDZ($A$1,$B6,G$1,$B$1) -> 14716.9 | H6: =_xll.EQNXTDZ($A$1,$B6,H$1,$B$1) -> 16808.51 | I6: =_xll.EQNXTDZ($A$1,$B6,I$1,$B$1) -> 20877.32 | J6: =_xll.EQNXTDZ($A$1,$B6,J$1,$B$1) -> 29819.46 | ... AF6: =_xll.EQNXTDZ($A$1,$B6,AF$1,$B$1) -> 0
A7: Less: Inter divisional transfers | B7: PL_INTER_DIV_TRF | C7: =_xll.EQNXTDZ($A$1,$B7,C$1,$B$1) -> 0 | D7: =_xll.EQNXTDZ($A$1,$B7,D$1,$B$1) -> 0 | E7: =_xll.EQNXTDZ($A$1,$B7,E$1,$B$1) -> 0 | F7: =_xll.EQNXTDZ($A$1,$B7,F$1,$B$1) -> 0 | G7: =_xll.EQNXTDZ($A$1,$B7,G$1,$B$1) -> 0 | H7: =_xll.EQNXTDZ($A$1,$B7,H$1,$B$1) -> 0 | I7: =_xll.EQNXTDZ($A$1,$B7,I$1,$B$1) -> 0 | J7: =_xll.EQNXTDZ($A$1,$B7,J$1,$B$1) -> 0 | ... AF7: =_xll.EQNXTDZ($A$1,$B7,AF$1,$B$1) -> 0
A8: Less: Sales Returns | B8: PL_SALES_RETURN | C8: =_xll.EQNXTDZ($A$1,$B8,C$1,$B$1) -> 0 | D8: =_xll.EQNXTDZ($A$1,$B8,D$1,$B$1) -> 0 | E8: =_xll.EQNXTDZ($A$1,$B8,E$1,$B$1) -> 0 | F8: =_xll.EQNXTDZ($A$1,$B8,F$1,$B$1) -> 0 | G8: =_xll.EQNXTDZ($A$1,$B8,G$1,$B$1) -> 0 | H8: =_xll.EQNXTDZ($A$1,$B8,H$1,$B$1) -> 0 | I8: =_xll.EQNXTDZ($A$1,$B8,I$1,$B$1) -> 0 | J8: =_xll.EQNXTDZ($A$1,$B8,J$1,$B$1) -> 0 | ... AF8: =_xll.EQNXTDZ($A$1,$B8,AF$1,$B$1) -> 0
A9: Less: Excise | B9: PL_EXCISE | C9: =_xll.EQNXTDZ($A$1,$B9,C$1,$B$1) -> 446.78 | D9: =_xll.EQNXTDZ($A$1,$B9,D$1,$B$1) -> 480.66 | E9: =_xll.EQNXTDZ($A$1,$B9,E$1,$B$1) -> 530.06 | F9: =_xll.EQNXTDZ($A$1,$B9,F$1,$B$1) -> 258.56 | G9: =_xll.EQNXTDZ($A$1,$B9,G$1,$B$1) -> 220.01 | H9: =_xll.EQNXTDZ($A$1,$B9,H$1,$B$1) -> 247.2 | I9: =_xll.EQNXTDZ($A$1,$B9,I$1,$B$1) -> 364.46 | J9: =_xll.EQNXTDZ($A$1,$B9,J$1,$B$1) -> 362.61 | ... AF9: =_xll.EQNXTDZ($A$1,$B9,AF$1,$B$1) -> 0
A10: Net Sales | B10: PL_NET_SALES | C10: =_xll.EQNXTDZ($A$1,$B10,C$1,$B$1) -> 7378.65 | D10: =_xll.EQNXTDZ($A$1,$B10,D$1,$B$1) -> 8689.36 | E10: =_xll.EQNXTDZ($A$1,$B10,E$1,$B$1) -> 10283.07 | F10: =_xll.EQNXTDZ($A$1,$B10,F$1,$B$1) -> 10973.78 | G10: =_xll.EQNXTDZ($A$1,$B10,G$1,$B$1) -> 14496.89 | H10: =_xll.EQNXTDZ($A$1,$B10,H$1,$B$1) -> 16561.31 | I10: =_xll.EQNXTDZ($A$1,$B10,I$1,$B$1) -> 20512.86 | J10: =_xll.EQNXTDZ($A$1,$B10,J$1,$B$1) -> 29456.85 | ... AF10: =_xll.EQNXTDZ($A$1,$B10,AF$1,$B$1) -> 0
A11: Increase/Decrease in Stock | B11: PL_INC_DEC_INVENTORY | C11: =_xll.EQNXTDZ($A$1,$B11,C$1,$B$1) -> 1.25 | D11: =_xll.EQNXTDZ($A$1,$B11,D$1,$B$1) -> 33.06 | E11: =_xll.EQNXTDZ($A$1,$B11,E$1,$B$1) -> 20.66 | F11: =_xll.EQNXTDZ($A$1,$B11,F$1,$B$1) -> -404.83 | G11: =_xll.EQNXTDZ($A$1,$B11,G$1,$B$1) -> -81.46 | H11: =_xll.EQNXTDZ($A$1,$B11,H$1,$B$1) -> 137.63 | I11: =_xll.EQNXTDZ($A$1,$B11,I$1,$B$1) -> -111.28 | J11: =_xll.EQNXTDZ($A$1,$B11,J$1,$B$1) -> -681.89 | ... AF11: =_xll.EQNXTDZ($A$1,$B11,AF$1,$B$1) -> 0
A12: Raw Material Consumed | B12: PL_RAW_MATRS_CONSUMED | C12: =_xll.EQNXTDZ($A$1,$B12,C$1,$B$1) -> 2198.87 | D12: =_xll.EQNXTDZ($A$1,$B12,D$1,$B$1) -> 2322.62 | E12: =_xll.EQNXTDZ($A$1,$B12,E$1,$B$1) -> 3305.69 | F12: =_xll.EQNXTDZ($A$1,$B12,F$1,$B$1) -> 4499.4 | G12: =_xll.EQNXTDZ($A$1,$B12,G$1,$B$1) -> 6521.43 | H12: =_xll.EQNXTDZ($A$1,$B12,H$1,$B$1) -> 7227.44 | I12: =_xll.EQNXTDZ($A$1,$B12,I$1,$B$1) -> 8765.17 | J12: =_xll.EQNXTDZ($A$1,$B12,J$1,$B$1) -> 13900.13 | ... AF12: =_xll.EQNXTDZ($A$1,$B12,AF$1,$B$1) -> 0
A13: Power & Fuel Cost | B13: PL_POWER_FUEL | C13: =_xll.EQNXTDZ($A$1,$B13,C$1,$B$1) -> 622.03 | D13: =_xll.EQNXTDZ($A$1,$B13,D$1,$B$1) -> 725.55 | E13: =_xll.EQNXTDZ($A$1,$B13,E$1,$B$1) -> 747.86 | F13: =_xll.EQNXTDZ($A$1,$B13,F$1,$B$1) -> 92.89 | G13: =_xll.EQNXTDZ($A$1,$B13,G$1,$B$1) -> 215.49 | H13: =_xll.EQNXTDZ($A$1,$B13,H$1,$B$1) -> 249.86 | I13: =_xll.EQNXTDZ($A$1,$B13,I$1,$B$1) -> 339.3 | J13: =_xll.EQNXTDZ($A$1,$B13,J$1,$B$1) -> 447.6 | ... AF13: =_xll.EQNXTDZ($A$1,$B13,AF$1,$B$1) -> 0
A14: Employee Cost | B14: PL_EMPLOYEES | C14: =_xll.EQNXTDZ($A$1,$B14,C$1,$B$1) -> 585.12 | D14: =_xll.EQNXTDZ($A$1,$B14,D$1,$B$1) -> 634.37 | E14: =_xll.EQNXTDZ($A$1,$B14,E$1,$B$1) -> 727.94 | F14: =_xll.EQNXTDZ($A$1,$B14,F$1,$B$1) -> 741.23 | G14: =_xll.EQNXTDZ($A$1,$B14,G$1,$B$1) -> 855.94 | H14: =_xll.EQNXTDZ($A$1,$B14,H$1,$B$1) -> 1029.76 | I14: =_xll.EQNXTDZ($A$1,$B14,I$1,$B$1) -> 1461 | J14: =_xll.EQNXTDZ($A$1,$B14,J$1,$B$1) -> 2011.41 | ... AF14: =_xll.EQNXTDZ($A$1,$B14,AF$1,$B$1) -> 0
A15: Operating & Manufacturing Expenses | B15: PL_GEN_OTHER_MFG_EXPS | C15: =_xll.EQNXTDZ($A$1,$B15,C$1,$B$1) -> 2351.51 | D15: =_xll.EQNXTDZ($A$1,$B15,D$1,$B$1) -> 2235.39 | E15: =_xll.EQNXTDZ($A$1,$B15,E$1,$B$1) -> 2776.74 | F15: =_xll.EQNXTDZ($A$1,$B15,F$1,$B$1) -> 3719.27 | G15: =_xll.EQNXTDZ($A$1,$B15,G$1,$B$1) -> 4170.22 | H15: =_xll.EQNXTDZ($A$1,$B15,H$1,$B$1) -> 4379.42 | I15: =_xll.EQNXTDZ($A$1,$B15,I$1,$B$1) -> 4731.69 | J15: =_xll.EQNXTDZ($A$1,$B15,J$1,$B$1) -> 6444.69 | ... AF15: =_xll.EQNXTDZ($A$1,$B15,AF$1,$B$1) -> 0
A16: Cost of Software development | B16: PL_COST_SW | C16: =_xll.EQNXTDZ($A$1,$B16,C$1,$B$1) -> 0 | D16: =_xll.EQNXTDZ($A$1,$B16,D$1,$B$1) -> 0 | E16: =_xll.EQNXTDZ($A$1,$B16,E$1,$B$1) -> 0 | F16: =_xll.EQNXTDZ($A$1,$B16,F$1,$B$1) -> 0 | G16: =_xll.EQNXTDZ($A$1,$B16,G$1,$B$1) -> 0 | H16: =_xll.EQNXTDZ($A$1,$B16,H$1,$B$1) -> 0 | I16: =_xll.EQNXTDZ($A$1,$B16,I$1,$B$1) -> 0 | J16: =_xll.EQNXTDZ($A$1,$B16,J$1,$B$1) -> 0 | ... AF16: =_xll.EQNXTDZ($A$1,$B16,AF$1,$B$1) -> 0
... A36: Profit After Tax from Discontinued Operations | B36: PL_PAT_DIS_OP | C36: =_xll.EQNXTDZ($A$1,$B36,C$1,$B$1) -> 0 | D36: =_xll.EQNXTDZ($A$1,$B36,D$1,$B$1) -> 0 | E36: =_xll.EQNXTDZ($A$1,$B36,E$1,$B$1) -> 0 | F36: =_xll.EQNXTDZ($A$1,$B36,F$1,$B$1) -> 0 | G36: =_xll.EQNXTDZ($A$1,$B36,G$1,$B$1) -> 0 | H36: =_xll.EQNXTDZ($A$1,$B36,H$1,$B$1) -> 0 | I36: =_xll.EQNXTDZ($A$1,$B36,I$1,$B$1) -> 0 | J36: =_xll.EQNXTDZ($A$1,$B36,J$1,$B$1) -> 0 | ... AF36: =_xll.EQNXTDZ($A$1,$B36,AF$1,$B$1) -> 0
A39: Field Description | B39: Field Name
A40: Year End | B40: BS_YEAR_END | C40: =_xll.EQNXTDZ($A$1,$B40,C$1,$B$1) -> 200103 | D40: =_xll.EQNXTDZ($A$1,$B40,D$1,$B$1) -> 200203 | E40: =_xll.EQNXTDZ($A$1,$B40,E$1,$B$1) -> 200303 | F40: =_xll.EQNXTDZ($A$1,$B40,F$1,$B$1) -> 200403 | G40: =_xll.EQNXTDZ($A$1,$B40,G$1,$B$1) -> 200503 | H40: =_xll.EQNXTDZ($A$1,$B40,H$1,$B$1) -> 200603 | I40: =_xll.EQNXTDZ($A$1,$B40,I$1,$B$1) -> 200703 | J40: =_xll.EQNXTDZ($A$1,$B40,J$1,$B$1) -> 200803 | ... AF40: =_xll.EQNXTDZ($A$1,$B40,AF$1,$B$1) -> 0
A41: Share Capital | B41: BS_SHARE_CAPITAL | C41: =_xll.EQNXTDZ($A$1,$B41,C$1,$B$1) -> 248.65 | D41: =_xll.EQNXTDZ($A$1,$B41,D$1,$B$1) -> 248.66 | E41: =_xll.EQNXTDZ($A$1,$B41,E$1,$B$1) -> 248.67 | F41: =_xll.EQNXTDZ($A$1,$B41,F$1,$B$1) -> 24.88 | G41: =_xll.EQNXTDZ($A$1,$B41,G$1,$B$1) -> 25.98 | H41: =_xll.EQNXTDZ($A$1,$B41,H$1,$B$1) -> 27.48 | I41: =_xll.EQNXTDZ($A$1,$B41,I$1,$B$1) -> 56.65 | J41: =_xll.EQNXTDZ($A$1,$B41,J$1,$B$1) -> 58.47 | ... AF41: =_xll.EQNXTDZ($A$1,$B41,AF$1,$B$1) -> 0
A42: Share Warrants & Outstandings | B42: BS_SHAREWROUTST | C42: =_xll.EQNXTDZ($A$1,$B42,C$1,$B$1) -> 0 | D42: =_xll.EQNXTDZ($A$1,$B42,D$1,$B$1) -> 0.11 | E42: =_xll.EQNXTDZ($A$1,$B42,E$1,$B$1) -> 0.04 | F42: =_xll.EQNXTDZ($A$1,$B42,F$1,$B$1) -> 0 | G42: =_xll.EQNXTDZ($A$1,$B42,G$1,$B$1) -> 28.19 | H42: =_xll.EQNXTDZ($A$1,$B42,H$1,$B$1) -> 34.99 | I42: =_xll.EQNXTDZ($A$1,$B42,I$1,$B$1) -> 79.41 | J42: =_xll.EQNXTDZ($A$1,$B42,J$1,$B$1) -> 144.31 | ... AF42: =_xll.EQNXTDZ($A$1,$B42,AF$1,$B$1) -> 0
A43: Total Reserves | B43: BS_RESERVE | C43: =_xll.EQNXTDZ($A$1,$B43,C$1,$B$1) -> 3750.76 | D43: =_xll.EQNXTDZ($A$1,$B43,D$1,$B$1) -> 2888.79 | E43: =_xll.EQNXTDZ($A$1,$B43,E$1,$B$1) -> 2967.89 | F43: =_xll.EQNXTDZ($A$1,$B43,F$1,$B$1) -> 2622.44 | G43: =_xll.EQNXTDZ($A$1,$B43,G$1,$B$1) -> 3261.76 | H43: =_xll.EQNXTDZ($A$1,$B43,H$1,$B$1) -> 4902.01 | I43: =_xll.EQNXTDZ($A$1,$B43,I$1,$B$1) -> 6785.49 | J43: =_xll.EQNXTDZ($A$1,$B43,J$1,$B$1) -> 10628.33 | ... AF43: =_xll.EQNXTDZ($A$1,$B43,AF$1,$B$1) -> 0
A44: Shareholder's Funds | B44: BS_SHAREHODERS_FUNDS | C44: =_xll.EQNXTDZ($A$1,$B44,C$1,$B$1) -> 3999.41 | D44: =_xll.EQNXTDZ($A$1,$B44,D$1,$B$1) -> 3137.56 | E44: =_xll.EQNXTDZ($A$1,$B44,E$1,$B$1) -> 3216.6 | F44: =_xll.EQNXTDZ($A$1,$B44,F$1,$B$1) -> 2647.32 | G44: =_xll.EQNXTDZ($A$1,$B44,G$1,$B$1) -> 3315.93 | H44: =_xll.EQNXTDZ($A$1,$B44,H$1,$B$1) -> 4964.48 | I44: =_xll.EQNXTDZ($A$1,$B44,I$1,$B$1) -> 6921.55 | J44: =_xll.EQNXTDZ($A$1,$B44,J$1,$B$1) -> 10831.11 | ... AF44: =_xll.EQNXTDZ($A$1,$B44,AF$1,$B$1) -> 0
A45: Minority Interest | B45: BS_MINORITY_INTEREST | C45: =_xll.EQNXTDZ($A$1,$B45,C$1,$B$1) -> 0 | D45: =_xll.EQNXTDZ($A$1,$B45,D$1,$B$1) -> 44.4 | E45: =_xll.EQNXTDZ($A$1,$B45,E$1,$B$1) -> 50.15 | F45: =_xll.EQNXTDZ($A$1,$B45,F$1,$B$1) -> 54.08 | G45: =_xll.EQNXTDZ($A$1,$B45,G$1,$B$1) -> 104.77 | H45: =_xll.EQNXTDZ($A$1,$B45,H$1,$B$1) -> 106.63 | I45: =_xll.EQNXTDZ($A$1,$B45,I$1,$B$1) -> 645.7 | J45: =_xll.EQNXTDZ($A$1,$B45,J$1,$B$1) -> 922.62 | ... AF45: =_xll.EQNXTDZ($A$1,$B45,AF$1,$B$1) -> 0
A46: Long-Term Borrowings | B46: BS_LTRM_BORROWING | C46: =_xll.EQNXTDZ($A$1,$B46,C$1,$B$1) -> 0 | D46: =_xll.EQNXTDZ($A$1,$B46,D$1,$B$1) -> 0 | E46: =_xll.EQNXTDZ($A$1,$B46,E$1,$B$1) -> 0 | F46: =_xll.EQNXTDZ($A$1,$B46,F$1,$B$1) -> 0 | G46: =_xll.EQNXTDZ($A$1,$B46,G$1,$B$1) -> 0 | H46: =_xll.EQNXTDZ($A$1,$B46,H$1,$B$1) -> 0 | I46: =_xll.EQNXTDZ($A$1,$B46,I$1,$B$1) -> 0 | J46: =_xll.EQNXTDZ($A$1,$B46,J$1,$B$1) -> 0 | ... AF46: =_xll.EQNXTDZ($A$1,$B46,AF$1,$B$1) -> 0
A47: Secured Loans | B47: BS_SECURED_LOANS | C47: =_xll.EQNXTDZ($A$1,$B47,C$1,$B$1) -> 3001.95 | D47: =_xll.EQNXTDZ($A$1,$B47,D$1,$B$1) -> 4081.21 | E47: =_xll.EQNXTDZ($A$1,$B47,E$1,$B$1) -> 3979.65 | F47: =_xll.EQNXTDZ($A$1,$B47,F$1,$B$1) -> 2269.06 | G47: =_xll.EQNXTDZ($A$1,$B47,G$1,$B$1) -> 1848.28 | H47: =_xll.EQNXTDZ($A$1,$B47,H$1,$B$1) -> 1911.43 | I47: =_xll.EQNXTDZ($A$1,$B47,I$1,$B$1) -> 3109.04 | J47: =_xll.EQNXTDZ($A$1,$B47,J$1,$B$1) -> 6756.16 | ... AF47: =_xll.EQNXTDZ($A$1,$B47,AF$1,$B$1) -> 0
A48: Unsecured Loans | B48: BS_UNSECURED_LOANS_NF | C48: =_xll.EQNXTDZ($A$1,$B48,C$1,$B$1) -> 1261.44 | D48: =_xll.EQNXTDZ($A$1,$B48,D$1,$B$1) -> 896.88 | E48: =_xll.EQNXTDZ($A$1,$B48,E$1,$B$1) -> 721.24 | F48: =_xll.EQNXTDZ($A$1,$B48,F$1,$B$1) -> 500.16 | G48: =_xll.EQNXTDZ($A$1,$B48,G$1,$B$1) -> 1605.55 | H48: =_xll.EQNXTDZ($A$1,$B48,H$1,$B$1) -> 1587.26 | I48: =_xll.EQNXTDZ($A$1,$B48,I$1,$B$1) -> 3323.18 | J48: =_xll.EQNXTDZ($A$1,$B48,J$1,$B$1) -> 5559.77 | ... AF48: =_xll.EQNXTDZ($A$1,$B48,AF$1,$B$1) -> 0
A49: Deferred Tax Assets / Liabilities | B49: BS_NET_DEF_TAX_NF | C49: =_xll.EQNXTDZ($A$1,$B49,C$1,$B$1) -> 0 | D49: =_xll.EQNXTDZ($A$1,$B49,D$1,$B$1) -> 927.92 | E49: =_xll.EQNXTDZ($A$1,$B49,E$1,$B$1) -> 913.01 | F49: =_xll.EQNXTDZ($A$1,$B49,F$1,$B$1) -> 213.51 | G49: =_xll.EQNXTDZ($A$1,$B49,G$1,$B$1) -> 137.58 | H49: =_xll.EQNXTDZ($A$1,$B49,H$1,$B$1) -> 126.75 | I49: =_xll.EQNXTDZ($A$1,$B49,I$1,$B$1) -> 107.41 | J49: =_xll.EQNXTDZ($A$1,$B49,J$1,$B$1) -> 121.72 | ... AF49: =_xll.EQNXTDZ($A$1,$B49,AF$1,$B$1) -> 0
A50: Other Long Term Liabilities | B50: BS_OTH_LT_LIAB | C50: =_xll.EQNXTDZ($A$1,$B50,C$1,$B$1) -> 0 | D50: =_xll.EQNXTDZ($A$1,$B50,D$1,$B$1) -> 0 | E50: =_xll.EQNXTDZ($A$1,$B50,E$1,$B$1) -> 0 | F50: =_xll.EQNXTDZ($A$1,$B50,F$1,$B$1) -> 0 | G50: =_xll.EQNXTDZ($A$1,$B50,G$1,$B$1) -> 0 | H50: =_xll.EQNXTDZ($A$1,$B50,H$1,$B$1) -> 0 | I50: =_xll.EQNXTDZ($A$1,$B50,I$1,$B$1) -> 0 | J50: =_xll.EQNXTDZ($A$1,$B50,J$1,$B$1) -> 0 | ... AF50: =_xll.EQNXTDZ($A$1,$B50,AF$1,$B$1) -> 0
A51: Long Term Trade Payables | B51: BS_LT_TRADE_PAYABLES | C51: =_xll.EQNXTDZ($A$1,$B51,C$1,$B$1) -> 0 | D51: =_xll.EQNXTDZ($A$1,$B51,D$1,$B$1) -> 0 | E51: =_xll.EQNXTDZ($A$1,$B51,E$1,$B$1) -> 0 | F51: =_xll.EQNXTDZ($A$1,$B51,F$1,$B$1) -> 0 | G51: =_xll.EQNXTDZ($A$1,$B51,G$1,$B$1) -> 0 | H51: =_xll.EQNXTDZ($A$1,$B51,H$1,$B$1) -> 0 | I51: =_xll.EQNXTDZ($A$1,$B51,I$1,$B$1) -> 0 | J51: =_xll.EQNXTDZ($A$1,$B51,J$1,$B$1) -> 0 | ... AF51: =_xll.EQNXTDZ($A$1,$B51,AF$1,$B$1) -> 0
... A99: Estimated Capital Contracts Remaining | B99: BS_ESTIMATED_CAPITAL_CONTRACT | C99: =_xll.EQNXTDZ($A$1,$B99,C$1,$B$1) -> 0 | D99: =_xll.EQNXTDZ($A$1,$B99,D$1,$B$1) -> 0 | E99: =_xll.EQNXTDZ($A$1,$B99,E$1,$B$1) -> 0 | F99: =_xll.EQNXTDZ($A$1,$B99,F$1,$B$1) -> 0 | G99: =_xll.EQNXTDZ($A$1,$B99,G$1,$B$1) -> 0 | H99: =_xll.EQNXTDZ($A$1,$B99,H$1,$B$1) -> 0 | I99: =_xll.EQNXTDZ($A$1,$B99,I$1,$B$1) -> 0 | J99: =_xll.EQNXTDZ($A$1,$B99,J$1,$B$1) -> 0 | ... AF99: =_xll.EQNXTDZ($A$1,$B99,AF$1,$B$1) -> 0
A103: Field Description | B103: Field Name
A104: Equity Paid Up | B104: BS_EQUITY_PAIDUP | C104: =_xll.EQNXTDZ($A$1,$B104,C$1,$B$1) -> 248.65 | D104: =_xll.EQNXTDZ($A$1,$B104,D$1,$B$1) -> 248.66 | E104: =_xll.EQNXTDZ($A$1,$B104,E$1,$B$1) -> 248.67 | F104: =_xll.EQNXTDZ($A$1,$B104,F$1,$B$1) -> 24.88 | G104: =_xll.EQNXTDZ($A$1,$B104,G$1,$B$1) -> 25.98 | H104: =_xll.EQNXTDZ($A$1,$B104,H$1,$B$1) -> 27.48 | I104: =_xll.EQNXTDZ($A$1,$B104,I$1,$B$1) -> 56.65 | J104: =_xll.EQNXTDZ($A$1,$B104,J$1,$B$1) -> 58.47 | ... AF104: =_xll.EQNXTDZ($A$1,$B104,AF$1,$B$1) -> 0
A105: Face Value | B105: BS_FACE_VALUE | C105: =_xll.EQNXTDZ($A$1,$B105,C$1,$B$1) -> 10 | D105: =_xll.EQNXTDZ($A$1,$B105,D$1,$B$1) -> 10 | E105: =_xll.EQNXTDZ($A$1,$B105,E$1,$B$1) -> 10 | F105: =_xll.EQNXTDZ($A$1,$B105,F$1,$B$1) -> 2 | G105: =_xll.EQNXTDZ($A$1,$B105,G$1,$B$1) -> 2 | H105: =_xll.EQNXTDZ($A$1,$B105,H$1,$B$1) -> 2 | I105: =_xll.EQNXTDZ($A$1,$B105,I$1,$B$1) -> 2 | J105: =_xll.EQNXTDZ($A$1,$B105,J$1,$B$1) -> 2 | ... AF105: =_xll.EQNXTDZ($A$1,$B105,AF$1,$B$1) -> 0
A106: Close Price (Unit Curr.) | B106: FH_YEAR_PRICE | C106: =_xll.EQNXTDZ($A$1,$B106,C$1,$B$1) -> 24.588889 | D106: =_xll.EQNXTDZ($A$1,$B106,D$1,$B$1) -> 20.083333 | E106: =_xll.EQNXTDZ($A$1,$B106,E$1,$B$1) -> 20.516667 | F106: =_xll.EQNXTDZ($A$1,$B106,F$1,$B$1) -> 63.816667 | G106: =_xll.EQNXTDZ($A$1,$B106,G$1,$B$1) -> 110.57222 | H106: =_xll.EQNXTDZ($A$1,$B106,H$1,$B$1) -> 270.28889 | I106: =_xll.EQNXTDZ($A$1,$B106,I$1,$B$1) -> 359.81111 | J106: =_xll.EQNXTDZ($A$1,$B106,J$1,$B$1) -> 672.17778 | ... AF106: =_xll.EQNXTDZ($A$1,$B106,AF$1,$B$1) -> 0
A107: High Price (Unit Curr.) | B107: FH_HIGH | C107: =_xll.EQNXTDZ($A$1,$B107,C$1,$B$1) -> 35.877778 | D107: =_xll.EQNXTDZ($A$1,$B107,D$1,$B$1) -> 28.755556 | E107: =_xll.EQNXTDZ($A$1,$B107,E$1,$B$1) -> 24.444444 | F107: =_xll.EQNXTDZ($A$1,$B107,F$1,$B$1) -> 68.166667 | G107: =_xll.EQNXTDZ($A$1,$B107,G$1,$B$1) -> 127.55556 | H107: =_xll.EQNXTDZ($A$1,$B107,H$1,$B$1) -> 290.71111 | I107: =_xll.EQNXTDZ($A$1,$B107,I$1,$B$1) -> 395.11111 | J107: =_xll.EQNXTDZ($A$1,$B107,J$1,$B$1) -> 1037.7778 | ... AF107: =_xll.EQNXTDZ($A$1,$B107,AF$1,$B$1) -> 0
A108: Low Price (Unit Curr.) | B108: FH_LOW | C108: =_xll.EQNXTDZ($A$1,$B108,C$1,$B$1) -> 15.694444 | D108: =_xll.EQNXTDZ($A$1,$B108,D$1,$B$1) -> 15.972222 | E108: =_xll.EQNXTDZ($A$1,$B108,E$1,$B$1) -> 16.177778 | F108: =_xll.EQNXTDZ($A$1,$B108,F$1,$B$1) -> 19.488889 | G108: =_xll.EQNXTDZ($A$1,$B108,G$1,$B$1) -> 44.888889 | H108: =_xll.EQNXTDZ($A$1,$B108,H$1,$B$1) -> 102.11111 | I108: =_xll.EQNXTDZ($A$1,$B108,I$1,$B$1) -> 200.58333 | J108: =_xll.EQNXTDZ($A$1,$B108,J$1,$B$1) -> 335.11111 | ... AF108: =_xll.EQNXTDZ($A$1,$B108,AF$1,$B$1) -> 0
A109: Market Capitalization | B109: FH_MCAP | C109: =_xll.EQNXTDZ($A$1,$B109,C$1,$B$1) -> 5502.6245 | D109: =_xll.EQNXTDZ($A$1,$B109,D$1,$B$1) -> 4494.5295 | E109: =_xll.EQNXTDZ($A$1,$B109,E$1,$B$1) -> 4591.6915 | F109: =_xll.EQNXTDZ($A$1,$B109,F$1,$B$1) -> 7144.914 | G109: =_xll.EQNXTDZ($A$1,$B109,G$1,$B$1) -> 12926.998 | H109: =_xll.EQNXTDZ($A$1,$B109,H$1,$B$1) -> 33423.924 | I109: =_xll.EQNXTDZ($A$1,$B109,I$1,$B$1) -> 45862.424 | J109: =_xll.EQNXTDZ($A$1,$B109,J$1,$B$1) -> 88430.028 | ... AF109: =_xll.EQNXTDZ($A$1,$B109,AF$1,$B$1) -> 0
A110: Adj DPS(Rs) | B110: FR_ADJ_DPS | C110: =_xll.EQNXTDZ($A$1,$B110,C$1,$B$1) -> 0.72222222 | D110: =_xll.EQNXTDZ($A$1,$B110,D$1,$B$1) -> 0.77777778 | E110: =_xll.EQNXTDZ($A$1,$B110,E$1,$B$1) -> 0.83333333 | F110: =_xll.EQNXTDZ($A$1,$B110,F$1,$B$1) -> 1.7777778 | G110: =_xll.EQNXTDZ($A$1,$B110,G$1,$B$1) -> 3.0555556 | H110: =_xll.EQNXTDZ($A$1,$B110,H$1,$B$1) -> 2.4444444 | I110: =_xll.EQNXTDZ($A$1,$B110,I$1,$B$1) -> 2.8888889 | J110: =_xll.EQNXTDZ($A$1,$B110,J$1,$B$1) -> 3.7777778 | ... AF110: =_xll.EQNXTDZ($A$1,$B110,AF$1,$B$1) -> 0
A111: Date End | B111: SHP_DATE_END | C111: =_xll.EQNXTDZ($A$1,$B111,C$5) -> 200103 | D111: =_xll.EQNXTDZ($A$1,$B111,D$5) -> 200203 | E111: =_xll.EQNXTDZ($A$1,$B111,E$5) -> 200303 | F111: =_xll.EQNXTDZ($A$1,$B111,F$5) -> 200403 | G111: =_xll.EQNXTDZ($A$1,$B111,G$5) -> 200503 | H111: =_xll.EQNXTDZ($A$1,$B111,H$5) -> 200603 | I111: =_xll.EQNXTDZ($A$1,$B111,I$5) -> 200703 | J111: =_xll.EQNXTDZ($A$1,$B111,J$5) -> 200803 | ... AF111: =_xll.EQNXTDZ($A$1,$B111,AF$5) -> 0
A112: Total of Promoter and Promoter Group | B112: SHP_TPFTOTALPROMOTER | C112: =_xll.EQNXTDZ($A$1,$B112,C$5) -> 0 | D112: =_xll.EQNXTDZ($A$1,$B112,D$5) -> 0 | E112: =_xll.EQNXTDZ($A$1,$B112,E$5) -> 0 | F112: =_xll.EQNXTDZ($A$1,$B112,F$5) -> 0 | G112: =_xll.EQNXTDZ($A$1,$B112,G$5) -> 0 | H112: =_xll.EQNXTDZ($A$1,$B112,H$5) -> 0 | I112: =_xll.EQNXTDZ($A$1,$B112,I$5) -> 0 | J112: =_xll.EQNXTDZ($A$1,$B112,J$5) -> 0 | ... AF112: =_xll.EQNXTDZ($A$1,$B112,AF$5) -> 0
A113: Total of Promoter and Promoter Group Pledged | B113: SHP_PSHFTOTALPROMOTER | C113: =_xll.EQNXTDZ($A$1,$B113,C$5) -> 0 | D113: =_xll.EQNXTDZ($A$1,$B113,D$5) -> 0 | E113: =_xll.EQNXTDZ($A$1,$B113,E$5) -> 0 | F113: =_xll.EQNXTDZ($A$1,$B113,F$5) -> 0 | G113: =_xll.EQNXTDZ($A$1,$B113,G$5) -> 0 | H113: =_xll.EQNXTDZ($A$1,$B113,H$5) -> 0 | I113: =_xll.EQNXTDZ($A$1,$B113,I$5) -> 0 | J113: =_xll.EQNXTDZ($A$1,$B113,J$5) -> 0 | ... AF113: =_xll.EQNXTDZ($A$1,$B113,AF$5) -> 0

Sheet QTR Share Price
A1: ='QTR Raw'!A1 -> 100510 | C1: 201206 | D1: 201207 | E1: 201208 | F1: 201209 | G1: 201210 | H1: 201211 | I1: 201212 | J1: 201301 | K1: 201302 | L1: 201303 | M1: 201304 | N1: 201305 | O1: 201306 | P1: 201307 | Q1: 201308 | R1: 201309 | S1: 201310 | T1: 201311 | U1: 201312 | V1: 201401 | W1: 201402 | X1: 201403 | Y1: 201404 | Z1: 201405 | AA1: 201406 | AB1: 201407 | AC1: 201408 | AD1: 201409 | AE1: 201410 | AF1: 201411 | AG1: 201412 | AH1: 201501 | AI1: 201502 | AJ1: 201503 | AK1: 201504 | AL1: 201505 | AM1: 201506 | AN1: 201507 | AO1: 201508 | AP1: 201509 | AQ1: 201510 | AR1: 201511 | AS1: 201512 | AT1: 201601 | AU1: 201602 | AV1: 201603 | AW1: 201604 | AX1: 201605 | AY1: 201606 | AZ1: 201607 | BA1: 201608 | BB1: 201609 | BC1: 201610 | BD1: 201611 | BE1: 201612 | BF1: 201701 | BG1: 201702 | BH1: 201703 | BI1: 201704 | BJ1: 201705 | BK1: 201706 | BL1: 201707 | BM1: 201708 | BN1: 201709 | BO1: 201710 | BP1: 201711 | BQ1: 201712 | BR1: 201801 | BS1: 201802 | BT1: 201803 | BU1: 201804 | BV1: 201805 | BW1: 201806 | BX1: 201807 | BY1: 201808 | BZ1: 201809 | CA1: 201810 | CB1: 201811 | CC1: 201812 | CD1: 201901 | CE1: 201902 | CF1: 201903 | CG1: 201904 | CH1: 201905 | CI1: 201906 | CJ1: 201907 | CK1: 201908 | CL1: 201909 | CM1: 201910 | CN1: 201911 | CO1: 201912 | CP1: 202001 | CQ1: 202002 | CR1: 202003 | CS1: 202004 | CT1: 202005 | CU1: 202006 | CV1: 202007 | CW1: 202008 | CX1: 202009 | CY1: 202010 | CZ1: 202011 | DA1: 202012 | DB1: 202101 | DC1: 202102 | DD1: 202103 | DE1: 202104 | DF1: 202105 | DG1: 202106 | DH1: 202107 | DI1: 202108 | DJ1: 202109 | DK1: 202110 | DL1: 202111 | DM1: 202112 | DN1: 202201 | DO1: 202202 | DP1: 202203 | DQ1: 202204 | DR1: 202205 | DS1: 202206 | DT1: 202207 | DU1: 202208 | DV1: 202209 | DW1: 202210 | DX1: 202211 | DY1: 202212 | DZ1: 202301 | EA1: 202302 | EB1: 202303 | EC1: 202304 | ED1: 202305 | EE1: 202306 | EF1: 202307 | EG1: 202308 | EH1: 202309 | EI1: 202310 | EJ1: 202311 | EK1: 202312 | EL1: 202401 | EM1: 202402 | EN1: 202403 | EO1: 202404 | EP1: 202405 | EQ1: 202406 | ER1: 202407 | ES1: 202408 | ET1: 202409 | EU1: 202410 | EV1: 202411 | EW1: 202412 | EX1: 202501 | EY1: 202502 | EZ1: 202503 | FA1: 202504 | FB1: 202505 | FC1: 202506 | FD1: 202507 | FE1: 202508 | FF1: 202509 | FG1: 202510 | FH1: 202511 | FI1: 202512 | FJ1: 202601 | FK1: 202602 | FL1: 202603 | FM1: 202604 | FN1: 202605 | FO1: 202606 | FP1: 202607 | FQ1: 202608 | FR1: 202609 | FS1: 202610 | FT1: 202611 | FU1: 202612 | FV1: 202701 | FW1: 202702 | FX1: 202703 | FY1: 202704 | FZ1: 202705 | GA1: 202706 | GB1: 202707 | GC1: 202708 | GD1: 202709 | GE1: 202710 | GF1: 202711 | GG1: 202712 | GH1: 202801 | GI1: 202802 | GJ1: 202803 | GK1: 202804 | GL1: 202805 | GM1: 202806 | GN1: 202807 | GO1: 202808 | GP1: 202809 | GQ1: 202810 | GR1: 202811 | GS1: 202812 | GT1: 202901 | GU1: 202902 | GV1: 202903 | GW1: 202904 | GX1: 202905 | GY1: 202906 | GZ1: 202907 | HA1: 202908 | HB1: 202909 | HC1: 202910 | HD1: 202911 | HE1: 202912 | HF1: 203001 | HG1: 203002 | HH1: 203003 | HM1: 201206 | HN1: 201207 | HO1: 201208 | HP1: 201209 | HQ1: 201212 | HR1: 201303 | HS1: 201306 | HT1: 201309 | HU1: 201312 | HV1: 201403 | HW1: 201406 | HX1: 201409 | HY1: 201412 | HZ1: 201503 | IA1: 201506 | IB1: 201509 | IC1: 201512 | ID1: 201603 | IE1: 201606 | IF1: 201609 | IG1: 201612 | IH1: 201703 | II1: 201706 | IJ1: 201709 | IK1: 201712 | IL1: 201803 | IM1: 201806 | IN1: 201809 | IO1: 201812 | IP1: 201903 | IQ1: 201906 | IR1: 201909 | IS1: 201912 | IT1: 202003 | IU1: 202006 | IV1: 202009 | IW1: 202012 | IX1: 202103 | IY1: 202106 | IZ1: 202109 | JA1: 202112 | JB1: 202203 | JC1: 202206 | JD1: 202209 | JE1: 202212 | JF1: 202303 | JG1: 202306 | JH1: 202309 | JI1: 202312 | JJ1: 202403 | JK1: 202406 | JL1: 202409 | JM1: 202412 | JN1: 202503 | JO1: 202506 | JP1: 202509 | JQ1: 202512 | JR1: 202603 | JS1: 202606 | JT1: 202609 | JU1: 202612 | JV1: 202703 | JW1: 202706 | JX1: 202709 | JY1: 202712 | JZ1: 202803 | KA1: 202806 | KB1: 202809 | KC1: 202812 | KD1: 202903 | KE1: 202906 | KF1: 202909 | KG1: 202912 | KH1: 203003
FF2: 45901 | FG2: =+EOMONTH(FF2,1) -> 45961 | FH2: =+EOMONTH(FG2,1) -> 45991 | FI2: =+EOMONTH(FH2,1) -> 46022 | FJ2: =+EOMONTH(FI2,1) -> 46053 | FK2: =+EOMONTH(FJ2,1) -> 46081 | FL2: =+EOMONTH(FK2,1) -> 46112 | FM2: =+EOMONTH(FL2,1) -> 46142 | FN2: =+EOMONTH(FM2,1) -> 46173 | ... HH2: =+EOMONTH(HG2,1) -> 47573
A4: Field Description | B4: Field Name
A5: MonthEnd | B5: NMONTH_MONTHEND | C5: {=_xll.EQNXTDZ($A$1,$B5,C$1)} -> 201206 | D5: {=_xll.EQNXTDZ($A$1,$B5,D$1)} -> 201207 | E5: {=_xll.EQNXTDZ($A$1,$B5,E$1)} -> 201208 | F5: {=_xll.EQNXTDZ($A$1,$B5,F$1)} -> 201209 | G5: {=_xll.EQNXTDZ($A$1,$B5,G$1)} -> 201210 | H5: {=_xll.EQNXTDZ($A$1,$B5,H$1)} -> 201211 | I5: {=_xll.EQNXTDZ($A$1,$B5,I$1)} -> 201212 | J5: {=_xll.EQNXTDZ($A$1,$B5,J$1)} -> 201301 | ... HH5: {=_xll.EQNXTDZ($A$1,$B5,HH$1)} -> 0
A6: Open | B6: NMONTH_OPEN | C6: {=_xll.EQNXTDZ($A$1,$B6,C$1)} -> 518 | D6: {=_xll.EQNXTDZ($A$1,$B6,D$1)} -> 622.55556 | E6: {=_xll.EQNXTDZ($A$1,$B6,E$1)} -> 606.93333 | F6: {=_xll.EQNXTDZ($A$1,$B6,F$1)} -> 602.84444 | G6: {=_xll.EQNXTDZ($A$1,$B6,G$1)} -> 707.8 | H6: {=_xll.EQNXTDZ($A$1,$B6,H$1)} -> 724.97778 | I6: {=_xll.EQNXTDZ($A$1,$B6,I$1)} -> 744.28889 | J6: {=_xll.EQNXTDZ($A$1,$B6,J$1)} -> 718.31111 | ... HH6: {=_xll.EQNXTDZ($A$1,$B6,HH$1)} -> 0
A7: High | B7: NMONTH_HIGH | C7: {=_xll.EQNXTDZ($A$1,$B7,C$1)} -> 622.66667 | D7: {=_xll.EQNXTDZ($A$1,$B7,D$1)} -> 640.88889 | E7: {=_xll.EQNXTDZ($A$1,$B7,E$1)} -> 658.53333 | F7: {=_xll.EQNXTDZ($A$1,$B7,F$1)} -> 719.91111 | G7: {=_xll.EQNXTDZ($A$1,$B7,G$1)} -> 764.44444 | H7: {=_xll.EQNXTDZ($A$1,$B7,H$1)} -> 751.11111 | I7: {=_xll.EQNXTDZ($A$1,$B7,I$1)} -> 755.11111 | J7: {=_xll.EQNXTDZ($A$1,$B7,J$1)} -> 738.35556 | ... HH7: {=_xll.EQNXTDZ($A$1,$B7,HH$1)} -> 0 | HP7: =+MAX(D7:F7) -> 719.91111 | HQ7: =+MAX(G7:I7) -> 764.44444 | HR7: =+MAX(J7:L7) -> 738.35556 | HS7: =+MAX(M7:O7) -> 734.22222 | HT7: =+MAX(P7:R7) -> 673.93333 | HU7: =+MAX(S7:U7) -> 769.6 | HV7: =+MAX(V7:X7) -> 868.16667 | HW7: =+MAX(Y7:AA7) -> 1184.4 | HX7: =+MAX(AB7:AD7) -> 1177.2667 | HY7: =+MAX(AE7:AG7) -> 1128.6 | HZ7: =+MAX(AH7:AJ7) -> 1262.5333 | IA7: =+MAX(AK7:AM7) -> 1213.3 | IB7: =+MAX(AN7:AP7) -> 1258.6667 | IC7: =+MAX(AQ7:AS7) -> 1073.3333 | ID7: =+MAX(AT7:AV7) -> 860.66667 | IE7: =+MAX(AW7:AY7) -> 1011.3333 | IF7: =+MAX(AZ7:BB7) -> 1076.6667 | IG7: =+MAX(BC7:BE7) -> 1013.3333 | IH7: =+MAX(BF7:BH7) -> 1062.4333 | II7: =+MAX(BI7:BK7) -> 1222.6333 | IJ7: =+MAX(BL7:BN7) -> 1250.5 | IK7: =+MAX(BO7:BQ7) -> 1275.95 | IL7: =+MAX(BR7:BT7) -> 1470 | IM7: =+MAX(BU7:BW7) -> 1424.95 | IN7: =+MAX(BX7:BZ7) -> 1390 | IO7: =+MAX(CA7:CC7) -> 1459.7 | IP7: =+MAX(CD7:CF7) -> 1445 | IQ7: =+MAX(CG7:CI7) -> 1607 | IR7: =+MAX(CJ7:CL7) -> 1591.65 | IS7: =+MAX(CM7:CO7) -> 1496.45 | IT7: =+MAX(CP7:CR7) -> 1383.7 | IU7: =+MAX(CS7:CU7) -> 995 | IV7: =+MAX(CV7:CX7) -> 1024.95 | IW7: =+MAX(CY7:DA7) -> 1338.5 | IX7: =+MAX(DB7:DD7) -> 1593 | IY7: =+MAX(DE7:DG7) -> 1583 | IZ7: =+MAX(DH7:DJ7) -> 1810 | JA7: =+MAX(DK7:DM7) -> 1981.75 | JB7: =+MAX(DN7:DP7) -> 2078.55 | JC7: =+MAX(DQ7:DS7) -> 1858 | JD7: =+MAX(DT7:DV7) -> 1995 | JE7: =+MAX(DW7:DY7) -> 2211.6 | JF7: =+MAX(DZ7:EB7) -> 2297.65 | JG7: =+MAX(EC7:EE7) -> 2483.5 | JH7: =+MAX(EF7:EH7) -> 3058.35 | JI7: =+MAX(EI7:EK7) -> 3559.95 | JJ7: =+MAX(EL7:EN7) -> 3813.35 | JK7: =MAX(EO7:EQ7) -> 3919.9 | JL7: =MAX(ER7:ET7) -> 3838.95 | JM7: =MAX(EU7:EW7) -> 3963.5 | JN7: =MAX(EX7:EZ7) -> 3724.1 | JO7: =MAX(FA7:FC7) -> 3731.4 | JP7: =MAX(FD7:FF7) -> 3794.9 | JQ7: =MAX(FG7:FI7) -> 4140 | JR7: =MAX(FJ7:FL7) -> 4440 | JS7: =MAX(FM7:FO7) -> 4235.4 | JT7: =MAX(FP7:FR7) -> 0 | JU7: =MAX(FS7:FU7) -> 0 | JV7: =MAX(FV7:FX7) -> 0 | JW7: =MAX(FY7:GA7) -> 0 | JX7: =MAX(GB7:GD7) -> 0 | JY7: =MAX(GE7:GG7) -> 0 | JZ7: =MAX(GH7:GJ7) -> 0 | KA7: =MAX(GK7:GM7) -> 0 | KB7: =MAX(GN7:GP7) -> 0 | KC7: =MAX(GQ7:GS7) -> 0 | KD7: =MAX(GT7:GV7) -> 0 | KE7: =MAX(GW7:GY7) -> 0 | KF7: =MAX(GZ7:HB7) -> 0 | KG7: =MAX(HC7:HE7) -> 0 | KH7: =MAX(HF7:HH7) -> 0
A8: Low | B8: NMONTH_LOW | C8: {=_xll.EQNXTDZ($A$1,$B8,C$1)} -> 491.57778 | D8: {=_xll.EQNXTDZ($A$1,$B8,D$1)} -> 581.28889 | E8: {=_xll.EQNXTDZ($A$1,$B8,E$1)} -> 588.6 | F8: {=_xll.EQNXTDZ($A$1,$B8,F$1)} -> 581.8 | G8: {=_xll.EQNXTDZ($A$1,$B8,G$1)} -> 581 | H8: {=_xll.EQNXTDZ($A$1,$B8,H$1)} -> 682.71111 | I8: {=_xll.EQNXTDZ($A$1,$B8,I$1)} -> 698.93333 | J8: {=_xll.EQNXTDZ($A$1,$B8,J$1)} -> 666.22222 | ... HH8: {=_xll.EQNXTDZ($A$1,$B8,HH$1)} -> 0 | HP8: =+MIN(D8:F8) -> 581.28889 | HQ8: =+MIN(G8:I8) -> 581 | HR8: =+MIN(J8:L8) -> 592.66667 | HS8: =+MIN(M8:O8) -> 583.55556 | HT8: =+MIN(P8:R8) -> 451.43333 | HU8: =+MIN(S8:U8) -> 517.7 | HV8: =+MIN(V8:X8) -> 634.33333 | HW8: =+MIN(Y8:AA8) -> 828 | HX8: =+MIN(AB8:AD8) -> 954.43333 | HY8: =+MIN(AE8:AG8) -> 934 | HZ8: =+MIN(AH8:AJ8) -> 990.36667 | IA8: =+MIN(AK8:AM8) -> 1029.0667 | IB8: =+MIN(AN8:AP8) -> 941.56667 | IC8: =+MIN(AQ8:AS8) -> 843 | ID8: =+MIN(AT8:AV8) -> 677.36667 | IE8: =+MIN(AW8:AY8) -> 785.2 | IF8: =+MIN(AZ8:BB8) -> 941 | IG8: =+MIN(BC8:BE8) -> 863.4 | IH8: =+MIN(BF8:BH8) -> 899.43333 | II8: =+MIN(BI8:BK8) -> 1051.0667 | IJ8: =+MIN(BL8:BN8) -> 1113.05 | IK8: =+MIN(BO8:BQ8) -> 1123.2 | IL8: =+MIN(BR8:BT8) -> 1242.85 | IM8: =+MIN(BU8:BW8) -> 1206 | IN8: =+MIN(BX8:BZ8) -> 1226 | IO8: =+MIN(CA8:CC8) -> 1182.5 | IP8: =+MIN(CD8:CF8) -> 1201.1 | IQ8: =+MIN(CG8:CI8) -> 1285.3 | IR8: =+MIN(CJ8:CL8) -> 1274 | IS8: =+MIN(CM8:CO8) -> 1255 | IT8: =+MIN(CP8:CR8) -> 661 | IU8: =+MIN(CS8:CU8) -> 762.8 | IV8: =+MIN(CV8:CX8) -> 843 | IW8: =+MIN(CY8:DA8) -> 876.05 | IX8: =+MIN(DB8:DD8) -> 1283 | IY8: =+MIN(DE8:DG8) -> 1306 | IZ8: =+MIN(DH8:DJ8) -> 1475.5 | JA8: =+MIN(DK8:DM8) -> 1684.05 | JB8: =+MIN(DN8:DP8) -> 1595 | JC8: =+MIN(DQ8:DS8) -> 1456.35 | JD8: =+MIN(DT8:DV8) -> 1534.6 | JE8: =+MIN(DW8:DY8) -> 1814 | JF8: =+MIN(DZ8:EB8) -> 2058 | JG8: =+MIN(EC8:EE8) -> 2155 | JH8: =+MIN(EF8:EH8) -> 2420 | JI8: =+MIN(EI8:EK8) -> 2856.15 | JJ8: =+MIN(EL8:EN8) -> 3263.05 | JK8: =MIN(EO8:EQ8) -> 3175.05 | JL8: =MIN(ER8:ET8) -> 3460 | JM8: =MIN(EU8:EW8) -> 3262.55 | JN8: =MIN(EX8:EZ8) -> 3141 | JO8: =MIN(FA8:FC8) -> 2965.3 | JP8: =MIN(FD8:FF8) -> 3405.1 | JQ8: =MIN(FG8:FI8) -> 3615 | JR8: =MIN(FJ8:FL8) -> 3288.1 | JS8: =MIN(FM8:FO8) -> 3470 | JT8: =MIN(FP8:FR8) -> 0 | JU8: =MIN(FS8:FU8) -> 0 | JV8: =MIN(FV8:FX8) -> 0 | JW8: =MIN(FY8:GA8) -> 0 | JX8: =MIN(GB8:GD8) -> 0 | JY8: =MIN(GE8:GG8) -> 0 | JZ8: =MIN(GH8:GJ8) -> 0 | KA8: =MIN(GK8:GM8) -> 0 | KB8: =MIN(GN8:GP8) -> 0 | KC8: =MIN(GQ8:GS8) -> 0 | KD8: =MIN(GT8:GV8) -> 0 | KE8: =MIN(GW8:GY8) -> 0 | KF8: =MIN(GZ8:HB8) -> 0 | KG8: =MIN(HC8:HE8) -> 0 | KH8: =MIN(HF8:HH8) -> 0
A9: Close | B9: NMONTH_CLOSE | C9: {=_xll.EQNXTDZ($A$1,$B9,C$1)} -> 621.24444 | D9: {=_xll.EQNXTDZ($A$1,$B9,D$1)} -> 608.62222 | E9: {=_xll.EQNXTDZ($A$1,$B9,E$1)} -> 596.84444 | F9: {=_xll.EQNXTDZ($A$1,$B9,F$1)} -> 709.68889 | G9: {=_xll.EQNXTDZ($A$1,$B9,G$1)} -> 723.04444 | H9: {=_xll.EQNXTDZ($A$1,$B9,H$1)} -> 741.28889 | I9: {=_xll.EQNXTDZ($A$1,$B9,I$1)} -> 714.28889 | J9: {=_xll.EQNXTDZ($A$1,$B9,J$1)} -> 685.26667 | ... HH9: {=_xll.EQNXTDZ($A$1,$B9,HH$1)} -> 0 | HP9: =+F9 -> 709.68889 | HQ9: =+I9 -> 714.28889 | HR9: =+L9 -> 607.2 | HS9: =+O9 -> 625.73333 | HT9: =+R9 -> 525.83333 | HU9: =+U9 -> 713.5 | HV9: =+X9 -> 847.93333 | HW9: =+AA9 -> 1134.4667 | HX9: =+AD9 -> 972.16667 | HY9: =+AG9 -> 996.43333 | HZ9: =+AJ9 -> 1146.4333 | IA9: =+AM9 -> 1188.5333 | IB9: =+AP9 -> 977.5 | IC9: =+AS9 -> 850.3 | ID9: =+AV9 -> 811.13333 | IE9: =+AY9 -> 997.66667 | IF9: =+BB9 -> 955.43333 | IG9: =+BE9 -> 899.4 | IH9: =+BH9 -> 1049.9333 | II9: =+BK9 -> 1125.0667 | IJ9: =+BN9 -> 1142.05 | IK9: =+BQ9 -> 1258.25 | IL9: =+BT9 -> 1310.9 | IM9: =+BW9 -> 1275.1 | IN9: =+BZ9 -> 1272.1 | IO9: =+CC9 -> 1437.55 | IP9: =+CF9 -> 1385.3 | IQ9: =+CI9 -> 1553.2 | IR9: =+CL9 -> 1474.25 | IS9: =+CO9 -> 1298.2 | IT9: =+CR9 -> 808.5 | IU9: =+CU9 -> 943.65 | IV9: =+CX9 -> 901.6 | IW9: =+DA9 -> 1287.6 | IX9: =+DD9 -> 1418.9 | IY9: =+DG9 -> 1500.55 | IZ9: =+DJ9 -> 1702.95 | JA9: =+DM9 -> 1895.9 | JB9: =+DP9 -> 1767.65 | JC9: =+DS9 -> 1558.25 | JD9: =+DV9 -> 1847.7 | JE9: =+DY9 -> 2085.8 | JF9: =+EB9 -> 2164.2 | JG9: =+EE9 -> 2475.55 | JH9: =+EH9 -> 3023.55 | JI9: =+EK9 -> 3526 | JJ9: =+EN9 -> 3763.9 | JK9: =EQ9 -> 3548.45 | JL9: =ET9 -> 3675.55 | JM9: =EW9 -> 3607.65 | JN9: =EZ9 -> 3492.3 | JO9: =FC9 -> 3669.8 | JP9: =FF9 -> 3659 | JQ9: =FI9 -> 4083.5 | JR9: =FL9 -> 3504.1 | JS9: =FO9 -> 4186.4 | JT9: =FR9 -> 0 | JU9: =FU9 -> 0 | JV9: =FX9 -> 0 | JW9: =GA9 -> 0 | JX9: =GD9 -> 0 | JY9: =GG9 -> 0 | JZ9: =GJ9 -> 0 | KA9: =GM9 -> 0 | KB9: =GP9 -> 0 | KC9: =GS9 -> 0 | KD9: =GV9 -> 0 | KE9: =GY9 -> 0 | KF9: =HB9 -> 0 | KG9: =HE9 -> 0 | KH9: =HH9 -> 0
A11: Field Description | B11: Field Name | C11: {=_xll.EQNXTDZ($A$1,$B11,C$1)} -> 0 | D11: {=_xll.EQNXTDZ($A$1,$B11,D$1)} -> 0 | E11: {=_xll.EQNXTDZ($A$1,$B11,E$1)} -> 0 | F11: {=_xll.EQNXTDZ($A$1,$B11,F$1)} -> 0 | G11: {=_xll.EQNXTDZ($A$1,$B11,G$1)} -> 0 | H11: {=_xll.EQNXTDZ($A$1,$B11,H$1)} -> 0 | I11: {=_xll.EQNXTDZ($A$1,$B11,I$1)} -> 0 | J11: {=_xll.EQNXTDZ($A$1,$B11,J$1)} -> 0 | ... HH11: {=_xll.EQNXTDZ($A$1,$B11,HH$1)} -> 0
A12: Month End | B12: BMONTH_MONTHEND | C12: {=_xll.EQNXTDZ($A$1,$B12,C$1)} -> 201206 | D12: {=_xll.EQNXTDZ($A$1,$B12,D$1)} -> 201207 | E12: {=_xll.EQNXTDZ($A$1,$B12,E$1)} -> 201208 | F12: {=_xll.EQNXTDZ($A$1,$B12,F$1)} -> 201209 | G12: {=_xll.EQNXTDZ($A$1,$B12,G$1)} -> 201210 | H12: {=_xll.EQNXTDZ($A$1,$B12,H$1)} -> 201211 | I12: {=_xll.EQNXTDZ($A$1,$B12,I$1)} -> 201212 | J12: {=_xll.EQNXTDZ($A$1,$B12,J$1)} -> 201301 | ... HH12: {=_xll.EQNXTDZ($A$1,$B12,HH$1)} -> 0
A13: Open | B13: BMONTH_OPEN | C13: {=_xll.EQNXTDZ($A$1,$B13,C$1)} -> 519.11111 | D13: {=_xll.EQNXTDZ($A$1,$B13,D$1)} -> 622.22222 | E13: {=_xll.EQNXTDZ($A$1,$B13,E$1)} -> 607.91111 | F13: {=_xll.EQNXTDZ($A$1,$B13,F$1)} -> 601.77778 | G13: {=_xll.EQNXTDZ($A$1,$B13,G$1)} -> 707.55556 | H13: {=_xll.EQNXTDZ($A$1,$B13,H$1)} -> 724.44444 | I13: {=_xll.EQNXTDZ($A$1,$B13,I$1)} -> 742.22222 | J13: {=_xll.EQNXTDZ($A$1,$B13,J$1)} -> 718.22222 | ... HH13: {=_xll.EQNXTDZ($A$1,$B13,HH$1)} -> 0
A14: High | B14: BMONTH_HIGH | C14: {=_xll.EQNXTDZ($A$1,$B14,C$1)} -> 622.22222 | D14: {=_xll.EQNXTDZ($A$1,$B14,D$1)} -> 640.82222 | E14: {=_xll.EQNXTDZ($A$1,$B14,E$1)} -> 658.31111 | F14: {=_xll.EQNXTDZ($A$1,$B14,F$1)} -> 719.55556 | G14: {=_xll.EQNXTDZ($A$1,$B14,G$1)} -> 764.22222 | H14: {=_xll.EQNXTDZ($A$1,$B14,H$1)} -> 751.82222 | I14: {=_xll.EQNXTDZ($A$1,$B14,I$1)} -> 755.11111 | J14: {=_xll.EQNXTDZ($A$1,$B14,J$1)} -> 738.22222 | ... HH14: {=_xll.EQNXTDZ($A$1,$B14,HH$1)} -> 0 | HP14: =+MAX(D14:F14) -> 719.55556 | HQ14: =+MAX(G14:I14) -> 764.22222 | HR14: =+MAX(J14:L14) -> 738.22222 | HS14: =+MAX(M14:O14) -> 734.26667 | HT14: =+MAX(P14:R14) -> 673.2 | HU14: =+MAX(S14:U14) -> 768.26667 | HV14: =+MAX(V14:X14) -> 867.33333 | HW14: =+MAX(Y14:AA14) -> 1183.1333 | HX14: =+MAX(AB14:AD14) -> 1175.3333 | HY14: =+MAX(AE14:AG14) -> 1128.4 | HZ14: =+MAX(AH14:AJ14) -> 1261.9667 | IA14: =+MAX(AK14:AM14) -> 1213.3333 | IB14: =+MAX(AN14:AP14) -> 1257.5 | IC14: =+MAX(AQ14:AS14) -> 1073.6 | ID14: =+MAX(AT14:AV14) -> 860.83333 | IE14: =+MAX(AW14:AY14) -> 1010 | IF14: =+MAX(AZ14:BB14) -> 1076.6667 | IG14: =+MAX(BC14:BE14) -> 1013.3333 | IH14: =+MAX(BF14:BH14) -> 1062 | II14: =+MAX(BI14:BK14) -> 1222.6667 | IJ14: =+MAX(BL14:BN14) -> 1249.95 | IK14: =+MAX(BO14:BQ14) -> 1275 | IL14: =+MAX(BR14:BT14) -> 1469.6 | IM14: =+MAX(BU14:BW14) -> 1424.5 | IN14: =+MAX(BX14:BZ14) -> 1389 | IO14: =+MAX(CA14:CC14) -> 1459.1 | IP14: =+MAX(CD14:CF14) -> 1449 | IQ14: =+MAX(CG14:CI14) -> 1606.7 | IR14: =+MAX(CJ14:CL14) -> 1591.6 | IS14: =+MAX(CM14:CO14) -> 1495.95 | IT14: =+MAX(CP14:CR14) -> 1383.85 | IU14: =+MAX(CS14:CU14) -> 995 | IV14: =+MAX(CV14:CX14) -> 1024.95 | IW14: =+MAX(CY14:DA14) -> 1338.4 | IX14: =+MAX(DB14:DD14) -> 1593 | IY14: =+MAX(DE14:DG14) -> 1582.65 | IZ14: =+MAX(DH14:DJ14) -> 1810 | JA14: =+MAX(DK14:DM14) -> 1982.95 | JB14: =+MAX(DN14:DP14) -> 2078.2 | JC14: =+MAX(DQ14:DS14) -> 1860 | JD14: =+MAX(DT14:DV14) -> 1995 | JE14: =+MAX(DW14:DY14) -> 2210.5 | JF14: =+MAX(DZ14:EB14) -> 2297.3 | JG14: =+MAX(EC14:EE14) -> 2482.95 | JH14: =+MAX(EF14:EH14) -> 3057 | JI14: =+MAX(EI14:EK14) -> 3559.75 | JJ14: =+MAX(EL14:EN14) -> 3812 | JK14: =MAX(EO14:EQ14) -> 3948.6 | JL14: =MAX(ER14:ET14) -> 3838 | JM14: =MAX(EU14:EW14) -> 3963 | JN14: =MAX(EX14:EZ14) -> 3724 | JO14: =MAX(FA14:FC14) -> 3730 | JP14: =MAX(FD14:FF14) -> 3794.7 | JQ14: =MAX(FG14:FI14) -> 4139 | JR14: =MAX(FJ14:FL14) -> 4440 | JS14: =MAX(FM14:FO14) -> 4235 | JT14: =MAX(FP14:FR14) -> 0 | JU14: =MAX(FS14:FU14) -> 0 | JV14: =MAX(FV14:FX14) -> 0 | JW14: =MAX(FY14:GA14) -> 0 | JX14: =MAX(GB14:GD14) -> 0 | JY14: =MAX(GE14:GG14) -> 0 | JZ14: =MAX(GH14:GJ14) -> 0 | KA14: =MAX(GK14:GM14) -> 0 | KB14: =MAX(GN14:GP14) -> 0 | KC14: =MAX(GQ14:GS14) -> 0 | KD14: =MAX(GT14:GV14) -> 0 | KE14: =MAX(GW14:GY14) -> 0 | KF14: =MAX(GZ14:HB14) -> 0 | KG14: =MAX(HC14:HE14) -> 0 | KH14: =MAX(HF14:HH14) -> 0
A15: Low | B15: BMONTH_LOW | C15: {=_xll.EQNXTDZ($A$1,$B15,C$1)} -> 491.73333 | D15: {=_xll.EQNXTDZ($A$1,$B15,D$1)} -> 581.33333 | E15: {=_xll.EQNXTDZ($A$1,$B15,E$1)} -> 588.48889 | F15: {=_xll.EQNXTDZ($A$1,$B15,F$1)} -> 582.22222 | G15: {=_xll.EQNXTDZ($A$1,$B15,G$1)} -> 702.88889 | H15: {=_xll.EQNXTDZ($A$1,$B15,H$1)} -> 683.2 | I15: {=_xll.EQNXTDZ($A$1,$B15,I$1)} -> 698.88889 | J15: {=_xll.EQNXTDZ($A$1,$B15,J$1)} -> 666.66667 | ... HH15: {=_xll.EQNXTDZ($A$1,$B15,HH$1)} -> 0 | HP15: =+MIN(D15:F15) -> 581.33333 | HQ15: =+MIN(G15:I15) -> 683.2 | HR15: =+MIN(J15:L15) -> 591.55556 | HS15: =+MIN(M15:O15) -> 583.64444 | HT15: =+MIN(P15:R15) -> 452.06667 | HU15: =+MIN(S15:U15) -> 518.06667 | HV15: =+MIN(V15:X15) -> 634.4 | HW15: =+MIN(Y15:AA15) -> 828.3 | HX15: =+MIN(AB15:AD15) -> 956.9 | HY15: =+MIN(AE15:AG15) -> 933.33333 | HZ15: =+MIN(AH15:AJ15) -> 991.03333 | IA15: =+MIN(AK15:AM15) -> 1030.2333 | IB15: =+MIN(AN15:AP15) -> 942.1 | IC15: =+MIN(AQ15:AS15) -> 843.66667 | ID15: =+MIN(AT15:AV15) -> 677.73333 | IE15: =+MIN(AW15:AY15) -> 784.66667 | IF15: =+MIN(AZ15:BB15) -> 941.7 | IG15: =+MIN(BC15:BE15) -> 863.53333 | IH15: =+MIN(BF15:BH15) -> 900 | II15: =+MIN(BI15:BK15) -> 1052 | IJ15: =+MIN(BL15:BN15) -> 1114 | IK15: =+MIN(BO15:BQ15) -> 1124.5 | IL15: =+MIN(BR15:BT15) -> 1243.15 | IM15: =+MIN(BU15:BW15) -> 1205.6 | IN15: =+MIN(BX15:BZ15) -> 1226.05 | IO15: =+MIN(CA15:CC15) -> 1183.4 | IP15: =+MIN(CD15:CF15) -> 1202.3 | IQ15: =+MIN(CG15:CI15) -> 1284.9 | IR15: =+MIN(CJ15:CL15) -> 1274.1 | IS15: =+MIN(CM15:CO15) -> 1255.6 | IT15: =+MIN(CP15:CR15) -> 661.05 | IU15: =+MIN(CS15:CU15) -> 763 | IV15: =+MIN(CV15:CX15) -> 842.5 | IW15: =+MIN(CY15:DA15) -> 876.25 | IX15: =+MIN(DB15:DD15) -> 1281 | IY15: =+MIN(DE15:DG15) -> 1306.4 | IZ15: =+MIN(DH15:DJ15) -> 1475.85 | JA15: =+MIN(DK15:DM15) -> 1684.4 | JB15: =+MIN(DN15:DP15) -> 1595 | JC15: =+MIN(DQ15:DS15) -> 1456.8 | JD15: =+MIN(DT15:DV15) -> 1535 | JE15: =+MIN(DW15:DY15) -> 1814 | JF15: =+MIN(DZ15:EB15) -> 2058.1 | JG15: =+MIN(EC15:EE15) -> 2155.55 | JH15: =+MIN(EF15:EH15) -> 2419.95 | JI15: =+MIN(EI15:EK15) -> 2856.85 | JJ15: =+MIN(EL15:EN15) -> 3264 | JK15: =MIN(EO15:EQ15) -> 3175.5 | JL15: =MIN(ER15:ET15) -> 3401.05 | JM15: =MIN(EU15:EW15) -> 3262.95 | JN15: =MIN(EX15:EZ15) -> 3141.3 | JO15: =MIN(FA15:FC15) -> 2967.65 | JP15: =MIN(FD15:FF15) -> 3405.3 | JQ15: =MIN(FG15:FI15) -> 3614.8 | JR15: =MIN(FJ15:FL15) -> 3288.65 | JS15: =MIN(FM15:FO15) -> 3470 | JT15: =MIN(FP15:FR15) -> 0 | JU15: =MIN(FS15:FU15) -> 0 | JV15: =MIN(FV15:FX15) -> 0 | JW15: =MIN(FY15:GA15) -> 0 | JX15: =MIN(GB15:GD15) -> 0 | JY15: =MIN(GE15:GG15) -> 0 | JZ15: =MIN(GH15:GJ15) -> 0 | KA15: =MIN(GK15:GM15) -> 0 | KB15: =MIN(GN15:GP15) -> 0 | KC15: =MIN(GQ15:GS15) -> 0 | KD15: =MIN(GT15:GV15) -> 0 | KE15: =MIN(GW15:GY15) -> 0 | KF15: =MIN(GZ15:HB15) -> 0 | KG15: =MIN(HC15:HE15) -> 0 | KH15: =MIN(HF15:HH15) -> 0
A16: Close | B16: BMONTH_CLOSE | C16: {=_xll.EQNXTDZ($A$1,$B16,C$1)} -> 621.04444 | D16: {=_xll.EQNXTDZ($A$1,$B16,D$1)} -> 608.73333 | E16: {=_xll.EQNXTDZ($A$1,$B16,E$1)} -> 596.17778 | F16: {=_xll.EQNXTDZ($A$1,$B16,F$1)} -> 709.66667 | G16: {=_xll.EQNXTDZ($A$1,$B16,G$1)} -> 722.11111 | H16: {=_xll.EQNXTDZ($A$1,$B16,H$1)} -> 740.93333 | I16: {=_xll.EQNXTDZ($A$1,$B16,I$1)} -> 713.71111 | J16: {=_xll.EQNXTDZ($A$1,$B16,J$1)} -> 685.73333 | ... HH16: {=_xll.EQNXTDZ($A$1,$B16,HH$1)} -> 0 | HP16: =+F16 -> 709.66667 | HQ16: =+I16 -> 713.71111 | HR16: =+L16 -> 606.62222 | HS16: =+O16 -> 624.06667 | HT16: =+R16 -> 525.73333 | HU16: =+U16 -> 713.26667 | HV16: =+X16 -> 848.43333 | HW16: =+AA16 -> 1134.4 | HX16: =+AD16 -> 971.63333 | HY16: =+AG16 -> 997.66667 | HZ16: =+AJ16 -> 1146 | IA16: =+AM16 -> 1188.5 | IB16: =+AP16 -> 977.8 | IC16: =+AS16 -> 850.43333 | ID16: =+AV16 -> 810.8 | IE16: =+AY16 -> 997.46667 | IF16: =+BB16 -> 954.43333 | IG16: =+BE16 -> 899.6 | IH16: =+BH16 -> 1051.7333 | II16: =+BK16 -> 1125.2 | IJ16: =+BN16 -> 1141.2 | IK16: =+BQ16 -> 1256.95 | IL16: =+BT16 -> 1311.9 | IM16: =+BW16 -> 1271.3 | IN16: =+BZ16 -> 1266.65 | IO16: =+CC16 -> 1438.5 | IP16: =+CF16 -> 1384.05 | IQ16: =+CI16 -> 1553.05 | IR16: =+CL16 -> 1476.6 | IS16: =+CO16 -> 1298.95 | IT16: =+CR16 -> 806.85 | IU16: =+CU16 -> 944.05 | IV16: =+CX16 -> 902.45 | IW16: =+DA16 -> 1287.55 | IX16: =+DD16 -> 1418.35 | IY16: =+DG16 -> 1501.25 | IZ16: =+DJ16 -> 1703.15 | JA16: =+DM16 -> 1895 | JB16: =+DP16 -> 1767.45 | JC16: =+DS16 -> 1557.05 | JD16: =+DV16 -> 1848.7 | JE16: =+DY16 -> 2086.3 | JF16: =+EB16 -> 2164.75 | JG16: =+EE16 -> 2474.5 | JH16: =+EH16 -> 3021.95 | JI16: =+EK16 -> 3527.05 | JJ16: =+EN16 -> 3774.1 | JK16: =EQ16 -> 3549.4 | JL16: =ET16 -> 3675.5 | JM16: =EW16 -> 3608 | JN16: =EZ16 -> 3491 | JO16: =FC16 -> 3668.55 | JP16: =FF16 -> 3658.8 | JQ16: =FI16 -> 4083.1 | JR16: =FL16 -> 3504.3 | JS16: =FO16 -> 4185.7 | JT16: =FR16 -> 0 | JU16: =FU16 -> 0 | JV16: =FX16 -> 0 | JW16: =GA16 -> 0 | JX16: =GD16 -> 0 | JY16: =GG16 -> 0 | JZ16: =GJ16 -> 0 | KA16: =GM16 -> 0 | KB16: =GP16 -> 0 | KC16: =GS16 -> 0 | KD16: =GV16 -> 0 | KE16: =GY16 -> 0 | KF16: =HB16 -> 0 | KG16: =HE16 -> 0 | KH16: =HH16 -> 0
A19: High | HP19: =+IF(HP14=0,HP7,HP14) -> 719.55556 | HQ19: =+IF(HQ14=0,HQ7,HQ14) -> 764.22222 | HR19: =+IF(HR14=0,HR7,HR14) -> 738.22222 | HS19: =+IF(HS14=0,HS7,HS14) -> 734.26667 | HT19: =+IF(HT14=0,HT7,HT14) -> 673.2 | HU19: =+IF(HU14=0,HU7,HU14) -> 768.26667 | HV19: =+IF(HV14=0,HV7,HV14) -> 867.33333 | HW19: =+IF(HW14=0,HW7,HW14) -> 1183.1333 | ... KH19: =+IF(KH14=0,KH7,KH14) -> 0
A20: Low | HP20: =+IF(HP15=0,HP8,HP15) -> 581.33333 | HQ20: =+IF(HQ15=0,HQ8,HQ15) -> 683.2 | HR20: =+IF(HR15=0,HR8,HR15) -> 591.55556 | HS20: =+IF(HS15=0,HS8,HS15) -> 583.64444 | HT20: =+IF(HT15=0,HT8,HT15) -> 452.06667 | HU20: =+IF(HU15=0,HU8,HU15) -> 518.06667 | HV20: =+IF(HV15=0,HV8,HV15) -> 634.4 | HW20: =+IF(HW15=0,HW8,HW15) -> 828.3 | ... KH20: =+IF(KH15=0,KH8,KH15) -> 0
A21: Close | HP21: =+IF(HP16=0,HP9,HP16) -> 709.66667 | HQ21: =+IF(HQ16=0,HQ9,HQ16) -> 713.71111 | HR21: =+IF(HR16=0,HR9,HR16) -> 606.62222 | HS21: =+IF(HS16=0,HS9,HS16) -> 624.06667 | HT21: =+IF(HT16=0,HT9,HT16) -> 525.73333 | HU21: =+IF(HU16=0,HU9,HU16) -> 713.26667 | HV21: =+IF(HV16=0,HV9,HV16) -> 848.43333 | HW21: =+IF(HW16=0,HW9,HW16) -> 1134.4 | ... KH21: =+IF(KH16=0,KH9,KH16) -> 0

Sheet QTR No. of Shares
A1: ='QTR Raw'!A1 -> 100510 | C1: 201206 | D1: 201209 | E1: 201212 | F1: 201303 | G1: 201306 | H1: 201309 | I1: 201312 | J1: 201403 | K1: 201406 | L1: 201409 | M1: 201412 | N1: 201503 | O1: 201506 | P1: 201509 | Q1: 201512 | R1: 201603 | S1: 201606 | T1: 201609 | U1: 201612 | V1: 201703 | W1: 201706 | X1: 201709 | Y1: 201712 | Z1: 201803 | AA1: 201806 | AB1: 201809 | AC1: 201812 | AD1: 201903 | AE1: 201906 | AF1: 201909 | AG1: 201912 | AH1: 202003 | AI1: 202006 | AJ1: 202009 | AK1: 202012 | AL1: 202103 | AM1: 202106 | AN1: 202109 | AO1: 202112 | AP1: 202203 | AQ1: 202206 | AR1: 202209 | AS1: 202212 | AT1: 202303 | AU1: 202306 | AV1: 202309 | AW1: 202312 | AX1: 202403 | AY1: 202406
A4: Field Description | B4: Field Name
A5: Date End | B5: SHP_DATE_END | C5: {=_xll.EQNXTDZ($A$1,$B5,C$1)} -> 201206 | D5: {=_xll.EQNXTDZ($A$1,$B5,D$1)} -> 201209 | E5: {=_xll.EQNXTDZ($A$1,$B5,E$1)} -> 201212 | F5: {=_xll.EQNXTDZ($A$1,$B5,F$1)} -> 201303 | G5: {=_xll.EQNXTDZ($A$1,$B5,G$1)} -> 201306 | H5: {=_xll.EQNXTDZ($A$1,$B5,H$1)} -> 201309 | I5: {=_xll.EQNXTDZ($A$1,$B5,I$1)} -> 201312 | J5: {=_xll.EQNXTDZ($A$1,$B5,J$1)} -> 201403 | ... AY5: {=_xll.EQNXTDZ($A$1,$B5,AY$1)} -> 202406
A6: Grand Total | B6: SHP_NSGRANDTOTAL | C6: {=_xll.EQNXTDZ($A$1,$B6,C$1)} -> 612779461 | D6: {=_xll.EQNXTDZ($A$1,$B6,D$1)} -> 613810633 | E6: {=_xll.EQNXTDZ($A$1,$B6,E$1)} -> 614923903 | F6: {=_xll.EQNXTDZ($A$1,$B6,F$1)} -> 615385981 | G6: {=_xll.EQNXTDZ($A$1,$B6,G$1)} -> 616227540 | H6: {=_xll.EQNXTDZ($A$1,$B6,H$1)} -> 925256379 | I6: {=_xll.EQNXTDZ($A$1,$B6,I$1)} -> 926068994 | J6: {=_xll.EQNXTDZ($A$1,$B6,J$1)} -> 926912658 | ... AY6: {=_xll.EQNXTDZ($A$1,$B6,AY$1)} -> 1374848104
B7: In Crs. | C7: =+C6/10^7 -> 61.277946 | D7: =+D6/10^7 -> 61.381063 | E7: =+E6/10^7 -> 61.49239 | F7: =+F6/10^7 -> 61.538598 | G7: =+G6/10^7 -> 61.622754 | H7: =+H6/10^7 -> 92.525638 | I7: =+I6/10^7 -> 92.606899 | J7: =+J6/10^7 -> 92.691266 | ... AY7: =+AY6/10^7 -> 137.48481

Sheet Share price Daily
A1: =_xll.EQNXTH(B1,"[ADJC];[ADJH];[ADJL];[ADJO];[UCLS];[VOLUME]","2015-Jan-01","Y","All traded days","Asc") -> EQNXTH | B1: =+'Annual Raw'!A1 -> 100510 | L1: =_xll.EQNXTH(B1,"[NADJC];[NADJH];[NADJLOW];[NADJOPEN];[NUCLOSE];[NVOLUME]","2015-Jan-01","Y","All traded days","Asc") -> EQNXTH
A2: Larsen & Toubro Ltd. | L2: Larsen & Toubro Ltd.
A3: DATE | B3: ADJHIGH | C3: ADJCLOSE | D3: ADJLOW | E3: ADJOPEN | F3: CLOSE | G3: VOLUME | L3: DATE | M3: ADJCLOSE | N3: ADJHIGH | O3: ADJLOW | P3: ADJOPEN | Q3: CLOSE | R3: VOLUME
A4: 42005 | B4: 1004.0667 | C4: 1001.5333 | D4: 994.8 | E4: 995.6 | F4: 1502.3 | G4: 69174 | L4: 42005 | M4: 1001.9667 | N4: 1004.6 | O4: 994.66667 | P4: 995.86667 | Q4: 1502.95 | R4: 449532
A5: 42006 | B5: 1026.3333 | C5: 1023.1333 | D5: 1001.3333 | E5: 1001.3333 | F5: 1534.7 | G5: 161638 | L5: 42006 | M5: 1023.1 | N5: 1026 | O5: 1001 | P5: 1001 | Q5: 1534.65 | R5: 1291056
A6: 42009 | B6: 1046.6667 | C6: 1037.6667 | D6: 1028.2 | E6: 1028.2 | F6: 1556.5 | G6: 219899 | L6: 42009 | M6: 1037.3333 | N6: 1047.3333 | O6: 1030.2333 | P6: 1030.2333 | Q6: 1556 | R6: 1451018
A7: 42010 | B7: 1027.3333 | C7: 1002.5667 | D7: 997.33333 | E7: 1027.2667 | F7: 1503.85 | G7: 298634 | L7: 42010 | M7: 1002.7333 | N7: 1029.8333 | O7: 997.36667 | P7: 1027.3333 | Q7: 1504.1 | R7: 2032017
A8: 42011 | B8: 1006.5 | C8: 1000.0333 | D8: 991.03333 | E8: 1000 | F8: 1500.05 | G8: 196238 | L8: 42011 | M8: 1000.3333 | N8: 1006.6667 | O8: 990.36667 | P8: 999.16667 | Q8: 1500.5 | R8: 1375757
A9: 42012 | B9: 1016.6 | C9: 1006.4 | D9: 1003.3667 | E9: 1009.3333 | F9: 1509.6 | G9: 113249 | L9: 42012 | M9: 1006.7 | N9: 1015.6667 | O9: 1002.7667 | P9: 1013 | Q9: 1510.05 | R9: 970636
A10: 42013 | B10: 1015.2333 | C10: 1000.2667 | D10: 992.23333 | E10: 1012.6667 | F10: 1500.4 | G10: 146275 | L10: 42013 | M10: 1000.1667 | N10: 1016 | O10: 992 | P10: 1014.6667 | Q10: 1500.25 | R10: 1157153
A11: 42016 | B11: 1026 | C11: 1023.1333 | D11: 996.66667 | E11: 1002.4667 | F11: 1534.7 | G11: 153180 | L11: 42016 | M11: 1022.8 | N11: 1024.6667 | O11: 996.73333 | P11: 1002.6 | Q11: 1534.2 | R11: 1023547
A12: 42017 | B12: 1031.4667 | C12: 1013.6 | D12: 1011.3333 | E12: 1026.9 | F12: 1520.4 | G12: 131435 | L12: 42017 | M12: 1013 | N12: 1031.4333 | O12: 1010.8 | P12: 1029.9667 | Q12: 1519.5 | R12: 878899
A13: 42018 | B13: 1022.5 | C13: 1011.7667 | D13: 1000 | E13: 1016.4667 | F13: 1517.65 | G13: 145908 | L13: 42018 | M13: 1012 | N13: 1022.7333 | O13: 1000 | P13: 1015 | Q13: 1518 | R13: 984594
A14: 42019 | B14: 1057.3333 | C14: 1048.2667 | D14: 1023.9 | E14: 1033.5 | F14: 1572.4 | G14: 301272 | L14: 42019 | M14: 1049.1333 | N14: 1057.4667 | O14: 1023.6667 | P14: 1030 | Q14: 1573.7 | R14: 2279394
A15: 42020 | B15: 1074 | C15: 1061.9333 | D15: 1043.3333 | E15: 1053.3333 | F15: 1592.9 | G15: 247695 | L15: 42020 | M15: 1061.1667 | N15: 1074.6667 | O15: 1040 | P15: 1055 | Q15: 1591.75 | R15: 2796685
... A2841: 46190 | B2841: 4214 | C2841: 4206.95 | D2841: 4171.55 | E2841: 4198 | F2841: 4206.95 | G2841: 51155 | L2841: 46190 | M2841: 4207.7 | N2841: 4214.7 | O2841: 4172 | P2841: 4200.1 | Q2841: 4207.7 | R2841: 1312925

Sheet Sheet2
J19: 219.3 | K19: 186.25 | L19: 186.75
J20: 192.9 | K20: 135.5 | L20: 146.9 | N20: 219.3 | O20: 192.9 | P20: 186 | Q20: 178.7 | R20: 207 | S20: 255.15 | T20: 348.25 | U20: 374 | V20: 495.9 | W20: 659.9 | X20: 613.4 | Y20: 607.9 | Z20: 555.95 | AA20: 497.8 | AB20: 459.9 | AC20: 374 | AD20: 362 | AE20: 341.5 | AF20: 384.2 | AG20: 433.8 | AH20: 460 | AI20: 474.4 | AJ20: 414.4 | AK20: 318.7 | AL20: 303.25 | AM20: 332.7 | AN20: 295 | AO20: 247 | AP20: 214.4 | AQ20: 179.5 | AR20: 97.9 | AS20: 119.1 | AT20: 130.65 | AU20: 148.55 | AV20: 153.8 | AW20: 152.9 | AX20: 136 | AY20: 141.15 | AZ20: 128.1 | BA20: 142.5 | BB20: 143.55 | BC20: 124.5 | BD20: 241 | BE20: 450 | BF20: 503.35
J21: 186 | K21: 145.4 | L21: 169.1 | N21: 186.25 | O21: 135.5 | P21: 145.4 | Q21: 108.95 | R21: 137 | S21: 170 | T21: 243.15 | U21: 307.5 | V21: 325.1 | W21: 463 | X21: 467.05 | Y21: 436.5 | Z21: 467 | AA21: 348.2 | AB21: 325 | AC21: 313.1 | AD21: 285 | AE21: 277.85 | AF21: 327 | AG21: 317 | AH21: 370.7 | AI21: 360 | AJ21: 271.15 | AK21: 233.15 | AL21: 218.8 | AM21: 262 | AN21: 223.6 | AO21: 137.6 | AP21: 142 | AQ21: 59.3 | AR21: 58 | AS21: 72.8 | AT21: 80 | AU21: 107.25 | AV21: 106 | AW21: 125.1 | AX21: 112.25 | AY21: 81.45 | AZ21: 88 | BA21: 90.35 | BB21: 106.05 | BC21: 98.55 | BD21: 119.25 | BE21: 210 | BF21: 349
J22: 178.7 | K22: 108.95 | L22: 139.75 | N22: 186.75 | O22: 146.9 | P22: 169.1 | Q22: 139.75 | R22: 202.15 | S22: 249.05 | T22: 346.4 | U22: 349.2 | V22: 469.9 | W22: 584.8 | X22: 536.15 | Y22: 513.35 | Z22: 474 | AA22: 438.55 | AB22: 355.4 | AC22: 334.95 | AD22: 298.8 | AE22: 328.35 | AF22: 343 | AG22: 389.9 | AH22: 443.05 | AI22: 407.5 | AJ22: 290.1 | AK22: 235.75 | AL22: 292.65 | AM22: 276.1 | AN22: 237.05 | AO22: 190.1 | AP22: 147.2 | AQ22: 71.9 | AR22: 75.2 | AS22: 90.1 | AT22: 117.2 | AU22: 116.3 | AV22: 140.5 | AW22: 128.6 | AX22: 133.65 | AY22: 91.65 | AZ22: 97.65 | BA22: 125 | BB22: 115.35 | BC22: 119.25 | BD22: 219.3 | BE22: 442.65 | BF22: 503.35
J23: 207 | K23: 137 | L23: 202.15
J24: 255.15 | K24: 170 | L24: 249.05
J25: 348.25 | K25: 243.15 | L25: 346.4
J26: 374 | K26: 307.5 | L26: 349.2
J27: 495.9 | K27: 325.1 | L27: 469.9
J28: 659.9 | K28: 463 | L28: 584.8
J29: 613.4 | K29: 467.05 | L29: 536.15
J30: 607.9 | K30: 436.5 | L30: 513.35
J31: 555.95 | K31: 467 | L31: 474
J32: 497.8 | K32: 348.2 | L32: 438.55
J33: 459.9 | K33: 325 | L33: 355.4
J34: 374 | K34: 313.1 | L34: 334.95
... J63: 503.35 | K63: 349 | L63: 503.35
