Workbook

Sheet Template
A1: =+'Annual Raw'!C4 -> Lloyds Metals & Energy Ltd. | B1: 36951 | C1: =EOMONTH(B1,12) -> 37346 | D1: =EOMONTH(C1,12) -> 37711 | E1: =EOMONTH(D1,12) -> 38077 | F1: =EOMONTH(E1,12) -> 38442 | G1: =EOMONTH(F1,12) -> 38807 | H1: =EOMONTH(G1,12) -> 39172 | I1: =EOMONTH(H1,12) -> 39538 | J1: =EOMONTH(I1,12) -> 39903 | ... AE1: =EOMONTH(AD1,12) -> 47573 | AH1: QTR | AI1: 41061 | AJ1: 41153 | AK1: 41244 | AL1: 41334 | AM1: 41426 | AN1: 41518 | AO1: 41609 | AP1: 41699 | AQ1: 41791 | AR1: 41883 | AS1: 41974 | AT1: 42064 | AU1: 42156 | AV1: 42248 | AW1: 42339 | AX1: 42430 | AY1: 42522 | AZ1: 42614 | BA1: 42705 | BB1: 42795 | BC1: 42887 | BD1: 42979 | BE1: 43070 | BF1: 43160 | BG1: 43252 | BH1: 43344 | BI1: 43435 | BJ1: 43525 | BK1: 43617 | BL1: 43709 | BM1: 43800 | BN1: 43891 | BO1: 43983 | BP1: 44075 | BQ1: =EOMONTH(BP1,3) -> 44196 | BR1: =EOMONTH(BQ1,3) -> 44286 | BS1: =EOMONTH(BR1,3) -> 44377 | BT1: =EOMONTH(BS1,3) -> 44469 | BU1: =EOMONTH(BT1,3) -> 44561 | BV1: =EOMONTH(BU1,3) -> 44651 | BW1: =EOMONTH(BV1,3) -> 44742 | BX1: =EOMONTH(BW1,3) -> 44834 | ... DB1: =EOMONTH(DA1,3) -> 47573 | DE1: HISTORICAL ESTIMATES | DF1: 46112
A2: Presentation Data (Start)
A4: Capacity
A5: Iron Ore Mining (mntpa) | Y5: 10 | Z5: 10 | AA5: 26 | AB5: 26 | AC5: 26 | AD5: 26 | AE5: 26 | CA5: =+Y5/4 -> 2.5 | CB5: =+CA5 -> 2.5 | CC5: =+CB5 -> 2.5 | CD5: =+CC5 -> 2.5 | CE5: =+Z5/4 -> 2.5 | CF5: =+CE5 -> 2.5 | CG5: =+CF5 -> 2.5 | CH5: =+CG5 -> 2.5 | CI5: =+AA5/4 -> 6.5 | CJ5: =+CI5 -> 6.5 | CK5: =+CJ5 -> 6.5 | CL5: =+CK5 -> 6.5 | CM5: =+AB5/4 -> 6.5 | CN5: =+CM5 -> 6.5 | CO5: =+CN5 -> 6.5 | CP5: =+CO5 -> 6.5 | CQ5: =+AC5/4 -> 6.5 | CR5: =+CQ5 -> 6.5 | CS5: =+CR5 -> 6.5 | CT5: =+CS5 -> 6.5 | CU5: =+AD5/4 -> 6.5 | CV5: =+CU5 -> 6.5 | CW5: =+CV5 -> 6.5 | CX5: =+CW5 -> 6.5 | CY5: =+AE5/4 -> 6.5 | CZ5: =+CY5 -> 6.5 | DA5: =+CZ5 -> 6.5 | DB5: =+DA5 -> 6.5 | DF5: 26
A6: Pellet(mntpa) Gadchiroli+Ghusghus | AA6: 4 | AB6: =4+4 -> 8 | AC6: =8+4 -> 12 | AD6: =8+4 -> 12 | AE6: =8+4 -> 12 | CI6: =+AA6/4 -> 1 | CJ6: =+CI6 -> 1 | CK6: =+CJ6 -> 1 | CL6: =+CK6 -> 1 | CM6: =+AB6/4 -> 2 | CN6: =+CM6 -> 2 | CO6: =+CN6 -> 2 | CP6: =+CO6 -> 2 | CQ6: =+CP6 -> 2 | CR6: =+CS6 -> 3 | CS6: =+CT6 -> 3 | CT6: =+AC6/4 -> 3 | CU6: =+AD6/4 -> 3 | CV6: =+CU6 -> 3 | CW6: =+CV6 -> 3 | CX6: =+CW6 -> 3 | CY6: =+AE6/4 -> 3 | CZ6: =+CY6 -> 3 | DA6: =+CZ6 -> 3 | DB6: =+DA6 -> 3 | DF6: 4
A7: DRI(Gadchiroli+Ghusghus) | Y7: 0.344 | Z7: 0.344 | AA7: 0.704 | AB7: 0.704 | AC7: 0.704 | AD7: 0.704 | AE7: 0.704 | CA7: =+Y7/4 -> 0.086 | CB7: =+CA7 -> 0.086 | CC7: =+CB7 -> 0.086 | CD7: =+CC7 -> 0.086 | CE7: =+Z7/4 -> 0.086 | CF7: =+CE7 -> 0.086 | CG7: =+CF7 -> 0.086 | CH7: =+CG7 -> 0.086 | CI7: =+AA7/4 -> 0.176 | CJ7: =+CI7 -> 0.176 | CK7: =+CJ7 -> 0.176 | CL7: =+CK7 -> 0.176 | CM7: =+AB7/4 -> 0.176 | CN7: =+CM7 -> 0.176 | CO7: =+CN7 -> 0.176 | CP7: =+CO7 -> 0.176 | CQ7: =+AC7/4 -> 0.176 | CR7: =+CQ7 -> 0.176 | CS7: =+CR7 -> 0.176 | CT7: =+CS7 -> 0.176 | CU7: =+AD7/4 -> 0.176 | CV7: =+CU7 -> 0.176 | CW7: =+CV7 -> 0.176 | CX7: =+CW7 -> 0.176 | CY7: =+AE7/4 -> 0.176 | CZ7: =+CY7 -> 0.176 | DA7: =+CZ7 -> 0.176 | DB7: =+DA7 -> 0.176
A8: Wire Rod in Ghusghus-Steel | AB8: 1.2 | AC8: =+AB8 -> 1.2 | AD8: =+AC8 -> 1.2 | AE8: =+AD8 -> 1.2 | CP8: =+AB8/4 -> 0.3 | CQ8: =+AC8/4 -> 0.3 | CR8: =+CQ8 -> 0.3 | CS8: =+CR8 -> 0.3 | CT8: =+CS8 -> 0.3 | CU8: =+AD8/4 -> 0.3 | CV8: =+CU8 -> 0.3 | CW8: =+CV8 -> 0.3 | CX8: =+CW8 -> 0.3 | CY8: =+AE8/4 -> 0.3 | CZ8: =+CY8 -> 0.3 | DA8: =+CZ8 -> 0.3 | DB8: =+DA8 -> 0.3
A9: HRC in Gadchiroli-Steel | AE9: 3 | CY9: =+AE9/4 -> 0.75 | CZ9: =+CY9 -> 0.75 | DA9: =+CZ9 -> 0.75 | DB9: =+DA9 -> 0.75
A10: Production
A11: Iron Ore Production | W11: =SUM(BS11:BV11) -> 0 | X11: =SUM(BW11:BZ11) -> 3.59 | Y11: =SUM(CA11:CD11) -> 10 | Z11: =SUM(CE11:CH11) -> 10 | AA11: =SUM(CI11:CL11) -> 22 | AB11: =+SUM(CM11:CP11) -> 24 | AC11: =+SUM(CQ11:CT11) -> 16 | AD11: =+SUM(CU11:CX11) -> 11 | AE11: =+SUM(CY11:DB11) -> 11 | BW11: 0.76 | BX11: 0.73 | BY11: 1.52 | BZ11: 0.58 | CA11: 3.8 | CB11: 1.9 | CC11: 2.42 | CD11: 1.88 | CE11: 4 | CF11: 1.9 | CG11: 2.7 | CH11: 1.4 | CI11: 4 | CJ11: 3.4 | CK11: 5.5 | CL11: 9.1 | CM11: 7 | CN11: =+CM11 -> 7 | CO11: 5 | CP11: =+CO11 -> 5 | CQ11: 4 | CR11: =+CQ11 -> 4 | CS11: =+CR11 -> 4 | CT11: =+CS11 -> 4 | CU11: 2.75 | CV11: =+CU11 -> 2.75 | CW11: =+CV11 -> 2.75 | CX11: =+CW11 -> 2.75 | CY11: 2.75 | CZ11: =+CY11 -> 2.75 | DA11: =+CZ11 -> 2.75 | DB11: =+DA11 -> 2.75
A12: BHQ Production | W12: =SUM(BS12:BV12) -> 0 | X12: =SUM(BW12:BZ12) -> 0 | Y12: =SUM(CA12:CD12) -> 0 | Z12: =SUM(CE12:CH12) -> 0 | AA12: =SUM(CI12:CL12) -> 0 | AB12: =+SUM(CM12:CP12) -> 2 | AC12: =+SUM(CQ12:CT12) -> 9 | AD12: =+SUM(CU12:CX12) -> 15 | AE12: =+SUM(CY12:DB12) -> 15 | CO12: 1 | CP12: =+CO12 -> 1 | CQ12: 2.25 | CR12: =+CQ12 -> 2.25 | CS12: =+CR12 -> 2.25 | CT12: =+CS12 -> 2.25 | CU12: 3.75 | CV12: =+CU12 -> 3.75 | CW12: =+CV12 -> 3.75 | CX12: =+CW12 -> 3.75 | CY12: =+CX12 -> 3.75 | CZ12: =+CY12 -> 3.75 | DA12: =+CZ12 -> 3.75 | DB12: =+DA12 -> 3.75
A13: Total Iron Ore Production | W13: =+W11+W12 -> 0 | X13: =+X11+X12 -> 3.59 | Y13: =+Y11+Y12 -> 10 | Z13: =+Z11+Z12 -> 10 | AA13: =+AA11+AA12 -> 22 | AB13: =+AB11+AB12 -> 26 | AC13: =+AC11+AC12 -> 25 | AD13: =+AD11+AD12 -> 26 | AE13: =+AE11+AE12 -> 26 | CE13: =+CE11+CE12 -> 4 | CF13: =+CF11+CF12 -> 1.9 | CG13: =+CG11+CG12 -> 2.7 | CH13: =+CH11+CH12 -> 1.4 | CI13: =+CI11+CI12 -> 4 | CJ13: =+CJ11+CJ12 -> 3.4 | CK13: =+CK11+CK12 -> 5.5 | CL13: =+CL11+CL12 -> 9.1 | ... DB13: =+DB11+DB12 -> 6.5
A14: Pellet Production | W14: =SUM(BS14:BV14) -> 0 | X14: =SUM(BW14:BZ14) -> 0 | Y14: =SUM(CA14:CD14) -> 0 | Z14: =SUM(CE14:CH14) -> 0 | AA14: =SUM(CI14:CL14) -> 3.03 | AB14: =+SUM(CM14:CP14) -> 7.2 | AC14: =+SUM(CQ14:CT14) -> 9.9 | AD14: =+SUM(CU14:CX14) -> 10.92 | AE14: =+SUM(CY14:DB14) -> 10.92 | CI14: 0.02 | CJ14: 0.69 | CK14: =1.95-CJ14-CI14 -> 1.24 | CL14: =3.03-CK14-CJ14-CI14 -> 1.08 | CM14: =+CM6*90% -> 1.8 | CN14: =+CN6*90% -> 1.8 | CO14: =+CO6*90% -> 1.8 | CP14: =+CP6*90% -> 1.8 | CQ14: =+CQ6*90% -> 1.8 | CR14: =+CR6*90% -> 2.7 | CS14: =+CS6*90% -> 2.7 | CT14: =+CT6*90% -> 2.7 | CU14: =+CU6*91% -> 2.73 | CV14: =+CV6*91% -> 2.73 | CW14: =+CW6*91% -> 2.73 | CX14: =+CX6*91% -> 2.73 | CY14: =+CY6*91% -> 2.73 | CZ14: =+CZ6*91% -> 2.73 | DA14: =+DA6*91% -> 2.73 | DB14: =+DB6*91% -> 2.73
A15: DRI production | W15: =SUM(BS15:BV15) -> 0 | X15: =SUM(BW15:BZ15) -> 0.20423 | Y15: =SUM(CA15:CD15) -> 0.261836 | Z15: =SUM(CE15:CH15) -> 0.308243 | AA15: =SUM(CI15:CL15) -> 0.484 | AB15: =+SUM(CM15:CP15) -> 0.704 | AC15: =+SUM(CQ15:CT15) -> 0.704 | AD15: =+SUM(CU15:CX15) -> 0.704 | AE15: =+SUM(CY15:DB15) -> 0.704 | BW15: 0.046 | BX15: 0.04728 | BY15: 0.06048 | BZ15: 0.05047 | CA15: 0.0663 | CB15: 0.04815 | CC15: 0.081581 | CD15: 0.065805 | CE15: 0.076704 | CF15: 0.084968 | CG15: 0.076761 | CH15: 0.06981 | CI15: 0.079033 | CJ15: 0.088767 | CK15: =0.291-CJ15-CI15 -> 0.1232 | CL15: =0.484-CK15-CJ15-CI15 -> 0.193 | CM15: =+CM7 -> 0.176 | CN15: =+CN7 -> 0.176 | CO15: =+CO7 -> 0.176 | CP15: =+CP7 -> 0.176 | CQ15: =+CQ7 -> 0.176 | CR15: =+CR7 -> 0.176 | CS15: =+CS7 -> 0.176 | CT15: =+CT7 -> 0.176 | ... DB15: =+DB7 -> 0.176
A16: Wire Rod Production | W16: =SUM(BS16:BV16) -> 0 | X16: =SUM(BW16:BZ16) -> 0 | Y16: =SUM(CA16:CD16) -> 0 | Z16: =SUM(CE16:CH16) -> 0 | AA16: =SUM(CI16:CL16) -> 0 | AB16: =+SUM(CM16:CP16) -> 0.21 | AC16: =+SUM(CQ16:CT16) -> 0.96 | AD16: =+SUM(CU16:CX16) -> 1.02 | AE16: =+SUM(CY16:DB16) -> 1.08 | CP16: =+CP8*70% -> 0.21 | CQ16: =+CQ8*80% -> 0.24 | CR16: =+CR8*80% -> 0.24 | CS16: =+CS8*80% -> 0.24 | CT16: =+CT8*80% -> 0.24 | CU16: =+CU8*85% -> 0.255 | CV16: =+CV8*85% -> 0.255 | CW16: =+CW8*85% -> 0.255 | CX16: =+CX8*85% -> 0.255 | CY16: =+CY8*90% -> 0.27 | CZ16: =+CZ8*90% -> 0.27 | DA16: =+DA8*90% -> 0.27 | DB16: =+DB8*90% -> 0.27
A17: HRC Steel Production | W17: =SUM(BS17:BV17) -> 0 | X17: =SUM(BW17:BZ17) -> 0 | Y17: =SUM(CA17:CD17) -> 0 | Z17: =SUM(CE17:CH17) -> 0 | AA17: =SUM(CI17:CL17) -> 0 | AB17: =+SUM(CM17:CP17) -> 0 | AC17: =+SUM(CQ17:CT17) -> 0 | AD17: =+SUM(CU17:CX17) -> 0 | AE17: =+SUM(CY17:DB17) -> 2.4 | CY17: =+CY9*80% -> 0.6 | CZ17: =+CZ9*80% -> 0.6 | DA17: =+DA9*80% -> 0.6 | DB17: =+DB9*80% -> 0.6
A19: Intersegmental Usage
A20: Material Used for Pellet Production
A21: Iron Ore Used For Pellet production (1.2 tonnes of raw Iron Ore (IO) to produce 1 tonne of finished iron ore pellets) | W21: =SUM(BS21:BV21) -> 0 | X21: =SUM(BW21:BZ21) -> 0 | Y21: =SUM(CA21:CD21) -> 0 | Z21: =SUM(CE21:CH21) -> 0 | AA21: =SUM(CI21:CL21) -> 3.636 | AB21: =+SUM(CM21:CP21) -> 8.64 | AC21: =+SUM(CQ21:CT21) -> 11.88 | AD21: =+SUM(CU21:CX21) -> 13.104 | AE21: =+SUM(CY21:DB21) -> 13.104 | CI21: =+CI14*1.2 -> 0.024 | CJ21: =+CJ14*1.2 -> 0.828 | CK21: =+CK14*1.2 -> 1.488 | CL21: =+CL14*1.2 -> 1.296 | CM21: =+CM14*1.2 -> 2.16 | CN21: =+CN14*1.2 -> 2.16 | CO21: =+CO14*1.2 -> 2.16 | CP21: =+CP14*1.2 -> 2.16 | ... DB21: =+DB14*1.2 -> 3.276
A22: Materials used for DRI production
A23: Iron Ore used for making DRI(1.62 tonnes of raw ore = 1 tonne of DRI) | W23: =SUM(BS23:BV23) -> 0 | X23: =SUM(BW23:BZ23) -> 0.3308526 | Y23: =SUM(CA23:CD23) -> 0.42417432 | Z23: =SUM(CE23:CH23) -> 0.49935366 | AA23: =SUM(CI23:CL23) -> 0.10803346 | AB23: =+SUM(CM23:CP23) -> 0 | AC23: =+SUM(CQ23:CT23) -> 0 | AD23: =+SUM(CU23:CX23) -> 0 | AE23: =+SUM(CY23:DB23) -> 0 | BW23: =+BW15*1.62 -> 0.07452 | BX23: =+BX15*1.62 -> 0.0765936 | BY23: =+BY15*1.62 -> 0.0979776 | BZ23: =+BZ15*1.62 -> 0.0817614 | CA23: =+CA15*1.62 -> 0.107406 | CB23: =+CB15*1.62 -> 0.078003 | CC23: =+CC15*1.62 -> 0.13216122 | CD23: =+CD15*1.62 -> 0.1066041 | ... CH23: =+CH15*1.62 -> 0.1130922 | CI23: =+(CI15*1.62)-CI24 -> 0.10803346 | CJ23: 0 | CK23: 0
A24: Pellet Used for making DRI((1.35 tonnes of pellets = 1 tonne of DRI) | W24: =SUM(BS24:BV24) -> 0 | X24: =SUM(BW24:BZ24) -> 0 | Y24: =SUM(CA24:CD24) -> 0 | Z24: =SUM(CE24:CH24) -> 0 | AA24: =SUM(CI24:CL24) -> 0.56670545 | AB24: =+SUM(CM24:CP24) -> 0.9504 | AC24: =+SUM(CQ24:CT24) -> 0.9504 | AD24: =+SUM(CU24:CX24) -> 0.9504 | AE24: =+SUM(CY24:DB24) -> 0.9504 | CI24: =+CI14 -> 0.02 | CJ24: =+CJ15*1.35 -> 0.11983545 | CK24: =+CK15*1.35 -> 0.16632 | CL24: =+CL15*1.35 -> 0.26055 | CM24: =+CM15*1.35 -> 0.2376 | CN24: =+CN15*1.35 -> 0.2376 | CO24: =+CO15*1.35 -> 0.2376 | CP24: =+CP15*1.35 -> 0.2376 | CQ24: =+CQ15*1.35 -> 0.2376 | ... DB24: =+DB15*1.35 -> 0.2376
A25: Materials used for Wire Rod plant
A26: Total RM used to make Wire Rod | W26: =SUM(BS26:BV26) -> 0 | X26: =SUM(BW26:BZ26) -> 0 | Y26: =SUM(CA26:CD26) -> 0 | Z26: =SUM(CE26:CH26) -> 0 | AA26: =SUM(CI26:CL26) -> 0 | AB26: =+SUM(CM26:CP26) -> 0.231 | AC26: =+SUM(CQ26:CT26) -> 1.056 | AD26: =+SUM(CU26:CX26) -> 1.122 | AE26: =+SUM(CY26:DB26) -> 1.188 | CP26: =+CP16*1.1 -> 0.231 | CQ26: =+CQ16*1.1 -> 0.264 | CR26: =+CR16*1.1 -> 0.264 | CS26: =+CS16*1.1 -> 0.264 | CT26: =+CT16*1.1 -> 0.264 | CU26: =+CU16*1.1 -> 0.2805 | CV26: =+CV16*1.1 -> 0.2805 | CW26: =+CW16*1.1 -> 0.2805 | ... DB26: =+DB16*1.1 -> 0.297
A27: DRI Used to make Wire Rod | W27: =SUM(BS27:BV27) -> 0 | X27: =SUM(BW27:BZ27) -> 0 | Y27: =SUM(CA27:CD27) -> 0 | Z27: =SUM(CE27:CH27) -> 0 | AA27: =SUM(CI27:CL27) -> 0 | AB27: =+SUM(CM27:CP27) -> 0.176 | AC27: =+SUM(CQ27:CT27) -> 0.704 | AD27: =+SUM(CU27:CX27) -> 0.704 | AE27: =+SUM(CY27:DB27) -> 0.704 | CP27: =+CP15 -> 0.176 | CQ27: =+CQ15 -> 0.176 | CR27: =+CR15 -> 0.176 | CS27: =+CS15 -> 0.176 | CT27: =+CT15 -> 0.176 | CU27: =+CU15 -> 0.176 | CV27: =+CV15 -> 0.176 | CW27: =+CW15 -> 0.176 | ... DB27: =+DB15 -> 0.176
A28: Pellet Used to make Wire Rod(b/f) | W28: =SUM(BS28:BV28) -> 0 | X28: =SUM(BW28:BZ28) -> 0 | Y28: =SUM(CA28:CD28) -> 0 | Z28: =SUM(CE28:CH28) -> 0 | AA28: =SUM(CI28:CL28) -> 0 | AB28: =+SUM(CM28:CP28) -> 0.055 | AC28: =+SUM(CQ28:CT28) -> 0.352 | AD28: =+SUM(CU28:CX28) -> 0.418 | AE28: =+SUM(CY28:DB28) -> 0.484 | CP28: =+CP26-CP27 -> 0.055 | CQ28: =+CQ26-CQ27 -> 0.088 | CR28: =+CR26-CR27 -> 0.088 | CS28: =+CS26-CS27 -> 0.088 | CT28: =+CT26-CT27 -> 0.088 | CU28: =+CU26-CU27 -> 0.1045 | CV28: =+CV26-CV27 -> 0.1045 | CW28: =+CW26-CW27 -> 0.1045 | ... DB28: =+DB26-DB27 -> 0.121
A29: Material Used For HRC
A30: Pellet used for making HRC(1.1 tonne of pellet to make 1 tonne of HRC) | AA30: =SUM(CI30:CL30) -> 0 | AB30: =+SUM(CM30:CP30) -> 0 | AC30: =+SUM(CQ30:CT30) -> 0 | AD30: =+SUM(CU30:CX30) -> 0 | AE30: =+SUM(CY30:DB30) -> 2.64 | CY30: =+CY17*1.1 -> 0.66 | CZ30: =+CZ17*1.1 -> 0.66 | DA30: =+DA17*1.1 -> 0.66 | DB30: =+DB17*1.1 -> 0.66
CJ31: =CJ50/(CJ21+CJ23+CJ24+CJ26+CJ30) -> 501.77486 | CK31: =CK50/(CK21+CK23+CK24+CK26+CK30) -> 554.16123 | CL31: =CL50/(CL21+CL23+CL24+CL26+CL30) -> 938.91619 | CM31: =+CL31 -> 938.91619 | CN31: =+CM31 -> 938.91619 | CO31: =+CN31 -> 938.91619 | CP31: =+CO31 -> 938.91619 | CQ31: 250 | CR31: =+CQ31 -> 250 | CS31: =+CR31 -> 250 | CT31: =+CS31 -> 250 | CU31: =+CT31 -> 250 | CV31: =+CU31 -> 250 | CW31: =+CV31 -> 250 | CX31: =+CW31 -> 250 | CY31: 230 | CZ31: =+CY31 -> 230 | DA31: =+CZ31 -> 230 | DB31: =+DA31 -> 230
A32: Sales (Mn T)
A33: Iron Ore Mining-Sales | W33: =+W13-W21-W23 -> 0 | X33: =+X13-X21-X23 -> 3.2591474 | Y33: =+Y13-Y21-Y23 -> 9.5758257 | Z33: =+Z13-Z21-Z23 -> 9.5006463 | AA33: =+AA13-AA21-AA23 -> 18.255967 | AB33: =+AB13-AB21-AB23 -> 17.36 | AC33: =+AC13-AC21-AC23 -> 13.12 | AD33: =+AD13-AD21-AD23 -> 12.896 | AE33: =+AE13-AE21-AE23 -> 12.896 | BU33: 0.06 | BV33: 0.3 | BW33: 1.15 | BX33: 1.32 | BY33: 1.73 | BZ33: 1.1 | CA33: 3.2 | CB33: 1.98 | CC33: 2.49 | CD33: 1.98 | CE33: 3.6 | CF33: 1.98 | CG33: 2.48 | CH33: 1.66 | CI33: 3.45 | CJ33: 2.5 | CK33: 4.1 | CL33: 6.16 | CM33: =+CM13-CM21-CM23 -> 4.84 | CN33: =+CN13-CN21-CN23 -> 4.84 | CO33: =+CO13-CO21-CO23 -> 3.84 | CP33: =+CP13-CP21-CP23 -> 3.84 | CQ33: =+CQ13-CQ21-CQ23 -> 4.09 | CR33: =+CR13-CR21-CR23 -> 3.01 | CS33: =+CS13-CS21-CS23 -> 3.01 | CT33: =+CT13-CT21-CT23 -> 3.01 | ... DB33: =+DB13-DB21-DB23 -> 3.224 | DF33: 4.92
A34: Pellet-Sales | W34: =+W14-W24-W28-W30 -> 0 | X34: =+X14-X24-X28-X30 -> 0 | Y34: =+Y14-Y24-Y28-Y30 -> 0 | Z34: =+Z14-Z24-Z28-Z30 -> 0 | AA34: =+AA14-AA24-AA28-AA30 -> 2.4632945 | AB34: =+AB14-AB24-AB28-AB30 -> 6.1946 | AC34: =+AC14-AC24-AC28-AC30 -> 8.5976 | AD34: =+AD14-AD24-AD28-AD30 -> 9.5516 | AE34: =+AE14-AE24-AE28-AE30 -> 6.8456 | CJ34: 0.69 | CK34: 1 | CL34: 0.89 | CM34: =+CM14-CM24-CM28-CM30 -> 1.5624 | CN34: =+CN14-CN24-CN28-CN30 -> 1.5624 | CO34: =+CO14-CO24-CO28-CO30 -> 1.5624 | CP34: =+CP14-CP24-CP28-CP30 -> 1.5074 | CQ34: =+CQ14-CQ24-CQ28-CQ30 -> 1.4744 | CR34: =+CR14-CR24-CR28-CR30 -> 2.3744 | CS34: =+CS14-CS24-CS28-CS30 -> 2.3744 | CT34: =+CT14-CT24-CT28-CT30 -> 2.3744 | ... DB34: =+DB14-DB24-DB28-DB30 -> 1.7114 | DF34: 0.684
A35: DRI-Sales | W35: =+W15-W27 -> 0 | X35: =+X15-X27 -> 0.20423 | Y35: =+Y15-Y27 -> 0.261836 | Z35: =+Z15-Z27 -> 0.308243 | AA35: =+AA15-AA27 -> 0.484 | AB35: =+AB15-AB27 -> 0.528 | AC35: =+AC15-AC27 -> 0 | AD35: =+AD15-AD27 -> 0 | AE35: =+AE15-AE27 -> 0 | BU35: 0.03405 | BV35: 0.03484 | BW35: 0.04475 | BX35: 0.04685 | BY35: 0.06089 | BZ35: 0.05167 | CA35: 0.06701 | CB35: 0.04815 | CC35: 0.08096 | CD35: 0.06724 | CE35: =+CE15 -> 0.076704 | CF35: =+CF15 -> 0.084968 | CG35: =+CG15 -> 0.076761 | CH35: =+CH15 -> 0.06981 | CI35: =+CI15 -> 0.079033 | CJ35: =+CJ15 -> 0.088767 | CK35: =+CK15 -> 0.1232 | CL35: 0.188 | CM35: =+CM15-CM27 -> 0.176 | CN35: =+CN15-CN27 -> 0.176 | CO35: =+CO15-CO27 -> 0.176 | CP35: =+CP15-CP27 -> 0 | CQ35: =+CQ15-CQ27 -> 0 | CR35: =+CR15-CR27 -> 0 | CS35: =+CS15-CS27 -> 0 | CT35: =+CT15-CT27 -> 0 | ... DB35: =+DB15-DB27 -> 0 | DF35: 0.12
A36: Wire Rod-Steel Sales | W36: =+W16 -> 0 | X36: =+X16 -> 0 | Y36: =+Y16 -> 0 | Z36: =+Z16 -> 0 | AA36: =+AA16 -> 0 | AB36: =+AB16 -> 0.21 | AC36: =+AC16 -> 0.96 | AD36: =+AD16 -> 1.02 | AE36: =+AE16 -> 1.08 | CP36: =+CP16*50% -> 0.105 | CQ36: =+CQ16*70% -> 0.168 | CR36: =+CR16*70% -> 0.168 | CS36: =+CS16*70% -> 0.168 | CT36: =+CT16*70% -> 0.168 | CU36: =+CU16*80% -> 0.204 | CV36: =+CV16*80% -> 0.204 | CW36: =+CW16*80% -> 0.204 | CX36: =+CX16*80% -> 0.204 | CY36: =+CY16*90% -> 0.243 | CZ36: =+CZ16*90% -> 0.243 | DA36: =+DA16*90% -> 0.243 | DB36: =+DB16*90% -> 0.243
A37: HRC-Steel Sales | W37: =+W17 -> 0 | X37: =+X17 -> 0 | Y37: =+Y17 -> 0 | Z37: =+Z17 -> 0 | AA37: =+AA17 -> 0 | AB37: =+AB17 -> 0 | AC37: =+AC17 -> 0 | AD37: =+AD17 -> 0 | AE37: =+AE17 -> 2.4 | CY37: =+CY17*70% -> 0.42 | CZ37: =+CZ17*70% -> 0.42 | DA37: =+DA17*70% -> 0.42 | DB37: =+DB17*70% -> 0.42
A38: Power(MW) Sales | W38: =SUM(BS38:BV38) -> 66.19 | X38: =SUM(BW38:BZ38) -> 109.42 | Y38: =SUM(CA38:CD38) -> 187.72 | Z38: =SUM(CE38:CH38) -> 200.64 | AA38: =SUM(CI38:CL38) -> 193.1 | AB38: =+SUM(CM38:CP38) -> 256 | AC38: =+SUM(CQ38:CT38) -> 256 | AD38: =+SUM(CU38:CX38) -> 256 | AE38: =+SUM(CY38:DB38) -> 256 | BU38: 30.32 | BV38: 35.87 | BX38: 16.99 | BY38: 46.67 | BZ38: 45.76 | CA38: 49.46 | CB38: 36.82 | CC38: 53.64 | CD38: 47.8 | CE38: 49.1 | CF38: 50.98 | CG38: 53.64 | CH38: 46.92 | CI38: 50.1 | CJ38: 43 | CK38: 36 | CL38: 64 | CM38: =+CL38 -> 64 | CN38: =+CM38 -> 64 | CO38: =+CN38 -> 64 | CP38: =+CO38 -> 64 | CQ38: =+CP38 -> 64 | CR38: =+CQ38 -> 64 | CS38: =+CR38 -> 64 | CT38: =+CS38 -> 64 | ... DB38: =+DA38 -> 64 | DF38: 43
A39: Realisation Per Tonne
A40: Mining (Iron Ore) | W40: =W44/W33*10 -> #DIV/0! | X40: =X44/X33*10 -> 8134.2746 | Y40: =Y44/Y33*10 -> 5558.5598 | Z40: =Z44/Z33*10 -> 5917.2606 | AA40: =AA44/AA33*10 -> 5184.8583 | AB40: =AB44/AB33*10 -> 5745.8986 | AC40: =AC44/AC33*10 -> 5350.5869 | AD40: =AD44/AD33*10 -> 5308.0081 | AE40: =AE44/AE33*10 -> 5300.746 | BU40: =(BU44-BU50)/BU33*10 -> -258.33333 | BV40: =(BV44-BV50)/BV33*10 -> 6187.6667 | BW40: =(BW44-BW50)/BW33*10 -> 5657.3043 | BX40: =(BX44-BX50)/BX33*10 -> 3798.5606 | BY40: =(BY44-BY50)/BY33*10 -> 4581.1561 | BZ40: =(BZ44-BZ50)/BZ33*10 -> 6347.3636 | CA40: =(CA44-CA50)/CA33*10 -> 5362.6562 | CB40: =(CB44-CB50)/CB33*10 -> 4742.5253 | ... CI40: =(CI44-CI50)/CI33*10 -> 6064.9855 | CJ40: =CJ44/CJ33*10 -> 5503.2 | CK40: =CK44/CK33*10 -> 5672.6829 | CL40: =CL44/CL33*10 -> 5849.8377 | CM40: =+AVERAGE(CI40:CL40) -> 5772.6765 | CN40: =+AVERAGE(CJ40:CM40) -> 5699.5993 | CO40: =+AVERAGE(CK40:CN40) -> 5748.6991 | CP40: =+AVERAGE(CL40:CO40) -> 5767.7031 | CQ40: =+AVERAGE(CM40:CP40)*0.95 -> 5459.811 | CR40: =+AVERAGE(CN40:CQ40)*0.95 -> 5385.5055 | CS40: =+AVERAGE(CO40:CR40)*0.95 -> 5310.9082 | CT40: =+AVERAGE(CP40:CS40)*0.95 -> 5206.9329 | CU40: =+AVERAGE(CQ40:CT40) -> 5340.7894 | CV40: =+AVERAGE(CR40:CU40) -> 5311.034 | CW40: =+AVERAGE(CS40:CV40) -> 5292.4161 | CX40: =+AVERAGE(CT40:CW40) -> 5287.7931 | CY40: =+AVERAGE(CU40:CX40) -> 5308.0081 | CZ40: =+AVERAGE(CV40:CY40) -> 5299.8128 | DA40: =+AVERAGE(CW40:CZ40) -> 5297.0075 | DB40: =+AVERAGE(CX40:DA40) -> 5298.1554 | DF40: 5500
A41: Pellet+ DRI | W41: =W45/SUM(W34:W35)*10 -> #DIV/0! | X41: =X45/SUM(X34:X35)*10 -> 36674.338 | Y41: =Y45/SUM(Y34:Y35)*10 -> 31602.988 | Z41: =Z45/SUM(Z34:Z35)*10 -> 32230.091 | AA41: =AA45/SUM(AA34:AA35)*10 -> 15071.381 | AB41: =AB45/SUM(AB34:AB35)*10 -> 13799.239 | AC41: =AC45/SUM(AC34:AC35)*10 -> 12722.276 | AD41: =AD45/SUM(AD34:AD35)*10 -> 12664.883 | AE41: =AE45/SUM(AE34:AE35)*10 -> 12644.587 | BV41: =BV45/SUM(BV34:BV35)*10 -> 42063.72 | BW41: =BW45/SUM(BW34:BW35)*10 -> 41483.799 | BX41: =BX45/SUM(BX34:BX35)*10 -> 37052.295 | BY41: =BY45/SUM(BY34:BY35)*10 -> 36055.181 | BZ41: =BZ45/SUM(BZ34:BZ35)*10 -> 32945.616 | CA41: =CA45/SUM(CA34:CA35)*10 -> 32739.89 | CB41: =CB45/SUM(CB34:CB35)*10 -> 31744.548 | CC41: =CC45/SUM(CC34:CC35)*10 -> 31500.741 | ... CL41: =CL45/SUM(CL34:CL35)*10 -> 12744.898 | CM41: =+AVERAGE(CJ41:CL41) -> 13980.487 | CN41: =+AVERAGE(CJ41:CM41) -> 13980.487 | CO41: =+AVERAGE(CK41:CN41) -> 13624.585 | CP41: =+AVERAGE(CL41:CO41) -> 13582.614 | CQ41: =+AVERAGE(CM41:CP41)*0.95 -> 13102.441 | CR41: =+AVERAGE(CN41:CQ41)*0.95 -> 12893.905 | CS41: =+AVERAGE(CO41:CR41)*0.95 -> 12635.842 | CT41: =+AVERAGE(CP41:CS41)*0.95 -> 12401.015 | CU41: =+AVERAGE(CQ41:CT41) -> 12758.301 | CV41: =+AVERAGE(CR41:CU41) -> 12672.266 | CW41: =+AVERAGE(CS41:CV41) -> 12616.856 | CX41: =+AVERAGE(CT41:CW41) -> 12612.109 | CY41: =+AVERAGE(CU41:CX41) -> 12664.883 | CZ41: =+AVERAGE(CV41:CY41) -> 12641.529 | DA41: =+AVERAGE(CW41:CZ41) -> 12633.844 | DB41: =+AVERAGE(CX41:DA41) -> 12638.091 | DF41: 15000
A42: Steel | AB42: =+AB47/(AB36+AB37)*10 -> 25500 | AC42: =+AC47/(AC36+AC37)*10 -> 36050 | AD42: =+AD47/(AD36+AD37)*10 -> 42400 | AE42: =+AE47/(AE36+AE37)*10 -> 41151.724 | CP42: 51000 | CQ42: 51500 | CR42: =+CQ42 -> 51500 | CS42: =+CR42 -> 51500 | CT42: =+CS42 -> 51500 | CU42: 53000 | CV42: =+CU42 -> 53000 | CW42: =+CV42 -> 53000 | CX42: =+CW42 -> 53000 | CY42: 54000 | CZ42: =+CY42 -> 54000 | DA42: =+CZ42 -> 54000 | DB42: =+DA42 -> 54000
A43: Revenue
A44: Iron Ore Mining Revenue -take from PPT | W44: =SUM(BS44:BV44) -> 187.14 | X44: =SUM(BW44:BZ44) -> 2651.08 | Y44: =SUM(CA44:CD44) -> 5322.78 | Z44: =SUM(CE44:CH44) -> 5621.78 | AA44: =SUM(CI44:CL44) -> 9465.46 | AB44: =+SUM(CM44:CP44) -> 9974.8799 | AC44: =+SUM(CQ44:CT44) -> 7019.97 | AD44: =+SUM(CU44:CX44) -> 6845.2073 | AE44: =+SUM(CY44:DB44) -> 6835.842 | BV44: 187.14 | BW44: 652.59 | BX44: 503.48 | BY44: 794.9 | BZ44: 700.11 | CA44: 1718.55 | CB44: 940.44 | CC44: 1365.79 | CD44: 1298 | CE44: 1985 | CF44: 1120.51 | CG44: 1474.61 | CH44: 1041.66 | CI44: 2160.36 | CJ44: 1375.8 | CK44: 2325.8 | CL44: 3603.5 | CM44: =+CM40*CM33/10 -> 2793.9754 | CN44: =+CN40*CN33/10 -> 2758.6061 | CO44: =+CO40*CO33/10 -> 2207.5005 | CP44: =+CP40*CP33/10 -> 2214.798 | CQ44: =+CQ40*CQ33/10 -> 2233.0627 | CR44: =+CR40*CR33/10 -> 1621.0371 | CS44: =+CS40*CS33/10 -> 1598.5834 | CT44: =+CT40*CT33/10 -> 1567.2868 | ... DB44: =+DB40*DB33/10 -> 1708.1253 | DF44: 2706
A45: Value Added Products(DRI+Pellet) Revenue PPT | W45: =SUM(BS45:BV45) -> 496.25 | X45: =SUM(BW45:BZ45) -> 749 | Y45: =SUM(CA45:CD45) -> 827.48 | Z45: =SUM(CE45:CH45) -> 993.47 | AA45: =SUM(CI45:CL45) -> 4441.98 | AB45: =+SUM(CM45:CP45) -> 9276.6766 | AC45: =+SUM(CQ45:CT45) -> 10938.104 | AD45: =+SUM(CU45:CX45) -> 12096.99 | AE45: =+SUM(CY45:DB45) -> 8655.9783 | AI45: 233.63 | AJ45: 123.08 | AK45: 124.24 | AL45: 221.94 | AM45: 131 | AN45: 106.09 | AO45: 126.22 | AP45: 182.24 | AQ45: 168.3 | AR45: 217.68 | AS45: 116.84 | AT45: 119.18 | AU45: 120.1 | AV45: 71.16 | AW45: 69.98 | AX45: 71.97 | AY45: 78.5 | AZ45: 75.71 | BA45: 105.61 | BB45: 120.34 | BC45: 85.09 | BD45: 68.54 | BE45: 106.93 | BF45: 102.1 | BG45: 125.97 | BH45: 93 | BI45: 97.14 | BJ45: 130.8 | BK45: 114.18 | BL45: 46.57 | BM45: 78.66 | BN45: 93.45 | BO45: 10.92 | BP45: 71 | BQ45: 69.27 | BR45: 90.68 | BS45: 88.04 | BT45: 97.07 | BU45: 164.59 | BV45: 146.55 | BW45: 185.64 | BX45: 173.59 | BY45: 219.54 | BZ45: 170.23 | CA45: 219.39 | CB45: 152.85 | CC45: 255.03 | CD45: 200.21 | CE45: 240.6 | CF45: 353.61 | CG45: 181.75 | CH45: 217.51 | CI45: 319.29 | CJ45: 1199.62 | CK45: 1549.17 | CL45: 1373.9 | CM45: =+CM41*SUM(CM34:CM35)/10 -> 2430.3678 | CN45: =+CN41*SUM(CN34:CN35)/10 -> 2430.3678 | CO45: =+CO41*SUM(CO34:CO35)/10 -> 2368.4978 | CP45: =+CP41*SUM(CP34:CP35)/10 -> 2047.4432 | CQ45: =+CQ41*SUM(CQ34:CQ35)/10 -> 1931.8239 | CR45: =+CR41*SUM(CR34:CR35)/10 -> 3061.5288 | CS45: =+CS41*SUM(CS34:CS35)/10 -> 3000.2543 | CT45: =+CT41*SUM(CT34:CT35)/10 -> 2944.4971 | ... DB45: =+DB41*SUM(DB34:DB35)/10 -> 2162.8829 | DF45: 1206
A46: Thriveni MDO operation Revenue | W46: =SUM(BS46:BV46) -> 0 | X46: =SUM(BW46:BZ46) -> 0 | Y46: =SUM(CA46:CD46) -> 0 | Z46: =SUM(CE46:CH46) -> 0 | AA46: =SUM(CI46:CL46) -> 6319.1 | AB46: =+SUM(CM46:CP46) -> 11446.74 | AC46: =+SUM(CQ46:CT46) -> 12591.414 | AD46: =+SUM(CU46:CX46) -> 15109.697 | AE46: =+SUM(CY46:DB46) -> 15865.182 | CJ46: 1607 | CK46: 2197.1 | CL46: 2515 | CM46: 2600 | CN46: =+CJ46*140% -> 2249.8 | CO46: =+CK46*140% -> 3075.94 | CP46: =+CL46*140% -> 3521 | CQ46: =+CM46*110% -> 2860 | CR46: =+CN46*110% -> 2474.78 | CS46: =+CO46*110% -> 3383.534 | CT46: =+CP46*110% -> 3873.1 | CU46: =+CQ46*120% -> 3432 | CV46: =+CR46*120% -> 2969.736 | CW46: =+CS46*120% -> 4060.2408 | CX46: =+CT46*120% -> 4647.72 | CY46: =+CU46*105% -> 3603.6 | CZ46: =+CV46*105% -> 3118.2228 | DA46: =+CW46*105% -> 4263.2528 | DB46: =+CX46*105% -> 4880.106 | DF46: 1607.3715
A47: Wire Rod+HRC-->Steel Revenue | AA47: =SUM(CI47:CL47) -> 0 | AB47: =+SUM(CM47:CP47) -> 535.5 | AC47: =+SUM(CQ47:CT47) -> 3460.8 | AD47: =+SUM(CU47:CX47) -> 4324.8 | AE47: =+SUM(CY47:DB47) -> 14320.8 | CP47: =+(CP36+CP37)*CP42/10 -> 535.5 | CQ47: =+(CQ36+CQ37)*CQ42/10 -> 865.2 | CR47: =+(CR36+CR37)*CR42/10 -> 865.2 | CS47: =+(CS36+CS37)*CS42/10 -> 865.2 | CT47: =+(CT36+CT37)*CT42/10 -> 865.2 | CU47: =+(CU36+CU37)*CU42/10 -> 1081.2 | CV47: =+(CV36+CV37)*CV42/10 -> 1081.2 | CW47: =+(CW36+CW37)*CW42/10 -> 1081.2 | ... DB47: =+(DB36+DB37)*DB42/10 -> 3580.2
A48: Power | W48: =SUM(BS48:BV48) -> 49.72 | X48: =SUM(BW48:BZ48) -> 75.01 | Y48: =SUM(CA48:CD48) -> 127.32 | Z48: =SUM(CE48:CH48) -> 83.92 | AA48: =SUM(CI48:CL48) -> 0 | AB48: =+SUM(CM48:CP48) -> 0 | AC48: =+SUM(CQ48:CT48) -> 0 | AD48: =+SUM(CU48:CX48) -> 0 | AE48: =+SUM(CY48:DB48) -> 0 | AI48: 19.89 | AJ48: 13.43 | AK48: 18.57 | AL48: 20.69 | AM48: 14.37 | AN48: 7.92 | AO48: 8.83 | AP48: 7.76 | AQ48: 12.7 | AR48: 8.73 | AS48: 6.91 | AT48: 11 | AU48: 17.6 | AV48: 9.67 | AW48: 12.79 | AX48: 17.7 | AY48: 18.72 | AZ48: 15.34 | BA48: 15.49 | BB48: 13.91 | BC48: 14.77 | BD48: 15.93 | BE48: 16.36 | BF48: 16.77 | BG48: 19.4 | BH48: 12.11 | BI48: 13.66 | BJ48: 21.13 | BK48: 21.83 | BL48: 15.36 | BM48: 13.56 | BN48: 20.43 | BO48: 1.44 | BP48: 10.08 | BQ48: 12.27 | BR48: 12.63 | BS48: 17.04 | BT48: 12.95 | BU48: 8.3 | BV48: 11.43 | BW48: 19.06 | BX48: 11.36 | BY48: 17.32 | BZ48: 27.27 | CA48: 41.95 | CB48: 19.34 | CC48: 38.92 | CD48: 27.11 | CE48: 36.58 | CF48: 22.5 | CG48: 24.84
A49: Pellet Trading | W49: =SUM(BS49:BV49) -> 0 | X49: =SUM(BW49:BZ49) -> 0 | Y49: =SUM(CA49:CD49) -> 346.08 | Z49: =SUM(CE49:CH49) -> 267.82 | AA49: =SUM(CI49:CL49) -> 0 | AB49: =+SUM(CM49:CP49) -> 0 | AC49: =+SUM(CQ49:CT49) -> 0 | AD49: =+SUM(CU49:CX49) -> 0 | AE49: =+SUM(CY49:DB49) -> 0 | CC49: 267.23 | CD49: 78.85 | CE49: 212.8 | CF49: 0.66 | CG49: 54.36
A50: Less Inter Segment Revenue (b/F) | W50: =SUM(BS50:BV50) -> 5.86 | X50: =SUM(BW50:BZ50) -> 8.33 | Y50: =SUM(CA50:CD50) -> 49.09 | Z50: =SUM(CE50:CH50) -> 168.92 | AA50: =SUM(CI50:CL50) -> 2921.77 | AB50: =+SUM(CM50:CP50) -> 9221.4715 | AC50: =+SUM(CQ50:CT50) -> 3471.6 | AD50: =+SUM(CU50:CX50) -> 3794.1 | AE50: =+SUM(CY50:DB50) -> 4112.952 | AI50: 2.69 | AJ50: 2.12 | AK50: 2.15 | AL50: 2.43 | AM50: 2.54 | AN50: 2.15 | AO50: 2.58 | AP50: 2.88 | AQ50: 2.47 | AR50: 1.61 | AS50: 1.75 | AT50: 1.91 | AU50: 2.36 | AV50: 1.11 | AW50: 1.92 | AX50: 2.26 | AY50: 2.24 | AZ50: 2.29 | BA50: 2.03 | BB50: 30.13 | BC50: 8.48 | BD50: 1.94 | BE50: 3.67 | BF50: 2.23 | BG50: 2.55 | BH50: 2.02 | BI50: 2.25 | BJ50: 2.47 | BK50: 2.37 | BL50: 1.47 | BM50: 1.98 | BN50: 2.16 | BO50: 1.05 | BP50: 1.67 | BQ50: 1.47 | BR50: 0.78 | BS50: 1.3 | BT50: 1.5 | BU50: 1.55 | BV50: 1.51 | BW50: 2 | BX50: 2.07 | BY50: 2.36 | BZ50: 1.9 | CA50: 2.5 | CB50: 1.42 | CC50: 3.35 | CD50: 41.82 | CE50: 52.44 | CF50: 27.48 | CG50: 42.39 | CH50: 46.61 | CI50: 67.94 | CJ50: 475.6 | CK50: 916.76 | CL50: 1461.47 | CM50: =+CM31*(CM21+CM23+CM24+CM26+CM30) -> 2251.1455 | CN50: =+CN31*(CN21+CN23+CN24+CN26+CN30) -> 2251.1455 | CO50: =+CO31*(CO21+CO23+CO24+CO26+CO30) -> 2251.1455 | CP50: =+CP31*(CP21+CP23+CP24+CP26+CP30) -> 2468.0351 | CQ50: =+CQ31*(CQ21+CQ23+CQ24+CQ26+CQ30) -> 665.4 | CR50: =+CR31*(CR21+CR23+CR24+CR26+CR30) -> 935.4 | CS50: =+CS31*(CS21+CS23+CS24+CS26+CS30) -> 935.4 | CT50: =+CT31*(CT21+CT23+CT24+CT26+CT30) -> 935.4 | ... DB50: =+DB31*(DB21+DB23+DB24+DB26+DB30) -> 1028.238 | DF50: 500
A51: Total Revenue | W51: =SUM(W44:W49)-W50 -> 727.25 | X51: =SUM(X44:X49)-X50 -> 3466.76 | Y51: =SUM(Y44:Y49)-Y50 -> 6574.57 | Z51: =SUM(Z44:Z49)-Z50 -> 6798.07 | AA51: =SUM(AA44:AA49)-AA50 -> 17304.77 | AB51: =SUM(AB44:AB49)-AB50 -> 22012.325 | AC51: =SUM(AC44:AC49)-AC50 -> 30538.688 | AD51: =SUM(AD44:AD49)-AD50 -> 34582.594 | AE51: =SUM(AE44:AE49)-AE50 -> 41564.85 | AI51: =SUM(AI44:AI49)-AI50 -> 250.83 | AJ51: =SUM(AJ44:AJ49)-AJ50 -> 134.39 | AK51: =SUM(AK44:AK49)-AK50 -> 140.66 | AL51: =SUM(AL44:AL49)-AL50 -> 240.2 | AM51: =SUM(AM44:AM49)-AM50 -> 142.83 | AN51: =SUM(AN44:AN49)-AN50 -> 111.86 | AO51: =SUM(AO44:AO49)-AO50 -> 132.47 | AP51: =SUM(AP44:AP49)-AP50 -> 187.12 | ... DB51: =SUM(DB44:DB49)-DB50 -> 11303.076 | DF51: 5019.3715
A52: Checksum | W52: =W51-W74-W102 -> 1.1368684e-13 | X52: =X51-X74-X102 -> -0.01 | Y52: =Y51-Y74-Y102 -> -0.03 | Z52: =Z51-Z74-Z102 -> 23.31 | AA52: =AA51-AA74-AA102 -> -1.63 | AB52: =AB51-AB74-AB102 -> 0 | AC52: =AC51-AC74-AC102 -> 0 | AD52: =AD51-AD74-AD102 -> 0 | AE52: =AE51-AE74-AE102 -> 0 | AI52: =AI51-AI74-AI102 -> 0.001 | AJ52: =AJ51-AJ74-AJ102 -> -0.003 | AK52: =AK51-AK74-AK102 -> -4.4408921e-15 | AL52: =AL51-AL74-AL102 -> 0.009 | AM52: =AM51-AM74-AM102 -> 0.008 | AN52: =AN51-AN74-AN102 -> -0.003 | AO52: =AO51-AO74-AO102 -> 0.007 | AP52: =AP51-AP74-AP102 -> 0.009 | ... DB52: =DB51-DB74-DB102 -> 0 | DF52: 0
A54: EBITDA Per Tonne (co. Reported)
A55: Iron ore | Y55: =+Y61/Y33*10 -> 924.29001 | Z55: =+Z61/Z33*10 -> 1842.2262 | AA55: =+AA61/AA33*10 -> 1712.9408 | AB55: =+AB61/AB33*10 -> 1889.4068 | AC55: =+AC61/AC33*10 -> 1964.5311 | AD55: =+AD61/AD33*10 -> 1973.1825 | AE55: =+AE61/AE33*10 -> 1974.8422 | CC55: 1666 | CD55: 2375 | CE55: 1848 | CF55: 1668 | CG55: 2021 | CH55: 1527 | CI55: 2223 | CJ55: 1781 | CK55: 1825 | CL55: 1894 | CM55: =+AVERAGE(CI55:CL55) -> 1930.75 | CN55: =+AVERAGE(CJ55:CM55) -> 1857.6875 | CO55: =+AVERAGE(CK55:CN55) -> 1876.8594 | CP55: =+AVERAGE(CL55:CO55) -> 1889.8242 | CQ55: =+AVERAGE(CM55:CP55)*1.03 -> 1945.4437 | CR55: =+AVERAGE(CN55:CQ55)*1.03 -> 1949.2273 | CS55: =+AVERAGE(CO55:CR55)*1.03 -> 1972.7988 | CT55: =+AVERAGE(CP55:CS55)*1.03 -> 1997.5032 | CU55: =+AVERAGE(CQ55:CT55) -> 1966.2432 | CV55: =+AVERAGE(CR55:CU55) -> 1971.4431 | CW55: =+AVERAGE(CS55:CV55) -> 1976.9971 | CX55: =+AVERAGE(CT55:CW55) -> 1978.0467 | CY55: =+AVERAGE(CU55:CX55) -> 1973.1825 | CZ55: =+AVERAGE(CV55:CY55) -> 1974.9174 | DA55: =+AVERAGE(CW55:CZ55) -> 1975.7859 | DB55: =+AVERAGE(CX55:DA55) -> 1975.4831
A56: Pellet | AA56: =+AA62/AA34*10 -> 4659.0449 | AB56: =+AB62/AB34*10 -> 4115.7593 | AC56: =+AC62/AC34*10 -> 4440.7169 | AD56: =+AD62/AD34*10 -> 4457.5886 | AE56: =+AE62/AE34*10 -> 4593.1908 | CJ56: 4900 | CK56: 4500 | CL56: 4040 | CM56: =+AVERAGE(CI56:CL56)*0.9 -> 4032 | CN56: =+AVERAGE(CJ56:CM56)*0.95 -> 4149.6 | CO56: =+AVERAGE(CK56:CN56) -> 4180.4 | CP56: =+AVERAGE(CL56:CO56) -> 4100.5 | CQ56: =+AVERAGE(CM56:CP56)*1.05 -> 4321.4062 | CR56: =+AVERAGE(CN56:CQ56)*1.05 -> 4397.3754 | CS56: =+AVERAGE(CO56:CR56)*1.05 -> 4462.4164 | CT56: =+AVERAGE(CP56:CS56)*1.05 -> 4536.4457 | CU56: =+AVERAGE(CQ56:CT56) -> 4429.411 | CV56: =+AVERAGE(CR56:CU56) -> 4456.4121 | CW56: =+AVERAGE(CS56:CV56) -> 4471.1713 | CX56: =+AVERAGE(CT56:CW56) -> 4473.36 | CY56: =+AVERAGE(CU56:CX56)*1.02 -> 4546.7404 | CZ56: =+AVERAGE(CV56:CY56)*1.02 -> 4576.6594 | DA56: =+AVERAGE(CW56:CZ56)*1.02 -> 4607.3224 | DB56: =+AVERAGE(CX56:DA56)*1.02 -> 4642.041
A57: DRI | AA57: =+AA63/AA35*10 -> 5862.0124 | AB57: =+AB63/AB35*10 -> 5000 | CJ57: 6000 | CK57: 6500 | CL57: 7999 | CM57: 5000 | CN57: =+CM57 -> 5000 | CO57: =+CN57 -> 5000
A58: Wire Rod+HRC-->Steel | AA58: =+AA65/AA36*10 -> #DIV/0! | AB58: =+AB65/AB36*10 -> 4750 | AC58: =+AC65/AC36*10 -> 7700 | AD58: =+AD65/AD36*10 -> 8800 | AE58: =+AE65/(AE36+AE37)*10 -> 11431.034 | CP58: 9500 | CQ58: 11000 | CR58: =+CQ58 -> 11000 | CS58: =+CR58 -> 11000 | CT58: =+CS58 -> 11000 | CU58: =+CT58 -> 11000 | CV58: =+CU58 -> 11000 | CW58: =+CV58 -> 11000 | CX58: =+CW58 -> 11000 | CY58: 15000 | CZ58: =+CY58 -> 15000 | DA58: =+CZ58 -> 15000 | DB58: =+DA58 -> 15000
A60: EBITDA
A61: Iron Ore EBITDA | Y61: =SUM(CA61:CD61) -> 885.084 | Z61: =SUM(CE61:CH61) -> 1750.234 | AA61: =SUM(CI61:CL61) -> 3127.139 | AB61: =+SUM(CM61:CP61) -> 3280.0103 | AC61: =+SUM(CQ61:CT61) -> 2577.4648 | AD61: =+SUM(CU61:CX61) -> 2544.6162 | AE61: =+SUM(CY61:DB61) -> 2546.7566 | CC61: =+CC55*CC33/10 -> 414.834 | CD61: =+CD55*CD33/10 -> 470.25 | CE61: =+CE55*CE33/10 -> 665.28 | CF61: =+CF55*CF33/10 -> 330.264 | CG61: =+CG55*CG33/10 -> 501.208 | CH61: =+CH55*CH33/10 -> 253.482 | CI61: =+CI55*CI33/10 -> 766.935 | CJ61: =+CJ55*CJ33/10 -> 445.25 | ... DB61: =+DB55*DB33/10 -> 636.89576
A62: Pellet EBITDA | Y62: =SUM(CA62:CD62) -> 0 | Z62: =SUM(CE62:CH62) -> 0 | AA62: =SUM(CI62:CL62) -> 1147.66 | AB62: =+SUM(CM62:CP62) -> 2549.5483 | AC62: =+SUM(CQ62:CT62) -> 3817.9508 | AD62: =+SUM(CU62:CX62) -> 4257.7103 | AE62: =+SUM(CY62:DB62) -> 3144.3147 | CJ62: =+CJ56*CJ34/10 -> 338.1 | CK62: =+CK56*CK34/10 -> 450 | CL62: =+CL56*CL34/10 -> 359.56 | CM62: =+CM56*CM34/10 -> 629.95968 | CN62: =+CN56*CN34/10 -> 648.3335 | CO62: =+CO56*CO34/10 -> 653.1457 | CP62: =+CP56*CP34/10 -> 618.10937 | CQ62: =+CQ56*CQ34/10 -> 637.14814 | ... DB62: =+DB56*DB34/10 -> 794.43889
A63: DRI EBITDA | AA63: =SUM(CI63:CL63) -> 283.7214 | AB63: =+SUM(CM63:CP63) -> 264 | AC63: =+SUM(CQ63:CT63) -> 0 | AD63: =+SUM(CU63:CX63) -> 0 | AE63: =+SUM(CY63:DB63) -> 0 | CJ63: =+CJ57*CJ35/10 -> 53.2602 | CK63: =+CK57*CK35/10 -> 80.08 | CL63: =+CL57*CL35/10 -> 150.3812 | CM63: =+CM57*CM35/10 -> 88 | CN63: =+CN57*CN35/10 -> 88 | CO63: =+CO57*CO35/10 -> 88 | CP63: =+CP57*CP35/10 -> 0 | CQ63: =+CQ57*CQ35/10 -> 0 | ... DB63: =+DB57*DB35/10 -> 0
A64: Thriveni MDO operation EBITDA(standalone coEBITDA-console Co.EBITDA) | Y64: =SUM(CA64:CD64) -> 0 | Z64: =SUM(CE64:CH64) -> 0 | AA64: =SUM(CI64:CL64) -> 1746.4 | AB64: =+SUM(CM64:CP64) -> 2861.685 | AC64: =+SUM(CQ64:CT64) -> 3777.4242 | AD64: =+SUM(CU64:CX64) -> 4835.103 | AE64: =+SUM(CY64:DB64) -> 5076.8581 | CJ64: 226.5 | CK64: 545.5 | CL64: 974.4 | CM64: =+CM46*25% -> 650 | CN64: =+CN46*25% -> 562.45 | CO64: =+CO46*25% -> 768.985 | CP64: =+CP46*25% -> 880.25 | CQ64: =+CQ46*30% -> 858 | CR64: =+CR46*30% -> 742.434 | CS64: =+CS46*30% -> 1015.0602 | CT64: =+CT46*30% -> 1161.93 | CU64: =+CU46*32% -> 1098.24 | CV64: =+CV46*32% -> 950.31552 | CW64: =+CW46*32% -> 1299.2771 | CX64: =+CX46*32% -> 1487.2704 | CY64: =+CY46*32% -> 1153.152 | CZ64: =+CZ46*32% -> 997.8313 | DA64: =+DA46*32% -> 1364.2409 | DB64: =+DB46*32% -> 1561.6339
A65: Wire Rod+HRC-->Steel EBITDA | Y65: =SUM(CA65:CD65) -> 0 | Z65: =SUM(CE65:CH65) -> 0 | AA65: =SUM(CI65:CL65) -> 0 | AB65: =+SUM(CM65:CP65) -> 99.75 | AC65: =+SUM(CQ65:CT65) -> 739.2 | AD65: =+SUM(CU65:CX65) -> 897.6 | AE65: =+SUM(CY65:DB65) -> 3978 | CP65: =+CP58*(CP37+CP36)/10 -> 99.75 | CQ65: =+CQ58*(CQ37+CQ36)/10 -> 184.8 | CR65: =+CR58*(CR37+CR36)/10 -> 184.8 | CS65: =+CS58*(CS37+CS36)/10 -> 184.8 | CT65: =+CT58*(CT37+CT36)/10 -> 184.8 | CU65: =+CU58*(CU37+CU36)/10 -> 224.4 | CV65: =+CV58*(CV37+CV36)/10 -> 224.4 | CW65: =+CW58*(CW37+CW36)/10 -> 224.4 | ... DB65: =+DB58*(DB37+DB36)/10 -> 994.5
A66: Others (b/f) | AA66: =SUM(CI66:CL66) -> -163.1304 | AB66: =+SUM(CM66:CP66) -> 0 | AC66: =+SUM(CQ66:CT66) -> 0 | AD66: =+SUM(CU66:CX66) -> 0 | AE66: =+SUM(CY66:DB66) -> 0 | CC66: 34.636 | CD66: -11.84 | CE66: 53.39 | CF66: 80.446 | CG66: 35.222 | CH66: 7.618 | CI66: 27.255 | CJ66: -20.0202 | CK66: -64.62 | CL66: -105.7452
A67: Total EBITDA | Y67: =+SUM(Y61:Y66) -> 885.084 | Z67: =+SUM(Z61:Z66) -> 1750.234 | AA67: =+SUM(AA61:AA66) -> 6141.79 | AB67: =+SUM(AB61:AB66) -> 9054.9935 | AC67: =+SUM(AC61:AC66) -> 10912.04 | AD67: =+SUM(AD61:AD66) -> 12535.03 | AE67: =+SUM(AE61:AE66) -> 14745.929 | CC67: =+SUM(CC61:CC66) -> 449.47 | CD67: =+SUM(CD61:CD66) -> 458.41 | CE67: =+SUM(CE61:CE66) -> 718.67 | CF67: =+SUM(CF61:CF66) -> 410.71 | CG67: =+SUM(CG61:CG66) -> 536.43 | CH67: =+SUM(CH61:CH66) -> 261.1 | CI67: =+SUM(CI61:CI66) -> 794.19 | CJ67: =+SUM(CJ61:CJ66) -> 1043.09 | ... DB67: =+SUM(DB61:DB66) -> 3987.4686
Y68: =+Y67-Y95 -> -846.166 | Z68: =+Z67-Z95 -> -205.506 | AA68: =+AA67-AA95 -> -10.37 | AB68: =+AB67-AB95 -> 0 | AC68: =+AC67-AC95 -> 0 | AD68: =+AD67-AD95 -> 0 | AE68: =+AE67-AE95 -> 0 | CC68: =+CC67-CC95 -> 0 | CD68: =+CD67-CD95 -> 0 | CE68: =+CE67-CE95 -> 0 | CF68: =+CF67-CF95 -> 0 | CG68: =+CG67-CG95 -> 0 | CH68: =+CH67-CH95 -> 0 | CI68: =+CI67-CI95 -> 0 | CJ68: =+CJ67-CJ95 -> 0 | ... DB68: =+DB67-DB95 -> 0
A70: Presentation Data (End)
A71: Profit & Loss- Annual (Start)
A72: Gross Revenue | B72: ='Annual Raw'!C6 -> 114.754 | C72: ='Annual Raw'!D6 -> 117.1898 | D72: ='Annual Raw'!E6 -> 169.7335 | E72: ='Annual Raw'!F6 -> 198.8392 | F72: ='Annual Raw'!G6 -> 281.165 | G72: ='Annual Raw'!H6 -> 295.0468 | H72: ='Annual Raw'!I6 -> 336.6405 | I72: ='Annual Raw'!J6 -> 381.998 | ... AA72: ='Annual Raw'!AB6 -> 17112.67 | AB72: =+SUM(CM72:CP72) -> 22012.325 | AC72: =+SUM(CQ72:CT72) -> 30538.688 | AD72: =+SUM(CU72:CX72) -> 34582.594 | AE72: =+SUM(CY72:DB72) -> 41564.85 | AI72: ='QTR Raw'!C6+'QTR Raw'!C8 -> 260.709 | AJ72: ='QTR Raw'!D6+'QTR Raw'!D8 -> 130.556 | AK72: ='QTR Raw'!E6+'QTR Raw'!E8 -> 147.374 | AL72: ='QTR Raw'!F6+'QTR Raw'!F8 -> 253.529 | AM72: ='QTR Raw'!G6+'QTR Raw'!G8 -> 147.415 | AN72: ='QTR Raw'!H6+'QTR Raw'!H8 -> 115.678 | AO72: ='QTR Raw'!I6+'QTR Raw'!I8 -> 139.526 | AP72: ='QTR Raw'!J6+'QTR Raw'!J8 -> 197.025 | ... CL72: ='QTR Raw'!BF6+'QTR Raw'!BF8 -> 6019.72 | CM72: =+CM51 -> 5573.1978 | CN72: =+CN51 -> 5187.6284 | CO72: =+CO51 -> 5400.7928 | CP72: =+CP51 -> 5850.7061 | CQ72: =+CQ51 -> 7224.6866 | CR72: =+CR51 -> 7087.1459 | CS72: =+CS51 -> 7912.1717 | CT72: =+CT51 -> 8314.6839 | ... DB72: =+DB51 -> 11303.076 | DF72: 17112.67
A73: Less: Exise Duty | B73: ='Annual Raw'!C7+'Annual Raw'!C8+'Annual Raw'!C9 -> 12.6164 | C73: ='Annual Raw'!D7+'Annual Raw'!D8+'Annual Raw'!D9 -> 11.2066 | D73: ='Annual Raw'!E7+'Annual Raw'!E8+'Annual Raw'!E9 -> 19.686 | E73: ='Annual Raw'!F7+'Annual Raw'!F8+'Annual Raw'!F9 -> 23.016 | F73: ='Annual Raw'!G7+'Annual Raw'!G8+'Annual Raw'!G9 -> 23.548 | G73: ='Annual Raw'!H7+'Annual Raw'!H8+'Annual Raw'!H9 -> 41.0368 | H73: ='Annual Raw'!I7+'Annual Raw'!I8+'Annual Raw'!I9 -> 0 | I73: ='Annual Raw'!J7+'Annual Raw'!J8+'Annual Raw'!J9 -> 0 | ... AA73: ='Annual Raw'!AB7+'Annual Raw'!AB8+'Annual Raw'!AB9 -> 0 | AB73: =+SUM(CM73:CP73) -> 0 | AC73: =+SUM(CQ73:CT73) -> 0 | AD73: =+SUM(CU73:CX73) -> 0 | AE73: =+SUM(CY73:DB73) -> 0 | AI73: =+'QTR Raw'!C20+'QTR Raw'!C19+'QTR Raw'!C13+'QTR Raw'!C7 -> 13.487 | AJ73: =+'QTR Raw'!D20+'QTR Raw'!D19+'QTR Raw'!D13+'QTR Raw'!D7 -> 9.078 | AK73: =+'QTR Raw'!E20+'QTR Raw'!E19+'QTR Raw'!E13+'QTR Raw'!E7 -> 9.094 | AL73: =+'QTR Raw'!F20+'QTR Raw'!F19+'QTR Raw'!F13+'QTR Raw'!F7 -> 10.699 | AM73: =+'QTR Raw'!G20+'QTR Raw'!G19+'QTR Raw'!G13+'QTR Raw'!G7 -> 9.803 | AN73: =+'QTR Raw'!H20+'QTR Raw'!H19+'QTR Raw'!H13+'QTR Raw'!H7 -> 7.53 | AO73: =+'QTR Raw'!I20+'QTR Raw'!I19+'QTR Raw'!I13+'QTR Raw'!I7 -> 11.234 | AP73: =+'QTR Raw'!J20+'QTR Raw'!J19+'QTR Raw'!J13+'QTR Raw'!J7 -> 13.495 | ... CL73: =+'QTR Raw'!BF20+'QTR Raw'!BF19+'QTR Raw'!BF13+'QTR Raw'!BF7 -> 0 | DF73: 0
A74: Net Revenue | B74: =+B72-B73 -> 102.1376 | C74: =+C72-C73 -> 105.9832 | D74: =+D72-D73 -> 150.0475 | E74: =+E72-E73 -> 175.8232 | F74: =+F72-F73 -> 257.617 | G74: =+G72-G73 -> 254.01 | H74: =+H72-H73 -> 336.6405 | I74: =+I72-I73 -> 381.998 | ... AE74: =+AE72-AE73 -> 41564.85 | AI74: =+AI72-AI73 -> 247.222 | AJ74: =+AJ72-AJ73 -> 121.478 | AK74: =+AK72-AK73 -> 138.28 | AL74: =+AL72-AL73 -> 242.83 | AM74: =+AM72-AM73 -> 137.612 | AN74: =+AN72-AN73 -> 108.148 | AO74: =+AO72-AO73 -> 128.292 | AP74: =+AP72-AP73 -> 183.53 | ... DB74: =+DB72-DB73 -> 11303.076 | DF74: 17112.67
A75: Net Revenue YOY% | C75: =C74/B74-1 -> 0.037651169 | D75: =D74/C74-1 -> 0.41576684 | E75: =E74/D74-1 -> 0.1717836 | F75: =F74/E74-1 -> 0.46520482 | G75: =G74/F74-1 -> -0.014001405 | H75: =H74/G74-1 -> 0.32530412 | I75: =I74/H74-1 -> 0.13473572 | J75: =J74/I74-1 -> 0.78321274 | ... AE75: =AE74/AD74-1 -> 0.20190088 | AM75: =+IF(AI74<0,1-AM74/AI74,AM74/AI74-1) -> -0.44336669 | AN75: =+IF(AJ74<0,1-AN74/AJ74,AN74/AJ74-1) -> -0.1097318 | AO75: =+IF(AK74<0,1-AO74/AK74,AO74/AK74-1) -> -0.072230257 | AP75: =+IF(AL74<0,1-AP74/AL74,AP74/AL74-1) -> -0.24420376 | AQ75: =+IF(AM74<0,1-AQ74/AM74,AQ74/AM74-1) -> 0.26540563 | AR75: =+IF(AN74<0,1-AR74/AN74,AR74/AN74-1) -> 0.99641232 | AS75: =+IF(AO74<0,1-AS74/AO74,AS74/AO74-1) -> -0.080301188 | AT75: =+IF(AP74<0,1-AT74/AP74,AT74/AP74-1) -> -0.32899798 | ... DB75: =+IF(CX74<0,1-DB74/CX74,DB74/CX74-1) -> 0.19019526 | DF75: 1.5461304
A76: Net Revenue QOQ% | AJ76: =+IF(AI74<0,1-AJ74/AI74,AJ74/AI74-1) -> -0.50862787 | AK76: =+IF(AJ74<0,1-AK74/AJ74,AK74/AJ74-1) -> 0.13831311 | AL76: =+IF(AK74<0,1-AL74/AK74,AL74/AK74-1) -> 0.75607463 | AM76: =+IF(AL74<0,1-AM74/AL74,AM74/AL74-1) -> -0.43329902 | AN76: =+IF(AM74<0,1-AN74/AM74,AN74/AM74-1) -> -0.21410923 | AO76: =+IF(AN74<0,1-AO74/AN74,AO74/AN74-1) -> 0.18626327 | AP76: =+IF(AO74<0,1-AP74/AO74,AP74/AO74-1) -> 0.43056465 | AQ76: =+IF(AP74<0,1-AQ74/AP74,AQ74/AP74-1) -> -0.051190541 | ... DB76: =+IF(DA74<0,1-DB74/DA74,DB74/DA74-1) -> 0.057832735
A77: Increase/Decrease in Stock | B77: ='Annual Raw'!C11 -> -0.876 | C77: ='Annual Raw'!D11 -> 0.8327 | D77: ='Annual Raw'!E11 -> -1.1713 | E77: ='Annual Raw'!F11 -> -4.0017 | F77: ='Annual Raw'!G11 -> 6.6035 | G77: ='Annual Raw'!H11 -> -21.5463 | H77: ='Annual Raw'!I11 -> 62.954 | I77: ='Annual Raw'!J11 -> 35.1021 | ... AA77: ='Annual Raw'!AB11 -> -719.66 | AB77: =+SUM(CM77:CP77) -> 0 | AC77: =+SUM(CQ77:CT77) -> 0 | AD77: =+SUM(CU77:CX77) -> 0 | AE77: =+SUM(CY77:DB77) -> 0 | AI77: ='QTR Raw'!C10 -> 1.27 | AJ77: ='QTR Raw'!D10 -> -0.906 | AK77: ='QTR Raw'!E10 -> -3.725 | AL77: ='QTR Raw'!F10 -> 3.858 | AM77: ='QTR Raw'!G10 -> 2.473 | AN77: ='QTR Raw'!H10 -> -1.462 | AO77: ='QTR Raw'!I10 -> 0.664 | AP77: ='QTR Raw'!J10 -> -8.448 | ... CL77: ='QTR Raw'!BF10 -> -492.72 | DF77: -719.66
A78: Purchase of Finished Goods | B78: 0 | C78: 0 | D78: 0 | E78: 0 | F78: 0 | G78: 0 | H78: 0 | I78: 0 | J78: 0 | K78: 0 | L78: 0 | M78: 0 | N78: 0 | O78: 0 | P78: 0 | Q78: 0 | R78: 0 | S78: 0 | T78: 0 | U78: 0 | V78: 0 | W78: 0 | X78: 0 | Y78: 0 | Z78: 0 | AA78: 0 | AB78: =+SUM(CM78:CP78) -> 0 | AC78: =+SUM(CQ78:CT78) -> 0 | AD78: =+SUM(CU78:CX78) -> 0 | AE78: =+SUM(CY78:DB78) -> 0 | AI78: ='QTR Raw'!C12 -> 126.523 | AJ78: ='QTR Raw'!D12 -> 36.508 | AK78: ='QTR Raw'!E12 -> 46.562 | AL78: ='QTR Raw'!F12 -> 111.535 | AM78: ='QTR Raw'!G12 -> 45.612 | AN78: ='QTR Raw'!H12 -> 41.833 | AO78: ='QTR Raw'!I12 -> 30.953 | AP78: ='QTR Raw'!J12 -> 78.351 | ... CL78: ='QTR Raw'!BF12 -> 10.51 | DF78: 0
A79: Raw Material Consumed | B79: ='Annual Raw'!C12 -> 76.1407 | C79: ='Annual Raw'!D12 -> 79.6914 | D79: ='Annual Raw'!E12 -> 110.4087 | E79: ='Annual Raw'!F12 -> 128.3885 | F79: ='Annual Raw'!G12 -> 179.9905 | G79: ='Annual Raw'!H12 -> 224.977 | H79: ='Annual Raw'!I12 -> 222.043 | I79: ='Annual Raw'!J12 -> 267.9909 | ... AA79: ='Annual Raw'!AB12 -> 2538.3 | AB79: =+SUM(CM79:CP79) -> 2382.7362 | AC79: =+SUM(CQ79:CT79) -> 3032.7678 | AD79: =+SUM(CU79:CX79) -> 3401.333 | AE79: =+SUM(CY79:DB79) -> 4079.1226 | AI79: ='QTR Raw'!C11 -> 100.856 | AJ79: ='QTR Raw'!D11 -> 76.447 | AK79: ='QTR Raw'!E11 -> 83.288 | AL79: ='QTR Raw'!F11 -> 93.1 | AM79: ='QTR Raw'!G11 -> 87.046 | AN79: ='QTR Raw'!H11 -> 62.196 | AO79: ='QTR Raw'!I11 -> 86.789 | AP79: ='QTR Raw'!J11 -> 108.294 | ... CL79: ='QTR Raw'!BF11 -> 855.07 | CM79: =+CM74-CM80 -> 618.66061 | CN79: =+CN74-CN80 -> 614.35927 | CO79: =+CO74-CO80 -> 569.33862 | CP79: =+CP74-CP80 -> 580.37766 | CQ79: =+CQ74-CQ80 -> 747.84475 | CR79: =+CR74-CR80 -> 720.32984 | CS79: =+CS74-CS80 -> 770.97549 | CT79: =+CT74-CT80 -> 793.6177 | ... DB79: =+DB74-DB80 -> 1108.5357 | DF79: 2538.3
A80: Gross Profit | B80: =B74-B77-B79-B78 -> 26.8729 | C80: =C74-C77-C79-C78 -> 25.4591 | D80: =D74-D77-D79-D78 -> 40.8101 | E80: =E74-E77-E79-E78 -> 51.4364 | F80: =F74-F77-F79-F78 -> 71.023 | G80: =G74-G77-G79-G78 -> 50.5793 | H80: =H74-H77-H79-H78 -> 51.6435 | I80: =I74-I77-I79-I78 -> 78.905 | ... AE80: =AE74-AE77-AE79-AE78 -> 37485.727 | AI80: =AI74-AI77-AI79-AI78 -> 18.573 | AJ80: =AJ74-AJ77-AJ79-AJ78 -> 9.429 | AK80: =AK74-AK77-AK79-AK78 -> 12.155 | AL80: =AL74-AL77-AL79-AL78 -> 34.337 | AM80: =AM74-AM77-AM79-AM78 -> 2.481 | AN80: =AN74-AN77-AN79-AN78 -> 5.581 | AO80: =AO74-AO77-AO79-AO78 -> 9.886 | AP80: =AP74-AP77-AP79-AP78 -> 5.333 | ... CL80: =CL74-CL77-CL79-CL78 -> 5646.86 | CM80: =+CM81*CM74 -> 4954.5372 | CN80: =+CN81*CN74 -> 4573.2691 | CO80: =+CO81*CO74 -> 4831.4542 | CP80: =+CP81*CP74 -> 5270.3285 | CQ80: =+CQ81*CQ74 -> 6476.8418 | CR80: =+CR81*CR74 -> 6366.8161 | CS80: =+CS81*CS74 -> 7141.1962 | CT80: =+CT81*CT74 -> 7521.0662 | ... DB80: =+DB81*DB74 -> 10194.541 | DF80: 15294.03
A81: GP% | B81: =B80/B74 -> 0.26310487 | C81: =C80/C74 -> 0.24021826 | D81: =D80/D74 -> 0.27198121 | E81: =E80/E74 -> 0.29254615 | F81: =F80/F74 -> 0.27569221 | G81: =G80/G74 -> 0.19912326 | H81: =H80/H74 -> 0.15340846 | I81: =I80/I74 -> 0.20655867 | ... AE81: =AE80/AE74 -> 0.90186124 | AI81: =AI80/AI74 -> 0.075126809 | AJ81: =AJ80/AJ74 -> 0.077618993 | AK81: =AK80/AK74 -> 0.08790136 | AL81: =AL80/AL74 -> 0.14140345 | AM81: =AM80/AM74 -> 0.018028951 | AN81: =AN80/AN74 -> 0.051605208 | AO81: =AO80/AO74 -> 0.077058585 | AP81: =AP80/AP74 -> 0.02905792 | ... CL81: =CL80/CL74 -> 0.93806024 | CM81: =AVERAGE(CI81:CL81) -> 0.8889936 | CN81: =AVERAGE(CJ81:CM81) -> 0.88157223 | CO81: =AVERAGE(CK81:CN81) -> 0.8945824 | CP81: =AVERAGE(CL81:CO81) -> 0.90080212 | CQ81: =AVERAGE(CM81:CP81)+0.5% -> 0.89648759 | CR81: =AVERAGE(CN81:CQ81)+0.5% -> 0.89836108 | CS81: =AVERAGE(CO81:CR81)+0.5% -> 0.9025583 | CT81: =AVERAGE(CP81:CS81)+0.5% -> 0.90455227 | CU81: =AVERAGE(CQ81:CT81) -> 0.90048981 | CV81: =AVERAGE(CR81:CU81) -> 0.90149036 | CW81: =AVERAGE(CS81:CV81) -> 0.90227269 | CX81: =AVERAGE(CT81:CW81) -> 0.90220128 | CY81: =AVERAGE(CU81:CX81) -> 0.90161354 | CZ81: =AVERAGE(CV81:CY81) -> 0.90189447 | DA81: =AVERAGE(CW81:CZ81) -> 0.90199549 | DB81: =AVERAGE(CX81:DA81) -> 0.90192619 | DF81: 0.89372553
A82: GP YOY% | C82: =+IF(B80<0,1-C80/B80,C80/B80-1) -> -0.052610623 | D82: =+IF(C80<0,1-D80/C80,D80/C80-1) -> 0.60296711 | E82: =+IF(D80<0,1-E80/D80,E80/D80-1) -> 0.26038407 | F82: =+IF(E80<0,1-F80/E80,F80/E80-1) -> 0.38079259 | G82: =+IF(F80<0,1-G80/F80,G80/F80-1) -> -0.28784619 | H82: =+IF(G80<0,1-H80/G80,H80/G80-1) -> 0.021040228 | I82: =+IF(H80<0,1-I80/H80,I80/H80-1) -> 0.52787863 | J82: =+IF(I80<0,1-J80/I80,J80/I80-1) -> 0.63817629 | ... AE82: =+IF(AD80<0,1-AE80/AD80,AE80/AD80-1) -> 0.20218767 | AM82: =+IF(AI80<0,1-AM80/AI80,AM80/AI80-1) -> -0.866419 | AN82: =+IF(AJ80<0,1-AN80/AJ80,AN80/AJ80-1) -> -0.40810266 | AO82: =+IF(AK80<0,1-AO80/AK80,AO80/AK80-1) -> -0.18667215 | AP82: =+IF(AL80<0,1-AP80/AL80,AP80/AL80-1) -> -0.84468649 | AQ82: =+IF(AM80<0,1-AQ80/AM80,AQ80/AM80-1) -> 0.60620717 | AR82: =+IF(AN80<0,1-AR80/AN80,AR80/AN80-1) -> -0.45296542 | AS82: =+IF(AO80<0,1-AS80/AO80,AS80/AO80-1) -> -0.36091442 | AT82: =+IF(AP80<0,1-AT80/AP80,AT80/AP80-1) -> 1.1091318 | ... CL82: =+IF(CH80<0,1-CL80/CH80,CL80/CH80-1) -> 4.4309264 | CM82: =+CM80/CI80-1 -> 1.262666 | CN82: =+CN80/CJ80-1 -> 0.50987289 | CO82: =+CO80/CK80-1 -> 0.098299894 | CP82: =+CP80/CL80-1 -> -0.066679805 | CQ82: =+CQ80/CM80-1 -> 0.30725467 | CR82: =+CR80/CN80-1 -> 0.39218051 | CS82: =+CS80/CO80-1 -> 0.47806352 | CT82: =+CT80/CP80-1 -> 0.42705834 | ... DB82: =+DB80/CX80-1 -> 0.18983236 | DF82: 1.5856436
A83: GP QOQ% | AJ83: =+IF(AI80<0,1-AJ80/AI80,AJ80/AI80-1) -> -0.49232757 | AK83: =+IF(AJ80<0,1-AK80/AJ80,AK80/AJ80-1) -> 0.28910807 | AL83: =+IF(AK80<0,1-AL80/AK80,AL80/AK80-1) -> 1.824928 | AM83: =+IF(AL80<0,1-AM80/AL80,AM80/AL80-1) -> -0.92774558 | AN83: =+IF(AM80<0,1-AN80/AM80,AN80/AM80-1) -> 1.2494962 | AO83: =+IF(AN80<0,1-AO80/AN80,AO80/AN80-1) -> 0.77136714 | AP83: =+IF(AO80<0,1-AP80/AO80,AP80/AO80-1) -> -0.46055027 | AQ83: =+IF(AP80<0,1-AQ80/AP80,AQ80/AP80-1) -> -0.2527658 | ... CL83: =+IF(CK80<0,1-CL80/CK80,CL80/CK80-1) -> 0.28366026 | CM83: =+CM80/CL80-1 -> -0.12260315 | CN83: =+CN80/CM80-1 -> -0.076953313 | CO83: =+CO80/CN80-1 -> 0.056455256 | CP83: =+CP80/CO80-1 -> 0.090836893 | CQ83: =+CQ80/CP80-1 -> 0.22892565 | CR83: =+CR80/CQ80-1 -> -0.01698756 | CS83: =+CS80/CR80-1 -> 0.12162752 | CT83: =+CT80/CS80-1 -> 0.053194172 | ... DB83: =+DB80/DA80-1 -> 0.057751464
A84: Freight Expenses | X84: 706.66 | Y84: 1495.52 | Z84: 1494.99 | AA84: 1494.99 | AB84: =+SUM(CM84:CP84) -> 0 | AC84: =+SUM(CQ84:CT84) -> 0 | AD84: =+SUM(CU84:CX84) -> 0 | AE84: =+SUM(CY84:DB84) -> 0 | DF84: 1494.99
A85: Mining Charges | X85: 672.9 | Y85: 994 | Z85: 974.84 | AA85: 974.84 | AB85: =+SUM(CM85:CP85) -> 0 | AC85: =+SUM(CQ85:CT85) -> 0 | AD85: =+SUM(CU85:CX85) -> 0 | AE85: =+SUM(CY85:DB85) -> 0 | DF85: 974.84
A86: Royalty | X86: 372.06 | Y86: 750.2 | Z86: 854.13 | AA86: 854.13 | AB86: =+SUM(CM86:CP86) -> 0 | AC86: =+SUM(CQ86:CT86) -> 0 | AD86: =+SUM(CU86:CX86) -> 0 | AE86: =+SUM(CY86:DB86) -> 0 | DF86: 854.13
A87: Miscellaneous Expenses | B87: ='Annual Raw'!C19-'Annual Raw'!C20 -> 1.7669 | C87: ='Annual Raw'!D19-'Annual Raw'!D20 -> 1.5674 | D87: ='Annual Raw'!E19-'Annual Raw'!E20 -> 4.3116 | E87: ='Annual Raw'!F19-'Annual Raw'!F20 -> 15.3442 | F87: ='Annual Raw'!G19-'Annual Raw'!G20 -> 5.2389 | G87: ='Annual Raw'!H19-'Annual Raw'!H20 -> 1.4515 | H87: ='Annual Raw'!I19-'Annual Raw'!I20 -> 2.3901 | I87: ='Annual Raw'!J19-'Annual Raw'!J20 -> 1.5755 | ... AA87: ='Annual Raw'!AB19-'Annual Raw'!AB20 -> 600.2 | AB87: =+SUM(CM87:CP87) -> 0 | AC87: =+SUM(CQ87:CT87) -> 0 | AD87: =+SUM(CU87:CX87) -> 0 | AE87: =+SUM(CY87:DB87) -> 0 | AI87: =+'QTR Raw'!C21 -> 0 | AJ87: =+'QTR Raw'!D21 -> 0 | AK87: =+'QTR Raw'!E21 -> 0 | AL87: =+'QTR Raw'!F21 -> 0 | AM87: =+'QTR Raw'!G21 -> 0 | AN87: =+'QTR Raw'!H21 -> 0 | AO87: =+'QTR Raw'!I21 -> 0 | AP87: =+'QTR Raw'!J21 -> 0 | ... CL87: =+'QTR Raw'!BF21 -> 0 | DF87: 600.2
A88: Employee Cost | B88: ='Annual Raw'!C14 -> 4.1956 | C88: ='Annual Raw'!D14 -> 3.6184 | D88: ='Annual Raw'!E14 -> 4.1629 | E88: ='Annual Raw'!F14 -> 4.8744 | F88: ='Annual Raw'!G14 -> 5.0217 | G88: ='Annual Raw'!H14 -> 7.4762 | H88: ='Annual Raw'!I14 -> 8.0661 | I88: ='Annual Raw'!J14 -> 8.3048 | ... AA88: ='Annual Raw'!AB14 -> 1281.8 | AB88: =+SUM(CM88:CP88) -> 1695.1584 | AC88: =+SUM(CQ88:CT88) -> 1813.8195 | AD88: =+SUM(CU88:CX88) -> 1940.7869 | AE88: =+SUM(CY88:DB88) -> 2076.6419 | AI88: ='QTR Raw'!C16 -> 3.281 | AJ88: ='QTR Raw'!D16 -> 3.231 | AK88: ='QTR Raw'!E16 -> 4.403 | AL88: ='QTR Raw'!F16 -> 4.234 | AM88: ='QTR Raw'!G16 -> 3.719 | AN88: ='QTR Raw'!H16 -> 3.837 | AO88: ='QTR Raw'!I16 -> 3.664 | AP88: ='QTR Raw'!J16 -> 3.954 | ... CL88: ='QTR Raw'!BF16 -> 449.77 | CM88: 380 | CN88: =CJ88*107% -> 393.5888 | CO88: =CK88*107% -> 440.3157 | CP88: =CL88*107% -> 481.2539 | CQ88: =CM88*107% -> 406.6 | CR88: =CN88*107% -> 421.14002 | CS88: =CO88*107% -> 471.1378 | CT88: =CP88*107% -> 514.94167 | CU88: =CQ88*107% -> 435.062 | ... DB88: =CX88*107% -> 589.55672 | DF88: 1281.8
A89: Selling and Distribution Expenses | B89: ='Annual Raw'!C18 -> 3.3503 | C89: ='Annual Raw'!D18 -> 5.5152 | D89: ='Annual Raw'!E18 -> 11.2133 | E89: ='Annual Raw'!F18 -> 10.3751 | F89: ='Annual Raw'!G18 -> 13.8767 | G89: ='Annual Raw'!H18 -> 20.5504 | H89: ='Annual Raw'!I18 -> 14.7865 | I89: ='Annual Raw'!J18 -> 4.9219 | ... W89: ='Annual Raw'!X18 -> 80.24 | X89: =('Annual Raw'!Y18)-706.66 -> 110.68 | Y89: =('Annual Raw'!Z18)-1495.52 -> 237.85 | Z89: =('Annual Raw'!AA18)-1494.99 -> 123.8 | AA89: =('Annual Raw'!AB18)-1494.99 -> 559.68 | AB89: =+SUM(CM89:CP89) -> 0 | AC89: =+SUM(CQ89:CT89) -> 0 | AD89: =+SUM(CU89:CX89) -> 0 | AE89: =+SUM(CY89:DB89) -> 0 | AI89: ='QTR Raw'!C18 -> 0 | AJ89: ='QTR Raw'!D18 -> 0 | AK89: ='QTR Raw'!E18 -> 0 | AL89: ='QTR Raw'!F18 -> 0 | AM89: ='QTR Raw'!G18 -> 0 | AN89: ='QTR Raw'!H18 -> 0 | AO89: ='QTR Raw'!I18 -> 0 | AP89: ='QTR Raw'!J18 -> 0 | ... CL89: ='QTR Raw'!BF18 -> 0 | DF89: 559.68
A90: Other Manufacturing Expenses | B90: ='Annual Raw'!C15+'Annual Raw'!C16 -> 4.36 | C90: ='Annual Raw'!D15+'Annual Raw'!D16 -> 4.8002 | D90: ='Annual Raw'!E15+'Annual Raw'!E16 -> 6.796 | E90: ='Annual Raw'!F15+'Annual Raw'!F16 -> 6.7952 | F90: ='Annual Raw'!G15+'Annual Raw'!G16 -> 13.9955 | G90: ='Annual Raw'!H15+'Annual Raw'!H16 -> 13.1343 | H90: ='Annual Raw'!I15+'Annual Raw'!I16 -> 12.4647 | I90: ='Annual Raw'!J15+'Annual Raw'!J16 -> 14.8685 | ... W90: ='Annual Raw'!X15+'Annual Raw'!X16 -> 126.51 | X90: =(('Annual Raw'!Y15+'Annual Raw'!Y16)-372.06)-672.9 -> 72.97 | Y90: =(('Annual Raw'!Z15+'Annual Raw'!Z16)-750.2)-994 -> 124.22 | Z90: =(('Annual Raw'!AA15+'Annual Raw'!AA16)-854.13)-974.84 -> 95.5 | AA90: =(('Annual Raw'!AB15+'Annual Raw'!AB16)-854.13)-974.84 -> 2507.9 | AB90: =+SUM(CM90:CP90) -> 8879.437 | AC90: =+SUM(CQ90:CT90) -> 14780.061 | AD90: =+SUM(CU90:CX90) -> 16705.444 | AE90: =+SUM(CY90:DB90) -> 20663.156 | AI90: ='QTR Raw'!C14 -> 8.671 | AJ90: ='QTR Raw'!D14 -> 11.904 | AK90: ='QTR Raw'!E14 -> 8.394 | AL90: ='QTR Raw'!F14 -> 9.704 | AM90: ='QTR Raw'!G14 -> 8.294 | AN90: ='QTR Raw'!H14 -> 7.814 | AO90: ='QTR Raw'!I14 -> 7.919 | AP90: ='QTR Raw'!J14 -> 9.317 | ... CL90: ='QTR Raw'!BF14 -> 2651.79 | CM90: =+CM80-CM88-CM67 -> 2272.0945 | CN90: =+CN80-CN88-CN67 -> 1981.7761 | CO90: =+CO80-CO88-CO67 -> 2160.2938 | CP90: =+CP80-CP88-CP67 -> 2465.2727 | CQ90: =+CQ80-CQ88-CQ67 -> 3594.6072 | CR90: =+CR80-CR88-CR67 -> 3387.6119 | CS90: =+CS80-CS88-CS67 -> 3816.8296 | CT90: =+CT80-CT88-CT67 -> 3981.0124 | ... DB90: =+DB80-DB88-DB67 -> 5617.5152 | DF90: 2507.9
A91: General and Administration Expenses | B91: ='Annual Raw'!C17 -> 0.8587 | C91: ='Annual Raw'!D17 -> 1.5423 | D91: ='Annual Raw'!E17 -> 1.7327 | E91: ='Annual Raw'!F17 -> 2.0072 | F91: ='Annual Raw'!G17 -> 1.8207 | G91: ='Annual Raw'!H17 -> 2.4184 | H91: ='Annual Raw'!I17 -> 2.0555 | I91: ='Annual Raw'!J17 -> 3.8814 | ... AA91: ='Annual Raw'!AB17 -> 662.32 | AB91: =+SUM(CM91:CP91) -> 0 | AC91: =+SUM(CQ91:CT91) -> 0 | AD91: =+SUM(CU91:CX91) -> 0 | AE91: =+SUM(CY91:DB91) -> 0 | AI91: ='QTR Raw'!C17 -> 0 | AJ91: ='QTR Raw'!D17 -> 0 | AK91: ='QTR Raw'!E17 -> 0 | AL91: ='QTR Raw'!F17 -> 0 | AM91: ='QTR Raw'!G17 -> 0 | AN91: ='QTR Raw'!H17 -> 0 | AO91: ='QTR Raw'!I17 -> 0 | AP91: ='QTR Raw'!J17 -> 0 | ... CL91: ='QTR Raw'!BF17 -> 0 | DF91: 662.32
A92: Power & Fuel Cost | B92: ='Annual Raw'!C13 -> 5.8522 | C92: ='Annual Raw'!D13 -> 5.3826 | D92: ='Annual Raw'!E13 -> 5.5084 | E92: ='Annual Raw'!F13 -> 5.4717 | F92: ='Annual Raw'!G13 -> 5.7165 | G92: ='Annual Raw'!H13 -> 6.2518 | H92: ='Annual Raw'!I13 -> 10.4088 | I92: ='Annual Raw'!J13 -> 10.6621 | ... AA92: ='Annual Raw'!AB13 -> 206.01 | AB92: =+SUM(CM92:CP92) -> 0 | AC92: =+SUM(CQ92:CT92) -> 0 | AD92: =+SUM(CU92:CX92) -> 0 | AE92: =+SUM(CY92:DB92) -> 0 | AI92: ='QTR Raw'!C15 -> 0 | AJ92: ='QTR Raw'!D15 -> 0 | AK92: ='QTR Raw'!E15 -> 0 | AL92: ='QTR Raw'!F15 -> 0 | AM92: ='QTR Raw'!G15 -> 0 | AN92: ='QTR Raw'!H15 -> 0 | AO92: ='QTR Raw'!I15 -> 0 | AP92: ='QTR Raw'!J15 -> 0 | ... CL92: ='QTR Raw'!BF15 -> 0 | DF92: 206.01
A93: Total Cost | B93: =+SUM(B84:B92) -> 20.3837 | C93: =+SUM(C84:C92) -> 22.4261 | D93: =+SUM(D84:D92) -> 33.7249 | E93: =+SUM(E84:E92) -> 44.8678 | F93: =+SUM(F84:F92) -> 45.67 | G93: =+SUM(G84:G92) -> 51.2826 | H93: =+SUM(H84:H92) -> 50.1717 | I93: =+SUM(I84:I92) -> 44.2142 | ... AE93: =+SUM(AE84:AE92) -> 22739.798 | AI93: =+SUM(AI84:AI91) -> 11.952 | AJ93: =+SUM(AJ84:AJ91) -> 15.135 | AK93: =+SUM(AK84:AK91) -> 12.797 | AL93: =+SUM(AL84:AL91) -> 13.938 | AM93: =+SUM(AM84:AM91) -> 12.013 | AN93: =+SUM(AN84:AN91) -> 11.651 | AO93: =+SUM(AO84:AO91) -> 11.583 | AP93: =+SUM(AP84:AP91) -> 13.271 | ... DB93: =+SUM(DB84:DB91) -> 6207.072 | DF93: 9141.87
A94: Cost % | B94: =B93/B74 -> 0.19957097 | C94: =C93/C74 -> 0.21160052 | D94: =D93/D74 -> 0.22476149 | E94: =E93/E74 -> 0.25518703 | F94: =F93/F74 -> 0.17727867 | G94: =G93/G74 -> 0.20189205 | H94: =H93/H74 -> 0.14903644 | I94: =I93/I74 -> 0.11574459 | ... AE94: =AE93/AE74 -> 0.54709203 | AI94: =AI93/AI74 -> 0.048345212 | AJ94: =AJ93/AJ74 -> 0.12459046 | AK94: =AK93/AK74 -> 0.092544113 | AL94: =AL93/AL74 -> 0.05739818 | AM94: =AM93/AM74 -> 0.087296166 | AN94: =AN93/AN74 -> 0.107732 | AO94: =AO93/AO74 -> 0.090286222 | AP94: =AP93/AP74 -> 0.072309704 | ... DB94: =DB93/DB74 -> 0.54914891 | DF94: 0.53421646
A95: EBITDA | B95: =B80-B93 -> 6.4892 | C95: =C80-C93 -> 3.033 | D95: =D80-D93 -> 7.0852 | E95: =E80-E93 -> 6.5686 | F95: =F80-F93 -> 25.353 | G95: =G80-G93 -> -0.7033 | H95: =H80-H93 -> 1.4718 | I95: =I80-I93 -> 34.6908 | ... AE95: =AE80-AE93 -> 14745.929 | AI95: =AI80-AI93 -> 6.621 | AJ95: =AJ80-AJ93 -> -5.706 | AK95: =AK80-AK93 -> -0.642 | AL95: =AL80-AL93 -> 20.399 | AM95: =AM80-AM93 -> -9.532 | AN95: =AN80-AN93 -> -6.07 | AO95: =AO80-AO93 -> -1.697 | AP95: =AP80-AP93 -> -7.938 | ... DB95: =DB80-DB93 -> 3987.4686 | DF95: 6152.16
A96: EBITDA Margins | B96: =B95/B74 -> 0.063533899 | C96: =C95/C74 -> 0.028617743 | D96: =D95/D74 -> 0.047219714 | E96: =E95/E74 -> 0.03735912 | F96: =F95/F74 -> 0.098413536 | G96: =G95/G74 -> -0.0027687886 | H96: =H95/H74 -> 0.004372023 | I96: =I95/I74 -> 0.090814088 | ... AE96: =AE95/AE74 -> 0.35476922 | AI96: =AI95/AI74 -> 0.026781597 | AJ96: =AJ95/AJ74 -> -0.046971468 | AK96: =AK95/AK74 -> -0.0046427538 | AL96: =AL95/AL74 -> 0.084005271 | AM96: =AM95/AM74 -> -0.069267215 | AN96: =AN95/AN74 -> -0.056126789 | AO96: =AO95/AO74 -> -0.013227637 | AP96: =AP95/AP74 -> -0.043251784 | ... DB96: =DB95/DB74 -> 0.35277729 | DF96: 0.35950907
A97: EBITDA YOY% | C97: =+IF(B95<0,1-C95/B95,C95/B95-1) -> -0.53260803 | D97: =+IF(C95<0,1-D95/C95,D95/C95-1) -> 1.3360369 | E97: =+IF(D95<0,1-E95/D95,E95/D95-1) -> -0.07291255 | F97: =+IF(E95<0,1-F95/E95,F95/E95-1) -> 2.8597266 | G97: =+IF(F95<0,1-G95/F95,G95/F95-1) -> -1.0277403 | H97: =+IF(G95<0,1-H95/G95,H95/G95-1) -> 3.0927058 | I97: =+IF(H95<0,1-I95/H95,I95/H95-1) -> 22.570322 | J97: =+IF(I95<0,1-J95/I95,J95/I95-1) -> 0.46397316 | ... AE97: =+IF(AD95<0,1-AE95/AD95,AE95/AD95-1) -> 0.17637771 | AM97: =+IF(AI95<0,1-AM95/AI95,AM95/AI95-1) -> -2.4396617 | AN97: =+IF(AJ95<0,1-AN95/AJ95,AN95/AJ95-1) -> -0.063792499 | AO97: =+IF(AK95<0,1-AO95/AK95,AO95/AK95-1) -> -1.6433022 | AP97: =+IF(AL95<0,1-AP95/AL95,AP95/AL95-1) -> -1.3891367 | AQ97: =+IF(AM95<0,1-AQ95/AM95,AQ95/AM95-1) -> 0.065778431 | AR97: =+IF(AN95<0,1-AR95/AN95,AR95/AN95-1) -> -0.26375618 | AS97: =+IF(AO95<0,1-AS95/AO95,AS95/AO95-1) -> -2.8249853 | AT97: =+IF(AP95<0,1-AT95/AP95,AT95/AP95-1) -> 0.5835223 | ... DB97: =+IF(CX95<0,1-DB95/CX95,DB95/CX95-1) -> 0.16674993 | DF97: 2.1456942
A98: EBITDA QOQ% | AJ98: =+IF(AI95<0,1-AJ95/AI95,AJ95/AI95-1) -> -1.8618034 | AK98: =+IF(AJ95<0,1-AK95/AJ95,AK95/AJ95-1) -> 0.88748686 | AL98: =+IF(AK95<0,1-AL95/AK95,AL95/AK95-1) -> 32.774143 | AM98: =+IF(AL95<0,1-AM95/AL95,AM95/AL95-1) -> -1.4672778 | AN98: =+IF(AM95<0,1-AN95/AM95,AN95/AM95-1) -> 0.36319765 | AO98: =+IF(AN95<0,1-AO95/AN95,AO95/AN95-1) -> 0.72042834 | AP98: =+IF(AO95<0,1-AP95/AO95,AP95/AO95-1) -> -3.6776665 | AQ98: =+IF(AP95<0,1-AQ95/AP95,AQ95/AP95-1) -> -0.1218191 | ... CI98: =+IF(CH95<0,1-CI95/CH95,CI95/CH95-1) -> 2.0417082 | CJ98: =+IF(CI95>1,CJ95/CI95-1,1-CJ95/CI95) -> 0.31340108 | CK98: =+IF(CJ95>1,CK95/CJ95-1,1-CK95/CJ95) -> 0.68653712 | CL98: =+IF(CK95>1,CL95/CK95-1,1-CL95/CK95) -> 0.44684262 | CM98: =+IF(CL95>1,CM95/CL95-1,1-CM95/CL95) -> -0.095414026 | CN98: =+IF(CM95>1,CN95/CM95-1,1-CN95/CM95) -> -0.04540327 | CO98: =+IF(CN95>1,CO95/CN95-1,1-CO95/CN95) -> 0.014987205 | CP98: =+IF(CO95>1,CP95/CO95-1,1-CP95/CO95) -> 0.041669048 | CQ98: =+IF(CP95>1,CQ95/CP95-1,1-CQ95/CP95) -> 0.065338072 | ... DB98: =+IF(DA95>1,DB95/DA95-1,1-DB95/DA95) -> 0.053706313
A99: Depreciation | B99: ='Annual Raw'!C27 -> 15.932 | C99: ='Annual Raw'!D27 -> 15.9398 | D99: ='Annual Raw'!E27 -> 15.9014 | E99: ='Annual Raw'!F27 -> 15.9565 | F99: ='Annual Raw'!G27 -> 16.0655 | G99: ='Annual Raw'!H27 -> 15.8018 | H99: ='Annual Raw'!I27 -> 20.6364 | I99: ='Annual Raw'!J27 -> 21.239 | ... AA99: ='Annual Raw'!AB27 -> 607.16 | AB99: =+SUM(CM99:CP99) -> 730.63073 | AC99: =+SUM(CQ99:CT99) -> 784.9492 | AD99: =+SUM(CU99:CX99) -> 835.87383 | AE99: =+SUM(CY99:DB99) -> 883.61668 | AI99: ='QTR Raw'!C28 -> 6.566 | AJ99: ='QTR Raw'!D28 -> 6.658 | AK99: ='QTR Raw'!E28 -> 6.677 | AL99: ='QTR Raw'!F28 -> 6.617 | AM99: ='QTR Raw'!G28 -> 6.672 | AN99: ='QTR Raw'!H28 -> 6.747 | AO99: ='QTR Raw'!I28 -> 6.715 | AP99: ='QTR Raw'!J28 -> 6.595 | ... CL99: ='QTR Raw'!BF28 -> 224.35 | CM99: =CM100*CL200 -> 177.37136 | CN99: =CN100*CM200 -> 180.93342 | CO99: =CO100*CN200 -> 184.43848 | CP99: =CP100*CO200 -> 187.88747 | CQ99: =CQ100*CP200 -> 191.28127 | CR99: =CR100*CQ200 -> 194.62077 | CS99: =CS100*CR200 -> 197.90684 | CT99: =CT100*CS200 -> 201.14033 | ... DB99: =DB100*DA200 -> 225.21365 | DF99: 607.16
A100: Depreciation % of Net Block | B100: =+B99/B200 -> 0.069445231 | C100: =+C99/C200 -> 0.074792921 | D100: =+D99/D200 -> 0.080449343 | E100: =+E99/E200 -> 0.086855254 | F100: =+F99/F200 -> 0.095610846 | G100: =+G99/G200 -> 0.06772378 | H100: =+H99/H200 -> 0.092299559 | I100: =+I99/I200 -> 0.1076757 | ... AE100: =+AE99/AE200 -> 0.062005405 | AI100: =+AI99/AH200 -> #DIV/0! | AJ100: =+AJ99/AI200 -> #DIV/0! | AK100: =+AK99/AJ200 -> 0.021742599 | AL100: =+AL99/AK200 -> 0.021547219 | AM100: =+AM99/AL200 -> 0.022325357 | AN100: =+AN99/AM200 -> 0.022576317 | AO100: =+AO99/AN200 -> 0.023148547 | AP100: =+AP99/AO200 -> 0.022734872 | ... CL100: =+CL99/CK200 -> 0.035893129 | CM100: 0.016 | CN100: =+CM100 -> 0.016 | CO100: =+CN100 -> 0.016 | CP100: =+CO100 -> 0.016 | CQ100: =+CP100 -> 0.016 | CR100: =+CQ100 -> 0.016 | CS100: =+CR100 -> 0.016 | CT100: =+CS100 -> 0.016 | CU100: =+CT100 -> 0.016 | ... DB100: =+DA100 -> 0.016 | DF100: 0.052917219
A101: EBIT | B101: =B95-B99 -> -9.4428 | C101: =C95-C99 -> -12.9068 | D101: =D95-D99 -> -8.8162 | E101: =E95-E99 -> -9.3879 | F101: =F95-F99 -> 9.2875 | G101: =G95-G99 -> -16.5051 | H101: =H95-H99 -> -19.1646 | I101: =I95-I99 -> 13.4518 | ... AE101: =AE95-AE99 -> 13862.313 | AI101: =AI95-AI99 -> 0.055 | AJ101: =AJ95-AJ99 -> -12.364 | AK101: =AK95-AK99 -> -7.319 | AL101: =AL95-AL99 -> 13.782 | AM101: =AM95-AM99 -> -16.204 | AN101: =AN95-AN99 -> -12.817 | AO101: =AO95-AO99 -> -8.412 | AP101: =AP95-AP99 -> -14.533 | ... DB101: =DB95-DB99 -> 3762.2549 | DF101: 5545
A102: Other Income | B102: ='Annual Raw'!C23 -> 2.4842 | C102: ='Annual Raw'!D23 -> 1.4049 | D102: ='Annual Raw'!E23 -> 1.2411 | E102: ='Annual Raw'!F23 -> 1.6714 | F102: ='Annual Raw'!G23 -> 0.4606 | G102: ='Annual Raw'!H23 -> 1.681 | H102: ='Annual Raw'!I23 -> 0.9704 | I102: ='Annual Raw'!J23 -> 1.805 | ... AA102: ='Annual Raw'!AB23 -> 193.73 | AB102: =+SUM(CM102:CP102) -> 0 | AC102: =+SUM(CQ102:CT102) -> 0 | AD102: =+SUM(CU102:CX102) -> 0 | AE102: =+SUM(CY102:DB102) -> 0 | AI102: ='QTR Raw'!C23 -> 3.607 | AJ102: ='QTR Raw'!D23 -> 12.915 | AK102: ='QTR Raw'!E23 -> 2.38 | AL102: ='QTR Raw'!F23 -> -2.639 | AM102: ='QTR Raw'!G23 -> 5.21 | AN102: ='QTR Raw'!H23 -> 3.715 | AO102: ='QTR Raw'!I23 -> 4.171 | AP102: ='QTR Raw'!J23 -> 3.581 | ... CL102: ='QTR Raw'!BF23 -> 11.21 | DF102: 193.73
A103: Interest | B103: ='Annual Raw'!C25 -> 65.3599 | C103: ='Annual Raw'!D25 -> 74.8036 | D103: ='Annual Raw'!E25 -> 24.839 | E103: ='Annual Raw'!F25 -> 7.1648 | F103: ='Annual Raw'!G25 -> 4.1778 | G103: ='Annual Raw'!H25 -> 5.1316 | H103: ='Annual Raw'!I25 -> 12.3703 | I103: ='Annual Raw'!J25 -> 21.2317 | ... AA103: ='Annual Raw'!AB25 -> 522.36 | AB103: =+SUM(CM103:CP103) -> 163.75879 | AC103: =+SUM(CQ103:CT103) -> 298.7894 | AD103: =+SUM(CU103:CX103) -> 198.29023 | AE103: =+SUM(CY103:DB103) -> 79.355154 | AI103: ='QTR Raw'!C25 -> 2.127 | AJ103: ='QTR Raw'!D25 -> 1.897 | AK103: ='QTR Raw'!E25 -> 1.32 | AL103: ='QTR Raw'!F25 -> 3.156 | AM103: ='QTR Raw'!G25 -> 1.715 | AN103: ='QTR Raw'!H25 -> 1.703 | AO103: ='QTR Raw'!I25 -> 1.672 | AP103: ='QTR Raw'!J25 -> 2.068 | ... CL103: ='QTR Raw'!BF25 -> 167.56 | CM103: =CM104*CL234 -> 44.809722 | CN103: =CN104*CM234 -> 42.718091 | CO103: =CO104*CN234 -> 38.423872 | CP103: =CP104*CO234 -> 37.807104 | CQ103: =CQ104*CP234 -> 74.426206 | CR103: =CR104*CQ234 -> 81.734461 | CS103: =CS104*CR234 -> 72.858105 | CT103: =CT104*CS234 -> 69.770625 | ... DB103: =DB104*DA234 -> 8.0690972 | DF103: 522.36
A104: Interest % of Debt | B104: =+B103/B194 -> 0.16139909 | C104: =+C103/C194 -> 0.15620691 | D104: =+D103/D194 -> 0.048994942 | E104: =+E103/E194 -> 0.014750284 | F104: =+F103/F194 -> 0.01345949 | G104: =+G103/G194 -> 0.024392528 | H104: =+H103/H194 -> 0.064067963 | I104: =+I103/I194 -> 0.1571116 | ... AE104: =+AE103/AE194 -> 0.0038936938 | AI104: =(AI103-AI102)/AH234 -> #DIV/0! | AJ104: =(AJ103-AJ102)/AI234 -> #DIV/0! | AK104: =(AK103-AK102)/AJ234 -> -0.058843122 | AL104: =(AL103-AL102)/AK234 -> 0.17665192 | AM104: =(AM103-AM102)/AL234 -> -0.27454831 | AN104: =(AN103-AN102)/AM234 -> -0.020788552 | AO104: =(AO103-AO102)/AN234 -> -0.23813608 | AP104: =(AP103-AP102)/AO234 -> 0.32376985 | ... CL104: =(CL103-CL102)/CK234 -> 0.021559864 | CM104: 0.00255 | CN104: =+CM104 -> 0.00255 | CO104: =+CN104 -> 0.00255 | CP104: =+CO104 -> 0.00255 | CQ104: 0.005 | CR104: =+CQ104 -> 0.005 | CS104: =+CR104 -> 0.005 | CT104: =+CS104 -> 0.005 | CU104: =+CT104 -> 0.005 | CV104: =+CU104 -> 0.005 | CW104: =+CV104 -> 0.005 | CX104: =+CW104 -> 0.005 | CY104: =+CX104 -> 0.005 | ... DB104: =+DA104 -> 0.005 | DF104: 0.025630457
A105: PBT | B105: =B101+B102-B103 -> -72.3185 | C105: =C101+C102-C103 -> -86.3055 | D105: =D101+D102-D103 -> -32.4141 | E105: =E101+E102-E103 -> -14.8813 | F105: =F101+F102-F103 -> 5.5703 | G105: =G101+G102-G103 -> -19.9557 | H105: =H101+H102-H103 -> -30.5645 | I105: =I101+I102-I103 -> -5.9749 | ... AE105: =AE101+AE102-AE103 -> 13782.958 | AI105: =AI101+AI102-AI103 -> 1.535 | AJ105: =AJ101+AJ102-AJ103 -> -1.346 | AK105: =AK101+AK102-AK103 -> -6.259 | AL105: =AL101+AL102-AL103 -> 7.987 | AM105: =AM101+AM102-AM103 -> -12.709 | AN105: =AN101+AN102-AN103 -> -10.805 | AO105: =AO101+AO102-AO103 -> -5.913 | AP105: =AP101+AP102-AP103 -> -13.02 | ... DB105: =DB101+DB102-DB103 -> 3754.1858 | DF105: 5216.37
...

Sheet QTR Raw
A1: ='Annual Raw'!A1 -> 112455 | B1: X | C1: 201206 | D1: 201209 | E1: 201212 | F1: 201303 | G1: 201306 | H1: 201309 | I1: 201312 | J1: 201403 | K1: 201406 | L1: 201409 | M1: 201412 | N1: 201503 | O1: 201506 | P1: 201509 | Q1: 201512 | R1: 201603 | S1: 201606 | T1: 201609 | U1: 201612 | V1: 201703 | W1: 201706 | X1: 201709 | Y1: 201712 | Z1: 201803 | AA1: 201806 | AB1: 201809 | AC1: 201812 | AD1: 201903 | AE1: 201906 | AF1: 201909 | AG1: 201912 | AH1: 202003 | AI1: 202006 | AJ1: 202009 | AK1: 202012 | AL1: 202103 | AM1: 202106 | AN1: 202109 | AO1: 202112 | AP1: 202203 | AQ1: 202206 | AR1: 202209 | AS1: 202212 | AT1: 202303 | AU1: 202306 | AV1: 202309 | AW1: 202312 | AX1: 202403 | AY1: 202406 | AZ1: 202409 | BA1: 202412 | BB1: 202503 | BC1: 202506 | BD1: 202509 | BE1: 202512 | BF1: 202603 | BG1: 202606 | BH1: 202609 | BI1: 202612 | BJ1: 202703 | BK1: 202706 | BL1: 202709 | BM1: 202712 | BN1: 202803 | BO1: 202806 | BP1: 202809 | BQ1: 202812 | BR1: 202903 | BS1: 202906 | BT1: 202909 | BU1: 202912 | BV1: 203003
A3: Field Description | B3: Field Name
A4: Company Name | B4: CD_COMPNAME | C4: =_xll.EQNXTDZ(A1,B4,C1) -> Lloyds Metals & Energy Ltd.
A5: Date End | B5: QTR_DATE_END | C5: =_xll.EQNXTDZ($A$1,$B5,C$1,$B$1) -> 201206 | D5: =_xll.EQNXTDZ($A$1,$B5,D$1,$B$1) -> 201209 | E5: =_xll.EQNXTDZ($A$1,$B5,E$1,$B$1) -> 201212 | F5: =_xll.EQNXTDZ($A$1,$B5,F$1,$B$1) -> 201303 | G5: =_xll.EQNXTDZ($A$1,$B5,G$1,$B$1) -> 201306 | H5: =_xll.EQNXTDZ($A$1,$B5,H$1,$B$1) -> 201309 | I5: =_xll.EQNXTDZ($A$1,$B5,I$1,$B$1) -> 201312 | J5: =_xll.EQNXTDZ($A$1,$B5,J$1,$B$1) -> 201403 | ... BV5: =_xll.EQNXTDZ($A$1,$B5,BV$1,$B$1) -> 0
A6: Gross Sales | B6: QTR_GROSS_SALE | C6: =_xll.EQNXTDZ($A$1,$B6,C$1,$B$1) -> 260.709 | D6: =_xll.EQNXTDZ($A$1,$B6,D$1,$B$1) -> 130.556 | E6: =_xll.EQNXTDZ($A$1,$B6,E$1,$B$1) -> 147.374 | F6: =_xll.EQNXTDZ($A$1,$B6,F$1,$B$1) -> 253.529 | G6: =_xll.EQNXTDZ($A$1,$B6,G$1,$B$1) -> 147.415 | H6: =_xll.EQNXTDZ($A$1,$B6,H$1,$B$1) -> 115.678 | I6: =_xll.EQNXTDZ($A$1,$B6,I$1,$B$1) -> 139.526 | J6: =_xll.EQNXTDZ($A$1,$B6,J$1,$B$1) -> 197.025 | ... BV6: =_xll.EQNXTDZ($A$1,$B6,BV$1,$B$1) -> 0
A7: Less: Excise Duty | B7: QTR_EXCISE_DUTY | C7: =_xll.EQNXTDZ($A$1,$B7,C$1,$B$1) -> 13.487 | D7: =_xll.EQNXTDZ($A$1,$B7,D$1,$B$1) -> 9.078 | E7: =_xll.EQNXTDZ($A$1,$B7,E$1,$B$1) -> 9.094 | F7: =_xll.EQNXTDZ($A$1,$B7,F$1,$B$1) -> 10.699 | G7: =_xll.EQNXTDZ($A$1,$B7,G$1,$B$1) -> 9.803 | H7: =_xll.EQNXTDZ($A$1,$B7,H$1,$B$1) -> 7.53 | I7: =_xll.EQNXTDZ($A$1,$B7,I$1,$B$1) -> 11.234 | J7: =_xll.EQNXTDZ($A$1,$B7,J$1,$B$1) -> 13.495 | ... BV7: =_xll.EQNXTDZ($A$1,$B7,BV$1,$B$1) -> 0
A8: Other operating income | B8: QTR_JOB_WORKS | C8: =_xll.EQNXTDZ($A$1,$B8,C$1,$B$1) -> 0 | D8: =_xll.EQNXTDZ($A$1,$B8,D$1,$B$1) -> 0 | E8: =_xll.EQNXTDZ($A$1,$B8,E$1,$B$1) -> 0 | F8: =_xll.EQNXTDZ($A$1,$B8,F$1,$B$1) -> 0 | G8: =_xll.EQNXTDZ($A$1,$B8,G$1,$B$1) -> 0 | H8: =_xll.EQNXTDZ($A$1,$B8,H$1,$B$1) -> 0 | I8: =_xll.EQNXTDZ($A$1,$B8,I$1,$B$1) -> 0 | J8: =_xll.EQNXTDZ($A$1,$B8,J$1,$B$1) -> 0 | ... BV8: =_xll.EQNXTDZ($A$1,$B8,BV$1,$B$1) -> 0
A9: Net Sales & Other Operating Income | B9: QTR_NET_SALES | C9: =_xll.EQNXTDZ($A$1,$B9,C$1,$B$1) -> 247.222 | D9: =_xll.EQNXTDZ($A$1,$B9,D$1,$B$1) -> 121.477 | E9: =_xll.EQNXTDZ($A$1,$B9,E$1,$B$1) -> 138.28 | F9: =_xll.EQNXTDZ($A$1,$B9,F$1,$B$1) -> 242.83 | G9: =_xll.EQNXTDZ($A$1,$B9,G$1,$B$1) -> 137.612 | H9: =_xll.EQNXTDZ($A$1,$B9,H$1,$B$1) -> 108.149 | I9: =_xll.EQNXTDZ($A$1,$B9,I$1,$B$1) -> 128.292 | J9: =_xll.EQNXTDZ($A$1,$B9,J$1,$B$1) -> 183.53 | ... BV9: =_xll.EQNXTDZ($A$1,$B9,BV$1,$B$1) -> 0
A10: (Increase) / Decrease In Stocks | B10: QTR_INC_DEC_INVENTORY | C10: =_xll.EQNXTDZ($A$1,$B10,C$1,$B$1) -> 1.27 | D10: =_xll.EQNXTDZ($A$1,$B10,D$1,$B$1) -> -0.906 | E10: =_xll.EQNXTDZ($A$1,$B10,E$1,$B$1) -> -3.725 | F10: =_xll.EQNXTDZ($A$1,$B10,F$1,$B$1) -> 3.858 | G10: =_xll.EQNXTDZ($A$1,$B10,G$1,$B$1) -> 2.473 | H10: =_xll.EQNXTDZ($A$1,$B10,H$1,$B$1) -> -1.462 | I10: =_xll.EQNXTDZ($A$1,$B10,I$1,$B$1) -> 0.664 | J10: =_xll.EQNXTDZ($A$1,$B10,J$1,$B$1) -> -8.448 | ... BV10: =_xll.EQNXTDZ($A$1,$B10,BV$1,$B$1) -> 0
A11: Cost of Services & Raw Materials | B11: QTR_RAW_MATERIAL_COST | C11: =_xll.EQNXTDZ($A$1,$B11,C$1,$B$1) -> 100.856 | D11: =_xll.EQNXTDZ($A$1,$B11,D$1,$B$1) -> 76.447 | E11: =_xll.EQNXTDZ($A$1,$B11,E$1,$B$1) -> 83.288 | F11: =_xll.EQNXTDZ($A$1,$B11,F$1,$B$1) -> 93.1 | G11: =_xll.EQNXTDZ($A$1,$B11,G$1,$B$1) -> 87.046 | H11: =_xll.EQNXTDZ($A$1,$B11,H$1,$B$1) -> 62.196 | I11: =_xll.EQNXTDZ($A$1,$B11,I$1,$B$1) -> 86.789 | J11: =_xll.EQNXTDZ($A$1,$B11,J$1,$B$1) -> 108.294 | ... BV11: =_xll.EQNXTDZ($A$1,$B11,BV$1,$B$1) -> 0
A12: Purchase of Finished Goods | B12: QTR_PURCHASE_FIN_GOOD | C12: =_xll.EQNXTDZ($A$1,$B12,C$1,$B$1) -> 126.523 | D12: =_xll.EQNXTDZ($A$1,$B12,D$1,$B$1) -> 36.508 | E12: =_xll.EQNXTDZ($A$1,$B12,E$1,$B$1) -> 46.562 | F12: =_xll.EQNXTDZ($A$1,$B12,F$1,$B$1) -> 111.535 | G12: =_xll.EQNXTDZ($A$1,$B12,G$1,$B$1) -> 45.612 | H12: =_xll.EQNXTDZ($A$1,$B12,H$1,$B$1) -> 41.833 | I12: =_xll.EQNXTDZ($A$1,$B12,I$1,$B$1) -> 30.953 | J12: =_xll.EQNXTDZ($A$1,$B12,J$1,$B$1) -> 78.351 | ... BV12: =_xll.EQNXTDZ($A$1,$B12,BV$1,$B$1) -> 0
A13: Excise Duty | B13: QTR_EXCISE | C13: =_xll.EQNXTDZ($A$1,$B13,C$1,$B$1) -> 0 | D13: =_xll.EQNXTDZ($A$1,$B13,D$1,$B$1) -> 0 | E13: =_xll.EQNXTDZ($A$1,$B13,E$1,$B$1) -> 0 | F13: =_xll.EQNXTDZ($A$1,$B13,F$1,$B$1) -> 0 | G13: =_xll.EQNXTDZ($A$1,$B13,G$1,$B$1) -> 0 | H13: =_xll.EQNXTDZ($A$1,$B13,H$1,$B$1) -> 0 | I13: =_xll.EQNXTDZ($A$1,$B13,I$1,$B$1) -> 0 | J13: =_xll.EQNXTDZ($A$1,$B13,J$1,$B$1) -> 0 | ... BV13: =_xll.EQNXTDZ($A$1,$B13,BV$1,$B$1) -> 0
A14: Operating & Manufacturing Expenses | B14: QTR_MFG_EXPS | C14: =_xll.EQNXTDZ($A$1,$B14,C$1,$B$1) -> 8.671 | D14: =_xll.EQNXTDZ($A$1,$B14,D$1,$B$1) -> 11.904 | E14: =_xll.EQNXTDZ($A$1,$B14,E$1,$B$1) -> 8.394 | F14: =_xll.EQNXTDZ($A$1,$B14,F$1,$B$1) -> 9.704 | G14: =_xll.EQNXTDZ($A$1,$B14,G$1,$B$1) -> 8.294 | H14: =_xll.EQNXTDZ($A$1,$B14,H$1,$B$1) -> 7.814 | I14: =_xll.EQNXTDZ($A$1,$B14,I$1,$B$1) -> 7.919 | J14: =_xll.EQNXTDZ($A$1,$B14,J$1,$B$1) -> 9.317 | ... BV14: =_xll.EQNXTDZ($A$1,$B14,BV$1,$B$1) -> 0
A15: Electricity Power & Fuel Cost | B15: QTR_ELECTRICITY_POWER_FUEL | C15: =_xll.EQNXTDZ($A$1,$B15,C$1,$B$1) -> 0 | D15: =_xll.EQNXTDZ($A$1,$B15,D$1,$B$1) -> 0 | E15: =_xll.EQNXTDZ($A$1,$B15,E$1,$B$1) -> 0 | F15: =_xll.EQNXTDZ($A$1,$B15,F$1,$B$1) -> 0 | G15: =_xll.EQNXTDZ($A$1,$B15,G$1,$B$1) -> 0 | H15: =_xll.EQNXTDZ($A$1,$B15,H$1,$B$1) -> 0 | I15: =_xll.EQNXTDZ($A$1,$B15,I$1,$B$1) -> 0 | J15: =_xll.EQNXTDZ($A$1,$B15,J$1,$B$1) -> 0 | ... BV15: =_xll.EQNXTDZ($A$1,$B15,BV$1,$B$1) -> 0
A16: Employee Cost | B16: QTR_EXPLOYEE_COST | C16: =_xll.EQNXTDZ($A$1,$B16,C$1,$B$1) -> 3.281 | D16: =_xll.EQNXTDZ($A$1,$B16,D$1,$B$1) -> 3.231 | E16: =_xll.EQNXTDZ($A$1,$B16,E$1,$B$1) -> 4.403 | F16: =_xll.EQNXTDZ($A$1,$B16,F$1,$B$1) -> 4.234 | G16: =_xll.EQNXTDZ($A$1,$B16,G$1,$B$1) -> 3.719 | H16: =_xll.EQNXTDZ($A$1,$B16,H$1,$B$1) -> 3.837 | I16: =_xll.EQNXTDZ($A$1,$B16,I$1,$B$1) -> 3.664 | J16: =_xll.EQNXTDZ($A$1,$B16,J$1,$B$1) -> 3.954 | ... BV16: =_xll.EQNXTDZ($A$1,$B16,BV$1,$B$1) -> 0
... A42: Consolidated PAT(after extra items) | B42: QTR_CONS_PAT_EXITM | C42: =_xll.EQNXTDZ($A$1,$B42,C$1,$B$1) -> 1.535 | D42: =_xll.EQNXTDZ($A$1,$B42,D$1,$B$1) -> -1.348 | E42: =_xll.EQNXTDZ($A$1,$B42,E$1,$B$1) -> -6.259 | F42: =_xll.EQNXTDZ($A$1,$B42,F$1,$B$1) -> 7.987 | G42: =_xll.EQNXTDZ($A$1,$B42,G$1,$B$1) -> -12.709 | H42: =_xll.EQNXTDZ($A$1,$B42,H$1,$B$1) -> -10.804 | I42: =_xll.EQNXTDZ($A$1,$B42,I$1,$B$1) -> -5.913 | J42: =_xll.EQNXTDZ($A$1,$B42,J$1,$B$1) -> -13.02 | ... BV42: =_xll.EQNXTDZ($A$1,$B42,BV$1,$B$1) -> 0
A44: Field Description | B44: Field Name
A45: Equity Capital | B45: QTR_EQUITY_CAP | C45: =_xll.EQNXTDZ($A$1,$B45,C$1,$B$1) -> 22.431 | D45: =_xll.EQNXTDZ($A$1,$B45,D$1,$B$1) -> 22.431 | E45: =_xll.EQNXTDZ($A$1,$B45,E$1,$B$1) -> 22.431 | F45: =_xll.EQNXTDZ($A$1,$B45,F$1,$B$1) -> 22.431 | G45: =_xll.EQNXTDZ($A$1,$B45,G$1,$B$1) -> 22.431 | H45: =_xll.EQNXTDZ($A$1,$B45,H$1,$B$1) -> 22.431 | I45: =_xll.EQNXTDZ($A$1,$B45,I$1,$B$1) -> 22.431 | J45: =_xll.EQNXTDZ($A$1,$B45,J$1,$B$1) -> 22.431 | ... BV45: =_xll.EQNXTDZ($A$1,$B45,BV$1,$B$1) -> 0
A46: Face Value | B46: QTR_FV | C46: =_xll.EQNXTDZ($A$1,$B46,C$1,$B$1) -> 2 | D46: =_xll.EQNXTDZ($A$1,$B46,D$1,$B$1) -> 2 | E46: =_xll.EQNXTDZ($A$1,$B46,E$1,$B$1) -> 2 | F46: =_xll.EQNXTDZ($A$1,$B46,F$1,$B$1) -> 2 | G46: =_xll.EQNXTDZ($A$1,$B46,G$1,$B$1) -> 2 | H46: =_xll.EQNXTDZ($A$1,$B46,H$1,$B$1) -> 2 | I46: =_xll.EQNXTDZ($A$1,$B46,I$1,$B$1) -> 2 | J46: =_xll.EQNXTDZ($A$1,$B46,J$1,$B$1) -> 2 | ... BV46: =_xll.EQNXTDZ($A$1,$B46,BV$1,$B$1) -> 0
A47: Month End | B47: BMONTH_MONTHEND | C47: =_xll.EQNXTDZ($A$1,$B47,C$5) -> 201206 | D47: =_xll.EQNXTDZ($A$1,$B47,D$5) -> 201209 | E47: =_xll.EQNXTDZ($A$1,$B47,E$5) -> 201212 | F47: =_xll.EQNXTDZ($A$1,$B47,F$5) -> 201303 | G47: =_xll.EQNXTDZ($A$1,$B47,G$5) -> 201306 | H47: =_xll.EQNXTDZ($A$1,$B47,H$5) -> 201309 | I47: =_xll.EQNXTDZ($A$1,$B47,I$5) -> 201312 | J47: =_xll.EQNXTDZ($A$1,$B47,J$5) -> 201403 | ... BV47: =_xll.EQNXTDZ($A$1,$B47,BV$5) -> 0
A48: Close | B48: BMONTH_CLOSE | C48: =_xll.EQNXTDZ($A$1,$B48,C$5) -> 9.975 | D48: =_xll.EQNXTDZ($A$1,$B48,D$5) -> 8.2 | E48: =_xll.EQNXTDZ($A$1,$B48,E$5) -> 8.65 | F48: =_xll.EQNXTDZ($A$1,$B48,F$5) -> 5.99 | G48: =_xll.EQNXTDZ($A$1,$B48,G$5) -> 4.455 | H48: =_xll.EQNXTDZ($A$1,$B48,H$5) -> 8.65 | I48: =_xll.EQNXTDZ($A$1,$B48,I$5) -> 4.96 | J48: =_xll.EQNXTDZ($A$1,$B48,J$5) -> 3.955 | ... BV48: =_xll.EQNXTDZ($A$1,$B48,BV$5) -> 0
A49: Total of Promoter and Promoter Group | B49: SHP_TPFTOTALPROMOTER | C49: =_xll.EQNXTDZ($A$1,$B49,C$5) -> 47.78 | D49: =_xll.EQNXTDZ($A$1,$B49,D$5) -> 51.15 | E49: =_xll.EQNXTDZ($A$1,$B49,E$5) -> 51.15 | F49: =_xll.EQNXTDZ($A$1,$B49,F$5) -> 51.15 | G49: =_xll.EQNXTDZ($A$1,$B49,G$5) -> 52.15 | H49: =_xll.EQNXTDZ($A$1,$B49,H$5) -> 52.38 | I49: =_xll.EQNXTDZ($A$1,$B49,I$5) -> 52.38 | J49: =_xll.EQNXTDZ($A$1,$B49,J$5) -> 53.09 | ... BV49: =_xll.EQNXTDZ($A$1,$B49,BV$5) -> 0
A50: Total of Promoter and Promoter Group Pledged | B50: SHP_PSHFTOTALPROMOTER | C50: =_xll.EQNXTDZ($A$1,$B50,C$5) -> 38.5 | D50: =_xll.EQNXTDZ($A$1,$B50,D$5) -> 35.97 | E50: =_xll.EQNXTDZ($A$1,$B50,E$5) -> 35.97 | F50: =_xll.EQNXTDZ($A$1,$B50,F$5) -> 35.97 | G50: =_xll.EQNXTDZ($A$1,$B50,G$5) -> 35.27 | H50: =_xll.EQNXTDZ($A$1,$B50,H$5) -> 35.12 | I50: =_xll.EQNXTDZ($A$1,$B50,I$5) -> 35.12 | J50: =_xll.EQNXTDZ($A$1,$B50,J$5) -> 34.65 | ... BV50: =_xll.EQNXTDZ($A$1,$B50,BV$5) -> 0
A54: Field Description | B54: Field Name | C54: =_xll.EQNXTDZ($A$1,$B54,C$5) -> 0 | D54: =_xll.EQNXTDZ($A$1,$B54,D$5) -> 0 | E54: =_xll.EQNXTDZ($A$1,$B54,E$5) -> 0 | F54: =_xll.EQNXTDZ($A$1,$B54,F$5) -> 0 | G54: =_xll.EQNXTDZ($A$1,$B54,G$5) -> 0 | H54: =_xll.EQNXTDZ($A$1,$B54,H$5) -> 0 | I54: =_xll.EQNXTDZ($A$1,$B54,I$5) -> 0 | J54: =_xll.EQNXTDZ($A$1,$B54,J$5) -> 0 | ... BV54: =_xll.EQNXTDZ($A$1,$B54,BV$5) -> 0
A55: Year End | B55: QTRB_DATE_END | C55: =_xll.EQNXTDZ($A$1,$B55,C$5,$B$1) -> 0 | D55: =_xll.EQNXTDZ($A$1,$B55,D$5,$B$1) -> 201209 | E55: =_xll.EQNXTDZ($A$1,$B55,E$5,$B$1) -> 0 | F55: =_xll.EQNXTDZ($A$1,$B55,F$5,$B$1) -> 201303 | G55: =_xll.EQNXTDZ($A$1,$B55,G$5,$B$1) -> 0 | H55: =_xll.EQNXTDZ($A$1,$B55,H$5,$B$1) -> 201309 | I55: =_xll.EQNXTDZ($A$1,$B55,I$5,$B$1) -> 0 | J55: =_xll.EQNXTDZ($A$1,$B55,J$5,$B$1) -> 201403 | ... BV55: =_xll.EQNXTDZ($A$1,$B55,BV$5,$B$1) -> 0
A56: Share Capital | B56: QTRB_SHARE_CAPITAL | C56: =_xll.EQNXTDZ($A$1,$B56,C$5,$B$1) -> 0 | D56: =_xll.EQNXTDZ($A$1,$B56,D$5,$B$1) -> 22.431 | E56: =_xll.EQNXTDZ($A$1,$B56,E$5,$B$1) -> 0 | F56: =_xll.EQNXTDZ($A$1,$B56,F$5,$B$1) -> 22.431 | G56: =_xll.EQNXTDZ($A$1,$B56,G$5,$B$1) -> 0 | H56: =_xll.EQNXTDZ($A$1,$B56,H$5,$B$1) -> 22.431 | I56: =_xll.EQNXTDZ($A$1,$B56,I$5,$B$1) -> 0 | J56: =_xll.EQNXTDZ($A$1,$B56,J$5,$B$1) -> 22.431 | ... BV56: =_xll.EQNXTDZ($A$1,$B56,BV$5,$B$1) -> 0
A57: Share Warrants & outstandings | B57: QTRB_SHAREWARNDOUT | C57: =_xll.EQNXTDZ($A$1,$B57,C$5,$B$1) -> 0 | D57: =_xll.EQNXTDZ($A$1,$B57,D$5,$B$1) -> 0 | E57: =_xll.EQNXTDZ($A$1,$B57,E$5,$B$1) -> 0 | F57: =_xll.EQNXTDZ($A$1,$B57,F$5,$B$1) -> 0 | G57: =_xll.EQNXTDZ($A$1,$B57,G$5,$B$1) -> 0 | H57: =_xll.EQNXTDZ($A$1,$B57,H$5,$B$1) -> 0 | I57: =_xll.EQNXTDZ($A$1,$B57,I$5,$B$1) -> 0 | J57: =_xll.EQNXTDZ($A$1,$B57,J$5,$B$1) -> 0 | ... BV57: =_xll.EQNXTDZ($A$1,$B57,BV$5,$B$1) -> 0
A58: Reserves & Surplus | B58: QTRB_RESERVE | C58: =_xll.EQNXTDZ($A$1,$B58,C$5,$B$1) -> 0 | D58: =_xll.EQNXTDZ($A$1,$B58,D$5,$B$1) -> 100.69 | E58: =_xll.EQNXTDZ($A$1,$B58,E$5,$B$1) -> 0 | F58: =_xll.EQNXTDZ($A$1,$B58,F$5,$B$1) -> 102.418 | G58: =_xll.EQNXTDZ($A$1,$B58,G$5,$B$1) -> 0 | H58: =_xll.EQNXTDZ($A$1,$B58,H$5,$B$1) -> 78.906 | I58: =_xll.EQNXTDZ($A$1,$B58,I$5,$B$1) -> 0 | J58: =_xll.EQNXTDZ($A$1,$B58,J$5,$B$1) -> 59.973 | ... BV58: =_xll.EQNXTDZ($A$1,$B58,BV$5,$B$1) -> 0
A59: Shareholder's Funds | B59: QTRB_SHAREHODERS_FUNDS | C59: =_xll.EQNXTDZ($A$1,$B59,C$5,$B$1) -> 0 | D59: =_xll.EQNXTDZ($A$1,$B59,D$5,$B$1) -> 123.121 | E59: =_xll.EQNXTDZ($A$1,$B59,E$5,$B$1) -> 0 | F59: =_xll.EQNXTDZ($A$1,$B59,F$5,$B$1) -> 124.849 | G59: =_xll.EQNXTDZ($A$1,$B59,G$5,$B$1) -> 0 | H59: =_xll.EQNXTDZ($A$1,$B59,H$5,$B$1) -> 101.337 | I59: =_xll.EQNXTDZ($A$1,$B59,I$5,$B$1) -> 0 | J59: =_xll.EQNXTDZ($A$1,$B59,J$5,$B$1) -> 82.404 | ... BV59: =_xll.EQNXTDZ($A$1,$B59,BV$5,$B$1) -> 0
A60: Minority Interest | B60: QTRB_MINORITY_INTEREST_BS | C60: =_xll.EQNXTDZ($A$1,$B60,C$5,$B$1) -> 0 | D60: =_xll.EQNXTDZ($A$1,$B60,D$5,$B$1) -> 0 | E60: =_xll.EQNXTDZ($A$1,$B60,E$5,$B$1) -> 0 | F60: =_xll.EQNXTDZ($A$1,$B60,F$5,$B$1) -> 0 | G60: =_xll.EQNXTDZ($A$1,$B60,G$5,$B$1) -> 0 | H60: =_xll.EQNXTDZ($A$1,$B60,H$5,$B$1) -> 0 | I60: =_xll.EQNXTDZ($A$1,$B60,I$5,$B$1) -> 0 | J60: =_xll.EQNXTDZ($A$1,$B60,J$5,$B$1) -> 0 | ... BV60: =_xll.EQNXTDZ($A$1,$B60,BV$5,$B$1) -> 0
A61: Long Term Borrowings | B61: QTRB_TOTAL_DEBTS | C61: =_xll.EQNXTDZ($A$1,$B61,C$5,$B$1) -> 0 | D61: =_xll.EQNXTDZ($A$1,$B61,D$5,$B$1) -> 26.697 | E61: =_xll.EQNXTDZ($A$1,$B61,E$5,$B$1) -> 0 | F61: =_xll.EQNXTDZ($A$1,$B61,F$5,$B$1) -> 20.585 | G61: =_xll.EQNXTDZ($A$1,$B61,G$5,$B$1) -> 0 | H61: =_xll.EQNXTDZ($A$1,$B61,H$5,$B$1) -> 18.124 | I61: =_xll.EQNXTDZ($A$1,$B61,I$5,$B$1) -> 0 | J61: =_xll.EQNXTDZ($A$1,$B61,J$5,$B$1) -> 15.663 | ... BV61: =_xll.EQNXTDZ($A$1,$B61,BV$5,$B$1) -> 0
A62: Secured Loans | B62: QTRB_SECURED_LOANS | C62: =_xll.EQNXTDZ($A$1,$B62,C$5,$B$1) -> 0 | D62: =_xll.EQNXTDZ($A$1,$B62,D$5,$B$1) -> 0 | E62: =_xll.EQNXTDZ($A$1,$B62,E$5,$B$1) -> 0 | F62: =_xll.EQNXTDZ($A$1,$B62,F$5,$B$1) -> 0 | G62: =_xll.EQNXTDZ($A$1,$B62,G$5,$B$1) -> 0 | H62: =_xll.EQNXTDZ($A$1,$B62,H$5,$B$1) -> 0 | I62: =_xll.EQNXTDZ($A$1,$B62,I$5,$B$1) -> 0 | J62: =_xll.EQNXTDZ($A$1,$B62,J$5,$B$1) -> 0 | ... BV62: =_xll.EQNXTDZ($A$1,$B62,BV$5,$B$1) -> 0
A63: Unsecured Loans | B63: QTRB_UNSECURED_LOANS_NF | C63: =_xll.EQNXTDZ($A$1,$B63,C$5,$B$1) -> 0 | D63: =_xll.EQNXTDZ($A$1,$B63,D$5,$B$1) -> 26.697 | E63: =_xll.EQNXTDZ($A$1,$B63,E$5,$B$1) -> 0 | F63: =_xll.EQNXTDZ($A$1,$B63,F$5,$B$1) -> 20.585 | G63: =_xll.EQNXTDZ($A$1,$B63,G$5,$B$1) -> 0 | H63: =_xll.EQNXTDZ($A$1,$B63,H$5,$B$1) -> 18.124 | I63: =_xll.EQNXTDZ($A$1,$B63,I$5,$B$1) -> 0 | J63: =_xll.EQNXTDZ($A$1,$B63,J$5,$B$1) -> 15.663 | ... BV63: =_xll.EQNXTDZ($A$1,$B63,BV$5,$B$1) -> 0
A64: Other Long Term Liabilities | B64: QTRB_OTHER_LT_LIABILITIES | C64: =_xll.EQNXTDZ($A$1,$B64,C$5,$B$1) -> 0 | D64: =_xll.EQNXTDZ($A$1,$B64,D$5,$B$1) -> 0 | E64: =_xll.EQNXTDZ($A$1,$B64,E$5,$B$1) -> 0 | F64: =_xll.EQNXTDZ($A$1,$B64,F$5,$B$1) -> 0 | G64: =_xll.EQNXTDZ($A$1,$B64,G$5,$B$1) -> 0 | H64: =_xll.EQNXTDZ($A$1,$B64,H$5,$B$1) -> 0 | I64: =_xll.EQNXTDZ($A$1,$B64,I$5,$B$1) -> 0 | J64: =_xll.EQNXTDZ($A$1,$B64,J$5,$B$1) -> 158.995 | ... BV64: =_xll.EQNXTDZ($A$1,$B64,BV$5,$B$1) -> 0
A65: Long Term Trade Payables | B65: QTRB_LT_TRADE_PAYABLE | C65: =_xll.EQNXTDZ($A$1,$B65,C$5,$B$1) -> 0 | D65: =_xll.EQNXTDZ($A$1,$B65,D$5,$B$1) -> 0 | E65: =_xll.EQNXTDZ($A$1,$B65,E$5,$B$1) -> 0 | F65: =_xll.EQNXTDZ($A$1,$B65,F$5,$B$1) -> 0 | G65: =_xll.EQNXTDZ($A$1,$B65,G$5,$B$1) -> 0 | H65: =_xll.EQNXTDZ($A$1,$B65,H$5,$B$1) -> 0 | I65: =_xll.EQNXTDZ($A$1,$B65,I$5,$B$1) -> 0 | J65: =_xll.EQNXTDZ($A$1,$B65,J$5,$B$1) -> 0 | ... BV65: =_xll.EQNXTDZ($A$1,$B65,BV$5,$B$1) -> 0
A66: Lont Term Provisions | B66: QTRB_LT_PROVISIONS | C66: =_xll.EQNXTDZ($A$1,$B66,C$5,$B$1) -> 0 | D66: =_xll.EQNXTDZ($A$1,$B66,D$5,$B$1) -> 3.209 | E66: =_xll.EQNXTDZ($A$1,$B66,E$5,$B$1) -> 0 | F66: =_xll.EQNXTDZ($A$1,$B66,F$5,$B$1) -> 3.189 | G66: =_xll.EQNXTDZ($A$1,$B66,G$5,$B$1) -> 0 | H66: =_xll.EQNXTDZ($A$1,$B66,H$5,$B$1) -> 3.325 | I66: =_xll.EQNXTDZ($A$1,$B66,I$5,$B$1) -> 0 | J66: =_xll.EQNXTDZ($A$1,$B66,J$5,$B$1) -> 3.551 | ... BV66: =_xll.EQNXTDZ($A$1,$B66,BV$5,$B$1) -> 0
... A97: Total Assets | B97: QTRB_TOTAL_APPLICATIONS | C97: =_xll.EQNXTDZ($A$1,$B97,C$5,$B$1) -> 0 | D97: =_xll.EQNXTDZ($A$1,$B97,D$5,$B$1) -> 153.027 | E97: =_xll.EQNXTDZ($A$1,$B97,E$5,$B$1) -> 0 | F97: =_xll.EQNXTDZ($A$1,$B97,F$5,$B$1) -> 148.623 | G97: =_xll.EQNXTDZ($A$1,$B97,G$5,$B$1) -> 0 | H97: =_xll.EQNXTDZ($A$1,$B97,H$5,$B$1) -> 122.786 | I97: =_xll.EQNXTDZ($A$1,$B97,I$5,$B$1) -> 0 | J97: =_xll.EQNXTDZ($A$1,$B97,J$5,$B$1) -> 260.613 | ... BV97: =_xll.EQNXTDZ($A$1,$B97,BV$5,$B$1) -> 0

Sheet Annual Raw
A1: 112455 | B1: X | C1: 200103 | D1: 200203 | E1: 200303 | F1: 200403 | G1: 200503 | H1: 200603 | I1: 200703 | J1: 200803 | K1: 200903 | L1: 201003 | M1: 201103 | N1: 201203 | O1: 201303 | P1: 201403 | Q1: 201503 | R1: 201603 | S1: 201703 | T1: 201803 | U1: 201903 | V1: 202003 | W1: 202103 | X1: 202203 | Y1: 202303 | Z1: 202403 | AA1: 202503 | AB1: 202603 | AC1: 202703 | AD1: 202803 | AE1: 202903 | AF1: 203003
A3: Field Description | B3: Field Name
A4: Company Name | B4: CD_COMPNAME | C4: =_xll.EQNXTDZ(A1,B4,"L") -> Lloyds Metals & Energy Ltd.
A5: Year End | B5: PL_YEAR_END | C5: =_xll.EQNXTDZ($A$1,$B5,C$1,$B$1) -> 200103 | D5: =_xll.EQNXTDZ($A$1,$B5,D$1,$B$1) -> 200203 | E5: =_xll.EQNXTDZ($A$1,$B5,E$1,$B$1) -> 200303 | F5: =_xll.EQNXTDZ($A$1,$B5,F$1,$B$1) -> 200403 | G5: =_xll.EQNXTDZ($A$1,$B5,G$1,$B$1) -> 200503 | H5: =_xll.EQNXTDZ($A$1,$B5,H$1,$B$1) -> 200603 | I5: =_xll.EQNXTDZ($A$1,$B5,I$1,$B$1) -> 200703 | J5: =_xll.EQNXTDZ($A$1,$B5,J$1,$B$1) -> 200803 | ... AF5: =_xll.EQNXTDZ($A$1,$B5,AF$1,$B$1) -> 0
A6: Sales Turnover | B6: PL_TOTAL_GROSS_SALES | C6: =_xll.EQNXTDZ($A$1,$B6,C$1,$B$1) -> 114.754 | D6: =_xll.EQNXTDZ($A$1,$B6,D$1,$B$1) -> 117.1898 | E6: =_xll.EQNXTDZ($A$1,$B6,E$1,$B$1) -> 169.7335 | F6: =_xll.EQNXTDZ($A$1,$B6,F$1,$B$1) -> 198.8392 | G6: =_xll.EQNXTDZ($A$1,$B6,G$1,$B$1) -> 281.165 | H6: =_xll.EQNXTDZ($A$1,$B6,H$1,$B$1) -> 295.0468 | I6: =_xll.EQNXTDZ($A$1,$B6,I$1,$B$1) -> 336.6405 | J6: =_xll.EQNXTDZ($A$1,$B6,J$1,$B$1) -> 381.998 | ... AF6: =_xll.EQNXTDZ($A$1,$B6,AF$1,$B$1) -> 0
A7: Less: Inter divisional transfers | B7: PL_INTER_DIV_TRF | C7: =_xll.EQNXTDZ($A$1,$B7,C$1,$B$1) -> 0 | D7: =_xll.EQNXTDZ($A$1,$B7,D$1,$B$1) -> 0 | E7: =_xll.EQNXTDZ($A$1,$B7,E$1,$B$1) -> 0 | F7: =_xll.EQNXTDZ($A$1,$B7,F$1,$B$1) -> 0 | G7: =_xll.EQNXTDZ($A$1,$B7,G$1,$B$1) -> 0 | H7: =_xll.EQNXTDZ($A$1,$B7,H$1,$B$1) -> 0 | I7: =_xll.EQNXTDZ($A$1,$B7,I$1,$B$1) -> 0 | J7: =_xll.EQNXTDZ($A$1,$B7,J$1,$B$1) -> 0 | ... AF7: =_xll.EQNXTDZ($A$1,$B7,AF$1,$B$1) -> 0
A8: Less: Sales Returns | B8: PL_SALES_RETURN | C8: =_xll.EQNXTDZ($A$1,$B8,C$1,$B$1) -> 0 | D8: =_xll.EQNXTDZ($A$1,$B8,D$1,$B$1) -> 0 | E8: =_xll.EQNXTDZ($A$1,$B8,E$1,$B$1) -> 0 | F8: =_xll.EQNXTDZ($A$1,$B8,F$1,$B$1) -> 0 | G8: =_xll.EQNXTDZ($A$1,$B8,G$1,$B$1) -> 0 | H8: =_xll.EQNXTDZ($A$1,$B8,H$1,$B$1) -> 0 | I8: =_xll.EQNXTDZ($A$1,$B8,I$1,$B$1) -> 0 | J8: =_xll.EQNXTDZ($A$1,$B8,J$1,$B$1) -> 0 | ... AF8: =_xll.EQNXTDZ($A$1,$B8,AF$1,$B$1) -> 0
A9: Less: Excise | B9: PL_EXCISE | C9: =_xll.EQNXTDZ($A$1,$B9,C$1,$B$1) -> 12.6164 | D9: =_xll.EQNXTDZ($A$1,$B9,D$1,$B$1) -> 11.2066 | E9: =_xll.EQNXTDZ($A$1,$B9,E$1,$B$1) -> 19.686 | F9: =_xll.EQNXTDZ($A$1,$B9,F$1,$B$1) -> 23.016 | G9: =_xll.EQNXTDZ($A$1,$B9,G$1,$B$1) -> 23.548 | H9: =_xll.EQNXTDZ($A$1,$B9,H$1,$B$1) -> 41.0368 | I9: =_xll.EQNXTDZ($A$1,$B9,I$1,$B$1) -> 0 | J9: =_xll.EQNXTDZ($A$1,$B9,J$1,$B$1) -> 0 | ... AF9: =_xll.EQNXTDZ($A$1,$B9,AF$1,$B$1) -> 0
A10: Net Sales | B10: PL_NET_SALES | C10: =_xll.EQNXTDZ($A$1,$B10,C$1,$B$1) -> 102.1376 | D10: =_xll.EQNXTDZ($A$1,$B10,D$1,$B$1) -> 105.9832 | E10: =_xll.EQNXTDZ($A$1,$B10,E$1,$B$1) -> 150.0475 | F10: =_xll.EQNXTDZ($A$1,$B10,F$1,$B$1) -> 175.8232 | G10: =_xll.EQNXTDZ($A$1,$B10,G$1,$B$1) -> 257.617 | H10: =_xll.EQNXTDZ($A$1,$B10,H$1,$B$1) -> 254.01 | I10: =_xll.EQNXTDZ($A$1,$B10,I$1,$B$1) -> 336.6405 | J10: =_xll.EQNXTDZ($A$1,$B10,J$1,$B$1) -> 381.998 | ... AF10: =_xll.EQNXTDZ($A$1,$B10,AF$1,$B$1) -> 0
A11: Increase/Decrease in Stock | B11: PL_INC_DEC_INVENTORY | C11: =_xll.EQNXTDZ($A$1,$B11,C$1,$B$1) -> -0.876 | D11: =_xll.EQNXTDZ($A$1,$B11,D$1,$B$1) -> 0.8327 | E11: =_xll.EQNXTDZ($A$1,$B11,E$1,$B$1) -> -1.1713 | F11: =_xll.EQNXTDZ($A$1,$B11,F$1,$B$1) -> -4.0017 | G11: =_xll.EQNXTDZ($A$1,$B11,G$1,$B$1) -> 6.6035 | H11: =_xll.EQNXTDZ($A$1,$B11,H$1,$B$1) -> -21.5463 | I11: =_xll.EQNXTDZ($A$1,$B11,I$1,$B$1) -> 62.954 | J11: =_xll.EQNXTDZ($A$1,$B11,J$1,$B$1) -> 35.1021 | ... AF11: =_xll.EQNXTDZ($A$1,$B11,AF$1,$B$1) -> 0
A12: Raw Material Consumed | B12: PL_RAW_MATRS_CONSUMED | C12: =_xll.EQNXTDZ($A$1,$B12,C$1,$B$1) -> 76.1407 | D12: =_xll.EQNXTDZ($A$1,$B12,D$1,$B$1) -> 79.6914 | E12: =_xll.EQNXTDZ($A$1,$B12,E$1,$B$1) -> 110.4087 | F12: =_xll.EQNXTDZ($A$1,$B12,F$1,$B$1) -> 128.3885 | G12: =_xll.EQNXTDZ($A$1,$B12,G$1,$B$1) -> 179.9905 | H12: =_xll.EQNXTDZ($A$1,$B12,H$1,$B$1) -> 224.977 | I12: =_xll.EQNXTDZ($A$1,$B12,I$1,$B$1) -> 222.043 | J12: =_xll.EQNXTDZ($A$1,$B12,J$1,$B$1) -> 267.9909 | ... AF12: =_xll.EQNXTDZ($A$1,$B12,AF$1,$B$1) -> 0
A13: Power & Fuel Cost | B13: PL_POWER_FUEL | C13: =_xll.EQNXTDZ($A$1,$B13,C$1,$B$1) -> 5.8522 | D13: =_xll.EQNXTDZ($A$1,$B13,D$1,$B$1) -> 5.3826 | E13: =_xll.EQNXTDZ($A$1,$B13,E$1,$B$1) -> 5.5084 | F13: =_xll.EQNXTDZ($A$1,$B13,F$1,$B$1) -> 5.4717 | G13: =_xll.EQNXTDZ($A$1,$B13,G$1,$B$1) -> 5.7165 | H13: =_xll.EQNXTDZ($A$1,$B13,H$1,$B$1) -> 6.2518 | I13: =_xll.EQNXTDZ($A$1,$B13,I$1,$B$1) -> 10.4088 | J13: =_xll.EQNXTDZ($A$1,$B13,J$1,$B$1) -> 10.6621 | ... AF13: =_xll.EQNXTDZ($A$1,$B13,AF$1,$B$1) -> 0
A14: Employee Cost | B14: PL_EMPLOYEES | C14: =_xll.EQNXTDZ($A$1,$B14,C$1,$B$1) -> 4.1956 | D14: =_xll.EQNXTDZ($A$1,$B14,D$1,$B$1) -> 3.6184 | E14: =_xll.EQNXTDZ($A$1,$B14,E$1,$B$1) -> 4.1629 | F14: =_xll.EQNXTDZ($A$1,$B14,F$1,$B$1) -> 4.8744 | G14: =_xll.EQNXTDZ($A$1,$B14,G$1,$B$1) -> 5.0217 | H14: =_xll.EQNXTDZ($A$1,$B14,H$1,$B$1) -> 7.4762 | I14: =_xll.EQNXTDZ($A$1,$B14,I$1,$B$1) -> 8.0661 | J14: =_xll.EQNXTDZ($A$1,$B14,J$1,$B$1) -> 8.3048 | ... AF14: =_xll.EQNXTDZ($A$1,$B14,AF$1,$B$1) -> 0
A15: Operating & Manufacturing Expenses | B15: PL_GEN_OTHER_MFG_EXPS | C15: =_xll.EQNXTDZ($A$1,$B15,C$1,$B$1) -> 4.36 | D15: =_xll.EQNXTDZ($A$1,$B15,D$1,$B$1) -> 4.8002 | E15: =_xll.EQNXTDZ($A$1,$B15,E$1,$B$1) -> 6.796 | F15: =_xll.EQNXTDZ($A$1,$B15,F$1,$B$1) -> 6.7952 | G15: =_xll.EQNXTDZ($A$1,$B15,G$1,$B$1) -> 13.9955 | H15: =_xll.EQNXTDZ($A$1,$B15,H$1,$B$1) -> 13.1343 | I15: =_xll.EQNXTDZ($A$1,$B15,I$1,$B$1) -> 12.4647 | J15: =_xll.EQNXTDZ($A$1,$B15,J$1,$B$1) -> 14.8685 | ... AF15: =_xll.EQNXTDZ($A$1,$B15,AF$1,$B$1) -> 0
A16: Cost of Software development | B16: PL_COST_SW | C16: =_xll.EQNXTDZ($A$1,$B16,C$1,$B$1) -> 0 | D16: =_xll.EQNXTDZ($A$1,$B16,D$1,$B$1) -> 0 | E16: =_xll.EQNXTDZ($A$1,$B16,E$1,$B$1) -> 0 | F16: =_xll.EQNXTDZ($A$1,$B16,F$1,$B$1) -> 0 | G16: =_xll.EQNXTDZ($A$1,$B16,G$1,$B$1) -> 0 | H16: =_xll.EQNXTDZ($A$1,$B16,H$1,$B$1) -> 0 | I16: =_xll.EQNXTDZ($A$1,$B16,I$1,$B$1) -> 0 | J16: =_xll.EQNXTDZ($A$1,$B16,J$1,$B$1) -> 0 | ... AF16: =_xll.EQNXTDZ($A$1,$B16,AF$1,$B$1) -> 0
... A36: Profit After Tax from Discontinued Operations | B36: PL_PAT_DIS_OP | C36: =_xll.EQNXTDZ($A$1,$B36,C$1,$B$1) -> 0 | D36: =_xll.EQNXTDZ($A$1,$B36,D$1,$B$1) -> 0 | E36: =_xll.EQNXTDZ($A$1,$B36,E$1,$B$1) -> 0 | F36: =_xll.EQNXTDZ($A$1,$B36,F$1,$B$1) -> 0 | G36: =_xll.EQNXTDZ($A$1,$B36,G$1,$B$1) -> 0 | H36: =_xll.EQNXTDZ($A$1,$B36,H$1,$B$1) -> 0 | I36: =_xll.EQNXTDZ($A$1,$B36,I$1,$B$1) -> 0 | J36: =_xll.EQNXTDZ($A$1,$B36,J$1,$B$1) -> 0 | ... AF36: =_xll.EQNXTDZ($A$1,$B36,AF$1,$B$1) -> 0
A39: Field Description | B39: Field Name
A40: Year End | B40: BS_YEAR_END | C40: =_xll.EQNXTDZ($A$1,$B40,C$1,$B$1) -> 200103 | D40: =_xll.EQNXTDZ($A$1,$B40,D$1,$B$1) -> 200203 | E40: =_xll.EQNXTDZ($A$1,$B40,E$1,$B$1) -> 200303 | F40: =_xll.EQNXTDZ($A$1,$B40,F$1,$B$1) -> 200403 | G40: =_xll.EQNXTDZ($A$1,$B40,G$1,$B$1) -> 200503 | H40: =_xll.EQNXTDZ($A$1,$B40,H$1,$B$1) -> 200603 | I40: =_xll.EQNXTDZ($A$1,$B40,I$1,$B$1) -> 200703 | J40: =_xll.EQNXTDZ($A$1,$B40,J$1,$B$1) -> 200803 | ... AF40: =_xll.EQNXTDZ($A$1,$B40,AF$1,$B$1) -> 0
A41: Share Capital | B41: BS_SHARE_CAPITAL | C41: =_xll.EQNXTDZ($A$1,$B41,C$1,$B$1) -> 39.4305 | D41: =_xll.EQNXTDZ($A$1,$B41,D$1,$B$1) -> 39.4305 | E41: =_xll.EQNXTDZ($A$1,$B41,E$1,$B$1) -> 39.4305 | F41: =_xll.EQNXTDZ($A$1,$B41,F$1,$B$1) -> 39.4305 | G41: =_xll.EQNXTDZ($A$1,$B41,G$1,$B$1) -> 39.4305 | H41: =_xll.EQNXTDZ($A$1,$B41,H$1,$B$1) -> 39.4305 | I41: =_xll.EQNXTDZ($A$1,$B41,I$1,$B$1) -> 21.4305 | J41: =_xll.EQNXTDZ($A$1,$B41,J$1,$B$1) -> 22.4305 | ... AF41: =_xll.EQNXTDZ($A$1,$B41,AF$1,$B$1) -> 0
A42: Share Warrants & Outstandings | B42: BS_SHAREWROUTST | C42: =_xll.EQNXTDZ($A$1,$B42,C$1,$B$1) -> 0 | D42: =_xll.EQNXTDZ($A$1,$B42,D$1,$B$1) -> 0 | E42: =_xll.EQNXTDZ($A$1,$B42,E$1,$B$1) -> 0 | F42: =_xll.EQNXTDZ($A$1,$B42,F$1,$B$1) -> 0 | G42: =_xll.EQNXTDZ($A$1,$B42,G$1,$B$1) -> 0 | H42: =_xll.EQNXTDZ($A$1,$B42,H$1,$B$1) -> 0 | I42: =_xll.EQNXTDZ($A$1,$B42,I$1,$B$1) -> 0 | J42: =_xll.EQNXTDZ($A$1,$B42,J$1,$B$1) -> 0 | ... AF42: =_xll.EQNXTDZ($A$1,$B42,AF$1,$B$1) -> 0
A43: Total Reserves | B43: BS_RESERVE | C43: =_xll.EQNXTDZ($A$1,$B43,C$1,$B$1) -> -28.3366 | D43: =_xll.EQNXTDZ($A$1,$B43,D$1,$B$1) -> -114.6459 | E43: =_xll.EQNXTDZ($A$1,$B43,E$1,$B$1) -> -147.4108 | F43: =_xll.EQNXTDZ($A$1,$B43,F$1,$B$1) -> -148.2136 | G43: =_xll.EQNXTDZ($A$1,$B43,G$1,$B$1) -> -118.6306 | H43: =_xll.EQNXTDZ($A$1,$B43,H$1,$B$1) -> -53.9715 | I43: =_xll.EQNXTDZ($A$1,$B43,I$1,$B$1) -> -65.9696 | J43: =_xll.EQNXTDZ($A$1,$B43,J$1,$B$1) -> -24.0726 | ... AF43: =_xll.EQNXTDZ($A$1,$B43,AF$1,$B$1) -> 0
A44: Shareholder's Funds | B44: BS_SHAREHODERS_FUNDS | C44: =_xll.EQNXTDZ($A$1,$B44,C$1,$B$1) -> 11.0939 | D44: =_xll.EQNXTDZ($A$1,$B44,D$1,$B$1) -> -75.2154 | E44: =_xll.EQNXTDZ($A$1,$B44,E$1,$B$1) -> -107.9803 | F44: =_xll.EQNXTDZ($A$1,$B44,F$1,$B$1) -> -108.7831 | G44: =_xll.EQNXTDZ($A$1,$B44,G$1,$B$1) -> -79.2001 | H44: =_xll.EQNXTDZ($A$1,$B44,H$1,$B$1) -> -14.541 | I44: =_xll.EQNXTDZ($A$1,$B44,I$1,$B$1) -> -44.5391 | J44: =_xll.EQNXTDZ($A$1,$B44,J$1,$B$1) -> -1.6421 | ... AF44: =_xll.EQNXTDZ($A$1,$B44,AF$1,$B$1) -> 0
A45: Minority Interest | B45: BS_MINORITY_INTEREST | C45: =_xll.EQNXTDZ($A$1,$B45,C$1,$B$1) -> 0 | D45: =_xll.EQNXTDZ($A$1,$B45,D$1,$B$1) -> 0 | E45: =_xll.EQNXTDZ($A$1,$B45,E$1,$B$1) -> 0 | F45: =_xll.EQNXTDZ($A$1,$B45,F$1,$B$1) -> 0 | G45: =_xll.EQNXTDZ($A$1,$B45,G$1,$B$1) -> 0 | H45: =_xll.EQNXTDZ($A$1,$B45,H$1,$B$1) -> 0 | I45: =_xll.EQNXTDZ($A$1,$B45,I$1,$B$1) -> 0 | J45: =_xll.EQNXTDZ($A$1,$B45,J$1,$B$1) -> 0 | ... AF45: =_xll.EQNXTDZ($A$1,$B45,AF$1,$B$1) -> 0
A46: Long-Term Borrowings | B46: BS_LTRM_BORROWING | C46: =_xll.EQNXTDZ($A$1,$B46,C$1,$B$1) -> 0 | D46: =_xll.EQNXTDZ($A$1,$B46,D$1,$B$1) -> 0 | E46: =_xll.EQNXTDZ($A$1,$B46,E$1,$B$1) -> 0 | F46: =_xll.EQNXTDZ($A$1,$B46,F$1,$B$1) -> 0 | G46: =_xll.EQNXTDZ($A$1,$B46,G$1,$B$1) -> 0 | H46: =_xll.EQNXTDZ($A$1,$B46,H$1,$B$1) -> 0 | I46: =_xll.EQNXTDZ($A$1,$B46,I$1,$B$1) -> 0 | J46: =_xll.EQNXTDZ($A$1,$B46,J$1,$B$1) -> 0 | ... AF46: =_xll.EQNXTDZ($A$1,$B46,AF$1,$B$1) -> 0
A47: Secured Loans | B47: BS_SECURED_LOANS | C47: =_xll.EQNXTDZ($A$1,$B47,C$1,$B$1) -> 361.2153 | D47: =_xll.EQNXTDZ($A$1,$B47,D$1,$B$1) -> 454.9876 | E47: =_xll.EQNXTDZ($A$1,$B47,E$1,$B$1) -> 478.0315 | F47: =_xll.EQNXTDZ($A$1,$B47,F$1,$B$1) -> 458.1041 | G47: =_xll.EQNXTDZ($A$1,$B47,G$1,$B$1) -> 305.8907 | H47: =_xll.EQNXTDZ($A$1,$B47,H$1,$B$1) -> 205.8685 | I47: =_xll.EQNXTDZ($A$1,$B47,I$1,$B$1) -> 188.5858 | J47: =_xll.EQNXTDZ($A$1,$B47,J$1,$B$1) -> 124.3943 | ... AF47: =_xll.EQNXTDZ($A$1,$B47,AF$1,$B$1) -> 0
A48: Unsecured Loans | B48: BS_UNSECURED_LOANS_NF | C48: =_xll.EQNXTDZ($A$1,$B48,C$1,$B$1) -> 43.743 | D48: =_xll.EQNXTDZ($A$1,$B48,D$1,$B$1) -> 23.8875 | E48: =_xll.EQNXTDZ($A$1,$B48,E$1,$B$1) -> 28.9392 | F48: =_xll.EQNXTDZ($A$1,$B48,F$1,$B$1) -> 27.6357 | G48: =_xll.EQNXTDZ($A$1,$B48,G$1,$B$1) -> 4.5074 | H48: =_xll.EQNXTDZ($A$1,$B48,H$1,$B$1) -> 4.5074 | I48: =_xll.EQNXTDZ($A$1,$B48,I$1,$B$1) -> 4.4951 | J48: =_xll.EQNXTDZ($A$1,$B48,J$1,$B$1) -> 10.7434 | ... AF48: =_xll.EQNXTDZ($A$1,$B48,AF$1,$B$1) -> 0
A49: Deferred Tax Assets / Liabilities | B49: BS_NET_DEF_TAX_NF | C49: =_xll.EQNXTDZ($A$1,$B49,C$1,$B$1) -> 0 | D49: =_xll.EQNXTDZ($A$1,$B49,D$1,$B$1) -> 0 | E49: =_xll.EQNXTDZ($A$1,$B49,E$1,$B$1) -> 0 | F49: =_xll.EQNXTDZ($A$1,$B49,F$1,$B$1) -> 0 | G49: =_xll.EQNXTDZ($A$1,$B49,G$1,$B$1) -> 0 | H49: =_xll.EQNXTDZ($A$1,$B49,H$1,$B$1) -> 0 | I49: =_xll.EQNXTDZ($A$1,$B49,I$1,$B$1) -> 0 | J49: =_xll.EQNXTDZ($A$1,$B49,J$1,$B$1) -> 0 | ... AF49: =_xll.EQNXTDZ($A$1,$B49,AF$1,$B$1) -> 0
A50: Other Long Term Liabilities | B50: BS_OTH_LT_LIAB | C50: =_xll.EQNXTDZ($A$1,$B50,C$1,$B$1) -> 0 | D50: =_xll.EQNXTDZ($A$1,$B50,D$1,$B$1) -> 0 | E50: =_xll.EQNXTDZ($A$1,$B50,E$1,$B$1) -> 0 | F50: =_xll.EQNXTDZ($A$1,$B50,F$1,$B$1) -> 0 | G50: =_xll.EQNXTDZ($A$1,$B50,G$1,$B$1) -> 0 | H50: =_xll.EQNXTDZ($A$1,$B50,H$1,$B$1) -> 0 | I50: =_xll.EQNXTDZ($A$1,$B50,I$1,$B$1) -> 0 | J50: =_xll.EQNXTDZ($A$1,$B50,J$1,$B$1) -> 0 | ... AF50: =_xll.EQNXTDZ($A$1,$B50,AF$1,$B$1) -> 0
A51: Long Term Trade Payables | B51: BS_LT_TRADE_PAYABLES | C51: =_xll.EQNXTDZ($A$1,$B51,C$1,$B$1) -> 0 | D51: =_xll.EQNXTDZ($A$1,$B51,D$1,$B$1) -> 0 | E51: =_xll.EQNXTDZ($A$1,$B51,E$1,$B$1) -> 0 | F51: =_xll.EQNXTDZ($A$1,$B51,F$1,$B$1) -> 0 | G51: =_xll.EQNXTDZ($A$1,$B51,G$1,$B$1) -> 0 | H51: =_xll.EQNXTDZ($A$1,$B51,H$1,$B$1) -> 0 | I51: =_xll.EQNXTDZ($A$1,$B51,I$1,$B$1) -> 0 | J51: =_xll.EQNXTDZ($A$1,$B51,J$1,$B$1) -> 0 | ... AF51: =_xll.EQNXTDZ($A$1,$B51,AF$1,$B$1) -> 0
... A99: Estimated Capital Contracts Remaining | B99: BS_ESTIMATED_CAPITAL_CONTRACT | C99: =_xll.EQNXTDZ($A$1,$B99,C$1,$B$1) -> 25.2835 | D99: =_xll.EQNXTDZ($A$1,$B99,D$1,$B$1) -> 25.2835 | E99: =_xll.EQNXTDZ($A$1,$B99,E$1,$B$1) -> 16.7835 | F99: =_xll.EQNXTDZ($A$1,$B99,F$1,$B$1) -> 16.7835 | G99: =_xll.EQNXTDZ($A$1,$B99,G$1,$B$1) -> 0 | H99: =_xll.EQNXTDZ($A$1,$B99,H$1,$B$1) -> 0 | I99: =_xll.EQNXTDZ($A$1,$B99,I$1,$B$1) -> 0 | J99: =_xll.EQNXTDZ($A$1,$B99,J$1,$B$1) -> 0 | ... AF99: =_xll.EQNXTDZ($A$1,$B99,AF$1,$B$1) -> 0
A103: Field Description | B103: Field Name
A104: Equity Paid Up | B104: BS_EQUITY_PAIDUP | C104: =_xll.EQNXTDZ($A$1,$B104,C$1,$B$1) -> 16.2583 | D104: =_xll.EQNXTDZ($A$1,$B104,D$1,$B$1) -> 16.2583 | E104: =_xll.EQNXTDZ($A$1,$B104,E$1,$B$1) -> 16.2583 | F104: =_xll.EQNXTDZ($A$1,$B104,F$1,$B$1) -> 16.2583 | G104: =_xll.EQNXTDZ($A$1,$B104,G$1,$B$1) -> 16.2583 | H104: =_xll.EQNXTDZ($A$1,$B104,H$1,$B$1) -> 16.2583 | I104: =_xll.EQNXTDZ($A$1,$B104,I$1,$B$1) -> 21.2583 | J104: =_xll.EQNXTDZ($A$1,$B104,J$1,$B$1) -> 22.2583 | ... AF104: =_xll.EQNXTDZ($A$1,$B104,AF$1,$B$1) -> 0
A105: Face Value | B105: BS_FACE_VALUE | C105: =_xll.EQNXTDZ($A$1,$B105,C$1,$B$1) -> 10 | D105: =_xll.EQNXTDZ($A$1,$B105,D$1,$B$1) -> 10 | E105: =_xll.EQNXTDZ($A$1,$B105,E$1,$B$1) -> 10 | F105: =_xll.EQNXTDZ($A$1,$B105,F$1,$B$1) -> 10 | G105: =_xll.EQNXTDZ($A$1,$B105,G$1,$B$1) -> 10 | H105: =_xll.EQNXTDZ($A$1,$B105,H$1,$B$1) -> 10 | I105: =_xll.EQNXTDZ($A$1,$B105,I$1,$B$1) -> 10 | J105: =_xll.EQNXTDZ($A$1,$B105,J$1,$B$1) -> 2 | ... AF105: =_xll.EQNXTDZ($A$1,$B105,AF$1,$B$1) -> 0
A106: Close Price (Unit Curr.) | B106: FH_YEAR_PRICE | C106: =_xll.EQNXTDZ($A$1,$B106,C$1,$B$1) -> 0.41 | D106: =_xll.EQNXTDZ($A$1,$B106,D$1,$B$1) -> 0.1 | E106: =_xll.EQNXTDZ($A$1,$B106,E$1,$B$1) -> 0.155 | F106: =_xll.EQNXTDZ($A$1,$B106,F$1,$B$1) -> 0.839 | G106: =_xll.EQNXTDZ($A$1,$B106,G$1,$B$1) -> 4.535 | H106: =_xll.EQNXTDZ($A$1,$B106,H$1,$B$1) -> 3.95 | I106: =_xll.EQNXTDZ($A$1,$B106,I$1,$B$1) -> 2.535 | J106: =_xll.EQNXTDZ($A$1,$B106,J$1,$B$1) -> 37.7 | ... AF106: =_xll.EQNXTDZ($A$1,$B106,AF$1,$B$1) -> 0
A107: High Price (Unit Curr.) | B107: FH_HIGH | C107: =_xll.EQNXTDZ($A$1,$B107,C$1,$B$1) -> 1.13 | D107: =_xll.EQNXTDZ($A$1,$B107,D$1,$B$1) -> 0.35 | E107: =_xll.EQNXTDZ($A$1,$B107,E$1,$B$1) -> 0.905 | F107: =_xll.EQNXTDZ($A$1,$B107,F$1,$B$1) -> 1.47 | G107: =_xll.EQNXTDZ($A$1,$B107,G$1,$B$1) -> 5.08 | H107: =_xll.EQNXTDZ($A$1,$B107,H$1,$B$1) -> 6.77 | I107: =_xll.EQNXTDZ($A$1,$B107,I$1,$B$1) -> 4.67 | J107: =_xll.EQNXTDZ($A$1,$B107,J$1,$B$1) -> 83 | ... AF107: =_xll.EQNXTDZ($A$1,$B107,AF$1,$B$1) -> 0
A108: Low Price (Unit Curr.) | B108: FH_LOW | C108: =_xll.EQNXTDZ($A$1,$B108,C$1,$B$1) -> 0.345 | D108: =_xll.EQNXTDZ($A$1,$B108,D$1,$B$1) -> 0.065 | E108: =_xll.EQNXTDZ($A$1,$B108,E$1,$B$1) -> 0.08 | F108: =_xll.EQNXTDZ($A$1,$B108,F$1,$B$1) -> 0.145 | G108: =_xll.EQNXTDZ($A$1,$B108,G$1,$B$1) -> 0.417 | H108: =_xll.EQNXTDZ($A$1,$B108,H$1,$B$1) -> 2.205 | I108: =_xll.EQNXTDZ($A$1,$B108,I$1,$B$1) -> 1.81 | J108: =_xll.EQNXTDZ($A$1,$B108,J$1,$B$1) -> 2.365 | ... AF108: =_xll.EQNXTDZ($A$1,$B108,AF$1,$B$1) -> 0
A109: Market Capitalization | B109: FH_MCAP | C109: =_xll.EQNXTDZ($A$1,$B109,C$1,$B$1) -> 6.665903 | D109: =_xll.EQNXTDZ($A$1,$B109,D$1,$B$1) -> 1.62583 | E109: =_xll.EQNXTDZ($A$1,$B109,E$1,$B$1) -> 2.5200365 | F109: =_xll.EQNXTDZ($A$1,$B109,F$1,$B$1) -> 13.640714 | G109: =_xll.EQNXTDZ($A$1,$B109,G$1,$B$1) -> 73.731391 | H109: =_xll.EQNXTDZ($A$1,$B109,H$1,$B$1) -> 64.220285 | I109: =_xll.EQNXTDZ($A$1,$B109,I$1,$B$1) -> 53.88979 | J109: =_xll.EQNXTDZ($A$1,$B109,J$1,$B$1) -> 839.13791 | ... AF109: =_xll.EQNXTDZ($A$1,$B109,AF$1,$B$1) -> 0
A110: Adj DPS(Rs) | B110: FR_ADJ_DPS | C110: =_xll.EQNXTDZ($A$1,$B110,C$1,$B$1) -> 0 | D110: =_xll.EQNXTDZ($A$1,$B110,D$1,$B$1) -> 0 | E110: =_xll.EQNXTDZ($A$1,$B110,E$1,$B$1) -> 0 | F110: =_xll.EQNXTDZ($A$1,$B110,F$1,$B$1) -> 0 | G110: =_xll.EQNXTDZ($A$1,$B110,G$1,$B$1) -> 0 | H110: =_xll.EQNXTDZ($A$1,$B110,H$1,$B$1) -> 0 | I110: =_xll.EQNXTDZ($A$1,$B110,I$1,$B$1) -> 0 | J110: =_xll.EQNXTDZ($A$1,$B110,J$1,$B$1) -> 0 | ... AF110: =_xll.EQNXTDZ($A$1,$B110,AF$1,$B$1) -> 0
A111: Date End | B111: SHP_DATE_END | C111: =_xll.EQNXTDZ($A$1,$B111,C$5) -> 200103 | D111: =_xll.EQNXTDZ($A$1,$B111,D$5) -> 200203 | E111: =_xll.EQNXTDZ($A$1,$B111,E$5) -> 200303 | F111: =_xll.EQNXTDZ($A$1,$B111,F$5) -> 200403 | G111: =_xll.EQNXTDZ($A$1,$B111,G$5) -> 0 | H111: =_xll.EQNXTDZ($A$1,$B111,H$5) -> 200603 | I111: =_xll.EQNXTDZ($A$1,$B111,I$5) -> 200703 | J111: =_xll.EQNXTDZ($A$1,$B111,J$5) -> 200803 | ... AF111: =_xll.EQNXTDZ($A$1,$B111,AF$5) -> 0
A112: Total of Promoter and Promoter Group | B112: SHP_TPFTOTALPROMOTER | C112: =_xll.EQNXTDZ($A$1,$B112,C$5) -> 32.99 | D112: =_xll.EQNXTDZ($A$1,$B112,D$5) -> 32.99 | E112: =_xll.EQNXTDZ($A$1,$B112,E$5) -> 32.99 | F112: =_xll.EQNXTDZ($A$1,$B112,F$5) -> 32.99 | G112: =_xll.EQNXTDZ($A$1,$B112,G$5) -> 0 | H112: =_xll.EQNXTDZ($A$1,$B112,H$5) -> 32.4 | I112: =_xll.EQNXTDZ($A$1,$B112,I$5) -> 47.67 | J112: =_xll.EQNXTDZ($A$1,$B112,J$5) -> 45.53 | ... AF112: =_xll.EQNXTDZ($A$1,$B112,AF$5) -> 0
A113: Total of Promoter and Promoter Group Pledged | B113: SHP_PSHFTOTALPROMOTER | C113: =_xll.EQNXTDZ($A$1,$B113,C$5) -> 0 | D113: =_xll.EQNXTDZ($A$1,$B113,D$5) -> 0 | E113: =_xll.EQNXTDZ($A$1,$B113,E$5) -> 0 | F113: =_xll.EQNXTDZ($A$1,$B113,F$5) -> 0 | G113: =_xll.EQNXTDZ($A$1,$B113,G$5) -> 0 | H113: =_xll.EQNXTDZ($A$1,$B113,H$5) -> 0 | I113: =_xll.EQNXTDZ($A$1,$B113,I$5) -> 0 | J113: =_xll.EQNXTDZ($A$1,$B113,J$5) -> 0 | ... AF113: =_xll.EQNXTDZ($A$1,$B113,AF$5) -> 0

Sheet QTR Share Price
A1: ='QTR Raw'!A1 -> 112455 | C1: 201206 | D1: 201207 | E1: 201208 | F1: 201209 | G1: 201210 | H1: 201211 | I1: 201212 | J1: 201301 | K1: 201302 | L1: 201303 | M1: 201304 | N1: 201305 | O1: 201306 | P1: 201307 | Q1: 201308 | R1: 201309 | S1: 201310 | T1: 201311 | U1: 201312 | V1: 201401 | W1: 201402 | X1: 201403 | Y1: 201404 | Z1: 201405 | AA1: 201406 | AB1: 201407 | AC1: 201408 | AD1: 201409 | AE1: 201410 | AF1: 201411 | AG1: 201412 | AH1: 201501 | AI1: 201502 | AJ1: 201503 | AK1: 201504 | AL1: 201505 | AM1: 201506 | AN1: 201507 | AO1: 201508 | AP1: 201509 | AQ1: 201510 | AR1: 201511 | AS1: 201512 | AT1: 201601 | AU1: 201602 | AV1: 201603 | AW1: 201604 | AX1: 201605 | AY1: 201606 | AZ1: 201607 | BA1: 201608 | BB1: 201609 | BC1: 201610 | BD1: 201611 | BE1: 201612 | BF1: 201701 | BG1: 201702 | BH1: 201703 | BI1: 201704 | BJ1: 201705 | BK1: 201706 | BL1: 201707 | BM1: 201708 | BN1: 201709 | BO1: 201710 | BP1: 201711 | BQ1: 201712 | BR1: 201801 | BS1: 201802 | BT1: 201803 | BU1: 201804 | BV1: 201805 | BW1: 201806 | BX1: 201807 | BY1: 201808 | BZ1: 201809 | CA1: 201810 | CB1: 201811 | CC1: 201812 | CD1: 201901 | CE1: 201902 | CF1: 201903 | CG1: 201904 | CH1: 201905 | CI1: 201906 | CJ1: 201907 | CK1: 201908 | CL1: 201909 | CM1: 201910 | CN1: 201911 | CO1: 201912 | CP1: 202001 | CQ1: 202002 | CR1: 202003 | CS1: 202004 | CT1: 202005 | CU1: 202006 | CV1: 202007 | CW1: 202008 | CX1: 202009 | CY1: 202010 | CZ1: 202011 | DA1: 202012 | DB1: 202101 | DC1: 202102 | DD1: 202103 | DE1: 202104 | DF1: 202105 | DG1: 202106 | DH1: 202107 | DI1: 202108 | DJ1: 202109 | DK1: 202110 | DL1: 202111 | DM1: 202112 | DN1: 202201 | DO1: 202202 | DP1: 202203 | DQ1: 202204 | DR1: 202205 | DS1: 202206 | DT1: 202207 | DU1: 202208 | DV1: 202209 | DW1: 202210 | DX1: 202211 | DY1: 202212 | DZ1: 202301 | EA1: 202302 | EB1: 202303 | EC1: 202304 | ED1: 202305 | EE1: 202306 | EF1: 202307 | EG1: 202308 | EH1: 202309 | EI1: 202310 | EJ1: 202311 | EK1: 202312 | EL1: 202401 | EM1: 202402 | EN1: 202403 | EO1: 202404 | EP1: 202405 | EQ1: 202406 | ER1: 202407 | ES1: 202408 | ET1: 202409 | EU1: 202410 | EV1: 202411 | EW1: 202412 | EX1: 202501 | EY1: 202502 | EZ1: 202503 | FA1: 202504 | FB1: 202505 | FC1: 202506 | FD1: 202507 | FE1: 202508 | FF1: 202509 | FG1: 202510 | FH1: 202511 | FI1: 202512 | FJ1: 202601 | FK1: 202602 | FL1: 202603 | FM1: 202604 | FN1: 202605 | FO1: 202606 | FP1: 202607 | FQ1: 202608 | FR1: 202609 | FS1: 202610 | FT1: 202611 | FU1: 202612 | FV1: 202701 | FW1: 202702 | FX1: 202703 | FY1: 202704 | FZ1: 202705 | GA1: 202706 | GB1: 202707 | GC1: 202708 | GD1: 202709 | GE1: 202710 | GF1: 202711 | GG1: 202712 | GH1: 202801 | GI1: 202802 | GJ1: 202803 | GK1: 202804 | GL1: 202805 | GM1: 202806 | GN1: 202807 | GO1: 202808 | GP1: 202809 | GQ1: 202810 | GR1: 202811 | GS1: 202812 | GT1: 202901 | GU1: 202902 | GV1: 202903 | GW1: 202904 | GX1: 202905 | GY1: 202906 | GZ1: 202907 | HA1: 202908 | HB1: 202909 | HC1: 202910 | HD1: 202911 | HE1: 202912 | HF1: 203001 | HG1: 203002 | HH1: 203003 | HM1: 201206 | HN1: 201207 | HO1: 201208 | HP1: 201209 | HQ1: 201212 | HR1: 201303 | HS1: 201306 | HT1: 201309 | HU1: 201312 | HV1: 201403 | HW1: 201406 | HX1: 201409 | HY1: 201412 | HZ1: 201503 | IA1: 201506 | IB1: 201509 | IC1: 201512 | ID1: 201603 | IE1: 201606 | IF1: 201609 | IG1: 201612 | IH1: 201703 | II1: 201706 | IJ1: 201709 | IK1: 201712 | IL1: 201803 | IM1: 201806 | IN1: 201809 | IO1: 201812 | IP1: 201903 | IQ1: 201906 | IR1: 201909 | IS1: 201912 | IT1: 202003 | IU1: 202006 | IV1: 202009 | IW1: 202012 | IX1: 202103 | IY1: 202106 | IZ1: 202109 | JA1: 202112 | JB1: 202203 | JC1: 202206 | JD1: 202209 | JE1: 202212 | JF1: 202303 | JG1: 202306 | JH1: 202309 | JI1: 202312 | JJ1: 202403 | JK1: 202406 | JL1: 202409 | JM1: 202412 | JN1: 202503 | JO1: 202506 | JP1: 202509 | JQ1: 202512 | JR1: 202603 | JS1: 202606 | JT1: 202609 | JU1: 202612 | JV1: 202703 | JW1: 202706 | JX1: 202709 | JY1: 202712 | JZ1: 202803 | KA1: 202806 | KB1: 202809 | KC1: 202812 | KD1: 202903 | KE1: 202906 | KF1: 202909 | KG1: 202912 | KH1: 203003
FF2: 45901 | FG2: =+EOMONTH(FF2,1) -> 45961 | FH2: =+EOMONTH(FG2,1) -> 45991 | FI2: =+EOMONTH(FH2,1) -> 46022 | FJ2: =+EOMONTH(FI2,1) -> 46053 | FK2: =+EOMONTH(FJ2,1) -> 46081 | FL2: =+EOMONTH(FK2,1) -> 46112 | FM2: =+EOMONTH(FL2,1) -> 46142 | FN2: =+EOMONTH(FM2,1) -> 46173 | ... HH2: =+EOMONTH(HG2,1) -> 47573
A4: Field Description | B4: Field Name
A5: MonthEnd | B5: NMONTH_MONTHEND | C5: {=_xll.EQNXTDZ($A$1,$B5,C$1)} -> 0 | D5: {=_xll.EQNXTDZ($A$1,$B5,D$1)} -> 0 | E5: {=_xll.EQNXTDZ($A$1,$B5,E$1)} -> 0 | F5: {=_xll.EQNXTDZ($A$1,$B5,F$1)} -> 0 | G5: {=_xll.EQNXTDZ($A$1,$B5,G$1)} -> 0 | H5: {=_xll.EQNXTDZ($A$1,$B5,H$1)} -> 0 | I5: {=_xll.EQNXTDZ($A$1,$B5,I$1)} -> 0 | J5: {=_xll.EQNXTDZ($A$1,$B5,J$1)} -> 0 | ... HH5: {=_xll.EQNXTDZ($A$1,$B5,HH$1)} -> 0
A6: Open | B6: NMONTH_OPEN | C6: {=_xll.EQNXTDZ($A$1,$B6,C$1)} -> 0 | D6: {=_xll.EQNXTDZ($A$1,$B6,D$1)} -> 0 | E6: {=_xll.EQNXTDZ($A$1,$B6,E$1)} -> 0 | F6: {=_xll.EQNXTDZ($A$1,$B6,F$1)} -> 0 | G6: {=_xll.EQNXTDZ($A$1,$B6,G$1)} -> 0 | H6: {=_xll.EQNXTDZ($A$1,$B6,H$1)} -> 0 | I6: {=_xll.EQNXTDZ($A$1,$B6,I$1)} -> 0 | J6: {=_xll.EQNXTDZ($A$1,$B6,J$1)} -> 0 | ... HH6: {=_xll.EQNXTDZ($A$1,$B6,HH$1)} -> 0
A7: High | B7: NMONTH_HIGH | C7: {=_xll.EQNXTDZ($A$1,$B7,C$1)} -> 0 | D7: {=_xll.EQNXTDZ($A$1,$B7,D$1)} -> 0 | E7: {=_xll.EQNXTDZ($A$1,$B7,E$1)} -> 0 | F7: {=_xll.EQNXTDZ($A$1,$B7,F$1)} -> 0 | G7: {=_xll.EQNXTDZ($A$1,$B7,G$1)} -> 0 | H7: {=_xll.EQNXTDZ($A$1,$B7,H$1)} -> 0 | I7: {=_xll.EQNXTDZ($A$1,$B7,I$1)} -> 0 | J7: {=_xll.EQNXTDZ($A$1,$B7,J$1)} -> 0 | ... HH7: {=_xll.EQNXTDZ($A$1,$B7,HH$1)} -> 0 | HP7: =+MAX(D7:F7) -> 0 | HQ7: =+MAX(G7:I7) -> 0 | HR7: =+MAX(J7:L7) -> 0 | HS7: =+MAX(M7:O7) -> 0 | HT7: =+MAX(P7:R7) -> 0 | HU7: =+MAX(S7:U7) -> 0 | HV7: =+MAX(V7:X7) -> 0 | HW7: =+MAX(Y7:AA7) -> 0 | HX7: =+MAX(AB7:AD7) -> 0 | HY7: =+MAX(AE7:AG7) -> 0 | HZ7: =+MAX(AH7:AJ7) -> 0 | IA7: =+MAX(AK7:AM7) -> 0 | IB7: =+MAX(AN7:AP7) -> 0 | IC7: =+MAX(AQ7:AS7) -> 0 | ID7: =+MAX(AT7:AV7) -> 0 | IE7: =+MAX(AW7:AY7) -> 0 | IF7: =+MAX(AZ7:BB7) -> 0 | IG7: =+MAX(BC7:BE7) -> 0 | IH7: =+MAX(BF7:BH7) -> 0 | II7: =+MAX(BI7:BK7) -> 0 | IJ7: =+MAX(BL7:BN7) -> 0 | IK7: =+MAX(BO7:BQ7) -> 0 | IL7: =+MAX(BR7:BT7) -> 0 | IM7: =+MAX(BU7:BW7) -> 0 | IN7: =+MAX(BX7:BZ7) -> 0 | IO7: =+MAX(CA7:CC7) -> 0 | IP7: =+MAX(CD7:CF7) -> 0 | IQ7: =+MAX(CG7:CI7) -> 0 | IR7: =+MAX(CJ7:CL7) -> 0 | IS7: =+MAX(CM7:CO7) -> 0 | IT7: =+MAX(CP7:CR7) -> 0 | IU7: =+MAX(CS7:CU7) -> 0 | IV7: =+MAX(CV7:CX7) -> 0 | IW7: =+MAX(CY7:DA7) -> 0 | IX7: =+MAX(DB7:DD7) -> 0 | IY7: =+MAX(DE7:DG7) -> 0 | IZ7: =+MAX(DH7:DJ7) -> 0 | JA7: =+MAX(DK7:DM7) -> 0 | JB7: =+MAX(DN7:DP7) -> 0 | JC7: =+MAX(DQ7:DS7) -> 0 | JD7: =+MAX(DT7:DV7) -> 0 | JE7: =+MAX(DW7:DY7) -> 0 | JF7: =+MAX(DZ7:EB7) -> 0 | JG7: =+MAX(EC7:EE7) -> 0 | JH7: =+MAX(EF7:EH7) -> 686.7 | JI7: =+MAX(EI7:EK7) -> 656 | JJ7: =+MAX(EL7:EN7) -> 637.95 | JK7: =MAX(EO7:EQ7) -> 774.9 | JL7: =MAX(ER7:ET7) -> 960 | JM7: =MAX(EU7:EW7) -> 1233 | JN7: =MAX(EX7:EZ7) -> 1478 | JO7: =MAX(FA7:FC7) -> 1590 | JP7: =MAX(FD7:FF7) -> 1612 | JQ7: =MAX(FG7:FI7) -> 1395 | JR7: =MAX(FJ7:FL7) -> 1374 | JS7: =MAX(FM7:FO7) -> 1888.6 | JT7: =MAX(FP7:FR7) -> 0 | JU7: =MAX(FS7:FU7) -> 0 | JV7: =MAX(FV7:FX7) -> 0 | JW7: =MAX(FY7:GA7) -> 0 | JX7: =MAX(GB7:GD7) -> 0 | JY7: =MAX(GE7:GG7) -> 0 | JZ7: =MAX(GH7:GJ7) -> 0 | KA7: =MAX(GK7:GM7) -> 0 | KB7: =MAX(GN7:GP7) -> 0 | KC7: =MAX(GQ7:GS7) -> 0 | KD7: =MAX(GT7:GV7) -> 0 | KE7: =MAX(GW7:GY7) -> 0 | KF7: =MAX(GZ7:HB7) -> 0 | KG7: =MAX(HC7:HE7) -> 0 | KH7: =MAX(HF7:HH7) -> 0
A8: Low | B8: NMONTH_LOW | C8: {=_xll.EQNXTDZ($A$1,$B8,C$1)} -> 0 | D8: {=_xll.EQNXTDZ($A$1,$B8,D$1)} -> 0 | E8: {=_xll.EQNXTDZ($A$1,$B8,E$1)} -> 0 | F8: {=_xll.EQNXTDZ($A$1,$B8,F$1)} -> 0 | G8: {=_xll.EQNXTDZ($A$1,$B8,G$1)} -> 0 | H8: {=_xll.EQNXTDZ($A$1,$B8,H$1)} -> 0 | I8: {=_xll.EQNXTDZ($A$1,$B8,I$1)} -> 0 | J8: {=_xll.EQNXTDZ($A$1,$B8,J$1)} -> 0 | ... HH8: {=_xll.EQNXTDZ($A$1,$B8,HH$1)} -> 0 | HP8: =+MIN(D8:F8) -> 0 | HQ8: =+MIN(G8:I8) -> 0 | HR8: =+MIN(J8:L8) -> 0 | HS8: =+MIN(M8:O8) -> 0 | HT8: =+MIN(P8:R8) -> 0 | HU8: =+MIN(S8:U8) -> 0 | HV8: =+MIN(V8:X8) -> 0 | HW8: =+MIN(Y8:AA8) -> 0 | HX8: =+MIN(AB8:AD8) -> 0 | HY8: =+MIN(AE8:AG8) -> 0 | HZ8: =+MIN(AH8:AJ8) -> 0 | IA8: =+MIN(AK8:AM8) -> 0 | IB8: =+MIN(AN8:AP8) -> 0 | IC8: =+MIN(AQ8:AS8) -> 0 | ID8: =+MIN(AT8:AV8) -> 0 | IE8: =+MIN(AW8:AY8) -> 0 | IF8: =+MIN(AZ8:BB8) -> 0 | IG8: =+MIN(BC8:BE8) -> 0 | IH8: =+MIN(BF8:BH8) -> 0 | II8: =+MIN(BI8:BK8) -> 0 | IJ8: =+MIN(BL8:BN8) -> 0 | IK8: =+MIN(BO8:BQ8) -> 0 | IL8: =+MIN(BR8:BT8) -> 0 | IM8: =+MIN(BU8:BW8) -> 0 | IN8: =+MIN(BX8:BZ8) -> 0 | IO8: =+MIN(CA8:CC8) -> 0 | IP8: =+MIN(CD8:CF8) -> 0 | IQ8: =+MIN(CG8:CI8) -> 0 | IR8: =+MIN(CJ8:CL8) -> 0 | IS8: =+MIN(CM8:CO8) -> 0 | IT8: =+MIN(CP8:CR8) -> 0 | IU8: =+MIN(CS8:CU8) -> 0 | IV8: =+MIN(CV8:CX8) -> 0 | IW8: =+MIN(CY8:DA8) -> 0 | IX8: =+MIN(DB8:DD8) -> 0 | IY8: =+MIN(DE8:DG8) -> 0 | IZ8: =+MIN(DH8:DJ8) -> 0 | JA8: =+MIN(DK8:DM8) -> 0 | JB8: =+MIN(DN8:DP8) -> 0 | JC8: =+MIN(DQ8:DS8) -> 0 | JD8: =+MIN(DT8:DV8) -> 0 | JE8: =+MIN(DW8:DY8) -> 0 | JF8: =+MIN(DZ8:EB8) -> 0 | JG8: =+MIN(EC8:EE8) -> 0 | JH8: =+MIN(EF8:EH8) -> 498.05 | JI8: =+MIN(EI8:EK8) -> 492 | JJ8: =+MIN(EL8:EN8) -> 525.9 | JK8: =MIN(EO8:EQ8) -> 592 | JL8: =MIN(ER8:ET8) -> 674.8 | JM8: =MIN(EU8:EW8) -> 891.05 | JN8: =MIN(EX8:EZ8) -> 942.15 | JO8: =MIN(FA8:FC8) -> 1015 | JP8: =MIN(FD8:FF8) -> 1201.3 | JQ8: =MIN(FG8:FI8) -> 1170 | JR8: =MIN(FJ8:FL8) -> 1042.9 | JS8: =MIN(FM8:FO8) -> 1290 | JT8: =MIN(FP8:FR8) -> 0 | JU8: =MIN(FS8:FU8) -> 0 | JV8: =MIN(FV8:FX8) -> 0 | JW8: =MIN(FY8:GA8) -> 0 | JX8: =MIN(GB8:GD8) -> 0 | JY8: =MIN(GE8:GG8) -> 0 | JZ8: =MIN(GH8:GJ8) -> 0 | KA8: =MIN(GK8:GM8) -> 0 | KB8: =MIN(GN8:GP8) -> 0 | KC8: =MIN(GQ8:GS8) -> 0 | KD8: =MIN(GT8:GV8) -> 0 | KE8: =MIN(GW8:GY8) -> 0 | KF8: =MIN(GZ8:HB8) -> 0 | KG8: =MIN(HC8:HE8) -> 0 | KH8: =MIN(HF8:HH8) -> 0
A9: Close | B9: NMONTH_CLOSE | C9: {=_xll.EQNXTDZ($A$1,$B9,C$1)} -> 0 | D9: {=_xll.EQNXTDZ($A$1,$B9,D$1)} -> 0 | E9: {=_xll.EQNXTDZ($A$1,$B9,E$1)} -> 0 | F9: {=_xll.EQNXTDZ($A$1,$B9,F$1)} -> 0 | G9: {=_xll.EQNXTDZ($A$1,$B9,G$1)} -> 0 | H9: {=_xll.EQNXTDZ($A$1,$B9,H$1)} -> 0 | I9: {=_xll.EQNXTDZ($A$1,$B9,I$1)} -> 0 | J9: {=_xll.EQNXTDZ($A$1,$B9,J$1)} -> 0 | ... HH9: {=_xll.EQNXTDZ($A$1,$B9,HH$1)} -> 0 | HP9: =+F9 -> 0 | HQ9: =+I9 -> 0 | HR9: =+L9 -> 0 | HS9: =+O9 -> 0 | HT9: =+R9 -> 0 | HU9: =+U9 -> 0 | HV9: =+X9 -> 0 | HW9: =+AA9 -> 0 | HX9: =+AD9 -> 0 | HY9: =+AG9 -> 0 | HZ9: =+AJ9 -> 0 | IA9: =+AM9 -> 0 | IB9: =+AP9 -> 0 | IC9: =+AS9 -> 0 | ID9: =+AV9 -> 0 | IE9: =+AY9 -> 0 | IF9: =+BB9 -> 0 | IG9: =+BE9 -> 0 | IH9: =+BH9 -> 0 | II9: =+BK9 -> 0 | IJ9: =+BN9 -> 0 | IK9: =+BQ9 -> 0 | IL9: =+BT9 -> 0 | IM9: =+BW9 -> 0 | IN9: =+BZ9 -> 0 | IO9: =+CC9 -> 0 | IP9: =+CF9 -> 0 | IQ9: =+CI9 -> 0 | IR9: =+CL9 -> 0 | IS9: =+CO9 -> 0 | IT9: =+CR9 -> 0 | IU9: =+CU9 -> 0 | IV9: =+CX9 -> 0 | IW9: =+DA9 -> 0 | IX9: =+DD9 -> 0 | IY9: =+DG9 -> 0 | IZ9: =+DJ9 -> 0 | JA9: =+DM9 -> 0 | JB9: =+DP9 -> 0 | JC9: =+DS9 -> 0 | JD9: =+DV9 -> 0 | JE9: =+DY9 -> 0 | JF9: =+EB9 -> 0 | JG9: =+EE9 -> 0 | JH9: =+EH9 -> 536.1 | JI9: =+EK9 -> 599.8 | JJ9: =+EN9 -> 602 | JK9: =EQ9 -> 732.2 | JL9: =ET9 -> 948.35 | JM9: =EW9 -> 1231.85 | JN9: =EZ9 -> 1287.25 | JO9: =FC9 -> 1588.9 | JP9: =FF9 -> 1225 | JQ9: =FI9 -> 1321.3 | JR9: =FL9 -> 1271.7 | JS9: =FO9 -> 1765 | JT9: =FR9 -> 0 | JU9: =FU9 -> 0 | JV9: =FX9 -> 0 | JW9: =GA9 -> 0 | JX9: =GD9 -> 0 | JY9: =GG9 -> 0 | JZ9: =GJ9 -> 0 | KA9: =GM9 -> 0 | KB9: =GP9 -> 0 | KC9: =GS9 -> 0 | KD9: =GV9 -> 0 | KE9: =GY9 -> 0 | KF9: =HB9 -> 0 | KG9: =HE9 -> 0 | KH9: =HH9 -> 0
A11: Field Description | B11: Field Name | C11: {=_xll.EQNXTDZ($A$1,$B11,C$1)} -> 0 | D11: {=_xll.EQNXTDZ($A$1,$B11,D$1)} -> 0 | E11: {=_xll.EQNXTDZ($A$1,$B11,E$1)} -> 0 | F11: {=_xll.EQNXTDZ($A$1,$B11,F$1)} -> 0 | G11: {=_xll.EQNXTDZ($A$1,$B11,G$1)} -> 0 | H11: {=_xll.EQNXTDZ($A$1,$B11,H$1)} -> 0 | I11: {=_xll.EQNXTDZ($A$1,$B11,I$1)} -> 0 | J11: {=_xll.EQNXTDZ($A$1,$B11,J$1)} -> 0 | ... HH11: {=_xll.EQNXTDZ($A$1,$B11,HH$1)} -> 0
A12: Month End | B12: BMONTH_MONTHEND | C12: {=_xll.EQNXTDZ($A$1,$B12,C$1)} -> 201206 | D12: {=_xll.EQNXTDZ($A$1,$B12,D$1)} -> 201207 | E12: {=_xll.EQNXTDZ($A$1,$B12,E$1)} -> 201208 | F12: {=_xll.EQNXTDZ($A$1,$B12,F$1)} -> 201209 | G12: {=_xll.EQNXTDZ($A$1,$B12,G$1)} -> 201210 | H12: {=_xll.EQNXTDZ($A$1,$B12,H$1)} -> 201211 | I12: {=_xll.EQNXTDZ($A$1,$B12,I$1)} -> 201212 | J12: {=_xll.EQNXTDZ($A$1,$B12,J$1)} -> 201301 | ... HH12: {=_xll.EQNXTDZ($A$1,$B12,HH$1)} -> 0
A13: Open | B13: BMONTH_OPEN | C13: {=_xll.EQNXTDZ($A$1,$B13,C$1)} -> 10 | D13: {=_xll.EQNXTDZ($A$1,$B13,D$1)} -> 10.475 | E13: {=_xll.EQNXTDZ($A$1,$B13,E$1)} -> 9.625 | F13: {=_xll.EQNXTDZ($A$1,$B13,F$1)} -> 8.475 | G13: {=_xll.EQNXTDZ($A$1,$B13,G$1)} -> 8.25 | H13: {=_xll.EQNXTDZ($A$1,$B13,H$1)} -> 7.11 | I13: {=_xll.EQNXTDZ($A$1,$B13,I$1)} -> 7.75 | J13: {=_xll.EQNXTDZ($A$1,$B13,J$1)} -> 8.35 | ... HH13: {=_xll.EQNXTDZ($A$1,$B13,HH$1)} -> 0
A14: High | B14: BMONTH_HIGH | C14: {=_xll.EQNXTDZ($A$1,$B14,C$1)} -> 10.475 | D14: {=_xll.EQNXTDZ($A$1,$B14,D$1)} -> 13.375 | E14: {=_xll.EQNXTDZ($A$1,$B14,E$1)} -> 10.5 | F14: {=_xll.EQNXTDZ($A$1,$B14,F$1)} -> 9.625 | G14: {=_xll.EQNXTDZ($A$1,$B14,G$1)} -> 8.5 | H14: {=_xll.EQNXTDZ($A$1,$B14,H$1)} -> 8.4 | I14: {=_xll.EQNXTDZ($A$1,$B14,I$1)} -> 8.8 | J14: {=_xll.EQNXTDZ($A$1,$B14,J$1)} -> 8.975 | ... HH14: {=_xll.EQNXTDZ($A$1,$B14,HH$1)} -> 0 | HP14: =+MAX(D14:F14) -> 13.375 | HQ14: =+MAX(G14:I14) -> 8.8 | HR14: =+MAX(J14:L14) -> 8.975 | HS14: =+MAX(M14:O14) -> 7.725 | HT14: =+MAX(P14:R14) -> 9.075 | HU14: =+MAX(S14:U14) -> 9.075 | HV14: =+MAX(V14:X14) -> 5 | HW14: =+MAX(Y14:AA14) -> 7.405 | HX14: =+MAX(AB14:AD14) -> 6.88 | HY14: =+MAX(AE14:AG14) -> 6.85 | HZ14: =+MAX(AH14:AJ14) -> 5.7 | IA14: =+MAX(AK14:AM14) -> 4.195 | IB14: =+MAX(AN14:AP14) -> 5 | IC14: =+MAX(AQ14:AS14) -> 4.695 | ID14: =+MAX(AT14:AV14) -> 10.8 | IE14: =+MAX(AW14:AY14) -> 17.475 | IF14: =+MAX(AZ14:BB14) -> 17.4 | IG14: =+MAX(BC14:BE14) -> 20.4 | IH14: =+MAX(BF14:BH14) -> 19.24 | II14: =+MAX(BI14:BK14) -> 23 | IJ14: =+MAX(BL14:BN14) -> 22.2 | IK14: =+MAX(BO14:BQ14) -> 22.95 | IL14: =+MAX(BR14:BT14) -> 22.55 | IM14: =+MAX(BU14:BW14) -> 19.9 | IN14: =+MAX(BX14:BZ14) -> 18.4 | IO14: =+MAX(CA14:CC14) -> 15.4 | IP14: =+MAX(CD14:CF14) -> 15.1 | IQ14: =+MAX(CG14:CI14) -> 13.42 | IR14: =+MAX(CJ14:CL14) -> 12.25 | IS14: =+MAX(CM14:CO14) -> 10.53 | IT14: =+MAX(CP14:CR14) -> 8.9 | IU14: =+MAX(CS14:CU14) -> 10.85 | IV14: =+MAX(CV14:CX14) -> 12.5 | IW14: =+MAX(CY14:DA14) -> 12.08 | IX14: =+MAX(DB14:DD14) -> 17.49 | IY14: =+MAX(DE14:DG14) -> 50.8 | IZ14: =+MAX(DH14:DJ14) -> 91.1 | JA14: =+MAX(DK14:DM14) -> 101.8 | JB14: =+MAX(DN14:DP14) -> 148.65 | JC14: =+MAX(DQ14:DS14) -> 232 | JD14: =+MAX(DT14:DV14) -> 204.55 | JE14: =+MAX(DW14:DY14) -> 253.9 | JF14: =+MAX(DZ14:EB14) -> 324.8 | JG14: =+MAX(EC14:EE14) -> 404 | JH14: =+MAX(EF14:EH14) -> 687.85 | JI14: =+MAX(EI14:EK14) -> 656.05 | JJ14: =+MAX(EL14:EN14) -> 637 | JK14: =MAX(EO14:EQ14) -> 774.95 | JL14: =MAX(ER14:ET14) -> 959.65 | JM14: =MAX(EU14:EW14) -> 1233 | JN14: =MAX(EX14:EZ14) -> 1477.5 | JO14: =MAX(FA14:FC14) -> 1601.65 | JP14: =MAX(FD14:FF14) -> 1613.4 | JQ14: =MAX(FG14:FI14) -> 1395.45 | JR14: =MAX(FJ14:FL14) -> 1374.8 | JS14: =MAX(FM14:FO14) -> 1889 | JT14: =MAX(FP14:FR14) -> 0 | JU14: =MAX(FS14:FU14) -> 0 | JV14: =MAX(FV14:FX14) -> 0 | JW14: =MAX(FY14:GA14) -> 0 | JX14: =MAX(GB14:GD14) -> 0 | JY14: =MAX(GE14:GG14) -> 0 | JZ14: =MAX(GH14:GJ14) -> 0 | KA14: =MAX(GK14:GM14) -> 0 | KB14: =MAX(GN14:GP14) -> 0 | KC14: =MAX(GQ14:GS14) -> 0 | KD14: =MAX(GT14:GV14) -> 0 | KE14: =MAX(GW14:GY14) -> 0 | KF14: =MAX(GZ14:HB14) -> 0 | KG14: =MAX(HC14:HE14) -> 0 | KH14: =MAX(HF14:HH14) -> 0
A15: Low | B15: BMONTH_LOW | C15: {=_xll.EQNXTDZ($A$1,$B15,C$1)} -> 9.275 | D15: {=_xll.EQNXTDZ($A$1,$B15,D$1)} -> 9.525 | E15: {=_xll.EQNXTDZ($A$1,$B15,E$1)} -> 8 | F15: {=_xll.EQNXTDZ($A$1,$B15,F$1)} -> 7.725 | G15: {=_xll.EQNXTDZ($A$1,$B15,G$1)} -> 6.85 | H15: {=_xll.EQNXTDZ($A$1,$B15,H$1)} -> 6.75 | I15: {=_xll.EQNXTDZ($A$1,$B15,I$1)} -> 7.175 | J15: {=_xll.EQNXTDZ($A$1,$B15,J$1)} -> 7.025 | ... HH15: {=_xll.EQNXTDZ($A$1,$B15,HH$1)} -> 0 | HP15: =+MIN(D15:F15) -> 7.725 | HQ15: =+MIN(G15:I15) -> 6.75 | HR15: =+MIN(J15:L15) -> 5.775 | HS15: =+MIN(M15:O15) -> 4.455 | HT15: =+MIN(P15:R15) -> 4.46 | HU15: =+MIN(S15:U15) -> 4.3 | HV15: =+MIN(V15:X15) -> 3.075 | HW15: =+MIN(Y15:AA15) -> 3.785 | HX15: =+MIN(AB15:AD15) -> 4.585 | HY15: =+MIN(AE15:AG15) -> 4.03 | HZ15: =+MIN(AH15:AJ15) -> 3.055 | IA15: =+MIN(AK15:AM15) -> 2.865 | IB15: =+MIN(AN15:AP15) -> 2.775 | IC15: =+MIN(AQ15:AS15) -> 3 | ID15: =+MIN(AT15:AV15) -> 3.63 | IE15: =+MIN(AW15:AY15) -> 9.6 | IF15: =+MIN(AZ15:BB15) -> 12.51 | IG15: =+MIN(BC15:BE15) -> 9.05 | IH15: =+MIN(BF15:BH15) -> 10.4 | II15: =+MIN(BI15:BK15) -> 15.05 | IJ15: =+MIN(BL15:BN15) -> 15 | IK15: =+MIN(BO15:BQ15) -> 16.05 | IL15: =+MIN(BR15:BT15) -> 13.5 | IM15: =+MIN(BU15:BW15) -> 11.5 | IN15: =+MIN(BX15:BZ15) -> 13 | IO15: =+MIN(CA15:CC15) -> 12.02 | IP15: =+MIN(CD15:CF15) -> 10.5 | IQ15: =+MIN(CG15:CI15) -> 7.03 | IR15: =+MIN(CJ15:CL15) -> 8 | IS15: =+MIN(CM15:CO15) -> 6.9 | IT15: =+MIN(CP15:CR15) -> 4.16 | IU15: =+MIN(CS15:CU15) -> 4.12 | IV15: =+MIN(CV15:CX15) -> 9.22 | IW15: =+MIN(CY15:DA15) -> 9.25 | IX15: =+MIN(DB15:DD15) -> 9.8 | IY15: =+MIN(DE15:DG15) -> 10.49 | IZ15: =+MIN(DH15:DJ15) -> 47.25 | JA15: =+MIN(DK15:DM15) -> 71.6 | JB15: =+MIN(DN15:DP15) -> 102.45 | JC15: =+MIN(DQ15:DS15) -> 126.1 | JD15: =+MIN(DT15:DV15) -> 132.45 | JE15: =+MIN(DW15:DY15) -> 163.15 | JF15: =+MIN(DZ15:EB15) -> 235.6 | JG15: =+MIN(EC15:EE15) -> 275 | JH15: =+MIN(EF15:EH15) -> 395.2 | JI15: =+MIN(EI15:EK15) -> 485.3 | JJ15: =+MIN(EL15:EN15) -> 522.4 | JK15: =MIN(EO15:EQ15) -> 592.1 | JL15: =MIN(ER15:ET15) -> 675 | JM15: =MIN(EU15:EW15) -> 880.95 | JN15: =MIN(EX15:EZ15) -> 943.25 | JO15: =MIN(FA15:FC15) -> 1005.05 | JP15: =MIN(FD15:FF15) -> 1201.5 | JQ15: =MIN(FG15:FI15) -> 1170.7 | JR15: =MIN(FJ15:FL15) -> 1044 | JS15: =MIN(FM15:FO15) -> 1289.15 | JT15: =MIN(FP15:FR15) -> 0 | JU15: =MIN(FS15:FU15) -> 0 | JV15: =MIN(FV15:FX15) -> 0 | JW15: =MIN(FY15:GA15) -> 0 | JX15: =MIN(GB15:GD15) -> 0 | JY15: =MIN(GE15:GG15) -> 0 | JZ15: =MIN(GH15:GJ15) -> 0 | KA15: =MIN(GK15:GM15) -> 0 | KB15: =MIN(GN15:GP15) -> 0 | KC15: =MIN(GQ15:GS15) -> 0 | KD15: =MIN(GT15:GV15) -> 0 | KE15: =MIN(GW15:GY15) -> 0 | KF15: =MIN(GZ15:HB15) -> 0 | KG15: =MIN(HC15:HE15) -> 0 | KH15: =MIN(HF15:HH15) -> 0
A16: Close | B16: BMONTH_CLOSE | C16: {=_xll.EQNXTDZ($A$1,$B16,C$1)} -> 9.975 | D16: {=_xll.EQNXTDZ($A$1,$B16,D$1)} -> 9.875 | E16: {=_xll.EQNXTDZ($A$1,$B16,E$1)} -> 8.275 | F16: {=_xll.EQNXTDZ($A$1,$B16,F$1)} -> 8.2 | G16: {=_xll.EQNXTDZ($A$1,$B16,G$1)} -> 7.3 | H16: {=_xll.EQNXTDZ($A$1,$B16,H$1)} -> 7.585 | I16: {=_xll.EQNXTDZ($A$1,$B16,I$1)} -> 8.65 | J16: {=_xll.EQNXTDZ($A$1,$B16,J$1)} -> 7.55 | ... HH16: {=_xll.EQNXTDZ($A$1,$B16,HH$1)} -> 0 | HP16: =+F16 -> 8.2 | HQ16: =+I16 -> 8.65 | HR16: =+L16 -> 5.99 | HS16: =+O16 -> 4.455 | HT16: =+R16 -> 8.65 | HU16: =+U16 -> 4.96 | HV16: =+X16 -> 3.955 | HW16: =+AA16 -> 6.63 | HX16: =+AD16 -> 4.9 | HY16: =+AG16 -> 4.965 | HZ16: =+AJ16 -> 3.195 | IA16: =+AM16 -> 2.94 | IB16: =+AP16 -> 3.795 | IC16: =+AS16 -> 3.75 | ID16: =+AV16 -> 10.1 | IE16: =+AY16 -> 15.325 | IF16: =+BB16 -> 13.45 | IG16: =+BE16 -> 10.67 | IH16: =+BH16 -> 15.3 | II16: =+BK16 -> 17.3 | IJ16: =+BN16 -> 17.7 | IK16: =+BQ16 -> 17.55 | IL16: =+BT16 -> 15.3 | IM16: =+BW16 -> 13.3 | IN16: =+BZ16 -> 13.55 | IO16: =+CC16 -> 14.25 | IP16: =+CF16 -> 12.46 | IQ16: =+CI16 -> 8.87 | IR16: =+CL16 -> 10.4 | IS16: =+CO16 -> 7.57 | IT16: =+CR16 -> 5.76 | IU16: =+CU16 -> 10.56 | IV16: =+CX16 -> 11.65 | IW16: =+DA16 -> 10.07 | IX16: =+DD16 -> 11 | IY16: =+DG16 -> 50.8 | IZ16: =+DJ16 -> 91.1 | JA16: =+DM16 -> 100.4 | JB16: =+DP16 -> 132.65 | JC16: =+DS16 -> 139.9 | JD16: =+DV16 -> 178.1 | JE16: =+DY16 -> 245.3 | JF16: =+EB16 -> 284.7 | JG16: =+EE16 -> 395.7 | JH16: =+EH16 -> 536.6 | JI16: =+EK16 -> 599.2 | JJ16: =+EN16 -> 602.95 | JK16: =EQ16 -> 732.25 | JL16: =ET16 -> 948.65 | JM16: =EW16 -> 1231.3 | JN16: =EZ16 -> 1285.5 | JO16: =FC16 -> 1590.65 | JP16: =FF16 -> 1226.5 | JQ16: =FI16 -> 1322 | JR16: =FL16 -> 1270.7 | JS16: =FO16 -> 1766.55 | JT16: =FR16 -> 0 | JU16: =FU16 -> 0 | JV16: =FX16 -> 0 | JW16: =GA16 -> 0 | JX16: =GD16 -> 0 | JY16: =GG16 -> 0 | JZ16: =GJ16 -> 0 | KA16: =GM16 -> 0 | KB16: =GP16 -> 0 | KC16: =GS16 -> 0 | KD16: =GV16 -> 0 | KE16: =GY16 -> 0 | KF16: =HB16 -> 0 | KG16: =HE16 -> 0 | KH16: =HH16 -> 0
A19: High | HP19: =+IF(HP14=0,HP7,HP14) -> 13.375 | HQ19: =+IF(HQ14=0,HQ7,HQ14) -> 8.8 | HR19: =+IF(HR14=0,HR7,HR14) -> 8.975 | HS19: =+IF(HS14=0,HS7,HS14) -> 7.725 | HT19: =+IF(HT14=0,HT7,HT14) -> 9.075 | HU19: =+IF(HU14=0,HU7,HU14) -> 9.075 | HV19: =+IF(HV14=0,HV7,HV14) -> 5 | HW19: =+IF(HW14=0,HW7,HW14) -> 7.405 | ... KH19: =+IF(KH14=0,KH7,KH14) -> 0
A20: Low | HP20: =+IF(HP15=0,HP8,HP15) -> 7.725 | HQ20: =+IF(HQ15=0,HQ8,HQ15) -> 6.75 | HR20: =+IF(HR15=0,HR8,HR15) -> 5.775 | HS20: =+IF(HS15=0,HS8,HS15) -> 4.455 | HT20: =+IF(HT15=0,HT8,HT15) -> 4.46 | HU20: =+IF(HU15=0,HU8,HU15) -> 4.3 | HV20: =+IF(HV15=0,HV8,HV15) -> 3.075 | HW20: =+IF(HW15=0,HW8,HW15) -> 3.785 | ... KH20: =+IF(KH15=0,KH8,KH15) -> 0
A21: Close | HP21: =+IF(HP16=0,HP9,HP16) -> 8.2 | HQ21: =+IF(HQ16=0,HQ9,HQ16) -> 8.65 | HR21: =+IF(HR16=0,HR9,HR16) -> 5.99 | HS21: =+IF(HS16=0,HS9,HS16) -> 4.455 | HT21: =+IF(HT16=0,HT9,HT16) -> 8.65 | HU21: =+IF(HU16=0,HU9,HU16) -> 4.96 | HV21: =+IF(HV16=0,HV9,HV16) -> 3.955 | HW21: =+IF(HW16=0,HW9,HW16) -> 6.63 | ... KH21: =+IF(KH16=0,KH9,KH16) -> 0

Sheet QTR No. of Shares
A1: ='QTR Raw'!A1 -> 112455 | C1: 201206 | D1: 201209 | E1: 201212 | F1: 201303 | G1: 201306 | H1: 201309 | I1: 201312 | J1: 201403 | K1: 201406 | L1: 201409 | M1: 201412 | N1: 201503 | O1: 201506 | P1: 201509 | Q1: 201512 | R1: 201603 | S1: 201606 | T1: 201609 | U1: 201612 | V1: 201703 | W1: 201706 | X1: 201709 | Y1: 201712 | Z1: 201803 | AA1: 201806 | AB1: 201809 | AC1: 201812 | AD1: 201903 | AE1: 201906 | AF1: 201909 | AG1: 201912 | AH1: 202003 | AI1: 202006 | AJ1: 202009 | AK1: 202012 | AL1: 202103 | AM1: 202106 | AN1: 202109 | AO1: 202112 | AP1: 202203 | AQ1: 202206 | AR1: 202209 | AS1: 202212 | AT1: 202303 | AU1: 202306 | AV1: 202309 | AW1: 202312 | AX1: 202403 | AY1: 202406
A4: Field Description | B4: Field Name
A5: Date End | B5: SHP_DATE_END | C5: {=_xll.EQNXTDZ($A$1,$B5,C$1)} -> 201206 | D5: {=_xll.EQNXTDZ($A$1,$B5,D$1)} -> 201209 | E5: {=_xll.EQNXTDZ($A$1,$B5,E$1)} -> 201212 | F5: {=_xll.EQNXTDZ($A$1,$B5,F$1)} -> 201303 | G5: {=_xll.EQNXTDZ($A$1,$B5,G$1)} -> 201306 | H5: {=_xll.EQNXTDZ($A$1,$B5,H$1)} -> 201309 | I5: {=_xll.EQNXTDZ($A$1,$B5,I$1)} -> 201312 | J5: {=_xll.EQNXTDZ($A$1,$B5,J$1)} -> 201403 | ... AY5: {=_xll.EQNXTDZ($A$1,$B5,AY$1)} -> 202406
A6: Grand Total | B6: SHP_NSGRANDTOTAL | C6: {=_xll.EQNXTDZ($A$1,$B6,C$1)} -> 111291290 | D6: {=_xll.EQNXTDZ($A$1,$B6,D$1)} -> 111291290 | E6: {=_xll.EQNXTDZ($A$1,$B6,E$1)} -> 111291290 | F6: {=_xll.EQNXTDZ($A$1,$B6,F$1)} -> 111291290 | G6: {=_xll.EQNXTDZ($A$1,$B6,G$1)} -> 111291290 | H6: {=_xll.EQNXTDZ($A$1,$B6,H$1)} -> 111291290 | I6: {=_xll.EQNXTDZ($A$1,$B6,I$1)} -> 111291290 | J6: {=_xll.EQNXTDZ($A$1,$B6,J$1)} -> 111291290 | ... AY6: {=_xll.EQNXTDZ($A$1,$B6,AY$1)} -> 505253535
B7: In Crs. | C7: =+C6/10^7 -> 11.129129 | D7: =+D6/10^7 -> 11.129129 | E7: =+E6/10^7 -> 11.129129 | F7: =+F6/10^7 -> 11.129129 | G7: =+G6/10^7 -> 11.129129 | H7: =+H6/10^7 -> 11.129129 | I7: =+I6/10^7 -> 11.129129 | J7: =+J6/10^7 -> 11.129129 | ... AY7: =+AY6/10^7 -> 50.525354

Sheet Share price Daily
A1: =_xll.EQNXTH(B1,"[ADJC];[ADJH];[ADJL];[ADJO];[UCLS];[VOLUME]","2015-Jan-01","Y","All traded days","Asc") -> EQNXTH | B1: =+'Annual Raw'!A1 -> 112455 | L1: =_xll.EQNXTH(B1,"[NADJC];[NADJH];[NADJLOW];[NADJOPEN];[NUCLOSE];[NVOLUME]","2015-Jan-01","Y","All traded days","Asc") -> EQNXTH
A2: Lloyds Metals & Energy Ltd. | L2: Lloyds Metals & Energy Ltd.
A3: DATE | B3: ADJHIGH | C3: ADJCLOSE | D3: ADJLOW | E3: ADJOPEN | F3: CLOSE | G3: VOLUME | L3: DATE | M3: ADJCLOSE | N3: ADJHIGH | O3: ADJLOW | P3: ADJOPEN | Q3: CLOSE | R3: VOLUME
A4: 42005 | B4: 5.3 | C4: 4.75 | D4: 4.75 | E4: 5.3 | F4: 9.5 | G4: 5201 | L4: 45124 | M4: 563.3 | N4: 582.7 | O4: 550.5 | P4: 554 | Q4: 563.3 | R4: 417232
A5: 42006 | B5: 4.9 | C5: 4.9 | D5: 4.85 | E5: 4.89 | F5: 9.8 | G5: 2631 | L5: 45125 | M5: 544.3 | N5: 573.9 | O5: 531 | P5: 573.9 | Q5: 544.3 | R5: 284708
A6: 42009 | B6: 5.24 | C6: 5.22 | D6: 4.775 | E6: 5 | F6: 10.44 | G6: 1316 | L6: 45126 | M6: 566.25 | N6: 572 | O6: 541.25 | P6: 564.7 | Q6: 566.25 | R6: 208966
A7: 42010 | B7: 5.7 | C7: 4.665 | D7: 4.575 | E7: 5.7 | F7: 9.33 | G7: 4452 | L7: 45127 | M7: 564.05 | N7: 572.7 | O7: 557 | P7: 572.7 | Q7: 564.05 | R7: 108284
A8: 42011 | B8: 5.2 | C8: 4.7 | D8: 4.645 | E8: 5 | F8: 9.4 | G8: 1018 | L8: 45128 | M8: 558.7 | N8: 564.5 | O8: 550.05 | P8: 564.5 | Q8: 558.7 | R8: 189224
A9: 42012 | B9: 5 | C9: 4.99 | D9: 4.625 | E9: 4.7 | F9: 9.98 | G9: 812 | L9: 45131 | M9: 575.1 | N9: 580 | O9: 560.05 | P9: 567 | Q9: 575.1 | R9: 6245467
A10: 42013 | B10: 4.9 | C10: 4.675 | D10: 4.655 | E10: 4.655 | F10: 9.35 | G10: 1046 | L10: 45132 | M10: 574.9 | N10: 584.7 | O10: 560.75 | P10: 578 | Q10: 574.9 | R10: 1710743
A11: 42016 | B11: 4.725 | C11: 4.725 | D11: 4.7 | E11: 4.7 | F11: 9.45 | G11: 301 | L11: 45133 | M11: 574.5 | N11: 579.7 | O11: 572 | P11: 572 | Q11: 574.5 | R11: 439499
A12: 42017 | B12: 4.945 | C12: 4.945 | D12: 4.61 | E12: 4.7 | F12: 9.89 | G12: 1970 | L12: 45134 | M12: 575.5 | N12: 580 | O12: 574 | P12: 580 | Q12: 575.5 | R12: 374132
A13: 42018 | B13: 5.21 | C13: 5.15 | D13: 4.995 | E13: 5.21 | F13: 10.3 | G13: 5599 | L13: 45135 | M13: 596.9 | N13: 599 | O13: 573 | P13: 578 | Q13: 596.9 | R13: 553490
A14: 42019 | B14: 5.445 | C14: 5.025 | D14: 4.85 | E14: 4.85 | F14: 10.05 | G14: 3554 | L14: 45138 | M14: 629.05 | N14: 632.2 | O14: 599.5 | P14: 599.75 | Q14: 629.05 | R14: 716078
A15: 42020 | B15: 5.445 | C15: 5.045 | D15: 5 | E15: 5.445 | F15: 10.09 | G15: 3307 | L15: 45139 | M15: 647.6 | N15: 652 | O15: 612.85 | P15: 636 | Q15: 647.6 | R15: 758470
... A727: 43080 | B727: 18.3 | C727: 17.85 | D727: 17.6 | E727: 17.65 | F727: 17.85 | G727: 25056 | L727: 46190 | M727: 1754.3 | N727: 1796 | O727: 1745 | P727: 1770 | Q727: 1754.3 | R727: 437120
A728: 43081 | B728: 18 | C728: 17.65 | D728: 17.25 | E728: 17.45 | F728: 17.65 | G728: 64954
A729: 43082 | B729: 17.6 | C729: 17.25 | D729: 17.1 | E729: 17.25 | F729: 17.25 | G729: 11765
A730: 43083 | B730: 17.7 | C730: 17.4 | D730: 16.2 | E730: 17.7 | F730: 17.4 | G730: 43228
A731: 43084 | B731: 18 | C731: 17.95 | D731: 17.5 | E731: 17.5 | F731: 17.95 | G731: 42838
A732: 43087 | B732: 17.8 | C732: 17.45 | D732: 16.5 | E732: 16.5 | F732: 17.45 | G732: 22244
A733: 43088 | B733: 18.3 | C733: 18 | D733: 17.65 | E733: 18.25 | F733: 18 | G733: 34336
A734: 43089 | B734: 18 | C734: 17.45 | D734: 17.45 | E734: 17.8 | F734: 17.45 | G734: 12235
A735: 43090 | B735: 18.25 | C735: 17.75 | D735: 17.55 | E735: 17.9 | F735: 17.75 | G735: 75930
A736: 43091 | B736: 19.4 | C736: 18.9 | D736: 17.8 | E736: 18.25 | F736: 18.9 | G736: 75211
A737: 43095 | B737: 19.45 | C737: 18.85 | D737: 18.25 | E737: 19.45 | F737: 18.85 | G737: 23766
A738: 43096 | B738: 18.6 | C738: 18.05 | D738: 18 | E738: 18.55 | F738: 18.05 | G738: 23129
A739: 43097 | B739: 18.35 | C739: 17.5 | D739: 17.4 | E739: 18.35 | F739: 17.5 | G739: 42120
... A877: 43299 | B877: 15 | C877: 13.88 | D877: 13.7 | E877: 15 | F877: 13.88 | G877: 22689
A878: 43300 | B878: 14.19 | C878: 13.56 | D878: 13.55 | E878: 13.65 | F878: 13.56 | G878: 14693 | L878: 43292 | M878: 336.15 | N878: 346.95 | O878: 335.1 | P878: 345.85 | Q878: 336.15 | R878: 447233
A879: 43301 | B879: 14 | C879: 13.94 | D879: 13.5 | E879: 13.84 | F879: 13.94 | G879: 7551 | L879: 43293 | M879: 332.55 | N879: 344 | O879: 331.15 | P879: 339.3 | Q879: 332.55 | R879: 622204
A880: 43304 | B880: 14 | C880: 13.8 | D880: 13.5 | E880: 13.5 | F880: 13.8 | G880: 57167 | L880: 43294 | M880: 330 | N880: 334.35 | O880: 325 | P880: 333 | Q880: 330 | R880: 405675
A881: 43305 | B881: 14.6 | C881: 14.41 | D881: 13.65 | E881: 13.65 | F881: 14.41 | G881: 40477 | L881: 43297 | M881: 324.2 | N881: 338 | O881: 320 | P881: 331 | Q881: 324.2 | R881: 903578
A882: 43306 | B882: 14.8 | C882: 14.77 | D882: 14.4 | E882: 14.45 | F882: 14.77 | G882: 19346 | L882: 43298 | M882: 331.15 | N882: 335 | O882: 321 | P882: 323.3 | Q882: 331.15 | R882: 629049
A883: 43307 | B883: 15.8 | C883: 14.45 | D883: 14.4 | E883: 14.99 | F883: 14.45 | G883: 92428 | L883: 43299 | M883: 329.65 | N883: 336.8 | O883: 323.75 | P883: 332.55 | Q883: 329.65 | R883: 435531
A884: 43308 | B884: 15 | C884: 14.6 | D884: 14.45 | E884: 14.45 | F884: 14.6 | G884: 52523 | L884: 43300 | M884: 328.05 | N884: 336.3 | O884: 324.7 | P884: 330.7 | Q884: 328.05 | R884: 345136
A885: 43311 | B885: 16.1 | C885: 15.44 | D885: 14.57 | E885: 14.9 | F885: 15.44 | G885: 170951 | L885: 43301 | M885: 325.8 | N885: 330.5 | O885: 324.4 | P885: 328.5 | Q885: 325.8 | R885: 342316
A886: 43312 | B886: 15.9 | C886: 15.33 | D886: 15 | E886: 15.9 | F886: 15.33 | G886: 39692 | L886: 43304 | M886: 330.9 | N886: 332 | O886: 320.1 | P886: 328 | Q886: 330.9 | R886: 531124
A887: 43313 | B887: 15.6 | C887: 15.2 | D887: 14.75 | E887: 15.6 | F887: 15.2 | G887: 44667 | L887: 43305 | M887: 345.3 | N887: 348 | O887: 328.35 | P887: 331.5 | Q887: 345.3 | R887: 801325
A888: 43314 | B888: 15.45 | C888: 15.3 | D888: 15 | E888: 15.05 | F888: 15.3 | G888: 29467 | L888: 43306 | M888: 355.7 | N888: 360 | O888: 345.3 | P888: 345.3 | Q888: 355.7 | R888: 975818
A889: 43315 | B889: 18.35 | C889: 18.2 | D889: 15.2 | E889: 15.2 | F889: 18.2 | G889: 469592 | L889: 43307 | M889: 352.7 | N889: 360.45 | O889: 349.4 | P889: 360 | Q889: 352.7 | R889: 773683
... A2722: 46021 | B2722: 1388 | C2722: 1292 | D2722: 1277.15 | E2722: 1387.95 | F2722: 1292 | G2722: 84043 | L2722: 46010 | M2722: 936.6 | N2722: 938.9 | O2722: 905 | P2722: 905 | Q2722: 936.6 | R2722: 296202
A2723: 46022 | B2723: 1337.5 | C2723: 1322 | D2723: 1297.95 | E2723: 1297.95 | F2723: 1322 | G2723: 29217
A2724: 46023 | B2724: 1370 | C2724: 1354.2 | D2724: 1315.3 | E2724: 1325.95 | F2724: 1354.2 | G2724: 31523
A2725: 46024 | B2725: 1374.8 | C2725: 1350.05 | D2725: 1345 | E2725: 1358.5 | F2725: 1350.05 | G2725: 27932
A2726: 46027 | B2726: 1350.1 | C2726: 1335.7 | D2726: 1332 | E2726: 1350.05 | F2726: 1335.7 | G2726: 19464
A2727: 46028 | B2727: 1339.75 | C2727: 1318.35 | D2727: 1313.65 | E2727: 1333 | F2727: 1318.35 | G2727: 14127
A2728: 46029 | B2728: 1348.35 | C2728: 1336.5 | D2728: 1310.25 | E2728: 1310.25 | F2728: 1336.5 | G2728: 12751
A2729: 46030 | B2729: 1338 | C2729: 1287.55 | D2729: 1273.1 | E2729: 1336.6 | F2729: 1287.55 | G2729: 22799
A2730: 46031 | B2730: 1295 | C2730: 1267.25 | D2730: 1260.25 | E2730: 1282.45 | F2730: 1267.25 | G2730: 32352
A2731: 46034 | B2731: 1268.8 | C2731: 1254.55 | D2731: 1225 | E2731: 1265 | F2731: 1254.55 | G2731: 26127
A2732: 46035 | B2732: 1283.85 | C2732: 1235.4 | D2732: 1232.6 | E2732: 1283.85 | F2732: 1235.4 | G2732: 17495
A2733: 46036 | B2733: 1248 | C2733: 1240.35 | D2733: 1226.35 | E2733: 1234.9 | F2733: 1240.35 | G2733: 14150
A2734: 46038 | B2734: 1245 | C2734: 1229.2 | D2734: 1223.6 | E2734: 1240.4 | F2734: 1229.2 | G2734: 14750
... A2835: 46190 | B2835: 1795 | C2835: 1753.1 | D2835: 1743.8 | E2835: 1757.9 | F2835: 1753.1 | G2835: 25826

Sheet Sheet2
J19: 219.3 | K19: 186.25 | L19: 186.75
J20: 192.9 | K20: 135.5 | L20: 146.9 | N20: 219.3 | O20: 192.9 | P20: 186 | Q20: 178.7 | R20: 207 | S20: 255.15 | T20: 348.25 | U20: 374 | V20: 495.9 | W20: 659.9 | X20: 613.4 | Y20: 607.9 | Z20: 555.95 | AA20: 497.8 | AB20: 459.9 | AC20: 374 | AD20: 362 | AE20: 341.5 | AF20: 384.2 | AG20: 433.8 | AH20: 460 | AI20: 474.4 | AJ20: 414.4 | AK20: 318.7 | AL20: 303.25 | AM20: 332.7 | AN20: 295 | AO20: 247 | AP20: 214.4 | AQ20: 179.5 | AR20: 97.9 | AS20: 119.1 | AT20: 130.65 | AU20: 148.55 | AV20: 153.8 | AW20: 152.9 | AX20: 136 | AY20: 141.15 | AZ20: 128.1 | BA20: 142.5 | BB20: 143.55 | BC20: 124.5 | BD20: 241 | BE20: 450 | BF20: 503.35
J21: 186 | K21: 145.4 | L21: 169.1 | N21: 186.25 | O21: 135.5 | P21: 145.4 | Q21: 108.95 | R21: 137 | S21: 170 | T21: 243.15 | U21: 307.5 | V21: 325.1 | W21: 463 | X21: 467.05 | Y21: 436.5 | Z21: 467 | AA21: 348.2 | AB21: 325 | AC21: 313.1 | AD21: 285 | AE21: 277.85 | AF21: 327 | AG21: 317 | AH21: 370.7 | AI21: 360 | AJ21: 271.15 | AK21: 233.15 | AL21: 218.8 | AM21: 262 | AN21: 223.6 | AO21: 137.6 | AP21: 142 | AQ21: 59.3 | AR21: 58 | AS21: 72.8 | AT21: 80 | AU21: 107.25 | AV21: 106 | AW21: 125.1 | AX21: 112.25 | AY21: 81.45 | AZ21: 88 | BA21: 90.35 | BB21: 106.05 | BC21: 98.55 | BD21: 119.25 | BE21: 210 | BF21: 349
J22: 178.7 | K22: 108.95 | L22: 139.75 | N22: 186.75 | O22: 146.9 | P22: 169.1 | Q22: 139.75 | R22: 202.15 | S22: 249.05 | T22: 346.4 | U22: 349.2 | V22: 469.9 | W22: 584.8 | X22: 536.15 | Y22: 513.35 | Z22: 474 | AA22: 438.55 | AB22: 355.4 | AC22: 334.95 | AD22: 298.8 | AE22: 328.35 | AF22: 343 | AG22: 389.9 | AH22: 443.05 | AI22: 407.5 | AJ22: 290.1 | AK22: 235.75 | AL22: 292.65 | AM22: 276.1 | AN22: 237.05 | AO22: 190.1 | AP22: 147.2 | AQ22: 71.9 | AR22: 75.2 | AS22: 90.1 | AT22: 117.2 | AU22: 116.3 | AV22: 140.5 | AW22: 128.6 | AX22: 133.65 | AY22: 91.65 | AZ22: 97.65 | BA22: 125 | BB22: 115.35 | BC22: 119.25 | BD22: 219.3 | BE22: 442.65 | BF22: 503.35
J23: 207 | K23: 137 | L23: 202.15
J24: 255.15 | K24: 170 | L24: 249.05
J25: 348.25 | K25: 243.15 | L25: 346.4
J26: 374 | K26: 307.5 | L26: 349.2
J27: 495.9 | K27: 325.1 | L27: 469.9
J28: 659.9 | K28: 463 | L28: 584.8
J29: 613.4 | K29: 467.05 | L29: 536.15
J30: 607.9 | K30: 436.5 | L30: 513.35
J31: 555.95 | K31: 467 | L31: 474
J32: 497.8 | K32: 348.2 | L32: 438.55
J33: 459.9 | K33: 325 | L33: 355.4
J34: 374 | K34: 313.1 | L34: 334.95
... J63: 503.35 | K63: 349 | L63: 503.35
