Workbook

Sheet Template
A1: =+'Annual Raw'!C4 -> Sangam (India) Ltd. | B1: 36951 | C1: =EOMONTH(B1,12) -> 37346 | D1: =EOMONTH(C1,12) -> 37711 | E1: =EOMONTH(D1,12) -> 38077 | F1: =EOMONTH(E1,12) -> 38442 | G1: =EOMONTH(F1,12) -> 38807 | H1: =EOMONTH(G1,12) -> 39172 | I1: =EOMONTH(H1,12) -> 39538 | J1: =EOMONTH(I1,12) -> 39903 | ... AE1: =EOMONTH(AD1,12) -> 47573 | AH1: QTR | AI1: 41061 | AJ1: 41153 | AK1: 41244 | AL1: 41334 | AM1: 41426 | AN1: 41518 | AO1: 41609 | AP1: 41699 | AQ1: 41791 | AR1: 41883 | AS1: 41974 | AT1: 42064 | AU1: 42156 | AV1: 42248 | AW1: 42339 | AX1: 42430 | AY1: 42522 | AZ1: 42614 | BA1: 42705 | BB1: 42795 | BC1: 42887 | BD1: 42979 | BE1: 43070 | BF1: 43160 | BG1: 43252 | BH1: 43344 | BI1: 43435 | BJ1: 43525 | BK1: 43617 | BL1: 43709 | BM1: 43800 | BN1: 43891 | BO1: 43983 | BP1: 44075 | BQ1: =EOMONTH(BP1,3) -> 44196 | BR1: =EOMONTH(BQ1,3) -> 44286 | BS1: =EOMONTH(BR1,3) -> 44377 | BT1: =EOMONTH(BS1,3) -> 44469 | BU1: =EOMONTH(BT1,3) -> 44561 | BV1: =EOMONTH(BU1,3) -> 44651 | BW1: =EOMONTH(BV1,3) -> 44742 | BX1: =EOMONTH(BW1,3) -> 44834 | ... DB1: =EOMONTH(DA1,3) -> 47573 | DE1: HISTORICAL ESTIMATES | DF1: 46112
A2: Presentation Data (Start)
A4: Capacity
A5: Yarn (MT) | V5: 85500 | Y5: 103140 | Z5: 114420 | AA5: 114420 | AB5: 114420 | AC5: 114420 | AD5: 114420 | AE5: 114420 | CE5: 28605 | CF5: 28605 | CG5: 28605 | CH5: 28605 | CI5: 28605 | CJ5: 28605 | CK5: 28605 | CL5: 28605 | CM5: =114420/4 -> 28605 | CN5: =114420/4 -> 28605 | CO5: =114420/4 -> 28605 | CP5: =114420/4 -> 28605 | CQ5: =114420/4 -> 28605 | CR5: =114420/4 -> 28605 | CS5: =114420/4 -> 28605 | CT5: =114420/4 -> 28605 | ... DB5: =114420/4 -> 28605
A6: Green Fibre (MT)(polyster) | AA6: =AA13/AA20 -> 15385.567 | AB6: 15385.567 | AC6: 15385.567 | AD6: 15385.567 | AE6: 15385.567 | CK6: =CK13/CK20 -> 3904.1237 | CL6: =CL13/CL20 -> 3788.6598 | CM6: =+CL6 -> 3788.6598 | CN6: =+CM6 -> 3788.6598 | CO6: =+CN6 -> 3788.6598 | CP6: =+CO6 -> 3788.6598 | CQ6: =+CP6 -> 3788.6598 | CR6: =+CQ6 -> 3788.6598 | CS6: =+CR6 -> 3788.6598 | CT6: =+CS6 -> 3788.6598 | ... DB6: =+DA6 -> 3788.6598
A7: PV Fabric MMPA (Weaving) | V7: 30 | W7: 30 | X7: 32.4 | Y7: 48 | Z7: 48 | AA7: 71 | AB7: 71 | AC7: 71 | AD7: 71 | AE7: 71 | CA7: 12 | CB7: 12 | CC7: 12 | CD7: 12 | CE7: 12 | CF7: 12 | CG7: 12 | CH7: 12 | CI7: 17.75 | CJ7: 17.75 | CK7: 17.75 | CL7: 17.75 | CM7: 17.75 | CN7: 17.75 | CO7: 17.75 | CP7: 17.75 | CQ7: 17.75 | CR7: 17.75 | CS7: 17.75 | CT7: 17.75 | CU7: 17.75 | CV7: 17.75 | CW7: 17.75 | CX7: 17.75 | CY7: 17.75 | CZ7: 17.75 | DA7: 17.75 | DB7: 17.75
A8: Denim Fabric MMPA | V8: 48 | W8: 48 | X8: 48 | Y8: 48 | Z8: 60 | AA8: 60 | AB8: 60 | AC8: 60 | AD8: 60 | AE8: 60 | CA8: 12 | CB8: 12 | CC8: 12 | CD8: 12 | CE8: 15 | CF8: 15 | CG8: 15 | CH8: 15 | CI8: 15 | CJ8: 15 | CK8: 15 | CL8: 15 | CM8: 15 | CN8: 15 | CO8: 15 | CP8: 15 | CQ8: 15 | CR8: 15 | CS8: 15 | CT8: 15 | CU8: 15 | CV8: 15 | CW8: 15 | CX8: 15 | CY8: 15 | CZ8: 15 | DA8: 15 | DB8: 15
A9: Garments (mn pieces pa) | Y9: =+Z9 -> 13.5 | Z9: =+AA9 -> 13.5 | AA9: 13.5 | AB9: =+AA9 -> 13.5 | AC9: =+AB9 -> 13.5 | AD9: =+AC9 -> 13.5 | AE9: =+AD9 -> 13.5 | CA9: =+CB9 -> 3.375 | CB9: =+CC9 -> 3.375 | CC9: =+CD9 -> 3.375 | CD9: =+CE9 -> 3.375 | CE9: =+CF9 -> 3.375 | CF9: =+CG9 -> 3.375 | CG9: =+CH9 -> 3.375 | CH9: =+CI9 -> 3.375 | ... CK9: =+CL9 -> 3.375 | CL9: =+AA9/4 -> 3.375 | CM9: =+CL9 -> 3.375 | CN9: =+CM9 -> 3.375 | CO9: =+CN9 -> 3.375 | CP9: =+CO9 -> 3.375 | CQ9: =+CP9 -> 3.375 | CR9: =+CQ9 -> 3.375 | CS9: =+CR9 -> 3.375 | CT9: =+CS9 -> 3.375 | ... DB9: =+DA9 -> 3.375
A11: Production Quantity
A12: Yarn (MT) -Production Quantity | X12: =SUM(BW12:BZ12) -> 77010 | Y12: =SUM(CA12:CD12) -> 85926 | Z12: =SUM(CE12:CH12) -> 84446 | AA12: =SUM(CI12:CL12) -> 93690 | AB12: =SUM(CM12:CP12) -> 108699 | AC12: =SUM(CQ12:CT12) -> 108699 | AD12: =SUM(CU12:CX12) -> 108699 | AE12: =SUM(CY12:DB12) -> 108699 | BW12: 16489 | BX12: 19507 | BY12: 20108 | BZ12: 20906 | CA12: 21135 | CB12: 21205 | CC12: 20867 | CD12: 22719 | CE12: 20862 | CF12: 21177 | CG12: 20531 | CH12: 21876 | CI12: 21226 | CJ12: 24470 | CK12: 23636 | CL12: 24358 | CM12: =CM5*CM19 -> 27174.75 | CN12: =CM12 -> 27174.75 | CO12: =CN12 -> 27174.75 | CP12: =CO12 -> 27174.75 | CQ12: =CP12 -> 27174.75 | CR12: =CQ12 -> 27174.75 | CS12: =CR12 -> 27174.75 | CT12: =CS12 -> 27174.75 | CU12: =CT12 -> 27174.75 | ... DB12: =DA12 -> 27174.75
A13: Green Fibre (MT) - Production Quantity | X13: =SUM(BW13:BZ13) -> 0 | Y13: =SUM(CA13:CD13) -> 0 | Z13: =SUM(CE13:CH13) -> 0 | AA13: =SUM(CI13:CL13) -> 7462 | AB13: =SUM(CM13:CP13) -> 14700 | AC13: =SUM(CQ13:CT13) -> 14700 | AD13: =SUM(CU13:CX13) -> 14700 | AE13: =SUM(CY13:DB13) -> 14700 | BW13: 0 | BX13: 0 | BY13: 0 | BZ13: 0 | CA13: 0 | CB13: 0 | CC13: 0 | CD13: 0 | CE13: 0 | CF13: 0 | CG13: 0 | CH13: 0 | CI13: 0 | CJ13: 0 | CK13: 3787 | CL13: 3675 | CM13: =CM6*CM20 -> 3675 | CN13: =CM13 -> 3675 | CO13: =CN13 -> 3675 | CP13: =CO13 -> 3675 | CQ13: =CP13 -> 3675 | CR13: =CQ13 -> 3675 | CS13: =CR13 -> 3675 | CT13: =CS13 -> 3675 | CU13: =CT13 -> 3675 | ... DB13: =DA13 -> 3675
A14: PV Fabric MMPA - Production Quantity | X14: =SUM(BW14:BZ14) -> 28.8 | Y14: =SUM(CA14:CD14) -> 36.6 | Z14: =SUM(CE14:CH14) -> 42.7 | AA14: =SUM(CI14:CL14) -> 63.4 | AB14: =SUM(CM14:CP14) -> 68.1245 | AC14: =SUM(CQ14:CT14) -> 68.1245 | AD14: =SUM(CU14:CX14) -> 68.1245 | AE14: =SUM(CY14:DB14) -> 68.1245 | BW14: 6.2 | BX14: 7.9 | BY14: 7.6 | BZ14: 7.1 | CA14: 9.7 | CB14: 7.8 | CC14: 9.5 | CD14: 9.6 | CE14: 9.3 | CF14: 10.8 | CG14: 8.2 | CH14: 14.4 | CI14: 12.9 | CJ14: 16.2 | CK14: 16.8 | CL14: 17.5 | CM14: =CM7*CM21 -> 17.031125 | CN14: =CN7*CN21 -> 17.031125 | CO14: =CO7*CO21 -> 17.031125 | CP14: =CP7*CP21 -> 17.031125 | CQ14: =CQ7*CQ21 -> 17.031125 | CR14: =CR7*CR21 -> 17.031125 | CS14: =CS7*CS21 -> 17.031125 | CT14: =CT7*CT21 -> 17.031125 | ... DB14: =DB7*DB21 -> 17.031125
A15: Denim Fabric MMPA - Production Quantity | X15: =SUM(BW15:BZ15) -> 34.4 | Y15: =SUM(CA15:CD15) -> 42.6 | Z15: =SUM(CE15:CH15) -> 48.8 | AA15: =SUM(CI15:CL15) -> 49.8 | AB15: =SUM(CM15:CP15) -> 58.8 | AC15: =SUM(CQ15:CT15) -> 58.8 | AD15: =SUM(CU15:CX15) -> 58.8 | AE15: =SUM(CY15:DB15) -> 58.8 | BW15: 10.6 | BX15: 7.4 | BY15: 7.2 | BZ15: 9.2 | CA15: 10.3 | CB15: 9.5 | CC15: 10.9 | CD15: 11.9 | CE15: 12.2 | CF15: 11.6 | CG15: 12 | CH15: 13 | CI15: 11.8 | CJ15: 11.2 | CK15: 13.2 | CL15: 13.6 | CM15: =CM8*CM22 -> 14.7 | CN15: =CN8*CN22 -> 14.7 | CO15: =CO8*CO22 -> 14.7 | CP15: =CP8*CP22 -> 14.7 | CQ15: =CQ8*CQ22 -> 14.7 | CR15: =CR8*CR22 -> 14.7 | CS15: =CS8*CS22 -> 14.7 | CT15: =CT8*CT22 -> 14.7 | ... DB15: =DB8*DB22 -> 14.7
A16: Garments (lakh pcs) | X16: =SUM(BW16:BZ16) -> 46 | Y16: =SUM(CA16:CD16) -> 41 | Z16: =SUM(CE16:CH16) -> 39 | AA16: =SUM(CI16:CL16) -> 44 | AB16: =SUM(CM16:CP16) -> 81 | AC16: =SUM(CQ16:CT16) -> 121.5 | AD16: =SUM(CU16:CX16) -> 128.25 | AE16: =SUM(CY16:DB16) -> 128.25 | BW16: 12 | BX16: 11 | BY16: 11 | BZ16: 12 | CA16: 8 | CB16: 9 | CC16: 10 | CD16: 14 | CE16: 12 | CF16: 11 | CG16: 9 | CH16: 7 | CI16: 6 | CJ16: 9 | CK16: 14 | CL16: 15 | CM16: =CM9*CM23*10 -> 18.5625 | CN16: =CN9*CN23*10 -> 18.5625 | CO16: =CO9*CO23*10 -> 20.25 | CP16: =CP9*CP23*10 -> 23.625 | CQ16: =CQ9*CQ23*10 -> 27 | CR16: =CR9*CR23*10 -> 30.375 | CS16: =CS9*CS23*10 -> 32.0625 | CT16: =CT9*CT23*10 -> 32.0625 | ... DB16: =DB9*DB23*10 -> 32.0625
A18: Utilization %
A19: Yarn - Utilization % | X19: =AVERAGE(BW19:BZ19) -> 0.87 | Y19: =AVERAGE(CA19:CD19) -> 0.855 | Z19: =AVERAGE(CE19:CH19) -> 0.7975 | AA19: =AVERAGE(CI19:CL19) -> 0.9 | AB19: =AVERAGE(CM19:CP19) -> 0.95 | AC19: =AVERAGE(CQ19:CT19) -> 0.95 | AD19: =AVERAGE(CU19:CX19) -> 0.95 | AE19: =AVERAGE(CY19:DB19) -> 0.95 | BW19: 0.77 | BX19: 0.91 | BY19: 0.94 | BZ19: 0.86 | CA19: 0.87 | CB19: 0.88 | CC19: 0.8 | CD19: 0.87 | CE19: 0.79 | CF19: 0.78 | CG19: 0.75 | CH19: 0.87 | CI19: 0.82 | CJ19: 0.92 | CK19: 0.91 | CL19: 0.95 | CM19: =+CL19 -> 0.95 | CN19: =+CM19 -> 0.95 | CO19: =+CN19 -> 0.95 | CP19: =+CO19 -> 0.95 | CQ19: =+CP19 -> 0.95 | CR19: =+CQ19 -> 0.95 | CS19: =+CR19 -> 0.95 | CT19: =+CS19 -> 0.95 | ... DB19: =+DA19 -> 0.95
A20: Green Fibre - Utilization % | X20: =SUM(BW20:BZ20) -> 0 | Y20: =SUM(CA20:CD20) -> 0 | Z20: =SUM(CE20:CH20) -> 0 | AA20: =AVERAGE(CI20:CL20) -> 0.485 | AB20: =AVERAGE(CM20:CP20) -> 0.97 | AC20: =AVERAGE(CQ20:CT20) -> 0.97 | AD20: =AVERAGE(CU20:CX20) -> 0.97 | AE20: =AVERAGE(CY20:DB20) -> 0.97 | BW20: 0 | BX20: 0 | BY20: 0 | BZ20: 0 | CA20: 0 | CB20: 0 | CC20: 0 | CD20: 0 | CE20: 0 | CF20: 0 | CG20: 0 | CH20: 0 | CI20: 0 | CJ20: 0 | CK20: 0.97 | CL20: 0.97 | CM20: =+CL20 -> 0.97 | CN20: =+CM20 -> 0.97 | CO20: =+CN20 -> 0.97 | CP20: =+CO20 -> 0.97 | CQ20: =+CP20 -> 0.97 | CR20: =+CQ20 -> 0.97 | CS20: =+CR20 -> 0.97 | CT20: =+CS20 -> 0.97 | ... DB20: =+DA20 -> 0.97
A21: PV Fabric - Utilization % | X21: =AVERAGE(BW21:BZ21) -> 0.8925 | Y21: =AVERAGE(CA21:CD21) -> 0.85 | Z21: =AVERAGE(CE21:CH21) -> 0.875 | AA21: =AVERAGE(CI21:CL21) -> 0.885 | AB21: =AVERAGE(CM21:CP21) -> 0.9595 | AC21: =AVERAGE(CQ21:CT21) -> 0.9595 | AD21: =AVERAGE(CU21:CX21) -> 0.9595 | AE21: =AVERAGE(CY21:DB21) -> 0.9595 | BW21: 0.77 | BX21: 0.98 | BY21: 0.94 | BZ21: 0.88 | CA21: 0.93 | CB21: 0.73 | CC21: 0.87 | CD21: 0.87 | CE21: 0.84 | CF21: 0.96 | CG21: 0.82 | CH21: 0.88 | CI21: 0.75 | CJ21: 0.94 | CK21: 0.9 | CL21: 0.95 | CM21: =+CL21*1.01 -> 0.9595 | CN21: =+CM21 -> 0.9595 | CO21: =+CN21 -> 0.9595 | CP21: =+CO21 -> 0.9595 | CQ21: =+CP21 -> 0.9595 | CR21: =+CQ21 -> 0.9595 | CS21: =+CR21 -> 0.9595 | CT21: =+CS21 -> 0.9595 | CU21: =+CT21 -> 0.9595 | ... DB21: =+DA21 -> 0.9595
A22: Denim Fabric - Utilization % | X22: =AVERAGE(BW22:BZ22) -> 0.715 | Y22: =AVERAGE(CA22:CD22) -> 0.8875 | Z22: =AVERAGE(CE22:CH22) -> 0.915 | AA22: =AVERAGE(CI22:CL22) -> 0.9225 | AB22: =AVERAGE(CM22:CP22) -> 0.98 | AC22: =AVERAGE(CQ22:CT22) -> 0.98 | AD22: =AVERAGE(CU22:CX22) -> 0.98 | AE22: =AVERAGE(CY22:DB22) -> 0.98 | BW22: 0.88 | BX22: 0.62 | BY22: 0.6 | BZ22: 0.76 | CA22: 0.86 | CB22: 0.79 | CC22: 0.91 | CD22: 0.99 | CE22: 0.94 | CF22: 0.9 | CG22: 0.89 | CH22: 0.93 | CI22: 0.92 | CJ22: 0.86 | CK22: 0.93 | CL22: 0.98 | CM22: =+CL22 -> 0.98 | CN22: =+CM22 -> 0.98 | CO22: =+CN22 -> 0.98 | CP22: =+CO22 -> 0.98 | CQ22: =+CP22 -> 0.98 | CR22: =+CQ22 -> 0.98 | CS22: =+CR22 -> 0.98 | CT22: =+CS22 -> 0.98 | ... DB22: =+DA22 -> 0.98
A23: Garments - Utilization % | X23: =AVERAGE(BW23:BZ23) -> 0.595 | Y23: =AVERAGE(CA23:CD23) -> 0.425 | Z23: =AVERAGE(CE23:CH23) -> 0.39 | AA23: =AVERAGE(CI23:CL23) -> 0.3025 | AB23: =AVERAGE(CM23:CP23) -> 0.6 | AC23: =AVERAGE(CQ23:CT23) -> 0.9 | AD23: =AVERAGE(CU23:CX23) -> 0.95 | AE23: =AVERAGE(CY23:DB23) -> 0.95 | BW23: 0.86 | BX23: 0.54 | BY23: 0.55 | BZ23: 0.43 | CA23: 0.31 | CB23: 0.39 | CC23: 0.4 | CD23: 0.6 | CE23: 0.5 | CF23: 0.46 | CG23: 0.36 | CH23: 0.24 | CI23: 0.2 | CJ23: 0.18 | CK23: 0.34 | CL23: 0.49 | CM23: 0.55 | CN23: =+CM23 -> 0.55 | CO23: 0.6 | CP23: 0.7 | CQ23: 0.8 | CR23: 0.9 | CS23: 0.95 | CT23: =+CS23 -> 0.95 | CU23: =+CT23 -> 0.95 | CV23: =+CU23 -> 0.95 | CW23: =+CV23 -> 0.95 | CX23: =+CW23 -> 0.95 | CY23: =+CX23 -> 0.95 | CZ23: =+CY23 -> 0.95 | DA23: =+CZ23 -> 0.95 | DB23: =+DA23 -> 0.95
A25: Unit metrics
A26: Spinning - per kg | Y26: =Y34*10^7/Y12/1000 -> 74.491586 | Z26: =Z34*10^7/Z12/1000 -> 169.41841 | AA26: =AA34*10^7/AA12/1000 -> 174.31685 | AB26: =AB34*10^7/AB12/1000 -> 185.53548 | AC26: =AC34*10^7/AC12/1000 -> 190.50577 | AD26: =AD34*10^7/AD12/1000 -> 193.8424 | AE26: =AE34*10^7/AE12/1000 -> 194.61893 | CC26: =CC34*10^7/CC12/1000 -> 148.8235 | CD26: =CD34*10^7/CD12/1000 -> 145.04441 | CE26: =CE34*10^7/CE12/1000 -> 159.4593 | CF26: =CF34*10^7/CF12/1000 -> 153.13444 | CG26: =CG34*10^7/CG12/1000 -> 187.29477 | CH26: =CH34*10^7/CH12/1000 -> 177.90227 | CI26: =CI34*10^7/CI12/1000 -> 163.71375 | CJ26: =CJ34*10^7/CJ12/1000 -> 167.06727 | ... CL26: =CL34*10^7/CL12/1000 -> 185.07234 | CM26: =+CL26*1.001 -> 185.25741 | CN26: =+CM26*1.001 -> 185.44267 | CO26: =+CN26*1.001 -> 185.62811 | CP26: =+CO26*1.001 -> 185.81374 | CQ26: =+CP26*1.01 -> 187.67188 | CR26: =+CQ26*1.01 -> 189.54859 | CS26: =+CR26*1.01 -> 191.44408 | CT26: =+CS26*1.01 -> 193.35852 | CU26: =+CT26*1.001 -> 193.55188 | CV26: =+CU26*1.001 -> 193.74543 | CW26: =+CV26*1.001 -> 193.93918 | CX26: =+CW26*1.001 -> 194.13312 | CY26: =+CX26*1.001 -> 194.32725 | CZ26: =+CY26*1.001 -> 194.52158 | DA26: =+CZ26*1.001 -> 194.7161 | DB26: =+DA26*1.001 -> 194.91081
A27: PV Fabric - per meter | Y27: =Y36*100/Y14 -> 775.62077 | Z27: =Z36*100/Z14 -> 1179.6993 | AA27: =AA36*100/AA14 -> 993.83407 | AB27: =AB36*100/AB14 -> 911.45007 | AC27: =AC36*100/AC14 -> 915.10134 | AD27: =AD36*100/AD14 -> 918.76724 | AE27: =AE36*100/AE14 -> 922.44783 | CC27: =CC36*10/CC14 -> 143.83368 | CD27: =CD36*10/CD14 -> 153.37 | CE27: =CE36*10/CE14 -> 149.04301 | CF27: =CF36*10/CF14 -> 131.36861 | CG27: =CG36*10/CG14 -> 137.925 | CH27: =CH36*10/CH14 -> 76.489583 | CI27: =CI36*10/CI14 -> 171.42295 | CJ27: =CJ36*10/CJ14 -> 82.50037 | ... CL27: =CL36*10/CL14 -> 90.917486 | CM27: =+CL27*1.001 -> 91.008403 | CN27: =+CM27*1.001 -> 91.099412 | CO27: =+CN27*1.001 -> 91.190511 | CP27: =+CO27*1.001 -> 91.281702 | CQ27: =+CP27*1.001 -> 91.372983 | CR27: =+CQ27*1.001 -> 91.464356 | CS27: =+CR27*1.001 -> 91.555821 | CT27: =+CS27*1.001 -> 91.647376 | ... DB27: =+DA27*1.001 -> 92.383127
A28: Denim - per meter | Y28: =Y35*100/Y15 -> 858.24178 | Z28: =Z35*100/Z15 -> 1714.8344 | AA28: =AA35*100/AA15 -> 1771.0347 | AB28: =AB35*100/AB15 -> 1824.3894 | AC28: =AC35*100/AC15 -> 1831.6979 | AD28: =AD35*100/AD15 -> 1839.0357 | AE28: =AE35*100/AE15 -> 1846.4029 | CC28: =CC35*10/CC15 -> 142.45413 | CD28: =CD35*10/CD15 -> 176.75294 | CE28: =CE35*10/CE15 -> 164.74139 | CF28: =CF35*10/CF15 -> 163.07828 | CG28: =CG35*10/CG15 -> 194.78075 | CH28: =CH35*10/CH15 -> 163.80538 | CI28: =CI35*10/CI15 -> 167.32415 | CJ28: =CJ35*10/CJ15 -> 196.545 | ... CL28: =CL35*10/CL15 -> 181.98353 | CM28: =+CL28*1.001 -> 182.16551 | CN28: =+CM28*1.001 -> 182.34768 | CO28: =+CN28*1.001 -> 182.53003 | CP28: =+CO28*1.001 -> 182.71256 | CQ28: =+CP28*1.001 -> 182.89527 | CR28: =+CQ28*1.001 -> 183.07816 | CS28: =+CR28*1.001 -> 183.26124 | CT28: =+CS28*1.001 -> 183.4445 | ... DB28: =+DA28*1.001 -> 184.91721
A29: Garments (per pcs) | Y29: =Y38*100/Y16 -> 79.647317 | Z29: =Z38*100/Z16 -> 219.76538 | AA29: =AA38*100/AA16 -> 202.93023 | AB29: =AB38*100/AB16 -> 177.24486 | AC29: =AC38*100/AC16 -> 177.94872 | AD29: =AD38*100/AD16 -> 178.64919 | AE29: =AE38*100/AE16 -> 179.36486 | CC29: =CC38*100/CC16 -> 186.33 | CD29: =CD38*100/CD16 -> 100.16 | CE29: =CE38*100/CE16 -> 173.2625 | CF29: =CF38*100/CF16 -> 184.25727 | CG29: =CG38*100/CG16 -> 251.33 | CH29: =CH38*100/CH16 -> 314.7 | CI29: =CI38*100/CI16 -> 394.885 | CJ29: =CJ38*100/CJ16 -> 262.06 | ... CL29: =CL38*100/CL16 -> 176.784 | CM29: =+CL29*1.001 -> 176.96078 | CN29: =+CM29*1.001 -> 177.13774 | CO29: =+CN29*1.001 -> 177.31488 | CP29: =+CO29*1.001 -> 177.4922 | CQ29: =+CP29*1.001 -> 177.66969 | CR29: =+CQ29*1.001 -> 177.84736 | CS29: =+CR29*1.001 -> 178.02521 | CT29: =+CS29*1.001 -> 178.20323 | ... DB29: =+DA29*1.001 -> 179.63386
A31: Revenue Breakup - Segment wise
A32: PV Yarn | Y32: =SUM(CA32:CD32) -> 393.4652 | Z32: =SUM(CE32:CH32) -> 730.6655 | AA32: =SUM(CI32:CL32) -> 744.4301 | CC32: =CC57*34% -> 211.174 | CD32: =CD57*26% -> 182.2912 | CE32: =CE57*26% -> 180.193 | CF32: =CF57*22% -> 148.6342 | CG32: =CG57*27% -> 203.5773 | CH32: =CH57*27% -> 198.261 | CI32: =CI57*19% -> 150.0563 | CJ32: =CJ57*23% -> 180.8214 | CK32: =CK57*26% -> 201.4116 | CL32: =CL57*24% -> 212.1408
A33: Cotton Yarn | Y33: =SUM(CA33:CD33) -> 246.6112 | Z33: =SUM(CE33:CH33) -> 700.0052 | AA33: =SUM(CI33:CL33) -> 888.7445 | CC33: =CC57*16% -> 99.376 | CD33: =CD57*21% -> 147.2352 | CE33: =CE57*22% -> 152.471 | CF33: =CF57*26% -> 175.6586 | CG33: =CG57*24% -> 180.9576 | CH33: =CH57*26% -> 190.918 | CI33: =CI57*25% -> 197.4425 | CJ33: =CJ57*29% -> 227.9922 | CK33: =CK57*29% -> 224.6514 | CL33: =CL57*27% -> 238.6584
A34: Spinning (PV + Cotton Yarn) | Y34: =SUM(Y32:Y33) -> 640.0764 | Z34: =SUM(Z32:Z33) -> 1430.6707 | AA34: =SUM(AA32:AA33) -> 1633.1746 | AB34: =SUM(CM34:CP34) -> 2016.7521 | AC34: =SUM(CQ34:CT34) -> 2070.7786 | AD34: =SUM(CU34:CX34) -> 2107.0475 | AE34: =SUM(CY34:DB34) -> 2115.4884 | CC34: =SUM(CC32:CC33) -> 310.55 | CD34: =SUM(CD32:CD33) -> 329.5264 | CE34: =SUM(CE32:CE33) -> 332.664 | CF34: =SUM(CF32:CF33) -> 324.2928 | CG34: =SUM(CG32:CG33) -> 384.5349 | CH34: =SUM(CH32:CH33) -> 389.179 | CI34: =SUM(CI32:CI33) -> 347.4988 | CJ34: =SUM(CJ32:CJ33) -> 408.8136 | ... CL34: =SUM(CL32:CL33) -> 450.7992 | CM34: =CM26*CM12/10000 -> 503.43238 | CN34: =CN26*CN12/10000 -> 503.93581 | CO34: =CO26*CO12/10000 -> 504.43975 | CP34: =CP26*CP12/10000 -> 504.94419 | CQ34: =CQ26*CQ12/10000 -> 509.99363 | CR34: =CR26*CR12/10000 -> 515.09357 | CS34: =CS26*CS12/10000 -> 520.2445 | CT34: =CT26*CT12/10000 -> 525.44695 | ... DB34: =DB26*DB12/10000 -> 529.66526
A35: Denim Fabric | Y35: =SUM(CA35:CD35) -> 365.611 | Z35: =SUM(CE35:CH35) -> 836.8392 | AA35: =SUM(CI35:CL35) -> 881.9753 | AB35: =SUM(CM35:CP35) -> 1072.741 | AC35: =SUM(CQ35:CT35) -> 1077.0384 | AD35: =SUM(CU35:CX35) -> 1081.353 | AE35: =SUM(CY35:DB35) -> 1085.6849 | CC35: =CC57*25% -> 155.275 | CD35: =CD57*30% -> 210.336 | CE35: =CE57*29% -> 200.9845 | CF35: =CF57*28% -> 189.1708 | CG35: =CG57*31% -> 233.7369 | CH35: =CH57*29% -> 212.947 | CI35: =CI57*25% -> 197.4425 | CJ35: =CJ57*28% -> 220.1304 | CK35: =CK57*28% -> 216.9048 | CL35: =CL57*28% -> 247.4976 | CM35: =CM28*CM15/10 -> 267.7833 | CN35: =CN28*CN15/10 -> 268.05109 | CO35: =CO28*CO15/10 -> 268.31914 | CP35: =CP28*CP15/10 -> 268.58746 | CQ35: =CQ28*CQ15/10 -> 268.85605 | CR35: =CR28*CR15/10 -> 269.1249 | CS35: =CS28*CS15/10 -> 269.39403 | CT35: =CT28*CT15/10 -> 269.66342 | ... DB35: =DB28*DB15/10 -> 271.82829
A36: Woven Fabric with processing | Y36: =SUM(CA36:CD36) -> 283.8772 | Z36: =SUM(CE36:CH36) -> 503.7316 | AA36: =SUM(CI36:CL36) -> 630.0908 | AB36: =SUM(CM36:CP36) -> 620.9208 | AC36: =SUM(CQ36:CT36) -> 623.40821 | AD36: =SUM(CU36:CX36) -> 625.90559 | AE36: =SUM(CY36:DB36) -> 628.41297 | CC36: =CC57*22% -> 136.642 | CD36: =CD57*21% -> 147.2352 | CE36: =CE57*20% -> 138.61 | CF36: =CF57*21% -> 141.8781 | CG36: =CG57*15% -> 113.0985 | CH36: =CH57*15% -> 110.145 | CI36: =CI57*28% -> 221.1356 | CJ36: =CJ57*17% -> 133.6506 | CK36: =CK57*15% -> 116.199 | CL36: =CL57*18% -> 159.1056 | CM36: =CM27*CM14/10 -> 154.99755 | CN36: =CN27*CN14/10 -> 155.15255 | CO36: =CO27*CO14/10 -> 155.3077 | CP36: =CP27*CP14/10 -> 155.46301 | CQ36: =CQ27*CQ14/10 -> 155.61847 | CR36: =CR27*CR14/10 -> 155.77409 | CS36: =CS27*CS14/10 -> 155.92986 | CT36: =CT27*CT14/10 -> 156.08579 | ... DB36: =DB27*DB14/10 -> 157.33886
A37: Knitting & Weaving (Denim + Woven Fabric) | Y37: =SUM(Y35:Y36) -> 649.4882 | Z37: =SUM(Z35:Z36) -> 1340.5708 | AA37: =SUM(AA35:AA36) -> 1512.0661 | AB37: =SUM(AB35:AB36) -> 1693.6618 | AC37: =SUM(AC35:AC36) -> 1700.4466 | AD37: =SUM(AD35:AD36) -> 1707.2586 | AE37: =SUM(AE35:AE36) -> 1714.0979 | CC37: =SUM(CC35:CC36) -> 291.917 | CD37: =SUM(CD35:CD36) -> 357.5712 | CE37: =SUM(CE35:CE36) -> 339.5945 | CF37: =SUM(CF35:CF36) -> 331.0489 | CG37: =SUM(CG35:CG36) -> 346.8354 | CH37: =SUM(CH35:CH36) -> 323.092 | CI37: =SUM(CI35:CI36) -> 418.5781 | CJ37: =SUM(CJ35:CJ36) -> 353.781 | ... DB37: =SUM(DB35:DB36) -> 429.16715
A38: Garments | Y38: =SUM(CA38:CD38) -> 32.6554 | Z38: =SUM(CE38:CH38) -> 85.7085 | AA38: =SUM(CI38:CL38) -> 89.2893 | AB38: =SUM(CM38:CP38) -> 143.56833 | AC38: =SUM(CQ38:CT38) -> 216.20769 | AD38: =SUM(CU38:CX38) -> 229.11758 | AE38: =SUM(CY38:DB38) -> 230.03543 | CC38: =CC57*3% -> 18.633 | CD38: =CD57*2% -> 14.0224 | CE38: =CE57*3% -> 20.7915 | CF38: =CF57*3% -> 20.2683 | CG38: =CG57*3% -> 22.6197 | CH38: =CH57*3% -> 22.029 | CI38: =CI57*3% -> 23.6931 | CJ38: =CJ57*3% -> 23.5854 | CK38: =CK57*2% -> 15.4932 | CL38: =CL57*3% -> 26.5176 | CM38: =CM29*CM16/100 -> 32.848346 | CN38: =CN29*CN16/100 -> 32.881194 | CO38: =CO29*CO16/100 -> 35.906264 | CP38: =CP29*CP16/100 -> 41.932532 | CQ38: =CQ29*CQ16/100 -> 47.970816 | CR38: =CR29*CR16/100 -> 54.021135 | CS38: =CS29*CS16/100 -> 57.079332 | CT38: =CT29*CT16/100 -> 57.136411 | ... DB38: =DB29*DB16/100 -> 57.595106
A39: Total | Y39: =Y38+Y37+Y34 -> 1322.22 | Z39: =Z38+Z37+Z34 -> 2856.95 | AA39: =AA38+AA37+AA34 -> 3234.53 | AB39: =AB38+AB37+AB34 -> 3853.9823 | AC39: =AC38+AC37+AC34 -> 3987.4329 | AD39: =AD38+AD37+AD34 -> 4043.4237 | AE39: =AE38+AE37+AE34 -> 4059.6217 | CC39: =CC38+CC37+CC34 -> 621.1 | CD39: =CD38+CD37+CD34 -> 701.12 | CE39: =CE38+CE37+CE34 -> 693.05 | CF39: =CF38+CF37+CF34 -> 675.61 | CG39: =CG38+CG37+CG34 -> 753.99 | CH39: =CH38+CH37+CH34 -> 734.3 | CI39: =CI38+CI37+CI34 -> 789.77 | CJ39: =CJ38+CJ37+CJ34 -> 786.18 | ... DB39: =DB38+DB37+DB34 -> 1016.4275
A40: Checksum | CC40: =CC57-CC39 -> 0 | CD40: =CD57-CD39 -> 0 | CE40: =CE57-CE39 -> 0 | CF40: =CF57-CF39 -> 0 | CG40: =CG57-CG39 -> 0 | CH40: =CH57-CH39 -> 0 | CI40: =CI57-CI39 -> 0 | CJ40: =CJ57-CJ39 -> 0 | ... CL40: =CL57-CL39 -> 0
A42: Revenue Growth % y-o-y
A43: PV Yarn - % | Z43: =Z32/Y32-1 -> 0.85700158 | AA43: =AA32/Z32-1 -> 0.018838442 | CG43: =CG32/CC32-1 -> -0.035973652 | CH43: =CH32/CD32-1 -> 0.087605984 | CI43: =CI32/CE32-1 -> -0.16724679 | CJ43: =CJ32/CF32-1 -> 0.21655312 | CK43: =CK32/CG32-1 -> -0.010638219 | CL43: =CL32/CH32-1 -> 0.070007717
A44: Cotton Yarn - % | Z44: =Z33/Y33-1 -> 1.8384972 | AA44: =AA33/Z33-1 -> 0.26962557 | CG44: =CG33/CC33-1 -> 0.82093866 | CH44: =CH33/CD33-1 -> 0.29668721 | CI44: =CI33/CE33-1 -> 0.29495117 | CJ44: =CJ33/CF33-1 -> 0.29792791 | CK44: =CK33/CG33-1 -> 0.24145877 | CL44: =CL33/CH33-1 -> 0.25005709
A45: Spinning (PV + Cotton Yarn) - % | Z45: =Z34/Y34-1 -> 1.2351561 | AA45: =AA34/Z34-1 -> 0.14154473 | AB45: =AB34/AA34-1 -> 0.23486621 | AC45: =AC34/AB34-1 -> 0.026788873 | AD45: =AD34/AC34-1 -> 0.017514605 | AE45: =AE34/AD34-1 -> 0.004006004 | CG45: =CG34/CC34-1 -> 0.23823829 | CH45: =CH34/CD34-1 -> 0.18102525 | CI45: =CI34/CE34-1 -> 0.044593945 | CJ45: =CJ34/CF34-1 -> 0.26063113 | CK45: =CK34/CG34-1 -> 0.10799566 | CL45: =CL34/CH34-1 -> 0.15833383 | CM45: =CM34/CI34-1 -> 0.44873128 | CN45: =CN34/CJ34-1 -> 0.23267869 | ... DB45: =DB34/CX34-1 -> 0.004006004
A46: Denim Fabric - % | Z46: =Z35/Y35-1 -> 1.2888786 | AA46: =AA35/Z35-1 -> 0.053936407 | AB46: =AB35/AA35-1 -> 0.21629368 | AC46: =AC35/AB35-1 -> 0.004006004 | AD46: =AD35/AC35-1 -> 0.004006004 | AE46: =AE35/AD35-1 -> 0.004006004 | CG46: =CG35/CC35-1 -> 0.50530929 | CH46: =CH35/CD35-1 -> 0.012413472 | CI46: =CI35/CE35-1 -> -0.01762325 | CJ46: =CJ35/CF35-1 -> 0.16365951 | CK46: =CK35/CG35-1 -> -0.07201302 | CL46: =CL35/CH35-1 -> 0.16224976 | CM46: =CM35/CI35-1 -> 0.35625969 | CN46: =CN35/CJ35-1 -> 0.21769227 | ... DB46: =DB35/CX35-1 -> 0.004006004
A47: Woven Fabric with processing -% | Z47: =Z36/Y36-1 -> 0.77447009 | AA47: =AA36/Z36-1 -> 0.25084628 | AB47: =AB36/AA36-1 -> -0.014553455 | AC47: =AC36/AB36-1 -> 0.004006004 | AD47: =AD36/AC36-1 -> 0.004006004 | AE47: =AE36/AD36-1 -> 0.004006004 | CG47: =CG36/CC36-1 -> -0.17230061 | CH47: =CH36/CD36-1 -> -0.25191123 | CI47: =CI36/CE36-1 -> 0.59537984 | CJ47: =CJ36/CF36-1 -> -0.057989922 | CK47: =CK36/CG36-1 -> 0.027414157 | CL47: =CL36/CH36-1 -> 0.44451042 | CM47: =CM36/CI36-1 -> -0.29908369 | CN47: =CN36/CJ36-1 -> 0.16088178 | ... DB47: =DB36/CX36-1 -> 0.004006004
A48: Knitting & Weaving (Denim + Woven Fabric) - % | Z48: =Z37/Y37-1 -> 1.0640418 | AA48: =AA37/Z37-1 -> 0.12792707 | AB48: =AB37/AA37-1 -> 0.12009772 | AC48: =AC37/AB37-1 -> 0.004006004 | AD48: =AD37/AC37-1 -> 0.004006004 | AE48: =AE37/AD37-1 -> 0.004006004 | CG48: =CG37/CC37-1 -> 0.18813019 | CH48: =CH37/CD37-1 -> -0.09642611 | CI48: =CI37/CE37-1 -> 0.23258209 | CJ48: =CJ37/CF37-1 -> 0.068666895 | CK48: =CK37/CG37-1 -> -0.039591114 | CL48: =CL37/CH37-1 -> 0.25847499 | CM48: =CM37/CI37-1 -> 0.010040547 | CN48: =CN37/CJ37-1 -> 0.19623053 | ... DB48: =DB37/CX37-1 -> 0.004006004
A49: Garments - % | Z49: =Z38/Y38-1 -> 1.6246348 | AA49: =AA38/Z38-1 -> 0.04177882 | AB49: =AB38/AA38-1 -> 0.60790078 | AC49: =AC38/AB38-1 -> 0.50595669 | AD49: =AD38/AC38-1 -> 0.059710576 | AE49: =AE38/AD38-1 -> 0.004006004 | CG49: =CG38/CC38-1 -> 0.2139591 | CH49: =CH38/CD38-1 -> 0.57098642 | CI49: =CI38/CE38-1 -> 0.13955703 | CJ49: =CJ38/CF38-1 -> 0.16365951 | CK49: =CK38/CG38-1 -> -0.31505723 | CL49: =CL38/CH38-1 -> 0.20375868 | CM49: =CM38/CI38-1 -> 0.38640978 | CN49: =CN38/CJ38-1 -> 0.3941334 | ... DB49: =DB38/CX38-1 -> 0.004006004
A50: Total - % | Z50: =Z39/Y39-1 -> 1.1607221 | AA50: =AA39/Z39-1 -> 0.13216192 | AB50: =AB39/AA39-1 -> 0.19151229 | AC50: =AC39/AB39-1 -> 0.034626701 | AD50: =AD39/AC39-1 -> 0.014041804 | AE50: =AE39/AD39-1 -> 0.004006004 | CG50: =CG39/CC39-1 -> 0.2139591 | CH50: =CH39/CD39-1 -> 0.047324281 | CI50: =CI39/CE39-1 -> 0.13955703 | CJ50: =CJ39/CF39-1 -> 0.16365951 | CK50: =CK39/CG39-1 -> 0.027414157 | CL50: =CL39/CH39-1 -> 0.20375868 | CM50: =CM39/CI39-1 -> 0.21435555 | CN50: =CN39/CJ39-1 -> 0.22112066 | ... DB50: =DB39/CX39-1 -> 0.004006004
A53: Presentation Data (End)
A54: Profit & Loss- Annual (Start)
A55: Gross Revenue | B55: ='Annual Raw'!C6 -> 228.61852 | C55: ='Annual Raw'!D6 -> 217.23503 | D55: ='Annual Raw'!E6 -> 225.45649 | E55: ='Annual Raw'!F6 -> 298.60219 | F55: ='Annual Raw'!G6 -> 311.36159 | G55: ='Annual Raw'!H6 -> 363.44456 | H55: ='Annual Raw'!I6 -> 554.76021 | I55: ='Annual Raw'!J6 -> 695.05185 | ... AA55: ='Annual Raw'!AB6 -> 3234.53 | AB55: =+SUM(CM55:CP55) -> 3853.9823 | AC55: =+SUM(CQ55:CT55) -> 3987.4329 | AD55: =+SUM(CU55:CX55) -> 4043.4237 | AE55: =+SUM(CY55:DB55) -> 4059.6217 | AI55: ='QTR Raw'!C6+'QTR Raw'!C8 -> 412.54 | AJ55: ='QTR Raw'!D6+'QTR Raw'!D8 -> 385.66 | AK55: ='QTR Raw'!E6+'QTR Raw'!E8 -> 329.46 | AL55: ='QTR Raw'!F6+'QTR Raw'!F8 -> 357.26 | AM55: ='QTR Raw'!G6+'QTR Raw'!G8 -> 367.62 | AN55: ='QTR Raw'!H6+'QTR Raw'!H8 -> 353.04 | AO55: ='QTR Raw'!I6+'QTR Raw'!I8 -> 349.58 | AP55: ='QTR Raw'!J6+'QTR Raw'!J8 -> 369.38 | ... CL55: ='QTR Raw'!BF6+'QTR Raw'!BF8 -> 883.92 | CM55: =CM39 -> 959.06158 | CN55: =CN39 -> 960.02064 | CO55: =CO39 -> 963.97285 | CP55: =CP39 -> 970.92718 | CQ55: =CQ39 -> 982.43896 | CR55: =CR39 -> 994.01369 | CS55: =CS39 -> 1002.6477 | CT55: =CT39 -> 1008.3326 | ... DB55: =DB39 -> 1016.4275 | DF55: 803.68308
A56: Less: Exise Duty | B56: ='Annual Raw'!C7+'Annual Raw'!C8+'Annual Raw'!C9 -> 45.12743 | C56: ='Annual Raw'!D7+'Annual Raw'!D8+'Annual Raw'!D9 -> 27.553137 | D56: ='Annual Raw'!E7+'Annual Raw'!E8+'Annual Raw'!E9 -> 29.747753 | E56: ='Annual Raw'!F7+'Annual Raw'!F8+'Annual Raw'!F9 -> 31.447642 | F56: ='Annual Raw'!G7+'Annual Raw'!G8+'Annual Raw'!G9 -> 21.784497 | G56: ='Annual Raw'!H7+'Annual Raw'!H8+'Annual Raw'!H9 -> 16.657603 | H56: ='Annual Raw'!I7+'Annual Raw'!I8+'Annual Raw'!I9 -> 2.4015717 | I56: ='Annual Raw'!J7+'Annual Raw'!J8+'Annual Raw'!J9 -> 1.6698029 | ... AA56: ='Annual Raw'!AB7+'Annual Raw'!AB8+'Annual Raw'!AB9 -> 0 | AB56: =+SUM(CM56:CP56) -> 0 | AC56: =+SUM(CQ56:CT56) -> 0 | AD56: =+SUM(CU56:CX56) -> 0 | AE56: =+SUM(CY56:DB56) -> 0 | AI56: =+'QTR Raw'!C20+'QTR Raw'!C19+'QTR Raw'!C13+'QTR Raw'!C7 -> 0 | AJ56: =+'QTR Raw'!D20+'QTR Raw'!D19+'QTR Raw'!D13+'QTR Raw'!D7 -> 0 | AK56: =+'QTR Raw'!E20+'QTR Raw'!E19+'QTR Raw'!E13+'QTR Raw'!E7 -> 0 | AL56: =+'QTR Raw'!F20+'QTR Raw'!F19+'QTR Raw'!F13+'QTR Raw'!F7 -> 0 | AM56: =+'QTR Raw'!G20+'QTR Raw'!G19+'QTR Raw'!G13+'QTR Raw'!G7 -> 0 | AN56: =+'QTR Raw'!H20+'QTR Raw'!H19+'QTR Raw'!H13+'QTR Raw'!H7 -> 0 | AO56: =+'QTR Raw'!I20+'QTR Raw'!I19+'QTR Raw'!I13+'QTR Raw'!I7 -> 0 | AP56: =+'QTR Raw'!J20+'QTR Raw'!J19+'QTR Raw'!J13+'QTR Raw'!J7 -> 0 | ... CL56: =+'QTR Raw'!BF20+'QTR Raw'!BF19+'QTR Raw'!BF13+'QTR Raw'!BF7 -> 0 | DF56: 0
A57: Net Revenue | B57: =+B55-B56 -> 183.49109 | C57: =+C55-C56 -> 189.68189 | D57: =+D55-D56 -> 195.70873 | E57: =+E55-E56 -> 267.15454 | F57: =+F55-F56 -> 289.57709 | G57: =+G55-G56 -> 346.78696 | H57: =+H55-H56 -> 552.35864 | I57: =+I55-I56 -> 693.38204 | ... AE57: =+AE55-AE56 -> 4059.6217 | AI57: =+AI55-AI56 -> 412.54 | AJ57: =+AJ55-AJ56 -> 385.66 | AK57: =+AK55-AK56 -> 329.46 | AL57: =+AL55-AL56 -> 357.26 | AM57: =+AM55-AM56 -> 367.62 | AN57: =+AN55-AN56 -> 353.04 | AO57: =+AO55-AO56 -> 349.58 | AP57: =+AP55-AP56 -> 369.38 | ... DB57: =+DB55-DB56 -> 1016.4275 | DF57: 803.68308
A58: Net Revenue YOY% | C58: =C57/B57-1 -> 0.033738993 | D58: =D57/C57-1 -> 0.031773434 | E58: =E57/D57-1 -> 0.36506194 | F58: =F57/E57-1 -> 0.083930999 | G58: =G57/F57-1 -> 0.19756352 | H58: =H57/G57-1 -> 0.59278952 | I58: =I57/H57-1 -> 0.25531131 | J58: =J57/I57-1 -> 0.079159641 | ... AE58: =AE57/AD57-1 -> 0.004006004 | AM58: =+IF(AI57<0,1-AM57/AI57,AM57/AI57-1) -> -0.10888641 | AN58: =+IF(AJ57<0,1-AN57/AJ57,AN57/AJ57-1) -> -0.084582275 | AO58: =+IF(AK57<0,1-AO57/AK57,AO57/AK57-1) -> 0.061069629 | AP58: =+IF(AL57<0,1-AP57/AL57,AP57/AL57-1) -> 0.033924873 | AQ58: =+IF(AM57<0,1-AQ57/AM57,AQ57/AM57-1) -> 0.020156684 | AR58: =+IF(AN57<0,1-AR57/AN57,AR57/AN57-1) -> 0.050277589 | AS58: =+IF(AO57<0,1-AS57/AO57,AS57/AO57-1) -> 0.055609589 | AT58: =+IF(AP57<0,1-AT57/AP57,AT57/AP57-1) -> -0.019708701 | ... CL58: =+IF(CH57<0,1-CL57/CH57,CL57/CH57-1) -> 0.20375868 | CM58: =+AVERAGE(CI58:CL58) -> 0.13359734 | CN58: =+AVERAGE(CJ58:CM58) -> 0.13210742 | CO58: =+AVERAGE(CK58:CN58) -> 0.1242194 | CP58: =+AVERAGE(CL58:CO58) -> 0.14842071 | CQ58: =+AVERAGE(CM58:CP58) -> 0.13458622 | CR58: =+AVERAGE(CN58:CQ58) -> 0.13483344 | CS58: =+AVERAGE(CO58:CR58) -> 0.13551494 | CT58: =+AVERAGE(CP58:CS58) -> 0.13833883 | ... DB58: =+AVERAGE(CX58:DA58) -> 0.13644526 | DF58: 0.094488744
A59: Net Revenue QOQ% | AJ59: =+IF(AI57<0,1-AJ57/AI57,AJ57/AI57-1) -> -0.065157318 | AK59: =+IF(AJ57<0,1-AK57/AJ57,AK57/AJ57-1) -> -0.14572421 | AL59: =+IF(AK57<0,1-AL57/AK57,AL57/AK57-1) -> 0.084380501 | AM59: =+IF(AL57<0,1-AM57/AL57,AM57/AL57-1) -> 0.028998488 | AN59: =+IF(AM57<0,1-AN57/AM57,AN57/AM57-1) -> -0.039660519 | AO59: =+IF(AN57<0,1-AO57/AN57,AO57/AN57-1) -> -0.0098005892 | AP59: =+IF(AO57<0,1-AP57/AO57,AP57/AO57-1) -> 0.056639396 | AQ59: =+IF(AP57<0,1-AQ57/AP57,AQ57/AP57-1) -> 0.015295901 | ... CL59: =+IF(CK57<0,1-CL57/CK57,CL57/CK57-1) -> 0.14104252 | CM59: =+CM57/CL57-1 -> 0.085009479 | CN59: =+CN57/CM57-1 -> 0.001 | CO59: =+CO57/CN57-1 -> 0.0041167962 | CP59: =+CP57/CO57-1 -> 0.0072142431 | CQ59: =+CQ57/CP57-1 -> 0.011856478 | CR59: =+CR57/CQ57-1 -> 0.011781628 | CS59: =+CS57/CR57-1 -> 0.0086860284 | CT59: =+CT57/CS57-1 -> 0.0056698361 | ... DB59: =+DB57/DA57-1 -> 0.001 | DF59: 0.037465578
A60: Increase/Decrease in Stock | B60: ='Annual Raw'!C11 -> -0.5067473 | C60: ='Annual Raw'!D11 -> 3.5157219 | D60: ='Annual Raw'!E11 -> -7.2267181 | E60: ='Annual Raw'!F11 -> -2.8291686 | F60: ='Annual Raw'!G11 -> -5.3305705 | G60: ='Annual Raw'!H11 -> -6.716897 | H60: ='Annual Raw'!I11 -> -20.445548 | I60: ='Annual Raw'!J11 -> -21.801716 | ... AA60: ='Annual Raw'!AB11 -> 61.25 | AB60: =+SUM(CM60:CP60) -> 0 | AC60: =+SUM(CQ60:CT60) -> 0 | AD60: =+SUM(CU60:CX60) -> 0 | AE60: =+SUM(CY60:DB60) -> 0 | AI60: ='QTR Raw'!C10 -> 11.8 | AJ60: ='QTR Raw'!D10 -> -23.48 | AK60: ='QTR Raw'!E10 -> 9.31 | AL60: ='QTR Raw'!F10 -> -14.47 | AM60: ='QTR Raw'!G10 -> 22.28 | AN60: ='QTR Raw'!H10 -> -21.76 | AO60: ='QTR Raw'!I10 -> -13.23 | AP60: ='QTR Raw'!J10 -> 1.59 | ... CL60: ='QTR Raw'!BF10 -> 59.57 | DF60: 61.03
A61: Purchase of Finished Goods | B61: 0 | C61: 0 | D61: 0 | E61: 0 | F61: 0 | G61: 0 | H61: 0 | I61: 0 | J61: 0 | K61: 0 | L61: 0 | M61: 0 | N61: 0 | O61: 0 | P61: 0 | Q61: 0 | R61: 0 | S61: 0 | T61: 0 | U61: 0 | V61: 0 | W61: 0 | X61: 0 | Y61: 0 | Z61: 0 | AA61: 0 | AB61: =+SUM(CM61:CP61) -> 0 | AC61: =+SUM(CQ61:CT61) -> 0 | AD61: =+SUM(CU61:CX61) -> 0 | AE61: =+SUM(CY61:DB61) -> 0 | AI61: ='QTR Raw'!C12 -> 0 | AJ61: ='QTR Raw'!D12 -> 0 | AK61: ='QTR Raw'!E12 -> 0 | AL61: ='QTR Raw'!F12 -> 0 | AM61: ='QTR Raw'!G12 -> 0 | AN61: ='QTR Raw'!H12 -> 0 | AO61: ='QTR Raw'!I12 -> 0 | AP61: ='QTR Raw'!J12 -> 0 | ... CL61: ='QTR Raw'!BF12 -> 10.59 | DF61: 116.44
A62: Consumption Of Dyes &Chemicals | R62: 64.62 | S62: 63.51 | T62: 80 | U62: 80.74 | V62: 52.31 | W62: 96.91 | X62: 126.99 | Y62: 113.91 | Z62: 113.44 | AA62: 113.44
A63: Raw Material Consumed | B63: ='Annual Raw'!C12 -> 108.21479 | C63: ='Annual Raw'!D12 -> 106.92158 | D63: ='Annual Raw'!E12 -> 120.69857 | E63: ='Annual Raw'!F12 -> 163.01752 | F63: ='Annual Raw'!G12 -> 177.16084 | G63: ='Annual Raw'!H12 -> 202.08444 | H63: ='Annual Raw'!I12 -> 331.10324 | I63: ='Annual Raw'!J12 -> 434.69338 | ... AA63: ='Annual Raw'!AB12 -> 1762.08 | AB63: =+SUM(CM63:CP63) -> 2286.0944 | AC63: =+SUM(CQ63:CT63) -> 2360.9699 | AD63: =+SUM(CU63:CX63) -> 2393.6294 | AE63: =+SUM(CY63:DB63) -> 2403.1885 | AI63: ='QTR Raw'!C11 -> 203.73 | AJ63: ='QTR Raw'!D11 -> 225.81 | AK63: ='QTR Raw'!E11 -> 183.37 | AL63: ='QTR Raw'!F11 -> 221.43 | AM63: ='QTR Raw'!G11 -> 186.1 | AN63: ='QTR Raw'!H11 -> 210.12 | AO63: ='QTR Raw'!I11 -> 214.51 | AP63: ='QTR Raw'!J11 -> 216.54 | ... CL63: ='QTR Raw'!BF11 -> 452.79 | CM63: =+CM57-CM64 -> 575.7014 | CN63: =+CN57-CN64 -> 567.15722 | CO63: =+CO57-CO64 -> 567.59963 | CP63: =+CP57-CP64 -> 575.63618 | CQ63: =+CQ57-CQ64 -> 582.7674 | CR63: =+CR57-CR64 -> 587.87111 | CS63: =+CS57-CS64 -> 593.13665 | CT63: =+CT57-CT64 -> 597.19475 | ... DB63: =+DB57-DB64 -> 601.71101 | DF63: 491.61123
A64: Gross Profit | B64: =B57-B60-B63-B61-B62 -> 75.783041 | C64: =C57-C60-C63-C61-C62 -> 79.244591 | D64: =D57-D60-D63-D61-D62 -> 82.236881 | E64: =E57-E60-E63-E61-E62 -> 106.96619 | F64: =F57-F60-F63-F61-F62 -> 117.74682 | G64: =G57-G60-G63-G61-G62 -> 151.41942 | H64: =H57-H60-H63-H61-H62 -> 241.70095 | I64: =I57-I60-I63-I61-I62 -> 280.49038 | ... AE64: =AE57-AE60-AE63-AE61-AE62 -> 1656.4331 | AI64: =AI57-AI60-AI63-AI61 -> 197.01 | AJ64: =AJ57-AJ60-AJ63-AJ61 -> 183.33 | AK64: =AK57-AK60-AK63-AK61 -> 136.78 | AL64: =AL57-AL60-AL63-AL61 -> 150.3 | AM64: =AM57-AM60-AM63-AM61 -> 159.24 | AN64: =AN57-AN60-AN63-AN61 -> 164.68 | AO64: =AO57-AO60-AO63-AO61 -> 148.3 | AP64: =AP57-AP60-AP63-AP61 -> 151.25 | ... BV64: =BV57-BV60-BV63-BV61 -> 316.98 | BW64: =BW57-BW60-BW63-BW61-BW62 -> 314.71 | BX64: =BX57-BX60-BX63-BX61-BX62 -> 317.77 | BY64: =BY57-BY60-BY63-BY61-BY62 -> 263.92 | BZ64: =BZ57-BZ60-BZ63-BZ61-BZ62 -> 282.55 | CA64: =CA57-CA60-CA63-CA61-CA62 -> 273.46 | CB64: =CB57-CB60-CB63-CB61-CB62 -> 258.71 | CC64: =CC57-CC60-CC63-CC61-CC62 -> 245.93 | CD64: =CD57-CD60-CD63-CD61-CD62 -> 294.18 | ... CL64: =CL57-CL60-CL63-CL61-CL62 -> 360.97 | CM64: =+CM65*CM57 -> 383.36018 | CN64: =+CN65*CN57 -> 392.86342 | CO64: =+CO65*CO57 -> 396.37322 | CP64: =+CP65*CP57 -> 395.29101 | CQ64: =+CQ65*CQ57 -> 399.67156 | CR64: =+CR65*CR57 -> 406.14258 | CS64: =+CS65*CS57 -> 409.51107 | CT64: =+CT65*CT57 -> 411.13782 | ... DB64: =+DB65*DB57 -> 414.71652 | DF64: 312.07186
A65: GP% | B65: =B64/B57 -> 0.41300666 | C65: =C64/C57 -> 0.41777626 | D65: =D64/D57 -> 0.42020036 | E65: =E64/E57 -> 0.40039069 | F65: =F64/F57 -> 0.40661649 | G65: =G64/G57 -> 0.43663527 | H65: =H64/H57 -> 0.43757974 | I65: =I64/I57 -> 0.40452502 | ... AE65: =AE64/AE57 -> 0.40802648 | AI65: =AI64/AI57 -> 0.47755369 | AJ65: =AJ64/AJ57 -> 0.4753669 | AK65: =AK64/AK57 -> 0.41516421 | AL65: =AL64/AL57 -> 0.42070201 | AM65: =AM64/AM57 -> 0.43316468 | AN65: =AN64/AN57 -> 0.46646272 | AO65: =AO64/AO57 -> 0.42422335 | AP65: =AP64/AP57 -> 0.40946992 | ... CL65: =CL64/CL57 -> 0.40837406 | CM65: =AVERAGE(CI65:CL65) -> 0.39972426 | CN65: =AVERAGE(CJ65:CM65) -> 0.40922393 | CO65: =AVERAGE(CK65:CN65) -> 0.41118712 | CP65: =AVERAGE(CL65:CO65) -> 0.40712734 | CQ65: =AVERAGE(CM65:CP65) -> 0.40681566 | CR65: =AVERAGE(CN65:CQ65) -> 0.40858852 | CS65: =AVERAGE(CO65:CR65) -> 0.40842966 | CT65: =AVERAGE(CP65:CS65) -> 0.4077403 | ... DB65: =AVERAGE(CX65:DA65) -> 0.40801386 | DF65: 0.38830213
A66: GP YOY% | C66: =+IF(B64<0,1-C64/B64,C64/B64-1) -> 0.045677103 | D66: =+IF(C64<0,1-D64/C64,D64/C64-1) -> 0.037760177 | E66: =+IF(D64<0,1-E64/D64,E64/D64-1) -> 0.30070828 | F66: =+IF(E64<0,1-F64/E64,F64/E64-1) -> 0.1007854 | G66: =+IF(F64<0,1-G64/F64,G64/F64-1) -> 0.28597457 | H66: =+IF(G64<0,1-H64/G64,H64/G64-1) -> 0.59623482 | I66: =+IF(H64<0,1-I64/H64,I64/H64-1) -> 0.16048524 | J66: =+IF(I64<0,1-J64/I64,J64/I64-1) -> 0.11607746 | ... AE66: =+IF(AD64<0,1-AE64/AD64,AE64/AD64-1) -> 0.0040240502 | AM66: =+IF(AI64<0,1-AM64/AI64,AM64/AI64-1) -> -0.19171616 | AN66: =+IF(AJ64<0,1-AN64/AJ64,AN64/AJ64-1) -> -0.10172912 | AO66: =+IF(AK64<0,1-AO64/AK64,AO64/AK64-1) -> 0.08422284 | AP66: =+IF(AL64<0,1-AP64/AL64,AP64/AL64-1) -> 0.0063206919 | AQ66: =+IF(AM64<0,1-AQ64/AM64,AQ64/AM64-1) -> -0.067947752 | AR66: =+IF(AN64<0,1-AR64/AN64,AR64/AN64-1) -> -0.022407093 | AS66: =+IF(AO64<0,1-AS64/AO64,AS64/AO64-1) -> 0.042886042 | AT66: =+IF(AP64<0,1-AT64/AP64,AT64/AP64-1) -> 0.090247934 | ... CL66: =+IF(CH64<0,1-CL64/CH64,CL64/CH64-1) -> 0.35539952 | CM66: =+CM64/CI64-1 -> 0.34192166 | CN66: =+CN64/CJ64-1 -> 0.24501164 | CO66: =+CO64/CK64-1 -> 0.19710435 | CP66: =+CP64/CL64-1 -> 0.095079938 | CQ66: =+CQ64/CM64-1 -> 0.042548443 | CR66: =+CR64/CN64-1 -> 0.033800947 | CS66: =+CS64/CO64-1 -> 0.033145149 | CT66: =+CT64/CP64-1 -> 0.040088986 | ... DB66: =+DB64/CX64-1 -> 0.0041302739 | DF66: 0.17179279
A67: GP QOQ% | AJ67: =+IF(AI64<0,1-AJ64/AI64,AJ64/AI64-1) -> -0.0694381 | AK67: =+IF(AJ64<0,1-AK64/AJ64,AK64/AJ64-1) -> -0.25391371 | AL67: =+IF(AK64<0,1-AL64/AK64,AL64/AK64-1) -> 0.09884486 | AM67: =+IF(AL64<0,1-AM64/AL64,AM64/AL64-1) -> 0.059481038 | AN67: =+IF(AM64<0,1-AN64/AM64,AN64/AM64-1) -> 0.034162271 | AO67: =+IF(AN64<0,1-AO64/AN64,AO64/AN64-1) -> -0.09946563 | AP67: =+IF(AO64<0,1-AP64/AO64,AP64/AO64-1) -> 0.019892111 | AQ67: =+IF(AP64<0,1-AQ64/AP64,AQ64/AP64-1) -> -0.018710744 | ... CL67: =+IF(CK64<0,1-CL64/CK64,CL64/CK64-1) -> 0.090181511 | CM67: =+CM64/CL64-1 -> 0.062027813 | CN67: =+CN64/CM64-1 -> 0.024789332 | CO67: =+CO64/CN64-1 -> 0.0089338863 | CP67: =+CP64/CO64-1 -> -0.0027302917 | CQ67: =+CQ64/CP64-1 -> 0.011081844 | CR67: =+CR64/CQ64-1 -> 0.016190844 | CS67: =+CS64/CR64-1 -> 0.0082938628 | CT67: =+CT64/CS64-1 -> 0.0039724241 | ... DB67: =+DB64/DA64-1 -> 0.00097901737 | DF67: -0.057497945
A68: Power & Fuel Cost | B68: ='Annual Raw'!C13 -> 16.030761 | C68: ='Annual Raw'!D13 -> 14.32233 | D68: ='Annual Raw'!E13 -> 16.242541 | E68: ='Annual Raw'!F13 -> 24.662792 | F68: ='Annual Raw'!G13 -> 26.673482 | G68: ='Annual Raw'!H13 -> 27.422207 | H68: ='Annual Raw'!I13 -> 56.216065 | I68: ='Annual Raw'!J13 -> 75.572922 | ... AA68: ='Annual Raw'!AB13 -> 318.18 | AB68: =+SUM(CM68:CP68) -> 0 | AC68: =+SUM(CQ68:CT68) -> 0 | AD68: =+SUM(CU68:CX68) -> 0 | AE68: =+SUM(CY68:DB68) -> 0 | AI68: ='QTR Raw'!C15 -> 36.21 | AJ68: ='QTR Raw'!D15 -> 38.58 | AK68: ='QTR Raw'!E15 -> 34.23 | AL68: ='QTR Raw'!F15 -> 33.62 | AM68: ='QTR Raw'!G15 -> 32.77 | AN68: ='QTR Raw'!H15 -> 34.32 | AO68: ='QTR Raw'!I15 -> 35.28 | AP68: ='QTR Raw'!J15 -> 36.21 | ... CL68: ='QTR Raw'!BF15 -> 87.65 | DF68: 318.18
A69: Employee Cost | B69: ='Annual Raw'!C14 -> 9.3838041 | C69: ='Annual Raw'!D14 -> 9.9036198 | D69: ='Annual Raw'!E14 -> 10.181259 | E69: ='Annual Raw'!F14 -> 13.762118 | F69: ='Annual Raw'!G14 -> 16.245073 | G69: ='Annual Raw'!H14 -> 18.710016 | H69: ='Annual Raw'!I14 -> 34.036641 | I69: ='Annual Raw'!J14 -> 44.658973 | ... AA69: ='Annual Raw'!AB14 -> 293.47 | AB69: =+SUM(CM69:CP69) -> 314.0129 | AC69: =+SUM(CQ69:CT69) -> 335.9938 | AD69: =+SUM(CU69:CX69) -> 359.51337 | AE69: =+SUM(CY69:DB69) -> 384.67931 | AI69: ='QTR Raw'!C16 -> 22.78 | AJ69: ='QTR Raw'!D16 -> 24.72 | AK69: ='QTR Raw'!E16 -> 22.07 | AL69: ='QTR Raw'!F16 -> 24.65 | AM69: ='QTR Raw'!G16 -> 25.51 | AN69: ='QTR Raw'!H16 -> 27.64 | AO69: ='QTR Raw'!I16 -> 26.14 | AP69: ='QTR Raw'!J16 -> 25.96 | ... CL69: ='QTR Raw'!BF16 -> 79.75 | CM69: =CI69*107% -> 70.6521 | CN69: =CJ69*107% -> 78.7306 | CO69: =CK69*107% -> 79.2977 | CP69: =CL69*107% -> 85.3325 | CQ69: =CM69*107% -> 75.597747 | CR69: =CN69*107% -> 84.241742 | CS69: =CO69*107% -> 84.848539 | CT69: =CP69*107% -> 91.305775 | ... DB69: =CX69*107% -> 104.53598 | DF69: 68.9187
A70: Freight Octroi | R70: 29.56 | S70: 29.51 | T70: 29.57 | U70: 30.41 | V70: 41.03 | W70: 105.16 | X70: 57.78 | Y70: 55.57 | Z70: 77.67 | AA70: 77.67 | AB70: =+SUM(CM70:CP70) -> 0 | AC70: =+SUM(CQ70:CT70) -> 0 | AD70: =+SUM(CU70:CX70) -> 0 | AE70: =+SUM(CY70:DB70) -> 0 | DF70: 0
A71: Sales Commissions & Incentives | R71: 17.64 | S71: 16 | T71: 21.36 | U71: 22.31 | V71: 19.1 | W71: 37.96 | X71: 33.08 | Y71: 35.31 | Z71: 45.5 | AA71: 45.5 | AB71: =+SUM(CM71:CP71) -> 0 | AC71: =+SUM(CQ71:CT71) -> 0 | AD71: =+SUM(CU71:CX71) -> 0 | AE71: =+SUM(CY71:DB71) -> 0 | DF71: 0
A72: Processing Charges | R72: 31.06 | S72: 18.75 | T72: 17.93 | U72: 25.71 | V72: 20.2 | W72: 33.65 | X72: 64.39 | Y72: 40.87 | Z72: 44.08 | AA72: 44.08 | AB72: =+SUM(CM72:CP72) -> 0 | AC72: =+SUM(CQ72:CT72) -> 0 | AD72: =+SUM(CU72:CX72) -> 0 | AE72: =+SUM(CY72:DB72) -> 0 | DF72: 0
A73: General and Administration Expenses | B73: ='Annual Raw'!C17 -> 1.5825881 | C73: ='Annual Raw'!D17 -> 1.7474395 | D73: ='Annual Raw'!E17 -> 2.1740622 | E73: ='Annual Raw'!F17 -> 3.0154554 | F73: ='Annual Raw'!G17 -> 2.9152571 | G73: ='Annual Raw'!H17 -> 4.0560089 | H73: ='Annual Raw'!I17 -> 6.3435568 | I73: ='Annual Raw'!J17 -> 6.0165523 | ... AA73: ='Annual Raw'!AB17 -> 50.71 | AB73: =+SUM(CM73:CP73) -> 0 | AC73: =+SUM(CQ73:CT73) -> 0 | AD73: =+SUM(CU73:CX73) -> 0 | AE73: =+SUM(CY73:DB73) -> 0 | AI73: ='QTR Raw'!C17 -> 0 | AJ73: ='QTR Raw'!D17 -> 0 | AK73: ='QTR Raw'!E17 -> 0 | AL73: ='QTR Raw'!F17 -> 0 | AM73: ='QTR Raw'!G17 -> 0 | AN73: ='QTR Raw'!H17 -> 0 | AO73: ='QTR Raw'!I17 -> 10.38 | AP73: ='QTR Raw'!J17 -> 3.52 | ... CL73: ='QTR Raw'!BF17 -> 0 | DF73: 0
A74: Stores & spare Parts Consumed | R74: 33.67 | S74: 33.63 | T74: 33.09 | U74: 35.92 | V74: 31.47 | W74: 39.5 | X74: 43.07 | Y74: 39.94 | Z74: 36.78 | AA74: 36.78 | AB74: =+SUM(CM74:CP74) -> 0 | AC74: =+SUM(CQ74:CT74) -> 0 | AD74: =+SUM(CU74:CX74) -> 0 | AE74: =+SUM(CY74:DB74) -> 0 | DF74: 0
A75: Other Manufacturing Expenses(others) | B75: ='Annual Raw'!C15+'Annual Raw'!C16 -> 16.031576 | C75: ='Annual Raw'!D15+'Annual Raw'!D16 -> 22.908752 | D75: ='Annual Raw'!E15+'Annual Raw'!E16 -> 16.674619 | E75: ='Annual Raw'!F15+'Annual Raw'!F16 -> 19.261937 | F75: ='Annual Raw'!G15+'Annual Raw'!G16 -> 19.939484 | G75: ='Annual Raw'!H15+'Annual Raw'!H16 -> 27.49286 | H75: ='Annual Raw'!I15+'Annual Raw'!I16 -> 29.696939 | I75: ='Annual Raw'!J15+'Annual Raw'!J16 -> 40.396378 | ... Q75: ='Annual Raw'!R15+'Annual Raw'!R16 -> 162.49 | R75: =((((('Annual Raw'!S15+'Annual Raw'!S16)-64.62)-19.07)-31.06)-33.67)-5.39 -> 18.47 | S75: =((((('Annual Raw'!T15+'Annual Raw'!T16)-63.51)-20.33)-18.75)-33.63)-5.09 -> 20.21 | T75: =((((('Annual Raw'!U15+'Annual Raw'!U16)-80)-20.98)-17.93)-33.09)-6.46 -> 26.05 | U75: =((((('Annual Raw'!V15+'Annual Raw'!V16)-80.74)-20.45)-25.71)-35.92)-7.27 -> 26.26 | V75: =((((('Annual Raw'!W15+'Annual Raw'!W16)-52.31)-16.98)-20.2)-31.47)-4.64 -> 20.14 | W75: =((((('Annual Raw'!X15+'Annual Raw'!X16)-96.91)-29.3)-33.65)-39.5)-6.03 -> 28.37 | X75: =((((('Annual Raw'!Y15+'Annual Raw'!Y16)-126.99)-32.09)-64.39)-43.07)-7.63 -> 32.25 | Y75: =((((('Annual Raw'!Z15+'Annual Raw'!Z16)-113.91)-32.52)-40.87)-39.94)-8.95 -> 33.9 | Z75: =((((('Annual Raw'!AA15+'Annual Raw'!AA16)-113.44)-30.16)-44.08)-36.78)-8.9 -> 34.13 | AA75: =((((('Annual Raw'!AB15+'Annual Raw'!AB16)-113.44)-30.16)-44.08)-36.78)-8.9 -> 61.23 | AB75: =+SUM(CM75:CP75) -> 801.75311 | AC75: =+SUM(CQ75:CT75) -> 781.15039 | AD75: =+SUM(CU75:CX75) -> 769.43687 | AE75: =+SUM(CY75:DB75) -> 747.91272 | AI75: ='QTR Raw'!C14 -> 86.1 | AJ75: ='QTR Raw'!D14 -> 59.2 | AK75: ='QTR Raw'!E14 -> 29.18 | AL75: ='QTR Raw'!F14 -> 41.63 | AM75: ='QTR Raw'!G14 -> 54.79 | AN75: ='QTR Raw'!H14 -> 52.5 | AO75: ='QTR Raw'!I14 -> 28.14 | AP75: ='QTR Raw'!J14 -> 34.57 | ... CL75: ='QTR Raw'!BF14 -> 91.79 | CM75: =+CM80-CM69 -> 209.36265 | CN75: =+CN80-CN69 -> 202.31205 | CO75: =+CO80-CO69 -> 200.38686 | CP75: =+CP80-CP69 -> 189.69156 | CQ75: =+CQ80-CQ69 -> 203.1566 | CR75: =+CR80-CR69 -> 195.79242 | CS75: =+CS80-CS69 -> 194.90952 | CT75: =+CT80-CT69 -> 187.29184 | ... DB75: =+DB80-DB69 -> 178.96263 | DF75: 171.15527
A76: Packing Material Consumed | R76: 19.07 | S76: 20.33 | T76: 20.98 | U76: 20.45 | V76: 16.98 | W76: 29.3 | X76: 32.09 | Y76: 32.52 | Z76: 30.16 | AA76: 30.16 | AB76: =+SUM(CM76:CP76) -> 0 | AC76: =+SUM(CQ76:CT76) -> 0 | AD76: =+SUM(CU76:CX76) -> 0 | AE76: =+SUM(CY76:DB76) -> 0 | DF76: 0
A77: Miscellaneous Expenses | B77: ='Annual Raw'!C19-'Annual Raw'!C20 -> 0.8595843 | C77: ='Annual Raw'!D19-'Annual Raw'!D20 -> 1.8891447 | D77: ='Annual Raw'!E19-'Annual Raw'!E20 -> 3.2918764 | E77: ='Annual Raw'!F19-'Annual Raw'!F20 -> 0.9687212 | F77: ='Annual Raw'!G19-'Annual Raw'!G20 -> 1.1552369 | G77: ='Annual Raw'!H19-'Annual Raw'!H20 -> 1.4491317 | H77: ='Annual Raw'!I19-'Annual Raw'!I20 -> 2.2141858 | I77: ='Annual Raw'!J19-'Annual Raw'!J20 -> 3.2491787 | ... AA77: ='Annual Raw'!AB19-'Annual Raw'!AB20 -> 40.29 | AB77: =+SUM(CM77:CP77) -> 0 | AC77: =+SUM(CQ77:CT77) -> 0 | AD77: =+SUM(CU77:CX77) -> 0 | AE77: =+SUM(CY77:DB77) -> 0 | AI77: =+'QTR Raw'!C21 -> 0 | AJ77: =+'QTR Raw'!D21 -> 0 | AK77: =+'QTR Raw'!E21 -> 0 | AL77: =+'QTR Raw'!F21 -> 0 | AM77: =+'QTR Raw'!G21 -> 0 | AN77: =+'QTR Raw'!H21 -> 0 | AO77: =+'QTR Raw'!I21 -> 0 | AP77: =+'QTR Raw'!J21 -> 0 | ... CL77: =+'QTR Raw'!BF21 -> 0 | DF77: 0
A78: Repairs & Maintenance | R78: 5.39 | S78: 5.09 | T78: 6.46 | U78: 7.27 | V78: 4.64 | W78: 6.03 | X78: 7.63 | Y78: 8.95 | Z78: 8.9 | AA78: 8.9 | AB78: =+SUM(CM78:CP78) -> 0 | AC78: =+SUM(CQ78:CT78) -> 0 | AD78: =+SUM(CU78:CX78) -> 0 | AE78: =+SUM(CY78:DB78) -> 0 | DF78: 0
A79: Selling and Distribution Expenses | B79: ='Annual Raw'!C18 -> 6.9516516 | C79: ='Annual Raw'!D18 -> 6.2951079 | D79: ='Annual Raw'!E18 -> 6.0050941 | E79: ='Annual Raw'!F18 -> 8.0091558 | F79: ='Annual Raw'!G18 -> 7.7686247 | G79: ='Annual Raw'!H18 -> 12.491468 | H79: ='Annual Raw'!I18 -> 18.145626 | I79: ='Annual Raw'!J18 -> 22.320438 | ... Q79: ='Annual Raw'!R18 -> 44.52 | R79: =(('Annual Raw'!S18)-17.64)-29.56 -> 0 | S79: =(('Annual Raw'!T18)-16)-29.51 -> 0 | T79: =(('Annual Raw'!U18)-21.36)-29.57 -> 0 | U79: =(('Annual Raw'!V18)-22.31)-30.41 -> 0 | V79: =(('Annual Raw'!W18)-19.1)-41.03 -> 0 | W79: =(('Annual Raw'!X18)-37.96)-105.16 -> 0 | X79: =(('Annual Raw'!Y18)-33.08)-57.78 -> 0 | Y79: =(('Annual Raw'!Z18)-35.31)-55.57 -> 0 | Z79: =(('Annual Raw'!AA18)-45.5)-77.67 -> 0 | AA79: =(('Annual Raw'!AB18)-45.5)-77.67 -> -12.81 | AB79: =+SUM(CM79:CP79) -> 0 | AC79: =+SUM(CQ79:CT79) -> 0 | AD79: =+SUM(CU79:CX79) -> 0 | AE79: =+SUM(CY79:DB79) -> 0 | AI79: ='QTR Raw'!C18 -> 0 | AJ79: ='QTR Raw'!D18 -> 0 | AK79: ='QTR Raw'!E18 -> 0 | AL79: ='QTR Raw'!F18 -> 0 | AM79: ='QTR Raw'!G18 -> 0 | AN79: ='QTR Raw'!H18 -> 0 | AO79: ='QTR Raw'!I18 -> 0 | AP79: ='QTR Raw'!J18 -> 0 | ... CL79: ='QTR Raw'!BF18 -> 0 | DF79: 0
A80: Total Cost | B80: =+SUM(B68:B79) -> 50.839965 | C80: =+SUM(C68:C79) -> 57.066394 | D80: =+SUM(D68:D79) -> 54.569452 | E80: =+SUM(E68:E79) -> 69.680181 | F80: =+SUM(F68:F79) -> 74.697158 | G80: =+SUM(G68:G79) -> 91.621693 | H80: =+SUM(H68:H79) -> 146.65301 | I80: =+SUM(I68:I79) -> 192.21444 | ... AE80: =+SUM(AE68:AE79) -> 1132.592 | AI80: =+SUM(AI68:AI77) -> 145.09 | AJ80: =+SUM(AJ68:AJ77) -> 122.5 | AK80: =+SUM(AK68:AK77) -> 85.48 | AL80: =+SUM(AL68:AL77) -> 99.9 | AM80: =+SUM(AM68:AM77) -> 113.07 | AN80: =+SUM(AN68:AN77) -> 114.46 | AO80: =+SUM(AO68:AO77) -> 99.94 | AP80: =+SUM(AP68:AP77) -> 100.26 | ... BV80: =+SUM(BV68:BV77) -> 209.35 | BW80: =+SUM(BW68:BW79) -> 221.56 | BX80: =+SUM(BX68:BX79) -> 239.1 | BY80: =+SUM(BY68:BY79) -> 205.06 | BZ80: =+SUM(BZ68:BZ79) -> 211.66 | CA80: =+SUM(CA68:CA79) -> 219.61 | CB80: =+SUM(CB68:CB79) -> 212.21 | CC80: =+SUM(CC68:CC79) -> 197.49 | CD80: =+SUM(CD68:CD79) -> 227.49 | ... CL80: =+SUM(CL68:CL79) -> 259.19 | CM80: =CM81*CM57 -> 280.01475 | CN80: =CN81*CN57 -> 281.04265 | CO80: =CO81*CO57 -> 279.68456 | CP80: =CP81*CP57 -> 275.02406 | CQ80: =CQ81*CQ57 -> 278.75435 | CR80: =CR81*CR57 -> 280.03416 | CS80: =CS81*CS57 -> 279.75806 | CT80: =CT81*CT57 -> 278.59762 | ... DB80: =DB81*DB57 -> 283.49861 | DF80: 240.07397
A81: Cost % | B81: =B80/B57 -> 0.27707049 | C81: =C80/C57 -> 0.30085315 | D81: =D80/D57 -> 0.27882992 | E81: =E80/E57 -> 0.26082349 | F81: =F80/F57 -> 0.25795258 | G81: =G80/G57 -> 0.26420166 | H81: =H80/H57 -> 0.26550325 | I81: =I80/I57 -> 0.27721289 | ... AE81: =AE80/AE57 -> 0.27898955 | AI81: =AI80/AI57 -> 0.35169923 | AJ81: =AJ80/AJ57 -> 0.3176373 | AK81: =AK80/AK57 -> 0.25945487 | AL81: =AL80/AL57 -> 0.27962828 | AM81: =AM80/AM57 -> 0.30757304 | AN81: =AN80/AN57 -> 0.32421255 | AO81: =AO80/AO57 -> 0.28588592 | AP81: =AP80/AP57 -> 0.2714278 | ... CL81: =CL80/CL57 -> 0.29322789 | CM81: =AVERAGE(CI81:CL81)*0.97 -> 0.29196744 | CN81: =AVERAGE(CJ81:CM81)*0.97 -> 0.29274646 | CO81: =AVERAGE(CK81:CN81)*0.97 -> 0.29013738 | CP81: =AVERAGE(CL81:CO81)*0.97 -> 0.2832592 | CQ81: =AVERAGE(CM81:CP81)*0.98 -> 0.28373707 | CR81: =AVERAGE(CN81:CQ81)*0.98 -> 0.28172063 | CS81: =AVERAGE(CO81:CR81)*0.98 -> 0.2790193 | CT81: =AVERAGE(CP81:CS81)*0.98 -> 0.27629537 | CU81: =AVERAGE(CQ81:CT81) -> 0.28019309 | CV81: =AVERAGE(CR81:CU81) -> 0.2793071 | CW81: =AVERAGE(CS81:CV81) -> 0.27870371 | CX81: =AVERAGE(CT81:CW81) -> 0.27862482 | CY81: =AVERAGE(CU81:CX81) -> 0.27920718 | CZ81: =AVERAGE(CV81:CY81) -> 0.2789607 | DA81: =AVERAGE(CW81:CZ81) -> 0.2788741 | DB81: =AVERAGE(CX81:DA81) -> 0.2789167 | DF81: 0.29871721
A82: EBITDA | B82: =B64-B80 -> 24.943077 | C82: =C64-C80 -> 22.178197 | D82: =D64-D80 -> 27.667429 | E82: =E64-E80 -> 37.286011 | F82: =F64-F80 -> 43.049665 | G82: =G64-G80 -> 59.797726 | H82: =H64-H80 -> 95.047936 | I82: =I64-I80 -> 88.275942 | ... AE82: =AE64-AE80 -> 523.8411 | AI82: =AI64-AI80 -> 51.92 | AJ82: =AJ64-AJ80 -> 60.83 | AK82: =AK64-AK80 -> 51.3 | AL82: =AL64-AL80 -> 50.4 | AM82: =AM64-AM80 -> 46.17 | AN82: =AN64-AN80 -> 50.22 | AO82: =AO64-AO80 -> 48.36 | AP82: =AP64-AP80 -> 50.99 | ... DB82: =DB64-DB80 -> 131.21791 | DF82: 71.997886
A83: EBITDA Margins | B83: =B82/B57 -> 0.13593618 | C83: =C82/C57 -> 0.11692311 | D83: =D82/D57 -> 0.14137043 | E83: =E82/E57 -> 0.1395672 | F83: =F82/F57 -> 0.14866392 | G83: =G82/G57 -> 0.17243361 | H83: =H82/H57 -> 0.17207649 | I83: =I82/I57 -> 0.12731213 | ... AE83: =AE82/AE57 -> 0.12903693 | AI83: =AI82/AI57 -> 0.12585446 | AJ83: =AJ82/AJ57 -> 0.15772961 | AK83: =AK82/AK57 -> 0.15570934 | AL83: =AL82/AL57 -> 0.14107373 | AM83: =AM82/AM57 -> 0.12559164 | AN83: =AN82/AN57 -> 0.14225017 | AO83: =AO82/AO57 -> 0.13833743 | AP83: =AP82/AP57 -> 0.13804212 | ... DB83: =DB82/DB57 -> 0.12909716 | DF83: 0.089584921
A84: EBITDA YOY% | C84: =+IF(B82<0,1-C82/B82,C82/B82-1) -> -0.11084757 | D84: =+IF(C82<0,1-D82/C82,D82/C82-1) -> 0.24750577 | E84: =+IF(D82<0,1-E82/D82,E82/D82-1) -> 0.34765002 | F84: =+IF(E82<0,1-F82/E82,F82/E82-1) -> 0.15457951 | G84: =+IF(F82<0,1-G82/F82,G82/F82-1) -> 0.38904047 | H84: =+IF(G82<0,1-H82/G82,H82/G82-1) -> 0.5894908 | I84: =+IF(H82<0,1-I82/H82,I82/H82-1) -> -0.071248193 | J84: =+IF(I82<0,1-J82/I82,J82/I82-1) -> -0.18680363 | ... AE84: =+IF(AD82<0,1-AE82/AD82,AE82/AD82-1) -> 0.005754259 | AM84: =+IF(AI82<0,1-AM82/AI82,AM82/AI82-1) -> -0.1107473 | AN84: =+IF(AJ82<0,1-AN82/AJ82,AN82/AJ82-1) -> -0.17442052 | AO84: =+IF(AK82<0,1-AO82/AK82,AO82/AK82-1) -> -0.057309942 | AP84: =+IF(AL82<0,1-AP82/AL82,AP82/AL82-1) -> 0.011706349 | AQ84: =+IF(AM82<0,1-AQ82/AM82,AQ82/AM82-1) -> 0.10223089 | AR84: =+IF(AN82<0,1-AR82/AN82,AR82/AN82-1) -> 0.068896854 | AS84: =+IF(AO82<0,1-AS82/AO82,AS82/AO82-1) -> 0.1002895 | AT84: =+IF(AP82<0,1-AT82/AP82,AT82/AP82-1) -> 0.16905276 | ... CL84: =+IF(CH82<0,1-CL82/CH82,CL82/CH82-1) -> 0.76395147 | CM84: =+CM82/CI82-1 -> 0.7932575 | CN84: =+CN82/CJ82-1 -> 0.45335035 | CO84: =+CO82/CK82-1 -> 0.38289477 | CP84: =+CP82/CL82-1 -> 0.18163635 | CQ84: =+CQ82/CM82-1 -> 0.17002957 | CR84: =+CR82/CN82-1 -> 0.12777269 | CS84: =+CS82/CO82-1 -> 0.11195899 | CT84: =+CT82/CP82-1 -> 0.10205011 | ... DB84: =+DB82/CX82-1 -> 0.0021322018 | DF84: 0.24779698
A85: EBITDA QOQ% | AJ85: =+IF(AI82<0,1-AJ82/AI82,AJ82/AI82-1) -> 0.17161017 | AK85: =+IF(AJ82<0,1-AK82/AJ82,AK82/AJ82-1) -> -0.15666612 | AL85: =+IF(AK82<0,1-AL82/AK82,AL82/AK82-1) -> -0.01754386 | AM85: =+IF(AL82<0,1-AM82/AL82,AM82/AL82-1) -> -0.083928571 | AN85: =+IF(AM82<0,1-AN82/AM82,AN82/AM82-1) -> 0.087719298 | AO85: =+IF(AN82<0,1-AO82/AN82,AO82/AN82-1) -> -0.037037037 | AP85: =+IF(AO82<0,1-AP82/AO82,AP82/AO82-1) -> 0.054383788 | AQ85: =+IF(AP82<0,1-AQ82/AP82,AQ82/AP82-1) -> -0.0019611689 | ... CI85: =+IF(CH82<0,1-CI82/CH82,CI82/CH82-1) -> -0.0012131716 | CJ85: =+IF(CI82>1,CJ82/CI82-1,1-CJ82/CI82) -> 0.33506854 | CK85: =+IF(CJ82>1,CK82/CJ82-1,1-CK82/CJ82) -> 0.096698726 | CL85: =+IF(CK82>1,CL82/CK82-1,1-CL82/CK82) -> 0.20621 | CM85: =+CM82/CL82-1 -> 0.015380525 | CN85: =+CN82/CM82-1 -> 0.08200988 | CO85: =+CO82/CN82-1 -> 0.04353292 | CP85: =+CP82/CO82-1 -> 0.030665251 | CQ85: =+CQ82/CP82-1 -> 0.0054068095 | CR85: =+CR82/CQ82-1 -> 0.042931928 | CS85: =+CS82/CR82-1 -> 0.028900435 | CT85: =+CT82/CS82-1 -> 0.021480791 | ... DB85: =+DB82/DA82-1 -> 0.00060354612 | DF85: -0.14674229
A86: Depreciation | B86: ='Annual Raw'!C27 -> 9.6357153 | C86: ='Annual Raw'!D27 -> 10.673755 | D86: ='Annual Raw'!E27 -> 11.880889 | E86: ='Annual Raw'!F27 -> 16.128715 | F86: ='Annual Raw'!G27 -> 20.371764 | G86: ='Annual Raw'!H27 -> 20.087075 | H86: ='Annual Raw'!I27 -> 36.570471 | I86: ='Annual Raw'!J27 -> 49.103024 | ... AA86: ='Annual Raw'!AB27 -> 95.36 | AB86: =+SUM(CM86:CP86) -> 111.64516 | AC86: =+SUM(CQ86:CT86) -> 110.7516 | AD86: =+SUM(CU86:CX86) -> 102.87685 | AE86: =+SUM(CY86:DB86) -> 95.562007 | AI86: ='QTR Raw'!C28 -> 19.39 | AJ86: ='QTR Raw'!D28 -> 19.35 | AK86: ='QTR Raw'!E28 -> 19.45 | AL86: ='QTR Raw'!F28 -> 18.79 | AM86: ='QTR Raw'!G28 -> 18.67 | AN86: ='QTR Raw'!H28 -> 18.81 | AO86: ='QTR Raw'!I28 -> 18.89 | AP86: ='QTR Raw'!J28 -> 17.95 | ... CL86: ='QTR Raw'!BF28 -> 24.5 | CM86: =CM87*CL188 -> 27.574901 | CN86: =CN87*CM188 -> 27.801912 | CO86: =CO87*CN188 -> 28.024775 | CP86: =CP87*CO188 -> 28.243567 | CQ86: =CQ87*CP188 -> 28.458361 | CR86: =CR87*CQ188 -> 27.938417 | CS86: =CS87*CR188 -> 27.427972 | CT86: =CT87*CS188 -> 26.926853 | ... DB86: =DB87*DA188 -> 23.233832 | DF86: 24.079696
A87: Depreciation % of Net Block | B87: =+B86/B188 -> 0.11377848 | C87: =+C86/C188 -> 0.11822523 | D87: =+D86/D188 -> 0.1074055 | E87: =+E86/E188 -> 0.094127028 | F87: =+F86/F188 -> 0.11118589 | G87: =+G86/G188 -> 0.080817188 | H87: =+H86/H188 -> 0.099978867 | I87: =+I86/I188 -> 0.099056703 | ... AE87: =+AE86/AE188 -> 0.076545478 | AI87: =+AI86/AH188 -> #DIV/0! | AJ87: =+AJ86/AI188 -> #DIV/0! | AK87: =+AK86/AJ188 -> 0.031405412 | AL87: =+AL86/AK188 -> 0.030339727 | AM87: =+AM86/AL188 -> 0.031555818 | AN87: =+AN86/AM188 -> 0.031792445 | AO87: =+AO86/AN188 -> 0.033251188 | AP87: =+AP86/AO188 -> 0.03159655 | ... CL87: =+CL86/CK188 -> 0.018270357 | CM87: =CL87 -> 0.018270357 | CN87: =CM87 -> 0.018270357 | CO87: =CN87 -> 0.018270357 | CP87: =CO87 -> 0.018270357 | CQ87: =CP87 -> 0.018270357 | CR87: =CQ87 -> 0.018270357 | CS87: =CR87 -> 0.018270357 | CT87: =CS87 -> 0.018270357 | ... DB87: =DA87 -> 0.018270357 | DF87: 0.017956924
A88: EBIT | B88: =B82-B86 -> 15.307361 | C88: =C82-C86 -> 11.504442 | D88: =D82-D86 -> 15.786539 | E88: =E82-E86 -> 21.157296 | F88: =F82-F86 -> 22.677901 | G88: =G82-G86 -> 39.710651 | H88: =H82-H86 -> 58.477464 | I88: =I82-I86 -> 39.172918 | ... AE88: =AE82-AE86 -> 428.2791 | AI88: =AI82-AI86 -> 32.53 | AJ88: =AJ82-AJ86 -> 41.48 | AK88: =AK82-AK86 -> 31.85 | AL88: =AL82-AL86 -> 31.61 | AM88: =AM82-AM86 -> 27.5 | AN88: =AN82-AN86 -> 31.41 | AO88: =AO82-AO86 -> 29.47 | AP88: =AP82-AP86 -> 33.04 | ... DB88: =DB82-DB86 -> 107.98407 | DF88: 47.918189
A89: Other Income | B89: ='Annual Raw'!C23 -> 2.8652171 | C89: ='Annual Raw'!D23 -> 3.3725736 | D89: ='Annual Raw'!E23 -> 2.4245481 | E89: ='Annual Raw'!F23 -> 3.939631 | F89: ='Annual Raw'!G23 -> 4.060573 | G89: ='Annual Raw'!H23 -> 3.8310629 | H89: ='Annual Raw'!I23 -> 1.2023453 | I89: ='Annual Raw'!J23 -> 6.8410063 | ... AA89: ='Annual Raw'!AB23 -> 25.19 | AB89: =+SUM(CM89:CP89) -> 0 | AC89: =+SUM(CQ89:CT89) -> 0 | AD89: =+SUM(CU89:CX89) -> 0 | AE89: =+SUM(CY89:DB89) -> 0 | AI89: ='QTR Raw'!C23 -> 1.54 | AJ89: ='QTR Raw'!D23 -> 0.49 | AK89: ='QTR Raw'!E23 -> 0.92 | AL89: ='QTR Raw'!F23 -> 3.53 | AM89: ='QTR Raw'!G23 -> 1.68 | AN89: ='QTR Raw'!H23 -> 1.78 | AO89: ='QTR Raw'!I23 -> 3.9 | AP89: ='QTR Raw'!J23 -> -1.27 | ... CL89: ='QTR Raw'!BF23 -> -3.61 | DF89: 8.06
A90: Interest | B90: ='Annual Raw'!C25 -> 10.024017 | C90: ='Annual Raw'!D25 -> 8.969594 | D90: ='Annual Raw'!E25 -> 7.0409124 | E90: ='Annual Raw'!F25 -> 9.2696583 | F90: ='Annual Raw'!G25 -> 9.0136955 | G90: ='Annual Raw'!H25 -> 9.7867101 | H90: ='Annual Raw'!I25 -> 22.619981 | I90: ='Annual Raw'!J25 -> 39.262989 | ... AA90: ='Annual Raw'!AB25 -> 113.95 | AB90: =+SUM(CM90:CP90) -> 120.85536 | AC90: =+SUM(CQ90:CT90) -> 106.20474 | AD90: =+SUM(CU90:CX90) -> 69.571231 | AE90: =+SUM(CY90:DB90) -> 26.850193 | AI90: ='QTR Raw'!C25 -> 20.03 | AJ90: ='QTR Raw'!D25 -> 15.64 | AK90: ='QTR Raw'!E25 -> 16.72 | AL90: ='QTR Raw'!F25 -> 16.28 | AM90: ='QTR Raw'!G25 -> 16.94 | AN90: ='QTR Raw'!H25 -> 15.05 | AO90: ='QTR Raw'!I25 -> 16.51 | AP90: ='QTR Raw'!J25 -> 17.56 | ... CL90: ='QTR Raw'!BF25 -> 26.92 | CM90: =CM91*CL227 -> 29.804913 | CN90: =CN91*CM227 -> 30.863428 | CO90: =CO91*CN227 -> 30.379393 | CP90: =CP91*CO227 -> 29.807628 | CQ90: =CQ91*CP227 -> 29.208061 | CR90: =CR91*CQ227 -> 27.585784 | CS90: =CS91*CR227 -> 25.826418 | CT90: =CT91*CS227 -> 23.584479 | ... DB90: =DB91*DA227 -> 2.5015741 | DF90: 25.677383
A91: Interest % of Debt | B91: =+B90/B182 -> 0.13429696 | C91: =+C90/C182 -> 0.1253277 | D91: =+D90/D182 -> 0.067421763 | E91: =+E90/E182 -> 0.056424232 | F91: =+F90/F182 -> 0.048711286 | G91: =+G90/G182 -> 0.031371355 | H91: =+H90/H182 -> 0.035083276 | I91: =+I90/I182 -> 0.053812343 | ... AE91: =+AE90/AE182 -> 0.02612039 | AI91: =(AI90-AI89)/AH227 -> #DIV/0! | AJ91: =(AJ90-AJ89)/AI227 -> #DIV/0! | AK91: =(AK90-AK89)/AJ227 -> 0.026690993 | AL91: =(AL90-AL89)/AK227 -> 0.024103052 | AM91: =(AM90-AM89)/AL227 -> 0.027433215 | AN91: =(AN90-AN89)/AM227 -> 0.023711585 | AO91: =(AO90-AO89)/AN227 -> 0.024169126 | AP91: =(AP90-AP89)/AO227 -> 0.037193344 | ... CL91: =(CL90-CL89)/CK227 -> 0.027572122 | CM91: =+CL91 -> 0.027572122 | CN91: =+CM91 -> 0.027572122 | CO91: =+CN91 -> 0.027572122 | CP91: =+CO91 -> 0.027572122 | CQ91: =+CP91 -> 0.027572122 | CR91: =+CQ91 -> 0.027572122 | CS91: =+CR91 -> 0.027572122 | CT91: =+CS91 -> 0.027572122 | ... DB91: =+DA91 -> 0.027572122 | DF91: 0.023189648
A92: PBT | B92: =B88+B89-B90 -> 8.1485614 | C92: =C88+C89-C90 -> 5.9074215 | D92: =D88+D89-D90 -> 11.170175 | E92: =E88+E89-E90 -> 15.827268 | F92: =F88+F89-F90 -> 17.724779 | G92: =G88+G89-G90 -> 33.755004 | H92: =H88+H89-H90 -> 37.059829 | I92: =I88+I89-I90 -> 6.7509348 | ... AE92: =AE88+AE89-AE90 -> 401.4289 | AI92: =AI88+AI89-AI90 -> 14.04 | AJ92: =AJ88+AJ89-AJ90 -> 26.33 | AK92: =AK88+AK89-AK90 -> 16.05 | AL92: =AL88+AL89-AL90 -> 18.86 | AM92: =AM88+AM89-AM90 -> 12.24 | AN92: =AN88+AN89-AN90 -> 18.14 | AO92: =AO88+AO89-AO90 -> 16.86 | AP92: =AP88+AP89-AP90 -> 14.21 | ... DB92: =DB88+DB89-DB90 -> 105.4825 | DF92: 22.240806
A93: Tax | B93: ='Annual Raw'!C30 -> 0.68 | C93: ='Annual Raw'!D30 -> 1.3049264 | D93: ='Annual Raw'!E30 -> 3.6016778 | E93: ='Annual Raw'!F30 -> 3.7636771 | F93: ='Annual Raw'!G30 -> 3.6759642 | G93: ='Annual Raw'!H30 -> 8.979659 | H93: ='Annual Raw'!I30 -> 10.03495 | I93: ='Annual Raw'!J30 -> 1.3763657 | ... AA93: ='Annual Raw'!AB30 -> 30.23 | AB93: =+SUM(CM93:CP93) -> 47.015802 | AC93: =+SUM(CQ93:CT93) -> 62.198617 | AD93: =+SUM(CU93:CX93) -> 73.996947 | AE93: =+SUM(CY93:DB93) -> 85.228786 | AI93: ='QTR Raw'!C29 -> 4.27 | AJ93: ='QTR Raw'!D29 -> 8.24 | AK93: ='QTR Raw'!E29 -> 4.98 | AL93: ='QTR Raw'!F29 -> 6.04 | AM93: ='QTR Raw'!G29 -> 6.21 | AN93: ='QTR Raw'!H29 -> 5.9 | AO93: ='QTR Raw'!I29 -> 4.71 | AP93: ='QTR Raw'!J29 -> 3.83 | ... CL93: ='QTR Raw'!BF29 -> 12.21 | CM93: =+CM92*CM94 -> 9.9558643 | CN93: =+CN92*CN94 -> 12.059683 | CO93: =+CO92*CO94 -> 12.064885 | CP93: =+CP92*CP94 -> 12.93537 | CQ93: =+CQ92*CQ94 -> 13.573318 | CR93: =+CR92*CR94 -> 15.111771 | CS93: =+CS92*CS94 -> 16.133601 | CT93: =+CT92*CT94 -> 17.379926 | ... DB93: =+DB92*DB94 -> 22.395175 | DF93: 4.6262607
A94: Tax Rate % | B94: =B93/B92 -> 0.083450313 | C94: =C93/C92 -> 0.22089611 | D94: =D93/D92 -> 0.322437 | E94: =E93/E92 -> 0.23779701 | F94: =F93/F92 -> 0.20739126 | G94: =G93/G92 -> 0.26602453 | H94: =H93/H92 -> 0.27077702 | I94: =I93/I92 -> 0.20387779 | ... AE94: =AE93/AE92 -> 0.21231353 | AI94: =AI93/AI92 -> 0.30413105 | AJ94: =AJ93/AJ92 -> 0.31295101 | AK94: =AK93/AK92 -> 0.31028037 | AL94: =AL93/AL92 -> 0.32025451 | AM94: =AM93/AM92 -> 0.50735294 | AN94: =AN93/AN92 -> 0.32524807 | AO94: =AO93/AO92 -> 0.27935943 | AP94: =AP93/AP92 -> 0.2695285 | ... CL94: =CL93/CL92 -> 0.26117647 | CM94: =AVERAGE(CI94:CL94) -> 0.21659373 | CN94: =AVERAGE(CJ94:CM94)-2% -> 0.22687582 | CO94: =AVERAGE(CK94:CN94)-2% -> 0.20699992 | CP94: =AVERAGE(CL94:CO94)-2% -> 0.20791148 | CQ94: =AVERAGE(CM94:CP94) -> 0.21459524 | CR94: =AVERAGE(CN94:CQ94) -> 0.21409562 | CS94: =AVERAGE(CO94:CR94) -> 0.21090056 | CT94: =AVERAGE(CP94:CS94) -> 0.21187573 | CU94: =AVERAGE(CQ94:CT94) -> 0.21286679 | CV94: =AVERAGE(CR94:CU94) -> 0.21243467 | CW94: =AVERAGE(CS94:CV94) -> 0.21201944 | CX94: =AVERAGE(CT94:CW94) -> 0.21229916 | ... DB94: =AVERAGE(CX94:DA94) -> 0.21231176 | DF94: 0.20800778
A95: PAT | B95: =B92-B93 -> 7.4685614 | C95: =C92-C93 -> 4.6024951 | D95: =D92-D93 -> 7.5684974 | E95: =E92-E93 -> 12.063591 | F95: =F92-F93 -> 14.048814 | G95: =G92-G93 -> 24.775345 | H95: =H92-H93 -> 27.024879 | I95: =I92-I93 -> 5.3745691 | ... AE95: =AE92-AE93 -> 316.20012 | AI95: =AI92-AI93 -> 9.77 | AJ95: =AJ92-AJ93 -> 18.09 | AK95: =AK92-AK93 -> 11.07 | AL95: =AL92-AL93 -> 12.82 | AM95: =AM92-AM93 -> 6.03 | AN95: =AN92-AN93 -> 12.24 | AO95: =AO92-AO93 -> 12.15 | AP95: =AP92-AP93 -> 10.38 | ... DB95: =DB92-DB93 -> 83.087325 | DF95: 17.614546
A96: PAT % | B96: =+B95/B57 -> 0.040702584 | C96: =+C95/C57 -> 0.024264283 | D96: =+D95/D57 -> 0.038672251 | E96: =+E95/E57 -> 0.045155853 | F96: =+F95/F57 -> 0.048514937 | G96: =+G95/G57 -> 0.071442549 | H96: =+H95/H57 -> 0.048926326 | I96: =+I95/I57 -> 0.0077512378 | ... AE96: =+AE95/AE57 -> 0.07788906 | AI96: =+AI95/AI57 -> 0.023682552 | AJ96: =+AJ95/AJ57 -> 0.046906602 | AK96: =+AK95/AK57 -> 0.033600437 | AL96: =+AL95/AL57 -> 0.03588423 | AM96: =+AM95/AM57 -> 0.016402807 | AN96: =+AN95/AN57 -> 0.034670292 | AO96: =+AO95/AO57 -> 0.034755993 | AP96: =+AP95/AP57 -> 0.028101142 | ... DB96: =+DB95/DB57 -> 0.081744466 | DF96: 0.021917278
A97: PAT YOY% | C97: =+IF(B95<0,1-C95/B95,C95/B95-1) -> -0.38375078 | D97: =+IF(C95<0,1-D95/C95,D95/C95-1) -> 0.64443356 | E97: =+IF(D95<0,1-E95/D95,E95/D95-1) -> 0.59392158 | F97: =+IF(E95<0,1-F95/E95,F95/E95-1) -> 0.16456319 | G97: =+IF(F95<0,1-G95/F95,G95/F95-1) -> 0.76351854 | H97: =+IF(G95<0,1-H95/G95,H95/G95-1) -> 0.090797296 | I97: =+IF(H95<0,1-I95/H95,I95/H95-1) -> -0.80112514 | J97: =+IF(I95<0,1-J95/I95,J95/I95-1) -> -3.9740908 | ... AE97: =+IF(AD95<0,1-AE95/AD95,AE95/AD95-1) -> 0.15233696 | AM97: =+IF(AI95<0,1-AM95/AI95,AM95/AI95-1) -> -0.3828045 | AN97: =+IF(AJ95<0,1-AN95/AJ95,AN95/AJ95-1) -> -0.32338308 | AO97: =+IF(AK95<0,1-AO95/AK95,AO95/AK95-1) -> 0.097560976 | AP97: =+IF(AL95<0,1-AP95/AL95,AP95/AL95-1) -> -0.19032761 | AQ97: =+IF(AM95<0,1-AQ95/AM95,AQ95/AM95-1) -> 0.88059701 | AR97: =+IF(AN95<0,1-AR95/AN95,AR95/AN95-1) -> -0.022058824 | AS97: =+IF(AO95<0,1-AS95/AO95,AS95/AO95-1) -> 0.13333333 | AT97: =+IF(AP95<0,1-AT95/AP95,AT95/AP95-1) -> 0.42967245 | ... CL97: =+IF(CH95<0,1-CL95/CH95,CL95/CH95-1) -> 2.0894454 | CM97: =+CM95/CI95-1 -> 8.5012537 | CN97: =+CN95/CJ95-1 -> 0.65775528 | CO97: =+CO95/CK95-1 -> 0.76883305 | CP97: =+CP95/CL95-1 -> 0.42676269 | CQ97: =+CQ95/CM95-1 -> 0.37955599 | CR97: =+CR95/CN95-1 -> 0.349834 | CS97: =+CS95/CO95-1 -> 0.30604775 | CT97: =+CT95/CP95-1 -> 0.3118596 | ... DB97: =+DB95/CX95-1 -> 0.1416688 | DF97: 0.57554077
A98: PAT QOQ% | AJ98: =+IF(AI95<0,1-AJ95/AI95,AJ95/AI95-1) -> 0.85158649 | AK98: =+IF(AJ95<0,1-AK95/AJ95,AK95/AJ95-1) -> -0.3880597 | AL98: =+IF(AK95<0,1-AL95/AK95,AL95/AK95-1) -> 0.15808491 | AM98: =+IF(AL95<0,1-AM95/AL95,AM95/AL95-1) -> -0.52964119 | AN98: =+IF(AM95<0,1-AN95/AM95,AN95/AM95-1) -> 1.0298507 | AO98: =+IF(AN95<0,1-AO95/AN95,AO95/AN95-1) -> -0.0073529412 | AP98: =+IF(AO95<0,1-AP95/AO95,AP95/AO95-1) -> -0.14567901 | AQ98: =+IF(AP95<0,1-AQ95/AP95,AQ95/AP95-1) -> 0.092485549 | ... CL98: =+IF(CK95<0,1-CL95/CK95,CL95/CK95-1) -> 0.32185228 | CM98: =+CM95/CL95-1 -> 0.042552159 | CN98: =+CN95/CM95-1 -> 0.14123957 | CO98: =+CO95/CN95-1 -> 0.12468087 | CP98: =+CP95/CO95-1 -> 0.066222451 | CQ98: =+CQ95/CP95-1 -> 0.0080576754 | CR98: =+CR95/CQ95-1 -> 0.11665201 | CS98: =+CS95/CR95-1 -> 0.088198193 | CT98: =+CT95/CS95-1 -> 0.070967088 | ... DB98: =+DB95/DA95-1 -> 0.032834044 | DF98: -0.32588803
A99: Minority Interest | B99: ='Annual Raw'!C32 -> 0 | C99: ='Annual Raw'!D32 -> 0 | D99: ='Annual Raw'!E32 -> 0 | E99: ='Annual Raw'!F32 -> 0 | F99: ='Annual Raw'!G32 -> 0 | G99: ='Annual Raw'!H32 -> 0 | H99: ='Annual Raw'!I32 -> 0 | I99: ='Annual Raw'!J32 -> 0 | ... AA99: ='Annual Raw'!AB32 -> 0 | AB99: =+SUM(CM99:CP99) -> 0 | AC99: =+SUM(CQ99:CT99) -> 0 | AD99: =+SUM(CU99:CX99) -> 0 | AE99: =+SUM(CY99:DB99) -> 0 | AI99: ='QTR Raw'!C34 -> 0 | AJ99: ='QTR Raw'!D34 -> 0 | AK99: ='QTR Raw'!E34 -> 0 | AL99: ='QTR Raw'!F34 -> 0 | AM99: ='QTR Raw'!G34 -> 0 | AN99: ='QTR Raw'!H34 -> 0 | AO99: ='QTR Raw'!I34 -> 0 | AP99: ='QTR Raw'!J34 -> 0 | ... CL99: ='QTR Raw'!BF34 -> 0 | CM99: =+CL99 -> 0 | CN99: =+CM99 -> 0 | CO99: =+CN99 -> 0 | CP99: =+CO99 -> 0 | CQ99: =+CP99 -> 0 | CR99: =+CQ99 -> 0 | CS99: =+CR99 -> 0 | CT99: =+CS99 -> 0 | ... DB99: =+DA99 -> 0 | DF99: 0
A100: Share of Associate | B100: ='Annual Raw'!C33+'Annual Raw'!C28 -> 0 | C100: ='Annual Raw'!D33+'Annual Raw'!D28 -> 0 | D100: ='Annual Raw'!E33+'Annual Raw'!E28 -> 0 | E100: ='Annual Raw'!F33+'Annual Raw'!F28 -> 0 | F100: ='Annual Raw'!G33+'Annual Raw'!G28 -> 0 | G100: ='Annual Raw'!H33+'Annual Raw'!H28 -> 0 | H100: ='Annual Raw'!I33+'Annual Raw'!I28 -> 0 | I100: ='Annual Raw'!J33+'Annual Raw'!J28 -> 0 | ... AA100: ='Annual Raw'!AB33+'Annual Raw'!AB28 -> -0.01 | AB100: =+SUM(CM100:CP100) -> -0.04 | AC100: =+SUM(CQ100:CT100) -> -0.04 | AD100: =+SUM(CU100:CX100) -> -0.04 | AE100: =+SUM(CY100:DB100) -> -0.04 | AI100: ='QTR Raw'!C35 -> 0 | AJ100: ='QTR Raw'!D35 -> 0 | AK100: ='QTR Raw'!E35 -> 0 | AL100: ='QTR Raw'!F35 -> 0 | AM100: ='QTR Raw'!G35 -> 0 | AN100: ='QTR Raw'!H35 -> 0 | AO100: ='QTR Raw'!I35 -> 0 | AP100: ='QTR Raw'!J35 -> 0 | ... CL100: ='QTR Raw'!BF35 -> -0.01 | CM100: =+CL100 -> -0.01 | CN100: =+CM100 -> -0.01 | CO100: =+CN100 -> -0.01 | CP100: =+CO100 -> -0.01 | CQ100: =+CP100 -> -0.01 | CR100: =+CQ100 -> -0.01 | CS100: =+CR100 -> -0.01 | CT100: =+CS100 -> -0.01 | ... DB100: =+DA100 -> -0.01 | DF100: 0
A101: Exceptional Income / Expenses | B101: ='Annual Raw'!C29+'Annual Raw'!C31+'Annual Raw'!C34+'Annual Raw'!C36 -> 0 | C101: ='Annual Raw'!D29+'Annual Raw'!D31+'Annual Raw'!D34+'Annual Raw'!D36 -> 0 | D101: ='Annual Raw'!E29+'Annual Raw'!E31+'Annual Raw'!E34+'Annual Raw'!E36 -> 0 | E101: ='Annual Raw'!F29+'Annual Raw'!F31+'Annual Raw'!F34+'Annual Raw'!F36 -> 0 | F101: ='Annual Raw'!G29+'Annual Raw'!G31+'Annual Raw'!G34+'Annual Raw'!G36 -> 0 | G101: ='Annual Raw'!H29+'Annual Raw'!H31+'Annual Raw'!H34+'Annual Raw'!H36 -> 0 | H101: ='Annual Raw'!I29+'Annual Raw'!I31+'Annual Raw'!I34+'Annual Raw'!I36 -> 0 | I101: ='Annual Raw'!J29+'Annual Raw'!J31+'Annual Raw'!J34+'Annual Raw'!J36 -> 0 | ... AA101: ='Annual Raw'!AB29+'Annual Raw'!AB31+'Annual Raw'!AB34+'Annual Raw'!AB36 -> -6.64 | AB101: =+SUM(CM101:CP101) -> 0 | AC101: =+SUM(CQ101:CT101) -> 0 | AD101: =+SUM(CU101:CX101) -> 0 | AE101: =+SUM(CY101:DB101) -> 0 | AI101: ='QTR Raw'!C26+'QTR Raw'!C31+'QTR Raw'!C32+'QTR Raw'!C33+'QTR Raw'!C36+'QTR Raw'!C37+'QTR Raw'!C39 -> 0 | AJ101: ='QTR Raw'!D26+'QTR Raw'!D31+'QTR Raw'!D32+'QTR Raw'!D33+'QTR Raw'!D36+'QTR Raw'!D37+'QTR Raw'!D39 -> 0 | AK101: ='QTR Raw'!E26+'QTR Raw'!E31+'QTR Raw'!E32+'QTR Raw'!E33+'QTR Raw'!E36+'QTR Raw'!E37+'QTR Raw'!E39 -> 0 | AL101: ='QTR Raw'!F26+'QTR Raw'!F31+'QTR Raw'!F32+'QTR Raw'!F33+'QTR Raw'!F36+'QTR Raw'!F37+'QTR Raw'!F39 -> -0.45 | AM101: ='QTR Raw'!G26+'QTR Raw'!G31+'QTR Raw'!G32+'QTR Raw'!G33+'QTR Raw'!G36+'QTR Raw'!G37+'QTR Raw'!G39 -> 0 | AN101: ='QTR Raw'!H26+'QTR Raw'!H31+'QTR Raw'!H32+'QTR Raw'!H33+'QTR Raw'!H36+'QTR Raw'!H37+'QTR Raw'!H39 -> 0 | AO101: ='QTR Raw'!I26+'QTR Raw'!I31+'QTR Raw'!I32+'QTR Raw'!I33+'QTR Raw'!I36+'QTR Raw'!I37+'QTR Raw'!I39 -> 0 | AP101: ='QTR Raw'!J26+'QTR Raw'!J31+'QTR Raw'!J32+'QTR Raw'!J33+'QTR Raw'!J36+'QTR Raw'!J37+'QTR Raw'!J39 -> -0.3 | ... CL101: ='QTR Raw'!BF26+'QTR Raw'!BF31+'QTR Raw'!BF32+'QTR Raw'!BF33+'QTR Raw'!BF36+'QTR Raw'!BF37+'QTR Raw'!BF39 -> -1.66 | DF101: -6.64
A102: Consolidated Net Profit | B102: =B95+B99+B100+B101 -> 7.4685614 | C102: =C95+C99+C100+C101 -> 4.6024951 | D102: =D95+D99+D100+D101 -> 7.5684974 | E102: =E95+E99+E100+E101 -> 12.063591 | F102: =F95+F99+F100+F101 -> 14.048814 | G102: =G95+G99+G100+G101 -> 24.775345 | H102: =H95+H99+H100+H101 -> 27.024879 | I102: =I95+I99+I100+I101 -> 5.3745691 | ... AE102: =AE95+AE99+AE100+AE101 -> 316.16012 | AI102: =AI95+AI99+AI100+AI101 -> 9.77 | AJ102: =AJ95+AJ99+AJ100+AJ101 -> 18.09 | AK102: =AK95+AK99+AK100+AK101 -> 11.07 | AL102: =AL95+AL99+AL100+AL101 -> 12.37 | AM102: =AM95+AM99+AM100+AM101 -> 6.03 | AN102: =AN95+AN99+AN100+AN101 -> 12.24 | AO102: =AO95+AO99+AO100+AO101 -> 12.15 | AP102: =AP95+AP99+AP100+AP101 -> 10.08 | ... DB102: =DB95+DB99+DB100+DB101 -> 83.077325 | DF102: 17.614546
A103: Profit & Loss- Annual (End)
A105: Ace - PAT | B105: ='Annual Raw'!C35 -> 7.4685614 | C105: ='Annual Raw'!D35 -> 4.6024951 | D105: ='Annual Raw'!E35 -> 7.5684974 | E105: ='Annual Raw'!F35 -> 12.063591 | F105: ='Annual Raw'!G35 -> 14.048814 | G105: ='Annual Raw'!H35 -> 24.775345 | H105: ='Annual Raw'!I35 -> 27.024879 | I105: ='Annual Raw'!J35 -> 5.3745691 | ... AA105: ='Annual Raw'!AB35 -> 82.6 | AB105: =+AB102 -> 172.5655 | AC105: =+AC102 -> 230.12387 | AD105: =+AD102 -> 274.35901 | AE105: =+AE102 -> 316.16012 | AI105: ='QTR Raw'!C42 -> 9.77 | AJ105: ='QTR Raw'!D42 -> 18.09 | AK105: ='QTR Raw'!E42 -> 11.07 | AL105: ='QTR Raw'!F42 -> 12.37 | AM105: ='QTR Raw'!G42 -> 6.03 | AN105: ='QTR Raw'!H42 -> 12.24 | AO105: ='QTR Raw'!I42 -> 12.15 | AP105: ='QTR Raw'!J42 -> 10.08 | ... CL105: ='QTR Raw'!BF42 -> 32.87 | DF105: 82.6
A106: Checksum - PAT | B106: =B105-B102 -> 0 | C106: =C105-C102 -> -3.375078e-14 | D106: =D105-D102 -> 7.9936058e-15 | E106: =E105-E102 -> 0 | F106: =F105-F102 -> -4.0856207e-14 | G106: =G105-G102 -> 0 | H106: =H105-H102 -> -5.3290705e-14 | I106: =I105-I102 -> -3.1086245e-14 | ... AE106: =AE105-AE102 -> 0 | AI106: =AI105-AI102 -> 4.2632564e-14 | AJ106: =AJ105-AJ102 -> -3.907985e-14 | AK106: =AK105-AK102 -> 1.7763568e-14 | AL106: =AL105-AL102 -> 0 | AM106: =AM105-AM102 -> -4.0856207e-14 | AN106: =AN105-AN102 -> 6.0396133e-14 | AO106: =AO105-AO102 -> 0 | AP106: =AP105-AP102 -> -3.5527137e-14 | ... CL106: =CL105-CL102 -> 7.8159701e-14 | DF106: 0
A107: Ratios (Start)
A108: ROE (%) | B108: =(B102-B101)/B174 -> 0.14309011 | C108: =(C102-C101)/C174 -> 0.099510211 | D108: =(D102-D101)/D174 -> 0.1462349 | E108: =(E102-E101)/E174 -> 0.16575104 | F108: =(F102-F101)/F174 -> 0.16897975 | G108: =(G102-G101)/G174 -> 0.17749604 | H108: =(H102-H101)/H174 -> 0.14381119 | I108: =(I102-I101)/I174 -> 0.02780519 | ... AE108: =(AE102-AE101)/AE174 -> 0.15277284 | AL108: =(SUM(AI102:AL102)-SUM(AI101:AL101))/AL174 -> 0.17374517 | AM108: =(SUM(AJ102:AM102)-SUM(AJ101:AM101))/AM174 -> 0.15799 | AN108: =(SUM(AK102:AN102)-SUM(AK101:AN101))/AN174 -> 0.13336708 | AO108: =(SUM(AL102:AO102)-SUM(AL101:AO101))/AO174 -> 0.13172084 | AP108: =(SUM(AM102:AP102)-SUM(AM101:AP101))/AP174 -> 0.12310292 | AQ108: =(SUM(AN102:AQ102)-SUM(AN101:AQ101))/AQ174 -> 0.13452169 | AR108: =(SUM(AO102:AR102)-SUM(AO101:AR101))/AR174 -> 0.1292214 | AS108: =(SUM(AP102:AS102)-SUM(AP101:AS101))/AS174 -> 0.12878891 | ... DB108: =(SUM(CY102:DB102)-SUM(CY101:DB101))/DB174 -> 0.15277284 | DF108: 0.06805834
A109: ROCE (%) | B109: =+B88/B183 -> 0.12068673 | C109: =+C88/C183 -> 0.097643714 | D109: =+D88/D183 -> 0.10107486 | E109: =+E88/E183 -> 0.089246267 | F109: =+F88/F183 -> 0.08456151 | G109: =+G88/G183 -> 0.087943798 | H109: =+H88/H183 -> 0.070228837 | I109: =+I88/I183 -> 0.042444466 | ... AE109: =+AE88/AE183 -> 0.13826969 | AL109: =+SUM(AI88:AL88)/AL183 -> 0.15942617 | AM109: =+SUM(AJ88:AM88)/AM183 -> 0.15252617 | AN109: =+SUM(AK88:AN88)/AN183 -> 0.14561616 | AO109: =+SUM(AL88:AO88)/AO183 -> 0.14074908 | AP109: =+SUM(AM88:AP88)/AP183 -> 0.14645325 | AQ109: =+SUM(AN88:AQ88)/AQ183 -> 0.14977214 | AR109: =+SUM(AO88:AR88)/AR183 -> 0.15153544 | AS109: =+SUM(AP88:AS88)/AS183 -> 0.15409427 | ... DB109: =+SUM(CY88:DB88)/DB183 -> 0.13826969 | DF109: 0.083329568
...

Sheet Sheet1
C3: 18 | D3: 19 | E3: 20 | F3: 21 | G3: 22 | H3: 23 | I3: 24 | J3: 25
A5: Yarn (MTPA) | F5: 85500 | I5: 103140 | J5: 114420
A7: Weaving (MMPA)
B8: PV Fabric (weaving) | F8: 30 | G8: 30 | H8: 32.4 | I8: 48 | J8: 48
B9: Fabric (processing) | F9: 72 | G9: 72 | H9: 72 | I9: 72 | J9: 72
B10: Denim Fabric | F10: 48 | G10: 48 | H10: 48 | I10: 48 | J10: 60
A12: Garments | B12: mn pcs | F12: 4 | G12: 5 | H12: 5.6 | I12: 251.94 | J12: 251.94
B13: Processing | F13: 511 | G13: 511

Sheet QTR Raw
A1: ='Annual Raw'!A1 -> 114234 | B1: X | C1: 201206 | D1: 201209 | E1: 201212 | F1: 201303 | G1: 201306 | H1: 201309 | I1: 201312 | J1: 201403 | K1: 201406 | L1: 201409 | M1: 201412 | N1: 201503 | O1: 201506 | P1: 201509 | Q1: 201512 | R1: 201603 | S1: 201606 | T1: 201609 | U1: 201612 | V1: 201703 | W1: 201706 | X1: 201709 | Y1: 201712 | Z1: 201803 | AA1: 201806 | AB1: 201809 | AC1: 201812 | AD1: 201903 | AE1: 201906 | AF1: 201909 | AG1: 201912 | AH1: 202003 | AI1: 202006 | AJ1: 202009 | AK1: 202012 | AL1: 202103 | AM1: 202106 | AN1: 202109 | AO1: 202112 | AP1: 202203 | AQ1: 202206 | AR1: 202209 | AS1: 202212 | AT1: 202303 | AU1: 202306 | AV1: 202309 | AW1: 202312 | AX1: 202403 | AY1: 202406 | AZ1: 202409 | BA1: 202412 | BB1: 202503 | BC1: 202506 | BD1: 202509 | BE1: 202512 | BF1: 202603 | BG1: 202606 | BH1: 202609 | BI1: 202612 | BJ1: 202703 | BK1: 202706 | BL1: 202709 | BM1: 202712 | BN1: 202803 | BO1: 202806 | BP1: 202809 | BQ1: 202812 | BR1: 202903 | BS1: 202906 | BT1: 202909 | BU1: 202912 | BV1: 203003
A3: Field Description | B3: Field Name
A4: Company Name | B4: CD_COMPNAME | C4: =_xll.EQNXTDZ(A1,B4,C1) -> Sangam (India) Ltd.
A5: Date End | B5: QTR_DATE_END | C5: =_xll.EQNXTDZ($A$1,$B5,C$1,$B$1) -> 201206 | D5: =_xll.EQNXTDZ($A$1,$B5,D$1,$B$1) -> 201209 | E5: =_xll.EQNXTDZ($A$1,$B5,E$1,$B$1) -> 201212 | F5: =_xll.EQNXTDZ($A$1,$B5,F$1,$B$1) -> 201303 | G5: =_xll.EQNXTDZ($A$1,$B5,G$1,$B$1) -> 201306 | H5: =_xll.EQNXTDZ($A$1,$B5,H$1,$B$1) -> 201309 | I5: =_xll.EQNXTDZ($A$1,$B5,I$1,$B$1) -> 201312 | J5: =_xll.EQNXTDZ($A$1,$B5,J$1,$B$1) -> 201403 | ... BV5: =_xll.EQNXTDZ($A$1,$B5,BV$1,$B$1) -> 0
A6: Gross Sales | B6: QTR_GROSS_SALE | C6: =_xll.EQNXTDZ($A$1,$B6,C$1,$B$1) -> 411.09 | D6: =_xll.EQNXTDZ($A$1,$B6,D$1,$B$1) -> 384.06 | E6: =_xll.EQNXTDZ($A$1,$B6,E$1,$B$1) -> 327.96 | F6: =_xll.EQNXTDZ($A$1,$B6,F$1,$B$1) -> 355.73 | G6: =_xll.EQNXTDZ($A$1,$B6,G$1,$B$1) -> 365.8 | H6: =_xll.EQNXTDZ($A$1,$B6,H$1,$B$1) -> 351.4 | I6: =_xll.EQNXTDZ($A$1,$B6,I$1,$B$1) -> 347.89 | J6: =_xll.EQNXTDZ($A$1,$B6,J$1,$B$1) -> 367.52 | ... BV6: =_xll.EQNXTDZ($A$1,$B6,BV$1,$B$1) -> 0
A7: Less: Excise Duty | B7: QTR_EXCISE_DUTY | C7: =_xll.EQNXTDZ($A$1,$B7,C$1,$B$1) -> 0 | D7: =_xll.EQNXTDZ($A$1,$B7,D$1,$B$1) -> 0 | E7: =_xll.EQNXTDZ($A$1,$B7,E$1,$B$1) -> 0 | F7: =_xll.EQNXTDZ($A$1,$B7,F$1,$B$1) -> 0 | G7: =_xll.EQNXTDZ($A$1,$B7,G$1,$B$1) -> 0 | H7: =_xll.EQNXTDZ($A$1,$B7,H$1,$B$1) -> 0 | I7: =_xll.EQNXTDZ($A$1,$B7,I$1,$B$1) -> 0 | J7: =_xll.EQNXTDZ($A$1,$B7,J$1,$B$1) -> 0 | ... BV7: =_xll.EQNXTDZ($A$1,$B7,BV$1,$B$1) -> 0
A8: Other operating income | B8: QTR_JOB_WORKS | C8: =_xll.EQNXTDZ($A$1,$B8,C$1,$B$1) -> 1.45 | D8: =_xll.EQNXTDZ($A$1,$B8,D$1,$B$1) -> 1.6 | E8: =_xll.EQNXTDZ($A$1,$B8,E$1,$B$1) -> 1.5 | F8: =_xll.EQNXTDZ($A$1,$B8,F$1,$B$1) -> 1.53 | G8: =_xll.EQNXTDZ($A$1,$B8,G$1,$B$1) -> 1.82 | H8: =_xll.EQNXTDZ($A$1,$B8,H$1,$B$1) -> 1.64 | I8: =_xll.EQNXTDZ($A$1,$B8,I$1,$B$1) -> 1.69 | J8: =_xll.EQNXTDZ($A$1,$B8,J$1,$B$1) -> 1.86 | ... BV8: =_xll.EQNXTDZ($A$1,$B8,BV$1,$B$1) -> 0
A9: Net Sales & Other Operating Income | B9: QTR_NET_SALES | C9: =_xll.EQNXTDZ($A$1,$B9,C$1,$B$1) -> 412.54 | D9: =_xll.EQNXTDZ($A$1,$B9,D$1,$B$1) -> 385.66 | E9: =_xll.EQNXTDZ($A$1,$B9,E$1,$B$1) -> 329.46 | F9: =_xll.EQNXTDZ($A$1,$B9,F$1,$B$1) -> 357.26 | G9: =_xll.EQNXTDZ($A$1,$B9,G$1,$B$1) -> 367.62 | H9: =_xll.EQNXTDZ($A$1,$B9,H$1,$B$1) -> 353.04 | I9: =_xll.EQNXTDZ($A$1,$B9,I$1,$B$1) -> 349.58 | J9: =_xll.EQNXTDZ($A$1,$B9,J$1,$B$1) -> 369.38 | ... BV9: =_xll.EQNXTDZ($A$1,$B9,BV$1,$B$1) -> 0
A10: (Increase) / Decrease In Stocks | B10: QTR_INC_DEC_INVENTORY | C10: =_xll.EQNXTDZ($A$1,$B10,C$1,$B$1) -> 11.8 | D10: =_xll.EQNXTDZ($A$1,$B10,D$1,$B$1) -> -23.48 | E10: =_xll.EQNXTDZ($A$1,$B10,E$1,$B$1) -> 9.31 | F10: =_xll.EQNXTDZ($A$1,$B10,F$1,$B$1) -> -14.47 | G10: =_xll.EQNXTDZ($A$1,$B10,G$1,$B$1) -> 22.28 | H10: =_xll.EQNXTDZ($A$1,$B10,H$1,$B$1) -> -21.76 | I10: =_xll.EQNXTDZ($A$1,$B10,I$1,$B$1) -> -13.23 | J10: =_xll.EQNXTDZ($A$1,$B10,J$1,$B$1) -> 1.59 | ... BV10: =_xll.EQNXTDZ($A$1,$B10,BV$1,$B$1) -> 0
A11: Cost of Services & Raw Materials | B11: QTR_RAW_MATERIAL_COST | C11: =_xll.EQNXTDZ($A$1,$B11,C$1,$B$1) -> 203.73 | D11: =_xll.EQNXTDZ($A$1,$B11,D$1,$B$1) -> 225.81 | E11: =_xll.EQNXTDZ($A$1,$B11,E$1,$B$1) -> 183.37 | F11: =_xll.EQNXTDZ($A$1,$B11,F$1,$B$1) -> 221.43 | G11: =_xll.EQNXTDZ($A$1,$B11,G$1,$B$1) -> 186.1 | H11: =_xll.EQNXTDZ($A$1,$B11,H$1,$B$1) -> 210.12 | I11: =_xll.EQNXTDZ($A$1,$B11,I$1,$B$1) -> 214.51 | J11: =_xll.EQNXTDZ($A$1,$B11,J$1,$B$1) -> 216.54 | ... BV11: =_xll.EQNXTDZ($A$1,$B11,BV$1,$B$1) -> 0
A12: Purchase of Finished Goods | B12: QTR_PURCHASE_FIN_GOOD | C12: =_xll.EQNXTDZ($A$1,$B12,C$1,$B$1) -> 0 | D12: =_xll.EQNXTDZ($A$1,$B12,D$1,$B$1) -> 0 | E12: =_xll.EQNXTDZ($A$1,$B12,E$1,$B$1) -> 0 | F12: =_xll.EQNXTDZ($A$1,$B12,F$1,$B$1) -> 0 | G12: =_xll.EQNXTDZ($A$1,$B12,G$1,$B$1) -> 0 | H12: =_xll.EQNXTDZ($A$1,$B12,H$1,$B$1) -> 0 | I12: =_xll.EQNXTDZ($A$1,$B12,I$1,$B$1) -> 0 | J12: =_xll.EQNXTDZ($A$1,$B12,J$1,$B$1) -> 0 | ... BV12: =_xll.EQNXTDZ($A$1,$B12,BV$1,$B$1) -> 0
A13: Excise Duty | B13: QTR_EXCISE | C13: =_xll.EQNXTDZ($A$1,$B13,C$1,$B$1) -> 0 | D13: =_xll.EQNXTDZ($A$1,$B13,D$1,$B$1) -> 0 | E13: =_xll.EQNXTDZ($A$1,$B13,E$1,$B$1) -> 0 | F13: =_xll.EQNXTDZ($A$1,$B13,F$1,$B$1) -> 0 | G13: =_xll.EQNXTDZ($A$1,$B13,G$1,$B$1) -> 0 | H13: =_xll.EQNXTDZ($A$1,$B13,H$1,$B$1) -> 0 | I13: =_xll.EQNXTDZ($A$1,$B13,I$1,$B$1) -> 0 | J13: =_xll.EQNXTDZ($A$1,$B13,J$1,$B$1) -> 0 | ... BV13: =_xll.EQNXTDZ($A$1,$B13,BV$1,$B$1) -> 0
A14: Operating & Manufacturing Expenses | B14: QTR_MFG_EXPS | C14: =_xll.EQNXTDZ($A$1,$B14,C$1,$B$1) -> 86.1 | D14: =_xll.EQNXTDZ($A$1,$B14,D$1,$B$1) -> 59.2 | E14: =_xll.EQNXTDZ($A$1,$B14,E$1,$B$1) -> 29.18 | F14: =_xll.EQNXTDZ($A$1,$B14,F$1,$B$1) -> 41.63 | G14: =_xll.EQNXTDZ($A$1,$B14,G$1,$B$1) -> 54.79 | H14: =_xll.EQNXTDZ($A$1,$B14,H$1,$B$1) -> 52.5 | I14: =_xll.EQNXTDZ($A$1,$B14,I$1,$B$1) -> 28.14 | J14: =_xll.EQNXTDZ($A$1,$B14,J$1,$B$1) -> 34.57 | ... BV14: =_xll.EQNXTDZ($A$1,$B14,BV$1,$B$1) -> 0
A15: Electricity Power & Fuel Cost | B15: QTR_ELECTRICITY_POWER_FUEL | C15: =_xll.EQNXTDZ($A$1,$B15,C$1,$B$1) -> 36.21 | D15: =_xll.EQNXTDZ($A$1,$B15,D$1,$B$1) -> 38.58 | E15: =_xll.EQNXTDZ($A$1,$B15,E$1,$B$1) -> 34.23 | F15: =_xll.EQNXTDZ($A$1,$B15,F$1,$B$1) -> 33.62 | G15: =_xll.EQNXTDZ($A$1,$B15,G$1,$B$1) -> 32.77 | H15: =_xll.EQNXTDZ($A$1,$B15,H$1,$B$1) -> 34.32 | I15: =_xll.EQNXTDZ($A$1,$B15,I$1,$B$1) -> 35.28 | J15: =_xll.EQNXTDZ($A$1,$B15,J$1,$B$1) -> 36.21 | ... BV15: =_xll.EQNXTDZ($A$1,$B15,BV$1,$B$1) -> 0
A16: Employee Cost | B16: QTR_EXPLOYEE_COST | C16: =_xll.EQNXTDZ($A$1,$B16,C$1,$B$1) -> 22.78 | D16: =_xll.EQNXTDZ($A$1,$B16,D$1,$B$1) -> 24.72 | E16: =_xll.EQNXTDZ($A$1,$B16,E$1,$B$1) -> 22.07 | F16: =_xll.EQNXTDZ($A$1,$B16,F$1,$B$1) -> 24.65 | G16: =_xll.EQNXTDZ($A$1,$B16,G$1,$B$1) -> 25.51 | H16: =_xll.EQNXTDZ($A$1,$B16,H$1,$B$1) -> 27.64 | I16: =_xll.EQNXTDZ($A$1,$B16,I$1,$B$1) -> 26.14 | J16: =_xll.EQNXTDZ($A$1,$B16,J$1,$B$1) -> 25.96 | ... BV16: =_xll.EQNXTDZ($A$1,$B16,BV$1,$B$1) -> 0
... A42: Consolidated PAT(after extra items) | B42: QTR_CONS_PAT_EXITM | C42: =_xll.EQNXTDZ($A$1,$B42,C$1,$B$1) -> 9.77 | D42: =_xll.EQNXTDZ($A$1,$B42,D$1,$B$1) -> 18.09 | E42: =_xll.EQNXTDZ($A$1,$B42,E$1,$B$1) -> 11.07 | F42: =_xll.EQNXTDZ($A$1,$B42,F$1,$B$1) -> 12.37 | G42: =_xll.EQNXTDZ($A$1,$B42,G$1,$B$1) -> 6.03 | H42: =_xll.EQNXTDZ($A$1,$B42,H$1,$B$1) -> 12.24 | I42: =_xll.EQNXTDZ($A$1,$B42,I$1,$B$1) -> 12.15 | J42: =_xll.EQNXTDZ($A$1,$B42,J$1,$B$1) -> 10.08 | ... BV42: =_xll.EQNXTDZ($A$1,$B42,BV$1,$B$1) -> 0
A44: Field Description | B44: Field Name
A45: Equity Capital | B45: QTR_EQUITY_CAP | C45: =_xll.EQNXTDZ($A$1,$B45,C$1,$B$1) -> 39.42 | D45: =_xll.EQNXTDZ($A$1,$B45,D$1,$B$1) -> 39.42 | E45: =_xll.EQNXTDZ($A$1,$B45,E$1,$B$1) -> 39.42 | F45: =_xll.EQNXTDZ($A$1,$B45,F$1,$B$1) -> 39.42 | G45: =_xll.EQNXTDZ($A$1,$B45,G$1,$B$1) -> 39.42 | H45: =_xll.EQNXTDZ($A$1,$B45,H$1,$B$1) -> 39.42 | I45: =_xll.EQNXTDZ($A$1,$B45,I$1,$B$1) -> 39.42 | J45: =_xll.EQNXTDZ($A$1,$B45,J$1,$B$1) -> 39.42 | ... BV45: =_xll.EQNXTDZ($A$1,$B45,BV$1,$B$1) -> 0
A46: Face Value | B46: QTR_FV | C46: =_xll.EQNXTDZ($A$1,$B46,C$1,$B$1) -> 10 | D46: =_xll.EQNXTDZ($A$1,$B46,D$1,$B$1) -> 10 | E46: =_xll.EQNXTDZ($A$1,$B46,E$1,$B$1) -> 10 | F46: =_xll.EQNXTDZ($A$1,$B46,F$1,$B$1) -> 10 | G46: =_xll.EQNXTDZ($A$1,$B46,G$1,$B$1) -> 10 | H46: =_xll.EQNXTDZ($A$1,$B46,H$1,$B$1) -> 10 | I46: =_xll.EQNXTDZ($A$1,$B46,I$1,$B$1) -> 10 | J46: =_xll.EQNXTDZ($A$1,$B46,J$1,$B$1) -> 10 | ... BV46: =_xll.EQNXTDZ($A$1,$B46,BV$1,$B$1) -> 0
A47: Month End | B47: BMONTH_MONTHEND | C47: =_xll.EQNXTDZ($A$1,$B47,C$5) -> 201206 | D47: =_xll.EQNXTDZ($A$1,$B47,D$5) -> 201209 | E47: =_xll.EQNXTDZ($A$1,$B47,E$5) -> 201212 | F47: =_xll.EQNXTDZ($A$1,$B47,F$5) -> 201303 | G47: =_xll.EQNXTDZ($A$1,$B47,G$5) -> 201306 | H47: =_xll.EQNXTDZ($A$1,$B47,H$5) -> 201309 | I47: =_xll.EQNXTDZ($A$1,$B47,I$5) -> 201312 | J47: =_xll.EQNXTDZ($A$1,$B47,J$5) -> 201403 | ... BV47: =_xll.EQNXTDZ($A$1,$B47,BV$5) -> 0
A48: Close | B48: BMONTH_CLOSE | C48: =_xll.EQNXTDZ($A$1,$B48,C$5) -> 47.85 | D48: =_xll.EQNXTDZ($A$1,$B48,D$5) -> 55.75 | E48: =_xll.EQNXTDZ($A$1,$B48,E$5) -> 51 | F48: =_xll.EQNXTDZ($A$1,$B48,F$5) -> 34 | G48: =_xll.EQNXTDZ($A$1,$B48,G$5) -> 41.25 | H48: =_xll.EQNXTDZ($A$1,$B48,H$5) -> 28.05 | I48: =_xll.EQNXTDZ($A$1,$B48,I$5) -> 35.85 | J48: =_xll.EQNXTDZ($A$1,$B48,J$5) -> 35.1 | ... BV48: =_xll.EQNXTDZ($A$1,$B48,BV$5) -> 0
A49: Total of Promoter and Promoter Group | B49: SHP_TPFTOTALPROMOTER | C49: =_xll.EQNXTDZ($A$1,$B49,C$5) -> 36.99 | D49: =_xll.EQNXTDZ($A$1,$B49,D$5) -> 37.99 | E49: =_xll.EQNXTDZ($A$1,$B49,E$5) -> 37.99 | F49: =_xll.EQNXTDZ($A$1,$B49,F$5) -> 38.65 | G49: =_xll.EQNXTDZ($A$1,$B49,G$5) -> 38.65 | H49: =_xll.EQNXTDZ($A$1,$B49,H$5) -> 38.65 | I49: =_xll.EQNXTDZ($A$1,$B49,I$5) -> 38.65 | J49: =_xll.EQNXTDZ($A$1,$B49,J$5) -> 42.8 | ... BV49: =_xll.EQNXTDZ($A$1,$B49,BV$5) -> 0
A50: Total of Promoter and Promoter Group Pledged | B50: SHP_PSHFTOTALPROMOTER | C50: =_xll.EQNXTDZ($A$1,$B50,C$5) -> 21.26 | D50: =_xll.EQNXTDZ($A$1,$B50,D$5) -> 20.7 | E50: =_xll.EQNXTDZ($A$1,$B50,E$5) -> 20.7 | F50: =_xll.EQNXTDZ($A$1,$B50,F$5) -> 20.35 | G50: =_xll.EQNXTDZ($A$1,$B50,G$5) -> 20.35 | H50: =_xll.EQNXTDZ($A$1,$B50,H$5) -> 20.35 | I50: =_xll.EQNXTDZ($A$1,$B50,I$5) -> 20.35 | J50: =_xll.EQNXTDZ($A$1,$B50,J$5) -> 0 | ... BV50: =_xll.EQNXTDZ($A$1,$B50,BV$5) -> 0
A54: Field Description | B54: Field Name | C54: =_xll.EQNXTDZ($A$1,$B54,C$5) -> 0 | D54: =_xll.EQNXTDZ($A$1,$B54,D$5) -> 0 | E54: =_xll.EQNXTDZ($A$1,$B54,E$5) -> 0 | F54: =_xll.EQNXTDZ($A$1,$B54,F$5) -> 0 | G54: =_xll.EQNXTDZ($A$1,$B54,G$5) -> 0 | H54: =_xll.EQNXTDZ($A$1,$B54,H$5) -> 0 | I54: =_xll.EQNXTDZ($A$1,$B54,I$5) -> 0 | J54: =_xll.EQNXTDZ($A$1,$B54,J$5) -> 0 | ... BV54: =_xll.EQNXTDZ($A$1,$B54,BV$5) -> 0
A55: Year End | B55: QTRB_DATE_END | C55: =_xll.EQNXTDZ($A$1,$B55,C$5,$B$1) -> 0 | D55: =_xll.EQNXTDZ($A$1,$B55,D$5,$B$1) -> 201209 | E55: =_xll.EQNXTDZ($A$1,$B55,E$5,$B$1) -> 0 | F55: =_xll.EQNXTDZ($A$1,$B55,F$5,$B$1) -> 201303 | G55: =_xll.EQNXTDZ($A$1,$B55,G$5,$B$1) -> 0 | H55: =_xll.EQNXTDZ($A$1,$B55,H$5,$B$1) -> 201309 | I55: =_xll.EQNXTDZ($A$1,$B55,I$5,$B$1) -> 0 | J55: =_xll.EQNXTDZ($A$1,$B55,J$5,$B$1) -> 201403 | ... BV55: =_xll.EQNXTDZ($A$1,$B55,BV$5,$B$1) -> 0
A56: Share Capital | B56: QTRB_SHARE_CAPITAL | C56: =_xll.EQNXTDZ($A$1,$B56,C$5,$B$1) -> 0 | D56: =_xll.EQNXTDZ($A$1,$B56,D$5,$B$1) -> 39.42 | E56: =_xll.EQNXTDZ($A$1,$B56,E$5,$B$1) -> 0 | F56: =_xll.EQNXTDZ($A$1,$B56,F$5,$B$1) -> 39.42 | G56: =_xll.EQNXTDZ($A$1,$B56,G$5,$B$1) -> 0 | H56: =_xll.EQNXTDZ($A$1,$B56,H$5,$B$1) -> 39.42 | I56: =_xll.EQNXTDZ($A$1,$B56,I$5,$B$1) -> 0 | J56: =_xll.EQNXTDZ($A$1,$B56,J$5,$B$1) -> 39.42 | ... BV56: =_xll.EQNXTDZ($A$1,$B56,BV$5,$B$1) -> 0
A57: Share Warrants & outstandings | B57: QTRB_SHAREWARNDOUT | C57: =_xll.EQNXTDZ($A$1,$B57,C$5,$B$1) -> 0 | D57: =_xll.EQNXTDZ($A$1,$B57,D$5,$B$1) -> 0 | E57: =_xll.EQNXTDZ($A$1,$B57,E$5,$B$1) -> 0 | F57: =_xll.EQNXTDZ($A$1,$B57,F$5,$B$1) -> 0 | G57: =_xll.EQNXTDZ($A$1,$B57,G$5,$B$1) -> 0 | H57: =_xll.EQNXTDZ($A$1,$B57,H$5,$B$1) -> 0 | I57: =_xll.EQNXTDZ($A$1,$B57,I$5,$B$1) -> 0 | J57: =_xll.EQNXTDZ($A$1,$B57,J$5,$B$1) -> 0 | ... BV57: =_xll.EQNXTDZ($A$1,$B57,BV$5,$B$1) -> 0
A58: Reserves & Surplus | B58: QTRB_RESERVE | C58: =_xll.EQNXTDZ($A$1,$B58,C$5,$B$1) -> 0 | D58: =_xll.EQNXTDZ($A$1,$B58,D$5,$B$1) -> 240.52 | E58: =_xll.EQNXTDZ($A$1,$B58,E$5,$B$1) -> 0 | F58: =_xll.EQNXTDZ($A$1,$B58,F$5,$B$1) -> 258.43 | G58: =_xll.EQNXTDZ($A$1,$B58,G$5,$B$1) -> 0 | H58: =_xll.EQNXTDZ($A$1,$B58,H$5,$B$1) -> 276.7 | I58: =_xll.EQNXTDZ($A$1,$B58,I$5,$B$1) -> 0 | J58: =_xll.EQNXTDZ($A$1,$B58,J$5,$B$1) -> 292.01 | ... BV58: =_xll.EQNXTDZ($A$1,$B58,BV$5,$B$1) -> 0
A59: Shareholder's Funds | B59: QTRB_SHAREHODERS_FUNDS | C59: =_xll.EQNXTDZ($A$1,$B59,C$5,$B$1) -> 0 | D59: =_xll.EQNXTDZ($A$1,$B59,D$5,$B$1) -> 279.94 | E59: =_xll.EQNXTDZ($A$1,$B59,E$5,$B$1) -> 0 | F59: =_xll.EQNXTDZ($A$1,$B59,F$5,$B$1) -> 297.85 | G59: =_xll.EQNXTDZ($A$1,$B59,G$5,$B$1) -> 0 | H59: =_xll.EQNXTDZ($A$1,$B59,H$5,$B$1) -> 316.12 | I59: =_xll.EQNXTDZ($A$1,$B59,I$5,$B$1) -> 0 | J59: =_xll.EQNXTDZ($A$1,$B59,J$5,$B$1) -> 331.43 | ... BV59: =_xll.EQNXTDZ($A$1,$B59,BV$5,$B$1) -> 0
A60: Minority Interest | B60: QTRB_MINORITY_INTEREST_BS | C60: =_xll.EQNXTDZ($A$1,$B60,C$5,$B$1) -> 0 | D60: =_xll.EQNXTDZ($A$1,$B60,D$5,$B$1) -> 0 | E60: =_xll.EQNXTDZ($A$1,$B60,E$5,$B$1) -> 0 | F60: =_xll.EQNXTDZ($A$1,$B60,F$5,$B$1) -> 0 | G60: =_xll.EQNXTDZ($A$1,$B60,G$5,$B$1) -> 0 | H60: =_xll.EQNXTDZ($A$1,$B60,H$5,$B$1) -> 0 | I60: =_xll.EQNXTDZ($A$1,$B60,I$5,$B$1) -> 0 | J60: =_xll.EQNXTDZ($A$1,$B60,J$5,$B$1) -> 0 | ... BV60: =_xll.EQNXTDZ($A$1,$B60,BV$5,$B$1) -> 0
A61: Long Term Borrowings | B61: QTRB_TOTAL_DEBTS | C61: =_xll.EQNXTDZ($A$1,$B61,C$5,$B$1) -> 0 | D61: =_xll.EQNXTDZ($A$1,$B61,D$5,$B$1) -> 387.85 | E61: =_xll.EQNXTDZ($A$1,$B61,E$5,$B$1) -> 0 | F61: =_xll.EQNXTDZ($A$1,$B61,F$5,$B$1) -> 344.86 | G61: =_xll.EQNXTDZ($A$1,$B61,G$5,$B$1) -> 0 | H61: =_xll.EQNXTDZ($A$1,$B61,H$5,$B$1) -> 296.25 | I61: =_xll.EQNXTDZ($A$1,$B61,I$5,$B$1) -> 0 | J61: =_xll.EQNXTDZ($A$1,$B61,J$5,$B$1) -> 275.86 | ... BV61: =_xll.EQNXTDZ($A$1,$B61,BV$5,$B$1) -> 0
A62: Secured Loans | B62: QTRB_SECURED_LOANS | C62: =_xll.EQNXTDZ($A$1,$B62,C$5,$B$1) -> 0 | D62: =_xll.EQNXTDZ($A$1,$B62,D$5,$B$1) -> 0 | E62: =_xll.EQNXTDZ($A$1,$B62,E$5,$B$1) -> 0 | F62: =_xll.EQNXTDZ($A$1,$B62,F$5,$B$1) -> 0 | G62: =_xll.EQNXTDZ($A$1,$B62,G$5,$B$1) -> 0 | H62: =_xll.EQNXTDZ($A$1,$B62,H$5,$B$1) -> 0 | I62: =_xll.EQNXTDZ($A$1,$B62,I$5,$B$1) -> 0 | J62: =_xll.EQNXTDZ($A$1,$B62,J$5,$B$1) -> 0 | ... BV62: =_xll.EQNXTDZ($A$1,$B62,BV$5,$B$1) -> 0
A63: Unsecured Loans | B63: QTRB_UNSECURED_LOANS_NF | C63: =_xll.EQNXTDZ($A$1,$B63,C$5,$B$1) -> 0 | D63: =_xll.EQNXTDZ($A$1,$B63,D$5,$B$1) -> 387.85 | E63: =_xll.EQNXTDZ($A$1,$B63,E$5,$B$1) -> 0 | F63: =_xll.EQNXTDZ($A$1,$B63,F$5,$B$1) -> 344.86 | G63: =_xll.EQNXTDZ($A$1,$B63,G$5,$B$1) -> 0 | H63: =_xll.EQNXTDZ($A$1,$B63,H$5,$B$1) -> 296.25 | I63: =_xll.EQNXTDZ($A$1,$B63,I$5,$B$1) -> 0 | J63: =_xll.EQNXTDZ($A$1,$B63,J$5,$B$1) -> 275.86 | ... BV63: =_xll.EQNXTDZ($A$1,$B63,BV$5,$B$1) -> 0
A64: Other Long Term Liabilities | B64: QTRB_OTHER_LT_LIABILITIES | C64: =_xll.EQNXTDZ($A$1,$B64,C$5,$B$1) -> 0 | D64: =_xll.EQNXTDZ($A$1,$B64,D$5,$B$1) -> 0 | E64: =_xll.EQNXTDZ($A$1,$B64,E$5,$B$1) -> 0 | F64: =_xll.EQNXTDZ($A$1,$B64,F$5,$B$1) -> 0 | G64: =_xll.EQNXTDZ($A$1,$B64,G$5,$B$1) -> 0 | H64: =_xll.EQNXTDZ($A$1,$B64,H$5,$B$1) -> 0 | I64: =_xll.EQNXTDZ($A$1,$B64,I$5,$B$1) -> 0 | J64: =_xll.EQNXTDZ($A$1,$B64,J$5,$B$1) -> 0 | ... BV64: =_xll.EQNXTDZ($A$1,$B64,BV$5,$B$1) -> 0
A65: Long Term Trade Payables | B65: QTRB_LT_TRADE_PAYABLE | C65: =_xll.EQNXTDZ($A$1,$B65,C$5,$B$1) -> 0 | D65: =_xll.EQNXTDZ($A$1,$B65,D$5,$B$1) -> 0 | E65: =_xll.EQNXTDZ($A$1,$B65,E$5,$B$1) -> 0 | F65: =_xll.EQNXTDZ($A$1,$B65,F$5,$B$1) -> 0 | G65: =_xll.EQNXTDZ($A$1,$B65,G$5,$B$1) -> 0 | H65: =_xll.EQNXTDZ($A$1,$B65,H$5,$B$1) -> 0 | I65: =_xll.EQNXTDZ($A$1,$B65,I$5,$B$1) -> 0 | J65: =_xll.EQNXTDZ($A$1,$B65,J$5,$B$1) -> 0 | ... BV65: =_xll.EQNXTDZ($A$1,$B65,BV$5,$B$1) -> 0
A66: Lont Term Provisions | B66: QTRB_LT_PROVISIONS | C66: =_xll.EQNXTDZ($A$1,$B66,C$5,$B$1) -> 0 | D66: =_xll.EQNXTDZ($A$1,$B66,D$5,$B$1) -> 0 | E66: =_xll.EQNXTDZ($A$1,$B66,E$5,$B$1) -> 0 | F66: =_xll.EQNXTDZ($A$1,$B66,F$5,$B$1) -> 0 | G66: =_xll.EQNXTDZ($A$1,$B66,G$5,$B$1) -> 0 | H66: =_xll.EQNXTDZ($A$1,$B66,H$5,$B$1) -> 0 | I66: =_xll.EQNXTDZ($A$1,$B66,I$5,$B$1) -> 0 | J66: =_xll.EQNXTDZ($A$1,$B66,J$5,$B$1) -> 0 | ... BV66: =_xll.EQNXTDZ($A$1,$B66,BV$5,$B$1) -> 0
... A97: Total Assets | B97: QTRB_TOTAL_APPLICATIONS | C97: =_xll.EQNXTDZ($A$1,$B97,C$5,$B$1) -> 0 | D97: =_xll.EQNXTDZ($A$1,$B97,D$5,$B$1) -> 667.79 | E97: =_xll.EQNXTDZ($A$1,$B97,E$5,$B$1) -> 0 | F97: =_xll.EQNXTDZ($A$1,$B97,F$5,$B$1) -> 642.71 | G97: =_xll.EQNXTDZ($A$1,$B97,G$5,$B$1) -> 0 | H97: =_xll.EQNXTDZ($A$1,$B97,H$5,$B$1) -> 612.37 | I97: =_xll.EQNXTDZ($A$1,$B97,I$5,$B$1) -> 0 | J97: =_xll.EQNXTDZ($A$1,$B97,J$5,$B$1) -> 607.27 | ... BV97: =_xll.EQNXTDZ($A$1,$B97,BV$5,$B$1) -> 0

Sheet Sheet3

Sheet Annual Raw
A1: 114234 | B1: X | C1: 200103 | D1: 200203 | E1: 200303 | F1: 200403 | G1: 200503 | H1: 200603 | I1: 200703 | J1: 200803 | K1: 200903 | L1: 201003 | M1: 201103 | N1: 201203 | O1: 201303 | P1: 201403 | Q1: 201503 | R1: 201603 | S1: 201703 | T1: 201803 | U1: 201903 | V1: 202003 | W1: 202103 | X1: 202203 | Y1: 202303 | Z1: 202403 | AA1: 202503 | AB1: 202603 | AC1: 202703 | AD1: 202803 | AE1: 202903 | AF1: 203003
A3: Field Description | B3: Field Name
A4: Company Name | B4: CD_COMPNAME | C4: =_xll.EQNXTDZ(A1,B4,"L") -> Sangam (India) Ltd.
A5: Year End | B5: PL_YEAR_END | C5: =_xll.EQNXTDZ($A$1,$B5,C$1,$B$1) -> 200103 | D5: =_xll.EQNXTDZ($A$1,$B5,D$1,$B$1) -> 200203 | E5: =_xll.EQNXTDZ($A$1,$B5,E$1,$B$1) -> 200303 | F5: =_xll.EQNXTDZ($A$1,$B5,F$1,$B$1) -> 200403 | G5: =_xll.EQNXTDZ($A$1,$B5,G$1,$B$1) -> 200503 | H5: =_xll.EQNXTDZ($A$1,$B5,H$1,$B$1) -> 200603 | I5: =_xll.EQNXTDZ($A$1,$B5,I$1,$B$1) -> 200703 | J5: =_xll.EQNXTDZ($A$1,$B5,J$1,$B$1) -> 200803 | ... AF5: =_xll.EQNXTDZ($A$1,$B5,AF$1,$B$1) -> 0
A6: Sales Turnover | B6: PL_TOTAL_GROSS_SALES | C6: =_xll.EQNXTDZ($A$1,$B6,C$1,$B$1) -> 228.61852 | D6: =_xll.EQNXTDZ($A$1,$B6,D$1,$B$1) -> 217.23503 | E6: =_xll.EQNXTDZ($A$1,$B6,E$1,$B$1) -> 225.45649 | F6: =_xll.EQNXTDZ($A$1,$B6,F$1,$B$1) -> 298.60219 | G6: =_xll.EQNXTDZ($A$1,$B6,G$1,$B$1) -> 311.36159 | H6: =_xll.EQNXTDZ($A$1,$B6,H$1,$B$1) -> 363.44456 | I6: =_xll.EQNXTDZ($A$1,$B6,I$1,$B$1) -> 554.76021 | J6: =_xll.EQNXTDZ($A$1,$B6,J$1,$B$1) -> 695.05185 | ... AF6: =_xll.EQNXTDZ($A$1,$B6,AF$1,$B$1) -> 0
A7: Less: Inter divisional transfers | B7: PL_INTER_DIV_TRF | C7: =_xll.EQNXTDZ($A$1,$B7,C$1,$B$1) -> 20.628236 | D7: =_xll.EQNXTDZ($A$1,$B7,D$1,$B$1) -> 0 | E7: =_xll.EQNXTDZ($A$1,$B7,E$1,$B$1) -> 0 | F7: =_xll.EQNXTDZ($A$1,$B7,F$1,$B$1) -> 0 | G7: =_xll.EQNXTDZ($A$1,$B7,G$1,$B$1) -> 0 | H7: =_xll.EQNXTDZ($A$1,$B7,H$1,$B$1) -> 0 | I7: =_xll.EQNXTDZ($A$1,$B7,I$1,$B$1) -> 0 | J7: =_xll.EQNXTDZ($A$1,$B7,J$1,$B$1) -> 0 | ... AF7: =_xll.EQNXTDZ($A$1,$B7,AF$1,$B$1) -> 0
A8: Less: Sales Returns | B8: PL_SALES_RETURN | C8: =_xll.EQNXTDZ($A$1,$B8,C$1,$B$1) -> 0 | D8: =_xll.EQNXTDZ($A$1,$B8,D$1,$B$1) -> 0 | E8: =_xll.EQNXTDZ($A$1,$B8,E$1,$B$1) -> 0 | F8: =_xll.EQNXTDZ($A$1,$B8,F$1,$B$1) -> 0 | G8: =_xll.EQNXTDZ($A$1,$B8,G$1,$B$1) -> 0 | H8: =_xll.EQNXTDZ($A$1,$B8,H$1,$B$1) -> 0 | I8: =_xll.EQNXTDZ($A$1,$B8,I$1,$B$1) -> 0 | J8: =_xll.EQNXTDZ($A$1,$B8,J$1,$B$1) -> 0 | ... AF8: =_xll.EQNXTDZ($A$1,$B8,AF$1,$B$1) -> 0
A9: Less: Excise | B9: PL_EXCISE | C9: =_xll.EQNXTDZ($A$1,$B9,C$1,$B$1) -> 24.499193 | D9: =_xll.EQNXTDZ($A$1,$B9,D$1,$B$1) -> 27.553137 | E9: =_xll.EQNXTDZ($A$1,$B9,E$1,$B$1) -> 29.747753 | F9: =_xll.EQNXTDZ($A$1,$B9,F$1,$B$1) -> 31.447642 | G9: =_xll.EQNXTDZ($A$1,$B9,G$1,$B$1) -> 21.784497 | H9: =_xll.EQNXTDZ($A$1,$B9,H$1,$B$1) -> 16.657603 | I9: =_xll.EQNXTDZ($A$1,$B9,I$1,$B$1) -> 2.4015717 | J9: =_xll.EQNXTDZ($A$1,$B9,J$1,$B$1) -> 1.6698029 | ... AF9: =_xll.EQNXTDZ($A$1,$B9,AF$1,$B$1) -> 0
A10: Net Sales | B10: PL_NET_SALES | C10: =_xll.EQNXTDZ($A$1,$B10,C$1,$B$1) -> 183.49109 | D10: =_xll.EQNXTDZ($A$1,$B10,D$1,$B$1) -> 189.68189 | E10: =_xll.EQNXTDZ($A$1,$B10,E$1,$B$1) -> 195.70873 | F10: =_xll.EQNXTDZ($A$1,$B10,F$1,$B$1) -> 267.15454 | G10: =_xll.EQNXTDZ($A$1,$B10,G$1,$B$1) -> 289.57709 | H10: =_xll.EQNXTDZ($A$1,$B10,H$1,$B$1) -> 346.78696 | I10: =_xll.EQNXTDZ($A$1,$B10,I$1,$B$1) -> 552.35864 | J10: =_xll.EQNXTDZ($A$1,$B10,J$1,$B$1) -> 693.38204 | ... AF10: =_xll.EQNXTDZ($A$1,$B10,AF$1,$B$1) -> 0
A11: Increase/Decrease in Stock | B11: PL_INC_DEC_INVENTORY | C11: =_xll.EQNXTDZ($A$1,$B11,C$1,$B$1) -> -0.5067473 | D11: =_xll.EQNXTDZ($A$1,$B11,D$1,$B$1) -> 3.5157219 | E11: =_xll.EQNXTDZ($A$1,$B11,E$1,$B$1) -> -7.2267181 | F11: =_xll.EQNXTDZ($A$1,$B11,F$1,$B$1) -> -2.8291686 | G11: =_xll.EQNXTDZ($A$1,$B11,G$1,$B$1) -> -5.3305705 | H11: =_xll.EQNXTDZ($A$1,$B11,H$1,$B$1) -> -6.716897 | I11: =_xll.EQNXTDZ($A$1,$B11,I$1,$B$1) -> -20.445548 | J11: =_xll.EQNXTDZ($A$1,$B11,J$1,$B$1) -> -21.801716 | ... AF11: =_xll.EQNXTDZ($A$1,$B11,AF$1,$B$1) -> 0
A12: Raw Material Consumed | B12: PL_RAW_MATRS_CONSUMED | C12: =_xll.EQNXTDZ($A$1,$B12,C$1,$B$1) -> 108.21479 | D12: =_xll.EQNXTDZ($A$1,$B12,D$1,$B$1) -> 106.92158 | E12: =_xll.EQNXTDZ($A$1,$B12,E$1,$B$1) -> 120.69857 | F12: =_xll.EQNXTDZ($A$1,$B12,F$1,$B$1) -> 163.01752 | G12: =_xll.EQNXTDZ($A$1,$B12,G$1,$B$1) -> 177.16084 | H12: =_xll.EQNXTDZ($A$1,$B12,H$1,$B$1) -> 202.08444 | I12: =_xll.EQNXTDZ($A$1,$B12,I$1,$B$1) -> 331.10324 | J12: =_xll.EQNXTDZ($A$1,$B12,J$1,$B$1) -> 434.69338 | ... AF12: =_xll.EQNXTDZ($A$1,$B12,AF$1,$B$1) -> 0
A13: Power & Fuel Cost | B13: PL_POWER_FUEL | C13: =_xll.EQNXTDZ($A$1,$B13,C$1,$B$1) -> 16.030761 | D13: =_xll.EQNXTDZ($A$1,$B13,D$1,$B$1) -> 14.32233 | E13: =_xll.EQNXTDZ($A$1,$B13,E$1,$B$1) -> 16.242541 | F13: =_xll.EQNXTDZ($A$1,$B13,F$1,$B$1) -> 24.662792 | G13: =_xll.EQNXTDZ($A$1,$B13,G$1,$B$1) -> 26.673482 | H13: =_xll.EQNXTDZ($A$1,$B13,H$1,$B$1) -> 27.422207 | I13: =_xll.EQNXTDZ($A$1,$B13,I$1,$B$1) -> 56.216065 | J13: =_xll.EQNXTDZ($A$1,$B13,J$1,$B$1) -> 75.572922 | ... AF13: =_xll.EQNXTDZ($A$1,$B13,AF$1,$B$1) -> 0
A14: Employee Cost | B14: PL_EMPLOYEES | C14: =_xll.EQNXTDZ($A$1,$B14,C$1,$B$1) -> 9.3838041 | D14: =_xll.EQNXTDZ($A$1,$B14,D$1,$B$1) -> 9.9036198 | E14: =_xll.EQNXTDZ($A$1,$B14,E$1,$B$1) -> 10.181259 | F14: =_xll.EQNXTDZ($A$1,$B14,F$1,$B$1) -> 13.762118 | G14: =_xll.EQNXTDZ($A$1,$B14,G$1,$B$1) -> 16.245073 | H14: =_xll.EQNXTDZ($A$1,$B14,H$1,$B$1) -> 18.710016 | I14: =_xll.EQNXTDZ($A$1,$B14,I$1,$B$1) -> 34.036641 | J14: =_xll.EQNXTDZ($A$1,$B14,J$1,$B$1) -> 44.658973 | ... AF14: =_xll.EQNXTDZ($A$1,$B14,AF$1,$B$1) -> 0
A15: Operating & Manufacturing Expenses | B15: PL_GEN_OTHER_MFG_EXPS | C15: =_xll.EQNXTDZ($A$1,$B15,C$1,$B$1) -> 16.031576 | D15: =_xll.EQNXTDZ($A$1,$B15,D$1,$B$1) -> 22.908752 | E15: =_xll.EQNXTDZ($A$1,$B15,E$1,$B$1) -> 16.674619 | F15: =_xll.EQNXTDZ($A$1,$B15,F$1,$B$1) -> 19.261937 | G15: =_xll.EQNXTDZ($A$1,$B15,G$1,$B$1) -> 19.939484 | H15: =_xll.EQNXTDZ($A$1,$B15,H$1,$B$1) -> 27.49286 | I15: =_xll.EQNXTDZ($A$1,$B15,I$1,$B$1) -> 29.696939 | J15: =_xll.EQNXTDZ($A$1,$B15,J$1,$B$1) -> 40.396378 | ... AF15: =_xll.EQNXTDZ($A$1,$B15,AF$1,$B$1) -> 0
A16: Cost of Software development | B16: PL_COST_SW | C16: =_xll.EQNXTDZ($A$1,$B16,C$1,$B$1) -> 0 | D16: =_xll.EQNXTDZ($A$1,$B16,D$1,$B$1) -> 0 | E16: =_xll.EQNXTDZ($A$1,$B16,E$1,$B$1) -> 0 | F16: =_xll.EQNXTDZ($A$1,$B16,F$1,$B$1) -> 0 | G16: =_xll.EQNXTDZ($A$1,$B16,G$1,$B$1) -> 0 | H16: =_xll.EQNXTDZ($A$1,$B16,H$1,$B$1) -> 0 | I16: =_xll.EQNXTDZ($A$1,$B16,I$1,$B$1) -> 0 | J16: =_xll.EQNXTDZ($A$1,$B16,J$1,$B$1) -> 0 | ... AF16: =_xll.EQNXTDZ($A$1,$B16,AF$1,$B$1) -> 0
... A36: Profit After Tax from Discontinued Operations | B36: PL_PAT_DIS_OP | C36: =_xll.EQNXTDZ($A$1,$B36,C$1,$B$1) -> 0 | D36: =_xll.EQNXTDZ($A$1,$B36,D$1,$B$1) -> 0 | E36: =_xll.EQNXTDZ($A$1,$B36,E$1,$B$1) -> 0 | F36: =_xll.EQNXTDZ($A$1,$B36,F$1,$B$1) -> 0 | G36: =_xll.EQNXTDZ($A$1,$B36,G$1,$B$1) -> 0 | H36: =_xll.EQNXTDZ($A$1,$B36,H$1,$B$1) -> 0 | I36: =_xll.EQNXTDZ($A$1,$B36,I$1,$B$1) -> 0 | J36: =_xll.EQNXTDZ($A$1,$B36,J$1,$B$1) -> 0 | ... AF36: =_xll.EQNXTDZ($A$1,$B36,AF$1,$B$1) -> 0
A39: Field Description | B39: Field Name
A40: Year End | B40: BS_YEAR_END | C40: =_xll.EQNXTDZ($A$1,$B40,C$1,$B$1) -> 200103 | D40: =_xll.EQNXTDZ($A$1,$B40,D$1,$B$1) -> 200203 | E40: =_xll.EQNXTDZ($A$1,$B40,E$1,$B$1) -> 200303 | F40: =_xll.EQNXTDZ($A$1,$B40,F$1,$B$1) -> 200403 | G40: =_xll.EQNXTDZ($A$1,$B40,G$1,$B$1) -> 200503 | H40: =_xll.EQNXTDZ($A$1,$B40,H$1,$B$1) -> 200603 | I40: =_xll.EQNXTDZ($A$1,$B40,I$1,$B$1) -> 200703 | J40: =_xll.EQNXTDZ($A$1,$B40,J$1,$B$1) -> 200803 | ... AF40: =_xll.EQNXTDZ($A$1,$B40,AF$1,$B$1) -> 0
A41: Share Capital | B41: BS_SHARE_CAPITAL | C41: =_xll.EQNXTDZ($A$1,$B41,C$1,$B$1) -> 20.4359 | D41: =_xll.EQNXTDZ($A$1,$B41,D$1,$B$1) -> 21.6359 | E41: =_xll.EQNXTDZ($A$1,$B41,E$1,$B$1) -> 21.6359 | F41: =_xll.EQNXTDZ($A$1,$B41,F$1,$B$1) -> 29.850452 | G41: =_xll.EQNXTDZ($A$1,$B41,G$1,$B$1) -> 29.850452 | H41: =_xll.EQNXTDZ($A$1,$B41,H$1,$B$1) -> 33.32923 | I41: =_xll.EQNXTDZ($A$1,$B41,I$1,$B$1) -> 39.421559 | J41: =_xll.EQNXTDZ($A$1,$B41,J$1,$B$1) -> 39.421559 | ... AF41: =_xll.EQNXTDZ($A$1,$B41,AF$1,$B$1) -> 0
A42: Share Warrants & Outstandings | B42: BS_SHAREWROUTST | C42: =_xll.EQNXTDZ($A$1,$B42,C$1,$B$1) -> 0 | D42: =_xll.EQNXTDZ($A$1,$B42,D$1,$B$1) -> 0 | E42: =_xll.EQNXTDZ($A$1,$B42,E$1,$B$1) -> 0 | F42: =_xll.EQNXTDZ($A$1,$B42,F$1,$B$1) -> 0 | G42: =_xll.EQNXTDZ($A$1,$B42,G$1,$B$1) -> 0 | H42: =_xll.EQNXTDZ($A$1,$B42,H$1,$B$1) -> 2.261339 | I42: =_xll.EQNXTDZ($A$1,$B42,I$1,$B$1) -> 0 | J42: =_xll.EQNXTDZ($A$1,$B42,J$1,$B$1) -> 0 | ... AF42: =_xll.EQNXTDZ($A$1,$B42,AF$1,$B$1) -> 0
A43: Total Reserves | B43: BS_RESERVE | C43: =_xll.EQNXTDZ($A$1,$B43,C$1,$B$1) -> 31.758912 | D43: =_xll.EQNXTDZ($A$1,$B43,D$1,$B$1) -> 24.615586 | E43: =_xll.EQNXTDZ($A$1,$B43,E$1,$B$1) -> 30.119852 | F43: =_xll.EQNXTDZ($A$1,$B43,F$1,$B$1) -> 42.930938 | G43: =_xll.EQNXTDZ($A$1,$B43,G$1,$B$1) -> 53.288591 | H43: =_xll.EQNXTDZ($A$1,$B43,H$1,$B$1) -> 103.99195 | I43: =_xll.EQNXTDZ($A$1,$B43,I$1,$B$1) -> 148.49761 | J43: =_xll.EQNXTDZ($A$1,$B43,J$1,$B$1) -> 153.87218 | ... AF43: =_xll.EQNXTDZ($A$1,$B43,AF$1,$B$1) -> 0
A44: Shareholder's Funds | B44: BS_SHAREHODERS_FUNDS | C44: =_xll.EQNXTDZ($A$1,$B44,C$1,$B$1) -> 52.194812 | D44: =_xll.EQNXTDZ($A$1,$B44,D$1,$B$1) -> 46.251486 | E44: =_xll.EQNXTDZ($A$1,$B44,E$1,$B$1) -> 51.755752 | F44: =_xll.EQNXTDZ($A$1,$B44,F$1,$B$1) -> 72.78139 | G44: =_xll.EQNXTDZ($A$1,$B44,G$1,$B$1) -> 83.139043 | H44: =_xll.EQNXTDZ($A$1,$B44,H$1,$B$1) -> 139.58252 | I44: =_xll.EQNXTDZ($A$1,$B44,I$1,$B$1) -> 187.91917 | J44: =_xll.EQNXTDZ($A$1,$B44,J$1,$B$1) -> 193.29374 | ... AF44: =_xll.EQNXTDZ($A$1,$B44,AF$1,$B$1) -> 0
A45: Minority Interest | B45: BS_MINORITY_INTEREST | C45: =_xll.EQNXTDZ($A$1,$B45,C$1,$B$1) -> 0 | D45: =_xll.EQNXTDZ($A$1,$B45,D$1,$B$1) -> 0 | E45: =_xll.EQNXTDZ($A$1,$B45,E$1,$B$1) -> 0 | F45: =_xll.EQNXTDZ($A$1,$B45,F$1,$B$1) -> 0 | G45: =_xll.EQNXTDZ($A$1,$B45,G$1,$B$1) -> 0 | H45: =_xll.EQNXTDZ($A$1,$B45,H$1,$B$1) -> 0 | I45: =_xll.EQNXTDZ($A$1,$B45,I$1,$B$1) -> 0 | J45: =_xll.EQNXTDZ($A$1,$B45,J$1,$B$1) -> 0 | ... AF45: =_xll.EQNXTDZ($A$1,$B45,AF$1,$B$1) -> 0
A46: Long-Term Borrowings | B46: BS_LTRM_BORROWING | C46: =_xll.EQNXTDZ($A$1,$B46,C$1,$B$1) -> 0 | D46: =_xll.EQNXTDZ($A$1,$B46,D$1,$B$1) -> 0 | E46: =_xll.EQNXTDZ($A$1,$B46,E$1,$B$1) -> 0 | F46: =_xll.EQNXTDZ($A$1,$B46,F$1,$B$1) -> 0 | G46: =_xll.EQNXTDZ($A$1,$B46,G$1,$B$1) -> 0 | H46: =_xll.EQNXTDZ($A$1,$B46,H$1,$B$1) -> 0 | I46: =_xll.EQNXTDZ($A$1,$B46,I$1,$B$1) -> 0 | J46: =_xll.EQNXTDZ($A$1,$B46,J$1,$B$1) -> 0 | ... AF46: =_xll.EQNXTDZ($A$1,$B46,AF$1,$B$1) -> 0
A47: Secured Loans | B47: BS_SECURED_LOANS | C47: =_xll.EQNXTDZ($A$1,$B47,C$1,$B$1) -> 72.910683 | D47: =_xll.EQNXTDZ($A$1,$B47,D$1,$B$1) -> 66.359124 | E47: =_xll.EQNXTDZ($A$1,$B47,E$1,$B$1) -> 99.220855 | F47: =_xll.EQNXTDZ($A$1,$B47,F$1,$B$1) -> 158.01656 | G47: =_xll.EQNXTDZ($A$1,$B47,G$1,$B$1) -> 180.04327 | H47: =_xll.EQNXTDZ($A$1,$B47,H$1,$B$1) -> 291.96326 | I47: =_xll.EQNXTDZ($A$1,$B47,I$1,$B$1) -> 603.93683 | J47: =_xll.EQNXTDZ($A$1,$B47,J$1,$B$1) -> 677.54288 | ... AF47: =_xll.EQNXTDZ($A$1,$B47,AF$1,$B$1) -> 0
A48: Unsecured Loans | B48: BS_UNSECURED_LOANS_NF | C48: =_xll.EQNXTDZ($A$1,$B48,C$1,$B$1) -> 1.73 | D48: =_xll.EQNXTDZ($A$1,$B48,D$1,$B$1) -> 5.21 | E48: =_xll.EQNXTDZ($A$1,$B48,E$1,$B$1) -> 5.21 | F48: =_xll.EQNXTDZ($A$1,$B48,F$1,$B$1) -> 6.2685 | G48: =_xll.EQNXTDZ($A$1,$B48,G$1,$B$1) -> 5 | H48: =_xll.EQNXTDZ($A$1,$B48,H$1,$B$1) -> 20 | I48: =_xll.EQNXTDZ($A$1,$B48,I$1,$B$1) -> 40.81427 | J48: =_xll.EQNXTDZ($A$1,$B48,J$1,$B$1) -> 52.08507 | ... AF48: =_xll.EQNXTDZ($A$1,$B48,AF$1,$B$1) -> 0
A49: Deferred Tax Assets / Liabilities | B49: BS_NET_DEF_TAX_NF | C49: =_xll.EQNXTDZ($A$1,$B49,C$1,$B$1) -> 0 | D49: =_xll.EQNXTDZ($A$1,$B49,D$1,$B$1) -> 12.721459 | E49: =_xll.EQNXTDZ($A$1,$B49,E$1,$B$1) -> 15.423137 | F49: =_xll.EQNXTDZ($A$1,$B49,F$1,$B$1) -> 17.972214 | G49: =_xll.EQNXTDZ($A$1,$B49,G$1,$B$1) -> 20.601136 | H49: =_xll.EQNXTDZ($A$1,$B49,H$1,$B$1) -> 27.008712 | I49: =_xll.EQNXTDZ($A$1,$B49,I$1,$B$1) -> 40.793093 | J49: =_xll.EQNXTDZ($A$1,$B49,J$1,$B$1) -> 41.692893 | ... AF49: =_xll.EQNXTDZ($A$1,$B49,AF$1,$B$1) -> 0
A50: Other Long Term Liabilities | B50: BS_OTH_LT_LIAB | C50: =_xll.EQNXTDZ($A$1,$B50,C$1,$B$1) -> 0 | D50: =_xll.EQNXTDZ($A$1,$B50,D$1,$B$1) -> 0 | E50: =_xll.EQNXTDZ($A$1,$B50,E$1,$B$1) -> 0 | F50: =_xll.EQNXTDZ($A$1,$B50,F$1,$B$1) -> 0 | G50: =_xll.EQNXTDZ($A$1,$B50,G$1,$B$1) -> 0 | H50: =_xll.EQNXTDZ($A$1,$B50,H$1,$B$1) -> 0 | I50: =_xll.EQNXTDZ($A$1,$B50,I$1,$B$1) -> 0 | J50: =_xll.EQNXTDZ($A$1,$B50,J$1,$B$1) -> 0 | ... AF50: =_xll.EQNXTDZ($A$1,$B50,AF$1,$B$1) -> 0
A51: Long Term Trade Payables | B51: BS_LT_TRADE_PAYABLES | C51: =_xll.EQNXTDZ($A$1,$B51,C$1,$B$1) -> 0 | D51: =_xll.EQNXTDZ($A$1,$B51,D$1,$B$1) -> 0 | E51: =_xll.EQNXTDZ($A$1,$B51,E$1,$B$1) -> 0 | F51: =_xll.EQNXTDZ($A$1,$B51,F$1,$B$1) -> 0 | G51: =_xll.EQNXTDZ($A$1,$B51,G$1,$B$1) -> 0 | H51: =_xll.EQNXTDZ($A$1,$B51,H$1,$B$1) -> 0 | I51: =_xll.EQNXTDZ($A$1,$B51,I$1,$B$1) -> 0 | J51: =_xll.EQNXTDZ($A$1,$B51,J$1,$B$1) -> 0 | ... AF51: =_xll.EQNXTDZ($A$1,$B51,AF$1,$B$1) -> 0
... A99: Estimated Capital Contracts Remaining | B99: BS_ESTIMATED_CAPITAL_CONTRACT | C99: =_xll.EQNXTDZ($A$1,$B99,C$1,$B$1) -> 2.923 | D99: =_xll.EQNXTDZ($A$1,$B99,D$1,$B$1) -> 0.045 | E99: =_xll.EQNXTDZ($A$1,$B99,E$1,$B$1) -> 10.0352 | F99: =_xll.EQNXTDZ($A$1,$B99,F$1,$B$1) -> 3.9863 | G99: =_xll.EQNXTDZ($A$1,$B99,G$1,$B$1) -> 18.5439 | H99: =_xll.EQNXTDZ($A$1,$B99,H$1,$B$1) -> 132.7168 | I99: =_xll.EQNXTDZ($A$1,$B99,I$1,$B$1) -> 69.2557 | J99: =_xll.EQNXTDZ($A$1,$B99,J$1,$B$1) -> 18.8218 | ... AF99: =_xll.EQNXTDZ($A$1,$B99,AF$1,$B$1) -> 0
A103: Field Description | B103: Field Name
A104: Equity Paid Up | B104: BS_EQUITY_PAIDUP | C104: =_xll.EQNXTDZ($A$1,$B104,C$1,$B$1) -> 16.4359 | D104: =_xll.EQNXTDZ($A$1,$B104,D$1,$B$1) -> 16.4359 | E104: =_xll.EQNXTDZ($A$1,$B104,E$1,$B$1) -> 16.4359 | F104: =_xll.EQNXTDZ($A$1,$B104,F$1,$B$1) -> 24.650452 | G104: =_xll.EQNXTDZ($A$1,$B104,G$1,$B$1) -> 24.650452 | H104: =_xll.EQNXTDZ($A$1,$B104,H$1,$B$1) -> 33.32923 | I104: =_xll.EQNXTDZ($A$1,$B104,I$1,$B$1) -> 39.421559 | J104: =_xll.EQNXTDZ($A$1,$B104,J$1,$B$1) -> 39.421559 | ... AF104: =_xll.EQNXTDZ($A$1,$B104,AF$1,$B$1) -> 0
A105: Face Value | B105: BS_FACE_VALUE | C105: =_xll.EQNXTDZ($A$1,$B105,C$1,$B$1) -> 10 | D105: =_xll.EQNXTDZ($A$1,$B105,D$1,$B$1) -> 10 | E105: =_xll.EQNXTDZ($A$1,$B105,E$1,$B$1) -> 10 | F105: =_xll.EQNXTDZ($A$1,$B105,F$1,$B$1) -> 10 | G105: =_xll.EQNXTDZ($A$1,$B105,G$1,$B$1) -> 10 | H105: =_xll.EQNXTDZ($A$1,$B105,H$1,$B$1) -> 10 | I105: =_xll.EQNXTDZ($A$1,$B105,I$1,$B$1) -> 10 | J105: =_xll.EQNXTDZ($A$1,$B105,J$1,$B$1) -> 10 | ... AF105: =_xll.EQNXTDZ($A$1,$B105,AF$1,$B$1) -> 0
A106: Close Price (Unit Curr.) | B106: FH_YEAR_PRICE | C106: =_xll.EQNXTDZ($A$1,$B106,C$1,$B$1) -> 9.0231214 | D106: =_xll.EQNXTDZ($A$1,$B106,D$1,$B$1) -> 7.2184971 | E106: =_xll.EQNXTDZ($A$1,$B106,E$1,$B$1) -> 8.5934489 | F106: =_xll.EQNXTDZ($A$1,$B106,F$1,$B$1) -> 16.5 | G106: =_xll.EQNXTDZ($A$1,$B106,G$1,$B$1) -> 34.3 | H106: =_xll.EQNXTDZ($A$1,$B106,H$1,$B$1) -> 75.65 | I106: =_xll.EQNXTDZ($A$1,$B106,I$1,$B$1) -> 79.15 | J106: =_xll.EQNXTDZ($A$1,$B106,J$1,$B$1) -> 28.1 | ... AF106: =_xll.EQNXTDZ($A$1,$B106,AF$1,$B$1) -> 0
A107: High Price (Unit Curr.) | B107: FH_HIGH | C107: =_xll.EQNXTDZ($A$1,$B107,C$1,$B$1) -> 23.589017 | D107: =_xll.EQNXTDZ($A$1,$B107,D$1,$B$1) -> 11.85896 | E107: =_xll.EQNXTDZ($A$1,$B107,E$1,$B$1) -> 18.475915 | F107: =_xll.EQNXTDZ($A$1,$B107,F$1,$B$1) -> 40.5 | G107: =_xll.EQNXTDZ($A$1,$B107,G$1,$B$1) -> 42.25 | H107: =_xll.EQNXTDZ($A$1,$B107,H$1,$B$1) -> 96 | I107: =_xll.EQNXTDZ($A$1,$B107,I$1,$B$1) -> 103 | J107: =_xll.EQNXTDZ($A$1,$B107,J$1,$B$1) -> 90.9 | ... AF107: =_xll.EQNXTDZ($A$1,$B107,AF$1,$B$1) -> 0
A108: Low Price (Unit Curr.) | B108: FH_LOW | C108: =_xll.EQNXTDZ($A$1,$B108,C$1,$B$1) -> 8.8942197 | D108: =_xll.EQNXTDZ($A$1,$B108,D$1,$B$1) -> 6.1872832 | E108: =_xll.EQNXTDZ($A$1,$B108,E$1,$B$1) -> 6.5739884 | F108: =_xll.EQNXTDZ($A$1,$B108,F$1,$B$1) -> 8.5934489 | G108: =_xll.EQNXTDZ($A$1,$B108,G$1,$B$1) -> 14.75 | H108: =_xll.EQNXTDZ($A$1,$B108,H$1,$B$1) -> 33 | I108: =_xll.EQNXTDZ($A$1,$B108,I$1,$B$1) -> 50.1 | J108: =_xll.EQNXTDZ($A$1,$B108,J$1,$B$1) -> 24.05 | ... AF108: =_xll.EQNXTDZ($A$1,$B108,AF$1,$B$1) -> 0
A109: Market Capitalization | B109: FH_MCAP | C109: =_xll.EQNXTDZ($A$1,$B109,C$1,$B$1) -> 17.257695 | D109: =_xll.EQNXTDZ($A$1,$B109,D$1,$B$1) -> 13.806156 | E109: =_xll.EQNXTDZ($A$1,$B109,E$1,$B$1) -> 16.4359 | F109: =_xll.EQNXTDZ($A$1,$B109,F$1,$B$1) -> 40.673246 | G109: =_xll.EQNXTDZ($A$1,$B109,G$1,$B$1) -> 84.55105 | H109: =_xll.EQNXTDZ($A$1,$B109,H$1,$B$1) -> 252.13562 | I109: =_xll.EQNXTDZ($A$1,$B109,I$1,$B$1) -> 312.02164 | J109: =_xll.EQNXTDZ($A$1,$B109,J$1,$B$1) -> 110.77458 | ... AF109: =_xll.EQNXTDZ($A$1,$B109,AF$1,$B$1) -> 0
A110: Adj DPS(Rs) | B110: FR_ADJ_DPS | C110: =_xll.EQNXTDZ($A$1,$B110,C$1,$B$1) -> 0.86206897 | D110: =_xll.EQNXTDZ($A$1,$B110,D$1,$B$1) -> 0 | E110: =_xll.EQNXTDZ($A$1,$B110,E$1,$B$1) -> 0.68965517 | F110: =_xll.EQNXTDZ($A$1,$B110,F$1,$B$1) -> 0.8 | G110: =_xll.EQNXTDZ($A$1,$B110,G$1,$B$1) -> 1.1 | H110: =_xll.EQNXTDZ($A$1,$B110,H$1,$B$1) -> 1.5 | I110: =_xll.EQNXTDZ($A$1,$B110,I$1,$B$1) -> 1 | J110: =_xll.EQNXTDZ($A$1,$B110,J$1,$B$1) -> 0 | ... AF110: =_xll.EQNXTDZ($A$1,$B110,AF$1,$B$1) -> 0
A111: Date End | B111: SHP_DATE_END | C111: =_xll.EQNXTDZ($A$1,$B111,C$5) -> 200103 | D111: =_xll.EQNXTDZ($A$1,$B111,D$5) -> 200203 | E111: =_xll.EQNXTDZ($A$1,$B111,E$5) -> 200303 | F111: =_xll.EQNXTDZ($A$1,$B111,F$5) -> 200403 | G111: =_xll.EQNXTDZ($A$1,$B111,G$5) -> 200503 | H111: =_xll.EQNXTDZ($A$1,$B111,H$5) -> 200603 | I111: =_xll.EQNXTDZ($A$1,$B111,I$5) -> 200703 | J111: =_xll.EQNXTDZ($A$1,$B111,J$5) -> 200803 | ... AF111: =_xll.EQNXTDZ($A$1,$B111,AF$5) -> 0
A112: Total of Promoter and Promoter Group | B112: SHP_TPFTOTALPROMOTER | C112: =_xll.EQNXTDZ($A$1,$B112,C$5) -> 51.26 | D112: =_xll.EQNXTDZ($A$1,$B112,D$5) -> 50.73 | E112: =_xll.EQNXTDZ($A$1,$B112,E$5) -> 48.69 | F112: =_xll.EQNXTDZ($A$1,$B112,F$5) -> 41.83 | G112: =_xll.EQNXTDZ($A$1,$B112,G$5) -> 41.83 | H112: =_xll.EQNXTDZ($A$1,$B112,H$5) -> 35.44 | I112: =_xll.EQNXTDZ($A$1,$B112,I$5) -> 36.03 | J112: =_xll.EQNXTDZ($A$1,$B112,J$5) -> 36.03 | ... AF112: =_xll.EQNXTDZ($A$1,$B112,AF$5) -> 0
A113: Total of Promoter and Promoter Group Pledged | B113: SHP_PSHFTOTALPROMOTER | C113: =_xll.EQNXTDZ($A$1,$B113,C$5) -> 0 | D113: =_xll.EQNXTDZ($A$1,$B113,D$5) -> 0 | E113: =_xll.EQNXTDZ($A$1,$B113,E$5) -> 0 | F113: =_xll.EQNXTDZ($A$1,$B113,F$5) -> 0 | G113: =_xll.EQNXTDZ($A$1,$B113,G$5) -> 0 | H113: =_xll.EQNXTDZ($A$1,$B113,H$5) -> 0 | I113: =_xll.EQNXTDZ($A$1,$B113,I$5) -> 0 | J113: =_xll.EQNXTDZ($A$1,$B113,J$5) -> 0 | ... AF113: =_xll.EQNXTDZ($A$1,$B113,AF$5) -> 0

Sheet QTR Share Price
A1: ='QTR Raw'!A1 -> 114234 | C1: 201206 | D1: 201207 | E1: 201208 | F1: 201209 | G1: 201210 | H1: 201211 | I1: 201212 | J1: 201301 | K1: 201302 | L1: 201303 | M1: 201304 | N1: 201305 | O1: 201306 | P1: 201307 | Q1: 201308 | R1: 201309 | S1: 201310 | T1: 201311 | U1: 201312 | V1: 201401 | W1: 201402 | X1: 201403 | Y1: 201404 | Z1: 201405 | AA1: 201406 | AB1: 201407 | AC1: 201408 | AD1: 201409 | AE1: 201410 | AF1: 201411 | AG1: 201412 | AH1: 201501 | AI1: 201502 | AJ1: 201503 | AK1: 201504 | AL1: 201505 | AM1: 201506 | AN1: 201507 | AO1: 201508 | AP1: 201509 | AQ1: 201510 | AR1: 201511 | AS1: 201512 | AT1: 201601 | AU1: 201602 | AV1: 201603 | AW1: 201604 | AX1: 201605 | AY1: 201606 | AZ1: 201607 | BA1: 201608 | BB1: 201609 | BC1: 201610 | BD1: 201611 | BE1: 201612 | BF1: 201701 | BG1: 201702 | BH1: 201703 | BI1: 201704 | BJ1: 201705 | BK1: 201706 | BL1: 201707 | BM1: 201708 | BN1: 201709 | BO1: 201710 | BP1: 201711 | BQ1: 201712 | BR1: 201801 | BS1: 201802 | BT1: 201803 | BU1: 201804 | BV1: 201805 | BW1: 201806 | BX1: 201807 | BY1: 201808 | BZ1: 201809 | CA1: 201810 | CB1: 201811 | CC1: 201812 | CD1: 201901 | CE1: 201902 | CF1: 201903 | CG1: 201904 | CH1: 201905 | CI1: 201906 | CJ1: 201907 | CK1: 201908 | CL1: 201909 | CM1: 201910 | CN1: 201911 | CO1: 201912 | CP1: 202001 | CQ1: 202002 | CR1: 202003 | CS1: 202004 | CT1: 202005 | CU1: 202006 | CV1: 202007 | CW1: 202008 | CX1: 202009 | CY1: 202010 | CZ1: 202011 | DA1: 202012 | DB1: 202101 | DC1: 202102 | DD1: 202103 | DE1: 202104 | DF1: 202105 | DG1: 202106 | DH1: 202107 | DI1: 202108 | DJ1: 202109 | DK1: 202110 | DL1: 202111 | DM1: 202112 | DN1: 202201 | DO1: 202202 | DP1: 202203 | DQ1: 202204 | DR1: 202205 | DS1: 202206 | DT1: 202207 | DU1: 202208 | DV1: 202209 | DW1: 202210 | DX1: 202211 | DY1: 202212 | DZ1: 202301 | EA1: 202302 | EB1: 202303 | EC1: 202304 | ED1: 202305 | EE1: 202306 | EF1: 202307 | EG1: 202308 | EH1: 202309 | EI1: 202310 | EJ1: 202311 | EK1: 202312 | EL1: 202401 | EM1: 202402 | EN1: 202403 | EO1: 202404 | EP1: 202405 | EQ1: 202406 | ER1: 202407 | ES1: 202408 | ET1: 202409 | EU1: 202410 | EV1: 202411 | EW1: 202412 | EX1: 202501 | EY1: 202502 | EZ1: 202503 | FA1: 202504 | FB1: 202505 | FC1: 202506 | FD1: 202507 | FE1: 202508 | FF1: 202509 | FG1: 202510 | FH1: 202511 | FI1: 202512 | FJ1: 202601 | FK1: 202602 | FL1: 202603 | FM1: 202604 | FN1: 202605 | FO1: 202606 | FP1: 202607 | FQ1: 202608 | FR1: 202609 | FS1: 202610 | FT1: 202611 | FU1: 202612 | FV1: 202701 | FW1: 202702 | FX1: 202703 | FY1: 202704 | FZ1: 202705 | GA1: 202706 | GB1: 202707 | GC1: 202708 | GD1: 202709 | GE1: 202710 | GF1: 202711 | GG1: 202712 | GH1: 202801 | GI1: 202802 | GJ1: 202803 | GK1: 202804 | GL1: 202805 | GM1: 202806 | GN1: 202807 | GO1: 202808 | GP1: 202809 | GQ1: 202810 | GR1: 202811 | GS1: 202812 | GT1: 202901 | GU1: 202902 | GV1: 202903 | GW1: 202904 | GX1: 202905 | GY1: 202906 | GZ1: 202907 | HA1: 202908 | HB1: 202909 | HC1: 202910 | HD1: 202911 | HE1: 202912 | HF1: 203001 | HG1: 203002 | HH1: 203003 | HM1: 201206 | HN1: 201207 | HO1: 201208 | HP1: 201209 | HQ1: 201212 | HR1: 201303 | HS1: 201306 | HT1: 201309 | HU1: 201312 | HV1: 201403 | HW1: 201406 | HX1: 201409 | HY1: 201412 | HZ1: 201503 | IA1: 201506 | IB1: 201509 | IC1: 201512 | ID1: 201603 | IE1: 201606 | IF1: 201609 | IG1: 201612 | IH1: 201703 | II1: 201706 | IJ1: 201709 | IK1: 201712 | IL1: 201803 | IM1: 201806 | IN1: 201809 | IO1: 201812 | IP1: 201903 | IQ1: 201906 | IR1: 201909 | IS1: 201912 | IT1: 202003 | IU1: 202006 | IV1: 202009 | IW1: 202012 | IX1: 202103 | IY1: 202106 | IZ1: 202109 | JA1: 202112 | JB1: 202203 | JC1: 202206 | JD1: 202209 | JE1: 202212 | JF1: 202303 | JG1: 202306 | JH1: 202309 | JI1: 202312 | JJ1: 202403 | JK1: 202406 | JL1: 202409 | JM1: 202412 | JN1: 202503 | JO1: 202506 | JP1: 202509 | JQ1: 202512 | JR1: 202603 | JS1: 202606 | JT1: 202609 | JU1: 202612 | JV1: 202703 | JW1: 202706 | JX1: 202709 | JY1: 202712 | JZ1: 202803 | KA1: 202806 | KB1: 202809 | KC1: 202812 | KD1: 202903 | KE1: 202906 | KF1: 202909 | KG1: 202912 | KH1: 203003
FF2: 45901 | FG2: =+EOMONTH(FF2,1) -> 45961 | FH2: =+EOMONTH(FG2,1) -> 45991 | FI2: =+EOMONTH(FH2,1) -> 46022 | FJ2: =+EOMONTH(FI2,1) -> 46053 | FK2: =+EOMONTH(FJ2,1) -> 46081 | FL2: =+EOMONTH(FK2,1) -> 46112 | FM2: =+EOMONTH(FL2,1) -> 46142 | FN2: =+EOMONTH(FM2,1) -> 46173 | ... HH2: =+EOMONTH(HG2,1) -> 47573
A4: Field Description | B4: Field Name
A5: MonthEnd | B5: NMONTH_MONTHEND | C5: {=_xll.EQNXTDZ($A$1,$B5,C$1)} -> 201206 | D5: {=_xll.EQNXTDZ($A$1,$B5,D$1)} -> 201207 | E5: {=_xll.EQNXTDZ($A$1,$B5,E$1)} -> 201208 | F5: {=_xll.EQNXTDZ($A$1,$B5,F$1)} -> 201209 | G5: {=_xll.EQNXTDZ($A$1,$B5,G$1)} -> 201210 | H5: {=_xll.EQNXTDZ($A$1,$B5,H$1)} -> 201211 | I5: {=_xll.EQNXTDZ($A$1,$B5,I$1)} -> 201212 | J5: {=_xll.EQNXTDZ($A$1,$B5,J$1)} -> 201301 | ... HH5: {=_xll.EQNXTDZ($A$1,$B5,HH$1)} -> 0
A6: Open | B6: NMONTH_OPEN | C6: {=_xll.EQNXTDZ($A$1,$B6,C$1)} -> 44 | D6: {=_xll.EQNXTDZ($A$1,$B6,D$1)} -> 47.1 | E6: {=_xll.EQNXTDZ($A$1,$B6,E$1)} -> 47 | F6: {=_xll.EQNXTDZ($A$1,$B6,F$1)} -> 54.1 | G6: {=_xll.EQNXTDZ($A$1,$B6,G$1)} -> 55.3 | H6: {=_xll.EQNXTDZ($A$1,$B6,H$1)} -> 60.8 | I6: {=_xll.EQNXTDZ($A$1,$B6,I$1)} -> 57 | J6: {=_xll.EQNXTDZ($A$1,$B6,J$1)} -> 50.6 | ... HH6: {=_xll.EQNXTDZ($A$1,$B6,HH$1)} -> 0
A7: High | B7: NMONTH_HIGH | C7: {=_xll.EQNXTDZ($A$1,$B7,C$1)} -> 49.7 | D7: {=_xll.EQNXTDZ($A$1,$B7,D$1)} -> 49.7 | E7: {=_xll.EQNXTDZ($A$1,$B7,E$1)} -> 62.3 | F7: {=_xll.EQNXTDZ($A$1,$B7,F$1)} -> 59 | G7: {=_xll.EQNXTDZ($A$1,$B7,G$1)} -> 60.9 | H7: {=_xll.EQNXTDZ($A$1,$B7,H$1)} -> 67 | I7: {=_xll.EQNXTDZ($A$1,$B7,I$1)} -> 61.5 | J7: {=_xll.EQNXTDZ($A$1,$B7,J$1)} -> 57.85 | ... HH7: {=_xll.EQNXTDZ($A$1,$B7,HH$1)} -> 0 | HP7: =+MAX(D7:F7) -> 62.3 | HQ7: =+MAX(G7:I7) -> 67 | HR7: =+MAX(J7:L7) -> 57.85 | HS7: =+MAX(M7:O7) -> 49.4 | HT7: =+MAX(P7:R7) -> 42.2 | HU7: =+MAX(S7:U7) -> 43.05 | HV7: =+MAX(V7:X7) -> 46 | HW7: =+MAX(Y7:AA7) -> 58.15 | HX7: =+MAX(AB7:AD7) -> 88.6 | HY7: =+MAX(AE7:AG7) -> 93.85 | HZ7: =+MAX(AH7:AJ7) -> 107.95 | IA7: =+MAX(AK7:AM7) -> 152.1 | IB7: =+MAX(AN7:AP7) -> 277 | IC7: =+MAX(AQ7:AS7) -> 324.9 | ID7: =+MAX(AT7:AV7) -> 319.95 | IE7: =+MAX(AW7:AY7) -> 294 | IF7: =+MAX(AZ7:BB7) -> 282 | IG7: =+MAX(BC7:BE7) -> 325.8 | IH7: =+MAX(BF7:BH7) -> 304.9 | II7: =+MAX(BI7:BK7) -> 325.8 | IJ7: =+MAX(BL7:BN7) -> 296.5 | IK7: =+MAX(BO7:BQ7) -> 224 | IL7: =+MAX(BR7:BT7) -> 210.7 | IM7: =+MAX(BU7:BW7) -> 142 | IN7: =+MAX(BX7:BZ7) -> 100 | IO7: =+MAX(CA7:CC7) -> 88.25 | IP7: =+MAX(CD7:CF7) -> 84.6 | IQ7: =+MAX(CG7:CI7) -> 70 | IR7: =+MAX(CJ7:CL7) -> 54.95 | IS7: =+MAX(CM7:CO7) -> 70.5 | IT7: =+MAX(CP7:CR7) -> 67.6 | IU7: =+MAX(CS7:CU7) -> 55.85 | IV7: =+MAX(CV7:CX7) -> 65.2 | IW7: =+MAX(CY7:DA7) -> 83.95 | IX7: =+MAX(DB7:DD7) -> 104 | IY7: =+MAX(DE7:DG7) -> 116 | IZ7: =+MAX(DH7:DJ7) -> 173.55 | JA7: =+MAX(DK7:DM7) -> 355 | JB7: =+MAX(DN7:DP7) -> 419.8 | JC7: =+MAX(DQ7:DS7) -> 423 | JD7: =+MAX(DT7:DV7) -> 358.4 | JE7: =+MAX(DW7:DY7) -> 299.2 | JF7: =+MAX(DZ7:EB7) -> 249.7 | JG7: =+MAX(EC7:EE7) -> 344.4 | JH7: =+MAX(EF7:EH7) -> 393 | JI7: =+MAX(EI7:EK7) -> 455.2 | JJ7: =+MAX(EL7:EN7) -> 629.95 | JK7: =MAX(EO7:EQ7) -> 487.6 | JL7: =MAX(ER7:ET7) -> 498.4 | JM7: =MAX(EU7:EW7) -> 471.85 | JN7: =MAX(EX7:EZ7) -> 453.3 | JO7: =MAX(FA7:FC7) -> 513 | JP7: =MAX(FD7:FF7) -> 484.1 | JQ7: =MAX(FG7:FI7) -> 502.7 | JR7: =MAX(FJ7:FL7) -> 524 | JS7: =MAX(FM7:FO7) -> 576.95 | JT7: =MAX(FP7:FR7) -> 0 | JU7: =MAX(FS7:FU7) -> 0 | JV7: =MAX(FV7:FX7) -> 0 | JW7: =MAX(FY7:GA7) -> 0 | JX7: =MAX(GB7:GD7) -> 0 | JY7: =MAX(GE7:GG7) -> 0 | JZ7: =MAX(GH7:GJ7) -> 0 | KA7: =MAX(GK7:GM7) -> 0 | KB7: =MAX(GN7:GP7) -> 0 | KC7: =MAX(GQ7:GS7) -> 0 | KD7: =MAX(GT7:GV7) -> 0 | KE7: =MAX(GW7:GY7) -> 0 | KF7: =MAX(GZ7:HB7) -> 0 | KG7: =MAX(HC7:HE7) -> 0 | KH7: =MAX(HF7:HH7) -> 0
A8: Low | B8: NMONTH_LOW | C8: {=_xll.EQNXTDZ($A$1,$B8,C$1)} -> 42 | D8: {=_xll.EQNXTDZ($A$1,$B8,D$1)} -> 44.1 | E8: {=_xll.EQNXTDZ($A$1,$B8,E$1)} -> 44.4 | F8: {=_xll.EQNXTDZ($A$1,$B8,F$1)} -> 54.1 | G8: {=_xll.EQNXTDZ($A$1,$B8,G$1)} -> 53 | H8: {=_xll.EQNXTDZ($A$1,$B8,H$1)} -> 53.85 | I8: {=_xll.EQNXTDZ($A$1,$B8,I$1)} -> 40.4 | J8: {=_xll.EQNXTDZ($A$1,$B8,J$1)} -> 46.75 | ... HH8: {=_xll.EQNXTDZ($A$1,$B8,HH$1)} -> 0 | HP8: =+MIN(D8:F8) -> 44.1 | HQ8: =+MIN(G8:I8) -> 40.4 | HR8: =+MIN(J8:L8) -> 33 | HS8: =+MIN(M8:O8) -> 33.5 | HT8: =+MIN(P8:R8) -> 26.8 | HU8: =+MIN(S8:U8) -> 28.7 | HV8: =+MIN(V8:X8) -> 30.95 | HW8: =+MIN(Y8:AA8) -> 34.15 | HX8: =+MIN(AB8:AD8) -> 52.8 | HY8: =+MIN(AE8:AG8) -> 69 | HZ8: =+MIN(AH8:AJ8) -> 68.05 | IA8: =+MIN(AK8:AM8) -> 72 | IB8: =+MIN(AN8:AP8) -> 146.5 | IC8: =+MIN(AQ8:AS8) -> 238.85 | ID8: =+MIN(AT8:AV8) -> 235.1 | IE8: =+MIN(AW8:AY8) -> 246.6 | IF8: =+MIN(AZ8:BB8) -> 242.6 | IG8: =+MIN(BC8:BE8) -> 222.55 | IH8: =+MIN(BF8:BH8) -> 241.1 | II8: =+MIN(BI8:BK8) -> 250 | IJ8: =+MIN(BL8:BN8) -> 188.6 | IK8: =+MIN(BO8:BQ8) -> 182 | IL8: =+MIN(BR8:BT8) -> 120.1 | IM8: =+MIN(BU8:BW8) -> 76.95 | IN8: =+MIN(BX8:BZ8) -> 59.15 | IO8: =+MIN(CA8:CC8) -> 53.4 | IP8: =+MIN(CD8:CF8) -> 53.4 | IQ8: =+MIN(CG8:CI8) -> 50 | IR8: =+MIN(CJ8:CL8) -> 32.4 | IS8: =+MIN(CM8:CO8) -> 35.2 | IT8: =+MIN(CP8:CR8) -> 32.35 | IU8: =+MIN(CS8:CU8) -> 35 | IV8: =+MIN(CV8:CX8) -> 43.3 | IW8: =+MIN(CY8:DA8) -> 46.1 | IX8: =+MIN(DB8:DD8) -> 71.1 | IY8: =+MIN(DE8:DG8) -> 74.5 | IZ8: =+MIN(DH8:DJ8) -> 103.8 | JA8: =+MIN(DK8:DM8) -> 167.8 | JB8: =+MIN(DN8:DP8) -> 254.3 | JC8: =+MIN(DQ8:DS8) -> 237 | JD8: =+MIN(DT8:DV8) -> 252.45 | JE8: =+MIN(DW8:DY8) -> 225.55 | JF8: =+MIN(DZ8:EB8) -> 194.65 | JG8: =+MIN(EC8:EE8) -> 217.9 | JH8: =+MIN(EF8:EH8) -> 290.35 | JI8: =+MIN(EI8:EK8) -> 273.75 | JJ8: =+MIN(EL8:EN8) -> 353.9 | JK8: =MIN(EO8:EQ8) -> 317.6 | JL8: =MIN(ER8:ET8) -> 375 | JM8: =MIN(EU8:EW8) -> 348.15 | JN8: =MIN(EX8:EZ8) -> 293.15 | JO8: =MIN(FA8:FC8) -> 351.6 | JP8: =MIN(FD8:FF8) -> 341.55 | JQ8: =MIN(FG8:FI8) -> 391.2 | JR8: =MIN(FJ8:FL8) -> 410.1 | JS8: =MIN(FM8:FO8) -> 413 | JT8: =MIN(FP8:FR8) -> 0 | JU8: =MIN(FS8:FU8) -> 0 | JV8: =MIN(FV8:FX8) -> 0 | JW8: =MIN(FY8:GA8) -> 0 | JX8: =MIN(GB8:GD8) -> 0 | JY8: =MIN(GE8:GG8) -> 0 | JZ8: =MIN(GH8:GJ8) -> 0 | KA8: =MIN(GK8:GM8) -> 0 | KB8: =MIN(GN8:GP8) -> 0 | KC8: =MIN(GQ8:GS8) -> 0 | KD8: =MIN(GT8:GV8) -> 0 | KE8: =MIN(GW8:GY8) -> 0 | KF8: =MIN(GZ8:HB8) -> 0 | KG8: =MIN(HC8:HE8) -> 0 | KH8: =MIN(HF8:HH8) -> 0
A9: Close | B9: NMONTH_CLOSE | C9: {=_xll.EQNXTDZ($A$1,$B9,C$1)} -> 48.4 | D9: {=_xll.EQNXTDZ($A$1,$B9,D$1)} -> 47 | E9: {=_xll.EQNXTDZ($A$1,$B9,E$1)} -> 55.7 | F9: {=_xll.EQNXTDZ($A$1,$B9,F$1)} -> 56.05 | G9: {=_xll.EQNXTDZ($A$1,$B9,G$1)} -> 59.85 | H9: {=_xll.EQNXTDZ($A$1,$B9,H$1)} -> 58.1 | I9: {=_xll.EQNXTDZ($A$1,$B9,I$1)} -> 51.4 | J9: {=_xll.EQNXTDZ($A$1,$B9,J$1)} -> 53.55 | ... HH9: {=_xll.EQNXTDZ($A$1,$B9,HH$1)} -> 0 | HP9: =+F9 -> 56.05 | HQ9: =+I9 -> 51.4 | HR9: =+L9 -> 33.55 | HS9: =+O9 -> 41.2 | HT9: =+R9 -> 29.5 | HU9: =+U9 -> 36.2 | HV9: =+X9 -> 35.15 | HW9: =+AA9 -> 54.45 | HX9: =+AD9 -> 83.75 | HY9: =+AG9 -> 77.95 | HZ9: =+AJ9 -> 78.2 | IA9: =+AM9 -> 150 | IB9: =+AP9 -> 261.95 | IC9: =+AS9 -> 306.5 | ID9: =+AV9 -> 250.6 | IE9: =+AY9 -> 275.85 | IF9: =+BB9 -> 252.65 | IG9: =+BE9 -> 246.6 | IH9: =+BH9 -> 277.7 | II9: =+BK9 -> 262.5 | IJ9: =+BN9 -> 193.1 | IK9: =+BQ9 -> 190.35 | IL9: =+BT9 -> 120.85 | IM9: =+BW9 -> 82.05 | IN9: =+BZ9 -> 60.6 | IO9: =+CC9 -> 71.45 | IP9: =+CF9 -> 65.6 | IQ9: =+CI9 -> 52 | IR9: =+CL9 -> 38.5 | IS9: =+CO9 -> 61.35 | IT9: =+CR9 -> 36.5 | IU9: =+CU9 -> 48.45 | IV9: =+CX9 -> 47.75 | IW9: =+DA9 -> 76.85 | IX9: =+DD9 -> 74.5 | IY9: =+DG9 -> 105.5 | IZ9: =+DJ9 -> 166.4 | JA9: =+DM9 -> 347.85 | JB9: =+DP9 -> 258.95 | JC9: =+DS9 -> 271.85 | JD9: =+DV9 -> 278.9 | JE9: =+DY9 -> 243.55 | JF9: =+EB9 -> 215.05 | JG9: =+EE9 -> 300.85 | JH9: =+EH9 -> 341.7 | JI9: =+EK9 -> 424.85 | JJ9: =+EN9 -> 442.9 | JK9: =EQ9 -> 409.1 | JL9: =ET9 -> 465.7 | JM9: =EW9 -> 414.75 | JN9: =EZ9 -> 435.15 | JO9: =FC9 -> 487.15 | JP9: =FF9 -> 435.9 | JQ9: =FI9 -> 497.95 | JR9: =FL9 -> 414.7 | JS9: =FO9 -> 526.25 | JT9: =FR9 -> 0 | JU9: =FU9 -> 0 | JV9: =FX9 -> 0 | JW9: =GA9 -> 0 | JX9: =GD9 -> 0 | JY9: =GG9 -> 0 | JZ9: =GJ9 -> 0 | KA9: =GM9 -> 0 | KB9: =GP9 -> 0 | KC9: =GS9 -> 0 | KD9: =GV9 -> 0 | KE9: =GY9 -> 0 | KF9: =HB9 -> 0 | KG9: =HE9 -> 0 | KH9: =HH9 -> 0
A11: Field Description | B11: Field Name | C11: {=_xll.EQNXTDZ($A$1,$B11,C$1)} -> 0 | D11: {=_xll.EQNXTDZ($A$1,$B11,D$1)} -> 0 | E11: {=_xll.EQNXTDZ($A$1,$B11,E$1)} -> 0 | F11: {=_xll.EQNXTDZ($A$1,$B11,F$1)} -> 0 | G11: {=_xll.EQNXTDZ($A$1,$B11,G$1)} -> 0 | H11: {=_xll.EQNXTDZ($A$1,$B11,H$1)} -> 0 | I11: {=_xll.EQNXTDZ($A$1,$B11,I$1)} -> 0 | J11: {=_xll.EQNXTDZ($A$1,$B11,J$1)} -> 0 | ... HH11: {=_xll.EQNXTDZ($A$1,$B11,HH$1)} -> 0
A12: Month End | B12: BMONTH_MONTHEND | C12: {=_xll.EQNXTDZ($A$1,$B12,C$1)} -> 201206 | D12: {=_xll.EQNXTDZ($A$1,$B12,D$1)} -> 201207 | E12: {=_xll.EQNXTDZ($A$1,$B12,E$1)} -> 201208 | F12: {=_xll.EQNXTDZ($A$1,$B12,F$1)} -> 201209 | G12: {=_xll.EQNXTDZ($A$1,$B12,G$1)} -> 201210 | H12: {=_xll.EQNXTDZ($A$1,$B12,H$1)} -> 201211 | I12: {=_xll.EQNXTDZ($A$1,$B12,I$1)} -> 201212 | J12: {=_xll.EQNXTDZ($A$1,$B12,J$1)} -> 201301 | ... HH12: {=_xll.EQNXTDZ($A$1,$B12,HH$1)} -> 0
A13: Open | B13: BMONTH_OPEN | C13: {=_xll.EQNXTDZ($A$1,$B13,C$1)} -> 45.15 | D13: {=_xll.EQNXTDZ($A$1,$B13,D$1)} -> 47.7 | E13: {=_xll.EQNXTDZ($A$1,$B13,E$1)} -> 46.65 | F13: {=_xll.EQNXTDZ($A$1,$B13,F$1)} -> 56.5 | G13: {=_xll.EQNXTDZ($A$1,$B13,G$1)} -> 56.85 | H13: {=_xll.EQNXTDZ($A$1,$B13,H$1)} -> 62 | I13: {=_xll.EQNXTDZ($A$1,$B13,I$1)} -> 58 | J13: {=_xll.EQNXTDZ($A$1,$B13,J$1)} -> 50.6 | ... HH13: {=_xll.EQNXTDZ($A$1,$B13,HH$1)} -> 0
A14: High | B14: BMONTH_HIGH | C14: {=_xll.EQNXTDZ($A$1,$B14,C$1)} -> 49.5 | D14: {=_xll.EQNXTDZ($A$1,$B14,D$1)} -> 49 | E14: {=_xll.EQNXTDZ($A$1,$B14,E$1)} -> 62.3 | F14: {=_xll.EQNXTDZ($A$1,$B14,F$1)} -> 58.85 | G14: {=_xll.EQNXTDZ($A$1,$B14,G$1)} -> 61.3 | H14: {=_xll.EQNXTDZ($A$1,$B14,H$1)} -> 66.9 | I14: {=_xll.EQNXTDZ($A$1,$B14,I$1)} -> 61.5 | J14: {=_xll.EQNXTDZ($A$1,$B14,J$1)} -> 57.95 | ... HH14: {=_xll.EQNXTDZ($A$1,$B14,HH$1)} -> 0 | HP14: =+MAX(D14:F14) -> 62.3 | HQ14: =+MAX(G14:I14) -> 66.9 | HR14: =+MAX(J14:L14) -> 57.95 | HS14: =+MAX(M14:O14) -> 52.5 | HT14: =+MAX(P14:R14) -> 41.6 | HU14: =+MAX(S14:U14) -> 38.9 | HV14: =+MAX(V14:X14) -> 45.9 | HW14: =+MAX(Y14:AA14) -> 59 | HX14: =+MAX(AB14:AD14) -> 88.7 | HY14: =+MAX(AE14:AG14) -> 94.05 | HZ14: =+MAX(AH14:AJ14) -> 107.5 | IA14: =+MAX(AK14:AM14) -> 152.4 | IB14: =+MAX(AN14:AP14) -> 278 | IC14: =+MAX(AQ14:AS14) -> 324 | ID14: =+MAX(AT14:AV14) -> 320 | IE14: =+MAX(AW14:AY14) -> 305 | IF14: =+MAX(AZ14:BB14) -> 282 | IG14: =+MAX(BC14:BE14) -> 325 | IH14: =+MAX(BF14:BH14) -> 304.5 | II14: =+MAX(BI14:BK14) -> 324 | IJ14: =+MAX(BL14:BN14) -> 295 | IK14: =+MAX(BO14:BQ14) -> 223.6 | IL14: =+MAX(BR14:BT14) -> 210 | IM14: =+MAX(BU14:BW14) -> 141.85 | IN14: =+MAX(BX14:BZ14) -> 99.8 | IO14: =+MAX(CA14:CC14) -> 87.5 | IP14: =+MAX(CD14:CF14) -> 82.9 | IQ14: =+MAX(CG14:CI14) -> 69.55 | IR14: =+MAX(CJ14:CL14) -> 56.5 | IS14: =+MAX(CM14:CO14) -> 70.5 | IT14: =+MAX(CP14:CR14) -> 65.45 | IU14: =+MAX(CS14:CU14) -> 55 | IV14: =+MAX(CV14:CX14) -> 66.2 | IW14: =+MAX(CY14:DA14) -> 83.9 | IX14: =+MAX(DB14:DD14) -> 103.75 | IY14: =+MAX(DE14:DG14) -> 114.6 | IZ14: =+MAX(DH14:DJ14) -> 173.8 | JA14: =+MAX(DK14:DM14) -> 354 | JB14: =+MAX(DN14:DP14) -> 423.4 | JC14: =+MAX(DQ14:DS14) -> 422 | JD14: =+MAX(DT14:DV14) -> 359.95 | JE14: =+MAX(DW14:DY14) -> 298.8 | JF14: =+MAX(DZ14:EB14) -> 254 | JG14: =+MAX(EC14:EE14) -> 344 | JH14: =+MAX(EF14:EH14) -> 393.3 | JI14: =+MAX(EI14:EK14) -> 454.9 | JJ14: =+MAX(EL14:EN14) -> 627.2 | JK14: =MAX(EO14:EQ14) -> 485 | JL14: =MAX(ER14:ET14) -> 498.2 | JM14: =MAX(EU14:EW14) -> 469.05 | JN14: =MAX(EX14:EZ14) -> 453 | JO14: =MAX(FA14:FC14) -> 512.45 | JP14: =MAX(FD14:FF14) -> 487 | JQ14: =MAX(FG14:FI14) -> 501 | JR14: =MAX(FJ14:FL14) -> 524.1 | JS14: =MAX(FM14:FO14) -> 575.5 | JT14: =MAX(FP14:FR14) -> 0 | JU14: =MAX(FS14:FU14) -> 0 | JV14: =MAX(FV14:FX14) -> 0 | JW14: =MAX(FY14:GA14) -> 0 | JX14: =MAX(GB14:GD14) -> 0 | JY14: =MAX(GE14:GG14) -> 0 | JZ14: =MAX(GH14:GJ14) -> 0 | KA14: =MAX(GK14:GM14) -> 0 | KB14: =MAX(GN14:GP14) -> 0 | KC14: =MAX(GQ14:GS14) -> 0 | KD14: =MAX(GT14:GV14) -> 0 | KE14: =MAX(GW14:GY14) -> 0 | KF14: =MAX(GZ14:HB14) -> 0 | KG14: =MAX(HC14:HE14) -> 0 | KH14: =MAX(HF14:HH14) -> 0
A15: Low | B15: BMONTH_LOW | C15: {=_xll.EQNXTDZ($A$1,$B15,C$1)} -> 42.5 | D15: {=_xll.EQNXTDZ($A$1,$B15,D$1)} -> 42.2 | E15: {=_xll.EQNXTDZ($A$1,$B15,E$1)} -> 44.95 | F15: {=_xll.EQNXTDZ($A$1,$B15,F$1)} -> 55 | G15: {=_xll.EQNXTDZ($A$1,$B15,G$1)} -> 54.05 | H15: {=_xll.EQNXTDZ($A$1,$B15,H$1)} -> 55 | I15: {=_xll.EQNXTDZ($A$1,$B15,I$1)} -> 49.15 | J15: {=_xll.EQNXTDZ($A$1,$B15,J$1)} -> 50 | ... HH15: {=_xll.EQNXTDZ($A$1,$B15,HH$1)} -> 0 | HP15: =+MIN(D15:F15) -> 42.2 | HQ15: =+MIN(G15:I15) -> 49.15 | HR15: =+MIN(J15:L15) -> 33 | HS15: =+MIN(M15:O15) -> 34 | HT15: =+MIN(P15:R15) -> 26 | HU15: =+MIN(S15:U15) -> 28.05 | HV15: =+MIN(V15:X15) -> 31.3 | HW15: =+MIN(Y15:AA15) -> 33.65 | HX15: =+MIN(AB15:AD15) -> 53.1 | HY15: =+MIN(AE15:AG15) -> 69.65 | HZ15: =+MIN(AH15:AJ15) -> 68 | IA15: =+MIN(AK15:AM15) -> 71.5 | IB15: =+MIN(AN15:AP15) -> 150 | IC15: =+MIN(AQ15:AS15) -> 239.3 | ID15: =+MIN(AT15:AV15) -> 238.5 | IE15: =+MIN(AW15:AY15) -> 246.3 | IF15: =+MIN(AZ15:BB15) -> 244.05 | IG15: =+MIN(BC15:BE15) -> 225 | IH15: =+MIN(BF15:BH15) -> 236 | II15: =+MIN(BI15:BK15) -> 250 | IJ15: =+MIN(BL15:BN15) -> 189.45 | IK15: =+MIN(BO15:BQ15) -> 177 | IL15: =+MIN(BR15:BT15) -> 118.2 | IM15: =+MIN(BU15:BW15) -> 77.8 | IN15: =+MIN(BX15:BZ15) -> 60.2 | IO15: =+MIN(CA15:CC15) -> 54 | IP15: =+MIN(CD15:CF15) -> 53.7 | IQ15: =+MIN(CG15:CI15) -> 50.05 | IR15: =+MIN(CJ15:CL15) -> 32.15 | IS15: =+MIN(CM15:CO15) -> 35.8 | IT15: =+MIN(CP15:CR15) -> 33.6 | IU15: =+MIN(CS15:CU15) -> 34.55 | IV15: =+MIN(CV15:CX15) -> 45 | IW15: =+MIN(CY15:DA15) -> 45.95 | IX15: =+MIN(DB15:DD15) -> 70.35 | IY15: =+MIN(DE15:DG15) -> 73.55 | IZ15: =+MIN(DH15:DJ15) -> 101.6 | JA15: =+MIN(DK15:DM15) -> 166.75 | JB15: =+MIN(DN15:DP15) -> 257.25 | JC15: =+MIN(DQ15:DS15) -> 237 | JD15: =+MIN(DT15:DV15) -> 252.1 | JE15: =+MIN(DW15:DY15) -> 215 | JF15: =+MIN(DZ15:EB15) -> 185 | JG15: =+MIN(EC15:EE15) -> 218 | JH15: =+MIN(EF15:EH15) -> 290.25 | JI15: =+MIN(EI15:EK15) -> 274.45 | JJ15: =+MIN(EL15:EN15) -> 360 | JK15: =MIN(EO15:EQ15) -> 319.85 | JL15: =MIN(ER15:ET15) -> 360.9 | JM15: =MIN(EU15:EW15) -> 350 | JN15: =MIN(EX15:EZ15) -> 295.25 | JO15: =MIN(FA15:FC15) -> 367.8 | JP15: =MIN(FD15:FF15) -> 340.9 | JQ15: =MIN(FG15:FI15) -> 391.5 | JR15: =MIN(FJ15:FL15) -> 411.35 | JS15: =MIN(FM15:FO15) -> 415.7 | JT15: =MIN(FP15:FR15) -> 0 | JU15: =MIN(FS15:FU15) -> 0 | JV15: =MIN(FV15:FX15) -> 0 | JW15: =MIN(FY15:GA15) -> 0 | JX15: =MIN(GB15:GD15) -> 0 | JY15: =MIN(GE15:GG15) -> 0 | JZ15: =MIN(GH15:GJ15) -> 0 | KA15: =MIN(GK15:GM15) -> 0 | KB15: =MIN(GN15:GP15) -> 0 | KC15: =MIN(GQ15:GS15) -> 0 | KD15: =MIN(GT15:GV15) -> 0 | KE15: =MIN(GW15:GY15) -> 0 | KF15: =MIN(GZ15:HB15) -> 0 | KG15: =MIN(HC15:HE15) -> 0 | KH15: =MIN(HF15:HH15) -> 0
A16: Close | B16: BMONTH_CLOSE | C16: {=_xll.EQNXTDZ($A$1,$B16,C$1)} -> 47.85 | D16: {=_xll.EQNXTDZ($A$1,$B16,D$1)} -> 46.1 | E16: {=_xll.EQNXTDZ($A$1,$B16,E$1)} -> 55.4 | F16: {=_xll.EQNXTDZ($A$1,$B16,F$1)} -> 55.75 | G16: {=_xll.EQNXTDZ($A$1,$B16,G$1)} -> 59.85 | H16: {=_xll.EQNXTDZ($A$1,$B16,H$1)} -> 58.2 | I16: {=_xll.EQNXTDZ($A$1,$B16,I$1)} -> 51 | J16: {=_xll.EQNXTDZ($A$1,$B16,J$1)} -> 53.4 | ... HH16: {=_xll.EQNXTDZ($A$1,$B16,HH$1)} -> 0 | HP16: =+F16 -> 55.75 | HQ16: =+I16 -> 51 | HR16: =+L16 -> 34 | HS16: =+O16 -> 41.25 | HT16: =+R16 -> 28.05 | HU16: =+U16 -> 35.85 | HV16: =+X16 -> 35.1 | HW16: =+AA16 -> 54.8 | HX16: =+AD16 -> 82.8 | HY16: =+AG16 -> 77.3 | HZ16: =+AJ16 -> 78.15 | IA16: =+AM16 -> 149.6 | IB16: =+AP16 -> 263.2 | IC16: =+AS16 -> 306 | ID16: =+AV16 -> 249.1 | IE16: =+AY16 -> 274.15 | IF16: =+BB16 -> 252.05 | IG16: =+BE16 -> 246.5 | IH16: =+BH16 -> 276.05 | II16: =+BK16 -> 262.15 | IJ16: =+BN16 -> 197.2 | IK16: =+BQ16 -> 190.2 | IL16: =+BT16 -> 119.5 | IM16: =+BW16 -> 81.65 | IN16: =+BZ16 -> 60.3 | IO16: =+CC16 -> 68.25 | IP16: =+CF16 -> 65.55 | IQ16: =+CI16 -> 52.05 | IR16: =+CL16 -> 38.45 | IS16: =+CO16 -> 61 | IT16: =+CR16 -> 35.3 | IU16: =+CU16 -> 48.8 | IV16: =+CX16 -> 46.9 | IW16: =+DA16 -> 76.85 | IX16: =+DD16 -> 73.55 | IY16: =+DG16 -> 105.25 | IZ16: =+DJ16 -> 166.8 | JA16: =+DM16 -> 348.15 | JB16: =+DP16 -> 258.45 | JC16: =+DS16 -> 272.2 | JD16: =+DV16 -> 278.9 | JE16: =+DY16 -> 243.65 | JF16: =+EB16 -> 215.4 | JG16: =+EE16 -> 300.45 | JH16: =+EH16 -> 342.3 | JI16: =+EK16 -> 426.45 | JJ16: =+EN16 -> 438.55 | JK16: =EQ16 -> 408.8 | JL16: =ET16 -> 466.6 | JM16: =EW16 -> 414.95 | JN16: =EZ16 -> 436.5 | JO16: =FC16 -> 488.15 | JP16: =FF16 -> 434.15 | JQ16: =FI16 -> 495.35 | JR16: =FL16 -> 415.8 | JS16: =FO16 -> 527.25 | JT16: =FR16 -> 0 | JU16: =FU16 -> 0 | JV16: =FX16 -> 0 | JW16: =GA16 -> 0 | JX16: =GD16 -> 0 | JY16: =GG16 -> 0 | JZ16: =GJ16 -> 0 | KA16: =GM16 -> 0 | KB16: =GP16 -> 0 | KC16: =GS16 -> 0 | KD16: =GV16 -> 0 | KE16: =GY16 -> 0 | KF16: =HB16 -> 0 | KG16: =HE16 -> 0 | KH16: =HH16 -> 0
A19: High | HP19: =+IF(HP14=0,HP7,HP14) -> 62.3 | HQ19: =+IF(HQ14=0,HQ7,HQ14) -> 66.9 | HR19: =+IF(HR14=0,HR7,HR14) -> 57.95 | HS19: =+IF(HS14=0,HS7,HS14) -> 52.5 | HT19: =+IF(HT14=0,HT7,HT14) -> 41.6 | HU19: =+IF(HU14=0,HU7,HU14) -> 38.9 | HV19: =+IF(HV14=0,HV7,HV14) -> 45.9 | HW19: =+IF(HW14=0,HW7,HW14) -> 59 | ... KH19: =+IF(KH14=0,KH7,KH14) -> 0
A20: Low | HP20: =+IF(HP15=0,HP8,HP15) -> 42.2 | HQ20: =+IF(HQ15=0,HQ8,HQ15) -> 49.15 | HR20: =+IF(HR15=0,HR8,HR15) -> 33 | HS20: =+IF(HS15=0,HS8,HS15) -> 34 | HT20: =+IF(HT15=0,HT8,HT15) -> 26 | HU20: =+IF(HU15=0,HU8,HU15) -> 28.05 | HV20: =+IF(HV15=0,HV8,HV15) -> 31.3 | HW20: =+IF(HW15=0,HW8,HW15) -> 33.65 | ... KH20: =+IF(KH15=0,KH8,KH15) -> 0
A21: Close | HP21: =+IF(HP16=0,HP9,HP16) -> 55.75 | HQ21: =+IF(HQ16=0,HQ9,HQ16) -> 51 | HR21: =+IF(HR16=0,HR9,HR16) -> 34 | HS21: =+IF(HS16=0,HS9,HS16) -> 41.25 | HT21: =+IF(HT16=0,HT9,HT16) -> 28.05 | HU21: =+IF(HU16=0,HU9,HU16) -> 35.85 | HV21: =+IF(HV16=0,HV9,HV16) -> 35.1 | HW21: =+IF(HW16=0,HW9,HW16) -> 54.8 | ... KH21: =+IF(KH16=0,KH9,KH16) -> 0

Sheet QTR No. of Shares
A1: ='QTR Raw'!A1 -> 114234 | C1: 201206 | D1: 201209 | E1: 201212 | F1: 201303 | G1: 201306 | H1: 201309 | I1: 201312 | J1: 201403 | K1: 201406 | L1: 201409 | M1: 201412 | N1: 201503 | O1: 201506 | P1: 201509 | Q1: 201512 | R1: 201603 | S1: 201606 | T1: 201609 | U1: 201612 | V1: 201703 | W1: 201706 | X1: 201709 | Y1: 201712 | Z1: 201803 | AA1: 201806 | AB1: 201809 | AC1: 201812 | AD1: 201903 | AE1: 201906 | AF1: 201909 | AG1: 201912 | AH1: 202003 | AI1: 202006 | AJ1: 202009 | AK1: 202012 | AL1: 202103 | AM1: 202106 | AN1: 202109 | AO1: 202112 | AP1: 202203 | AQ1: 202206 | AR1: 202209 | AS1: 202212 | AT1: 202303 | AU1: 202306 | AV1: 202309 | AW1: 202312 | AX1: 202403 | AY1: 202406
A4: Field Description | B4: Field Name
A5: Date End | B5: SHP_DATE_END | C5: {=_xll.EQNXTDZ($A$1,$B5,C$1)} -> 201206 | D5: {=_xll.EQNXTDZ($A$1,$B5,D$1)} -> 201209 | E5: {=_xll.EQNXTDZ($A$1,$B5,E$1)} -> 201212 | F5: {=_xll.EQNXTDZ($A$1,$B5,F$1)} -> 201303 | G5: {=_xll.EQNXTDZ($A$1,$B5,G$1)} -> 201306 | H5: {=_xll.EQNXTDZ($A$1,$B5,H$1)} -> 201309 | I5: {=_xll.EQNXTDZ($A$1,$B5,I$1)} -> 201312 | J5: {=_xll.EQNXTDZ($A$1,$B5,J$1)} -> 201403 | ... AY5: {=_xll.EQNXTDZ($A$1,$B5,AY$1)} -> 202406
A6: Grand Total | B6: SHP_NSGRANDTOTAL | C6: {=_xll.EQNXTDZ($A$1,$B6,C$1)} -> 39421559 | D6: {=_xll.EQNXTDZ($A$1,$B6,D$1)} -> 39421559 | E6: {=_xll.EQNXTDZ($A$1,$B6,E$1)} -> 39421559 | F6: {=_xll.EQNXTDZ($A$1,$B6,F$1)} -> 39421559 | G6: {=_xll.EQNXTDZ($A$1,$B6,G$1)} -> 39421559 | H6: {=_xll.EQNXTDZ($A$1,$B6,H$1)} -> 39421559 | I6: {=_xll.EQNXTDZ($A$1,$B6,I$1)} -> 39421559 | J6: {=_xll.EQNXTDZ($A$1,$B6,J$1)} -> 39421559 | ... AY6: {=_xll.EQNXTDZ($A$1,$B6,AY$1)} -> 50246559
B7: In Crs. | C7: =+C6/10^7 -> 3.9421559 | D7: =+D6/10^7 -> 3.9421559 | E7: =+E6/10^7 -> 3.9421559 | F7: =+F6/10^7 -> 3.9421559 | G7: =+G6/10^7 -> 3.9421559 | H7: =+H6/10^7 -> 3.9421559 | I7: =+I6/10^7 -> 3.9421559 | J7: =+J6/10^7 -> 3.9421559 | ... AY7: =+AY6/10^7 -> 5.0246559

Sheet Share price Daily
A1: =_xll.EQNXTH(B1,"[ADJC];[ADJH];[ADJL];[ADJO];[UCLS];[VOLUME]","2015-Jan-01","Y","All traded days","Asc") -> EQNXTH | B1: =+'Annual Raw'!A1 -> 114234 | L1: =_xll.EQNXTH(B1,"[NADJC];[NADJH];[NADJLOW];[NADJOPEN];[NUCLOSE];[NVOLUME]","2015-Jan-01","Y","All traded days","Asc") -> EQNXTH
A2: Sangam (India) Ltd. | L2: Sangam (India) Ltd.
A3: DATE | B3: ADJHIGH | C3: ADJCLOSE | D3: ADJLOW | E3: ADJOPEN | F3: CLOSE | G3: VOLUME | L3: DATE | M3: ADJCLOSE | N3: ADJHIGH | O3: ADJLOW | P3: ADJOPEN | Q3: CLOSE | R3: VOLUME
A4: 42005 | B4: 79.6 | C4: 78.1 | D4: 77.5 | E4: 78.5 | F4: 78.1 | G4: 1649 | L4: 42005 | M4: 78.05 | N4: 79 | O4: 77.1 | P4: 78 | Q4: 78.05 | R4: 4424
A5: 42006 | B5: 81.5 | C5: 80.5 | D5: 78 | E5: 79.3 | F5: 80.5 | G5: 4470 | L5: 42006 | M5: 80.9 | N5: 81.55 | O5: 77.1 | P5: 78 | Q5: 80.9 | R5: 10261
A6: 42009 | B6: 81 | C6: 79.1 | D6: 78.8 | E6: 80 | F6: 79.1 | G6: 615 | L6: 42009 | M6: 79.4 | N6: 80.9 | O6: 78 | P6: 78 | Q6: 79.4 | R6: 3664
A7: 42010 | B7: 77.5 | C7: 76.25 | D7: 75.8 | E7: 77.05 | F7: 76.25 | G7: 11723 | L7: 42010 | M7: 76.1 | N7: 78.7 | O7: 75.35 | P7: 78.7 | Q7: 76.1 | R7: 4980
A8: 42011 | B8: 77.7 | C8: 74.45 | D8: 74 | E8: 77.7 | F8: 74.45 | G8: 1450 | L8: 42011 | M8: 74.45 | N8: 77.95 | O8: 73.95 | P8: 77.95 | Q8: 74.45 | R8: 5013
A9: 42012 | B9: 80 | C9: 78.65 | D9: 76 | E9: 76 | F9: 78.65 | G9: 2890 | L9: 42012 | M9: 78.5 | N9: 80 | O9: 73.8 | P9: 73.8 | Q9: 78.5 | R9: 10798
A10: 42013 | B10: 80.35 | C10: 77.7 | D10: 77.3 | E10: 79 | F10: 77.7 | G10: 1181 | L10: 42013 | M10: 77.3 | N10: 80.7 | O10: 77.1 | P10: 78 | Q10: 77.3 | R10: 5956
A11: 42016 | B11: 76.7 | C11: 76.05 | D11: 75.2 | E11: 76.6 | F11: 76.05 | G11: 4192 | L11: 42016 | M11: 76.15 | N11: 78.3 | O11: 75.15 | P11: 78.3 | Q11: 76.15 | R11: 6384
A12: 42017 | B12: 77.4 | C12: 76.45 | D12: 76 | E12: 77 | F12: 76.45 | G12: 1102 | L12: 42017 | M12: 77.05 | N12: 80 | O12: 76 | P12: 76.1 | Q12: 77.05 | R12: 2659
A13: 42018 | B13: 77.2 | C13: 74.8 | D13: 74 | E13: 77.2 | F13: 74.8 | G13: 3150 | L13: 42018 | M13: 74.2 | N13: 78.2 | O13: 73.05 | P13: 76.5 | Q13: 74.2 | R13: 4433
A14: 42019 | B14: 76 | C14: 74.7 | D14: 74.05 | E14: 74.65 | F14: 74.7 | G14: 1701 | L14: 42019 | M14: 74.4 | N14: 76.4 | O14: 74 | P14: 74.6 | Q14: 74.4 | R14: 9523
A15: 42020 | B15: 74.9 | C15: 72.05 | D15: 70 | E15: 74.9 | F15: 72.05 | G15: 21358 | L15: 42020 | M15: 70.85 | N15: 75.8 | O15: 68.7 | P15: 74.05 | Q15: 70.85 | R15: 32551
... A2818: 46190 | B2818: 530.65 | C2818: 524.05 | D2818: 520.65 | E2818: 526.75 | F2818: 524.05 | G2818: 641 | L2818: 46156 | M2818: 505.55 | N2818: 518.55 | O2818: 502.05 | P2818: 518.55 | Q2818: 505.55 | R2818: 14094
L2819: 46157 | M2819: 496.3 | N2819: 509.75 | O2819: 495 | P2819: 504.15 | Q2819: 496.3 | R2819: 18788
L2820: 46160 | M2820: 485.4 | N2820: 505 | O2820: 477 | P2820: 488.05 | Q2820: 485.4 | R2820: 26221
L2821: 46161 | M2821: 486.1 | N2821: 497.9 | O2821: 483.2 | P2821: 485 | Q2821: 486.1 | R2821: 17178
L2822: 46162 | M2822: 483.45 | N2822: 487.4 | O2822: 469.8 | P2822: 482.95 | Q2822: 483.45 | R2822: 20672
L2823: 46163 | M2823: 484.8 | N2823: 494.5 | O2823: 481.5 | P2823: 484 | Q2823: 484.8 | R2823: 21207
L2824: 46164 | M2824: 495.75 | N2824: 498.55 | O2824: 481.25 | P2824: 481.25 | Q2824: 495.75 | R2824: 21364
L2825: 46167 | M2825: 513.85 | N2825: 518.8 | O2825: 495.7 | P2825: 495.7 | Q2825: 513.85 | R2825: 57290
L2826: 46168 | M2826: 519.95 | N2826: 531.85 | O2826: 510 | P2826: 510 | Q2826: 519.95 | R2826: 29776
L2827: 46169 | M2827: 515.9 | N2827: 520 | O2827: 510.4 | P2827: 520 | Q2827: 515.9 | R2827: 12136
L2828: 46171 | M2828: 515.95 | N2828: 525 | O2828: 511.85 | P2828: 516 | Q2828: 515.95 | R2828: 31310
L2829: 46174 | M2829: 525.75 | N2829: 553 | O2829: 516 | P2829: 516 | Q2829: 525.75 | R2829: 195831
L2830: 46175 | M2830: 527.2 | N2830: 531.2 | O2830: 518.95 | P2830: 525 | Q2830: 527.2 | R2830: 32615
... L2841: 46190 | M2841: 524.65 | N2841: 529.3 | O2841: 521.55 | P2841: 527 | Q2841: 524.65 | R2841: 12405

Sheet Sheet2
J19: 219.3 | K19: 186.25 | L19: 186.75
J20: 192.9 | K20: 135.5 | L20: 146.9 | N20: 219.3 | O20: 192.9 | P20: 186 | Q20: 178.7 | R20: 207 | S20: 255.15 | T20: 348.25 | U20: 374 | V20: 495.9 | W20: 659.9 | X20: 613.4 | Y20: 607.9 | Z20: 555.95 | AA20: 497.8 | AB20: 459.9 | AC20: 374 | AD20: 362 | AE20: 341.5 | AF20: 384.2 | AG20: 433.8 | AH20: 460 | AI20: 474.4 | AJ20: 414.4 | AK20: 318.7 | AL20: 303.25 | AM20: 332.7 | AN20: 295 | AO20: 247 | AP20: 214.4 | AQ20: 179.5 | AR20: 97.9 | AS20: 119.1 | AT20: 130.65 | AU20: 148.55 | AV20: 153.8 | AW20: 152.9 | AX20: 136 | AY20: 141.15 | AZ20: 128.1 | BA20: 142.5 | BB20: 143.55 | BC20: 124.5 | BD20: 241 | BE20: 450 | BF20: 503.35
J21: 186 | K21: 145.4 | L21: 169.1 | N21: 186.25 | O21: 135.5 | P21: 145.4 | Q21: 108.95 | R21: 137 | S21: 170 | T21: 243.15 | U21: 307.5 | V21: 325.1 | W21: 463 | X21: 467.05 | Y21: 436.5 | Z21: 467 | AA21: 348.2 | AB21: 325 | AC21: 313.1 | AD21: 285 | AE21: 277.85 | AF21: 327 | AG21: 317 | AH21: 370.7 | AI21: 360 | AJ21: 271.15 | AK21: 233.15 | AL21: 218.8 | AM21: 262 | AN21: 223.6 | AO21: 137.6 | AP21: 142 | AQ21: 59.3 | AR21: 58 | AS21: 72.8 | AT21: 80 | AU21: 107.25 | AV21: 106 | AW21: 125.1 | AX21: 112.25 | AY21: 81.45 | AZ21: 88 | BA21: 90.35 | BB21: 106.05 | BC21: 98.55 | BD21: 119.25 | BE21: 210 | BF21: 349
J22: 178.7 | K22: 108.95 | L22: 139.75 | N22: 186.75 | O22: 146.9 | P22: 169.1 | Q22: 139.75 | R22: 202.15 | S22: 249.05 | T22: 346.4 | U22: 349.2 | V22: 469.9 | W22: 584.8 | X22: 536.15 | Y22: 513.35 | Z22: 474 | AA22: 438.55 | AB22: 355.4 | AC22: 334.95 | AD22: 298.8 | AE22: 328.35 | AF22: 343 | AG22: 389.9 | AH22: 443.05 | AI22: 407.5 | AJ22: 290.1 | AK22: 235.75 | AL22: 292.65 | AM22: 276.1 | AN22: 237.05 | AO22: 190.1 | AP22: 147.2 | AQ22: 71.9 | AR22: 75.2 | AS22: 90.1 | AT22: 117.2 | AU22: 116.3 | AV22: 140.5 | AW22: 128.6 | AX22: 133.65 | AY22: 91.65 | AZ22: 97.65 | BA22: 125 | BB22: 115.35 | BC22: 119.25 | BD22: 219.3 | BE22: 442.65 | BF22: 503.35
J23: 207 | K23: 137 | L23: 202.15
J24: 255.15 | K24: 170 | L24: 249.05
J25: 348.25 | K25: 243.15 | L25: 346.4
J26: 374 | K26: 307.5 | L26: 349.2
J27: 495.9 | K27: 325.1 | L27: 469.9
J28: 659.9 | K28: 463 | L28: 584.8
J29: 613.4 | K29: 467.05 | L29: 536.15
J30: 607.9 | K30: 436.5 | L30: 513.35
J31: 555.95 | K31: 467 | L31: 474
J32: 497.8 | K32: 348.2 | L32: 438.55
J33: 459.9 | K33: 325 | L33: 355.4
J34: 374 | K34: 313.1 | L34: 334.95
... J63: 503.35 | K63: 349 | L63: 503.35
