Workbook

Sheet Template
A1: =+'Annual Raw'!C4 -> Schaeffler India Ltd. | B1: 36951 | C1: =EOMONTH(B1,12) -> 37346 | D1: 37591 | E1: =EOMONTH(D1,12) -> 37986 | F1: =EOMONTH(E1,12) -> 38352 | G1: =EOMONTH(F1,12) -> 38717 | H1: =EOMONTH(G1,12) -> 39082 | I1: =EOMONTH(H1,12) -> 39447 | J1: =EOMONTH(I1,12) -> 39813 | K1: =EOMONTH(J1,12) -> 40178 | L1: =EOMONTH(K1,12) -> 40543 | ... AE1: =EOMONTH(AD1,12) -> 47483 | AH1: QTR | AI1: 41061 | AJ1: 41153 | AK1: 41244 | AL1: 41334 | AM1: 41426 | AN1: 41518 | AO1: 41609 | AP1: 41699 | AQ1: 41791 | AR1: 41883 | AS1: 41974 | AT1: 42064 | AU1: 42156 | AV1: 42248 | AW1: 42339 | AX1: 42430 | AY1: 42522 | AZ1: 42614 | BA1: 42705 | BB1: 42795 | BC1: 42887 | BD1: 42979 | BE1: 43070 | BF1: 43160 | BG1: 43252 | BH1: 43344 | BI1: 43435 | BJ1: 43525 | BK1: 43617 | BL1: 43709 | BM1: 43800 | BN1: 43891 | BO1: 43983 | BP1: 44075 | BQ1: =EOMONTH(BP1,3) -> 44196 | BR1: =EOMONTH(BQ1,3) -> 44286 | BS1: =EOMONTH(BR1,3) -> 44377 | BT1: =EOMONTH(BS1,3) -> 44469 | BU1: =EOMONTH(BT1,3) -> 44561 | BV1: =EOMONTH(BU1,3) -> 44651 | BW1: =EOMONTH(BV1,3) -> 44742 | BX1: =EOMONTH(BW1,3) -> 44834 | ... DA1: =EOMONTH(CZ1,3) -> 47483 | DD1: HISTORICAL ESTIMATES | DE1: 46022
A2: Presentation Data (Start)
A4: Revenue From Operations
A5: Revenue- Automotive Technologies | W5: =SUM(BR5:BU5) -> 2186.05 | X5: =SUM(BV5:BY5) -> 2706.5 | Y5: =SUM(BZ5:CC5) -> 3025.18 | Z5: =SUM(CD5:CG5) -> 2733.32 | AA5: =SUM(CH5:CK5) -> 3137.27 | AB5: =SUM(CL5:CO5) -> 3945.4039 | AC5: =SUM(CP5:CS5) -> 4916.0353 | AD5: =SUM(CT5:CW5) -> 5950.2807 | AE5: =SUM(CX5:DA5) -> 7190.0936 | BQ5: =BQ$21*47% -> 598.6719 | BR5: 574.3 | BS5: 484.52 | BT5: 560 | BU5: 567.23 | BV5: 609.42 | BW5: 679.49 | BX5: 717.05 | BY5: 700.54 | BZ5: 737.71 | CA5: 749.15 | CB5: 772.66 | CC5: 765.66 | CD5: 652.41 | CE5: 683.72 | CF5: 688.9 | CG5: 708.29 | CH5: 694.17 | CI5: 705.43 | CJ5: 817.71 | CK5: 919.96 | CL5: 907.84 | CM5: =CI5*(1+CM13) -> 850.99283 | CN5: =CJ5*(1+CN13) -> 1022.1331 | CO5: =CK5*(1+CO13) -> 1164.4379 | CP5: =CL5*(1+CP13) -> 1136.9102 | CQ5: =CM5*(1+CQ13) -> 1054.1515 | CR5: =CN5*(1+CR13) -> 1274.2583 | CS5: =CO5*(1+CS13) -> 1450.7152 | CT5: =CP5*(1+CT13) -> 1388.5126 | ... DA5: =CW5*(1+DA13) -> 2101.5303 | DE5: 795.10012
A6: Revenue- Vehicle Lifetime Solutions | W6: =SUM(BR6:BU6) -> 501.87 | X6: =SUM(BV6:BY6) -> 593.58 | Y6: =SUM(BZ6:CC6) -> 708.8 | Z6: =SUM(CD6:CG6) -> 857.76 | AA6: =SUM(CH6:CK6) -> 1430.32 | AB6: =SUM(CL6:CO6) -> 1601.948 | AC6: =SUM(CP6:CS6) -> 1762.1428 | AD6: =SUM(CT6:CW6) -> 1938.3571 | AE6: =SUM(CX6:DA6) -> 2132.1928 | BQ6: 0 | BR6: 107.92 | BS6: 96.68 | BT6: 145.08 | BU6: 152.19 | BV6: 124.67 | BW6: 149.25 | BX6: 150.59 | BY6: 169.07 | BZ6: 146.42 | CA6: 184.8 | CB6: 173.06 | CC6: 204.52 | CD6: 184.5 | CE6: 218.61 | CF6: 222.9 | CG6: 231.75 | CH6: 319.14 | CI6: 374.03 | CJ6: 353.32 | CK6: 383.83 | CL6: 379.65 | CM6: =CI6*(1+CM14) -> 411.433 | CN6: =CJ6*(1+CN14) -> 388.652 | CO6: =CK6*(1+CO14) -> 422.213 | CP6: =CL6*(1+CP14) -> 417.615 | CQ6: =CM6*(1+CQ14) -> 452.5763 | CR6: =CN6*(1+CR14) -> 427.5172 | CS6: =CO6*(1+CS14) -> 464.4343 | CT6: =CP6*(1+CT14) -> 459.3765 | ... DA6: =CW6*(1+DA14) -> 561.9655 | DE6: 351.054
A7: Revenue- Bearings & Industrial Solutions | W7: =SUM(BR7:BU7) -> 2156.62 | X7: =SUM(BV7:BY7) -> 2424.66 | Y7: =SUM(BZ7:CC7) -> 2538.9 | Z7: =SUM(CD7:CG7) -> 3561.71 | AA7: =SUM(CH7:CK7) -> 3686.53 | AB7: =SUM(CL7:CO7) -> 3828.4995 | AC7: =SUM(CP7:CS7) -> 3974.6314 | AD7: =SUM(CT7:CW7) -> 4127.634 | AE7: =SUM(CX7:DA7) -> 4286.9035 | BQ7: =BQ$21*43% -> 547.7211 | BR7: 481.18 | BS7: 479.02 | BT7: 606.76 | BU7: 589.66 | BV7: 585.67 | BW7: 640.62 | BX7: 605.86 | BY7: 592.51 | BZ7: 535.86 | CA7: 625.58 | CB7: 684.53 | CC7: 692.93 | CD7: 783.28 | CE7: 898.79 | CF7: 943.32 | CG7: 936.32 | CH7: 849.36 | CI7: 897.82 | CJ7: 905.35 | CK7: 1034 | CL7: 884.85 | CM7: =CI7*(1+CM15) -> 921.33773 | CN7: =CJ7*(1+CN15) -> 935.23798 | CO7: =CK7*(1+CO15) -> 1087.0738 | CP7: =CL7*(1+CP15) -> 917.87117 | CQ7: =CM7*(1+CQ15) -> 954.71246 | CR7: =CN7*(1+CR15) -> 971.41444 | CS7: =CO7*(1+CS15) -> 1130.6333 | CT7: =CP7*(1+CT15) -> 952.81787 | ... DA7: =CW7*(1+DA15) -> 1219.8611 | DE7: 880.64953
A8: Revenue- Intercompany Exports & Others | W8: =SUM(BR8:BU8) -> 715.97 | X8: =SUM(BV8:BY8) -> 1142.68 | Y8: =SUM(BZ8:CC8) -> 977.83 | Z8: =SUM(CD8:CG8) -> 1079.59 | AA8: =SUM(CH8:CK8) -> 1431.73 | AB8: =SUM(CL8:CO8) -> 1898.1652 | AC8: =SUM(CP8:CS8) -> 2516.5576 | AD8: =SUM(CT8:CW8) -> 2818.5445 | AE8: =SUM(CX8:DA8) -> 3156.7698 | BQ8: =BQ$21*10% -> 127.377 | BR8: 153.42 | BS8: 172.67 | BT8: 175.74 | BU8: 214.14 | BV8: 247.75 | BW8: 279.47 | BX8: 282.93 | BY8: 332.53 | BZ8: 273.63 | CA8: 269.61 | CB8: 223.15 | CC8: 211.44 | CD8: 252.94 | CE8: 305.72 | CF8: 261.23 | CG8: 259.7 | CH8: 311.74 | CI8: 375.31 | CJ8: 358.27 | CK8: 386.41 | CL8: 413.3 | CM8: =CI8*(1+CM16) -> 497.58011 | CN8: =CJ8*(1+CN16) -> 474.98874 | CO8: =CK8*(1+CO16) -> 512.29631 | CP8: =CL8*(1+CP16) -> 547.94665 | CQ8: =CM8*(1+CQ16) -> 659.6839 | CR8: =CN8*(1+CR16) -> 629.73262 | CS8: =CO8*(1+CS16) -> 679.19441 | CT8: =CP8*(1+CT16) -> 613.70025 | ... DA8: =CW8*(1+DA16) -> 851.98147 | DE8: 358.501
A9: Total Revenue | W9: =SUM(W5:W8) -> 5560.51 | X9: =SUM(X5:X8) -> 6867.42 | Y9: =SUM(Y5:Y8) -> 7250.71 | Z9: =SUM(Z5:Z8) -> 8232.38 | AA9: =SUM(AA5:AA8) -> 9685.85 | AB9: =SUM(AB5:AB8) -> 11274.017 | AC9: =SUM(AC5:AC8) -> 13169.367 | AD9: =SUM(AD5:AD8) -> 14834.816 | AE9: =SUM(AE5:AE8) -> 16765.96 | BN9: =SUM(BN5:BN8) -> 0 | BO9: =SUM(BO5:BO8) -> 0 | BP9: =SUM(BP5:BP8) -> 0 | BQ9: =SUM(BQ5:BQ8) -> 1273.77 | BR9: =SUM(BR5:BR8) -> 1316.82 | BS9: =SUM(BS5:BS8) -> 1232.89 | BT9: =SUM(BT5:BT8) -> 1487.58 | BU9: =SUM(BU5:BU8) -> 1523.22 | ... DA9: =SUM(DA5:DA8) -> 4735.3384 | DE9: 2385.3047
A10: Revenue- Checksum | W10: =W23-W9 -> 0 | X10: =X23-X9 -> 0 | Y10: =Y23-Y9 -> 0.2 | Z10: =Z23-Z9 -> 0 | AA10: =AA23-AA9 -> 0 | AB10: =AB23-AB9 -> 0 | AC10: =AC23-AC9 -> 0 | AD10: =AD23-AD9 -> 0 | AE10: =AE23-AE9 -> 0 | BN10: =BN21-BN9 -> 928.54 | BO10: =BO21-BO9 -> 438.88 | BP10: =BP21-BP9 -> 1120.65 | BQ10: =BQ21-BQ9 -> 0 | BR10: =BR21-BR9 -> 0 | BS10: =BS21-BS9 -> 0 | BT10: =BT21-BT9 -> 0 | BU10: =BU21-BU9 -> 0 | ... CL10: =CL21-CL9 -> 0
A12: Revenue Growth %
A13: Automotive Technologies- Growth% | X13: =X5/W5-1 -> 0.23807781 | Y13: =Y5/X5-1 -> 0.11774617 | Z13: =Z5/Y5-1 -> -0.096476904 | AA13: =AA5/Z5-1 -> 0.14778731 | AB13: =AB5/AA5-1 -> 0.25759143 | AC13: =AC5/AB5-1 -> 0.24601572 | AD13: =AD5/AC5-1 -> 0.21038203 | AE13: =AE5/AD5-1 -> 0.20836208 | BU13: =BU5/BQ5-1 -> -0.052519418 | BV13: =BV5/BR5-1 -> 0.061152708 | BW13: =BW5/BS5-1 -> 0.40239825 | BX13: =BX5/BT5-1 -> 0.28044643 | BY13: =BY5/BU5-1 -> 0.2350193 | BZ13: =BZ5/BV5-1 -> 0.21051163 | CA13: =CA5/BW5-1 -> 0.10251807 | CB13: =CB5/BX5-1 -> 0.077553867 | ... CL13: =CL5/CH5-1 -> 0.30780645 | CM13: =AVERAGE(CI13:CL13) -> 0.20634624 | CN13: =AVERAGE(CJ13:CM13) -> 0.24999461 | CO13: =AVERAGE(CK13:CN13) -> 0.26574845 | CP13: =AVERAGE(CL13:CO13)*0.98 -> 0.25232446 | CQ13: =AVERAGE(CM13:CP13)*0.98 -> 0.23873137 | CR13: =AVERAGE(CN13:CQ13)*0.98 -> 0.24666573 | CS13: =AVERAGE(CO13:CR13)*0.98 -> 0.24585015 | CT13: =AVERAGE(CP13:CS13)*0.9 -> 0.22130364 | CU13: =AVERAGE(CQ13:CT13)*0.9 -> 0.21432395 | CV13: =AVERAGE(CR13:CU13)*0.9 -> 0.20883228 | CW13: =AVERAGE(CS13:CV13)*0.9 -> 0.20031976 | CX13: =AVERAGE(CT13:CW13) -> 0.21119491 | CY13: =AVERAGE(CU13:CX13) -> 0.20866772 | CZ13: =AVERAGE(CV13:CY13) -> 0.20725367 | DA13: =AVERAGE(CW13:CZ13) -> 0.20685901 | DE13: 0.14539684
A14: Vehicle Lifetime Solutions- Growth% | X14: =X6/W6-1 -> 0.18273657 | Y14: =Y6/X6-1 -> 0.19411031 | Z14: =Z6/Y6-1 -> 0.21015801 | AA14: =AA6/Z6-1 -> 0.66750606 | AB14: =AB6/AA6-1 -> 0.11999273 | AC14: =AC6/AB6-1 -> 0.1 | AD14: =AD6/AC6-1 -> 0.1 | AE14: =AE6/AD6-1 -> 0.1 | BU14: =BU6/BQ6-1 -> #DIV/0! | BV14: =BV6/BR6-1 -> 0.15520756 | BW14: =BW6/BS6-1 -> 0.54375259 | BX14: =BX6/BT6-1 -> 0.037979046 | BY14: =BY6/BU6-1 -> 0.11091399 | BZ14: =BZ6/BV6-1 -> 0.17446058 | CA14: =CA6/BW6-1 -> 0.23819095 | CB14: =CB6/BX6-1 -> 0.1492131 | ... CL14: =CL6/CH6-1 -> 0.18960331 | CM14: 0.1 | CN14: 0.1 | CO14: 0.1 | CP14: 0.1 | CQ14: 0.1 | CR14: 0.1 | CS14: 0.1 | CT14: 0.1 | CU14: 0.1 | CV14: 0.1 | CW14: 0.1 | CX14: 0.1 | CY14: 0.1 | CZ14: 0.1 | DA14: 0.1 | DE14: 0.1
A15: Bearings & Industrial Solutions- Growth% | X15: =X7/W7-1 -> 0.12428708 | Y15: =Y7/X7-1 -> 0.047115884 | Z15: =Z7/Y7-1 -> 0.40285557 | AA15: =AA7/Z7-1 -> 0.035044964 | AB15: =AB7/AA7-1 -> 0.038510343 | AC15: =AC7/AB7-1 -> 0.038169491 | AD15: =AD7/AC7-1 -> 0.03849478 | AE15: =AE7/AD7-1 -> 0.038586145 | BU15: =BU7/BQ7-1 -> 0.076569809 | BV15: =BV7/BR7-1 -> 0.21715366 | BW15: =BW7/BS7-1 -> 0.33735543 | BX15: =BX7/BT7-1 -> -0.0014832883 | BY15: =BY7/BU7-1 -> 0.0048332938 | BZ15: =BZ7/BV7-1 -> -0.085047894 | CA15: =CA7/BW7-1 -> -0.023477256 | CB15: =CB7/BX7-1 -> 0.12984848 | ... CL15: =CL7/CH7-1 -> 0.041784402 | CM15: =AVERAGE(CI15:CL15) -> 0.026194257 | CN15: =AVERAGE(CJ15:CM15) -> 0.033012629 | CO15: =AVERAGE(CK15:CN15) -> 0.051328649 | CP15: =AVERAGE(CL15:CO15)*0.98 -> 0.037318385 | CQ15: =AVERAGE(CM15:CP15)*0.98 -> 0.03622421 | CR15: =AVERAGE(CN15:CQ15)*0.98 -> 0.038681549 | CS15: =AVERAGE(CO15:CR15)*0.98 -> 0.040070434 | CT15: =AVERAGE(CP15:CS15) -> 0.038073645 | CU15: =AVERAGE(CQ15:CT15) -> 0.03826246 | CV15: =AVERAGE(CR15:CU15) -> 0.038772022 | CW15: =AVERAGE(CS15:CV15) -> 0.03879464 | CX15: =AVERAGE(CT15:CW15) -> 0.038475692 | CY15: =AVERAGE(CU15:CX15) -> 0.038576203 | CZ15: =AVERAGE(CV15:CY15) -> 0.038654639 | DA15: =AVERAGE(CW15:CZ15) -> 0.038625294 | DE15: 0.036838954
A16: Intercompany Exports & Others- Growth% | X16: =X8/W8-1 -> 0.59598866 | Y16: =Y8/X8-1 -> -0.14426611 | Z16: =Z8/Y8-1 -> 0.10406717 | AA16: =AA8/Z8-1 -> 0.32617938 | AB16: =AB8/AA8-1 -> 0.32578431 | AC16: =AC8/AB8-1 -> 0.32578431 | AD16: =AD8/AC8-1 -> 0.12 | AE16: =AE8/AD8-1 -> 0.12 | BU16: =BU8/BQ8-1 -> 0.68115123 | BV16: =BV8/BR8-1 -> 0.61484813 | BW16: =BW8/BS8-1 -> 0.61852088 | BX16: =BX8/BT8-1 -> 0.60993513 | BY16: =BY8/BU8-1 -> 0.55286261 | BZ16: =BZ8/BV8-1 -> 0.10446014 | CA16: =CA8/BW8-1 -> -0.035281068 | CB16: =CB8/BX8-1 -> -0.21128901 | ... CL16: =CL8/CH8-1 -> 0.32578431 | CM16: =+CL16 -> 0.32578431 | CN16: =+CM16 -> 0.32578431 | CO16: =+CN16 -> 0.32578431 | CP16: =+CO16 -> 0.32578431 | CQ16: =+CP16 -> 0.32578431 | CR16: =+CQ16 -> 0.32578431 | CS16: =+CR16 -> 0.32578431 | CT16: 0.12 | CU16: =+CT16 -> 0.12 | CV16: =+CU16 -> 0.12 | CW16: =+CV16 -> 0.12 | CX16: =+CW16 -> 0.12 | CY16: =+CX16 -> 0.12 | CZ16: =+CY16 -> 0.12 | DA16: =+CZ16 -> 0.12 | DE16: 0.15
A19: Presentation Data (End)
A20: Profit & Loss- Annual (Start)
A21: Gross Revenue | B21: ='Annual Raw'!C6 -> 0 | C21: ='Annual Raw'!D6 -> 0 | D21: ='Annual Raw'!E6 -> 278.59 | E21: ='Annual Raw'!F6 -> 305.78 | F21: ='Annual Raw'!G6 -> 368.75 | G21: ='Annual Raw'!H6 -> 462.65 | H21: ='Annual Raw'!I6 -> 612.25 | I21: ='Annual Raw'!J6 -> 715.97 | ... AA21: ='Annual Raw'!AB6 -> 9823.91 | AB21: =+SUM(CL21:CO21) -> 11274.017 | AC21: =+SUM(CP21:CS21) -> 13169.367 | AD21: =+SUM(CT21:CW21) -> 14834.816 | AE21: =+SUM(CX21:DA21) -> 16765.96 | AI21: ='QTR Raw'!C6+'QTR Raw'!C8 -> 380.12 | AJ21: ='QTR Raw'!D6+'QTR Raw'!D8 -> 356.17 | AK21: ='QTR Raw'!E6+'QTR Raw'!E8 -> 347.12 | AL21: ='QTR Raw'!F6+'QTR Raw'!F8 -> 332.61 | AM21: ='QTR Raw'!G6+'QTR Raw'!G8 -> 304.59 | AN21: ='QTR Raw'!H6+'QTR Raw'!H8 -> 371.37 | AO21: ='QTR Raw'!I6+'QTR Raw'!I8 -> 393.85 | AP21: ='QTR Raw'!J6+'QTR Raw'!J8 -> 400.7 | ... CJ21: ='QTR Raw'!BD6+'QTR Raw'!BD8 -> 2434.65 | CK21: 2724.2 | CL21: ='QTR Raw'!BF6+'QTR Raw'!BF8 -> 2585.64 | CM21: =CM9 -> 2681.3437 | CN21: =CN9 -> 2821.0118 | CO21: =CO9 -> 3186.0211 | CP21: =CP9 -> 3020.3431 | CQ21: =CQ9 -> 3121.1242 | CR21: =CR9 -> 3302.9226 | CS21: =CS9 -> 3724.9773 | CT21: =CT9 -> 3414.4072 | ... DA21: =DA9 -> 4735.3384 | DE21: 9685.85
A22: Less: Exise Duty | B22: ='Annual Raw'!C7+'Annual Raw'!C8+'Annual Raw'!C9 -> 0 | C22: ='Annual Raw'!D7+'Annual Raw'!D8+'Annual Raw'!D9 -> 0 | D22: ='Annual Raw'!E7+'Annual Raw'!E8+'Annual Raw'!E9 -> 34.28 | E22: ='Annual Raw'!F7+'Annual Raw'!F8+'Annual Raw'!F9 -> 38.87 | F22: ='Annual Raw'!G7+'Annual Raw'!G8+'Annual Raw'!G9 -> 45.63 | G22: ='Annual Raw'!H7+'Annual Raw'!H8+'Annual Raw'!H9 -> 54.33 | H22: ='Annual Raw'!I7+'Annual Raw'!I8+'Annual Raw'!I9 -> 70.21 | I22: ='Annual Raw'!J7+'Annual Raw'!J8+'Annual Raw'!J9 -> 74.67 | ... AA22: ='Annual Raw'!AB7+'Annual Raw'!AB8+'Annual Raw'!AB9 -> 138.06 | AB22: =+SUM(CL22:CO22) -> 0 | AC22: =+SUM(CP22:CS22) -> 0 | AD22: =+SUM(CT22:CW22) -> 0 | AE22: =+SUM(CX22:DA22) -> 0 | AI22: ='QTR Raw'!C21+'QTR Raw'!C20+'QTR Raw'!C19+'QTR Raw'!C13+'QTR Raw'!C7 -> 0 | AJ22: ='QTR Raw'!D21+'QTR Raw'!D20+'QTR Raw'!D19+'QTR Raw'!D13+'QTR Raw'!D7 -> 0 | AK22: ='QTR Raw'!E21+'QTR Raw'!E20+'QTR Raw'!E19+'QTR Raw'!E13+'QTR Raw'!E7 -> 0 | AL22: ='QTR Raw'!F21+'QTR Raw'!F20+'QTR Raw'!F19+'QTR Raw'!F13+'QTR Raw'!F7 -> 0 | AM22: ='QTR Raw'!G21+'QTR Raw'!G20+'QTR Raw'!G19+'QTR Raw'!G13+'QTR Raw'!G7 -> 0 | AN22: ='QTR Raw'!H21+'QTR Raw'!H20+'QTR Raw'!H19+'QTR Raw'!H13+'QTR Raw'!H7 -> 0 | AO22: ='QTR Raw'!I21+'QTR Raw'!I20+'QTR Raw'!I19+'QTR Raw'!I13+'QTR Raw'!I7 -> 0 | AP22: ='QTR Raw'!J21+'QTR Raw'!J20+'QTR Raw'!J19+'QTR Raw'!J13+'QTR Raw'!J7 -> 0 | ... CJ22: ='QTR Raw'!BD21+'QTR Raw'!BD20+'QTR Raw'!BD19+'QTR Raw'!BD13+'QTR Raw'!BD7 -> 0 | CL22: ='QTR Raw'!BF21+'QTR Raw'!BF20+'QTR Raw'!BF19+'QTR Raw'!BF13+'QTR Raw'!BF7 -> 0 | DE22: 0
A23: Net Revenue | B23: =+B21-B22 -> 0 | C23: =+C21-C22 -> 0 | D23: =+D21-D22 -> 244.31 | E23: =+E21-E22 -> 266.91 | F23: =+F21-F22 -> 323.12 | G23: =+G21-G22 -> 408.32 | H23: =+H21-H22 -> 542.04 | I23: =+I21-I22 -> 641.3 | ... AE23: =+AE21-AE22 -> 16765.96 | AI23: =+AI21-AI22 -> 380.12 | AJ23: =+AJ21-AJ22 -> 356.17 | AK23: =+AK21-AK22 -> 347.12 | AL23: =+AL21-AL22 -> 332.61 | AM23: =+AM21-AM22 -> 304.59 | AN23: =+AN21-AN22 -> 371.37 | AO23: =+AO21-AO22 -> 393.85 | AP23: =+AP21-AP22 -> 400.7 | ... DA23: =+DA21-DA22 -> 4735.3384 | DE23: 9685.85
A24: Net Revenue YOY% | C24: =C23/B23-1 -> #DIV/0! | D24: =D23/C23-1 -> #DIV/0! | E24: =E23/D23-1 -> 0.092505423 | F24: =F23/E23-1 -> 0.21059533 | G24: =G23/F23-1 -> 0.26367913 | H24: =H23/G23-1 -> 0.32748824 | I24: =I23/H23-1 -> 0.18312302 | J24: =J23/I23-1 -> 0.16078278 | ... AE24: =AE23/AD23-1 -> 0.13017643 | AM24: =+IF(AI23<0,1-AM23/AI23,AM23/AI23-1) -> -0.19870041 | AN24: =+IF(AJ23<0,1-AN23/AJ23,AN23/AJ23-1) -> 0.04267625 | AO24: =+IF(AK23<0,1-AO23/AK23,AO23/AK23-1) -> 0.13462203 | AP24: =+IF(AL23<0,1-AP23/AL23,AP23/AL23-1) -> 0.20471423 | AQ24: =+IF(AM23<0,1-AQ23/AM23,AQ23/AM23-1) -> 0.28622082 | AR24: =+IF(AN23<0,1-AR23/AN23,AR23/AN23-1) -> 0.10450494 | AS24: =+IF(AO23<0,1-AS23/AO23,AS23/AO23-1) -> 0.090516694 | AT24: =+IF(AP23<0,1-AT23/AP23,AT23/AP23-1) -> 0.020813576 | ... DA24: =+IF(CW23<0,1-DA23/CW23,DA23/CW23-1) -> 0.13085585 | DE24: 0.17655526
A25: Net Revenue QOQ% | AJ25: =+IF(AI23<0,1-AJ23/AI23,AJ23/AI23-1) -> -0.063006419 | AK25: =+IF(AJ23<0,1-AK23/AJ23,AK23/AJ23-1) -> -0.025409215 | AL25: =+IF(AK23<0,1-AL23/AK23,AL23/AK23-1) -> -0.041801106 | AM25: =+IF(AL23<0,1-AM23/AL23,AM23/AL23-1) -> -0.084242807 | AN25: =+IF(AM23<0,1-AN23/AM23,AN23/AM23-1) -> 0.21924554 | AO25: =+IF(AN23<0,1-AO23/AN23,AO23/AN23-1) -> 0.060532622 | AP25: =+IF(AO23<0,1-AP23/AO23,AP23/AO23-1) -> 0.017392408 | AQ25: =+IF(AP23<0,1-AQ23/AP23,AQ23/AP23-1) -> -0.022286 | ... DA25: =+IF(CZ23<0,1-DA23/CZ23,DA23/CZ23-1) -> 0.12346869
A26: Increase/Decrease in Stock | B26: ='Annual Raw'!C11 -> 0 | C26: ='Annual Raw'!D11 -> 0 | D26: ='Annual Raw'!E11 -> -3.371 | E26: ='Annual Raw'!F11 -> 4.7 | F26: ='Annual Raw'!G11 -> 0.58 | G26: ='Annual Raw'!H11 -> -4.68 | H26: ='Annual Raw'!I11 -> -17.98 | I26: ='Annual Raw'!J11 -> -6.41 | ... AA26: ='Annual Raw'!AB11 -> -94.1 | AB26: =+SUM(CL26:CO26) -> -137.41 | AC26: =+SUM(CP26:CS26) -> 0 | AD26: =+SUM(CT26:CW26) -> 0 | AE26: =+SUM(CX26:DA26) -> 0 | AI26: ='QTR Raw'!C10 -> 10.69 | AJ26: ='QTR Raw'!D10 -> -17.41 | AK26: ='QTR Raw'!E10 -> 22.81 | AL26: ='QTR Raw'!F10 -> 3.36 | AM26: ='QTR Raw'!G10 -> -28.38 | AN26: ='QTR Raw'!H10 -> -9.71 | AO26: ='QTR Raw'!I10 -> 2.53 | AP26: ='QTR Raw'!J10 -> 5.57 | ... CJ26: ='QTR Raw'!BD10 -> -112.03 | CK26: 25.4 | CL26: ='QTR Raw'!BF10 -> -137.41 | DE26: -94.1
A27: Purchase of Finished Goods | B27: 0 | C27: 0 | D27: 0 | E27: 0 | F27: 0 | G27: 0 | H27: 0 | I27: 0 | J27: 0 | K27: 0 | L27: 0 | M27: 0 | N27: 0 | O27: 0 | P27: 0 | Q27: 0 | R27: 0 | S27: 0 | T27: 0 | U27: 0 | V27: 0 | W27: 0 | X27: 0 | Y27: 0 | Z27: 0 | AA27: 0 | AB27: =+SUM(CL27:CO27) -> 574.01 | AC27: =+SUM(CP27:CS27) -> 0 | AD27: =+SUM(CT27:CW27) -> 0 | AE27: =+SUM(CX27:DA27) -> 0 | AI27: ='QTR Raw'!C12 -> 97.75 | AJ27: ='QTR Raw'!D12 -> 110.68 | AK27: ='QTR Raw'!E12 -> 103.85 | AL27: ='QTR Raw'!F12 -> 90.3 | AM27: ='QTR Raw'!G12 -> 90.04 | AN27: ='QTR Raw'!H12 -> 124.51 | AO27: ='QTR Raw'!I12 -> 120.76 | AP27: ='QTR Raw'!J12 -> 99.17 | ... CJ27: ='QTR Raw'!BD12 -> 539.41 | CK27: 534.29 | CL27: ='QTR Raw'!BF12 -> 574.01 | DE27: 1986.37
A28: Raw Material Consumed | B28: ='Annual Raw'!C12 -> 0 | C28: ='Annual Raw'!D12 -> 0 | D28: ='Annual Raw'!E12 -> 96.38 | E28: ='Annual Raw'!F12 -> 109.2 | F28: ='Annual Raw'!G12 -> 146.91 | G28: ='Annual Raw'!H12 -> 195.24 | H28: ='Annual Raw'!I12 -> 278.23 | I28: ='Annual Raw'!J12 -> 321.7 | ... AA28: ='Annual Raw'!AB12 -> 6026.64 | AB28: =+SUM(CL28:CO28) -> 6478.3757 | AC28: =+SUM(CP28:CS28) -> 8073.3197 | AD28: =+SUM(CT28:CW28) -> 9093.7579 | AE28: =+SUM(CX28:DA28) -> 10277.502 | AI28: ='QTR Raw'!C11 -> 130.26 | AJ28: ='QTR Raw'!D11 -> 126.94 | AK28: ='QTR Raw'!E11 -> 100.03 | AL28: ='QTR Raw'!F11 -> 119.5 | AM28: ='QTR Raw'!G11 -> 118.01 | AN28: ='QTR Raw'!H11 -> 125.63 | AO28: ='QTR Raw'!I11 -> 140.54 | AP28: ='QTR Raw'!J11 -> 144.93 | ... CJ28: ='QTR Raw'!BD11 -> 1063.5 | CK28: 1105.56 | CL28: ='QTR Raw'!BF11 -> 1156.3 | CM28: =+CM23-CM29 -> 1640.2414 | CN28: =+CN23-CN29 -> 1728.8708 | CO28: =+CO23-CO29 -> 1952.9635 | CP28: =+CP23-CP29 -> 1852.6888 | CQ28: =+CQ23-CQ29 -> 1912.4383 | CR28: =+CR23-CR29 -> 2024.6728 | CS28: =+CS23-CS29 -> 2283.5198 | CT28: =+CT23-CT29 -> 2093.1743 | ... DA28: =+DA23-DA29 -> 2902.7613 | DE28: 4040.27
A29: Gross Profit | B29: =B23-B26-B28-B27 -> 0 | C29: =C23-C26-C28-C27 -> 0 | D29: =D23-D26-D28-D27 -> 151.301 | E29: =E23-E26-E28-E27 -> 153.01 | F29: =F23-F26-F28-F27 -> 175.63 | G29: =G23-G26-G28-G27 -> 217.76 | H29: =H23-H26-H28-H27 -> 281.79 | I29: =I23-I26-I28-I27 -> 326.01 | ... AE29: =AE23-AE26-AE28-AE27 -> 6488.4572 | AI29: =AI23-AI26-AI28-AI27 -> 141.42 | AJ29: =AJ23-AJ26-AJ28-AJ27 -> 135.96 | AK29: =AK23-AK26-AK28-AK27 -> 120.43 | AL29: =AL23-AL26-AL28-AL27 -> 119.45 | AM29: =AM23-AM26-AM28-AM27 -> 124.92 | AN29: =AN23-AN26-AN28-AN27 -> 130.94 | AO29: =AO23-AO26-AO28-AO27 -> 130.02 | AP29: =AP23-AP26-AP28-AP27 -> 151.03 | ... CL29: =CL23-CL26-CL28-CL27 -> 992.74 | CM29: =+CM30*CM23 -> 1041.1023 | CN29: =+CN30*CN23 -> 1092.141 | CO29: =+CO30*CO23 -> 1233.0576 | CP29: =+CP30*CP23 -> 1167.6543 | CQ29: =+CQ30*CQ23 -> 1208.6859 | CR29: =+CR30*CR23 -> 1278.2497 | CS29: =+CS30*CS23 -> 1441.4574 | CT29: =+CT30*CT23 -> 1321.2329 | ... DA29: =+DA30*DA23 -> 1832.577 | DE29: 3753.31
A30: GP% | B30: =B29/B23 -> #DIV/0! | C30: =C29/C23 -> #DIV/0! | D30: =D29/D23 -> 0.61929925 | E30: =E29/E23 -> 0.5732644 | F30: =F29/F23 -> 0.54354419 | G30: =G29/G23 -> 0.53330721 | H30: =H29/H23 -> 0.51986938 | I30: =I29/I23 -> 0.50835802 | ... AE30: =AE29/AE23 -> 0.38700184 | AI30: =AI29/AI23 -> 0.37204041 | AJ30: =AJ29/AJ23 -> 0.38172783 | AK30: =AK29/AK23 -> 0.34694054 | AL30: =AL29/AL23 -> 0.35912931 | AM30: =AM29/AM23 -> 0.41012509 | AN30: =AN29/AN23 -> 0.35258637 | AO30: =AO29/AO23 -> 0.33012568 | AP30: =AP29/AP23 -> 0.3769154 | ... CL30: =CL29/CL23 -> 0.38394363 | CM30: =AVERAGE(CI30:CL30) -> 0.38827633 | CN30: =AVERAGE(CJ30:CM30) -> 0.38714513 | CO30: =AVERAGE(CK30:CN30) -> 0.38702118 | CP30: =AVERAGE(CL30:CO30) -> 0.38659656 | CQ30: =AVERAGE(CM30:CP30) -> 0.3872598 | CR30: =AVERAGE(CN30:CQ30) -> 0.38700567 | CS30: =AVERAGE(CO30:CR30) -> 0.3869708 | CT30: =AVERAGE(CP30:CS30) -> 0.38695821 | ... DA30: =AVERAGE(CW30:CZ30) -> 0.38700023 | DE30: 0.38750445
A31: GP YOY% | C31: =+IF(B29<0,1-C29/B29,C29/B29-1) -> #DIV/0! | D31: =+IF(C29<0,1-D29/C29,D29/C29-1) -> #DIV/0! | E31: =+IF(D29<0,1-E29/D29,E29/D29-1) -> 0.011295365 | F31: =+IF(E29<0,1-F29/E29,F29/E29-1) -> 0.14783347 | G31: =+IF(F29<0,1-G29/F29,G29/F29-1) -> 0.23987929 | H31: =+IF(G29<0,1-H29/G29,H29/G29-1) -> 0.29403931 | I31: =+IF(H29<0,1-I29/H29,I29/H29-1) -> 0.15692537 | J31: =+IF(I29<0,1-J29/I29,J29/I29-1) -> 0.12616177 | ... AE31: =+IF(AD29<0,1-AE29/AD29,AE29/AD29-1) -> 0.13018485 | AM31: =+IF(AI29<0,1-AM29/AI29,AM29/AI29-1) -> -0.11667374 | AN31: =+IF(AJ29<0,1-AN29/AJ29,AN29/AJ29-1) -> -0.036922624 | AO31: =+IF(AK29<0,1-AO29/AK29,AO29/AK29-1) -> 0.079631321 | AP31: =+IF(AL29<0,1-AP29/AL29,AP29/AL29-1) -> 0.2643784 | AQ31: =+IF(AM29<0,1-AQ29/AM29,AQ29/AM29-1) -> 0.23775216 | AR31: =+IF(AN29<0,1-AR29/AN29,AR29/AN29-1) -> 0.26867267 | AS31: =+IF(AO29<0,1-AS29/AO29,AS29/AO29-1) -> 0.25411475 | AT31: =+IF(AP29<0,1-AT29/AP29,AT29/AP29-1) -> 0.14679203 | ... CL31: =+IF(CH29<0,1-CL29/CH29,CL29/CH29-1) -> 0.20115186 | CM31: =+CM29/CI29-1 -> 0.12661213 | CN31: =+CN29/CJ29-1 -> 0.15721096 | CO31: =+CO29/CK29-1 -> 0.16441535 | CP31: =+CP29/CL29-1 -> 0.17619342 | CQ31: =+CQ29/CM29-1 -> 0.16096752 | CR31: =+CR29/CN29-1 -> 0.17040727 | CS31: =+CS29/CO29-1 -> 0.1690106 | CT31: =+CT29/CP29-1 -> 0.13152751 | ... DA31: =+DA29/CW29-1 -> 0.13087591 | DE31: 0.22041002
A32: GP QOQ% | AJ32: =+IF(AI29<0,1-AJ29/AI29,AJ29/AI29-1) -> -0.038608401 | AK32: =+IF(AJ29<0,1-AK29/AJ29,AK29/AJ29-1) -> -0.11422477 | AL32: =+IF(AK29<0,1-AL29/AK29,AL29/AK29-1) -> -0.0081375073 | AM32: =+IF(AL29<0,1-AM29/AL29,AM29/AL29-1) -> 0.045793219 | AN32: =+IF(AM29<0,1-AN29/AM29,AN29/AM29-1) -> 0.048190842 | AO32: =+IF(AN29<0,1-AO29/AN29,AO29/AN29-1) -> -0.0070261188 | AP32: =+IF(AO29<0,1-AP29/AO29,AP29/AO29-1) -> 0.16159052 | AQ32: =+IF(AP29<0,1-AQ29/AP29,AQ29/AP29-1) -> 0.023770112 | ... CL32: =+IF(CK29<0,1-CL29/CK29,CL29/CK29-1) -> -0.062524198 | CM32: =+CM29/CL29-1 -> 0.04871595 | CN32: =+CN29/CM29-1 -> 0.049023725 | CO32: =+CO29/CN29-1 -> 0.12902789 | CP32: =+CP29/CO29-1 -> -0.053041621 | CQ32: =+CQ29/CP29-1 -> 0.035140255 | CR32: =+CR29/CQ29-1 -> 0.05755327 | CS32: =+CS29/CR29-1 -> 0.12768059 | CT32: =+CT29/CS29-1 -> -0.083404842 | ... DA32: =+DA29/CZ29-1 -> 0.12347124
A33: Power & Fuel Cost | B33: ='Annual Raw'!C13 -> 0 | C33: ='Annual Raw'!D13 -> 0 | D33: ='Annual Raw'!E13 -> 9.8 | E33: ='Annual Raw'!F13 -> 9.72 | F33: ='Annual Raw'!G13 -> 10.4 | G33: ='Annual Raw'!H13 -> 10.95 | H33: ='Annual Raw'!I13 -> 13.32 | I33: ='Annual Raw'!J13 -> 14.94 | ... AA33: ='Annual Raw'!AB13 -> 121.56 | AB33: =+SUM(CL33:CO33) -> 0 | AC33: =+SUM(CP33:CS33) -> 0 | AD33: =+SUM(CT33:CW33) -> 0 | AE33: =+SUM(CX33:DA33) -> 0 | AI33: ='QTR Raw'!C15 -> 0 | AJ33: ='QTR Raw'!D15 -> 0 | AK33: ='QTR Raw'!E15 -> 0 | AL33: ='QTR Raw'!F15 -> 0 | AM33: ='QTR Raw'!G15 -> 0 | AN33: ='QTR Raw'!H15 -> 0 | AO33: ='QTR Raw'!I15 -> 0 | AP33: ='QTR Raw'!J15 -> 0 | ... CJ33: ='QTR Raw'!BD15 -> 0 | CL33: ='QTR Raw'!BF15 -> 0 | DE33: 0
A34: Selling and Distribution Expenses | B34: =('Annual Raw'!C18) -> 0 | C34: =('Annual Raw'!D18) -> 0 | D34: =('Annual Raw'!E18) -> 10.31 | E34: =('Annual Raw'!F18) -> 13.57 | F34: =('Annual Raw'!G18) -> 15.67 | G34: =('Annual Raw'!H18) -> 15.75 | H34: =('Annual Raw'!I18) -> 19.31 | I34: =('Annual Raw'!J18) -> 25.71 | ... AA34: =('Annual Raw'!AB18) -> 136.94 | AB34: =+SUM(CL34:CO34) -> 0 | AC34: =+SUM(CP34:CS34) -> 0 | AD34: =+SUM(CT34:CW34) -> 0 | AE34: =+SUM(CX34:DA34) -> 0 | AI34: ='QTR Raw'!C18 -> 0 | AJ34: ='QTR Raw'!D18 -> 0 | AK34: ='QTR Raw'!E18 -> 0 | AL34: ='QTR Raw'!F18 -> 0 | AM34: ='QTR Raw'!G18 -> 0 | AN34: ='QTR Raw'!H18 -> 0 | AO34: ='QTR Raw'!I18 -> 0 | AP34: ='QTR Raw'!J18 -> 0 | ... CJ34: ='QTR Raw'!BD18 -> 0 | CL34: ='QTR Raw'!BF18 -> 0 | DE34: 0
A35: Other Manufacturing Expenses | B35: ='Annual Raw'!C15+'Annual Raw'!C16 -> 0 | C35: ='Annual Raw'!D15+'Annual Raw'!D16 -> 0 | D35: ='Annual Raw'!E15+'Annual Raw'!E16 -> 34.35 | E35: ='Annual Raw'!F15+'Annual Raw'!F16 -> 36.17 | F35: ='Annual Raw'!G15+'Annual Raw'!G16 -> 47.84 | G35: ='Annual Raw'!H15+'Annual Raw'!H16 -> 55.7 | H35: ='Annual Raw'!I15+'Annual Raw'!I16 -> 65.14 | I35: ='Annual Raw'!J15+'Annual Raw'!J16 -> 68.68 | ... AA35: ='Annual Raw'!AB15+'Annual Raw'!AB16 -> 708.8 | AB35: =+SUM(CL35:CO35) -> 1637.2225 | AC35: =+SUM(CP35:CS35) -> 1984.397 | AD35: =+SUM(CT35:CW35) -> 2320.8337 | AE35: =+SUM(CX35:DA35) -> 2671.7653 | AI35: ='QTR Raw'!C14 -> 49.64 | AJ35: ='QTR Raw'!D14 -> 56.7 | AK35: ='QTR Raw'!E14 -> 48.75 | AL35: ='QTR Raw'!F14 -> 48.06 | AM35: ='QTR Raw'!G14 -> 51.53 | AN35: ='QTR Raw'!H14 -> 49.01 | AO35: ='QTR Raw'!I14 -> 54.01 | AP35: ='QTR Raw'!J14 -> 57.84 | ... CJ35: ='QTR Raw'!BD14 -> 336.76 | CK35: 403.44 | CL35: ='QTR Raw'!BF14 -> 367.12 | CM35: =CM39-CM36 -> 387.81698 | CN35: =CN39-CN36 -> 413.42334 | CO35: =CO39-CO36 -> 468.86223 | CP35: =CP39-CP36 -> 455.97374 | CQ35: =CQ39-CQ36 -> 463.92756 | CR35: =CR39-CR36 -> 500.77415 | CS35: =CS39-CS36 -> 563.72158 | CT35: =CT39-CT36 -> 534.29658 | ... DA35: =DA39-DA36 -> 757.07616 | DE35: 1381.65
A36: Employee Cost | B36: ='Annual Raw'!C14 -> 0 | C36: ='Annual Raw'!D14 -> 0 | D36: ='Annual Raw'!E14 -> 27.84 | E36: ='Annual Raw'!F14 -> 28.02 | F36: ='Annual Raw'!G14 -> 32.32 | G36: ='Annual Raw'!H14 -> 35.32 | H36: ='Annual Raw'!I14 -> 41.34 | I36: ='Annual Raw'!J14 -> 51.56 | ... AA36: ='Annual Raw'!AB14 -> 608.64 | AB36: =+SUM(CL36:CO36) -> 654.3944 | AC36: =+SUM(CP36:CS36) -> 700.20201 | AD36: =+SUM(CT36:CW36) -> 749.21615 | AE36: =+SUM(CX36:DA36) -> 801.66128 | AI36: ='QTR Raw'!C16 -> 27.87 | AJ36: ='QTR Raw'!D16 -> 27.67 | AK36: ='QTR Raw'!E16 -> 30.36 | AL36: ='QTR Raw'!F16 -> 29.94 | AM36: ='QTR Raw'!G16 -> 31.76 | AN36: ='QTR Raw'!H16 -> 31.27 | AO36: ='QTR Raw'!I16 -> 26.16 | AP36: ='QTR Raw'!J16 -> 37.48 | ... CJ36: ='QTR Raw'!BD16 -> 151.07 | CK36: 171.39 | CL36: ='QTR Raw'!BF16 -> 147.3 | CM36: =CI36*107% -> 162.0622 | CN36: =CJ36*107% -> 161.6449 | CO36: =CK36*107% -> 183.3873 | CP36: =CL36*107% -> 157.611 | CQ36: =CM36*107% -> 173.40655 | CR36: =CN36*107% -> 172.96004 | CS36: =CO36*107% -> 196.22441 | CT36: =CP36*107% -> 168.64377 | ... DA36: =CW36*107% -> 224.65733 | DE36: 608.64
A37: General and Administration Expenses | B37: ='Annual Raw'!C17 -> 0 | C37: ='Annual Raw'!D17 -> 0 | D37: ='Annual Raw'!E17 -> 19.26 | E37: ='Annual Raw'!F17 -> 19.14 | F37: ='Annual Raw'!G17 -> 13.69 | G37: ='Annual Raw'!H17 -> 17.67 | H37: ='Annual Raw'!I17 -> 20.63 | I37: ='Annual Raw'!J17 -> 24.51 | ... AA37: ='Annual Raw'!AB17 -> 369.01 | AB37: =+SUM(CL37:CO37) -> 0 | AC37: =+SUM(CP37:CS37) -> 0 | AD37: =+SUM(CT37:CW37) -> 0 | AE37: =+SUM(CX37:DA37) -> 0 | AI37: ='QTR Raw'!C17 -> 0 | AJ37: ='QTR Raw'!D17 -> 0 | AK37: ='QTR Raw'!E17 -> 0 | AL37: ='QTR Raw'!F17 -> 0 | AM37: ='QTR Raw'!G17 -> 0 | AN37: ='QTR Raw'!H17 -> 0 | AO37: ='QTR Raw'!I17 -> 0 | AP37: ='QTR Raw'!J17 -> 0 | ... CJ37: ='QTR Raw'!BD17 -> 0 | CL37: ='QTR Raw'!BF17 -> 0 | DE37: 0
A38: Miscellaneous Expenses | B38: ='Annual Raw'!C19-'Annual Raw'!C20 -> 0 | C38: ='Annual Raw'!D19-'Annual Raw'!D20 -> 0 | D38: ='Annual Raw'!E19-'Annual Raw'!E20 -> 5.611 | E38: ='Annual Raw'!F19-'Annual Raw'!F20 -> 4.1 | F38: ='Annual Raw'!G19-'Annual Raw'!G20 -> 2.92 | G38: ='Annual Raw'!H19-'Annual Raw'!H20 -> 3.79 | H38: ='Annual Raw'!I19-'Annual Raw'!I20 -> 3.91 | I38: ='Annual Raw'!J19-'Annual Raw'!J20 -> 9.68 | ... AA38: ='Annual Raw'!AB19-'Annual Raw'!AB20 -> 45.18 | AB38: =+SUM(CL38:CO38) -> 0 | AC38: =+SUM(CP38:CS38) -> 0 | AD38: =+SUM(CT38:CW38) -> 0 | AE38: =+SUM(CX38:DA38) -> 0 | DE38: 0
A39: Total Cost | B39: =+SUM(B33:B38) -> 0 | C39: =+SUM(C33:C38) -> 0 | D39: =+SUM(D33:D38) -> 107.171 | E39: =+SUM(E33:E38) -> 110.72 | F39: =+SUM(F33:F38) -> 122.84 | G39: =+SUM(G33:G38) -> 139.18 | H39: =+SUM(H33:H38) -> 163.65 | I39: =+SUM(I33:I38) -> 195.08 | ... AE39: =+SUM(AE33:AE38) -> 3473.4266 | AI39: =+SUM(AI33:AI38) -> 77.51 | AJ39: =+SUM(AJ33:AJ38) -> 84.37 | AK39: =+SUM(AK33:AK38) -> 79.11 | AL39: =+SUM(AL33:AL38) -> 78 | AM39: =+SUM(AM33:AM38) -> 83.29 | AN39: =+SUM(AN33:AN38) -> 80.28 | AO39: =+SUM(AO33:AO38) -> 80.17 | AP39: =+SUM(AP33:AP38) -> 95.32 | ... CL39: =+SUM(CL33:CL38) -> 514.42 | CM39: =CM40*CM23 -> 549.87918 | CN39: =CN40*CN23 -> 575.06824 | CO39: =CO40*CO23 -> 652.24953 | CP39: =CP40*CP23 -> 613.58474 | CQ39: =CQ40*CQ23 -> 637.33411 | CR39: =CR40*CR23 -> 673.7342 | CS39: =CS40*CS23 -> 759.94599 | CT39: =CT40*CT23 -> 702.94035 | ... DA39: =DA40*DA23 -> 981.73348 | DE39: 1990.29
A40: Cost % | B40: =B39/B23 -> #DIV/0! | C40: =C39/C23 -> #DIV/0! | D40: =D39/D23 -> 0.43866809 | E40: =E39/E23 -> 0.41482148 | F40: =F39/F23 -> 0.38016836 | G40: =G39/G23 -> 0.34086011 | H40: =H39/H23 -> 0.30191499 | I40: =I39/I23 -> 0.3041946 | ... AE40: =AE39/AE23 -> 0.20717135 | AI40: =AI39/AI23 -> 0.20390929 | AJ40: =AJ39/AJ23 -> 0.23688126 | AK40: =AK39/AK23 -> 0.22790389 | AL40: =AL39/AL23 -> 0.23450888 | AM40: =AM39/AM23 -> 0.27344956 | AN40: =AN39/AN23 -> 0.21617255 | AO40: =AO39/AO23 -> 0.20355465 | AP40: =AP39/AP23 -> 0.2378837 | ... CL40: =CL39/CL23 -> 0.19895268 | CM40: =AVERAGE(CI40:CL40) -> 0.20507598 | CN40: =AVERAGE(CJ40:CM40) -> 0.20385176 | CO40: =AVERAGE(CK40:CN40) -> 0.20472229 | CP40: =AVERAGE(CL40:CO40) -> 0.20315068 | CQ40: =AVERAGE(CM40:CP40) -> 0.20420018 | CR40: =AVERAGE(CN40:CQ40) -> 0.20398123 | CS40: =AVERAGE(CO40:CR40) -> 0.20401359 | CT40: =AVERAGE(CP40:CS40)*1.01 -> 0.20587478 | CU40: =AVERAGE(CQ40:CT40)*1.01 -> 0.20656262 | CV40: =AVERAGE(CR40:CU40)*1.01 -> 0.20715914 | CW40: =AVERAGE(CS40:CV40)*1.01 -> 0.20796156 | CX40: =AVERAGE(CT40:CW40) -> 0.20688952 | CY40: =AVERAGE(CU40:CX40) -> 0.20714321 | CZ40: =AVERAGE(CV40:CY40) -> 0.20728836 | DA40: =AVERAGE(CW40:CZ40) -> 0.20732066 | DE40: 0.20548429
A41: EBITDA | B41: =B29-B39 -> 0 | C41: =C29-C39 -> 0 | D41: =D29-D39 -> 44.13 | E41: =E29-E39 -> 42.29 | F41: =F29-F39 -> 52.79 | G41: =G29-G39 -> 78.58 | H41: =H29-H39 -> 118.14 | I41: =I29-I39 -> 130.93 | ... AE41: =AE29-AE39 -> 3015.0307 | AI41: =AI29-AI39 -> 63.91 | AJ41: =AJ29-AJ39 -> 51.59 | AK41: =AK29-AK39 -> 41.32 | AL41: =AL29-AL39 -> 41.45 | AM41: =AM29-AM39 -> 41.63 | AN41: =AN29-AN39 -> 50.66 | AO41: =AO29-AO39 -> 49.85 | AP41: =AP29-AP39 -> 55.71 | ... DA41: =DA29-DA39 -> 850.84355 | DE41: 1763.02
A42: EBITDA Margins | B42: =B41/B23 -> #DIV/0! | C42: =C41/C23 -> #DIV/0! | D42: =D41/D23 -> 0.18063117 | E42: =E41/E23 -> 0.15844292 | F42: =F41/F23 -> 0.16337584 | G42: =G41/G23 -> 0.1924471 | H42: =H41/H23 -> 0.21795439 | I42: =I41/I23 -> 0.20416342 | ... AE42: =AE41/AE23 -> 0.17983049 | AI42: =AI41/AI23 -> 0.16813112 | AJ42: =AJ41/AJ23 -> 0.14484656 | AK42: =AK41/AK23 -> 0.11903664 | AL42: =AL41/AL23 -> 0.12462043 | AM42: =AM41/AM23 -> 0.13667553 | AN42: =AN41/AN23 -> 0.13641382 | AO42: =AO41/AO23 -> 0.12657103 | AP42: =AP41/AP23 -> 0.13903169 | ... DA42: =DA41/DA23 -> 0.17967957 | DE42: 0.18202016
A43: EBITDA YOY% | C43: =+IF(B41<0,1-C41/B41,C41/B41-1) -> #DIV/0! | D43: =+IF(C41<0,1-D41/C41,D41/C41-1) -> #DIV/0! | E43: =+IF(D41<0,1-E41/D41,E41/D41-1) -> -0.041694992 | F43: =+IF(E41<0,1-F41/E41,F41/E41-1) -> 0.24828565 | G43: =+IF(F41<0,1-G41/F41,G41/F41-1) -> 0.4885395 | H43: =+IF(G41<0,1-H41/G41,H41/G41-1) -> 0.50343599 | I43: =+IF(H41<0,1-I41/H41,I41/H41-1) -> 0.10826138 | J43: =+IF(I41<0,1-J41/I41,J41/I41-1) -> 0.12082792 | ... AE43: =+IF(AD41<0,1-AE41/AD41,AE41/AD41-1) -> 0.1287986 | AM43: =+IF(AI41<0,1-AM41/AI41,AM41/AI41-1) -> -0.34861524 | AN43: =+IF(AJ41<0,1-AN41/AJ41,AN41/AJ41-1) -> -0.018026749 | AO43: =+IF(AK41<0,1-AO41/AK41,AO41/AK41-1) -> 0.20643756 | AP43: =+IF(AL41<0,1-AP41/AL41,AP41/AL41-1) -> 0.34402895 | AQ43: =+IF(AM41<0,1-AQ41/AM41,AQ41/AM41-1) -> 0.52822484 | AR43: =+IF(AN41<0,1-AR41/AN41,AR41/AN41-1) -> 0.18535334 | AS43: =+IF(AO41<0,1-AS41/AO41,AS41/AO41-1) -> 0.25095286 | AT43: =+IF(AP41<0,1-AT41/AP41,AT41/AP41-1) -> 0.13713875 | ... CL43: =+IF(CH41<0,1-CL41/CH41,CL41/CH41-1) -> 0.21759495 | CM43: =+CM41/CI41-1 -> 0.14206058 | CN43: =+CN41/CJ41-1 -> 0.13408069 | CO43: =+CO41/CK41-1 -> 0.19971928 | CP43: =+CP41/CL41-1 -> 0.15836577 | CQ43: =+CQ41/CM41-1 -> 0.16312083 | CR43: =+CR41/CN41-1 -> 0.16911123 | CS43: =+CS41/CO41-1 -> 0.17338488 | CT43: =+CT41/CP41-1 -> 0.11591153 | ... DA43: =+DA41/CW41-1 -> 0.13494744 | DE43: 0.2193489
A44: EBITDA QOQ% | AJ44: =+IF(AI41<0,1-AJ41/AI41,AJ41/AI41-1) -> -0.19277108 | AK44: =+IF(AJ41<0,1-AK41/AJ41,AK41/AJ41-1) -> -0.19906959 | AL44: =+IF(AK41<0,1-AL41/AK41,AL41/AK41-1) -> 0.0031461762 | AM44: =+IF(AL41<0,1-AM41/AL41,AM41/AL41-1) -> 0.0043425814 | AN44: =+IF(AM41<0,1-AN41/AM41,AN41/AM41-1) -> 0.21691088 | AO44: =+IF(AN41<0,1-AO41/AN41,AO41/AN41-1) -> -0.015988946 | AP44: =+IF(AO41<0,1-AP41/AO41,AP41/AO41-1) -> 0.11755266 | AQ44: =+IF(AP41<0,1-AQ41/AP41,AQ41/AP41-1) -> 0.14198528 | ... CI44: =+IF(CH41<0,1-CI41/CH41,CI41/CH41-1) -> 0.094898686 | CJ44: =+IF(CI41>1,CJ41/CI41-1,1-CJ41/CI41) -> 0.060029759 | CK44: =+IF(CJ41<0,1-CK41/CJ41,CK41/CJ41-1) -> 0.061806378 | CL44: =+IF(CK41>1,CL41/CK41-1,1-CL41/CK41) -> -0.011980501 | CM44: =+CM41/CL41-1 -> 0.026975864 | CN44: =+CN41/CM41-1 -> 0.05262304 | CO44: =+CO41/CN41-1 -> 0.12326187 | CP44: =+CP41/CO41-1 -> -0.046036867 | CQ44: =+CQ41/CP41-1 -> 0.031191569 | CR44: =+CR41/CQ41-1 -> 0.058044344 | CS44: =+CS41/CR41-1 -> 0.12736792 | CT44: =+CT41/CS41-1 -> -0.092762764 | ... DA44: =+DA41/CZ41-1 -> 0.12327224
A45: Depreciation | B45: ='Annual Raw'!C27 -> 0 | C45: ='Annual Raw'!D27 -> 0 | D45: ='Annual Raw'!E27 -> 16.98 | E45: ='Annual Raw'!F27 -> 16.74 | F45: ='Annual Raw'!G27 -> 16.99 | G45: ='Annual Raw'!H27 -> 16.83 | H45: ='Annual Raw'!I27 -> 18.3 | I45: ='Annual Raw'!J27 -> 19.36 | ... AA45: ='Annual Raw'!AB27 -> 343.72 | AB45: =+SUM(CL45:CO45) -> 361.84 | AC45: =+SUM(CP45:CS45) -> 361.84 | AD45: =+SUM(CT45:CW45) -> 427.48316 | AE45: =+SUM(CX45:DA45) -> 427.48316 | AI45: ='QTR Raw'!C28 -> 6.63 | AJ45: ='QTR Raw'!D28 -> 8.6 | AK45: ='QTR Raw'!E28 -> 8.76 | AL45: ='QTR Raw'!F28 -> 9.61 | AM45: ='QTR Raw'!G28 -> 10.49 | AN45: ='QTR Raw'!H28 -> 11.27 | AO45: ='QTR Raw'!I28 -> 11.88 | AP45: ='QTR Raw'!J28 -> 12.05 | ... CJ45: ='QTR Raw'!BD28 -> 87.88 | CK45: 92.02 | CL45: ='QTR Raw'!BF28 -> 90.46 | CM45: =CM46*CL147 -> 90.46 | CN45: =CN46*CM147 -> 90.46 | CO45: =CO46*CN147 -> 90.46 | CP45: =CP46*CO147 -> 90.46 | CQ45: =CQ46*CP147 -> 90.46 | CR45: =CR46*CQ147 -> 90.46 | CS45: =CS46*CR147 -> 90.46 | CT45: =CT46*CS147 -> 106.87079 | ... DA45: =DA46*CZ147 -> 106.87079 | DE45: 343.72
A46: Depreciation % of Net Block | B46: =+B45/B147 -> #DIV/0! | C46: =+C45/C147 -> #DIV/0! | D46: =+D45/D147 -> 0.17619591 | E46: =+E45/E147 -> 0.18962392 | F46: =+F45/F147 -> 0.2104546 | G46: =+G45/G147 -> 0.20250271 | H46: =+H45/H147 -> 0.16452396 | I46: =+I45/I147 -> 0.14752724 | ... AE46: =+AE45/AE147 -> 0.24735121 | AI46: =+AI45/AH147 -> #DIV/0! | AJ46: =+AJ45/AI147 -> 0.025708478 | AK46: =+AK45/AJ147 -> 0.026186775 | AL46: =+AL45/AK147 -> 0.024470984 | AM46: =+AM45/AL147 -> 0.026711823 | AN46: =+AN45/AM147 -> 0.028342932 | AO46: =+AO45/AN147 -> 0.029877021 | AP46: =+AP45/AO147 -> 0.029224874 | ... CE46: =+CE45/CD147 -> 0.053536952 | CF46: =+CF45/CE144 -> 0.05120808 | CG46: =+CG45/CF147 -> 0.054567934 | CH46: =+CH45/CG147 -> 0.044031389 | CI46: =+CI45/CH147 -> 0.042770321 | CJ46: =+CJ45/CI147 -> 0.051657957 | CK46: =CJ46 -> 0.051657957 | CL46: =+CL45/CK147 -> 0.044861463 | CM46: =CL46 -> 0.044861463 | CN46: =CM46 -> 0.044861463 | CO46: =CN46 -> 0.044861463 | CP46: =CO46 -> 0.044861463 | CQ46: =CP46 -> 0.044861463 | CR46: =CQ46 -> 0.044861463 | CS46: =CR46 -> 0.044861463 | CT46: 0.053 | CU46: =CT46 -> 0.053 | CV46: =CU46 -> 0.053 | CW46: =CV46 -> 0.053 | CX46: =CW46 -> 0.053 | CY46: =CX46 -> 0.053 | CZ46: =CY46 -> 0.053 | DA46: =CZ46 -> 0.053 | DE46: 0.17045967
A47: EBIT | B47: =B41-B45 -> 0 | C47: =C41-C45 -> 0 | D47: =D41-D45 -> 27.15 | E47: =E41-E45 -> 25.55 | F47: =F41-F45 -> 35.8 | G47: =G41-G45 -> 61.75 | H47: =H41-H45 -> 99.84 | I47: =I41-I45 -> 111.57 | ... AE47: =AE41-AE45 -> 2587.5475 | AI47: =AI41-AI45 -> 57.28 | AJ47: =AJ41-AJ45 -> 42.99 | AK47: =AK41-AK45 -> 32.56 | AL47: =AL41-AL45 -> 31.84 | AM47: =AM41-AM45 -> 31.14 | AN47: =AN41-AN45 -> 39.39 | AO47: =AO41-AO45 -> 37.97 | AP47: =AP41-AP45 -> 43.66 | ... DA47: =DA41-DA45 -> 743.97276 | DE47: 1419.3
A48: Other Income | B48: ='Annual Raw'!C23 -> 0 | C48: ='Annual Raw'!D23 -> 0 | D48: ='Annual Raw'!E23 -> 5.2 | E48: ='Annual Raw'!F23 -> 9.97 | F48: ='Annual Raw'!G23 -> 9.45 | G48: ='Annual Raw'!H23 -> 8.04 | H48: ='Annual Raw'!I23 -> 12.27 | I48: ='Annual Raw'!J23 -> 13.31 | ... AA48: ='Annual Raw'!AB23 -> 148.28 | AB48: =+SUM(CL48:CO48) -> 42.32 | AC48: =+SUM(CP48:CS48) -> 0 | AD48: =+SUM(CT48:CW48) -> 0 | AE48: =+SUM(CX48:DA48) -> 0 | AI48: ='QTR Raw'!C23 -> 11.73 | AJ48: ='QTR Raw'!D23 -> 12.1 | AK48: ='QTR Raw'!E23 -> 9.47 | AL48: ='QTR Raw'!F23 -> 7.22 | AM48: ='QTR Raw'!G23 -> 7.86 | AN48: ='QTR Raw'!H23 -> 15.21 | AO48: ='QTR Raw'!I23 -> 15.57 | AP48: ='QTR Raw'!J23 -> 9.09 | ... CJ48: ='QTR Raw'!BD23 -> 28.39 | CK48: 43.31 | CL48: ='QTR Raw'!BF23 -> 42.32 | DE48: 148.28
A49: Interest | B49: ='Annual Raw'!C25 -> 0 | C49: ='Annual Raw'!D25 -> 0 | D49: ='Annual Raw'!E25 -> 6.96 | E49: ='Annual Raw'!F25 -> 4.55 | F49: ='Annual Raw'!G25 -> 1.85 | G49: ='Annual Raw'!H25 -> 2.03 | H49: ='Annual Raw'!I25 -> 1.33 | I49: ='Annual Raw'!J25 -> 0.4 | ... AA49: ='Annual Raw'!AB25 -> 5.38 | AB49: =+SUM(CL49:CO49) -> -157.47932 | AC49: =+SUM(CP49:CS49) -> -303.81899 | AD49: =+SUM(CT49:CW49) -> -431.31912 | AE49: =+SUM(CX49:DA49) -> -583.84595 | AI49: ='QTR Raw'!C25 -> 0.35 | AJ49: ='QTR Raw'!D25 -> 0.37 | AK49: ='QTR Raw'!E25 -> 0.22 | AL49: ='QTR Raw'!F25 -> 0.21 | AM49: ='QTR Raw'!G25 -> 0.22 | AN49: ='QTR Raw'!H25 -> 0.16 | AO49: ='QTR Raw'!I25 -> 0.17 | AP49: ='QTR Raw'!J25 -> 0.17 | ... CJ49: ='QTR Raw'!BD25 -> 0.97 | CK49: 1.61 | CL49: ='QTR Raw'!BF25 -> 1.18 | CM49: =CM50*CL181 -> -46.918235 | CN49: =CN50*CM181 -> -53.005615 | CO49: =CO50*CN181 -> -58.735468 | CP49: =CP50*CO181 -> -62.157404 | CQ49: =CQ50*CP181 -> -73.281431 | CR49: =CR50*CQ181 -> -80.755092 | CS49: =CS50*CR181 -> -87.625065 | CT49: =CT50*CS181 -> -90.932439 | ... DA49: =DA50*CZ181 -> -161.82478 | DE49: 5.22
A50: Interest % of Debt | B50: =+B49/B141 -> #DIV/0! | C50: =+C49/C141 -> #DIV/0! | D50: =+D49/D141 -> 0.12756598 | E50: =+E49/E141 -> 0.18287781 | F50: =+F49/F141 -> 46.25 | G50: =+G49/G141 -> 0.18141197 | H50: =+H49/H141 -> #DIV/0! | I50: =+I49/I141 -> #DIV/0! | ... AE50: =+AE49/AE141 -> #DIV/0! | AI50: =(AI49-AI48)/AH181 -> #DIV/0! | AJ50: =(AJ49-AJ48)/AI181 -> 0.063535912 | AK50: =(AK49-AK48)/AJ181 -> 0.037201037 | AL50: =(AL49-AL48)/AK181 -> 0.035981932 | AM50: =(AM49-AM48)/AL181 -> 0.033304911 | AN50: =(AN49-AN48)/AM181 -> 0.066078328 | AO50: =(AO49-AO48)/AN181 -> 0.089362373 | AP50: =(AP49-AP48)/AO181 -> 0.03753261 | ... CL50: =(CL49-CL48)/CK181 -> 0.022290371 | CM50: =+CL50 -> 0.022290371 | CN50: =+CM50 -> 0.022290371 | CO50: =+CN50 -> 0.022290371 | CP50: =+CO50 -> 0.022290371 | CQ50: =+CP50 -> 0.022290371 | CR50: =+CQ50 -> 0.022290371 | CS50: =+CR50 -> 0.022290371 | CT50: 0.022 | CU50: =+CT50 -> 0.022 | CV50: =+CU50 -> 0.022 | CW50: =+CV50 -> 0.022 | CX50: =+CW50 -> 0.022 | CY50: =+CX50 -> 0.022 | CZ50: =+CY50 -> 0.022 | DA50: =+CZ50 -> 0.022
A51: PBT | B51: =B47+B48-B49 -> 0 | C51: =C47+C48-C49 -> 0 | D51: =D47+D48-D49 -> 25.39 | E51: =E47+E48-E49 -> 30.97 | F51: =F47+F48-F49 -> 43.4 | G51: =G47+G48-G49 -> 67.76 | H51: =H47+H48-H49 -> 110.78 | I51: =I47+I48-I49 -> 124.48 | ... AE51: =AE47+AE48-AE49 -> 3171.3935 | AI51: =AI47+AI48-AI49 -> 68.66 | AJ51: =AJ47+AJ48-AJ49 -> 54.72 | AK51: =AK47+AK48-AK49 -> 41.81 | AL51: =AL47+AL48-AL49 -> 38.85 | AM51: =AM47+AM48-AM49 -> 38.78 | AN51: =AN47+AN48-AN49 -> 54.44 | AO51: =AO47+AO48-AO49 -> 53.37 | AP51: =AP47+AP48-AP49 -> 52.58 | ... DA51: =DA47+DA48-DA49 -> 905.79754 | DE51: 1562.36
A52: Tax | B52: ='Annual Raw'!C30 -> 0 | C52: ='Annual Raw'!D30 -> 0 | D52: ='Annual Raw'!E30 -> 5.62 | E52: ='Annual Raw'!F30 -> 7.81 | F52: ='Annual Raw'!G30 -> 12.52 | G52: ='Annual Raw'!H30 -> 19.87 | H52: ='Annual Raw'!I30 -> 37.08 | I52: ='Annual Raw'!J30 -> 44.95 | ... AA52: ='Annual Raw'!AB30 -> 412.01 | AB52: =+SUM(CL52:CO52) -> 500.93859 | AC52: =+SUM(CP52:CS52) -> 636.80874 | AD52: =+SUM(CT52:CW52) -> 746.57217 | AE52: =+SUM(CX52:DA52) -> 887.25846 | AI52: ='QTR Raw'!C29 -> 22.42 | AJ52: ='QTR Raw'!D29 -> 17.78 | AK52: ='QTR Raw'!E29 -> 12.12 | AL52: ='QTR Raw'!F29 -> 13.4 | AM52: ='QTR Raw'!G29 -> 13.2 | AN52: ='QTR Raw'!H29 -> 18.55 | AO52: ='QTR Raw'!I29 -> 18.46 | AP52: ='QTR Raw'!J29 -> 17.9 | ... CJ52: ='QTR Raw'!BD29 -> 106.22 | CK52: 111.44 | CL52: ='QTR Raw'!BF29 -> 112.93 | CM52: =+CM51*CM53 -> 118.08465 | CN52: =+CN51*CN53 -> 126.19804 | CO52: =+CO51*CO53 -> 143.7259 | CP52: =+CP51*CP53 -> 141.02712 | CQ52: =+CQ51*CQ53 -> 149.35191 | CR52: =+CR51*CR53 -> 161.17365 | CS52: =+CS51*CS53 -> 185.25607 | CT52: =+CT51*CT53 -> 166.14459 | ... DA52: =+DA51*DA53 -> 253.81452 | DE52: 412.01
A53: Tax Rate % | B53: =B52/B51 -> #DIV/0! | C53: =C52/C51 -> #DIV/0! | D53: =D52/D51 -> 0.22134699 | E53: =E52/E51 -> 0.25217953 | F53: =F52/F51 -> 0.28847926 | G53: =G52/G51 -> 0.29324085 | H53: =H52/H51 -> 0.33471746 | I53: =I52/I51 -> 0.36110219 | ... AE53: =AE52/AE51 -> 0.27976928 | AI53: =AI52/AI51 -> 0.32653656 | AJ53: =AJ52/AJ51 -> 0.3249269 | AK53: =AK52/AK51 -> 0.2898828 | AL53: =AL52/AL51 -> 0.34491634 | AM53: =AM52/AM51 -> 0.34038164 | AN53: =AN52/AN51 -> 0.3407421 | AO53: =AO52/AO51 -> 0.3458872 | AP53: =AP52/AP51 -> 0.34043362 | ... CL53: =CL52/CL51 -> 0.26324009 | CM53: =AVERAGE(CI53:CL53) -> 0.26376943 | CN53: =AVERAGE(CJ53:CM53) -> 0.26312178 | CO53: =AVERAGE(CK53:CN53) -> 0.26175597 | CP53: =AVERAGE(CL53:CO53)*1.02 -> 0.26823125 | CQ53: =AVERAGE(CM53:CP53)*1.02 -> 0.269504 | CR53: =AVERAGE(CN53:CQ53)*1.02 -> 0.27096632 | CS53: =AVERAGE(CO53:CR53)*1.02 -> 0.27296667 | CT53: =AVERAGE(CP53:CS53)*1.02 -> 0.2758254 | CU53: =AVERAGE(CQ53:CT53)*1.02 -> 0.27776191 | CV53: =AVERAGE(CR53:CU53)*1.02 -> 0.27986768 | CW53: =AVERAGE(CS53:CV53)*1.02 -> 0.28213752 | CX53: =AVERAGE(CT53:CW53) -> 0.27889813 | CY53: =AVERAGE(CU53:CX53) -> 0.27966631 | CZ53: =AVERAGE(CV53:CY53) -> 0.28014241 | DA53: =AVERAGE(CW53:CZ53) -> 0.28021109 | DE53: 0.26371003
A54: PAT | B54: =B51-B52 -> 0 | C54: =C51-C52 -> 0 | D54: =D51-D52 -> 19.77 | E54: =E51-E52 -> 23.16 | F54: =F51-F52 -> 30.88 | G54: =G51-G52 -> 47.89 | H54: =H51-H52 -> 73.7 | I54: =I51-I52 -> 79.53 | ... AE54: =AE51-AE52 -> 2284.135 | AI54: =AI51-AI52 -> 46.24 | AJ54: =AJ51-AJ52 -> 36.94 | AK54: =AK51-AK52 -> 29.69 | AL54: =AL51-AL52 -> 25.45 | AM54: =AM51-AM52 -> 25.58 | AN54: =AN51-AN52 -> 35.89 | AO54: =AO51-AO52 -> 34.91 | AP54: =AP51-AP52 -> 34.68 | ... DA54: =DA51-DA52 -> 651.98303 | DE54: 1150.35
A55: PAT % | B55: =+B54/B23 -> #DIV/0! | C55: =+C54/C23 -> #DIV/0! | D55: =+D54/D23 -> 0.08092178 | E55: =+E54/E23 -> 0.086770822 | F55: =+F54/F23 -> 0.09556821 | G55: =+G54/G23 -> 0.11728546 | H55: =+H54/H23 -> 0.13596783 | I55: =+I54/I23 -> 0.12401372 | ... AE55: =+AE54/AE23 -> 0.13623646 | AI55: =+AI54/AI23 -> 0.1216458 | AJ55: =+AJ54/AJ23 -> 0.10371452 | AK55: =+AK54/AK23 -> 0.085532381 | AL55: =+AL54/AL23 -> 0.07651604 | AM55: =+AM54/AM23 -> 0.083981746 | AN55: =+AN54/AN23 -> 0.096642163 | AO55: =+AO54/AO23 -> 0.088637806 | AP55: =+AP54/AP23 -> 0.08654854 | ... DA55: =+DA54/DA23 -> 0.13768457 | DE55: 0.11876603
A56: PAT YOY% | C56: =+IF(B54<0,1-C54/B54,C54/B54-1) -> #DIV/0! | D56: =+IF(C54<0,1-D54/C54,D54/C54-1) -> #DIV/0! | E56: =+IF(D54<0,1-E54/D54,E54/D54-1) -> 0.17147193 | F56: =+IF(E54<0,1-F54/E54,F54/E54-1) -> 0.33333333 | G56: =+IF(F54<0,1-G54/F54,G54/F54-1) -> 0.55084197 | H56: =+IF(G54<0,1-H54/G54,H54/G54-1) -> 0.53894341 | I56: =+IF(H54<0,1-I54/H54,I54/H54-1) -> 0.079104478 | J56: =+IF(I54<0,1-J54/I54,J54/I54-1) -> 0.20357098 | ... AE56: =+IF(AD54<0,1-AE54/AD54,AE54/AD54-1) -> 0.18455002 | AM56: =+IF(AI54<0,1-AM54/AI54,AM54/AI54-1) -> -0.44679931 | AN56: =+IF(AJ54<0,1-AN54/AJ54,AN54/AJ54-1) -> -0.028424472 | AO56: =+IF(AK54<0,1-AO54/AK54,AO54/AK54-1) -> 0.17581677 | AP56: =+IF(AL54<0,1-AP54/AL54,AP54/AL54-1) -> 0.36267191 | AQ56: =+IF(AM54<0,1-AQ54/AM54,AQ54/AM54-1) -> 0.5938233 | AR56: =+IF(AN54<0,1-AR54/AN54,AR54/AN54-1) -> 0.045137921 | AS56: =+IF(AO54<0,1-AS54/AO54,AS54/AO54-1) -> 0.14351189 | AT56: =+IF(AP54<0,1-AT54/AP54,AT54/AP54-1) -> 0.19377163 | ... CL56: =+IF(CH54<0,1-CL54/CH54,CL54/CH54-1) -> 0.25614021 | CM56: =+CM54/CI54-1 -> 0.1479805 | CN56: =+CN54/CJ54-1 -> 0.2218085 | CO56: =+CO54/CK54-1 -> 0.25746887 | CP56: =+CP54/CL54-1 -> 0.21726136 | CQ56: =+CQ54/CM54-1 -> 0.22823245 | CR56: =+CR54/CN54-1 -> 0.22697243 | CS56: =+CS54/CO54-1 -> 0.21724709 | CT56: =+CT54/CP54-1 -> 0.13377825 | ... DA56: =+DA54/CW54-1 -> 0.18863671 | DE56: 0.22526255
A57: PAT QOQ% | AJ57: =+IF(AI54<0,1-AJ54/AI54,AJ54/AI54-1) -> -0.20112457 | AK57: =+IF(AJ54<0,1-AK54/AJ54,AK54/AJ54-1) -> -0.19626421 | AL57: =+IF(AK54<0,1-AL54/AK54,AL54/AK54-1) -> -0.14280903 | AM57: =+IF(AL54<0,1-AM54/AL54,AM54/AL54-1) -> 0.005108055 | AN57: =+IF(AM54<0,1-AN54/AM54,AN54/AM54-1) -> 0.40304926 | AO57: =+IF(AN54<0,1-AO54/AN54,AO54/AN54-1) -> -0.027305656 | AP57: =+IF(AO54<0,1-AP54/AO54,AP54/AO54-1) -> -0.0065883701 | AQ57: =+IF(AP54<0,1-AQ54/AP54,AQ54/AP54-1) -> 0.17560554 | ... CL57: =+IF(CK54<0,1-CL54/CK54,CL54/CK54-1) -> -0.019512346 | CM57: =+CM54/CL54-1 -> 0.042796473 | CN57: =+CN54/CM54-1 -> 0.072281205 | CO57: =+CO54/CN54-1 -> 0.14695629 | CP57: =+CP54/CO54-1 -> -0.050863396 | CQ57: =+CQ54/CP54-1 -> 0.052195118 | CR57: =+CR54/CQ54-1 -> 0.071181176 | CS57: =+CS54/CR54-1 -> 0.13786518 | CT57: =+CT54/CS54-1 -> -0.11594741 | ... DA57: =+DA54/CZ54-1 -> 0.12694254
A58: Minority Interest | B58: ='Annual Raw'!C32 -> 0 | C58: ='Annual Raw'!D32 -> 0 | D58: ='Annual Raw'!E32 -> 0 | E58: ='Annual Raw'!F32 -> 0 | F58: ='Annual Raw'!G32 -> 0 | G58: ='Annual Raw'!H32 -> 0 | H58: ='Annual Raw'!I32 -> 0 | I58: ='Annual Raw'!J32 -> 0 | ... AA58: ='Annual Raw'!AB32 -> 0 | AB58: =+SUM(CL58:CO58) -> 0 | AC58: =+SUM(CP58:CS58) -> 0 | AD58: =+SUM(CT58:CW58) -> 0 | AE58: =+SUM(CX58:DA58) -> 0 | AI58: ='QTR Raw'!C34 -> 0 | AJ58: ='QTR Raw'!D34 -> 0 | AK58: ='QTR Raw'!E34 -> 0 | AL58: ='QTR Raw'!F34 -> 0 | AM58: ='QTR Raw'!G34 -> 0 | AN58: ='QTR Raw'!H34 -> 0 | AO58: ='QTR Raw'!I34 -> 0 | AP58: ='QTR Raw'!J34 -> 0 | ... CJ58: ='QTR Raw'!BD34 -> 0 | CK58: =+CJ58 -> 0 | CL58: ='QTR Raw'!BF34 -> 0 | CM58: =+CL58 -> 0 | CN58: =+CM58 -> 0 | CO58: =+CN58 -> 0 | CP58: =+CO58 -> 0 | CQ58: =+CP58 -> 0 | CR58: =+CQ58 -> 0 | CS58: =+CR58 -> 0 | CT58: =+CS58 -> 0 | ... DA58: =+CZ58 -> 0 | DE58: 0
A59: Share of Associate | B59: ='Annual Raw'!C33+'Annual Raw'!C28 -> 0 | C59: ='Annual Raw'!D33+'Annual Raw'!D28 -> 0 | D59: ='Annual Raw'!E33+'Annual Raw'!E28 -> 0 | E59: ='Annual Raw'!F33+'Annual Raw'!F28 -> 0 | F59: ='Annual Raw'!G33+'Annual Raw'!G28 -> 0 | G59: ='Annual Raw'!H33+'Annual Raw'!H28 -> 0 | H59: ='Annual Raw'!I33+'Annual Raw'!I28 -> 0 | I59: ='Annual Raw'!J33+'Annual Raw'!J28 -> 0 | ... AA59: ='Annual Raw'!AB33+'Annual Raw'!AB28 -> 0 | AB59: =+SUM(CL59:CO59) -> 0 | AC59: =+SUM(CP59:CS59) -> 0 | AD59: =+SUM(CT59:CW59) -> 0 | AE59: =+SUM(CX59:DA59) -> 0 | AI59: ='QTR Raw'!C35 -> 0 | AJ59: ='QTR Raw'!D35 -> 0 | AK59: ='QTR Raw'!E35 -> 0 | AL59: ='QTR Raw'!F35 -> 0 | AM59: ='QTR Raw'!G35 -> 0 | AN59: ='QTR Raw'!H35 -> 0 | AO59: ='QTR Raw'!I35 -> 0 | AP59: ='QTR Raw'!J35 -> 0 | ... CJ59: ='QTR Raw'!BD35 -> 0 | CK59: =+CJ59 -> 0 | CL59: ='QTR Raw'!BF35 -> 0 | CM59: =+CL59 -> 0 | CN59: =+CM59 -> 0 | CO59: =+CN59 -> 0 | CP59: =+CO59 -> 0 | CQ59: =+CP59 -> 0 | CR59: =+CQ59 -> 0 | CS59: =+CR59 -> 0 | CT59: =+CS59 -> 0 | ... DA59: =+CZ59 -> 0 | DE59: 0
A60: Exceptional Income / Expenses | B60: ='Annual Raw'!C29+'Annual Raw'!C31+'Annual Raw'!C34+'Annual Raw'!C36 -> 0 | C60: ='Annual Raw'!D29+'Annual Raw'!D31+'Annual Raw'!D34+'Annual Raw'!D36 -> 0 | D60: ='Annual Raw'!E29+'Annual Raw'!E31+'Annual Raw'!E34+'Annual Raw'!E36 -> 0 | E60: ='Annual Raw'!F29+'Annual Raw'!F31+'Annual Raw'!F34+'Annual Raw'!F36 -> 0 | F60: ='Annual Raw'!G29+'Annual Raw'!G31+'Annual Raw'!G34+'Annual Raw'!G36 -> 0 | G60: ='Annual Raw'!H29+'Annual Raw'!H31+'Annual Raw'!H34+'Annual Raw'!H36 -> 0 | H60: ='Annual Raw'!I29+'Annual Raw'!I31+'Annual Raw'!I34+'Annual Raw'!I36 -> 0 | I60: ='Annual Raw'!J29+'Annual Raw'!J31+'Annual Raw'!J34+'Annual Raw'!J36 -> 0 | ... AA60: ='Annual Raw'!AB29+'Annual Raw'!AB31+'Annual Raw'!AB34+'Annual Raw'!AB36 -> 0 | AB60: =+SUM(CL60:CO60) -> 0 | AC60: =+SUM(CP60:CS60) -> 0 | AD60: =+SUM(CT60:CW60) -> 0 | AE60: =+SUM(CX60:DA60) -> 0 | AI60: ='QTR Raw'!C26+'QTR Raw'!C31+'QTR Raw'!C32+'QTR Raw'!C33+'QTR Raw'!C36+'QTR Raw'!C37+'QTR Raw'!C39 -> 0 | AJ60: ='QTR Raw'!D26+'QTR Raw'!D31+'QTR Raw'!D32+'QTR Raw'!D33+'QTR Raw'!D36+'QTR Raw'!D37+'QTR Raw'!D39 -> 0 | AK60: ='QTR Raw'!E26+'QTR Raw'!E31+'QTR Raw'!E32+'QTR Raw'!E33+'QTR Raw'!E36+'QTR Raw'!E37+'QTR Raw'!E39 -> 0 | AL60: ='QTR Raw'!F26+'QTR Raw'!F31+'QTR Raw'!F32+'QTR Raw'!F33+'QTR Raw'!F36+'QTR Raw'!F37+'QTR Raw'!F39 -> 0 | AM60: ='QTR Raw'!G26+'QTR Raw'!G31+'QTR Raw'!G32+'QTR Raw'!G33+'QTR Raw'!G36+'QTR Raw'!G37+'QTR Raw'!G39 -> 0 | AN60: ='QTR Raw'!H26+'QTR Raw'!H31+'QTR Raw'!H32+'QTR Raw'!H33+'QTR Raw'!H36+'QTR Raw'!H37+'QTR Raw'!H39 -> 0 | AO60: ='QTR Raw'!I26+'QTR Raw'!I31+'QTR Raw'!I32+'QTR Raw'!I33+'QTR Raw'!I36+'QTR Raw'!I37+'QTR Raw'!I39 -> 0 | AP60: ='QTR Raw'!J26+'QTR Raw'!J31+'QTR Raw'!J32+'QTR Raw'!J33+'QTR Raw'!J36+'QTR Raw'!J37+'QTR Raw'!J39 -> 0 | ... CJ60: ='QTR Raw'!BD26+'QTR Raw'!BD31+'QTR Raw'!BD32+'QTR Raw'!BD33+'QTR Raw'!BD36+'QTR Raw'!BD37+'QTR Raw'!BD39 -> 0 | CL60: ='QTR Raw'!BF26+'QTR Raw'!BF31+'QTR Raw'!BF32+'QTR Raw'!BF33+'QTR Raw'!BF36+'QTR Raw'!BF37+'QTR Raw'!BF39 -> 0 | DE60: 0
A61: Consolidated Net Profit | B61: =B54+B58+B59+B60 -> 0 | C61: =C54+C58+C59+C60 -> 0 | D61: =D54+D58+D59+D60 -> 19.77 | E61: =E54+E58+E59+E60 -> 23.16 | F61: =F54+F58+F59+F60 -> 30.88 | G61: =G54+G58+G59+G60 -> 47.89 | H61: =H54+H58+H59+H60 -> 73.7 | I61: =I54+I58+I59+I60 -> 79.53 | ... AE61: =AE54+AE58+AE59+AE60 -> 2284.135 | AI61: =AI54+AI58+AI59+AI60 -> 46.24 | AJ61: =AJ54+AJ58+AJ59+AJ60 -> 36.94 | AK61: =AK54+AK58+AK59+AK60 -> 29.69 | AL61: =AL54+AL58+AL59+AL60 -> 25.45 | AM61: =AM54+AM58+AM59+AM60 -> 25.58 | AN61: =AN54+AN58+AN59+AN60 -> 35.89 | AO61: =AO54+AO58+AO59+AO60 -> 34.91 | AP61: =AP54+AP58+AP59+AP60 -> 34.68 | ... DA61: =DA54+DA58+DA59+DA60 -> 651.98303 | DE61: 1150.35
A62: Profit & Loss- Annual (End)
A63: Rat
A64: Ace - PAT | B64: ='Annual Raw'!C35 -> 0 | C64: ='Annual Raw'!D35 -> 0 | D64: ='Annual Raw'!E35 -> 19.77 | E64: ='Annual Raw'!F35 -> 23.16 | F64: ='Annual Raw'!G35 -> 30.88 | G64: ='Annual Raw'!H35 -> 47.89 | H64: ='Annual Raw'!I35 -> 73.7 | I64: ='Annual Raw'!J35 -> 79.53 | ... AA64: ='Annual Raw'!AB35 -> 1150.35 | AB64: =+AB61 -> 1404.4447 | AC64: =+AC61 -> 1716.6186 | AD64: =+AD61 -> 1928.2723 | AE64: =+AE61 -> 2284.135 | AI64: ='QTR Raw'!C42 -> 46.24 | AJ64: ='QTR Raw'!D42 -> 36.94 | AK64: ='QTR Raw'!E42 -> 29.69 | AL64: ='QTR Raw'!F42 -> 25.45 | AM64: ='QTR Raw'!G42 -> 25.58 | AN64: ='QTR Raw'!H42 -> 35.89 | AO64: ='QTR Raw'!I42 -> 34.91 | AP64: ='QTR Raw'!J42 -> 34.68 | ... CL64: ='QTR Raw'!BF42 -> 316.07 | DE64: 1150.35
A65: Checksum - PAT | B65: =B64-B61 -> 0 | C65: =C64-C61 -> 0 | D65: =D64-D61 -> 0 | E65: =E64-E61 -> 0 | F65: =F64-F61 -> -4.2632564e-14 | G65: =G64-G61 -> 0 | H65: =H64-H61 -> 0 | I65: =I64-I61 -> 0 | ... AE65: =AE64-AE61 -> 0 | AI65: =AI64-AI61 -> 0 | AJ65: =AJ64-AJ61 -> 0 | AK65: =AK64-AK61 -> 0 | AL65: =AL64-AL61 -> 5.3290705e-14 | AM65: =AM64-AM61 -> 3.1974423e-14 | AN65: =AN64-AN61 -> 0 | AO65: =AO64-AO61 -> 0 | AP65: =AP64-AP61 -> 0 | ... CL65: =CL64-CL61 -> 0 | DE65: 0
A66: Ratios (Start)
A67: ROE (%) | B67: =(B61-B60)/B133 -> #DIV/0! | C67: =(C61-C60)/C133 -> #DIV/0! | D67: =(D61-D60)/D133 -> 0.19310412 | E67: =(E61-E60)/E133 -> 0.19932869 | F67: =(F61-F60)/F133 -> 0.21989603 | G67: =(G61-G60)/G133 -> 0.26375503 | H67: =(H61-H60)/H133 -> 0.29762145 | I67: =(I61-I60)/I133 -> 0.25001572 | ... AE67: =(AE61-AE60)/AE133 -> 0.17069438 | AL67: =(SUM(AI61:AL61)-SUM(AI60:AL60))/AL133 -> 0.15284822 | AM67: =(SUM(AJ61:AM61)-SUM(AJ60:AM60))/AM133 -> 0.1264563 | AN67: =(SUM(AK61:AN61)-SUM(AK60:AN60))/AN133 -> 0.12067306 | AO67: =(SUM(AL61:AO61)-SUM(AL60:AO60))/AO133 -> 0.12311657 | AP67: =(SUM(AM61:AP61)-SUM(AM60:AP60))/AP133 -> 0.12795954 | AQ67: =(SUM(AN61:AQ61)-SUM(AN60:AQ60))/AQ133 -> 0.13732781 | AR67: =(SUM(AO61:AR61)-SUM(AO60:AR60))/AR133 -> 0.13412488 | AS67: =(SUM(AP61:AS61)-SUM(AP60:AS60))/AS133 -> 0.13804188 | ... DA67: =(SUM(CX61:DA61)-SUM(CX60:DA60))/DA133 -> 0.17069438 | DE67: 0.19020463
A68: ROCE (%) | B68: =+B47/B142 -> #DIV/0! | C68: =+C47/C142 -> #DIV/0! | D68: =+D47/D142 -> 0.17299605 | E68: =+E47/E142 -> 0.18111576 | F68: =+F47/F142 -> 0.25485869 | G68: =+G47/G142 -> 0.32034654 | H68: =+H47/H142 -> 0.40318217 | I68: =+I47/I142 -> 0.35073876 | ... AE68: =+AE47/AE142 -> 0.19336853 | AL68: =+SUM(AI47:AL47)/AL142 -> 0.18196585 | AM68: =+SUM(AJ47:AM47)/AM142 -> 0.14888655 | AN68: =+SUM(AK47:AN47)/AN142 -> 0.13963139 | AO68: =+SUM(AL47:AO47)/AO142 -> 0.14182204 | AP68: =+SUM(AM47:AP47)/AP142 -> 0.14856038 | AQ68: =+SUM(AN47:AQ47)/AQ142 -> 0.16183554 | AR68: =+SUM(AO47:AR47)/AR142 -> 0.16371272 | AS68: =+SUM(AP47:AS47)/AS142 -> 0.17371714 | ... DA68: =+SUM(CX47:DA47)/DA142 -> 0.19336853 | DE68: 0.23467417
A69: Ratios (End)
A70: Checksum Of qtr to Annual
A71: Revenue - Checksum Of qtr to Annual | N71: =N23-SUM(AI23:AL23) -> 30.63 | R71: =R23-SUM(AX23:BA23) -> 0 | S71: =S23-SUM(BB23:BE23) -> 986.63 | T71: =T23-SUM(BF23:BI23) -> 0 | U71: =U23-SUM(BJ23:BM23) -> 0 | V71: =V23-SUM(BN23:BQ23) -> 0 | W71: =W23-SUM(BR23:BU23) -> 0 | X71: =X23-SUM(BV23:BY23) -> 0 | Y71: =Y23-SUM(BZ23:CC23) -> 0 | Z71: =Z23-SUM(CD23:CG23) -> 0 | AA71: =AA23-SUM(CE23:CH23) -> 1152.19 | AB71: =AB23-SUM(CL23:CO23) -> 0 | AC71: =AC23-SUM(CP23:CS23) -> 0 | AD71: =AD23-SUM(CT23:CW23) -> 0 | AE71: =AE23-SUM(CX23:DA23) -> 0 | DE71: 0
A72: GP - Checksum Of qtr to Annual | N72: =N29-SUM(AI29:AL29) -> 21.87 | R72: =R29-SUM(AX29:BA29) -> -1.76 | S72: =S29-SUM(BB29:BE29) -> 368.72 | T72: =T29-SUM(BF29:BI29) -> 0.01 | U72: =U29-SUM(BJ29:BM29) -> 0 | V72: =V29-SUM(BN29:BQ29) -> 0 | W72: =W29-SUM(BR29:BU29) -> 0 | X72: =X29-SUM(BV29:BY29) -> 0 | Y72: =Y29-SUM(BZ29:CC29) -> 0 | Z72: =Z29-SUM(CD29:CG29) -> 0 | AA72: =AA29-SUM(CE29:CH29) -> 560.47 | AB72: =AB29-SUM(CL29:CO29) -> 0 | AC72: =AC29-SUM(CP29:CS29) -> 0 | AD72: =AD29-SUM(CT29:CW29) -> 0 | AE72: =AE29-SUM(CX29:DA29) -> 0 | DE72: 0
A73: EBITDA - Checksum Of qtr to Annual | N73: =N41-SUM(AI41:AL41) -> 22.65 | R73: =R41-SUM(AX41:BA41) -> 0.36 | S73: =S41-SUM(BB41:BE41) -> 152.01 | T73: =T41-SUM(BF41:BI41) -> -38.46 | U73: =U41-SUM(BJ41:BM41) -> 0.67 | V73: =V41-SUM(BN41:BQ41) -> 0.7 | W73: =W41-SUM(BR41:BU41) -> 1.23 | X73: =X41-SUM(BV41:BY41) -> 1.46 | Y73: =Y41-SUM(BZ41:CC41) -> 0.59 | Z73: =Z41-SUM(CD41:CG41) -> 0.51 | AA73: =AA41-SUM(CE41:CH41) -> 254.84 | AB73: =AB41-SUM(CL41:CO41) -> 0 | AC73: =AC41-SUM(CP41:CS41) -> 0 | AD73: =AD41-SUM(CT41:CW41) -> 0 | AE73: =AE41-SUM(CX41:DA41) -> 0 | DE73: 0
A74: PAT - Checksum Of qtr to Annual | N74: =N61-SUM(AI61:AL61) -> 20.86 | R74: =R54-SUM(AX54:BA54) -> 0 | S74: =S54-SUM(BB54:BE54) -> 77.6 | T74: =T54-SUM(BF54:BI54) -> 0.01 | U74: =U54-SUM(BJ54:BM54) -> -1.1368684e-12 | V74: =V54-SUM(BN54:BQ54) -> 0 | W74: =W54-SUM(BR54:BU54) -> 0 | X74: =X54-SUM(BV54:BY54) -> 0 | Y74: =Y54-SUM(BZ54:CC54) -> 0 | Z74: =Z54-SUM(CD54:CG54) -> 0 | AA74: =AA54-SUM(CE54:CH54) -> 179.59 | AB74: =AB54-SUM(CL54:CO54) -> 0 | AC74: =AC54-SUM(CP54:CS54) -> 0 | AD74: =AD54-SUM(CT54:CW54) -> 0 | AE74: =AE54-SUM(CX54:DA54) -> 0 | DE74: 0
A75: Valuation (Start)
A76: Eq | B76: ='Annual Raw'!C104 -> 0 | C76: ='Annual Raw'!D104 -> 0 | D76: ='Annual Raw'!E104 -> 16.62 | E76: =+F76 -> 31.26 | F76: =+G76 -> 31.26 | G76: =+H76 -> 31.26 | H76: =+I76 -> 31.26 | I76: =+J76 -> 31.26 | J76: =+K76 -> 31.26 | K76: =+L76 -> 31.26 | L76: =+M76 -> 31.26 | ... AA76: =+AB76 -> 31.26 | AB76: =AA76 -> 31.26 | AC76: =AB76 -> 31.26 | AD76: =AC76 -> 31.26 | AE76: =AD76 -> 31.26 | AI76: =+AJ76 -> 31.26 | AJ76: =+AK76 -> 31.26 | AK76: =+AL76 -> 31.26 | AL76: =+AM76 -> 31.26 | AM76: =+AN76 -> 31.26 | AN76: =+AO76 -> 31.26 | AO76: =+AP76 -> 31.26 | AP76: =+AQ76 -> 31.26 | ... CI76: =+CJ76 -> 31.26 | CJ76: ='QTR Raw'!BD45 -> 31.26 | CK76: =+CJ76 -> 31.26 | CL76: ='QTR Raw'!BF45 -> 31.26 | CM76: =+CL76 -> 31.26 | CN76: =+CM76 -> 31.26 | CO76: =+CN76 -> 31.26 | CP76: =+CO76 -> 31.26 | CQ76: =+CP76 -> 31.26 | CR76: =+CQ76 -> 31.26 | CS76: =+CR76 -> 31.26 | CT76: =+CS76 -> 31.26 | ... DA76: =+CZ76 -> 31.26 | DE76: 31.26
A77: FV | B77: ='Annual Raw'!C105 -> 0 | C77: ='Annual Raw'!D105 -> 0 | D77: ='Annual Raw'!E105 -> 10 | E77: =+F77 -> 2 | F77: =+G77 -> 2 | G77: =+H77 -> 2 | H77: =+I77 -> 2 | I77: =+J77 -> 2 | J77: =+K77 -> 2 | K77: =+L77 -> 2 | L77: =+M77 -> 2 | ... AA77: =+AB77 -> 2 | AB77: =AA77 -> 2 | AC77: =AB77 -> 2 | AD77: =AC77 -> 2 | AE77: =AD77 -> 2 | AI77: =AJ77 -> 2 | AJ77: =AK77 -> 2 | AK77: =AL77 -> 2 | AL77: =AM77 -> 2 | AM77: =AN77 -> 2 | AN77: =AO77 -> 2 | AO77: =AP77 -> 2 | AP77: =AQ77 -> 2 | ... CI77: =CJ77 -> 2 | CJ77: ='QTR Raw'!BD46 -> 2 | CK77: =+CJ77 -> 2 | CL77: ='QTR Raw'!BF46 -> 2 | CM77: =+CL77 -> 2 | CN77: =+CM77 -> 2 | CO77: =+CN77 -> 2 | CP77: =+CO77 -> 2 | CQ77: =+CP77 -> 2 | CR77: =+CQ77 -> 2 | CS77: =+CR77 -> 2 | CT77: =+CS77 -> 2 | ... DA77: =+CZ77 -> 2 | DE77: 2
A78: No of share | B78: =B76/B77 -> #DIV/0! | C78: =C76/C77 -> #DIV/0! | D78: =D76/D77 -> 1.662 | E78: =E76/E77 -> 15.63 | F78: =F76/F77 -> 15.63 | G78: =G76/G77 -> 15.63 | H78: =H76/H77 -> 15.63 | I78: =I76/I77 -> 15.63 | ... AE78: =AE76/AE77 -> 15.63 | AI78: =AI76/AI77 -> 15.63 | AJ78: =AJ76/AJ77 -> 15.63 | AK78: =AK76/AK77 -> 15.63 | AL78: =AL76/AL77 -> 15.63 | AM78: =AM76/AM77 -> 15.63 | AN78: =AN76/AN77 -> 15.63 | AO78: =AO76/AO77 -> 15.63 | AP78: =AP76/AP77 -> 15.63 | ... DA78: =DA76/DA77 -> 15.63 | DE78: 15.63
A79: EPS | B79: =(B61-B60)/B78 -> #DIV/0! | C79: =(C61-C60)/C78 -> #DIV/0! | D79: =(D61-D60)/D78 -> 11.895307 | E79: =(E61-E60)/E78 -> 1.4817658 | F79: =(F61-F60)/F78 -> 1.9756878 | G79: =(G61-G60)/G78 -> 3.0639795 | H79: =(H61-H60)/H78 -> 4.7152911 | I79: =(I61-I60)/I78 -> 5.0882917 | ... AE79: =(AE61-AE60)/AE78 -> 146.13788 | AI79: =(AI61-AI60)/AI78 -> 2.9584133 | AJ79: =(AJ61-AJ60)/AJ78 -> 2.3634037 | AK79: =(AK61-AK60)/AK78 -> 1.8995521 | AL79: =(AL61-AL60)/AL78 -> 1.628279 | AM79: =(AM61-AM60)/AM78 -> 1.6365963 | AN79: =(AN61-AN60)/AN78 -> 2.2962252 | AO79: =(AO61-AO60)/AO78 -> 2.2335253 | AP79: =(AP61-AP60)/AP78 -> 2.21881 | ... DA79: =(DA61-DA60)/DA78 -> 41.713565 | DE79: 73.598848
A80: DPS | B80: ='Annual Raw'!C110 -> 0 | C80: ='Annual Raw'!D110 -> 0 | D80: ='Annual Raw'!E110 -> 0.8 | E80: ='Annual Raw'!F110 -> 0.9 | F80: ='Annual Raw'!G110 -> 0.7 | G80: ='Annual Raw'!H110 -> 0.7 | H80: ='Annual Raw'!I110 -> 0.8 | I80: ='Annual Raw'!J110 -> 0.8 | ... AA80: ='Annual Raw'!AB110 -> 35 | DE80: 35
A81: DPS % of EPS | B81: =B80/B79 -> #DIV/0! | C81: =C80/C79 -> #DIV/0! | D81: =D80/D79 -> 0.067253414 | E81: =E80/E79 -> 0.60738342 | F81: =F80/F79 -> 0.35430699 | G81: =G80/G79 -> 0.22846106 | H81: =H80/H79 -> 0.16966079 | I81: =I80/I79 -> 0.15722369 | ... AE81: =AE80/AE79 -> 0 | DE81: 0
A82: EPS TTM | B82: =+B79 -> #DIV/0! | C82: =+C79 -> #DIV/0! | D82: =+D79 -> 11.895307 | E82: =+E79 -> 1.4817658 | F82: =+F79 -> 1.9756878 | G82: =+G79 -> 3.0639795 | H82: =+H79 -> 4.7152911 | I82: =+I79 -> 5.0882917 | ... AE82: =+AE79 -> 146.13788 | AL82: =SUM(AI79:AL79) -> 8.8496481 | AM82: =SUM(AJ79:AM79) -> 7.5278311 | AN82: =SUM(AK79:AN79) -> 7.4606526 | AO82: =SUM(AL79:AO79) -> 7.7946257 | AP82: =SUM(AM79:AP79) -> 8.3851567 | AQ82: =SUM(AN79:AQ79) -> 9.3570058 | AR82: =SUM(AO79:AR79) -> 9.4606526 | AS82: =SUM(AP79:AS79) -> 9.78119 | ... DA82: =SUM(CX79:DA79) -> 146.13788 | DE82: 73.598848
A83: EPS Growth YoY % | C83: =+C82/B82-1 -> #DIV/0! | D83: =+D82/C82-1 -> #DIV/0! | E83: =+E82/D82-1 -> -0.87543274 | F83: =+F82/E82-1 -> 0.33333333 | G83: =+G82/F82-1 -> 0.55084197 | H83: =+H82/G82-1 -> 0.53894341 | I83: =+I82/H82-1 -> 0.079104478 | J83: =+J82/I82-1 -> 0.20357098 | ... AE83: =+AE82/AD82-1 -> 0.18455002 | AP83: =+IF(AL82<0,1-AP82/AL82,AP82/AL82-1) -> -0.052486987 | AQ83: =+IF(AM82<0,1-AQ82/AM82,AQ82/AM82-1) -> 0.24298827 | AR83: =+IF(AN82<0,1-AR82/AN82,AR82/AN82-1) -> 0.26807306 | AS83: =+IF(AO82<0,1-AS82/AO82,AS82/AO82-1) -> 0.25486333 | AT83: =+IF(AP82<0,1-AT82/AP82,AT82/AP82-1) -> 0.21776286 | AU83: =+IF(AQ82<0,1-AU82/AQ82,AU82/AQ82-1) -> 0.14940171 | AV83: =+IF(AR82<0,1-AV82/AR82,AV82/AR82-1) -> 0.22533306 | AW83: =+IF(AS82<0,1-AW82/AS82,AW82/AS82-1) -> 0.29173208 | ... DA83: =+IF(CW82<0,1-DA82/CW82,DA82/CW82-1) -> 0.18455002 | DE83: 0.22526255
CO84: 87.3 | CS84: 100.1 | CW84: 111.6
A85: Estimate deviation | CO85: =CO82/CO84-1 -> 0.029274975 | CS85: =CS82/CS84-1 -> 0.09718725 | CW85: =CW82/CW84-1 -> 0.1054655
A86: Promoter Share holding % | B86: ='Annual Raw'!C112 -> 0 | C86: ='Annual Raw'!D112 -> 0 | D86: ='Annual Raw'!E112 -> 51 | E86: ='Annual Raw'!F112 -> 51 | F86: ='Annual Raw'!G112 -> 51.33 | G86: ='Annual Raw'!H112 -> 51.33 | H86: ='Annual Raw'!I112 -> 51.33 | I86: ='Annual Raw'!J112 -> 51.33 | ... AA86: ='Annual Raw'!AB112 -> 74.13 | AI86: ='QTR Raw'!C49 -> 51.33 | AJ86: ='QTR Raw'!D49 -> 51.33 | AK86: ='QTR Raw'!E49 -> 51.33 | AL86: ='QTR Raw'!F49 -> 51.33 | AM86: ='QTR Raw'!G49 -> 51.33 | AN86: ='QTR Raw'!H49 -> 51.33 | AO86: ='QTR Raw'!I49 -> 51.33 | AP86: ='QTR Raw'!J49 -> 51.33 | ... CL86: ='QTR Raw'!BF49 -> 74.13 | DE86: 74.13
A87: Pledge Share % | B87: ='Annual Raw'!C113 -> 0 | C87: ='Annual Raw'!D113 -> 0 | D87: ='Annual Raw'!E113 -> 0 | E87: ='Annual Raw'!F113 -> 0 | F87: ='Annual Raw'!G113 -> 0 | G87: ='Annual Raw'!H113 -> 0 | H87: ='Annual Raw'!I113 -> 0 | I87: ='Annual Raw'!J113 -> 0 | ... AA87: ='Annual Raw'!AB113 -> 0 | AI87: ='QTR Raw'!C50 -> 0 | AJ87: ='QTR Raw'!D50 -> 0 | AK87: ='QTR Raw'!E50 -> 0 | AL87: ='QTR Raw'!F50 -> 0 | AM87: ='QTR Raw'!G50 -> 0 | AN87: ='QTR Raw'!H50 -> 0 | AO87: ='QTR Raw'!I50 -> 0 | AP87: ='QTR Raw'!J50 -> 0 | ... CL87: ='QTR Raw'!BF50 -> 0 | DE87: 0
A89: Share Price
A90: Share Price - Close | B90: ='Annual Raw'!C106 -> 0 | C90: ='Annual Raw'!D106 -> 0 | D90: ='Annual Raw'!E106 -> 10.88 | E90: ='Annual Raw'!F106 -> 25.47 | F90: ='Annual Raw'!G106 -> 32.34 | G90: ='Annual Raw'!H106 -> 80.1 | H90: ='Annual Raw'!I106 -> 128.82 | I90: ='Annual Raw'!J106 -> 139.57 | ... AA90: ='Annual Raw'!AB106 -> 3885.25 | AB90: =+CO90 -> 3844.7 | AC90: =+CS90 -> 3844.7 | AD90: =+CW90 -> 3844.7 | AE90: =+DA90 -> 3844.7 | AJ90: ='QTR Share Price'!HP21 -> 352.06 | AK90: ='QTR Share Price'!HQ21 -> 339.94 | AL90: ='QTR Share Price'!HR21 -> 293.93 | AM90: ='QTR Share Price'!HS21 -> 284 | AN90: ='QTR Share Price'!HT21 -> 249.7 | AO90: ='QTR Share Price'!HU21 -> 322.79 | AP90: ='QTR Share Price'!HV21 -> 375.5 | AQ90: ='QTR Share Price'!HW21 -> 497.28 | ... CL90: ='QTR Share Price'!JR21 -> 3844.7 | CM90: =+CL90 -> 3844.7 | CN90: =+CM90 -> 3844.7 | CO90: =+CN90 -> 3844.7 | CP90: =+CO90 -> 3844.7 | CQ90: =+CP90 -> 3844.7 | CR90: =+CQ90 -> 3844.7 | CS90: =+CR90 -> 3844.7 | CT90: =+CS90 -> 3844.7 | ... DA90: =+CZ90 -> 3844.7 | DE90: 3885.25
A91: Share Price - High | B91: ='Annual Raw'!C107 -> 0 | C91: ='Annual Raw'!D107 -> 0 | D91: ='Annual Raw'!E107 -> 13.78 | E91: ='Annual Raw'!F107 -> 29 | F91: ='Annual Raw'!G107 -> 34.2 | G91: ='Annual Raw'!H107 -> 95.77 | H91: ='Annual Raw'!I107 -> 155 | I91: ='Annual Raw'!J107 -> 145 | ... AA91: ='Annual Raw'!AB107 -> 4392.85 | AB91: =+MAX(CL91:CO91) -> 5162.0394 | AC91: =+MAX(CP91:CS91) -> 6309.4352 | AD91: =+MAX(CT91:CW91) -> 7087.369 | AE91: =+MAX(CX91:DA91) -> 8395.3432 | AJ91: ='QTR Share Price'!HP19 -> 360 | AK91: ='QTR Share Price'!HQ19 -> 365.37 | AL91: ='QTR Share Price'!HR19 -> 340 | AM91: ='QTR Share Price'!HS19 -> 308 | AN91: ='QTR Share Price'!HT19 -> 293.8 | AO91: ='QTR Share Price'!HU19 -> 329.79 | AP91: ='QTR Share Price'!HV19 -> 383 | AQ91: ='QTR Share Price'!HW19 -> 522 | ... CL91: ='QTR Share Price'!JR19 -> 4465 | CM91: =+CM82*CM99 -> 4621.1599 | CN91: =+CN82*CN99 -> 4856.9813 | CO91: =+CO82*CO99 -> 5162.0394 | CP91: =+CP82*CP99 -> 5414.4354 | CQ91: =+CQ82*CQ99 -> 5690.9238 | CR91: =+CR82*CR99 -> 5985.7603 | CS91: =+CS82*CS99 -> 6309.4352 | CT91: =+CT82*CT99 -> 6498.6127 | ... DA91: =+DA82*DA99 -> 8395.3432 | DE91: 4392.85
A92: Share Price - Low | B92: ='Annual Raw'!C108 -> 0 | C92: ='Annual Raw'!D108 -> 0 | D92: ='Annual Raw'!E108 -> 7.6 | E92: ='Annual Raw'!F108 -> 9.9 | F92: ='Annual Raw'!G108 -> 17.27 | G92: ='Annual Raw'!H108 -> 29.23 | H92: ='Annual Raw'!I108 -> 74.94 | I92: ='Annual Raw'!J108 -> 105.4 | ... AA92: ='Annual Raw'!AB108 -> 2836.55 | AB92: =+MIN(CL92:CO92) -> 3519 | AC92: =+MIN(CP92:CS92) -> 4267.2784 | AD92: =+MIN(CT92:CW92) -> 5121.751 | AE92: =+MIN(CX92:DA92) -> 5816.5205 | AJ92: =+'QTR Share Price'!HP20 -> 283 | AK92: =+'QTR Share Price'!HQ20 -> 325 | AL92: =+'QTR Share Price'!HR20 -> 269.8 | AM92: =+'QTR Share Price'!HS20 -> 257.94 | AN92: =+'QTR Share Price'!HT20 -> 220 | AO92: =+'QTR Share Price'!HU20 -> 250.04 | AP92: =+'QTR Share Price'!HV20 -> 293.54 | AQ92: =+'QTR Share Price'!HW20 -> 366 | ... CL92: =+'QTR Share Price'!JR20 -> 3519 | CM92: =+CM100*CM82 -> 3642.0743 | CN92: =+CN100*CN82 -> 3827.9322 | CO92: =+CO100*CO82 -> 4068.3576 | CP92: =+CP100*CP82 -> 4267.2784 | CQ92: =+CQ100*CQ82 -> 4485.1872 | CR92: =+CR100*CR82 -> 4717.5567 | CS92: =+CS100*CS82 -> 4972.6546 | CT92: =+CT100*CT82 -> 5121.751 | ... DA92: =+DA100*DA82 -> 6616.621 | DE92: 2836.55
A94: Upside (%) | AB94: =+AB91/AB90-1 -> 0.34263776 | AC94: =+AC91/AC90-1 -> 0.64107349 | AD94: =+AD91/AD90-1 -> 0.84341276 | AE94: =+AE91/AE90-1 -> 1.1836146 | CM94: =+CM91/CM90-1 -> 0.20195591 | CN94: =+CN91/CN90-1 -> 0.26329266 | CO94: =+CO91/CO90-1 -> 0.34263776 | CP94: =+CP91/CP90-1 -> 0.40828554 | CQ94: =+CQ91/CQ90-1 -> 0.4801997 | CR94: =+CR91/CR90-1 -> 0.55688619 | CS94: =+CS91/CS90-1 -> 0.64107349 | CT94: =+CT91/CT90-1 -> 0.69027822 | ... DA94: =+DA91/DA90-1 -> 1.1836146 | DE94: 0.13064796
A95: Downside (%) | AB95: =+AB92/AB90-1 -> -0.084714022 | AC95: =+AC92/AC90-1 -> 0.10991194 | AD95: =+AD92/AD90-1 -> 0.3321588 | AE95: =+AE92/AE90-1 -> 0.51286719 | CM95: =+CM92/CM90-1 -> -0.05270261 | CN95: =+CN92/CN90-1 -> -0.0043612799 | CO95: =+CO92/CO90-1 -> 0.058172965 | CP95: =+CP92/CP90-1 -> 0.10991194 | CQ95: =+CQ92/CQ90-1 -> 0.16658964 | CR95: =+CR92/CR90-1 -> 0.22702856 | CS95: =+CS92/CS90-1 -> 0.29337908 | CT95: =+CT92/CT90-1 -> 0.3321588 | ... DA95: =+DA92/DA90-1 -> 0.72097197 | DE95: -0.26991828
A97: PE
A98: PE - Close | B98: =+B90/B82 -> #DIV/0! | C98: =+C90/C82 -> #DIV/0! | D98: =+D90/D82 -> 0.91464643 | E98: =+E90/E82 -> 17.188951 | F98: =+F90/F82 -> 16.368983 | G98: =+G90/G82 -> 26.142472 | H98: =+H90/H82 -> 27.319628 | I98: =+I90/I82 -> 27.429638 | ... AE98: =+AE90/AE82 -> 26.308717 | AL98: =+AL90/AL82 -> 33.21375 | AM98: =+AM90/AM82 -> 37.72667 | AN98: =+AN90/AN82 -> 33.468922 | AO98: =+AO90/AO82 -> 41.411867 | AP98: =+AP90/AP82 -> 44.781512 | AQ98: =+AQ90/AQ82 -> 53.145206 | AR98: =+AR90/AR82 -> 60.880578 | AS98: =+AS90/AS82 -> 72.999297 | ... DA98: =+DA90/DA82 -> 26.308717 | DE98: 52.789549
A99: PE - High | B99: =+B91/B82 -> #DIV/0! | C99: =+C91/C82 -> #DIV/0! | D99: =+D91/D82 -> 1.1584401 | E99: =+E91/E82 -> 19.571244 | F99: =+F91/F82 -> 17.310427 | G99: =+G91/G82 -> 31.256736 | H99: =+H91/H82 -> 32.871777 | I99: =+I91/I82 -> 28.496794 | ... AE99: =+AE91/AE82 -> 57.448098 | AL99: =+AL91/AL82 -> 38.419607 | AM99: =+AM91/AM82 -> 40.914839 | AN99: =+AN91/AN82 -> 39.379933 | AO99: =+AO91/AO82 -> 42.309921 | AP99: =+AP91/AP82 -> 45.67595 | AQ99: =+AQ91/AQ82 -> 55.787077 | AR99: =+AR91/AR82 -> 64.249268 | AS99: =+AS91/AS82 -> 78.211342 | ... CL99: =+CL91/CL82 -> 57.448098 | CM99: =+CL99 -> 57.448098 | CN99: =+CM99 -> 57.448098 | CO99: =+CN99 -> 57.448098 | CP99: =+CO99 -> 57.448098 | CQ99: =+CP99 -> 57.448098 | CR99: =+CQ99 -> 57.448098 | CS99: =+CR99 -> 57.448098 | CT99: =+CS99 -> 57.448098 | ... DA99: =+CZ99 -> 57.448098 | DE99: 59.686396
A100: PE - Low | B100: =+B92/B82 -> #DIV/0! | C100: =+C92/C82 -> #DIV/0! | D100: =+D92/D82 -> 0.63890744 | E100: =+E92/E82 -> 6.6812176 | F100: =+F92/F82 -> 8.7412597 | G100: =+G92/G82 -> 9.539881 | H100: =+H92/H82 -> 15.892974 | I100: =+I92/I82 -> 20.714221 | ... AE100: =+AE92/AE82 -> 39.801594 | AL100: =+AL92/AL82 -> 30.487088 | AM100: =+AM92/AM82 -> 34.26485 | AN100: =+AN92/AN82 -> 29.488037 | AO100: =+AO92/AO82 -> 32.078513 | AP100: =+AP92/AP82 -> 35.007098 | AQ100: =+AQ92/AQ82 -> 39.115077 | AR100: =+AR92/AR82 -> 52.850477 | AS100: =+AS92/AS82 -> 56.235489 | ... CL100: =+CL92/CL82 -> 45.276564 | CM100: =+CL100 -> 45.276564 | CN100: =+CM100 -> 45.276564 | CO100: =+CN100 -> 45.276564 | CP100: =+CO100 -> 45.276564 | CQ100: =+CP100 -> 45.276564 | CR100: =+CQ100 -> 45.276564 | CS100: =+CR100 -> 45.276564 | CT100: =+CS100 -> 45.276564 | ... DA100: =+CZ100 -> 45.276564 | DE100: 38.540685
A102: PE - 1Yr Fwd | B102: =+B91/C82 -> #DIV/0! | C102: =+C91/D82 -> 0 | D102: =+D91/E82 -> 9.299715 | E102: =+E91/F82 -> 14.678433 | F102: =+F91/G82 -> 11.161954 | G102: =+G91/H82 -> 20.310517 | H102: =+H91/I82 -> 30.46209 | I102: =+I91/J82 -> 23.67687 | ... AD102: =+AD91/AE82 -> 48.497824 | AL102: =+AL91/AP82 -> 40.547841 | AM102: =+AM91/AQ82 -> 32.916513 | AN102: =+AN91/AR82 -> 31.05494 | AO102: =+AO91/AS82 -> 33.716756 | AP102: =+AP91/AT82 -> 37.508083 | AQ102: =+AQ91/AU82 -> 48.535753 | AR102: =+AR91/AV82 -> 52.434126 | AS102: =+AS91/AW82 -> 60.54765 | ... CL102: =+CL91/CP82 -> 47.374424 | DE102: 48.887825
A103: Correlation | AO103: =+CORREL(AL82:AO82,AL99:AO99) -> -0.55046245 | AP103: =+CORREL(AM82:AP82,AM99:AP99) -> 0.98394365 | AQ103: =+CORREL(AN82:AQ82,AN99:AQ99) -> 0.99285703 | AR103: =+CORREL(AO82:AR82,AO99:AR99) -> 0.94323788 | AS103: =+CORREL(AP82:AS82,AP99:AS99) -> 0.90622597 | AT103: =+CORREL(AQ82:AT82,AQ99:AT99) -> 0.96806594 | AU103: =+CORREL(AR82:AU82,AR99:AU99) -> 0.8405403 | AV103: =+CORREL(AS82:AV82,AS99:AV99) -> 0.47508098 | ... CL103: =+CORREL(CI82:CL82,CI99:CL99) -> -0.99486473
A105: BVPS | E105: =+E$133/E$78 -> 7.4337812 | F105: =+F$133/F$78 -> 8.9846449 | G105: =+G$133/G$78 -> 11.616763 | H105: =+H$133/H$78 -> 15.84325 | I105: =+I$133/I$78 -> 20.351887 | J105: =+J$133/J$78 -> 25.912348 | K105: =+K$133/K$78 -> 29.541907 | L105: =+L$133/L$78 -> 36.689699 | ... AE105: =+AE$133/AE$78 -> 856.13759 | AL105: =+AL$133/AL$78 -> 57.898273 | AM105: =+AM$133/AM$78 -> 59.529111 | AN105: =+AN$133/AN$78 -> 61.825336 | AO105: =+AO$133/AO$78 -> 63.31094 | AP105: =+AP$133/AP$78 -> 65.52975 | AQ105: =+AQ$133/AQ$78 -> 68.136276 | AR105: =+AR$133/AR$78 -> 70.536148 | AS105: =+AS$133/AS$78 -> 70.856686 | ... DA105: =+DA$133/DA$78 -> 856.13759 | DE105: 386.94562
A106: PB
A107: PB - Close | E107: =+E90/E$105 -> 3.426251 | F107: =+F90/F$105 -> 3.5994745 | G107: =+G90/G$105 -> 6.8952085 | H107: =+H90/H$105 -> 8.1309074 | I107: =+I90/I$105 -> 6.8578406 | J107: =+J90/J$105 -> 1.7366238 | K107: =+K90/K$105 -> 4.1144941 | L107: =+L90/L$105 -> 4.7784529 | ... AE107: =+AE90/AE$105 -> 4.4907501 | AL107: =+AL90/AL$105 -> 5.0766627 | AM107: =+AM90/AM$105 -> 4.7707751 | AN107: =+AN90/AN$105 -> 4.0387973 | AO107: =+AO90/AO$105 -> 5.0984869 | AP107: =+AP90/AP$105 -> 5.7302217 | AQ107: =+AQ90/AQ$105 -> 7.2983149 | AR107: =+AR90/AR$105 -> 8.1656004 | AS107: =+AS90/AS$105 -> 10.07696 | ... DA107: =+DA90/DA$105 -> 4.4907501 | DE107: 10.040817
A108: PB - High | E108: =+E91/E$105 -> 3.9011103 | F108: =+F91/F$105 -> 3.8064943 | G108: =+G91/G$105 -> 8.2441213 | H108: =+H91/H$105 -> 9.7833461 | I108: =+I91/I$105 -> 7.1246463 | J108: =+J91/J$105 -> 5.4028296 | K108: =+K91/K$105 -> 4.6029527 | L108: =+L91/L$105 -> 5.3420988 | ... AE108: =+AE91/AE$105 -> 9.8060676 | AL108: =+AL91/AL$105 -> 5.8723686 | AM108: =+AM91/AM$105 -> 5.1739392 | AN108: =+AN91/AN$105 -> 4.7520971 | AO108: =+AO91/AO$105 -> 5.2090523 | AP108: =+AP91/AP$105 -> 5.8446736 | AQ108: =+AQ91/AQ$105 -> 7.6611172 | AR108: =+AR91/AR$105 -> 8.6174254 | AS108: =+AS91/AS$105 -> 10.796441 | ... CL108: =+CL91/CL$105 -> 10.966 | CM108: =+CL108 -> 10.966 | CN108: =+CM108 -> 10.966 | CO108: =+CN108 -> 10.966 | CP108: =+CO108 -> 10.966 | CQ108: =+CP108 -> 10.966 | CR108: =+CQ108 -> 10.966 | CS108: =+CR108 -> 10.966 | CT108: =+CS108 -> 10.966 | ... DA108: =+CZ108 -> 10.966 | DE108: 11.352629
A109: PB - Low | E109: =+E92/E$105 -> 1.3317583 | F109: =+F92/F$105 -> 1.9221683 | G109: =+G92/G$105 -> 2.5161916 | H109: =+H92/H$105 -> 4.7300901 | I109: =+I92/I$105 -> 5.1788809 | J109: =+J92/J$105 -> 1.6679307 | K109: =+K92/K$105 -> 1.4894096 | L109: =+L92/L$105 -> 2.7266509 | ... AE109: =+AE92/AE$105 -> 6.7939085 | AL109: =+AL92/AL$105 -> 4.6598972 | AM109: =+AM92/AM$105 -> 4.3330061 | AN109: =+AN92/AN$105 -> 3.5584117 | AO109: =+AO92/AO$105 -> 3.9493964 | AP109: =+AP92/AP$105 -> 4.4794921 | AQ109: =+AQ92/AQ$105 -> 5.3715879 | AR109: =+AR92/AR$105 -> 7.088564 | AS109: =+AS92/AS$105 -> 7.7628525 | ... CL109: =+CL92/CL$105 -> 8.6426321 | CM109: =+CL109 -> 8.6426321 | CN109: =+CM109 -> 8.6426321 | CO109: =+CN109 -> 8.6426321 | CP109: =+CO109 -> 8.6426321 | CQ109: =+CP109 -> 8.6426321 | CR109: =+CQ109 -> 8.6426321 | CS109: =+CR109 -> 8.6426321 | CT109: =+CS109 -> 8.6426321 | ... DA109: =+CZ109 -> 8.6426321 | DE109: 7.3306167
...

Sheet QTR Raw
A1: ='Annual Raw'!A1 -> 105790 | B1: X | C1: 201206 | D1: 201209 | E1: 201212 | F1: 201303 | G1: 201306 | H1: 201309 | I1: 201312 | J1: 201403 | K1: 201406 | L1: 201409 | M1: 201412 | N1: 201503 | O1: 201506 | P1: 201509 | Q1: 201512 | R1: 201603 | S1: 201606 | T1: 201609 | U1: 201612 | V1: 201703 | W1: 201706 | X1: 201709 | Y1: 201712 | Z1: 201803 | AA1: 201806 | AB1: 201809 | AC1: 201812 | AD1: 201903 | AE1: 201906 | AF1: 201909 | AG1: 201912 | AH1: 202003 | AI1: 202006 | AJ1: 202009 | AK1: 202012 | AL1: 202103 | AM1: 202106 | AN1: 202109 | AO1: 202112 | AP1: 202203 | AQ1: 202206 | AR1: 202209 | AS1: 202212 | AT1: 202303 | AU1: 202306 | AV1: 202309 | AW1: 202312 | AX1: 202403 | AY1: 202406 | AZ1: 202409 | BA1: 202412 | BB1: 202503 | BC1: 202506 | BD1: 202509 | BE1: 202512 | BF1: 202603 | BG1: 202606 | BH1: 202609 | BI1: 202612 | BJ1: 202703 | BK1: 202706 | BL1: 202709 | BM1: 202712 | BN1: 202803 | BO1: 202806 | BP1: 202809 | BQ1: 202812 | BR1: 202903 | BS1: 202906 | BT1: 202909 | BU1: 202912
A3: Field Description | B3: Field Name
A4: Company Name | B4: CD_COMPNAME | C4: =_xll.EQNXTDZ(A1,B4,C1) -> Schaeffler India Ltd.
A5: Date End | B5: QTR_DATE_END | C5: =_xll.EQNXTDZ($A$1,$B5,C$1,$B$1) -> 201206 | D5: =_xll.EQNXTDZ($A$1,$B5,D$1,$B$1) -> 201209 | E5: =_xll.EQNXTDZ($A$1,$B5,E$1,$B$1) -> 201212 | F5: =_xll.EQNXTDZ($A$1,$B5,F$1,$B$1) -> 201303 | G5: =_xll.EQNXTDZ($A$1,$B5,G$1,$B$1) -> 201306 | H5: =_xll.EQNXTDZ($A$1,$B5,H$1,$B$1) -> 201309 | I5: =_xll.EQNXTDZ($A$1,$B5,I$1,$B$1) -> 201312 | J5: =_xll.EQNXTDZ($A$1,$B5,J$1,$B$1) -> 201403 | ... BU5: =_xll.EQNXTDZ($A$1,$B5,BU$1,$B$1) -> 0
A6: Gross Sales | B6: QTR_GROSS_SALE | C6: =_xll.EQNXTDZ($A$1,$B6,C$1,$B$1) -> 378.25 | D6: =_xll.EQNXTDZ($A$1,$B6,D$1,$B$1) -> 353.93 | E6: =_xll.EQNXTDZ($A$1,$B6,E$1,$B$1) -> 343.56 | F6: =_xll.EQNXTDZ($A$1,$B6,F$1,$B$1) -> 331.27 | G6: =_xll.EQNXTDZ($A$1,$B6,G$1,$B$1) -> 302.53 | H6: =_xll.EQNXTDZ($A$1,$B6,H$1,$B$1) -> 368.07 | I6: =_xll.EQNXTDZ($A$1,$B6,I$1,$B$1) -> 390.78 | J6: =_xll.EQNXTDZ($A$1,$B6,J$1,$B$1) -> 397.67 | ... BU6: =_xll.EQNXTDZ($A$1,$B6,BU$1,$B$1) -> 0
A7: Less: Excise Duty | B7: QTR_EXCISE_DUTY | C7: =_xll.EQNXTDZ($A$1,$B7,C$1,$B$1) -> 0 | D7: =_xll.EQNXTDZ($A$1,$B7,D$1,$B$1) -> 0 | E7: =_xll.EQNXTDZ($A$1,$B7,E$1,$B$1) -> 0 | F7: =_xll.EQNXTDZ($A$1,$B7,F$1,$B$1) -> 0 | G7: =_xll.EQNXTDZ($A$1,$B7,G$1,$B$1) -> 0 | H7: =_xll.EQNXTDZ($A$1,$B7,H$1,$B$1) -> 0 | I7: =_xll.EQNXTDZ($A$1,$B7,I$1,$B$1) -> 0 | J7: =_xll.EQNXTDZ($A$1,$B7,J$1,$B$1) -> 0 | ... BU7: =_xll.EQNXTDZ($A$1,$B7,BU$1,$B$1) -> 0
A8: Other operating income | B8: QTR_JOB_WORKS | C8: =_xll.EQNXTDZ($A$1,$B8,C$1,$B$1) -> 1.87 | D8: =_xll.EQNXTDZ($A$1,$B8,D$1,$B$1) -> 2.24 | E8: =_xll.EQNXTDZ($A$1,$B8,E$1,$B$1) -> 3.56 | F8: =_xll.EQNXTDZ($A$1,$B8,F$1,$B$1) -> 1.34 | G8: =_xll.EQNXTDZ($A$1,$B8,G$1,$B$1) -> 2.06 | H8: =_xll.EQNXTDZ($A$1,$B8,H$1,$B$1) -> 3.3 | I8: =_xll.EQNXTDZ($A$1,$B8,I$1,$B$1) -> 3.07 | J8: =_xll.EQNXTDZ($A$1,$B8,J$1,$B$1) -> 3.03 | ... BU8: =_xll.EQNXTDZ($A$1,$B8,BU$1,$B$1) -> 0
A9: Net Sales & Other Operating Income | B9: QTR_NET_SALES | C9: =_xll.EQNXTDZ($A$1,$B9,C$1,$B$1) -> 380.12 | D9: =_xll.EQNXTDZ($A$1,$B9,D$1,$B$1) -> 356.17 | E9: =_xll.EQNXTDZ($A$1,$B9,E$1,$B$1) -> 347.12 | F9: =_xll.EQNXTDZ($A$1,$B9,F$1,$B$1) -> 332.61 | G9: =_xll.EQNXTDZ($A$1,$B9,G$1,$B$1) -> 304.59 | H9: =_xll.EQNXTDZ($A$1,$B9,H$1,$B$1) -> 371.37 | I9: =_xll.EQNXTDZ($A$1,$B9,I$1,$B$1) -> 393.85 | J9: =_xll.EQNXTDZ($A$1,$B9,J$1,$B$1) -> 400.7 | ... BU9: =_xll.EQNXTDZ($A$1,$B9,BU$1,$B$1) -> 0
A10: (Increase) / Decrease In Stocks | B10: QTR_INC_DEC_INVENTORY | C10: =_xll.EQNXTDZ($A$1,$B10,C$1,$B$1) -> 10.69 | D10: =_xll.EQNXTDZ($A$1,$B10,D$1,$B$1) -> -17.41 | E10: =_xll.EQNXTDZ($A$1,$B10,E$1,$B$1) -> 22.81 | F10: =_xll.EQNXTDZ($A$1,$B10,F$1,$B$1) -> 3.36 | G10: =_xll.EQNXTDZ($A$1,$B10,G$1,$B$1) -> -28.38 | H10: =_xll.EQNXTDZ($A$1,$B10,H$1,$B$1) -> -9.71 | I10: =_xll.EQNXTDZ($A$1,$B10,I$1,$B$1) -> 2.53 | J10: =_xll.EQNXTDZ($A$1,$B10,J$1,$B$1) -> 5.57 | ... BU10: =_xll.EQNXTDZ($A$1,$B10,BU$1,$B$1) -> 0
A11: Cost of Services & Raw Materials | B11: QTR_RAW_MATERIAL_COST | C11: =_xll.EQNXTDZ($A$1,$B11,C$1,$B$1) -> 130.26 | D11: =_xll.EQNXTDZ($A$1,$B11,D$1,$B$1) -> 126.94 | E11: =_xll.EQNXTDZ($A$1,$B11,E$1,$B$1) -> 100.03 | F11: =_xll.EQNXTDZ($A$1,$B11,F$1,$B$1) -> 119.5 | G11: =_xll.EQNXTDZ($A$1,$B11,G$1,$B$1) -> 118.01 | H11: =_xll.EQNXTDZ($A$1,$B11,H$1,$B$1) -> 125.63 | I11: =_xll.EQNXTDZ($A$1,$B11,I$1,$B$1) -> 140.54 | J11: =_xll.EQNXTDZ($A$1,$B11,J$1,$B$1) -> 144.93 | ... BU11: =_xll.EQNXTDZ($A$1,$B11,BU$1,$B$1) -> 0
A12: Purchase of Finished Goods | B12: QTR_PURCHASE_FIN_GOOD | C12: =_xll.EQNXTDZ($A$1,$B12,C$1,$B$1) -> 97.75 | D12: =_xll.EQNXTDZ($A$1,$B12,D$1,$B$1) -> 110.68 | E12: =_xll.EQNXTDZ($A$1,$B12,E$1,$B$1) -> 103.85 | F12: =_xll.EQNXTDZ($A$1,$B12,F$1,$B$1) -> 90.3 | G12: =_xll.EQNXTDZ($A$1,$B12,G$1,$B$1) -> 90.04 | H12: =_xll.EQNXTDZ($A$1,$B12,H$1,$B$1) -> 124.51 | I12: =_xll.EQNXTDZ($A$1,$B12,I$1,$B$1) -> 120.76 | J12: =_xll.EQNXTDZ($A$1,$B12,J$1,$B$1) -> 99.17 | ... BU12: =_xll.EQNXTDZ($A$1,$B12,BU$1,$B$1) -> 0
A13: Excise Duty | B13: QTR_EXCISE | C13: =_xll.EQNXTDZ($A$1,$B13,C$1,$B$1) -> 0 | D13: =_xll.EQNXTDZ($A$1,$B13,D$1,$B$1) -> 0 | E13: =_xll.EQNXTDZ($A$1,$B13,E$1,$B$1) -> 0 | F13: =_xll.EQNXTDZ($A$1,$B13,F$1,$B$1) -> 0 | G13: =_xll.EQNXTDZ($A$1,$B13,G$1,$B$1) -> 0 | H13: =_xll.EQNXTDZ($A$1,$B13,H$1,$B$1) -> 0 | I13: =_xll.EQNXTDZ($A$1,$B13,I$1,$B$1) -> 0 | J13: =_xll.EQNXTDZ($A$1,$B13,J$1,$B$1) -> 0 | ... BU13: =_xll.EQNXTDZ($A$1,$B13,BU$1,$B$1) -> 0
A14: Operating & Manufacturing Expenses | B14: QTR_MFG_EXPS | C14: =_xll.EQNXTDZ($A$1,$B14,C$1,$B$1) -> 49.64 | D14: =_xll.EQNXTDZ($A$1,$B14,D$1,$B$1) -> 56.7 | E14: =_xll.EQNXTDZ($A$1,$B14,E$1,$B$1) -> 48.75 | F14: =_xll.EQNXTDZ($A$1,$B14,F$1,$B$1) -> 48.06 | G14: =_xll.EQNXTDZ($A$1,$B14,G$1,$B$1) -> 51.53 | H14: =_xll.EQNXTDZ($A$1,$B14,H$1,$B$1) -> 49.01 | I14: =_xll.EQNXTDZ($A$1,$B14,I$1,$B$1) -> 54.01 | J14: =_xll.EQNXTDZ($A$1,$B14,J$1,$B$1) -> 57.84 | ... BU14: =_xll.EQNXTDZ($A$1,$B14,BU$1,$B$1) -> 0
A15: Electricity Power & Fuel Cost | B15: QTR_ELECTRICITY_POWER_FUEL | C15: =_xll.EQNXTDZ($A$1,$B15,C$1,$B$1) -> 0 | D15: =_xll.EQNXTDZ($A$1,$B15,D$1,$B$1) -> 0 | E15: =_xll.EQNXTDZ($A$1,$B15,E$1,$B$1) -> 0 | F15: =_xll.EQNXTDZ($A$1,$B15,F$1,$B$1) -> 0 | G15: =_xll.EQNXTDZ($A$1,$B15,G$1,$B$1) -> 0 | H15: =_xll.EQNXTDZ($A$1,$B15,H$1,$B$1) -> 0 | I15: =_xll.EQNXTDZ($A$1,$B15,I$1,$B$1) -> 0 | J15: =_xll.EQNXTDZ($A$1,$B15,J$1,$B$1) -> 0 | ... BU15: =_xll.EQNXTDZ($A$1,$B15,BU$1,$B$1) -> 0
A16: Employee Cost | B16: QTR_EXPLOYEE_COST | C16: =_xll.EQNXTDZ($A$1,$B16,C$1,$B$1) -> 27.87 | D16: =_xll.EQNXTDZ($A$1,$B16,D$1,$B$1) -> 27.67 | E16: =_xll.EQNXTDZ($A$1,$B16,E$1,$B$1) -> 30.36 | F16: =_xll.EQNXTDZ($A$1,$B16,F$1,$B$1) -> 29.94 | G16: =_xll.EQNXTDZ($A$1,$B16,G$1,$B$1) -> 31.76 | H16: =_xll.EQNXTDZ($A$1,$B16,H$1,$B$1) -> 31.27 | I16: =_xll.EQNXTDZ($A$1,$B16,I$1,$B$1) -> 26.16 | J16: =_xll.EQNXTDZ($A$1,$B16,J$1,$B$1) -> 37.48 | ... BU16: =_xll.EQNXTDZ($A$1,$B16,BU$1,$B$1) -> 0
... A42: Consolidated PAT(after extra items) | B42: QTR_CONS_PAT_EXITM | C42: =_xll.EQNXTDZ($A$1,$B42,C$1,$B$1) -> 46.24 | D42: =_xll.EQNXTDZ($A$1,$B42,D$1,$B$1) -> 36.94 | E42: =_xll.EQNXTDZ($A$1,$B42,E$1,$B$1) -> 29.69 | F42: =_xll.EQNXTDZ($A$1,$B42,F$1,$B$1) -> 25.45 | G42: =_xll.EQNXTDZ($A$1,$B42,G$1,$B$1) -> 25.58 | H42: =_xll.EQNXTDZ($A$1,$B42,H$1,$B$1) -> 35.89 | I42: =_xll.EQNXTDZ($A$1,$B42,I$1,$B$1) -> 34.91 | J42: =_xll.EQNXTDZ($A$1,$B42,J$1,$B$1) -> 34.68 | ... BU42: =_xll.EQNXTDZ($A$1,$B42,BU$1,$B$1) -> 0
A44: Field Description | B44: Field Name
A45: Equity Capital | B45: QTR_EQUITY_CAP | C45: =_xll.EQNXTDZ($A$1,$B45,C$1,$B$1) -> 16.62 | D45: =_xll.EQNXTDZ($A$1,$B45,D$1,$B$1) -> 16.62 | E45: =_xll.EQNXTDZ($A$1,$B45,E$1,$B$1) -> 16.62 | F45: =_xll.EQNXTDZ($A$1,$B45,F$1,$B$1) -> 16.62 | G45: =_xll.EQNXTDZ($A$1,$B45,G$1,$B$1) -> 16.62 | H45: =_xll.EQNXTDZ($A$1,$B45,H$1,$B$1) -> 16.62 | I45: =_xll.EQNXTDZ($A$1,$B45,I$1,$B$1) -> 16.62 | J45: =_xll.EQNXTDZ($A$1,$B45,J$1,$B$1) -> 16.62 | ... BU45: =_xll.EQNXTDZ($A$1,$B45,BU$1,$B$1) -> 0
A46: Face Value | B46: QTR_FV | C46: =_xll.EQNXTDZ($A$1,$B46,C$1,$B$1) -> 10 | D46: =_xll.EQNXTDZ($A$1,$B46,D$1,$B$1) -> 10 | E46: =_xll.EQNXTDZ($A$1,$B46,E$1,$B$1) -> 10 | F46: =_xll.EQNXTDZ($A$1,$B46,F$1,$B$1) -> 10 | G46: =_xll.EQNXTDZ($A$1,$B46,G$1,$B$1) -> 10 | H46: =_xll.EQNXTDZ($A$1,$B46,H$1,$B$1) -> 10 | I46: =_xll.EQNXTDZ($A$1,$B46,I$1,$B$1) -> 10 | J46: =_xll.EQNXTDZ($A$1,$B46,J$1,$B$1) -> 10 | ... BU46: =_xll.EQNXTDZ($A$1,$B46,BU$1,$B$1) -> 0
A47: Month End | B47: BMONTH_MONTHEND | C47: =_xll.EQNXTDZ($A$1,$B47,C$5) -> 201206 | D47: =_xll.EQNXTDZ($A$1,$B47,D$5) -> 201209 | E47: =_xll.EQNXTDZ($A$1,$B47,E$5) -> 201212 | F47: =_xll.EQNXTDZ($A$1,$B47,F$5) -> 201303 | G47: =_xll.EQNXTDZ($A$1,$B47,G$5) -> 201306 | H47: =_xll.EQNXTDZ($A$1,$B47,H$5) -> 201309 | I47: =_xll.EQNXTDZ($A$1,$B47,I$5) -> 201312 | J47: =_xll.EQNXTDZ($A$1,$B47,J$5) -> 201403 | ... BU47: =_xll.EQNXTDZ($A$1,$B47,BU$5) -> 0
A48: Close | B48: BMONTH_CLOSE | C48: =_xll.EQNXTDZ($A$1,$B48,C$5) -> 287.61 | D48: =_xll.EQNXTDZ($A$1,$B48,D$5) -> 352.06 | E48: =_xll.EQNXTDZ($A$1,$B48,E$5) -> 339.94 | F48: =_xll.EQNXTDZ($A$1,$B48,F$5) -> 293.93 | G48: =_xll.EQNXTDZ($A$1,$B48,G$5) -> 284 | H48: =_xll.EQNXTDZ($A$1,$B48,H$5) -> 249.7 | I48: =_xll.EQNXTDZ($A$1,$B48,I$5) -> 322.79 | J48: =_xll.EQNXTDZ($A$1,$B48,J$5) -> 375.5 | ... BU48: =_xll.EQNXTDZ($A$1,$B48,BU$5) -> 0
A49: Total of Promoter and Promoter Group | B49: SHP_TPFTOTALPROMOTER | C49: =_xll.EQNXTDZ($A$1,$B49,C$5) -> 51.33 | D49: =_xll.EQNXTDZ($A$1,$B49,D$5) -> 51.33 | E49: =_xll.EQNXTDZ($A$1,$B49,E$5) -> 51.33 | F49: =_xll.EQNXTDZ($A$1,$B49,F$5) -> 51.33 | G49: =_xll.EQNXTDZ($A$1,$B49,G$5) -> 51.33 | H49: =_xll.EQNXTDZ($A$1,$B49,H$5) -> 51.33 | I49: =_xll.EQNXTDZ($A$1,$B49,I$5) -> 51.33 | J49: =_xll.EQNXTDZ($A$1,$B49,J$5) -> 51.33 | ... BU49: =_xll.EQNXTDZ($A$1,$B49,BU$5) -> 0
A50: Total of Promoter and Promoter Group Pledged | B50: SHP_PSHFTOTALPROMOTER | C50: =_xll.EQNXTDZ($A$1,$B50,C$5) -> 0 | D50: =_xll.EQNXTDZ($A$1,$B50,D$5) -> 0 | E50: =_xll.EQNXTDZ($A$1,$B50,E$5) -> 0 | F50: =_xll.EQNXTDZ($A$1,$B50,F$5) -> 0 | G50: =_xll.EQNXTDZ($A$1,$B50,G$5) -> 0 | H50: =_xll.EQNXTDZ($A$1,$B50,H$5) -> 0 | I50: =_xll.EQNXTDZ($A$1,$B50,I$5) -> 0 | J50: =_xll.EQNXTDZ($A$1,$B50,J$5) -> 0 | ... BU50: =_xll.EQNXTDZ($A$1,$B50,BU$5) -> 0
A54: Field Description | B54: Field Name | C54: =_xll.EQNXTDZ($A$1,$B54,C$5) -> 0 | D54: =_xll.EQNXTDZ($A$1,$B54,D$5) -> 0 | E54: =_xll.EQNXTDZ($A$1,$B54,E$5) -> 0 | F54: =_xll.EQNXTDZ($A$1,$B54,F$5) -> 0 | G54: =_xll.EQNXTDZ($A$1,$B54,G$5) -> 0 | H54: =_xll.EQNXTDZ($A$1,$B54,H$5) -> 0 | I54: =_xll.EQNXTDZ($A$1,$B54,I$5) -> 0 | J54: =_xll.EQNXTDZ($A$1,$B54,J$5) -> 0 | ... BU54: =_xll.EQNXTDZ($A$1,$B54,BU$5) -> 0
A55: Year End | B55: QTRB_DATE_END | C55: =_xll.EQNXTDZ($A$1,$B55,C$5,$B$1) -> 201206 | D55: =_xll.EQNXTDZ($A$1,$B55,D$5,$B$1) -> 0 | E55: =_xll.EQNXTDZ($A$1,$B55,E$5,$B$1) -> 201212 | F55: =_xll.EQNXTDZ($A$1,$B55,F$5,$B$1) -> 0 | G55: =_xll.EQNXTDZ($A$1,$B55,G$5,$B$1) -> 201306 | H55: =_xll.EQNXTDZ($A$1,$B55,H$5,$B$1) -> 0 | I55: =_xll.EQNXTDZ($A$1,$B55,I$5,$B$1) -> 201312 | J55: =_xll.EQNXTDZ($A$1,$B55,J$5,$B$1) -> 0 | ... BU55: =_xll.EQNXTDZ($A$1,$B55,BU$5,$B$1) -> 0
A56: Share Capital | B56: QTRB_SHARE_CAPITAL | C56: =_xll.EQNXTDZ($A$1,$B56,C$5,$B$1) -> 16.62 | D56: =_xll.EQNXTDZ($A$1,$B56,D$5,$B$1) -> 0 | E56: =_xll.EQNXTDZ($A$1,$B56,E$5,$B$1) -> 16.62 | F56: =_xll.EQNXTDZ($A$1,$B56,F$5,$B$1) -> 0 | G56: =_xll.EQNXTDZ($A$1,$B56,G$5,$B$1) -> 16.62 | H56: =_xll.EQNXTDZ($A$1,$B56,H$5,$B$1) -> 0 | I56: =_xll.EQNXTDZ($A$1,$B56,I$5,$B$1) -> 16.62 | J56: =_xll.EQNXTDZ($A$1,$B56,J$5,$B$1) -> 0 | ... BU56: =_xll.EQNXTDZ($A$1,$B56,BU$5,$B$1) -> 0
A57: Share Warrants & outstandings | B57: QTRB_SHAREWARNDOUT | C57: =_xll.EQNXTDZ($A$1,$B57,C$5,$B$1) -> 0 | D57: =_xll.EQNXTDZ($A$1,$B57,D$5,$B$1) -> 0 | E57: =_xll.EQNXTDZ($A$1,$B57,E$5,$B$1) -> 0 | F57: =_xll.EQNXTDZ($A$1,$B57,F$5,$B$1) -> 0 | G57: =_xll.EQNXTDZ($A$1,$B57,G$5,$B$1) -> 0 | H57: =_xll.EQNXTDZ($A$1,$B57,H$5,$B$1) -> 0 | I57: =_xll.EQNXTDZ($A$1,$B57,I$5,$B$1) -> 0 | J57: =_xll.EQNXTDZ($A$1,$B57,J$5,$B$1) -> 0 | ... BU57: =_xll.EQNXTDZ($A$1,$B57,BU$5,$B$1) -> 0
A58: Reserves & Surplus | B58: QTRB_RESERVE | C58: =_xll.EQNXTDZ($A$1,$B58,C$5,$B$1) -> 786.63 | D58: =_xll.EQNXTDZ($A$1,$B58,D$5,$B$1) -> 0 | E58: =_xll.EQNXTDZ($A$1,$B58,E$5,$B$1) -> 862.88 | F58: =_xll.EQNXTDZ($A$1,$B58,F$5,$B$1) -> 0 | G58: =_xll.EQNXTDZ($A$1,$B58,G$5,$B$1) -> 913.82 | H58: =_xll.EQNXTDZ($A$1,$B58,H$5,$B$1) -> 0 | I58: =_xll.EQNXTDZ($A$1,$B58,I$5,$B$1) -> 972.93 | J58: =_xll.EQNXTDZ($A$1,$B58,J$5,$B$1) -> 0 | ... BU58: =_xll.EQNXTDZ($A$1,$B58,BU$5,$B$1) -> 0
A59: Shareholder's Funds | B59: QTRB_SHAREHODERS_FUNDS | C59: =_xll.EQNXTDZ($A$1,$B59,C$5,$B$1) -> 803.25 | D59: =_xll.EQNXTDZ($A$1,$B59,D$5,$B$1) -> 0 | E59: =_xll.EQNXTDZ($A$1,$B59,E$5,$B$1) -> 879.5 | F59: =_xll.EQNXTDZ($A$1,$B59,F$5,$B$1) -> 0 | G59: =_xll.EQNXTDZ($A$1,$B59,G$5,$B$1) -> 930.44 | H59: =_xll.EQNXTDZ($A$1,$B59,H$5,$B$1) -> 0 | I59: =_xll.EQNXTDZ($A$1,$B59,I$5,$B$1) -> 989.55 | J59: =_xll.EQNXTDZ($A$1,$B59,J$5,$B$1) -> 0 | ... BU59: =_xll.EQNXTDZ($A$1,$B59,BU$5,$B$1) -> 0
A60: Minority Interest | B60: QTRB_MINORITY_INTEREST_BS | C60: =_xll.EQNXTDZ($A$1,$B60,C$5,$B$1) -> 0 | D60: =_xll.EQNXTDZ($A$1,$B60,D$5,$B$1) -> 0 | E60: =_xll.EQNXTDZ($A$1,$B60,E$5,$B$1) -> 0 | F60: =_xll.EQNXTDZ($A$1,$B60,F$5,$B$1) -> 0 | G60: =_xll.EQNXTDZ($A$1,$B60,G$5,$B$1) -> 0 | H60: =_xll.EQNXTDZ($A$1,$B60,H$5,$B$1) -> 0 | I60: =_xll.EQNXTDZ($A$1,$B60,I$5,$B$1) -> 0 | J60: =_xll.EQNXTDZ($A$1,$B60,J$5,$B$1) -> 0 | ... BU60: =_xll.EQNXTDZ($A$1,$B60,BU$5,$B$1) -> 0
A61: Long Term Borrowings | B61: QTRB_TOTAL_DEBTS | C61: =_xll.EQNXTDZ($A$1,$B61,C$5,$B$1) -> 0 | D61: =_xll.EQNXTDZ($A$1,$B61,D$5,$B$1) -> 0 | E61: =_xll.EQNXTDZ($A$1,$B61,E$5,$B$1) -> 0 | F61: =_xll.EQNXTDZ($A$1,$B61,F$5,$B$1) -> 0 | G61: =_xll.EQNXTDZ($A$1,$B61,G$5,$B$1) -> 0 | H61: =_xll.EQNXTDZ($A$1,$B61,H$5,$B$1) -> 0 | I61: =_xll.EQNXTDZ($A$1,$B61,I$5,$B$1) -> 0 | J61: =_xll.EQNXTDZ($A$1,$B61,J$5,$B$1) -> 0 | ... BU61: =_xll.EQNXTDZ($A$1,$B61,BU$5,$B$1) -> 0
A62: Secured Loans | B62: QTRB_SECURED_LOANS | C62: =_xll.EQNXTDZ($A$1,$B62,C$5,$B$1) -> 0 | D62: =_xll.EQNXTDZ($A$1,$B62,D$5,$B$1) -> 0 | E62: =_xll.EQNXTDZ($A$1,$B62,E$5,$B$1) -> 0 | F62: =_xll.EQNXTDZ($A$1,$B62,F$5,$B$1) -> 0 | G62: =_xll.EQNXTDZ($A$1,$B62,G$5,$B$1) -> 0 | H62: =_xll.EQNXTDZ($A$1,$B62,H$5,$B$1) -> 0 | I62: =_xll.EQNXTDZ($A$1,$B62,I$5,$B$1) -> 0 | J62: =_xll.EQNXTDZ($A$1,$B62,J$5,$B$1) -> 0 | ... BU62: =_xll.EQNXTDZ($A$1,$B62,BU$5,$B$1) -> 0
A63: Unsecured Loans | B63: QTRB_UNSECURED_LOANS_NF | C63: =_xll.EQNXTDZ($A$1,$B63,C$5,$B$1) -> 0 | D63: =_xll.EQNXTDZ($A$1,$B63,D$5,$B$1) -> 0 | E63: =_xll.EQNXTDZ($A$1,$B63,E$5,$B$1) -> 0 | F63: =_xll.EQNXTDZ($A$1,$B63,F$5,$B$1) -> 0 | G63: =_xll.EQNXTDZ($A$1,$B63,G$5,$B$1) -> 0 | H63: =_xll.EQNXTDZ($A$1,$B63,H$5,$B$1) -> 0 | I63: =_xll.EQNXTDZ($A$1,$B63,I$5,$B$1) -> 0 | J63: =_xll.EQNXTDZ($A$1,$B63,J$5,$B$1) -> 0 | ... BU63: =_xll.EQNXTDZ($A$1,$B63,BU$5,$B$1) -> 0
A64: Other Long Term Liabilities | B64: QTRB_OTHER_LT_LIABILITIES | C64: =_xll.EQNXTDZ($A$1,$B64,C$5,$B$1) -> 1.51 | D64: =_xll.EQNXTDZ($A$1,$B64,D$5,$B$1) -> 0 | E64: =_xll.EQNXTDZ($A$1,$B64,E$5,$B$1) -> 1.52 | F64: =_xll.EQNXTDZ($A$1,$B64,F$5,$B$1) -> 0 | G64: =_xll.EQNXTDZ($A$1,$B64,G$5,$B$1) -> 1.6 | H64: =_xll.EQNXTDZ($A$1,$B64,H$5,$B$1) -> 0 | I64: =_xll.EQNXTDZ($A$1,$B64,I$5,$B$1) -> 1.61 | J64: =_xll.EQNXTDZ($A$1,$B64,J$5,$B$1) -> 0 | ... BU64: =_xll.EQNXTDZ($A$1,$B64,BU$5,$B$1) -> 0
A65: Long Term Trade Payables | B65: QTRB_LT_TRADE_PAYABLE | C65: =_xll.EQNXTDZ($A$1,$B65,C$5,$B$1) -> 196.46 | D65: =_xll.EQNXTDZ($A$1,$B65,D$5,$B$1) -> 0 | E65: =_xll.EQNXTDZ($A$1,$B65,E$5,$B$1) -> 0 | F65: =_xll.EQNXTDZ($A$1,$B65,F$5,$B$1) -> 0 | G65: =_xll.EQNXTDZ($A$1,$B65,G$5,$B$1) -> 0 | H65: =_xll.EQNXTDZ($A$1,$B65,H$5,$B$1) -> 0 | I65: =_xll.EQNXTDZ($A$1,$B65,I$5,$B$1) -> 0 | J65: =_xll.EQNXTDZ($A$1,$B65,J$5,$B$1) -> 0 | ... BU65: =_xll.EQNXTDZ($A$1,$B65,BU$5,$B$1) -> 0
A66: Lont Term Provisions | B66: QTRB_LT_PROVISIONS | C66: =_xll.EQNXTDZ($A$1,$B66,C$5,$B$1) -> 13.18 | D66: =_xll.EQNXTDZ($A$1,$B66,D$5,$B$1) -> 0 | E66: =_xll.EQNXTDZ($A$1,$B66,E$5,$B$1) -> 22.94 | F66: =_xll.EQNXTDZ($A$1,$B66,F$5,$B$1) -> 0 | G66: =_xll.EQNXTDZ($A$1,$B66,G$5,$B$1) -> 22.04 | H66: =_xll.EQNXTDZ($A$1,$B66,H$5,$B$1) -> 0 | I66: =_xll.EQNXTDZ($A$1,$B66,I$5,$B$1) -> 20.5 | J66: =_xll.EQNXTDZ($A$1,$B66,J$5,$B$1) -> 0 | ... BU66: =_xll.EQNXTDZ($A$1,$B66,BU$5,$B$1) -> 0
... A97: Total Assets | B97: QTRB_TOTAL_APPLICATIONS | C97: =_xll.EQNXTDZ($A$1,$B97,C$5,$B$1) -> 1014.4 | D97: =_xll.EQNXTDZ($A$1,$B97,D$5,$B$1) -> 0 | E97: =_xll.EQNXTDZ($A$1,$B97,E$5,$B$1) -> 903.96 | F97: =_xll.EQNXTDZ($A$1,$B97,F$5,$B$1) -> 0 | G97: =_xll.EQNXTDZ($A$1,$B97,G$5,$B$1) -> 954.08 | H97: =_xll.EQNXTDZ($A$1,$B97,H$5,$B$1) -> 0 | I97: =_xll.EQNXTDZ($A$1,$B97,I$5,$B$1) -> 1011.66 | J97: =_xll.EQNXTDZ($A$1,$B97,J$5,$B$1) -> 0 | ... BU97: =_xll.EQNXTDZ($A$1,$B97,BU$5,$B$1) -> 0

Sheet Annual Raw
A1: 105790 | B1: X | C1: 200003 | D1: 200103 | E1: 200212 | F1: 200312 | G1: 200412 | H1: 200512 | I1: 200612 | J1: 200712 | K1: 200812 | L1: 200912 | M1: 201012 | N1: 201112 | O1: 201212 | P1: 201312 | Q1: 201412 | R1: 201512 | S1: 201612 | T1: 201712 | U1: 201812 | V1: 201912 | W1: 202012 | X1: 202112 | Y1: 202212 | Z1: 202312 | AA1: 202412 | AB1: 202512 | AC1: 202612 | AD1: 202712 | AE1: 202812 | AF1: 202912 | AG1: 203012
A3: Field Description | B3: Field Name
A4: Company Name | B4: CD_COMPNAME | C4: =_xll.EQNXTDZ(A1,B4,"L") -> Schaeffler India Ltd.
A5: Year End | B5: PL_YEAR_END | C5: =_xll.EQNXTDZ($A$1,$B5,C$1,$B$1) -> 0 | D5: =_xll.EQNXTDZ($A$1,$B5,D$1,$B$1) -> 0 | E5: =_xll.EQNXTDZ($A$1,$B5,E$1,$B$1) -> 200212 | F5: =_xll.EQNXTDZ($A$1,$B5,F$1,$B$1) -> 200312 | G5: =_xll.EQNXTDZ($A$1,$B5,G$1,$B$1) -> 200412 | H5: =_xll.EQNXTDZ($A$1,$B5,H$1,$B$1) -> 200512 | I5: =_xll.EQNXTDZ($A$1,$B5,I$1,$B$1) -> 200612 | J5: =_xll.EQNXTDZ($A$1,$B5,J$1,$B$1) -> 200712 | ... AG5: =_xll.EQNXTDZ($A$1,$B5,AG$1,$B$1) -> 0
A6: Sales Turnover | B6: PL_TOTAL_GROSS_SALES | C6: =_xll.EQNXTDZ($A$1,$B6,C$1,$B$1) -> 0 | D6: =_xll.EQNXTDZ($A$1,$B6,D$1,$B$1) -> 0 | E6: =_xll.EQNXTDZ($A$1,$B6,E$1,$B$1) -> 278.59 | F6: =_xll.EQNXTDZ($A$1,$B6,F$1,$B$1) -> 305.78 | G6: =_xll.EQNXTDZ($A$1,$B6,G$1,$B$1) -> 368.75 | H6: =_xll.EQNXTDZ($A$1,$B6,H$1,$B$1) -> 462.65 | I6: =_xll.EQNXTDZ($A$1,$B6,I$1,$B$1) -> 612.25 | J6: =_xll.EQNXTDZ($A$1,$B6,J$1,$B$1) -> 715.97 | ... AG6: =_xll.EQNXTDZ($A$1,$B6,AG$1,$B$1) -> 0
A7: Less: Inter divisional transfers | B7: PL_INTER_DIV_TRF | C7: =_xll.EQNXTDZ($A$1,$B7,C$1,$B$1) -> 0 | D7: =_xll.EQNXTDZ($A$1,$B7,D$1,$B$1) -> 0 | E7: =_xll.EQNXTDZ($A$1,$B7,E$1,$B$1) -> 0 | F7: =_xll.EQNXTDZ($A$1,$B7,F$1,$B$1) -> 0 | G7: =_xll.EQNXTDZ($A$1,$B7,G$1,$B$1) -> 0 | H7: =_xll.EQNXTDZ($A$1,$B7,H$1,$B$1) -> 0 | I7: =_xll.EQNXTDZ($A$1,$B7,I$1,$B$1) -> 0 | J7: =_xll.EQNXTDZ($A$1,$B7,J$1,$B$1) -> 0 | ... AG7: =_xll.EQNXTDZ($A$1,$B7,AG$1,$B$1) -> 0
A8: Less: Sales Returns | B8: PL_SALES_RETURN | C8: =_xll.EQNXTDZ($A$1,$B8,C$1,$B$1) -> 0 | D8: =_xll.EQNXTDZ($A$1,$B8,D$1,$B$1) -> 0 | E8: =_xll.EQNXTDZ($A$1,$B8,E$1,$B$1) -> 0 | F8: =_xll.EQNXTDZ($A$1,$B8,F$1,$B$1) -> 0 | G8: =_xll.EQNXTDZ($A$1,$B8,G$1,$B$1) -> 0 | H8: =_xll.EQNXTDZ($A$1,$B8,H$1,$B$1) -> 0 | I8: =_xll.EQNXTDZ($A$1,$B8,I$1,$B$1) -> 0 | J8: =_xll.EQNXTDZ($A$1,$B8,J$1,$B$1) -> 0 | ... AG8: =_xll.EQNXTDZ($A$1,$B8,AG$1,$B$1) -> 0
A9: Less: Excise | B9: PL_EXCISE | C9: =_xll.EQNXTDZ($A$1,$B9,C$1,$B$1) -> 0 | D9: =_xll.EQNXTDZ($A$1,$B9,D$1,$B$1) -> 0 | E9: =_xll.EQNXTDZ($A$1,$B9,E$1,$B$1) -> 34.28 | F9: =_xll.EQNXTDZ($A$1,$B9,F$1,$B$1) -> 38.87 | G9: =_xll.EQNXTDZ($A$1,$B9,G$1,$B$1) -> 45.63 | H9: =_xll.EQNXTDZ($A$1,$B9,H$1,$B$1) -> 54.33 | I9: =_xll.EQNXTDZ($A$1,$B9,I$1,$B$1) -> 70.21 | J9: =_xll.EQNXTDZ($A$1,$B9,J$1,$B$1) -> 74.67 | ... AG9: =_xll.EQNXTDZ($A$1,$B9,AG$1,$B$1) -> 0
A10: Net Sales | B10: PL_NET_SALES | C10: =_xll.EQNXTDZ($A$1,$B10,C$1,$B$1) -> 0 | D10: =_xll.EQNXTDZ($A$1,$B10,D$1,$B$1) -> 0 | E10: =_xll.EQNXTDZ($A$1,$B10,E$1,$B$1) -> 244.31 | F10: =_xll.EQNXTDZ($A$1,$B10,F$1,$B$1) -> 266.91 | G10: =_xll.EQNXTDZ($A$1,$B10,G$1,$B$1) -> 323.12 | H10: =_xll.EQNXTDZ($A$1,$B10,H$1,$B$1) -> 408.32 | I10: =_xll.EQNXTDZ($A$1,$B10,I$1,$B$1) -> 542.04 | J10: =_xll.EQNXTDZ($A$1,$B10,J$1,$B$1) -> 641.3 | ... AG10: =_xll.EQNXTDZ($A$1,$B10,AG$1,$B$1) -> 0
A11: Increase/Decrease in Stock | B11: PL_INC_DEC_INVENTORY | C11: =_xll.EQNXTDZ($A$1,$B11,C$1,$B$1) -> 0 | D11: =_xll.EQNXTDZ($A$1,$B11,D$1,$B$1) -> 0 | E11: =_xll.EQNXTDZ($A$1,$B11,E$1,$B$1) -> -3.371 | F11: =_xll.EQNXTDZ($A$1,$B11,F$1,$B$1) -> 4.7 | G11: =_xll.EQNXTDZ($A$1,$B11,G$1,$B$1) -> 0.58 | H11: =_xll.EQNXTDZ($A$1,$B11,H$1,$B$1) -> -4.68 | I11: =_xll.EQNXTDZ($A$1,$B11,I$1,$B$1) -> -17.98 | J11: =_xll.EQNXTDZ($A$1,$B11,J$1,$B$1) -> -6.41 | ... AG11: =_xll.EQNXTDZ($A$1,$B11,AG$1,$B$1) -> 0
A12: Raw Material Consumed | B12: PL_RAW_MATRS_CONSUMED | C12: =_xll.EQNXTDZ($A$1,$B12,C$1,$B$1) -> 0 | D12: =_xll.EQNXTDZ($A$1,$B12,D$1,$B$1) -> 0 | E12: =_xll.EQNXTDZ($A$1,$B12,E$1,$B$1) -> 96.38 | F12: =_xll.EQNXTDZ($A$1,$B12,F$1,$B$1) -> 109.2 | G12: =_xll.EQNXTDZ($A$1,$B12,G$1,$B$1) -> 146.91 | H12: =_xll.EQNXTDZ($A$1,$B12,H$1,$B$1) -> 195.24 | I12: =_xll.EQNXTDZ($A$1,$B12,I$1,$B$1) -> 278.23 | J12: =_xll.EQNXTDZ($A$1,$B12,J$1,$B$1) -> 321.7 | ... AG12: =_xll.EQNXTDZ($A$1,$B12,AG$1,$B$1) -> 0
A13: Power & Fuel Cost | B13: PL_POWER_FUEL | C13: =_xll.EQNXTDZ($A$1,$B13,C$1,$B$1) -> 0 | D13: =_xll.EQNXTDZ($A$1,$B13,D$1,$B$1) -> 0 | E13: =_xll.EQNXTDZ($A$1,$B13,E$1,$B$1) -> 9.8 | F13: =_xll.EQNXTDZ($A$1,$B13,F$1,$B$1) -> 9.72 | G13: =_xll.EQNXTDZ($A$1,$B13,G$1,$B$1) -> 10.4 | H13: =_xll.EQNXTDZ($A$1,$B13,H$1,$B$1) -> 10.95 | I13: =_xll.EQNXTDZ($A$1,$B13,I$1,$B$1) -> 13.32 | J13: =_xll.EQNXTDZ($A$1,$B13,J$1,$B$1) -> 14.94 | ... AG13: =_xll.EQNXTDZ($A$1,$B13,AG$1,$B$1) -> 0
A14: Employee Cost | B14: PL_EMPLOYEES | C14: =_xll.EQNXTDZ($A$1,$B14,C$1,$B$1) -> 0 | D14: =_xll.EQNXTDZ($A$1,$B14,D$1,$B$1) -> 0 | E14: =_xll.EQNXTDZ($A$1,$B14,E$1,$B$1) -> 27.84 | F14: =_xll.EQNXTDZ($A$1,$B14,F$1,$B$1) -> 28.02 | G14: =_xll.EQNXTDZ($A$1,$B14,G$1,$B$1) -> 32.32 | H14: =_xll.EQNXTDZ($A$1,$B14,H$1,$B$1) -> 35.32 | I14: =_xll.EQNXTDZ($A$1,$B14,I$1,$B$1) -> 41.34 | J14: =_xll.EQNXTDZ($A$1,$B14,J$1,$B$1) -> 51.56 | ... AG14: =_xll.EQNXTDZ($A$1,$B14,AG$1,$B$1) -> 0
A15: Operating & Manufacturing Expenses | B15: PL_GEN_OTHER_MFG_EXPS | C15: =_xll.EQNXTDZ($A$1,$B15,C$1,$B$1) -> 0 | D15: =_xll.EQNXTDZ($A$1,$B15,D$1,$B$1) -> 0 | E15: =_xll.EQNXTDZ($A$1,$B15,E$1,$B$1) -> 34.35 | F15: =_xll.EQNXTDZ($A$1,$B15,F$1,$B$1) -> 36.17 | G15: =_xll.EQNXTDZ($A$1,$B15,G$1,$B$1) -> 47.84 | H15: =_xll.EQNXTDZ($A$1,$B15,H$1,$B$1) -> 55.7 | I15: =_xll.EQNXTDZ($A$1,$B15,I$1,$B$1) -> 65.14 | J15: =_xll.EQNXTDZ($A$1,$B15,J$1,$B$1) -> 68.68 | ... AG15: =_xll.EQNXTDZ($A$1,$B15,AG$1,$B$1) -> 0
A16: Cost of Software development | B16: PL_COST_SW | C16: =_xll.EQNXTDZ($A$1,$B16,C$1,$B$1) -> 0 | D16: =_xll.EQNXTDZ($A$1,$B16,D$1,$B$1) -> 0 | E16: =_xll.EQNXTDZ($A$1,$B16,E$1,$B$1) -> 0 | F16: =_xll.EQNXTDZ($A$1,$B16,F$1,$B$1) -> 0 | G16: =_xll.EQNXTDZ($A$1,$B16,G$1,$B$1) -> 0 | H16: =_xll.EQNXTDZ($A$1,$B16,H$1,$B$1) -> 0 | I16: =_xll.EQNXTDZ($A$1,$B16,I$1,$B$1) -> 0 | J16: =_xll.EQNXTDZ($A$1,$B16,J$1,$B$1) -> 0 | ... AG16: =_xll.EQNXTDZ($A$1,$B16,AG$1,$B$1) -> 0
... A36: Profit After Tax from Discontinued Operations | B36: PL_PAT_DIS_OP | C36: =_xll.EQNXTDZ($A$1,$B36,C$1,$B$1) -> 0 | D36: =_xll.EQNXTDZ($A$1,$B36,D$1,$B$1) -> 0 | E36: =_xll.EQNXTDZ($A$1,$B36,E$1,$B$1) -> 0 | F36: =_xll.EQNXTDZ($A$1,$B36,F$1,$B$1) -> 0 | G36: =_xll.EQNXTDZ($A$1,$B36,G$1,$B$1) -> 0 | H36: =_xll.EQNXTDZ($A$1,$B36,H$1,$B$1) -> 0 | I36: =_xll.EQNXTDZ($A$1,$B36,I$1,$B$1) -> 0 | J36: =_xll.EQNXTDZ($A$1,$B36,J$1,$B$1) -> 0 | ... AG36: =_xll.EQNXTDZ($A$1,$B36,AG$1,$B$1) -> 0
A39: Field Description | B39: Field Name
A40: Year End | B40: BS_YEAR_END | C40: =_xll.EQNXTDZ($A$1,$B40,C$1,$B$1) -> 0 | D40: =_xll.EQNXTDZ($A$1,$B40,D$1,$B$1) -> 0 | E40: =_xll.EQNXTDZ($A$1,$B40,E$1,$B$1) -> 200212 | F40: =_xll.EQNXTDZ($A$1,$B40,F$1,$B$1) -> 200312 | G40: =_xll.EQNXTDZ($A$1,$B40,G$1,$B$1) -> 200412 | H40: =_xll.EQNXTDZ($A$1,$B40,H$1,$B$1) -> 200512 | I40: =_xll.EQNXTDZ($A$1,$B40,I$1,$B$1) -> 200612 | J40: =_xll.EQNXTDZ($A$1,$B40,J$1,$B$1) -> 200712 | ... AG40: =_xll.EQNXTDZ($A$1,$B40,AG$1,$B$1) -> 0
A41: Share Capital | B41: BS_SHARE_CAPITAL | C41: =_xll.EQNXTDZ($A$1,$B41,C$1,$B$1) -> 0 | D41: =_xll.EQNXTDZ($A$1,$B41,D$1,$B$1) -> 0 | E41: =_xll.EQNXTDZ($A$1,$B41,E$1,$B$1) -> 16.62 | F41: =_xll.EQNXTDZ($A$1,$B41,F$1,$B$1) -> 16.62 | G41: =_xll.EQNXTDZ($A$1,$B41,G$1,$B$1) -> 16.62 | H41: =_xll.EQNXTDZ($A$1,$B41,H$1,$B$1) -> 16.62 | I41: =_xll.EQNXTDZ($A$1,$B41,I$1,$B$1) -> 16.62 | J41: =_xll.EQNXTDZ($A$1,$B41,J$1,$B$1) -> 16.62 | ... AG41: =_xll.EQNXTDZ($A$1,$B41,AG$1,$B$1) -> 0
A42: Share Warrants & Outstandings | B42: BS_SHAREWROUTST | C42: =_xll.EQNXTDZ($A$1,$B42,C$1,$B$1) -> 0 | D42: =_xll.EQNXTDZ($A$1,$B42,D$1,$B$1) -> 0 | E42: =_xll.EQNXTDZ($A$1,$B42,E$1,$B$1) -> 0 | F42: =_xll.EQNXTDZ($A$1,$B42,F$1,$B$1) -> 0 | G42: =_xll.EQNXTDZ($A$1,$B42,G$1,$B$1) -> 0 | H42: =_xll.EQNXTDZ($A$1,$B42,H$1,$B$1) -> 0 | I42: =_xll.EQNXTDZ($A$1,$B42,I$1,$B$1) -> 0 | J42: =_xll.EQNXTDZ($A$1,$B42,J$1,$B$1) -> 0 | ... AG42: =_xll.EQNXTDZ($A$1,$B42,AG$1,$B$1) -> 0
A43: Total Reserves | B43: BS_RESERVE | C43: =_xll.EQNXTDZ($A$1,$B43,C$1,$B$1) -> 0 | D43: =_xll.EQNXTDZ($A$1,$B43,D$1,$B$1) -> 0 | E43: =_xll.EQNXTDZ($A$1,$B43,E$1,$B$1) -> 85.76 | F43: =_xll.EQNXTDZ($A$1,$B43,F$1,$B$1) -> 99.57 | G43: =_xll.EQNXTDZ($A$1,$B43,G$1,$B$1) -> 123.81 | H43: =_xll.EQNXTDZ($A$1,$B43,H$1,$B$1) -> 164.95 | I43: =_xll.EQNXTDZ($A$1,$B43,I$1,$B$1) -> 231.01 | J43: =_xll.EQNXTDZ($A$1,$B43,J$1,$B$1) -> 301.48 | ... AG43: =_xll.EQNXTDZ($A$1,$B43,AG$1,$B$1) -> 0
A44: Shareholder's Funds | B44: BS_SHAREHODERS_FUNDS | C44: =_xll.EQNXTDZ($A$1,$B44,C$1,$B$1) -> 0 | D44: =_xll.EQNXTDZ($A$1,$B44,D$1,$B$1) -> 0 | E44: =_xll.EQNXTDZ($A$1,$B44,E$1,$B$1) -> 102.38 | F44: =_xll.EQNXTDZ($A$1,$B44,F$1,$B$1) -> 116.19 | G44: =_xll.EQNXTDZ($A$1,$B44,G$1,$B$1) -> 140.43 | H44: =_xll.EQNXTDZ($A$1,$B44,H$1,$B$1) -> 181.57 | I44: =_xll.EQNXTDZ($A$1,$B44,I$1,$B$1) -> 247.63 | J44: =_xll.EQNXTDZ($A$1,$B44,J$1,$B$1) -> 318.1 | ... AG44: =_xll.EQNXTDZ($A$1,$B44,AG$1,$B$1) -> 0
A45: Minority Interest | B45: BS_MINORITY_INTEREST | C45: =_xll.EQNXTDZ($A$1,$B45,C$1,$B$1) -> 0 | D45: =_xll.EQNXTDZ($A$1,$B45,D$1,$B$1) -> 0 | E45: =_xll.EQNXTDZ($A$1,$B45,E$1,$B$1) -> 0 | F45: =_xll.EQNXTDZ($A$1,$B45,F$1,$B$1) -> 0 | G45: =_xll.EQNXTDZ($A$1,$B45,G$1,$B$1) -> 0 | H45: =_xll.EQNXTDZ($A$1,$B45,H$1,$B$1) -> 0 | I45: =_xll.EQNXTDZ($A$1,$B45,I$1,$B$1) -> 0 | J45: =_xll.EQNXTDZ($A$1,$B45,J$1,$B$1) -> 0 | ... AG45: =_xll.EQNXTDZ($A$1,$B45,AG$1,$B$1) -> 0
A46: Long-Term Borrowings | B46: BS_LTRM_BORROWING | C46: =_xll.EQNXTDZ($A$1,$B46,C$1,$B$1) -> 0 | D46: =_xll.EQNXTDZ($A$1,$B46,D$1,$B$1) -> 0 | E46: =_xll.EQNXTDZ($A$1,$B46,E$1,$B$1) -> 0 | F46: =_xll.EQNXTDZ($A$1,$B46,F$1,$B$1) -> 0 | G46: =_xll.EQNXTDZ($A$1,$B46,G$1,$B$1) -> 0 | H46: =_xll.EQNXTDZ($A$1,$B46,H$1,$B$1) -> 0 | I46: =_xll.EQNXTDZ($A$1,$B46,I$1,$B$1) -> 0 | J46: =_xll.EQNXTDZ($A$1,$B46,J$1,$B$1) -> 0 | ... AG46: =_xll.EQNXTDZ($A$1,$B46,AG$1,$B$1) -> 0
A47: Secured Loans | B47: BS_SECURED_LOANS | C47: =_xll.EQNXTDZ($A$1,$B47,C$1,$B$1) -> 0 | D47: =_xll.EQNXTDZ($A$1,$B47,D$1,$B$1) -> 0 | E47: =_xll.EQNXTDZ($A$1,$B47,E$1,$B$1) -> 9.89 | F47: =_xll.EQNXTDZ($A$1,$B47,F$1,$B$1) -> 7.89 | G47: =_xll.EQNXTDZ($A$1,$B47,G$1,$B$1) -> 0.04 | H47: =_xll.EQNXTDZ($A$1,$B47,H$1,$B$1) -> 11.19 | I47: =_xll.EQNXTDZ($A$1,$B47,I$1,$B$1) -> 0 | J47: =_xll.EQNXTDZ($A$1,$B47,J$1,$B$1) -> 0 | ... AG47: =_xll.EQNXTDZ($A$1,$B47,AG$1,$B$1) -> 0
A48: Unsecured Loans | B48: BS_UNSECURED_LOANS_NF | C48: =_xll.EQNXTDZ($A$1,$B48,C$1,$B$1) -> 0 | D48: =_xll.EQNXTDZ($A$1,$B48,D$1,$B$1) -> 0 | E48: =_xll.EQNXTDZ($A$1,$B48,E$1,$B$1) -> 44.67 | F48: =_xll.EQNXTDZ($A$1,$B48,F$1,$B$1) -> 16.99 | G48: =_xll.EQNXTDZ($A$1,$B48,G$1,$B$1) -> 0 | H48: =_xll.EQNXTDZ($A$1,$B48,H$1,$B$1) -> 0 | I48: =_xll.EQNXTDZ($A$1,$B48,I$1,$B$1) -> 0 | J48: =_xll.EQNXTDZ($A$1,$B48,J$1,$B$1) -> 0 | ... AG48: =_xll.EQNXTDZ($A$1,$B48,AG$1,$B$1) -> 0
A49: Deferred Tax Assets / Liabilities | B49: BS_NET_DEF_TAX_NF | C49: =_xll.EQNXTDZ($A$1,$B49,C$1,$B$1) -> 0 | D49: =_xll.EQNXTDZ($A$1,$B49,D$1,$B$1) -> 0 | E49: =_xll.EQNXTDZ($A$1,$B49,E$1,$B$1) -> 8.59 | F49: =_xll.EQNXTDZ($A$1,$B49,F$1,$B$1) -> 8.86 | G49: =_xll.EQNXTDZ($A$1,$B49,G$1,$B$1) -> 8.36 | H49: =_xll.EQNXTDZ($A$1,$B49,H$1,$B$1) -> 6.83 | I49: =_xll.EQNXTDZ($A$1,$B49,I$1,$B$1) -> 5.18 | J49: =_xll.EQNXTDZ($A$1,$B49,J$1,$B$1) -> 6.63 | ... AG49: =_xll.EQNXTDZ($A$1,$B49,AG$1,$B$1) -> 0
A50: Other Long Term Liabilities | B50: BS_OTH_LT_LIAB | C50: =_xll.EQNXTDZ($A$1,$B50,C$1,$B$1) -> 0 | D50: =_xll.EQNXTDZ($A$1,$B50,D$1,$B$1) -> 0 | E50: =_xll.EQNXTDZ($A$1,$B50,E$1,$B$1) -> 0 | F50: =_xll.EQNXTDZ($A$1,$B50,F$1,$B$1) -> 0 | G50: =_xll.EQNXTDZ($A$1,$B50,G$1,$B$1) -> 0 | H50: =_xll.EQNXTDZ($A$1,$B50,H$1,$B$1) -> 0 | I50: =_xll.EQNXTDZ($A$1,$B50,I$1,$B$1) -> 0 | J50: =_xll.EQNXTDZ($A$1,$B50,J$1,$B$1) -> 0 | ... AG50: =_xll.EQNXTDZ($A$1,$B50,AG$1,$B$1) -> 0
A51: Long Term Trade Payables | B51: BS_LT_TRADE_PAYABLES | C51: =_xll.EQNXTDZ($A$1,$B51,C$1,$B$1) -> 0 | D51: =_xll.EQNXTDZ($A$1,$B51,D$1,$B$1) -> 0 | E51: =_xll.EQNXTDZ($A$1,$B51,E$1,$B$1) -> 0 | F51: =_xll.EQNXTDZ($A$1,$B51,F$1,$B$1) -> 0 | G51: =_xll.EQNXTDZ($A$1,$B51,G$1,$B$1) -> 0 | H51: =_xll.EQNXTDZ($A$1,$B51,H$1,$B$1) -> 0 | I51: =_xll.EQNXTDZ($A$1,$B51,I$1,$B$1) -> 0 | J51: =_xll.EQNXTDZ($A$1,$B51,J$1,$B$1) -> 0 | ... AG51: =_xll.EQNXTDZ($A$1,$B51,AG$1,$B$1) -> 0
... A99: Estimated Capital Contracts Remaining | B99: BS_ESTIMATED_CAPITAL_CONTRACT | C99: =_xll.EQNXTDZ($A$1,$B99,C$1,$B$1) -> 0 | D99: =_xll.EQNXTDZ($A$1,$B99,D$1,$B$1) -> 0 | E99: =_xll.EQNXTDZ($A$1,$B99,E$1,$B$1) -> 0 | F99: =_xll.EQNXTDZ($A$1,$B99,F$1,$B$1) -> 0 | G99: =_xll.EQNXTDZ($A$1,$B99,G$1,$B$1) -> 0 | H99: =_xll.EQNXTDZ($A$1,$B99,H$1,$B$1) -> 0 | I99: =_xll.EQNXTDZ($A$1,$B99,I$1,$B$1) -> 0 | J99: =_xll.EQNXTDZ($A$1,$B99,J$1,$B$1) -> 0 | ... AG99: =_xll.EQNXTDZ($A$1,$B99,AG$1,$B$1) -> 0
A103: Field Description | B103: Field Name
A104: Equity Paid Up | B104: BS_EQUITY_PAIDUP | C104: =_xll.EQNXTDZ($A$1,$B104,C$1,$B$1) -> 0 | D104: =_xll.EQNXTDZ($A$1,$B104,D$1,$B$1) -> 0 | E104: =_xll.EQNXTDZ($A$1,$B104,E$1,$B$1) -> 16.62 | F104: =_xll.EQNXTDZ($A$1,$B104,F$1,$B$1) -> 16.62 | G104: =_xll.EQNXTDZ($A$1,$B104,G$1,$B$1) -> 16.62 | H104: =_xll.EQNXTDZ($A$1,$B104,H$1,$B$1) -> 16.62 | I104: =_xll.EQNXTDZ($A$1,$B104,I$1,$B$1) -> 16.62 | J104: =_xll.EQNXTDZ($A$1,$B104,J$1,$B$1) -> 16.62 | ... AG104: =_xll.EQNXTDZ($A$1,$B104,AG$1,$B$1) -> 0
A105: Face Value | B105: BS_FACE_VALUE | C105: =_xll.EQNXTDZ($A$1,$B105,C$1,$B$1) -> 0 | D105: =_xll.EQNXTDZ($A$1,$B105,D$1,$B$1) -> 0 | E105: =_xll.EQNXTDZ($A$1,$B105,E$1,$B$1) -> 10 | F105: =_xll.EQNXTDZ($A$1,$B105,F$1,$B$1) -> 10 | G105: =_xll.EQNXTDZ($A$1,$B105,G$1,$B$1) -> 10 | H105: =_xll.EQNXTDZ($A$1,$B105,H$1,$B$1) -> 10 | I105: =_xll.EQNXTDZ($A$1,$B105,I$1,$B$1) -> 10 | J105: =_xll.EQNXTDZ($A$1,$B105,J$1,$B$1) -> 10 | ... AG105: =_xll.EQNXTDZ($A$1,$B105,AG$1,$B$1) -> 0
A106: Close Price (Unit Curr.) | B106: FH_YEAR_PRICE | C106: =_xll.EQNXTDZ($A$1,$B106,C$1,$B$1) -> 0 | D106: =_xll.EQNXTDZ($A$1,$B106,D$1,$B$1) -> 0 | E106: =_xll.EQNXTDZ($A$1,$B106,E$1,$B$1) -> 10.88 | F106: =_xll.EQNXTDZ($A$1,$B106,F$1,$B$1) -> 25.47 | G106: =_xll.EQNXTDZ($A$1,$B106,G$1,$B$1) -> 32.34 | H106: =_xll.EQNXTDZ($A$1,$B106,H$1,$B$1) -> 80.1 | I106: =_xll.EQNXTDZ($A$1,$B106,I$1,$B$1) -> 128.82 | J106: =_xll.EQNXTDZ($A$1,$B106,J$1,$B$1) -> 139.57 | ... AG106: =_xll.EQNXTDZ($A$1,$B106,AG$1,$B$1) -> 0
A107: High Price (Unit Curr.) | B107: FH_HIGH | C107: =_xll.EQNXTDZ($A$1,$B107,C$1,$B$1) -> 0 | D107: =_xll.EQNXTDZ($A$1,$B107,D$1,$B$1) -> 0 | E107: =_xll.EQNXTDZ($A$1,$B107,E$1,$B$1) -> 13.78 | F107: =_xll.EQNXTDZ($A$1,$B107,F$1,$B$1) -> 29 | G107: =_xll.EQNXTDZ($A$1,$B107,G$1,$B$1) -> 34.2 | H107: =_xll.EQNXTDZ($A$1,$B107,H$1,$B$1) -> 95.77 | I107: =_xll.EQNXTDZ($A$1,$B107,I$1,$B$1) -> 155 | J107: =_xll.EQNXTDZ($A$1,$B107,J$1,$B$1) -> 145 | ... AG107: =_xll.EQNXTDZ($A$1,$B107,AG$1,$B$1) -> 0
A108: Low Price (Unit Curr.) | B108: FH_LOW | C108: =_xll.EQNXTDZ($A$1,$B108,C$1,$B$1) -> 0 | D108: =_xll.EQNXTDZ($A$1,$B108,D$1,$B$1) -> 0 | E108: =_xll.EQNXTDZ($A$1,$B108,E$1,$B$1) -> 7.6 | F108: =_xll.EQNXTDZ($A$1,$B108,F$1,$B$1) -> 9.9 | G108: =_xll.EQNXTDZ($A$1,$B108,G$1,$B$1) -> 17.27 | H108: =_xll.EQNXTDZ($A$1,$B108,H$1,$B$1) -> 29.23 | I108: =_xll.EQNXTDZ($A$1,$B108,I$1,$B$1) -> 74.94 | J108: =_xll.EQNXTDZ($A$1,$B108,J$1,$B$1) -> 105.4 | ... AG108: =_xll.EQNXTDZ($A$1,$B108,AG$1,$B$1) -> 0
A109: Market Capitalization | B109: FH_MCAP | C109: =_xll.EQNXTDZ($A$1,$B109,C$1,$B$1) -> 0 | D109: =_xll.EQNXTDZ($A$1,$B109,D$1,$B$1) -> 0 | E109: =_xll.EQNXTDZ($A$1,$B109,E$1,$B$1) -> 90.4128 | F109: =_xll.EQNXTDZ($A$1,$B109,F$1,$B$1) -> 211.6557 | G109: =_xll.EQNXTDZ($A$1,$B109,G$1,$B$1) -> 268.7454 | H109: =_xll.EQNXTDZ($A$1,$B109,H$1,$B$1) -> 665.631 | I109: =_xll.EQNXTDZ($A$1,$B109,I$1,$B$1) -> 1070.4942 | J109: =_xll.EQNXTDZ($A$1,$B109,J$1,$B$1) -> 1159.8267 | ... AG109: =_xll.EQNXTDZ($A$1,$B109,AG$1,$B$1) -> 0
A110: Adj DPS(Rs) | B110: FR_ADJ_DPS | C110: =_xll.EQNXTDZ($A$1,$B110,C$1,$B$1) -> 0 | D110: =_xll.EQNXTDZ($A$1,$B110,D$1,$B$1) -> 0 | E110: =_xll.EQNXTDZ($A$1,$B110,E$1,$B$1) -> 0.8 | F110: =_xll.EQNXTDZ($A$1,$B110,F$1,$B$1) -> 0.9 | G110: =_xll.EQNXTDZ($A$1,$B110,G$1,$B$1) -> 0.7 | H110: =_xll.EQNXTDZ($A$1,$B110,H$1,$B$1) -> 0.7 | I110: =_xll.EQNXTDZ($A$1,$B110,I$1,$B$1) -> 0.8 | J110: =_xll.EQNXTDZ($A$1,$B110,J$1,$B$1) -> 0.8 | ... AG110: =_xll.EQNXTDZ($A$1,$B110,AG$1,$B$1) -> 0
A111: Date End | B111: SHP_DATE_END | C111: =_xll.EQNXTDZ($A$1,$B111,C$5) -> 0 | D111: =_xll.EQNXTDZ($A$1,$B111,D$5) -> 0 | E111: =_xll.EQNXTDZ($A$1,$B111,E$5) -> 200212 | F111: =_xll.EQNXTDZ($A$1,$B111,F$5) -> 200312 | G111: =_xll.EQNXTDZ($A$1,$B111,G$5) -> 200412 | H111: =_xll.EQNXTDZ($A$1,$B111,H$5) -> 200512 | I111: =_xll.EQNXTDZ($A$1,$B111,I$5) -> 200612 | J111: =_xll.EQNXTDZ($A$1,$B111,J$5) -> 200712 | ... AG111: =_xll.EQNXTDZ($A$1,$B111,AG$5) -> 0
A112: Total of Promoter and Promoter Group | B112: SHP_TPFTOTALPROMOTER | C112: =_xll.EQNXTDZ($A$1,$B112,C$5) -> 0 | D112: =_xll.EQNXTDZ($A$1,$B112,D$5) -> 0 | E112: =_xll.EQNXTDZ($A$1,$B112,E$5) -> 51 | F112: =_xll.EQNXTDZ($A$1,$B112,F$5) -> 51 | G112: =_xll.EQNXTDZ($A$1,$B112,G$5) -> 51.33 | H112: =_xll.EQNXTDZ($A$1,$B112,H$5) -> 51.33 | I112: =_xll.EQNXTDZ($A$1,$B112,I$5) -> 51.33 | J112: =_xll.EQNXTDZ($A$1,$B112,J$5) -> 51.33 | ... AG112: =_xll.EQNXTDZ($A$1,$B112,AG$5) -> 0
A113: Total of Promoter and Promoter Group Pledged | B113: SHP_PSHFTOTALPROMOTER | C113: =_xll.EQNXTDZ($A$1,$B113,C$5) -> 0 | D113: =_xll.EQNXTDZ($A$1,$B113,D$5) -> 0 | E113: =_xll.EQNXTDZ($A$1,$B113,E$5) -> 0 | F113: =_xll.EQNXTDZ($A$1,$B113,F$5) -> 0 | G113: =_xll.EQNXTDZ($A$1,$B113,G$5) -> 0 | H113: =_xll.EQNXTDZ($A$1,$B113,H$5) -> 0 | I113: =_xll.EQNXTDZ($A$1,$B113,I$5) -> 0 | J113: =_xll.EQNXTDZ($A$1,$B113,J$5) -> 0 | ... AG113: =_xll.EQNXTDZ($A$1,$B113,AG$5) -> 0

Sheet QTR Share Price
A1: ='QTR Raw'!A1 -> 105790 | C1: 201206 | D1: 201207 | E1: 201208 | F1: 201209 | G1: 201210 | H1: 201211 | I1: 201212 | J1: 201301 | K1: 201302 | L1: 201303 | M1: 201304 | N1: 201305 | O1: 201306 | P1: 201307 | Q1: 201308 | R1: 201309 | S1: 201310 | T1: 201311 | U1: 201312 | V1: 201401 | W1: 201402 | X1: 201403 | Y1: 201404 | Z1: 201405 | AA1: 201406 | AB1: 201407 | AC1: 201408 | AD1: 201409 | AE1: 201410 | AF1: 201411 | AG1: 201412 | AH1: 201501 | AI1: 201502 | AJ1: 201503 | AK1: 201504 | AL1: 201505 | AM1: 201506 | AN1: 201507 | AO1: 201508 | AP1: 201509 | AQ1: 201510 | AR1: 201511 | AS1: 201512 | AT1: 201601 | AU1: 201602 | AV1: 201603 | AW1: 201604 | AX1: 201605 | AY1: 201606 | AZ1: 201607 | BA1: 201608 | BB1: 201609 | BC1: 201610 | BD1: 201611 | BE1: 201612 | BF1: 201701 | BG1: 201702 | BH1: 201703 | BI1: 201704 | BJ1: 201705 | BK1: 201706 | BL1: 201707 | BM1: 201708 | BN1: 201709 | BO1: 201710 | BP1: 201711 | BQ1: 201712 | BR1: 201801 | BS1: 201802 | BT1: 201803 | BU1: 201804 | BV1: 201805 | BW1: 201806 | BX1: 201807 | BY1: 201808 | BZ1: 201809 | CA1: 201810 | CB1: 201811 | CC1: 201812 | CD1: 201901 | CE1: 201902 | CF1: 201903 | CG1: 201904 | CH1: 201905 | CI1: 201906 | CJ1: 201907 | CK1: 201908 | CL1: 201909 | CM1: 201910 | CN1: 201911 | CO1: 201912 | CP1: 202001 | CQ1: 202002 | CR1: 202003 | CS1: 202004 | CT1: 202005 | CU1: 202006 | CV1: 202007 | CW1: 202008 | CX1: 202009 | CY1: 202010 | CZ1: 202011 | DA1: 202012 | DB1: 202101 | DC1: 202102 | DD1: 202103 | DE1: 202104 | DF1: 202105 | DG1: 202106 | DH1: 202107 | DI1: 202108 | DJ1: 202109 | DK1: 202110 | DL1: 202111 | DM1: 202112 | DN1: 202201 | DO1: 202202 | DP1: 202203 | DQ1: 202204 | DR1: 202205 | DS1: 202206 | DT1: 202207 | DU1: 202208 | DV1: 202209 | DW1: 202210 | DX1: 202211 | DY1: 202212 | DZ1: 202301 | EA1: 202302 | EB1: 202303 | EC1: 202304 | ED1: 202305 | EE1: 202306 | EF1: 202307 | EG1: 202308 | EH1: 202309 | EI1: 202310 | EJ1: 202311 | EK1: 202312 | EL1: 202401 | EM1: 202402 | EN1: 202403 | EO1: 202404 | EP1: 202405 | EQ1: 202406 | ER1: 202407 | ES1: 202408 | ET1: 202409 | EU1: 202410 | EV1: 202411 | EW1: 202412 | EX1: 202501 | EY1: 202502 | EZ1: 202503 | FA1: 202504 | FB1: 202505 | FC1: 202506 | FD1: 202507 | FE1: 202508 | FF1: 202509 | FG1: 202510 | FH1: 202511 | FI1: 202512 | FJ1: 202601 | FK1: 202602 | FL1: 202603 | FM1: 202604 | FN1: 202605 | FO1: 202606 | FP1: 202607 | FQ1: 202608 | FR1: 202609 | FS1: 202610 | FT1: 202611 | FU1: 202612 | FV1: 202701 | FW1: 202702 | FX1: 202703 | FY1: 202704 | FZ1: 202705 | GA1: 202706 | GB1: 202707 | GC1: 202708 | GD1: 202709 | GE1: 202710 | GF1: 202711 | GG1: 202712 | GH1: 202801 | GI1: 202802 | GJ1: 202803 | GK1: 202804 | GL1: 202805 | GM1: 202806 | GN1: 202807 | GO1: 202808 | GP1: 202809 | GQ1: 202810 | GR1: 202811 | GS1: 202812 | GT1: 202901 | GU1: 202902 | GV1: 202903 | GW1: 202904 | GX1: 202905 | GY1: 202906 | GZ1: 202907 | HA1: 202908 | HB1: 202909 | HC1: 202910 | HD1: 202911 | HE1: 202912 | HF1: 203001 | HG1: 203002 | HH1: 203003 | HM1: 201206 | HN1: 201207 | HO1: 201208 | HP1: 201209 | HQ1: 201212 | HR1: 201303 | HS1: 201306 | HT1: 201309 | HU1: 201312 | HV1: 201403 | HW1: 201406 | HX1: 201409 | HY1: 201412 | HZ1: 201503 | IA1: 201506 | IB1: 201509 | IC1: 201512 | ID1: 201603 | IE1: 201606 | IF1: 201609 | IG1: 201612 | IH1: 201703 | II1: 201706 | IJ1: 201709 | IK1: 201712 | IL1: 201803 | IM1: 201806 | IN1: 201809 | IO1: 201812 | IP1: 201903 | IQ1: 201906 | IR1: 201909 | IS1: 201912 | IT1: 202003 | IU1: 202006 | IV1: 202009 | IW1: 202012 | IX1: 202103 | IY1: 202106 | IZ1: 202109 | JA1: 202112 | JB1: 202203 | JC1: 202206 | JD1: 202209 | JE1: 202212 | JF1: 202303 | JG1: 202306 | JH1: 202309 | JI1: 202312 | JJ1: 202403 | JK1: 202406 | JL1: 202409 | JM1: 202412 | JN1: 202503 | JO1: 202506 | JP1: 202509 | JQ1: 202512 | JR1: 202603 | JS1: 202606 | JT1: 202609 | JU1: 202612 | JV1: 202703 | JW1: 202706 | JX1: 202709 | JY1: 202712 | JZ1: 202803 | KA1: 202806 | KB1: 202809 | KC1: 202812 | KD1: 202903 | KE1: 202906 | KF1: 202909 | KG1: 202912 | KH1: 203003
A4: Field Description | B4: Field Name
A5: MonthEnd | B5: NMONTH_MONTHEND | C5: {=_xll.EQNXTDZ($A$1,$B5,C$1)} -> 201206 | D5: {=_xll.EQNXTDZ($A$1,$B5,D$1)} -> 201207 | E5: {=_xll.EQNXTDZ($A$1,$B5,E$1)} -> 201208 | F5: {=_xll.EQNXTDZ($A$1,$B5,F$1)} -> 201209 | G5: {=_xll.EQNXTDZ($A$1,$B5,G$1)} -> 201210 | H5: {=_xll.EQNXTDZ($A$1,$B5,H$1)} -> 201211 | I5: {=_xll.EQNXTDZ($A$1,$B5,I$1)} -> 201212 | J5: {=_xll.EQNXTDZ($A$1,$B5,J$1)} -> 201301 | ... HH5: {=_xll.EQNXTDZ($A$1,$B5,HH$1)} -> 0
A6: Open | B6: NMONTH_OPEN | C6: {=_xll.EQNXTDZ($A$1,$B6,C$1)} -> 298.01 | D6: {=_xll.EQNXTDZ($A$1,$B6,D$1)} -> 289.8 | E6: {=_xll.EQNXTDZ($A$1,$B6,E$1)} -> 288.61 | F6: {=_xll.EQNXTDZ($A$1,$B6,F$1)} -> 322.8 | G6: {=_xll.EQNXTDZ($A$1,$B6,G$1)} -> 354.84 | H6: {=_xll.EQNXTDZ($A$1,$B6,H$1)} -> 348 | I6: {=_xll.EQNXTDZ($A$1,$B6,I$1)} -> 338 | J6: {=_xll.EQNXTDZ($A$1,$B6,J$1)} -> 339.8 | ... HH6: {=_xll.EQNXTDZ($A$1,$B6,HH$1)} -> 0
A7: High | B7: NMONTH_HIGH | C7: {=_xll.EQNXTDZ($A$1,$B7,C$1)} -> 317.4 | D7: {=_xll.EQNXTDZ($A$1,$B7,D$1)} -> 310.8 | E7: {=_xll.EQNXTDZ($A$1,$B7,E$1)} -> 325.2 | F7: {=_xll.EQNXTDZ($A$1,$B7,F$1)} -> 359.97 | G7: {=_xll.EQNXTDZ($A$1,$B7,G$1)} -> 369.99 | H7: {=_xll.EQNXTDZ($A$1,$B7,H$1)} -> 353.8 | I7: {=_xll.EQNXTDZ($A$1,$B7,I$1)} -> 370.92 | J7: {=_xll.EQNXTDZ($A$1,$B7,J$1)} -> 340 | ... HH7: {=_xll.EQNXTDZ($A$1,$B7,HH$1)} -> 0 | HP7: =+MAX(D7:F7) -> 359.97 | HQ7: =+MAX(G7:I7) -> 370.92 | HR7: =+MAX(J7:L7) -> 340 | HS7: =+MAX(M7:O7) -> 305.98 | HT7: =+MAX(P7:R7) -> 318.99 | HU7: =+MAX(S7:U7) -> 332 | HV7: =+MAX(V7:X7) -> 380 | HW7: =+MAX(Y7:AA7) -> 517.8 | HX7: =+MAX(AB7:AD7) -> 603 | HY7: =+MAX(AE7:AG7) -> 766 | HZ7: =+MAX(AH7:AJ7) -> 890 | IA7: =+MAX(AK7:AM7) -> 919.8 | IB7: =+MAX(AN7:AP7) -> 984 | IC7: =+MAX(AQ7:AS7) -> 883 | ID7: =+MAX(AT7:AV7) -> 880.4 | IE7: =+MAX(AW7:AY7) -> 859.99 | IF7: =+MAX(AZ7:BB7) -> 854.8 | IG7: =+MAX(BC7:BE7) -> 895.8 | IH7: =+MAX(BF7:BH7) -> 930 | II7: =+MAX(BI7:BK7) -> 996.78 | IJ7: =+MAX(BL7:BN7) -> 1033.4 | IK7: =+MAX(BO7:BQ7) -> 1197.74 | IL7: =+MAX(BR7:BT7) -> 1187.56 | IM7: =+MAX(BU7:BW7) -> 1124.05 | IN7: =+MAX(BX7:BZ7) -> 1150 | IO7: =+MAX(CA7:CC7) -> 1144 | IP7: =+MAX(CD7:CF7) -> 1159.6 | IQ7: =+MAX(CG7:CI7) -> 1120 | IR7: =+MAX(CJ7:CL7) -> 980 | IS7: =+MAX(CM7:CO7) -> 952.43 | IT7: =+MAX(CP7:CR7) -> 991.97 | IU7: =+MAX(CS7:CU7) -> 760 | IV7: =+MAX(CV7:CX7) -> 847.8 | IW7: =+MAX(CY7:DA7) -> 950 | IX7: =+MAX(DB7:DD7) -> 1097.53 | IY7: =+MAX(DE7:DG7) -> 1149.59 | IZ7: =+MAX(DH7:DJ7) -> 1530 | JA7: =+MAX(DK7:DM7) -> 1765.59 | JB7: =+MAX(DN7:DP7) -> 2000 | JC7: =+MAX(DQ7:DS7) -> 2488 | JD7: =+MAX(DT7:DV7) -> 3969.85 | JE7: =+MAX(DW7:DY7) -> 3419.95 | JF7: =+MAX(DZ7:EB7) -> 3137.85 | JG7: =+MAX(EC7:EE7) -> 3294.05 | JH7: =+MAX(EF7:EH7) -> 3726.05 | JI7: =+MAX(EI7:EK7) -> 3335 | JJ7: =+MAX(EL7:EN7) -> 3434 | JK7: =MAX(EO7:EQ7) -> 4951 | JL7: =MAX(ER7:ET7) -> 4747 | JM7: =MAX(EU7:EW7) -> 4083.05 | JN7: =MAX(EX7:EZ7) -> 3736.95 | JO7: =MAX(FA7:FC7) -> 4364.8 | JP7: =MAX(FD7:FF7) -> 4374.9 | JQ7: =MAX(FG7:FI7) -> 4392 | JR7: =MAX(FJ7:FL7) -> 4467.7 | JS7: =MAX(FM7:FO7) -> 4445 | JT7: =MAX(FP7:FR7) -> 0 | JU7: =MAX(FS7:FU7) -> 0 | JV7: =MAX(FV7:FX7) -> 0 | JW7: =MAX(FY7:GA7) -> 0 | JX7: =MAX(GB7:GD7) -> 0 | JY7: =MAX(GE7:GG7) -> 0 | JZ7: =MAX(GH7:GJ7) -> 0 | KA7: =MAX(GK7:GM7) -> 0 | KB7: =MAX(GN7:GP7) -> 0 | KC7: =MAX(GQ7:GS7) -> 0 | KD7: =MAX(GT7:GV7) -> 0 | KE7: =MAX(GW7:GY7) -> 0 | KF7: =MAX(GZ7:HB7) -> 0 | KG7: =MAX(HC7:HE7) -> 0 | KH7: =MAX(HF7:HH7) -> 0
A8: Low | B8: NMONTH_LOW | C8: {=_xll.EQNXTDZ($A$1,$B8,C$1)} -> 284.2 | D8: {=_xll.EQNXTDZ($A$1,$B8,D$1)} -> 284.4 | E8: {=_xll.EQNXTDZ($A$1,$B8,E$1)} -> 288.61 | F8: {=_xll.EQNXTDZ($A$1,$B8,F$1)} -> 300.02 | G8: {=_xll.EQNXTDZ($A$1,$B8,G$1)} -> 333 | H8: {=_xll.EQNXTDZ($A$1,$B8,H$1)} -> 327.03 | I8: {=_xll.EQNXTDZ($A$1,$B8,I$1)} -> 333.83 | J8: {=_xll.EQNXTDZ($A$1,$B8,J$1)} -> 304 | ... HH8: {=_xll.EQNXTDZ($A$1,$B8,HH$1)} -> 0 | HP8: =+MIN(D8:F8) -> 284.4 | HQ8: =+MIN(G8:I8) -> 327.03 | HR8: =+MIN(J8:L8) -> 268.32 | HS8: =+MIN(M8:O8) -> 253.9 | HT8: =+MIN(P8:R8) -> 216 | HU8: =+MIN(S8:U8) -> 246.01 | HV8: =+MIN(V8:X8) -> 301 | HW8: =+MIN(Y8:AA8) -> 366 | HX8: =+MIN(AB8:AD8) -> 496 | HY8: =+MIN(AE8:AG8) -> 541.32 | HZ8: =+MIN(AH8:AJ8) -> 678 | IA8: =+MIN(AK8:AM8) -> 771.44 | IB8: =+MIN(AN8:AP8) -> 800 | IC8: =+MIN(AQ8:AS8) -> 750 | ID8: =+MIN(AT8:AV8) -> 740 | IE8: =+MIN(AW8:AY8) -> 752.68 | IF8: =+MIN(AZ8:BB8) -> 788.8 | IG8: =+MIN(BC8:BE8) -> 755.03 | IH8: =+MIN(BF8:BH8) -> 754.74 | II8: =+MIN(BI8:BK8) -> 880 | IJ8: =+MIN(BL8:BN8) -> 825.61 | IK8: =+MIN(BO8:BQ8) -> 952.23 | IL8: =+MIN(BR8:BT8) -> 1024.2 | IM8: =+MIN(BU8:BW8) -> 1041.06 | IN8: =+MIN(BX8:BZ8) -> 1025.66 | IO8: =+MIN(CA8:CC8) -> 921.11 | IP8: =+MIN(CD8:CF8) -> 1026 | IQ8: =+MIN(CG8:CI8) -> 936.41 | IR8: =+MIN(CJ8:CL8) -> 767.1 | IS8: =+MIN(CM8:CO8) -> 791.6 | IT8: =+MIN(CP8:CR8) -> 662.3 | IU8: =+MIN(CS8:CU8) -> 605.05 | IV8: =+MIN(CV8:CX8) -> 685.1 | IW8: =+MIN(CY8:DA8) -> 688.66 | IX8: =+MIN(DB8:DD8) -> 851.59 | IY8: =+MIN(DE8:DG8) -> 965.2 | IZ8: =+MIN(DH8:DJ8) -> 1063.06 | JA8: =+MIN(DK8:DM8) -> 1415 | JB8: =+MIN(DN8:DP8) -> 1598 | JC8: =+MIN(DQ8:DS8) -> 1915 | JD8: =+MIN(DT8:DV8) -> 2245.35 | JE8: =+MIN(DW8:DY8) -> 2601.15 | JF8: =+MIN(DZ8:EB8) -> 2555.55 | JG8: =+MIN(EC8:EE8) -> 2685 | JH8: =+MIN(EF8:EH8) -> 2912.55 | JI8: =+MIN(EI8:EK8) -> 2612.2 | JJ8: =+MIN(EL8:EN8) -> 2743.5 | JK8: =MIN(EO8:EQ8) -> 2823.35 | JL8: =MIN(ER8:ET8) -> 3752.8 | JM8: =MIN(EU8:EW8) -> 3256.7 | JN8: =MIN(EX8:EZ8) -> 2832.05 | JO8: =MIN(FA8:FC8) -> 2823 | JP8: =MIN(FD8:FF8) -> 3750.5 | JQ8: =MIN(FG8:FI8) -> 3704 | JR8: =MIN(FJ8:FL8) -> 3518.4 | JS8: =MIN(FM8:FO8) -> 3690.8 | JT8: =MIN(FP8:FR8) -> 0 | JU8: =MIN(FS8:FU8) -> 0 | JV8: =MIN(FV8:FX8) -> 0 | JW8: =MIN(FY8:GA8) -> 0 | JX8: =MIN(GB8:GD8) -> 0 | JY8: =MIN(GE8:GG8) -> 0 | JZ8: =MIN(GH8:GJ8) -> 0 | KA8: =MIN(GK8:GM8) -> 0 | KB8: =MIN(GN8:GP8) -> 0 | KC8: =MIN(GQ8:GS8) -> 0 | KD8: =MIN(GT8:GV8) -> 0 | KE8: =MIN(GW8:GY8) -> 0 | KF8: =MIN(GZ8:HB8) -> 0 | KG8: =MIN(HC8:HE8) -> 0 | KH8: =MIN(HF8:HH8) -> 0
A9: Close | B9: NMONTH_CLOSE | C9: {=_xll.EQNXTDZ($A$1,$B9,C$1)} -> 287.67 | D9: {=_xll.EQNXTDZ($A$1,$B9,D$1)} -> 290.16 | E9: {=_xll.EQNXTDZ($A$1,$B9,E$1)} -> 319.61 | F9: {=_xll.EQNXTDZ($A$1,$B9,F$1)} -> 354.85 | G9: {=_xll.EQNXTDZ($A$1,$B9,G$1)} -> 346.48 | H9: {=_xll.EQNXTDZ($A$1,$B9,H$1)} -> 337.48 | I9: {=_xll.EQNXTDZ($A$1,$B9,I$1)} -> 339.99 | J9: {=_xll.EQNXTDZ($A$1,$B9,J$1)} -> 306.94 | ... HH9: {=_xll.EQNXTDZ($A$1,$B9,HH$1)} -> 0 | HP9: =+F9 -> 354.85 | HQ9: =+I9 -> 339.99 | HR9: =+L9 -> 294.02 | HS9: =+O9 -> 285.01 | HT9: =+R9 -> 250.92 | HU9: =+U9 -> 326.65 | HV9: =+X9 -> 375.92 | HW9: =+AA9 -> 499.93 | HX9: =+AD9 -> 580.22 | HY9: =+AG9 -> 716.23 | HZ9: =+AJ9 -> 834.65 | IA9: =+AM9 -> 823.72 | IB9: =+AP9 -> 806.99 | IC9: =+AS9 -> 880.26 | ID9: =+AV9 -> 759.56 | IE9: =+AY9 -> 824.88 | IF9: =+BB9 -> 818.27 | IG9: =+BE9 -> 772.31 | IH9: =+BH9 -> 915.81 | II9: =+BK9 -> 889.61 | IJ9: =+BN9 -> 977.99 | IK9: =+BQ9 -> 1172.59 | IL9: =+BT9 -> 1040.23 | IM9: =+BW9 -> 1110.72 | IN9: =+BZ9 -> 1075.18 | IO9: =+CC9 -> 1139.55 | IP9: =+CF9 -> 1100.77 | IQ9: =+CI9 -> 977.63 | IR9: =+CL9 -> 874.77 | IS9: =+CO9 -> 940.35 | IT9: =+CR9 -> 743.33 | IU9: =+CU9 -> 713.44 | IV9: =+CX9 -> 708.26 | IW9: =+DA9 -> 907.25 | IX9: =+DD9 -> 1088.41 | IY9: =+DG9 -> 1126.88 | IZ9: =+DJ9 -> 1511.71 | JA9: =+DM9 -> 1756.88 | JB9: =+DP9 -> 1942 | JC9: =+DS9 -> 2290.5 | JD9: =+DV9 -> 3212.35 | JE9: =+DY9 -> 2746.65 | JF9: =+EB9 -> 2867.55 | JG9: =+EE9 -> 3097.55 | JH9: =+EH9 -> 3314.9 | JI9: =+EK9 -> 3203 | JJ9: =+EN9 -> 2811.35 | JK9: =EQ9 -> 4740.5 | JL9: =ET9 -> 3913.7 | JM9: =EW9 -> 3405.8 | JN9: =EZ9 -> 3376.4 | JO9: =FC9 -> 4047.3 | JP9: =FF9 -> 4208.8 | JQ9: =FI9 -> 3879 | JR9: =FL9 -> 3844.8 | JS9: =FO9 -> 4163 | JT9: =FR9 -> 0 | JU9: =FU9 -> 0 | JV9: =FX9 -> 0 | JW9: =GA9 -> 0 | JX9: =GD9 -> 0 | JY9: =GG9 -> 0 | JZ9: =GJ9 -> 0 | KA9: =GM9 -> 0 | KB9: =GP9 -> 0 | KC9: =GS9 -> 0 | KD9: =GV9 -> 0 | KE9: =GY9 -> 0 | KF9: =HB9 -> 0 | KG9: =HE9 -> 0 | KH9: =HH9 -> 0
A11: Field Description | B11: Field Name | C11: {=_xll.EQNXTDZ($A$1,$B11,C$1)} -> 0 | D11: {=_xll.EQNXTDZ($A$1,$B11,D$1)} -> 0 | E11: {=_xll.EQNXTDZ($A$1,$B11,E$1)} -> 0 | F11: {=_xll.EQNXTDZ($A$1,$B11,F$1)} -> 0 | G11: {=_xll.EQNXTDZ($A$1,$B11,G$1)} -> 0 | H11: {=_xll.EQNXTDZ($A$1,$B11,H$1)} -> 0 | I11: {=_xll.EQNXTDZ($A$1,$B11,I$1)} -> 0 | J11: {=_xll.EQNXTDZ($A$1,$B11,J$1)} -> 0 | ... HH11: {=_xll.EQNXTDZ($A$1,$B11,HH$1)} -> 0
A12: Month End | B12: BMONTH_MONTHEND | C12: {=_xll.EQNXTDZ($A$1,$B12,C$1)} -> 201206 | D12: {=_xll.EQNXTDZ($A$1,$B12,D$1)} -> 201207 | E12: {=_xll.EQNXTDZ($A$1,$B12,E$1)} -> 201208 | F12: {=_xll.EQNXTDZ($A$1,$B12,F$1)} -> 201209 | G12: {=_xll.EQNXTDZ($A$1,$B12,G$1)} -> 201210 | H12: {=_xll.EQNXTDZ($A$1,$B12,H$1)} -> 201211 | I12: {=_xll.EQNXTDZ($A$1,$B12,I$1)} -> 201212 | J12: {=_xll.EQNXTDZ($A$1,$B12,J$1)} -> 201301 | ... HH12: {=_xll.EQNXTDZ($A$1,$B12,HH$1)} -> 0
A13: Open | B13: BMONTH_OPEN | C13: {=_xll.EQNXTDZ($A$1,$B13,C$1)} -> 305 | D13: {=_xll.EQNXTDZ($A$1,$B13,D$1)} -> 290 | E13: {=_xll.EQNXTDZ($A$1,$B13,E$1)} -> 295.97 | F13: {=_xll.EQNXTDZ($A$1,$B13,F$1)} -> 326 | G13: {=_xll.EQNXTDZ($A$1,$B13,G$1)} -> 358.99 | H13: {=_xll.EQNXTDZ($A$1,$B13,H$1)} -> 346 | I13: {=_xll.EQNXTDZ($A$1,$B13,I$1)} -> 340 | J13: {=_xll.EQNXTDZ($A$1,$B13,J$1)} -> 339.94 | ... HH13: {=_xll.EQNXTDZ($A$1,$B13,HH$1)} -> 0
A14: High | B14: BMONTH_HIGH | C14: {=_xll.EQNXTDZ($A$1,$B14,C$1)} -> 350 | D14: {=_xll.EQNXTDZ($A$1,$B14,D$1)} -> 311.79 | E14: {=_xll.EQNXTDZ($A$1,$B14,E$1)} -> 326 | F14: {=_xll.EQNXTDZ($A$1,$B14,F$1)} -> 360 | G14: {=_xll.EQNXTDZ($A$1,$B14,G$1)} -> 365.37 | H14: {=_xll.EQNXTDZ($A$1,$B14,H$1)} -> 353.93 | I14: {=_xll.EQNXTDZ($A$1,$B14,I$1)} -> 353.69 | J14: {=_xll.EQNXTDZ($A$1,$B14,J$1)} -> 340 | ... HH14: {=_xll.EQNXTDZ($A$1,$B14,HH$1)} -> 0 | HP14: =+MAX(D14:F14) -> 360 | HQ14: =+MAX(G14:I14) -> 365.37 | HR14: =+MAX(J14:L14) -> 340 | HS14: =+MAX(M14:O14) -> 308 | HT14: =+MAX(P14:R14) -> 293.8 | HU14: =+MAX(S14:U14) -> 329.79 | HV14: =+MAX(V14:X14) -> 383 | HW14: =+MAX(Y14:AA14) -> 522 | HX14: =+MAX(AB14:AD14) -> 607.84 | HY14: =+MAX(AE14:AG14) -> 765 | HZ14: =+MAX(AH14:AJ14) -> 886.21 | IA14: =+MAX(AK14:AM14) -> 916 | IB14: =+MAX(AN14:AP14) -> 978 | IC14: =+MAX(AQ14:AS14) -> 879.99 | ID14: =+MAX(AT14:AV14) -> 887.6 | IE14: =+MAX(AW14:AY14) -> 862.97 | IF14: =+MAX(AZ14:BB14) -> 852 | IG14: =+MAX(BC14:BE14) -> 999.6 | IH14: =+MAX(BF14:BH14) -> 929.2 | II14: =+MAX(BI14:BK14) -> 994.67 | IJ14: =+MAX(BL14:BN14) -> 1029.8 | IK14: =+MAX(BO14:BQ14) -> 1192 | IL14: =+MAX(BR14:BT14) -> 1183.41 | IM14: =+MAX(BU14:BW14) -> 1130 | IN14: =+MAX(BX14:BZ14) -> 1159.99 | IO14: =+MAX(CA14:CC14) -> 1144.84 | IP14: =+MAX(CD14:CF14) -> 1167.26 | IQ14: =+MAX(CG14:CI14) -> 1139.99 | IR14: =+MAX(CJ14:CL14) -> 980 | IS14: =+MAX(CM14:CO14) -> 950 | IT14: =+MAX(CP14:CR14) -> 990 | IU14: =+MAX(CS14:CU14) -> 752 | IV14: =+MAX(CV14:CX14) -> 851 | IW14: =+MAX(CY14:DA14) -> 949.31 | IX14: =+MAX(DB14:DD14) -> 1099.99 | IY14: =+MAX(DE14:DG14) -> 1149 | IZ14: =+MAX(DH14:DJ14) -> 1536.76 | JA14: =+MAX(DK14:DM14) -> 1773.99 | JB14: =+MAX(DN14:DP14) -> 1965.4 | JC14: =+MAX(DQ14:DS14) -> 2489.4 | JD14: =+MAX(DT14:DV14) -> 3968.75 | JE14: =+MAX(DW14:DY14) -> 3420 | JF14: =+MAX(DZ14:EB14) -> 3135.5 | JG14: =+MAX(EC14:EE14) -> 3293.5 | JH14: =+MAX(EF14:EH14) -> 3719.2 | JI14: =+MAX(EI14:EK14) -> 3335.7 | JJ14: =+MAX(EL14:EN14) -> 3433.85 | JK14: =MAX(EO14:EQ14) -> 4950 | JL14: =MAX(ER14:ET14) -> 4794.9 | JM14: =MAX(EU14:EW14) -> 4079.95 | JN14: =MAX(EX14:EZ14) -> 3737.3 | JO14: =MAX(FA14:FC14) -> 4360.7 | JP14: =MAX(FD14:FF14) -> 4372.7 | JQ14: =MAX(FG14:FI14) -> 4392.85 | JR14: =MAX(FJ14:FL14) -> 4465 | JS14: =MAX(FM14:FO14) -> 4444.4 | JT14: =MAX(FP14:FR14) -> 0 | JU14: =MAX(FS14:FU14) -> 0 | JV14: =MAX(FV14:FX14) -> 0 | JW14: =MAX(FY14:GA14) -> 0 | JX14: =MAX(GB14:GD14) -> 0 | JY14: =MAX(GE14:GG14) -> 0 | JZ14: =MAX(GH14:GJ14) -> 0 | KA14: =MAX(GK14:GM14) -> 0 | KB14: =MAX(GN14:GP14) -> 0 | KC14: =MAX(GQ14:GS14) -> 0 | KD14: =MAX(GT14:GV14) -> 0 | KE14: =MAX(GW14:GY14) -> 0 | KF14: =MAX(GZ14:HB14) -> 0 | KG14: =MAX(HC14:HE14) -> 0 | KH14: =MAX(HF14:HH14) -> 0
A15: Low | B15: BMONTH_LOW | C15: {=_xll.EQNXTDZ($A$1,$B15,C$1)} -> 286 | D15: {=_xll.EQNXTDZ($A$1,$B15,D$1)} -> 283 | E15: {=_xll.EQNXTDZ($A$1,$B15,E$1)} -> 292.01 | F15: {=_xll.EQNXTDZ($A$1,$B15,F$1)} -> 300.4 | G15: {=_xll.EQNXTDZ($A$1,$B15,G$1)} -> 334 | H15: {=_xll.EQNXTDZ($A$1,$B15,H$1)} -> 329.03 | I15: {=_xll.EQNXTDZ($A$1,$B15,I$1)} -> 325 | J15: {=_xll.EQNXTDZ($A$1,$B15,J$1)} -> 302.41 | ... HH15: {=_xll.EQNXTDZ($A$1,$B15,HH$1)} -> 0 | HP15: =+MIN(D15:F15) -> 283 | HQ15: =+MIN(G15:I15) -> 325 | HR15: =+MIN(J15:L15) -> 269.8 | HS15: =+MIN(M15:O15) -> 257.94 | HT15: =+MIN(P15:R15) -> 220 | HU15: =+MIN(S15:U15) -> 250.04 | HV15: =+MIN(V15:X15) -> 293.54 | HW15: =+MIN(Y15:AA15) -> 366 | HX15: =+MIN(AB15:AD15) -> 500 | HY15: =+MIN(AE15:AG15) -> 550.05 | HZ15: =+MIN(AH15:AJ15) -> 680.98 | IA15: =+MIN(AK15:AM15) -> 776 | IB15: =+MIN(AN15:AP15) -> 802 | IC15: =+MIN(AQ15:AS15) -> 745 | ID15: =+MIN(AT15:AV15) -> 741.3 | IE15: =+MIN(AW15:AY15) -> 754 | IF15: =+MIN(AZ15:BB15) -> 793.13 | IG15: =+MIN(BC15:BE15) -> 756 | IH15: =+MIN(BF15:BH15) -> 760.52 | II15: =+MIN(BI15:BK15) -> 880 | IJ15: =+MIN(BL15:BN15) -> 827.21 | IK15: =+MIN(BO15:BQ15) -> 952 | IL15: =+MIN(BR15:BT15) -> 1030 | IM15: =+MIN(BU15:BW15) -> 1040 | IN15: =+MIN(BX15:BZ15) -> 1035.47 | IO15: =+MIN(CA15:CC15) -> 919.8 | IP15: =+MIN(CD15:CF15) -> 1028.2 | IQ15: =+MIN(CG15:CI15) -> 934.21 | IR15: =+MIN(CJ15:CL15) -> 768.2 | IS15: =+MIN(CM15:CO15) -> 793.4 | IT15: =+MIN(CP15:CR15) -> 641.2 | IU15: =+MIN(CS15:CU15) -> 608.82 | IV15: =+MIN(CV15:CX15) -> 687.4 | IW15: =+MIN(CY15:DA15) -> 690 | IX15: =+MIN(DB15:DD15) -> 852 | IY15: =+MIN(DE15:DG15) -> 964.95 | IZ15: =+MIN(DH15:DJ15) -> 1065 | JA15: =+MIN(DK15:DM15) -> 1416 | JB15: =+MIN(DN15:DP15) -> 1600 | JC15: =+MIN(DQ15:DS15) -> 1913.8 | JD15: =+MIN(DT15:DV15) -> 2241 | JE15: =+MIN(DW15:DY15) -> 2602.5 | JF15: =+MIN(DZ15:EB15) -> 2554.75 | JG15: =+MIN(EC15:EE15) -> 2685.9 | JH15: =+MIN(EF15:EH15) -> 2928.4 | JI15: =+MIN(EI15:EK15) -> 2616.05 | JJ15: =+MIN(EL15:EN15) -> 2699.55 | JK15: =MIN(EO15:EQ15) -> 2840 | JL15: =MIN(ER15:ET15) -> 3755 | JM15: =MIN(EU15:EW15) -> 3258.7 | JN15: =MIN(EX15:EZ15) -> 2836.55 | JO15: =MIN(FA15:FC15) -> 2851 | JP15: =MIN(FD15:FF15) -> 3760.85 | JQ15: =MIN(FG15:FI15) -> 3703.05 | JR15: =MIN(FJ15:FL15) -> 3519 | JS15: =MIN(FM15:FO15) -> 3686 | JT15: =MIN(FP15:FR15) -> 0 | JU15: =MIN(FS15:FU15) -> 0 | JV15: =MIN(FV15:FX15) -> 0 | JW15: =MIN(FY15:GA15) -> 0 | JX15: =MIN(GB15:GD15) -> 0 | JY15: =MIN(GE15:GG15) -> 0 | JZ15: =MIN(GH15:GJ15) -> 0 | KA15: =MIN(GK15:GM15) -> 0 | KB15: =MIN(GN15:GP15) -> 0 | KC15: =MIN(GQ15:GS15) -> 0 | KD15: =MIN(GT15:GV15) -> 0 | KE15: =MIN(GW15:GY15) -> 0 | KF15: =MIN(GZ15:HB15) -> 0 | KG15: =MIN(HC15:HE15) -> 0 | KH15: =MIN(HF15:HH15) -> 0
A16: Close | B16: BMONTH_CLOSE | C16: {=_xll.EQNXTDZ($A$1,$B16,C$1)} -> 287.61 | D16: {=_xll.EQNXTDZ($A$1,$B16,D$1)} -> 291.37 | E16: {=_xll.EQNXTDZ($A$1,$B16,E$1)} -> 318.23 | F16: {=_xll.EQNXTDZ($A$1,$B16,F$1)} -> 352.06 | G16: {=_xll.EQNXTDZ($A$1,$B16,G$1)} -> 345.67 | H16: {=_xll.EQNXTDZ($A$1,$B16,H$1)} -> 336.99 | I16: {=_xll.EQNXTDZ($A$1,$B16,I$1)} -> 339.94 | J16: {=_xll.EQNXTDZ($A$1,$B16,J$1)} -> 305.52 | ... HH16: {=_xll.EQNXTDZ($A$1,$B16,HH$1)} -> 0 | HP16: =+F16 -> 352.06 | HQ16: =+I16 -> 339.94 | HR16: =+L16 -> 293.93 | HS16: =+O16 -> 284 | HT16: =+R16 -> 249.7 | HU16: =+U16 -> 322.79 | HV16: =+X16 -> 375.5 | HW16: =+AA16 -> 497.28 | HX16: =+AD16 -> 575.97 | HY16: =+AG16 -> 714.02 | HZ16: =+AJ16 -> 828.63 | IA16: =+AM16 -> 824.52 | IB16: =+AP16 -> 806.75 | IC16: =+AS16 -> 877.42 | ID16: =+AV16 -> 764.09 | IE16: =+AY16 -> 822.08 | IF16: =+BB16 -> 816.76 | IG16: =+BE16 -> 773.14 | IH16: =+BH16 -> 911.96 | II16: =+BK16 -> 892.68 | IJ16: =+BN16 -> 979.1 | IK16: =+BQ16 -> 1168.83 | IL16: =+BT16 -> 1033.03 | IM16: =+BW16 -> 1106.28 | IN16: =+BZ16 -> 1079.03 | IO16: =+CC16 -> 1138.25 | IP16: =+CF16 -> 1101.34 | IQ16: =+CI16 -> 975.34 | IR16: =+CL16 -> 877.07 | IS16: =+CO16 -> 939.69 | IT16: =+CR16 -> 739.82 | IU16: =+CU16 -> 715.26 | IV16: =+CX16 -> 710.68 | IW16: =+DA16 -> 907.71 | IX16: =+DD16 -> 1082.14 | IY16: =+DG16 -> 1128.25 | IZ16: =+DJ16 -> 1522.08 | JA16: =+DM16 -> 1758.09 | JB16: =+DP16 -> 1950.6 | JC16: =+DS16 -> 2290.8 | JD16: =+DV16 -> 3213.3 | JE16: =+DY16 -> 2744.5 | JF16: =+EB16 -> 2873.9 | JG16: =+EE16 -> 3099.6 | JH16: =+EH16 -> 3313.95 | JI16: =+EK16 -> 3202.2 | JJ16: =+EN16 -> 2812.3 | JK16: =EQ16 -> 4738.9 | JL16: =ET16 -> 3908.55 | JM16: =EW16 -> 3405.45 | JN16: =EZ16 -> 3370.3 | JO16: =FC16 -> 4048.15 | JP16: =FF16 -> 4210.25 | JQ16: =FI16 -> 3885.25 | JR16: =FL16 -> 3844.7 | JS16: =FO16 -> 4165.75 | JT16: =FR16 -> 0 | JU16: =FU16 -> 0 | JV16: =FX16 -> 0 | JW16: =GA16 -> 0 | JX16: =GD16 -> 0 | JY16: =GG16 -> 0 | JZ16: =GJ16 -> 0 | KA16: =GM16 -> 0 | KB16: =GP16 -> 0 | KC16: =GS16 -> 0 | KD16: =GV16 -> 0 | KE16: =GY16 -> 0 | KF16: =HB16 -> 0 | KG16: =HE16 -> 0 | KH16: =HH16 -> 0
A19: High | HP19: =+IF(HP14=0,HP7,HP14) -> 360 | HQ19: =+IF(HQ14=0,HQ7,HQ14) -> 365.37 | HR19: =+IF(HR14=0,HR7,HR14) -> 340 | HS19: =+IF(HS14=0,HS7,HS14) -> 308 | HT19: =+IF(HT14=0,HT7,HT14) -> 293.8 | HU19: =+IF(HU14=0,HU7,HU14) -> 329.79 | HV19: =+IF(HV14=0,HV7,HV14) -> 383 | HW19: =+IF(HW14=0,HW7,HW14) -> 522 | ... KH19: =+IF(KH14=0,KH7,KH14) -> 0
A20: Low | HP20: =+IF(HP15=0,HP8,HP15) -> 283 | HQ20: =+IF(HQ15=0,HQ8,HQ15) -> 325 | HR20: =+IF(HR15=0,HR8,HR15) -> 269.8 | HS20: =+IF(HS15=0,HS8,HS15) -> 257.94 | HT20: =+IF(HT15=0,HT8,HT15) -> 220 | HU20: =+IF(HU15=0,HU8,HU15) -> 250.04 | HV20: =+IF(HV15=0,HV8,HV15) -> 293.54 | HW20: =+IF(HW15=0,HW8,HW15) -> 366 | ... KH20: =+IF(KH15=0,KH8,KH15) -> 0
A21: Close | HP21: =+IF(HP16=0,HP9,HP16) -> 352.06 | HQ21: =+IF(HQ16=0,HQ9,HQ16) -> 339.94 | HR21: =+IF(HR16=0,HR9,HR16) -> 293.93 | HS21: =+IF(HS16=0,HS9,HS16) -> 284 | HT21: =+IF(HT16=0,HT9,HT16) -> 249.7 | HU21: =+IF(HU16=0,HU9,HU16) -> 322.79 | HV21: =+IF(HV16=0,HV9,HV16) -> 375.5 | HW21: =+IF(HW16=0,HW9,HW16) -> 497.28 | ... KH21: =+IF(KH16=0,KH9,KH16) -> 0

Sheet QTR No. of Shares
A1: ='QTR Raw'!A1 -> 105790 | C1: 201206 | D1: 201209 | E1: 201212 | F1: 201303 | G1: 201306 | H1: 201309 | I1: 201312 | J1: 201403 | K1: 201406 | L1: 201409 | M1: 201412 | N1: 201503 | O1: 201506 | P1: 201509 | Q1: 201512 | R1: 201603 | S1: 201606 | T1: 201609 | U1: 201612 | V1: 201703 | W1: 201706 | X1: 201709 | Y1: 201712 | Z1: 201803 | AA1: 201806 | AB1: 201809 | AC1: 201812 | AD1: 201903 | AE1: 201906 | AF1: 201909 | AG1: 201912 | AH1: 202003 | AI1: 202006 | AJ1: 202009 | AK1: 202012 | AL1: 202103 | AM1: 202106 | AN1: 202109 | AO1: 202112 | AP1: 202203 | AQ1: 202206 | AR1: 202209 | AS1: 202212 | AT1: 202303 | AU1: 202306 | AV1: 202309 | AW1: 202312 | AX1: 202403 | AY1: 202406
A4: Field Description | B4: Field Name
A5: Date End | B5: SHP_DATE_END | C5: {=_xll.EQNXTDZ($A$1,$B5,C$1)} -> 201206 | D5: {=_xll.EQNXTDZ($A$1,$B5,D$1)} -> 201209 | E5: {=_xll.EQNXTDZ($A$1,$B5,E$1)} -> 201212 | F5: {=_xll.EQNXTDZ($A$1,$B5,F$1)} -> 201303 | G5: {=_xll.EQNXTDZ($A$1,$B5,G$1)} -> 201306 | H5: {=_xll.EQNXTDZ($A$1,$B5,H$1)} -> 201309 | I5: {=_xll.EQNXTDZ($A$1,$B5,I$1)} -> 201312 | J5: {=_xll.EQNXTDZ($A$1,$B5,J$1)} -> 201403 | ... AY5: {=_xll.EQNXTDZ($A$1,$B5,AY$1)} -> 202406
A6: Grand Total | B6: SHP_NSGRANDTOTAL | C6: {=_xll.EQNXTDZ($A$1,$B6,C$1)} -> 16617270 | D6: {=_xll.EQNXTDZ($A$1,$B6,D$1)} -> 16617270 | E6: {=_xll.EQNXTDZ($A$1,$B6,E$1)} -> 16617270 | F6: {=_xll.EQNXTDZ($A$1,$B6,F$1)} -> 16617270 | G6: {=_xll.EQNXTDZ($A$1,$B6,G$1)} -> 16617270 | H6: {=_xll.EQNXTDZ($A$1,$B6,H$1)} -> 16617270 | I6: {=_xll.EQNXTDZ($A$1,$B6,I$1)} -> 16617270 | J6: {=_xll.EQNXTDZ($A$1,$B6,J$1)} -> 16617270 | ... AY6: {=_xll.EQNXTDZ($A$1,$B6,AY$1)} -> 156303670
B7: In Crs. | C7: =+C6/10^7 -> 1.661727 | D7: =+D6/10^7 -> 1.661727 | E7: =+E6/10^7 -> 1.661727 | F7: =+F6/10^7 -> 1.661727 | G7: =+G6/10^7 -> 1.661727 | H7: =+H6/10^7 -> 1.661727 | I7: =+I6/10^7 -> 1.661727 | J7: =+J6/10^7 -> 1.661727 | ... AY7: =+AY6/10^7 -> 15.630367

Sheet Share price Daily
A1: =_xll.EQNXTH(B1,"[ADJC];[ADJH];[ADJL];[ADJO];[UCLS];[VOLUME]","2015-Jan-01","Y","All traded days","Asc") -> EQNXTH | B1: =+'Annual Raw'!A1 -> 105790 | L1: =_xll.EQNXTH(B1,"[NADJC];[NADJH];[NADJLOW];[NADJOPEN];[NUCLOSE];[NVOLUME]","2015-Jan-01","Y","All traded days","Asc") -> EQNXTH
A2: Schaeffler India Ltd. | L2: Schaeffler India Ltd.
A3: DATE | B3: ADJHIGH | C3: ADJCLOSE | D3: ADJLOW | E3: ADJOPEN | F3: CLOSE | G3: VOLUME | L3: DATE | M3: ADJCLOSE | N3: ADJHIGH | O3: ADJLOW | P3: ADJOPEN | Q3: CLOSE | R3: VOLUME
A4: 42005 | B4: 717.33 | C4: 708.01 | D4: 706.6 | E4: 717.32 | F4: 3540.05 | G4: 138 | L4: 42005 | M4: 706.52 | N4: 720 | O4: 702.22 | P4: 720 | Q4: 3532.6 | R4: 1483
A5: 42006 | B5: 724.99 | C5: 719.57 | D5: 713.87 | E5: 715.87 | F5: 3597.85 | G5: 135 | L5: 42006 | M5: 717.93 | N5: 720 | O5: 710.8 | P5: 710.8 | Q5: 3589.65 | R5: 1032
A6: 42009 | B6: 720.01 | C6: 712.86 | D6: 709.14 | E6: 720 | F6: 3564.3 | G6: 162 | L6: 42009 | M6: 711 | N6: 722.39 | O6: 707.34 | P6: 722.01 | Q6: 3555 | R6: 6927
A7: 42010 | B7: 712.5 | C7: 700.14 | D7: 691 | E7: 712.42 | F7: 3500.7 | G7: 277 | L7: 42010 | M7: 698.01 | N7: 715.4 | O7: 693 | P7: 710 | Q7: 3490.05 | R7: 586
A8: 42011 | B8: 710 | C8: 698.33 | D8: 690 | E8: 705.39 | F8: 3491.65 | G8: 550 | L8: 42011 | M8: 694.16 | N8: 711.6 | O8: 685.8 | P8: 693 | Q8: 3470.8 | R8: 1251
A9: 42012 | B9: 710 | C9: 696.02 | D9: 691 | E9: 704.41 | F9: 3480.1 | G9: 305 | L9: 42012 | M9: 692.8 | N9: 718.19 | O9: 687.4 | P9: 687.4 | Q9: 3464 | R9: 1190
A10: 42013 | B10: 702 | C10: 695.1 | D10: 685.03 | E10: 695 | F10: 3475.5 | G10: 200 | L10: 42013 | M10: 694.66 | N10: 701.6 | O10: 684.29 | P10: 696.03 | Q10: 3473.3 | R10: 646
A11: 42016 | B11: 697.4 | C11: 693.91 | D11: 689.32 | E11: 689.32 | F11: 3469.55 | G11: 64 | L11: 42016 | M11: 692.05 | N11: 698.8 | O11: 684.52 | P11: 687.21 | Q11: 3460.25 | R11: 3157
A12: 42017 | B12: 707.42 | C12: 684.33 | D12: 680.98 | E12: 696.49 | F12: 3421.65 | G12: 169 | L12: 42017 | M12: 684.34 | N12: 708.68 | O12: 678 | P12: 697.98 | Q12: 3421.7 | R12: 1820
A13: 42018 | B13: 704.99 | C13: 692.68 | D13: 683.56 | E13: 683.72 | F13: 3463.4 | G13: 199 | L13: 42018 | M13: 694.76 | N13: 705 | O13: 684.2 | P13: 684.2 | Q13: 3473.8 | R13: 7281
A14: 42019 | B14: 709 | C14: 705.04 | D14: 693.8 | E14: 693.8 | F14: 3525.2 | G14: 293 | L14: 42019 | M14: 705.33 | N14: 710 | O14: 699.98 | P14: 699.98 | Q14: 3526.65 | R14: 1939
A15: 42020 | B15: 708.99 | C15: 706.68 | D15: 701.57 | E15: 705.42 | F15: 3533.4 | G15: 114 | L15: 42020 | M15: 706.87 | N15: 709.98 | O15: 696.02 | P15: 698.51 | Q15: 3534.35 | R15: 2464
... A2840: 46189 | B2840: 4207.2 | C2840: 4165.75 | D2840: 4035.5 | E2840: 4050 | F2840: 4165.75 | G2840: 2656 | L2840: 46190 | M2840: 4197.1 | N2840: 4252 | O2840: 4135.9 | P2840: 4188 | Q2840: 4197.1 | R2840: 38058
A2841: 46190 | B2841: 4250 | C2841: 4193.8 | D2841: 4133.55 | E2841: 4217.75 | F2841: 4193.8 | G2841: 1631

Sheet Sheet2
J19: 219.3 | K19: 186.25 | L19: 186.75
J20: 192.9 | K20: 135.5 | L20: 146.9 | N20: 219.3 | O20: 192.9 | P20: 186 | Q20: 178.7 | R20: 207 | S20: 255.15 | T20: 348.25 | U20: 374 | V20: 495.9 | W20: 659.9 | X20: 613.4 | Y20: 607.9 | Z20: 555.95 | AA20: 497.8 | AB20: 459.9 | AC20: 374 | AD20: 362 | AE20: 341.5 | AF20: 384.2 | AG20: 433.8 | AH20: 460 | AI20: 474.4 | AJ20: 414.4 | AK20: 318.7 | AL20: 303.25 | AM20: 332.7 | AN20: 295 | AO20: 247 | AP20: 214.4 | AQ20: 179.5 | AR20: 97.9 | AS20: 119.1 | AT20: 130.65 | AU20: 148.55 | AV20: 153.8 | AW20: 152.9 | AX20: 136 | AY20: 141.15 | AZ20: 128.1 | BA20: 142.5 | BB20: 143.55 | BC20: 124.5 | BD20: 241 | BE20: 450 | BF20: 503.35
J21: 186 | K21: 145.4 | L21: 169.1 | N21: 186.25 | O21: 135.5 | P21: 145.4 | Q21: 108.95 | R21: 137 | S21: 170 | T21: 243.15 | U21: 307.5 | V21: 325.1 | W21: 463 | X21: 467.05 | Y21: 436.5 | Z21: 467 | AA21: 348.2 | AB21: 325 | AC21: 313.1 | AD21: 285 | AE21: 277.85 | AF21: 327 | AG21: 317 | AH21: 370.7 | AI21: 360 | AJ21: 271.15 | AK21: 233.15 | AL21: 218.8 | AM21: 262 | AN21: 223.6 | AO21: 137.6 | AP21: 142 | AQ21: 59.3 | AR21: 58 | AS21: 72.8 | AT21: 80 | AU21: 107.25 | AV21: 106 | AW21: 125.1 | AX21: 112.25 | AY21: 81.45 | AZ21: 88 | BA21: 90.35 | BB21: 106.05 | BC21: 98.55 | BD21: 119.25 | BE21: 210 | BF21: 349
J22: 178.7 | K22: 108.95 | L22: 139.75 | N22: 186.75 | O22: 146.9 | P22: 169.1 | Q22: 139.75 | R22: 202.15 | S22: 249.05 | T22: 346.4 | U22: 349.2 | V22: 469.9 | W22: 584.8 | X22: 536.15 | Y22: 513.35 | Z22: 474 | AA22: 438.55 | AB22: 355.4 | AC22: 334.95 | AD22: 298.8 | AE22: 328.35 | AF22: 343 | AG22: 389.9 | AH22: 443.05 | AI22: 407.5 | AJ22: 290.1 | AK22: 235.75 | AL22: 292.65 | AM22: 276.1 | AN22: 237.05 | AO22: 190.1 | AP22: 147.2 | AQ22: 71.9 | AR22: 75.2 | AS22: 90.1 | AT22: 117.2 | AU22: 116.3 | AV22: 140.5 | AW22: 128.6 | AX22: 133.65 | AY22: 91.65 | AZ22: 97.65 | BA22: 125 | BB22: 115.35 | BC22: 119.25 | BD22: 219.3 | BE22: 442.65 | BF22: 503.35
J23: 207 | K23: 137 | L23: 202.15
J24: 255.15 | K24: 170 | L24: 249.05
J25: 348.25 | K25: 243.15 | L25: 346.4
J26: 374 | K26: 307.5 | L26: 349.2
J27: 495.9 | K27: 325.1 | L27: 469.9
J28: 659.9 | K28: 463 | L28: 584.8
J29: 613.4 | K29: 467.05 | L29: 536.15
J30: 607.9 | K30: 436.5 | L30: 513.35
J31: 555.95 | K31: 467 | L31: 474
J32: 497.8 | K32: 348.2 | L32: 438.55
J33: 459.9 | K33: 325 | L33: 355.4
J34: 374 | K34: 313.1 | L34: 334.95
... J63: 503.35 | K63: 349 | L63: 503.35
