Workbook

Sheet Template
A1: =+'Annual Raw'!C4 -> Siemens Energy India Ltd. | B1: 37135 | C1: =EOMONTH(B1,12) -> 37529 | D1: =EOMONTH(C1,12) -> 37894 | E1: =EOMONTH(D1,12) -> 38260 | F1: =EOMONTH(E1,12) -> 38625 | G1: =EOMONTH(F1,12) -> 38990 | H1: =EOMONTH(G1,12) -> 39355 | I1: =EOMONTH(H1,12) -> 39721 | J1: =EOMONTH(I1,12) -> 40086 | ... AE1: =EOMONTH(AD1,12) -> 47756 | AH1: QTR | AI1: 41061 | AJ1: 41153 | AK1: 41244 | AL1: 41334 | AM1: 41426 | AN1: 41518 | AO1: 41609 | AP1: 41699 | AQ1: 41791 | AR1: 41883 | AS1: 41974 | AT1: 42064 | AU1: 42156 | AV1: 42248 | AW1: 42339 | AX1: 42430 | AY1: 42522 | AZ1: 42614 | BA1: 42705 | BB1: 42795 | BC1: 42887 | BD1: 42979 | BE1: 43070 | BF1: 43160 | BG1: 43252 | BH1: 43344 | BI1: 43435 | BJ1: 43525 | BK1: 43617 | BL1: 43709 | BM1: 43800 | BN1: 43891 | BO1: 43983 | BP1: 44075 | BQ1: =EOMONTH(BP1,3) -> 44196 | BR1: =EOMONTH(BQ1,3) -> 44286 | BS1: =EOMONTH(BR1,3) -> 44377 | BT1: =EOMONTH(BS1,3) -> 44469 | BU1: =EOMONTH(BT1,3) -> 44561 | BV1: =EOMONTH(BU1,3) -> 44651 | BW1: =EOMONTH(BV1,3) -> 44742 | BX1: =EOMONTH(BW1,3) -> 44834 | ... DD1: =EOMONTH(DC1,3) -> 47756 | DE1: HISTORICAL ESTIMATES | DF1: 45930
A2: Presentation Data (Start)
A4: Revenue Breakup
A5: Power Transmission | Z5: =+SUM(CG5:CJ5) -> 4189.6 | AA5: =SUM(CK5:CN5) -> 5436.6989 | AB5: =+SUM(CO5:CR5) -> 6481.286 | AC5: =+SUM(CS5:CV5) -> 7742.7769 | AD5: =+SUM(CW5:CZ5) -> 9212.6239 | AE5: =+SUM(DA5:DD5) -> 10953.875 | CD5: 604.9 | CE5: 720.9 | CF5: 919.7 | CG5: 839.4 | CH5: 1013.8 | CI5: 976.4 | CJ5: 1360 | CK5: 1123.7 | CL5: 1279.2 | CM5: =+CI5+(CI5*CM11) -> 1273.8594 | CN5: =+CJ5+(CJ5*CN11) -> 1759.9395 | CO5: =+CK5+(CK5*CO11) -> 1460.5864 | CP5: =+CL5+(CL5*CP11) -> 1650.2673 | CQ5: =+CM5+(CM5*CQ11) -> 1429.0557 | CR5: =+CN5+(CN5*CR11) -> 1941.3766 | CS5: =+CO5+(CO5*CS11) -> 1781.9107 | CT5: =+CP5+(CP5*CT11) -> 1977.7624 | ... DD5: =+CZ5+(CZ5*DD11) -> 3261.1551 | DF5: 1411.8837
A6: Power Generation | Z6: =+SUM(CG6:CJ6) -> 3637.1 | AA6: =SUM(CK6:CN6) -> 4598.7491 | AB6: =+SUM(CO6:CR6) -> 5415.9516 | AC6: =+SUM(CS6:CV6) -> 6228.3444 | AD6: =+SUM(CW6:CZ6) -> 7162.596 | AE6: =+SUM(DA6:DD6) -> 8236.9854 | CD6: 591.7 | CE6: 763.3 | CF6: 1159.1 | CG6: 677.5 | CH6: 865.7 | CI6: 808.2 | CJ6: 1285.7 | CK6: 787.2 | CL6: 1114.9 | CM6: =+CI6+(CI6*CM12) -> 1040.8481 | CN6: =+CJ6+(CJ6*CN12) -> 1655.801 | CO6: =+CK6+(CK6*CO12) -> 1013.803 | CP6: =+CL6+(CL6*CP12) -> 1435.8346 | CQ6: =+CM6+(CM6*CQ12) -> 1144.9329 | CR6: =+CN6+(CN6*CR12) -> 1821.3811 | CS6: =+CO6+(CO6*CS12) -> 1165.8735 | CT6: =+CP6+(CP6*CT12) -> 1651.2098 | ... DD6: =+CZ6+(CZ6*DD12) -> 2770.093 | DF6: 952.27
A7: Total | Z7: =+Z5+Z6 -> 7826.7 | AA7: =+AA5+AA6 -> 10035.448 | AB7: =+AB5+AB6 -> 11897.238 | AC7: =+AC5+AC6 -> 13971.121 | AD7: =+AD5+AD6 -> 16375.22 | AE7: =+AE5+AE6 -> 19190.86 | CD7: =+CD5+CD6 -> 1196.6 | CE7: =+CE5+CE6 -> 1484.2 | CF7: =+CF5+CF6 -> 2078.8 | CG7: =+CG5+CG6 -> 1516.9 | CH7: =+CH5+CH6 -> 1879.5 | CI7: =+CI5+CI6 -> 1784.6 | CJ7: =+CJ5+CJ6 -> 2645.7 | CK7: =+CK5+CK6 -> 1910.9 | ... DD7: =+DD5+DD6 -> 6031.2481 | DF7: 2364.1537
A8: Checksum- Revenue | Z8: =+Z7-Z34 -> 0 | AA8: =+AA7-AA34 -> 0 | AB8: =+AB7-AB34 -> 0 | AC8: =+AC7-AC34 -> 0 | AD8: =+AD7-AD34 -> 0 | AE8: =+AE7-AE34 -> 0 | CD8: =+CD7-CD34 -> 0 | CE8: =+CE7-CE34 -> 0 | CF8: =+CF7-CF34 -> 0 | CG8: =+CG7-CG34 -> 0 | CH8: =+CH7-CH34 -> 0 | CI8: =+CI7-CI34 -> 0 | CJ8: =+CJ7-CJ34 -> 0 | CK8: =+CK7-CK34 -> 0 | ... DD8: =+DD7-DD34 -> 0 | DF8: 0
A10: Revenue Growth %
A11: Power Transmission yoy% | AA11: =+AA5/Z5-1 -> 0.29766539 | AB11: =+AB5/AA5-1 -> 0.19213628 | AC11: =+AC5/AB5-1 -> 0.1946359 | AD11: =+AD5/AC5-1 -> 0.1898346 | AE11: =+AE5/AD5-1 -> 0.18900702 | CH11: =+CH5/CD5-1 -> 0.6759795 | CI11: =+CI5/CE5-1 -> 0.35441809 | CJ11: =+CJ5/CF5-1 -> 0.47874307 | CK11: =+CK5/CG5-1 -> 0.33869431 | CL11: =+CL5/CH5-1 -> 0.26178733 | CM11: =+AVERAGE(CI11:CL11)*0.85 -> 0.30464909 | CN11: =+AVERAGE(CJ11:CM11)*0.85 -> 0.29407318 | CO11: =+AVERAGE(CK11:CN11) -> 0.29980098 | CP11: =+AVERAGE(CL11:CO11) -> 0.29007765 | CQ11: =+AVERAGE(CM11:CP11)*0.41 -> 0.12183159 | CR11: =+AVERAGE(CN11:CQ11)*0.41 -> 0.1030928 | CS11: =+AVERAGE(CO11:CR11)*1.08 -> 0.21999682 | CT11: =+AVERAGE(CP11:CS11)*1.08 -> 0.19844969 | CU11: =+AVERAGE(CQ11:CT11)*1.08 -> 0.17371014 | CV11: =+AVERAGE(CR11:CU11)*1.08 -> 0.18771735 | CW11: =+AVERAGE(CS11:CV11) -> 0.1949685 | CX11: =+AVERAGE(CT11:CW11) -> 0.18871142 | CY11: =+AVERAGE(CU11:CX11) -> 0.18627685 | CZ11: =+AVERAGE(CV11:CY11) -> 0.18941853 | DA11: =+AVERAGE(CW11:CZ11) -> 0.18984383 | DB11: =+AVERAGE(CX11:DA11) -> 0.18856266 | DC11: =+AVERAGE(CY11:DB11) -> 0.18852547 | DD11: =+AVERAGE(CZ11:DC11) -> 0.18908762 | DF11: 0.39266493
A12: Power Generation yoy% | AA12: =+AA6/Z6-1 -> 0.26439996 | AB12: =+AB6/AA6-1 -> 0.17770105 | AC12: =+AC6/AB6-1 -> 0.15 | AD12: =+AD6/AC6-1 -> 0.15 | AE12: =+AE6/AD6-1 -> 0.15 | CH12: =+CH6/CD6-1 -> 0.4630725 | CI12: =+CI6/CE6-1 -> 0.058823529 | CJ12: =+CJ6/CF6-1 -> 0.10922267 | CK12: =+CK6/CG6-1 -> 0.16191882 | CL12: =+CL6/CH6-1 -> 0.28785954 | CM12: =+CL12 -> 0.28785954 | CN12: =+CM12 -> 0.28785954 | CO12: =+CN12 -> 0.28785954 | CP12: =+CO12 -> 0.28785954 | CQ12: 0.1 | CR12: =+CQ12 -> 0.1 | CS12: 0.15 | CT12: =+CS12 -> 0.15 | CU12: =+CT12 -> 0.15 | CV12: =+CU12 -> 0.15 | CW12: =+CV12 -> 0.15 | CX12: =+CW12 -> 0.15 | CY12: =+CX12 -> 0.15 | CZ12: =+CY12 -> 0.15 | DA12: =+CZ12 -> 0.15 | ... DD12: =+DC12 -> 0.15 | DF12: 0.1
A14: EBIT Breakup
A15: Power Transmission-EBIT | Z15: =+SUM(CG15:CJ15) -> 804.6 | AA15: =SUM(CK15:CN15) -> 1021.4741 | AB15: =+SUM(CO15:CR15) -> 1287.7628 | AC15: =+SUM(CS15:CV15) -> 1630.9701 | AD15: =+SUM(CW15:CZ15) -> 1949.767 | AE15: =+SUM(DA15:DD15) -> 2321.0474 | CD15: 127.4 | CE15: 73.1 | CF15: 148 | CG15: 169.9 | CH15: 205.4 | CI15: 182.5 | CJ15: 246.8 | CK15: 273.3 | CL15: 214.3 | CM15: =+CM21*CM5 -> 225.79209 | CN15: =+CN21*CN5 -> 308.08198 | CO15: =+CO21*CO5 -> 295.34027 | CP15: =+CP21*CP5 -> 315.76149 | CQ15: =+CQ21*CQ5 -> 282.45293 | CR15: =+CR21*CR5 -> 394.20809 | CS15: =+CS21*CS5 -> 367.97452 | CT15: =+CT21*CT5 -> 410.62957 | ... DD15: =+DD21*DD5 -> 691.32975 | DF15: 261.52397
A16: Power Generation -EBIT | Z16: =+SUM(CG16:CJ16) -> 605.8 | AA16: =SUM(CK16:CN16) -> 912.38146 | AB16: =+SUM(CO16:CR16) -> 1066.1027 | AC16: =+SUM(CS16:CV16) -> 1222.2307 | AD16: =+SUM(CW16:CZ16) -> 1404.7579 | AE16: =+SUM(DA16:DD16) -> 1615.3337 | CD16: 131.8 | CE16: 124.3 | CF16: 217.8 | CG16: 144.7 | CH16: 128.8 | CI16: 131.2 | CJ16: 201.1 | CK16: 155.2 | CL16: 249.3 | CM16: =+CM22*CM6 -> 192.42962 | CN16: =+CN22*CN6 -> 315.45184 | CO16: =+CO22*CO6 -> 201.78554 | CP16: =+CP22*CP6 -> 286.46212 | CQ16: =+CQ22*CQ6 -> 221.52682 | CR16: =+CR22*CR6 -> 356.32818 | CS16: =+CS22*CS6 -> 229.58035 | CT16: =+CT22*CT6 -> 324.27572 | ... DD16: =+DD22*DD6 -> 543.24977 | DF16: 158.23983
A17: Total EBIT | Z17: =+Z15+Z16 -> 1410.4 | AA17: =+AA15+AA16 -> 1933.8555 | AB17: =+AB15+AB16 -> 2353.8654 | AC17: =+AC15+AC16 -> 2853.2007 | AD17: =+AD15+AD16 -> 3354.5249 | AE17: =+AE15+AE16 -> 3936.3811 | CD17: =+CD15+CD16 -> 259.2 | CE17: =+CE15+CE16 -> 197.4 | CF17: =+CF15+CF16 -> 365.8 | CG17: =+CG15+CG16 -> 314.6 | CH17: =+CH15+CH16 -> 334.2 | CI17: =+CI15+CI16 -> 313.7 | CJ17: =+CJ15+CJ16 -> 447.9 | CK17: =+CK15+CK16 -> 428.5 | ... DD17: =+DD15+DD16 -> 1234.5795 | DF17: 419.7638
A18: Checksum -EBIT | Z18: =+Z17-Z60 -> 23.4 | AA18: =+AA17-AA60 -> 0 | AB18: =+AB17-AB60 -> 0 | AC18: =+AC17-AC60 -> 0 | AD18: =+AD17-AD60 -> 0 | AE18: =+AE17-AE60 -> 0 | CD18: =+CD17-CD60 -> 0 | CE18: =+CE17-CE60 -> 0 | CF18: =+CF17-CF60 -> 0 | CG18: =+CG17-CG60 -> 0 | CH18: =+CH17-CH60 -> 0 | CI18: =+CI17-CI60 -> 0 | CJ18: =+CJ17-CJ60 -> 0 | CK18: =+CK17-CK60 -> 0 | ... DD18: =+DD17-DD60 -> 0 | DF18: 0
A20: EBIT Margins %
A21: Power Transmission-EBIT% | Z21: =+Z15/Z5 -> 0.19204697 | AA21: =+AA15/AA5 -> 0.18788498 | AB21: =+AB15/AB5 -> 0.19868939 | AC21: =+AC15/AC5 -> 0.21064407 | AD21: =+AD15/AD5 -> 0.21164079 | AE21: =+AE15/AE5 -> 0.21189283 | CD21: =+CD15/CD5 -> 0.21061332 | CE21: =+CE15/CE5 -> 0.10140103 | CF21: =+CF15/CF5 -> 0.16092204 | CG21: =+CG15/CG5 -> 0.20240648 | CH21: =+CH15/CH5 -> 0.20260406 | CI21: =+CI15/CI5 -> 0.1869111 | CJ21: =+CJ15/CJ5 -> 0.18147059 | CK21: =+CK15/CK5 -> 0.24321438 | CL21: =+CL15/CL5 -> 0.16752658 | CM21: =+AVERAGE(CI21:CL21)*0.91 -> 0.1772504 | CN21: =+AVERAGE(CJ21:CM21)*0.91 -> 0.17505259 | CO21: =+AVERAGE(CK21:CN21)*1.06 -> 0.20220665 | CP21: =+AVERAGE(CL21:CO21)*1.06 -> 0.1913396 | CQ21: =+AVERAGE(CM21:CP21)*1.06 -> 0.19765005 | CR21: =+AVERAGE(CN21:CQ21)*1.06 -> 0.20305596 | CS21: =+AVERAGE(CO21:CR21)*1.04 -> 0.20650559 | CT21: =+AVERAGE(CP21:CS21)*1.04 -> 0.20762331 | CU21: =+AVERAGE(CQ21:CT21)*1.04 -> 0.21185707 | CV21: =+AVERAGE(CR21:CU21)*1.04 -> 0.2155509 | CW21: =+AVERAGE(CS21:CV21) -> 0.21038422 | CX21: =+AVERAGE(CT21:CW21) -> 0.21135388 | CY21: =+AVERAGE(CU21:CX21) -> 0.21228652 | CZ21: =+AVERAGE(CV21:CY21) -> 0.21239388 | DA21: =+AVERAGE(CW21:CZ21) -> 0.21160462 | DB21: =+AVERAGE(CX21:DA21) -> 0.21190972 | DC21: =+AVERAGE(CY21:DB21) -> 0.21204869 | DD21: =+AVERAGE(CZ21:DC21) -> 0.21198923 | DF21: 0.18523053
A22: Power Generation -EBIT% | Z22: =+Z16/Z6 -> 0.16656127 | AA22: =+AA16/AA6 -> 0.19839775 | AB22: =+AB16/AB6 -> 0.19684494 | AC22: =+AC16/AC6 -> 0.19623685 | AD22: =+AD16/AD6 -> 0.19612413 | AE22: =+AE16/AE6 -> 0.19610738 | CD22: =+CD16/CD6 -> 0.22274801 | CE22: =+CE16/CE6 -> 0.16284554 | CF22: =+CF16/CF6 -> 0.18790441 | CG22: =+CG16/CG6 -> 0.21357934 | CH22: =+CH16/CH6 -> 0.14878133 | CI22: =+CI16/CI6 -> 0.16233606 | CJ22: =+CJ16/CJ6 -> 0.15641285 | CK22: =+CK16/CK6 -> 0.19715447 | CL22: =+CL16/CL6 -> 0.2236075 | CM22: =+AVERAGE(CI22:CL22) -> 0.18487772 | CN22: =+AVERAGE(CJ22:CM22) -> 0.19051313 | CO22: =+AVERAGE(CK22:CN22) -> 0.19903821 | CP22: =+AVERAGE(CL22:CO22) -> 0.19950914 | CQ22: =+AVERAGE(CM22:CP22) -> 0.19348455 | CR22: =+AVERAGE(CN22:CQ22) -> 0.19563626 | CS22: =+AVERAGE(CO22:CR22) -> 0.19691704 | CT22: =+AVERAGE(CP22:CS22) -> 0.19638675 | ... DD22: =+AVERAGE(CZ22:DC22) -> 0.19611247 | DF22: 0.16617118
A25: Order Book
A26: Opening Order Book | Y26: 7720 | Z26: =+Y29 -> 11050 | AA26: =+Z29 -> 16210 | AB26: =+AA29 -> 21474.452 | AC26: =+AB29 -> 26407.104 | AD26: =+AC29 -> 30948.862 | AE26: =+AD29 -> 34937.809 | CJ26: =+CJ29+CJ28-CJ27 -> 15565.7 | CK26: =+CJ29 -> 16210 | CL26: =+CK29 -> 17599 | CM26: =+CL29 -> 19204.9 | CN26: =+CM29 -> 20890.193 | CO26: =+CN29 -> 21474.452 | CP26: =+CO29 -> 22629.953 | CQ26: =+CP29 -> 23943.851 | CR26: =+CQ29 -> 25769.862 | ... DD26: =+DC29 -> 39826.398 | DF26: 17599
A27: Addition | Y27: =+Y29+Y28-Y26 -> 8089.6 | Z27: =+Z29+Z28-Z26 -> 12986.7 | AA27: =SUM(CK27:CN27) -> 15299.9 | AB27: =+SUM(CO27:CR27) -> 16829.89 | AC27: =+SUM(CS27:CV27) -> 18512.879 | AD27: =+SUM(CW27:CZ27) -> 20364.167 | AE27: =+SUM(DA27:DD27) -> 24437 | CJ27: 3290 | CK27: =+CK29+CK28-CK26 -> 3299.9 | CL27: 4000 | CM27: =+CL27 -> 4000 | CN27: =+CM27 -> 4000 | CO27: =+CK27*110% -> 3629.89 | CP27: =+CL27*110% -> 4400 | CQ27: =+CM27*110% -> 4400 | CR27: =+CN27*110% -> 4400 | CS27: =+CO27*110% -> 3992.879 | CT27: =+CP27*110% -> 4840 | CU27: =+CQ27*110% -> 4840 | CV27: =+CR27*110% -> 4840 | ... CZ27: =+CV27*110% -> 5324 | DA27: =+CW27*120% -> 5270.6003 | DB27: =+CX27*120% -> 6388.8 | DC27: =+CY27*120% -> 6388.8 | DD27: =+CZ27*120% -> 6388.8 | DF27: 4000
A28: Execution | Y28: =+Y34 -> 4759.6 | Z28: =+Z34 -> 7826.7 | AA28: =+AA34 -> 10035.448 | AB28: =+AB34 -> 11897.238 | AC28: =+AC34 -> 13971.121 | AD28: =+AD34 -> 16375.22 | AE28: =+AE34 -> 19190.86 | CJ28: =+CJ34 -> 2645.7 | CK28: =+CK34 -> 1910.9 | CL28: =+CL7 -> 2394.1 | CM28: =+CM7 -> 2314.7075 | CN28: =+CN7 -> 3415.7405 | CO28: =+CO7 -> 2474.3894 | CP28: =+CP7 -> 3086.1019 | CQ28: =+CQ7 -> 2573.9886 | CR28: =+CR7 -> 3762.7577 | CS28: =+CS7 -> 2947.7842 | ... DD28: =+DD7 -> 6031.2481 | DF28: 2364.1537
A29: Closing Order Book | Y29: 11050 | Z29: 16210 | AA29: =+AA26+AA27-AA28 -> 21474.452 | AB29: =+AB26+AB27-AB28 -> 26407.104 | AC29: =+AC26+AC27-AC28 -> 30948.862 | AD29: =+AD26+AD27-AD28 -> 34937.809 | AE29: =+AE26+AE27-AE28 -> 40183.949 | CJ29: 16210 | CK29: 17599 | CL29: =+CL26+CL27-CL28 -> 19204.9 | CM29: =+CM26+CM27-CM28 -> 20890.193 | CN29: =+CN26+CN27-CN28 -> 21474.452 | CO29: =+CO26+CO27-CO28 -> 22629.953 | CP29: =+CP26+CP27-CP28 -> 23943.851 | CQ29: =+CQ26+CQ27-CQ28 -> 25769.862 | CR29: =+CR26+CR27-CR28 -> 26407.104 | CS29: =+CS26+CS27-CS28 -> 27452.199 | ... DD29: =+DD26+DD27-DD28 -> 40183.949 | DF29: 19234.846
A32: Presentation Data (End)
A33: Profit & Loss- Annual (Start)
A34: Gross Revenue | B34: ='Annual Raw'!C6 -> 0 | C34: ='Annual Raw'!D6 -> 0 | D34: ='Annual Raw'!E6 -> 0 | E34: ='Annual Raw'!F6 -> 0 | F34: ='Annual Raw'!G6 -> 0 | G34: ='Annual Raw'!H6 -> 0 | H34: ='Annual Raw'!I6 -> 0 | I34: ='Annual Raw'!J6 -> 0 | ... Z34: ='Annual Raw'!AA6 -> 7826.7 | AA34: =SUM(CK34:CN34) -> 10035.448 | AB34: =+SUM(CO34:CR34) -> 11897.238 | AC34: =+SUM(CS34:CV34) -> 13971.121 | AD34: =+SUM(CW34:CZ34) -> 16375.22 | AE34: =+SUM(DA34:DD34) -> 19190.86 | AI34: ='QTR Raw'!C6+'QTR Raw'!C8 -> 0 | AJ34: ='QTR Raw'!D6+'QTR Raw'!D8 -> 0 | AK34: ='QTR Raw'!E6+'QTR Raw'!E8 -> 0 | AL34: ='QTR Raw'!F6+'QTR Raw'!F8 -> 0 | AM34: ='QTR Raw'!G6+'QTR Raw'!G8 -> 0 | AN34: ='QTR Raw'!H6+'QTR Raw'!H8 -> 0 | AO34: ='QTR Raw'!I6+'QTR Raw'!I8 -> 0 | AP34: ='QTR Raw'!J6+'QTR Raw'!J8 -> 0 | ... CL34: ='QTR Raw'!BF6+'QTR Raw'!BF8 -> 2394.1 | CM34: =+CM7 -> 2314.7075 | CN34: =+CN7 -> 3415.7405 | CO34: =+CO7 -> 2474.3894 | CP34: =+CP7 -> 3086.1019 | CQ34: =+CQ7 -> 2573.9886 | CR34: =+CR7 -> 3762.7577 | CS34: =+CS7 -> 2947.7842 | CT34: =+CT7 -> 3628.9722 | ... DD34: =+DD7 -> 6031.2481 | DF34: 7826.7
A35: Less: Exise Duty | B35: ='Annual Raw'!C7+'Annual Raw'!C8+'Annual Raw'!C9 -> 0 | C35: ='Annual Raw'!D7+'Annual Raw'!D8+'Annual Raw'!D9 -> 0 | D35: ='Annual Raw'!E7+'Annual Raw'!E8+'Annual Raw'!E9 -> 0 | E35: ='Annual Raw'!F7+'Annual Raw'!F8+'Annual Raw'!F9 -> 0 | F35: ='Annual Raw'!G7+'Annual Raw'!G8+'Annual Raw'!G9 -> 0 | G35: ='Annual Raw'!H7+'Annual Raw'!H8+'Annual Raw'!H9 -> 0 | H35: ='Annual Raw'!I7+'Annual Raw'!I8+'Annual Raw'!I9 -> 0 | I35: ='Annual Raw'!J7+'Annual Raw'!J8+'Annual Raw'!J9 -> 0 | ... Z35: ='Annual Raw'!AA7+'Annual Raw'!AA8+'Annual Raw'!AA9 -> 0 | AA35: =SUM(CK35:CN35) -> 0 | AB35: =+SUM(CO35:CR35) -> 0 | AC35: =+SUM(CS35:CV35) -> 0 | AD35: =+SUM(CW35:CZ35) -> 0 | AE35: =+SUM(DA35:DD35) -> 0 | AI35: =+'QTR Raw'!C20+'QTR Raw'!C19+'QTR Raw'!C13+'QTR Raw'!C7 -> 0 | AJ35: =+'QTR Raw'!D20+'QTR Raw'!D19+'QTR Raw'!D13+'QTR Raw'!D7 -> 0 | AK35: =+'QTR Raw'!E20+'QTR Raw'!E19+'QTR Raw'!E13+'QTR Raw'!E7 -> 0 | AL35: =+'QTR Raw'!F20+'QTR Raw'!F19+'QTR Raw'!F13+'QTR Raw'!F7 -> 0 | AM35: =+'QTR Raw'!G20+'QTR Raw'!G19+'QTR Raw'!G13+'QTR Raw'!G7 -> 0 | AN35: =+'QTR Raw'!H20+'QTR Raw'!H19+'QTR Raw'!H13+'QTR Raw'!H7 -> 0 | AO35: =+'QTR Raw'!I20+'QTR Raw'!I19+'QTR Raw'!I13+'QTR Raw'!I7 -> 0 | AP35: =+'QTR Raw'!J20+'QTR Raw'!J19+'QTR Raw'!J13+'QTR Raw'!J7 -> 0 | ... CL35: =+'QTR Raw'!BF20+'QTR Raw'!BF19+'QTR Raw'!BF13+'QTR Raw'!BF7 -> 0 | DF35: 0
A36: Net Revenue | B36: =+B34-B35 -> 0 | C36: =+C34-C35 -> 0 | D36: =+D34-D35 -> 0 | E36: =+E34-E35 -> 0 | F36: =+F34-F35 -> 0 | G36: =+G34-G35 -> 0 | H36: =+H34-H35 -> 0 | I36: =+I34-I35 -> 0 | ... AE36: =+AE34-AE35 -> 19190.86 | AI36: =+AI34-AI35 -> 0 | AJ36: =+AJ34-AJ35 -> 0 | AK36: =+AK34-AK35 -> 0 | AL36: =+AL34-AL35 -> 0 | AM36: =+AM34-AM35 -> 0 | AN36: =+AN34-AN35 -> 0 | AO36: =+AO34-AO35 -> 0 | AP36: =+AP34-AP35 -> 0 | ... DD36: =+DD34-DD35 -> 6031.2481 | DF36: 7826.7
A37: Net Revenue YOY% | C37: =C36/B36-1 -> #DIV/0! | D37: =D36/C36-1 -> #DIV/0! | E37: =E36/D36-1 -> #DIV/0! | F37: =F36/E36-1 -> #DIV/0! | G37: =G36/F36-1 -> #DIV/0! | H37: =H36/G36-1 -> #DIV/0! | I37: =I36/H36-1 -> #DIV/0! | J37: =J36/I36-1 -> #DIV/0! | ... AE37: =AE36/AD36-1 -> 0.17194517 | AM37: =+IF(AI36<0,1-AM36/AI36,AM36/AI36-1) -> #DIV/0! | AN37: =+IF(AJ36<0,1-AN36/AJ36,AN36/AJ36-1) -> #DIV/0! | AO37: =+IF(AK36<0,1-AO36/AK36,AO36/AK36-1) -> #DIV/0! | AP37: =+IF(AL36<0,1-AP36/AL36,AP36/AL36-1) -> #DIV/0! | AQ37: =+IF(AM36<0,1-AQ36/AM36,AQ36/AM36-1) -> #DIV/0! | AR37: =+IF(AN36<0,1-AR36/AN36,AR36/AN36-1) -> #DIV/0! | AS37: =+IF(AO36<0,1-AS36/AO36,AS36/AO36-1) -> #DIV/0! | AT37: =+IF(AP36<0,1-AT36/AP36,AT36/AP36-1) -> #DIV/0! | ... DD37: =+IF(CZ36<0,1-DD36/CZ36,DD36/CZ36-1) -> 0.17081019 | DF37: 0.64440289
A38: Net Revenue QOQ% | AJ38: =+IF(AI36<0,1-AJ36/AI36,AJ36/AI36-1) -> #DIV/0! | AK38: =+IF(AJ36<0,1-AK36/AJ36,AK36/AJ36-1) -> #DIV/0! | AL38: =+IF(AK36<0,1-AL36/AK36,AL36/AK36-1) -> #DIV/0! | AM38: =+IF(AL36<0,1-AM36/AL36,AM36/AL36-1) -> #DIV/0! | AN38: =+IF(AM36<0,1-AN36/AM36,AN36/AM36-1) -> #DIV/0! | AO38: =+IF(AN36<0,1-AO36/AN36,AO36/AN36-1) -> #DIV/0! | AP38: =+IF(AO36<0,1-AP36/AO36,AP36/AO36-1) -> #DIV/0! | AQ38: =+IF(AP36<0,1-AQ36/AP36,AQ36/AP36-1) -> #DIV/0! | ... DD38: =+IF(DC36<0,1-DD36/DC36,DD36/DC36-1) -> 0.46883107
A39: Increase/Decrease in Stock | B39: ='Annual Raw'!C11 -> 0 | C39: ='Annual Raw'!D11 -> 0 | D39: ='Annual Raw'!E11 -> 0 | E39: ='Annual Raw'!F11 -> 0 | F39: ='Annual Raw'!G11 -> 0 | G39: ='Annual Raw'!H11 -> 0 | H39: ='Annual Raw'!I11 -> 0 | I39: ='Annual Raw'!J11 -> 0 | ... Z39: ='Annual Raw'!AA11 -> 49 | AA39: =SUM(CK39:CN39) -> -84 | AB39: =+SUM(CO39:CR39) -> 0 | AC39: =+SUM(CS39:CV39) -> 0 | AD39: =+SUM(CW39:CZ39) -> 0 | AE39: =+SUM(DA39:DD39) -> 0 | AI39: ='QTR Raw'!C10 -> 0 | AJ39: ='QTR Raw'!D10 -> 0 | AK39: ='QTR Raw'!E10 -> 0 | AL39: ='QTR Raw'!F10 -> 0 | AM39: ='QTR Raw'!G10 -> 0 | AN39: ='QTR Raw'!H10 -> 0 | AO39: ='QTR Raw'!I10 -> 0 | AP39: ='QTR Raw'!J10 -> 0 | ... CL39: ='QTR Raw'!BF10 -> -55.8 | DF39: 49
A40: Purchase of Finished Goods | B40: 0 | C40: 0 | D40: 0 | E40: 0 | F40: 0 | G40: 0 | H40: 0 | I40: 0 | J40: 0 | K40: 0 | L40: 0 | M40: 0 | N40: 0 | O40: 0 | P40: 0 | Q40: 0 | R40: 0 | S40: 0 | T40: 0 | U40: 0 | V40: 0 | W40: 0 | X40: 0 | Y40: 0 | Z40: 0 | AA40: =SUM(CK40:CN40) -> 198.9 | AB40: =+SUM(CO40:CR40) -> 0 | AC40: =+SUM(CS40:CV40) -> 0 | AD40: =+SUM(CW40:CZ40) -> 0 | AE40: =+SUM(DA40:DD40) -> 0 | AI40: ='QTR Raw'!C12 -> 0 | AJ40: ='QTR Raw'!D12 -> 0 | AK40: ='QTR Raw'!E12 -> 0 | AL40: ='QTR Raw'!F12 -> 0 | AM40: ='QTR Raw'!G12 -> 0 | AN40: ='QTR Raw'!H12 -> 0 | AO40: ='QTR Raw'!I12 -> 0 | AP40: ='QTR Raw'!J12 -> 0 | ... CL40: ='QTR Raw'!BF12 -> 81.2 | DF40: 0
A41: Raw Material Consumed | B41: ='Annual Raw'!C12 -> 0 | C41: ='Annual Raw'!D12 -> 0 | D41: ='Annual Raw'!E12 -> 0 | E41: ='Annual Raw'!F12 -> 0 | F41: ='Annual Raw'!G12 -> 0 | G41: ='Annual Raw'!H12 -> 0 | H41: ='Annual Raw'!I12 -> 0 | I41: ='Annual Raw'!J12 -> 0 | ... Z41: ='Annual Raw'!AA12 -> 2131.8 | AA41: =SUM(CK41:CN41) -> 2052.8669 | AB41: =+SUM(CO41:CR41) -> 2660.9834 | AC41: =+SUM(CS41:CV41) -> 3129.9239 | AD41: =+SUM(CW41:CZ41) -> 3669.8691 | AE41: =+SUM(DA41:DD41) -> 4301.1472 | AI41: ='QTR Raw'!C11 -> 0 | AJ41: ='QTR Raw'!D11 -> 0 | AK41: ='QTR Raw'!E11 -> 0 | AL41: ='QTR Raw'!F11 -> 0 | AM41: ='QTR Raw'!G11 -> 0 | AN41: ='QTR Raw'!H11 -> 0 | AO41: ='QTR Raw'!I11 -> 0 | AP41: ='QTR Raw'!J11 -> 0 | ... CL41: ='QTR Raw'!BF11 -> 352.5 | CM41: =+CM36-CM42 -> 555.47166 | CN41: =+CN36-CN42 -> 766.99525 | CO41: =+CO36-CO42 -> 555.68332 | CP41: =+CP36-CP42 -> 677.76433 | CQ41: =+CQ36-CQ42 -> 584.75508 | CR41: =+CR36-CR42 -> 842.78063 | CS41: =+CS36-CS42 -> 659.82484 | CT41: =+CT36-CT42 -> 811.63225 | ... DD41: =+DD36-DD42 -> 1351.7205 | DF41: 2131.8
A42: Gross Profit | B42: =B36-B39-B41-B40 -> 0 | C42: =C36-C39-C41-C40 -> 0 | D42: =D36-D39-D41-D40 -> 0 | E42: =E36-E39-E41-E40 -> 0 | F42: =F36-F39-F41-F40 -> 0 | G42: =G36-G39-G41-G40 -> 0 | H42: =H36-H39-H41-H40 -> 0 | I42: =I36-I39-I41-I40 -> 0 | ... AE42: =AE36-AE39-AE41-AE40 -> 14889.713 | AI42: =AI36-AI39-AI41-AI40 -> 0 | AJ42: =AJ36-AJ39-AJ41-AJ40 -> 0 | AK42: =AK36-AK39-AK41-AK40 -> 0 | AL42: =AL36-AL39-AL41-AL40 -> 0 | AM42: =AM36-AM39-AM41-AM40 -> 0 | AN42: =AN36-AN39-AN41-AN40 -> 0 | AO42: =AO36-AO39-AO41-AO40 -> 0 | AP42: =AP36-AP39-AP41-AP40 -> 0 | ... CL42: =CL36-CL39-CL41-CL40 -> 2016.2 | CM42: =+CM43*CM36 -> 1759.2358 | CN42: =+CN43*CN36 -> 2648.7453 | CO42: =+CO43*CO36 -> 1918.7061 | CP42: =+CP43*CP36 -> 2408.3376 | CQ42: =+CQ43*CQ36 -> 1989.2335 | CR42: =+CR43*CR36 -> 2919.9771 | CS42: =+CS43*CS36 -> 2287.9593 | CT42: =+CT43*CT36 -> 2817.3399 | ... DD42: =+DD43*DD36 -> 4679.5276 | DF42: 5645.9
A43: GP% | B43: =B42/B36 -> #DIV/0! | C43: =C42/C36 -> #DIV/0! | D43: =D42/D36 -> #DIV/0! | E43: =E42/E36 -> #DIV/0! | F43: =F42/F36 -> #DIV/0! | G43: =G42/G36 -> #DIV/0! | H43: =H42/H36 -> #DIV/0! | I43: =I42/I36 -> #DIV/0! | ... AE43: =AE42/AE36 -> 0.77587522 | AI43: =AI42/AI36 -> #DIV/0! | AJ43: =AJ42/AJ36 -> #DIV/0! | AK43: =AK42/AK36 -> #DIV/0! | AL43: =AL42/AL36 -> #DIV/0! | AM43: =AM42/AM36 -> #DIV/0! | AN43: =AN42/AN36 -> #DIV/0! | AO43: =AO42/AO36 -> #DIV/0! | AP43: =AP42/AP36 -> #DIV/0! | ... CL43: =CL42/CL36 -> 0.84215363 | CM43: =AVERAGE(CI43:CL43)*0.99 -> 0.76002511 | CN43: =AVERAGE(CJ43:CM43)*0.99 -> 0.77545272 | CO43: =AVERAGE(CK43:CN43)*0.99 -> 0.77542608 | CP43: =AVERAGE(CL43:CO43)*0.99 -> 0.78038174 | CQ43: =AVERAGE(CM43:CP43) -> 0.77282141 | CR43: =AVERAGE(CN43:CQ43) -> 0.77602049 | CS43: =AVERAGE(CO43:CR43) -> 0.77616243 | CT43: =AVERAGE(CP43:CS43) -> 0.77634652 | CU43: =AVERAGE(CQ43:CT43) -> 0.77533771 | CV43: =AVERAGE(CR43:CU43) -> 0.77596679 | CW43: =AVERAGE(CS43:CV43) -> 0.77595336 | CX43: =AVERAGE(CT43:CW43) -> 0.7759011 | ... DD43: =AVERAGE(CZ43:DC43) -> 0.77588047 | DF43: 0.72136405
A44: GP YOY% | C44: =+IF(B42<0,1-C42/B42,C42/B42-1) -> #DIV/0! | D44: =+IF(C42<0,1-D42/C42,D42/C42-1) -> #DIV/0! | E44: =+IF(D42<0,1-E42/D42,E42/D42-1) -> #DIV/0! | F44: =+IF(E42<0,1-F42/E42,F42/E42-1) -> #DIV/0! | G44: =+IF(F42<0,1-G42/F42,G42/F42-1) -> #DIV/0! | H44: =+IF(G42<0,1-H42/G42,H42/G42-1) -> #DIV/0! | I44: =+IF(H42<0,1-I42/H42,I42/H42-1) -> #DIV/0! | J44: =+IF(I42<0,1-J42/I42,J42/I42-1) -> #DIV/0! | ... AE44: =+IF(AD42<0,1-AE42/AD42,AE42/AD42-1) -> 0.17192457 | AM44: =+IF(AI42<0,1-AM42/AI42,AM42/AI42-1) -> #DIV/0! | AN44: =+IF(AJ42<0,1-AN42/AJ42,AN42/AJ42-1) -> #DIV/0! | AO44: =+IF(AK42<0,1-AO42/AK42,AO42/AK42-1) -> #DIV/0! | AP44: =+IF(AL42<0,1-AP42/AL42,AP42/AL42-1) -> #DIV/0! | AQ44: =+IF(AM42<0,1-AQ42/AM42,AQ42/AM42-1) -> #DIV/0! | AR44: =+IF(AN42<0,1-AR42/AN42,AR42/AN42-1) -> #DIV/0! | AS44: =+IF(AO42<0,1-AS42/AO42,AS42/AO42-1) -> #DIV/0! | AT44: =+IF(AP42<0,1-AT42/AP42,AT42/AP42-1) -> #DIV/0! | ... CL44: =+IF(CH42<0,1-CL42/CH42,CL42/CH42-1) -> 0.53125237 | CM44: =+CM42/CI42-1 -> 0.41292731 | CN44: =+CN42/CJ42-1 -> 0.29087445 | CO44: =+CO42/CK42-1 -> 0.32920406 | CP44: =+CP42/CL42-1 -> 0.1944934 | CQ44: =+CQ42/CM42-1 -> 0.13073728 | CR44: =+CR42/CN42-1 -> 0.10240011 | CS44: =+CS42/CO42-1 -> 0.19244911 | CT44: =+CT42/CP42-1 -> 0.16982765 | ... DD44: =+DD42/CZ42-1 -> 0.17077658 | DF44: 0.58574879
A45: GP QOQ% | AJ45: =+IF(AI42<0,1-AJ42/AI42,AJ42/AI42-1) -> #DIV/0! | AK45: =+IF(AJ42<0,1-AK42/AJ42,AK42/AJ42-1) -> #DIV/0! | AL45: =+IF(AK42<0,1-AL42/AK42,AL42/AK42-1) -> #DIV/0! | AM45: =+IF(AL42<0,1-AM42/AL42,AM42/AL42-1) -> #DIV/0! | AN45: =+IF(AM42<0,1-AN42/AM42,AN42/AM42-1) -> #DIV/0! | AO45: =+IF(AN42<0,1-AO42/AN42,AO42/AN42-1) -> #DIV/0! | AP45: =+IF(AO42<0,1-AP42/AO42,AP42/AO42-1) -> #DIV/0! | AQ45: =+IF(AP42<0,1-AQ42/AP42,AQ42/AP42-1) -> #DIV/0! | ... CL45: =+IF(CK42<0,1-CL42/CK42,CL42/CK42-1) -> 0.39674402 | CM45: =+CM42/CL42-1 -> -0.12744976 | CN45: =+CN42/CM42-1 -> 0.50562266 | CO45: =+CO42/CN42-1 -> -0.275617 | CP45: =+CP42/CO42-1 -> 0.2551884 | CQ45: =+CQ42/CP42-1 -> -0.17402216 | CR45: =+CR42/CQ42-1 -> 0.46789057 | CS45: =+CS42/CR42-1 -> -0.21644613 | CT45: =+CT42/CS42-1 -> 0.23137673 | ... DD45: =+DD42/DC42-1 -> 0.46886542
A46: Employee Cost | B46: ='Annual Raw'!C14 -> 0 | C46: ='Annual Raw'!D14 -> 0 | D46: ='Annual Raw'!E14 -> 0 | E46: ='Annual Raw'!F14 -> 0 | F46: ='Annual Raw'!G14 -> 0 | G46: ='Annual Raw'!H14 -> 0 | H46: ='Annual Raw'!I14 -> 0 | I46: ='Annual Raw'!J14 -> 0 | ... Z46: ='Annual Raw'!AA14 -> 985.4 | AA46: =SUM(CK46:CN46) -> 1098.937 | AB46: =+SUM(CO46:CR46) -> 1175.8626 | AC46: =+SUM(CS46:CV46) -> 1258.173 | AD46: =+SUM(CW46:CZ46) -> 1346.2451 | AE46: =+SUM(DA46:DD46) -> 1440.4822 | AI46: ='QTR Raw'!C16 -> 0 | AJ46: ='QTR Raw'!D16 -> 0 | AK46: ='QTR Raw'!E16 -> 0 | AL46: ='QTR Raw'!F16 -> 0 | AM46: ='QTR Raw'!G16 -> 0 | AN46: ='QTR Raw'!H16 -> 0 | AO46: ='QTR Raw'!I16 -> 0 | AP46: ='QTR Raw'!J16 -> 0 | ... CL46: ='QTR Raw'!BF16 -> 259.7 | CM46: =CI46*107% -> 258.619 | CN46: =CJ46*107% -> 328.918 | CO46: =CK46*107% -> 269.319 | CP46: =CL46*107% -> 277.879 | CQ46: =CM46*107% -> 276.72233 | CR46: =CN46*107% -> 351.94226 | CS46: =CO46*107% -> 288.17133 | CT46: =CP46*107% -> 297.33053 | ... DD46: =CZ46*107% -> 431.1444 | DF46: 985.4
A47: General and Administration Expenses | B47: ='Annual Raw'!C17 -> 0 | C47: ='Annual Raw'!D17 -> 0 | D47: ='Annual Raw'!E17 -> 0 | E47: ='Annual Raw'!F17 -> 0 | F47: ='Annual Raw'!G17 -> 0 | G47: ='Annual Raw'!H17 -> 0 | H47: ='Annual Raw'!I17 -> 0 | I47: ='Annual Raw'!J17 -> 0 | ... Z47: ='Annual Raw'!AA17 -> 538.1 | AA47: =SUM(CK47:CN47) -> 0 | AB47: =+SUM(CO47:CR47) -> 0 | AC47: =+SUM(CS47:CV47) -> 0 | AD47: =+SUM(CW47:CZ47) -> 0 | AE47: =+SUM(DA47:DD47) -> 0 | AI47: ='QTR Raw'!C17 -> 0 | AJ47: ='QTR Raw'!D17 -> 0 | AK47: ='QTR Raw'!E17 -> 0 | AL47: ='QTR Raw'!F17 -> 0 | AM47: ='QTR Raw'!G17 -> 0 | AN47: ='QTR Raw'!H17 -> 0 | AO47: ='QTR Raw'!I17 -> 0 | AP47: ='QTR Raw'!J17 -> 0 | ... CL47: ='QTR Raw'!BF17 -> 0 | DF47: 538.1
A48: Miscellaneous Expenses | B48: ='Annual Raw'!C19-'Annual Raw'!C20 -> 0 | C48: ='Annual Raw'!D19-'Annual Raw'!D20 -> 0 | D48: ='Annual Raw'!E19-'Annual Raw'!E20 -> 0 | E48: ='Annual Raw'!F19-'Annual Raw'!F20 -> 0 | F48: ='Annual Raw'!G19-'Annual Raw'!G20 -> 0 | G48: ='Annual Raw'!H19-'Annual Raw'!H20 -> 0 | H48: ='Annual Raw'!I19-'Annual Raw'!I20 -> 0 | I48: ='Annual Raw'!J19-'Annual Raw'!J20 -> 0 | ... Z48: ='Annual Raw'!AA19-'Annual Raw'!AA20 -> 82.5 | AA48: =SUM(CK48:CN48) -> 0 | AB48: =+SUM(CO48:CR48) -> 0 | AC48: =+SUM(CS48:CV48) -> 0 | AD48: =+SUM(CW48:CZ48) -> 0 | AE48: =+SUM(DA48:DD48) -> 0 | AI48: =+'QTR Raw'!C21 -> 0 | AJ48: =+'QTR Raw'!D21 -> 0 | AK48: =+'QTR Raw'!E21 -> 0 | AL48: =+'QTR Raw'!F21 -> 0 | AM48: =+'QTR Raw'!G21 -> 0 | AN48: =+'QTR Raw'!H21 -> 0 | AO48: =+'QTR Raw'!I21 -> 0 | AP48: =+'QTR Raw'!J21 -> 0 | ... CL48: =+'QTR Raw'!BF21 -> 0 | DF48: 82.5
A49: Other Manufacturing Expenses | B49: ='Annual Raw'!C15+'Annual Raw'!C16 -> 0 | C49: ='Annual Raw'!D15+'Annual Raw'!D16 -> 0 | D49: ='Annual Raw'!E15+'Annual Raw'!E16 -> 0 | E49: ='Annual Raw'!F15+'Annual Raw'!F16 -> 0 | F49: ='Annual Raw'!G15+'Annual Raw'!G16 -> 0 | G49: ='Annual Raw'!H15+'Annual Raw'!H16 -> 0 | H49: ='Annual Raw'!I15+'Annual Raw'!I16 -> 0 | I49: ='Annual Raw'!J15+'Annual Raw'!J16 -> 0 | ... Z49: ='Annual Raw'!AA15+'Annual Raw'!AA16 -> 2416.3 | AA49: =SUM(CK49:CN49) -> 4697.0662 | AB49: =+SUM(CO49:CR49) -> 5495.6665 | AC49: =+SUM(CS49:CV49) -> 6433.5585 | AD49: =+SUM(CW49:CZ49) -> 7647.1316 | AE49: =+SUM(DA49:DD49) -> 9111.5686 | AI49: ='QTR Raw'!C14 -> 0 | AJ49: ='QTR Raw'!D14 -> 0 | AK49: ='QTR Raw'!E14 -> 0 | AL49: ='QTR Raw'!F14 -> 0 | AM49: ='QTR Raw'!G14 -> 0 | AN49: ='QTR Raw'!H14 -> 0 | AO49: ='QTR Raw'!I14 -> 0 | AP49: ='QTR Raw'!J14 -> 0 | ... CL49: ='QTR Raw'!BF14 -> 1258.2 | CM49: =+CM42-CM46-CM58-CM17 -> 1049.6751 | CN49: =+CN42-CN46-CN58-CN17 -> 1658.1911 | CO49: =+CO42-CO46-CO58-CO17 -> 1109.2071 | CP49: =+CP42-CP46-CP58-CP17 -> 1478.3851 | CQ49: =+CQ42-CQ46-CQ58-CQ17 -> 1152.4295 | CR49: =+CR42-CR46-CR58-CR17 -> 1755.6448 | CS49: =+CS42-CS46-CS58-CS17 -> 1335.0877 | CT49: =+CT42-CT46-CT58-CT17 -> 1713.0903 | ... DD49: =+DD42-DD46-DD58-DD17 -> 2910.1235 | DF49: 2416.3
A50: Power & Fuel Cost | B50: ='Annual Raw'!C13 -> 0 | C50: ='Annual Raw'!D13 -> 0 | D50: ='Annual Raw'!E13 -> 0 | E50: ='Annual Raw'!F13 -> 0 | F50: ='Annual Raw'!G13 -> 0 | G50: ='Annual Raw'!H13 -> 0 | H50: ='Annual Raw'!I13 -> 0 | I50: ='Annual Raw'!J13 -> 0 | ... Z50: ='Annual Raw'!AA13 -> 22.1 | AA50: =SUM(CK50:CN50) -> 0 | AB50: =+SUM(CO50:CR50) -> 0 | AC50: =+SUM(CS50:CV50) -> 0 | AD50: =+SUM(CW50:CZ50) -> 0 | AE50: =+SUM(DA50:DD50) -> 0 | AI50: ='QTR Raw'!C15 -> 0 | AJ50: ='QTR Raw'!D15 -> 0 | AK50: ='QTR Raw'!E15 -> 0 | AL50: ='QTR Raw'!F15 -> 0 | AM50: ='QTR Raw'!G15 -> 0 | AN50: ='QTR Raw'!H15 -> 0 | AO50: ='QTR Raw'!I15 -> 0 | AP50: ='QTR Raw'!J15 -> 0 | ... CL50: ='QTR Raw'!BF15 -> 0 | DF50: 22.1
A51: Selling and Distribution Expenses | B51: ='Annual Raw'!C18 -> 0 | C51: ='Annual Raw'!D18 -> 0 | D51: ='Annual Raw'!E18 -> 0 | E51: ='Annual Raw'!F18 -> 0 | F51: ='Annual Raw'!G18 -> 0 | G51: ='Annual Raw'!H18 -> 0 | H51: ='Annual Raw'!I18 -> 0 | I51: ='Annual Raw'!J18 -> 0 | ... Z51: ='Annual Raw'!AA18 -> 111.5 | AA51: =SUM(CK51:CN51) -> 0 | AB51: =+SUM(CO51:CR51) -> 0 | AC51: =+SUM(CS51:CV51) -> 0 | AD51: =+SUM(CW51:CZ51) -> 0 | AE51: =+SUM(DA51:DD51) -> 0 | AI51: ='QTR Raw'!C18 -> 0 | AJ51: ='QTR Raw'!D18 -> 0 | AK51: ='QTR Raw'!E18 -> 0 | AL51: ='QTR Raw'!F18 -> 0 | AM51: ='QTR Raw'!G18 -> 0 | AN51: ='QTR Raw'!H18 -> 0 | AO51: ='QTR Raw'!I18 -> 0 | AP51: ='QTR Raw'!J18 -> 0 | ... CL51: ='QTR Raw'!BF18 -> 0 | DF51: 111.5
A52: Total Cost | B52: =+SUM(B46:B51) -> 0 | C52: =+SUM(C46:C51) -> 0 | D52: =+SUM(D46:D51) -> 0 | E52: =+SUM(E46:E51) -> 0 | F52: =+SUM(F46:F51) -> 0 | G52: =+SUM(G46:G51) -> 0 | H52: =+SUM(H46:H51) -> 0 | I52: =+SUM(I46:I51) -> 0 | ... AE52: =+SUM(AE46:AE51) -> 10552.051 | AI52: =+SUM(AI46:AI51) -> 0 | AJ52: =+SUM(AJ46:AJ51) -> 0 | AK52: =+SUM(AK46:AK51) -> 0 | AL52: =+SUM(AL46:AL51) -> 0 | AM52: =+SUM(AM46:AM51) -> 0 | AN52: =+SUM(AN46:AN51) -> 0 | AO52: =+SUM(AO46:AO51) -> 0 | AP52: =+SUM(AP46:AP51) -> 0 | ... DD52: =+SUM(DD46:DD51) -> 3341.2679 | DF52: 4155.9
A53: Cost % | B53: =B52/B36 -> #DIV/0! | C53: =C52/C36 -> #DIV/0! | D53: =D52/D36 -> #DIV/0! | E53: =E52/E36 -> #DIV/0! | F53: =F52/F36 -> #DIV/0! | G53: =G52/G36 -> #DIV/0! | H53: =H52/H36 -> #DIV/0! | I53: =I52/I36 -> #DIV/0! | ... AE53: =AE52/AE36 -> 0.54984773 | AI53: =AI52/AI36 -> #DIV/0! | AJ53: =AJ52/AJ36 -> #DIV/0! | AK53: =AK52/AK36 -> #DIV/0! | AL53: =AL52/AL36 -> #DIV/0! | AM53: =AM52/AM36 -> #DIV/0! | AN53: =AN52/AN36 -> #DIV/0! | AO53: =AO52/AO36 -> #DIV/0! | AP53: =AP52/AP36 -> #DIV/0! | ... DD53: =DD52/DD36 -> 0.55399277 | DF53: 0.53099007
A54: EBITDA | B54: =B42-B52 -> 0 | C54: =C42-C52 -> 0 | D54: =D42-D52 -> 0 | E54: =E42-E52 -> 0 | F54: =F42-F52 -> 0 | G54: =G42-G52 -> 0 | H54: =H42-H52 -> 0 | I54: =I42-I52 -> 0 | ... AE54: =AE42-AE52 -> 4337.6619 | AI54: =AI42-AI52 -> 0 | AJ54: =AJ42-AJ52 -> 0 | AK54: =AK42-AK52 -> 0 | AL54: =AL42-AL52 -> 0 | AM54: =AM42-AM52 -> 0 | AN54: =AN42-AN52 -> 0 | AO54: =AO42-AO52 -> 0 | AP54: =AP42-AP52 -> 0 | ... DD54: =DD42-DD52 -> 1338.2598 | DF54: 1490
A55: EBITDA Margins | B55: =B54/B36 -> #DIV/0! | C55: =C54/C36 -> #DIV/0! | D55: =D54/D36 -> #DIV/0! | E55: =E54/E36 -> #DIV/0! | F55: =F54/F36 -> #DIV/0! | G55: =G54/G36 -> #DIV/0! | H55: =H54/H36 -> #DIV/0! | I55: =I54/I36 -> #DIV/0! | ... AE55: =AE54/AE36 -> 0.22602749 | AI55: =AI54/AI36 -> #DIV/0! | AJ55: =AJ54/AJ36 -> #DIV/0! | AK55: =AK54/AK36 -> #DIV/0! | AL55: =AL54/AL36 -> #DIV/0! | AM55: =AM54/AM36 -> #DIV/0! | AN55: =AN54/AN36 -> #DIV/0! | AO55: =AO54/AO36 -> #DIV/0! | AP55: =AP54/AP36 -> #DIV/0! | ... DD55: =DD54/DD36 -> 0.2218877 | DF55: 0.19037398
A56: EBITDA YOY% | C56: =+IF(B54<0,1-C54/B54,C54/B54-1) -> #DIV/0! | D56: =+IF(C54<0,1-D54/C54,D54/C54-1) -> #DIV/0! | E56: =+IF(D54<0,1-E54/D54,E54/D54-1) -> #DIV/0! | F56: =+IF(E54<0,1-F54/E54,F54/E54-1) -> #DIV/0! | G56: =+IF(F54<0,1-G54/F54,G54/F54-1) -> #DIV/0! | H56: =+IF(G54<0,1-H54/G54,H54/G54-1) -> #DIV/0! | I56: =+IF(H54<0,1-I54/H54,I54/H54-1) -> #DIV/0! | J56: =+IF(I54<0,1-J54/I54,J54/I54-1) -> #DIV/0! | ... AE56: =+IF(AD54<0,1-AE54/AD54,AE54/AD54-1) -> 0.16855934 | AM56: =+IF(AI54<0,1-AM54/AI54,AM54/AI54-1) -> #DIV/0! | AN56: =+IF(AJ54<0,1-AN54/AJ54,AN54/AJ54-1) -> #DIV/0! | AO56: =+IF(AK54<0,1-AO54/AK54,AO54/AK54-1) -> #DIV/0! | AP56: =+IF(AL54<0,1-AP54/AL54,AP54/AL54-1) -> #DIV/0! | AQ56: =+IF(AM54<0,1-AQ54/AM54,AQ54/AM54-1) -> #DIV/0! | AR56: =+IF(AN54<0,1-AR54/AN54,AR54/AN54-1) -> #DIV/0! | AS56: =+IF(AO54<0,1-AS54/AO54,AS54/AO54-1) -> #DIV/0! | AT56: =+IF(AP54<0,1-AT54/AP54,AT54/AP54-1) -> #DIV/0! | ... DD56: =+IF(CZ54<0,1-DD54/CZ54,DD54/CZ54-1) -> 0.16472545 | DF56: 0.74167154
A57: EBITDA QOQ% | AJ57: =+IF(AI54<0,1-AJ54/AI54,AJ54/AI54-1) -> #DIV/0! | AK57: =+IF(AJ54<0,1-AK54/AJ54,AK54/AJ54-1) -> #DIV/0! | AL57: =+IF(AK54<0,1-AL54/AK54,AL54/AK54-1) -> #DIV/0! | AM57: =+IF(AL54<0,1-AM54/AL54,AM54/AL54-1) -> #DIV/0! | AN57: =+IF(AM54<0,1-AN54/AM54,AN54/AM54-1) -> #DIV/0! | AO57: =+IF(AN54<0,1-AO54/AN54,AO54/AN54-1) -> #DIV/0! | AP57: =+IF(AO54<0,1-AP54/AO54,AP54/AO54-1) -> #DIV/0! | AQ57: =+IF(AP54<0,1-AQ54/AP54,AQ54/AP54-1) -> #DIV/0! | ... CI57: =+IF(CH54<0,1-CI54/CH54,CI54/CH54-1) -> -0.050767085 | CJ57: =+IF(CI54>1,CJ54/CI54-1,1-CJ54/CI54) -> 0.40846312 | CK57: =+IF(CJ54>1,CK54/CJ54-1,1-CK54/CJ54) -> -0.038597955 | CL57: =+IF(CK54>1,CL54/CK54-1,1-CL54/CK54) -> 0.081380208 | CM57: =+IF(CL54>1,CM54/CL54-1,1-CM54/CL54) -> -0.095039724 | CN57: =+IF(CM54>1,CN54/CM54-1,1-CN54/CM54) -> 0.46723226 | CO57: =+IF(CN54>1,CO54/CN54-1,1-CO54/CN54) -> -0.18356946 | CP57: =+IF(CO54>1,CP54/CO54-1,1-CP54/CO54) -> 0.20714107 | CQ57: =+IF(CP54>1,CQ54/CP54-1,1-CQ54/CP54) -> -0.1410759 | ... DD57: =+IF(DC54>1,DD54/DC54-1,1-DD54/DC54) -> 0.41691222
A58: Depreciation | B58: ='Annual Raw'!C27 -> 0 | C58: ='Annual Raw'!D27 -> 0 | D58: ='Annual Raw'!E27 -> 0 | E58: ='Annual Raw'!F27 -> 0 | F58: ='Annual Raw'!G27 -> 0 | G58: ='Annual Raw'!H27 -> 0 | H58: ='Annual Raw'!I27 -> 0 | I58: ='Annual Raw'!J27 -> 0 | ... Z58: ='Annual Raw'!AA27 -> 103 | AA58: =SUM(CK58:CN58) -> 137.8224 | AB58: =+SUM(CO58:CR58) -> 210.85969 | AC58: =+SUM(CS58:CV58) -> 296.2652 | AD58: =+SUM(CW58:CZ58) -> 357.44911 | AE58: =+SUM(DA58:DD58) -> 401.28083 | AI58: ='QTR Raw'!C28 -> 0 | AJ58: ='QTR Raw'!D28 -> 0 | AK58: ='QTR Raw'!E28 -> 0 | AL58: ='QTR Raw'!F28 -> 0 | AM58: ='QTR Raw'!G28 -> 0 | AN58: ='QTR Raw'!H28 -> 0 | AO58: ='QTR Raw'!I28 -> 0 | AP58: ='QTR Raw'!J28 -> 0 | ... CL58: ='QTR Raw'!BF28 -> 34.7 | CM58: =CM59*CL160 -> 32.72 | CN58: =CN59*CM160 -> 38.1024 | CO58: =CO59*CN160 -> 43.054208 | CP58: =CP59*CO160 -> 49.849871 | CQ58: =CQ59*CP160 -> 56.101882 | CR58: =CR59*CQ160 -> 61.853731 | CS58: =CS59*CR160 -> 67.145433 | CT58: =CT59*CS160 -> 72.013798 | ... DD58: =DD59*DC160 -> 103.68024 | DF58: 103
A59: Depreciation % of Net Block | B59: =+B58/B160 -> #DIV/0! | C59: =+C58/C160 -> #DIV/0! | D59: =+D58/D160 -> #DIV/0! | E59: =+E58/E160 -> #DIV/0! | F59: =+F58/F160 -> #DIV/0! | G59: =+G58/G160 -> #DIV/0! | H59: =+H58/H160 -> #DIV/0! | I59: =+I58/I160 -> #DIV/0! | ... AE59: =+AE58/AE160 -> 0.30392631 | AI59: =+AI58/AH160 -> #DIV/0! | AJ59: =+AJ58/AI160 -> #DIV/0! | AK59: =+AK58/AJ160 -> #DIV/0! | AL59: =+AL58/AK160 -> #DIV/0! | AM59: =+AM58/AL160 -> #DIV/0! | AN59: =+AN58/AM160 -> #DIV/0! | AO59: =+AO58/AN160 -> #DIV/0! | AP59: =+AP58/AO160 -> #DIV/0! | ... CL59: =+CL58/CK160 -> 0.073423614 | CM59: 0.08 | CN59: =CM59 -> 0.08 | CO59: =CN59 -> 0.08 | CP59: =CO59 -> 0.08 | CQ59: =CP59 -> 0.08 | CR59: =CQ59 -> 0.08 | CS59: =CR59 -> 0.08 | CT59: =CS59 -> 0.08 | CU59: =CT59 -> 0.08 | ... DD59: =DC59 -> 0.08 | DF59: 0.19212833
A60: EBIT | B60: =B54-B58 -> 0 | C60: =C54-C58 -> 0 | D60: =D54-D58 -> 0 | E60: =E54-E58 -> 0 | F60: =F54-F58 -> 0 | G60: =G54-G58 -> 0 | H60: =H54-H58 -> 0 | I60: =I54-I58 -> 0 | ... AE60: =AE54-AE58 -> 3936.3811 | AI60: =AI54-AI58 -> 0 | AJ60: =AJ54-AJ58 -> 0 | AK60: =AK54-AK58 -> 0 | AL60: =AL54-AL58 -> 0 | AM60: =AM54-AM58 -> 0 | AN60: =AN54-AN58 -> 0 | AO60: =AO54-AO58 -> 0 | AP60: =AP54-AP58 -> 0 | ... DD60: =DD54-DD58 -> 1234.5795 | DF60: 1387
A61: Other Income | B61: ='Annual Raw'!C23 -> 0 | C61: ='Annual Raw'!D23 -> 0 | D61: ='Annual Raw'!E23 -> 0 | E61: ='Annual Raw'!F23 -> 0 | F61: ='Annual Raw'!G23 -> 0 | G61: ='Annual Raw'!H23 -> 0 | H61: ='Annual Raw'!I23 -> 0 | I61: ='Annual Raw'!J23 -> 0 | ... Z61: ='Annual Raw'!AA23 -> 139.7 | AA61: =SUM(CK61:CN61) -> 95.2 | AB61: =+SUM(CO61:CR61) -> 0 | AC61: =+SUM(CS61:CV61) -> 0 | AD61: =+SUM(CW61:CZ61) -> 0 | AE61: =+SUM(DA61:DD61) -> 0 | AI61: ='QTR Raw'!C23 -> 0 | AJ61: ='QTR Raw'!D23 -> 0 | AK61: ='QTR Raw'!E23 -> 0 | AL61: ='QTR Raw'!F23 -> 0 | AM61: ='QTR Raw'!G23 -> 0 | AN61: ='QTR Raw'!H23 -> 0 | AO61: ='QTR Raw'!I23 -> 0 | AP61: ='QTR Raw'!J23 -> 0 | ... CL61: ='QTR Raw'!BF23 -> 45.9 | DF61: 139.7
A62: Interest | B62: ='Annual Raw'!C25 -> 0 | C62: ='Annual Raw'!D25 -> 0 | D62: ='Annual Raw'!E25 -> 0 | E62: ='Annual Raw'!F25 -> 0 | F62: ='Annual Raw'!G25 -> 0 | G62: ='Annual Raw'!H25 -> 0 | H62: ='Annual Raw'!I25 -> 0 | I62: ='Annual Raw'!J25 -> 0 | ... Z62: ='Annual Raw'!AA25 -> 39.2 | AA62: =SUM(CK62:CN62) -> -55.785818 | AB62: =+SUM(CO62:CR62) -> -157.71893 | AC62: =+SUM(CS62:CV62) -> -191.76829 | AD62: =+SUM(CW62:CZ62) -> -258.31596 | AE62: =+SUM(DA62:DD62) -> -340.009 | AI62: ='QTR Raw'!C25 -> 0 | AJ62: ='QTR Raw'!D25 -> 0 | AK62: ='QTR Raw'!E25 -> 0 | AL62: ='QTR Raw'!F25 -> 0 | AM62: ='QTR Raw'!G25 -> 0 | AN62: ='QTR Raw'!H25 -> 0 | AO62: ='QTR Raw'!I25 -> 0 | AP62: ='QTR Raw'!J25 -> 0 | ... CL62: ='QTR Raw'!BF25 -> 7.3 | CM62: =CM63*CL194 -> -33.731674 | CN62: =CN63*CM194 -> -36.754144 | CO62: =CO63*CN194 -> -37.67014 | CP62: =CP63*CO194 -> -43.9398 | CQ62: =CQ63*CP194 -> -36.077413 | CR62: =CR63*CQ194 -> -40.031582 | CS62: =CS63*CR194 -> -41.319701 | CT62: =CT63*CS194 -> -46.715343 | ... DD62: =DD63*DC194 -> -94.753575 | DF62: 39.2
A63: Interest % of Debt | B63: =+B62/B154 -> #DIV/0! | C63: =+C62/C154 -> #DIV/0! | D63: =+D62/D154 -> #DIV/0! | E63: =+E62/E154 -> #DIV/0! | F63: =+F62/F154 -> #DIV/0! | G63: =+G62/G154 -> #DIV/0! | H63: =+H62/H154 -> #DIV/0! | I63: =+I62/I154 -> #DIV/0! | ... AE63: =+AE62/AE154 -> #DIV/0! | AI63: =(AI62-AI61)/AH194 -> #DIV/0! | AJ63: =(AJ62-AJ61)/AI194 -> #DIV/0! | AK63: =(AK62-AK61)/AJ194 -> #DIV/0! | AL63: =(AL62-AL61)/AK194 -> #DIV/0! | AM63: =(AM62-AM61)/AL194 -> #DIV/0! | AN63: =(AN62-AN61)/AM194 -> #DIV/0! | AO63: =(AO62-AO61)/AN194 -> #DIV/0! | AP63: =(AP62-AP61)/AO194 -> #DIV/0! | ... CL63: =(CL62-CL61)/CK194 -> 0.01023723 | CM63: =+CL63 -> 0.01023723 | CN63: =+CM63 -> 0.01023723 | CO63: =+CN63 -> 0.01023723 | CP63: =+CO63 -> 0.01023723 | CQ63: 0.008 | CR63: =+CQ63 -> 0.008 | CS63: =+CR63 -> 0.008 | CT63: =+CS63 -> 0.008 | CU63: =+CT63 -> 0.008 | CV63: =+CU63 -> 0.008 | CW63: =+CV63 -> 0.008 | CX63: =+CW63 -> 0.008 | CY63: =+CX63 -> 0.008 | ... DD63: =+DC63 -> 0.008
A64: PBT | B64: =B60+B61-B62 -> 0 | C64: =C60+C61-C62 -> 0 | D64: =D60+D61-D62 -> 0 | E64: =E60+E61-E62 -> 0 | F64: =F60+F61-F62 -> 0 | G64: =G60+G61-G62 -> 0 | H64: =H60+H61-H62 -> 0 | I64: =I60+I61-I62 -> 0 | ... AE64: =AE60+AE61-AE62 -> 4276.3901 | AI64: =AI60+AI61-AI62 -> 0 | AJ64: =AJ60+AJ61-AJ62 -> 0 | AK64: =AK60+AK61-AK62 -> 0 | AL64: =AL60+AL61-AL62 -> 0 | AM64: =AM60+AM61-AM62 -> 0 | AN64: =AN60+AN61-AN62 -> 0 | AO64: =AO60+AO61-AO62 -> 0 | AP64: =AP60+AP61-AP62 -> 0 | ... DD64: =DD60+DD61-DD62 -> 1329.3331 | DF64: 1487.5
A65: Tax | B65: ='Annual Raw'!C30 -> 0 | C65: ='Annual Raw'!D30 -> 0 | D65: ='Annual Raw'!E30 -> 0 | E65: ='Annual Raw'!F30 -> 0 | F65: ='Annual Raw'!G30 -> 0 | G65: ='Annual Raw'!H30 -> 0 | H65: ='Annual Raw'!I30 -> 0 | I65: ='Annual Raw'!J30 -> 0 | ... Z65: ='Annual Raw'!AA30 -> 387.4 | AA65: =SUM(CK65:CN65) -> 513.84145 | AB65: =+SUM(CO65:CR65) -> 617.28839 | AC65: =+SUM(CS65:CV65) -> 748.88207 | AD65: =+SUM(CW65:CZ65) -> 888.51551 | AE65: =+SUM(DA65:DD65) -> 1051.673 | AI65: ='QTR Raw'!C29 -> 0 | AJ65: ='QTR Raw'!D29 -> 0 | AK65: ='QTR Raw'!E29 -> 0 | AL65: ='QTR Raw'!F29 -> 0 | AM65: ='QTR Raw'!G29 -> 0 | AN65: ='QTR Raw'!H29 -> 0 | AO65: ='QTR Raw'!I29 -> 0 | AP65: ='QTR Raw'!J29 -> 0 | ... CL65: ='QTR Raw'!BF29 -> 127.6 | CM65: =+CM64*CM66 -> 114.11942 | CN65: =+CN64*CN66 -> 166.52203 | CO65: =+CO64*CO66 -> 130.14765 | CP65: =+CP64*CP66 -> 160.26772 | CQ65: =+CQ64*CQ66 -> 133.14124 | CR65: =+CR64*CR66 -> 193.73178 | CS65: =+CS64*CS66 -> 156.99941 | CT65: =+CT64*CT66 -> 192.54425 | ... DD65: =+DD64*DD66 -> 326.91023 | DF65: 387.4
A66: Tax Rate % | B66: =B65/B64 -> #DIV/0! | C66: =C65/C64 -> #DIV/0! | D66: =D65/D64 -> #DIV/0! | E66: =E65/E64 -> #DIV/0! | F66: =F65/F64 -> #DIV/0! | G66: =G65/G64 -> #DIV/0! | H66: =H65/H64 -> #DIV/0! | I66: =I65/I64 -> #DIV/0! | ... AE66: =AE65/AE64 -> 0.24592542 | AI66: =AI65/AI64 -> #DIV/0! | AJ66: =AJ65/AJ64 -> #DIV/0! | AK66: =AK65/AK64 -> #DIV/0! | AL66: =AL65/AL64 -> #DIV/0! | AM66: =AM65/AM64 -> #DIV/0! | AN66: =AN65/AN64 -> #DIV/0! | AO66: =AO65/AO64 -> #DIV/0! | AP66: =AP65/AP64 -> #DIV/0! | ... CL66: =CL65/CL64 -> 0.25408204 | CM66: =AVERAGE(CI66:CL66)*1.03 -> 0.25250264 | CN66: =AVERAGE(CJ66:CM66)*1.03 -> 0.25219608 | CO66: =AVERAGE(CK66:CN66)*0.99 -> 0.24335946 | CP66: =AVERAGE(CL66:CO66)*0.99 -> 0.2480297 | CQ66: =AVERAGE(CM66:CP66)*0.99 -> 0.24653175 | CR66: =AVERAGE(CN66:CQ66)*0.99 -> 0.24505395 | CS66: =AVERAGE(CO66:CR66) -> 0.24574372 | CT66: =AVERAGE(CP66:CS66) -> 0.24633978 | CU66: =AVERAGE(CQ66:CT66) -> 0.2459173 | CV66: =AVERAGE(CR66:CU66) -> 0.24576369 | CW66: =AVERAGE(CS66:CV66) -> 0.24594112 | CX66: =AVERAGE(CT66:CW66) -> 0.24599047 | CY66: =AVERAGE(CU66:CX66) -> 0.24590315 | CZ66: =AVERAGE(CV66:CY66) -> 0.24589961 | ... DD66: =AVERAGE(CZ66:DC66) -> 0.24592048 | DF66: 0.26043697
A67: PAT | B67: =B64-B65 -> 0 | C67: =C64-C65 -> 0 | D67: =D64-D65 -> 0 | E67: =E64-E65 -> 0 | F67: =F64-F65 -> 0 | G67: =G64-G65 -> 0 | H67: =H64-H65 -> 0 | I67: =I64-I65 -> 0 | ... AE67: =AE64-AE65 -> 3224.7171 | AI67: =AI64-AI65 -> 0 | AJ67: =AJ64-AJ65 -> 0 | AK67: =AK64-AK65 -> 0 | AL67: =AL64-AL65 -> 0 | AM67: =AM64-AM65 -> 0 | AN67: =AN64-AN65 -> 0 | AO67: =AO64-AO65 -> 0 | AP67: =AP64-AP65 -> 0 | ... DD67: =DD64-DD65 -> 1002.4229 | DF67: 1100.1
A68: PAT % | B68: =+B67/B36 -> #DIV/0! | C68: =+C67/C36 -> #DIV/0! | D68: =+D67/D36 -> #DIV/0! | E68: =+E67/E36 -> #DIV/0! | F68: =+F67/F36 -> #DIV/0! | G68: =+G67/G36 -> #DIV/0! | H68: =+H67/H36 -> #DIV/0! | I68: =+I67/I36 -> #DIV/0! | ... AE68: =+AE67/AE36 -> 0.16803401 | AI68: =+AI67/AI36 -> #DIV/0! | AJ68: =+AJ67/AJ36 -> #DIV/0! | AK68: =+AK67/AK36 -> #DIV/0! | AL68: =+AL67/AL36 -> #DIV/0! | AM68: =+AM67/AM36 -> #DIV/0! | AN68: =+AN67/AN36 -> #DIV/0! | AO68: =+AO67/AO36 -> #DIV/0! | AP68: =+AP67/AP36 -> #DIV/0! | ... DD68: =+DD67/DD36 -> 0.16620488 | DF68: 0.14055732
A69: PAT YOY% | C69: =+IF(B67<0,1-C67/B67,C67/B67-1) -> #DIV/0! | D69: =+IF(C67<0,1-D67/C67,D67/C67-1) -> #DIV/0! | E69: =+IF(D67<0,1-E67/D67,E67/D67-1) -> #DIV/0! | F69: =+IF(E67<0,1-F67/E67,F67/E67-1) -> #DIV/0! | G69: =+IF(F67<0,1-G67/F67,G67/F67-1) -> #DIV/0! | H69: =+IF(G67<0,1-H67/G67,H67/G67-1) -> #DIV/0! | I69: =+IF(H67<0,1-I67/H67,I67/H67-1) -> #DIV/0! | J69: =+IF(I67<0,1-J67/I67,J67/I67-1) -> #DIV/0! | ... AE69: =+IF(AD67<0,1-AE67/AD67,AE67/AD67-1) -> 0.18367544 | AM69: =+IF(AI67<0,1-AM67/AI67,AM67/AI67-1) -> #DIV/0! | AN69: =+IF(AJ67<0,1-AN67/AJ67,AN67/AJ67-1) -> #DIV/0! | AO69: =+IF(AK67<0,1-AO67/AK67,AO67/AK67-1) -> #DIV/0! | AP69: =+IF(AL67<0,1-AP67/AL67,AP67/AL67-1) -> #DIV/0! | AQ69: =+IF(AM67<0,1-AQ67/AM67,AQ67/AM67-1) -> #DIV/0! | AR69: =+IF(AN67<0,1-AR67/AN67,AR67/AN67-1) -> #DIV/0! | AS69: =+IF(AO67<0,1-AS67/AO67,AS67/AO67-1) -> #DIV/0! | AT69: =+IF(AP67<0,1-AT67/AP67,AT67/AP67-1) -> #DIV/0! | ... CL69: =+IF(CH67<0,1-CL67/CH67,CL67/CH67-1) -> 0.52214547 | CM69: =+CM67/CI67-1 -> 0.28600669 | CN69: =+CN67/CJ67-1 -> 0.37309769 | CO69: =+CO67/CK67-1 -> 0.10923326 | CP69: =+CP67/CL67-1 -> 0.29710543 | CQ69: =+CQ67/CM67-1 -> 0.20448498 | CR69: =+CR67/CN67-1 -> 0.20874292 | CS69: =+CS67/CO67-1 -> 0.19084935 | CT69: =+CT67/CP67-1 -> 0.2123515 | ... DD69: =+DD67/CZ67-1 -> 0.1789005 | DF69: 0.8335
A70: PAT QOQ% | AJ70: =+IF(AI67<0,1-AJ67/AI67,AJ67/AI67-1) -> #DIV/0! | AK70: =+IF(AJ67<0,1-AK67/AJ67,AK67/AJ67-1) -> #DIV/0! | AL70: =+IF(AK67<0,1-AL67/AK67,AL67/AK67-1) -> #DIV/0! | AM70: =+IF(AL67<0,1-AM67/AL67,AM67/AL67-1) -> #DIV/0! | AN70: =+IF(AM67<0,1-AN67/AM67,AN67/AM67-1) -> #DIV/0! | AO70: =+IF(AN67<0,1-AO67/AN67,AO67/AN67-1) -> #DIV/0! | AP70: =+IF(AO67<0,1-AP67/AO67,AP67/AO67-1) -> #DIV/0! | AQ70: =+IF(AP67<0,1-AQ67/AP67,AQ67/AP67-1) -> #DIV/0! | ... CL70: =+IF(CK67<0,1-CL67/CK67,CL67/CK67-1) -> 0.026864035 | CM70: =+CM67/CL67-1 -> -0.098147468 | CN70: =+CN67/CM67-1 -> 0.46156394 | CO70: =+CO67/CN67-1 -> -0.18048559 | CP70: =+CP67/CO67-1 -> 0.20078523 | CQ70: =+CQ67/CP67-1 -> -0.16254469 | CR70: =+CR67/CQ67-1 -> 0.46673068 | CS70: =+CS67/CR67-1 -> -0.19261724 | CT70: =+CT67/CS67-1 -> 0.22246678 | ... DD70: =+DD67/DC67-1 -> 0.42921518
A71: Minority Interest | B71: ='Annual Raw'!C32 -> 0 | C71: ='Annual Raw'!D32 -> 0 | D71: ='Annual Raw'!E32 -> 0 | E71: ='Annual Raw'!F32 -> 0 | F71: ='Annual Raw'!G32 -> 0 | G71: ='Annual Raw'!H32 -> 0 | H71: ='Annual Raw'!I32 -> 0 | I71: ='Annual Raw'!J32 -> 0 | ... Z71: ='Annual Raw'!AA32 -> 0 | AA71: =SUM(CK71:CN71) -> 0 | AB71: =+SUM(CO71:CR71) -> 0 | AC71: =+SUM(CS71:CV71) -> 0 | AD71: =+SUM(CW71:CZ71) -> 0 | AE71: =+SUM(DA71:DD71) -> 0 | AI71: ='QTR Raw'!C34 -> 0 | AJ71: ='QTR Raw'!D34 -> 0 | AK71: ='QTR Raw'!E34 -> 0 | AL71: ='QTR Raw'!F34 -> 0 | AM71: ='QTR Raw'!G34 -> 0 | AN71: ='QTR Raw'!H34 -> 0 | AO71: ='QTR Raw'!I34 -> 0 | AP71: ='QTR Raw'!J34 -> 0 | ... CL71: ='QTR Raw'!BF34 -> 0 | CM71: =+CL71 -> 0 | CN71: =+CM71 -> 0 | CO71: =+CN71 -> 0 | CP71: =+CO71 -> 0 | CQ71: =+CP71 -> 0 | CR71: =+CQ71 -> 0 | CS71: =+CR71 -> 0 | CT71: =+CS71 -> 0 | ... DD71: =+DC71 -> 0 | DF71: 0
A72: Share of Associate | B72: ='Annual Raw'!C33+'Annual Raw'!C28 -> 0 | C72: ='Annual Raw'!D33+'Annual Raw'!D28 -> 0 | D72: ='Annual Raw'!E33+'Annual Raw'!E28 -> 0 | E72: ='Annual Raw'!F33+'Annual Raw'!F28 -> 0 | F72: ='Annual Raw'!G33+'Annual Raw'!G28 -> 0 | G72: ='Annual Raw'!H33+'Annual Raw'!H28 -> 0 | H72: ='Annual Raw'!I33+'Annual Raw'!I28 -> 0 | I72: ='Annual Raw'!J33+'Annual Raw'!J28 -> 0 | ... Z72: ='Annual Raw'!AA33+'Annual Raw'!AA28 -> 0 | AA72: =SUM(CK72:CN72) -> 0 | AB72: =+SUM(CO72:CR72) -> 0 | AC72: =+SUM(CS72:CV72) -> 0 | AD72: =+SUM(CW72:CZ72) -> 0 | AE72: =+SUM(DA72:DD72) -> 0 | AI72: ='QTR Raw'!C35 -> 0 | AJ72: ='QTR Raw'!D35 -> 0 | AK72: ='QTR Raw'!E35 -> 0 | AL72: ='QTR Raw'!F35 -> 0 | AM72: ='QTR Raw'!G35 -> 0 | AN72: ='QTR Raw'!H35 -> 0 | AO72: ='QTR Raw'!I35 -> 0 | AP72: ='QTR Raw'!J35 -> 0 | ... CL72: ='QTR Raw'!BF35 -> 0 | CM72: =+CL72 -> 0 | CN72: =+CM72 -> 0 | CO72: =+CN72 -> 0 | CP72: =+CO72 -> 0 | CQ72: =+CP72 -> 0 | CR72: =+CQ72 -> 0 | CS72: =+CR72 -> 0 | CT72: =+CS72 -> 0 | ... DD72: =+DC72 -> 0 | DF72: 0
A73: Exceptional Income / Expenses | B73: ='Annual Raw'!C29+'Annual Raw'!C31+'Annual Raw'!C34+'Annual Raw'!C36 -> 0 | C73: ='Annual Raw'!D29+'Annual Raw'!D31+'Annual Raw'!D34+'Annual Raw'!D36 -> 0 | D73: ='Annual Raw'!E29+'Annual Raw'!E31+'Annual Raw'!E34+'Annual Raw'!E36 -> 0 | E73: ='Annual Raw'!F29+'Annual Raw'!F31+'Annual Raw'!F34+'Annual Raw'!F36 -> 0 | F73: ='Annual Raw'!G29+'Annual Raw'!G31+'Annual Raw'!G34+'Annual Raw'!G36 -> 0 | G73: ='Annual Raw'!H29+'Annual Raw'!H31+'Annual Raw'!H34+'Annual Raw'!H36 -> 0 | H73: ='Annual Raw'!I29+'Annual Raw'!I31+'Annual Raw'!I34+'Annual Raw'!I36 -> 0 | I73: ='Annual Raw'!J29+'Annual Raw'!J31+'Annual Raw'!J34+'Annual Raw'!J36 -> 0 | ... Z73: ='Annual Raw'!AA29+'Annual Raw'!AA31+'Annual Raw'!AA34+'Annual Raw'!AA36 -> 0 | AA73: =SUM(CK73:CN73) -> -51.9 | AB73: =+SUM(CO73:CR73) -> 0 | AC73: =+SUM(CS73:CV73) -> 0 | AD73: =+SUM(CW73:CZ73) -> 0 | AE73: =+SUM(DA73:DD73) -> 0 | AI73: ='QTR Raw'!C26+'QTR Raw'!C31+'QTR Raw'!C32+'QTR Raw'!C33+'QTR Raw'!C36+'QTR Raw'!C37+'QTR Raw'!C39 -> 0 | AJ73: ='QTR Raw'!D26+'QTR Raw'!D31+'QTR Raw'!D32+'QTR Raw'!D33+'QTR Raw'!D36+'QTR Raw'!D37+'QTR Raw'!D39 -> 0 | AK73: ='QTR Raw'!E26+'QTR Raw'!E31+'QTR Raw'!E32+'QTR Raw'!E33+'QTR Raw'!E36+'QTR Raw'!E37+'QTR Raw'!E39 -> 0 | AL73: ='QTR Raw'!F26+'QTR Raw'!F31+'QTR Raw'!F32+'QTR Raw'!F33+'QTR Raw'!F36+'QTR Raw'!F37+'QTR Raw'!F39 -> 0 | AM73: ='QTR Raw'!G26+'QTR Raw'!G31+'QTR Raw'!G32+'QTR Raw'!G33+'QTR Raw'!G36+'QTR Raw'!G37+'QTR Raw'!G39 -> 0 | AN73: ='QTR Raw'!H26+'QTR Raw'!H31+'QTR Raw'!H32+'QTR Raw'!H33+'QTR Raw'!H36+'QTR Raw'!H37+'QTR Raw'!H39 -> 0 | AO73: ='QTR Raw'!I26+'QTR Raw'!I31+'QTR Raw'!I32+'QTR Raw'!I33+'QTR Raw'!I36+'QTR Raw'!I37+'QTR Raw'!I39 -> 0 | AP73: ='QTR Raw'!J26+'QTR Raw'!J31+'QTR Raw'!J32+'QTR Raw'!J33+'QTR Raw'!J36+'QTR Raw'!J37+'QTR Raw'!J39 -> 0 | ... CL73: ='QTR Raw'!BF26+'QTR Raw'!BF31+'QTR Raw'!BF32+'QTR Raw'!BF33+'QTR Raw'!BF36+'QTR Raw'!BF37+'QTR Raw'!BF39 -> 0 | DF73: 0
A74: Consolidated Net Profit | B74: =B67+B71+B72+B73 -> 0 | C74: =C67+C71+C72+C73 -> 0 | D74: =D67+D71+D72+D73 -> 0 | E74: =E67+E71+E72+E73 -> 0 | F74: =F67+F71+F72+F73 -> 0 | G74: =G67+G71+G72+G73 -> 0 | H74: =H67+H71+H72+H73 -> 0 | I74: =I67+I71+I72+I73 -> 0 | ... AE74: =AE67+AE71+AE72+AE73 -> 3224.7171 | AI74: =AI67+AI71+AI72+AI73 -> 0 | AJ74: =AJ67+AJ71+AJ72+AJ73 -> 0 | AK74: =AK67+AK71+AK72+AK73 -> 0 | AL74: =AL67+AL71+AL72+AL73 -> 0 | AM74: =AM67+AM71+AM72+AM73 -> 0 | AN74: =AN67+AN71+AN72+AN73 -> 0 | AO74: =AO67+AO71+AO72+AO73 -> 0 | AP74: =AP67+AP71+AP72+AP73 -> 0 | ... DD74: =DD67+DD71+DD72+DD73 -> 1002.4229 | DF74: 1100.1
A75: Profit & Loss- Annual (End)
A77: Ace - PAT | B77: ='Annual Raw'!C35 -> 0 | C77: ='Annual Raw'!D35 -> 0 | D77: ='Annual Raw'!E35 -> 0 | E77: ='Annual Raw'!F35 -> 0 | F77: ='Annual Raw'!G35 -> 0 | G77: ='Annual Raw'!H35 -> 0 | H77: ='Annual Raw'!I35 -> 0 | I77: ='Annual Raw'!J35 -> 0 | ... Z77: ='Annual Raw'!AA35 -> 1100.1 | AA77: =+AA74 -> 1519.0999 | AB77: =+AB74 -> 1894.296 | AC77: =+AC74 -> 2296.087 | AD77: =+AD74 -> 2724.3254 | AE77: =+AE74 -> 3224.7171 | AI77: ='QTR Raw'!C42 -> 0 | AJ77: ='QTR Raw'!D42 -> 0 | AK77: ='QTR Raw'!E42 -> 0 | AL77: ='QTR Raw'!F42 -> 0 | AM77: ='QTR Raw'!G42 -> 0 | AN77: ='QTR Raw'!H42 -> 0 | AO77: ='QTR Raw'!I42 -> 0 | AP77: ='QTR Raw'!J42 -> 0 | ... CL77: ='QTR Raw'!BF42 -> 374.6 | DF77: 1100.1
A78: Checksum - PAT | B78: =B77-B74 -> 0 | C78: =C77-C74 -> 0 | D78: =D77-D74 -> 0 | E78: =E77-E74 -> 0 | F78: =F77-F74 -> 0 | G78: =G77-G74 -> 0 | H78: =H77-H74 -> 0 | I78: =I77-I74 -> 0 | ... AE78: =AE77-AE74 -> 0 | AI78: =AI77-AI74 -> 0 | AJ78: =AJ77-AJ74 -> 0 | AK78: =AK77-AK74 -> 0 | AL78: =AL77-AL74 -> 0 | AM78: =AM77-AM74 -> 0 | AN78: =AN77-AN74 -> 0 | AO78: =AO77-AO74 -> 0 | AP78: =AP77-AP74 -> 0 | ... CL78: =CL77-CL74 -> 0 | DF78: 0
A79: Ratios (Start)
A80: ROE (%) | B80: =(B74-B73)/B146 -> #DIV/0! | C80: =(C74-C73)/C146 -> #DIV/0! | D80: =(D74-D73)/D146 -> #DIV/0! | E80: =(E74-E73)/E146 -> #DIV/0! | F80: =(F74-F73)/F146 -> #DIV/0! | G80: =(G74-G73)/G146 -> #DIV/0! | H80: =(H74-H73)/H146 -> #DIV/0! | I80: =(I74-I73)/I146 -> #DIV/0! | ... AE80: =(AE74-AE73)/AE146 -> 0.20431811 | AL80: =(SUM(AI74:AL74)-SUM(AI73:AL73))/AL146 -> #DIV/0! | AM80: =(SUM(AJ74:AM74)-SUM(AJ73:AM73))/AM146 -> #DIV/0! | AN80: =(SUM(AK74:AN74)-SUM(AK73:AN73))/AN146 -> #DIV/0! | AO80: =(SUM(AL74:AO74)-SUM(AL73:AO73))/AO146 -> #DIV/0! | AP80: =(SUM(AM74:AP74)-SUM(AM73:AP73))/AP146 -> #DIV/0! | AQ80: =(SUM(AN74:AQ74)-SUM(AN73:AQ73))/AQ146 -> #DIV/0! | AR80: =(SUM(AO74:AR74)-SUM(AO73:AR73))/AR146 -> #DIV/0! | AS80: =(SUM(AP74:AS74)-SUM(AP73:AS73))/AS146 -> #DIV/0! | ... DD80: =(SUM(DA74:DD74)-SUM(DA73:DD73))/DD146 -> 0.20431811 | DF80: 0.25108986
A81: ROCE (%) | B81: =+B60/B155 -> #DIV/0! | C81: =+C60/C155 -> #DIV/0! | D81: =+D60/D155 -> #DIV/0! | E81: =+E60/E155 -> #DIV/0! | F81: =+F60/F155 -> #DIV/0! | G81: =+G60/G155 -> #DIV/0! | H81: =+H60/H155 -> #DIV/0! | I81: =+I60/I155 -> #DIV/0! | ... AE81: =+AE60/AE155 -> 0.24940915 | AL81: =+SUM(AI60:AL60)/AL155 -> #DIV/0! | AM81: =+SUM(AJ60:AM60)/AM155 -> #DIV/0! | AN81: =+SUM(AK60:AN60)/AN155 -> #DIV/0! | AO81: =+SUM(AL60:AO60)/AO155 -> #DIV/0! | AP81: =+SUM(AM60:AP60)/AP155 -> #DIV/0! | AQ81: =+SUM(AN60:AQ60)/AQ155 -> #DIV/0! | AR81: =+SUM(AO60:AR60)/AR155 -> #DIV/0! | AS81: =+SUM(AP60:AS60)/AS155 -> #DIV/0! | ... DD81: =+SUM(DA60:DD60)/DD155 -> 0.24940915 | DF81: 0.31657271
A82: Ratios (End)
A83: Checksum Of qtr to Annual
A84: Revenue - Checksum Of qtr to Annual | N84: =N36-SUM(AI36:AL36) -> 0 | O84: =O36-SUM(AM36:AP36) -> 0 | P84: =P36-SUM(AQ36:AT36) -> 0 | Q84: =Q36-SUM(AU36:AX36) -> 0 | R84: =R36-SUM(AY36:BB36) -> 0 | S84: =S36-SUM(BC36:BF36) -> 0 | T84: =T36-SUM(BG36:BJ36) -> 0 | U84: =U36-SUM(BK36:BN36) -> 0 | V84: =V36-SUM(BO36:BR36) -> 0 | W84: =W36-SUM(BS36:BV36) -> 0 | X84: =X36-SUM(BW36:BZ36) -> 0 | Y84: =Y36-SUM(CA36:CD36) -> 3563 | Z84: =Z36-SUM(CB36:CE36) -> 5145.9 | AA84: =AA36-SUM(CK36:CN36) -> 0 | AB84: =AB36-SUM(CO36:CR36) -> 0 | AC84: =AC36-SUM(CS36:CV36) -> 0 | AD84: =AD36-SUM(CW36:CZ36) -> 0 | AE84: =AE36-SUM(DA36:DD36) -> 0 | DF84: 0
A85: GP - Checksum Of qtr to Annual | N85: =N42-SUM(AI42:AL42) -> 0 | O85: =O42-SUM(AM42:AP42) -> 0 | P85: =P42-SUM(AQ42:AT42) -> 0 | Q85: =Q42-SUM(AU42:AX42) -> 0 | R85: =R42-SUM(AY42:BB42) -> 0 | S85: =S42-SUM(BC42:BF42) -> 0 | T85: =T42-SUM(BG42:BJ42) -> 0 | U85: =U42-SUM(BK42:BN42) -> 0 | V85: =V42-SUM(BO42:BR42) -> 0 | W85: =W42-SUM(BS42:BV42) -> 0 | X85: =X42-SUM(BW42:BZ42) -> 0 | Y85: =Y42-SUM(CA42:CD42) -> 2660.8 | Z85: =Z42-SUM(CB42:CE42) -> 3623.3 | AA85: =AA42-SUM(CK42:CN42) -> 0 | AB85: =AB42-SUM(CO42:CR42) -> 0 | AC85: =AC42-SUM(CS42:CV42) -> 0 | AD85: =AD42-SUM(CW42:CZ42) -> 0 | AE85: =AE42-SUM(DA42:DD42) -> 0 | DF85: 0
A86: EBITDA - Checksum Of qtr to Annual | N86: =N54-SUM(AI54:AL54) -> 0 | O86: =O54-SUM(AM54:AP54) -> 0 | P86: =P54-SUM(AQ54:AT54) -> 0 | Q86: =Q54-SUM(AU54:AX54) -> 0 | R86: =R54-SUM(AY54:BB54) -> 0 | S86: =S54-SUM(BC54:BF54) -> 0 | T86: =T54-SUM(BG54:BJ54) -> 0 | U86: =U54-SUM(BK54:BN54) -> 0 | V86: =V54-SUM(BO54:BR54) -> 0 | W86: =W54-SUM(BS54:BV54) -> 0 | X86: =X54-SUM(BW54:BZ54) -> 0 | Y86: =Y54-SUM(CA54:CD54) -> 586 | Z86: =Z54-SUM(CB54:CE54) -> 1007.1 | AA86: =AA54-SUM(CK54:CN54) -> 0 | AB86: =AB54-SUM(CO54:CR54) -> 0 | AC86: =AC54-SUM(CS54:CV54) -> 0 | AD86: =AD54-SUM(CW54:CZ54) -> 0 | AE86: =AE54-SUM(DA54:DD54) -> 0 | DF86: -23.4
A87: PAT - Checksum Of qtr to Annual | N87: =N74-SUM(AI74:AL74) -> 0 | O87: =O74-SUM(AM74:AP74) -> 0 | P87: =P74-SUM(AQ74:AT74) -> 0 | Q87: =Q74-SUM(AU74:AX74) -> 0 | R87: =R74-SUM(AY74:BB74) -> 0 | S87: =S74-SUM(BC74:BF74) -> 0 | T87: =T74-SUM(BG74:BJ74) -> 0 | U87: =U74-SUM(BK74:BN74) -> 0 | V87: =V74-SUM(BO74:BR74) -> 0 | W87: =W67-SUM(BS67:BV67) -> 0 | X87: =X67-SUM(BW67:BZ67) -> 0 | Y87: =Y67-SUM(CA67:CD67) -> 419.5 | Z87: =Z67-SUM(CB67:CE67) -> 773.8 | AA87: =AA67-SUM(CK67:CN67) -> 0 | AB87: =AB67-SUM(CO67:CR67) -> 0 | AC87: =AC67-SUM(CS67:CV67) -> 0 | AD87: =AD67-SUM(CW67:CZ67) -> 0 | AE87: =AE67-SUM(DA67:DD67) -> 0 | DF87: 0
A88: Valuation (Start)
A89: Eq | B89: ='Annual Raw'!C104 -> 0 | C89: ='Annual Raw'!D104 -> 0 | D89: ='Annual Raw'!E104 -> 0 | E89: =+F89 -> 71.2 | F89: =+G89 -> 71.2 | G89: =+H89 -> 71.2 | H89: =+I89 -> 71.2 | I89: =+J89 -> 71.2 | J89: =+K89 -> 71.2 | K89: =+L89 -> 71.2 | L89: =+M89 -> 71.2 | ... Z89: =+AA89 -> 71.2 | AA89: =+CN89 -> 71.2 | AB89: =CR89 -> 71.2 | AC89: =CV89 -> 71.2 | AD89: =CZ89 -> 71.2 | AE89: =DD89 -> 71.2 | AI89: =+AJ89 -> 71.2 | AJ89: =+AK89 -> 71.2 | AK89: =+AL89 -> 71.2 | AL89: =+AM89 -> 71.2 | AM89: =+AN89 -> 71.2 | AN89: =+AO89 -> 71.2 | AO89: =+AP89 -> 71.2 | AP89: =+AQ89 -> 71.2 | ... CI89: =+CJ89 -> 71.2 | CJ89: ='QTR Raw'!BD45 -> 71.2 | CK89: ='QTR Raw'!BE45 -> 71.2 | CL89: ='QTR Raw'!BF45 -> 71.2 | CM89: =+CL89 -> 71.2 | CN89: =+CM89 -> 71.2 | CO89: =+CN89 -> 71.2 | CP89: =+CO89 -> 71.2 | CQ89: =+CP89 -> 71.2 | CR89: =+CQ89 -> 71.2 | CS89: =+CR89 -> 71.2 | CT89: =+CS89 -> 71.2 | ... DD89: =+DC89 -> 71.2 | DF89: 71.2
A90: FV | B90: ='Annual Raw'!C105 -> 0 | C90: ='Annual Raw'!D105 -> 0 | D90: ='Annual Raw'!E105 -> 0 | E90: =+F90 -> 2 | F90: =+G90 -> 2 | G90: =+H90 -> 2 | H90: =+I90 -> 2 | I90: =+J90 -> 2 | J90: =+K90 -> 2 | K90: =+L90 -> 2 | L90: =+M90 -> 2 | ... Z90: =+AA90 -> 2 | AA90: =+CN90 -> 2 | AB90: =CR90 -> 2 | AC90: =CV90 -> 2 | AD90: =CZ90 -> 2 | AE90: =DD90 -> 2 | AI90: =AJ90 -> 2 | AJ90: =AK90 -> 2 | AK90: =AL90 -> 2 | AL90: =AM90 -> 2 | AM90: =AN90 -> 2 | AN90: =AO90 -> 2 | AO90: =AP90 -> 2 | AP90: =AQ90 -> 2 | ... CI90: =CJ90 -> 2 | CJ90: ='QTR Raw'!BD46 -> 2 | CK90: ='QTR Raw'!BE46 -> 2 | CL90: ='QTR Raw'!BF46 -> 2 | CM90: =+CL90 -> 2 | CN90: =+CM90 -> 2 | CO90: =+CN90 -> 2 | CP90: =+CO90 -> 2 | CQ90: =+CP90 -> 2 | CR90: =+CQ90 -> 2 | CS90: =+CR90 -> 2 | CT90: =+CS90 -> 2 | ... DD90: =+DC90 -> 2 | DF90: 2
A91: No of share | B91: =B89/B90 -> #DIV/0! | C91: =C89/C90 -> #DIV/0! | D91: =D89/D90 -> #DIV/0! | E91: =E89/E90 -> 35.6 | F91: =F89/F90 -> 35.6 | G91: =G89/G90 -> 35.6 | H91: =H89/H90 -> 35.6 | I91: =I89/I90 -> 35.6 | ... Z91: =Z89/Z90 -> 35.6 | AA91: =+CN91 -> 35.6 | AB91: =CR91 -> 35.6 | AC91: =CV91 -> 35.6 | AD91: =CZ91 -> 35.6 | AE91: =DD91 -> 35.6 | AI91: =AI89/AI90 -> 35.6 | AJ91: =AJ89/AJ90 -> 35.6 | AK91: =AK89/AK90 -> 35.6 | AL91: =AL89/AL90 -> 35.6 | AM91: =AM89/AM90 -> 35.6 | AN91: =AN89/AN90 -> 35.6 | AO91: =AO89/AO90 -> 35.6 | AP91: =AP89/AP90 -> 35.6 | ... DD91: =DD89/DD90 -> 35.6 | DF91: 35.6
A92: EPS | B92: =(B74-B73)/B91 -> #DIV/0! | C92: =(C74-C73)/C91 -> #DIV/0! | D92: =(D74-D73)/D91 -> #DIV/0! | E92: =(E74-E73)/E91 -> 0 | F92: =(F74-F73)/F91 -> 0 | G92: =(G74-G73)/G91 -> 0 | H92: =(H74-H73)/H91 -> 0 | I92: =(I74-I73)/I91 -> 0 | ... AE92: =(AE74-AE73)/AE91 -> 90.58194 | AI92: =(AI74-AI73)/AI91 -> 0 | AJ92: =(AJ74-AJ73)/AJ91 -> 0 | AK92: =(AK74-AK73)/AK91 -> 0 | AL92: =(AL74-AL73)/AL91 -> 0 | AM92: =(AM74-AM73)/AM91 -> 0 | AN92: =(AN74-AN73)/AN91 -> 0 | AO92: =(AO74-AO73)/AO91 -> 0 | AP92: =(AP74-AP73)/AP91 -> 0 | ... DD92: =(DD74-DD73)/DD91 -> 28.157946 | DF92: 30.901685
A93: DPS | B93: ='Annual Raw'!C110 -> 0 | C93: ='Annual Raw'!D110 -> 0 | D93: ='Annual Raw'!E110 -> 0 | E93: ='Annual Raw'!F110 -> 0 | F93: ='Annual Raw'!G110 -> 0 | G93: ='Annual Raw'!H110 -> 0 | H93: ='Annual Raw'!I110 -> 0 | I93: ='Annual Raw'!J110 -> 0 | ... Z93: ='Annual Raw'!AA110 -> 4 | DF93: 4
A94: DPS % of EPS | B94: =B93/B92 -> #DIV/0! | C94: =C93/C92 -> #DIV/0! | D94: =D93/D92 -> #DIV/0! | E94: =E93/E92 -> #DIV/0! | F94: =F93/F92 -> #DIV/0! | G94: =G93/G92 -> #DIV/0! | H94: =H93/H92 -> #DIV/0! | I94: =I93/I92 -> #DIV/0! | ... AE94: =AE93/AE92 -> 0 | DF94: 0.12944278
A95: EPS TTM | B95: =+B92 -> #DIV/0! | C95: =+C92 -> #DIV/0! | D95: =+D92 -> #DIV/0! | E95: =+E92 -> 0 | F95: =+F92 -> 0 | G95: =+G92 -> 0 | H95: =+H92 -> 0 | I95: =+I92 -> 0 | ... AE95: =+AE92 -> 90.58194 | AL95: =SUM(AI92:AL92) -> 0 | AM95: =SUM(AJ92:AM92) -> 0 | AN95: =SUM(AK92:AN92) -> 0 | AO95: =SUM(AL92:AO92) -> 0 | AP95: =SUM(AM92:AP92) -> 0 | AQ95: =SUM(AN92:AQ92) -> 0 | AR95: =SUM(AO92:AR92) -> 0 | AS95: =SUM(AP92:AS92) -> 0 | ... DD95: =SUM(DA92:DD92) -> 90.58194 | DF95: 30.901685
A96: EPS Growth YoY % | C96: =+C95/B95-1 -> #DIV/0! | D96: =+D95/C95-1 -> #DIV/0! | E96: =+E95/D95-1 -> #DIV/0! | F96: =+F95/E95-1 -> #DIV/0! | G96: =+G95/F95-1 -> #DIV/0! | H96: =+H95/G95-1 -> #DIV/0! | I96: =+I95/H95-1 -> #DIV/0! | J96: =+J95/I95-1 -> #DIV/0! | ... AE96: =+AE95/AD95-1 -> 0.18367544 | AP96: =+IF(AL95<0,1-AP95/AL95,AP95/AL95-1) -> #DIV/0! | AQ96: =+IF(AM95<0,1-AQ95/AM95,AQ95/AM95-1) -> #DIV/0! | AR96: =+IF(AN95<0,1-AR95/AN95,AR95/AN95-1) -> #DIV/0! | AS96: =+IF(AO95<0,1-AS95/AO95,AS95/AO95-1) -> #DIV/0! | AT96: =+IF(AP95<0,1-AT95/AP95,AT95/AP95-1) -> #DIV/0! | AU96: =+IF(AQ95<0,1-AU95/AQ95,AU95/AQ95-1) -> #DIV/0! | AV96: =+IF(AR95<0,1-AV95/AR95,AV95/AR95-1) -> #DIV/0! | AW96: =+IF(AS95<0,1-AW95/AS95,AW95/AS95-1) -> #DIV/0! | ... DD96: =+IF(CZ95<0,1-DD95/CZ95,DD95/CZ95-1) -> 0.18367544 | DF96: 0.8335
A97: Bloomberg Estimate | CN97: 40.5 | CR97: 52.7 | CV97: 64.1
A98: Estimate deviation | CN98: =+CN97/CN95-1 -> -0.082240546 | CR98: =+CR97/CR95-1 -> -0.009595115 | CV98: =+CV97/CV95-1 -> -0.006152625
A99: Promoter Share holding % | B99: ='Annual Raw'!C112 -> 0 | C99: ='Annual Raw'!D112 -> 0 | D99: ='Annual Raw'!E112 -> 0 | E99: ='Annual Raw'!F112 -> 0 | F99: ='Annual Raw'!G112 -> 0 | G99: ='Annual Raw'!H112 -> 0 | H99: ='Annual Raw'!I112 -> 0 | I99: ='Annual Raw'!J112 -> 0 | ... Z99: ='Annual Raw'!AA112 -> 75 | AI99: ='QTR Raw'!C49 -> 0 | AJ99: ='QTR Raw'!D49 -> 0 | AK99: ='QTR Raw'!E49 -> 0 | AL99: ='QTR Raw'!F49 -> 0 | AM99: ='QTR Raw'!G49 -> 0 | AN99: ='QTR Raw'!H49 -> 0 | AO99: ='QTR Raw'!I49 -> 0 | AP99: ='QTR Raw'!J49 -> 0 | ... CL99: ='QTR Raw'!BF49 -> 75 | DF99: 75
A100: Pledge Share % | B100: ='Annual Raw'!C113 -> 0 | C100: ='Annual Raw'!D113 -> 0 | D100: ='Annual Raw'!E113 -> 0 | E100: ='Annual Raw'!F113 -> 0 | F100: ='Annual Raw'!G113 -> 0 | G100: ='Annual Raw'!H113 -> 0 | H100: ='Annual Raw'!I113 -> 0 | I100: ='Annual Raw'!J113 -> 0 | ... Z100: ='Annual Raw'!AA113 -> 0 | AI100: ='QTR Raw'!C50 -> 0 | AJ100: ='QTR Raw'!D50 -> 0 | AK100: ='QTR Raw'!E50 -> 0 | AL100: ='QTR Raw'!F50 -> 0 | AM100: ='QTR Raw'!G50 -> 0 | AN100: ='QTR Raw'!H50 -> 0 | AO100: ='QTR Raw'!I50 -> 0 | AP100: ='QTR Raw'!J50 -> 0 | ... CL100: ='QTR Raw'!BF50 -> 0 | DF100: 0
A102: Share Price
A103: Share Price - Close | B103: ='Annual Raw'!C106 -> 0 | C103: ='Annual Raw'!D106 -> 0 | D103: ='Annual Raw'!E106 -> 0 | E103: ='Annual Raw'!F106 -> 0 | F103: ='Annual Raw'!G106 -> 0 | G103: ='Annual Raw'!H106 -> 0 | H103: ='Annual Raw'!I106 -> 0 | I103: ='Annual Raw'!J106 -> 0 | ... Z103: ='Annual Raw'!AA106 -> 3430.35 | AA103: =+CN103 -> 3105 | AB103: =CR103 -> 3105 | AC103: =CV103 -> 3105 | AD103: =CZ103 -> 3105 | AE103: =DD103 -> 3105 | AJ103: ='QTR Share Price'!HP21 -> 0 | AK103: ='QTR Share Price'!HQ21 -> 0 | AL103: ='QTR Share Price'!HR21 -> 0 | AM103: ='QTR Share Price'!HS21 -> 0 | AN103: ='QTR Share Price'!HT21 -> 0 | AO103: ='QTR Share Price'!HU21 -> 0 | AP103: ='QTR Share Price'!HV21 -> 0 | AQ103: ='QTR Share Price'!HW21 -> 0 | ... CL103: ='QTR Share Price'!JR21 -> 2569.65 | CM103: 3105 | CN103: =+CM103 -> 3105 | CO103: =+CN103 -> 3105 | CP103: =+CO103 -> 3105 | CQ103: =+CP103 -> 3105 | CR103: =+CQ103 -> 3105 | CS103: =+CR103 -> 3105 | CT103: =+CS103 -> 3105 | CU103: =+CT103 -> 3105 | ... DD103: =+DC103 -> 3105 | DF103: 3430.35
A104: Share Price - High | B104: ='Annual Raw'!C107 -> 0 | C104: ='Annual Raw'!D107 -> 0 | D104: ='Annual Raw'!E107 -> 0 | E104: ='Annual Raw'!F107 -> 0 | F104: ='Annual Raw'!G107 -> 0 | G104: ='Annual Raw'!H107 -> 0 | H104: ='Annual Raw'!I107 -> 0 | I104: ='Annual Raw'!J107 -> 0 | ... Z104: ='Annual Raw'!AA107 -> 3624 | AA104: =+CN104 -> 3485.8615 | AB104: =CR104 -> 4203.217 | AC104: =CV104 -> 5094.7433 | AD104: =CZ104 -> 6044.9533 | AE104: =DD104 -> 7155.2628 | AJ104: ='QTR Share Price'!HP19 -> 0 | AK104: ='QTR Share Price'!HQ19 -> 0 | AL104: ='QTR Share Price'!HR19 -> 0 | AM104: ='QTR Share Price'!HS19 -> 0 | AN104: ='QTR Share Price'!HT19 -> 0 | AO104: ='QTR Share Price'!HU19 -> 0 | AP104: ='QTR Share Price'!HV19 -> 0 | AQ104: ='QTR Share Price'!HW19 -> 0 | ... CL104: ='QTR Share Price'!JR19 -> 3021.45 | CM104: =+CM95*CM112 -> 3188.1633 | CN104: =+CN95*CN112 -> 3485.8615 | CO104: =+CO95*CO112 -> 3574.2801 | CP104: =+CP95*CP112 -> 3821.232 | CQ104: =+CQ95*CQ112 -> 3974.5167 | CR104: =+CR95*CR112 -> 4203.217 | CS104: =+CS95*CS112 -> 4374.5742 | CT104: =+CT95*CT112 -> 4603.5199 | ... DD104: =+DD95*DD112 -> 7155.2628 | DF104: 3624
A105: Share Price - Low | B105: ='Annual Raw'!C108 -> 0 | C105: ='Annual Raw'!D108 -> 0 | D105: ='Annual Raw'!E108 -> 0 | E105: ='Annual Raw'!F108 -> 0 | F105: ='Annual Raw'!G108 -> 0 | G105: ='Annual Raw'!H108 -> 0 | H105: ='Annual Raw'!I108 -> 0 | I105: ='Annual Raw'!J108 -> 0 | ... Z105: ='Annual Raw'!AA108 -> 2529 | AA105: =+CN105 -> 2428.7218 | AB105: =CR105 -> 2928.5285 | AC105: =CV105 -> 3549.686 | AD105: =CZ105 -> 4211.7306 | AE105: =DD105 -> 4985.3221 | AJ105: =+'QTR Share Price'!HP20 -> 0 | AK105: =+'QTR Share Price'!HQ20 -> 0 | AL105: =+'QTR Share Price'!HR20 -> 0 | AM105: =+'QTR Share Price'!HS20 -> 0 | AN105: =+'QTR Share Price'!HT20 -> 0 | AO105: =+'QTR Share Price'!HU20 -> 0 | AP105: =+'QTR Share Price'!HV20 -> 0 | AQ105: =+'QTR Share Price'!HW20 -> 0 | ... CL105: =+'QTR Share Price'!JR20 -> 2105.15 | CM105: =+CM113*CM95 -> 2221.305 | CN105: =+CN113*CN95 -> 2428.7218 | CO105: =+CO113*CO95 -> 2490.3261 | CP105: =+CP113*CP95 -> 2662.3861 | CQ105: =+CQ113*CQ95 -> 2769.1849 | CR105: =+CR113*CR95 -> 2928.5285 | CS105: =+CS113*CS95 -> 3047.919 | CT105: =+CT113*CT95 -> 3207.4335 | ... DD105: =+DD113*DD95 -> 4985.3221 | DF105: 2529
A107: Upside (%) | AA107: =+AA104/AA103-1 -> 0.12266071 | AB107: =+AB104/AB103-1 -> 0.35369308 | AC107: =+AC104/AC103-1 -> 0.6408191 | AD107: =+AD104/AD103-1 -> 0.94684487 | AE107: =+AE104/AE103-1 -> 1.3044325 | CM107: =+CM104/CM103-1 -> 0.026783671 | CN107: =+CN104/CN103-1 -> 0.12266071 | CO107: =+CO104/CO103-1 -> 0.15113692 | CP107: =+CP104/CP103-1 -> 0.23067053 | CQ107: =+CQ104/CQ103-1 -> 0.28003757 | CR107: =+CR104/CR103-1 -> 0.35369308 | CS107: =+CS104/CS103-1 -> 0.40888059 | CT107: =+CT104/CT103-1 -> 0.48261509 | ... DD107: =+DD104/DD103-1 -> 1.3044325
A108: Downside (%) | AA108: =+AA105/AA103-1 -> -0.21780298 | AB108: =+AB105/AB103-1 -> -0.056834636 | AC108: =+AC105/AC103-1 -> 0.14321611 | AD108: =+AD105/AD103-1 -> 0.35643498 | AE108: =+AE105/AE103-1 -> 0.60557878 | CM108: =+CM105/CM103-1 -> -0.28460387 | CN108: =+CN105/CN103-1 -> -0.21780298 | CO108: =+CO105/CO103-1 -> -0.19796261 | CP108: =+CP105/CP103-1 -> -0.14254875 | CQ108: =+CQ105/CQ103-1 -> -0.10815301 | CR108: =+CR105/CR103-1 -> -0.056834636 | CS108: =+CS105/CS103-1 -> -0.018383569 | CT108: =+CT105/CT103-1 -> 0.032989841 | ... DD108: =+DD105/DD103-1 -> 0.60557878
A110: PE
A111: PE - Close | B111: =+B103/B95 -> #DIV/0! | C111: =+C103/C95 -> #DIV/0! | D111: =+D103/D95 -> #DIV/0! | E111: =+E103/E95 -> #DIV/0! | F111: =+F103/F95 -> #DIV/0! | G111: =+G103/G95 -> #DIV/0! | H111: =+H103/H95 -> #DIV/0! | I111: =+I103/I95 -> #DIV/0! | ... AE111: =+AE103/AE95 -> 34.278356 | AL111: =+AL103/AL95 -> #DIV/0! | AM111: =+AM103/AM95 -> #DIV/0! | AN111: =+AN103/AN95 -> #DIV/0! | AO111: =+AO103/AO95 -> #DIV/0! | AP111: =+AP103/AP95 -> #DIV/0! | AQ111: =+AQ103/AQ95 -> #DIV/0! | AR111: =+AR103/AR95 -> #DIV/0! | AS111: =+AS103/AS95 -> #DIV/0! | ... DD111: =+DD103/DD95 -> 34.278356 | DF111: 111.00851
A112: PE - High | B112: =+B104/B95 -> #DIV/0! | C112: =+C104/C95 -> #DIV/0! | D112: =+D104/D95 -> #DIV/0! | E112: =+E104/E95 -> #DIV/0! | F112: =+F104/F95 -> #DIV/0! | G112: =+G104/G95 -> #DIV/0! | H112: =+H104/H95 -> #DIV/0! | I112: =+I104/I95 -> #DIV/0! | ... AE112: =+AE104/AE95 -> 78.992157 | AL112: =+AL104/AL95 -> #DIV/0! | AM112: =+AM104/AM95 -> #DIV/0! | AN112: =+AN104/AN95 -> #DIV/0! | AO112: =+AO104/AO95 -> #DIV/0! | AP112: =+AP104/AP95 -> #DIV/0! | AQ112: =+AQ104/AQ95 -> #DIV/0! | AR112: =+AR104/AR95 -> #DIV/0! | AS112: =+AS104/AS95 -> #DIV/0! | ... CL112: =+CL104/CL95 -> 78.992157 | CM112: =+CL112 -> 78.992157 | CN112: =+CM112 -> 78.992157 | CO112: =+CN112 -> 78.992157 | CP112: =+CO112 -> 78.992157 | CQ112: =+CP112 -> 78.992157 | CR112: =+CQ112 -> 78.992157 | CS112: =+CR112 -> 78.992157 | CT112: =+CS112 -> 78.992157 | ... DD112: =+DC112 -> 78.992157 | DF112: 117.27516
...

Sheet QTR Raw
A1: ='Annual Raw'!A1 -> 320028 | B1: X | C1: 201206 | D1: 201209 | E1: 201212 | F1: 201303 | G1: 201306 | H1: 201309 | I1: 201312 | J1: 201403 | K1: 201406 | L1: 201409 | M1: 201412 | N1: 201503 | O1: 201506 | P1: 201509 | Q1: 201512 | R1: 201603 | S1: 201606 | T1: 201609 | U1: 201612 | V1: 201703 | W1: 201706 | X1: 201709 | Y1: 201712 | Z1: 201803 | AA1: 201806 | AB1: 201809 | AC1: 201812 | AD1: 201903 | AE1: 201906 | AF1: 201909 | AG1: 201912 | AH1: 202003 | AI1: 202006 | AJ1: 202009 | AK1: 202012 | AL1: 202103 | AM1: 202106 | AN1: 202109 | AO1: 202112 | AP1: 202203 | AQ1: 202206 | AR1: 202209 | AS1: 202212 | AT1: 202303 | AU1: 202306 | AV1: 202309 | AW1: 202312 | AX1: 202403 | AY1: 202406 | AZ1: 202409 | BA1: 202412 | BB1: 202503 | BC1: 202506 | BD1: 202509 | BE1: 202512 | BF1: 202603 | BG1: 202606 | BH1: 202609 | BI1: 202612 | BJ1: 202703 | BK1: 202706 | BL1: 202709 | BM1: 202712 | BN1: 202803 | BO1: 202806 | BP1: 202809 | BQ1: 202812 | BR1: 202903 | BS1: 202906 | BT1: 202909 | BU1: 202912 | BV1: 203003
A3: Field Description | B3: Field Name
A4: Company Name | B4: CD_COMPNAME | C4: =_xll.EQNXTDZ(A1,B4,C1) -> Siemens Energy India Ltd.
A5: Date End | B5: QTR_DATE_END | C5: =_xll.EQNXTDZ($A$1,$B5,C$1,$B$1) -> 0 | D5: =_xll.EQNXTDZ($A$1,$B5,D$1,$B$1) -> 0 | E5: =_xll.EQNXTDZ($A$1,$B5,E$1,$B$1) -> 0 | F5: =_xll.EQNXTDZ($A$1,$B5,F$1,$B$1) -> 0 | G5: =_xll.EQNXTDZ($A$1,$B5,G$1,$B$1) -> 0 | H5: =_xll.EQNXTDZ($A$1,$B5,H$1,$B$1) -> 0 | I5: =_xll.EQNXTDZ($A$1,$B5,I$1,$B$1) -> 0 | J5: =_xll.EQNXTDZ($A$1,$B5,J$1,$B$1) -> 0 | ... BV5: =_xll.EQNXTDZ($A$1,$B5,BV$1,$B$1) -> 0
A6: Gross Sales | B6: QTR_GROSS_SALE | C6: =_xll.EQNXTDZ($A$1,$B6,C$1,$B$1) -> 0 | D6: =_xll.EQNXTDZ($A$1,$B6,D$1,$B$1) -> 0 | E6: =_xll.EQNXTDZ($A$1,$B6,E$1,$B$1) -> 0 | F6: =_xll.EQNXTDZ($A$1,$B6,F$1,$B$1) -> 0 | G6: =_xll.EQNXTDZ($A$1,$B6,G$1,$B$1) -> 0 | H6: =_xll.EQNXTDZ($A$1,$B6,H$1,$B$1) -> 0 | I6: =_xll.EQNXTDZ($A$1,$B6,I$1,$B$1) -> 0 | J6: =_xll.EQNXTDZ($A$1,$B6,J$1,$B$1) -> 0 | ... BV6: =_xll.EQNXTDZ($A$1,$B6,BV$1,$B$1) -> 0
A7: Less: Excise Duty | B7: QTR_EXCISE_DUTY | C7: =_xll.EQNXTDZ($A$1,$B7,C$1,$B$1) -> 0 | D7: =_xll.EQNXTDZ($A$1,$B7,D$1,$B$1) -> 0 | E7: =_xll.EQNXTDZ($A$1,$B7,E$1,$B$1) -> 0 | F7: =_xll.EQNXTDZ($A$1,$B7,F$1,$B$1) -> 0 | G7: =_xll.EQNXTDZ($A$1,$B7,G$1,$B$1) -> 0 | H7: =_xll.EQNXTDZ($A$1,$B7,H$1,$B$1) -> 0 | I7: =_xll.EQNXTDZ($A$1,$B7,I$1,$B$1) -> 0 | J7: =_xll.EQNXTDZ($A$1,$B7,J$1,$B$1) -> 0 | ... BV7: =_xll.EQNXTDZ($A$1,$B7,BV$1,$B$1) -> 0
A8: Other operating income | B8: QTR_JOB_WORKS | C8: =_xll.EQNXTDZ($A$1,$B8,C$1,$B$1) -> 0 | D8: =_xll.EQNXTDZ($A$1,$B8,D$1,$B$1) -> 0 | E8: =_xll.EQNXTDZ($A$1,$B8,E$1,$B$1) -> 0 | F8: =_xll.EQNXTDZ($A$1,$B8,F$1,$B$1) -> 0 | G8: =_xll.EQNXTDZ($A$1,$B8,G$1,$B$1) -> 0 | H8: =_xll.EQNXTDZ($A$1,$B8,H$1,$B$1) -> 0 | I8: =_xll.EQNXTDZ($A$1,$B8,I$1,$B$1) -> 0 | J8: =_xll.EQNXTDZ($A$1,$B8,J$1,$B$1) -> 0 | ... BV8: =_xll.EQNXTDZ($A$1,$B8,BV$1,$B$1) -> 0
A9: Net Sales & Other Operating Income | B9: QTR_NET_SALES | C9: =_xll.EQNXTDZ($A$1,$B9,C$1,$B$1) -> 0 | D9: =_xll.EQNXTDZ($A$1,$B9,D$1,$B$1) -> 0 | E9: =_xll.EQNXTDZ($A$1,$B9,E$1,$B$1) -> 0 | F9: =_xll.EQNXTDZ($A$1,$B9,F$1,$B$1) -> 0 | G9: =_xll.EQNXTDZ($A$1,$B9,G$1,$B$1) -> 0 | H9: =_xll.EQNXTDZ($A$1,$B9,H$1,$B$1) -> 0 | I9: =_xll.EQNXTDZ($A$1,$B9,I$1,$B$1) -> 0 | J9: =_xll.EQNXTDZ($A$1,$B9,J$1,$B$1) -> 0 | ... BV9: =_xll.EQNXTDZ($A$1,$B9,BV$1,$B$1) -> 0
A10: (Increase) / Decrease In Stocks | B10: QTR_INC_DEC_INVENTORY | C10: =_xll.EQNXTDZ($A$1,$B10,C$1,$B$1) -> 0 | D10: =_xll.EQNXTDZ($A$1,$B10,D$1,$B$1) -> 0 | E10: =_xll.EQNXTDZ($A$1,$B10,E$1,$B$1) -> 0 | F10: =_xll.EQNXTDZ($A$1,$B10,F$1,$B$1) -> 0 | G10: =_xll.EQNXTDZ($A$1,$B10,G$1,$B$1) -> 0 | H10: =_xll.EQNXTDZ($A$1,$B10,H$1,$B$1) -> 0 | I10: =_xll.EQNXTDZ($A$1,$B10,I$1,$B$1) -> 0 | J10: =_xll.EQNXTDZ($A$1,$B10,J$1,$B$1) -> 0 | ... BV10: =_xll.EQNXTDZ($A$1,$B10,BV$1,$B$1) -> 0
A11: Cost of Services & Raw Materials | B11: QTR_RAW_MATERIAL_COST | C11: =_xll.EQNXTDZ($A$1,$B11,C$1,$B$1) -> 0 | D11: =_xll.EQNXTDZ($A$1,$B11,D$1,$B$1) -> 0 | E11: =_xll.EQNXTDZ($A$1,$B11,E$1,$B$1) -> 0 | F11: =_xll.EQNXTDZ($A$1,$B11,F$1,$B$1) -> 0 | G11: =_xll.EQNXTDZ($A$1,$B11,G$1,$B$1) -> 0 | H11: =_xll.EQNXTDZ($A$1,$B11,H$1,$B$1) -> 0 | I11: =_xll.EQNXTDZ($A$1,$B11,I$1,$B$1) -> 0 | J11: =_xll.EQNXTDZ($A$1,$B11,J$1,$B$1) -> 0 | ... BV11: =_xll.EQNXTDZ($A$1,$B11,BV$1,$B$1) -> 0
A12: Purchase of Finished Goods | B12: QTR_PURCHASE_FIN_GOOD | C12: =_xll.EQNXTDZ($A$1,$B12,C$1,$B$1) -> 0 | D12: =_xll.EQNXTDZ($A$1,$B12,D$1,$B$1) -> 0 | E12: =_xll.EQNXTDZ($A$1,$B12,E$1,$B$1) -> 0 | F12: =_xll.EQNXTDZ($A$1,$B12,F$1,$B$1) -> 0 | G12: =_xll.EQNXTDZ($A$1,$B12,G$1,$B$1) -> 0 | H12: =_xll.EQNXTDZ($A$1,$B12,H$1,$B$1) -> 0 | I12: =_xll.EQNXTDZ($A$1,$B12,I$1,$B$1) -> 0 | J12: =_xll.EQNXTDZ($A$1,$B12,J$1,$B$1) -> 0 | ... BV12: =_xll.EQNXTDZ($A$1,$B12,BV$1,$B$1) -> 0
A13: Excise Duty | B13: QTR_EXCISE | C13: =_xll.EQNXTDZ($A$1,$B13,C$1,$B$1) -> 0 | D13: =_xll.EQNXTDZ($A$1,$B13,D$1,$B$1) -> 0 | E13: =_xll.EQNXTDZ($A$1,$B13,E$1,$B$1) -> 0 | F13: =_xll.EQNXTDZ($A$1,$B13,F$1,$B$1) -> 0 | G13: =_xll.EQNXTDZ($A$1,$B13,G$1,$B$1) -> 0 | H13: =_xll.EQNXTDZ($A$1,$B13,H$1,$B$1) -> 0 | I13: =_xll.EQNXTDZ($A$1,$B13,I$1,$B$1) -> 0 | J13: =_xll.EQNXTDZ($A$1,$B13,J$1,$B$1) -> 0 | ... BV13: =_xll.EQNXTDZ($A$1,$B13,BV$1,$B$1) -> 0
A14: Operating & Manufacturing Expenses | B14: QTR_MFG_EXPS | C14: =_xll.EQNXTDZ($A$1,$B14,C$1,$B$1) -> 0 | D14: =_xll.EQNXTDZ($A$1,$B14,D$1,$B$1) -> 0 | E14: =_xll.EQNXTDZ($A$1,$B14,E$1,$B$1) -> 0 | F14: =_xll.EQNXTDZ($A$1,$B14,F$1,$B$1) -> 0 | G14: =_xll.EQNXTDZ($A$1,$B14,G$1,$B$1) -> 0 | H14: =_xll.EQNXTDZ($A$1,$B14,H$1,$B$1) -> 0 | I14: =_xll.EQNXTDZ($A$1,$B14,I$1,$B$1) -> 0 | J14: =_xll.EQNXTDZ($A$1,$B14,J$1,$B$1) -> 0 | ... BV14: =_xll.EQNXTDZ($A$1,$B14,BV$1,$B$1) -> 0
A15: Electricity Power & Fuel Cost | B15: QTR_ELECTRICITY_POWER_FUEL | C15: =_xll.EQNXTDZ($A$1,$B15,C$1,$B$1) -> 0 | D15: =_xll.EQNXTDZ($A$1,$B15,D$1,$B$1) -> 0 | E15: =_xll.EQNXTDZ($A$1,$B15,E$1,$B$1) -> 0 | F15: =_xll.EQNXTDZ($A$1,$B15,F$1,$B$1) -> 0 | G15: =_xll.EQNXTDZ($A$1,$B15,G$1,$B$1) -> 0 | H15: =_xll.EQNXTDZ($A$1,$B15,H$1,$B$1) -> 0 | I15: =_xll.EQNXTDZ($A$1,$B15,I$1,$B$1) -> 0 | J15: =_xll.EQNXTDZ($A$1,$B15,J$1,$B$1) -> 0 | ... BV15: =_xll.EQNXTDZ($A$1,$B15,BV$1,$B$1) -> 0
A16: Employee Cost | B16: QTR_EXPLOYEE_COST | C16: =_xll.EQNXTDZ($A$1,$B16,C$1,$B$1) -> 0 | D16: =_xll.EQNXTDZ($A$1,$B16,D$1,$B$1) -> 0 | E16: =_xll.EQNXTDZ($A$1,$B16,E$1,$B$1) -> 0 | F16: =_xll.EQNXTDZ($A$1,$B16,F$1,$B$1) -> 0 | G16: =_xll.EQNXTDZ($A$1,$B16,G$1,$B$1) -> 0 | H16: =_xll.EQNXTDZ($A$1,$B16,H$1,$B$1) -> 0 | I16: =_xll.EQNXTDZ($A$1,$B16,I$1,$B$1) -> 0 | J16: =_xll.EQNXTDZ($A$1,$B16,J$1,$B$1) -> 0 | ... BV16: =_xll.EQNXTDZ($A$1,$B16,BV$1,$B$1) -> 0
... A42: Consolidated PAT(after extra items) | B42: QTR_CONS_PAT_EXITM | C42: =_xll.EQNXTDZ($A$1,$B42,C$1,$B$1) -> 0 | D42: =_xll.EQNXTDZ($A$1,$B42,D$1,$B$1) -> 0 | E42: =_xll.EQNXTDZ($A$1,$B42,E$1,$B$1) -> 0 | F42: =_xll.EQNXTDZ($A$1,$B42,F$1,$B$1) -> 0 | G42: =_xll.EQNXTDZ($A$1,$B42,G$1,$B$1) -> 0 | H42: =_xll.EQNXTDZ($A$1,$B42,H$1,$B$1) -> 0 | I42: =_xll.EQNXTDZ($A$1,$B42,I$1,$B$1) -> 0 | J42: =_xll.EQNXTDZ($A$1,$B42,J$1,$B$1) -> 0 | ... BV42: =_xll.EQNXTDZ($A$1,$B42,BV$1,$B$1) -> 0
A44: Field Description | B44: Field Name
A45: Equity Capital | B45: QTR_EQUITY_CAP | C45: =_xll.EQNXTDZ($A$1,$B45,C$1,$B$1) -> 0 | D45: =_xll.EQNXTDZ($A$1,$B45,D$1,$B$1) -> 0 | E45: =_xll.EQNXTDZ($A$1,$B45,E$1,$B$1) -> 0 | F45: =_xll.EQNXTDZ($A$1,$B45,F$1,$B$1) -> 0 | G45: =_xll.EQNXTDZ($A$1,$B45,G$1,$B$1) -> 0 | H45: =_xll.EQNXTDZ($A$1,$B45,H$1,$B$1) -> 0 | I45: =_xll.EQNXTDZ($A$1,$B45,I$1,$B$1) -> 0 | J45: =_xll.EQNXTDZ($A$1,$B45,J$1,$B$1) -> 0 | ... BV45: =_xll.EQNXTDZ($A$1,$B45,BV$1,$B$1) -> 0
A46: Face Value | B46: QTR_FV | C46: =_xll.EQNXTDZ($A$1,$B46,C$1,$B$1) -> 0 | D46: =_xll.EQNXTDZ($A$1,$B46,D$1,$B$1) -> 0 | E46: =_xll.EQNXTDZ($A$1,$B46,E$1,$B$1) -> 0 | F46: =_xll.EQNXTDZ($A$1,$B46,F$1,$B$1) -> 0 | G46: =_xll.EQNXTDZ($A$1,$B46,G$1,$B$1) -> 0 | H46: =_xll.EQNXTDZ($A$1,$B46,H$1,$B$1) -> 0 | I46: =_xll.EQNXTDZ($A$1,$B46,I$1,$B$1) -> 0 | J46: =_xll.EQNXTDZ($A$1,$B46,J$1,$B$1) -> 0 | ... BV46: =_xll.EQNXTDZ($A$1,$B46,BV$1,$B$1) -> 0
A47: Month End | B47: BMONTH_MONTHEND | C47: =_xll.EQNXTDZ($A$1,$B47,C$5) -> 0 | D47: =_xll.EQNXTDZ($A$1,$B47,D$5) -> 0 | E47: =_xll.EQNXTDZ($A$1,$B47,E$5) -> 0 | F47: =_xll.EQNXTDZ($A$1,$B47,F$5) -> 0 | G47: =_xll.EQNXTDZ($A$1,$B47,G$5) -> 0 | H47: =_xll.EQNXTDZ($A$1,$B47,H$5) -> 0 | I47: =_xll.EQNXTDZ($A$1,$B47,I$5) -> 0 | J47: =_xll.EQNXTDZ($A$1,$B47,J$5) -> 0 | ... BV47: =_xll.EQNXTDZ($A$1,$B47,BV$5) -> 0
A48: Close | B48: BMONTH_CLOSE | C48: =_xll.EQNXTDZ($A$1,$B48,C$5) -> 0 | D48: =_xll.EQNXTDZ($A$1,$B48,D$5) -> 0 | E48: =_xll.EQNXTDZ($A$1,$B48,E$5) -> 0 | F48: =_xll.EQNXTDZ($A$1,$B48,F$5) -> 0 | G48: =_xll.EQNXTDZ($A$1,$B48,G$5) -> 0 | H48: =_xll.EQNXTDZ($A$1,$B48,H$5) -> 0 | I48: =_xll.EQNXTDZ($A$1,$B48,I$5) -> 0 | J48: =_xll.EQNXTDZ($A$1,$B48,J$5) -> 0 | ... BV48: =_xll.EQNXTDZ($A$1,$B48,BV$5) -> 0
A49: Total of Promoter and Promoter Group | B49: SHP_TPFTOTALPROMOTER | C49: =_xll.EQNXTDZ($A$1,$B49,C$5) -> 0 | D49: =_xll.EQNXTDZ($A$1,$B49,D$5) -> 0 | E49: =_xll.EQNXTDZ($A$1,$B49,E$5) -> 0 | F49: =_xll.EQNXTDZ($A$1,$B49,F$5) -> 0 | G49: =_xll.EQNXTDZ($A$1,$B49,G$5) -> 0 | H49: =_xll.EQNXTDZ($A$1,$B49,H$5) -> 0 | I49: =_xll.EQNXTDZ($A$1,$B49,I$5) -> 0 | J49: =_xll.EQNXTDZ($A$1,$B49,J$5) -> 0 | ... BV49: =_xll.EQNXTDZ($A$1,$B49,BV$5) -> 0
A50: Total of Promoter and Promoter Group Pledged | B50: SHP_PSHFTOTALPROMOTER | C50: =_xll.EQNXTDZ($A$1,$B50,C$5) -> 0 | D50: =_xll.EQNXTDZ($A$1,$B50,D$5) -> 0 | E50: =_xll.EQNXTDZ($A$1,$B50,E$5) -> 0 | F50: =_xll.EQNXTDZ($A$1,$B50,F$5) -> 0 | G50: =_xll.EQNXTDZ($A$1,$B50,G$5) -> 0 | H50: =_xll.EQNXTDZ($A$1,$B50,H$5) -> 0 | I50: =_xll.EQNXTDZ($A$1,$B50,I$5) -> 0 | J50: =_xll.EQNXTDZ($A$1,$B50,J$5) -> 0 | ... BV50: =_xll.EQNXTDZ($A$1,$B50,BV$5) -> 0
A54: Field Description | B54: Field Name | C54: =_xll.EQNXTDZ($A$1,$B54,C$5) -> 0 | D54: =_xll.EQNXTDZ($A$1,$B54,D$5) -> 0 | E54: =_xll.EQNXTDZ($A$1,$B54,E$5) -> 0 | F54: =_xll.EQNXTDZ($A$1,$B54,F$5) -> 0 | G54: =_xll.EQNXTDZ($A$1,$B54,G$5) -> 0 | H54: =_xll.EQNXTDZ($A$1,$B54,H$5) -> 0 | I54: =_xll.EQNXTDZ($A$1,$B54,I$5) -> 0 | J54: =_xll.EQNXTDZ($A$1,$B54,J$5) -> 0 | ... BV54: =_xll.EQNXTDZ($A$1,$B54,BV$5) -> 0
A55: Year End | B55: QTRB_DATE_END | C55: =_xll.EQNXTDZ($A$1,$B55,C$5,$B$1) -> 0 | D55: =_xll.EQNXTDZ($A$1,$B55,D$5,$B$1) -> 0 | E55: =_xll.EQNXTDZ($A$1,$B55,E$5,$B$1) -> 0 | F55: =_xll.EQNXTDZ($A$1,$B55,F$5,$B$1) -> 0 | G55: =_xll.EQNXTDZ($A$1,$B55,G$5,$B$1) -> 0 | H55: =_xll.EQNXTDZ($A$1,$B55,H$5,$B$1) -> 0 | I55: =_xll.EQNXTDZ($A$1,$B55,I$5,$B$1) -> 0 | J55: =_xll.EQNXTDZ($A$1,$B55,J$5,$B$1) -> 0 | ... BV55: =_xll.EQNXTDZ($A$1,$B55,BV$5,$B$1) -> 0
A56: Share Capital | B56: QTRB_SHARE_CAPITAL | C56: =_xll.EQNXTDZ($A$1,$B56,C$5,$B$1) -> 0 | D56: =_xll.EQNXTDZ($A$1,$B56,D$5,$B$1) -> 0 | E56: =_xll.EQNXTDZ($A$1,$B56,E$5,$B$1) -> 0 | F56: =_xll.EQNXTDZ($A$1,$B56,F$5,$B$1) -> 0 | G56: =_xll.EQNXTDZ($A$1,$B56,G$5,$B$1) -> 0 | H56: =_xll.EQNXTDZ($A$1,$B56,H$5,$B$1) -> 0 | I56: =_xll.EQNXTDZ($A$1,$B56,I$5,$B$1) -> 0 | J56: =_xll.EQNXTDZ($A$1,$B56,J$5,$B$1) -> 0 | ... BV56: =_xll.EQNXTDZ($A$1,$B56,BV$5,$B$1) -> 0
A57: Share Warrants & outstandings | B57: QTRB_SHAREWARNDOUT | C57: =_xll.EQNXTDZ($A$1,$B57,C$5,$B$1) -> 0 | D57: =_xll.EQNXTDZ($A$1,$B57,D$5,$B$1) -> 0 | E57: =_xll.EQNXTDZ($A$1,$B57,E$5,$B$1) -> 0 | F57: =_xll.EQNXTDZ($A$1,$B57,F$5,$B$1) -> 0 | G57: =_xll.EQNXTDZ($A$1,$B57,G$5,$B$1) -> 0 | H57: =_xll.EQNXTDZ($A$1,$B57,H$5,$B$1) -> 0 | I57: =_xll.EQNXTDZ($A$1,$B57,I$5,$B$1) -> 0 | J57: =_xll.EQNXTDZ($A$1,$B57,J$5,$B$1) -> 0 | ... BV57: =_xll.EQNXTDZ($A$1,$B57,BV$5,$B$1) -> 0
A58: Reserves & Surplus | B58: QTRB_RESERVE | C58: =_xll.EQNXTDZ($A$1,$B58,C$5,$B$1) -> 0 | D58: =_xll.EQNXTDZ($A$1,$B58,D$5,$B$1) -> 0 | E58: =_xll.EQNXTDZ($A$1,$B58,E$5,$B$1) -> 0 | F58: =_xll.EQNXTDZ($A$1,$B58,F$5,$B$1) -> 0 | G58: =_xll.EQNXTDZ($A$1,$B58,G$5,$B$1) -> 0 | H58: =_xll.EQNXTDZ($A$1,$B58,H$5,$B$1) -> 0 | I58: =_xll.EQNXTDZ($A$1,$B58,I$5,$B$1) -> 0 | J58: =_xll.EQNXTDZ($A$1,$B58,J$5,$B$1) -> 0 | ... BV58: =_xll.EQNXTDZ($A$1,$B58,BV$5,$B$1) -> 0
A59: Shareholder's Funds | B59: QTRB_SHAREHODERS_FUNDS | C59: =_xll.EQNXTDZ($A$1,$B59,C$5,$B$1) -> 0 | D59: =_xll.EQNXTDZ($A$1,$B59,D$5,$B$1) -> 0 | E59: =_xll.EQNXTDZ($A$1,$B59,E$5,$B$1) -> 0 | F59: =_xll.EQNXTDZ($A$1,$B59,F$5,$B$1) -> 0 | G59: =_xll.EQNXTDZ($A$1,$B59,G$5,$B$1) -> 0 | H59: =_xll.EQNXTDZ($A$1,$B59,H$5,$B$1) -> 0 | I59: =_xll.EQNXTDZ($A$1,$B59,I$5,$B$1) -> 0 | J59: =_xll.EQNXTDZ($A$1,$B59,J$5,$B$1) -> 0 | ... BV59: =_xll.EQNXTDZ($A$1,$B59,BV$5,$B$1) -> 0
A60: Minority Interest | B60: QTRB_MINORITY_INTEREST_BS | C60: =_xll.EQNXTDZ($A$1,$B60,C$5,$B$1) -> 0 | D60: =_xll.EQNXTDZ($A$1,$B60,D$5,$B$1) -> 0 | E60: =_xll.EQNXTDZ($A$1,$B60,E$5,$B$1) -> 0 | F60: =_xll.EQNXTDZ($A$1,$B60,F$5,$B$1) -> 0 | G60: =_xll.EQNXTDZ($A$1,$B60,G$5,$B$1) -> 0 | H60: =_xll.EQNXTDZ($A$1,$B60,H$5,$B$1) -> 0 | I60: =_xll.EQNXTDZ($A$1,$B60,I$5,$B$1) -> 0 | J60: =_xll.EQNXTDZ($A$1,$B60,J$5,$B$1) -> 0 | ... BV60: =_xll.EQNXTDZ($A$1,$B60,BV$5,$B$1) -> 0
A61: Long Term Borrowings | B61: QTRB_TOTAL_DEBTS | C61: =_xll.EQNXTDZ($A$1,$B61,C$5,$B$1) -> 0 | D61: =_xll.EQNXTDZ($A$1,$B61,D$5,$B$1) -> 0 | E61: =_xll.EQNXTDZ($A$1,$B61,E$5,$B$1) -> 0 | F61: =_xll.EQNXTDZ($A$1,$B61,F$5,$B$1) -> 0 | G61: =_xll.EQNXTDZ($A$1,$B61,G$5,$B$1) -> 0 | H61: =_xll.EQNXTDZ($A$1,$B61,H$5,$B$1) -> 0 | I61: =_xll.EQNXTDZ($A$1,$B61,I$5,$B$1) -> 0 | J61: =_xll.EQNXTDZ($A$1,$B61,J$5,$B$1) -> 0 | ... BV61: =_xll.EQNXTDZ($A$1,$B61,BV$5,$B$1) -> 0
A62: Secured Loans | B62: QTRB_SECURED_LOANS | C62: =_xll.EQNXTDZ($A$1,$B62,C$5,$B$1) -> 0 | D62: =_xll.EQNXTDZ($A$1,$B62,D$5,$B$1) -> 0 | E62: =_xll.EQNXTDZ($A$1,$B62,E$5,$B$1) -> 0 | F62: =_xll.EQNXTDZ($A$1,$B62,F$5,$B$1) -> 0 | G62: =_xll.EQNXTDZ($A$1,$B62,G$5,$B$1) -> 0 | H62: =_xll.EQNXTDZ($A$1,$B62,H$5,$B$1) -> 0 | I62: =_xll.EQNXTDZ($A$1,$B62,I$5,$B$1) -> 0 | J62: =_xll.EQNXTDZ($A$1,$B62,J$5,$B$1) -> 0 | ... BV62: =_xll.EQNXTDZ($A$1,$B62,BV$5,$B$1) -> 0
A63: Unsecured Loans | B63: QTRB_UNSECURED_LOANS_NF | C63: =_xll.EQNXTDZ($A$1,$B63,C$5,$B$1) -> 0 | D63: =_xll.EQNXTDZ($A$1,$B63,D$5,$B$1) -> 0 | E63: =_xll.EQNXTDZ($A$1,$B63,E$5,$B$1) -> 0 | F63: =_xll.EQNXTDZ($A$1,$B63,F$5,$B$1) -> 0 | G63: =_xll.EQNXTDZ($A$1,$B63,G$5,$B$1) -> 0 | H63: =_xll.EQNXTDZ($A$1,$B63,H$5,$B$1) -> 0 | I63: =_xll.EQNXTDZ($A$1,$B63,I$5,$B$1) -> 0 | J63: =_xll.EQNXTDZ($A$1,$B63,J$5,$B$1) -> 0 | ... BV63: =_xll.EQNXTDZ($A$1,$B63,BV$5,$B$1) -> 0
A64: Other Long Term Liabilities | B64: QTRB_OTHER_LT_LIABILITIES | C64: =_xll.EQNXTDZ($A$1,$B64,C$5,$B$1) -> 0 | D64: =_xll.EQNXTDZ($A$1,$B64,D$5,$B$1) -> 0 | E64: =_xll.EQNXTDZ($A$1,$B64,E$5,$B$1) -> 0 | F64: =_xll.EQNXTDZ($A$1,$B64,F$5,$B$1) -> 0 | G64: =_xll.EQNXTDZ($A$1,$B64,G$5,$B$1) -> 0 | H64: =_xll.EQNXTDZ($A$1,$B64,H$5,$B$1) -> 0 | I64: =_xll.EQNXTDZ($A$1,$B64,I$5,$B$1) -> 0 | J64: =_xll.EQNXTDZ($A$1,$B64,J$5,$B$1) -> 0 | ... BV64: =_xll.EQNXTDZ($A$1,$B64,BV$5,$B$1) -> 0
A65: Long Term Trade Payables | B65: QTRB_LT_TRADE_PAYABLE | C65: =_xll.EQNXTDZ($A$1,$B65,C$5,$B$1) -> 0 | D65: =_xll.EQNXTDZ($A$1,$B65,D$5,$B$1) -> 0 | E65: =_xll.EQNXTDZ($A$1,$B65,E$5,$B$1) -> 0 | F65: =_xll.EQNXTDZ($A$1,$B65,F$5,$B$1) -> 0 | G65: =_xll.EQNXTDZ($A$1,$B65,G$5,$B$1) -> 0 | H65: =_xll.EQNXTDZ($A$1,$B65,H$5,$B$1) -> 0 | I65: =_xll.EQNXTDZ($A$1,$B65,I$5,$B$1) -> 0 | J65: =_xll.EQNXTDZ($A$1,$B65,J$5,$B$1) -> 0 | ... BV65: =_xll.EQNXTDZ($A$1,$B65,BV$5,$B$1) -> 0
A66: Lont Term Provisions | B66: QTRB_LT_PROVISIONS | C66: =_xll.EQNXTDZ($A$1,$B66,C$5,$B$1) -> 0 | D66: =_xll.EQNXTDZ($A$1,$B66,D$5,$B$1) -> 0 | E66: =_xll.EQNXTDZ($A$1,$B66,E$5,$B$1) -> 0 | F66: =_xll.EQNXTDZ($A$1,$B66,F$5,$B$1) -> 0 | G66: =_xll.EQNXTDZ($A$1,$B66,G$5,$B$1) -> 0 | H66: =_xll.EQNXTDZ($A$1,$B66,H$5,$B$1) -> 0 | I66: =_xll.EQNXTDZ($A$1,$B66,I$5,$B$1) -> 0 | J66: =_xll.EQNXTDZ($A$1,$B66,J$5,$B$1) -> 0 | ... BV66: =_xll.EQNXTDZ($A$1,$B66,BV$5,$B$1) -> 0
... A97: Total Assets | B97: QTRB_TOTAL_APPLICATIONS | C97: =_xll.EQNXTDZ($A$1,$B97,C$5,$B$1) -> 0 | D97: =_xll.EQNXTDZ($A$1,$B97,D$5,$B$1) -> 0 | E97: =_xll.EQNXTDZ($A$1,$B97,E$5,$B$1) -> 0 | F97: =_xll.EQNXTDZ($A$1,$B97,F$5,$B$1) -> 0 | G97: =_xll.EQNXTDZ($A$1,$B97,G$5,$B$1) -> 0 | H97: =_xll.EQNXTDZ($A$1,$B97,H$5,$B$1) -> 0 | I97: =_xll.EQNXTDZ($A$1,$B97,I$5,$B$1) -> 0 | J97: =_xll.EQNXTDZ($A$1,$B97,J$5,$B$1) -> 0 | ... BV97: =_xll.EQNXTDZ($A$1,$B97,BV$5,$B$1) -> 0

Sheet Annual Raw
A1: 320028 | B1: X | C1: 200109 | D1: 200209 | E1: 200909 | F1: 200409 | G1: 200509 | H1: 200609 | I1: 200709 | J1: 200809 | K1: 200909 | L1: 201009 | M1: 201109 | N1: 201209 | O1: 201309 | P1: 201409 | Q1: 201509 | R1: 201609 | S1: 201709 | T1: 201809 | U1: 201909 | V1: 202009 | W1: 202109 | X1: 202209 | Y1: 202309 | Z1: 202409 | AA1: 202509 | AB1: 202609 | AC1: 202709 | AD1: 202809 | AE1: 202909 | AF1: 209009
A3: Field Description | B3: Field Name
A4: Company Name | B4: CD_COMPNAME | C4: =_xll.EQNXTDZ(A1,B4,"L") -> Siemens Energy India Ltd.
A5: Year End | B5: PL_YEAR_END | C5: =_xll.EQNXTDZ($A$1,$B5,C$1,$B$1) -> 0 | D5: =_xll.EQNXTDZ($A$1,$B5,D$1,$B$1) -> 0 | E5: =_xll.EQNXTDZ($A$1,$B5,E$1,$B$1) -> 0 | F5: =_xll.EQNXTDZ($A$1,$B5,F$1,$B$1) -> 0 | G5: =_xll.EQNXTDZ($A$1,$B5,G$1,$B$1) -> 0 | H5: =_xll.EQNXTDZ($A$1,$B5,H$1,$B$1) -> 0 | I5: =_xll.EQNXTDZ($A$1,$B5,I$1,$B$1) -> 0 | J5: =_xll.EQNXTDZ($A$1,$B5,J$1,$B$1) -> 0 | ... AF5: =_xll.EQNXTDZ($A$1,$B5,AF$1,$B$1) -> 0
A6: Sales Turnover | B6: PL_TOTAL_GROSS_SALES | C6: =_xll.EQNXTDZ($A$1,$B6,C$1,$B$1) -> 0 | D6: =_xll.EQNXTDZ($A$1,$B6,D$1,$B$1) -> 0 | E6: =_xll.EQNXTDZ($A$1,$B6,E$1,$B$1) -> 0 | F6: =_xll.EQNXTDZ($A$1,$B6,F$1,$B$1) -> 0 | G6: =_xll.EQNXTDZ($A$1,$B6,G$1,$B$1) -> 0 | H6: =_xll.EQNXTDZ($A$1,$B6,H$1,$B$1) -> 0 | I6: =_xll.EQNXTDZ($A$1,$B6,I$1,$B$1) -> 0 | J6: =_xll.EQNXTDZ($A$1,$B6,J$1,$B$1) -> 0 | ... AF6: =_xll.EQNXTDZ($A$1,$B6,AF$1,$B$1) -> 0
A7: Less: Inter divisional transfers | B7: PL_INTER_DIV_TRF | C7: =_xll.EQNXTDZ($A$1,$B7,C$1,$B$1) -> 0 | D7: =_xll.EQNXTDZ($A$1,$B7,D$1,$B$1) -> 0 | E7: =_xll.EQNXTDZ($A$1,$B7,E$1,$B$1) -> 0 | F7: =_xll.EQNXTDZ($A$1,$B7,F$1,$B$1) -> 0 | G7: =_xll.EQNXTDZ($A$1,$B7,G$1,$B$1) -> 0 | H7: =_xll.EQNXTDZ($A$1,$B7,H$1,$B$1) -> 0 | I7: =_xll.EQNXTDZ($A$1,$B7,I$1,$B$1) -> 0 | J7: =_xll.EQNXTDZ($A$1,$B7,J$1,$B$1) -> 0 | ... AF7: =_xll.EQNXTDZ($A$1,$B7,AF$1,$B$1) -> 0
A8: Less: Sales Returns | B8: PL_SALES_RETURN | C8: =_xll.EQNXTDZ($A$1,$B8,C$1,$B$1) -> 0 | D8: =_xll.EQNXTDZ($A$1,$B8,D$1,$B$1) -> 0 | E8: =_xll.EQNXTDZ($A$1,$B8,E$1,$B$1) -> 0 | F8: =_xll.EQNXTDZ($A$1,$B8,F$1,$B$1) -> 0 | G8: =_xll.EQNXTDZ($A$1,$B8,G$1,$B$1) -> 0 | H8: =_xll.EQNXTDZ($A$1,$B8,H$1,$B$1) -> 0 | I8: =_xll.EQNXTDZ($A$1,$B8,I$1,$B$1) -> 0 | J8: =_xll.EQNXTDZ($A$1,$B8,J$1,$B$1) -> 0 | ... AF8: =_xll.EQNXTDZ($A$1,$B8,AF$1,$B$1) -> 0
A9: Less: Excise | B9: PL_EXCISE | C9: =_xll.EQNXTDZ($A$1,$B9,C$1,$B$1) -> 0 | D9: =_xll.EQNXTDZ($A$1,$B9,D$1,$B$1) -> 0 | E9: =_xll.EQNXTDZ($A$1,$B9,E$1,$B$1) -> 0 | F9: =_xll.EQNXTDZ($A$1,$B9,F$1,$B$1) -> 0 | G9: =_xll.EQNXTDZ($A$1,$B9,G$1,$B$1) -> 0 | H9: =_xll.EQNXTDZ($A$1,$B9,H$1,$B$1) -> 0 | I9: =_xll.EQNXTDZ($A$1,$B9,I$1,$B$1) -> 0 | J9: =_xll.EQNXTDZ($A$1,$B9,J$1,$B$1) -> 0 | ... AF9: =_xll.EQNXTDZ($A$1,$B9,AF$1,$B$1) -> 0
A10: Net Sales | B10: PL_NET_SALES | C10: =_xll.EQNXTDZ($A$1,$B10,C$1,$B$1) -> 0 | D10: =_xll.EQNXTDZ($A$1,$B10,D$1,$B$1) -> 0 | E10: =_xll.EQNXTDZ($A$1,$B10,E$1,$B$1) -> 0 | F10: =_xll.EQNXTDZ($A$1,$B10,F$1,$B$1) -> 0 | G10: =_xll.EQNXTDZ($A$1,$B10,G$1,$B$1) -> 0 | H10: =_xll.EQNXTDZ($A$1,$B10,H$1,$B$1) -> 0 | I10: =_xll.EQNXTDZ($A$1,$B10,I$1,$B$1) -> 0 | J10: =_xll.EQNXTDZ($A$1,$B10,J$1,$B$1) -> 0 | ... AF10: =_xll.EQNXTDZ($A$1,$B10,AF$1,$B$1) -> 0
A11: Increase/Decrease in Stock | B11: PL_INC_DEC_INVENTORY | C11: =_xll.EQNXTDZ($A$1,$B11,C$1,$B$1) -> 0 | D11: =_xll.EQNXTDZ($A$1,$B11,D$1,$B$1) -> 0 | E11: =_xll.EQNXTDZ($A$1,$B11,E$1,$B$1) -> 0 | F11: =_xll.EQNXTDZ($A$1,$B11,F$1,$B$1) -> 0 | G11: =_xll.EQNXTDZ($A$1,$B11,G$1,$B$1) -> 0 | H11: =_xll.EQNXTDZ($A$1,$B11,H$1,$B$1) -> 0 | I11: =_xll.EQNXTDZ($A$1,$B11,I$1,$B$1) -> 0 | J11: =_xll.EQNXTDZ($A$1,$B11,J$1,$B$1) -> 0 | ... AF11: =_xll.EQNXTDZ($A$1,$B11,AF$1,$B$1) -> 0
A12: Raw Material Consumed | B12: PL_RAW_MATRS_CONSUMED | C12: =_xll.EQNXTDZ($A$1,$B12,C$1,$B$1) -> 0 | D12: =_xll.EQNXTDZ($A$1,$B12,D$1,$B$1) -> 0 | E12: =_xll.EQNXTDZ($A$1,$B12,E$1,$B$1) -> 0 | F12: =_xll.EQNXTDZ($A$1,$B12,F$1,$B$1) -> 0 | G12: =_xll.EQNXTDZ($A$1,$B12,G$1,$B$1) -> 0 | H12: =_xll.EQNXTDZ($A$1,$B12,H$1,$B$1) -> 0 | I12: =_xll.EQNXTDZ($A$1,$B12,I$1,$B$1) -> 0 | J12: =_xll.EQNXTDZ($A$1,$B12,J$1,$B$1) -> 0 | ... AF12: =_xll.EQNXTDZ($A$1,$B12,AF$1,$B$1) -> 0
A13: Power & Fuel Cost | B13: PL_POWER_FUEL | C13: =_xll.EQNXTDZ($A$1,$B13,C$1,$B$1) -> 0 | D13: =_xll.EQNXTDZ($A$1,$B13,D$1,$B$1) -> 0 | E13: =_xll.EQNXTDZ($A$1,$B13,E$1,$B$1) -> 0 | F13: =_xll.EQNXTDZ($A$1,$B13,F$1,$B$1) -> 0 | G13: =_xll.EQNXTDZ($A$1,$B13,G$1,$B$1) -> 0 | H13: =_xll.EQNXTDZ($A$1,$B13,H$1,$B$1) -> 0 | I13: =_xll.EQNXTDZ($A$1,$B13,I$1,$B$1) -> 0 | J13: =_xll.EQNXTDZ($A$1,$B13,J$1,$B$1) -> 0 | ... AF13: =_xll.EQNXTDZ($A$1,$B13,AF$1,$B$1) -> 0
A14: Employee Cost | B14: PL_EMPLOYEES | C14: =_xll.EQNXTDZ($A$1,$B14,C$1,$B$1) -> 0 | D14: =_xll.EQNXTDZ($A$1,$B14,D$1,$B$1) -> 0 | E14: =_xll.EQNXTDZ($A$1,$B14,E$1,$B$1) -> 0 | F14: =_xll.EQNXTDZ($A$1,$B14,F$1,$B$1) -> 0 | G14: =_xll.EQNXTDZ($A$1,$B14,G$1,$B$1) -> 0 | H14: =_xll.EQNXTDZ($A$1,$B14,H$1,$B$1) -> 0 | I14: =_xll.EQNXTDZ($A$1,$B14,I$1,$B$1) -> 0 | J14: =_xll.EQNXTDZ($A$1,$B14,J$1,$B$1) -> 0 | ... AF14: =_xll.EQNXTDZ($A$1,$B14,AF$1,$B$1) -> 0
A15: Operating & Manufacturing Expenses | B15: PL_GEN_OTHER_MFG_EXPS | C15: =_xll.EQNXTDZ($A$1,$B15,C$1,$B$1) -> 0 | D15: =_xll.EQNXTDZ($A$1,$B15,D$1,$B$1) -> 0 | E15: =_xll.EQNXTDZ($A$1,$B15,E$1,$B$1) -> 0 | F15: =_xll.EQNXTDZ($A$1,$B15,F$1,$B$1) -> 0 | G15: =_xll.EQNXTDZ($A$1,$B15,G$1,$B$1) -> 0 | H15: =_xll.EQNXTDZ($A$1,$B15,H$1,$B$1) -> 0 | I15: =_xll.EQNXTDZ($A$1,$B15,I$1,$B$1) -> 0 | J15: =_xll.EQNXTDZ($A$1,$B15,J$1,$B$1) -> 0 | ... AF15: =_xll.EQNXTDZ($A$1,$B15,AF$1,$B$1) -> 0
A16: Cost of Software development | B16: PL_COST_SW | C16: =_xll.EQNXTDZ($A$1,$B16,C$1,$B$1) -> 0 | D16: =_xll.EQNXTDZ($A$1,$B16,D$1,$B$1) -> 0 | E16: =_xll.EQNXTDZ($A$1,$B16,E$1,$B$1) -> 0 | F16: =_xll.EQNXTDZ($A$1,$B16,F$1,$B$1) -> 0 | G16: =_xll.EQNXTDZ($A$1,$B16,G$1,$B$1) -> 0 | H16: =_xll.EQNXTDZ($A$1,$B16,H$1,$B$1) -> 0 | I16: =_xll.EQNXTDZ($A$1,$B16,I$1,$B$1) -> 0 | J16: =_xll.EQNXTDZ($A$1,$B16,J$1,$B$1) -> 0 | ... AF16: =_xll.EQNXTDZ($A$1,$B16,AF$1,$B$1) -> 0
... A36: Profit After Tax from Discontinued Operations | B36: PL_PAT_DIS_OP | C36: =_xll.EQNXTDZ($A$1,$B36,C$1,$B$1) -> 0 | D36: =_xll.EQNXTDZ($A$1,$B36,D$1,$B$1) -> 0 | E36: =_xll.EQNXTDZ($A$1,$B36,E$1,$B$1) -> 0 | F36: =_xll.EQNXTDZ($A$1,$B36,F$1,$B$1) -> 0 | G36: =_xll.EQNXTDZ($A$1,$B36,G$1,$B$1) -> 0 | H36: =_xll.EQNXTDZ($A$1,$B36,H$1,$B$1) -> 0 | I36: =_xll.EQNXTDZ($A$1,$B36,I$1,$B$1) -> 0 | J36: =_xll.EQNXTDZ($A$1,$B36,J$1,$B$1) -> 0 | ... AF36: =_xll.EQNXTDZ($A$1,$B36,AF$1,$B$1) -> 0
A39: Field Description | B39: Field Name
A40: Year End | B40: BS_YEAR_END | C40: =_xll.EQNXTDZ($A$1,$B40,C$1,$B$1) -> 0 | D40: =_xll.EQNXTDZ($A$1,$B40,D$1,$B$1) -> 0 | E40: =_xll.EQNXTDZ($A$1,$B40,E$1,$B$1) -> 0 | F40: =_xll.EQNXTDZ($A$1,$B40,F$1,$B$1) -> 0 | G40: =_xll.EQNXTDZ($A$1,$B40,G$1,$B$1) -> 0 | H40: =_xll.EQNXTDZ($A$1,$B40,H$1,$B$1) -> 0 | I40: =_xll.EQNXTDZ($A$1,$B40,I$1,$B$1) -> 0 | J40: =_xll.EQNXTDZ($A$1,$B40,J$1,$B$1) -> 0 | ... AF40: =_xll.EQNXTDZ($A$1,$B40,AF$1,$B$1) -> 0
A41: Share Capital | B41: BS_SHARE_CAPITAL | C41: =_xll.EQNXTDZ($A$1,$B41,C$1,$B$1) -> 0 | D41: =_xll.EQNXTDZ($A$1,$B41,D$1,$B$1) -> 0 | E41: =_xll.EQNXTDZ($A$1,$B41,E$1,$B$1) -> 0 | F41: =_xll.EQNXTDZ($A$1,$B41,F$1,$B$1) -> 0 | G41: =_xll.EQNXTDZ($A$1,$B41,G$1,$B$1) -> 0 | H41: =_xll.EQNXTDZ($A$1,$B41,H$1,$B$1) -> 0 | I41: =_xll.EQNXTDZ($A$1,$B41,I$1,$B$1) -> 0 | J41: =_xll.EQNXTDZ($A$1,$B41,J$1,$B$1) -> 0 | ... AF41: =_xll.EQNXTDZ($A$1,$B41,AF$1,$B$1) -> 0
A42: Share Warrants & Outstandings | B42: BS_SHAREWROUTST | C42: =_xll.EQNXTDZ($A$1,$B42,C$1,$B$1) -> 0 | D42: =_xll.EQNXTDZ($A$1,$B42,D$1,$B$1) -> 0 | E42: =_xll.EQNXTDZ($A$1,$B42,E$1,$B$1) -> 0 | F42: =_xll.EQNXTDZ($A$1,$B42,F$1,$B$1) -> 0 | G42: =_xll.EQNXTDZ($A$1,$B42,G$1,$B$1) -> 0 | H42: =_xll.EQNXTDZ($A$1,$B42,H$1,$B$1) -> 0 | I42: =_xll.EQNXTDZ($A$1,$B42,I$1,$B$1) -> 0 | J42: =_xll.EQNXTDZ($A$1,$B42,J$1,$B$1) -> 0 | ... AF42: =_xll.EQNXTDZ($A$1,$B42,AF$1,$B$1) -> 0
A43: Total Reserves | B43: BS_RESERVE | C43: =_xll.EQNXTDZ($A$1,$B43,C$1,$B$1) -> 0 | D43: =_xll.EQNXTDZ($A$1,$B43,D$1,$B$1) -> 0 | E43: =_xll.EQNXTDZ($A$1,$B43,E$1,$B$1) -> 0 | F43: =_xll.EQNXTDZ($A$1,$B43,F$1,$B$1) -> 0 | G43: =_xll.EQNXTDZ($A$1,$B43,G$1,$B$1) -> 0 | H43: =_xll.EQNXTDZ($A$1,$B43,H$1,$B$1) -> 0 | I43: =_xll.EQNXTDZ($A$1,$B43,I$1,$B$1) -> 0 | J43: =_xll.EQNXTDZ($A$1,$B43,J$1,$B$1) -> 0 | ... AF43: =_xll.EQNXTDZ($A$1,$B43,AF$1,$B$1) -> 0
A44: Shareholder's Funds | B44: BS_SHAREHODERS_FUNDS | C44: =_xll.EQNXTDZ($A$1,$B44,C$1,$B$1) -> 0 | D44: =_xll.EQNXTDZ($A$1,$B44,D$1,$B$1) -> 0 | E44: =_xll.EQNXTDZ($A$1,$B44,E$1,$B$1) -> 0 | F44: =_xll.EQNXTDZ($A$1,$B44,F$1,$B$1) -> 0 | G44: =_xll.EQNXTDZ($A$1,$B44,G$1,$B$1) -> 0 | H44: =_xll.EQNXTDZ($A$1,$B44,H$1,$B$1) -> 0 | I44: =_xll.EQNXTDZ($A$1,$B44,I$1,$B$1) -> 0 | J44: =_xll.EQNXTDZ($A$1,$B44,J$1,$B$1) -> 0 | ... AF44: =_xll.EQNXTDZ($A$1,$B44,AF$1,$B$1) -> 0
A45: Minority Interest | B45: BS_MINORITY_INTEREST | C45: =_xll.EQNXTDZ($A$1,$B45,C$1,$B$1) -> 0 | D45: =_xll.EQNXTDZ($A$1,$B45,D$1,$B$1) -> 0 | E45: =_xll.EQNXTDZ($A$1,$B45,E$1,$B$1) -> 0 | F45: =_xll.EQNXTDZ($A$1,$B45,F$1,$B$1) -> 0 | G45: =_xll.EQNXTDZ($A$1,$B45,G$1,$B$1) -> 0 | H45: =_xll.EQNXTDZ($A$1,$B45,H$1,$B$1) -> 0 | I45: =_xll.EQNXTDZ($A$1,$B45,I$1,$B$1) -> 0 | J45: =_xll.EQNXTDZ($A$1,$B45,J$1,$B$1) -> 0 | ... AF45: =_xll.EQNXTDZ($A$1,$B45,AF$1,$B$1) -> 0
A46: Long-Term Borrowings | B46: BS_LTRM_BORROWING | C46: =_xll.EQNXTDZ($A$1,$B46,C$1,$B$1) -> 0 | D46: =_xll.EQNXTDZ($A$1,$B46,D$1,$B$1) -> 0 | E46: =_xll.EQNXTDZ($A$1,$B46,E$1,$B$1) -> 0 | F46: =_xll.EQNXTDZ($A$1,$B46,F$1,$B$1) -> 0 | G46: =_xll.EQNXTDZ($A$1,$B46,G$1,$B$1) -> 0 | H46: =_xll.EQNXTDZ($A$1,$B46,H$1,$B$1) -> 0 | I46: =_xll.EQNXTDZ($A$1,$B46,I$1,$B$1) -> 0 | J46: =_xll.EQNXTDZ($A$1,$B46,J$1,$B$1) -> 0 | ... AF46: =_xll.EQNXTDZ($A$1,$B46,AF$1,$B$1) -> 0
A47: Secured Loans | B47: BS_SECURED_LOANS | C47: =_xll.EQNXTDZ($A$1,$B47,C$1,$B$1) -> 0 | D47: =_xll.EQNXTDZ($A$1,$B47,D$1,$B$1) -> 0 | E47: =_xll.EQNXTDZ($A$1,$B47,E$1,$B$1) -> 0 | F47: =_xll.EQNXTDZ($A$1,$B47,F$1,$B$1) -> 0 | G47: =_xll.EQNXTDZ($A$1,$B47,G$1,$B$1) -> 0 | H47: =_xll.EQNXTDZ($A$1,$B47,H$1,$B$1) -> 0 | I47: =_xll.EQNXTDZ($A$1,$B47,I$1,$B$1) -> 0 | J47: =_xll.EQNXTDZ($A$1,$B47,J$1,$B$1) -> 0 | ... AF47: =_xll.EQNXTDZ($A$1,$B47,AF$1,$B$1) -> 0
A48: Unsecured Loans | B48: BS_UNSECURED_LOANS_NF | C48: =_xll.EQNXTDZ($A$1,$B48,C$1,$B$1) -> 0 | D48: =_xll.EQNXTDZ($A$1,$B48,D$1,$B$1) -> 0 | E48: =_xll.EQNXTDZ($A$1,$B48,E$1,$B$1) -> 0 | F48: =_xll.EQNXTDZ($A$1,$B48,F$1,$B$1) -> 0 | G48: =_xll.EQNXTDZ($A$1,$B48,G$1,$B$1) -> 0 | H48: =_xll.EQNXTDZ($A$1,$B48,H$1,$B$1) -> 0 | I48: =_xll.EQNXTDZ($A$1,$B48,I$1,$B$1) -> 0 | J48: =_xll.EQNXTDZ($A$1,$B48,J$1,$B$1) -> 0 | ... AF48: =_xll.EQNXTDZ($A$1,$B48,AF$1,$B$1) -> 0
A49: Deferred Tax Assets / Liabilities | B49: BS_NET_DEF_TAX_NF | C49: =_xll.EQNXTDZ($A$1,$B49,C$1,$B$1) -> 0 | D49: =_xll.EQNXTDZ($A$1,$B49,D$1,$B$1) -> 0 | E49: =_xll.EQNXTDZ($A$1,$B49,E$1,$B$1) -> 0 | F49: =_xll.EQNXTDZ($A$1,$B49,F$1,$B$1) -> 0 | G49: =_xll.EQNXTDZ($A$1,$B49,G$1,$B$1) -> 0 | H49: =_xll.EQNXTDZ($A$1,$B49,H$1,$B$1) -> 0 | I49: =_xll.EQNXTDZ($A$1,$B49,I$1,$B$1) -> 0 | J49: =_xll.EQNXTDZ($A$1,$B49,J$1,$B$1) -> 0 | ... AF49: =_xll.EQNXTDZ($A$1,$B49,AF$1,$B$1) -> 0
A50: Other Long Term Liabilities | B50: BS_OTH_LT_LIAB | C50: =_xll.EQNXTDZ($A$1,$B50,C$1,$B$1) -> 0 | D50: =_xll.EQNXTDZ($A$1,$B50,D$1,$B$1) -> 0 | E50: =_xll.EQNXTDZ($A$1,$B50,E$1,$B$1) -> 0 | F50: =_xll.EQNXTDZ($A$1,$B50,F$1,$B$1) -> 0 | G50: =_xll.EQNXTDZ($A$1,$B50,G$1,$B$1) -> 0 | H50: =_xll.EQNXTDZ($A$1,$B50,H$1,$B$1) -> 0 | I50: =_xll.EQNXTDZ($A$1,$B50,I$1,$B$1) -> 0 | J50: =_xll.EQNXTDZ($A$1,$B50,J$1,$B$1) -> 0 | ... AF50: =_xll.EQNXTDZ($A$1,$B50,AF$1,$B$1) -> 0
A51: Long Term Trade Payables | B51: BS_LT_TRADE_PAYABLES | C51: =_xll.EQNXTDZ($A$1,$B51,C$1,$B$1) -> 0 | D51: =_xll.EQNXTDZ($A$1,$B51,D$1,$B$1) -> 0 | E51: =_xll.EQNXTDZ($A$1,$B51,E$1,$B$1) -> 0 | F51: =_xll.EQNXTDZ($A$1,$B51,F$1,$B$1) -> 0 | G51: =_xll.EQNXTDZ($A$1,$B51,G$1,$B$1) -> 0 | H51: =_xll.EQNXTDZ($A$1,$B51,H$1,$B$1) -> 0 | I51: =_xll.EQNXTDZ($A$1,$B51,I$1,$B$1) -> 0 | J51: =_xll.EQNXTDZ($A$1,$B51,J$1,$B$1) -> 0 | ... AF51: =_xll.EQNXTDZ($A$1,$B51,AF$1,$B$1) -> 0
... A99: Estimated Capital Contracts Remaining | B99: BS_ESTIMATED_CAPITAL_CONTRACT | C99: =_xll.EQNXTDZ($A$1,$B99,C$1,$B$1) -> 0 | D99: =_xll.EQNXTDZ($A$1,$B99,D$1,$B$1) -> 0 | E99: =_xll.EQNXTDZ($A$1,$B99,E$1,$B$1) -> 0 | F99: =_xll.EQNXTDZ($A$1,$B99,F$1,$B$1) -> 0 | G99: =_xll.EQNXTDZ($A$1,$B99,G$1,$B$1) -> 0 | H99: =_xll.EQNXTDZ($A$1,$B99,H$1,$B$1) -> 0 | I99: =_xll.EQNXTDZ($A$1,$B99,I$1,$B$1) -> 0 | J99: =_xll.EQNXTDZ($A$1,$B99,J$1,$B$1) -> 0 | ... AF99: =_xll.EQNXTDZ($A$1,$B99,AF$1,$B$1) -> 0
A103: Field Description | B103: Field Name
A104: Equity Paid Up | B104: BS_EQUITY_PAIDUP | C104: =_xll.EQNXTDZ($A$1,$B104,C$1,$B$1) -> 0 | D104: =_xll.EQNXTDZ($A$1,$B104,D$1,$B$1) -> 0 | E104: =_xll.EQNXTDZ($A$1,$B104,E$1,$B$1) -> 0 | F104: =_xll.EQNXTDZ($A$1,$B104,F$1,$B$1) -> 0 | G104: =_xll.EQNXTDZ($A$1,$B104,G$1,$B$1) -> 0 | H104: =_xll.EQNXTDZ($A$1,$B104,H$1,$B$1) -> 0 | I104: =_xll.EQNXTDZ($A$1,$B104,I$1,$B$1) -> 0 | J104: =_xll.EQNXTDZ($A$1,$B104,J$1,$B$1) -> 0 | ... AF104: =_xll.EQNXTDZ($A$1,$B104,AF$1,$B$1) -> 0
A105: Face Value | B105: BS_FACE_VALUE | C105: =_xll.EQNXTDZ($A$1,$B105,C$1,$B$1) -> 0 | D105: =_xll.EQNXTDZ($A$1,$B105,D$1,$B$1) -> 0 | E105: =_xll.EQNXTDZ($A$1,$B105,E$1,$B$1) -> 0 | F105: =_xll.EQNXTDZ($A$1,$B105,F$1,$B$1) -> 0 | G105: =_xll.EQNXTDZ($A$1,$B105,G$1,$B$1) -> 0 | H105: =_xll.EQNXTDZ($A$1,$B105,H$1,$B$1) -> 0 | I105: =_xll.EQNXTDZ($A$1,$B105,I$1,$B$1) -> 0 | J105: =_xll.EQNXTDZ($A$1,$B105,J$1,$B$1) -> 0 | ... AF105: =_xll.EQNXTDZ($A$1,$B105,AF$1,$B$1) -> 0
A106: Close Price (Unit Curr.) | B106: FH_YEAR_PRICE | C106: =_xll.EQNXTDZ($A$1,$B106,C$1,$B$1) -> 0 | D106: =_xll.EQNXTDZ($A$1,$B106,D$1,$B$1) -> 0 | E106: =_xll.EQNXTDZ($A$1,$B106,E$1,$B$1) -> 0 | F106: =_xll.EQNXTDZ($A$1,$B106,F$1,$B$1) -> 0 | G106: =_xll.EQNXTDZ($A$1,$B106,G$1,$B$1) -> 0 | H106: =_xll.EQNXTDZ($A$1,$B106,H$1,$B$1) -> 0 | I106: =_xll.EQNXTDZ($A$1,$B106,I$1,$B$1) -> 0 | J106: =_xll.EQNXTDZ($A$1,$B106,J$1,$B$1) -> 0 | ... AF106: =_xll.EQNXTDZ($A$1,$B106,AF$1,$B$1) -> 0
A107: High Price (Unit Curr.) | B107: FH_HIGH | C107: =_xll.EQNXTDZ($A$1,$B107,C$1,$B$1) -> 0 | D107: =_xll.EQNXTDZ($A$1,$B107,D$1,$B$1) -> 0 | E107: =_xll.EQNXTDZ($A$1,$B107,E$1,$B$1) -> 0 | F107: =_xll.EQNXTDZ($A$1,$B107,F$1,$B$1) -> 0 | G107: =_xll.EQNXTDZ($A$1,$B107,G$1,$B$1) -> 0 | H107: =_xll.EQNXTDZ($A$1,$B107,H$1,$B$1) -> 0 | I107: =_xll.EQNXTDZ($A$1,$B107,I$1,$B$1) -> 0 | J107: =_xll.EQNXTDZ($A$1,$B107,J$1,$B$1) -> 0 | ... AF107: =_xll.EQNXTDZ($A$1,$B107,AF$1,$B$1) -> 0
A108: Low Price (Unit Curr.) | B108: FH_LOW | C108: =_xll.EQNXTDZ($A$1,$B108,C$1,$B$1) -> 0 | D108: =_xll.EQNXTDZ($A$1,$B108,D$1,$B$1) -> 0 | E108: =_xll.EQNXTDZ($A$1,$B108,E$1,$B$1) -> 0 | F108: =_xll.EQNXTDZ($A$1,$B108,F$1,$B$1) -> 0 | G108: =_xll.EQNXTDZ($A$1,$B108,G$1,$B$1) -> 0 | H108: =_xll.EQNXTDZ($A$1,$B108,H$1,$B$1) -> 0 | I108: =_xll.EQNXTDZ($A$1,$B108,I$1,$B$1) -> 0 | J108: =_xll.EQNXTDZ($A$1,$B108,J$1,$B$1) -> 0 | ... AF108: =_xll.EQNXTDZ($A$1,$B108,AF$1,$B$1) -> 0
A109: Market Capitalization | B109: FH_MCAP | C109: =_xll.EQNXTDZ($A$1,$B109,C$1,$B$1) -> 0 | D109: =_xll.EQNXTDZ($A$1,$B109,D$1,$B$1) -> 0 | E109: =_xll.EQNXTDZ($A$1,$B109,E$1,$B$1) -> 0 | F109: =_xll.EQNXTDZ($A$1,$B109,F$1,$B$1) -> 0 | G109: =_xll.EQNXTDZ($A$1,$B109,G$1,$B$1) -> 0 | H109: =_xll.EQNXTDZ($A$1,$B109,H$1,$B$1) -> 0 | I109: =_xll.EQNXTDZ($A$1,$B109,I$1,$B$1) -> 0 | J109: =_xll.EQNXTDZ($A$1,$B109,J$1,$B$1) -> 0 | ... AF109: =_xll.EQNXTDZ($A$1,$B109,AF$1,$B$1) -> 0
A110: Adj DPS(Rs) | B110: FR_ADJ_DPS | C110: =_xll.EQNXTDZ($A$1,$B110,C$1,$B$1) -> 0 | D110: =_xll.EQNXTDZ($A$1,$B110,D$1,$B$1) -> 0 | E110: =_xll.EQNXTDZ($A$1,$B110,E$1,$B$1) -> 0 | F110: =_xll.EQNXTDZ($A$1,$B110,F$1,$B$1) -> 0 | G110: =_xll.EQNXTDZ($A$1,$B110,G$1,$B$1) -> 0 | H110: =_xll.EQNXTDZ($A$1,$B110,H$1,$B$1) -> 0 | I110: =_xll.EQNXTDZ($A$1,$B110,I$1,$B$1) -> 0 | J110: =_xll.EQNXTDZ($A$1,$B110,J$1,$B$1) -> 0 | ... AF110: =_xll.EQNXTDZ($A$1,$B110,AF$1,$B$1) -> 0
A111: Date End | B111: SHP_DATE_END | C111: =_xll.EQNXTDZ($A$1,$B111,C$5) -> 0 | D111: =_xll.EQNXTDZ($A$1,$B111,D$5) -> 0 | E111: =_xll.EQNXTDZ($A$1,$B111,E$5) -> 0 | F111: =_xll.EQNXTDZ($A$1,$B111,F$5) -> 0 | G111: =_xll.EQNXTDZ($A$1,$B111,G$5) -> 0 | H111: =_xll.EQNXTDZ($A$1,$B111,H$5) -> 0 | I111: =_xll.EQNXTDZ($A$1,$B111,I$5) -> 0 | J111: =_xll.EQNXTDZ($A$1,$B111,J$5) -> 0 | ... AF111: =_xll.EQNXTDZ($A$1,$B111,AF$5) -> 0
A112: Total of Promoter and Promoter Group | B112: SHP_TPFTOTALPROMOTER | C112: =_xll.EQNXTDZ($A$1,$B112,C$5) -> 0 | D112: =_xll.EQNXTDZ($A$1,$B112,D$5) -> 0 | E112: =_xll.EQNXTDZ($A$1,$B112,E$5) -> 0 | F112: =_xll.EQNXTDZ($A$1,$B112,F$5) -> 0 | G112: =_xll.EQNXTDZ($A$1,$B112,G$5) -> 0 | H112: =_xll.EQNXTDZ($A$1,$B112,H$5) -> 0 | I112: =_xll.EQNXTDZ($A$1,$B112,I$5) -> 0 | J112: =_xll.EQNXTDZ($A$1,$B112,J$5) -> 0 | ... AF112: =_xll.EQNXTDZ($A$1,$B112,AF$5) -> 0
A113: Total of Promoter and Promoter Group Pledged | B113: SHP_PSHFTOTALPROMOTER | C113: =_xll.EQNXTDZ($A$1,$B113,C$5) -> 0 | D113: =_xll.EQNXTDZ($A$1,$B113,D$5) -> 0 | E113: =_xll.EQNXTDZ($A$1,$B113,E$5) -> 0 | F113: =_xll.EQNXTDZ($A$1,$B113,F$5) -> 0 | G113: =_xll.EQNXTDZ($A$1,$B113,G$5) -> 0 | H113: =_xll.EQNXTDZ($A$1,$B113,H$5) -> 0 | I113: =_xll.EQNXTDZ($A$1,$B113,I$5) -> 0 | J113: =_xll.EQNXTDZ($A$1,$B113,J$5) -> 0 | ... AF113: =_xll.EQNXTDZ($A$1,$B113,AF$5) -> 0

Sheet QTR Share Price
A1: ='QTR Raw'!A1 -> 320028 | C1: 201206 | D1: 201207 | E1: 201208 | F1: 201209 | G1: 201210 | H1: 201211 | I1: 201212 | J1: 201301 | K1: 201302 | L1: 201303 | M1: 201304 | N1: 201305 | O1: 201306 | P1: 201307 | Q1: 201308 | R1: 201309 | S1: 201310 | T1: 201311 | U1: 201312 | V1: 201401 | W1: 201402 | X1: 201403 | Y1: 201404 | Z1: 201405 | AA1: 201406 | AB1: 201407 | AC1: 201408 | AD1: 201409 | AE1: 201410 | AF1: 201411 | AG1: 201412 | AH1: 201501 | AI1: 201502 | AJ1: 201503 | AK1: 201504 | AL1: 201505 | AM1: 201506 | AN1: 201507 | AO1: 201508 | AP1: 201509 | AQ1: 201510 | AR1: 201511 | AS1: 201512 | AT1: 201601 | AU1: 201602 | AV1: 201603 | AW1: 201604 | AX1: 201605 | AY1: 201606 | AZ1: 201607 | BA1: 201608 | BB1: 201609 | BC1: 201610 | BD1: 201611 | BE1: 201612 | BF1: 201701 | BG1: 201702 | BH1: 201703 | BI1: 201704 | BJ1: 201705 | BK1: 201706 | BL1: 201707 | BM1: 201708 | BN1: 201709 | BO1: 201710 | BP1: 201711 | BQ1: 201712 | BR1: 201801 | BS1: 201802 | BT1: 201803 | BU1: 201804 | BV1: 201805 | BW1: 201806 | BX1: 201807 | BY1: 201808 | BZ1: 201809 | CA1: 201810 | CB1: 201811 | CC1: 201812 | CD1: 201901 | CE1: 201902 | CF1: 201903 | CG1: 201904 | CH1: 201905 | CI1: 201906 | CJ1: 201907 | CK1: 201908 | CL1: 201909 | CM1: 201910 | CN1: 201911 | CO1: 201912 | CP1: 202001 | CQ1: 202002 | CR1: 202003 | CS1: 202004 | CT1: 202005 | CU1: 202006 | CV1: 202007 | CW1: 202008 | CX1: 202009 | CY1: 202010 | CZ1: 202011 | DA1: 202012 | DB1: 202101 | DC1: 202102 | DD1: 202103 | DE1: 202104 | DF1: 202105 | DG1: 202106 | DH1: 202107 | DI1: 202108 | DJ1: 202109 | DK1: 202110 | DL1: 202111 | DM1: 202112 | DN1: 202201 | DO1: 202202 | DP1: 202203 | DQ1: 202204 | DR1: 202205 | DS1: 202206 | DT1: 202207 | DU1: 202208 | DV1: 202209 | DW1: 202210 | DX1: 202211 | DY1: 202212 | DZ1: 202301 | EA1: 202302 | EB1: 202303 | EC1: 202304 | ED1: 202305 | EE1: 202306 | EF1: 202307 | EG1: 202308 | EH1: 202309 | EI1: 202310 | EJ1: 202311 | EK1: 202312 | EL1: 202401 | EM1: 202402 | EN1: 202403 | EO1: 202404 | EP1: 202405 | EQ1: 202406 | ER1: 202407 | ES1: 202408 | ET1: 202409 | EU1: 202410 | EV1: 202411 | EW1: 202412 | EX1: 202501 | EY1: 202502 | EZ1: 202503 | FA1: 202504 | FB1: 202505 | FC1: 202506 | FD1: 202507 | FE1: 202508 | FF1: 202509 | FG1: 202510 | FH1: 202511 | FI1: 202512 | FJ1: 202601 | FK1: 202602 | FL1: 202603 | FM1: 202604 | FN1: 202605 | FO1: 202606 | FP1: 202607 | FQ1: 202608 | FR1: 202609 | FS1: 202610 | FT1: 202611 | FU1: 202612 | FV1: 202701 | FW1: 202702 | FX1: 202703 | FY1: 202704 | FZ1: 202705 | GA1: 202706 | GB1: 202707 | GC1: 202708 | GD1: 202709 | GE1: 202710 | GF1: 202711 | GG1: 202712 | GH1: 202801 | GI1: 202802 | GJ1: 202803 | GK1: 202804 | GL1: 202805 | GM1: 202806 | GN1: 202807 | GO1: 202808 | GP1: 202809 | GQ1: 202810 | GR1: 202811 | GS1: 202812 | GT1: 202901 | GU1: 202902 | GV1: 202903 | GW1: 202904 | GX1: 202905 | GY1: 202906 | GZ1: 202907 | HA1: 202908 | HB1: 202909 | HC1: 202910 | HD1: 202911 | HE1: 202912 | HF1: 203001 | HG1: 203002 | HH1: 203003 | HM1: 201206 | HN1: 201207 | HO1: 201208 | HP1: 201209 | HQ1: 201212 | HR1: 201303 | HS1: 201306 | HT1: 201309 | HU1: 201312 | HV1: 201403 | HW1: 201406 | HX1: 201409 | HY1: 201412 | HZ1: 201503 | IA1: 201506 | IB1: 201509 | IC1: 201512 | ID1: 201603 | IE1: 201606 | IF1: 201609 | IG1: 201612 | IH1: 201703 | II1: 201706 | IJ1: 201709 | IK1: 201712 | IL1: 201803 | IM1: 201806 | IN1: 201809 | IO1: 201812 | IP1: 201903 | IQ1: 201906 | IR1: 201909 | IS1: 201912 | IT1: 202003 | IU1: 202006 | IV1: 202009 | IW1: 202012 | IX1: 202103 | IY1: 202106 | IZ1: 202109 | JA1: 202112 | JB1: 202203 | JC1: 202206 | JD1: 202209 | JE1: 202212 | JF1: 202303 | JG1: 202306 | JH1: 202309 | JI1: 202312 | JJ1: 202403 | JK1: 202406 | JL1: 202409 | JM1: 202412 | JN1: 202503 | JO1: 202506 | JP1: 202509 | JQ1: 202512 | JR1: 202603 | JS1: 202606 | JT1: 202609 | JU1: 202612 | JV1: 202703 | JW1: 202706 | JX1: 202709 | JY1: 202712 | JZ1: 202803 | KA1: 202806 | KB1: 202809 | KC1: 202812 | KD1: 202903 | KE1: 202906 | KF1: 202909 | KG1: 202912 | KH1: 203003
FF2: 45901 | FG2: =+EOMONTH(FF2,1) -> 45961 | FH2: =+EOMONTH(FG2,1) -> 45991 | FI2: =+EOMONTH(FH2,1) -> 46022 | FJ2: =+EOMONTH(FI2,1) -> 46053 | FK2: =+EOMONTH(FJ2,1) -> 46081 | FL2: =+EOMONTH(FK2,1) -> 46112 | FM2: =+EOMONTH(FL2,1) -> 46142 | FN2: =+EOMONTH(FM2,1) -> 46173 | ... HH2: =+EOMONTH(HG2,1) -> 47573
A4: Field Description | B4: Field Name
A5: MonthEnd | B5: NMONTH_MONTHEND | C5: {=_xll.EQNXTDZ($A$1,$B5,C$1)} -> 0 | D5: {=_xll.EQNXTDZ($A$1,$B5,D$1)} -> 0 | E5: {=_xll.EQNXTDZ($A$1,$B5,E$1)} -> 0 | F5: {=_xll.EQNXTDZ($A$1,$B5,F$1)} -> 0 | G5: {=_xll.EQNXTDZ($A$1,$B5,G$1)} -> 0 | H5: {=_xll.EQNXTDZ($A$1,$B5,H$1)} -> 0 | I5: {=_xll.EQNXTDZ($A$1,$B5,I$1)} -> 0 | J5: {=_xll.EQNXTDZ($A$1,$B5,J$1)} -> 0 | ... HH5: {=_xll.EQNXTDZ($A$1,$B5,HH$1)} -> 0
A6: Open | B6: NMONTH_OPEN | C6: {=_xll.EQNXTDZ($A$1,$B6,C$1)} -> 0 | D6: {=_xll.EQNXTDZ($A$1,$B6,D$1)} -> 0 | E6: {=_xll.EQNXTDZ($A$1,$B6,E$1)} -> 0 | F6: {=_xll.EQNXTDZ($A$1,$B6,F$1)} -> 0 | G6: {=_xll.EQNXTDZ($A$1,$B6,G$1)} -> 0 | H6: {=_xll.EQNXTDZ($A$1,$B6,H$1)} -> 0 | I6: {=_xll.EQNXTDZ($A$1,$B6,I$1)} -> 0 | J6: {=_xll.EQNXTDZ($A$1,$B6,J$1)} -> 0 | ... HH6: {=_xll.EQNXTDZ($A$1,$B6,HH$1)} -> 0
A7: High | B7: NMONTH_HIGH | C7: {=_xll.EQNXTDZ($A$1,$B7,C$1)} -> 0 | D7: {=_xll.EQNXTDZ($A$1,$B7,D$1)} -> 0 | E7: {=_xll.EQNXTDZ($A$1,$B7,E$1)} -> 0 | F7: {=_xll.EQNXTDZ($A$1,$B7,F$1)} -> 0 | G7: {=_xll.EQNXTDZ($A$1,$B7,G$1)} -> 0 | H7: {=_xll.EQNXTDZ($A$1,$B7,H$1)} -> 0 | I7: {=_xll.EQNXTDZ($A$1,$B7,I$1)} -> 0 | J7: {=_xll.EQNXTDZ($A$1,$B7,J$1)} -> 0 | ... HH7: {=_xll.EQNXTDZ($A$1,$B7,HH$1)} -> 0 | HP7: =+MAX(D7:F7) -> 0 | HQ7: =+MAX(G7:I7) -> 0 | HR7: =+MAX(J7:L7) -> 0 | HS7: =+MAX(M7:O7) -> 0 | HT7: =+MAX(P7:R7) -> 0 | HU7: =+MAX(S7:U7) -> 0 | HV7: =+MAX(V7:X7) -> 0 | HW7: =+MAX(Y7:AA7) -> 0 | HX7: =+MAX(AB7:AD7) -> 0 | HY7: =+MAX(AE7:AG7) -> 0 | HZ7: =+MAX(AH7:AJ7) -> 0 | IA7: =+MAX(AK7:AM7) -> 0 | IB7: =+MAX(AN7:AP7) -> 0 | IC7: =+MAX(AQ7:AS7) -> 0 | ID7: =+MAX(AT7:AV7) -> 0 | IE7: =+MAX(AW7:AY7) -> 0 | IF7: =+MAX(AZ7:BB7) -> 0 | IG7: =+MAX(BC7:BE7) -> 0 | IH7: =+MAX(BF7:BH7) -> 0 | II7: =+MAX(BI7:BK7) -> 0 | IJ7: =+MAX(BL7:BN7) -> 0 | IK7: =+MAX(BO7:BQ7) -> 0 | IL7: =+MAX(BR7:BT7) -> 0 | IM7: =+MAX(BU7:BW7) -> 0 | IN7: =+MAX(BX7:BZ7) -> 0 | IO7: =+MAX(CA7:CC7) -> 0 | IP7: =+MAX(CD7:CF7) -> 0 | IQ7: =+MAX(CG7:CI7) -> 0 | IR7: =+MAX(CJ7:CL7) -> 0 | IS7: =+MAX(CM7:CO7) -> 0 | IT7: =+MAX(CP7:CR7) -> 0 | IU7: =+MAX(CS7:CU7) -> 0 | IV7: =+MAX(CV7:CX7) -> 0 | IW7: =+MAX(CY7:DA7) -> 0 | IX7: =+MAX(DB7:DD7) -> 0 | IY7: =+MAX(DE7:DG7) -> 0 | IZ7: =+MAX(DH7:DJ7) -> 0 | JA7: =+MAX(DK7:DM7) -> 0 | JB7: =+MAX(DN7:DP7) -> 0 | JC7: =+MAX(DQ7:DS7) -> 0 | JD7: =+MAX(DT7:DV7) -> 0 | JE7: =+MAX(DW7:DY7) -> 0 | JF7: =+MAX(DZ7:EB7) -> 0 | JG7: =+MAX(EC7:EE7) -> 0 | JH7: =+MAX(EF7:EH7) -> 0 | JI7: =+MAX(EI7:EK7) -> 0 | JJ7: =+MAX(EL7:EN7) -> 0 | JK7: =MAX(EO7:EQ7) -> 0 | JL7: =MAX(ER7:ET7) -> 0 | JM7: =MAX(EU7:EW7) -> 0 | JN7: =MAX(EX7:EZ7) -> 0 | JO7: =MAX(FA7:FC7) -> 2994 | JP7: =MAX(FD7:FF7) -> 3625 | JQ7: =MAX(FG7:FI7) -> 3446.9 | JR7: =MAX(FJ7:FL7) -> 3020.6 | JS7: =MAX(FM7:FO7) -> 3968 | JT7: =MAX(FP7:FR7) -> 0 | JU7: =MAX(FS7:FU7) -> 0 | JV7: =MAX(FV7:FX7) -> 0 | JW7: =MAX(FY7:GA7) -> 0 | JX7: =MAX(GB7:GD7) -> 0 | JY7: =MAX(GE7:GG7) -> 0 | JZ7: =MAX(GH7:GJ7) -> 0 | KA7: =MAX(GK7:GM7) -> 0 | KB7: =MAX(GN7:GP7) -> 0 | KC7: =MAX(GQ7:GS7) -> 0 | KD7: =MAX(GT7:GV7) -> 0 | KE7: =MAX(GW7:GY7) -> 0 | KF7: =MAX(GZ7:HB7) -> 0 | KG7: =MAX(HC7:HE7) -> 0 | KH7: =MAX(HF7:HH7) -> 0
A8: Low | B8: NMONTH_LOW | C8: {=_xll.EQNXTDZ($A$1,$B8,C$1)} -> 0 | D8: {=_xll.EQNXTDZ($A$1,$B8,D$1)} -> 0 | E8: {=_xll.EQNXTDZ($A$1,$B8,E$1)} -> 0 | F8: {=_xll.EQNXTDZ($A$1,$B8,F$1)} -> 0 | G8: {=_xll.EQNXTDZ($A$1,$B8,G$1)} -> 0 | H8: {=_xll.EQNXTDZ($A$1,$B8,H$1)} -> 0 | I8: {=_xll.EQNXTDZ($A$1,$B8,I$1)} -> 0 | J8: {=_xll.EQNXTDZ($A$1,$B8,J$1)} -> 0 | ... HH8: {=_xll.EQNXTDZ($A$1,$B8,HH$1)} -> 0 | HP8: =+MIN(D8:F8) -> 0 | HQ8: =+MIN(G8:I8) -> 0 | HR8: =+MIN(J8:L8) -> 0 | HS8: =+MIN(M8:O8) -> 0 | HT8: =+MIN(P8:R8) -> 0 | HU8: =+MIN(S8:U8) -> 0 | HV8: =+MIN(V8:X8) -> 0 | HW8: =+MIN(Y8:AA8) -> 0 | HX8: =+MIN(AB8:AD8) -> 0 | HY8: =+MIN(AE8:AG8) -> 0 | HZ8: =+MIN(AH8:AJ8) -> 0 | IA8: =+MIN(AK8:AM8) -> 0 | IB8: =+MIN(AN8:AP8) -> 0 | IC8: =+MIN(AQ8:AS8) -> 0 | ID8: =+MIN(AT8:AV8) -> 0 | IE8: =+MIN(AW8:AY8) -> 0 | IF8: =+MIN(AZ8:BB8) -> 0 | IG8: =+MIN(BC8:BE8) -> 0 | IH8: =+MIN(BF8:BH8) -> 0 | II8: =+MIN(BI8:BK8) -> 0 | IJ8: =+MIN(BL8:BN8) -> 0 | IK8: =+MIN(BO8:BQ8) -> 0 | IL8: =+MIN(BR8:BT8) -> 0 | IM8: =+MIN(BU8:BW8) -> 0 | IN8: =+MIN(BX8:BZ8) -> 0 | IO8: =+MIN(CA8:CC8) -> 0 | IP8: =+MIN(CD8:CF8) -> 0 | IQ8: =+MIN(CG8:CI8) -> 0 | IR8: =+MIN(CJ8:CL8) -> 0 | IS8: =+MIN(CM8:CO8) -> 0 | IT8: =+MIN(CP8:CR8) -> 0 | IU8: =+MIN(CS8:CU8) -> 0 | IV8: =+MIN(CV8:CX8) -> 0 | IW8: =+MIN(CY8:DA8) -> 0 | IX8: =+MIN(DB8:DD8) -> 0 | IY8: =+MIN(DE8:DG8) -> 0 | IZ8: =+MIN(DH8:DJ8) -> 0 | JA8: =+MIN(DK8:DM8) -> 0 | JB8: =+MIN(DN8:DP8) -> 0 | JC8: =+MIN(DQ8:DS8) -> 0 | JD8: =+MIN(DT8:DV8) -> 0 | JE8: =+MIN(DW8:DY8) -> 0 | JF8: =+MIN(DZ8:EB8) -> 0 | JG8: =+MIN(EC8:EE8) -> 0 | JH8: =+MIN(EF8:EH8) -> 0 | JI8: =+MIN(EI8:EK8) -> 0 | JJ8: =+MIN(EL8:EN8) -> 0 | JK8: =MIN(EO8:EQ8) -> 0 | JL8: =MIN(ER8:ET8) -> 0 | JM8: =MIN(EU8:EW8) -> 0 | JN8: =MIN(EX8:EZ8) -> 0 | JO8: =MIN(FA8:FC8) -> 0 | JP8: =MIN(FD8:FF8) -> 2876.7 | JQ8: =MIN(FG8:FI8) -> 2540.1 | JR8: =MIN(FJ8:FL8) -> 2115 | JS8: =MIN(FM8:FO8) -> 2521.7 | JT8: =MIN(FP8:FR8) -> 0 | JU8: =MIN(FS8:FU8) -> 0 | JV8: =MIN(FV8:FX8) -> 0 | JW8: =MIN(FY8:GA8) -> 0 | JX8: =MIN(GB8:GD8) -> 0 | JY8: =MIN(GE8:GG8) -> 0 | JZ8: =MIN(GH8:GJ8) -> 0 | KA8: =MIN(GK8:GM8) -> 0 | KB8: =MIN(GN8:GP8) -> 0 | KC8: =MIN(GQ8:GS8) -> 0 | KD8: =MIN(GT8:GV8) -> 0 | KE8: =MIN(GW8:GY8) -> 0 | KF8: =MIN(GZ8:HB8) -> 0 | KG8: =MIN(HC8:HE8) -> 0 | KH8: =MIN(HF8:HH8) -> 0
A9: Close | B9: NMONTH_CLOSE | C9: {=_xll.EQNXTDZ($A$1,$B9,C$1)} -> 0 | D9: {=_xll.EQNXTDZ($A$1,$B9,D$1)} -> 0 | E9: {=_xll.EQNXTDZ($A$1,$B9,E$1)} -> 0 | F9: {=_xll.EQNXTDZ($A$1,$B9,F$1)} -> 0 | G9: {=_xll.EQNXTDZ($A$1,$B9,G$1)} -> 0 | H9: {=_xll.EQNXTDZ($A$1,$B9,H$1)} -> 0 | I9: {=_xll.EQNXTDZ($A$1,$B9,I$1)} -> 0 | J9: {=_xll.EQNXTDZ($A$1,$B9,J$1)} -> 0 | ... HH9: {=_xll.EQNXTDZ($A$1,$B9,HH$1)} -> 0 | HP9: =+F9 -> 0 | HQ9: =+I9 -> 0 | HR9: =+L9 -> 0 | HS9: =+O9 -> 0 | HT9: =+R9 -> 0 | HU9: =+U9 -> 0 | HV9: =+X9 -> 0 | HW9: =+AA9 -> 0 | HX9: =+AD9 -> 0 | HY9: =+AG9 -> 0 | HZ9: =+AJ9 -> 0 | IA9: =+AM9 -> 0 | IB9: =+AP9 -> 0 | IC9: =+AS9 -> 0 | ID9: =+AV9 -> 0 | IE9: =+AY9 -> 0 | IF9: =+BB9 -> 0 | IG9: =+BE9 -> 0 | IH9: =+BH9 -> 0 | II9: =+BK9 -> 0 | IJ9: =+BN9 -> 0 | IK9: =+BQ9 -> 0 | IL9: =+BT9 -> 0 | IM9: =+BW9 -> 0 | IN9: =+BZ9 -> 0 | IO9: =+CC9 -> 0 | IP9: =+CF9 -> 0 | IQ9: =+CI9 -> 0 | IR9: =+CL9 -> 0 | IS9: =+CO9 -> 0 | IT9: =+CR9 -> 0 | IU9: =+CU9 -> 0 | IV9: =+CX9 -> 0 | IW9: =+DA9 -> 0 | IX9: =+DD9 -> 0 | IY9: =+DG9 -> 0 | IZ9: =+DJ9 -> 0 | JA9: =+DM9 -> 0 | JB9: =+DP9 -> 0 | JC9: =+DS9 -> 0 | JD9: =+DV9 -> 0 | JE9: =+DY9 -> 0 | JF9: =+EB9 -> 0 | JG9: =+EE9 -> 0 | JH9: =+EH9 -> 0 | JI9: =+EK9 -> 0 | JJ9: =+EN9 -> 0 | JK9: =EQ9 -> 0 | JL9: =ET9 -> 0 | JM9: =EW9 -> 0 | JN9: =EZ9 -> 0 | JO9: =FC9 -> 2975.9 | JP9: =FF9 -> 3432.8 | JQ9: =FI9 -> 2560.1 | JR9: =FL9 -> 2565.5 | JS9: =FO9 -> 3608.9 | JT9: =FR9 -> 0 | JU9: =FU9 -> 0 | JV9: =FX9 -> 0 | JW9: =GA9 -> 0 | JX9: =GD9 -> 0 | JY9: =GG9 -> 0 | JZ9: =GJ9 -> 0 | KA9: =GM9 -> 0 | KB9: =GP9 -> 0 | KC9: =GS9 -> 0 | KD9: =GV9 -> 0 | KE9: =GY9 -> 0 | KF9: =HB9 -> 0 | KG9: =HE9 -> 0 | KH9: =HH9 -> 0
A11: Field Description | B11: Field Name | C11: {=_xll.EQNXTDZ($A$1,$B11,C$1)} -> 0 | D11: {=_xll.EQNXTDZ($A$1,$B11,D$1)} -> 0 | E11: {=_xll.EQNXTDZ($A$1,$B11,E$1)} -> 0 | F11: {=_xll.EQNXTDZ($A$1,$B11,F$1)} -> 0 | G11: {=_xll.EQNXTDZ($A$1,$B11,G$1)} -> 0 | H11: {=_xll.EQNXTDZ($A$1,$B11,H$1)} -> 0 | I11: {=_xll.EQNXTDZ($A$1,$B11,I$1)} -> 0 | J11: {=_xll.EQNXTDZ($A$1,$B11,J$1)} -> 0 | ... HH11: {=_xll.EQNXTDZ($A$1,$B11,HH$1)} -> 0
A12: Month End | B12: BMONTH_MONTHEND | C12: {=_xll.EQNXTDZ($A$1,$B12,C$1)} -> 0 | D12: {=_xll.EQNXTDZ($A$1,$B12,D$1)} -> 0 | E12: {=_xll.EQNXTDZ($A$1,$B12,E$1)} -> 0 | F12: {=_xll.EQNXTDZ($A$1,$B12,F$1)} -> 0 | G12: {=_xll.EQNXTDZ($A$1,$B12,G$1)} -> 0 | H12: {=_xll.EQNXTDZ($A$1,$B12,H$1)} -> 0 | I12: {=_xll.EQNXTDZ($A$1,$B12,I$1)} -> 0 | J12: {=_xll.EQNXTDZ($A$1,$B12,J$1)} -> 0 | ... HH12: {=_xll.EQNXTDZ($A$1,$B12,HH$1)} -> 0
A13: Open | B13: BMONTH_OPEN | C13: {=_xll.EQNXTDZ($A$1,$B13,C$1)} -> 0 | D13: {=_xll.EQNXTDZ($A$1,$B13,D$1)} -> 0 | E13: {=_xll.EQNXTDZ($A$1,$B13,E$1)} -> 0 | F13: {=_xll.EQNXTDZ($A$1,$B13,F$1)} -> 0 | G13: {=_xll.EQNXTDZ($A$1,$B13,G$1)} -> 0 | H13: {=_xll.EQNXTDZ($A$1,$B13,H$1)} -> 0 | I13: {=_xll.EQNXTDZ($A$1,$B13,I$1)} -> 0 | J13: {=_xll.EQNXTDZ($A$1,$B13,J$1)} -> 0 | ... HH13: {=_xll.EQNXTDZ($A$1,$B13,HH$1)} -> 0
A14: High | B14: BMONTH_HIGH | C14: {=_xll.EQNXTDZ($A$1,$B14,C$1)} -> 0 | D14: {=_xll.EQNXTDZ($A$1,$B14,D$1)} -> 0 | E14: {=_xll.EQNXTDZ($A$1,$B14,E$1)} -> 0 | F14: {=_xll.EQNXTDZ($A$1,$B14,F$1)} -> 0 | G14: {=_xll.EQNXTDZ($A$1,$B14,G$1)} -> 0 | H14: {=_xll.EQNXTDZ($A$1,$B14,H$1)} -> 0 | I14: {=_xll.EQNXTDZ($A$1,$B14,I$1)} -> 0 | J14: {=_xll.EQNXTDZ($A$1,$B14,J$1)} -> 0 | ... HH14: {=_xll.EQNXTDZ($A$1,$B14,HH$1)} -> 0 | HP14: =+MAX(D14:F14) -> 0 | HQ14: =+MAX(G14:I14) -> 0 | HR14: =+MAX(J14:L14) -> 0 | HS14: =+MAX(M14:O14) -> 0 | HT14: =+MAX(P14:R14) -> 0 | HU14: =+MAX(S14:U14) -> 0 | HV14: =+MAX(V14:X14) -> 0 | HW14: =+MAX(Y14:AA14) -> 0 | HX14: =+MAX(AB14:AD14) -> 0 | HY14: =+MAX(AE14:AG14) -> 0 | HZ14: =+MAX(AH14:AJ14) -> 0 | IA14: =+MAX(AK14:AM14) -> 0 | IB14: =+MAX(AN14:AP14) -> 0 | IC14: =+MAX(AQ14:AS14) -> 0 | ID14: =+MAX(AT14:AV14) -> 0 | IE14: =+MAX(AW14:AY14) -> 0 | IF14: =+MAX(AZ14:BB14) -> 0 | IG14: =+MAX(BC14:BE14) -> 0 | IH14: =+MAX(BF14:BH14) -> 0 | II14: =+MAX(BI14:BK14) -> 0 | IJ14: =+MAX(BL14:BN14) -> 0 | IK14: =+MAX(BO14:BQ14) -> 0 | IL14: =+MAX(BR14:BT14) -> 0 | IM14: =+MAX(BU14:BW14) -> 0 | IN14: =+MAX(BX14:BZ14) -> 0 | IO14: =+MAX(CA14:CC14) -> 0 | IP14: =+MAX(CD14:CF14) -> 0 | IQ14: =+MAX(CG14:CI14) -> 0 | IR14: =+MAX(CJ14:CL14) -> 0 | IS14: =+MAX(CM14:CO14) -> 0 | IT14: =+MAX(CP14:CR14) -> 0 | IU14: =+MAX(CS14:CU14) -> 0 | IV14: =+MAX(CV14:CX14) -> 0 | IW14: =+MAX(CY14:DA14) -> 0 | IX14: =+MAX(DB14:DD14) -> 0 | IY14: =+MAX(DE14:DG14) -> 0 | IZ14: =+MAX(DH14:DJ14) -> 0 | JA14: =+MAX(DK14:DM14) -> 0 | JB14: =+MAX(DN14:DP14) -> 0 | JC14: =+MAX(DQ14:DS14) -> 0 | JD14: =+MAX(DT14:DV14) -> 0 | JE14: =+MAX(DW14:DY14) -> 0 | JF14: =+MAX(DZ14:EB14) -> 0 | JG14: =+MAX(EC14:EE14) -> 0 | JH14: =+MAX(EF14:EH14) -> 0 | JI14: =+MAX(EI14:EK14) -> 0 | JJ14: =+MAX(EL14:EN14) -> 0 | JK14: =MAX(EO14:EQ14) -> 0 | JL14: =MAX(ER14:ET14) -> 0 | JM14: =MAX(EU14:EW14) -> 0 | JN14: =MAX(EX14:EZ14) -> 0 | JO14: =MAX(FA14:FC14) -> 2998 | JP14: =MAX(FD14:FF14) -> 3624 | JQ14: =MAX(FG14:FI14) -> 3447.35 | JR14: =MAX(FJ14:FL14) -> 3021.45 | JS14: =MAX(FM14:FO14) -> 3966.8 | JT14: =MAX(FP14:FR14) -> 0 | JU14: =MAX(FS14:FU14) -> 0 | JV14: =MAX(FV14:FX14) -> 0 | JW14: =MAX(FY14:GA14) -> 0 | JX14: =MAX(GB14:GD14) -> 0 | JY14: =MAX(GE14:GG14) -> 0 | JZ14: =MAX(GH14:GJ14) -> 0 | KA14: =MAX(GK14:GM14) -> 0 | KB14: =MAX(GN14:GP14) -> 0 | KC14: =MAX(GQ14:GS14) -> 0 | KD14: =MAX(GT14:GV14) -> 0 | KE14: =MAX(GW14:GY14) -> 0 | KF14: =MAX(GZ14:HB14) -> 0 | KG14: =MAX(HC14:HE14) -> 0 | KH14: =MAX(HF14:HH14) -> 0
A15: Low | B15: BMONTH_LOW | C15: {=_xll.EQNXTDZ($A$1,$B15,C$1)} -> 0 | D15: {=_xll.EQNXTDZ($A$1,$B15,D$1)} -> 0 | E15: {=_xll.EQNXTDZ($A$1,$B15,E$1)} -> 0 | F15: {=_xll.EQNXTDZ($A$1,$B15,F$1)} -> 0 | G15: {=_xll.EQNXTDZ($A$1,$B15,G$1)} -> 0 | H15: {=_xll.EQNXTDZ($A$1,$B15,H$1)} -> 0 | I15: {=_xll.EQNXTDZ($A$1,$B15,I$1)} -> 0 | J15: {=_xll.EQNXTDZ($A$1,$B15,J$1)} -> 0 | ... HH15: {=_xll.EQNXTDZ($A$1,$B15,HH$1)} -> 0 | HP15: =+MIN(D15:F15) -> 0 | HQ15: =+MIN(G15:I15) -> 0 | HR15: =+MIN(J15:L15) -> 0 | HS15: =+MIN(M15:O15) -> 0 | HT15: =+MIN(P15:R15) -> 0 | HU15: =+MIN(S15:U15) -> 0 | HV15: =+MIN(V15:X15) -> 0 | HW15: =+MIN(Y15:AA15) -> 0 | HX15: =+MIN(AB15:AD15) -> 0 | HY15: =+MIN(AE15:AG15) -> 0 | HZ15: =+MIN(AH15:AJ15) -> 0 | IA15: =+MIN(AK15:AM15) -> 0 | IB15: =+MIN(AN15:AP15) -> 0 | IC15: =+MIN(AQ15:AS15) -> 0 | ID15: =+MIN(AT15:AV15) -> 0 | IE15: =+MIN(AW15:AY15) -> 0 | IF15: =+MIN(AZ15:BB15) -> 0 | IG15: =+MIN(BC15:BE15) -> 0 | IH15: =+MIN(BF15:BH15) -> 0 | II15: =+MIN(BI15:BK15) -> 0 | IJ15: =+MIN(BL15:BN15) -> 0 | IK15: =+MIN(BO15:BQ15) -> 0 | IL15: =+MIN(BR15:BT15) -> 0 | IM15: =+MIN(BU15:BW15) -> 0 | IN15: =+MIN(BX15:BZ15) -> 0 | IO15: =+MIN(CA15:CC15) -> 0 | IP15: =+MIN(CD15:CF15) -> 0 | IQ15: =+MIN(CG15:CI15) -> 0 | IR15: =+MIN(CJ15:CL15) -> 0 | IS15: =+MIN(CM15:CO15) -> 0 | IT15: =+MIN(CP15:CR15) -> 0 | IU15: =+MIN(CS15:CU15) -> 0 | IV15: =+MIN(CV15:CX15) -> 0 | IW15: =+MIN(CY15:DA15) -> 0 | IX15: =+MIN(DB15:DD15) -> 0 | IY15: =+MIN(DE15:DG15) -> 0 | IZ15: =+MIN(DH15:DJ15) -> 0 | JA15: =+MIN(DK15:DM15) -> 0 | JB15: =+MIN(DN15:DP15) -> 0 | JC15: =+MIN(DQ15:DS15) -> 0 | JD15: =+MIN(DT15:DV15) -> 0 | JE15: =+MIN(DW15:DY15) -> 0 | JF15: =+MIN(DZ15:EB15) -> 0 | JG15: =+MIN(EC15:EE15) -> 0 | JH15: =+MIN(EF15:EH15) -> 0 | JI15: =+MIN(EI15:EK15) -> 0 | JJ15: =+MIN(EL15:EN15) -> 0 | JK15: =MIN(EO15:EQ15) -> 0 | JL15: =MIN(ER15:ET15) -> 0 | JM15: =MIN(EU15:EW15) -> 0 | JN15: =MIN(EX15:EZ15) -> 0 | JO15: =MIN(FA15:FC15) -> 0 | JP15: =MIN(FD15:FF15) -> 2875 | JQ15: =MIN(FG15:FI15) -> 2535.8 | JR15: =MIN(FJ15:FL15) -> 2105.15 | JS15: =MIN(FM15:FO15) -> 2523 | JT15: =MIN(FP15:FR15) -> 0 | JU15: =MIN(FS15:FU15) -> 0 | JV15: =MIN(FV15:FX15) -> 0 | JW15: =MIN(FY15:GA15) -> 0 | JX15: =MIN(GB15:GD15) -> 0 | JY15: =MIN(GE15:GG15) -> 0 | JZ15: =MIN(GH15:GJ15) -> 0 | KA15: =MIN(GK15:GM15) -> 0 | KB15: =MIN(GN15:GP15) -> 0 | KC15: =MIN(GQ15:GS15) -> 0 | KD15: =MIN(GT15:GV15) -> 0 | KE15: =MIN(GW15:GY15) -> 0 | KF15: =MIN(GZ15:HB15) -> 0 | KG15: =MIN(HC15:HE15) -> 0 | KH15: =MIN(HF15:HH15) -> 0
A16: Close | B16: BMONTH_CLOSE | C16: {=_xll.EQNXTDZ($A$1,$B16,C$1)} -> 0 | D16: {=_xll.EQNXTDZ($A$1,$B16,D$1)} -> 0 | E16: {=_xll.EQNXTDZ($A$1,$B16,E$1)} -> 0 | F16: {=_xll.EQNXTDZ($A$1,$B16,F$1)} -> 0 | G16: {=_xll.EQNXTDZ($A$1,$B16,G$1)} -> 0 | H16: {=_xll.EQNXTDZ($A$1,$B16,H$1)} -> 0 | I16: {=_xll.EQNXTDZ($A$1,$B16,I$1)} -> 0 | J16: {=_xll.EQNXTDZ($A$1,$B16,J$1)} -> 0 | ... HH16: {=_xll.EQNXTDZ($A$1,$B16,HH$1)} -> 0 | HP16: =+F16 -> 0 | HQ16: =+I16 -> 0 | HR16: =+L16 -> 0 | HS16: =+O16 -> 0 | HT16: =+R16 -> 0 | HU16: =+U16 -> 0 | HV16: =+X16 -> 0 | HW16: =+AA16 -> 0 | HX16: =+AD16 -> 0 | HY16: =+AG16 -> 0 | HZ16: =+AJ16 -> 0 | IA16: =+AM16 -> 0 | IB16: =+AP16 -> 0 | IC16: =+AS16 -> 0 | ID16: =+AV16 -> 0 | IE16: =+AY16 -> 0 | IF16: =+BB16 -> 0 | IG16: =+BE16 -> 0 | IH16: =+BH16 -> 0 | II16: =+BK16 -> 0 | IJ16: =+BN16 -> 0 | IK16: =+BQ16 -> 0 | IL16: =+BT16 -> 0 | IM16: =+BW16 -> 0 | IN16: =+BZ16 -> 0 | IO16: =+CC16 -> 0 | IP16: =+CF16 -> 0 | IQ16: =+CI16 -> 0 | IR16: =+CL16 -> 0 | IS16: =+CO16 -> 0 | IT16: =+CR16 -> 0 | IU16: =+CU16 -> 0 | IV16: =+CX16 -> 0 | IW16: =+DA16 -> 0 | IX16: =+DD16 -> 0 | IY16: =+DG16 -> 0 | IZ16: =+DJ16 -> 0 | JA16: =+DM16 -> 0 | JB16: =+DP16 -> 0 | JC16: =+DS16 -> 0 | JD16: =+DV16 -> 0 | JE16: =+DY16 -> 0 | JF16: =+EB16 -> 0 | JG16: =+EE16 -> 0 | JH16: =+EH16 -> 0 | JI16: =+EK16 -> 0 | JJ16: =+EN16 -> 0 | JK16: =EQ16 -> 0 | JL16: =ET16 -> 0 | JM16: =EW16 -> 0 | JN16: =EZ16 -> 0 | JO16: =FC16 -> 2982 | JP16: =FF16 -> 3430.35 | JQ16: =FI16 -> 2560.8 | JR16: =FL16 -> 2569.65 | JS16: =FO16 -> 3606.65 | JT16: =FR16 -> 0 | JU16: =FU16 -> 0 | JV16: =FX16 -> 0 | JW16: =GA16 -> 0 | JX16: =GD16 -> 0 | JY16: =GG16 -> 0 | JZ16: =GJ16 -> 0 | KA16: =GM16 -> 0 | KB16: =GP16 -> 0 | KC16: =GS16 -> 0 | KD16: =GV16 -> 0 | KE16: =GY16 -> 0 | KF16: =HB16 -> 0 | KG16: =HE16 -> 0 | KH16: =HH16 -> 0
A19: High | HP19: =+IF(HP14=0,HP7,HP14) -> 0 | HQ19: =+IF(HQ14=0,HQ7,HQ14) -> 0 | HR19: =+IF(HR14=0,HR7,HR14) -> 0 | HS19: =+IF(HS14=0,HS7,HS14) -> 0 | HT19: =+IF(HT14=0,HT7,HT14) -> 0 | HU19: =+IF(HU14=0,HU7,HU14) -> 0 | HV19: =+IF(HV14=0,HV7,HV14) -> 0 | HW19: =+IF(HW14=0,HW7,HW14) -> 0 | ... KH19: =+IF(KH14=0,KH7,KH14) -> 0
A20: Low | HP20: =+IF(HP15=0,HP8,HP15) -> 0 | HQ20: =+IF(HQ15=0,HQ8,HQ15) -> 0 | HR20: =+IF(HR15=0,HR8,HR15) -> 0 | HS20: =+IF(HS15=0,HS8,HS15) -> 0 | HT20: =+IF(HT15=0,HT8,HT15) -> 0 | HU20: =+IF(HU15=0,HU8,HU15) -> 0 | HV20: =+IF(HV15=0,HV8,HV15) -> 0 | HW20: =+IF(HW15=0,HW8,HW15) -> 0 | ... KH20: =+IF(KH15=0,KH8,KH15) -> 0
A21: Close | HP21: =+IF(HP16=0,HP9,HP16) -> 0 | HQ21: =+IF(HQ16=0,HQ9,HQ16) -> 0 | HR21: =+IF(HR16=0,HR9,HR16) -> 0 | HS21: =+IF(HS16=0,HS9,HS16) -> 0 | HT21: =+IF(HT16=0,HT9,HT16) -> 0 | HU21: =+IF(HU16=0,HU9,HU16) -> 0 | HV21: =+IF(HV16=0,HV9,HV16) -> 0 | HW21: =+IF(HW16=0,HW9,HW16) -> 0 | ... KH21: =+IF(KH16=0,KH9,KH16) -> 0

Sheet QTR No. of Shares
A1: ='QTR Raw'!A1 -> 320028 | C1: 201206 | D1: 201209 | E1: 201212 | F1: 201303 | G1: 201306 | H1: 201309 | I1: 201312 | J1: 201403 | K1: 201406 | L1: 201409 | M1: 201412 | N1: 201503 | O1: 201506 | P1: 201509 | Q1: 201512 | R1: 201603 | S1: 201606 | T1: 201609 | U1: 201612 | V1: 201703 | W1: 201706 | X1: 201709 | Y1: 201712 | Z1: 201803 | AA1: 201806 | AB1: 201809 | AC1: 201812 | AD1: 201903 | AE1: 201906 | AF1: 201909 | AG1: 201912 | AH1: 202003 | AI1: 202006 | AJ1: 202009 | AK1: 202012 | AL1: 202103 | AM1: 202106 | AN1: 202109 | AO1: 202112 | AP1: 202203 | AQ1: 202206 | AR1: 202209 | AS1: 202212 | AT1: 202303 | AU1: 202306 | AV1: 202309 | AW1: 202312 | AX1: 202403 | AY1: 202406
A4: Field Description | B4: Field Name
A5: Date End | B5: SHP_DATE_END | C5: {=_xll.EQNXTDZ($A$1,$B5,C$1)} -> 0 | D5: {=_xll.EQNXTDZ($A$1,$B5,D$1)} -> 0 | E5: {=_xll.EQNXTDZ($A$1,$B5,E$1)} -> 0 | F5: {=_xll.EQNXTDZ($A$1,$B5,F$1)} -> 0 | G5: {=_xll.EQNXTDZ($A$1,$B5,G$1)} -> 0 | H5: {=_xll.EQNXTDZ($A$1,$B5,H$1)} -> 0 | I5: {=_xll.EQNXTDZ($A$1,$B5,I$1)} -> 0 | J5: {=_xll.EQNXTDZ($A$1,$B5,J$1)} -> 0 | ... AY5: {=_xll.EQNXTDZ($A$1,$B5,AY$1)} -> 0
A6: Grand Total | B6: SHP_NSGRANDTOTAL | C6: {=_xll.EQNXTDZ($A$1,$B6,C$1)} -> 0 | D6: {=_xll.EQNXTDZ($A$1,$B6,D$1)} -> 0 | E6: {=_xll.EQNXTDZ($A$1,$B6,E$1)} -> 0 | F6: {=_xll.EQNXTDZ($A$1,$B6,F$1)} -> 0 | G6: {=_xll.EQNXTDZ($A$1,$B6,G$1)} -> 0 | H6: {=_xll.EQNXTDZ($A$1,$B6,H$1)} -> 0 | I6: {=_xll.EQNXTDZ($A$1,$B6,I$1)} -> 0 | J6: {=_xll.EQNXTDZ($A$1,$B6,J$1)} -> 0 | ... AY6: {=_xll.EQNXTDZ($A$1,$B6,AY$1)} -> 0
B7: In Crs. | C7: =+C6/10^7 -> 0 | D7: =+D6/10^7 -> 0 | E7: =+E6/10^7 -> 0 | F7: =+F6/10^7 -> 0 | G7: =+G6/10^7 -> 0 | H7: =+H6/10^7 -> 0 | I7: =+I6/10^7 -> 0 | J7: =+J6/10^7 -> 0 | ... AY7: =+AY6/10^7 -> 0

Sheet Share price Daily
A1: =_xll.EQNXTH(B1,"[ADJC];[ADJH];[ADJL];[ADJO];[UCLS];[VOLUME]","2015-Jan-01","Y","All traded days","Asc") -> EQNXTH | B1: =+'Annual Raw'!A1 -> 320028 | L1: =_xll.EQNXTH(B1,"[NADJC];[NADJH];[NADJLOW];[NADJOPEN];[NUCLOSE];[NVOLUME]","2015-Jan-01","Y","All traded days","Asc") -> EQNXTH
A2: Siemens Energy India Ltd. | L2: Siemens Energy India Ltd.
A3: DATE | B3: ADJHIGH | C3: ADJCLOSE | D3: ADJLOW | E3: ADJOPEN | F3: CLOSE | G3: VOLUME | L3: DATE | M3: ADJCLOSE | N3: ADJHIGH | O3: ADJLOW | P3: ADJOPEN | Q3: CLOSE | R3: VOLUME
A4: 45827 | B4: 2992.45 | C4: 2738.35 | D4: 2707.5 | E4: 2850 | F4: 2738.35 | G4: 175923 | L4: 45827 | M4: 2735 | N4: 2982 | O4: 2698 | P4: 2840 | Q4: 2735 | R4: 4080416
A5: 45828 | B5: 2856 | C5: 2666.2 | D5: 2602.4 | E5: 2620 | F5: 2666.2 | G5: 66338 | L5: 45828 | M5: 2640.8 | N5: 2869 | O5: 2610 | P5: 2635 | Q5: 2640.8 | R5: 10030400
A6: 45831 | B6: 2720 | C6: 2623.8 | D6: 2532.9 | E6: 2534 | F6: 2623.8 | G6: 64424 | L6: 45831 | M6: 2615.8 | N6: 2721 | O6: 2508.8 | P6: 2508.8 | Q6: 2615.8 | R6: 3288612
A7: 45832 | B7: 2725 | C7: 2699.65 | D7: 2529 | E7: 2615 | F7: 2699.65 | G7: 42963 | L7: 45832 | M7: 2706.4 | N7: 2744 | O7: 2526.2 | P7: 2611 | Q7: 2706.4 | R7: 2439573
A8: 45833 | B8: 2824 | C8: 2800.15 | D8: 2641 | E8: 2688 | F8: 2800.15 | G8: 30088 | L8: 45833 | M8: 2802.1 | N8: 2835.9 | O8: 2670 | P8: 2670 | Q8: 2802.1 | R8: 1348714
A9: 45834 | B9: 2891 | C9: 2834.8 | D9: 2750 | E9: 2780 | F9: 2834.8 | G9: 22783 | L9: 45834 | M9: 2827.6 | N9: 2889 | O9: 2753 | P9: 2753 | Q9: 2827.6 | R9: 3328114
A10: 45835 | B10: 2927 | C10: 2901.5 | D10: 2825 | E10: 2890 | F10: 2901.5 | G10: 44845 | L10: 45835 | M10: 2901.2 | N10: 2934 | O10: 2840 | P10: 2860 | Q10: 2901.2 | R10: 663663
A11: 45838 | B11: 2998 | C11: 2982 | D11: 2860 | E11: 2925 | F11: 2982 | G11: 23577 | L11: 45838 | M11: 2975.9 | N11: 2994 | O11: 2892.2 | P11: 2924.9 | Q11: 2975.9 | R11: 601274
A12: 45839 | B12: 3020 | C12: 2950.25 | D12: 2900.05 | E12: 2999 | F12: 2950.25 | G12: 36297 | L12: 45839 | M12: 2971.5 | N12: 3024 | O12: 2916 | P12: 3000 | Q12: 2971.5 | R12: 536577
A13: 45840 | B13: 2987 | C13: 2946.65 | D13: 2876.6 | E13: 2950 | F13: 2946.65 | G13: 50519 | L13: 45840 | M13: 2951.1 | N13: 2971.5 | O13: 2876.7 | P13: 2960 | Q13: 2951.1 | R13: 568584
A14: 45841 | B14: 2970.1 | C14: 2922.45 | D14: 2886 | E14: 2949.7 | F14: 2922.45 | G14: 23766 | L14: 45841 | M14: 2922.3 | N14: 2971.7 | O14: 2881 | P14: 2948 | Q14: 2922.3 | R14: 650654
A15: 45842 | B15: 2977.4 | C15: 2891.85 | D15: 2875 | E15: 2948.95 | F15: 2891.85 | G15: 34729 | L15: 45842 | M15: 2894 | N15: 2978.8 | O15: 2880 | P15: 2935 | Q15: 2894 | R15: 654426
... A2722: 46010 | B2722: 939 | C2722: 932.5 | D2722: 906.25 | E2722: 910.9 | F2722: 932.5 | G2722: 8862 | L2722: 46010 | M2722: 936.6 | N2722: 938.9 | O2722: 905 | P2722: 905 | Q2722: 936.6 | R2722: 296202

Sheet Sheet2
J19: 219.3 | K19: 186.25 | L19: 186.75
J20: 192.9 | K20: 135.5 | L20: 146.9 | N20: 219.3 | O20: 192.9 | P20: 186 | Q20: 178.7 | R20: 207 | S20: 255.15 | T20: 348.25 | U20: 374 | V20: 495.9 | W20: 659.9 | X20: 613.4 | Y20: 607.9 | Z20: 555.95 | AA20: 497.8 | AB20: 459.9 | AC20: 374 | AD20: 362 | AE20: 341.5 | AF20: 384.2 | AG20: 433.8 | AH20: 460 | AI20: 474.4 | AJ20: 414.4 | AK20: 318.7 | AL20: 303.25 | AM20: 332.7 | AN20: 295 | AO20: 247 | AP20: 214.4 | AQ20: 179.5 | AR20: 97.9 | AS20: 119.1 | AT20: 130.65 | AU20: 148.55 | AV20: 153.8 | AW20: 152.9 | AX20: 136 | AY20: 141.15 | AZ20: 128.1 | BA20: 142.5 | BB20: 143.55 | BC20: 124.5 | BD20: 241 | BE20: 450 | BF20: 503.35
J21: 186 | K21: 145.4 | L21: 169.1 | N21: 186.25 | O21: 135.5 | P21: 145.4 | Q21: 108.95 | R21: 137 | S21: 170 | T21: 243.15 | U21: 307.5 | V21: 325.1 | W21: 463 | X21: 467.05 | Y21: 436.5 | Z21: 467 | AA21: 348.2 | AB21: 325 | AC21: 313.1 | AD21: 285 | AE21: 277.85 | AF21: 327 | AG21: 317 | AH21: 370.7 | AI21: 360 | AJ21: 271.15 | AK21: 233.15 | AL21: 218.8 | AM21: 262 | AN21: 223.6 | AO21: 137.6 | AP21: 142 | AQ21: 59.3 | AR21: 58 | AS21: 72.8 | AT21: 80 | AU21: 107.25 | AV21: 106 | AW21: 125.1 | AX21: 112.25 | AY21: 81.45 | AZ21: 88 | BA21: 90.35 | BB21: 106.05 | BC21: 98.55 | BD21: 119.25 | BE21: 210 | BF21: 349
J22: 178.7 | K22: 108.95 | L22: 139.75 | N22: 186.75 | O22: 146.9 | P22: 169.1 | Q22: 139.75 | R22: 202.15 | S22: 249.05 | T22: 346.4 | U22: 349.2 | V22: 469.9 | W22: 584.8 | X22: 536.15 | Y22: 513.35 | Z22: 474 | AA22: 438.55 | AB22: 355.4 | AC22: 334.95 | AD22: 298.8 | AE22: 328.35 | AF22: 343 | AG22: 389.9 | AH22: 443.05 | AI22: 407.5 | AJ22: 290.1 | AK22: 235.75 | AL22: 292.65 | AM22: 276.1 | AN22: 237.05 | AO22: 190.1 | AP22: 147.2 | AQ22: 71.9 | AR22: 75.2 | AS22: 90.1 | AT22: 117.2 | AU22: 116.3 | AV22: 140.5 | AW22: 128.6 | AX22: 133.65 | AY22: 91.65 | AZ22: 97.65 | BA22: 125 | BB22: 115.35 | BC22: 119.25 | BD22: 219.3 | BE22: 442.65 | BF22: 503.35
J23: 207 | K23: 137 | L23: 202.15
J24: 255.15 | K24: 170 | L24: 249.05
J25: 348.25 | K25: 243.15 | L25: 346.4
J26: 374 | K26: 307.5 | L26: 349.2
J27: 495.9 | K27: 325.1 | L27: 469.9
J28: 659.9 | K28: 463 | L28: 584.8
J29: 613.4 | K29: 467.05 | L29: 536.15
J30: 607.9 | K30: 436.5 | L30: 513.35
J31: 555.95 | K31: 467 | L31: 474
J32: 497.8 | K32: 348.2 | L32: 438.55
J33: 459.9 | K33: 325 | L33: 355.4
J34: 374 | K34: 313.1 | L34: 334.95
... J63: 503.35 | K63: 349 | L63: 503.35
