Workbook
Name \a: #REF!
Name \b: #REF!
Name \c: #REF!
Name \COMM: #REF!
Name \COMM2: #REF!
Name \d: #REF!
Name \e: #REF!
Name \f: #REF!
Name \g: #REF!
Name \GROW: [1]Financials!$F$785
Name \h: #REF!
Name \i: #REF!
Name \j: #REF!
Name \L: #REF!
Name \M: #REF!
Name \MUL: #REF!
Name \MUL1: #REF!
Name \o: #REF!
Name \p: #REF!
Name \Q: [2]B!#REF!
Name \r: #REF!
Name \s: #REF!
Name \T: #REF!
Name \v: #REF!
Name \VEH: [1]Financials!$C$919
Name \w: #REF!
Name \x: #REF!
Name \y: #REF!
Name \Z: #REF!
Name __bs2: '[4]main standalone'!$A$98
Name __GROSS_SALES_T: #REF!
Name __NET_SALES_TO_: #REF!
Name _1_: [5]Old!#REF!
Name _2_0RMconsu: '[6]Operating Statistics'!#REF!
Name _3_0RMconsu: '[5]Operating Statistics'!#REF!
Name _bs2: '[4]main standalone'!$A$98
Name _CD201..D205__: #REF!
Name _DOWN_: #REF!
Name _EDIT__HOME__DE: #REF!
Name _kd17: #REF!
Name _kd18: #REF!
Name _kd19: #REF!
Name _kd20: #REF!
Name _kd21: #REF!
Name _kd22: #REF!
Name _kd23: #REF!
Name _kd24: #REF!
Name _kd25: #REF!
Name _MUL2: #REF!
Name _pc01: #REF!
Name _pc02: #REF!
Name _pc03: #REF!
Name _pc04: #REF!
Name _PG1: #REF!
Name _PL1: [7]Financials!#REF!
Name _RT1: #REF!
Name _RT2: #REF!
Name _RT3: #REF!
Name _RV__: #REF!
Name a: #REF!

Sheet Template
A1: =+'Annual Raw'!C4 -> Tata Motors Passenger Vehicles Ltd. | B1: 36951 | C1: =EOMONTH(B1,12) -> 37346 | D1: =EOMONTH(C1,12) -> 37711 | E1: =EOMONTH(D1,12) -> 38077 | F1: =EOMONTH(E1,12) -> 38442 | G1: =EOMONTH(F1,12) -> 38807 | H1: =EOMONTH(G1,12) -> 39172 | I1: =EOMONTH(H1,12) -> 39538 | J1: =EOMONTH(I1,12) -> 39903 | ... AE1: =EOMONTH(AD1,12) -> 47573 | AH1: QTR | AI1: 41061 | AJ1: 41153 | AK1: 41244 | AL1: 41334 | AM1: 41426 | AN1: 41518 | AO1: 41609 | AP1: 41699 | AQ1: 41791 | AR1: 41883 | AS1: 41974 | AT1: 42064 | AU1: 42156 | AV1: 42248 | AW1: 42339 | AX1: 42430 | AY1: 42522 | AZ1: 42614 | BA1: 42705 | BB1: 42795 | BC1: 42887 | BD1: 42979 | BE1: 43070 | BF1: 43160 | BG1: 43252 | BH1: 43344 | BI1: 43435 | BJ1: 43525 | BK1: 43617 | BL1: 43709 | BM1: 43800 | BN1: 43891 | BO1: 43983 | BP1: 44075 | BQ1: =EOMONTH(BP1,3) -> 44196 | BR1: =EOMONTH(BQ1,3) -> 44286 | BS1: =EOMONTH(BR1,3) -> 44377 | BT1: =EOMONTH(BS1,3) -> 44469 | BU1: =EOMONTH(BT1,3) -> 44561 | BV1: =EOMONTH(BU1,3) -> 44651 | BW1: =EOMONTH(BV1,3) -> 44742 | BX1: =EOMONTH(BW1,3) -> 44834 | ... DB1: =EOMONTH(DA1,3) -> 47573 | DE1: HISTORICAL ESTIMATES | DF1: 46112
A2: Presentation Data (Start)
A4: Volume | N4: =+SUM(N5:N6) -> 228900 | O4: =+SUM(O5:O6) -> 145786 | P4: =+SUM(P5:P6) -> 137565 | Q4: =+SUM(Q5:Q6) -> 132974 | R4: =+SUM(R5:R6) -> 157294 | S4: =+SUM(S5:S6) -> 189512 | T4: =+SUM(T5:T6) -> 212164 | U4: =+SUM(U5:U6) -> 133424 | ... AA4: =+SUM(AA5:AA6) -> 642771 | AB4: =+SUM(CM4:CP4) -> 909104.42 | AC4: =+SUM(CQ4:CT4) -> 1292943.7 | AD4: =+SUM(CU4:CX4) -> 1838846.4 | AE4: =+SUM(CY4:DB4) -> 2615238.5 | AI4: =+SUM(AI5:AI6) -> 62140 | AJ4: =+SUM(AJ5:AJ6) -> 72423 | AK4: =+SUM(AK5:AK6) -> 54412 | AL4: =+SUM(AL5:AL6) -> 39925 | AM4: =+SUM(AM5:AM6) -> 36675 | AN4: =+SUM(AN5:AN6) -> 37722 | AO4: =+SUM(AO5:AO6) -> 34881 | AP4: =+SUM(AP5:AP6) -> 36508 | ... CJ4: =+SUM(CJ5:CJ6) -> 144397 | CK4: =SUM(CK5:CK6) -> 172197 | CL4: =SUM(CL5:CL6) -> 201368 | CM4: =+'Monthly Nos Company'!$J$173 -> 172450.09 | CN4: =+'Monthly Nos Company'!$J$176 -> 205363.86 | CO4: =+'Monthly Nos Company'!$J$179 -> 244901.49 | CP4: =+'Monthly Nos Company'!$J$182 -> 286388.98 | CQ4: =+'Monthly Nos Company'!$J$185 -> 245261.44 | CR4: =+'Monthly Nos Company'!$J$188 -> 292071.96 | CS4: =+'Monthly Nos Company'!$J$191 -> 348303.05 | CT4: =+'Monthly Nos Company'!$J$194 -> 407307.26 | CU4: =+'Monthly Nos Company'!$J$197 -> 348814.98 | CV4: =+'Monthly Nos Company'!$J$200 -> 415389.69 | CW4: =+'Monthly Nos Company'!$J$203 -> 495362.49 | CX4: =+'Monthly Nos Company'!$J$206 -> 579279.28 | CY4: =+'Monthly Nos Company'!$J$209 -> 496090.57 | CZ4: =+'Monthly Nos Company'!$J$212 -> 590774.25 | DA4: =+'Monthly Nos Company'!$J$215 -> 704512.93 | DB4: =+'Monthly Nos Company'!$J$218 -> 823860.8
A5: Volume - Domestic | N5: =+SUM(AI5:AL5) -> 222112 | O5: =+SUM(AM5:AP5) -> 138455 | P5: =+SUM(AQ5:AT5) -> 134079 | Q5: =+SUM(AU5:AX5) -> 126534 | R5: =+SUM(AY5:BB5) -> 153257 | S5: =+SUM(BC5:BF5) -> 187321 | T5: =+SUM(BG5:BJ5) -> 210143 | U5: =+SUM(BK5:BN5) -> 131891 | V5: =+SUM(BO5:BR5) -> 218876 | W5: =+SUM(BS5:BV5) -> 370372 | X5: =+SUM(BW5:BZ5) -> 538942 | Y5: =+SUM(CA5:CD5) -> 570985 | Z5: =+SUM(CE5:CH5) -> 553585 | AA5: =SUM(CI5:CL5) -> 631548 | AI5: =+'Monthly Nos Company'!$K$5 -> 60405 | AJ5: =+'Monthly Nos Company'!$K$8 -> 70203 | AK5: =+'Monthly Nos Company'!$K$11 -> 53335 | AL5: =+'Monthly Nos Company'!$K$14 -> 38169 | AM5: =+'Monthly Nos Company'!$K$17 -> 34508 | AN5: =+'Monthly Nos Company'!$K$20 -> 35227 | AO5: =+'Monthly Nos Company'!$K$23 -> 33781 | AP5: =+'Monthly Nos Company'!$K$26 -> 34939 | AQ5: =+'Monthly Nos Company'!$K$29 -> 24582 | AR5: =+'Monthly Nos Company'!$K$32 -> 32072 | AS5: =+'Monthly Nos Company'!$K$35 -> 35572 | AT5: =+'Monthly Nos Company'!$K$38 -> 41853 | AU5: =+'Monthly Nos Company'!$K$41 -> 31649 | AV5: =+'Monthly Nos Company'!$K$44 -> 33357 | AW5: =+'Monthly Nos Company'!$K$47 -> 31384 | AX5: =+'Monthly Nos Company'!$K$50 -> 30144 | AY5: =+'Monthly Nos Company'!$K$53 -> 31621 | AZ5: =+'Monthly Nos Company'!$K$56 -> 41150 | BA5: =+'Monthly Nos Company'!$K$59 -> 39874 | BB5: =+'Monthly Nos Company'!$K$62 -> 40612 | BC5: =+'Monthly Nos Company'!$K$65 -> 34858 | BD5: =+'Monthly Nos Company'!$K$68 -> 46559 | BE5: =+'Monthly Nos Company'!$K$71 -> 47812 | BF5: =+'Monthly Nos Company'!$K$74 -> 58092 | BG5: =+'Monthly Nos Company'!$K$77 -> 52937 | BH5: =+'Monthly Nos Company'!$K$80 -> 53928 | BI5: =+'Monthly Nos Company'!$K$83 -> 49532 | BJ5: =+'Monthly Nos Company'!$K$86 -> 53746 | BK5: =+'Monthly Nos Company'!$K$89 -> 37639 | BL5: =+'Monthly Nos Company'!$K$92 -> 25898 | BM5: =+'Monthly Nos Company'!$K$95 -> 36354 | BN5: =+'Monthly Nos Company'!$K$98 -> 32000 | BO5: =+'Monthly Nos Company'!$K$101 -> 11419 | BP5: =+'Monthly Nos Company'!$K$104 -> 54794 | BQ5: =+'Monthly Nos Company'!$K$107 -> 68806 | BR5: =+'Monthly Nos Company'!$K$110 -> 83857 | BS5: =+'Monthly Nos Company'!$K$113 -> 64386 | BT5: =+'Monthly Nos Company'!$K$116 -> 83933 | BU5: =+'Monthly Nos Company'!$K$119 -> 99002 | BV5: =+'Monthly Nos Company'!$K$122 -> 123051 | BW5: =+'Monthly Nos Company'!$K$125 -> 130125 | BX5: =+'Monthly Nos Company'!$K$128 -> 142325 | BY5: =+'Monthly Nos Company'!$K$131 -> 131297 | BZ5: =+'Monthly Nos Company'!$K$134 -> 135195 | CA5: =+'Monthly Nos Company'!$K$137 -> 140120 | CB5: =+'Monthly Nos Company'!$K$140 -> 137950 | CC5: =+'Monthly Nos Company'!$K$143 -> 137875 | CD5: =+'Monthly Nos Company'!$K$146 -> 155040 | CE5: =+'Monthly Nos Company'!$K$149 -> 138104 | CF5: =+'Monthly Nos Company'!$K$152 -> 129930 | CG5: =+'Monthly Nos Company'!$K$155 -> 139424 | CH5: =+'Monthly Nos Company'!$K$158 -> 146127 | CI5: =+'Monthly Nos Company'!$K$161 -> 123839 | CJ5: =+'Monthly Nos Company'!$K$164 -> 140189 | CK5: =+'Monthly Nos Company'!$K$167 -> 168777 | CL5: ='Monthly Nos Company'!K170 -> 198743
A6: Volume - Export | N6: =+SUM(AI6:AL6) -> 6788 | O6: =+SUM(AM6:AP6) -> 7331 | P6: =+SUM(AQ6:AT6) -> 3486 | Q6: =+SUM(AU6:AX6) -> 6440 | R6: =+SUM(AY6:BB6) -> 4037 | S6: =+SUM(BC6:BF6) -> 2191 | T6: =+SUM(BG6:BJ6) -> 2021 | U6: =+SUM(BK6:BN6) -> 1533 | V6: =+SUM(BO6:BR6) -> 552 | W6: =+SUM(BS6:BV6) -> 1892 | X6: =+SUM(BW6:BZ6) -> 2447 | Y6: =+SUM(CA6:CD6) -> 2540 | Z6: =+SUM(CE6:CH6) -> 2678 | AA6: =SUM(CI6:CL6) -> 11223 | AI6: =+'Monthly Nos Company'!$L$5 -> 1735 | AJ6: =+'Monthly Nos Company'!$L$8 -> 2220 | AK6: =+'Monthly Nos Company'!$L$11 -> 1077 | AL6: =+'Monthly Nos Company'!$L$14 -> 1756 | AM6: =+'Monthly Nos Company'!$L$17 -> 2167 | AN6: =+'Monthly Nos Company'!$L$20 -> 2495 | AO6: =+'Monthly Nos Company'!$L$23 -> 1100 | AP6: =+'Monthly Nos Company'!$L$26 -> 1569 | AQ6: =+'Monthly Nos Company'!$L$29 -> 887 | AR6: =+'Monthly Nos Company'!$L$32 -> 1127 | AS6: =+'Monthly Nos Company'!$L$35 -> 756 | AT6: =+'Monthly Nos Company'!$L$38 -> 716 | AU6: =+'Monthly Nos Company'!$L$41 -> 1444 | AV6: =+'Monthly Nos Company'!$L$44 -> 1455 | AW6: =+'Monthly Nos Company'!$L$47 -> 1419 | AX6: =+'Monthly Nos Company'!$L$50 -> 2122 | AY6: =+'Monthly Nos Company'!$L$53 -> 664 | AZ6: =+'Monthly Nos Company'!$L$56 -> 1539 | BA6: =+'Monthly Nos Company'!$L$59 -> 1090 | BB6: =+'Monthly Nos Company'!$L$62 -> 744 | BC6: =+'Monthly Nos Company'!$L$65 -> 313 | BD6: =+'Monthly Nos Company'!$L$68 -> 406 | BE6: =+'Monthly Nos Company'!$L$71 -> 605 | BF6: =+'Monthly Nos Company'!$L$74 -> 867 | BG6: =+'Monthly Nos Company'!$L$77 -> 382 | BH6: =+'Monthly Nos Company'!$L$80 -> 503 | BI6: =+'Monthly Nos Company'!$L$83 -> 460 | BJ6: =+'Monthly Nos Company'!$L$86 -> 676 | BK6: =+'Monthly Nos Company'!$L$89 -> 296 | BL6: =+'Monthly Nos Company'!$L$92 -> 531 | BM6: =+'Monthly Nos Company'!$L$95 -> 355 | BN6: =+'Monthly Nos Company'!$L$98 -> 351 | BO6: =+'Monthly Nos Company'!$L$101 -> 20 | BP6: =+'Monthly Nos Company'!$L$104 -> 64 | BQ6: =+'Monthly Nos Company'!$L$107 -> 89 | BR6: =+'Monthly Nos Company'!$L$110 -> 379 | BS6: =+'Monthly Nos Company'!$L$113 -> 343 | BT6: =+'Monthly Nos Company'!$L$116 -> 450 | BU6: =+'Monthly Nos Company'!$L$119 -> 561 | BV6: =+'Monthly Nos Company'!$L$122 -> 538 | BW6: =+'Monthly Nos Company'!$L$125 -> 202 | BX6: =+'Monthly Nos Company'!$L$128 -> 526 | BY6: =+'Monthly Nos Company'!$L$131 -> 958 | BZ6: =+'Monthly Nos Company'!$L$134 -> 761 | CA6: =+'Monthly Nos Company'!$L$137 -> 330 | CB6: =+'Monthly Nos Company'!$L$140 -> 989 | CC6: =+'Monthly Nos Company'!$L$143 -> 580 | CD6: =+'Monthly Nos Company'!$L$146 -> 641 | CE6: =+'Monthly Nos Company'!$L$149 -> 578 | CF6: =+'Monthly Nos Company'!$L$152 -> 823 | CG6: =+'Monthly Nos Company'!$L$155 -> 405 | CH6: =+'Monthly Nos Company'!$L$158 -> 872 | CI6: =+'Monthly Nos Company'!$L$161 -> 970 | CJ6: =+'Monthly Nos Company'!$L$164 -> 4208 | CK6: =+'Monthly Nos Company'!$L$167 -> 3420 | CL6: ='Monthly Nos Company'!L170 -> 2625
A7: Volume YoY% | O7: =+O4/N4-1 -> -0.36310179 | P7: =+P4/O4-1 -> -0.056390874 | Q7: =+Q4/P4-1 -> -0.033373314 | R7: =+R4/Q4-1 -> 0.1828929 | S7: =+S4/R4-1 -> 0.20482663 | T7: =+T4/S4-1 -> 0.11952805 | U7: =+U4/T4-1 -> -0.371128 | V7: =+V4/U4-1 -> 0.64459168 | ... AE7: =+AE4/AD4-1 -> 0.42221694 | AM7: =+AM4/AI4-1 -> -0.40980045 | AN7: =+AN4/AJ4-1 -> -0.47914337 | AO7: =+AO4/AK4-1 -> -0.35894656 | AP7: =+AP4/AL4-1 -> -0.085585473 | AQ7: =+AQ4/AM4-1 -> -0.30554874 | AR7: =+AR4/AN4-1 -> -0.1199035 | AS7: =+AS4/AO4-1 -> 0.041483902 | AT7: =+AT4/AP4-1 -> 0.16601841 | ... DB7: =+DB4/CX4-1 -> 0.42221694
A9: Co. reported Volume TTM | N9: =N4 -> 228900 | O9: =O4 -> 145786 | P9: =P4 -> 137565 | Q9: =Q4 -> 132974 | R9: =R4 -> 157294 | S9: =S4 -> 189512 | T9: =T4 -> 212164 | U9: =U4 -> 133424 | ... AA9: =AA4 -> 642771 | AL9: =SUM(AI4:AL4) -> 228900 | AM9: =SUM(AJ4:AM4) -> 203435 | AN9: =SUM(AK4:AN4) -> 168734 | AO9: =SUM(AL4:AO4) -> 149203 | AP9: =SUM(AM4:AP4) -> 145786 | AQ9: =SUM(AN4:AQ4) -> 134580 | AR9: =SUM(AO4:AR4) -> 130057 | AS9: =SUM(AP4:AS4) -> 131504 | ... CL9: =SUM(CI4:CL4) -> 642771
A10: Vahan Volume TTM | N10: =N28 -> 0 | O10: =O28 -> 0 | P10: =P28 -> 0 | Q10: =Q28 -> 0 | R10: =R28 -> 0 | S10: =S28 -> 0 | T10: =T28 -> 583718 | U10: =U28 -> 536165 | ... AA10: =AA28 -> 518234 | AL10: =SUM(AI28:AL28) -> 0 | AM10: =SUM(AJ28:AM28) -> 0 | AN10: =SUM(AK28:AN28) -> 0 | AO10: =SUM(AL28:AO28) -> 0 | AP10: =SUM(AM28:AP28) -> 0 | AQ10: =SUM(AN28:AQ28) -> 0 | AR10: =SUM(AO28:AR28) -> 0 | AS10: =SUM(AP28:AS28) -> 0 | ... CL10: =SUM(CI28:CL28) -> 518234
A11: Co. reported Volume TTM Growth YoY | O11: =O9/N9-1 -> -0.36310179 | P11: =P9/O9-1 -> -0.056390874 | Q11: =Q9/P9-1 -> -0.033373314 | R11: =R9/Q9-1 -> 0.1828929 | S11: =S9/R9-1 -> 0.20482663 | T11: =T9/S9-1 -> 0.11952805 | U11: =U9/T9-1 -> -0.371128 | V11: =V9/U9-1 -> 0.64459168 | ... AA11: =AA9/Z9-1 -> 0.15551637 | AP11: =AP9/AL9-1 -> -0.36310179 | AQ11: =AQ9/AM9-1 -> -0.33846192 | AR11: =AR9/AN9-1 -> -0.22921877 | AS11: =AS9/AO9-1 -> -0.11862362 | AT11: =AT9/AP9-1 -> -0.056390874 | AU11: =AU9/AQ9-1 -> 0.078830435 | AV11: =AV9/AR9-1 -> 0.12875124 | AW11: =AW9/AS9-1 -> 0.089525794 | ... CL11: =CL9/CH9-1 -> 0.15551637
A12: Vahan Volume TTM Growth YoY | U12: =U10/T10-1 -> -0.081465708 | V12: =V10/U10-1 -> -0.34499641 | W12: =W10/V10-1 -> 0.45944361 | X12: =X10/W10-1 -> -0.057285062 | Y12: =Y10/X10-1 -> -0.019479243 | Z12: =Z10/Y10-1 -> -0.013422153 | AA12: =AA10/Z10-1 -> 0.10873537 | BJ12: =BJ10/BF10-1 -> 2.7270887 | BK12: =BK10/BG10-1 -> 0.87123438 | BL12: =BL10/BH10-1 -> 0.2362062 | BM12: =BM10/BI10-1 -> -0.11804803 | BN12: =BN10/BJ10-1 -> -0.081465708 | BO12: =BO10/BK10-1 -> -0.25469276 | BP12: =BP10/BL10-1 -> -0.30775122 | BQ12: =BQ10/BM10-1 -> -0.28135714 | ... CL12: =CL10/CH10-1 -> 0.10873537
A14: Unit Matrix - Realisation | N14: =+N36*10^7/N4 -> 8247823.9 | O14: =+O36*10^7/O4 -> 15970920 | P14: =+P36*10^7/P4 -> 19129792 | Q14: =+Q36*10^7/Q4 -> 20533758 | R14: =+R36*10^7/R4 -> 17145760 | S14: =+S36*10^7/S4 -> 15384275 | T14: =+T36*10^7/T4 -> 14231368 | U14: =+U36*10^7/U4 -> 19566792 | ... AE14: =+AE36*10^7/AE4 -> 2191527.4 | AI14: =+AI36*10^7/AI4 -> 6971936 | AJ14: =+AJ36*10^7/AJ4 -> 5992969.1 | AK14: =+AK36*10^7/AK4 -> 8470466.1 | AL14: =+AL36*10^7/AL4 -> 14026760 | AM14: =+AM36*10^7/AM4 -> 12759774 | AN14: =+AN36*10^7/AN4 -> 15075227 | AO14: =+AO36*10^7/AO4 -> 18306035 | AP14: =+AP36*10^7/AP4 -> 17891185 | ... CL14: =+CL36*10^7/CL4 -> 5173314.5 | CM14: =+AVERAGE(CI14:CL14)*0.91 -> 5148762.5 | CN14: =+AVERAGE(CJ14:CM14)*0.91 -> 4407876.6 | CO14: =+AVERAGE(CK14:CN14)*0.91 -> 4276485 | CP14: =+AVERAGE(CL14:CO14)*0.91 -> 4323964.8 | CQ14: =+AVERAGE(CM14:CP14)*0.85 -> 3858381.4 | CR14: =+AVERAGE(CN14:CQ14)*0.85 -> 3584175.4 | CS14: =+AVERAGE(CO14:CR14)*0.85 -> 3409138.9 | CT14: =+AVERAGE(CP14:CS14)*0.85 -> 3224827.9 | CU14: =+AVERAGE(CQ14:CT14)*0.84 -> 2956070 | CV14: =+AVERAGE(CR14:CU14)*0.84 -> 2766584.6 | CW14: =+AVERAGE(CS14:CV14)*0.84 -> 2594890.5 | CX14: =+AVERAGE(CT14:CW14)*0.84 -> 2423898.3 | CY14: =+AVERAGE(CU14:CX14)*0.89 -> 2389971.1 | CZ14: =+AVERAGE(CV14:CY14)*0.89 -> 2264014.1 | DA14: =+AVERAGE(CW14:CZ14)*0.89 -> 2152192.2 | DB14: =+AVERAGE(CX14:DA14)*0.89 -> 2053691.9
A16: Standalone Revenue - TMPV | AI16: 10586.41 | AJ16: 12481.43 | AK16: 10630.09 | AL16: 11067.79 | AM16: 9104.5 | AN16: 8868.45 | AO16: 7769.67 | AP16: 8545.49 | AQ16: 7704.76 | AR16: 8752.08 | AS16: 9060.33 | AT16: 10785.79 | AU16: 9324.2 | AV16: 10693.69 | AW16: 11055.27 | AX16: 14147.98 | AY16: 11434.91 | AZ16: 11365.86 | BA16: 11207.2 | BB16: 15080.56 | BC16: 10366.19 | BD16: 13310.37 | BE16: 15962.39 | BF16: 19173.46 | BG16: 16674.99 | BH16: 17758.69 | BI16: 16207.67 | BJ16: 18561.41 | BK16: 13351.91 | BL16: 10000.48 | BM16: 10842.91 | BN16: 9732.87 | BO16: 2686.87 | BP16: 5594.6 | BQ16: 9635.78 | BR16: 13480.42 | BS16: 6576.61 | BT16: 10996.02 | BU16: 12352.78 | BV16: 17338.27 | BW16: 14874.44 | BX16: 14946.78 | BY16: 15793.98 | BZ16: 20142.13 | CA16: 15833 | CB16: 18542 | CC16: 18669 | CD16: 20260 | CE16: 16862 | CF16: 12055 | CG16: 17040 | CH16: 19999 | CI16: 15682 | CJ16: 12955
A18: Realisation YoY% | O18: =+O14/N14-1 -> 0.93637989 | P18: =+P14/O14-1 -> 0.19778894 | Q18: =+Q14/P14-1 -> 0.073391638 | R18: =+R14/Q14-1 -> -0.16499653 | S18: =+S14/R14-1 -> -0.10273585 | T18: =+T14/S14-1 -> -0.074940625 | U18: =+U14/T14-1 -> 0.37490592 | V18: =+V14/U14-1 -> -0.4182028 | ... AE18: =+AE14/AD14-1 -> -0.17248458 | AM18: =+AM14/AI14-1 -> 0.83016221 | AN18: =+AN14/AJ14-1 -> 1.5154855 | AO18: =+AO14/AK14-1 -> 1.1611603 | AP18: =+AP14/AL14-1 -> 0.27550377 | AQ18: =+AQ14/AM14-1 -> 0.99037152 | AR18: =+AR14/AN14-1 -> 0.21011636 | AS18: =+AS14/AO14-1 -> 0.055784452 | AT18: =+AT14/AP14-1 -> -0.11007299 | ... DB18: =+DB14/CX14-1 -> -0.15273183
A20: Volume - JLR | N20: =+SUM(N21:N22) -> 746698 | O20: =+SUM(O21:O22) -> 864172 | P20: =+SUM(P21:P22) -> 928688 | Q20: =+SUM(Q21:Q22) -> 1065656 | R20: =+SUM(R21:R22) -> 1204815 | S20: =+SUM(S21:S22) -> 1247819 | T20: =+SUM(T21:T22) -> 1144221 | U20: =+SUM(U21:U22) -> 1034061 | ... Z20: =+SUM(Z21:Z22) -> 829752 | AA20: =+SUM(CI20:CL20) -> 660266 | AB20: =+SUM(CM20:CP20) -> 0 | AC20: =+SUM(CQ20:CT20) -> 0 | AD20: =+SUM(CU20:CX20) -> 0 | AE20: =+SUM(CY20:DB20) -> 0 | AI20: =+SUM(AI21:AI22) -> 169210 | AJ20: =+SUM(AJ21:AJ22) -> 162191 | AK20: =+SUM(AK21:AK22) -> 183486 | AL20: =+SUM(AL21:AL22) -> 231811 | AM20: =+SUM(AM21:AM22) -> 185339 | AN20: =+SUM(AN21:AN22) -> 204575 | AO20: =+SUM(AO21:AO22) -> 228529 | AP20: =+SUM(AP21:AP22) -> 245729 | ... CL20: =+SUM(CL21:CL22) -> 188100
A21: Volume JLR - Wholesale | N21: =+SUM(AI21:AL21) -> 372062 | O21: =+SUM(AM21:AP21) -> 429861 | P21: =+SUM(AQ21:AT21) -> 466479 | Q21: =+SUM(AU21:AX21) -> 544085 | R21: =+SUM(AY21:BB21) -> 600806 | S21: =+SUM(BC21:BF21) -> 633510 | T21: =+SUM(BG21:BJ21) -> 565306 | U21: =+SUM(BK21:BN21) -> 525402 | V21: =+SUM(BO21:BR21) -> 412911 | W21: =+SUM(BS21:BV21) -> 347650 | X21: =+SUM(BW21:BZ21) -> 359480 | Y21: =+SUM(CA21:CD21) -> 401303 | Z21: =+SUM(CE21:CH21) -> 400898 | AI21: 83452 | AJ21: 77442 | AK21: 94828 | AL21: 116340 | AM21: 90620 | AN21: 101931 | AO21: 116357 | AP21: 120953 | AQ21: 115156 | AR21: 103975 | AS21: 122187 | AT21: 125161 | AU21: 114452 | AV21: 116745 | AW21: 150461 | AX21: 162427 | AY21: 134326 | AZ21: 139235 | BA21: 152245 | BB21: 175000 | BC21: 138476 | BD21: 153210 | BE21: 159067 | BF21: 182757 | BG21: 131560 | BH21: 130652 | BI21: 141552 | BJ21: 161542 | BK21: 118550 | BL21: 134489 | BM21: 145384 | BN21: 126979 | BO21: 65425 | BP21: 91367 | BQ21: 119658 | BR21: 136461 | BS21: 97141 | BT21: 78251 | BU21: 83110 | BV21: 89148 | BW21: 82587 | BX21: 89899 | BY21: 92345 | BZ21: 94649 | CA21: 93253 | CB21: 96817 | CC21: 101043 | CD21: 110190 | CE21: 97755 | CF21: 87303 | CG21: 104427 | CH21: 111413 | CI21: 87286 | CJ21: 66165 | CK21: 59200 | CL21: 95300
A22: Volume JLR - Retail | N22: =+SUM(AI22:AL22) -> 374636 | O22: =+SUM(AM22:AP22) -> 434311 | P22: =+SUM(AQ22:AT22) -> 462209 | Q22: =+SUM(AU22:AX22) -> 521571 | R22: =+SUM(AY22:BB22) -> 604009 | S22: =+SUM(BC22:BF22) -> 614309 | T22: =+SUM(BG22:BJ22) -> 578915 | U22: =+SUM(BK22:BN22) -> 508659 | V22: =+SUM(BO22:BR22) -> 439588 | W22: =+SUM(BS22:BV22) -> 376381 | X22: =+SUM(BW22:BZ22) -> 354662 | Y22: =+SUM(CA22:CD22) -> 431733 | Z22: =+SUM(CE22:CH22) -> 428854 | AI22: 85758 | AJ22: 84749 | AK22: 88658 | AL22: 115471 | AM22: 94719 | AN22: 102644 | AO22: 112172 | AP22: 124776 | AQ22: 115596 | AR22: 110781 | AS22: 111525 | AT22: 124307 | AU22: 114905 | AV22: 110200 | AW22: 137653 | AX22: 158813 | AY22: 132753 | AZ22: 142459 | BA22: 149288 | BB22: 179509 | BC22: 137463 | BD22: 149690 | BE22: 154447 | BF22: 172709 | BG22: 145510 | BH22: 129887 | BI22: 144602 | BJ22: 158916 | BK22: 128615 | BL22: 128953 | BM22: 141222 | BN22: 109869 | BO22: 74067 | BP22: 113569 | BQ22: 128469 | BR22: 123483 | BS22: 124537 | BT22: 92710 | BU22: 80126 | BV22: 79008 | BW22: 78825 | BX22: 88121 | BY22: 84827 | BZ22: 102889 | CA22: 101994 | CB22: 106561 | CC22: 109140 | CD22: 114038 | CE22: 111180 | CF22: 103108 | CG22: 106334 | CH22: 108232 | CI22: 94420 | CJ22: 85495 | CK22: 79600 | CL22: 92800
A24: Volume JLR YoY% | N24: =+N20/M20-1 -> #DIV/0! | O24: =+O20/N20-1 -> 0.15732465 | P24: =+P20/O20-1 -> 0.074656434 | Q24: =+Q20/P20-1 -> 0.14748548 | R24: =+R20/Q20-1 -> 0.13058529 | S24: =+S20/R20-1 -> 0.035693447 | T24: =+T20/S20-1 -> -0.083023259 | U24: =+U20/T20-1 -> -0.096275108 | ... AE24: =+AE20/AD20-1 -> #DIV/0! | AM24: =+AM20/AI20-1 -> 0.095319426 | AN24: =+AN20/AJ20-1 -> 0.26132153 | AO24: =+AO20/AK20-1 -> 0.24548467 | AP24: =+AP20/AL20-1 -> 0.060040291 | AQ24: =+AQ20/AM20-1 -> 0.24502668 | AR24: =+AR20/AN20-1 -> 0.049766589 | AS24: =+AS20/AO20-1 -> 0.022679835 | AT24: =+AT20/AP20-1 -> 0.015215949 | ... CL24: =+CL20/CH20-1 -> -0.14361811
A25: Volume JLR YoY% - Wholesale | N25: =+N21/M21-1 -> #DIV/0! | O25: =+O21/N21-1 -> 0.15534776 | P25: =+P21/O21-1 -> 0.085185676 | Q25: =+Q21/P21-1 -> 0.16636547 | R25: =+R21/Q21-1 -> 0.10425026 | S25: =+S21/R21-1 -> 0.054433544 | T25: =+T21/S21-1 -> -0.10766049 | U25: =+U21/T21-1 -> -0.070588319 | ... AE25: =+AE21/AD21-1 -> #DIV/0! | AM25: =+AM21/AI21-1 -> 0.085893687 | AN25: =+AN21/AJ21-1 -> 0.31622375 | AO25: =+AO21/AK21-1 -> 0.2270321 | AP25: =+AP21/AL21-1 -> 0.039651023 | AQ25: =+AQ21/AM21-1 -> 0.27075701 | AR25: =+AR21/AN21-1 -> 0.020052781 | AS25: =+AS21/AO21-1 -> 0.05010442 | AT25: =+AT21/AP21-1 -> 0.034790373 | ... CL25: =+CL21/CH21-1 -> -0.14462406
A26: Volume JLR YoY% - Retail | N26: =+N22/M22-1 -> #DIV/0! | O26: =+O22/N22-1 -> 0.15928795 | P26: =+P22/O22-1 -> 0.064235076 | Q26: =+Q22/P22-1 -> 0.12843108 | R26: =+R22/Q22-1 -> 0.1580571 | S26: =+S22/R22-1 -> 0.017052726 | T26: =+T22/S22-1 -> -0.057615955 | U26: =+U22/T22-1 -> -0.12135806 | ... AE26: =+AE22/AD22-1 -> #DIV/0! | AM26: =+AM22/AI22-1 -> 0.10449171 | AN26: =+AN22/AJ22-1 -> 0.21115293 | AO26: =+AO22/AK22-1 -> 0.26522141 | AP26: =+AP22/AL22-1 -> 0.080583004 | AQ26: =+AQ22/AM22-1 -> 0.22040984 | AR26: =+AR22/AN22-1 -> 0.079273996 | AS26: =+AS22/AO22-1 -> -0.0057679278 | AT26: =+AT22/AP22-1 -> -0.0037587357 | ... CL26: =+CL22/CH22-1 -> -0.1425826
A28: Volume Vahan | T28: =+SUM(BG28:BJ28) -> 583718 | U28: =+SUM(BK28:BN28) -> 536165 | V28: =+SUM(BO28:BR28) -> 351190 | W28: =+SUM(BS28:BV28) -> 512542 | X28: =+SUM(BW28:BZ28) -> 483181 | Y28: =+SUM(CA28:CD28) -> 473769 | Z28: =+SUM(CE28:CH28) -> 467410 | AA28: =+SUM(CI28:CL28) -> 518234 | AB28: =+SUM(CM28:CP28) -> 0 | AC28: =+SUM(CQ28:CT28) -> 0 | AD28: =+SUM(CU28:CX28) -> 0 | AE28: =+SUM(CY28:DB28) -> 0 | BF28: =+'Ignore-TMotors Retail-vaahan'!$F$6 -> 156615 | BG28: =+'Ignore-TMotors Retail-vaahan'!$F$9 -> 148381 | BH28: =+'Ignore-TMotors Retail-vaahan'!$F$12 -> 137558 | BI28: =+'Ignore-TMotors Retail-vaahan'!$F$15 -> 146452 | BJ28: =+'Ignore-TMotors Retail-vaahan'!$F$18 -> 151327 | BK28: =+'Ignore-TMotors Retail-vaahan'!$F$21 -> 135382 | BL28: =+'Ignore-TMotors Retail-vaahan'!$F$24 -> 113927 | BM28: =+'Ignore-TMotors Retail-vaahan'!$F$27 -> 118839 | BN28: =+'Ignore-TMotors Retail-vaahan'!$F$30 -> 168017 | BO28: =+'Ignore-TMotors Retail-vaahan'!$F$33 -> 24578 | BP28: =+'Ignore-TMotors Retail-vaahan'!$F$36 -> 67287 | BQ28: =+'Ignore-TMotors Retail-vaahan'!$F$39 -> 113435 | BR28: =+'Ignore-TMotors Retail-vaahan'!$F$42 -> 145890 | BS28: =+'Ignore-TMotors Retail-vaahan'!$F$45 -> 92557 | BT28: =+'Ignore-TMotors Retail-vaahan'!$F$48 -> 138997 | BU28: =+'Ignore-TMotors Retail-vaahan'!$F$51 -> 162102 | BV28: =+'Ignore-TMotors Retail-vaahan'!$F$54 -> 118886 | BW28: =+'Ignore-TMotors Retail-vaahan'!$F$57 -> 111072 | BX28: =+'Ignore-TMotors Retail-vaahan'!$F$60 -> 114327 | BY28: =+'Ignore-TMotors Retail-vaahan'!$F$63 -> 127271 | BZ28: =+'Ignore-TMotors Retail-vaahan'!$F$66 -> 130511 | CA28: =+'Ignore-TMotors Retail-vaahan'!$F$69 -> 113368 | CB28: =+'Ignore-TMotors Retail-vaahan'!$F$72 -> 102616 | CC28: =+'Ignore-TMotors Retail-vaahan'!$F$75 -> 131772 | CD28: =+'Ignore-TMotors Retail-vaahan'!$F$78 -> 126013 | CE28: =+'Ignore-TMotors Retail-vaahan'!$F$81 -> 108847 | CF28: =+'Ignore-TMotors Retail-vaahan'!$F$84 -> 100357 | CG28: =+'Ignore-TMotors Retail-vaahan'!$F$87 -> 130855 | CH28: =+'Ignore-TMotors Retail-vaahan'!$F$90 -> 127351 | CI28: =+'Ignore-TMotors Retail-vaahan'!$F$93 -> 100409 | CJ28: =+'Ignore-TMotors Retail-vaahan'!$F$96 -> 98985 | CK28: =+'Ignore-TMotors Retail-vaahan'!$F$99 -> 159488 | CL28: ='Ignore-TMotors Retail-vaahan'!F102 -> 159352
A29: Volume Vahan YoY% | U29: =+U28/T28-1 -> -0.081465708 | V29: =+V28/U28-1 -> -0.34499641 | W29: =+W28/V28-1 -> 0.45944361 | X29: =+X28/W28-1 -> -0.057285062 | Y29: =+Y28/X28-1 -> -0.019479243 | Z29: =+Z28/Y28-1 -> -0.013422153 | AA29: =+AA28/Z28-1 -> 0.10873537 | AB29: =+AB28/AA28-1 -> -1 | ... AE29: =+AE28/AD28-1 -> #DIV/0! | BJ29: =+BJ28/BF28-1 -> -0.033764327 | BK29: =+BK28/BG28-1 -> -0.087605556 | BL29: =+BL28/BH28-1 -> -0.17178935 | BM29: =+BM28/BI28-1 -> -0.18854642 | BN29: =+BN28/BJ28-1 -> 0.11029096 | BO29: =+BO28/BK28-1 -> -0.81845445 | BP29: =+BP28/BL28-1 -> -0.40938496 | BQ29: =+BQ28/BM28-1 -> -0.045473287 | ... CL29: =+CL28/CH28-1 -> 0.25128189
A32: Presentation Data (End)
A33: Profit & Loss- Annual (Start)
A34: Gross Revenue | B34: ='Annual Raw'!C6 -> 8077.81 | C34: ='Annual Raw'!D6 -> 9302.29 | D34: ='Annual Raw'!E6 -> 11425.36 | E34: ='Annual Raw'!F6 -> 16284.84 | F34: ='Annual Raw'!G6 -> 22708.23 | G34: ='Annual Raw'!H6 -> 27263.73 | H34: ='Annual Raw'!I6 -> 36922.61 | I34: ='Annual Raw'!J6 -> 40340.79 | ... AA34: ='Annual Raw'!AB6 -> 335582 | AB34: =+SUM(CM34:CP34) -> 407877.65 | AC34: =+SUM(CQ34:CT34) -> 449405.86 | AD34: =+SUM(CU34:CX34) -> 486985.76 | AE34: =+SUM(CY34:DB34) -> 573136.69 | AI34: ='QTR Raw'!C6+'QTR Raw'!C8 -> 44329.33 | AJ34: ='QTR Raw'!D6+'QTR Raw'!D8 -> 44689.05 | AK34: ='QTR Raw'!E6+'QTR Raw'!E8 -> 47322.45 | AL34: ='QTR Raw'!F6+'QTR Raw'!F8 -> 57273.79 | AM34: ='QTR Raw'!G6+'QTR Raw'!G8 -> 47862.53 | AN34: ='QTR Raw'!H6+'QTR Raw'!H8 -> 57827.96 | AO34: ='QTR Raw'!I6+'QTR Raw'!I8 -> 64718.41 | AP34: ='QTR Raw'!J6+'QTR Raw'!J8 -> 66217.53 | ... CL34: ='QTR Raw'!BF6+'QTR Raw'!BF8 -> 105447 | CM34: =+CM14*CM4/10^7 -> 88790.456 | CN34: =+CN14*CN4/10^7 -> 90521.856 | CO34: =+CO14*CO4/10^7 -> 104731.76 | CP34: =+CP14*CP4/10^7 -> 123833.59 | CQ34: =+CQ14*CQ4/10^7 -> 94631.219 | CR34: =+CR14*CR4/10^7 -> 104683.71 | CS34: =+CS14*CS4/10^7 -> 118741.35 | CT34: =+CT14*CT4/10^7 -> 131349.58 | ... DB34: =+DB14*DB4/10^7 -> 169195.62 | DF34: 102938.9
A35: Less: Exise Duty | B35: ='Annual Raw'!C7+'Annual Raw'!C8+'Annual Raw'!C9 -> 1292.24 | C35: ='Annual Raw'!D7+'Annual Raw'!D8+'Annual Raw'!D9 -> 1390.47 | D35: ='Annual Raw'!E7+'Annual Raw'!E8+'Annual Raw'!E9 -> 1816.72 | E35: ='Annual Raw'!F7+'Annual Raw'!F8+'Annual Raw'!F9 -> 2360.12 | F35: ='Annual Raw'!G7+'Annual Raw'!G8+'Annual Raw'!G9 -> 3175.39 | G35: ='Annual Raw'!H7+'Annual Raw'!H8+'Annual Raw'!H9 -> 3494.28 | H35: ='Annual Raw'!I7+'Annual Raw'!I8+'Annual Raw'!I9 -> 4561.41 | I35: ='Annual Raw'!J7+'Annual Raw'!J8+'Annual Raw'!J9 -> 4680.72 | ... AA35: ='Annual Raw'!AB7+'Annual Raw'!AB8+'Annual Raw'!AB9 -> 0 | AB35: =+SUM(CM35:CP35) -> 0 | AC35: =+SUM(CQ35:CT35) -> 0 | AD35: =+SUM(CU35:CX35) -> 0 | AE35: =+SUM(CY35:DB35) -> 0 | AI35: =+'QTR Raw'!C20+'QTR Raw'!C19+'QTR Raw'!C13+'QTR Raw'!C7 -> 1005.72 | AJ35: =+'QTR Raw'!D20+'QTR Raw'!D19+'QTR Raw'!D13+'QTR Raw'!D7 -> 1286.17 | AK35: =+'QTR Raw'!E20+'QTR Raw'!E19+'QTR Raw'!E13+'QTR Raw'!E7 -> 1232.95 | AL35: =+'QTR Raw'!F20+'QTR Raw'!F19+'QTR Raw'!F13+'QTR Raw'!F7 -> 1271.95 | AM35: =+'QTR Raw'!G20+'QTR Raw'!G19+'QTR Raw'!G13+'QTR Raw'!G7 -> 1066.06 | AN35: =+'QTR Raw'!H20+'QTR Raw'!H19+'QTR Raw'!H13+'QTR Raw'!H7 -> 961.19 | AO35: =+'QTR Raw'!I20+'QTR Raw'!I19+'QTR Raw'!I13+'QTR Raw'!I7 -> 865.13 | AP35: =+'QTR Raw'!J20+'QTR Raw'!J19+'QTR Raw'!J13+'QTR Raw'!J7 -> 900.39 | ... CL35: =+'QTR Raw'!BF20+'QTR Raw'!BF19+'QTR Raw'!BF13+'QTR Raw'!BF7 -> 1273 | DF35: 1696
A36: Net Revenue | B36: =+B34-B35 -> 6785.57 | C36: =+C34-C35 -> 7911.82 | D36: =+D34-D35 -> 9608.64 | E36: =+E34-E35 -> 13924.72 | F36: =+F34-F35 -> 19532.84 | G36: =+G34-G35 -> 23769.45 | H36: =+H34-H35 -> 32361.2 | I36: =+I34-I35 -> 35660.07 | ... AE36: =+AE34-AE35 -> 573136.69 | AI36: =+AI34-AI35 -> 43323.61 | AJ36: =+AJ34-AJ35 -> 43402.88 | AK36: =+AK34-AK35 -> 46089.5 | AL36: =+AL34-AL35 -> 56001.84 | AM36: =+AM34-AM35 -> 46796.47 | AN36: =+AN34-AN35 -> 56866.77 | AO36: =+AO34-AO35 -> 63853.28 | AP36: =+AP34-AP35 -> 65317.14 | ... DB36: =+DB34-DB35 -> 169195.62 | DF36: 102938.9
A37: Net Revenue YOY% | C37: =C36/B36-1 -> 0.16597721 | D37: =D36/C36-1 -> 0.21446646 | E37: =E36/D36-1 -> 0.4491874 | F37: =F36/E36-1 -> 0.40274562 | G37: =G36/F36-1 -> 0.21689677 | H37: =H36/G36-1 -> 0.36146188 | I37: =I36/H36-1 -> 0.10193905 | J37: =J36/I36-1 -> 0.98768398 | ... AE37: =AE36/AD36-1 -> 0.17690645 | AM37: =+IF(AI36<0,1-AM36/AI36,AM36/AI36-1) -> 0.08016091 | AN37: =+IF(AJ36<0,1-AN36/AJ36,AN36/AJ36-1) -> 0.31020729 | AO37: =+IF(AK36<0,1-AO36/AK36,AO36/AK36-1) -> 0.38541924 | AP37: =+IF(AL36<0,1-AP36/AL36,AP36/AL36-1) -> 0.16633918 | AQ37: =+IF(AM36<0,1-AQ36/AM36,AQ36/AM36-1) -> 0.38221601 | AR37: =+IF(AN36<0,1-AR36/AN36,AR36/AN36-1) -> 0.065019167 | AS37: =+IF(AO36<0,1-AS36/AO36,AS36/AO36-1) -> 0.099582512 | AT37: =+IF(AP36<0,1-AT36/AP36,AT36/AP36-1) -> 0.037671276 | ... DB37: =+IF(CX36<0,1-DB36/CX36,DB36/CX36-1) -> 0.20499913 | DF37: -0.13986063
A38: Net Revenue QOQ% | AJ38: =+IF(AI36<0,1-AJ36/AI36,AJ36/AI36-1) -> 0.0018297183 | AK38: =+IF(AJ36<0,1-AK36/AJ36,AK36/AJ36-1) -> 0.061899579 | AL38: =+IF(AK36<0,1-AL36/AK36,AL36/AK36-1) -> 0.21506721 | AM38: =+IF(AL36<0,1-AM36/AL36,AM36/AL36-1) -> -0.16437621 | AN38: =+IF(AM36<0,1-AN36/AM36,AN36/AM36-1) -> 0.21519358 | AO38: =+IF(AN36<0,1-AO36/AN36,AO36/AN36-1) -> 0.12285751 | AP38: =+IF(AO36<0,1-AP36/AO36,AP36/AO36-1) -> 0.022925369 | AQ38: =+IF(AP36<0,1-AQ36/AP36,AQ36/AP36-1) -> -0.0097112335 | ... CL38: =+IF(CK36<0,1-CL36/CK36,CL36/CK36-1) -> 0.48722268 | CM38: =+CM36/CL36-1 -> -0.14767162 | CN38: =+CN36/CM36-1 -> 0.019499839 | CO38: =+CO36/CN36-1 -> 0.15697756 | CP38: =+CP36/CO36-1 -> 0.18238815 | CQ38: =+CQ36/CP36-1 -> -0.23581945 | CR38: =+CR36/CQ36-1 -> 0.10622811 | CS38: =+CS36/CR36-1 -> 0.13428673 | CT38: =+CT36/CS36-1 -> 0.10618233 | ... DB38: =+DB36/DA36-1 -> 0.11588413 | DF38: 0.46958997
A39: Increase/Decrease in Stock | B39: ='Annual Raw'!C11 -> -56.67 | C39: ='Annual Raw'!D11 -> 97.92 | D39: ='Annual Raw'!E11 -> -103.48 | E39: ='Annual Raw'!F11 -> 75.33 | F39: ='Annual Raw'!G11 -> -231.75 | G39: ='Annual Raw'!H11 -> -207.62 | H39: ='Annual Raw'!I11 -> -333.76 | I39: ='Annual Raw'!J11 -> -13.49 | ... AA39: ='Annual Raw'!AB11 -> 1661 | AB39: =+SUM(CM39:CP39) -> 0 | AC39: =+SUM(CQ39:CT39) -> 0 | AD39: =+SUM(CU39:CX39) -> 0 | AE39: =+SUM(CY39:DB39) -> 0 | AI39: ='QTR Raw'!C10 -> -1962.03 | AJ39: ='QTR Raw'!D10 -> -1005.76 | AK39: ='QTR Raw'!E10 -> -1434.99 | AL39: ='QTR Raw'!F10 -> 1373 | AM39: ='QTR Raw'!G10 -> -2942.98 | AN39: ='QTR Raw'!H10 -> 253.76 | AO39: ='QTR Raw'!I10 -> 588.93 | AP39: ='QTR Raw'!J10 -> -740.29 | ... CL39: ='QTR Raw'!BF10 -> 6124 | DF39: 419
A40: Purchase of Finished Goods | B40: 0 | C40: 0 | D40: 0 | E40: 0 | F40: 0 | G40: 0 | H40: 0 | I40: 0 | J40: 0 | K40: 0 | L40: 0 | M40: 0 | N40: 0 | O40: 0 | P40: 0 | Q40: 0 | R40: 0 | S40: 0 | T40: 0 | U40: 0 | V40: 0 | W40: 0 | X40: 0 | Y40: 0 | Z40: 0 | AA40: 0 | AB40: =+SUM(CM40:CP40) -> 0 | AC40: =+SUM(CQ40:CT40) -> 0 | AD40: =+SUM(CU40:CX40) -> 0 | AE40: =+SUM(CY40:DB40) -> 0 | AI40: ='QTR Raw'!C12 -> 2913.9 | AJ40: ='QTR Raw'!D12 -> 3043.78 | AK40: ='QTR Raw'!E12 -> 2062.67 | AL40: ='QTR Raw'!F12 -> 2482.61 | AM40: ='QTR Raw'!G12 -> 2345.95 | AN40: ='QTR Raw'!H12 -> 3435.19 | AO40: ='QTR Raw'!I12 -> 1967.72 | AP40: ='QTR Raw'!J12 -> 3128.09 | ... CL40: ='QTR Raw'!BF12 -> 4989 | DF40: 18637
A41: Raw Material Consumed | B41: ='Annual Raw'!C12 -> 4728.07 | C41: ='Annual Raw'!D12 -> 4915.76 | D41: ='Annual Raw'!E12 -> 6018.45 | E41: ='Annual Raw'!F12 -> 8882.95 | F41: ='Annual Raw'!G12 -> 13504.17 | G41: ='Annual Raw'!H12 -> 16258.62 | H41: ='Annual Raw'!I12 -> 22372.59 | I41: ='Annual Raw'!J12 -> 24375.84 | ... AA41: ='Annual Raw'!AB12 -> 212421 | AB41: =+SUM(CM41:CP41) -> 261317.42 | AC41: =+SUM(CQ41:CT41) -> 287784.91 | AD41: =+SUM(CU41:CX41) -> 311820.34 | AE41: =+SUM(CY41:DB41) -> 366978.49 | AI41: ='QTR Raw'!C11 -> 26797.51 | AJ41: ='QTR Raw'!D11 -> 25683.23 | AK41: ='QTR Raw'!E11 -> 29043.7 | AL41: ='QTR Raw'!F11 -> 31274.13 | AM41: ='QTR Raw'!G11 -> 29440.78 | AN41: ='QTR Raw'!H11 -> 30873.07 | AO41: ='QTR Raw'!I11 -> 37340.23 | AP41: ='QTR Raw'!J11 -> 37895.96 | ... CL41: ='QTR Raw'!BF11 -> 55465 | CM41: =+CM36-CM42 -> 57011.81 | CN41: =+CN36-CN42 -> 58224.95 | CO41: =+CO36-CO42 -> 66767.639 | CP41: =+CP36-CP42 -> 79313.026 | CQ41: =+CQ36-CQ42 -> 60642.046 | CR41: =+CR36-CR42 -> 67050.727 | CS41: =+CS36-CS42 -> 75974.405 | CT41: =+CT36-CT42 -> 84117.731 | ... DB41: =+DB36-DB42 -> 108336.79 | DF41: 65687.1
A42: Gross Profit | B42: =B36-B39-B41-B40 -> 2114.17 | C42: =C36-C39-C41-C40 -> 2898.14 | D42: =D36-D39-D41-D40 -> 3693.67 | E42: =E36-E39-E41-E40 -> 4966.44 | F42: =F36-F39-F41-F40 -> 6260.42 | G42: =G36-G39-G41-G40 -> 7718.45 | H42: =H36-H39-H41-H40 -> 10322.37 | I42: =I36-I39-I41-I40 -> 11297.72 | ... AE42: =AE36-AE39-AE41-AE40 -> 206158.2 | AI42: =AI36-AI39-AI41-AI40 -> 15574.23 | AJ42: =AJ36-AJ39-AJ41-AJ40 -> 15681.63 | AK42: =AK36-AK39-AK41-AK40 -> 16418.12 | AL42: =AL36-AL39-AL41-AL40 -> 20872.1 | AM42: =AM36-AM39-AM41-AM40 -> 17952.72 | AN42: =AN36-AN39-AN41-AN40 -> 22304.75 | AO42: =AO36-AO39-AO41-AO40 -> 23956.4 | AP42: =AP36-AP39-AP41-AP40 -> 25033.38 | ... CL42: =CL36-CL39-CL41-CL40 -> 37596 | CM42: =+CM43*CM36 -> 31778.647 | CN42: =+CN43*CN36 -> 32296.906 | CO42: =+CO43*CO36 -> 37964.117 | CP42: =+CP43*CP36 -> 44520.561 | CQ42: =+CQ43*CQ36 -> 33989.172 | CR42: =+CR43*CR36 -> 37632.987 | CS42: =+CS43*CS36 -> 42766.943 | CT42: =+CT43*CT36 -> 47231.848 | ... DB42: =+DB43*DB36 -> 60858.837 | DF42: 37251.8
A43: GP% | B43: =B42/B36 -> 0.31156852 | C43: =C42/C36 -> 0.3663051 | D43: =D42/D36 -> 0.38441132 | E43: =E42/E36 -> 0.35666355 | F43: =F42/F36 -> 0.32050741 | G43: =G42/G36 -> 0.32472144 | H43: =H42/H36 -> 0.31897365 | I43: =I42/I36 -> 0.3168171 | ... AE43: =AE42/AE36 -> 0.35970163 | AI43: =AI42/AI36 -> 0.35948597 | AJ43: =AJ42/AJ36 -> 0.3613039 | AK43: =AK42/AK36 -> 0.35622257 | AL43: =AL42/AL36 -> 0.37270383 | AM43: =AM42/AM36 -> 0.38363406 | AN43: =AN42/AN36 -> 0.39222819 | AO43: =AO42/AO36 -> 0.37517885 | AP43: =AP42/AP36 -> 0.38325897 | ... CL43: =CL42/CL36 -> 0.36089619 | CM43: =AVERAGE(CI43:CL43) -> 0.35790611 | CN43: =AVERAGE(CJ43:CM43) -> 0.35678573 | CO43: =AVERAGE(CK43:CN43) -> 0.36248907 | CP43: =AVERAGE(CL43:CO43) -> 0.35951928 | CQ43: =AVERAGE(CM43:CP43) -> 0.35917505 | CR43: =AVERAGE(CN43:CQ43) -> 0.35949228 | CS43: =AVERAGE(CO43:CR43) -> 0.36016892 | CT43: =AVERAGE(CP43:CS43) -> 0.35958888 | ... DB43: =AVERAGE(CX43:DA43) -> 0.3596951 | DF43: 0.36188263
A44: GP YOY% | C44: =+IF(B42<0,1-C42/B42,C42/B42-1) -> 0.37081692 | D44: =+IF(C42<0,1-D42/C42,D42/C42-1) -> 0.27449675 | E44: =+IF(D42<0,1-E42/D42,E42/D42-1) -> 0.34458141 | F44: =+IF(E42<0,1-F42/E42,F42/E42-1) -> 0.26054478 | G44: =+IF(F42<0,1-G42/F42,G42/F42-1) -> 0.23289651 | H44: =+IF(G42<0,1-H42/G42,H42/G42-1) -> 0.33736307 | I44: =+IF(H42<0,1-I42/H42,I42/H42-1) -> 0.094488959 | J44: =+IF(I42<0,1-J42/I42,J42/I42-1) -> 1.0282845 | ... AE44: =+IF(AD42<0,1-AE42/AD42,AE42/AD42-1) -> 0.17693435 | AM44: =+IF(AI42<0,1-AM42/AI42,AM42/AI42-1) -> 0.15271959 | AN44: =+IF(AJ42<0,1-AN42/AJ42,AN42/AJ42-1) -> 0.42234895 | AO44: =+IF(AK42<0,1-AO42/AK42,AO42/AK42-1) -> 0.45914392 | AP44: =+IF(AL42<0,1-AP42/AL42,AP42/AL42-1) -> 0.19937045 | AQ44: =+IF(AM42<0,1-AQ42/AM42,AQ42/AM42-1) -> 0.38957495 | AR44: =+IF(AN42<0,1-AR42/AN42,AR42/AN42-1) -> 0.057913225 | AS44: =+IF(AO42<0,1-AS42/AO42,AS42/AO42-1) -> 0.1485148 | AT44: =+IF(AP42<0,1-AT42/AP42,AT42/AP42-1) -> 0.088916878 | ... CL44: =+IF(CH42<0,1-CL42/CH42,CL42/CH42-1) -> -0.03307443 | CM44: =+CM42/CI42-1 -> -0.16409378 | CN44: =+CN42/CJ42-1 -> 0.34335355 | CO44: =+CO42/CK42-1 -> 0.44774119 | CP44: =+CP42/CL42-1 -> 0.18418346 | CQ44: =+CQ42/CM42-1 -> 0.069560094 | CR44: =+CR42/CN42-1 -> 0.16521957 | CS44: =+CS42/CO42-1 -> 0.1265096 | CT44: =+CT42/CP42-1 -> 0.060899654 | ... DB44: =+DB42/CX42-1 -> 0.20508424 | DF44: -0.18055874
A45: GP QOQ% | AJ45: =+IF(AI42<0,1-AJ42/AI42,AJ42/AI42-1) -> 0.0068960071 | AK45: =+IF(AJ42<0,1-AK42/AJ42,AK42/AJ42-1) -> 0.046965143 | AL45: =+IF(AK42<0,1-AL42/AK42,AL42/AK42-1) -> 0.27128441 | AM45: =+IF(AL42<0,1-AM42/AL42,AM42/AL42-1) -> -0.13986997 | AN45: =+IF(AM42<0,1-AN42/AM42,AN42/AM42-1) -> 0.24241619 | AO45: =+IF(AN42<0,1-AO42/AN42,AO42/AN42-1) -> 0.07404925 | AP45: =+IF(AO42<0,1-AP42/AO42,AP42/AO42-1) -> 0.044955836 | AQ45: =+IF(AP42<0,1-AQ42/AP42,AQ42/AP42-1) -> -0.0034645741 | ... CL45: =+IF(CK42<0,1-CL42/CK42,CL42/CK42-1) -> 0.43370324 | CM45: =+CM42/CL42-1 -> -0.15473331 | CN45: =+CN42/CM42-1 -> 0.016308416 | CO45: =+CO42/CN42-1 -> 0.17547227 | CP45: =+CP42/CO42-1 -> 0.17270108 | CQ45: =+CQ42/CP42-1 -> -0.23655113 | CR45: =+CR42/CQ42-1 -> 0.10720516 | CS45: =+CS42/CR42-1 -> 0.13642169 | CT45: =+CT42/CS42-1 -> 0.10440086 | ... DB45: =+DB42/DA42-1 -> 0.11583794 | DF45: 0.42057734
A46: Employee Cost | B46: ='Annual Raw'!C14 -> 624.26 | C46: ='Annual Raw'!D14 -> 899.67 | D46: ='Annual Raw'!E14 -> 916.67 | E46: ='Annual Raw'!F14 -> 1084.33 | F46: ='Annual Raw'!G14 -> 1424.35 | G46: ='Annual Raw'!H14 -> 1777.43 | H46: ='Annual Raw'!I14 -> 2408.9 | I46: ='Annual Raw'!J14 -> 2735 | ... AA46: ='Annual Raw'!AB14 -> 45150 | AB46: =+SUM(CM46:CP46) -> 49863.07 | AC46: =+SUM(CQ46:CT46) -> 53353.485 | AD46: =+SUM(CU46:CX46) -> 57088.229 | AE46: =+SUM(CY46:DB46) -> 61084.405 | AI46: ='QTR Raw'!C16 -> 3789.69 | AJ46: ='QTR Raw'!D16 -> 4019.06 | AK46: ='QTR Raw'!E16 -> 4352.91 | AL46: ='QTR Raw'!F16 -> 4434.57 | AM46: ='QTR Raw'!G16 -> 4472.8 | AN46: ='QTR Raw'!H16 -> 5191.05 | AO46: ='QTR Raw'!I16 -> 5865.26 | AP46: ='QTR Raw'!J16 -> 6027.31 | ... CL46: ='QTR Raw'!BF16 -> 11898 | CM46: =CI46*107% -> 13365.37 | CN46: =CJ46*107% -> 11589.17 | CO46: =CK46*107% -> 12177.67 | CP46: =CL46*107% -> 12730.86 | CQ46: =CM46*107% -> 14300.946 | CR46: =CN46*107% -> 12400.412 | CS46: =CO46*107% -> 13030.107 | CT46: =CP46*107% -> 13622.02 | ... DB46: =CX46*107% -> 15595.851 | DF46: 13549.41
A47: General and Administration Expenses | B47: ='Annual Raw'!C17 -> 187.18 | C47: ='Annual Raw'!D17 -> 224.17 | D47: ='Annual Raw'!E17 -> 313.65 | E47: ='Annual Raw'!F17 -> 545.07 | F47: ='Annual Raw'!G17 -> 642.07 | G47: ='Annual Raw'!H17 -> 815.35 | H47: ='Annual Raw'!I17 -> 1015.66 | I47: ='Annual Raw'!J17 -> 772.69 | ... AA47: ='Annual Raw'!AB17 -> -4163 | AB47: =+SUM(CM47:CP47) -> 0 | AC47: =+SUM(CQ47:CT47) -> 0 | AD47: =+SUM(CU47:CX47) -> 0 | AE47: =+SUM(CY47:DB47) -> 0 | AI47: ='QTR Raw'!C17 -> 0 | AJ47: ='QTR Raw'!D17 -> 0 | AK47: ='QTR Raw'!E17 -> 0 | AL47: ='QTR Raw'!F17 -> 0 | AM47: ='QTR Raw'!G17 -> 0 | AN47: ='QTR Raw'!H17 -> 0 | AO47: ='QTR Raw'!I17 -> 0 | AP47: ='QTR Raw'!J17 -> 0 | ... CL47: ='QTR Raw'!BF17 -> 0 | DF47: 0
A48: Miscellaneous Expenses | B48: ='Annual Raw'!C19-'Annual Raw'!C20 -> 248.73 | C48: ='Annual Raw'!D19-'Annual Raw'!D20 -> 210.92 | D48: ='Annual Raw'!E19-'Annual Raw'!E20 -> 136.14 | E48: ='Annual Raw'!F19-'Annual Raw'!F20 -> 69.84 | F48: ='Annual Raw'!G19-'Annual Raw'!G20 -> 62.37 | G48: ='Annual Raw'!H19-'Annual Raw'!H20 -> 87.95 | H48: ='Annual Raw'!I19-'Annual Raw'!I20 -> 188.54 | I48: ='Annual Raw'!J19-'Annual Raw'!J20 -> 453.14 | ... AA48: ='Annual Raw'!AB19-'Annual Raw'!AB20 -> 1328 | AB48: =+SUM(CM48:CP48) -> 0 | AC48: =+SUM(CQ48:CT48) -> 0 | AD48: =+SUM(CU48:CX48) -> 0 | AE48: =+SUM(CY48:DB48) -> 0 | AI48: =+'QTR Raw'!C21 -> -2609.48 | AJ48: =+'QTR Raw'!D21 -> -2758.89 | AK48: =+'QTR Raw'!E21 -> -2532.49 | AL48: =+'QTR Raw'!F21 -> -2290.33 | AM48: =+'QTR Raw'!G21 -> -2811.29 | AN48: =+'QTR Raw'!H21 -> -3465.97 | AO48: =+'QTR Raw'!I21 -> -3598.72 | AP48: =+'QTR Raw'!J21 -> -3661.87 | ... CL48: =+'QTR Raw'!BF21 -> -8815 | DF48: -31983
A49: Other Manufacturing Expenses | B49: ='Annual Raw'!C15+'Annual Raw'!C16 -> 458.8 | C49: ='Annual Raw'!D15+'Annual Raw'!D16 -> 421.19 | D49: ='Annual Raw'!E15+'Annual Raw'!E16 -> 515.14 | E49: ='Annual Raw'!F15+'Annual Raw'!F16 -> 739.24 | F49: ='Annual Raw'!G15+'Annual Raw'!G16 -> 1071.26 | G49: ='Annual Raw'!H15+'Annual Raw'!H16 -> 1330.29 | H49: ='Annual Raw'!I15+'Annual Raw'!I16 -> 1762.78 | I49: ='Annual Raw'!J15+'Annual Raw'!J16 -> 1751.83 | ... AA49: ='Annual Raw'!AB15+'Annual Raw'!AB16 -> 29363 | AB49: =+SUM(CM49:CP49) -> 57951.14 | AC49: =+SUM(CQ49:CT49) -> 62423.392 | AD49: =+SUM(CU49:CX49) -> 63276.115 | AE49: =+SUM(CY49:DB49) -> 44909.033 | AI49: ='QTR Raw'!C14 -> 8639.14 | AJ49: ='QTR Raw'!D14 -> 9087.84 | AK49: ='QTR Raw'!E14 -> 8940.41 | AL49: ='QTR Raw'!F14 -> 10914.4 | AM49: ='QTR Raw'!G14 -> 10057.69 | AN49: ='QTR Raw'!H14 -> 11933.39 | AO49: ='QTR Raw'!I14 -> 11731.74 | AP49: ='QTR Raw'!J14 -> 12668.16 | ... CL49: ='QTR Raw'!BF14 -> 23254 | CM49: =CM52-CM46-CM47-CM48-CM50-CM51 -> 8531.1067 | CN49: =CN52-CN46-CN47-CN48-CN50-CN51 -> 14526.041 | CO49: =CO52-CO46-CO47-CO48-CO50-CO51 -> 16420.759 | CP49: =CP52-CP46-CP47-CP48-CP50-CP51 -> 18473.233 | CQ49: =CQ52-CQ46-CQ47-CQ48-CQ50-CQ51 -> 10278.313 | CR49: =CR52-CR46-CR47-CR48-CR50-CR51 -> 15126.578 | CS49: =CS52-CS46-CS47-CS48-CS50-CS51 -> 17450.325 | CT49: =CT52-CT46-CT47-CT48-CT50-CT51 -> 19568.176 | ... DB49: =DB52-DB46-DB47-DB48-DB50-DB51 -> 12928.864 | DF49: 12212.936
A50: Power & Fuel Cost | B50: ='Annual Raw'!C13 -> 185.18 | C50: ='Annual Raw'!D13 -> 200.7 | D50: ='Annual Raw'!E13 -> 210.52 | E50: ='Annual Raw'!F13 -> 235.34 | F50: ='Annual Raw'!G13 -> 267.69 | G50: ='Annual Raw'!H13 -> 291.45 | H50: ='Annual Raw'!I13 -> 368.53 | I50: ='Annual Raw'!J13 -> 377.72 | ... AA50: ='Annual Raw'!AB13 -> 1836 | AB50: =+SUM(CM50:CP50) -> 0 | AC50: =+SUM(CQ50:CT50) -> 0 | AD50: =+SUM(CU50:CX50) -> 0 | AE50: =+SUM(CY50:DB50) -> 0 | AI50: ='QTR Raw'!C15 -> 0 | AJ50: ='QTR Raw'!D15 -> 0 | AK50: ='QTR Raw'!E15 -> 0 | AL50: ='QTR Raw'!F15 -> 0 | AM50: ='QTR Raw'!G15 -> 0 | AN50: ='QTR Raw'!H15 -> 0 | AO50: ='QTR Raw'!I15 -> 0 | AP50: ='QTR Raw'!J15 -> 0 | ... CL50: ='QTR Raw'!BF15 -> 0 | DF50: 0
A51: Selling and Distribution Expenses | B51: ='Annual Raw'!C18 -> 205.82 | C51: ='Annual Raw'!D18 -> 304.66 | D51: ='Annual Raw'!E18 -> 373.84 | E51: ='Annual Raw'!F18 -> 284.61 | F51: ='Annual Raw'!G18 -> 366.15 | G51: ='Annual Raw'!H18 -> 439.5 | H51: ='Annual Raw'!I18 -> 614.45 | I51: ='Annual Raw'!J18 -> 1024.13 | ... AA51: ='Annual Raw'!AB18 -> 29910 | AB51: =+SUM(CM51:CP51) -> 0 | AC51: =+SUM(CQ51:CT51) -> 0 | AD51: =+SUM(CU51:CX51) -> 0 | AE51: =+SUM(CY51:DB51) -> 0 | AI51: ='QTR Raw'!C18 -> 0 | AJ51: ='QTR Raw'!D18 -> 0 | AK51: ='QTR Raw'!E18 -> 0 | AL51: ='QTR Raw'!F18 -> 0 | AM51: ='QTR Raw'!G18 -> 0 | AN51: ='QTR Raw'!H18 -> 0 | AO51: ='QTR Raw'!I18 -> 0 | AP51: ='QTR Raw'!J18 -> 0 | ... CL51: ='QTR Raw'!BF18 -> 0 | DF51: 0
A52: Total Cost | B52: =+SUM(B46:B51) -> 1909.97 | C52: =+SUM(C46:C51) -> 2261.31 | D52: =+SUM(D46:D51) -> 2465.96 | E52: =+SUM(E46:E51) -> 2958.43 | F52: =+SUM(F46:F51) -> 3833.89 | G52: =+SUM(G46:G51) -> 4741.97 | H52: =+SUM(H46:H51) -> 6358.86 | I52: =+SUM(I46:I51) -> 7114.51 | ... AE52: =+SUM(AE46:AE51) -> 105993.44 | AI52: =+SUM(AI46:AI51) -> 9819.35 | AJ52: =+SUM(AJ46:AJ51) -> 10348.01 | AK52: =+SUM(AK46:AK51) -> 10760.83 | AL52: =+SUM(AL46:AL51) -> 13058.64 | AM52: =+SUM(AM46:AM51) -> 11719.2 | AN52: =+SUM(AN46:AN51) -> 13658.47 | AO52: =+SUM(AO46:AO51) -> 13998.28 | AP52: =+SUM(AP46:AP51) -> 15033.6 | ... CL52: =+SUM(CL46:CL51) -> 26337 | CM52: =CM53*CM36 -> 21896.477 | CN52: =CN53*CN36 -> 26115.211 | CO52: =CO53*CO36 -> 28598.429 | CP52: =CP53*CP36 -> 31204.093 | CQ52: =CQ53*CQ36 -> 24579.259 | CR52: =CR53*CR36 -> 27526.99 | CS52: =CS53*CS36 -> 30480.432 | CT52: =CT53*CT36 -> 33190.196 | ... DB52: =DB53*DB36 -> 28524.715 | DF52: 25762.346
A53: Cost % | B53: =B52/B36 -> 0.28147525 | C53: =C52/C36 -> 0.28581414 | D53: =D52/D36 -> 0.25663986 | E53: =E52/E36 -> 0.21245885 | F53: =F52/F36 -> 0.19627919 | G53: =G52/G36 -> 0.19949852 | H53: =H52/H36 -> 0.19649642 | I53: =I52/I36 -> 0.19950914 | ... AE53: =AE52/AE36 -> 0.18493571 | AI53: =AI52/AI36 -> 0.22665124 | AJ53: =AJ52/AJ36 -> 0.23841759 | AK53: =AK52/AK36 -> 0.23347682 | AL53: =AL52/AL36 -> 0.23318234 | AM53: =AM52/AM36 -> 0.25042915 | AN53: =AN52/AN36 -> 0.24018368 | AO53: =AO52/AO36 -> 0.2192257 | AP53: =AP52/AP36 -> 0.23016317 | ... CL53: =CL52/CL36 -> 0.2528174 | CM53: =AVERAGE(CI53:CL53)*0.8 -> 0.24660845 | CN53: =AVERAGE(CJ53:CM53)*0.95 -> 0.28849619 | CO53: =AVERAGE(CK53:CN53)*0.95 -> 0.27306359 | CP53: =AVERAGE(CL53:CO53)*0.95 -> 0.25198409 | CQ53: =AVERAGE(CM53:CP53)*0.98 -> 0.25973732 | CR53: =AVERAGE(CN53:CQ53)*0.98 -> 0.26295389 | CS53: =AVERAGE(CO53:CR53)*0.98 -> 0.25669603 | CT53: =AVERAGE(CP53:CS53)*0.98 -> 0.25268597 | CU53: =AVERAGE(CQ53:CT53)*0.97 -> 0.25027775 | CV53: =AVERAGE(CR53:CU53)*0.97 -> 0.24798381 | CW53: =AVERAGE(CS53:CV53)*0.98 -> 0.24687267 | CX53: =AVERAGE(CT53:CW53)*0.98 -> 0.24446595 | CY53: =AVERAGE(CU53:CX53)*0.82 -> 0.20286804 | CZ53: =AVERAGE(CV53:CY53)*0.82 -> 0.19314905 | DA53: =AVERAGE(CW53:CZ53)*0.82 -> 0.18190792 | DB53: =AVERAGE(CX53:DA53)*0.82 -> 0.16859015 | DF53: 0.25026833
A54: EBITDA | B54: =B42-B52 -> 204.2 | C54: =C42-C52 -> 636.83 | D54: =D42-D52 -> 1227.71 | E54: =E42-E52 -> 2008.01 | F54: =F42-F52 -> 2426.53 | G54: =G42-G52 -> 2976.48 | H54: =H42-H52 -> 3963.51 | I54: =I42-I52 -> 4183.21 | ... AE54: =AE42-AE52 -> 100164.76 | AI54: =AI42-AI52 -> 5754.88 | AJ54: =AJ42-AJ52 -> 5333.62 | AK54: =AK42-AK52 -> 5657.29 | AL54: =AL42-AL52 -> 7813.46 | AM54: =AM42-AM52 -> 6233.52 | AN54: =AN42-AN52 -> 8646.28 | AO54: =AO42-AO52 -> 9958.12 | AP54: =AP42-AP52 -> 9999.78 | ... DB54: =DB42-DB52 -> 32334.122 | DF54: 11489.454
A55: EBITDA Margins | B55: =B54/B36 -> 0.030093271 | C55: =C54/C36 -> 0.080490962 | D55: =D54/D36 -> 0.12777146 | E55: =E54/E36 -> 0.14420469 | F55: =F54/F36 -> 0.12422822 | G55: =G54/G36 -> 0.12522292 | H55: =H54/H36 -> 0.12247723 | I55: =I54/I36 -> 0.11730796 | ... AE55: =AE54/AE36 -> 0.17476592 | AI55: =AI54/AI36 -> 0.13283473 | AJ55: =AJ54/AJ36 -> 0.12288632 | AK55: =AK54/AK36 -> 0.12274574 | AL55: =AL54/AL36 -> 0.13952149 | AM55: =AM54/AM36 -> 0.13320492 | AN55: =AN54/AN36 -> 0.15204451 | AO55: =AO54/AO36 -> 0.15595315 | AP55: =AP54/AP36 -> 0.1530958 | ... DB55: =DB54/DB36 -> 0.19110495 | DF55: 0.1116143
A56: EBITDA YOY% | C56: =+IF(B54<0,1-C54/B54,C54/B54-1) -> 2.1186582 | D56: =+IF(C54<0,1-D54/C54,D54/C54-1) -> 0.92784574 | E56: =+IF(D54<0,1-E54/D54,E54/D54-1) -> 0.63557355 | F56: =+IF(E54<0,1-F54/E54,F54/E54-1) -> 0.20842526 | G56: =+IF(F54<0,1-G54/F54,G54/F54-1) -> 0.22664051 | H56: =+IF(G54<0,1-H54/G54,H54/G54-1) -> 0.33160982 | I56: =+IF(H54<0,1-I54/H54,I54/H54-1) -> 0.055430666 | J56: =+IF(I54<0,1-J54/I54,J54/I54-1) -> -0.5580547 | ... AE56: =+IF(AD54<0,1-AE54/AD54,AE54/AD54-1) -> 0.82778825 | AM56: =+IF(AI54<0,1-AM54/AI54,AM54/AI54-1) -> 0.083171152 | AN56: =+IF(AJ54<0,1-AN54/AJ54,AN54/AJ54-1) -> 0.62109037 | AO56: =+IF(AK54<0,1-AO54/AK54,AO54/AK54-1) -> 0.76022795 | AP56: =+IF(AL54<0,1-AP54/AL54,AP54/AL54-1) -> 0.27981458 | AQ56: =+IF(AM54<0,1-AQ54/AM54,AQ54/AM54-1) -> 0.78811651 | AR56: =+IF(AN54<0,1-AR54/AN54,AR54/AN54-1) -> 0.10643421 | AS56: =+IF(AO54<0,1-AS54/AO54,AS54/AO54-1) -> 0.012759437 | AT56: =+IF(AP54<0,1-AT54/AP54,AT54/AP54-1) -> -0.15615144 | ... CL56: =+IF(CH54<0,1-CL54/CH54,CL54/CH54-1) -> -0.2174185 | CM56: =+CM54/CI54-1 -> -0.033434087 | CN56: =+CN54/CJ54-1 -> -5.4029169 | CO56: =+CO54/CK54-1 -> 9.6549356 | CP56: =+CP54/CL54-1 -> 0.18273986 | CQ56: =+CQ54/CM54-1 -> -0.047788739 | CR56: =+CR54/CN54-1 -> 0.63482616 | CS56: =+CS54/CO54-1 -> 0.31186414 | CT56: =+CT54/CP54-1 -> 0.054457667 | ... DB56: =+DB54/CX54-1 -> 0.99890462 | DF56: -0.31683591
A57: EBITDA QOQ% | AJ57: =+IF(AI54<0,1-AJ54/AI54,AJ54/AI54-1) -> -0.073200484 | AK57: =+IF(AJ54<0,1-AK54/AJ54,AK54/AJ54-1) -> 0.060684863 | AL57: =+IF(AK54<0,1-AL54/AK54,AL54/AK54-1) -> 0.38113125 | AM57: =+IF(AL54<0,1-AM54/AL54,AM54/AL54-1) -> -0.20220747 | AN57: =+IF(AM54<0,1-AN54/AM54,AN54/AM54-1) -> 0.38706221 | AO57: =+IF(AN54<0,1-AO54/AN54,AO54/AN54-1) -> 0.15172305 | AP57: =+IF(AO54<0,1-AP54/AO54,AP54/AO54-1) -> 0.0041835206 | AQ57: =+IF(AP54<0,1-AQ54/AP54,AQ54/AP54-1) -> 0.11465052 | ... CI57: =+IF(CH54<0,1-CI54/CH54,CI54/CH54-1) -> -0.28935845 | CJ57: =+IF(CI54>1,CJ54/CI54-1,1-CJ54/CI54) -> -1.1373239 | CK57: =+IF(CJ54>1,CK54/CJ54-1,1-CK54/CJ54) -> 1.6260684 | CL57: =+IF(CK54>1,CL54/CK54-1,1-CL54/CK54) -> 11.808874 | CM57: =+CM54/CL54-1 -> -0.12228707 | CN57: =+CN54/CM54-1 -> -0.37445972 | CO57: =+CO54/CN54-1 -> 0.51506793 | CP57: =+CP54/CO54-1 -> 0.42183549 | CQ57: =+CQ54/CP54-1 -> -0.29336267 | CR57: =+CR54/CQ54-1 -> 0.073973454 | CS57: =+CS54/CR54-1 -> 0.21576431 | CT57: =+CT54/CS54-1 -> 0.14285106 | ... DB57: =+DB54/DA54-1 -> 0.19937291 | DF57: 12.071051
A58: Depreciation | B58: ='Annual Raw'!C27 -> 347.37 | C58: ='Annual Raw'!D27 -> 392.22 | D58: ='Annual Raw'!E27 -> 400.74 | E58: ='Annual Raw'!F27 -> 429.34 | F58: ='Annual Raw'!G27 -> 531.01 | G58: ='Annual Raw'!H27 -> 623.31 | H58: ='Annual Raw'!I27 -> 688.09 | I58: ='Annual Raw'!J27 -> 782.07 | ... AA58: ='Annual Raw'!AB27 -> 19784 | AB58: =+SUM(CM58:CP58) -> 20522.3 | AC58: =+SUM(CQ58:CT58) -> 20462.388 | AD58: =+SUM(CU58:CX58) -> 20409.349 | AE58: =+SUM(CY58:DB58) -> 20362.394 | AI58: ='QTR Raw'!C28 -> 1565.87 | AJ58: ='QTR Raw'!D28 -> 1594.39 | AK58: ='QTR Raw'!E28 -> 2069.97 | AL58: ='QTR Raw'!F28 -> 2346.32 | AM58: ='QTR Raw'!G28 -> 2355.45 | AN58: ='QTR Raw'!H28 -> 2736.94 | AO58: ='QTR Raw'!I28 -> 2860.29 | AP58: ='QTR Raw'!J28 -> 3125.48 | ... CL58: ='QTR Raw'!BF28 -> 5092 | CM58: =CM59*CL160 -> 5136.6 | CN58: =CN59*CM160 -> 5132.502 | CO58: =CO59*CN160 -> 5128.5269 | CP58: =CP59*CO160 -> 5124.6711 | CQ58: =CQ59*CP160 -> 5120.931 | CR58: =CR59*CQ160 -> 5117.3031 | CS58: =CS59*CR160 -> 5113.784 | CT58: =CT59*CS160 -> 5110.3705 | ... DB58: =DB59*DA160 -> 5086.5021 | DF58: 5439.6
A59: Depreciation % of Net Block | B59: =+B58/B160 -> 0.09792049 | C59: =+C58/C160 -> 0.10537147 | D59: =+D58/D160 -> 0.11263576 | E59: =+E58/E160 -> 0.11486989 | F59: =+F58/F160 -> 0.13139584 | G59: =+G58/G160 -> 0.1397105 | H59: =+H58/H160 -> 0.13950042 | I59: =+I58/I160 -> 0.113095 | ... AE59: =+AE58/AE160 -> 0.12015794 | AI59: =+AI58/AH160 -> #DIV/0! | AJ59: =+AJ58/AI160 -> #DIV/0! | AK59: =+AK58/AJ160 -> 0.031368743 | AL59: =+AL58/AK160 -> 0.035556606 | AM59: =+AM58/AL160 -> 0.033715315 | AN59: =+AN58/AM160 -> 0.039175866 | AO59: =+AO58/AN160 -> 0.032363745 | AP59: =+AP58/AO160 -> 0.03536433 | ... CL59: =+CL58/CK160 -> 0.033699537 | CM59: 0.03 | CN59: =CM59 -> 0.03 | CO59: =CN59 -> 0.03 | CP59: =CO59 -> 0.03 | CQ59: 0.03 | CR59: =CQ59 -> 0.03 | CS59: =CR59 -> 0.03 | CT59: =CS59 -> 0.03 | CU59: =CT59 -> 0.03 | CV59: =CU59 -> 0.03 | CW59: =CV59 -> 0.03 | CX59: =CW59 -> 0.03 | CY59: =CX59 -> 0.03 | ... DB59: =DA59 -> 0.03 | DF59: 0.036
A60: EBIT | B60: =B54-B58 -> -143.17 | C60: =C54-C58 -> 244.61 | D60: =D54-D58 -> 826.97 | E60: =E54-E58 -> 1578.67 | F60: =F54-F58 -> 1895.52 | G60: =G54-G58 -> 2353.17 | H60: =H54-H58 -> 3275.42 | I60: =I54-I58 -> 3401.14 | ... AE60: =AE54-AE58 -> 79802.368 | AI60: =AI54-AI58 -> 4189.01 | AJ60: =AJ54-AJ58 -> 3739.23 | AK60: =AK54-AK58 -> 3587.32 | AL60: =AL54-AL58 -> 5467.14 | AM60: =AM54-AM58 -> 3878.07 | AN60: =AN54-AN58 -> 5909.34 | AO60: =AO54-AO58 -> 7097.83 | AP60: =AP54-AP58 -> 6874.3 | ... DB60: =DB54-DB58 -> 27247.62 | DF60: 6049.8536
A61: Other Income | B61: ='Annual Raw'!C23 -> 134.32 | C61: ='Annual Raw'!D23 -> 44.16 | D61: ='Annual Raw'!E23 -> 67.2 | E61: ='Annual Raw'!F23 -> 89.99 | F61: ='Annual Raw'!G23 -> 200.44 | G61: ='Annual Raw'!H23 -> 307.15 | H61: ='Annual Raw'!I23 -> 277.64 | I61: ='Annual Raw'!J23 -> 437.14 | ... AA61: ='Annual Raw'!AB23 -> 6608 | AB61: =+SUM(CM61:CP61) -> 0 | AC61: =+SUM(CQ61:CT61) -> 0 | AD61: =+SUM(CU61:CX61) -> 0 | AE61: =+SUM(CY61:DB61) -> 0 | AI61: ='QTR Raw'!C23 -> 238.6 | AJ61: ='QTR Raw'!D23 -> 206.82 | AK61: ='QTR Raw'!E23 -> 188.64 | AL61: ='QTR Raw'!F23 -> 178.6 | AM61: ='QTR Raw'!G23 -> 183.03 | AN61: ='QTR Raw'!H23 -> 232.77 | AO61: ='QTR Raw'!I23 -> 157.95 | AP61: ='QTR Raw'!J23 -> 254.84 | ... CL61: ='QTR Raw'!BF23 -> 1633 | DF61: 6580
A62: Interest | B62: ='Annual Raw'!C25 -> 491.49 | C62: ='Annual Raw'!D25 -> 468.92 | D62: ='Annual Raw'!E25 -> 353.67 | E62: ='Annual Raw'!F25 -> 227.57 | F62: ='Annual Raw'!G25 -> 236.16 | G62: ='Annual Raw'!H25 -> 309.64 | H62: ='Annual Raw'!I25 -> 465.06 | I62: ='Annual Raw'!J25 -> 912.72 | ... AA62: ='Annual Raw'!AB25 -> 2827 | AB62: =+SUM(CM62:CP62) -> -922.38524 | AC62: =+SUM(CQ62:CT62) -> 719.2359 | AD62: =+SUM(CU62:CX62) -> 6184.685 | AE62: =+SUM(CY62:DB62) -> 14752.929 | AI62: ='QTR Raw'!C25 -> 804.39 | AJ62: ='QTR Raw'!D25 -> 847.35 | AK62: ='QTR Raw'!E25 -> 934.58 | AL62: ='QTR Raw'!F25 -> 969.13 | AM62: ='QTR Raw'!G25 -> 948.88 | AN62: ='QTR Raw'!H25 -> 1112.52 | AO62: ='QTR Raw'!I25 -> 1004.83 | AP62: ='QTR Raw'!J25 -> 1667.55 | ... CL62: ='QTR Raw'!BF25 -> 767 | CM62: =CM63*CL194 -> -216.84 | CN62: =CN63*CM194 -> -299.16695 | CO62: =CO63*CN194 -> -274.29718 | CP62: =CP63*CO194 -> -132.08111 | CQ62: =CQ63*CP194 -> 377.6319 | CR62: =CR63*CQ194 -> -551.11948 | CS62: =CS63*CR194 -> 43.675125 | CT62: =CT63*CS194 -> 849.04835 | ... DB62: =DB63*DA194 -> 5176.3587 | DF62: -826.06316
A63: Interest % of Debt | B63: =+B62/B154 -> 0.16389119 | C63: =+C62/C154 -> 0.16626541 | D63: =+D62/D154 -> 0.19761965 | E63: =+E62/E154 -> 0.13398924 | F63: =+F62/F154 -> 0.087009063 | G63: =+G62/G154 -> 0.091632782 | H63: =+H62/H154 -> 0.063690272 | I63: =+I62/I154 -> 0.078785519 | ... AE63: =+AE62/AE154 -> 0.21089772 | AI63: =(AI62-AI61)/AH194 -> #DIV/0! | AJ63: =(AJ62-AJ61)/AI194 -> #DIV/0! | AK63: =(AK62-AK61)/AJ194 -> 0.041396748 | AL63: =(AL62-AL61)/AK194 -> 0.045666997 | AM63: =(AM62-AM61)/AL194 -> 0.05065695 | AN63: =(AN62-AN61)/AM194 -> 0.055839232 | AO63: =(AO62-AO61)/AN194 -> 0.036035806 | AP63: =(AP62-AP61)/AO194 -> 0.079672624 | ... CL63: =(CL62-CL61)/CK194 -> -0.071097331 | CM63: -0.01 | CN63: =+CM63 -> -0.01 | CO63: =+CN63 -> -0.01 | CP63: =+CO63 -> -0.01 | CQ63: -0.05 | CR63: =+CQ63 -> -0.05 | CS63: =+CR63 -> -0.05 | CT63: =+CS63 -> -0.05 | CU63: =+CT63 -> -0.05 | CV63: =+CU63 -> -0.05 | CW63: =+CV63 -> -0.05 | CX63: =+CW63 -> -0.05 | CY63: =+CX63 -> -0.05 | ... DB63: =+DA63 -> -0.05 | DF63: -0.067818575
A64: PBT | B64: =B60+B61-B62 -> -500.34 | C64: =C60+C61-C62 -> -180.15 | D64: =D60+D61-D62 -> 540.5 | E64: =E60+E61-E62 -> 1441.09 | F64: =F60+F61-F62 -> 1859.8 | G64: =G60+G61-G62 -> 2350.68 | H64: =H60+H61-H62 -> 3088 | I64: =I60+I61-I62 -> 2925.56 | ... AE64: =AE60+AE61-AE62 -> 65049.44 | AI64: =AI60+AI61-AI62 -> 3623.22 | AJ64: =AJ60+AJ61-AJ62 -> 3098.7 | AK64: =AK60+AK61-AK62 -> 2841.38 | AL64: =AL60+AL61-AL62 -> 4676.61 | AM64: =AM60+AM61-AM62 -> 3112.22 | AN64: =AN60+AN61-AN62 -> 5029.59 | AO64: =AO60+AO61-AO62 -> 6250.95 | AP64: =AP60+AP61-AP62 -> 5461.59 | ... DB64: =DB60+DB61-DB62 -> 22071.261 | DF64: 6875.9168
A65: Tax | B65: ='Annual Raw'!C30 -> 0 | C65: ='Annual Raw'!D30 -> -67.4 | D65: ='Annual Raw'!E30 -> 226.4 | E65: ='Annual Raw'!F30 -> 530.77 | F65: ='Annual Raw'!G30 -> 490.62 | G65: ='Annual Raw'!H30 -> 640 | H65: ='Annual Raw'!I30 -> 883.21 | I65: ='Annual Raw'!J30 -> 851.54 | ... AA65: ='Annual Raw'!AB30 -> -246 | AB65: =+SUM(CM65:CP65) -> 4291.8765 | AC65: =+SUM(CQ65:CT65) -> 5696.975 | AD65: =+SUM(CU65:CX65) -> 6524.2433 | AE65: =+SUM(CY65:DB65) -> 15047.528 | AI65: ='QTR Raw'!C29 -> 868.82 | AJ65: ='QTR Raw'!D29 -> 987.64 | AK65: ='QTR Raw'!E29 -> 1031.84 | AL65: ='QTR Raw'!F29 -> 884.83 | AM65: ='QTR Raw'!G29 -> 1165.54 | AN65: ='QTR Raw'!H29 -> 1194.02 | AO65: ='QTR Raw'!I29 -> 1308.3 | AP65: ='QTR Raw'!J29 -> 1096.93 | ... CL65: ='QTR Raw'!BF29 -> 1399 | CM65: =+CM64*CM66 -> 956.05312 | CN65: =+CN64*CN66 -> 323.35291 | CO65: =+CO64*CO66 -> 1048.4688 | CP65: =+CP64*CP66 -> 1964.0017 | CQ65: =+CQ64*CQ66 -> 880.8559 | CR65: =+CR64*CR66 -> 1292.6687 | CS65: =+CS64*CS66 -> 1651.972 | CT65: =+CT64*CT66 -> 1871.4784 | ... DB65: =+DB64*DB66 -> 5105.3653 | DF65: 2115.153
A66: Tax Rate % | B66: =B65/B64 -> 0 | C66: =C65/C64 -> 0.37413267 | D66: =D65/D64 -> 0.41887142 | E66: =E65/E64 -> 0.36831149 | F66: =F65/F64 -> 0.26380256 | G66: =G65/G64 -> 0.27226164 | H66: =H65/H64 -> 0.2860136 | I66: =I65/I64 -> 0.29106906 | ... AE66: =AE65/AE64 -> 0.23132448 | AI66: =AI65/AI64 -> 0.23979223 | AJ66: =AJ65/AJ64 -> 0.31872721 | AK66: =AK65/AK64 -> 0.36314748 | AL66: =AL65/AL64 -> 0.18920329 | AM66: =AM65/AM64 -> 0.37450437 | AN66: =AN65/AN64 -> 0.23739907 | AO66: =AO65/AO64 -> 0.20929619 | AP66: =AP65/AP64 -> 0.20084444 | ... CL66: =CL65/CL64 -> 0.19891938 | CM66: =AVERAGE(CI66:CL66)-10% -> 0.19265904 | CN66: =AVERAGE(CJ66:CM66)-3% -> 0.23981195 | CO66: =AVERAGE(CK66:CN66)-2% -> 0.2324013 | CP66: =AVERAGE(CL66:CO66)+2% -> 0.23594792 | CQ66: =AVERAGE(CM66:CP66) -> 0.22520505 | CR66: =AVERAGE(CN66:CQ66) -> 0.23334155 | CS66: =AVERAGE(CO66:CR66) -> 0.23172395 | CT66: =AVERAGE(CP66:CS66) -> 0.23155462 | CU66: =AVERAGE(CQ66:CT66) -> 0.23045629 | CV66: =AVERAGE(CR66:CU66) -> 0.2317691 | CW66: =AVERAGE(CS66:CV66) -> 0.23137599 | CX66: =AVERAGE(CT66:CW66) -> 0.231289 | ... DB66: =AVERAGE(CX66:DA66) -> 0.2313128 | DF66: 0.3076176
A67: PAT | B67: =B64-B65 -> -500.34 | C67: =C64-C65 -> -112.75 | D67: =D64-D65 -> 314.1 | E67: =E64-E65 -> 910.32 | F67: =F64-F65 -> 1369.18 | G67: =G64-G65 -> 1710.68 | H67: =H64-H65 -> 2204.79 | I67: =I64-I65 -> 2074.02 | ... AE67: =AE64-AE65 -> 50001.912 | AI67: =AI64-AI65 -> 2754.4 | AJ67: =AJ64-AJ65 -> 2111.06 | AK67: =AK64-AK65 -> 1809.54 | AL67: =AL64-AL65 -> 3791.78 | AM67: =AM64-AM65 -> 1946.68 | AN67: =AN64-AN65 -> 3835.57 | AO67: =AO64-AO65 -> 4942.65 | AP67: =AP64-AP65 -> 4364.66 | ... DB67: =DB64-DB65 -> 16965.896 | DF67: 4760.7638
A68: PAT % | B68: =+B67/B36 -> -0.073735884 | C68: =+C67/C36 -> -0.01425083 | D68: =+D67/D36 -> 0.03268933 | E68: =+E67/E36 -> 0.065374385 | F68: =+F67/F36 -> 0.07009631 | G68: =+G67/G36 -> 0.071969692 | H68: =+H67/H36 -> 0.068130663 | I68: =+I67/I36 -> 0.05816085 | ... AE68: =+AE67/AE36 -> 0.08724256 | AI68: =+AI67/AI36 -> 0.063577343 | AJ68: =+AJ67/AJ36 -> 0.048638708 | AK68: =+AK67/AK36 -> 0.039261437 | AL68: =+AL67/AL36 -> 0.067708132 | AM68: =+AM67/AM36 -> 0.041598864 | AN68: =+AN67/AN36 -> 0.067448353 | AO68: =+AO67/AO36 -> 0.07740636 | AP68: =+AP67/AP36 -> 0.066822583 | ... DB68: =+DB67/DB36 -> 0.10027385 | DF68: 0.046248442
A69: PAT YOY% | C69: =+IF(B67<0,1-C67/B67,C67/B67-1) -> 0.77465324 | D69: =+IF(C67<0,1-D67/C67,D67/C67-1) -> 3.7858093 | E69: =+IF(D67<0,1-E67/D67,E67/D67-1) -> 1.8981853 | F69: =+IF(E67<0,1-F67/E67,F67/E67-1) -> 0.5040645 | G69: =+IF(F67<0,1-G67/F67,G67/F67-1) -> 0.24941936 | H69: =+IF(G67<0,1-H67/G67,H67/G67-1) -> 0.28883836 | I69: =+IF(H67<0,1-I67/H67,I67/H67-1) -> -0.059311771 | J69: =+IF(I67<0,1-J67/I67,J67/I67-1) -> -2.0249226 | ... AE69: =+IF(AD67<0,1-AE67/AD67,AE67/AD67-1) -> 1.3060636 | AM69: =+IF(AI67<0,1-AM67/AI67,AM67/AI67-1) -> -0.29324717 | AN69: =+IF(AJ67<0,1-AN67/AJ67,AN67/AJ67-1) -> 0.81689294 | AO69: =+IF(AK67<0,1-AO67/AK67,AO67/AK67-1) -> 1.73144 | AP69: =+IF(AL67<0,1-AP67/AL67,AP67/AL67-1) -> 0.15108471 | AQ69: =+IF(AM67<0,1-AQ67/AM67,AQ67/AM67-1) -> 1.7325395 | AR69: =+IF(AN67<0,1-AR67/AN67,AR67/AN67-1) -> -0.14473729 | AS69: =+IF(AO67<0,1-AS67/AO67,AS67/AO67-1) -> -0.24413422 | AT69: =+IF(AP67<0,1-AT67/AP67,AT67/AP67-1) -> -0.56271966 | ... CL69: =+IF(CH67<0,1-CL67/CH67,CL67/CH67-1) -> -0.24890015 | CM69: =+CM67/CI67-1 -> 0.020207989 | CN69: =+CN67/CJ67-1 -> -1.2698808 | CO69: =+CO67/CK67-1 -> -2.6851532 | CP69: =+CP67/CL67-1 -> 0.12883855 | CQ69: =+CQ67/CM67-1 -> -0.24357844 | CR69: =+CR67/CN67-1 -> 3.1435262 | CS69: =+CS67/CO67-1 -> 0.58160433 | CT69: =+CT67/CP67-1 -> -0.023447267 | ... DB69: =+DB67/CX67-1 -> 1.5143756 | DF69: -0.47149603
A70: PAT QOQ% | AJ70: =+IF(AI67<0,1-AJ67/AI67,AJ67/AI67-1) -> -0.23356811 | AK70: =+IF(AJ67<0,1-AK67/AJ67,AK67/AJ67-1) -> -0.14282872 | AL70: =+IF(AK67<0,1-AL67/AK67,AL67/AK67-1) -> 1.0954386 | AM70: =+IF(AL67<0,1-AM67/AL67,AM67/AL67-1) -> -0.48660524 | AN70: =+IF(AM67<0,1-AN67/AM67,AN67/AM67-1) -> 0.97031356 | AO70: =+IF(AN67<0,1-AO67/AN67,AO67/AN67-1) -> 0.28863507 | AP70: =+IF(AO67<0,1-AP67/AO67,AP67/AO67-1) -> -0.11693929 | AQ70: =+IF(AP67<0,1-AQ67/AP67,AQ67/AP67-1) -> 0.21873869 | ... CL70: =+IF(CK67<0,1-CL67/CK67,CL67/CK67-1) -> 3.7416058 | CM70: =+CM67/CL67-1 -> -0.28889656 | CN70: =+CN67/CM67-1 -> -0.74415474 | CO70: =+CO67/CN67-1 -> 2.3785022 | CP70: =+CP67/CO67-1 -> 0.83652763 | CQ70: =+CQ67/CP67-1 -> -0.52349787 | CR70: =+CR67/CQ67-1 -> 0.4014692 | CS70: =+CS67/CR67-1 -> 0.28959094 | CT70: =+CT67/CS67-1 -> 0.1339537 | ... DB70: =+DB67/DA67-1 -> 0.22211164 | DF70: 3.3166734
A71: Minority Interest | B71: ='Annual Raw'!C32 -> 0 | C71: ='Annual Raw'!D32 -> 5.56 | D71: ='Annual Raw'!E32 -> -0.85 | E71: ='Annual Raw'!F32 -> -4.44 | F71: ='Annual Raw'!G32 -> -8.48 | G71: ='Annual Raw'!H32 -> -22.29 | H71: ='Annual Raw'!I32 -> -74.22 | I71: ='Annual Raw'!J32 -> -132.25 | ... AA71: ='Annual Raw'!AB32 -> -255 | AB71: =+SUM(CM71:CP71) -> -380 | AC71: =+SUM(CQ71:CT71) -> -380 | AD71: =+SUM(CU71:CX71) -> -380 | AE71: =+SUM(CY71:DB71) -> -380 | AI71: ='QTR Raw'!C34 -> -27.61 | AJ71: ='QTR Raw'!D34 -> -23.04 | AK71: ='QTR Raw'!E34 -> -15.19 | AL71: ='QTR Raw'!F34 -> -17.83 | AM71: ='QTR Raw'!G34 -> -19.81 | AN71: ='QTR Raw'!H34 -> -10.63 | AO71: ='QTR Raw'!I34 -> -8.5 | AP71: ='QTR Raw'!J34 -> -20.51 | ... CL71: ='QTR Raw'!BF34 -> -95 | CM71: =+CL71 -> -95 | CN71: =+CM71 -> -95 | CO71: =+CN71 -> -95 | CP71: =+CO71 -> -95 | CQ71: =+CP71 -> -95 | CR71: =+CQ71 -> -95 | CS71: =+CR71 -> -95 | CT71: =+CS71 -> -95 | ... DB71: =+DA71 -> -95 | DF71: -3
A72: Share of Associate | B72: ='Annual Raw'!C33+'Annual Raw'!C28 -> 0 | C72: ='Annual Raw'!D33+'Annual Raw'!D28 -> 0 | D72: ='Annual Raw'!E33+'Annual Raw'!E28 -> -16.13 | E72: ='Annual Raw'!F33+'Annual Raw'!F28 -> 18.05 | F72: ='Annual Raw'!G33+'Annual Raw'!G28 -> 40.13 | G72: ='Annual Raw'!H33+'Annual Raw'!H28 -> 43.93 | H72: ='Annual Raw'!I33+'Annual Raw'!I28 -> 39.42 | I72: ='Annual Raw'!J33+'Annual Raw'!J28 -> 65.2 | ... AA72: ='Annual Raw'!AB33+'Annual Raw'!AB28 -> 446 | AB72: =+SUM(CM72:CP72) -> 536 | AC72: =+SUM(CQ72:CT72) -> 536 | AD72: =+SUM(CU72:CX72) -> 536 | AE72: =+SUM(CY72:DB72) -> 536 | AI72: ='QTR Raw'!C35 -> -41.35 | AJ72: ='QTR Raw'!D35 -> -3.19 | AK72: ='QTR Raw'!E35 -> 6.68 | AL72: ='QTR Raw'!F35 -> 150.07 | AM72: ='QTR Raw'!G35 -> -22.16 | AN72: ='QTR Raw'!H35 -> -9.24 | AO72: ='QTR Raw'!I35 -> -5.01 | AP72: ='QTR Raw'!J35 -> -17.3 | ... CL72: ='QTR Raw'!BF35 -> 134 | CM72: =+CL72 -> 134 | CN72: =+CM72 -> 134 | CO72: =+CN72 -> 134 | CP72: =+CO72 -> 134 | CQ72: =+CP72 -> 134 | CR72: =+CQ72 -> 134 | CS72: =+CR72 -> 134 | CT72: =+CS72 -> 134 | ... DB72: =+DA72 -> 134 | DF72: 169
A73: Exceptional Income / Expenses | B73: ='Annual Raw'!C29+'Annual Raw'!C31+'Annual Raw'!C34+'Annual Raw'!C36 -> 0 | C73: ='Annual Raw'!D29+'Annual Raw'!D31+'Annual Raw'!D34+'Annual Raw'!D36 -> 0 | D73: ='Annual Raw'!E29+'Annual Raw'!E31+'Annual Raw'!E34+'Annual Raw'!E36 -> 0 | E73: ='Annual Raw'!F29+'Annual Raw'!F31+'Annual Raw'!F34+'Annual Raw'!F36 -> -8.64 | F73: ='Annual Raw'!G29+'Annual Raw'!G31+'Annual Raw'!G34+'Annual Raw'!G36 -> -15.49 | G73: ='Annual Raw'!H29+'Annual Raw'!H31+'Annual Raw'!H34+'Annual Raw'!H36 -> -4.23 | H73: ='Annual Raw'!I29+'Annual Raw'!I31+'Annual Raw'!I34+'Annual Raw'!I36 -> 0 | I73: ='Annual Raw'!J29+'Annual Raw'!J31+'Annual Raw'!J34+'Annual Raw'!J36 -> 160.73 | ... AA73: ='Annual Raw'!AB29+'Annual Raw'!AB31+'Annual Raw'!AB34+'Annual Raw'!AB36 -> 79880 | AB73: =+SUM(CM73:CP73) -> 0 | AC73: =+SUM(CQ73:CT73) -> 0 | AD73: =+SUM(CU73:CX73) -> 0 | AE73: =+SUM(CY73:DB73) -> 0 | AI73: ='QTR Raw'!C26+'QTR Raw'!C31+'QTR Raw'!C32+'QTR Raw'!C33+'QTR Raw'!C36+'QTR Raw'!C37+'QTR Raw'!C39 -> -440.53 | AJ73: ='QTR Raw'!D26+'QTR Raw'!D31+'QTR Raw'!D32+'QTR Raw'!D33+'QTR Raw'!D36+'QTR Raw'!D37+'QTR Raw'!D39 -> -10.1 | AK73: ='QTR Raw'!E26+'QTR Raw'!E31+'QTR Raw'!E32+'QTR Raw'!E33+'QTR Raw'!E36+'QTR Raw'!E37+'QTR Raw'!E39 -> -173.53 | AL73: ='QTR Raw'!F26+'QTR Raw'!F31+'QTR Raw'!F32+'QTR Raw'!F33+'QTR Raw'!F36+'QTR Raw'!F37+'QTR Raw'!F39 -> 21.45 | AM73: ='QTR Raw'!G26+'QTR Raw'!G31+'QTR Raw'!G32+'QTR Raw'!G33+'QTR Raw'!G36+'QTR Raw'!G37+'QTR Raw'!G39 -> -178.64 | AN73: ='QTR Raw'!H26+'QTR Raw'!H31+'QTR Raw'!H32+'QTR Raw'!H33+'QTR Raw'!H36+'QTR Raw'!H37+'QTR Raw'!H39 -> -273.84 | AO73: ='QTR Raw'!I26+'QTR Raw'!I31+'QTR Raw'!I32+'QTR Raw'!I33+'QTR Raw'!I36+'QTR Raw'!I37+'QTR Raw'!I39 -> -124.34 | AP73: ='QTR Raw'!J26+'QTR Raw'!J31+'QTR Raw'!J32+'QTR Raw'!J33+'QTR Raw'!J36+'QTR Raw'!J37+'QTR Raw'!J39 -> -408.56 | ... CL73: ='QTR Raw'!BF26+'QTR Raw'!BF31+'QTR Raw'!BF32+'QTR Raw'!BF33+'QTR Raw'!BF36+'QTR Raw'!BF37+'QTR Raw'!BF39 -> 110 | DF73: 78465
A74: Consolidated Net Profit | B74: =B67+B71+B72+B73 -> -500.34 | C74: =C67+C71+C72+C73 -> -107.19 | D74: =D67+D71+D72+D73 -> 297.12 | E74: =E67+E71+E72+E73 -> 915.29 | F74: =F67+F71+F72+F73 -> 1385.34 | G74: =G67+G71+G72+G73 -> 1728.09 | H74: =H67+H71+H72+H73 -> 2169.99 | I74: =I67+I71+I72+I73 -> 2167.7 | ... AE74: =AE67+AE71+AE72+AE73 -> 50157.912 | AI74: =AI67+AI71+AI72+AI73 -> 2244.91 | AJ74: =AJ67+AJ71+AJ72+AJ73 -> 2074.73 | AK74: =AK67+AK71+AK72+AK73 -> 1627.5 | AL74: =AL67+AL71+AL72+AL73 -> 3945.47 | AM74: =AM67+AM71+AM72+AM73 -> 1726.07 | AN74: =AN67+AN71+AN72+AN73 -> 3541.86 | AO74: =AO67+AO71+AO72+AO73 -> 4804.8 | AP74: =AP67+AP71+AP72+AP73 -> 3918.29 | ... DB74: =DB67+DB71+DB72+DB73 -> 17004.896 | DF74: 4926.7638
A75: Profit & Loss- Annual (End)
A77: Ace - PAT | B77: ='Annual Raw'!C35 -> -500.34 | C77: ='Annual Raw'!D35 -> -107.19 | D77: ='Annual Raw'!E35 -> 297.12 | E77: ='Annual Raw'!F35 -> 915.29 | F77: ='Annual Raw'!G35 -> 1385.34 | G77: ='Annual Raw'!H35 -> 1728.09 | H77: ='Annual Raw'!I35 -> 2169.99 | I77: ='Annual Raw'!J35 -> 2167.7 | ... AA77: ='Annual Raw'!AB35 -> 82390 | AB77: =+AB74 -> 15010.23 | AC77: =+AC74 -> 19121.474 | AD77: =+AD74 -> 21838.798 | AE77: =+AE74 -> 50157.912 | AI77: ='QTR Raw'!C42 -> 2244.91 | AJ77: ='QTR Raw'!D42 -> 2074.73 | AK77: ='QTR Raw'!E42 -> 1627.5 | AL77: ='QTR Raw'!F42 -> 3945.47 | AM77: ='QTR Raw'!G42 -> 1726.07 | AN77: ='QTR Raw'!H42 -> 3541.86 | AO77: ='QTR Raw'!I42 -> 4804.8 | AP77: ='QTR Raw'!J42 -> 3918.29 | ... CL77: ='QTR Raw'!BF42 -> 5783 | DF77: 82391
A78: Checksum - PAT | B78: =B77-B74 -> -9.094947e-13 | C78: =C77-C74 -> -3.126388e-13 | D78: =D77-D74 -> -9.094947e-13 | E78: =E77-E74 -> 0 | F78: =F77-F74 -> 0 | G78: =G77-G74 -> 0 | H78: =H77-H74 -> 0 | I78: =I77-I74 -> 0 | ... AE78: =AE77-AE74 -> 0 | AI78: =AI77-AI74 -> -3.6379788e-12 | AJ78: =AJ77-AJ74 -> -6.3664629e-12 | AK78: =AK77-AK74 -> -2.9558578e-12 | AL78: =AL77-AL74 -> -3.6379788e-12 | AM78: =AM77-AM74 -> -4.3200998e-12 | AN78: =AN77-AN74 -> 3.6379788e-12 | AO78: =AO77-AO74 -> 7.2759576e-12 | AP78: =AP77-AP74 -> 6.8212103e-12 | ... CL78: =CL77-CL74 -> 0 | DF78: 0
A79: Ratios (Start)
A80: ROE (%) | B80: =(B74-B73)/B146 -> -0.15377192 | C80: =(C74-C73)/C146 -> -0.049717299 | D80: =(D74-D73)/D146 -> 0.13383723 | E80: =(E74-E73)/E146 -> 0.2527389 | F80: =(F74-F73)/F146 -> 0.31857608 | G80: =(G74-G73)/G146 -> 0.28252931 | H80: =(H74-H73)/H146 -> 0.281026 | I80: =(I74-I73)/I146 -> 0.23075198 | ... AE80: =(AE74-AE73)/AE146 -> 0.22987505 | AL80: =(SUM(AI74:AL74)-SUM(AI73:AL73))/AL146 -> 0.27885422 | AM80: =(SUM(AJ74:AM74)-SUM(AJ73:AM73))/AM146 -> 0.24679264 | AN80: =(SUM(AK74:AN74)-SUM(AK73:AN73))/AN146 -> 0.20713399 | AO80: =(SUM(AL74:AO74)-SUM(AL73:AO73))/AO146 -> 0.2426457 | AP80: =(SUM(AM74:AP74)-SUM(AM73:AP73))/AP146 -> 0.22828677 | AQ80: =(SUM(AN74:AQ74)-SUM(AN73:AQ73))/AQ146 -> 0.25880916 | AR80: =(SUM(AO74:AR74)-SUM(AO73:AR73))/AR146 -> 0.26277968 | AS80: =(SUM(AP74:AS74)-SUM(AP73:AS73))/AS146 -> 0.23273732 | ... DB80: =(SUM(CY74:DB74)-SUM(CY73:DB73))/DB146 -> 0.22987505 | DF80: 0.028343484
A81: ROCE (%) | B81: =+B60/B155 -> -0.022897455 | C81: =+C60/C155 -> 0.0487607 | D81: =+D60/D155 -> 0.2041503 | E81: =+E60/E155 -> 0.29232735 | F81: =+F60/F155 -> 0.2642057 | G81: =+G60/G155 -> 0.24298211 | H81: =+H60/H155 -> 0.21445075 | I81: =+I60/I155 -> 0.16390483 | ... AE81: =+AE60/AE155 -> 0.27058675 | AL81: =+SUM(AI60:AL60)/AL155 -> 0.20765491 | AM81: =+SUM(AJ60:AM60)/AM155 -> 0.19963944 | AN81: =+SUM(AK60:AN60)/AN155 -> 0.16996168 | AO81: =+SUM(AL60:AO60)/AO155 -> 0.19325216 | AP81: =+SUM(AM60:AP60)/AP155 -> 0.19639462 | AQ81: =+SUM(AN60:AQ60)/AQ155 -> 0.22194077 | AR81: =+SUM(AO60:AR60)/AR155 -> 0.22081861 | AS81: =+SUM(AP60:AS60)/AS155 -> 0.2122052 | ... DB81: =+SUM(CY60:DB60)/DB155 -> 0.27058675 | DF81: 0.00050118026
A82: Ratios (End)
A83: Checksum Of qtr to Annual
A84: Revenue - Checksum Of qtr to Annual | N84: =N36-SUM(AI36:AL36) -> -25.14 | O84: =O36-SUM(AM36:AP36) -> 0 | P84: =P36-SUM(AQ36:AT36) -> -77.72 | Q84: =Q36-SUM(AU36:AX36) -> 2302.46 | R84: =R36-SUM(AY36:BB36) -> 3955.29 | S84: =S36-SUM(BC36:BF36) -> -611.16 | T84: =T36-SUM(BG36:BJ36) -> 994.81 | U84: =U36-SUM(BK36:BN36) -> 1738.74 | V84: =V36-SUM(BO36:BR36) -> -1732.15 | W84: =W36-SUM(BS36:BV36) -> 78.68 | X84: =X36-SUM(BW36:BZ36) -> 1073.39 | Y84: =Y36-SUM(CA36:CD36) -> -2842 | Z84: =Z36-SUM(CE36:CH36) -> 55074 | AA84: =AA36-SUM(CF36:CI36) -> -46568 | AB84: =AB36-SUM(CM36:CP36) -> 0 | AC84: =AC36-SUM(CQ36:CT36) -> 0 | AD84: =AD36-SUM(CU36:CX36) -> 0 | AE84: =AE36-SUM(CY36:DB36) -> 0 | DF84: 0
A85: GP - Checksum Of qtr to Annual | N85: =N42-SUM(AI42:AL42) -> 42.07 | O85: =O42-SUM(AM42:AP42) -> 48.33 | P85: =P42-SUM(AQ42:AT42) -> -237.82 | Q85: =Q42-SUM(AU42:AX42) -> 4529.34 | R85: =R42-SUM(AY42:BB42) -> 3177.72 | S85: =S42-SUM(BC42:BF42) -> -1989.76 | T85: =T42-SUM(BG42:BJ42) -> -250.56 | U85: =U42-SUM(BK42:BN42) -> 1441.47 | V85: =V42-SUM(BO42:BR42) -> -1732.15 | W85: =W42-SUM(BS42:BV42) -> 78.68 | X85: =X42-SUM(BW42:BZ42) -> 1073.39 | Y85: =Y42-SUM(CA42:CD42) -> -2841 | Z85: =Z42-SUM(CE42:CH42) -> 16627 | AA85: =AA42-SUM(CF42:CI42) -> -26334 | AB85: =AB42-SUM(CM42:CP42) -> 0 | AC85: =AC42-SUM(CQ42:CT42) -> 0 | AD85: =AD42-SUM(CU42:CX42) -> 0 | AE85: =AE42-SUM(CY42:DB42) -> 0 | DF85: 0
A86: EBITDA - Checksum Of qtr to Annual | N86: =N54-SUM(AI54:AL54) -> 36.73 | O86: =O54-SUM(AM54:AP54) -> -1613.46 | P86: =P54-SUM(AQ54:AT54) -> 2.37 | Q86: =Q54-SUM(AU54:AX54) -> -1686.91 | R86: =R54-SUM(AY54:BB54) -> -760.53 | S86: =S54-SUM(BC54:BF54) -> -1989.76 | T86: =T54-SUM(BG54:BJ54) -> -1241.22 | U86: =U54-SUM(BK54:BN54) -> -686.32 | V86: =V54-SUM(BO54:BR54) -> -3114.24 | W86: =W54-SUM(BS54:BV54) -> -1370.57 | X86: =X54-SUM(BW54:BZ54) -> 1073.39 | Y86: =Y54-SUM(CA54:CD54) -> -1187 | Z86: =Z54-SUM(CE54:CH54) -> 4941 | AA86: =AA54-SUM(CF54:CI54) -> -26929 | AB86: =AB54-SUM(CM54:CP54) -> 0 | AC86: =AC54-SUM(CQ54:CT54) -> 0 | AD86: =AD54-SUM(CU54:CX54) -> 0 | AE86: =AE54-SUM(CY54:DB54) -> 0 | DF86: 0
A87: PAT - Checksum Of qtr to Annual | N87: =N74-SUM(AI74:AL74) -> -2.0008883e-11 | O87: =O74-SUM(AM74:AP74) -> 2.7284841e-11 | P87: =P74-SUM(AQ74:AT74) -> 7.4578566e-11 | Q87: =Q74-SUM(AU74:AX74) -> 0 | R87: =R74-SUM(AY74:BB74) -> 1.0004442e-11 | S87: =S74-SUM(BC74:BF74) -> 5.2750693e-11 | T87: =T74-SUM(BG74:BJ74) -> 0 | U87: =U74-SUM(BK74:BN74) -> 0 | V87: =V74-SUM(BO74:BR74) -> 3.092282e-11 | W87: =W67-SUM(BS67:BV67) -> 0 | X87: =X67-SUM(BW67:BZ67) -> -5.1386451e-11 | Y87: =Y67-SUM(CA67:CD67) -> 464 | Z87: =Z67-SUM(CE67:CH67) -> 3291 | AA87: =AA67-SUM(CF67:CI67) -> -16314 | AB87: =AB67-SUM(CM67:CP67) -> 0 | AC87: =AC67-SUM(CQ67:CT67) -> 0 | AD87: =AD67-SUM(CU67:CX67) -> 0 | AE87: =AE67-SUM(CY67:DB67) -> 0 | DF87: 0
A88: Valuation (Start)
A89: Eq | B89: ='Annual Raw'!C104 -> 255.85 | C89: ='Annual Raw'!D104 -> 319.77 | D89: ='Annual Raw'!E104 -> 319.78 | E89: =+F89 -> 0 | F89: =+G89 -> 0 | G89: =+H89 -> 0 | H89: =+I89 -> 0 | I89: =+J89 -> 0 | J89: =+K89 -> 0 | K89: =+L89 -> 0 | L89: =+M89 -> 0 | ... AA89: =+AB89 -> 0 | AB89: =AA89 -> 0 | AC89: =AB89 -> 0 | AD89: =AC89 -> 0 | AE89: =AD89 -> 0 | AI89: =+AJ89 -> 737 | AJ89: =+AK89 -> 737 | AK89: =+AL89 -> 737 | AL89: =+AM89 -> 737 | AM89: =+AN89 -> 737 | AN89: =+AO89 -> 737 | AO89: =+AP89 -> 737 | AP89: =+AQ89 -> 737 | ... CI89: =+CJ89 -> 737 | CJ89: ='QTR Raw'!BD45 -> 737 | CK89: ='QTR Raw'!BE45 -> 737 | CL89: ='QTR Raw'!BF45 -> 737 | CM89: =+CL89 -> 737 | CN89: =+CM89 -> 737 | CO89: =+CN89 -> 737 | CP89: =+CO89 -> 737 | CQ89: =+CP89 -> 737 | CR89: =+CQ89 -> 737 | CS89: =+CR89 -> 737 | CT89: =+CS89 -> 737 | ... DB89: =+DA89 -> 737 | DF89: 737
A90: FV | B90: ='Annual Raw'!C105 -> 10 | C90: ='Annual Raw'!D105 -> 10 | D90: ='Annual Raw'!E105 -> 10 | E90: =+F90 -> 0 | F90: =+G90 -> 0 | G90: =+H90 -> 0 | H90: =+I90 -> 0 | I90: =+J90 -> 0 | J90: =+K90 -> 0 | K90: =+L90 -> 0 | L90: =+M90 -> 0 | ... AA90: =+AB90 -> 0 | AB90: =AA90 -> 0 | AC90: =AB90 -> 0 | AD90: =AC90 -> 0 | AE90: =AD90 -> 0 | AI90: =AJ90 -> 2 | AJ90: =AK90 -> 2 | AK90: =AL90 -> 2 | AL90: =AM90 -> 2 | AM90: =AN90 -> 2 | AN90: =AO90 -> 2 | AO90: =AP90 -> 2 | AP90: =AQ90 -> 2 | ... CI90: =CJ90 -> 2 | CJ90: ='QTR Raw'!BD46 -> 2 | CK90: ='QTR Raw'!BE46 -> 2 | CL90: ='QTR Raw'!BF46 -> 2 | CM90: =+CL90 -> 2 | CN90: =+CM90 -> 2 | CO90: =+CN90 -> 2 | CP90: =+CO90 -> 2 | CQ90: =+CP90 -> 2 | CR90: =+CQ90 -> 2 | CS90: =+CR90 -> 2 | CT90: =+CS90 -> 2 | ... DB90: =+DA90 -> 2 | DF90: 2
A91: No of share | B91: =B89/B90 -> 25.585 | C91: =C89/C90 -> 31.977 | D91: =D89/D90 -> 31.978 | E91: =E89/E90 -> #DIV/0! | F91: =F89/F90 -> #DIV/0! | G91: =G89/G90 -> #DIV/0! | H91: =H89/H90 -> #DIV/0! | I91: =I89/I90 -> #DIV/0! | ... AE91: =AE89/AE90 -> #DIV/0! | AI91: =AI89/AI90 -> 368.5 | AJ91: =AJ89/AJ90 -> 368.5 | AK91: =AK89/AK90 -> 368.5 | AL91: =AL89/AL90 -> 368.5 | AM91: =AM89/AM90 -> 368.5 | AN91: =AN89/AN90 -> 368.5 | AO91: =AO89/AO90 -> 368.5 | AP91: =AP89/AP90 -> 368.5 | ... DB91: =DB89/DB90 -> 368.5 | DF91: 368.5
A92: EPS | B92: =(B74-B73)/B91 -> -19.55599 | C92: =(C74-C73)/C91 -> -3.3520968 | D92: =(D74-D73)/D91 -> 9.2913878 | E92: =(E74-E73)/E91 -> #DIV/0! | F92: =(F74-F73)/F91 -> #DIV/0! | G92: =(G74-G73)/G91 -> #DIV/0! | H92: =(H74-H73)/H91 -> #DIV/0! | I92: =(I74-I73)/I91 -> #DIV/0! | ... AE92: =(AE74-AE73)/AE91 -> #DIV/0! | AI92: =(AI74-AI73)/AI91 -> 7.2874898 | AJ92: =(AJ74-AJ73)/AJ91 -> 5.6576119 | AK92: =(AK74-AK73)/AK91 -> 4.8874627 | AL92: =(AL74-AL73)/AL91 -> 10.64863 | AM92: =(AM74-AM73)/AM91 -> 5.1688195 | AN92: =(AN74-AN73)/AN91 -> 10.354681 | AO92: =(AO74-AO73)/AO91 -> 13.376228 | AP92: =(AP74-AP73)/AP91 -> 11.741791 | ... DB92: =(DB74-DB73)/DB91 -> 46.146257 | DF92: 13.36978
A93: DPS | B93: ='Annual Raw'!C110 -> 0 | C93: ='Annual Raw'!D110 -> 0 | D93: ='Annual Raw'!E110 -> 0.76628352 | E93: ='Annual Raw'!F110 -> 1.532567 | F93: ='Annual Raw'!G110 -> 2.394636 | G93: ='Annual Raw'!H110 -> 2.4904215 | H93: ='Annual Raw'!I110 -> 2.8735632 | I93: ='Annual Raw'!J110 -> 2.8735632 | ... AA93: ='Annual Raw'!AB110 -> 3 | DF93: company had spinoff so ace does not Adjust
A94: DPS % of EPS | B94: =B93/B92 -> 0 | C94: =C93/C92 -> 0 | D94: =D93/D92 -> 0.082472451 | E94: =E93/E92 -> #DIV/0! | F94: =F93/F92 -> #DIV/0! | G94: =G93/G92 -> #DIV/0! | H94: =H93/H92 -> #DIV/0! | I94: =I93/I92 -> #DIV/0! | ... AE94: =AE93/AE92 -> #DIV/0! | DF94: 0
A95: EPS TTM | B95: =+B92 -> -19.55599 | C95: =+C92 -> -3.3520968 | D95: =+D92 -> 9.2913878 | E95: =+E92 -> #DIV/0! | F95: =+F92 -> #DIV/0! | G95: =+G92 -> #DIV/0! | H95: =+H92 -> #DIV/0! | I95: =+I92 -> #DIV/0! | ... AE95: =+AE92 -> #DIV/0! | AL95: =SUM(AI92:AL92) -> 28.481194 | AM95: =SUM(AJ92:AM92) -> 26.362524 | AN95: =SUM(AK92:AN92) -> 31.059593 | AO95: =SUM(AL92:AO92) -> 39.548358 | AP95: =SUM(AM92:AP92) -> 40.64152 | AQ95: =SUM(AN92:AQ92) -> 49.866703 | AR95: =SUM(AO92:AR92) -> 48.370801 | AS95: =SUM(AP92:AS92) -> 45.102307 | ... DB95: =SUM(CY92:DB92) -> 136.11374 | DF95: 8.6289383
A96: EPS Growth YoY % | C96: =+C95/B95-1 -> -0.82858976 | D96: =+D95/C95-1 -> -3.7718137 | E96: =+E95/D95-1 -> #DIV/0! | F96: =+F95/E95-1 -> #DIV/0! | G96: =+G95/F95-1 -> #DIV/0! | H96: =+H95/G95-1 -> #DIV/0! | I96: =+I95/H95-1 -> #DIV/0! | J96: =+J95/I95-1 -> #DIV/0! | ... AE96: =+AE95/AD95-1 -> #DIV/0! | AP96: =+IF(AL95<0,1-AP95/AL95,AP95/AL95-1) -> 0.42695983 | AQ96: =+IF(AM95<0,1-AQ95/AM95,AQ95/AM95-1) -> 0.89157546 | AR96: =+IF(AN95<0,1-AR95/AN95,AR95/AN95-1) -> 0.55735462 | AS96: =+IF(AO95<0,1-AS95/AO95,AS95/AO95-1) -> 0.14043436 | AT96: =+IF(AP95<0,1-AT95/AP95,AT95/AP95-1) -> -0.053777944 | AU96: =+IF(AQ95<0,1-AU95/AQ95,AU95/AQ95-1) -> -0.2673004 | AV96: =+IF(AR95<0,1-AV95/AR95,AV95/AR95-1) -> -0.33917431 | AW96: =+IF(AS95<0,1-AW95/AS95,AW95/AS95-1) -> -0.32482581 | ... DB96: =+IF(CX95<0,1-DB95/CX95,DB95/CX95-1) -> 1.2967341 | DF96: -0.85327102
A97: Bloomberg Estimate | CP97: 38.9 | CT97: 55 | CX97: 65.6 | DF97: 3.39
A98: Estimate deviation | CP98: =CP95/CP97-1 -> 0.047129182 | CT98: =CT95/CT97-1 -> -0.056545017 | CX98: =CX95/CX97-1 -> -0.096584777 | DF98: 1.5454095
A99: Promoter Share holding % | B99: ='Annual Raw'!C112 -> 25.35 | C99: ='Annual Raw'!D112 -> 32.21 | D99: ='Annual Raw'!E112 -> 32.21 | E99: ='Annual Raw'!F112 -> 33.35 | F99: ='Annual Raw'!G112 -> 32.35 | G99: ='Annual Raw'!H112 -> 33.65 | H99: ='Annual Raw'!I112 -> 33.43 | I99: ='Annual Raw'!J112 -> 33.42 | ... AA99: ='Annual Raw'!AB112 -> 42.56 | AI99: ='QTR Raw'!C49 -> 34.71 | AJ99: ='QTR Raw'!D49 -> 34.74 | AK99: ='QTR Raw'!E49 -> 34.72 | AL99: ='QTR Raw'!F49 -> 34.71 | AM99: ='QTR Raw'!G49 -> 34.35 | AN99: ='QTR Raw'!H49 -> 34.33 | AO99: ='QTR Raw'!I49 -> 34.33 | AP99: ='QTR Raw'!J49 -> 34.33 | ... CL99: ='QTR Raw'!BF49 -> 42.56
A100: Pledge Share % | B100: ='Annual Raw'!C113 -> 0 | C100: ='Annual Raw'!D113 -> 0 | D100: ='Annual Raw'!E113 -> 0 | E100: ='Annual Raw'!F113 -> 0 | F100: ='Annual Raw'!G113 -> 0 | G100: ='Annual Raw'!H113 -> 0 | H100: ='Annual Raw'!I113 -> 0 | I100: ='Annual Raw'!J113 -> 0 | ... AA100: ='Annual Raw'!AB113 -> 0 | AI100: ='QTR Raw'!C50 -> 8.35 | AJ100: ='QTR Raw'!D50 -> 6.38 | AK100: ='QTR Raw'!E50 -> 7.55 | AL100: ='QTR Raw'!F50 -> 7.55 | AM100: ='QTR Raw'!G50 -> 5.96 | AN100: ='QTR Raw'!H50 -> 5.96 | AO100: ='QTR Raw'!I50 -> 5.96 | AP100: ='QTR Raw'!J50 -> 6.22 | ... CL100: ='QTR Raw'!BF50 -> 0
A102: Share Price
A103: Share Price - Close | B103: ='Annual Raw'!C106 -> 12.465899 | C103: ='Annual Raw'!D106 -> 24.194 | D103: ='Annual Raw'!E106 -> 29.828088 | E103: ='Annual Raw'!F106 -> 93.077432 | F103: ='Annual Raw'!G106 -> 79.327575 | G103: ='Annual Raw'!H106 -> 178.7194 | H103: ='Annual Raw'!I106 -> 139.46284 | I103: ='Annual Raw'!J106 -> 119.47524 | ... AA103: ='Annual Raw'!AB106 -> 296.25 | AB103: =+CP103 -> 385 | AC103: =+CT103 -> 385 | AD103: =+CX103 -> 385 | AE103: =+DB103 -> 385 | AJ103: ='QTR Share Price'!HP21 -> 264.61868 | AK103: ='QTR Share Price'!HQ21 -> 309.09283 | AL103: ='QTR Share Price'!HR21 -> 266.4491 | AM103: ='QTR Share Price'!HS21 -> 278.47047 | AN103: ='QTR Share Price'!HT21 -> 328.83163 | AO103: ='QTR Share Price'!HU21 -> 372.4153 | AP103: ='QTR Share Price'!HV21 -> 394.13293 | AQ103: ='QTR Share Price'!HW21 -> 426.5857 | ... CL103: ='QTR Share Price'!JR21 -> 296.25 | CM103: 385 | CN103: =+CM103 -> 385 | CO103: =+CN103 -> 385 | CP103: =+CO103 -> 385 | CQ103: =+CP103 -> 385 | CR103: =+CQ103 -> 385 | CS103: =+CR103 -> 385 | CT103: =+CS103 -> 385 | CU103: =+CT103 -> 385 | ... DB103: =+DA103 -> 385 | DF103: 314
A104: Share Price - High | B104: ='Annual Raw'!C107 -> 29.531053 | C104: ='Annual Raw'!D107 -> 29.368162 | D104: ='Annual Raw'!E107 -> 33.229621 | E104: ='Annual Raw'!F107 -> 109.23232 | F104: ='Annual Raw'!G107 -> 100.99198 | G104: ='Annual Raw'!H107 -> 180.94237 | H104: ='Annual Raw'!I107 -> 191.06074 | I104: ='Annual Raw'!J107 -> 160.97394 | ... AA104: ='Annual Raw'!AB107 -> 743.8 | AB104: =+MAX(CM104:CP104) -> 1506.3756 | AC104: =+MAX(CQ104:CT104) -> 1933.9314 | AD104: =+MAX(CU104:CX104) -> 2191.6675 | AE104: =+MAX(CY104:DB104) -> 5033.6774 | AJ104: ='QTR Share Price'!HP19 -> 286.23737 | AK104: ='QTR Share Price'!HQ19 -> 310.62642 | AL104: ='QTR Share Price'!HR19 -> 333.48187 | AM104: ='QTR Share Price'!HS19 -> 316.11766 | AN104: ='QTR Share Price'!HT19 -> 351.14291 | AO104: ='QTR Share Price'!HU19 -> 400.71253 | AP104: ='QTR Share Price'!HV19 -> 415.85056 | AQ104: ='QTR Share Price'!HW19 -> 459.28582 | ... CL104: ='QTR Share Price'!JR19 -> 394 | CM104: =+CM95*CM112 -> 400.55898 | CN104: =+CN95*CN112 -> 892.50776 | CO104: =+CO95*CO112 -> 1433.5292 | CP104: =+CP95*CP112 -> 1506.3756 | CQ104: =+CQ95*CQ112 -> 1408.4414 | CR104: =+CR95*CR112 -> 1731.8042 | CS104: =+CS95*CS112 -> 1933.9314 | CT104: =+CT95*CT112 -> 1918.966 | ... DB104: =+DB95*DB112 -> 5033.6774 | DF104: 983.69896
A105: Share Price - Low | B105: ='Annual Raw'!C108 -> 12.053882 | C105: ='Annual Raw'!D108 -> 11.114867 | D105: ='Annual Raw'!E108 -> 22.469279 | E105: ='Annual Raw'!F108 -> 28.467475 | F105: ='Annual Raw'!G108 -> 63.316417 | G105: ='Annual Raw'!H108 -> 77.085438 | H105: ='Annual Raw'!I108 -> 124.65899 | I105: ='Annual Raw'!J108 -> 102.52507 | ... AA105: ='Annual Raw'!AB108 -> 294.15 | AB105: =+MIN(CM105:CP105) -> 299.04676 | AC105: =+MIN(CQ105:CT105) -> 1051.5052 | AD105: =+MIN(CU105:CX105) -> 1466.7292 | AE105: =+MIN(CY105:DB105) -> 1974.8123 | AJ105: =+'QTR Share Price'!HP20 -> 200.8015 | AK105: =+'QTR Share Price'!HQ20 -> 242.75264 | AL105: =+'QTR Share Price'!HR20 -> 262.34303 | AM105: =+'QTR Share Price'!HS20 -> 249.43118 | AN105: =+'QTR Share Price'!HT20 -> 269.61522 | AO105: =+'QTR Share Price'!HU20 -> 326.75386 | AP105: =+'QTR Share Price'!HV20 -> 327.54539 | AQ105: =+'QTR Share Price'!HW20 -> 395.46864 | ... CL105: =+'QTR Share Price'!JR20 -> 294.15 | CM105: =+CM113*CM95 -> 299.04676 | CN105: =+CN113*CN95 -> 666.32274 | CO105: =+CO113*CO95 -> 1070.235 | CP105: =+CP113*CP95 -> 1124.6203 | CQ105: =+CQ113*CQ95 -> 1051.5052 | CR105: =+CR113*CR95 -> 1292.9193 | CS105: =+CS113*CS95 -> 1443.8221 | CT105: =+CT113*CT95 -> 1432.6494 | ... DB105: =+DB113*DB95 -> 3758.0106 | DF105: 759.34657
A107: Upside (%) | AB107: =+AB104/AB103-1 -> 2.912664 | AC107: =+AC104/AC103-1 -> 4.0231984 | AD107: =+AD104/AD103-1 -> 4.6926428 | AE107: =+AE104/AE103-1 -> 12.074487 | CM107: =+CM104/CM103-1 -> 0.040412944 | CN107: =+CN104/CN103-1 -> 1.318202 | CO107: =+CO104/CO103-1 -> 2.7234523 | CP107: =+CP104/CP103-1 -> 2.912664 | CQ107: =+CQ104/CQ103-1 -> 2.6582894 | CR107: =+CR104/CR103-1 -> 3.4981927 | CS107: =+CS104/CS103-1 -> 4.0231984 | CT107: =+CT104/CT103-1 -> 3.9843274 | ... DB107: =+DB104/DB103-1 -> 12.074487 | DF107: 2.1327992
A108: Downside (%) | AB108: =+AB105/AB103-1 -> -0.22325516 | AC108: =+AC105/AC103-1 -> 1.7311823 | AD108: =+AD105/AD103-1 -> 2.8096862 | AE108: =+AE105/AE103-1 -> 4.1293825 | CM108: =+CM105/CM103-1 -> -0.22325516 | CN108: =+CN105/CN103-1 -> 0.73070841 | CO108: =+CO105/CO103-1 -> 1.7798312 | CP108: =+CP105/CP103-1 -> 1.9210917 | CQ108: =+CQ105/CQ103-1 -> 1.7311823 | CR108: =+CR105/CR103-1 -> 2.3582319 | CS108: =+CS105/CS103-1 -> 2.7501874 | CT108: =+CT105/CT103-1 -> 2.7211673 | ... DB108: =+DB105/DB103-1 -> 8.7610666 | DF108: 1.4183012
A110: PE
A111: PE - Close | B111: =+B103/B95 -> -0.63744657 | C111: =+C103/C95 -> -7.2175719 | D111: =+D103/D95 -> 3.2102941 | E111: =+E103/E95 -> #DIV/0! | F111: =+F103/F95 -> #DIV/0! | G111: =+G103/G95 -> #DIV/0! | H111: =+H103/H95 -> #DIV/0! | I111: =+I103/I95 -> #DIV/0! | ... AE111: =+AE103/AE95 -> #DIV/0! | AL111: =+AL103/AL95 -> 9.3552643 | AM111: =+AM103/AM95 -> 10.563119 | AN111: =+AN103/AN95 -> 10.58712 | AO111: =+AO103/AO95 -> 9.4167069 | AP111: =+AP103/AP95 -> 9.6977901 | AQ111: =+AQ103/AQ95 -> 8.5545198 | AR111: =+AR103/AR95 -> 10.283636 | AS111: =+AS103/AS95 -> 10.882994 | ... DB111: =+DB103/DB95 -> 2.8285169 | DF111: 36.389181
A112: PE - High | B112: =+B104/B95 -> -1.5100771 | C112: =+C104/C95 -> -8.7611319 | D112: =+D104/D95 -> 3.5763894 | E112: =+E104/E95 -> #DIV/0! | F112: =+F104/F95 -> #DIV/0! | G112: =+G104/G95 -> #DIV/0! | H112: =+H104/H95 -> #DIV/0! | I112: =+I104/I95 -> #DIV/0! | ... AE112: =+AE104/AE95 -> #DIV/0! | AL112: =+AL104/AL95 -> 11.708844 | AM112: =+AM104/AM95 -> 11.991176 | AN112: =+AN104/AN95 -> 11.305457 | AO112: =+AO104/AO95 -> 10.132217 | AP112: =+AP104/AP95 -> 10.232161 | AQ112: =+AQ104/AQ95 -> 9.2102704 | AR112: =+AR104/AR95 -> 11.137623 | AS112: =+AS104/AS95 -> 12.082953 | ... CL112: =+CL104/CL95 -> 36.981406 | CM112: =+CL112 -> 36.981406 | CN112: =+CM112 -> 36.981406 | CO112: =+CN112 -> 36.981406 | CP112: =+CO112 -> 36.981406 | CQ112: =+CP112 -> 36.981406 | CR112: =+CQ112 -> 36.981406 | CS112: =+CR112 -> 36.981406 | CT112: =+CS112 -> 36.981406 | ... DB112: =+DA112 -> 36.981406 | DF112: 114
A113: PE - Low | B113: =+B105/B95 -> -0.616378 | C113: =+C105/C95 -> -3.3157954 | D113: =+D105/D95 -> 2.418291 | E113: =+E105/E95 -> #DIV/0! | F113: =+F105/F95 -> #DIV/0! | G113: =+G105/G95 -> #DIV/0! | H113: =+H105/H95 -> #DIV/0! | I113: =+I105/I95 -> #DIV/0! | ... AE113: =+AE105/AE95 -> #DIV/0! | AL113: =+AL105/AL95 -> 9.2110966 | AM113: =+AM105/AM95 -> 9.4615821 | AN113: =+AN105/AN95 -> 8.680578 | AO113: =+AO105/AO95 -> 8.2621346 | AP113: =+AP105/AP95 -> 8.0593785 | AQ113: =+AQ105/AQ95 -> 7.930515 | AR113: =+AR105/AR95 -> 8.805779 | AS113: =+AS105/AS95 -> 10.269852 | ... CL113: =+CL105/CL95 -> 27.609342 | CM113: =+CL113 -> 27.609342 | CN113: =+CM113 -> 27.609342 | CO113: =+CN113 -> 27.609342 | CP113: =+CO113 -> 27.609342 | CQ113: =+CP113 -> 27.609342 | CR113: =+CQ113 -> 27.609342 | CS113: =+CR113 -> 27.609342 | CT113: =+CS113 -> 27.609342 | ... DB113: =+DA113 -> 27.609342 | DF113: 88
A115: PE - 1Yr Fwd | B115: =+B104/C95 -> -8.8097254 | C115: =+C104/D95 -> 3.1607939 | D115: =+D104/E95 -> #DIV/0! | E115: =+E104/F95 -> #DIV/0! | F115: =+F104/G95 -> #DIV/0! | G115: =+G104/H95 -> #DIV/0! | H115: =+H104/I95 -> #DIV/0! | I115: =+I104/J95 -> #DIV/0! | ... AD115: =+AD104/AE95 -> #DIV/0! | AL115: =+AL104/AP95 -> 8.2054479 | AM115: =+AM104/AQ95 -> 6.3392533 | AN115: =+AN104/AR95 -> 7.2593983 | AO115: =+AO104/AS95 -> 8.8845241 | AP115: =+AP104/AT95 -> 10.813699 | AQ115: =+AQ104/AU95 -> 12.570323 | AR115: =+AR104/AV95 -> 16.854101 | AS115: =+AS104/AW95 -> 17.896053 | ... CL115: =+CL104/CP95 -> 9.6726697 | DF115: 18.477032
...

Sheet Monthly Nos Company
B2: Date | C2: PV Total | D2: Domestic | E2: PV Export | I2: 3 months rolling | J2: Total | K2: Domestic | L2: Export | M2: 3M Total YoY% | O2: 12 months rolling | P2: PV | Q2: Domestic | R2: Export | S2: 12M Total YoY%
B3: 41029 | C3: =+D3+E3 -> 23226 | D3: 22658 | E3: 568 | U3: 2781 | V3: 4219 | W3: 6071 | X3: 4864 | Y3: 4373 | Z3: 5441 | AA3: 3626 | AB3: 3671 | AC3: 3882 | AD3: 3880 | AE3: 3996 | AF3: 3552 | AG3: 3565 | AH3: 3874 | AI3: 3996 | AJ3: 4277 | AK3: 4894 | AL3: 5441 | AM3: 4712 | AN3: 3671 | AO3: 2826 | AP3: 3824 | AQ3: 4636 | AR3: 3552 | AS3: 3222 | AT3: 3191 | AU3: 3814 | AV3: 4363 | AW3: 4480 | AX3: 5246 | AY3: 4059 | AZ3: 4293 | BA3: 3958 | BB3: 3961 | BC3: 3895 | BD3: 5435 | BE3: 3786 | BF3: 4678 | BG3: 5047 | BH3: 5078 | BI3: 5212 | BJ3: 4402 | BK3: 4569 | BL3: 3573 | BM3: 4557 | BN3: 5636 | BO3: 5142 | BP3: 6356 | BQ3: 3785 | BR3: 4428 | BS3: 5603 | BT3: 5371 | BU3: 6595 | BV3: 5687 | BW3: 6333 | BX3: 5626 | BY3: 5119 | BZ3: 4921 | CA3: 4895 | CB3: 5836 | CC3: 2128 | CD3: 3900 | CE3: 3504 | CF3: 3441 | CG3: 3082 | CH3: 3887 | CI3: 4311 | CJ3: 4927 | CK3: 6293 | CL3: 5183 | CM3: 4768 | CN3: 6713 | CO3: 3010 | CP3: 3699 | CQ3: 5246 | CR3: 4971 | CS3: 5478 | CT3: 5393 | CU3: 4554 | CV3: 4604 | CW3: 3999 | CX3: 3270 | CY3: 2930 | CZ3: 5952 | DA3: 1402 | DB3: 1563 | DC3: 2701 | DD3: 3374 | DE3: 3203 | DF3: 4000 | DG3: 2202 | DH3: 3067 | DI3: 2649 | DJ3: 2620 | DK3: 2632 | DL3: 1912 | DO3: 856 | DP3: 687 | DQ3: 1085 | DR3: 1685 | DS3: 2463 | DT3: 1791 | DU3: 3003 | DV3: 2217 | DW3: 2892 | DX3: 3787 | DY3: 2328 | DZ3: 2109 | EA3: 2651 | EB3: 2138 | EC3: 3805 | ED3: 3168 | EE3: 2678 | EF3: 4119 | EG3: 3305 | EH3: 3725 | EI3: 3858 | EJ3: 2798 | EK3: 1001 | EL3: 1455 | EM3: 2964 | EN3: 2812 | EO3: 2364 | EP3: 2121 | EQ3: 1798 | ER3: 2011 | ES3: 1359 | ET3: 1388 | EU3: 1699 | EV3: 1697 | EW3: 1085 | EX3: 1525 | EY3: 1290 | EZ3: 1789 | FA3: 1749 | FB3: 2358 | FC3: 2129 | FD3: 1525 | FE3: 1717 | FF3: 1849 | FG3: 1572 | FH3: 1737
B4: =+EOMONTH(B3,1) -> 41060 | C4: =+D4+E4 -> 20970 | D4: 20503 | E4: 467 | U4: 18610 | V4: 17371 | W4: 13595 | X4: 21153 | Y4: 17727 | Z4: 17133 | AA4: 16444 | AB4: 13538 | AC4: 11257 | AD4: 11192 | AE4: 7769 | AF4: 8903 | AG4: 8918 | AH4: 8927 | AI4: 9628 | AJ4: 8546 | AK4: 8761 | AL4: 9766 | AM4: 10944 | AN4: 7910 | AO4: 6537 | AP4: 8463 | AQ4: 9026 | AR4: 9761 | AS4: 5653 | AT4: 6932 | AU4: 5933 | AV4: 6703 | AW4: 8229 | AX4: 9765 | AY4: 9594 | AZ4: 10286 | BA4: 9956 | BB4: 11637 | BC4: 11805 | BD4: 12977 | BE4: 8925 | BF4: 9176 | BG4: 8516 | BH4: 8520 | BI4: 9814 | BJ4: 10226 | BK4: 11049 | BL4: 9172 | BM4: 6900 | BN4: 9350 | BO4: 9284 | BP4: 6876 | BQ4: 9106 | BR4: 7787 | BS4: 11705 | BT4: 12209 | BU4: 11435 | BV4: 12997 | BW4: 14483 | BX4: 11546 | BY4: 9632 | BZ4: 10600 | CA4: 9967 | CB4: 13032 | CC4: 11220 | CD4: 9794 | CE4: 9985 | CF4: 12125 | CG4: 11462 | CH4: 14286 | CI4: 11331 | CJ4: 11556 | CK4: 8138 | CL4: 13415 | CM4: 11653 | CN4: 12513 | CO4: 10657 | CP4: 11516 | CQ4: 12291 | CR4: 11466 | CS4: 12024 | CT4: 12191 | CU4: 11563 | CV4: 11411 | CW4: 8082 | CX4: 11007 | CY4: 10384 | CZ4: 8795 | DA4: 6800 | DB4: 4162 | DC4: 7551 | DD4: 6137 | DE4: 4187 | DF4: 4087 | DG4: 7079 | DH4: 6022 | DI4: 6597 | DJ4: 9747 | DK4: 7743 | DL4: 2398
B5: =+EOMONTH(B4,1) -> 41090 | C5: =+D5+E5 -> 17944 | D5: 17244 | E5: 700 | J5: =+SUM(C3:C5) -> 62140 | K5: =+SUM(D3:D5) -> 60405 | L5: =+SUM(E3:E5) -> 1735
B6: =+EOMONTH(B5,1) -> 41121 | C6: =+D6+E6 -> 26908 | D6: 26240 | E6: 668 | J6: =+SUM(C4:C6) -> 65822 | K6: =+SUM(D4:D6) -> 63987 | L6: =+SUM(E4:E6) -> 1835
B7: =+EOMONTH(B6,1) -> 41152 | C7: =+D7+E7 -> 23081 | D7: 22311 | E7: 770 | J7: =+SUM(C5:C7) -> 67933 | K7: =+SUM(D5:D7) -> 65795 | L7: =+SUM(E5:E7) -> 2138
B8: =+EOMONTH(B7,1) -> 41182 | C8: =+D8+E8 -> 22434 | D8: 21652 | E8: 782 | J8: =+SUM(C6:C8) -> 72423 | K8: =+SUM(D6:D8) -> 70203 | L8: =+SUM(E6:E8) -> 2220
B9: =+EOMONTH(B8,1) -> 41213 | C9: =+D9+E9 -> 21367 | D9: 21119 | E9: 248 | J9: =+SUM(C7:C9) -> 66882 | K9: =+SUM(D7:D9) -> 65082 | L9: =+SUM(E7:E9) -> 1800
B10: =+EOMONTH(B9,1) -> 41243 | C10: =+D10+E10 -> 18402 | D10: 18031 | E10: 371 | J10: =+SUM(C8:C10) -> 62203 | K10: =+SUM(D8:D10) -> 60802 | L10: =+SUM(E8:E10) -> 1401
B11: =+EOMONTH(B10,1) -> 41274 | C11: =+D11+E11 -> 14643 | D11: 14185 | E11: 458 | J11: =+SUM(C9:C11) -> 54412 | K11: =+SUM(D9:D11) -> 53335 | L11: =+SUM(E9:E11) -> 1077
B12: =+EOMONTH(B11,1) -> 41305 | C12: =+D12+E12 -> 15708 | D12: 15209 | E12: 499 | J12: =+SUM(C10:C12) -> 48753 | K12: =+SUM(D10:D12) -> 47425 | L12: =+SUM(E10:E12) -> 1328
B13: =+EOMONTH(B12,1) -> 41333 | C13: =+D13+E13 -> 11177 | D13: 10613 | E13: 564 | J13: =+SUM(C11:C13) -> 41528 | K13: =+SUM(D11:D13) -> 40007 | L13: =+SUM(E11:E13) -> 1521
B14: =+EOMONTH(B13,1) -> 41364 | C14: =+D14+E14 -> 13040 | D14: 12347 | E14: 693 | J14: =+SUM(C12:C14) -> 39925 | K14: =+SUM(D12:D14) -> 38169 | L14: =+SUM(E12:E14) -> 1756 | P14: =+SUM(C3:C14) -> 228900 | Q14: =+SUM(D3:D14) -> 222112 | R14: =+SUM(E3:E14) -> 6788
B15: =+EOMONTH(B14,1) -> 41394 | C15: =+D15+E15 -> 12398 | D15: 11570 | E15: 828 | J15: =+SUM(C13:C15) -> 36615 | K15: =+SUM(D13:D15) -> 34530 | L15: =+SUM(E13:E15) -> 2085 | P15: =+SUM(C4:C15) -> 218072 | Q15: =+SUM(D4:D15) -> 211024 | R15: =+SUM(E4:E15) -> 7048
B16: =+EOMONTH(B15,1) -> 41425 | C16: =+D16+E16 -> 11932 | D16: 11134 | E16: 798 | J16: =+SUM(C14:C16) -> 37370 | K16: =+SUM(D14:D16) -> 35051 | L16: =+SUM(E14:E16) -> 2319 | P16: =+SUM(C5:C16) -> 209034 | Q16: =+SUM(D5:D16) -> 201655 | R16: =+SUM(E5:E16) -> 7379
B17: =+EOMONTH(B16,1) -> 41455 | C17: =+D17+E17 -> 12345 | D17: 11804 | E17: 541 | J17: =+SUM(C15:C17) -> 36675 | K17: =+SUM(D15:D17) -> 34508 | L17: =+SUM(E15:E17) -> 2167 | M17: =+J17/J5-1 -> -0.40980045 | P17: =+SUM(C6:C17) -> 203435 | Q17: =+SUM(D6:D17) -> 196215 | R17: =+SUM(E6:E17) -> 7220 | S17: =+P17/P5-1 -> #DIV/0!
B18: =+EOMONTH(B17,1) -> 41486 | C18: =+D18+E18 -> 11522 | D18: 10824 | E18: 698 | J18: =+SUM(C16:C18) -> 35799 | K18: =+SUM(D16:D18) -> 33762 | L18: =+SUM(E16:E18) -> 2037 | M18: =+J18/J6-1 -> -0.45612409 | P18: =+SUM(C7:C18) -> 188049 | Q18: =+SUM(D7:D18) -> 180799 | R18: =+SUM(E7:E18) -> 7250 | S18: =+P18/P6-1 -> #DIV/0!
B19: =+EOMONTH(B18,1) -> 41517 | C19: =+D19+E19 -> 12579 | D19: 11564 | E19: 1015 | J19: =+SUM(C17:C19) -> 36446 | K19: =+SUM(D17:D19) -> 34192 | L19: =+SUM(E17:E19) -> 2254 | M19: =+J19/J7-1 -> -0.4635008 | P19: =+SUM(C8:C19) -> 177547 | Q19: =+SUM(D8:D19) -> 170052 | R19: =+SUM(E8:E19) -> 7495 | S19: =+P19/P7-1 -> #DIV/0!
B20: =+EOMONTH(B19,1) -> 41547 | C20: =+D20+E20 -> 13621 | D20: 12839 | E20: 782 | J20: =+SUM(C18:C20) -> 37722 | K20: =+SUM(D18:D20) -> 35227 | L20: =+SUM(E18:E20) -> 2495 | M20: =+J20/J8-1 -> -0.47914337 | P20: =+SUM(C9:C20) -> 168734 | Q20: =+SUM(D9:D20) -> 161239 | R20: =+SUM(E9:E20) -> 7495 | S20: =+P20/P8-1 -> #DIV/0!
B21: =+EOMONTH(B20,1) -> 41578 | C21: =+D21+E21 -> 14657 | D21: 14133 | E21: 524 | J21: =+SUM(C19:C21) -> 40857 | K21: =+SUM(D19:D21) -> 38536 | L21: =+SUM(E19:E21) -> 2321 | M21: =+J21/J9-1 -> -0.38911815 | P21: =+SUM(C10:C21) -> 162024 | Q21: =+SUM(D10:D21) -> 154253 | R21: =+SUM(E10:E21) -> 7771 | S21: =+P21/P9-1 -> #DIV/0!
B22: =+EOMONTH(B21,1) -> 41608 | C22: =+D22+E22 -> 10747 | D22: 10376 | E22: 371 | J22: =+SUM(C20:C22) -> 39025 | K22: =+SUM(D20:D22) -> 37348 | L22: =+SUM(E20:E22) -> 1677 | M22: =+J22/J10-1 -> -0.37261868 | P22: =+SUM(C11:C22) -> 154369 | Q22: =+SUM(D11:D22) -> 146598 | R22: =+SUM(E11:E22) -> 7771 | S22: =+P22/P10-1 -> #DIV/0!
B23: =+EOMONTH(B22,1) -> 41639 | C23: =+D23+E23 -> 9477 | D23: 9272 | E23: 205 | J23: =+SUM(C21:C23) -> 34881 | K23: =+SUM(D21:D23) -> 33781 | L23: =+SUM(E21:E23) -> 1100 | M23: =+J23/J11-1 -> -0.35894656 | P23: =+SUM(C12:C23) -> 149203 | Q23: =+SUM(D12:D23) -> 141685 | R23: =+SUM(E12:E23) -> 7518 | S23: =+P23/P11-1 -> #DIV/0!
B24: =+EOMONTH(B23,1) -> 41670 | C24: =+D24+E24 -> 11411 | D24: 10974 | E24: 437 | J24: =+SUM(C22:C24) -> 31635 | K24: =+SUM(D22:D24) -> 30622 | L24: =+SUM(E22:E24) -> 1013 | M24: =+J24/J12-1 -> -0.35111685 | P24: =+SUM(C13:C24) -> 144906 | Q24: =+SUM(D13:D24) -> 137450 | R24: =+SUM(E13:E24) -> 7456 | S24: =+P24/P12-1 -> #DIV/0!
B25: =+EOMONTH(B24,1) -> 41698 | C25: =+D25+E25 -> 11764 | D25: 11325 | E25: 439 | J25: =+SUM(C23:C25) -> 32652 | K25: =+SUM(D23:D25) -> 31571 | L25: =+SUM(E23:E25) -> 1081 | M25: =+J25/J13-1 -> -0.21373531 | P25: =+SUM(C14:C25) -> 145493 | Q25: =+SUM(D14:D25) -> 138162 | R25: =+SUM(E14:E25) -> 7331 | S25: =+P25/P13-1 -> #DIV/0!
B26: =+EOMONTH(B25,1) -> 41729 | C26: =+D26+E26 -> 13333 | D26: 12640 | E26: 693 | J26: =+SUM(C24:C26) -> 36508 | K26: =+SUM(D24:D26) -> 34939 | L26: =+SUM(E24:E26) -> 1569 | M26: =+J26/J14-1 -> -0.085585473 | P26: =+SUM(C15:C26) -> 145786 | Q26: =+SUM(D15:D26) -> 138455 | R26: =+SUM(E15:E26) -> 7331 | S26: =+P26/P14-1 -> -0.36310179
B27: =+EOMONTH(B26,1) -> 41759 | C27: =+D27+E27 -> 7835 | D27: 7441 | E27: 394 | J27: =+SUM(C25:C27) -> 32932 | K27: =+SUM(D25:D27) -> 31406 | L27: =+SUM(E25:E27) -> 1526 | M27: =+J27/J15-1 -> -0.10058719 | P27: =+SUM(C16:C27) -> 141223 | Q27: =+SUM(D16:D27) -> 134326 | R27: =+SUM(E16:E27) -> 6897 | S27: =+P27/P15-1 -> -0.35240196
B28: =+EOMONTH(B27,1) -> 41790 | C28: =+D28+E28 -> 9416 | D28: 9230 | E28: 186 | J28: =+SUM(C26:C28) -> 30584 | K28: =+SUM(D26:D28) -> 29311 | L28: =+SUM(E26:E28) -> 1273 | M28: =+J28/J16-1 -> -0.18158951 | P28: =+SUM(C17:C28) -> 138707 | Q28: =+SUM(D17:D28) -> 132422 | R28: =+SUM(E17:E28) -> 6285 | S28: =+P28/P16-1 -> -0.33643809
... B98: =+EOMONTH(B97,1) -> 43921 | C98: =+D98+E98 -> 5801 | D98: 5676 | E98: 125 | J98: =+SUM(C96:C98) -> 32351 | K98: =+SUM(D96:D98) -> 32000 | L98: =+SUM(E96:E98) -> 351 | M98: =+J98/J86-1 -> -0.4055529 | P98: =+SUM(C87:C98) -> 133424 | Q98: =+SUM(D87:D98) -> 131891 | R98: =+SUM(E87:E98) -> 1533 | S98: =+P98/P86-1 -> -0.371128
B99: =+EOMONTH(B98,1) -> 43951 | C99: =+D99+E99 -> 0 | J99: =+SUM(C97:C99) -> 18349 | K99: =+SUM(D97:D99) -> 18106 | L99: =+SUM(E97:E99) -> 243 | M99: =+J99/J87-1 -> -0.63232141 | P99: =+SUM(C88:C99) -> 119931 | Q99: =+SUM(D88:D99) -> 118503 | R99: =+SUM(E88:E99) -> 1428 | S99: =+P99/P87-1 -> -0.42429988
B100: =+EOMONTH(B99,1) -> 43982 | C100: =+D100+E100 -> 0 | J100: =+SUM(C98:C100) -> 5801 | K100: =+SUM(D98:D100) -> 5676 | L100: =+SUM(E98:E100) -> 125 | M100: =+J100/J88-1 -> -0.86390616 | P100: =+SUM(C89:C100) -> 108942 | Q100: =+SUM(D89:D100) -> 107603 | R100: =+SUM(E89:E100) -> 1339 | S100: =+P100/P88-1 -> -0.45999613
B101: =+EOMONTH(B100,1) -> 44012 | C101: =+D101+E101 -> 11439 | D101: 11419 | E101: 20 | J101: =+SUM(C99:C101) -> 11439 | K101: =+SUM(D99:D101) -> 11419 | L101: =+SUM(E99:E101) -> 20 | M101: =+J101/J89-1 -> -0.69845789 | P101: =+SUM(C90:C101) -> 106928 | Q101: =+SUM(D90:D101) -> 105671 | R101: =+SUM(E90:E101) -> 1257 | S101: =+P101/P89-1 -> -0.45661144
B102: =+EOMONTH(B101,1) -> 44043 | C102: =+D102+E102 -> 15023 | D102: 15012 | E102: 11 | J102: =+SUM(C100:C102) -> 26462 | K102: =+SUM(D100:D102) -> 26431 | L102: =+SUM(E100:E102) -> 31 | M102: =+J102/J90-1 -> -0.24590351 | P102: =+SUM(C91:C102) -> 111302 | Q102: =+SUM(D91:D102) -> 110198 | R102: =+SUM(E91:E102) -> 1104 | S102: =+P102/P90-1 -> -0.41493902
B103: =+EOMONTH(B102,1) -> 44074 | C103: =+D103+E103 -> 18616 | D103: 18583 | E103: 33 | J103: =+SUM(C101:C103) -> 45078 | K103: =+SUM(D101:D103) -> 45014 | L103: =+SUM(E101:E103) -> 64 | M103: =+J103/J91-1 -> 0.42719645 | P103: =+SUM(C92:C103) -> 122435 | Q103: =+SUM(D92:D103) -> 121465 | R103: =+SUM(E92:E103) -> 970 | S103: =+P103/P91-1 -> -0.31620805
B104: =+EOMONTH(B103,1) -> 44104 | C104: =+D104+E104 -> 21219 | D104: 21199 | E104: 20 | J104: =+SUM(C102:C104) -> 54858 | K104: =+SUM(D102:D104) -> 54794 | L104: =+SUM(E102:E104) -> 64 | M104: =+J104/J92-1 -> 1.0756744 | P104: =+SUM(C93:C104) -> 135357 | Q104: =+SUM(D93:D104) -> 134567 | R104: =+SUM(E93:E104) -> 790 | S104: =+P104/P92-1 -> -0.19801751
B105: =+EOMONTH(B104,1) -> 44135 | C105: =+D105+E105 -> 23660 | D105: 23617 | E105: 43 | J105: =+SUM(C103:C105) -> 63495 | K105: =+SUM(D103:D105) -> 63399 | L105: =+SUM(E103:E105) -> 96 | M105: =+J105/J93-1 -> 1.179562 | P105: =+SUM(C94:C105) -> 145665 | Q105: =+SUM(D94:D105) -> 145015 | R105: =+SUM(E94:E105) -> 650 | S105: =+P105/P93-1 -> -0.11005688
B106: =+EOMONTH(B105,1) -> 44165 | C106: =+D106+E106 -> 21671 | D106: 21644 | E106: 27 | J106: =+SUM(C104:C106) -> 66550 | K106: =+SUM(D104:D106) -> 66460 | L106: =+SUM(E104:E106) -> 90 | M106: =+J106/J94-1 -> 1.0677334 | P106: =+SUM(C95:C106) -> 156800 | Q106: =+SUM(D95:D106) -> 156259 | R106: =+SUM(E95:E106) -> 541 | S106: =+P106/P94-1 -> -0.0018969051
B107: =+EOMONTH(B106,1) -> 44196 | C107: =+D107+E107 -> 23564 | D107: 23545 | E107: 19 | J107: =+SUM(C105:C107) -> 68895 | K107: =+SUM(D105:D107) -> 68806 | L107: =+SUM(E105:E107) -> 89 | M107: =+J107/J95-1 -> 0.87678771 | P107: =+SUM(C96:C107) -> 167543 | Q107: =+SUM(D96:D107) -> 167019 | R107: =+SUM(E96:E107) -> 524 | S107: =+P107/P95-1 -> 0.077481591
B108: =+EOMONTH(B107,1) -> 44227 | C108: =+D108+E108 -> 27050 | D108: 26978 | E108: 72 | J108: =+SUM(C106:C108) -> 72285 | K108: =+SUM(D106:D108) -> 72167 | L108: =+SUM(E106:E108) -> 118 | M108: =+J108/J96-1 -> 0.93487513 | P108: =+SUM(C97:C108) -> 180591 | Q108: =+SUM(D97:D108) -> 180103 | R108: =+SUM(E97:E108) -> 488 | S108: =+P108/P96-1 -> 0.1921221
B109: =+EOMONTH(B108,1) -> 44255 | C109: =+D109+E109 -> 27399 | D109: 27225 | E109: 174 | J109: =+SUM(C107:C109) -> 78013 | K109: =+SUM(D107:D109) -> 77748 | L109: =+SUM(E107:E109) -> 265 | M109: =+J109/J97-1 -> 0.98148383 | P109: =+SUM(C98:C109) -> 195442 | Q109: =+SUM(D98:D109) -> 194898 | R109: =+SUM(E98:E109) -> 544 | S109: =+P109/P97-1 -> 0.34079278
B110: =+EOMONTH(B109,1) -> 44286 | C110: =+D110+E110 -> 29787 | D110: 29654 | E110: 133 | J110: =+SUM(C108:C110) -> 84236 | K110: =+SUM(D108:D110) -> 83857 | L110: =+SUM(E108:E110) -> 379 | M110: =+J110/J98-1 -> 1.6038144 | P110: =+SUM(C99:C110) -> 219428 | Q110: =+SUM(D99:D110) -> 218876 | R110: =+SUM(E99:E110) -> 552 | S110: =+P110/P98-1 -> 0.64459168
B111: =+EOMONTH(B110,1) -> 44316 | C111: =+D111+E111 -> 25214 | D111: 25095 | E111: 119 | J111: =+SUM(C109:C111) -> 82400 | K111: =+SUM(D109:D111) -> 81974 | L111: =+SUM(E109:E111) -> 426 | M111: =+J111/J99-1 -> 3.4907079 | P111: =+SUM(C100:C111) -> 244642 | Q111: =+SUM(D100:D111) -> 243971 | R111: =+SUM(E100:E111) -> 671 | S111: =+P111/P99-1 -> 1.0398563
B112: =+EOMONTH(B111,1) -> 44347 | C112: =+D112+E112 -> 15260 | D112: 15181 | E112: 79 | J112: =+SUM(C110:C112) -> 70261 | K112: =+SUM(D110:D112) -> 69930 | L112: =+SUM(E110:E112) -> 331 | M112: =+J112/J100-1 -> 11.111877 | P112: =+SUM(C101:C112) -> 259902 | Q112: =+SUM(D101:D112) -> 259152 | R112: =+SUM(E101:E112) -> 750 | S112: =+P112/P100-1 -> 1.3856915
... B117: =+EOMONTH(B116,1) -> 44500 | C117: =+D117+E117 -> 34155 | D117: 33925 | E117: 230 | J117: =+SUM(C115:C117) -> 88267 | K117: =+SUM(D115:D117) -> 87673 | L117: =+SUM(E115:E117) -> 594 | M117: =+J117/J105-1 -> 0.39014096 | P117: =+SUM(C106:C117) -> 312738 | Q117: =+SUM(D106:D117) -> 311290 | R117: =+SUM(E106:E117) -> 1448 | S117: =+P117/P105-1 -> 1.1469674
B118: =+EOMONTH(B117,1) -> 44530 | C118: =+D118+E118 -> 29947 | D118: 29778 | E118: 169 | F118: =+C118/C106-1 -> 0.38189285 | J118: =+SUM(C116:C118) -> 90000 | K118: =+SUM(D116:D118) -> 89433 | L118: =+SUM(E116:E118) -> 567 | M118: =+J118/J106-1 -> 0.35236664 | P118: =+SUM(C107:C118) -> 321014 | Q118: =+SUM(D107:D118) -> 319424 | R118: =+SUM(E107:E118) -> 1590 | S118: =+P118/P106-1 -> 1.0472832
B119: =+EOMONTH(B118,1) -> 44561 | C119: =+D119+E119 -> 35461 | D119: 35299 | E119: 162 | F119: =+C119/C107-1 -> 0.50488033 | J119: =+SUM(C117:C119) -> 99563 | K119: =+SUM(D117:D119) -> 99002 | L119: =+SUM(E117:E119) -> 561 | M119: =+J119/J107-1 -> 0.44514116 | P119: =+SUM(C108:C119) -> 332911 | Q119: =+SUM(D108:D119) -> 331178 | R119: =+SUM(E108:E119) -> 1733 | S119: =+P119/P107-1 -> 0.98701826
B120: =+EOMONTH(B119,1) -> 44592 | C120: =+D120+E120 -> 40942 | D120: 40777 | E120: 165 | F120: =+C120/C108-1 -> 0.51356747 | J120: =+SUM(C118:C120) -> 106350 | K120: =+SUM(D118:D120) -> 105854 | L120: =+SUM(E118:E120) -> 496 | M120: =+J120/J108-1 -> 0.4712596 | P120: =+SUM(C109:C120) -> 346803 | Q120: =+SUM(D109:D120) -> 344977 | R120: =+SUM(E109:E120) -> 1826 | S120: =+P120/P108-1 -> 0.92037809
B121: =+EOMONTH(B120,1) -> 44620 | C121: =+D121+E121 -> 40181 | D121: 39981 | E121: 200 | F121: =+C121/C109-1 -> 0.46651338 | J121: =+SUM(C119:C121) -> 116584 | K121: =+SUM(D119:D121) -> 116057 | L121: =+SUM(E119:E121) -> 527 | M121: =+J121/J109-1 -> 0.4944176 | P121: =+SUM(C110:C121) -> 359585 | Q121: =+SUM(D110:D121) -> 357733 | R121: =+SUM(E110:E121) -> 1852 | S121: =+P121/P109-1 -> 0.8398553
B122: =+EOMONTH(B121,1) -> 44651 | C122: =+D122+E122 -> 42466 | D122: 42293 | E122: 173 | F122: =+C122/C110-1 -> 0.42565549 | J122: =+SUM(C120:C122) -> 123589 | K122: =+SUM(D120:D122) -> 123051 | L122: =+SUM(E120:E122) -> 538 | M122: =+J122/J110-1 -> 0.46717555 | P122: =+SUM(C111:C122) -> 372264 | Q122: =+SUM(D111:D122) -> 370372 | R122: =+SUM(E111:E122) -> 1892 | S122: =+P122/P110-1 -> 0.69652004
B123: =+EOMONTH(B122,1) -> 44681 | C123: =+D123+E123 -> 41630 | D123: 41587 | E123: 43 | F123: =+C123/C111-1 -> 0.65106687 | J123: =+SUM(C121:C123) -> 124277 | K123: =+SUM(D121:D123) -> 123861 | L123: =+SUM(E121:E123) -> 416 | M123: =+J123/J111-1 -> 0.50821602 | P123: =+SUM(C112:C123) -> 388680 | Q123: =+SUM(D112:D123) -> 386864 | R123: =+SUM(E112:E123) -> 1816 | S123: =+P123/P111-1 -> 0.58877053
B124: =+EOMONTH(B123,1) -> 44712 | C124: =+D124+E124 -> 43392 | D124: 43341 | E124: 51 | F124: =+C124/C112-1 -> 1.8435125 | J124: =+SUM(C122:C124) -> 127488 | K124: =+SUM(D122:D124) -> 127221 | L124: =+SUM(E122:E124) -> 267 | M124: =+J124/J112-1 -> 0.81449168 | P124: =+SUM(C113:C124) -> 416812 | Q124: =+SUM(D113:D124) -> 415024 | R124: =+SUM(E113:E124) -> 1788 | S124: =+P124/P112-1 -> 0.60372756
B125: =+EOMONTH(B124,1) -> 44742 | C125: =+D125+E125 -> 45305 | D125: 45197 | E125: 108 | F125: =+C125/C113-1 -> 0.8678623 | J125: =+SUM(C123:C125) -> 130327 | K125: =+SUM(D123:D125) -> 130125 | L125: =+SUM(E123:E125) -> 202 | M125: =+J125/J113-1 -> 1.0134252 | P125: =+SUM(C114:C125) -> 437862 | Q125: =+SUM(D114:D125) -> 436111 | R125: =+SUM(E114:E125) -> 1751 | S125: =+P125/P113-1 -> 0.60554859
B126: =+EOMONTH(B125,1) -> 44773 | C126: =+D126+E126 -> 47636 | D126: 47505 | E126: 131 | F126: =+C126/C114-1 -> 0.57365135 | J126: =+SUM(C124:C126) -> 136333 | K126: =+SUM(D124:D126) -> 136043 | L126: =+SUM(E124:E126) -> 290 | M126: =+J126/J114-1 -> 0.95358668 | P126: =+SUM(C115:C126) -> 455227 | Q126: =+SUM(D115:D126) -> 453431 | R126: =+SUM(E115:E126) -> 1796 | S126: =+P126/P114-1 -> 0.58083593
B127: =+EOMONTH(B126,1) -> 44804 | C127: =+D127+E127 -> 47351 | D127: 47166 | E127: 185 | F127: =+C127/C115-1 -> 0.67828029 | J127: =+SUM(C125:C127) -> 140292 | K127: =+SUM(D125:D127) -> 139868 | L127: =+SUM(E125:E127) -> 424 | M127: =+J127/J115-1 -> 0.6955765 | P127: =+SUM(C116:C127) -> 474364 | Q127: =+SUM(D116:D127) -> 472579 | R127: =+SUM(E116:E127) -> 1785 | S127: =+P127/P115-1 -> 0.5941579
B128: =+EOMONTH(B127,1) -> 44834 | C128: =+D128+E128 -> 47864 | D128: 47654 | E128: 210 | F128: =+C128/C116-1 -> 0.8481736 | J128: =+SUM(C126:C128) -> 142851 | K128: =+SUM(D126:D128) -> 142325 | L128: =+SUM(E126:E128) -> 526 | M128: =+J128/J116-1 -> 0.69288838 | P128: =+SUM(C117:C128) -> 496330 | Q128: =+SUM(D117:D128) -> 494503 | R128: =+SUM(E117:E128) -> 1827 | S128: =+P128/P116-1 -> 0.64215548
B129: =+EOMONTH(B128,1) -> 44865 | C129: =+D129+E129 -> 45423 | D129: 45217 | E129: 206 | F129: =+C129/C117-1 -> 0.32990777 | J129: =+SUM(C127:C129) -> 140638 | K129: =+SUM(D127:D129) -> 140037 | L129: =+SUM(E127:E129) -> 601 | M129: =+J129/J117-1 -> 0.5933248 | P129: =+SUM(C118:C129) -> 507598 | Q129: =+SUM(D118:D129) -> 505795 | R129: =+SUM(E118:E129) -> 1803 | S129: =+P129/P117-1 -> 0.62307746
... B170: =+EOMONTH(B169,1) -> 46112 | C170: =+D170+E170 -> 66971 | D170: 66192 | E170: 779 | F170: =+C170/C158-1 -> 0.29108189 | J170: =+SUM(C168:C170) -> 201368 | K170: =+SUM(D168:D170) -> 198743 | L170: =+SUM(E168:E170) -> 2625 | M170: =+J170/J158-1 -> 0.36985966 | P170: =+SUM(C159:C170) -> 642771 | Q170: =+SUM(D159:D170) -> 631548 | R170: =+SUM(E159:E170) -> 11223 | S170: =+P170/P158-1 -> 0.15551637
B171: =+EOMONTH(B170,1) -> 46142 | C171: 59701 | D171: 59000 | E171: 701 | F171: =+C171/C159-1 -> 0.31118774 | J171: =+SUM(C169:C171) -> 190003 | K171: =+SUM(D169:D171) -> 187521 | L171: =+SUM(E169:E171) -> 2482 | M171: =+J171/J159-1 -> 0.31749818 | P171: =+SUM(C160:C171) -> 656940 | Q171: =+SUM(D160:D171) -> 645349 | R171: =+SUM(E160:E171) -> 11591 | S171: =+P171/P159-1 -> 0.18621482
B172: =+EOMONTH(B171,1) -> 46173 | C172: 59790 | D172: 59090 | E172: 700 | F172: =+C172/C160-1 -> 0.42221694 | J172: =+SUM(C170:C172) -> 186462 | K172: =+SUM(D170:D172) -> 184282 | L172: =+SUM(E170:E172) -> 2180 | M172: =+J172/J160-1 -> 0.33718195 | P172: =+SUM(C161:C172) -> 674690 | Q172: =+SUM(D161:D172) -> 662882 | R172: =+SUM(E161:E172) -> 11808 | S172: =+P172/P160-1 -> 0.22944292
B173: =+EOMONTH(B172,1) -> 46203 | C173: =+C161*(F173+1) -> 52959.092 | F173: =F172 -> 0.42221694 | J173: =+SUM(C171:C173) -> 172450.09 | M173: =+J173/J161-1 -> 0.38171199 | P173: =+SUM(C162:C173) -> 690412.09 | Q173: =+SUM(D162:D173) -> 625799 | R173: =+SUM(E162:E173) -> 11654 | S173: =+P173/P161-1 -> 0.27290712
B174: =+EOMONTH(B173,1) -> 46234 | C174: =+C162*(F174+1) -> 57137.565 | F174: =F173 -> 0.42221694 | J174: =+SUM(C172:C174) -> 169886.66 | M174: =+J174/J162-1 -> 0.42221694 | P174: =+SUM(C163:C174) -> 707374.66 | Q174: =+SUM(D163:D174) -> 586278 | R174: =+SUM(E163:E174) -> 11000 | S174: =+P174/P162-1 -> 0.31577415
B175: =+EOMONTH(B174,1) -> 46265 | C175: =+C163*(F175+1) -> 61603.327 | F175: =F174 -> 0.42221694 | J175: =+SUM(C173:C175) -> 171699.98 | M175: =+J175/J163-1 -> 0.42221694 | P175: =+SUM(C164:C175) -> 725662.98 | Q175: =+SUM(D164:D175) -> 545277 | R175: =+SUM(E164:E175) -> 8686 | S175: =+P175/P163-1 -> 0.35273839
B176: =+EOMONTH(B175,1) -> 46295 | C176: =+C164*(F176+1) -> 86622.967 | F176: =F175 -> 0.42221694 | J176: =+SUM(C174:C176) -> 205363.86 | M176: =+J176/J164-1 -> 0.42221694 | P176: =+SUM(C165:C176) -> 751378.95 | Q176: =+SUM(D165:D176) -> 485610 | R176: =+SUM(E165:E176) -> 7446 | S176: =+P176/P164-1 -> 0.35131836
B177: =+EOMONTH(B176,1) -> 46326 | C177: =+C165*(F177+1) -> 87403.764 | F177: =F176 -> 0.42221694 | J177: =+SUM(C175:C177) -> 235630.06 | M177: =+J177/J165-1 -> 0.42221694 | P177: =+SUM(C166:C177) -> 777326.72 | Q177: =+SUM(D166:D177) -> 424315 | R177: =+SUM(E166:E177) -> 7285 | S177: =+P177/P165-1 -> 0.36596695
B178: =+EOMONTH(B177,1) -> 46356 | C178: =+C166*(F178+1) -> 85648.748 | F178: =F177 -> 0.42221694 | J178: =+SUM(C176:C178) -> 259675.48 | M178: =+J178/J166-1 -> 0.42221694 | P178: =+SUM(C167:C178) -> 802753.46 | Q178: =+SUM(D167:D178) -> 366879 | R178: =+SUM(E167:E178) -> 4499 | S178: =+P178/P166-1 -> 0.37889398
B179: =+EOMONTH(B178,1) -> 46387 | C179: =+C167*(F179+1) -> 71848.977 | F179: =F178 -> 0.42221694 | J179: =+SUM(C177:C179) -> 244901.49 | M179: =+J179/J167-1 -> 0.42221694 | P179: =+SUM(C168:C179) -> 824083.44 | Q179: =+SUM(D168:D179) -> 316833 | R179: =+SUM(E168:E179) -> 4026 | S179: =+P179/P167-1 -> 0.40054493
B180: =+EOMONTH(B179,1) -> 46418 | C180: =+C168*(F180+1) -> 101071.27 | F180: =F179 -> 0.42221694 | J180: =+SUM(C178:C180) -> 258568.99 | M180: =+J180/J168-1 -> 0.42221694 | P180: =+SUM(C169:C180) -> 854088.71 | Q180: =+SUM(D169:D180) -> 246611 | R180: =+SUM(E169:E180) -> 3182 | S180: =+P180/P168-1 -> 0.3975062
B181: =+EOMONTH(B180,1) -> 46446 | C181: =+C169*(F181+1) -> 90070.421 | F181: =F180 -> 0.42221694 | J181: =+SUM(C179:C181) -> 262990.67 | M181: =+J181/J169-1 -> 0.42221694 | P181: =+SUM(C170:C181) -> 880828.13 | Q181: =+SUM(D170:D181) -> 184282 | R181: =+SUM(E170:E181) -> 2180 | S181: =+P181/P169-1 -> 0.40332551
B182: =+EOMONTH(B181,1) -> 46477 | C182: =+C170*(F182+1) -> 95247.29 | F182: =F181 -> 0.42221694 | J182: =+SUM(C180:C182) -> 286388.98 | M182: =+J182/J170-1 -> 0.42221694 | P182: =+SUM(C171:C182) -> 909104.42 | Q182: =+SUM(D171:D182) -> 118090 | R182: =+SUM(E171:E182) -> 1401 | S182: =+P182/P170-1 -> 0.41435196
B183: =+EOMONTH(B182,1) -> 46507 | C183: =+C171*(F183+1) -> 84907.773 | F183: =F182 -> 0.42221694 | J183: =+SUM(C181:C183) -> 270225.48 | M183: =+J183/J171-1 -> 0.42221694 | P183: =+SUM(C172:C183) -> 934311.19 | Q183: =+SUM(D172:D183) -> 59090 | R183: =+SUM(E172:E183) -> 700 | S183: =+P183/P171-1 -> 0.42221694
B184: =+EOMONTH(B183,1) -> 46538 | C184: =+C172*(F184+1) -> 85034.351 | F184: =F183 -> 0.42221694 | J184: =+SUM(C182:C184) -> 265189.41 | M184: =+J184/J172-1 -> 0.42221694 | P184: =+SUM(C173:C184) -> 959555.54 | Q184: =+SUM(D173:D184) -> 0 | R184: =+SUM(E173:E184) -> 0 | S184: =+P184/P172-1 -> 0.42221694
... B218: =+EOMONTH(B217,1) -> 47573 | C218: =+C206*(F218+1) -> 273999.75 | F218: =F217 -> 0.42221694 | J218: =+SUM(C216:C218) -> 823860.8 | M218: =+J218/J206-1 -> 0.42221694 | P218: =+SUM(C207:C218) -> 2615238.5 | Q218: =+SUM(D207:D218) -> 0 | R218: =+SUM(E207:E218) -> 0 | S218: =+P218/P206-1 -> 0.42221694
B221: 45382 | C221: 52396.433 | F221: 0.18963839 | J221: 157750.43 | K221: 157750.43 | P221: 575594.43 | Q221: 575594.43
B222: 45412 | C222: 53481.082 | F222: 0.13772591 | J222: 154858.08 | K222: 154858.08 | L222: 4419.5745 | P222: 577459.08 | Q222: 577459.08
B223: 45443 | C223: 47713.12 | F223: 0.04 | J223: 145706.12 | K223: 145706.12 | L223: 4436.0046 | P223: 573696.12 | Q223: 573696.12
B224: 45473 | C224: 48078.225 | F224: 0.017851694 | J224: 142658.22 | K224: 142658.22 | L224: 4062.5213 | P224: 573523.22 | Q224: 573523.22
B225: 45504 | C225: 48580.56 | F225: 0.02 | J225: 138801.56 | K225: 138801.56 | L225: 5017.9 | P225: 569921.56 | Q225: 569921.56
B226: 45565 | C226: 43459.207 | F226: -0.030123261 | J226: 132326.21 | K226: 132326.21 | L226: 5796.4117 | P226: 563345.21 | Q226: 563345.21
B227: 45596 | C227: 44296.062 | F227: -0.083599277 | J227: 129501.06 | K227: 129501.06 | L227: 4828.6612 | P227: 556908.06 | Q227: 556908.06
B228: 45657 | C228: 44408.887 | F228: 0.021598507 | J228: 139602.89 | K228: 139602.89 | L228: 5046.7338 | P228: 562676.89 | Q228: 562676.89
B229: 45688 | C229: 54601.207 | F229: 0.017483322 | J229: 145894.21 | K229: 145894.21 | L229: 4757.3145 | P229: 563436.21 | Q229: 563436.21
B230: 45716 | C230: 45929.454 | F230: -0.1041127 | J230: 138235.45 | K230: 138235.45 | L230: 5533.656 | P230: 551573.45 | Q230: 551573.45
B231: 45747 | C231: 45387.049 | F231: -0.094251663 | J231: 139898.05 | K231: 139898.05 | L231: 6590.6794 | P231: 547356.05 | Q231: 547356.05
B232: 45777 | C232: 49322.07 | F232: 0.030053881 | J232: 147373.07 | K232: 147373.07 | L232: 5750.44 | P232: 555024.07 | Q232: 555024.07
B233: 45808 | C233: 44079.479 | F233: -0.056053297 | J233: 140894.48 | K233: 140894.48 | L233: 6825.4171 | P233: 548283.48 | Q233: 548283.48
... B239: 45991 | C239: 59934.898 | F239: 0.27350356 | J239: 180896.9 | K239: 180896.9 | L239: 8954.6142 | P239: 575614.9 | Q239: 575614.9
B240: 46022 | C240: 56607.427 | F240: 0.2781374 | J240: 178285.43 | K240: 178285.43 | L240: 2947 | M240: 0.27502469 | P240: 594490.43 | Q240: 594490.43 | R240: 8997 | S240: 0.27502469
B244: 46173 | C244: 55122.332 | F244: 0.31118774 | J244: 181794.33 | M244: 0.30370853 | P244: 670022.33 | Q244: 603792 | R244: 11108 | S244: 0.22093734

Sheet Ignore-TMotors Retail-vaahan
B1: Vaahan Data - Tata Motors PV
U2: Export
B3: Month | C3: Registrations | D3: YoY% | F3: 3M Rolling | G3: QoQ% | H3: YoY% | J3: 12M Rolling | K3: YoY%
B4: 43101 | C4: 55165
B5: 43159 | C5: 48810
B6: 43190 | C6: 52640 | F6: =+SUM(C4:C6) -> 156615
B7: 43220 | C7: 54004 | F7: =+SUM(C5:C7) -> 155454 | G7: =+F7/F6-1 -> -0.007413083
B8: 43251 | C8: 49410 | F8: =+SUM(C6:C8) -> 156054 | G8: =+F8/F7-1 -> 0.0038596627
B9: 43281 | C9: 44967 | F9: =+SUM(C7:C9) -> 148381 | G9: =+F9/F8-1 -> -0.049168877
B10: 43312 | C10: 46856 | F10: =+SUM(C8:C10) -> 141233 | G10: =+F10/F9-1 -> -0.048173284
B11: 43343 | C11: 44248 | F11: =+SUM(C9:C11) -> 136071 | G11: =+F11/F10-1 -> -0.036549532
B12: 43373 | C12: 46454 | F12: =+SUM(C10:C12) -> 137558 | G12: =+F12/F11-1 -> 0.010928118
B13: 43404 | C13: 50125 | F13: =+SUM(C11:C13) -> 140827 | G13: =+F13/F12-1 -> 0.023764521
B14: 43434 | C14: 50025 | F14: =+SUM(C12:C14) -> 146604 | G14: =+F14/F13-1 -> 0.041021963 | U14: =+SUM(F3:F14) -> 1318797
B15: 43465 | C15: 46302 | F15: =+SUM(C13:C15) -> 146452 | G15: =+F15/F14-1 -> -0.0010368066 | J15: =+SUM(C4:C15) -> 589006 | U15: =+SUM(F4:F15) -> 1465249
B16: 43496 | C16: 54043 | D16: =+C16/C4-1 -> -0.020338983 | F16: =+SUM(C14:C16) -> 150370 | G16: =+F16/F15-1 -> 0.026752793 | J16: =+SUM(C5:C16) -> 587884 | U16: =+SUM(F5:F16) -> 1615619
B17: 43524 | C17: 46567 | D17: =+C17/C5-1 -> -0.045953698 | F17: =+SUM(C15:C17) -> 146912 | G17: =+F17/F16-1 -> -0.022996608 | J17: =+SUM(C6:C17) -> 585641 | U17: =+SUM(F6:F17) -> 1762531
B18: 43555 | C18: 50717 | D18: =+C18/C6-1 -> -0.036531155 | F18: =+SUM(C16:C18) -> 151327 | G18: =+F18/F17-1 -> 0.030052004 | H18: =+F18/F6-1 -> -0.033764327 | J18: =+SUM(C7:C18) -> 583718 | U18: =+SUM(F7:F18) -> 1757243
B19: 43585 | C19: 49999 | D19: =+C19/C7-1 -> -0.074161173 | F19: =+SUM(C17:C19) -> 147283 | G19: =+F19/F18-1 -> -0.026723585 | H19: =+F19/F7-1 -> -0.052562173 | J19: =+SUM(C8:C19) -> 579713 | U19: =+SUM(F8:F19) -> 1749072
B20: 43616 | C20: 46580 | D20: =+C20/C8-1 -> -0.057275855 | F20: =+SUM(C18:C20) -> 147296 | G20: =+F20/F19-1 -> 8.8265448e-05 | H20: =+F20/F8-1 -> -0.056121599 | J20: =+SUM(C9:C20) -> 576883 | U20: =+SUM(F9:F20) -> 1740314
B21: 43646 | C21: 38803 | D21: =+C21/C9-1 -> -0.1370783 | F21: =+SUM(C19:C21) -> 135382 | G21: =+F21/F20-1 -> -0.080884749 | H21: =+F21/F9-1 -> -0.087605556 | J21: =+SUM(C10:C21) -> 570719 | U21: =+SUM(F10:F21) -> 1727315
B22: 43677 | C22: 40652 | D22: =+C22/C10-1 -> -0.13240567 | F22: =+SUM(C20:C22) -> 126035 | G22: =+F22/F21-1 -> -0.069041675 | H22: =+F22/F10-1 -> -0.10760941 | J22: =+SUM(C11:C22) -> 564515 | U22: =+SUM(F11:F22) -> 1712117
B23: 43708 | C23: 37547 | D23: =+C23/C11-1 -> -0.15144187 | F23: =+SUM(C21:C23) -> 117002 | G23: =+F23/F22-1 -> -0.071670568 | H23: =+F23/F11-1 -> -0.14014007 | J23: =+SUM(C12:C23) -> 557814 | U23: =+SUM(F12:F23) -> 1693048
B24: 43738 | C24: 35728 | D24: =+C24/C12-1 -> -0.23089508 | F24: =+SUM(C22:C24) -> 113927 | G24: =+F24/F23-1 -> -0.026281602 | H24: =+F24/F12-1 -> -0.17178935 | J24: =+SUM(C13:C24) -> 547088 | U24: =+SUM(F13:F24) -> 1669417
B25: 43769 | C25: 39095 | D25: =+C25/C13-1 -> -0.22004988 | F25: =+SUM(C23:C25) -> 112370 | G25: =+F25/F24-1 -> -0.013666646 | H25: =+F25/F13-1 -> -0.20207063 | J25: =+SUM(C14:C25) -> 536058 | U25: =+SUM(F14:F25) -> 1640960
B26: 43799 | C26: 43473 | D26: =+C26/C14-1 -> -0.13097451 | F26: =+SUM(C24:C26) -> 118296 | G26: =+F26/F25-1 -> 0.052736496 | H26: =+F26/F14-1 -> -0.19309159 | J26: =+SUM(C15:C26) -> 529506 | U26: =+SUM(F15:F26) -> 1612652
B27: 43830 | C27: 36271 | D27: =+C27/C15-1 -> -0.21664291 | F27: =+SUM(C25:C27) -> 118839 | G27: =+F27/F26-1 -> 0.0045901806 | H27: =+F27/F15-1 -> -0.18854642 | J27: =+SUM(C16:C27) -> 519475 | K27: =+J27/J15-1 -> -0.11804803 | U27: =+SUM(F16:F27) -> 1585039
B28: 43861 | C28: 47812 | D28: =+C28/C16-1 -> -0.11529708 | F28: =+SUM(C26:C28) -> 127556 | G28: =+F28/F27-1 -> 0.073351341 | H28: =+F28/F16-1 -> -0.15171909 | J28: =+SUM(C17:C28) -> 513244 | K28: =+J28/J16-1 -> -0.12696382 | U28: =+SUM(F17:F28) -> 1562225
B29: 43890 | C29: 49588 | D29: =+C29/C17-1 -> 0.064874267 | F29: =+SUM(C27:C29) -> 133671 | G29: =+F29/F28-1 -> 0.047939728 | H29: =+F29/F17-1 -> -0.090128785 | J29: =+SUM(C18:C29) -> 516265 | K29: =+J29/J17-1 -> -0.11846165 | U29: =+SUM(F18:F29) -> 1548984
B30: 43921 | C30: 70617 | D30: =+C30/C18-1 -> 0.39237337 | F30: =+SUM(C28:C30) -> 168017 | G30: =+F30/F29-1 -> 0.25694429 | H30: =+F30/F18-1 -> 0.11029096 | J30: =+SUM(C19:C30) -> 536165 | K30: =+J30/J18-1 -> -0.081465708 | U30: =+SUM(F19:F30) -> 1565674
B31: 43951 | C31: 12902 | D31: =+C31/C19-1 -> -0.74195484 | F31: =+SUM(C29:C31) -> 133107 | G31: =+F31/F30-1 -> -0.20777659 | H31: =+F31/F19-1 -> -0.096250076 | J31: =+SUM(C20:C31) -> 499068 | K31: =+J31/J19-1 -> -0.13911194 | U31: =+SUM(F20:F31) -> 1551498
B32: 43982 | C32: 1944 | D32: =+C32/C20-1 -> -0.95826535 | F32: =+SUM(C30:C32) -> 85463 | G32: =+F32/F31-1 -> -0.3579376 | H32: =+F32/F20-1 -> -0.41978737 | J32: =+SUM(C21:C32) -> 454432 | K32: =+J32/J20-1 -> -0.21226315 | U32: =+SUM(F21:F32) -> 1489665
B33: 44012 | C33: 9732 | D33: =+C33/C21-1 -> -0.74919465 | F33: =+SUM(C31:C33) -> 24578 | G33: =+F33/F32-1 -> -0.71241356 | H33: =+F33/F21-1 -> -0.81845445 | J33: =+SUM(C22:C33) -> 425361 | K33: =+J33/J21-1 -> -0.25469276 | U33: =+SUM(F22:F33) -> 1378861
B34: 44043 | C34: 17141 | D34: =+C34/C22-1 -> -0.57834793 | F34: =+SUM(C32:C34) -> 28817 | G34: =+F34/F33-1 -> 0.17247132 | H34: =+F34/F22-1 -> -0.77135716 | J34: =+SUM(C23:C34) -> 401850 | K34: =+J34/J22-1 -> -0.28815 | U34: =+SUM(F23:F34) -> 1281643
B35: 44074 | C35: 21616 | D35: =+C35/C23-1 -> -0.42429488 | F35: =+SUM(C33:C35) -> 48489 | G35: =+F35/F34-1 -> 0.6826526 | H35: =+F35/F23-1 -> -0.58557119 | J35: =+SUM(C24:C35) -> 385919 | K35: =+J35/J23-1 -> -0.30815827 | U35: =+SUM(F24:F35) -> 1213130
B36: 44104 | C36: 28530 | D36: =+C36/C24-1 -> -0.20146664 | F36: =+SUM(C34:C36) -> 67287 | G36: =+F36/F35-1 -> 0.38767556 | H36: =+F36/F24-1 -> -0.40938496 | J36: =+SUM(C25:C36) -> 378721 | K36: =+J36/J24-1 -> -0.30775122 | U36: =+SUM(F25:F36) -> 1166490
B37: 44135 | C37: 34202 | D37: =+C37/C25-1 -> -0.12515667 | F37: =+SUM(C35:C37) -> 84348 | G37: =+F37/F36-1 -> 0.25355566 | H37: =+F37/F25-1 -> -0.24937261 | J37: =+SUM(C26:C37) -> 373828 | K37: =+J37/J25-1 -> -0.30263516 | U37: =+SUM(F26:F37) -> 1138468
B38: 44165 | C38: 40086 | D38: =+C38/C26-1 -> -0.077910427 | F38: =+SUM(C36:C38) -> 102818 | G38: =+F38/F37-1 -> 0.21897378 | H38: =+F38/F26-1 -> -0.13084128 | J38: =+SUM(C27:C38) -> 370441 | K38: =+J38/J26-1 -> -0.30040264 | U38: =+SUM(F27:F38) -> 1122990
... B55: 44681 | C55: 36864 | D55: =+C55/C43-1 -> -0.10402489 | F55: =+SUM(C53:C55) -> 101114 | G55: =+F55/F54-1 -> -0.14948774 | H55: =+F55/F43-1 -> -0.28461462 | J55: =+SUM(C44:C55) -> 508262 | K55: =+J55/J43-1 -> 0.33953383 | U55: =+SUM(F44:F55) -> 1551616
B56: 44712 | C56: 36330 | D56: =+C56/C44-1 -> 1.1560831 | F56: =+SUM(C54:C56) -> 108986 | G56: =+F56/F55-1 -> 0.077852721 | H56: =+F56/F44-1 -> -0.027397016 | J56: =+SUM(C45:C56) -> 527742 | K56: =+J56/J44-1 -> 0.33829862 | N56: 27649 | U56: =+SUM(F45:F56) -> 1548546
B57: 44742 | C57: 37878 | D57: =+C57/C45-1 -> 0.095911813 | F57: =+SUM(C55:C57) -> 111072 | G57: =+F57/F56-1 -> 0.019140073 | H57: =+F57/F45-1 -> 0.20003889 | J57: =+SUM(C46:C57) -> 531057 | K57: =+J57/J45-1 -> 0.26692814 | N57: 28069 | U57: =+SUM(F46:F57) -> 1567061
B58: 44773 | C58: 37254 | D58: =+C58/C46-1 -> -0.15793043 | F58: =+SUM(C56:C58) -> 111462 | G58: =+F58/F57-1 -> 0.003511236 | H58: =+F58/F46-1 -> 0.1652623 | J58: =+SUM(C47:C58) -> 524070 | K58: =+J58/J46-1 -> 0.17433655 | N58: 27589 | U58: =+SUM(F47:F58) -> 1582869
B59: 44804 | C59: 39371 | D59: =+C59/C47-1 -> -0.15433027 | F59: =+SUM(C57:C59) -> 114503 | G59: =+F59/F58-1 -> 0.027282841 | H59: =+F59/F47-1 -> -0.086606573 | J59: =+SUM(C48:C59) -> 516885 | K59: =+J59/J47-1 -> 0.096933632 | N59: 27659 | U59: =+SUM(F48:F59) -> 1572012
B60: 44834 | C60: 37702 | D60: =+C60/C48-1 -> -0.21780083 | F60: =+SUM(C58:C60) -> 114327 | G60: =+F60/F59-1 -> -0.0015370776 | H60: =+F60/F48-1 -> -0.17748585 | J60: =+SUM(C49:C60) -> 506387 | K60: =+J60/J48-1 -> 0.031592307 | N60: 29109 | U60: =+SUM(F49:F60) -> 1547342
B61: 44865 | C61: 49917 | D61: =+C61/C49-1 -> -0.017633283 | F61: =+SUM(C59:C61) -> 126990 | G61: =+F61/F60-1 -> 0.11076124 | H61: =+F61/F49-1 -> -0.1276302 | J61: =+SUM(C50:C61) -> 505491 | K61: =+J61/J49-1 -> -0.0039389939 | N61: 27958 | U61: =+SUM(F50:F61) -> 1528763
B62: 44895 | C62: 40728 | D62: =+C62/C50-1 -> -0.24739449 | F62: =+SUM(C60:C62) -> 128347 | G62: =+F62/F61-1 -> 0.010685881 | H62: =+F62/F50-1 -> -0.16183741 | J62: =+SUM(C51:C62) -> 492103 | K62: =+J62/J50-1 -> -0.056406274 | N62: 30666 | U62: =+SUM(F51:F62) -> 1503981
B63: 44926 | C63: 36626 | D63: =+C63/C51-1 -> -0.35938293 | F63: =+SUM(C61:C63) -> 127271 | G63: =+F63/F62-1 -> -0.0083835228 | H63: =+F63/F51-1 -> -0.21487088 | J63: =+SUM(C52:C63) -> 471556 | K63: =+J63/J51-1 -> -0.12601335 | N63: 26577 | U63: =+SUM(F52:F63) -> 1469150
B64: 44957 | C64: 44907 | D64: =+C64/C52-1 -> -0.1780694 | F64: =+SUM(C62:C64) -> 122261 | G64: =+F64/F63-1 -> -0.03936482 | H64: =+F64/F52-1 -> -0.26315504 | J64: =+SUM(C53:C64) -> 461827 | K64: =+J64/J52-1 -> -0.15800288 | N64: 33724 | U64: =+SUM(F53:F64) -> 1425486
B65: 44985 | C65: 38946 | D65: =+C65/C53-1 -> 0.36854312 | F65: =+SUM(C63:C65) -> 120479 | G65: =+F65/F64-1 -> -0.014575376 | H65: =+F65/F53-1 -> -0.14107381 | J65: =+SUM(C54:C65) -> 472315 | K65: =+J65/J53-1 -> -0.11020286 | N65: 31487 | U65: =+SUM(F54:F65) -> 1405698
B66: 45016 | C66: 46658 | D66: =+C66/C54-1 -> 0.30358739 | F66: =+SUM(C64:C66) -> 130511 | G66: =+F66/F65-1 -> 0.083267623 | H66: =+F66/F54-1 -> 0.09778275 | J66: =+SUM(C55:C66) -> 483181 | K66: =+J66/J54-1 -> -0.057285062 | N66: 37140 | U66: =+SUM(F55:F66) -> 1417323
B67: 45046 | C67: 40872 | D67: =+C67/C55-1 -> 0.10872396 | F67: =+SUM(C65:C67) -> 126476 | G67: =+F67/F66-1 -> -0.030916934 | H67: =+F67/F55-1 -> 0.2508258 | J67: =+SUM(C56:C67) -> 487189 | K67: =+J67/J55-1 -> -0.0414609 | N67: 33749 | U67: =+SUM(F56:F67) -> 1442685
... B98: 45991 | C98: 46351 | D98: =+C98/C86-1 -> 0.22369185 | F98: =+SUM(C96:C98) -> 149523 | G98: =+F98/F97-1 -> 0.1174444 | H98: =+F98/F86-1 -> 0.19427316 | J98: =+SUM(C87:C98) -> 474916 | K98: =+J98/J86-1 -> 0.0074671826 | N98: 33257 | U98: =+SUM(F87:F98) -> 1398959
B99: 46022 | C99: 44962 | D99: =+C99/C87-1 -> 0.33636499 | F99: =+SUM(C97:C99) -> 159488 | G99: =+F99/F98-1 -> 0.066645265 | H99: =+F99/F87-1 -> 0.21881472 | J99: =+SUM(C88:C99) -> 486233 | K99: =+J99/J87-1 -> 0.043257265 | U99: =+SUM(F88:F99) -> 1427592
B100: =EOMONTH(B99,1) -> 46053 | C100: 54285 | D100: =+C100/C88-1 -> 0.1118735 | F100: =+SUM(C98:C100) -> 145598 | G100: =+F100/F99-1 -> -0.087091192 | H100: =+F100/F88-1 -> 0.20982833 | J100: =+SUM(C89:C100) -> 491695 | K100: =+J100/J88-1 -> 0.052505961 | U100: =+SUM(F89:F100) -> 1452844
B101: =EOMONTH(B100,1) -> 46081 | C101: 49734 | D101: =+C101/C89-1 -> 0.43016535 | F101: =+SUM(C99:C101) -> 148981 | G101: =+F101/F100-1 -> 0.023235209 | H101: =+F101/F89-1 -> 0.27070273 | J101: =+SUM(C90:C101) -> 506654 | K101: =+J101/J89-1 -> 0.096473307 | U101: =+SUM(F90:F101) -> 1484582
B102: =EOMONTH(B101,1) -> 46112 | C102: 55333 | D102: =+C102/C90-1 -> 0.26466757 | F102: =+SUM(C100:C102) -> 159352 | G102: =+F102/F101-1 -> 0.069612904 | H102: =+F102/F90-1 -> 0.25128189 | J102: =+SUM(C91:C102) -> 518234 | K102: =+J102/J90-1 -> 0.10873537 | U102: =+SUM(F91:F102) -> 1516583
B103: =EOMONTH(B102,1) -> 46142 | C103: 47396 | D103: =+C103/C91-1 -> 0.2139436 | F103: =+SUM(C101:C103) -> 152463 | G103: =+F103/F102-1 -> -0.043231337 | H103: =+F103/F91-1 -> 0.29677386 | J103: =+SUM(C92:C103) -> 526587 | K103: =+J103/J91-1 -> 0.13025029 | U103: =+SUM(F92:F103) -> 1551475
B104: =EOMONTH(B103,1) -> 46173 | C104: 43182 | D104: =+C104/C92-1 -> 0.36182156 | F104: =+SUM(C102:C104) -> 145911 | G104: =+F104/F103-1 -> -0.042974361 | H104: =+F104/F92-1 -> 0.27427623 | J104: =+SUM(C93:C104) -> 538060 | K104: =+J104/J92-1 -> 0.1652096 | U104: =+SUM(F93:F104) -> 1582881
B105: =EOMONTH(B104,1) -> 46203 | U105: =+SUM(F94:F105) -> 1482472
B106: =EOMONTH(B105,1) -> 46234 | U106: =+SUM(F95:F106) -> 1387754
B107: =EOMONTH(B106,1) -> 46265 | U107: =+SUM(F96:F107) -> 1294109
B108: =EOMONTH(B107,1) -> 46295 | U108: =+SUM(F97:F108) -> 1195124
B109: =EOMONTH(B108,1) -> 46326 | U109: =+SUM(F98:F109) -> 1061316
B110: =EOMONTH(B109,1) -> 46356 | U110: =+SUM(F99:F110) -> 911793
B111: =EOMONTH(B110,1) -> 46387 | U111: =+SUM(F100:F111) -> 752305
B112: =EOMONTH(B111,1) -> 46418 | U112: =+SUM(F101:F112) -> 606707
B113: =EOMONTH(B112,1) -> 46446 | U113: =+SUM(F102:F113) -> 457726
B114: =EOMONTH(B113,1) -> 46477 | U114: =+SUM(F103:F114) -> 298374
B115: =EOMONTH(B114,1) -> 46507 | U115: =+SUM(F104:F115) -> 145911
B116: =EOMONTH(B115,1) -> 46538 | U116: =+SUM(F105:F116) -> 0
... B134: =EOMONTH(B133,1) -> 47087 | U134: =+SUM(F123:F134) -> 0
U135: =+SUM(F124:F135) -> 0
U136: =+SUM(F125:F136) -> 0
U137: =+SUM(F126:F137) -> 0
U138: =+SUM(F127:F138) -> 0
U139: =+SUM(F128:F139) -> 0
U140: =+SUM(F129:F140) -> 0
U141: =+SUM(F130:F141) -> 0
U142: =+SUM(F131:F142) -> 0
U143: =+SUM(F132:F143) -> 0
U144: =+SUM(F133:F144) -> 0
U145: =+SUM(F134:F145) -> 0
U146: =+SUM(F135:F146) -> 0
... U182: =+SUM(F171:F182) -> 0

Sheet QTR Raw
A1: ='Annual Raw'!A1 -> 100570 | B1: X | C1: 201206 | D1: 201209 | E1: 201212 | F1: 201303 | G1: 201306 | H1: 201309 | I1: 201312 | J1: 201403 | K1: 201406 | L1: 201409 | M1: 201412 | N1: 201503 | O1: 201506 | P1: 201509 | Q1: 201512 | R1: 201603 | S1: 201606 | T1: 201609 | U1: 201612 | V1: 201703 | W1: 201706 | X1: 201709 | Y1: 201712 | Z1: 201803 | AA1: 201806 | AB1: 201809 | AC1: 201812 | AD1: 201903 | AE1: 201906 | AF1: 201909 | AG1: 201912 | AH1: 202003 | AI1: 202006 | AJ1: 202009 | AK1: 202012 | AL1: 202103 | AM1: 202106 | AN1: 202109 | AO1: 202112 | AP1: 202203 | AQ1: 202206 | AR1: 202209 | AS1: 202212 | AT1: 202303 | AU1: 202306 | AV1: 202309 | AW1: 202312 | AX1: 202403 | AY1: 202406 | AZ1: 202409 | BA1: 202412 | BB1: 202503 | BC1: 202506 | BD1: 202509 | BE1: 202512 | BF1: 202603 | BG1: 202606 | BH1: 202609 | BI1: 202612 | BJ1: 202703 | BK1: 202706 | BL1: 202709 | BM1: 202712 | BN1: 202803 | BO1: 202806 | BP1: 202809 | BQ1: 202812 | BR1: 202903 | BS1: 202906 | BT1: 202909 | BU1: 202912 | BV1: 203003
A3: Field Description | B3: Field Name
A4: Company Name | B4: CD_COMPNAME | C4: =_xll.EQNXTDZ(A1,B4,C1) -> Tata Motors Passenger Vehicles Ltd.
A5: Date End | B5: QTR_DATE_END | C5: =_xll.EQNXTDZ($A$1,$B5,C$1,$B$1) -> 201206 | D5: =_xll.EQNXTDZ($A$1,$B5,D$1,$B$1) -> 201209 | E5: =_xll.EQNXTDZ($A$1,$B5,E$1,$B$1) -> 201212 | F5: =_xll.EQNXTDZ($A$1,$B5,F$1,$B$1) -> 201303 | G5: =_xll.EQNXTDZ($A$1,$B5,G$1,$B$1) -> 201306 | H5: =_xll.EQNXTDZ($A$1,$B5,H$1,$B$1) -> 201309 | I5: =_xll.EQNXTDZ($A$1,$B5,I$1,$B$1) -> 201312 | J5: =_xll.EQNXTDZ($A$1,$B5,J$1,$B$1) -> 201403 | ... BV5: =_xll.EQNXTDZ($A$1,$B5,BV$1,$B$1) -> 0
A6: Gross Sales | B6: QTR_GROSS_SALE | C6: =_xll.EQNXTDZ($A$1,$B6,C$1,$B$1) -> 44176.85 | D6: =_xll.EQNXTDZ($A$1,$B6,D$1,$B$1) -> 44105.07 | E6: =_xll.EQNXTDZ($A$1,$B6,E$1,$B$1) -> 47054.26 | F6: =_xll.EQNXTDZ($A$1,$B6,F$1,$B$1) -> 57113.65 | G6: =_xll.EQNXTDZ($A$1,$B6,G$1,$B$1) -> 47827.97 | H6: =_xll.EQNXTDZ($A$1,$B6,H$1,$B$1) -> 56648.06 | I6: =_xll.EQNXTDZ($A$1,$B6,I$1,$B$1) -> 64377.64 | J6: =_xll.EQNXTDZ($A$1,$B6,J$1,$B$1) -> 65616.2 | ... BV6: =_xll.EQNXTDZ($A$1,$B6,BV$1,$B$1) -> 0
A7: Less: Excise Duty | B7: QTR_EXCISE_DUTY | C7: =_xll.EQNXTDZ($A$1,$B7,C$1,$B$1) -> 1005.72 | D7: =_xll.EQNXTDZ($A$1,$B7,D$1,$B$1) -> 1286.17 | E7: =_xll.EQNXTDZ($A$1,$B7,E$1,$B$1) -> 1232.95 | F7: =_xll.EQNXTDZ($A$1,$B7,F$1,$B$1) -> 1271.95 | G7: =_xll.EQNXTDZ($A$1,$B7,G$1,$B$1) -> 1066.06 | H7: =_xll.EQNXTDZ($A$1,$B7,H$1,$B$1) -> 961.19 | I7: =_xll.EQNXTDZ($A$1,$B7,I$1,$B$1) -> 865.13 | J7: =_xll.EQNXTDZ($A$1,$B7,J$1,$B$1) -> 900.39 | ... BV7: =_xll.EQNXTDZ($A$1,$B7,BV$1,$B$1) -> 0
A8: Other operating income | B8: QTR_JOB_WORKS | C8: =_xll.EQNXTDZ($A$1,$B8,C$1,$B$1) -> 152.48 | D8: =_xll.EQNXTDZ($A$1,$B8,D$1,$B$1) -> 583.98 | E8: =_xll.EQNXTDZ($A$1,$B8,E$1,$B$1) -> 268.19 | F8: =_xll.EQNXTDZ($A$1,$B8,F$1,$B$1) -> 160.14 | G8: =_xll.EQNXTDZ($A$1,$B8,G$1,$B$1) -> 34.56 | H8: =_xll.EQNXTDZ($A$1,$B8,H$1,$B$1) -> 1179.9 | I8: =_xll.EQNXTDZ($A$1,$B8,I$1,$B$1) -> 340.77 | J8: =_xll.EQNXTDZ($A$1,$B8,J$1,$B$1) -> 601.33 | ... BV8: =_xll.EQNXTDZ($A$1,$B8,BV$1,$B$1) -> 0
A9: Net Sales & Other Operating Income | B9: QTR_NET_SALES | C9: =_xll.EQNXTDZ($A$1,$B9,C$1,$B$1) -> 43323.61 | D9: =_xll.EQNXTDZ($A$1,$B9,D$1,$B$1) -> 43402.88 | E9: =_xll.EQNXTDZ($A$1,$B9,E$1,$B$1) -> 46089.5 | F9: =_xll.EQNXTDZ($A$1,$B9,F$1,$B$1) -> 56001.84 | G9: =_xll.EQNXTDZ($A$1,$B9,G$1,$B$1) -> 46796.47 | H9: =_xll.EQNXTDZ($A$1,$B9,H$1,$B$1) -> 56866.77 | I9: =_xll.EQNXTDZ($A$1,$B9,I$1,$B$1) -> 63853.28 | J9: =_xll.EQNXTDZ($A$1,$B9,J$1,$B$1) -> 65317.14 | ... BV9: =_xll.EQNXTDZ($A$1,$B9,BV$1,$B$1) -> 0
A10: (Increase) / Decrease In Stocks | B10: QTR_INC_DEC_INVENTORY | C10: =_xll.EQNXTDZ($A$1,$B10,C$1,$B$1) -> -1962.03 | D10: =_xll.EQNXTDZ($A$1,$B10,D$1,$B$1) -> -1005.76 | E10: =_xll.EQNXTDZ($A$1,$B10,E$1,$B$1) -> -1434.99 | F10: =_xll.EQNXTDZ($A$1,$B10,F$1,$B$1) -> 1373 | G10: =_xll.EQNXTDZ($A$1,$B10,G$1,$B$1) -> -2942.98 | H10: =_xll.EQNXTDZ($A$1,$B10,H$1,$B$1) -> 253.76 | I10: =_xll.EQNXTDZ($A$1,$B10,I$1,$B$1) -> 588.93 | J10: =_xll.EQNXTDZ($A$1,$B10,J$1,$B$1) -> -740.29 | ... BV10: =_xll.EQNXTDZ($A$1,$B10,BV$1,$B$1) -> 0
A11: Cost of Services & Raw Materials | B11: QTR_RAW_MATERIAL_COST | C11: =_xll.EQNXTDZ($A$1,$B11,C$1,$B$1) -> 26797.51 | D11: =_xll.EQNXTDZ($A$1,$B11,D$1,$B$1) -> 25683.23 | E11: =_xll.EQNXTDZ($A$1,$B11,E$1,$B$1) -> 29043.7 | F11: =_xll.EQNXTDZ($A$1,$B11,F$1,$B$1) -> 31274.13 | G11: =_xll.EQNXTDZ($A$1,$B11,G$1,$B$1) -> 29440.78 | H11: =_xll.EQNXTDZ($A$1,$B11,H$1,$B$1) -> 30873.07 | I11: =_xll.EQNXTDZ($A$1,$B11,I$1,$B$1) -> 37340.23 | J11: =_xll.EQNXTDZ($A$1,$B11,J$1,$B$1) -> 37895.96 | ... BV11: =_xll.EQNXTDZ($A$1,$B11,BV$1,$B$1) -> 0
A12: Purchase of Finished Goods | B12: QTR_PURCHASE_FIN_GOOD | C12: =_xll.EQNXTDZ($A$1,$B12,C$1,$B$1) -> 2913.9 | D12: =_xll.EQNXTDZ($A$1,$B12,D$1,$B$1) -> 3043.78 | E12: =_xll.EQNXTDZ($A$1,$B12,E$1,$B$1) -> 2062.67 | F12: =_xll.EQNXTDZ($A$1,$B12,F$1,$B$1) -> 2482.61 | G12: =_xll.EQNXTDZ($A$1,$B12,G$1,$B$1) -> 2345.95 | H12: =_xll.EQNXTDZ($A$1,$B12,H$1,$B$1) -> 3435.19 | I12: =_xll.EQNXTDZ($A$1,$B12,I$1,$B$1) -> 1967.72 | J12: =_xll.EQNXTDZ($A$1,$B12,J$1,$B$1) -> 3128.09 | ... BV12: =_xll.EQNXTDZ($A$1,$B12,BV$1,$B$1) -> 0
A13: Excise Duty | B13: QTR_EXCISE | C13: =_xll.EQNXTDZ($A$1,$B13,C$1,$B$1) -> 0 | D13: =_xll.EQNXTDZ($A$1,$B13,D$1,$B$1) -> 0 | E13: =_xll.EQNXTDZ($A$1,$B13,E$1,$B$1) -> 0 | F13: =_xll.EQNXTDZ($A$1,$B13,F$1,$B$1) -> 0 | G13: =_xll.EQNXTDZ($A$1,$B13,G$1,$B$1) -> 0 | H13: =_xll.EQNXTDZ($A$1,$B13,H$1,$B$1) -> 0 | I13: =_xll.EQNXTDZ($A$1,$B13,I$1,$B$1) -> 0 | J13: =_xll.EQNXTDZ($A$1,$B13,J$1,$B$1) -> 0 | ... BV13: =_xll.EQNXTDZ($A$1,$B13,BV$1,$B$1) -> 0
A14: Operating & Manufacturing Expenses | B14: QTR_MFG_EXPS | C14: =_xll.EQNXTDZ($A$1,$B14,C$1,$B$1) -> 8639.14 | D14: =_xll.EQNXTDZ($A$1,$B14,D$1,$B$1) -> 9087.84 | E14: =_xll.EQNXTDZ($A$1,$B14,E$1,$B$1) -> 8940.41 | F14: =_xll.EQNXTDZ($A$1,$B14,F$1,$B$1) -> 10914.4 | G14: =_xll.EQNXTDZ($A$1,$B14,G$1,$B$1) -> 10057.69 | H14: =_xll.EQNXTDZ($A$1,$B14,H$1,$B$1) -> 11933.39 | I14: =_xll.EQNXTDZ($A$1,$B14,I$1,$B$1) -> 11731.74 | J14: =_xll.EQNXTDZ($A$1,$B14,J$1,$B$1) -> 12668.16 | ... BV14: =_xll.EQNXTDZ($A$1,$B14,BV$1,$B$1) -> 0
A15: Electricity Power & Fuel Cost | B15: QTR_ELECTRICITY_POWER_FUEL | C15: =_xll.EQNXTDZ($A$1,$B15,C$1,$B$1) -> 0 | D15: =_xll.EQNXTDZ($A$1,$B15,D$1,$B$1) -> 0 | E15: =_xll.EQNXTDZ($A$1,$B15,E$1,$B$1) -> 0 | F15: =_xll.EQNXTDZ($A$1,$B15,F$1,$B$1) -> 0 | G15: =_xll.EQNXTDZ($A$1,$B15,G$1,$B$1) -> 0 | H15: =_xll.EQNXTDZ($A$1,$B15,H$1,$B$1) -> 0 | I15: =_xll.EQNXTDZ($A$1,$B15,I$1,$B$1) -> 0 | J15: =_xll.EQNXTDZ($A$1,$B15,J$1,$B$1) -> 0 | ... BV15: =_xll.EQNXTDZ($A$1,$B15,BV$1,$B$1) -> 0
A16: Employee Cost | B16: QTR_EXPLOYEE_COST | C16: =_xll.EQNXTDZ($A$1,$B16,C$1,$B$1) -> 3789.69 | D16: =_xll.EQNXTDZ($A$1,$B16,D$1,$B$1) -> 4019.06 | E16: =_xll.EQNXTDZ($A$1,$B16,E$1,$B$1) -> 4352.91 | F16: =_xll.EQNXTDZ($A$1,$B16,F$1,$B$1) -> 4434.57 | G16: =_xll.EQNXTDZ($A$1,$B16,G$1,$B$1) -> 4472.8 | H16: =_xll.EQNXTDZ($A$1,$B16,H$1,$B$1) -> 5191.05 | I16: =_xll.EQNXTDZ($A$1,$B16,I$1,$B$1) -> 5865.26 | J16: =_xll.EQNXTDZ($A$1,$B16,J$1,$B$1) -> 6027.31 | ... BV16: =_xll.EQNXTDZ($A$1,$B16,BV$1,$B$1) -> 0
... A42: Consolidated PAT(after extra items) | B42: QTR_CONS_PAT_EXITM | C42: =_xll.EQNXTDZ($A$1,$B42,C$1,$B$1) -> 2244.91 | D42: =_xll.EQNXTDZ($A$1,$B42,D$1,$B$1) -> 2074.73 | E42: =_xll.EQNXTDZ($A$1,$B42,E$1,$B$1) -> 1627.5 | F42: =_xll.EQNXTDZ($A$1,$B42,F$1,$B$1) -> 3945.47 | G42: =_xll.EQNXTDZ($A$1,$B42,G$1,$B$1) -> 1726.07 | H42: =_xll.EQNXTDZ($A$1,$B42,H$1,$B$1) -> 3541.86 | I42: =_xll.EQNXTDZ($A$1,$B42,I$1,$B$1) -> 4804.8 | J42: =_xll.EQNXTDZ($A$1,$B42,J$1,$B$1) -> 3918.29 | ... BV42: =_xll.EQNXTDZ($A$1,$B42,BV$1,$B$1) -> 0
A44: Field Description | B44: Field Name
A45: Equity Capital | B45: QTR_EQUITY_CAP | C45: =_xll.EQNXTDZ($A$1,$B45,C$1,$B$1) -> 637.98 | D45: =_xll.EQNXTDZ($A$1,$B45,D$1,$B$1) -> 637.98 | E45: =_xll.EQNXTDZ($A$1,$B45,E$1,$B$1) -> 638 | F45: =_xll.EQNXTDZ($A$1,$B45,F$1,$B$1) -> 638.07 | G45: =_xll.EQNXTDZ($A$1,$B45,G$1,$B$1) -> 643.78 | H45: =_xll.EQNXTDZ($A$1,$B45,H$1,$B$1) -> 643.78 | I45: =_xll.EQNXTDZ($A$1,$B45,I$1,$B$1) -> 643.78 | J45: =_xll.EQNXTDZ($A$1,$B45,J$1,$B$1) -> 643.78 | ... BV45: =_xll.EQNXTDZ($A$1,$B45,BV$1,$B$1) -> 0
A46: Face Value | B46: QTR_FV | C46: =_xll.EQNXTDZ($A$1,$B46,C$1,$B$1) -> 2 | D46: =_xll.EQNXTDZ($A$1,$B46,D$1,$B$1) -> 2 | E46: =_xll.EQNXTDZ($A$1,$B46,E$1,$B$1) -> 2 | F46: =_xll.EQNXTDZ($A$1,$B46,F$1,$B$1) -> 2 | G46: =_xll.EQNXTDZ($A$1,$B46,G$1,$B$1) -> 2 | H46: =_xll.EQNXTDZ($A$1,$B46,H$1,$B$1) -> 2 | I46: =_xll.EQNXTDZ($A$1,$B46,I$1,$B$1) -> 2 | J46: =_xll.EQNXTDZ($A$1,$B46,J$1,$B$1) -> 2 | ... BV46: =_xll.EQNXTDZ($A$1,$B46,BV$1,$B$1) -> 0
A47: Month End | B47: BMONTH_MONTHEND | C47: =_xll.EQNXTDZ($A$1,$B47,C$5) -> 201206 | D47: =_xll.EQNXTDZ($A$1,$B47,D$5) -> 201209 | E47: =_xll.EQNXTDZ($A$1,$B47,E$5) -> 201212 | F47: =_xll.EQNXTDZ($A$1,$B47,F$5) -> 201303 | G47: =_xll.EQNXTDZ($A$1,$B47,G$5) -> 201306 | H47: =_xll.EQNXTDZ($A$1,$B47,H$5) -> 201309 | I47: =_xll.EQNXTDZ($A$1,$B47,I$5) -> 201312 | J47: =_xll.EQNXTDZ($A$1,$B47,J$5) -> 201403 | ... BV47: =_xll.EQNXTDZ($A$1,$B47,BV$5) -> 0
A48: Close | B48: BMONTH_CLOSE | C48: =_xll.EQNXTDZ($A$1,$B48,C$5) -> 239.48757 | D48: =_xll.EQNXTDZ($A$1,$B48,D$5) -> 264.61868 | E48: =_xll.EQNXTDZ($A$1,$B48,E$5) -> 309.09283 | F48: =_xll.EQNXTDZ($A$1,$B48,F$5) -> 266.4491 | G48: =_xll.EQNXTDZ($A$1,$B48,G$5) -> 278.47047 | H48: =_xll.EQNXTDZ($A$1,$B48,H$5) -> 328.83163 | I48: =_xll.EQNXTDZ($A$1,$B48,I$5) -> 372.4153 | J48: =_xll.EQNXTDZ($A$1,$B48,J$5) -> 394.13293 | ... BV48: =_xll.EQNXTDZ($A$1,$B48,BV$5) -> 0
A49: Total of Promoter and Promoter Group | B49: SHP_TPFTOTALPROMOTER | C49: =_xll.EQNXTDZ($A$1,$B49,C$5) -> 34.71 | D49: =_xll.EQNXTDZ($A$1,$B49,D$5) -> 34.74 | E49: =_xll.EQNXTDZ($A$1,$B49,E$5) -> 34.72 | F49: =_xll.EQNXTDZ($A$1,$B49,F$5) -> 34.71 | G49: =_xll.EQNXTDZ($A$1,$B49,G$5) -> 34.35 | H49: =_xll.EQNXTDZ($A$1,$B49,H$5) -> 34.33 | I49: =_xll.EQNXTDZ($A$1,$B49,I$5) -> 34.33 | J49: =_xll.EQNXTDZ($A$1,$B49,J$5) -> 34.33 | ... BV49: =_xll.EQNXTDZ($A$1,$B49,BV$5) -> 0
A50: Total of Promoter and Promoter Group Pledged | B50: SHP_PSHFTOTALPROMOTER | C50: =_xll.EQNXTDZ($A$1,$B50,C$5) -> 8.35 | D50: =_xll.EQNXTDZ($A$1,$B50,D$5) -> 6.38 | E50: =_xll.EQNXTDZ($A$1,$B50,E$5) -> 7.55 | F50: =_xll.EQNXTDZ($A$1,$B50,F$5) -> 7.55 | G50: =_xll.EQNXTDZ($A$1,$B50,G$5) -> 5.96 | H50: =_xll.EQNXTDZ($A$1,$B50,H$5) -> 5.96 | I50: =_xll.EQNXTDZ($A$1,$B50,I$5) -> 5.96 | J50: =_xll.EQNXTDZ($A$1,$B50,J$5) -> 6.22 | ... BV50: =_xll.EQNXTDZ($A$1,$B50,BV$5) -> 0
A54: Field Description | B54: Field Name | C54: =_xll.EQNXTDZ($A$1,$B54,C$5) -> 0 | D54: =_xll.EQNXTDZ($A$1,$B54,D$5) -> 0 | E54: =_xll.EQNXTDZ($A$1,$B54,E$5) -> 0 | F54: =_xll.EQNXTDZ($A$1,$B54,F$5) -> 0 | G54: =_xll.EQNXTDZ($A$1,$B54,G$5) -> 0 | H54: =_xll.EQNXTDZ($A$1,$B54,H$5) -> 0 | I54: =_xll.EQNXTDZ($A$1,$B54,I$5) -> 0 | J54: =_xll.EQNXTDZ($A$1,$B54,J$5) -> 0 | ... BV54: =_xll.EQNXTDZ($A$1,$B54,BV$5) -> 0
A55: Year End | B55: QTRB_DATE_END | C55: =_xll.EQNXTDZ($A$1,$B55,C$5,$B$1) -> 0 | D55: =_xll.EQNXTDZ($A$1,$B55,D$5,$B$1) -> 201209 | E55: =_xll.EQNXTDZ($A$1,$B55,E$5,$B$1) -> 0 | F55: =_xll.EQNXTDZ($A$1,$B55,F$5,$B$1) -> 201303 | G55: =_xll.EQNXTDZ($A$1,$B55,G$5,$B$1) -> 0 | H55: =_xll.EQNXTDZ($A$1,$B55,H$5,$B$1) -> 201309 | I55: =_xll.EQNXTDZ($A$1,$B55,I$5,$B$1) -> 0 | J55: =_xll.EQNXTDZ($A$1,$B55,J$5,$B$1) -> 201403 | ... BV55: =_xll.EQNXTDZ($A$1,$B55,BV$5,$B$1) -> 0
A56: Share Capital | B56: QTRB_SHARE_CAPITAL | C56: =_xll.EQNXTDZ($A$1,$B56,C$5,$B$1) -> 0 | D56: =_xll.EQNXTDZ($A$1,$B56,D$5,$B$1) -> 637.98 | E56: =_xll.EQNXTDZ($A$1,$B56,E$5,$B$1) -> 0 | F56: =_xll.EQNXTDZ($A$1,$B56,F$5,$B$1) -> 638.07 | G56: =_xll.EQNXTDZ($A$1,$B56,G$5,$B$1) -> 0 | H56: =_xll.EQNXTDZ($A$1,$B56,H$5,$B$1) -> 643.78 | I56: =_xll.EQNXTDZ($A$1,$B56,I$5,$B$1) -> 0 | J56: =_xll.EQNXTDZ($A$1,$B56,J$5,$B$1) -> 643.78 | ... BV56: =_xll.EQNXTDZ($A$1,$B56,BV$5,$B$1) -> 0
A57: Share Warrants & outstandings | B57: QTRB_SHAREWARNDOUT | C57: =_xll.EQNXTDZ($A$1,$B57,C$5,$B$1) -> 0 | D57: =_xll.EQNXTDZ($A$1,$B57,D$5,$B$1) -> 0 | E57: =_xll.EQNXTDZ($A$1,$B57,E$5,$B$1) -> 0 | F57: =_xll.EQNXTDZ($A$1,$B57,F$5,$B$1) -> 0 | G57: =_xll.EQNXTDZ($A$1,$B57,G$5,$B$1) -> 0 | H57: =_xll.EQNXTDZ($A$1,$B57,H$5,$B$1) -> 0 | I57: =_xll.EQNXTDZ($A$1,$B57,I$5,$B$1) -> 0 | J57: =_xll.EQNXTDZ($A$1,$B57,J$5,$B$1) -> 0 | ... BV57: =_xll.EQNXTDZ($A$1,$B57,BV$5,$B$1) -> 0
A58: Reserves & Surplus | B58: QTRB_RESERVE | C58: =_xll.EQNXTDZ($A$1,$B58,C$5,$B$1) -> 0 | D58: =_xll.EQNXTDZ($A$1,$B58,D$5,$B$1) -> 39618.69 | E58: =_xll.EQNXTDZ($A$1,$B58,E$5,$B$1) -> 0 | F58: =_xll.EQNXTDZ($A$1,$B58,F$5,$B$1) -> 36999.23 | G58: =_xll.EQNXTDZ($A$1,$B58,G$5,$B$1) -> 0 | H58: =_xll.EQNXTDZ($A$1,$B58,H$5,$B$1) -> 54612.53 | I58: =_xll.EQNXTDZ($A$1,$B58,I$5,$B$1) -> 0 | J58: =_xll.EQNXTDZ($A$1,$B58,J$5,$B$1) -> 64959.67 | ... BV58: =_xll.EQNXTDZ($A$1,$B58,BV$5,$B$1) -> 0
A59: Shareholder's Funds | B59: QTRB_SHAREHODERS_FUNDS | C59: =_xll.EQNXTDZ($A$1,$B59,C$5,$B$1) -> 0 | D59: =_xll.EQNXTDZ($A$1,$B59,D$5,$B$1) -> 40256.67 | E59: =_xll.EQNXTDZ($A$1,$B59,E$5,$B$1) -> 0 | F59: =_xll.EQNXTDZ($A$1,$B59,F$5,$B$1) -> 37637.3 | G59: =_xll.EQNXTDZ($A$1,$B59,G$5,$B$1) -> 0 | H59: =_xll.EQNXTDZ($A$1,$B59,H$5,$B$1) -> 55256.31 | I59: =_xll.EQNXTDZ($A$1,$B59,I$5,$B$1) -> 0 | J59: =_xll.EQNXTDZ($A$1,$B59,J$5,$B$1) -> 65603.45 | ... BV59: =_xll.EQNXTDZ($A$1,$B59,BV$5,$B$1) -> 0
A60: Minority Interest | B60: QTRB_MINORITY_INTEREST_BS | C60: =_xll.EQNXTDZ($A$1,$B60,C$5,$B$1) -> 0 | D60: =_xll.EQNXTDZ($A$1,$B60,D$5,$B$1) -> 349.79 | E60: =_xll.EQNXTDZ($A$1,$B60,E$5,$B$1) -> 0 | F60: =_xll.EQNXTDZ($A$1,$B60,F$5,$B$1) -> 370.48 | G60: =_xll.EQNXTDZ($A$1,$B60,G$5,$B$1) -> 0 | H60: =_xll.EQNXTDZ($A$1,$B60,H$5,$B$1) -> 410.56 | I60: =_xll.EQNXTDZ($A$1,$B60,I$5,$B$1) -> 0 | J60: =_xll.EQNXTDZ($A$1,$B60,J$5,$B$1) -> 420.65 | ... BV60: =_xll.EQNXTDZ($A$1,$B60,BV$5,$B$1) -> 0
A61: Long Term Borrowings | B61: QTRB_TOTAL_DEBTS | C61: =_xll.EQNXTDZ($A$1,$B61,C$5,$B$1) -> 0 | D61: =_xll.EQNXTDZ($A$1,$B61,D$5,$B$1) -> 28501.41 | E61: =_xll.EQNXTDZ($A$1,$B61,E$5,$B$1) -> 0 | F61: =_xll.EQNXTDZ($A$1,$B61,F$5,$B$1) -> 32155.29 | G61: =_xll.EQNXTDZ($A$1,$B61,G$5,$B$1) -> 0 | H61: =_xll.EQNXTDZ($A$1,$B61,H$5,$B$1) -> 40425.56 | I61: =_xll.EQNXTDZ($A$1,$B61,I$5,$B$1) -> 0 | J61: =_xll.EQNXTDZ($A$1,$B61,J$5,$B$1) -> 45258.61 | ... BV61: =_xll.EQNXTDZ($A$1,$B61,BV$5,$B$1) -> 0
A62: Secured Loans | B62: QTRB_SECURED_LOANS | C62: =_xll.EQNXTDZ($A$1,$B62,C$5,$B$1) -> 0 | D62: =_xll.EQNXTDZ($A$1,$B62,D$5,$B$1) -> 0 | E62: =_xll.EQNXTDZ($A$1,$B62,E$5,$B$1) -> 0 | F62: =_xll.EQNXTDZ($A$1,$B62,F$5,$B$1) -> 0 | G62: =_xll.EQNXTDZ($A$1,$B62,G$5,$B$1) -> 0 | H62: =_xll.EQNXTDZ($A$1,$B62,H$5,$B$1) -> 0 | I62: =_xll.EQNXTDZ($A$1,$B62,I$5,$B$1) -> 0 | J62: =_xll.EQNXTDZ($A$1,$B62,J$5,$B$1) -> 0 | ... BV62: =_xll.EQNXTDZ($A$1,$B62,BV$5,$B$1) -> 0
A63: Unsecured Loans | B63: QTRB_UNSECURED_LOANS_NF | C63: =_xll.EQNXTDZ($A$1,$B63,C$5,$B$1) -> 0 | D63: =_xll.EQNXTDZ($A$1,$B63,D$5,$B$1) -> 28501.41 | E63: =_xll.EQNXTDZ($A$1,$B63,E$5,$B$1) -> 0 | F63: =_xll.EQNXTDZ($A$1,$B63,F$5,$B$1) -> 32155.29 | G63: =_xll.EQNXTDZ($A$1,$B63,G$5,$B$1) -> 0 | H63: =_xll.EQNXTDZ($A$1,$B63,H$5,$B$1) -> 40425.56 | I63: =_xll.EQNXTDZ($A$1,$B63,I$5,$B$1) -> 0 | J63: =_xll.EQNXTDZ($A$1,$B63,J$5,$B$1) -> 45258.61 | ... BV63: =_xll.EQNXTDZ($A$1,$B63,BV$5,$B$1) -> 0
A64: Other Long Term Liabilities | B64: QTRB_OTHER_LT_LIABILITIES | C64: =_xll.EQNXTDZ($A$1,$B64,C$5,$B$1) -> 0 | D64: =_xll.EQNXTDZ($A$1,$B64,D$5,$B$1) -> 2589.58 | E64: =_xll.EQNXTDZ($A$1,$B64,E$5,$B$1) -> 0 | F64: =_xll.EQNXTDZ($A$1,$B64,F$5,$B$1) -> 3284.06 | G64: =_xll.EQNXTDZ($A$1,$B64,G$5,$B$1) -> 0 | H64: =_xll.EQNXTDZ($A$1,$B64,H$5,$B$1) -> 2469.35 | I64: =_xll.EQNXTDZ($A$1,$B64,I$5,$B$1) -> 0 | J64: =_xll.EQNXTDZ($A$1,$B64,J$5,$B$1) -> 2596.86 | ... BV64: =_xll.EQNXTDZ($A$1,$B64,BV$5,$B$1) -> 0
A65: Long Term Trade Payables | B65: QTRB_LT_TRADE_PAYABLE | C65: =_xll.EQNXTDZ($A$1,$B65,C$5,$B$1) -> 0 | D65: =_xll.EQNXTDZ($A$1,$B65,D$5,$B$1) -> 0 | E65: =_xll.EQNXTDZ($A$1,$B65,E$5,$B$1) -> 0 | F65: =_xll.EQNXTDZ($A$1,$B65,F$5,$B$1) -> 0 | G65: =_xll.EQNXTDZ($A$1,$B65,G$5,$B$1) -> 0 | H65: =_xll.EQNXTDZ($A$1,$B65,H$5,$B$1) -> 0 | I65: =_xll.EQNXTDZ($A$1,$B65,I$5,$B$1) -> 0 | J65: =_xll.EQNXTDZ($A$1,$B65,J$5,$B$1) -> 0 | ... BV65: =_xll.EQNXTDZ($A$1,$B65,BV$5,$B$1) -> 0
A66: Lont Term Provisions | B66: QTRB_LT_PROVISIONS | C66: =_xll.EQNXTDZ($A$1,$B66,C$5,$B$1) -> 0 | D66: =_xll.EQNXTDZ($A$1,$B66,D$5,$B$1) -> 6602.04 | E66: =_xll.EQNXTDZ($A$1,$B66,E$5,$B$1) -> 0 | F66: =_xll.EQNXTDZ($A$1,$B66,F$5,$B$1) -> 8337.24 | G66: =_xll.EQNXTDZ($A$1,$B66,G$5,$B$1) -> 0 | H66: =_xll.EQNXTDZ($A$1,$B66,H$5,$B$1) -> 13147.36 | I66: =_xll.EQNXTDZ($A$1,$B66,I$5,$B$1) -> 0 | J66: =_xll.EQNXTDZ($A$1,$B66,J$5,$B$1) -> 12190.29 | ... BV66: =_xll.EQNXTDZ($A$1,$B66,BV$5,$B$1) -> 0
... A97: Total Assets | B97: QTRB_TOTAL_APPLICATIONS | C97: =_xll.EQNXTDZ($A$1,$B97,C$5,$B$1) -> 0 | D97: =_xll.EQNXTDZ($A$1,$B97,D$5,$B$1) -> 78299.49 | E97: =_xll.EQNXTDZ($A$1,$B97,E$5,$B$1) -> 0 | F97: =_xll.EQNXTDZ($A$1,$B97,F$5,$B$1) -> 81784.37 | G97: =_xll.EQNXTDZ($A$1,$B97,G$5,$B$1) -> 0 | H97: =_xll.EQNXTDZ($A$1,$B97,H$5,$B$1) -> 111709.14 | I97: =_xll.EQNXTDZ($A$1,$B97,I$5,$B$1) -> 0 | J97: =_xll.EQNXTDZ($A$1,$B97,J$5,$B$1) -> 126069.86 | ... BV97: =_xll.EQNXTDZ($A$1,$B97,BV$5,$B$1) -> 0

Sheet Annual Raw
A1: 100570 | B1: X | C1: 200103 | D1: 200203 | E1: 200303 | F1: 200403 | G1: 200503 | H1: 200603 | I1: 200703 | J1: 200803 | K1: 200903 | L1: 201003 | M1: 201103 | N1: 201203 | O1: 201303 | P1: 201403 | Q1: 201503 | R1: 201603 | S1: 201703 | T1: 201803 | U1: 201903 | V1: 202003 | W1: 202103 | X1: 202203 | Y1: 202303 | Z1: 202403 | AA1: 202503 | AB1: 202603 | AC1: 202703 | AD1: 202803 | AE1: 202903 | AF1: 203003
A3: Field Description | B3: Field Name
A4: Company Name | B4: CD_COMPNAME | C4: =_xll.EQNXTDZ(A1,B4,"L") -> Tata Motors Passenger Vehicles Ltd.
A5: Year End | B5: PL_YEAR_END | C5: =_xll.EQNXTDZ($A$1,$B5,C$1,$B$1) -> 200103 | D5: =_xll.EQNXTDZ($A$1,$B5,D$1,$B$1) -> 200203 | E5: =_xll.EQNXTDZ($A$1,$B5,E$1,$B$1) -> 200303 | F5: =_xll.EQNXTDZ($A$1,$B5,F$1,$B$1) -> 200403 | G5: =_xll.EQNXTDZ($A$1,$B5,G$1,$B$1) -> 200503 | H5: =_xll.EQNXTDZ($A$1,$B5,H$1,$B$1) -> 200603 | I5: =_xll.EQNXTDZ($A$1,$B5,I$1,$B$1) -> 200703 | J5: =_xll.EQNXTDZ($A$1,$B5,J$1,$B$1) -> 200803 | ... AF5: =_xll.EQNXTDZ($A$1,$B5,AF$1,$B$1) -> 0
A6: Sales Turnover | B6: PL_TOTAL_GROSS_SALES | C6: =_xll.EQNXTDZ($A$1,$B6,C$1,$B$1) -> 8077.81 | D6: =_xll.EQNXTDZ($A$1,$B6,D$1,$B$1) -> 9302.29 | E6: =_xll.EQNXTDZ($A$1,$B6,E$1,$B$1) -> 11425.36 | F6: =_xll.EQNXTDZ($A$1,$B6,F$1,$B$1) -> 16284.84 | G6: =_xll.EQNXTDZ($A$1,$B6,G$1,$B$1) -> 22708.23 | H6: =_xll.EQNXTDZ($A$1,$B6,H$1,$B$1) -> 27263.73 | I6: =_xll.EQNXTDZ($A$1,$B6,I$1,$B$1) -> 36922.61 | J6: =_xll.EQNXTDZ($A$1,$B6,J$1,$B$1) -> 40340.79 | ... AF6: =_xll.EQNXTDZ($A$1,$B6,AF$1,$B$1) -> 0
A7: Less: Inter divisional transfers | B7: PL_INTER_DIV_TRF | C7: =_xll.EQNXTDZ($A$1,$B7,C$1,$B$1) -> 0 | D7: =_xll.EQNXTDZ($A$1,$B7,D$1,$B$1) -> 0 | E7: =_xll.EQNXTDZ($A$1,$B7,E$1,$B$1) -> 0 | F7: =_xll.EQNXTDZ($A$1,$B7,F$1,$B$1) -> 0 | G7: =_xll.EQNXTDZ($A$1,$B7,G$1,$B$1) -> 0 | H7: =_xll.EQNXTDZ($A$1,$B7,H$1,$B$1) -> 0 | I7: =_xll.EQNXTDZ($A$1,$B7,I$1,$B$1) -> 0 | J7: =_xll.EQNXTDZ($A$1,$B7,J$1,$B$1) -> 0 | ... AF7: =_xll.EQNXTDZ($A$1,$B7,AF$1,$B$1) -> 0
A8: Less: Sales Returns | B8: PL_SALES_RETURN | C8: =_xll.EQNXTDZ($A$1,$B8,C$1,$B$1) -> 0 | D8: =_xll.EQNXTDZ($A$1,$B8,D$1,$B$1) -> 0 | E8: =_xll.EQNXTDZ($A$1,$B8,E$1,$B$1) -> 0 | F8: =_xll.EQNXTDZ($A$1,$B8,F$1,$B$1) -> 0 | G8: =_xll.EQNXTDZ($A$1,$B8,G$1,$B$1) -> 0 | H8: =_xll.EQNXTDZ($A$1,$B8,H$1,$B$1) -> 0 | I8: =_xll.EQNXTDZ($A$1,$B8,I$1,$B$1) -> 0 | J8: =_xll.EQNXTDZ($A$1,$B8,J$1,$B$1) -> 0 | ... AF8: =_xll.EQNXTDZ($A$1,$B8,AF$1,$B$1) -> 0
A9: Less: Excise | B9: PL_EXCISE | C9: =_xll.EQNXTDZ($A$1,$B9,C$1,$B$1) -> 1292.24 | D9: =_xll.EQNXTDZ($A$1,$B9,D$1,$B$1) -> 1390.47 | E9: =_xll.EQNXTDZ($A$1,$B9,E$1,$B$1) -> 1816.72 | F9: =_xll.EQNXTDZ($A$1,$B9,F$1,$B$1) -> 2360.12 | G9: =_xll.EQNXTDZ($A$1,$B9,G$1,$B$1) -> 3175.39 | H9: =_xll.EQNXTDZ($A$1,$B9,H$1,$B$1) -> 3494.28 | I9: =_xll.EQNXTDZ($A$1,$B9,I$1,$B$1) -> 4561.41 | J9: =_xll.EQNXTDZ($A$1,$B9,J$1,$B$1) -> 4680.72 | ... AF9: =_xll.EQNXTDZ($A$1,$B9,AF$1,$B$1) -> 0
A10: Net Sales | B10: PL_NET_SALES | C10: =_xll.EQNXTDZ($A$1,$B10,C$1,$B$1) -> 6785.57 | D10: =_xll.EQNXTDZ($A$1,$B10,D$1,$B$1) -> 7911.82 | E10: =_xll.EQNXTDZ($A$1,$B10,E$1,$B$1) -> 9608.64 | F10: =_xll.EQNXTDZ($A$1,$B10,F$1,$B$1) -> 13924.72 | G10: =_xll.EQNXTDZ($A$1,$B10,G$1,$B$1) -> 19532.84 | H10: =_xll.EQNXTDZ($A$1,$B10,H$1,$B$1) -> 23769.45 | I10: =_xll.EQNXTDZ($A$1,$B10,I$1,$B$1) -> 32361.2 | J10: =_xll.EQNXTDZ($A$1,$B10,J$1,$B$1) -> 35660.07 | ... AF10: =_xll.EQNXTDZ($A$1,$B10,AF$1,$B$1) -> 0
A11: Increase/Decrease in Stock | B11: PL_INC_DEC_INVENTORY | C11: =_xll.EQNXTDZ($A$1,$B11,C$1,$B$1) -> -56.67 | D11: =_xll.EQNXTDZ($A$1,$B11,D$1,$B$1) -> 97.92 | E11: =_xll.EQNXTDZ($A$1,$B11,E$1,$B$1) -> -103.48 | F11: =_xll.EQNXTDZ($A$1,$B11,F$1,$B$1) -> 75.33 | G11: =_xll.EQNXTDZ($A$1,$B11,G$1,$B$1) -> -231.75 | H11: =_xll.EQNXTDZ($A$1,$B11,H$1,$B$1) -> -207.62 | I11: =_xll.EQNXTDZ($A$1,$B11,I$1,$B$1) -> -333.76 | J11: =_xll.EQNXTDZ($A$1,$B11,J$1,$B$1) -> -13.49 | ... AF11: =_xll.EQNXTDZ($A$1,$B11,AF$1,$B$1) -> 0
A12: Raw Material Consumed | B12: PL_RAW_MATRS_CONSUMED | C12: =_xll.EQNXTDZ($A$1,$B12,C$1,$B$1) -> 4728.07 | D12: =_xll.EQNXTDZ($A$1,$B12,D$1,$B$1) -> 4915.76 | E12: =_xll.EQNXTDZ($A$1,$B12,E$1,$B$1) -> 6018.45 | F12: =_xll.EQNXTDZ($A$1,$B12,F$1,$B$1) -> 8882.95 | G12: =_xll.EQNXTDZ($A$1,$B12,G$1,$B$1) -> 13504.17 | H12: =_xll.EQNXTDZ($A$1,$B12,H$1,$B$1) -> 16258.62 | I12: =_xll.EQNXTDZ($A$1,$B12,I$1,$B$1) -> 22372.59 | J12: =_xll.EQNXTDZ($A$1,$B12,J$1,$B$1) -> 24375.84 | ... AF12: =_xll.EQNXTDZ($A$1,$B12,AF$1,$B$1) -> 0
A13: Power & Fuel Cost | B13: PL_POWER_FUEL | C13: =_xll.EQNXTDZ($A$1,$B13,C$1,$B$1) -> 185.18 | D13: =_xll.EQNXTDZ($A$1,$B13,D$1,$B$1) -> 200.7 | E13: =_xll.EQNXTDZ($A$1,$B13,E$1,$B$1) -> 210.52 | F13: =_xll.EQNXTDZ($A$1,$B13,F$1,$B$1) -> 235.34 | G13: =_xll.EQNXTDZ($A$1,$B13,G$1,$B$1) -> 267.69 | H13: =_xll.EQNXTDZ($A$1,$B13,H$1,$B$1) -> 291.45 | I13: =_xll.EQNXTDZ($A$1,$B13,I$1,$B$1) -> 368.53 | J13: =_xll.EQNXTDZ($A$1,$B13,J$1,$B$1) -> 377.72 | ... AF13: =_xll.EQNXTDZ($A$1,$B13,AF$1,$B$1) -> 0
A14: Employee Cost | B14: PL_EMPLOYEES | C14: =_xll.EQNXTDZ($A$1,$B14,C$1,$B$1) -> 624.26 | D14: =_xll.EQNXTDZ($A$1,$B14,D$1,$B$1) -> 899.67 | E14: =_xll.EQNXTDZ($A$1,$B14,E$1,$B$1) -> 916.67 | F14: =_xll.EQNXTDZ($A$1,$B14,F$1,$B$1) -> 1084.33 | G14: =_xll.EQNXTDZ($A$1,$B14,G$1,$B$1) -> 1424.35 | H14: =_xll.EQNXTDZ($A$1,$B14,H$1,$B$1) -> 1777.43 | I14: =_xll.EQNXTDZ($A$1,$B14,I$1,$B$1) -> 2408.9 | J14: =_xll.EQNXTDZ($A$1,$B14,J$1,$B$1) -> 2735 | ... AF14: =_xll.EQNXTDZ($A$1,$B14,AF$1,$B$1) -> 0
A15: Operating & Manufacturing Expenses | B15: PL_GEN_OTHER_MFG_EXPS | C15: =_xll.EQNXTDZ($A$1,$B15,C$1,$B$1) -> 458.8 | D15: =_xll.EQNXTDZ($A$1,$B15,D$1,$B$1) -> 421.19 | E15: =_xll.EQNXTDZ($A$1,$B15,E$1,$B$1) -> 515.14 | F15: =_xll.EQNXTDZ($A$1,$B15,F$1,$B$1) -> 739.24 | G15: =_xll.EQNXTDZ($A$1,$B15,G$1,$B$1) -> 1071.26 | H15: =_xll.EQNXTDZ($A$1,$B15,H$1,$B$1) -> 1330.29 | I15: =_xll.EQNXTDZ($A$1,$B15,I$1,$B$1) -> 1762.78 | J15: =_xll.EQNXTDZ($A$1,$B15,J$1,$B$1) -> 1751.83 | ... AF15: =_xll.EQNXTDZ($A$1,$B15,AF$1,$B$1) -> 0
A16: Cost of Software development | B16: PL_COST_SW | C16: =_xll.EQNXTDZ($A$1,$B16,C$1,$B$1) -> 0 | D16: =_xll.EQNXTDZ($A$1,$B16,D$1,$B$1) -> 0 | E16: =_xll.EQNXTDZ($A$1,$B16,E$1,$B$1) -> 0 | F16: =_xll.EQNXTDZ($A$1,$B16,F$1,$B$1) -> 0 | G16: =_xll.EQNXTDZ($A$1,$B16,G$1,$B$1) -> 0 | H16: =_xll.EQNXTDZ($A$1,$B16,H$1,$B$1) -> 0 | I16: =_xll.EQNXTDZ($A$1,$B16,I$1,$B$1) -> 0 | J16: =_xll.EQNXTDZ($A$1,$B16,J$1,$B$1) -> 0 | ... AF16: =_xll.EQNXTDZ($A$1,$B16,AF$1,$B$1) -> 0
... A36: Profit After Tax from Discontinued Operations | B36: PL_PAT_DIS_OP | C36: =_xll.EQNXTDZ($A$1,$B36,C$1,$B$1) -> 0 | D36: =_xll.EQNXTDZ($A$1,$B36,D$1,$B$1) -> 0 | E36: =_xll.EQNXTDZ($A$1,$B36,E$1,$B$1) -> 0 | F36: =_xll.EQNXTDZ($A$1,$B36,F$1,$B$1) -> 0 | G36: =_xll.EQNXTDZ($A$1,$B36,G$1,$B$1) -> 0 | H36: =_xll.EQNXTDZ($A$1,$B36,H$1,$B$1) -> 0 | I36: =_xll.EQNXTDZ($A$1,$B36,I$1,$B$1) -> 0 | J36: =_xll.EQNXTDZ($A$1,$B36,J$1,$B$1) -> 0 | ... AF36: =_xll.EQNXTDZ($A$1,$B36,AF$1,$B$1) -> 0
A39: Field Description | B39: Field Name
A40: Year End | B40: BS_YEAR_END | C40: =_xll.EQNXTDZ($A$1,$B40,C$1,$B$1) -> 200103 | D40: =_xll.EQNXTDZ($A$1,$B40,D$1,$B$1) -> 200203 | E40: =_xll.EQNXTDZ($A$1,$B40,E$1,$B$1) -> 200303 | F40: =_xll.EQNXTDZ($A$1,$B40,F$1,$B$1) -> 200403 | G40: =_xll.EQNXTDZ($A$1,$B40,G$1,$B$1) -> 200503 | H40: =_xll.EQNXTDZ($A$1,$B40,H$1,$B$1) -> 200603 | I40: =_xll.EQNXTDZ($A$1,$B40,I$1,$B$1) -> 200703 | J40: =_xll.EQNXTDZ($A$1,$B40,J$1,$B$1) -> 200803 | ... AF40: =_xll.EQNXTDZ($A$1,$B40,AF$1,$B$1) -> 0
A41: Share Capital | B41: BS_SHARE_CAPITAL | C41: =_xll.EQNXTDZ($A$1,$B41,C$1,$B$1) -> 255.9 | D41: =_xll.EQNXTDZ($A$1,$B41,D$1,$B$1) -> 319.82 | E41: =_xll.EQNXTDZ($A$1,$B41,E$1,$B$1) -> 319.83 | F41: =_xll.EQNXTDZ($A$1,$B41,F$1,$B$1) -> 353 | G41: =_xll.EQNXTDZ($A$1,$B41,G$1,$B$1) -> 361.79 | H41: =_xll.EQNXTDZ($A$1,$B41,H$1,$B$1) -> 382.87 | I41: =_xll.EQNXTDZ($A$1,$B41,I$1,$B$1) -> 385.41 | J41: =_xll.EQNXTDZ($A$1,$B41,J$1,$B$1) -> 385.54 | ... AF41: =_xll.EQNXTDZ($A$1,$B41,AF$1,$B$1) -> 0
A42: Share Warrants & Outstandings | B42: BS_SHAREWROUTST | C42: =_xll.EQNXTDZ($A$1,$B42,C$1,$B$1) -> 0 | D42: =_xll.EQNXTDZ($A$1,$B42,D$1,$B$1) -> 0 | E42: =_xll.EQNXTDZ($A$1,$B42,E$1,$B$1) -> 0 | F42: =_xll.EQNXTDZ($A$1,$B42,F$1,$B$1) -> 3.83 | G42: =_xll.EQNXTDZ($A$1,$B42,G$1,$B$1) -> 0 | H42: =_xll.EQNXTDZ($A$1,$B42,H$1,$B$1) -> 0 | I42: =_xll.EQNXTDZ($A$1,$B42,I$1,$B$1) -> 0 | J42: =_xll.EQNXTDZ($A$1,$B42,J$1,$B$1) -> 0 | ... AF42: =_xll.EQNXTDZ($A$1,$B42,AF$1,$B$1) -> 0
A43: Total Reserves | B43: BS_RESERVE | C43: =_xll.EQNXTDZ($A$1,$B43,C$1,$B$1) -> 2997.88 | D43: =_xll.EQNXTDZ($A$1,$B43,D$1,$B$1) -> 1836.17 | E43: =_xll.EQNXTDZ($A$1,$B43,E$1,$B$1) -> 1900.18 | F43: =_xll.EQNXTDZ($A$1,$B43,F$1,$B$1) -> 3298.84 | G43: =_xll.EQNXTDZ($A$1,$B43,G$1,$B$1) -> 4035.37 | H43: =_xll.EQNXTDZ($A$1,$B43,H$1,$B$1) -> 5748.6 | I43: =_xll.EQNXTDZ($A$1,$B43,I$1,$B$1) -> 7336.26 | J43: =_xll.EQNXTDZ($A$1,$B43,J$1,$B$1) -> 8311.98 | ... AF43: =_xll.EQNXTDZ($A$1,$B43,AF$1,$B$1) -> 0
A44: Shareholder's Funds | B44: BS_SHAREHODERS_FUNDS | C44: =_xll.EQNXTDZ($A$1,$B44,C$1,$B$1) -> 3253.78 | D44: =_xll.EQNXTDZ($A$1,$B44,D$1,$B$1) -> 2155.99 | E44: =_xll.EQNXTDZ($A$1,$B44,E$1,$B$1) -> 2220.01 | F44: =_xll.EQNXTDZ($A$1,$B44,F$1,$B$1) -> 3655.67 | G44: =_xll.EQNXTDZ($A$1,$B44,G$1,$B$1) -> 4397.16 | H44: =_xll.EQNXTDZ($A$1,$B44,H$1,$B$1) -> 6131.47 | I44: =_xll.EQNXTDZ($A$1,$B44,I$1,$B$1) -> 7721.67 | J44: =_xll.EQNXTDZ($A$1,$B44,J$1,$B$1) -> 8697.52 | ... AF44: =_xll.EQNXTDZ($A$1,$B44,AF$1,$B$1) -> 0
A45: Minority Interest | B45: BS_MINORITY_INTEREST | C45: =_xll.EQNXTDZ($A$1,$B45,C$1,$B$1) -> 0 | D45: =_xll.EQNXTDZ($A$1,$B45,D$1,$B$1) -> 40.24 | E45: =_xll.EQNXTDZ($A$1,$B45,E$1,$B$1) -> 41.13 | F45: =_xll.EQNXTDZ($A$1,$B45,F$1,$B$1) -> 46.26 | G45: =_xll.EQNXTDZ($A$1,$B45,G$1,$B$1) -> 63.05 | H45: =_xll.EQNXTDZ($A$1,$B45,H$1,$B$1) -> 173.93 | I45: =_xll.EQNXTDZ($A$1,$B45,I$1,$B$1) -> 249.96 | J45: =_xll.EQNXTDZ($A$1,$B45,J$1,$B$1) -> 468.31 | ... AF45: =_xll.EQNXTDZ($A$1,$B45,AF$1,$B$1) -> 0
A46: Long-Term Borrowings | B46: BS_LTRM_BORROWING | C46: =_xll.EQNXTDZ($A$1,$B46,C$1,$B$1) -> 0 | D46: =_xll.EQNXTDZ($A$1,$B46,D$1,$B$1) -> 0 | E46: =_xll.EQNXTDZ($A$1,$B46,E$1,$B$1) -> 0 | F46: =_xll.EQNXTDZ($A$1,$B46,F$1,$B$1) -> 0 | G46: =_xll.EQNXTDZ($A$1,$B46,G$1,$B$1) -> 0 | H46: =_xll.EQNXTDZ($A$1,$B46,H$1,$B$1) -> 0 | I46: =_xll.EQNXTDZ($A$1,$B46,I$1,$B$1) -> 0 | J46: =_xll.EQNXTDZ($A$1,$B46,J$1,$B$1) -> 0 | ... AF46: =_xll.EQNXTDZ($A$1,$B46,AF$1,$B$1) -> 0
A47: Secured Loans | B47: BS_SECURED_LOANS | C47: =_xll.EQNXTDZ($A$1,$B47,C$1,$B$1) -> 1813.33 | D47: =_xll.EQNXTDZ($A$1,$B47,D$1,$B$1) -> 1771.25 | E47: =_xll.EQNXTDZ($A$1,$B47,E$1,$B$1) -> 1356.1 | F47: =_xll.EQNXTDZ($A$1,$B47,F$1,$B$1) -> 1148.14 | G47: =_xll.EQNXTDZ($A$1,$B47,G$1,$B$1) -> 576.7 | H47: =_xll.EQNXTDZ($A$1,$B47,H$1,$B$1) -> 881.62 | I47: =_xll.EQNXTDZ($A$1,$B47,I$1,$B$1) -> 4462.65 | J47: =_xll.EQNXTDZ($A$1,$B47,J$1,$B$1) -> 6011.87 | ... AF47: =_xll.EQNXTDZ($A$1,$B47,AF$1,$B$1) -> 0
A48: Unsecured Loans | B48: BS_UNSECURED_LOANS_NF | C48: =_xll.EQNXTDZ($A$1,$B48,C$1,$B$1) -> 1185.55 | D48: =_xll.EQNXTDZ($A$1,$B48,D$1,$B$1) -> 1049.06 | E48: =_xll.EQNXTDZ($A$1,$B48,E$1,$B$1) -> 433.55 | F48: =_xll.EQNXTDZ($A$1,$B48,F$1,$B$1) -> 550.28 | G48: =_xll.EQNXTDZ($A$1,$B48,G$1,$B$1) -> 2137.5 | H48: =_xll.EQNXTDZ($A$1,$B48,H$1,$B$1) -> 2497.52 | I48: =_xll.EQNXTDZ($A$1,$B48,I$1,$B$1) -> 2839.25 | J48: =_xll.EQNXTDZ($A$1,$B48,J$1,$B$1) -> 5573 | ... AF48: =_xll.EQNXTDZ($A$1,$B48,AF$1,$B$1) -> 0
A49: Deferred Tax Assets / Liabilities | B49: BS_NET_DEF_TAX_NF | C49: =_xll.EQNXTDZ($A$1,$B49,C$1,$B$1) -> 0 | D49: =_xll.EQNXTDZ($A$1,$B49,D$1,$B$1) -> -102 | E49: =_xll.EQNXTDZ($A$1,$B49,E$1,$B$1) -> 100.98 | F49: =_xll.EQNXTDZ($A$1,$B49,F$1,$B$1) -> 533.7 | G49: =_xll.EQNXTDZ($A$1,$B49,G$1,$B$1) -> 620.54 | H49: =_xll.EQNXTDZ($A$1,$B49,H$1,$B$1) -> 676.79 | I49: =_xll.EQNXTDZ($A$1,$B49,I$1,$B$1) -> 817.27 | J49: =_xll.EQNXTDZ($A$1,$B49,J$1,$B$1) -> 974.45 | ... AF49: =_xll.EQNXTDZ($A$1,$B49,AF$1,$B$1) -> 0
A50: Other Long Term Liabilities | B50: BS_OTH_LT_LIAB | C50: =_xll.EQNXTDZ($A$1,$B50,C$1,$B$1) -> 0 | D50: =_xll.EQNXTDZ($A$1,$B50,D$1,$B$1) -> 0 | E50: =_xll.EQNXTDZ($A$1,$B50,E$1,$B$1) -> 0 | F50: =_xll.EQNXTDZ($A$1,$B50,F$1,$B$1) -> 0 | G50: =_xll.EQNXTDZ($A$1,$B50,G$1,$B$1) -> 0 | H50: =_xll.EQNXTDZ($A$1,$B50,H$1,$B$1) -> 0 | I50: =_xll.EQNXTDZ($A$1,$B50,I$1,$B$1) -> 0 | J50: =_xll.EQNXTDZ($A$1,$B50,J$1,$B$1) -> 0 | ... AF50: =_xll.EQNXTDZ($A$1,$B50,AF$1,$B$1) -> 0
A51: Long Term Trade Payables | B51: BS_LT_TRADE_PAYABLES | C51: =_xll.EQNXTDZ($A$1,$B51,C$1,$B$1) -> 0 | D51: =_xll.EQNXTDZ($A$1,$B51,D$1,$B$1) -> 0 | E51: =_xll.EQNXTDZ($A$1,$B51,E$1,$B$1) -> 0 | F51: =_xll.EQNXTDZ($A$1,$B51,F$1,$B$1) -> 0 | G51: =_xll.EQNXTDZ($A$1,$B51,G$1,$B$1) -> 0 | H51: =_xll.EQNXTDZ($A$1,$B51,H$1,$B$1) -> 0 | I51: =_xll.EQNXTDZ($A$1,$B51,I$1,$B$1) -> 0 | J51: =_xll.EQNXTDZ($A$1,$B51,J$1,$B$1) -> 0 | ... AF51: =_xll.EQNXTDZ($A$1,$B51,AF$1,$B$1) -> 0
... A99: Estimated Capital Contracts Remaining | B99: BS_ESTIMATED_CAPITAL_CONTRACT | C99: =_xll.EQNXTDZ($A$1,$B99,C$1,$B$1) -> 56.33 | D99: =_xll.EQNXTDZ($A$1,$B99,D$1,$B$1) -> 0 | E99: =_xll.EQNXTDZ($A$1,$B99,E$1,$B$1) -> 0 | F99: =_xll.EQNXTDZ($A$1,$B99,F$1,$B$1) -> 0 | G99: =_xll.EQNXTDZ($A$1,$B99,G$1,$B$1) -> 558.32 | H99: =_xll.EQNXTDZ($A$1,$B99,H$1,$B$1) -> 1182.04 | I99: =_xll.EQNXTDZ($A$1,$B99,I$1,$B$1) -> 3173.34 | J99: =_xll.EQNXTDZ($A$1,$B99,J$1,$B$1) -> 4045.52 | ... AF99: =_xll.EQNXTDZ($A$1,$B99,AF$1,$B$1) -> 0
A103: Field Description | B103: Field Name
A104: Equity Paid Up | B104: BS_EQUITY_PAIDUP | C104: =_xll.EQNXTDZ($A$1,$B104,C$1,$B$1) -> 255.85 | D104: =_xll.EQNXTDZ($A$1,$B104,D$1,$B$1) -> 319.77 | E104: =_xll.EQNXTDZ($A$1,$B104,E$1,$B$1) -> 319.78 | F104: =_xll.EQNXTDZ($A$1,$B104,F$1,$B$1) -> 352.95 | G104: =_xll.EQNXTDZ($A$1,$B104,G$1,$B$1) -> 361.74 | H104: =_xll.EQNXTDZ($A$1,$B104,H$1,$B$1) -> 382.82 | I104: =_xll.EQNXTDZ($A$1,$B104,I$1,$B$1) -> 385.36 | J104: =_xll.EQNXTDZ($A$1,$B104,J$1,$B$1) -> 385.49 | ... AF104: =_xll.EQNXTDZ($A$1,$B104,AF$1,$B$1) -> 0
A105: Face Value | B105: BS_FACE_VALUE | C105: =_xll.EQNXTDZ($A$1,$B105,C$1,$B$1) -> 10 | D105: =_xll.EQNXTDZ($A$1,$B105,D$1,$B$1) -> 10 | E105: =_xll.EQNXTDZ($A$1,$B105,E$1,$B$1) -> 10 | F105: =_xll.EQNXTDZ($A$1,$B105,F$1,$B$1) -> 10 | G105: =_xll.EQNXTDZ($A$1,$B105,G$1,$B$1) -> 10 | H105: =_xll.EQNXTDZ($A$1,$B105,H$1,$B$1) -> 10 | I105: =_xll.EQNXTDZ($A$1,$B105,I$1,$B$1) -> 10 | J105: =_xll.EQNXTDZ($A$1,$B105,J$1,$B$1) -> 10 | ... AF105: =_xll.EQNXTDZ($A$1,$B105,AF$1,$B$1) -> 0
A106: Close Price (Unit Curr.) | B106: FH_YEAR_PRICE | C106: =_xll.EQNXTDZ($A$1,$B106,C$1,$B$1) -> 12.465899 | D106: =_xll.EQNXTDZ($A$1,$B106,D$1,$B$1) -> 24.194 | E106: =_xll.EQNXTDZ($A$1,$B106,E$1,$B$1) -> 29.828088 | F106: =_xll.EQNXTDZ($A$1,$B106,F$1,$B$1) -> 93.077432 | G106: =_xll.EQNXTDZ($A$1,$B106,G$1,$B$1) -> 79.327575 | H106: =_xll.EQNXTDZ($A$1,$B106,H$1,$B$1) -> 178.7194 | I106: =_xll.EQNXTDZ($A$1,$B106,I$1,$B$1) -> 139.46284 | J106: =_xll.EQNXTDZ($A$1,$B106,J$1,$B$1) -> 119.47524 | ... AF106: =_xll.EQNXTDZ($A$1,$B106,AF$1,$B$1) -> 0
A107: High Price (Unit Curr.) | B107: FH_HIGH | C107: =_xll.EQNXTDZ($A$1,$B107,C$1,$B$1) -> 29.531053 | D107: =_xll.EQNXTDZ($A$1,$B107,D$1,$B$1) -> 29.368162 | E107: =_xll.EQNXTDZ($A$1,$B107,E$1,$B$1) -> 33.229621 | F107: =_xll.EQNXTDZ($A$1,$B107,F$1,$B$1) -> 109.23232 | G107: =_xll.EQNXTDZ($A$1,$B107,G$1,$B$1) -> 100.99198 | H107: =_xll.EQNXTDZ($A$1,$B107,H$1,$B$1) -> 180.94237 | I107: =_xll.EQNXTDZ($A$1,$B107,I$1,$B$1) -> 191.06074 | J107: =_xll.EQNXTDZ($A$1,$B107,J$1,$B$1) -> 160.97394 | ... AF107: =_xll.EQNXTDZ($A$1,$B107,AF$1,$B$1) -> 0
A108: Low Price (Unit Curr.) | B108: FH_LOW | C108: =_xll.EQNXTDZ($A$1,$B108,C$1,$B$1) -> 12.053882 | D108: =_xll.EQNXTDZ($A$1,$B108,D$1,$B$1) -> 11.114867 | E108: =_xll.EQNXTDZ($A$1,$B108,E$1,$B$1) -> 22.469279 | F108: =_xll.EQNXTDZ($A$1,$B108,F$1,$B$1) -> 28.467475 | G108: =_xll.EQNXTDZ($A$1,$B108,G$1,$B$1) -> 63.316417 | H108: =_xll.EQNXTDZ($A$1,$B108,H$1,$B$1) -> 77.085438 | I108: =_xll.EQNXTDZ($A$1,$B108,I$1,$B$1) -> 124.65899 | J108: =_xll.EQNXTDZ($A$1,$B108,J$1,$B$1) -> 102.52507 | ... AF108: =_xll.EQNXTDZ($A$1,$B108,AF$1,$B$1) -> 0
A109: Market Capitalization | B109: FH_MCAP | C109: =_xll.EQNXTDZ($A$1,$B109,C$1,$B$1) -> 1664.3042 | D109: =_xll.EQNXTDZ($A$1,$B109,D$1,$B$1) -> 4037.0963 | E109: =_xll.EQNXTDZ($A$1,$B109,E$1,$B$1) -> 4977.3757 | F109: =_xll.EQNXTDZ($A$1,$B109,F$1,$B$1) -> 17142.782 | G109: =_xll.EQNXTDZ($A$1,$B109,G$1,$B$1) -> 14974.227 | H109: =_xll.EQNXTDZ($A$1,$B109,H$1,$B$1) -> 35701.793 | I109: =_xll.EQNXTDZ($A$1,$B109,I$1,$B$1) -> 28044.574 | J109: =_xll.EQNXTDZ($A$1,$B109,J$1,$B$1) -> 24033.374 | ... AF109: =_xll.EQNXTDZ($A$1,$B109,AF$1,$B$1) -> 0
A110: Adj DPS(Rs) | B110: FR_ADJ_DPS | C110: =_xll.EQNXTDZ($A$1,$B110,C$1,$B$1) -> 0 | D110: =_xll.EQNXTDZ($A$1,$B110,D$1,$B$1) -> 0 | E110: =_xll.EQNXTDZ($A$1,$B110,E$1,$B$1) -> 0.76628352 | F110: =_xll.EQNXTDZ($A$1,$B110,F$1,$B$1) -> 1.532567 | G110: =_xll.EQNXTDZ($A$1,$B110,G$1,$B$1) -> 2.394636 | H110: =_xll.EQNXTDZ($A$1,$B110,H$1,$B$1) -> 2.4904215 | I110: =_xll.EQNXTDZ($A$1,$B110,I$1,$B$1) -> 2.8735632 | J110: =_xll.EQNXTDZ($A$1,$B110,J$1,$B$1) -> 2.8735632 | ... AF110: =_xll.EQNXTDZ($A$1,$B110,AF$1,$B$1) -> 0
A111: Date End | B111: SHP_DATE_END | C111: =_xll.EQNXTDZ($A$1,$B111,C$5) -> 200103 | D111: =_xll.EQNXTDZ($A$1,$B111,D$5) -> 200203 | E111: =_xll.EQNXTDZ($A$1,$B111,E$5) -> 200303 | F111: =_xll.EQNXTDZ($A$1,$B111,F$5) -> 200403 | G111: =_xll.EQNXTDZ($A$1,$B111,G$5) -> 200503 | H111: =_xll.EQNXTDZ($A$1,$B111,H$5) -> 200603 | I111: =_xll.EQNXTDZ($A$1,$B111,I$5) -> 200703 | J111: =_xll.EQNXTDZ($A$1,$B111,J$5) -> 200803 | ... AF111: =_xll.EQNXTDZ($A$1,$B111,AF$5) -> 0
A112: Total of Promoter and Promoter Group | B112: SHP_TPFTOTALPROMOTER | C112: =_xll.EQNXTDZ($A$1,$B112,C$5) -> 25.35 | D112: =_xll.EQNXTDZ($A$1,$B112,D$5) -> 32.21 | E112: =_xll.EQNXTDZ($A$1,$B112,E$5) -> 32.21 | F112: =_xll.EQNXTDZ($A$1,$B112,F$5) -> 33.35 | G112: =_xll.EQNXTDZ($A$1,$B112,G$5) -> 32.35 | H112: =_xll.EQNXTDZ($A$1,$B112,H$5) -> 33.65 | I112: =_xll.EQNXTDZ($A$1,$B112,I$5) -> 33.43 | J112: =_xll.EQNXTDZ($A$1,$B112,J$5) -> 33.42 | ... AF112: =_xll.EQNXTDZ($A$1,$B112,AF$5) -> 0
A113: Total of Promoter and Promoter Group Pledged | B113: SHP_PSHFTOTALPROMOTER | C113: =_xll.EQNXTDZ($A$1,$B113,C$5) -> 0 | D113: =_xll.EQNXTDZ($A$1,$B113,D$5) -> 0 | E113: =_xll.EQNXTDZ($A$1,$B113,E$5) -> 0 | F113: =_xll.EQNXTDZ($A$1,$B113,F$5) -> 0 | G113: =_xll.EQNXTDZ($A$1,$B113,G$5) -> 0 | H113: =_xll.EQNXTDZ($A$1,$B113,H$5) -> 0 | I113: =_xll.EQNXTDZ($A$1,$B113,I$5) -> 0 | J113: =_xll.EQNXTDZ($A$1,$B113,J$5) -> 0 | ... AF113: =_xll.EQNXTDZ($A$1,$B113,AF$5) -> 0

Sheet QTR Share Price
A1: ='QTR Raw'!A1 -> 100570 | C1: 201206 | D1: 201207 | E1: 201208 | F1: 201209 | G1: 201210 | H1: 201211 | I1: 201212 | J1: 201301 | K1: 201302 | L1: 201303 | M1: 201304 | N1: 201305 | O1: 201306 | P1: 201307 | Q1: 201308 | R1: 201309 | S1: 201310 | T1: 201311 | U1: 201312 | V1: 201401 | W1: 201402 | X1: 201403 | Y1: 201404 | Z1: 201405 | AA1: 201406 | AB1: 201407 | AC1: 201408 | AD1: 201409 | AE1: 201410 | AF1: 201411 | AG1: 201412 | AH1: 201501 | AI1: 201502 | AJ1: 201503 | AK1: 201504 | AL1: 201505 | AM1: 201506 | AN1: 201507 | AO1: 201508 | AP1: 201509 | AQ1: 201510 | AR1: 201511 | AS1: 201512 | AT1: 201601 | AU1: 201602 | AV1: 201603 | AW1: 201604 | AX1: 201605 | AY1: 201606 | AZ1: 201607 | BA1: 201608 | BB1: 201609 | BC1: 201610 | BD1: 201611 | BE1: 201612 | BF1: 201701 | BG1: 201702 | BH1: 201703 | BI1: 201704 | BJ1: 201705 | BK1: 201706 | BL1: 201707 | BM1: 201708 | BN1: 201709 | BO1: 201710 | BP1: 201711 | BQ1: 201712 | BR1: 201801 | BS1: 201802 | BT1: 201803 | BU1: 201804 | BV1: 201805 | BW1: 201806 | BX1: 201807 | BY1: 201808 | BZ1: 201809 | CA1: 201810 | CB1: 201811 | CC1: 201812 | CD1: 201901 | CE1: 201902 | CF1: 201903 | CG1: 201904 | CH1: 201905 | CI1: 201906 | CJ1: 201907 | CK1: 201908 | CL1: 201909 | CM1: 201910 | CN1: 201911 | CO1: 201912 | CP1: 202001 | CQ1: 202002 | CR1: 202003 | CS1: 202004 | CT1: 202005 | CU1: 202006 | CV1: 202007 | CW1: 202008 | CX1: 202009 | CY1: 202010 | CZ1: 202011 | DA1: 202012 | DB1: 202101 | DC1: 202102 | DD1: 202103 | DE1: 202104 | DF1: 202105 | DG1: 202106 | DH1: 202107 | DI1: 202108 | DJ1: 202109 | DK1: 202110 | DL1: 202111 | DM1: 202112 | DN1: 202201 | DO1: 202202 | DP1: 202203 | DQ1: 202204 | DR1: 202205 | DS1: 202206 | DT1: 202207 | DU1: 202208 | DV1: 202209 | DW1: 202210 | DX1: 202211 | DY1: 202212 | DZ1: 202301 | EA1: 202302 | EB1: 202303 | EC1: 202304 | ED1: 202305 | EE1: 202306 | EF1: 202307 | EG1: 202308 | EH1: 202309 | EI1: 202310 | EJ1: 202311 | EK1: 202312 | EL1: 202401 | EM1: 202402 | EN1: 202403 | EO1: 202404 | EP1: 202405 | EQ1: 202406 | ER1: 202407 | ES1: 202408 | ET1: 202409 | EU1: 202410 | EV1: 202411 | EW1: 202412 | EX1: 202501 | EY1: 202502 | EZ1: 202503 | FA1: 202504 | FB1: 202505 | FC1: 202506 | FD1: 202507 | FE1: 202508 | FF1: 202509 | FG1: 202510 | FH1: 202511 | FI1: 202512 | FJ1: 202601 | FK1: 202602 | FL1: 202603 | FM1: 202604 | FN1: 202605 | FO1: 202606 | FP1: 202607 | FQ1: 202608 | FR1: 202609 | FS1: 202610 | FT1: 202611 | FU1: 202612 | FV1: 202701 | FW1: 202702 | FX1: 202703 | FY1: 202704 | FZ1: 202705 | GA1: 202706 | GB1: 202707 | GC1: 202708 | GD1: 202709 | GE1: 202710 | GF1: 202711 | GG1: 202712 | GH1: 202801 | GI1: 202802 | GJ1: 202803 | GK1: 202804 | GL1: 202805 | GM1: 202806 | GN1: 202807 | GO1: 202808 | GP1: 202809 | GQ1: 202810 | GR1: 202811 | GS1: 202812 | GT1: 202901 | GU1: 202902 | GV1: 202903 | GW1: 202904 | GX1: 202905 | GY1: 202906 | GZ1: 202907 | HA1: 202908 | HB1: 202909 | HC1: 202910 | HD1: 202911 | HE1: 202912 | HF1: 203001 | HG1: 203002 | HH1: 203003 | HM1: 201206 | HN1: 201207 | HO1: 201208 | HP1: 201209 | HQ1: 201212 | HR1: 201303 | HS1: 201306 | HT1: 201309 | HU1: 201312 | HV1: 201403 | HW1: 201406 | HX1: 201409 | HY1: 201412 | HZ1: 201503 | IA1: 201506 | IB1: 201509 | IC1: 201512 | ID1: 201603 | IE1: 201606 | IF1: 201609 | IG1: 201612 | IH1: 201703 | II1: 201706 | IJ1: 201709 | IK1: 201712 | IL1: 201803 | IM1: 201806 | IN1: 201809 | IO1: 201812 | IP1: 201903 | IQ1: 201906 | IR1: 201909 | IS1: 201912 | IT1: 202003 | IU1: 202006 | IV1: 202009 | IW1: 202012 | IX1: 202103 | IY1: 202106 | IZ1: 202109 | JA1: 202112 | JB1: 202203 | JC1: 202206 | JD1: 202209 | JE1: 202212 | JF1: 202303 | JG1: 202306 | JH1: 202309 | JI1: 202312 | JJ1: 202403 | JK1: 202406 | JL1: 202409 | JM1: 202412 | JN1: 202503 | JO1: 202506 | JP1: 202509 | JQ1: 202512 | JR1: 202603 | JS1: 202606 | JT1: 202609 | JU1: 202612 | JV1: 202703 | JW1: 202706 | JX1: 202709 | JY1: 202712 | JZ1: 202803 | KA1: 202806 | KB1: 202809 | KC1: 202812 | KD1: 202903 | KE1: 202906 | KF1: 202909 | KG1: 202912 | KH1: 203003
FF2: 45901 | FG2: =+EOMONTH(FF2,1) -> 45961 | FH2: =+EOMONTH(FG2,1) -> 45991 | FI2: =+EOMONTH(FH2,1) -> 46022 | FJ2: =+EOMONTH(FI2,1) -> 46053 | FK2: =+EOMONTH(FJ2,1) -> 46081 | FL2: =+EOMONTH(FK2,1) -> 46112 | FM2: =+EOMONTH(FL2,1) -> 46142 | FN2: =+EOMONTH(FM2,1) -> 46173 | ... HH2: =+EOMONTH(HG2,1) -> 47573
A4: Field Description | B4: Field Name
A5: MonthEnd | B5: NMONTH_MONTHEND | C5: {=_xll.EQNXTDZ($A$1,$B5,C$1)} -> 201206 | D5: {=_xll.EQNXTDZ($A$1,$B5,D$1)} -> 201207 | E5: {=_xll.EQNXTDZ($A$1,$B5,E$1)} -> 201208 | F5: {=_xll.EQNXTDZ($A$1,$B5,F$1)} -> 201209 | G5: {=_xll.EQNXTDZ($A$1,$B5,G$1)} -> 201210 | H5: {=_xll.EQNXTDZ($A$1,$B5,H$1)} -> 201211 | I5: {=_xll.EQNXTDZ($A$1,$B5,I$1)} -> 201212 | J5: {=_xll.EQNXTDZ($A$1,$B5,J$1)} -> 201301 | ... HH5: {=_xll.EQNXTDZ($A$1,$B5,HH$1)} -> 0
A6: Open | B6: NMONTH_OPEN | C6: {=_xll.EQNXTDZ($A$1,$B6,C$1)} -> 232.50615 | D6: {=_xll.EQNXTDZ($A$1,$B6,D$1)} -> 237.20575 | E6: {=_xll.EQNXTDZ($A$1,$B6,E$1)} -> 222.16705 | F6: {=_xll.EQNXTDZ($A$1,$B6,F$1)} -> 233.69342 | G6: {=_xll.EQNXTDZ($A$1,$B6,G$1)} -> 265.15595 | H6: {=_xll.EQNXTDZ($A$1,$B6,H$1)} -> 254.27269 | I6: {=_xll.EQNXTDZ($A$1,$B6,I$1)} -> 270.10289 | J6: {=_xll.EQNXTDZ($A$1,$B6,J$1)} -> 312.64657 | ... HH6: {=_xll.EQNXTDZ($A$1,$B6,HH$1)} -> 0
A7: High | B7: NMONTH_HIGH | C7: {=_xll.EQNXTDZ($A$1,$B7,C$1)} -> 249.22681 | D7: {=_xll.EQNXTDZ($A$1,$B7,D$1)} -> 245.76395 | E7: {=_xll.EQNXTDZ($A$1,$B7,E$1)} -> 247.24803 | F7: {=_xll.EQNXTDZ($A$1,$B7,F$1)} -> 286.22992 | G7: {=_xll.EQNXTDZ($A$1,$B7,G$1)} -> 280.68934 | H7: {=_xll.EQNXTDZ($A$1,$B7,H$1)} -> 282.47024 | I7: {=_xll.EQNXTDZ($A$1,$B7,I$1)} -> 310.6678 | J7: {=_xll.EQNXTDZ($A$1,$B7,J$1)} -> 333.81947 | ... HH7: {=_xll.EQNXTDZ($A$1,$B7,HH$1)} -> 0 | HP7: =+MAX(D7:F7) -> 286.22992 | HQ7: =+MAX(G7:I7) -> 310.6678 | HR7: =+MAX(J7:L7) -> 333.81947 | HS7: =+MAX(M7:O7) -> 316.10943 | HT7: =+MAX(P7:R7) -> 351.08429 | HU7: =+MAX(S7:U7) -> 400.75156 | HV7: =+MAX(V7:X7) -> 416.23548 | HW7: =+MAX(Y7:AA7) -> 460.06537 | HX7: =+MAX(AB7:AD7) -> 536.84187 | HY7: =+MAX(AE7:AG7) -> 544.85591 | HZ7: =+MAX(AH7:AJ7) -> 605.90114 | IA7: =+MAX(AK7:AM7) -> 573.5 | IB7: =+MAX(AN7:AP7) -> 447.4 | IC7: =+MAX(AQ7:AS7) -> 431.9 | ID7: =+MAX(AT7:AV7) -> 403 | IE7: =+MAX(AW7:AY7) -> 489.9 | IF7: =+MAX(AZ7:BB7) -> 598.4 | IG7: =+MAX(BC7:BE7) -> 571.1 | IH7: =+MAX(BF7:BH7) -> 552 | II7: =+MAX(BI7:BK7) -> 488.25 | IJ7: =+MAX(BL7:BN7) -> 468.35 | IK7: =+MAX(BO7:BQ7) -> 468 | IL7: =+MAX(BR7:BT7) -> 443.5 | IM7: =+MAX(BU7:BW7) -> 372.35 | IN7: =+MAX(BX7:BZ7) -> 282 | IO7: =+MAX(CA7:CC7) -> 232.8 | IP7: =+MAX(CD7:CF7) -> 198.35 | IQ7: =+MAX(CG7:CI7) -> 239.35 | IR7: =+MAX(CJ7:CL7) -> 172.35 | IS7: =+MAX(CM7:CO7) -> 187.9 | IT7: =+MAX(CP7:CR7) -> 201.7 | IU7: =+MAX(CS7:CU7) -> 119.15 | IV7: =+MAX(CV7:CX7) -> 155.2 | IW7: =+MAX(CY7:DA7) -> 188.8 | IX7: =+MAX(DB7:DD7) -> 357 | IY7: =+MAX(DE7:DG7) -> 360.75 | IZ7: =+MAX(DH7:DJ7) -> 358.2 | JA7: =+MAX(DK7:DM7) -> 536.7 | JB7: =+MAX(DN7:DP7) -> 528.5 | JC7: =+MAX(DQ7:DS7) -> 462.7 | JD7: =+MAX(DT7:DV7) -> 494.4 | JE7: =+MAX(DW7:DY7) -> 443.6 | JF7: =+MAX(DZ7:EB7) -> 461.5 | JG7: =+MAX(EC7:EE7) -> 599 | JH7: =+MAX(EF7:EH7) -> 665.4 | JI7: =+MAX(EI7:EK7) -> 802.9 | JJ7: =+MAX(EL7:EN7) -> 1065.6 | JK7: =MAX(EO7:EQ7) -> 1050.35 | JL7: =MAX(ER7:ET7) -> 1179 | JM7: =MAX(EU7:EW7) -> 984.5 | JN7: =MAX(EX7:EZ7) -> 810 | JO7: =MAX(FA7:FC7) -> 744 | JP7: =MAX(FD7:FF7) -> 725.25 | JQ7: =MAX(FG7:FI7) -> 739.7 | JR7: =MAX(FJ7:FL7) -> 394.05 | JS7: =MAX(FM7:FO7) -> 408 | JT7: =MAX(FP7:FR7) -> 0 | JU7: =MAX(FS7:FU7) -> 0 | JV7: =MAX(FV7:FX7) -> 0 | JW7: =MAX(FY7:GA7) -> 0 | JX7: =MAX(GB7:GD7) -> 0 | JY7: =MAX(GE7:GG7) -> 0 | JZ7: =MAX(GH7:GJ7) -> 0 | KA7: =MAX(GK7:GM7) -> 0 | KB7: =MAX(GN7:GP7) -> 0 | KC7: =MAX(GQ7:GS7) -> 0 | KD7: =MAX(GT7:GV7) -> 0 | KE7: =MAX(GW7:GY7) -> 0 | KF7: =MAX(GZ7:HB7) -> 0 | KG7: =MAX(HC7:HE7) -> 0 | KH7: =MAX(HF7:HH7) -> 0
A8: Low | B8: NMONTH_LOW | C8: {=_xll.EQNXTDZ($A$1,$B8,C$1)} -> 214.94452 | D8: {=_xll.EQNXTDZ($A$1,$B8,D$1)} -> 200.89521 | E8: {=_xll.EQNXTDZ($A$1,$B8,E$1)} -> 213.85619 | F8: {=_xll.EQNXTDZ($A$1,$B8,F$1)} -> 222.66174 | G8: {=_xll.EQNXTDZ($A$1,$B8,G$1)} -> 217.12117 | H8: {=_xll.EQNXTDZ($A$1,$B8,H$1)} -> 253.2833 | I8: {=_xll.EQNXTDZ($A$1,$B8,I$1)} -> 266.44216 | J8: {=_xll.EQNXTDZ($A$1,$B8,J$1)} -> 278.80951 | ... HH8: {=_xll.EQNXTDZ($A$1,$B8,HH$1)} -> 0 | HP8: =+MIN(D8:F8) -> 200.89521 | HQ8: =+MIN(G8:I8) -> 217.12117 | HR8: =+MIN(J8:L8) -> 262.28673 | HS8: =+MIN(M8:O8) -> 249.12787 | HT8: =+MIN(P8:R8) -> 268.91563 | HU8: =+MIN(S8:U8) -> 326.79482 | HV8: =+MIN(V8:X8) -> 328.57572 | HW8: =+MIN(Y8:AA8) -> 395.26046 | HX8: =+MIN(AB8:AD8) -> 425.83255 | HY8: =+MIN(AE8:AG8) -> 463.03353 | HZ8: =+MIN(AH8:AJ8) -> 484.00855 | IA8: =+MIN(AK8:AM8) -> 417.25 | IB8: =+MIN(AN8:AP8) -> 279.1 | IC8: =+MIN(AQ8:AS8) -> 291.5 | ID8: =+MIN(AT8:AV8) -> 265.8 | IE8: =+MIN(AW8:AY8) -> 369 | IF8: =+MIN(AZ8:BB8) -> 454.1 | IG8: =+MIN(BC8:BE8) -> 428.3 | IH8: =+MIN(BF8:BH8) -> 434.35 | II8: =+MIN(BI8:BK8) -> 417.25 | IJ8: =+MIN(BL8:BN8) -> 358.5 | IK8: =+MIN(BO8:BQ8) -> 389.3 | IL8: =+MIN(BR8:BT8) -> 324.3 | IM8: =+MIN(BU8:BW8) -> 261.85 | IN8: =+MIN(BX8:BZ8) -> 219.5 | IO8: =+MIN(CA8:CC8) -> 154.65 | IP8: =+MIN(CD8:CF8) -> 129 | IQ8: =+MIN(CG8:CI8) -> 152.15 | IR8: =+MIN(CJ8:CL8) -> 106 | IS8: =+MIN(CM8:CO8) -> 112.65 | IT8: =+MIN(CP8:CR8) -> 63.5 | IU8: =+MIN(CS8:CU8) -> 64.8 | IV8: =+MIN(CV8:CX8) -> 98.2 | IW8: =+MIN(CY8:DA8) -> 126 | IX8: =+MIN(DB8:DD8) -> 184.5 | IY8: =+MIN(DE8:DG8) -> 280.55 | IZ8: =+MIN(DH8:DJ8) -> 268.45 | JA8: =+MIN(DK8:DM8) -> 325.7 | JB8: =+MIN(DN8:DP8) -> 376.35 | JC8: =+MIN(DQ8:DS8) -> 366.2 | JD8: =+MIN(DT8:DV8) -> 390.35 | JE8: =+MIN(DW8:DY8) -> 375.2 | JF8: =+MIN(DZ8:EB8) -> 381 | JG8: =+MIN(EC8:EE8) -> 419.5 | JH8: =+MIN(EF8:EH8) -> 584.95 | JI8: =+MIN(EI8:EK8) -> 608.3 | JJ8: =+MIN(EL8:EN8) -> 776.25 | JK8: =MIN(EO8:EQ8) -> 855.4 | JL8: =MIN(ER8:ET8) -> 949.2 | JM8: =MIN(EU8:EW8) -> 717.7 | JN8: =MIN(EX8:EZ8) -> 606.3 | JO8: =MIN(FA8:FC8) -> 535.75 | JP8: =MIN(FD8:FF8) -> 627.1 | JQ8: =MIN(FG8:FI8) -> 337.7 | JR8: =MIN(FJ8:FL8) -> 294.3 | JS8: =MIN(FM8:FO8) -> 295.05 | JT8: =MIN(FP8:FR8) -> 0 | JU8: =MIN(FS8:FU8) -> 0 | JV8: =MIN(FV8:FX8) -> 0 | JW8: =MIN(FY8:GA8) -> 0 | JX8: =MIN(GB8:GD8) -> 0 | JY8: =MIN(GE8:GG8) -> 0 | JZ8: =MIN(GH8:GJ8) -> 0 | KA8: =MIN(GK8:GM8) -> 0 | KB8: =MIN(GN8:GP8) -> 0 | KC8: =MIN(GQ8:GS8) -> 0 | KD8: =MIN(GT8:GV8) -> 0 | KE8: =MIN(GW8:GY8) -> 0 | KF8: =MIN(GZ8:HB8) -> 0 | KG8: =MIN(HC8:HE8) -> 0 | KH8: =MIN(HF8:HH8) -> 0
A9: Close | B9: NMONTH_CLOSE | C9: {=_xll.EQNXTDZ($A$1,$B9,C$1)} -> 239.87709 | D9: {=_xll.EQNXTDZ($A$1,$B9,D$1)} -> 223.84901 | E9: {=_xll.EQNXTDZ($A$1,$B9,E$1)} -> 231.81358 | F9: {=_xll.EQNXTDZ($A$1,$B9,F$1)} -> 264.71073 | G9: {=_xll.EQNXTDZ($A$1,$B9,G$1)} -> 252.04656 | H9: {=_xll.EQNXTDZ($A$1,$B9,H$1)} -> 270.54812 | I9: {=_xll.EQNXTDZ($A$1,$B9,I$1)} -> 309.33212 | J9: {=_xll.EQNXTDZ($A$1,$B9,J$1)} -> 294.83759 | ... HH9: {=_xll.EQNXTDZ($A$1,$B9,HH$1)} -> 0 | HP9: =+F9 -> 264.71073 | HQ9: =+I9 -> 309.33212 | HR9: =+L9 -> 266.29375 | HS9: =+O9 -> 278.31481 | HT9: =+R9 -> 328.97147 | HU9: =+U9 -> 372.4056 | HV9: =+X9 -> 394.41948 | HW9: =+AA9 -> 426.723 | HX9: =+AD9 -> 496.82113 | HY9: =+AG9 -> 490.29117 | HZ9: =+AJ9 -> 544.36122 | IA9: =+AM9 -> 434.15 | IB9: =+AP9 -> 298.6 | IC9: =+AS9 -> 391.3 | ID9: =+AV9 -> 386.6 | IE9: =+AY9 -> 459.25 | IF9: =+BB9 -> 534.85 | IG9: =+BE9 -> 472 | IH9: =+BH9 -> 465.85 | II9: =+BK9 -> 432.55 | IJ9: =+BN9 -> 401.5 | IK9: =+BQ9 -> 431.85 | IL9: =+BT9 -> 326.85 | IM9: =+BW9 -> 269.3 | IN9: =+BZ9 -> 223.7 | IO9: =+CC9 -> 172.7 | IP9: =+CF9 -> 174.25 | IQ9: =+CI9 -> 162.55 | IR9: =+CL9 -> 117.45 | IS9: =+CO9 -> 185.15 | IT9: =+CR9 -> 71.05 | IU9: =+CU9 -> 98.25 | IV9: =+CX9 -> 133.3 | IW9: =+DA9 -> 183.85 | IX9: =+DD9 -> 301.8 | IY9: =+DG9 -> 339.6 | IZ9: =+DJ9 -> 333.35 | JA9: =+DM9 -> 482.4 | JB9: =+DP9 -> 433.75 | JC9: =+DS9 -> 411.8 | JD9: =+DV9 -> 404.6 | JE9: =+DY9 -> 387.95 | JF9: =+EB9 -> 420.8 | JG9: =+EE9 -> 595.55 | JH9: =+EH9 -> 630.2 | JI9: =+EK9 -> 779.95 | JJ9: =+EN9 -> 992.8 | JK9: =EQ9 -> 989.75 | JL9: =ET9 -> 974.65 | JM9: =EW9 -> 740.15 | JN9: =EZ9 -> 674.45 | JO9: =FC9 -> 688 | JP9: =FF9 -> 680.2 | JQ9: =FI9 -> 367.35 | JR9: =FL9 -> 296.2 | JS9: =FO9 -> 393.6 | JT9: =FR9 -> 0 | JU9: =FU9 -> 0 | JV9: =FX9 -> 0 | JW9: =GA9 -> 0 | JX9: =GD9 -> 0 | JY9: =GG9 -> 0 | JZ9: =GJ9 -> 0 | KA9: =GM9 -> 0 | KB9: =GP9 -> 0 | KC9: =GS9 -> 0 | KD9: =GV9 -> 0 | KE9: =GY9 -> 0 | KF9: =HB9 -> 0 | KG9: =HE9 -> 0 | KH9: =HH9 -> 0
A11: Field Description | B11: Field Name | C11: {=_xll.EQNXTDZ($A$1,$B11,C$1)} -> 0 | D11: {=_xll.EQNXTDZ($A$1,$B11,D$1)} -> 0 | E11: {=_xll.EQNXTDZ($A$1,$B11,E$1)} -> 0 | F11: {=_xll.EQNXTDZ($A$1,$B11,F$1)} -> 0 | G11: {=_xll.EQNXTDZ($A$1,$B11,G$1)} -> 0 | H11: {=_xll.EQNXTDZ($A$1,$B11,H$1)} -> 0 | I11: {=_xll.EQNXTDZ($A$1,$B11,I$1)} -> 0 | J11: {=_xll.EQNXTDZ($A$1,$B11,J$1)} -> 0 | ... HH11: {=_xll.EQNXTDZ($A$1,$B11,HH$1)} -> 0
A12: Month End | B12: BMONTH_MONTHEND | C12: {=_xll.EQNXTDZ($A$1,$B12,C$1)} -> 201206 | D12: {=_xll.EQNXTDZ($A$1,$B12,D$1)} -> 201207 | E12: {=_xll.EQNXTDZ($A$1,$B12,E$1)} -> 201208 | F12: {=_xll.EQNXTDZ($A$1,$B12,F$1)} -> 201209 | G12: {=_xll.EQNXTDZ($A$1,$B12,G$1)} -> 201210 | H12: {=_xll.EQNXTDZ($A$1,$B12,H$1)} -> 201211 | I12: {=_xll.EQNXTDZ($A$1,$B12,I$1)} -> 201212 | J12: {=_xll.EQNXTDZ($A$1,$B12,J$1)} -> 201301 | ... HH12: {=_xll.EQNXTDZ($A$1,$B12,HH$1)} -> 0
A13: Open | B13: BMONTH_OPEN | C13: {=_xll.EQNXTDZ($A$1,$B13,C$1)} -> 232.51221 | D13: {=_xll.EQNXTDZ($A$1,$B13,D$1)} -> 237.36034 | E13: {=_xll.EQNXTDZ($A$1,$B13,E$1)} -> 222.12337 | F13: {=_xll.EQNXTDZ($A$1,$B13,F$1)} -> 234.49104 | G13: {=_xll.EQNXTDZ($A$1,$B13,G$1)} -> 264.47027 | H13: {=_xll.EQNXTDZ($A$1,$B13,H$1)} -> 254.27931 | I13: {=_xll.EQNXTDZ($A$1,$B13,I$1)} -> 270.30781 | J13: {=_xll.EQNXTDZ($A$1,$B13,J$1)} -> 311.31901 | ... HH13: {=_xll.EQNXTDZ($A$1,$B13,HH$1)} -> 0
A14: High | B14: BMONTH_HIGH | C14: {=_xll.EQNXTDZ($A$1,$B14,C$1)} -> 249.18383 | D14: {=_xll.EQNXTDZ($A$1,$B14,D$1)} -> 245.523 | E14: {=_xll.EQNXTDZ($A$1,$B14,E$1)} -> 247.10606 | F14: {=_xll.EQNXTDZ($A$1,$B14,F$1)} -> 286.23737 | G14: {=_xll.EQNXTDZ($A$1,$B14,G$1)} -> 280.64718 | H14: {=_xll.EQNXTDZ($A$1,$B14,H$1)} -> 282.4776 | I14: {=_xll.EQNXTDZ($A$1,$B14,I$1)} -> 310.62642 | J14: {=_xll.EQNXTDZ($A$1,$B14,J$1)} -> 333.48187 | ... HH14: {=_xll.EQNXTDZ($A$1,$B14,HH$1)} -> 0 | HP14: =+MAX(D14:F14) -> 286.23737 | HQ14: =+MAX(G14:I14) -> 310.62642 | HR14: =+MAX(J14:L14) -> 333.48187 | HS14: =+MAX(M14:O14) -> 316.11766 | HT14: =+MAX(P14:R14) -> 351.14291 | HU14: =+MAX(S14:U14) -> 400.71253 | HV14: =+MAX(V14:X14) -> 415.85056 | HW14: =+MAX(Y14:AA14) -> 459.28582 | HX14: =+MAX(AB14:AD14) -> 538.73573 | HY14: =+MAX(AE14:AG14) -> 544.96904 | HZ14: =+MAX(AH14:AJ14) -> 605.57063 | IA14: =+MAX(AK14:AM14) -> 573.15 | IB14: =+MAX(AN14:AP14) -> 447.4 | IC14: =+MAX(AQ14:AS14) -> 431.9 | ID14: =+MAX(AT14:AV14) -> 402.9 | IE14: =+MAX(AW14:AY14) -> 489.6 | IF14: =+MAX(AZ14:BB14) -> 598.6 | IG14: =+MAX(BC14:BE14) -> 571.05 | IH14: =+MAX(BF14:BH14) -> 553 | II14: =+MAX(BI14:BK14) -> 487 | IJ14: =+MAX(BL14:BN14) -> 468 | IK14: =+MAX(BO14:BQ14) -> 466.95 | IL14: =+MAX(BR14:BT14) -> 443.55 | IM14: =+MAX(BU14:BW14) -> 372.4 | IN14: =+MAX(BX14:BZ14) -> 282 | IO14: =+MAX(CA14:CC14) -> 232.75 | IP14: =+MAX(CD14:CF14) -> 198.3 | IQ14: =+MAX(CG14:CI14) -> 239.3 | IR14: =+MAX(CJ14:CL14) -> 172.4 | IS14: =+MAX(CM14:CO14) -> 187.9 | IT14: =+MAX(CP14:CR14) -> 201.8 | IU14: =+MAX(CS14:CU14) -> 119.05 | IV14: =+MAX(CV14:CX14) -> 155.15 | IW14: =+MAX(CY14:DA14) -> 188.75 | IX14: =+MAX(DB14:DD14) -> 357 | IY14: =+MAX(DE14:DG14) -> 360.65 | IZ14: =+MAX(DH14:DJ14) -> 358.1 | JA14: =+MAX(DK14:DM14) -> 536.5 | JB14: =+MAX(DN14:DP14) -> 528.35 | JC14: =+MAX(DQ14:DS14) -> 462.65 | JD14: =+MAX(DT14:DV14) -> 494.5 | JE14: =+MAX(DW14:DY14) -> 443.4 | JF14: =+MAX(DZ14:EB14) -> 461.3 | JG14: =+MAX(EC14:EE14) -> 599 | JH14: =+MAX(EF14:EH14) -> 665.3 | JI14: =+MAX(EI14:EK14) -> 802.6 | JJ14: =+MAX(EL14:EN14) -> 1065.6 | JK14: =MAX(EO14:EQ14) -> 1050 | JL14: =MAX(ER14:ET14) -> 1179.05 | JM14: =MAX(EU14:EW14) -> 984.4 | JN14: =MAX(EX14:EZ14) -> 809.95 | JO14: =MAX(FA14:FC14) -> 743.8 | JP14: =MAX(FD14:FF14) -> 725 | JQ14: =MAX(FG14:FI14) -> 739.55 | JR14: =MAX(FJ14:FL14) -> 394 | JS14: =MAX(FM14:FO14) -> 408.2 | JT14: =MAX(FP14:FR14) -> 0 | JU14: =MAX(FS14:FU14) -> 0 | JV14: =MAX(FV14:FX14) -> 0 | JW14: =MAX(FY14:GA14) -> 0 | JX14: =MAX(GB14:GD14) -> 0 | JY14: =MAX(GE14:GG14) -> 0 | JZ14: =MAX(GH14:GJ14) -> 0 | KA14: =MAX(GK14:GM14) -> 0 | KB14: =MAX(GN14:GP14) -> 0 | KC14: =MAX(GQ14:GS14) -> 0 | KD14: =MAX(GT14:GV14) -> 0 | KE14: =MAX(GW14:GY14) -> 0 | KF14: =MAX(GZ14:HB14) -> 0 | KG14: =MAX(HC14:HE14) -> 0 | KH14: =MAX(HF14:HH14) -> 0
A15: Low | B15: BMONTH_LOW | C15: {=_xll.EQNXTDZ($A$1,$B15,C$1)} -> 214.70276 | D15: {=_xll.EQNXTDZ($A$1,$B15,D$1)} -> 200.8015 | E15: {=_xll.EQNXTDZ($A$1,$B15,E$1)} -> 213.9607 | F15: {=_xll.EQNXTDZ($A$1,$B15,F$1)} -> 222.76648 | G15: {=_xll.EQNXTDZ($A$1,$B15,G$1)} -> 242.75264 | H15: {=_xll.EQNXTDZ($A$1,$B15,H$1)} -> 253.48778 | I15: {=_xll.EQNXTDZ($A$1,$B15,I$1)} -> 266.4491 | J15: {=_xll.EQNXTDZ($A$1,$B15,J$1)} -> 279.06412 | ... HH15: {=_xll.EQNXTDZ($A$1,$B15,HH$1)} -> 0 | HP15: =+MIN(D15:F15) -> 200.8015 | HQ15: =+MIN(G15:I15) -> 242.75264 | HR15: =+MIN(J15:L15) -> 262.34303 | HS15: =+MIN(M15:O15) -> 249.43118 | HT15: =+MIN(P15:R15) -> 269.61522 | HU15: =+MIN(S15:U15) -> 326.75386 | HV15: =+MIN(V15:X15) -> 327.54539 | HW15: =+MIN(Y15:AA15) -> 395.46864 | HX15: =+MIN(AB15:AD15) -> 425.94258 | HY15: =+MIN(AE15:AG15) -> 463.194 | HZ15: =+MIN(AH15:AJ15) -> 484.21904 | IA15: =+MIN(AK15:AM15) -> 418 | IB15: =+MIN(AN15:AP15) -> 279.15 | IC15: =+MIN(AQ15:AS15) -> 291.75 | ID15: =+MIN(AT15:AV15) -> 266 | IE15: =+MIN(AW15:AY15) -> 368.4 | IF15: =+MIN(AZ15:BB15) -> 454 | IG15: =+MIN(BC15:BE15) -> 429 | IH15: =+MIN(BF15:BH15) -> 435 | II15: =+MIN(BI15:BK15) -> 417.1 | IJ15: =+MIN(BL15:BN15) -> 357.95 | IK15: =+MIN(BO15:BQ15) -> 389.75 | IL15: =+MIN(BR15:BT15) -> 324.5 | IM15: =+MIN(BU15:BW15) -> 262.5 | IN15: =+MIN(BX15:BZ15) -> 219.65 | IO15: =+MIN(CA15:CC15) -> 154.7 | IP15: =+MIN(CD15:CF15) -> 141.9 | IQ15: =+MIN(CG15:CI15) -> 152.1 | IR15: =+MIN(CJ15:CL15) -> 106 | IS15: =+MIN(CM15:CO15) -> 112 | IT15: =+MIN(CP15:CR15) -> 63.6 | IU15: =+MIN(CS15:CU15) -> 64.8 | IV15: =+MIN(CV15:CX15) -> 98.2 | IW15: =+MIN(CY15:DA15) -> 126 | IX15: =+MIN(DB15:DD15) -> 184.55 | IY15: =+MIN(DE15:DG15) -> 280.55 | IZ15: =+MIN(DH15:DJ15) -> 268.5 | JA15: =+MIN(DK15:DM15) -> 325.8 | JB15: =+MIN(DN15:DP15) -> 376.15 | JC15: =+MIN(DQ15:DS15) -> 366.05 | JD15: =+MIN(DT15:DV15) -> 390.45 | JE15: =+MIN(DW15:DY15) -> 375.5 | JF15: =+MIN(DZ15:EB15) -> 381 | JG15: =+MIN(EC15:EE15) -> 419.45 | JH15: =+MIN(EF15:EH15) -> 585 | JI15: =+MIN(EI15:EK15) -> 608.45 | JJ15: =+MIN(EL15:EN15) -> 776.2 | JK15: =MIN(EO15:EQ15) -> 855.45 | JL15: =MIN(ER15:ET15) -> 950.05 | JM15: =MIN(EU15:EW15) -> 718 | JN15: =MIN(EX15:EZ15) -> 606.2 | JO15: =MIN(FA15:FC15) -> 542.55 | JP15: =MIN(FD15:FF15) -> 627.3 | JQ15: =MIN(FG15:FI15) -> 337.9 | JR15: =MIN(FJ15:FL15) -> 294.15 | JS15: =MIN(FM15:FO15) -> 295.1 | JT15: =MIN(FP15:FR15) -> 0 | JU15: =MIN(FS15:FU15) -> 0 | JV15: =MIN(FV15:FX15) -> 0 | JW15: =MIN(FY15:GA15) -> 0 | JX15: =MIN(GB15:GD15) -> 0 | JY15: =MIN(GE15:GG15) -> 0 | JZ15: =MIN(GH15:GJ15) -> 0 | KA15: =MIN(GK15:GM15) -> 0 | KB15: =MIN(GN15:GP15) -> 0 | KC15: =MIN(GQ15:GS15) -> 0 | KD15: =MIN(GT15:GV15) -> 0 | KE15: =MIN(GW15:GY15) -> 0 | KF15: =MIN(GZ15:HB15) -> 0 | KG15: =MIN(HC15:HE15) -> 0 | KH15: =MIN(HF15:HH15) -> 0
A16: Close | B16: BMONTH_CLOSE | C16: {=_xll.EQNXTDZ($A$1,$B16,C$1)} -> 239.48757 | D16: {=_xll.EQNXTDZ($A$1,$B16,D$1)} -> 223.50854 | E16: {=_xll.EQNXTDZ($A$1,$B16,E$1)} -> 231.27544 | F16: {=_xll.EQNXTDZ($A$1,$B16,F$1)} -> 264.61868 | G16: {=_xll.EQNXTDZ($A$1,$B16,G$1)} -> 251.95419 | H16: {=_xll.EQNXTDZ($A$1,$B16,H$1)} -> 271.34669 | I16: {=_xll.EQNXTDZ($A$1,$B16,I$1)} -> 309.09283 | J16: {=_xll.EQNXTDZ($A$1,$B16,J$1)} -> 294.84527 | ... HH16: {=_xll.EQNXTDZ($A$1,$B16,HH$1)} -> 0 | HP16: =+F16 -> 264.61868 | HQ16: =+I16 -> 309.09283 | HR16: =+L16 -> 266.4491 | HS16: =+O16 -> 278.47047 | HT16: =+R16 -> 328.83163 | HU16: =+U16 -> 372.4153 | HV16: =+X16 -> 394.13293 | HW16: =+AA16 -> 426.5857 | HX16: =+AD16 -> 497.42771 | HY16: =+AG16 -> 490.84811 | HZ16: =+AJ16 -> 544.12804 | IA16: =+AM16 -> 434.55 | IB16: =+AP16 -> 298.45 | IC16: =+AS16 -> 391.25 | ID16: =+AV16 -> 386.3 | IE16: =+AY16 -> 459.25 | IF16: =+BB16 -> 534.75 | IG16: =+BE16 -> 471.35 | IH16: =+BH16 -> 465.95 | II16: =+BK16 -> 432.5 | IJ16: =+BN16 -> 401.25 | IK16: =+BQ16 -> 431.2 | IL16: =+BT16 -> 327.45 | IM16: =+BW16 -> 269.3 | IN16: =+BZ16 -> 223.45 | IO16: =+CC16 -> 172.6 | IP16: =+CF16 -> 174.3 | IQ16: =+CI16 -> 162.6 | IR16: =+CL16 -> 117.45 | IS16: =+CO16 -> 185.1 | IT16: =+CR16 -> 71.05 | IU16: =+CU16 -> 98.25 | IV16: =+CX16 -> 133.3 | IW16: =+DA16 -> 183.7 | IX16: =+DD16 -> 301.85 | IY16: =+DG16 -> 339.55 | IZ16: =+DJ16 -> 333.2 | JA16: =+DM16 -> 482.35 | JB16: =+DP16 -> 433.5 | JC16: =+DS16 -> 411.7 | JD16: =+DV16 -> 404.65 | JE16: =+DY16 -> 388.1 | JF16: =+EB16 -> 420.6 | JG16: =+EE16 -> 595.5 | JH16: =+EH16 -> 630.35 | JI16: =+EK16 -> 780.75 | JJ16: =+EN16 -> 993 | JK16: =EQ16 -> 990.1 | JL16: =ET16 -> 974.7 | JM16: =EW16 -> 740.7 | JN16: =EZ16 -> 674.05 | JO16: =FC16 -> 688.05 | JP16: =FF16 -> 680.45 | JQ16: =FI16 -> 367.5 | JR16: =FL16 -> 296.25 | JS16: =FO16 -> 393.6 | JT16: =FR16 -> 0 | JU16: =FU16 -> 0 | JV16: =FX16 -> 0 | JW16: =GA16 -> 0 | JX16: =GD16 -> 0 | JY16: =GG16 -> 0 | JZ16: =GJ16 -> 0 | KA16: =GM16 -> 0 | KB16: =GP16 -> 0 | KC16: =GS16 -> 0 | KD16: =GV16 -> 0 | KE16: =GY16 -> 0 | KF16: =HB16 -> 0 | KG16: =HE16 -> 0 | KH16: =HH16 -> 0
A19: High | HP19: =+IF(HP14=0,HP7,HP14) -> 286.23737 | HQ19: =+IF(HQ14=0,HQ7,HQ14) -> 310.62642 | HR19: =+IF(HR14=0,HR7,HR14) -> 333.48187 | HS19: =+IF(HS14=0,HS7,HS14) -> 316.11766 | HT19: =+IF(HT14=0,HT7,HT14) -> 351.14291 | HU19: =+IF(HU14=0,HU7,HU14) -> 400.71253 | HV19: =+IF(HV14=0,HV7,HV14) -> 415.85056 | HW19: =+IF(HW14=0,HW7,HW14) -> 459.28582 | ... KH19: =+IF(KH14=0,KH7,KH14) -> 0
A20: Low | HP20: =+IF(HP15=0,HP8,HP15) -> 200.8015 | HQ20: =+IF(HQ15=0,HQ8,HQ15) -> 242.75264 | HR20: =+IF(HR15=0,HR8,HR15) -> 262.34303 | HS20: =+IF(HS15=0,HS8,HS15) -> 249.43118 | HT20: =+IF(HT15=0,HT8,HT15) -> 269.61522 | HU20: =+IF(HU15=0,HU8,HU15) -> 326.75386 | HV20: =+IF(HV15=0,HV8,HV15) -> 327.54539 | HW20: =+IF(HW15=0,HW8,HW15) -> 395.46864 | ... KH20: =+IF(KH15=0,KH8,KH15) -> 0
A21: Close | HP21: =+IF(HP16=0,HP9,HP16) -> 264.61868 | HQ21: =+IF(HQ16=0,HQ9,HQ16) -> 309.09283 | HR21: =+IF(HR16=0,HR9,HR16) -> 266.4491 | HS21: =+IF(HS16=0,HS9,HS16) -> 278.47047 | HT21: =+IF(HT16=0,HT9,HT16) -> 328.83163 | HU21: =+IF(HU16=0,HU9,HU16) -> 372.4153 | HV21: =+IF(HV16=0,HV9,HV16) -> 394.13293 | HW21: =+IF(HW16=0,HW9,HW16) -> 426.5857 | ... KH21: =+IF(KH16=0,KH9,KH16) -> 0

Sheet QTR No. of Shares
A1: ='QTR Raw'!A1 -> 100570 | C1: 201206 | D1: 201209 | E1: 201212 | F1: 201303 | G1: 201306 | H1: 201309 | I1: 201312 | J1: 201403 | K1: 201406 | L1: 201409 | M1: 201412 | N1: 201503 | O1: 201506 | P1: 201509 | Q1: 201512 | R1: 201603 | S1: 201606 | T1: 201609 | U1: 201612 | V1: 201703 | W1: 201706 | X1: 201709 | Y1: 201712 | Z1: 201803 | AA1: 201806 | AB1: 201809 | AC1: 201812 | AD1: 201903 | AE1: 201906 | AF1: 201909 | AG1: 201912 | AH1: 202003 | AI1: 202006 | AJ1: 202009 | AK1: 202012 | AL1: 202103 | AM1: 202106 | AN1: 202109 | AO1: 202112 | AP1: 202203 | AQ1: 202206 | AR1: 202209 | AS1: 202212 | AT1: 202303 | AU1: 202306 | AV1: 202309 | AW1: 202312 | AX1: 202403 | AY1: 202406
A4: Field Description | B4: Field Name
A5: Date End | B5: SHP_DATE_END | C5: {=_xll.EQNXTDZ($A$1,$B5,C$1)} -> 201206 | D5: {=_xll.EQNXTDZ($A$1,$B5,D$1)} -> 201209 | E5: {=_xll.EQNXTDZ($A$1,$B5,E$1)} -> 201212 | F5: {=_xll.EQNXTDZ($A$1,$B5,F$1)} -> 201303 | G5: {=_xll.EQNXTDZ($A$1,$B5,G$1)} -> 201306 | H5: {=_xll.EQNXTDZ($A$1,$B5,H$1)} -> 201309 | I5: {=_xll.EQNXTDZ($A$1,$B5,I$1)} -> 201312 | J5: {=_xll.EQNXTDZ($A$1,$B5,J$1)} -> 201403 | ... AY5: {=_xll.EQNXTDZ($A$1,$B5,AY$1)} -> 202406
A6: Grand Total | B6: SHP_NSGRANDTOTAL | C6: {=_xll.EQNXTDZ($A$1,$B6,C$1)} -> 2707731241 | D6: {=_xll.EQNXTDZ($A$1,$B6,D$1)} -> 2707731241 | E6: {=_xll.EQNXTDZ($A$1,$B6,E$1)} -> 2707846826 | F6: {=_xll.EQNXTDZ($A$1,$B6,F$1)} -> 2708156151 | G6: {=_xll.EQNXTDZ($A$1,$B6,G$1)} -> 2736705717 | H6: {=_xll.EQNXTDZ($A$1,$B6,H$1)} -> 2736705717 | I6: {=_xll.EQNXTDZ($A$1,$B6,I$1)} -> 2736712897 | J6: {=_xll.EQNXTDZ($A$1,$B6,J$1)} -> 2736713122 | ... AY6: {=_xll.EQNXTDZ($A$1,$B6,AY$1)} -> 3323978912
B7: In Crs. | C7: =+C6/10^7 -> 270.77312 | D7: =+D6/10^7 -> 270.77312 | E7: =+E6/10^7 -> 270.78468 | F7: =+F6/10^7 -> 270.81562 | G7: =+G6/10^7 -> 273.67057 | H7: =+H6/10^7 -> 273.67057 | I7: =+I6/10^7 -> 273.67129 | J7: =+J6/10^7 -> 273.67131 | ... AY7: =+AY6/10^7 -> 332.39789

Sheet Share price Daily
A1: =_xll.EQNXTH(B1,"[ADJC];[ADJH];[ADJL];[ADJO];[UCLS];[VOLUME]","2015-Jan-01","Y","All traded days","Asc") -> EQNXTH | B1: =+'Annual Raw'!A1 -> 100570 | L1: =_xll.EQNXTH(B1,"[NADJC];[NADJH];[NADJLOW];[NADJOPEN];[NUCLOSE];[NVOLUME]","2015-Jan-01","Y","All traded days","Asc") -> EQNXTH
A2: Tata Motors Passenger Vehicles Ltd. | L2: Tata Motors Passenger Vehicles Ltd.
A3: DATE | B3: ADJHIGH | C3: ADJCLOSE | D3: ADJLOW | E3: ADJOPEN | F3: CLOSE | G3: VOLUME | L3: DATE | M3: ADJCLOSE | N3: ADJHIGH | O3: ADJLOW | P3: ADJOPEN | Q3: CLOSE | R3: VOLUME
A4: 42005 | B4: 494.45947 | C4: 492.97535 | D4: 487.38517 | E4: 487.38517 | F4: 498.25 | G4: 107485 | L4: 42005 | M4: 493.16039 | N4: 494.14978 | O4: 487.02619 | P4: 489.25231 | Q4: 498.45 | R4: 934528
A5: 42006 | B5: 511.42792 | C5: 506.28297 | D5: 491.24388 | E5: 491.24388 | F5: 511.7 | G5: 299490 | L5: 42006 | M5: 506.36872 | N5: 511.90929 | O5: 491.97313 | P5: 491.97313 | Q5: 511.8 | R5: 4148596
A6: 42009 | B6: 520.43158 | C6: 518.5517 | D6: 502.02849 | E6: 505.98614 | F6: 524.1 | G6: 583670 | L6: 42009 | M6: 518.24138 | N6: 520.41803 | O6: 501.32284 | P6: 504.68676 | Q6: 523.8 | R6: 6686952
A7: 42010 | B7: 509.35015 | C7: 495.79518 | D7: 493.71741 | E7: 509.35015 | F7: 501.1 | G7: 495466 | L7: 42010 | M7: 496.07909 | N7: 508.89166 | O7: 493.9519 | P7: 508.89166 | Q7: 501.4 | R7: 7894918
A8: 42011 | B8: 495.39942 | C8: 488.77034 | D8: 484.21904 | E8: 491.09547 | F8: 494 | G8: 561630 | L8: 42011 | M8: 488.60921 | N8: 495.0897 | O8: 484.00855 | P8: 489.747 | Q8: 493.85 | R8: 9134678
A9: 42012 | B9: 509.35015 | C9: 506.77767 | D9: 496.24042 | E9: 498.02136 | F9: 512.2 | G9: 349366 | L9: 42012 | M9: 506.5666 | N9: 509.33688 | O9: 495.68333 | P9: 498.6515 | Q9: 512 | R9: 5476843
A10: 42013 | B10: 519.44217 | C10: 516.32552 | D10: 510.53745 | E10: 513.10992 | F10: 521.85 | G10: 345099 | L10: 42013 | M10: 516.75729 | N10: 519.37917 | O10: 510.02946 | P10: 515.71844 | Q10: 522.3 | R10: 4010545
A11: 42016 | B11: 519.19481 | C11: 516.86969 | D11: 506.67873 | E11: 512.51627 | F11: 522.4 | G11: 274107 | L11: 42016 | M11: 516.75729 | N11: 519.13182 | O11: 505.82456 | P11: 512.99762 | Q11: 522.3 | R11: 2533395
A12: 42017 | B12: 520.43158 | C12: 514.04986 | D12: 510.14168 | E12: 516.77075 | F12: 519.55 | G12: 348572 | L12: 42017 | M12: 513.93754 | N12: 520.12121 | O12: 509.78211 | P12: 514.82799 | Q12: 519.45 | R12: 4282874
A13: 42018 | B13: 521.0747 | C13: 514.84139 | D13: 508.85544 | E13: 515.03928 | F13: 520.35 | G13: 521222 | L13: 42018 | M13: 514.82799 | N13: 521.06113 | O13: 508.4959 | P13: 515.96578 | Q13: 520.35 | R13: 6006186
A14: 42019 | B14: 530.32572 | C14: 526.8133 | D14: 518.2054 | E14: 524.38924 | F14: 532.45 | G14: 474617 | L14: 42019 | M14: 527.29427 | N14: 530.31191 | O14: 518.19191 | P14: 522.69362 | Q14: 532.95 | R14: 6829305
A15: 42020 | B15: 525.87336 | C15: 520.03582 | D15: 516.96863 | E15: 524.38924 | F15: 525.6 | G15: 277994 | L15: 42020 | M15: 520.17068 | N15: 530.11403 | O15: 516.85623 | P15: 525.46391 | Q15: 525.75 | R15: 4205034
... A2841: 46190 | B2841: 397.05 | C2841: 361.05 | D2841: 355 | E2841: 397.05 | F2841: 361.05 | G2841: 3280898 | L2841: 46190 | M2841: 360.95 | N2841: 395.6 | O2841: 355 | P2841: 395.5 | Q2841: 360.95 | R2841: 51987488

Sheet Sheet2
J19: 219.3 | K19: 186.25 | L19: 186.75
J20: 192.9 | K20: 135.5 | L20: 146.9 | N20: 219.3 | O20: 192.9 | P20: 186 | Q20: 178.7 | R20: 207 | S20: 255.15 | T20: 348.25 | U20: 374 | V20: 495.9 | W20: 659.9 | X20: 613.4 | Y20: 607.9 | Z20: 555.95 | AA20: 497.8 | AB20: 459.9 | AC20: 374 | AD20: 362 | AE20: 341.5 | AF20: 384.2 | AG20: 433.8 | AH20: 460 | AI20: 474.4 | AJ20: 414.4 | AK20: 318.7 | AL20: 303.25 | AM20: 332.7 | AN20: 295 | AO20: 247 | AP20: 214.4 | AQ20: 179.5 | AR20: 97.9 | AS20: 119.1 | AT20: 130.65 | AU20: 148.55 | AV20: 153.8 | AW20: 152.9 | AX20: 136 | AY20: 141.15 | AZ20: 128.1 | BA20: 142.5 | BB20: 143.55 | BC20: 124.5 | BD20: 241 | BE20: 450 | BF20: 503.35
J21: 186 | K21: 145.4 | L21: 169.1 | N21: 186.25 | O21: 135.5 | P21: 145.4 | Q21: 108.95 | R21: 137 | S21: 170 | T21: 243.15 | U21: 307.5 | V21: 325.1 | W21: 463 | X21: 467.05 | Y21: 436.5 | Z21: 467 | AA21: 348.2 | AB21: 325 | AC21: 313.1 | AD21: 285 | AE21: 277.85 | AF21: 327 | AG21: 317 | AH21: 370.7 | AI21: 360 | AJ21: 271.15 | AK21: 233.15 | AL21: 218.8 | AM21: 262 | AN21: 223.6 | AO21: 137.6 | AP21: 142 | AQ21: 59.3 | AR21: 58 | AS21: 72.8 | AT21: 80 | AU21: 107.25 | AV21: 106 | AW21: 125.1 | AX21: 112.25 | AY21: 81.45 | AZ21: 88 | BA21: 90.35 | BB21: 106.05 | BC21: 98.55 | BD21: 119.25 | BE21: 210 | BF21: 349
J22: 178.7 | K22: 108.95 | L22: 139.75 | N22: 186.75 | O22: 146.9 | P22: 169.1 | Q22: 139.75 | R22: 202.15 | S22: 249.05 | T22: 346.4 | U22: 349.2 | V22: 469.9 | W22: 584.8 | X22: 536.15 | Y22: 513.35 | Z22: 474 | AA22: 438.55 | AB22: 355.4 | AC22: 334.95 | AD22: 298.8 | AE22: 328.35 | AF22: 343 | AG22: 389.9 | AH22: 443.05 | AI22: 407.5 | AJ22: 290.1 | AK22: 235.75 | AL22: 292.65 | AM22: 276.1 | AN22: 237.05 | AO22: 190.1 | AP22: 147.2 | AQ22: 71.9 | AR22: 75.2 | AS22: 90.1 | AT22: 117.2 | AU22: 116.3 | AV22: 140.5 | AW22: 128.6 | AX22: 133.65 | AY22: 91.65 | AZ22: 97.65 | BA22: 125 | BB22: 115.35 | BC22: 119.25 | BD22: 219.3 | BE22: 442.65 | BF22: 503.35
J23: 207 | K23: 137 | L23: 202.15
J24: 255.15 | K24: 170 | L24: 249.05
J25: 348.25 | K25: 243.15 | L25: 346.4
J26: 374 | K26: 307.5 | L26: 349.2
J27: 495.9 | K27: 325.1 | L27: 469.9
J28: 659.9 | K28: 463 | L28: 584.8
J29: 613.4 | K29: 467.05 | L29: 536.15
J30: 607.9 | K30: 436.5 | L30: 513.35
J31: 555.95 | K31: 467 | L31: 474
J32: 497.8 | K32: 348.2 | L32: 438.55
J33: 459.9 | K33: 325 | L33: 355.4
J34: 374 | K34: 313.1 | L34: 334.95
... J63: 503.35 | K63: 349 | L63: 503.35
