Workbook

Sheet Template
A1: =+'Annual Raw'!C4 -> Tata Power Company Ltd. | B1: 36951 | C1: =EOMONTH(B1,12) -> 37346 | D1: =EOMONTH(C1,12) -> 37711 | E1: =EOMONTH(D1,12) -> 38077 | F1: =EOMONTH(E1,12) -> 38442 | G1: =EOMONTH(F1,12) -> 38807 | H1: =EOMONTH(G1,12) -> 39172 | I1: =EOMONTH(H1,12) -> 39538 | J1: =EOMONTH(I1,12) -> 39903 | ... AE1: =EOMONTH(AD1,12) -> 47573 | AH1: QTR | AI1: 41061 | AJ1: 41153 | AK1: 41244 | AL1: 41334 | AM1: 41426 | AN1: 41518 | AO1: 41609 | AP1: 41699 | AQ1: 41791 | AR1: 41883 | AS1: 41974 | AT1: 42064 | AU1: 42156 | AV1: 42248 | AW1: 42339 | AX1: 42430 | AY1: 42522 | AZ1: 42614 | BA1: 42705 | BB1: 42795 | BC1: 42887 | BD1: 42979 | BE1: 43070 | BF1: 43160 | BG1: 43252 | BH1: 43344 | BI1: 43435 | BJ1: 43525 | BK1: 43617 | BL1: 43709 | BM1: 43800 | BN1: 43891 | BO1: 43983 | BP1: 44075 | BQ1: =EOMONTH(BP1,3) -> 44196 | BR1: =EOMONTH(BQ1,3) -> 44286 | BS1: =EOMONTH(BR1,3) -> 44377 | BT1: =EOMONTH(BS1,3) -> 44469 | BU1: =EOMONTH(BT1,3) -> 44561 | BV1: =EOMONTH(BU1,3) -> 44651 | BW1: =EOMONTH(BV1,3) -> 44742 | BX1: =EOMONTH(BW1,3) -> 44834 | ... DB1: =EOMONTH(DA1,3) -> 47573 | DE1: HISTORICAL ESTIMATES | DF1: 46112
A2: Presentation Data (Start)
A4: Sales - Segment wise
A5: Thermal Generation, Coal and Hydro | X5: =SUM(X6:X9) -> 18212 | Y5: =SUM(Y6:Y9) -> 19613 | Z5: =SUM(Z6:Z9) -> 19740 | AA5: =SUM(AA6:AA9) -> 11630 | AB5: =SUM(AB6:AB9) -> 17827 | AC5: =SUM(AC6:AC9) -> 20552 | AD5: =SUM(AD6:AD9) -> 20552 | AE5: =SUM(AE6:AE9) -> 20552 | BW5: =SUM(BW6:BW9) -> 5125 | BX5: =SUM(BX6:BX9) -> 4834 | BY5: =SUM(BY6:BY9) -> 5370 | BZ5: =SUM(BZ6:BZ9) -> 2883 | CA5: =SUM(CA6:CA9) -> 4827 | CB5: =SUM(CB6:CB9) -> 4973 | CC5: =SUM(CC6:CC9) -> 4958 | CD5: =SUM(CD6:CD9) -> 4855 | ... DB5: =SUM(DB6:DB9) -> 5159
A6: Maithon Power Limited (MPL) | X6: =SUM(BW6:BZ6) -> 3029 | Y6: =SUM(CA6:CD6) -> 3359 | Z6: =SUM(CE6:CH6) -> 2955 | AA6: =SUM(CI6:CL6) -> 3095 | AB6: =SUM(CM6:CP6) -> 3095 | AC6: =SUM(CQ6:CT6) -> 3095 | AD6: =SUM(CU6:CX6) -> 3095 | AE6: =SUM(CY6:DB6) -> 3095 | BW6: 754 | BX6: 810 | BY6: 809 | BZ6: 656 | CA6: 850 | CB6: 761 | CC6: 845 | CD6: 903 | CE6: 819 | CF6: 767 | CG6: 640 | CH6: 729 | CI6: 771 | CJ6: 829 | CK6: 695 | CL6: 800 | CM6: =CI6 -> 771 | CN6: =CJ6 -> 829 | CO6: =CK6 -> 695 | CP6: =CL6 -> 800 | CQ6: =CM6 -> 771 | CR6: =CN6 -> 829 | CS6: =CO6 -> 695 | CT6: =CP6 -> 800 | ... DB6: =CX6 -> 800
A7: Traditional Generation (incl. Mumbai and Hydro) | X7: =SUM(BW7:BZ7) -> 6884 | Y7: =SUM(CA7:CD7) -> 5880 | Z7: =SUM(CE7:CH7) -> 5262 | AA7: =SUM(CI7:CL7) -> 5124 | AB7: =SUM(CM7:CP7) -> 5124 | AC7: =SUM(CQ7:CT7) -> 5124 | AD7: =SUM(CU7:CX7) -> 5124 | AE7: =SUM(CY7:DB7) -> 5124 | BW7: 1978 | BX7: 1725 | BY7: 1671 | BZ7: 1510 | CA7: 1596 | CB7: 1422 | CC7: 1455 | CD7: 1407 | CE7: 1563 | CF7: 1402 | CG7: 927 | CH7: 1370 | CI7: 1266 | CJ7: 1291 | CK7: 1246 | CL7: 1321 | CM7: =CI7 -> 1266 | CN7: =CJ7 -> 1291 | CO7: =CK7 -> 1246 | CP7: =CL7 -> 1321 | CQ7: =CM7 -> 1266 | CR7: =CN7 -> 1291 | CS7: =CO7 -> 1246 | CT7: =CP7 -> 1321 | ... DB7: =CX7 -> 1321
A8: Others (Incl. eliminations) | X8: =SUM(BW8:BZ8) -> 130 | Y8: =SUM(CA8:CD8) -> 131 | Z8: =SUM(CE8:CH8) -> 126 | AA8: =SUM(CI8:CL8) -> 133 | AB8: =SUM(CM8:CP8) -> 133 | AC8: =SUM(CQ8:CT8) -> 133 | AD8: =SUM(CU8:CX8) -> 133 | AE8: =SUM(CY8:DB8) -> 133 | BW8: 32 | BX8: 30 | BY8: 34 | BZ8: 34 | CA8: 32 | CB8: 34 | CC8: 35 | CD8: 30 | CE8: 32 | CF8: 31 | CG8: 33 | CH8: 30 | CI8: 27 | CJ8: 33 | CK8: 35 | CL8: 38 | CM8: =CI8 -> 27 | CN8: =CJ8 -> 33 | CO8: =CK8 -> 35 | CP8: =CL8 -> 38 | CQ8: =CM8 -> 27 | CR8: =CN8 -> 33 | CS8: =CO8 -> 35 | CT8: =CP8 -> 38 | ... DB8: =CX8 -> 38
A9: Mundra, Coal and Shipping | X9: =SUM(BW9:BZ9) -> 8169 | Y9: =SUM(CA9:CD9) -> 10243 | Z9: =SUM(CE9:CH9) -> 11397 | AA9: =SUM(CI9:CL9) -> 3278 | AB9: =SUM(CM9:CP9) -> 9475 | AC9: =SUM(CQ9:CT9) -> 12200 | AD9: =SUM(CU9:CX9) -> 12200 | AE9: =SUM(CY9:DB9) -> 12200 | BW9: 2361 | BX9: 2269 | BY9: 2856 | BZ9: 683 | CA9: 2349 | CB9: 2756 | CC9: 2623 | CD9: 2515 | CE9: 2803 | CF9: 2110 | CG9: 3325 | CH9: 3159 | CI9: 2780 | CJ9: 177 | CK9: 46 | CL9: 275 | CM9: =CL9 -> 275 | CN9: 3200 | CO9: 3000 | CP9: 3000 | CQ9: 3000 | CR9: =CN9 -> 3200 | CS9: =CO9 -> 3000 | CT9: =CP9 -> 3000 | CU9: =CQ9 -> 3000 | CV9: =CR9 -> 3200 | CW9: =CS9 -> 3000 | CX9: =CT9 -> 3000 | CY9: =CU9 -> 3000 | ... DB9: =CX9 -> 3000
A11: Renewables | X11: =SUM(X12:X15) -> 8197 | Y11: =SUM(Y12:Y15) -> 10176 | Z11: =SUM(Z12:Z15) -> 9883 | AA11: =SUM(AA12:AA15) -> 15026 | AB11: =SUM(AB12:AB15) -> 17897.943 | AC11: =SUM(AC12:AC15) -> 19842.7 | AD11: =SUM(AD12:AD15) -> 22861.377 | AE11: =SUM(AE12:AE15) -> 26290.926 | BW11: =SUM(BW12:BW15) -> 2090 | BX11: =SUM(BX12:BX15) -> 1603 | BY11: =SUM(BY12:BY15) -> 1917 | BZ11: =SUM(BZ12:BZ15) -> 2587 | CA11: =SUM(CA12:CA15) -> 2089 | CB11: =SUM(CB12:CB15) -> 2146 | CC11: =SUM(CC12:CC15) -> 2484 | CD11: =SUM(CD12:CD15) -> 3457 | ... DB11: =SUM(DB12:DB15) -> 6427.5063
A12: RE Gencos (Incl. CSL) | X12: =SUM(BW12:BZ12) -> 3206 | Y12: =SUM(CA12:CD12) -> 3427 | Z12: =SUM(CE12:CH12) -> 3809 | AA12: =SUM(CI12:CL12) -> 4130 | AB12: =SUM(CM12:CP12) -> 4543 | AC12: =SUM(CQ12:CT12) -> 4997.3 | AD12: =SUM(CU12:CX12) -> 5746.895 | AE12: =SUM(CY12:DB12) -> 6608.9293 | BW12: 905 | BX12: 806 | BY12: 704 | BZ12: 791 | CA12: 933 | CB12: 910 | CC12: 737 | CD12: 847 | CE12: 1002 | CF12: 959 | CG12: 827 | CH12: 1021 | CI12: 1135 | CJ12: 991 | CK12: 978 | CL12: 1026 | CM12: =CI12*(1+CM38) -> 1248.5 | CN12: =CJ12*(1+CN38) -> 1090.1 | CO12: =CK12*(1+CO38) -> 1075.8 | CP12: =CL12*(1+CP38) -> 1128.6 | CQ12: =CM12*(1+CQ38) -> 1373.35 | CR12: =CN12*(1+CR38) -> 1199.11 | CS12: =CO12*(1+CS38) -> 1183.38 | CT12: =CP12*(1+CT38) -> 1241.46 | ... DB12: =CX12*(1+DB38) -> 1641.8309
A13: Solar EPC (TPSSL) | X13: =SUM(BW13:BZ13) -> 6876 | Y13: =SUM(CA13:CD13) -> 11726 | Z13: =SUM(CE13:CH13) -> 10043 | AA13: =SUM(CI13:CL13) -> 9797 | AB13: =SUM(CM13:CP13) -> 10874.67 | AC13: =SUM(CQ13:CT13) -> 12070.884 | AD13: =SUM(CU13:CX13) -> 13881.516 | AE13: =SUM(CY13:DB13) -> 15963.744 | BW13: 1353 | BX13: 1135 | BY13: 1430 | BZ13: 2958 | CA13: 1492 | CB13: 1910 | CC13: 4037 | CD13: 4287 | CE13: 2171 | CF13: 3013 | CG13: 1749 | CH13: 3110 | CI13: 2508 | CJ13: 2667 | CK13: 2414 | CL13: 2208 | CM13: =CI13*(1+CM39) -> 2783.88 | CN13: =CJ13*(1+CN39) -> 2960.37 | CO13: =CK13*(1+CO39) -> 2679.54 | CP13: =CL13*(1+CP39) -> 2450.88 | CQ13: =CM13*(1+CQ39) -> 3090.1068 | CR13: =CN13*(1+CR39) -> 3286.0107 | CS13: =CO13*(1+CS39) -> 2974.2894 | CT13: =CP13*(1+CT39) -> 2720.4768 | ... DB13: =CX13*(1+DB39) -> 3597.8306
A14: TP solar (4.3GW cell & module manufacturing plant | X14: =SUM(BW14:BZ14) -> 0 | Y14: =SUM(CA14:CD14) -> 233 | Z14: =SUM(CE14:CH14) -> 5337 | AA14: =SUM(CI14:CL14) -> 6968 | AB14: =SUM(CM14:CP14) -> 7734.48 | AC14: =SUM(CQ14:CT14) -> 8585.2728 | AD14: =SUM(CU14:CX14) -> 9873.0637 | AE14: =SUM(CY14:DB14) -> 11354.023 | CA14: 0 | CB14: 0 | CC14: 0 | CD14: 233 | CE14: 1068 | CF14: 1410 | CG14: 1353 | CH14: 1506 | CI14: 1613 | CJ14: 1772 | CK14: 1704 | CL14: 1879 | CM14: =CI14*(1+CM40) -> 1790.43 | CN14: =CJ14*(1+CN40) -> 1966.92 | CO14: =CK14*(1+CO40) -> 1891.44 | CP14: =CL14*(1+CP40) -> 2085.69 | CQ14: =CM14*(1+CQ40) -> 1987.3773 | CR14: =CN14*(1+CR40) -> 2183.2812 | CS14: =CO14*(1+CS40) -> 2099.4984 | CT14: =CP14*(1+CT40) -> 2315.1159 | ... DB14: =CX14*(1+DB40) -> 3061.7408
A15: Others (Incl. eliminations#) | X15: =SUM(BW15:BZ15) -> -1885 | Y15: =SUM(CA15:CD15) -> -5210 | Z15: =SUM(CE15:CH15) -> -9306 | AA15: =SUM(CI15:CL15) -> -5869 | AB15: =SUM(CM15:CP15) -> -5254.2075 | AC15: =SUM(CQ15:CT15) -> -5810.7568 | AD15: =SUM(CU15:CX15) -> -6640.0977 | AE15: =SUM(CY15:DB15) -> -7635.7699 | BW15: -168 | BX15: -338 | BY15: -217 | BZ15: -1162 | CA15: -336 | CB15: -674 | CC15: -2290 | CD15: -1910 | CE15: -1858 | CF15: -3462 | CG15: -1806 | CH15: -2180 | CI15: -1631 | CJ15: -1817 | CK15: -1312 | CL15: -1109 | CM15: =CL11*-30% -> -1201.2 | CN15: =CM11*-30% -> -1386.483 | CO15: =CN11*-30% -> -1389.2721 | CP15: =CO11*-30% -> -1277.2524 | CQ15: =CP11*-30% -> -1316.3753 | CR15: =CQ11*-30% -> -1540.3376 | CS15: =CR11*-30% -> -1538.4193 | CT15: =CS11*-30% -> -1415.6246 | ... DB15: =DA11*-30% -> -1873.8959
A17: Transmission & Distribution Services | X17: =SUM(X18:X19) -> 34533 | Y17: =SUM(Y18:Y19) -> 36206 | Z17: =SUM(Z18:Z19) -> 39122 | AA17: =SUM(AA18:AA19) -> 40890 | AB17: =SUM(AB18:AB19) -> 42617.81 | AC17: =SUM(AC18:AC19) -> 44486.497 | AD17: =SUM(AD18:AD19) -> 46669.139 | AE17: =SUM(AE18:AE19) -> 49050.704 | BW17: =SUM(BW18:BW19) -> 8961 | BX17: =SUM(BX18:BX19) -> 9020 | BY17: =SUM(BY18:BY19) -> 8256 | BZ17: =SUM(BZ18:BZ19) -> 8296 | CA17: =SUM(CA18:CA19) -> 9277 | CB17: =SUM(CB18:CB19) -> 9453 | CC17: =SUM(CC18:CC19) -> 8451 | CD17: =SUM(CD18:CD19) -> 9025 | ... DB17: =SUM(DB18:DB19) -> 12348.488
A18: Transmission | X18: =SUM(BW18:BZ18) -> 1111 | Y18: =SUM(CA18:CD18) -> 1261 | Z18: =SUM(CE18:CH18) -> 1413 | AA18: =SUM(CI18:CL18) -> 1354 | AB18: =SUM(CM18:CP18) -> 1394.62 | AC18: =SUM(CQ18:CT18) -> 1436.4586 | AD18: =SUM(CU18:CX18) -> 1479.5524 | AE18: =SUM(CY18:DB18) -> 1523.9389 | BW18: 249 | BX18: 249 | BY18: 254 | BZ18: 359 | CA18: 298 | CB18: 288 | CC18: 296 | CD18: 379 | CE18: 329 | CF18: 336 | CG18: 329 | CH18: 419 | CI18: 317 | CJ18: 309 | CK18: 314 | CL18: 414 | CM18: =CI18*(1+CM43) -> 326.51 | CN18: =CJ18*(1+CN43) -> 318.27 | CO18: =CK18*(1+CO43) -> 323.42 | CP18: =CL18*(1+CP43) -> 426.42 | CQ18: =CM18*(1+CQ43) -> 336.3053 | CR18: =CN18*(1+CR43) -> 327.8181 | CS18: =CO18*(1+CS43) -> 333.1226 | CT18: =CP18*(1+CT43) -> 439.2126 | ... DB18: =CX18*(1+DB43) -> 465.96065
A19: Distribution and Services | X19: =SUM(X20:X23) -> 33422 | Y19: =SUM(Y20:Y23) -> 34945 | Z19: =SUM(Z20:Z23) -> 37709 | AA19: =SUM(AA20:AA23) -> 39536 | AB19: =SUM(AB20:AB23) -> 41223.19 | AC19: =SUM(AC20:AC23) -> 43050.038 | AD19: =SUM(AD20:AD23) -> 45189.587 | AE19: =SUM(AE20:AE23) -> 47526.765 | BW19: =SUM(BW20:BW23) -> 8712 | BX19: =SUM(BX20:BX23) -> 8771 | BY19: =SUM(BY20:BY23) -> 8002 | BZ19: =SUM(BZ20:BZ23) -> 7937 | CA19: =SUM(CA20:CA23) -> 8979 | CB19: =SUM(CB20:CB23) -> 9165 | CC19: =SUM(CC20:CC23) -> 8155 | CD19: =SUM(CD20:CD23) -> 8646 | ... DB19: =SUM(DB20:DB23) -> 11882.527
A20: Mumbai | X20: =SUM(BW20:BZ20) -> 4972 | Y20: =SUM(CA20:CD20) -> 4388 | Z20: =SUM(CE20:CH20) -> 4418 | AA20: =SUM(CI20:CL20) -> 4569 | AB20: =SUM(CM20:CP20) -> 4934.52 | AC20: =SUM(CQ20:CT20) -> 5329.2816 | AD20: =SUM(CU20:CX20) -> 5915.5026 | AE20: =SUM(CY20:DB20) -> 6566.2079 | BW20: 1444 | BX20: 1227 | BY20: 1206 | BZ20: 1095 | CA20: 1183 | CB20: 1057 | CC20: 1089 | CD20: 1059 | CE20: 1240 | CF20: 1146 | CG20: 972 | CH20: 1060 | CI20: 1178 | CJ20: 1129 | CK20: 1091 | CL20: 1171 | CM20: =CI20*(1+CM45) -> 1272.24 | CN20: =CJ20*(1+CN45) -> 1219.32 | CO20: =CK20*(1+CO45) -> 1178.28 | CP20: =CL20*(1+CP45) -> 1264.68 | CQ20: =CM20*(1+CQ45) -> 1374.0192 | CR20: =CN20*(1+CR45) -> 1316.8656 | CS20: =CO20*(1+CS45) -> 1272.5424 | CT20: =CP20*(1+CT45) -> 1365.8544 | ... DB20: =CX20*(1+DB45) -> 1682.8692
A21: Odisha | X21: =SUM(BW21:BZ21) -> 16460 | Y21: =SUM(CA21:CD21) -> 18435 | Z21: =SUM(CE21:CH21) -> 19692 | AA21: =SUM(CI21:CL21) -> 19998 | AB21: =SUM(CM21:CP21) -> 20197.98 | AC21: =SUM(CQ21:CT21) -> 20399.96 | AD21: =SUM(CU21:CX21) -> 20603.959 | AE21: =SUM(CY21:DB21) -> 20809.999 | BW21: 3961 | BX21: 4226 | BY21: 4096 | BZ21: 4177 | CA21: 4622 | CB21: 4678 | CC21: 4396 | CD21: 4739 | CE21: 5156 | CF21: 4815 | CG21: 4589 | CH21: 5132 | CI21: 5164 | CJ21: 5198 | CK21: 4621 | CL21: 5015 | CM21: =CI21*(1+CM46) -> 5215.64 | CN21: =CJ21*(1+CN46) -> 5249.98 | CO21: =CK21*(1+CO46) -> 4667.21 | CP21: =CL21*(1+CP46) -> 5065.15 | CQ21: =CM21*(1+CQ46) -> 5267.7964 | CR21: =CN21*(1+CR46) -> 5302.4798 | CS21: =CO21*(1+CS46) -> 4713.8821 | CT21: =CP21*(1+CT46) -> 5115.8015 | ... DB21: =CX21*(1+DB46) -> 5218.6291
A22: Delhi | X22: =SUM(BW22:BZ22) -> 10381 | Y22: =SUM(CA22:CD22) -> 10027 | Z22: =SUM(CE22:CH22) -> 10303 | AA22: =SUM(CI22:CL22) -> 10800 | AB22: =SUM(CM22:CP22) -> 11880 | AC22: =SUM(CQ22:CT22) -> 13068 | AD22: =SUM(CU22:CX22) -> 14374.8 | AE22: =SUM(CY22:DB22) -> 15812.28 | BW22: 3124 | BX22: 2964 | BY22: 2236 | BZ22: 2057 | CA22: 2805 | CB22: 2940 | CC22: 2231 | CD22: 2051 | CE22: 2992 | CF22: 3105 | CG22: 2182 | CH22: 2024 | CI22: 2400 | CJ22: 3147 | CK22: 2460 | CL22: 2793 | CM22: =CI22*(1+CM47) -> 2640 | CN22: =CJ22*(1+CN47) -> 3461.7 | CO22: =CK22*(1+CO47) -> 2706 | CP22: =CL22*(1+CP47) -> 3072.3 | CQ22: =CM22*(1+CQ47) -> 2904 | CR22: =CN22*(1+CR47) -> 3807.87 | CS22: =CO22*(1+CS47) -> 2976.6 | CT22: =CP22*(1+CT47) -> 3379.53 | ... DB22: =CX22*(1+DB47) -> 4089.2313
A23: Others (T&D incl, TPADL, TPTCL and eliminations) | X23: =SUM(BW23:BZ23) -> 1609 | Y23: =SUM(CA23:CD23) -> 2095 | Z23: =SUM(CE23:CH23) -> 3296 | AA23: =SUM(CI23:CL23) -> 4169 | AB23: =SUM(CM23:CP23) -> 4210.69 | AC23: =SUM(CQ23:CT23) -> 4252.7969 | AD23: =SUM(CU23:CX23) -> 4295.3249 | AE23: =SUM(CY23:DB23) -> 4338.2781 | BW23: 183 | BX23: 354 | BY23: 464 | BZ23: 608 | CA23: 369 | CB23: 490 | CC23: 439 | CD23: 797 | CE23: 755 | CF23: 804 | CG23: 781 | CH23: 956 | CI23: 1019 | CJ23: 1153 | CK23: 1140 | CL23: 857 | CM23: =CI23*(1+CM48) -> 1029.19 | CN23: =CJ23*(1+CN48) -> 1164.53 | CO23: =CK23*(1+CO48) -> 1151.4 | CP23: =CL23*(1+CP48) -> 865.57 | CQ23: =CM23*(1+CQ48) -> 1039.4819 | CR23: =CN23*(1+CR48) -> 1176.1753 | CS23: =CO23*(1+CS48) -> 1162.914 | CT23: =CP23*(1+CT48) -> 874.2257 | ... DB23: =CX23*(1+DB48) -> 891.79764
A25: Others (Incl. Tata Projects, Nelco and inter cluster eliminations#) | X25: =SUM(BW25:BZ25) -> -4907 | Y25: =SUM(CA25:CD25) -> -4453 | Z25: =SUM(CE25:CH25) -> -4242 | AA25: =SUM(CI25:CL25) -> -4327 | BW25: -1399 | BX25: -1295 | BY25: -1203 | BZ25: -1010 | CA25: -1190 | CB25: -1130 | CC25: -1052 | CD25: -1081 | CE25: -1263 | CF25: -1190 | CG25: -782 | CH25: -1007 | CI25: -1084 | CJ25: -1116 | CK25: -949 | CL25: =145-1323 -> -1178
A26: Others (total movement in regulatory deferral balances | X26: =SUM(BW26:BZ26) -> 925.92 | Y26: =SUM(CA26:CD26) -> -524.26 | Z26: =SUM(CE26:CH26) -> -975.23 | AA26: =SUM(CI26:CL26) -> 792.74 | BW26: 281.52 | BX26: 131.28 | BY26: 210.88 | BZ26: 302.24 | CA26: -210.29 | CB26: -296.03 | CC26: 190 | CD26: -207.94 | CE26: -484.62 | CF26: -451.67 | CG26: -272.06 | CH26: 233.12 | CI26: -572.07 | CJ26: 218.09 | CK26: 536.92 | CL26: 609.8
A27: Total | X27: =X5+X11+X17+X25-X26 -> 55109.08 | Y27: =Y5+Y11+Y17+Y25-Y26 -> 62066.26 | Z27: =Z5+Z11+Z17+Z25-Z26 -> 65478.23 | AA27: =AA5+AA11+AA17+AA25-AA26 -> 62426.26 | AB27: =AB17+AB11+AB5 -> 78342.753 | AC27: =AC17+AC11+AC5 -> 84881.197 | AD27: =AD17+AD11+AD5 -> 90082.516 | AE27: =AE17+AE11+AE5 -> 95893.63 | BW27: =BW5+BW11+BW17+BW25-BW26 -> 14495.48 | BX27: =BX5+BX11+BX17+BX25-BX26 -> 14030.72 | BY27: =BY5+BY11+BY17+BY25-BY26 -> 14129.12 | BZ27: =BZ5+BZ11+BZ17+BZ25-BZ26 -> 12453.76 | CA27: =CA5+CA11+CA17+CA25-CA26 -> 15213.29 | CB27: =CB5+CB11+CB17+CB25-CB26 -> 15738.03 | CC27: =CC5+CC11+CC17+CC25-CC26 -> 14651 | CD27: =CD5+CD11+CD17+CD25-CD26 -> 16463.94 | ... CL27: =CL5+CL11+CL17+CL25-CL26 -> 14900.2 | CM27: =CM5+CM11+CM17 -> 17444.19 | CN27: =CN5+CN11+CN17 -> 21397.707 | CO27: =CO5+CO11+CO17 -> 19259.818 | CP27: =CP5+CP11+CP17 -> 20241.038 | CQ27: =CQ5+CQ11+CQ17 -> 21120.062 | CR27: =CR5+CR11+CR17 -> 22412.273 | CS27: =CS5+CS11+CS17 -> 20153.81 | CT27: =CT5+CT11+CT17 -> 21195.052 | ... DB27: =DB5+DB11+DB17 -> 23934.994
A28: checksum | X28: =X27-X101 -> 0 | Y28: =Y27-Y101 -> 617.36 | Z28: =Z27-Z101 -> -0.01 | AA28: =AA27-AA101 -> -2.33 | AB28: =AB27-AB101 -> 0 | AC28: =AC27-AC101 -> 0 | AD28: =AD27-AD101 -> 0 | AE28: =AE27-AE101 -> 0 | BW28: =BW27-BW101 -> 0 | BX28: =BX27-BX101 -> 0 | BY28: =BY27-BY101 -> 0 | BZ28: =BZ27-BZ101 -> 0 | CA28: =CA27-CA101 -> 0 | CB28: =CB27-CB101 -> 0 | CC28: =CC27-CC101 -> 0 | CD28: =CD27-CD101-CD127 -> -1.2505552e-12 | CE28: =CE27-CE101 -> 0 | CF28: =CF27-CF101 -> 0 | CG28: =CG27-CG101 -> 0 | CH28: =CH27-CH101 -> 0 | CI28: =CI27-CI101 -> 0 | CJ28: =CJ27-CJ101 -> 0 | CK28: =CK27-CK101 -> -2.33 | CL28: =CL27-CL101 -> 0
A30: Growth Y-o-Y %
A31: Thermal Generation, Coal and Hydro % | Y31: =Y5/X5-1 -> 0.076927301 | Z31: =Z5/Y5-1 -> 0.006475297 | AA31: =AA5/Z5-1 -> -0.41084093 | AB31: =AB5/AA5-1 -> 0.53284609 | AC31: =AC5/AB5-1 -> 0.15285802 | AD31: =AD5/AC5-1 -> 0 | AE31: =AE5/AD5-1 -> 0 | CA31: =CA5/BW5-1 -> -0.058146341 | CB31: =CB5/BX5-1 -> 0.028754655 | CC31: =CC5/BY5-1 -> -0.076722533 | CD31: =CD5/BZ5-1 -> 0.68400971 | CE31: =CE5/CA5-1 -> 0.080795525 | CF31: =CF5/CB5-1 -> -0.13331993 | CG31: =CG5/CC5-1 -> -0.0066559096 | CH31: =CH5/CD5-1 -> 0.089186406 | ... DB31: =DB5/CX5-1 -> 0
A32: Maithon Power Limited (MPL) % | Y32: =Y6/X6-1 -> 0.10894685 | Z32: =Z6/Y6-1 -> -0.12027389 | AA32: =AA6/Z6-1 -> 0.047377327 | AB32: =AB6/AA6-1 -> 0 | AC32: =AC6/AB6-1 -> 0 | AD32: =AD6/AC6-1 -> 0 | AE32: =AE6/AD6-1 -> 0 | CA32: =CA6/BW6-1 -> 0.12732095 | CB32: =CB6/BX6-1 -> -0.060493827 | CC32: =CC6/BY6-1 -> 0.044499382 | CD32: =CD6/BZ6-1 -> 0.37652439 | CE32: =CE6/CA6-1 -> -0.036470588 | CF32: =CF6/CB6-1 -> 0.0078843627 | CG32: =CG6/CC6-1 -> -0.24260355 | CH32: =CH6/CD6-1 -> -0.19269103 | ... DB32: =DB6/CX6-1 -> 0
A33: Traditional Generation (incl. Mumbai and Hydro) % | Y33: =Y7/X7-1 -> -0.14584544 | Z33: =Z7/Y7-1 -> -0.10510204 | AA33: =AA7/Z7-1 -> -0.02622577 | AB33: =AB7/AA7-1 -> 0 | AC33: =AC7/AB7-1 -> 0 | AD33: =AD7/AC7-1 -> 0 | AE33: =AE7/AD7-1 -> 0 | CA33: =CA7/BW7-1 -> -0.19312437 | CB33: =CB7/BX7-1 -> -0.17565217 | CC33: =CC7/BY7-1 -> -0.12926391 | CD33: =CD7/BZ7-1 -> -0.068211921 | CE33: =CE7/CA7-1 -> -0.020676692 | CF33: =CF7/CB7-1 -> -0.014064698 | CG33: =CG7/CC7-1 -> -0.3628866 | CH33: =CH7/CD7-1 -> -0.026297086 | ... DB33: =DB7/CX7-1 -> 0
A34: Others (Incl. eliminations) % | Y34: =Y8/X8-1 -> 0.0076923077 | Z34: =Z8/Y8-1 -> -0.038167939 | AA34: =AA8/Z8-1 -> 0.055555556 | AB34: =AB8/AA8-1 -> 0 | AC34: =AC8/AB8-1 -> 0 | AD34: =AD8/AC8-1 -> 0 | AE34: =AE8/AD8-1 -> 0 | CA34: =CA8/BW8-1 -> 0 | CB34: =CB8/BX8-1 -> 0.13333333 | CC34: =CC8/BY8-1 -> 0.029411765 | CD34: =CD8/BZ8-1 -> -0.11764706 | CE34: =CE8/CA8-1 -> 0 | CF34: =CF8/CB8-1 -> -0.088235294 | CG34: =CG8/CC8-1 -> -0.057142857 | CH34: =CH8/CD8-1 -> 0 | ... DB34: =DB8/CX8-1 -> 0
A35: Mundra, Coal and Shipping % | Y35: =Y9/X9-1 -> 0.25388664 | Z35: =Z9/Y9-1 -> 0.11266231 | AA35: =AA9/Z9-1 -> -0.71238045 | AB35: =AB9/AA9-1 -> 1.890482 | AC35: =AC9/AB9-1 -> 0.28759894 | AD35: =AD9/AC9-1 -> 0 | AE35: =AE9/AD9-1 -> 0 | CA35: =CA9/BW9-1 -> -0.0050825921 | CB35: =CB9/BX9-1 -> 0.214632 | CC35: =CC9/BY9-1 -> -0.081582633 | CD35: =CD9/BZ9-1 -> 2.682284 | CE35: =CE9/CA9-1 -> 0.19327373 | CF35: =CF9/CB9-1 -> -0.23439768 | CG35: =CG9/CC9-1 -> 0.26763248 | CH35: =CH9/CD9-1 -> 0.25606362 | ... DB35: =DB9/CX9-1 -> 0
A37: Renewables % | Y37: =Y11/X11-1 -> 0.24142979 | Z37: =Z11/Y11-1 -> -0.028793239 | AA37: =AA11/Z11-1 -> 0.52038855 | AB37: =AB11/AA11-1 -> 0.19113154 | AC37: =AC11/AB11-1 -> 0.10865814 | AD37: =AD11/AC11-1 -> 0.15213039 | AE37: =AE11/AD11-1 -> 0.15001498 | CA37: =CA11/BW11-1 -> -0.0004784689 | CB37: =CB11/BX11-1 -> 0.33873986 | CC37: =CC11/BY11-1 -> 0.29577465 | CD37: =CD11/BZ11-1 -> 0.33629687 | CE37: =CE11/CA11-1 -> 0.14073719 | CF37: =CF11/CB11-1 -> -0.10531221 | CG37: =CG11/CC11-1 -> -0.14533011 | CH37: =CH11/CD11-1 -> 0 | ... DB37: =DB11/CX11-1 -> 0.14999783
A38: RE Gencos (Incl. CSL) % | Y38: =Y12/X12-1 -> 0.06893325 | Z38: =Z12/Y12-1 -> 0.11146776 | AA38: =AA12/Z12-1 -> 0.084274088 | AB38: =AB12/AA12-1 -> 0.1 | AC38: =AC12/AB12-1 -> 0.1 | AD38: =AD12/AC12-1 -> 0.15 | AE38: =AE12/AD12-1 -> 0.15 | CA38: =CA12/BW12-1 -> 0.030939227 | CB38: =CB12/BX12-1 -> 0.12903226 | CC38: =CC12/BY12-1 -> 0.046875 | CD38: =CD12/BZ12-1 -> 0.07079646 | CE38: =CE12/CA12-1 -> 0.073954984 | CF38: =CF12/CB12-1 -> 0.053846154 | CG38: =CG12/CC12-1 -> 0.12211669 | CH38: =CH12/CD12-1 -> 0.20543093 | ... CL38: =CL12/CH12-1 -> 0.0048971596 | CM38: 0.1 | CN38: 0.1 | CO38: 0.1 | CP38: 0.1 | CQ38: 0.1 | CR38: 0.1 | CS38: 0.1 | CT38: 0.1 | CU38: 0.15 | CV38: 0.15 | CW38: 0.15 | CX38: 0.15 | CY38: 0.15 | CZ38: 0.15 | DA38: 0.15 | DB38: 0.15
A39: Solar EPC (TPSSL) % | Y39: =Y13/X13-1 -> 0.70535195 | Z39: =Z13/Y13-1 -> -0.1435272 | AA39: =AA13/Z13-1 -> -0.024494673 | AB39: =AB13/AA13-1 -> 0.11 | AC39: =AC13/AB13-1 -> 0.11 | AD39: =AD13/AC13-1 -> 0.15 | AE39: =AE13/AD13-1 -> 0.15 | CA39: =CA13/BW13-1 -> 0.10273466 | CB39: =CB13/BX13-1 -> 0.68281938 | CC39: =CC13/BY13-1 -> 1.8230769 | CD39: =CD13/BZ13-1 -> 0.44929006 | CE39: =CE13/CA13-1 -> 0.45509383 | CF39: =CF13/CB13-1 -> 0.57748691 | CG39: =CG13/CC13-1 -> -0.56675749 | CH39: =CH13/CD13-1 -> -0.27455097 | ... CL39: =CL13/CH13-1 -> -0.29003215 | CM39: 0.11 | CN39: 0.11 | CO39: 0.11 | CP39: 0.11 | CQ39: 0.11 | CR39: 0.11 | CS39: 0.11 | CT39: 0.11 | CU39: 0.15 | CV39: 0.15 | CW39: 0.15 | CX39: 0.15 | CY39: 0.15 | CZ39: 0.15 | DA39: 0.15 | DB39: 0.15
A40: TP solar (4.3GW cell & module manufacturing plant % | Y40: =Y14/X14-1 -> #DIV/0! | Z40: =Z14/Y14-1 -> 21.905579 | AA40: =AA14/Z14-1 -> 0.3056024 | AB40: =AB14/AA14-1 -> 0.11 | AC40: =AC14/AB14-1 -> 0.11 | AD40: =AD14/AC14-1 -> 0.15 | AE40: =AE14/AD14-1 -> 0.15 | CA40: =CA14/BW14-1 -> #DIV/0! | CB40: =CB14/BX14-1 -> #DIV/0! | CC40: =CC14/BY14-1 -> #DIV/0! | CD40: =CD14/BZ14-1 -> #DIV/0! | CE40: =CE14/CA14-1 -> #DIV/0! | CF40: =CF14/CB14-1 -> #DIV/0! | CG40: =CG14/CC14-1 -> #DIV/0! | CH40: =CH14/CD14-1 -> 5.4635193 | ... CL40: =CL14/CH14-1 -> 0.24767596 | CM40: 0.11 | CN40: 0.11 | CO40: 0.11 | CP40: 0.11 | CQ40: 0.11 | CR40: 0.11 | CS40: 0.11 | CT40: 0.11 | CU40: 0.15 | CV40: 0.15 | CW40: 0.15 | CX40: 0.15 | CY40: 0.15 | CZ40: 0.15 | DA40: 0.15 | DB40: 0.15
A42: Transmission & Distribution Services % | Y42: =Y17/X17-1 -> 0.048446414 | Z42: =Z17/Y17-1 -> 0.080539137 | AA42: =AA17/Z17-1 -> 0.045191964 | AB42: =AB17/AA17-1 -> 0.042255075 | AC42: =AC17/AB17-1 -> 0.043847558 | AD42: =AD17/AC17-1 -> 0.049063029 | AE42: =AE17/AD17-1 -> 0.051030825 | CA42: =CA17/BW17-1 -> 0.035263921 | CB42: =CB17/BX17-1 -> 0.048004435 | CC42: =CC17/BY17-1 -> 0.023619186 | CD42: =CD17/BZ17-1 -> 0.087873674 | CE42: =CE17/CA17-1 -> 0.12881319 | CF42: =CF17/CB17-1 -> 0.079657252 | CG42: =CG17/CC17-1 -> 0.047568335 | CH42: =CH17/CD17-1 -> 0.062714681 | ... CL42: =CL17/CH17-1 -> 0.068710249 | CM42: 0.05 | CN42: 0.05 | CO42: 0.05 | CP42: 0.05 | CQ42: 0.08 | CR42: 0.08 | CS42: 0.08 | CT42: 0.08 | CU42: 0.08 | CV42: 0.08 | CW42: 0.08 | CX42: 0.08 | CY42: 0.08 | CZ42: 0.08 | DA42: 0.08 | DB42: 0.08
A43: Transmission % | Y43: =Y18/X18-1 -> 0.1350135 | Z43: =Z18/Y18-1 -> 0.12053925 | AA43: =AA18/Z18-1 -> -0.041755131 | AB43: =AB18/AA18-1 -> 0.03 | AC43: =AC18/AB18-1 -> 0.03 | AD43: =AD18/AC18-1 -> 0.03 | AE43: =AE18/AD18-1 -> 0.03 | CA43: =CA18/BW18-1 -> 0.19678715 | CB43: =CB18/BX18-1 -> 0.15662651 | CC43: =CC18/BY18-1 -> 0.16535433 | CD43: =CD18/BZ18-1 -> 0.055710306 | CE43: =CE18/CA18-1 -> 0.10402685 | CF43: =CF18/CB18-1 -> 0.16666667 | CG43: =CG18/CC18-1 -> 0.11148649 | CH43: =CH18/CD18-1 -> 0.1055409 | ... CL43: =CL18/CH18-1 -> -0.011933174 | CM43: 0.03 | CN43: 0.03 | CO43: 0.03 | CP43: 0.03 | CQ43: 0.03 | CR43: 0.03 | CS43: 0.03 | CT43: 0.03 | CU43: 0.03 | CV43: 0.03 | CW43: 0.03 | CX43: 0.03 | CY43: 0.03 | CZ43: 0.03 | DA43: 0.03 | DB43: 0.03
A44: Distribution and Services % | Y44: =Y19/X19-1 -> 0.045568787 | Z44: =Z19/Y19-1 -> 0.079095722 | AA44: =AA19/Z19-1 -> 0.048449972 | AB44: =AB19/AA19-1 -> 0.042674777 | AC44: =AC19/AB19-1 -> 0.044316034 | AD44: =AD19/AC19-1 -> 0.049699109 | AE44: =AE19/AD19-1 -> 0.051719396 | CA44: =CA19/BW19-1 -> 0.030647383 | CB44: =CB19/BX19-1 -> 0.044920762 | CC44: =CC19/BY19-1 -> 0.01912022 | CD44: =CD19/BZ19-1 -> 0.089328462 | CE44: =CE19/CA19-1 -> 0.12963582 | CF44: =CF19/CB19-1 -> 0.076923077 | CG44: =CG19/CC19-1 -> 0.045248314 | CH44: =CH19/CD19-1 -> 0.060837381 | ... DB44: =DB19/CX19-1 -> 0.053087954
A45: Mumbai % | Y45: =Y20/X20-1 -> -0.11745776 | Z45: =Z20/Y20-1 -> 0.0068368277 | AA45: =AA20/Z20-1 -> 0.034178361 | AB45: =AB20/AA20-1 -> 0.08 | AC45: =AC20/AB20-1 -> 0.08 | AD45: =AD20/AC20-1 -> 0.11 | AE45: =AE20/AD20-1 -> 0.11 | CA45: =CA20/BW20-1 -> -0.18074792 | CB45: =CB20/BX20-1 -> -0.13854931 | CC45: =CC20/BY20-1 -> -0.097014925 | CD45: =CD20/BZ20-1 -> -0.032876712 | CE45: =CE20/CA20-1 -> 0.048182587 | CF45: =CF20/CB20-1 -> 0.084200568 | CG45: =CG20/CC20-1 -> -0.10743802 | CH45: =CH20/CD20-1 -> 0.00094428706 | ... CL45: =CL20/CH20-1 -> 0.10471698 | CM45: 0.08 | CN45: 0.08 | CO45: 0.08 | CP45: 0.08 | CQ45: 0.08 | CR45: 0.08 | CS45: 0.08 | CT45: 0.08 | CU45: 0.11 | CV45: 0.11 | CW45: 0.11 | CX45: 0.11 | CY45: 0.11 | CZ45: 0.11 | DA45: 0.11 | DB45: 0.11
A46: Odisha % | Y46: =Y21/X21-1 -> 0.11998785 | Z46: =Z21/Y21-1 -> 0.068185517 | AA46: =AA21/Z21-1 -> 0.015539305 | AB46: =AB21/AA21-1 -> 0.01 | AC46: =AC21/AB21-1 -> 0.01 | AD46: =AD21/AC21-1 -> 0.01 | AE46: =AE21/AD21-1 -> 0.01 | CA46: =CA21/BW21-1 -> 0.16687705 | CB46: =CB21/BX21-1 -> 0.10695693 | CC46: =CC21/BY21-1 -> 0.073242188 | CD46: =CD21/BZ21-1 -> 0.13454633 | CE46: =CE21/CA21-1 -> 0.1155344 | CF46: =CF21/CB21-1 -> 0.02928602 | CG46: =CG21/CC21-1 -> 0.043903549 | CH46: =CH21/CD21-1 -> 0.082928888 | ... CL46: =CL21/CH21-1 -> -0.022798129 | CM46: 0.01 | CN46: 0.01 | CO46: 0.01 | CP46: 0.01 | CQ46: 0.01 | CR46: 0.01 | CS46: 0.01 | CT46: 0.01 | CU46: 0.01 | CV46: 0.01 | CW46: 0.01 | CX46: 0.01 | CY46: 0.01 | CZ46: 0.01 | DA46: 0.01 | DB46: 0.01
A47: Delhi % | Y47: =Y22/X22-1 -> -0.034100761 | Z47: =Z22/Y22-1 -> 0.027525681 | AA47: =AA22/Z22-1 -> 0.048238377 | AB47: =AB22/AA22-1 -> 0.1 | AC47: =AC22/AB22-1 -> 0.1 | AD47: =AD22/AC22-1 -> 0.1 | AE47: =AE22/AD22-1 -> 0.1 | CA47: =CA22/BW22-1 -> -0.10211268 | CB47: =CB22/BX22-1 -> -0.008097166 | CC47: =CC22/BY22-1 -> -0.002236136 | CD47: =CD22/BZ22-1 -> -0.0029168692 | CE47: =CE22/CA22-1 -> 0.066666667 | CF47: =CF22/CB22-1 -> 0.056122449 | CG47: =CG22/CC22-1 -> -0.021963245 | CH47: =CH22/CD22-1 -> -0.01316431 | ... CL47: =CL22/CH22-1 -> 0.37994071 | CM47: 0.1 | CN47: 0.1 | CO47: 0.1 | CP47: 0.1 | CQ47: 0.1 | CR47: 0.1 | CS47: 0.1 | CT47: 0.1 | CU47: 0.1 | CV47: 0.1 | CW47: 0.1 | CX47: 0.1 | CY47: 0.1 | CZ47: 0.1 | DA47: 0.1 | DB47: 0.1
A48: Others (T&D incl, TPADL, TPTCL and eliminations) % | Y48: =Y23/X23-1 -> 0.30205096 | Z48: =Z23/Y23-1 -> 0.57326969 | AA48: =AA23/Z23-1 -> 0.2648665 | AB48: =AB23/AA23-1 -> 0.01 | AC48: =AC23/AB23-1 -> 0.01 | AD48: =AD23/AC23-1 -> 0.01 | AE48: =AE23/AD23-1 -> 0.01 | CA48: =CA23/BW23-1 -> 1.0163934 | CB48: =CB23/BX23-1 -> 0.38418079 | CC48: =CC23/BY23-1 -> -0.05387931 | CD48: =CD23/BZ23-1 -> 0.31085526 | CE48: =CE23/CA23-1 -> 1.0460705 | CF48: =CF23/CB23-1 -> 0.64081633 | CG48: =CG23/CC23-1 -> 0.77904328 | CH48: =CH23/CD23-1 -> 0.19949812 | ... CL48: =CL23/CH23-1 -> -0.10355649 | CM48: 0.01 | CN48: 0.01 | CO48: 0.01 | CP48: 0.01 | CQ48: 0.01 | CR48: 0.01 | CS48: 0.01 | CT48: 0.01 | CU48: 0.01 | CV48: 0.01 | CW48: 0.01 | CX48: 0.01 | CY48: 0.01 | CZ48: 0.01 | DA48: 0.01 | DB48: 0.01
A51: EBITDA
A52: Thermal Generation, Coal and Hydro -EBITDA | X52: =SUM(X53:X56) -> 2908 | Y52: =SUM(Y53:Y56) -> 3778 | Z52: =SUM(Z53:Z56) -> 4183 | BW52: =SUM(BW53:BW56) -> 459 | BX52: =SUM(BX53:BX56) -> 393 | BY52: =SUM(BY53:BY56) -> 1055 | BZ52: =SUM(BZ53:BZ56) -> 1001 | CA52: =SUM(CA53:CA56) -> 988 | CB52: =SUM(CB53:CB56) -> 1120 | CC52: =SUM(CC53:CC56) -> 883 | CD52: =SUM(CD53:CD56) -> 787 | ... CL52: =SUM(CL53:CL56) -> 508
A53: Maithon Power Limited (MPL) -EBITDA | X53: =SUM(BW53:BZ53) -> 778 | Y53: =SUM(CA53:CD53) -> 864 | Z53: =SUM(CE53:CH53) -> 628 | BW53: 188 | BX53: 191 | BY53: 213 | BZ53: 186 | CA53: 294 | CB53: 193 | CC53: 182 | CD53: 195 | CE53: 168 | CF53: 154 | CG53: 147 | CH53: 159 | CI53: 169 | CJ53: 201 | CK53: 213 | CL53: 155
A54: Traditional Generation (incl. Mumbai and Hydro) -EBITDA | X54: =SUM(BW54:BZ54) -> 918 | Y54: =SUM(CA54:CD54) -> 1263 | Z54: =SUM(CE54:CH54) -> 1285 | BW54: 278 | BX54: 235 | BY54: 259 | BZ54: 146 | CA54: 318 | CB54: 326 | CC54: 329 | CD54: 290 | CE54: 388 | CF54: 287 | CG54: 176 | CH54: 434 | CI54: 261 | CJ54: 255 | CK54: 192 | CL54: 205
A55: Others (Incl. eliminations) -EBITDA | X55: =SUM(BW55:BZ55) -> 139 | Y55: =SUM(CA55:CD55) -> 143 | Z55: =SUM(CE55:CH55) -> 147 | BW55: 32 | BX55: 32 | BY55: 37 | BZ55: 38 | CA55: 37 | CB55: 37 | CC55: 37 | CD55: 32 | CE55: 38 | CF55: 35 | CG55: 38 | CH55: 36 | CI55: 33 | CJ55: 42 | CK55: 35 | CL55: 36
A56: Mundra, Coal and Shipping -EBITDA | X56: =SUM(BW56:BZ56) -> 1073 | Y56: =SUM(CA56:CD56) -> 1508 | Z56: =SUM(CE56:CH56) -> 2123 | BW56: -39 | BX56: -65 | BY56: 546 | BZ56: 631 | CA56: 339 | CB56: 564 | CC56: 335 | CD56: 270 | CE56: 354 | CF56: 516 | CG56: 809 | CH56: 444 | CI56: 511 | CJ56: -12 | CK56: -145 | CL56: 112
A58: Renewables -EBITDA | X58: =SUM(X59:X62) -> 3203 | Y58: =SUM(Y59:Y62) -> 3423 | Z58: =SUM(Z59:Z62) -> 4317 | BW58: =SUM(BW59:BW62) -> 778 | BX58: =SUM(BX59:BX62) -> 736 | BY58: =SUM(BY59:BY62) -> 762 | BZ58: =SUM(BZ59:BZ62) -> 927 | CA58: =SUM(CA59:CA62) -> 907 | CB58: =SUM(CB59:CB62) -> 813 | CC58: =SUM(CC59:CC62) -> 757 | CD58: =SUM(CD59:CD62) -> 946 | ... CL58: =SUM(CL59:CL62) -> 1449
A59: RE Gencos (Incl. CSL) -EBITDA | X59: =SUM(BW59:BZ59) -> 2879 | Y59: =SUM(CA59:CD59) -> 2984 | Z59: =SUM(CE59:CH59) -> 3421 | BW59: 795 | BX59: 694 | BY59: 654 | BZ59: 736 | CA59: 875 | CB59: 758 | CC59: 614 | CD59: 737 | CE59: 903 | CF59: 878 | CG59: 744 | CH59: 896 | CI59: 1034 | CJ59: 918 | CK59: 867 | CL59: 821
A60: Solar EPC (TPSSL) -EBITDA | X60: =SUM(BW60:BZ60) -> 498 | Y60: =SUM(CA60:CD60) -> 719 | Z60: =SUM(CE60:CH60) -> 836 | BW60: 15 | BX60: 125 | BY60: 96 | BZ60: 262 | CA60: 64 | CB60: 128 | CC60: 203 | CD60: 324 | CE60: 80 | CF60: 242 | CG60: 280 | CH60: 234 | CI60: 287 | CJ60: 301 | CK60: 269 | CL60: 203
A61: TP solar (4.3GW cell & module manufacturing plant -EBITDA | X61: =SUM(BW61:BZ61) -> 0 | Y61: =SUM(CA61:CD61) -> 4 | Z61: =SUM(CE61:CH61) -> 874 | BW61: 0 | BX61: 0 | BY61: 0 | BZ61: 0 | CA61: 0 | CB61: 0 | CC61: 0 | CD61: 4 | CE61: 114 | CF61: 131 | CG61: 226 | CH61: 403 | CI61: 299 | CJ61: 466 | CK61: 478 | CL61: 501
A62: Others (Incl. eliminations#) -EBITDA | X62: =SUM(BW62:BZ62) -> -174 | Y62: =SUM(CA62:CD62) -> -284 | Z62: =SUM(CE62:CH62) -> -814 | BW62: -32 | BX62: -83 | BY62: 12 | BZ62: -71 | CA62: -32 | CB62: -73 | CC62: -60 | CD62: -119 | CE62: -143 | CF62: -249 | CG62: -261 | CH62: -161 | CI62: -54 | CJ62: -110 | CK62: 24 | CL62: -76
A64: Transmission & Distribution Services -EBITDA | X64: =SUM(X65:X66) -> 3819 | Y64: =SUM(Y65:Y66) -> 4557 | Z64: =SUM(Z65:Z66) -> 5551 | BW64: =SUM(BW65:BW66) -> 807 | BX64: =SUM(BX65:BX66) -> 891 | BY64: =SUM(BY65:BY66) -> 926 | BZ64: =SUM(BZ65:BZ66) -> 1195 | CA64: =SUM(CA65:CA66) -> 1070 | CB64: =SUM(CB65:CB66) -> 1110 | CC64: =SUM(CC65:CC66) -> 1132 | CD64: =SUM(CD65:CD66) -> 1245 | ... CL64: =SUM(CL65:CL66) -> 2070
A65: Transmission -EBITDA | X65: =SUM(BW65:BZ65) -> 799 | Y65: =SUM(CA65:CD65) -> 906 | Z65: =SUM(CE65:CH65) -> 985 | BW65: 179 | BX65: 172 | BY65: 215 | BZ65: 233 | CA65: 218 | CB65: 206 | CC65: 213 | CD65: 269 | CE65: 245 | CF65: 234 | CG65: 239 | CH65: 267 | CI65: 242 | CJ65: 236 | CK65: 268 | CL65: 323
A66: Distribution and Services -EBITDA | X66: =SUM(X67:X70) -> 3020 | Y66: =SUM(Y67:Y70) -> 3651 | Z66: =SUM(Z67:Z70) -> 4566 | BW66: =SUM(BW67:BW70) -> 628 | BX66: =SUM(BX67:BX70) -> 719 | BY66: =SUM(BY67:BY70) -> 711 | BZ66: =SUM(BZ67:BZ70) -> 962 | CA66: =SUM(CA67:CA70) -> 852 | CB66: =SUM(CB67:CB70) -> 904 | CC66: =SUM(CC67:CC70) -> 919 | CD66: =SUM(CD67:CD70) -> 976 | ... CL66: =SUM(CL67:CL70) -> 1747
A67: Mumbai -EBITDA | X67: =SUM(BW67:BZ67) -> 546 | Y67: =SUM(CA67:CD67) -> 635 | Z67: =SUM(CE67:CH67) -> 670 | BW67: 136 | BX67: 144 | BY67: 137 | BZ67: 129 | CA67: 152 | CB67: 153 | CC67: 171 | CD67: 159 | CE67: 164 | CF67: 162 | CG67: 142 | CH67: 202 | CI67: 130 | CJ67: 120 | CK67: 124 | CL67: 139
A68: Odisha -EBITDA | X68: =SUM(BW68:BZ68) -> 1111 | Y68: =SUM(CA68:CD68) -> 1527 | Z68: =SUM(CE68:CH68) -> 2080 | BW68: 160 | BX68: 248 | BY68: 211 | BZ68: 492 | CA68: 336 | CB68: 391 | CC68: 364 | CD68: 436 | CE68: 403 | CF68: 411 | CG68: 498 | CH68: 768 | CI68: 585 | CJ68: 687 | CK68: 777 | CL68: 860
A69: Delhi -EBITDA | X69: =SUM(BW69:BZ69) -> 1306 | Y69: =SUM(CA69:CD69) -> 1337 | Z69: =SUM(CE69:CH69) -> 1649 | BW69: 340 | BX69: 332 | BY69: 329 | BZ69: 305 | CA69: 336 | CB69: 326 | CC69: 325 | CD69: 350 | CE69: 578 | CF69: 582 | CG69: 343 | CH69: 146 | CI69: 332 | CJ69: 562 | CK69: 765 | CL69: 682
A70: Others (T&D incl, TPADL, TPTCL and eliminations) -EBITDA | X70: =SUM(BW70:BZ70) -> 57 | Y70: =SUM(CA70:CD70) -> 152 | Z70: =SUM(CE70:CH70) -> 167 | BW70: -8 | BX70: -5 | BY70: 34 | BZ70: 36 | CA70: 28 | CB70: 34 | CC70: 59 | CD70: 31 | CE70: 44 | CF70: 51 | CG70: 55 | CH70: 17 | CI70: 57 | CJ70: 74 | CK70: 86 | CL70: 66
A72: Others (Incl. Tata Projects, Nelco and inter cluster eliminations#) -EBITDA | X72: =SUM(BW72:BZ72) -> 139 | Y72: =SUM(CA72:CD72) -> 941 | Z72: =SUM(CE72:CH72) -> 414 | BW72: 63 | BX72: 23 | BY72: 75 | BZ72: -22 | CA72: 40 | CB72: 44 | CC72: 476 | CD72: 381 | CE72: 15 | CF72: 373 | CG72: 43 | CH72: -17 | CI72: 44 | CJ72: 291 | CK72: -40 | CL72: 190
A74: Total -EBITDA | X74: =X52+X58+X64+X72 -> 10069 | Y74: =Y52+Y58+Y64+Y72 -> 12699 | Z74: =Z52+Z58+Z64+Z72 -> 14465 | BW74: =BW52+BW58+BW64+BW72 -> 2107 | BX74: =BX52+BX58+BX64+BX72 -> 2043 | BY74: =BY52+BY58+BY64+BY72 -> 2818 | BZ74: =BZ52+BZ58+BZ64+BZ72 -> 3101 | CA74: =CA52+CA58+CA64+CA72 -> 3005 | CB74: =CB52+CB58+CB64+CB72 -> 3087 | CC74: =CC52+CC58+CC64+CC72 -> 3248 | CD74: =CD52+CD58+CD64+CD72 -> 3359 | ... CL74: =CL52+CL58+CL64+CL72 -> 4217
A75: Checksum -EBITDA | X75: =+X74-X120-X127 -> 0.41 | Y75: =+Y74-Y120-Y127 -> -1.88 | Z75: =+Z74-Z120-Z127 -> -2.8 | BW75: =+BW74-BW120-BW127 -> -0.11 | BX75: =+BX74-BX120-BX127 -> 0.16 | BY75: =+BY74-BY120-BY127 -> 0.38 | BZ75: =+BZ74-BZ120-BZ127 -> 0.18 | CA75: =+CA74-CA120-CA127 -> -0.05 | CB75: =+CB74-CB120-CB127 -> 0.12 | CC75: =+CC74-CC120-CC127 -> -2.27 | CD75: =+CD74-CD120-CD127 -> 0.52 | ... CL75: =+CL74-CL120-CL127 -> 0.81
A77: EBITDA Margin %
A78: Thermal Generation, Coal and Hydro % EBITDA margin | X78: =+X52/X5 -> 0.15967494 | Y78: =+Y52/Y5 -> 0.19262734 | Z78: =+Z52/Z5 -> 0.21190476 | BW78: =+BW52/BW5 -> 0.089560976 | BX78: =+BX52/BX5 -> 0.081299131 | BY78: =+BY52/BY5 -> 0.19646182 | BZ78: =+BZ52/BZ5 -> 0.34720777 | CA78: =+CA52/CA5 -> 0.204682 | CB78: =+CB52/CB5 -> 0.22521617 | CC78: =+CC52/CC5 -> 0.17809601 | CD78: =+CD52/CD5 -> 0.16210093 | ... CL78: =+CL52/CL5 -> 0.20870994
A79: Maithon Power Limited (MPL) % EBITDA margin | X79: =+X53/X6 -> 0.25685045 | Y79: =+Y53/Y6 -> 0.25721941 | Z79: =+Z53/Z6 -> 0.21252115 | BW79: =+BW53/BW6 -> 0.24933687 | BX79: =+BX53/BX6 -> 0.23580247 | BY79: =+BY53/BY6 -> 0.26328801 | BZ79: =+BZ53/BZ6 -> 0.28353659 | CA79: =+CA53/CA6 -> 0.34588235 | CB79: =+CB53/CB6 -> 0.25361367 | CC79: =+CC53/CC6 -> 0.21538462 | CD79: =+CD53/CD6 -> 0.21594684 | ... CL79: =+CL53/CL6 -> 0.19375
A80: Traditional Generation (incl. Mumbai and Hydro) % EBITDA margin | X80: =+X54/X7 -> 0.1333527 | Y80: =+Y54/Y7 -> 0.21479592 | Z80: =+Z54/Z7 -> 0.24420372 | BW80: =+BW54/BW7 -> 0.14054601 | BX80: =+BX54/BX7 -> 0.13623188 | BY80: =+BY54/BY7 -> 0.15499701 | BZ80: =+BZ54/BZ7 -> 0.096688742 | CA80: =+CA54/CA7 -> 0.19924812 | CB80: =+CB54/CB7 -> 0.22925457 | CC80: =+CC54/CC7 -> 0.22611684 | CD80: =+CD54/CD7 -> 0.2061123 | ... CL80: =+CL54/CL7 -> 0.15518547
A81: Mundra, Coal and Shipping % EBITDA margin | X81: =+X56/X9 -> 0.13135023 | Y81: =+Y56/Y9 -> 0.14722249 | Z81: =+Z56/Z9 -> 0.18627709 | BW81: =+BW56/BW9 -> -0.016518424 | BX81: =+BX56/BX9 -> -0.028646981 | BY81: =+BY56/BY9 -> 0.19117647 | BZ81: =+BZ56/BZ9 -> 0.9238653 | CA81: =+CA56/CA9 -> 0.14431673 | CB81: =+CB56/CB9 -> 0.20464441 | CC81: =+CC56/CC9 -> 0.12771636 | CD81: =+CD56/CD9 -> 0.10735586 | ... CL81: =+CL56/CL9 -> 0.40727273
A83: Renewables % EBITDA margin | X83: =X58/X11 -> 0.39075271 | Y83: =Y58/Y11 -> 0.33637972 | Z83: =Z58/Z11 -> 0.43681069 | BW83: =BW58/BW11 -> 0.3722488 | BX83: =BX58/BX11 -> 0.45913911 | BY83: =BY58/BY11 -> 0.39749609 | BZ83: =BZ58/BZ11 -> 0.35833011 | CA83: =CA58/CA11 -> 0.43417903 | CB83: =CB58/CB11 -> 0.37884436 | CC83: =CC58/CC11 -> 0.3047504 | CD83: =CD58/CD11 -> 0.27364767 | ... CL83: =CL58/CL11 -> 0.36188811
A84: RE Gencos (Incl. CSL) % EBITDA margin | X84: =X59/X12 -> 0.89800374 | Y84: =Y59/Y12 -> 0.87073242 | Z84: =Z59/Z12 -> 0.89813599 | BW84: =BW59/BW12 -> 0.87845304 | BX84: =BX59/BX12 -> 0.86104218 | BY84: =BY59/BY12 -> 0.92897727 | BZ84: =BZ59/BZ12 -> 0.93046776 | CA84: =CA59/CA12 -> 0.93783494 | CB84: =CB59/CB12 -> 0.83296703 | CC84: =CC59/CC12 -> 0.83310719 | CD84: =CD59/CD12 -> 0.87012987 | ... CL84: =CL59/CL12 -> 0.80019493
A85: Solar EPC (TPSSL) % EBITDA margin | X85: =X60/X13 -> 0.072425829 | Y85: =Y60/Y13 -> 0.061316732 | Z85: =Z60/Z13 -> 0.083242059 | BW85: =BW60/BW13 -> 0.011086475 | BX85: =BX60/BX13 -> 0.11013216 | BY85: =BY60/BY13 -> 0.067132867 | BZ85: =BZ60/BZ13 -> 0.08857336 | CA85: =CA60/CA13 -> 0.042895442 | CB85: =CB60/CB13 -> 0.067015707 | CC85: =CC60/CC13 -> 0.050284865 | CD85: =CD60/CD13 -> 0.075577327 | ... CL85: =CL60/CL13 -> 0.091938406
A86: TP solar (4.3GW cell & module manufacturing plant % EBITDA margin | X86: =X61/X14 -> #DIV/0! | Y86: =Y61/Y14 -> 0.017167382 | Z86: =Z61/Z14 -> 0.16376241 | BW86: =BW61/BW14 -> #DIV/0! | BX86: =BX61/BX14 -> #DIV/0! | BY86: =BY61/BY14 -> #DIV/0! | BZ86: =BZ61/BZ14 -> #DIV/0! | CA86: =CA61/CA14 -> #DIV/0! | CB86: =CB61/CB14 -> #DIV/0! | CC86: =CC61/CC14 -> #DIV/0! | CD86: =CD61/CD14 -> 0.017167382 | ... CL86: =CL61/CL14 -> 0.26663119
A88: Transmission & Distribution Services % EBITDA margin | X88: =X64/X17 -> 0.11058987 | Y88: =Y64/Y17 -> 0.12586312 | Z88: =Z64/Z17 -> 0.14188947 | BW88: =BW64/BW17 -> 0.090056913 | BX88: =BX64/BX17 -> 0.098780488 | BY88: =BY64/BY17 -> 0.11216085 | BZ88: =BZ64/BZ17 -> 0.14404532 | CA88: =CA64/CA17 -> 0.11533901 | CB88: =CB64/CB17 -> 0.11742304 | CC88: =CC64/CC17 -> 0.13394865 | CD88: =CD64/CD17 -> 0.13795014 | ... CL88: =CL64/CL17 -> 0.20195122
A89: Transmission % EBITDA margin | X89: =X65/X18 -> 0.71917192 | Y89: =Y65/Y18 -> 0.7184774 | Z89: =Z65/Z18 -> 0.69709837 | BW89: =BW65/BW18 -> 0.7188755 | BX89: =BX65/BX18 -> 0.69076305 | BY89: =BY65/BY18 -> 0.84645669 | BZ89: =BZ65/BZ18 -> 0.64902507 | CA89: =CA65/CA18 -> 0.73154362 | CB89: =CB65/CB18 -> 0.71527778 | CC89: =CC65/CC18 -> 0.71959459 | CD89: =CD65/CD18 -> 0.70976253 | ... CL89: =CL65/CL18 -> 0.78019324
A90: Distribution and Services % EBITDA margin | X90: =X66/X19 -> 0.090359643 | Y90: =Y66/Y19 -> 0.10447847 | Z90: =Z66/Z19 -> 0.12108515 | BW90: =BW66/BW19 -> 0.072084481 | BX90: =BX66/BX19 -> 0.081974689 | BY90: =BY66/BY19 -> 0.088852787 | BZ90: =BZ66/BZ19 -> 0.12120449 | CA90: =CA66/CA19 -> 0.094888072 | CB90: =CB66/CB19 -> 0.098636116 | CC90: =CC66/CC19 -> 0.1126916 | CD90: =CD66/CD19 -> 0.11288457 | ... CL90: =CL66/CL19 -> 0.17761285
A91: Mumbai % EBITDA margin | X91: =X67/X20 -> 0.10981496 | Y91: =Y67/Y20 -> 0.14471285 | Z91: =Z67/Z20 -> 0.15165233 | BW91: =BW67/BW20 -> 0.094182825 | BX91: =BX67/BX20 -> 0.11735941 | BY91: =BY67/BY20 -> 0.11359867 | BZ91: =BZ67/BZ20 -> 0.11780822 | CA91: =CA67/CA20 -> 0.1284869 | CB91: =CB67/CB20 -> 0.14474929 | CC91: =CC67/CC20 -> 0.15702479 | CD91: =CD67/CD20 -> 0.15014164 | ... CL91: =CL67/CL20 -> 0.11870196
A92: Odisha % EBITDA margin | X92: =X68/X21 -> 0.067496962 | Y92: =Y68/Y21 -> 0.08283157 | Z92: =Z68/Z21 -> 0.10562665 | BW92: =BW68/BW21 -> 0.04039384 | BX92: =BX68/BX21 -> 0.058684335 | BY92: =BY68/BY21 -> 0.051513672 | BZ92: =BZ68/BZ21 -> 0.11778789 | CA92: =CA68/CA21 -> 0.072695803 | CB92: =CB68/CB21 -> 0.083582728 | CC92: =CC68/CC21 -> 0.082802548 | CD92: =CD68/CD21 -> 0.092002532 | ... CL92: =CL68/CL21 -> 0.17148554
A93: Delhi % EBITDA margin | X93: =X69/X22 -> 0.12580676 | Y93: =Y69/Y22 -> 0.13333998 | Z93: =Z69/Z22 -> 0.16005047 | BW93: =BW69/BW22 -> 0.10883483 | BX93: =BX69/BX22 -> 0.1120108 | BY93: =BY69/BY22 -> 0.14713775 | BZ93: =BZ69/BZ22 -> 0.14827419 | CA93: =CA69/CA22 -> 0.1197861 | CB93: =CB69/CB22 -> 0.11088435 | CC93: =CC69/CC22 -> 0.14567459 | CD93: =CD69/CD22 -> 0.17064846 | ... CL93: =CL69/CL22 -> 0.24418188
A97: Presentation Data (End)
A98: Profit & Loss- Annual (Start)
A99: Gross Revenue | B99: ='Annual Raw'!C6 -> 3374.8175 | C99: ='Annual Raw'!D6 -> 3861.06 | D99: ='Annual Raw'!E6 -> 4805.45 | E99: ='Annual Raw'!F6 -> 4996.38 | F99: ='Annual Raw'!G6 -> 4900.58 | G99: ='Annual Raw'!H6 -> 5623.21 | H99: ='Annual Raw'!I6 -> 6484.23 | I99: ='Annual Raw'!J6 -> 10904.19 | ... AA99: ='Annual Raw'!AB6 -> 62428.59 | AB99: =+SUM(CM99:CP99) -> 78342.753 | AC99: =+SUM(CQ99:CT99) -> 84881.197 | AD99: =+SUM(CU99:CX99) -> 90082.516 | AE99: =+SUM(CY99:DB99) -> 95893.63 | AI99: ='QTR Raw'!C6+'QTR Raw'!C8 -> 7253.89 | AJ99: ='QTR Raw'!D6+'QTR Raw'!D8 -> 7699.77 | AK99: ='QTR Raw'!E6+'QTR Raw'!E8 -> 9039.31 | AL99: ='QTR Raw'!F6+'QTR Raw'!F8 -> 9032.46 | AM99: ='QTR Raw'!G6+'QTR Raw'!G8 -> 9339.49 | AN99: ='QTR Raw'!H6+'QTR Raw'!H8 -> 8764.69 | AO99: ='QTR Raw'!I6+'QTR Raw'!I8 -> 8700.02 | AP99: ='QTR Raw'!J6+'QTR Raw'!J8 -> 8901.81 | ... CL99: ='QTR Raw'!BF6+'QTR Raw'!BF8 -> 14900.2 | CM99: =CM27 -> 17444.19 | CN99: =CN27 -> 21397.707 | CO99: =CO27 -> 19259.818 | CP99: =CP27 -> 20241.038 | CQ99: =CQ27 -> 21120.062 | CR99: =CR27 -> 22412.273 | CS99: =CS27 -> 20153.81 | CT99: =CT27 -> 21195.052 | ... DB99: =DB27 -> 23934.994 | DF99: 17586.68
A100: Less: Exise Duty | B100: ='Annual Raw'!C7+'Annual Raw'!C8+'Annual Raw'!C9 -> 0.355909 | C100: ='Annual Raw'!D7+'Annual Raw'!D8+'Annual Raw'!D9 -> 0 | D100: ='Annual Raw'!E7+'Annual Raw'!E8+'Annual Raw'!E9 -> 0 | E100: ='Annual Raw'!F7+'Annual Raw'!F8+'Annual Raw'!F9 -> 2.66 | F100: ='Annual Raw'!G7+'Annual Raw'!G8+'Annual Raw'!G9 -> 0.29 | G100: ='Annual Raw'!H7+'Annual Raw'!H8+'Annual Raw'!H9 -> 1.95 | H100: ='Annual Raw'!I7+'Annual Raw'!I8+'Annual Raw'!I9 -> 8.59 | I100: ='Annual Raw'!J7+'Annual Raw'!J8+'Annual Raw'!J9 -> 13.33 | ... AA100: ='Annual Raw'!AB7+'Annual Raw'!AB8+'Annual Raw'!AB9 -> 0 | AB100: =+SUM(CM100:CP100) -> 0 | AC100: =+SUM(CQ100:CT100) -> 0 | AD100: =+SUM(CU100:CX100) -> 0 | AE100: =+SUM(CY100:DB100) -> 0 | AI100: =+'QTR Raw'!C20+'QTR Raw'!C19+'QTR Raw'!C13+'QTR Raw'!C7 -> 45.23 | AJ100: =+'QTR Raw'!D20+'QTR Raw'!D19+'QTR Raw'!D13+'QTR Raw'!D7 -> 31.63 | AK100: =+'QTR Raw'!E20+'QTR Raw'!E19+'QTR Raw'!E13+'QTR Raw'!E7 -> 86.03 | AL100: =+'QTR Raw'!F20+'QTR Raw'!F19+'QTR Raw'!F13+'QTR Raw'!F7 -> 24.75 | AM100: =+'QTR Raw'!G20+'QTR Raw'!G19+'QTR Raw'!G13+'QTR Raw'!G7 -> 292.76 | AN100: =+'QTR Raw'!H20+'QTR Raw'!H19+'QTR Raw'!H13+'QTR Raw'!H7 -> 354.52 | AO100: =+'QTR Raw'!I20+'QTR Raw'!I19+'QTR Raw'!I13+'QTR Raw'!I7 -> 159.69 | AP100: =+'QTR Raw'!J20+'QTR Raw'!J19+'QTR Raw'!J13+'QTR Raw'!J7 -> 0 | ... CL100: =+'QTR Raw'!BF20+'QTR Raw'!BF19+'QTR Raw'!BF13+'QTR Raw'!BF7 -> 0 | DF100: 0
A101: Net Revenue | B101: =+B99-B100 -> 3374.4616 | C101: =+C99-C100 -> 3861.06 | D101: =+D99-D100 -> 4805.45 | E101: =+E99-E100 -> 4993.72 | F101: =+F99-F100 -> 4900.29 | G101: =+G99-G100 -> 5621.26 | H101: =+H99-H100 -> 6475.64 | I101: =+I99-I100 -> 10890.86 | ... AE101: =+AE99-AE100 -> 95893.63 | AI101: =+AI99-AI100 -> 7208.66 | AJ101: =+AJ99-AJ100 -> 7668.14 | AK101: =+AK99-AK100 -> 8953.28 | AL101: =+AL99-AL100 -> 9007.71 | AM101: =+AM99-AM100 -> 9046.73 | AN101: =+AN99-AN100 -> 8410.17 | AO101: =+AO99-AO100 -> 8540.33 | AP101: =+AP99-AP100 -> 8901.81 | ... DB101: =+DB99-DB100 -> 23934.994 | DF101: 17586.68
A102: Net Revenue YOY% | C102: =C101/B101-1 -> 0.14420031 | D102: =D101/C101-1 -> 0.24459345 | E102: =E101/D101-1 -> 0.039178433 | F102: =F101/E101-1 -> -0.018709499 | G102: =G101/F101-1 -> 0.14712803 | H102: =H101/G101-1 -> 0.15199083 | I102: =I101/H101-1 -> 0.68181987 | J102: =J101/I101-1 -> 0.65839245 | ... AE102: =AE101/AD101-1 -> 0.064508785 | AM102: =+IF(AI101<0,1-AM101/AI101,AM101/AI101-1) -> 0.25498081 | AN102: =+IF(AJ101<0,1-AN101/AJ101,AN101/AJ101-1) -> 0.096767925 | AO102: =+IF(AK101<0,1-AO101/AK101,AO101/AK101-1) -> -0.046122762 | AP102: =+IF(AL101<0,1-AP101/AL101,AP101/AL101-1) -> -0.011756595 | AQ102: =+IF(AM101<0,1-AQ101/AM101,AQ101/AM101-1) -> -0.05261017 | AR102: =+IF(AN101<0,1-AR101/AN101,AR101/AN101-1) -> 0.0063054611 | AS102: =+IF(AO101<0,1-AS101/AO101,AS101/AO101-1) -> -0.0013969015 | AT102: =+IF(AP101<0,1-AT101/AP101,AT101/AP101-1) -> -0.12281098 | ... DB102: =+IF(CX101<0,1-DB101/CX101,DB101/CX101-1) -> 0.064532426 | DF102: 0.028708671
A103: Net Revenue QOQ% | AJ103: =+IF(AI101<0,1-AJ101/AI101,AJ101/AI101-1) -> 0.063740002 | AK103: =+IF(AJ101<0,1-AK101/AJ101,AK101/AJ101-1) -> 0.16759475 | AL103: =+IF(AK101<0,1-AL101/AK101,AL101/AK101-1) -> 0.0060793363 | AM103: =+IF(AL101<0,1-AM101/AL101,AM101/AL101-1) -> 0.0043318446 | AN103: =+IF(AM101<0,1-AN101/AM101,AN101/AM101-1) -> -0.070363546 | AO103: =+IF(AN101<0,1-AO101/AN101,AO101/AN101-1) -> 0.0154765 | AP103: =+IF(AO101<0,1-AP101/AO101,AP101/AO101-1) -> 0.042326233 | AQ103: =+IF(AP101<0,1-AQ101/AP101,AQ101/AP101-1) -> -0.037186819 | ... DB103: =+IF(DA101<0,1-DB101/DA101,DB101/DA101-1) -> 0.052539464 | DF103: 0.26083762
A104: Increase/Decrease in Stock | B104: ='Annual Raw'!C11 -> -7.9388933 | C104: ='Annual Raw'!D11 -> 1.81 | D104: ='Annual Raw'!E11 -> 19.2 | E104: ='Annual Raw'!F11 -> 0.58 | F104: ='Annual Raw'!G11 -> 1.88 | G104: ='Annual Raw'!H11 -> -28.48 | H104: ='Annual Raw'!I11 -> -7.71 | I104: ='Annual Raw'!J11 -> 17.26 | ... AA104: ='Annual Raw'!AB11 -> -84.11 | AB104: =+SUM(CM104:CP104) -> 0 | AC104: =+SUM(CQ104:CT104) -> 0 | AD104: =+SUM(CU104:CX104) -> 0 | AE104: =+SUM(CY104:DB104) -> 0 | AI104: ='QTR Raw'!C10 -> -0.18 | AJ104: ='QTR Raw'!D10 -> -252.37 | AK104: ='QTR Raw'!E10 -> -115.71 | AL104: ='QTR Raw'!F10 -> 93.14 | AM104: ='QTR Raw'!G10 -> 54.72 | AN104: ='QTR Raw'!H10 -> -129.44 | AO104: ='QTR Raw'!I10 -> 136.87 | AP104: ='QTR Raw'!J10 -> 68.62 | ... CL104: ='QTR Raw'!BF10 -> 7.74 | DF104: -84.11
A105: Purchase of Finished Goods | B105: 0 | C105: 0 | D105: 0 | E105: 0 | F105: 0 | G105: 0 | H105: 0 | I105: 0 | J105: 0 | K105: 0 | L105: 0 | M105: 0 | N105: 0 | O105: 0 | P105: 0 | Q105: 0 | R105: 0 | S105: 0 | T105: 0 | U105: 0 | V105: 0 | W105: 0 | X105: 0 | Y105: 0 | Z105: 0 | AA105: 0 | AB105: =+SUM(CM105:CP105) -> 0 | AC105: =+SUM(CQ105:CT105) -> 0 | AD105: =+SUM(CU105:CX105) -> 0 | AE105: =+SUM(CY105:DB105) -> 0 | AI105: ='QTR Raw'!C12 -> 11.77 | AJ105: ='QTR Raw'!D12 -> 9.26 | AK105: ='QTR Raw'!E12 -> 7.15 | AL105: ='QTR Raw'!F12 -> 9.29 | AM105: ='QTR Raw'!G12 -> 14.56 | AN105: ='QTR Raw'!H12 -> 9.7 | AO105: ='QTR Raw'!I12 -> 10.17 | AP105: ='QTR Raw'!J12 -> 9.27 | ... CD105: ='QTR Raw'!AX12 -> 13.42 | CE105: 5.55 | CF105: ='QTR Raw'!AZ12 -> 7.79 | CG105: ='QTR Raw'!BA12 -> 7.39 | CH105: ='QTR Raw'!BB12 -> 11.11 | CI105: 6.42 | CJ105: ='QTR Raw'!BD12 -> 12.94 | CK105: ='QTR Raw'!BE12 -> 14.75 | CL105: ='QTR Raw'!BF12 -> 8.24 | DF105: 42.35
A106: Raw Material Consumed | B106: ='Annual Raw'!C12 -> 0 | C106: ='Annual Raw'!D12 -> 0 | D106: ='Annual Raw'!E12 -> 0 | E106: ='Annual Raw'!F12 -> 0 | F106: ='Annual Raw'!G12 -> 0 | G106: ='Annual Raw'!H12 -> 0 | H106: ='Annual Raw'!I12 -> 0 | I106: ='Annual Raw'!J12 -> 0 | ... AA106: ='Annual Raw'!AB12 -> 0 | AB106: =+SUM(CM106:CP106) -> 90.604559 | AC106: =+SUM(CQ106:CT106) -> 124.71003 | AD106: =+SUM(CU106:CX106) -> 137.20249 | AE106: =+SUM(CY106:DB106) -> 146.54705 | CM106: =+CM101-CM107 -> -4.2863512 | CN106: =+CN101-CN107 -> 3.5096063 | CO106: =+CO101-CO107 -> 68.397286 | CP106: =+CP101-CP107 -> 22.984018 | CQ106: =+CQ101-CQ107 -> 24.315053 | CR106: =+CR101-CR107 -> 33.630208 | CS106: =+CS101-CS107 -> 36.975259 | CT106: =+CT101-CT107 -> 29.789505 | ... DB106: =+DB101-DB107 -> 36.439855 | DF106: 6.4068339
A107: Gross Profit | B107: =B101-B104-B106-B105 -> 3382.4005 | C107: =C101-C104-C106-C105 -> 3859.25 | D107: =D101-D104-D106-D105 -> 4786.25 | E107: =E101-E104-E106-E105 -> 4993.14 | F107: =F101-F104-F106-F105 -> 4898.41 | G107: =G101-G104-G106-G105 -> 5649.74 | H107: =H101-H104-H106-H105 -> 6483.35 | I107: =I101-I104-I106-I105 -> 10873.6 | ... AE107: =AE101-AE104-AE106-AE105 -> 95747.083 | AI107: =AI101-AI104-AI106-AI105 -> 7197.07 | AJ107: =AJ101-AJ104-AJ106-AJ105 -> 7911.25 | AK107: =AK101-AK104-AK106-AK105 -> 9061.84 | AL107: =AL101-AL104-AL106-AL105 -> 8905.28 | AM107: =AM101-AM104-AM106-AM105 -> 8977.45 | AN107: =AN101-AN104-AN106-AN105 -> 8529.91 | AO107: =AO101-AO104-AO106-AO105 -> 8393.29 | AP107: =AP101-AP104-AP106-AP105 -> 8823.92 | ... CL107: =CL101-CL104-CL106-CL105 -> 14884.22 | CM107: =+CM108*CM101 -> 17448.476 | CN107: =+CN108*CN101 -> 21394.197 | CO107: =+CO108*CO101 -> 19191.421 | CP107: =+CP108*CP101 -> 20218.054 | CQ107: =+CQ108*CQ101 -> 21095.747 | CR107: =+CR108*CR101 -> 22378.643 | CS107: =+CS108*CS101 -> 20116.834 | CT107: =+CT108*CT101 -> 21165.263 | ... DB107: =+DB108*DB101 -> 23898.554 | DF107: 17580.273
A108: GP% | B108: =B107/B101 -> 1.0023526 | C108: =C107/C101 -> 0.99953122 | D108: =D107/D101 -> 0.99600454 | E108: =E107/E101 -> 0.99988385 | F108: =F107/F101 -> 0.99961635 | G108: =G107/G101 -> 1.0050665 | H108: =H107/H101 -> 1.0011906 | I108: =I107/I101 -> 0.99841518 | ... AE108: =AE107/AE101 -> 0.99847177 | AI108: =AI107/AI101 -> 0.99839221 | AJ108: =AJ107/AJ101 -> 1.0317039 | AK108: =AK107/AK101 -> 1.0121252 | AL108: =AL107/AL101 -> 0.98862863 | AM108: =AM107/AM101 -> 0.99234198 | AN108: =AN107/AN101 -> 1.0142375 | AO108: =AO107/AO101 -> 0.98278287 | AP108: =AP107/AP101 -> 0.99125009 | ... CL108: =CL107/CL101 -> 0.99892753 | CM108: =AVERAGE(CI108:CL108) -> 1.0002457 | CN108: =AVERAGE(CJ108:CM108) -> 0.99983598 | CO108: =AVERAGE(CK108:CN108) -> 0.99644871 | CP108: =AVERAGE(CL108:CO108) -> 0.99886448 | CQ108: =AVERAGE(CM108:CP108) -> 0.99884872 | CR108: =AVERAGE(CN108:CQ108) -> 0.99849947 | CS108: =AVERAGE(CO108:CR108) -> 0.99816535 | CT108: =AVERAGE(CP108:CS108) -> 0.99859451 | ... DB108: =AVERAGE(CX108:DA108) -> 0.99847755 | DF108: 0.9996357
A109: GP YOY% | C109: =+IF(B107<0,1-C107/B107,C107/B107-1) -> 0.14097961 | D109: =+IF(C107<0,1-D107/C107,D107/C107-1) -> 0.24020211 | E109: =+IF(D107<0,1-E107/D107,E107/D107-1) -> 0.043225908 | F109: =+IF(E107<0,1-F107/E107,F107/E107-1) -> -0.01897203 | G109: =+IF(F107<0,1-G107/F107,G107/F107-1) -> 0.15338242 | H109: =+IF(G107<0,1-H107/G107,H107/G107-1) -> 0.14754838 | I109: =+IF(H107<0,1-I107/H107,I107/H107-1) -> 0.67715764 | J109: =+IF(I107<0,1-J107/I107,J107/I107-1) -> 0.66832512 | ... AE109: =+IF(AD107<0,1-AE107/AD107,AE107/AD107-1) -> 0.064503295 | AM109: =+IF(AI107<0,1-AM107/AI107,AM107/AI107-1) -> 0.24737567 | AN109: =+IF(AJ107<0,1-AN107/AJ107,AN107/AJ107-1) -> 0.078200032 | AO109: =+IF(AK107<0,1-AO107/AK107,AO107/AK107-1) -> -0.073776407 | AP109: =+IF(AL107<0,1-AP107/AL107,AP107/AL107-1) -> -0.0091361529 | AQ109: =+IF(AM107<0,1-AQ107/AM107,AQ107/AM107-1) -> -0.043157021 | AR109: =+IF(AN107<0,1-AR107/AN107,AR107/AN107-1) -> -0.0070434506 | AS109: =+IF(AO107<0,1-AS107/AO107,AS107/AO107-1) -> -0.0027414756 | AT109: =+IF(AP107<0,1-AT107/AP107,AT107/AP107-1) -> -0.11728461 | ... CL109: =+IF(CH107<0,1-CL107/CH107,CL107/CH107-1) -> -0.1262991 | CM109: =+CM107/CI107-1 -> -0.034345099 | CN109: =+CN107/CJ107-1 -> 0.35810478 | CO109: =+CO107/CK107-1 -> 0.39431089 | CP109: =+CP107/CL107-1 -> 0.35835493 | CQ109: =+CQ107/CM107-1 -> 0.20903087 | CR109: =+CR107/CN107-1 -> 0.046014601 | CS109: =+CS107/CO107-1 -> 0.04822018 | CT109: =+CT107/CP107-1 -> 0.046849674 | ... DB109: =+DB107/CX107-1 -> 0.064508099 | DF109: 0.031958711
A110: GP QOQ% | AJ110: =+IF(AI107<0,1-AJ107/AI107,AJ107/AI107-1) -> 0.099232049 | AK110: =+IF(AJ107<0,1-AK107/AJ107,AK107/AJ107-1) -> 0.14543719 | AL110: =+IF(AK107<0,1-AL107/AK107,AL107/AK107-1) -> -0.017276844 | AM110: =+IF(AL107<0,1-AM107/AL107,AM107/AL107-1) -> 0.0081041809 | AN110: =+IF(AM107<0,1-AN107/AM107,AN107/AM107-1) -> -0.049851573 | AO110: =+IF(AN107<0,1-AO107/AN107,AO107/AN107-1) -> -0.016016582 | AP110: =+IF(AO107<0,1-AP107/AO107,AP107/AO107-1) -> 0.05130646 | AQ110: =+IF(AP107<0,1-AQ107/AP107,AQ107/AP107-1) -> -0.026508627 | ... CL110: =+IF(CK107<0,1-CL107/CK107,CL107/CK107-1) -> 0.081380607 | CM110: =+CM107/CL107-1 -> 0.1722802 | CN110: =+CN107/CM107-1 -> 0.22613556 | CO110: =+CO107/CN107-1 -> -0.10296141 | CP110: =+CP107/CO107-1 -> 0.053494372 | CQ110: =+CQ107/CP107-1 -> 0.043411347 | CR110: =+CR107/CQ107-1 -> 0.060813031 | CS110: =+CS107/CR107-1 -> -0.10106996 | CT110: =+CT107/CS107-1 -> 0.052116971 | ... DB110: =+DB107/DA107-1 -> 0.05254878 | DF110: 0.27725648
A111: Power & Fuel Cost | B111: =+'Annual Raw'!C13 -> 2107.8016 | C111: =+'Annual Raw'!D13 -> 2188.79 | D111: =+'Annual Raw'!E13 -> 2783.68 | E111: =+'Annual Raw'!F13 -> 2698.83 | F111: =+'Annual Raw'!G13 -> 3011.47 | G111: =+'Annual Raw'!H13 -> 3770.73 | H111: =+'Annual Raw'!I13 -> 4626 | I111: =+'Annual Raw'!J13 -> 6512.76 | ... AA111: =+'Annual Raw'!AB13 -> 37274.37 | AB111: =+SUM(CM111:CP111) -> 0 | AC111: =+SUM(CQ111:CT111) -> 0 | AD111: =+SUM(CU111:CX111) -> 0 | AE111: =+SUM(CY111:DB111) -> 0 | AI111: ='QTR Raw'!C15+'QTR Raw'!C11 -> 3843.41 | AJ111: ='QTR Raw'!D15+'QTR Raw'!D11 -> 4336.21 | AK111: ='QTR Raw'!E15+'QTR Raw'!E11 -> 5036.87 | AL111: ='QTR Raw'!F15+'QTR Raw'!F11 -> 5361.26 | AM111: ='QTR Raw'!G15+'QTR Raw'!G11 -> 4897.95 | AN111: ='QTR Raw'!H15+'QTR Raw'!H11 -> 4596.73 | AO111: ='QTR Raw'!I15+'QTR Raw'!I11 -> 4146.29 | AP111: ='QTR Raw'!J15+'QTR Raw'!J11 -> 4419.19 | ... CD111: ='QTR Raw'!AX15+'QTR Raw'!AX11 -> 9737.94 | CE111: ='QTR Raw'!AY15+'QTR Raw'!AY11+5971 -> 10930.71 | CF111: ='QTR Raw'!AZ15+'QTR Raw'!AZ11 -> 8926.47 | CG111: ='QTR Raw'!BA15+'QTR Raw'!BA11 -> 9409.74 | CH111: ='QTR Raw'!BB15+'QTR Raw'!BB11 -> 10096.49 | CI111: ='QTR Raw'!BC15+'QTR Raw'!BC11+5260 -> 10763.76 | CJ111: ='QTR Raw'!BD15+'QTR Raw'!BD11 -> 9179.63 | CK111: ='QTR Raw'!BE15+'QTR Raw'!BE11 -> 7343.11 | CL111: ='QTR Raw'!BF15+'QTR Raw'!BF11 -> 8476.73 | DF111: 35763.23
A112: Employee Cost | B112: ='Annual Raw'!C14 -> 133.60525 | C112: ='Annual Raw'!D14 -> 137.15 | D112: ='Annual Raw'!E14 -> 181.63 | E112: ='Annual Raw'!F14 -> 245.5 | F112: ='Annual Raw'!G14 -> 209.4 | G112: ='Annual Raw'!H14 -> 234.95 | H112: ='Annual Raw'!I14 -> 275.21 | I112: ='Annual Raw'!J14 -> 448.32 | ... AA112: ='Annual Raw'!AB14 -> 4693.73 | AB112: =+SUM(CM112:CP112) -> 5022.2911 | AC112: =+SUM(CQ112:CT112) -> 5373.8515 | AD112: =+SUM(CU112:CX112) -> 5750.0211 | AE112: =+SUM(CY112:DB112) -> 6152.5226 | AI112: ='QTR Raw'!C16 -> 309.79 | AJ112: ='QTR Raw'!D16 -> 345.32 | AK112: ='QTR Raw'!E16 -> 333.66 | AL112: ='QTR Raw'!F16 -> 334.18 | AM112: ='QTR Raw'!G16 -> 330.16 | AN112: ='QTR Raw'!H16 -> 307.4 | AO112: ='QTR Raw'!I16 -> 323.03 | AP112: ='QTR Raw'!J16 -> 388.76 | ... CL112: ='QTR Raw'!BF16 -> 1233.77 | CM112: =CI112*107% -> 1242.6552 | CN112: =CJ112*107% -> 1179.2577 | CO112: =CK112*107% -> 1280.2443 | CP112: =CL112*107% -> 1320.1339 | CQ112: =CM112*107% -> 1329.6411 | CR112: =CN112*107% -> 1261.8057 | CS112: =CO112*107% -> 1369.8614 | CT112: =CP112*107% -> 1412.5433 | ... DB112: =CX112*107% -> 1617.2208 | DF112: 1348.8848
A113: General and Administration Expenses | B113: ='Annual Raw'!C17 -> 101.01734 | C113: ='Annual Raw'!D17 -> 64.54 | D113: ='Annual Raw'!E17 -> 73.15 | E113: ='Annual Raw'!F17 -> 100.9 | F113: ='Annual Raw'!G17 -> 195.38 | G113: ='Annual Raw'!H17 -> 99.68 | H113: ='Annual Raw'!I17 -> 97.03 | I113: ='Annual Raw'!J17 -> 157.74 | ... AA113: ='Annual Raw'!AB17 -> 863.74 | AB113: =+SUM(CM113:CP113) -> 0 | AC113: =+SUM(CQ113:CT113) -> 0 | AD113: =+SUM(CU113:CX113) -> 0 | AE113: =+SUM(CY113:DB113) -> 0 | AI113: ='QTR Raw'!C17 -> 0 | AJ113: ='QTR Raw'!D17 -> 0 | AK113: ='QTR Raw'!E17 -> 0 | AL113: ='QTR Raw'!F17 -> 0 | AM113: ='QTR Raw'!G17 -> 0 | AN113: ='QTR Raw'!H17 -> 0 | AO113: ='QTR Raw'!I17 -> 0 | AP113: ='QTR Raw'!J17 -> 0 | ... CL113: ='QTR Raw'!BF17 -> 0 | DF113: 0
A114: Miscellaneous Expenses | B114: ='Annual Raw'!C19-'Annual Raw'!C20 -> 145.92908 | C114: ='Annual Raw'!D19-'Annual Raw'!D20 -> 195.68 | D114: ='Annual Raw'!E19-'Annual Raw'!E20 -> 163.08 | E114: ='Annual Raw'!F19-'Annual Raw'!F20 -> 151.29 | F114: ='Annual Raw'!G19-'Annual Raw'!G20 -> 139.97 | G114: ='Annual Raw'!H19-'Annual Raw'!H20 -> 96.56 | H114: ='Annual Raw'!I19-'Annual Raw'!I20 -> 66.44 | I114: ='Annual Raw'!J19-'Annual Raw'!J20 -> 96.34 | ... AA114: ='Annual Raw'!AB19-'Annual Raw'!AB20 -> 1043.47 | AB114: =+SUM(CM114:CP114) -> 0 | AC114: =+SUM(CQ114:CT114) -> 0 | AD114: =+SUM(CU114:CX114) -> 0 | AE114: =+SUM(CY114:DB114) -> 0 | AI114: =+'QTR Raw'!C21 -> 0 | AJ114: =+'QTR Raw'!D21 -> 0 | AK114: =+'QTR Raw'!E21 -> 0 | AL114: =+'QTR Raw'!F21 -> 0 | AM114: =+'QTR Raw'!G21 -> 0 | AN114: =+'QTR Raw'!H21 -> 0 | AO114: =+'QTR Raw'!I21 -> 0 | AP114: =+'QTR Raw'!J21 -> 0 | ... CL114: =+'QTR Raw'!BF21 -> -1061.72 | DF114: -1252.04
A115: Other Manufacturing Expenses | B115: ='Annual Raw'!C15+'Annual Raw'!C16 -> 151.80271 | C115: ='Annual Raw'!D15+'Annual Raw'!D16 -> 195.58 | D115: ='Annual Raw'!E15+'Annual Raw'!E16 -> 190.96 | E115: ='Annual Raw'!F15+'Annual Raw'!F16 -> 322.6 | F115: ='Annual Raw'!G15+'Annual Raw'!G16 -> 237.45 | G115: ='Annual Raw'!H15+'Annual Raw'!H16 -> 470.94 | H115: ='Annual Raw'!I15+'Annual Raw'!I16 -> 333.98 | I115: ='Annual Raw'!J15+'Annual Raw'!J16 -> 1298.52 | ... AA115: ='Annual Raw'!AB15+'Annual Raw'!AB16 -> 5451.69 | AB115: =+SUM(CM115:CP115) -> 55339.241 | AC115: =+SUM(CQ115:CT115) -> 59983.068 | AD115: =+SUM(CU115:CX115) -> 63610.509 | AE115: =+SUM(CY115:DB115) -> 67684.119 | AI115: ='QTR Raw'!C14 -> 1674.97 | AJ115: ='QTR Raw'!D14 -> 1751.01 | AK115: ='QTR Raw'!E14 -> 1921.1 | AL115: ='QTR Raw'!F14 -> 1377.23 | AM115: ='QTR Raw'!G14 -> 1974.36 | AN115: ='QTR Raw'!H14 -> 1949.61 | AO115: ='QTR Raw'!I14 -> 2297.17 | AP115: ='QTR Raw'!J14 -> 2194.44 | ... CL115: ='QTR Raw'!BF14 -> 2574.53 | CM115: =+CM118-CM112 -> 12293.079 | CN115: =+CN118-CN112 -> 15272.669 | CO115: =+CO118-CO112 -> 13441.922 | CP115: =+CP118-CP112 -> 14331.571 | CQ115: =+CQ118-CQ112 -> 14945.864 | CR115: =+CR118-CR112 -> 15979.654 | CS115: =+CS118-CS112 -> 14136.322 | CT115: =+CT118-CT112 -> 14921.227 | ... DB115: =+DB118-DB112 -> 16812.936 | DF115: 12748.07
A116: Selling and Distribution Expenses | B116: ='Annual Raw'!C18 -> 52.609518 | C116: ='Annual Raw'!D18 -> 117.17 | D116: ='Annual Raw'!E18 -> 143.78 | E116: ='Annual Raw'!F18 -> 149.63 | F116: ='Annual Raw'!G18 -> 0 | G116: ='Annual Raw'!H18 -> 0 | H116: ='Annual Raw'!I18 -> 0 | I116: ='Annual Raw'!J18 -> 237.8 | ... AA116: ='Annual Raw'!AB18 -> 90.64 | AB116: =+SUM(CM116:CP116) -> 0 | AC116: =+SUM(CQ116:CT116) -> 0 | AD116: =+SUM(CU116:CX116) -> 0 | AE116: =+SUM(CY116:DB116) -> 0 | AI116: ='QTR Raw'!C18 -> 0 | AJ116: ='QTR Raw'!D18 -> 0 | AK116: ='QTR Raw'!E18 -> 0 | AL116: ='QTR Raw'!F18 -> 0 | AM116: ='QTR Raw'!G18 -> 0 | AN116: ='QTR Raw'!H18 -> 0 | AO116: ='QTR Raw'!I18 -> 0 | AP116: ='QTR Raw'!J18 -> 0 | ... BV116: ='QTR Raw'!AP18 -> 0 | DF116: 0
U117: -1378 | V117: -686 | X117: -924 | Y117: -93.43 | Z117: 976 | AA117: 976
A118: Total Cost | B118: =+SUM(B111:B117) -> 2692.7655 | C118: =+SUM(C111:C117) -> 2898.91 | D118: =+SUM(D111:D117) -> 3536.28 | E118: =+SUM(E111:E117) -> 3668.75 | F118: =+SUM(F111:F117) -> 3793.67 | G118: =+SUM(G111:G117) -> 4672.86 | H118: =+SUM(H111:H117) -> 5398.66 | I118: =+SUM(I111:I117) -> 8751.48 | ... AA118: =+SUM(AA111:AA117) -> 50393.64 | AB118: =+SUM(AB111:AB116) -> 60361.532 | AC118: =+SUM(AC111:AC116) -> 65356.919 | AD118: =+SUM(AD111:AD116) -> 69360.531 | AE118: =+SUM(AE111:AE116) -> 73836.641 | AI118: =+SUM(AI111:AI116) -> 5828.17 | AJ118: =+SUM(AJ111:AJ116) -> 6432.54 | AK118: =+SUM(AK111:AK116) -> 7291.63 | AL118: =+SUM(AL111:AL116) -> 7072.67 | AM118: =+SUM(AM111:AM116) -> 7202.47 | AN118: =+SUM(AN111:AN116) -> 6853.74 | AO118: =+SUM(AO111:AO116) -> 6766.49 | AP118: =+SUM(AP111:AP116) -> 7002.39 | ... CL118: =+SUM(CL111:CL116) -> 11223.31 | CM118: =CM119*CM101 -> 13535.734 | CN118: =CN119*CN101 -> 16451.927 | CO118: =CO119*CO101 -> 14722.166 | CP118: =CP119*CP101 -> 15651.705 | CQ118: =CQ119*CQ101 -> 16275.505 | CR118: =CR119*CR101 -> 17241.46 | CS118: =CS119*CS101 -> 15506.183 | CT118: =CT119*CT101 -> 16333.771 | ... DB118: =DB119*DB101 -> 18430.157 | DF118: 14096.955
A119: Cost % | B119: =B118/B101 -> 0.79798373 | C119: =C118/C101 -> 0.75080677 | D119: =D118/D101 -> 0.73588946 | E119: =E118/E101 -> 0.73467275 | F119: =F118/F101 -> 0.77417255 | G119: =G118/G101 -> 0.83128338 | H119: =H118/H101 -> 0.83368748 | I119: =I118/I101 -> 0.80356189 | ... AE119: =AE118/AE101 -> 0.76998484 | AI119: =AI118/AI101 -> 0.80849561 | AJ119: =AJ118/AJ101 -> 0.83886575 | AK119: =AK118/AK101 -> 0.8144088 | AL119: =AL118/AL101 -> 0.78517959 | AM119: =AM118/AM101 -> 0.7961407 | AN119: =AN118/AN101 -> 0.81493478 | AO119: =AO118/AO101 -> 0.79229842 | AP119: =AP118/AP101 -> 0.78662542 | ... CL119: =CL118/CL101 -> 0.75323217 | CM119: =AVERAGE(CI119:CL119)*1.01 -> 0.77594513 | CN119: =AVERAGE(CJ119:CM119)*1.01 -> 0.76886403 | CO119: =AVERAGE(CK119:CN119)*1.01 -> 0.76439798 | CP119: =AVERAGE(CL119:CO119)*1.01 -> 0.77326592 | CQ119: =AVERAGE(CM119:CP119) -> 0.77061826 | CR119: =AVERAGE(CN119:CQ119) -> 0.76928655 | CS119: =AVERAGE(CO119:CR119) -> 0.76939218 | CT119: =AVERAGE(CP119:CS119) -> 0.77064073 | CU119: =AVERAGE(CQ119:CT119) -> 0.76998443 | CV119: =AVERAGE(CR119:CU119) -> 0.76982597 | CW119: =AVERAGE(CS119:CV119) -> 0.76996083 | CX119: =AVERAGE(CT119:CW119) -> 0.77010299 | ... DB119: =AVERAGE(CX119:DA119) -> 0.77000884 | DF119: 0.80156999
...

Sheet QTR Raw
A1: ='Annual Raw'!A1 -> 100400 | B1: X | C1: 201206 | D1: 201209 | E1: 201212 | F1: 201303 | G1: 201306 | H1: 201309 | I1: 201312 | J1: 201403 | K1: 201406 | L1: 201409 | M1: 201412 | N1: 201503 | O1: 201506 | P1: 201509 | Q1: 201512 | R1: 201603 | S1: 201606 | T1: 201609 | U1: 201612 | V1: 201703 | W1: 201706 | X1: 201709 | Y1: 201712 | Z1: 201803 | AA1: 201806 | AB1: 201809 | AC1: 201812 | AD1: 201903 | AE1: 201906 | AF1: 201909 | AG1: 201912 | AH1: 202003 | AI1: 202006 | AJ1: 202009 | AK1: 202012 | AL1: 202103 | AM1: 202106 | AN1: 202109 | AO1: 202112 | AP1: 202203 | AQ1: 202206 | AR1: 202209 | AS1: 202212 | AT1: 202303 | AU1: 202306 | AV1: 202309 | AW1: 202312 | AX1: 202403 | AY1: 202406 | AZ1: 202409 | BA1: 202412 | BB1: 202503 | BC1: 202506 | BD1: 202509 | BE1: 202512 | BF1: 202603 | BG1: 202606 | BH1: 202609 | BI1: 202612 | BJ1: 202703 | BK1: 202706 | BL1: 202709 | BM1: 202712 | BN1: 202803 | BO1: 202806 | BP1: 202809 | BQ1: 202812 | BR1: 202903 | BS1: 202906 | BT1: 202909 | BU1: 202912 | BV1: 203003
A3: Field Description | B3: Field Name
A4: Company Name | B4: CD_COMPNAME | C4: =_xll.EQNXTDZ(A1,B4,C1) -> Tata Power Company Ltd.
A5: Date End | B5: QTR_DATE_END | C5: =_xll.EQNXTDZ($A$1,$B5,C$1,$B$1) -> 201206 | D5: =_xll.EQNXTDZ($A$1,$B5,D$1,$B$1) -> 201209 | E5: =_xll.EQNXTDZ($A$1,$B5,E$1,$B$1) -> 201212 | F5: =_xll.EQNXTDZ($A$1,$B5,F$1,$B$1) -> 201303 | G5: =_xll.EQNXTDZ($A$1,$B5,G$1,$B$1) -> 201306 | H5: =_xll.EQNXTDZ($A$1,$B5,H$1,$B$1) -> 201309 | I5: =_xll.EQNXTDZ($A$1,$B5,I$1,$B$1) -> 201312 | J5: =_xll.EQNXTDZ($A$1,$B5,J$1,$B$1) -> 201403 | ... BV5: =_xll.EQNXTDZ($A$1,$B5,BV$1,$B$1) -> 0
A6: Gross Sales | B6: QTR_GROSS_SALE | C6: =_xll.EQNXTDZ($A$1,$B6,C$1,$B$1) -> 7197.57 | D6: =_xll.EQNXTDZ($A$1,$B6,D$1,$B$1) -> 7649.49 | E6: =_xll.EQNXTDZ($A$1,$B6,E$1,$B$1) -> 8991.68 | F6: =_xll.EQNXTDZ($A$1,$B6,F$1,$B$1) -> 8997.31 | G6: =_xll.EQNXTDZ($A$1,$B6,G$1,$B$1) -> 9291.77 | H6: =_xll.EQNXTDZ($A$1,$B6,H$1,$B$1) -> 8717.11 | I6: =_xll.EQNXTDZ($A$1,$B6,I$1,$B$1) -> 8656.11 | J6: =_xll.EQNXTDZ($A$1,$B6,J$1,$B$1) -> 8862.5 | ... BV6: =_xll.EQNXTDZ($A$1,$B6,BV$1,$B$1) -> 0
A7: Less: Excise Duty | B7: QTR_EXCISE_DUTY | C7: =_xll.EQNXTDZ($A$1,$B7,C$1,$B$1) -> 0 | D7: =_xll.EQNXTDZ($A$1,$B7,D$1,$B$1) -> 0 | E7: =_xll.EQNXTDZ($A$1,$B7,E$1,$B$1) -> 0 | F7: =_xll.EQNXTDZ($A$1,$B7,F$1,$B$1) -> 0 | G7: =_xll.EQNXTDZ($A$1,$B7,G$1,$B$1) -> 0 | H7: =_xll.EQNXTDZ($A$1,$B7,H$1,$B$1) -> 0 | I7: =_xll.EQNXTDZ($A$1,$B7,I$1,$B$1) -> 0 | J7: =_xll.EQNXTDZ($A$1,$B7,J$1,$B$1) -> 0 | ... BV7: =_xll.EQNXTDZ($A$1,$B7,BV$1,$B$1) -> 0
A8: Other operating income | B8: QTR_JOB_WORKS | C8: =_xll.EQNXTDZ($A$1,$B8,C$1,$B$1) -> 56.32 | D8: =_xll.EQNXTDZ($A$1,$B8,D$1,$B$1) -> 50.28 | E8: =_xll.EQNXTDZ($A$1,$B8,E$1,$B$1) -> 47.63 | F8: =_xll.EQNXTDZ($A$1,$B8,F$1,$B$1) -> 35.15 | G8: =_xll.EQNXTDZ($A$1,$B8,G$1,$B$1) -> 47.72 | H8: =_xll.EQNXTDZ($A$1,$B8,H$1,$B$1) -> 47.58 | I8: =_xll.EQNXTDZ($A$1,$B8,I$1,$B$1) -> 43.91 | J8: =_xll.EQNXTDZ($A$1,$B8,J$1,$B$1) -> 39.31 | ... BV8: =_xll.EQNXTDZ($A$1,$B8,BV$1,$B$1) -> 0
A9: Net Sales & Other Operating Income | B9: QTR_NET_SALES | C9: =_xll.EQNXTDZ($A$1,$B9,C$1,$B$1) -> 7253.89 | D9: =_xll.EQNXTDZ($A$1,$B9,D$1,$B$1) -> 7699.77 | E9: =_xll.EQNXTDZ($A$1,$B9,E$1,$B$1) -> 9039.31 | F9: =_xll.EQNXTDZ($A$1,$B9,F$1,$B$1) -> 9032.46 | G9: =_xll.EQNXTDZ($A$1,$B9,G$1,$B$1) -> 9339.49 | H9: =_xll.EQNXTDZ($A$1,$B9,H$1,$B$1) -> 8764.69 | I9: =_xll.EQNXTDZ($A$1,$B9,I$1,$B$1) -> 8700.02 | J9: =_xll.EQNXTDZ($A$1,$B9,J$1,$B$1) -> 8901.81 | ... BV9: =_xll.EQNXTDZ($A$1,$B9,BV$1,$B$1) -> 0
A10: (Increase) / Decrease In Stocks | B10: QTR_INC_DEC_INVENTORY | C10: =_xll.EQNXTDZ($A$1,$B10,C$1,$B$1) -> -0.18 | D10: =_xll.EQNXTDZ($A$1,$B10,D$1,$B$1) -> -252.37 | E10: =_xll.EQNXTDZ($A$1,$B10,E$1,$B$1) -> -115.71 | F10: =_xll.EQNXTDZ($A$1,$B10,F$1,$B$1) -> 93.14 | G10: =_xll.EQNXTDZ($A$1,$B10,G$1,$B$1) -> 54.72 | H10: =_xll.EQNXTDZ($A$1,$B10,H$1,$B$1) -> -129.44 | I10: =_xll.EQNXTDZ($A$1,$B10,I$1,$B$1) -> 136.87 | J10: =_xll.EQNXTDZ($A$1,$B10,J$1,$B$1) -> 68.62 | ... BV10: =_xll.EQNXTDZ($A$1,$B10,BV$1,$B$1) -> 0
A11: Cost of Services & Raw Materials | B11: QTR_RAW_MATERIAL_COST | C11: =_xll.EQNXTDZ($A$1,$B11,C$1,$B$1) -> 72.17 | D11: =_xll.EQNXTDZ($A$1,$B11,D$1,$B$1) -> 110.85 | E11: =_xll.EQNXTDZ($A$1,$B11,E$1,$B$1) -> 141.34 | F11: =_xll.EQNXTDZ($A$1,$B11,F$1,$B$1) -> 154.48 | G11: =_xll.EQNXTDZ($A$1,$B11,G$1,$B$1) -> 116.02 | H11: =_xll.EQNXTDZ($A$1,$B11,H$1,$B$1) -> 123.09 | I11: =_xll.EQNXTDZ($A$1,$B11,I$1,$B$1) -> 204.04 | J11: =_xll.EQNXTDZ($A$1,$B11,J$1,$B$1) -> 308.51 | ... BV11: =_xll.EQNXTDZ($A$1,$B11,BV$1,$B$1) -> 0
A12: Purchase of Finished Goods | B12: QTR_PURCHASE_FIN_GOOD | C12: =_xll.EQNXTDZ($A$1,$B12,C$1,$B$1) -> 11.77 | D12: =_xll.EQNXTDZ($A$1,$B12,D$1,$B$1) -> 9.26 | E12: =_xll.EQNXTDZ($A$1,$B12,E$1,$B$1) -> 7.15 | F12: =_xll.EQNXTDZ($A$1,$B12,F$1,$B$1) -> 9.29 | G12: =_xll.EQNXTDZ($A$1,$B12,G$1,$B$1) -> 14.56 | H12: =_xll.EQNXTDZ($A$1,$B12,H$1,$B$1) -> 9.7 | I12: =_xll.EQNXTDZ($A$1,$B12,I$1,$B$1) -> 10.17 | J12: =_xll.EQNXTDZ($A$1,$B12,J$1,$B$1) -> 9.27 | ... BV12: =_xll.EQNXTDZ($A$1,$B12,BV$1,$B$1) -> 0
A13: Excise Duty | B13: QTR_EXCISE | C13: =_xll.EQNXTDZ($A$1,$B13,C$1,$B$1) -> 0 | D13: =_xll.EQNXTDZ($A$1,$B13,D$1,$B$1) -> 0 | E13: =_xll.EQNXTDZ($A$1,$B13,E$1,$B$1) -> 0 | F13: =_xll.EQNXTDZ($A$1,$B13,F$1,$B$1) -> 0 | G13: =_xll.EQNXTDZ($A$1,$B13,G$1,$B$1) -> 0 | H13: =_xll.EQNXTDZ($A$1,$B13,H$1,$B$1) -> 0 | I13: =_xll.EQNXTDZ($A$1,$B13,I$1,$B$1) -> 0 | J13: =_xll.EQNXTDZ($A$1,$B13,J$1,$B$1) -> 0 | ... BV13: =_xll.EQNXTDZ($A$1,$B13,BV$1,$B$1) -> 0
A14: Operating & Manufacturing Expenses | B14: QTR_MFG_EXPS | C14: =_xll.EQNXTDZ($A$1,$B14,C$1,$B$1) -> 1674.97 | D14: =_xll.EQNXTDZ($A$1,$B14,D$1,$B$1) -> 1751.01 | E14: =_xll.EQNXTDZ($A$1,$B14,E$1,$B$1) -> 1921.1 | F14: =_xll.EQNXTDZ($A$1,$B14,F$1,$B$1) -> 1377.23 | G14: =_xll.EQNXTDZ($A$1,$B14,G$1,$B$1) -> 1974.36 | H14: =_xll.EQNXTDZ($A$1,$B14,H$1,$B$1) -> 1949.61 | I14: =_xll.EQNXTDZ($A$1,$B14,I$1,$B$1) -> 2297.17 | J14: =_xll.EQNXTDZ($A$1,$B14,J$1,$B$1) -> 2194.44 | ... BV14: =_xll.EQNXTDZ($A$1,$B14,BV$1,$B$1) -> 0
A15: Electricity Power & Fuel Cost | B15: QTR_ELECTRICITY_POWER_FUEL | C15: =_xll.EQNXTDZ($A$1,$B15,C$1,$B$1) -> 3771.24 | D15: =_xll.EQNXTDZ($A$1,$B15,D$1,$B$1) -> 4225.36 | E15: =_xll.EQNXTDZ($A$1,$B15,E$1,$B$1) -> 4895.53 | F15: =_xll.EQNXTDZ($A$1,$B15,F$1,$B$1) -> 5206.78 | G15: =_xll.EQNXTDZ($A$1,$B15,G$1,$B$1) -> 4781.93 | H15: =_xll.EQNXTDZ($A$1,$B15,H$1,$B$1) -> 4473.64 | I15: =_xll.EQNXTDZ($A$1,$B15,I$1,$B$1) -> 3942.25 | J15: =_xll.EQNXTDZ($A$1,$B15,J$1,$B$1) -> 4110.68 | ... BV15: =_xll.EQNXTDZ($A$1,$B15,BV$1,$B$1) -> 0
A16: Employee Cost | B16: QTR_EXPLOYEE_COST | C16: =_xll.EQNXTDZ($A$1,$B16,C$1,$B$1) -> 309.79 | D16: =_xll.EQNXTDZ($A$1,$B16,D$1,$B$1) -> 345.32 | E16: =_xll.EQNXTDZ($A$1,$B16,E$1,$B$1) -> 333.66 | F16: =_xll.EQNXTDZ($A$1,$B16,F$1,$B$1) -> 334.18 | G16: =_xll.EQNXTDZ($A$1,$B16,G$1,$B$1) -> 330.16 | H16: =_xll.EQNXTDZ($A$1,$B16,H$1,$B$1) -> 307.4 | I16: =_xll.EQNXTDZ($A$1,$B16,I$1,$B$1) -> 323.03 | J16: =_xll.EQNXTDZ($A$1,$B16,J$1,$B$1) -> 388.76 | ... BV16: =_xll.EQNXTDZ($A$1,$B16,BV$1,$B$1) -> 0
... A42: Consolidated PAT(after extra items) | B42: QTR_CONS_PAT_EXITM | C42: =_xll.EQNXTDZ($A$1,$B42,C$1,$B$1) -> 145.93 | D42: =_xll.EQNXTDZ($A$1,$B42,D$1,$B$1) -> -83.8 | E42: =_xll.EQNXTDZ($A$1,$B42,E$1,$B$1) -> -328.92 | F42: =_xll.EQNXTDZ($A$1,$B42,F$1,$B$1) -> 181.36 | G42: =_xll.EQNXTDZ($A$1,$B42,G$1,$B$1) -> -114.7 | H42: =_xll.EQNXTDZ($A$1,$B42,H$1,$B$1) -> 74.97 | I42: =_xll.EQNXTDZ($A$1,$B42,I$1,$B$1) -> -74.91 | J42: =_xll.EQNXTDZ($A$1,$B42,J$1,$B$1) -> -145.33 | ... BV42: =_xll.EQNXTDZ($A$1,$B42,BV$1,$B$1) -> 0
A44: Field Description | B44: Field Name
A45: Equity Capital | B45: QTR_EQUITY_CAP | C45: =_xll.EQNXTDZ($A$1,$B45,C$1,$B$1) -> 237.29 | D45: =_xll.EQNXTDZ($A$1,$B45,D$1,$B$1) -> 237.29 | E45: =_xll.EQNXTDZ($A$1,$B45,E$1,$B$1) -> 237.29 | F45: =_xll.EQNXTDZ($A$1,$B45,F$1,$B$1) -> 237.29 | G45: =_xll.EQNXTDZ($A$1,$B45,G$1,$B$1) -> 237.29 | H45: =_xll.EQNXTDZ($A$1,$B45,H$1,$B$1) -> 237.29 | I45: =_xll.EQNXTDZ($A$1,$B45,I$1,$B$1) -> 237.29 | J45: =_xll.EQNXTDZ($A$1,$B45,J$1,$B$1) -> 237.29 | ... BV45: =_xll.EQNXTDZ($A$1,$B45,BV$1,$B$1) -> 0
A46: Face Value | B46: QTR_FV | C46: =_xll.EQNXTDZ($A$1,$B46,C$1,$B$1) -> 1 | D46: =_xll.EQNXTDZ($A$1,$B46,D$1,$B$1) -> 1 | E46: =_xll.EQNXTDZ($A$1,$B46,E$1,$B$1) -> 1 | F46: =_xll.EQNXTDZ($A$1,$B46,F$1,$B$1) -> 1 | G46: =_xll.EQNXTDZ($A$1,$B46,G$1,$B$1) -> 1 | H46: =_xll.EQNXTDZ($A$1,$B46,H$1,$B$1) -> 1 | I46: =_xll.EQNXTDZ($A$1,$B46,I$1,$B$1) -> 1 | J46: =_xll.EQNXTDZ($A$1,$B46,J$1,$B$1) -> 1 | ... BV46: =_xll.EQNXTDZ($A$1,$B46,BV$1,$B$1) -> 0
A47: Month End | B47: BMONTH_MONTHEND | C47: =_xll.EQNXTDZ($A$1,$B47,C$5) -> 201206 | D47: =_xll.EQNXTDZ($A$1,$B47,D$5) -> 201209 | E47: =_xll.EQNXTDZ($A$1,$B47,E$5) -> 201212 | F47: =_xll.EQNXTDZ($A$1,$B47,F$5) -> 201303 | G47: =_xll.EQNXTDZ($A$1,$B47,G$5) -> 201306 | H47: =_xll.EQNXTDZ($A$1,$B47,H$5) -> 201309 | I47: =_xll.EQNXTDZ($A$1,$B47,I$5) -> 201312 | J47: =_xll.EQNXTDZ($A$1,$B47,J$5) -> 201403 | ... BV47: =_xll.EQNXTDZ($A$1,$B47,BV$5) -> 0
A48: Close | B48: BMONTH_CLOSE | C48: =_xll.EQNXTDZ($A$1,$B48,C$5) -> 101.03726 | D48: =_xll.EQNXTDZ($A$1,$B48,D$5) -> 103.20855 | E48: =_xll.EQNXTDZ($A$1,$B48,E$5) -> 106.48961 | F48: =_xll.EQNXTDZ($A$1,$B48,F$5) -> 93.027623 | G48: =_xll.EQNXTDZ($A$1,$B48,G$5) -> 83.039698 | H48: =_xll.EQNXTDZ($A$1,$B48,H$5) -> 78.262865 | I48: =_xll.EQNXTDZ($A$1,$B48,I$5) -> 88.154288 | J48: =_xll.EQNXTDZ($A$1,$B48,J$5) -> 84.8 | ... BV48: =_xll.EQNXTDZ($A$1,$B48,BV$5) -> 0
A49: Total of Promoter and Promoter Group | B49: SHP_TPFTOTALPROMOTER | C49: =_xll.EQNXTDZ($A$1,$B49,C$5) -> 31.75 | D49: =_xll.EQNXTDZ($A$1,$B49,D$5) -> 31.75 | E49: =_xll.EQNXTDZ($A$1,$B49,E$5) -> 31.75 | F49: =_xll.EQNXTDZ($A$1,$B49,F$5) -> 32.47 | G49: =_xll.EQNXTDZ($A$1,$B49,G$5) -> 32.47 | H49: =_xll.EQNXTDZ($A$1,$B49,H$5) -> 32.47 | I49: =_xll.EQNXTDZ($A$1,$B49,I$5) -> 32.47 | J49: =_xll.EQNXTDZ($A$1,$B49,J$5) -> 32.47 | ... BV49: =_xll.EQNXTDZ($A$1,$B49,BV$5) -> 0
A50: Total of Promoter and Promoter Group Pledged | B50: SHP_PSHFTOTALPROMOTER | C50: =_xll.EQNXTDZ($A$1,$B50,C$5) -> 6.91 | D50: =_xll.EQNXTDZ($A$1,$B50,D$5) -> 6.91 | E50: =_xll.EQNXTDZ($A$1,$B50,E$5) -> 6.91 | F50: =_xll.EQNXTDZ($A$1,$B50,F$5) -> 6.76 | G50: =_xll.EQNXTDZ($A$1,$B50,G$5) -> 4.59 | H50: =_xll.EQNXTDZ($A$1,$B50,H$5) -> 4.59 | I50: =_xll.EQNXTDZ($A$1,$B50,I$5) -> 4.59 | J50: =_xll.EQNXTDZ($A$1,$B50,J$5) -> 4.59 | ... BV50: =_xll.EQNXTDZ($A$1,$B50,BV$5) -> 0
A54: Field Description | B54: Field Name | C54: =_xll.EQNXTDZ($A$1,$B54,C$5) -> 0 | D54: =_xll.EQNXTDZ($A$1,$B54,D$5) -> 0 | E54: =_xll.EQNXTDZ($A$1,$B54,E$5) -> 0 | F54: =_xll.EQNXTDZ($A$1,$B54,F$5) -> 0 | G54: =_xll.EQNXTDZ($A$1,$B54,G$5) -> 0 | H54: =_xll.EQNXTDZ($A$1,$B54,H$5) -> 0 | I54: =_xll.EQNXTDZ($A$1,$B54,I$5) -> 0 | J54: =_xll.EQNXTDZ($A$1,$B54,J$5) -> 0 | ... BV54: =_xll.EQNXTDZ($A$1,$B54,BV$5) -> 0
A55: Year End | B55: QTRB_DATE_END | C55: =_xll.EQNXTDZ($A$1,$B55,C$5,$B$1) -> 0 | D55: =_xll.EQNXTDZ($A$1,$B55,D$5,$B$1) -> 201209 | E55: =_xll.EQNXTDZ($A$1,$B55,E$5,$B$1) -> 0 | F55: =_xll.EQNXTDZ($A$1,$B55,F$5,$B$1) -> 201303 | G55: =_xll.EQNXTDZ($A$1,$B55,G$5,$B$1) -> 0 | H55: =_xll.EQNXTDZ($A$1,$B55,H$5,$B$1) -> 201309 | I55: =_xll.EQNXTDZ($A$1,$B55,I$5,$B$1) -> 0 | J55: =_xll.EQNXTDZ($A$1,$B55,J$5,$B$1) -> 201403 | ... BV55: =_xll.EQNXTDZ($A$1,$B55,BV$5,$B$1) -> 0
A56: Share Capital | B56: QTRB_SHARE_CAPITAL | C56: =_xll.EQNXTDZ($A$1,$B56,C$5,$B$1) -> 0 | D56: =_xll.EQNXTDZ($A$1,$B56,D$5,$B$1) -> 237.33 | E56: =_xll.EQNXTDZ($A$1,$B56,E$5,$B$1) -> 0 | F56: =_xll.EQNXTDZ($A$1,$B56,F$5,$B$1) -> 237.29 | G56: =_xll.EQNXTDZ($A$1,$B56,G$5,$B$1) -> 0 | H56: =_xll.EQNXTDZ($A$1,$B56,H$5,$B$1) -> 237.29 | I56: =_xll.EQNXTDZ($A$1,$B56,I$5,$B$1) -> 0 | J56: =_xll.EQNXTDZ($A$1,$B56,J$5,$B$1) -> 237.29 | ... BV56: =_xll.EQNXTDZ($A$1,$B56,BV$5,$B$1) -> 0
A57: Share Warrants & outstandings | B57: QTRB_SHAREWARNDOUT | C57: =_xll.EQNXTDZ($A$1,$B57,C$5,$B$1) -> 0 | D57: =_xll.EQNXTDZ($A$1,$B57,D$5,$B$1) -> 0 | E57: =_xll.EQNXTDZ($A$1,$B57,E$5,$B$1) -> 0 | F57: =_xll.EQNXTDZ($A$1,$B57,F$5,$B$1) -> 0 | G57: =_xll.EQNXTDZ($A$1,$B57,G$5,$B$1) -> 0 | H57: =_xll.EQNXTDZ($A$1,$B57,H$5,$B$1) -> 0 | I57: =_xll.EQNXTDZ($A$1,$B57,I$5,$B$1) -> 0 | J57: =_xll.EQNXTDZ($A$1,$B57,J$5,$B$1) -> 0 | ... BV57: =_xll.EQNXTDZ($A$1,$B57,BV$5,$B$1) -> 0
A58: Reserves & Surplus | B58: QTRB_RESERVE | C58: =_xll.EQNXTDZ($A$1,$B58,C$5,$B$1) -> 0 | D58: =_xll.EQNXTDZ($A$1,$B58,D$5,$B$1) -> 12164.02 | E58: =_xll.EQNXTDZ($A$1,$B58,E$5,$B$1) -> 0 | F58: =_xll.EQNXTDZ($A$1,$B58,F$5,$B$1) -> 12098.5 | G58: =_xll.EQNXTDZ($A$1,$B58,G$5,$B$1) -> 0 | H58: =_xll.EQNXTDZ($A$1,$B58,H$5,$B$1) -> 12811.78 | I58: =_xll.EQNXTDZ($A$1,$B58,I$5,$B$1) -> 0 | J58: =_xll.EQNXTDZ($A$1,$B58,J$5,$B$1) -> 12163.78 | ... BV58: =_xll.EQNXTDZ($A$1,$B58,BV$5,$B$1) -> 0
A59: Shareholder's Funds | B59: QTRB_SHAREHODERS_FUNDS | C59: =_xll.EQNXTDZ($A$1,$B59,C$5,$B$1) -> 0 | D59: =_xll.EQNXTDZ($A$1,$B59,D$5,$B$1) -> 12401.35 | E59: =_xll.EQNXTDZ($A$1,$B59,E$5,$B$1) -> 0 | F59: =_xll.EQNXTDZ($A$1,$B59,F$5,$B$1) -> 12335.79 | G59: =_xll.EQNXTDZ($A$1,$B59,G$5,$B$1) -> 0 | H59: =_xll.EQNXTDZ($A$1,$B59,H$5,$B$1) -> 13049.07 | I59: =_xll.EQNXTDZ($A$1,$B59,I$5,$B$1) -> 0 | J59: =_xll.EQNXTDZ($A$1,$B59,J$5,$B$1) -> 12401.07 | ... BV59: =_xll.EQNXTDZ($A$1,$B59,BV$5,$B$1) -> 0
A60: Minority Interest | B60: QTRB_MINORITY_INTEREST_BS | C60: =_xll.EQNXTDZ($A$1,$B60,C$5,$B$1) -> 0 | D60: =_xll.EQNXTDZ($A$1,$B60,D$5,$B$1) -> 0 | E60: =_xll.EQNXTDZ($A$1,$B60,E$5,$B$1) -> 0 | F60: =_xll.EQNXTDZ($A$1,$B60,F$5,$B$1) -> 2064.6 | G60: =_xll.EQNXTDZ($A$1,$B60,G$5,$B$1) -> 0 | H60: =_xll.EQNXTDZ($A$1,$B60,H$5,$B$1) -> 2163.78 | I60: =_xll.EQNXTDZ($A$1,$B60,I$5,$B$1) -> 0 | J60: =_xll.EQNXTDZ($A$1,$B60,J$5,$B$1) -> 2273.31 | ... BV60: =_xll.EQNXTDZ($A$1,$B60,BV$5,$B$1) -> 0
A61: Long Term Borrowings | B61: QTRB_TOTAL_DEBTS | C61: =_xll.EQNXTDZ($A$1,$B61,C$5,$B$1) -> 0 | D61: =_xll.EQNXTDZ($A$1,$B61,D$5,$B$1) -> 9940.71 | E61: =_xll.EQNXTDZ($A$1,$B61,E$5,$B$1) -> 0 | F61: =_xll.EQNXTDZ($A$1,$B61,F$5,$B$1) -> 33099.34 | G61: =_xll.EQNXTDZ($A$1,$B61,G$5,$B$1) -> 0 | H61: =_xll.EQNXTDZ($A$1,$B61,H$5,$B$1) -> 34342.24 | I61: =_xll.EQNXTDZ($A$1,$B61,I$5,$B$1) -> 0 | J61: =_xll.EQNXTDZ($A$1,$B61,J$5,$B$1) -> 31969.94 | ... BV61: =_xll.EQNXTDZ($A$1,$B61,BV$5,$B$1) -> 0
A62: Secured Loans | B62: QTRB_SECURED_LOANS | C62: =_xll.EQNXTDZ($A$1,$B62,C$5,$B$1) -> 0 | D62: =_xll.EQNXTDZ($A$1,$B62,D$5,$B$1) -> 0 | E62: =_xll.EQNXTDZ($A$1,$B62,E$5,$B$1) -> 0 | F62: =_xll.EQNXTDZ($A$1,$B62,F$5,$B$1) -> 0 | G62: =_xll.EQNXTDZ($A$1,$B62,G$5,$B$1) -> 0 | H62: =_xll.EQNXTDZ($A$1,$B62,H$5,$B$1) -> 0 | I62: =_xll.EQNXTDZ($A$1,$B62,I$5,$B$1) -> 0 | J62: =_xll.EQNXTDZ($A$1,$B62,J$5,$B$1) -> 0 | ... BV62: =_xll.EQNXTDZ($A$1,$B62,BV$5,$B$1) -> 0
A63: Unsecured Loans | B63: QTRB_UNSECURED_LOANS_NF | C63: =_xll.EQNXTDZ($A$1,$B63,C$5,$B$1) -> 0 | D63: =_xll.EQNXTDZ($A$1,$B63,D$5,$B$1) -> 9940.71 | E63: =_xll.EQNXTDZ($A$1,$B63,E$5,$B$1) -> 0 | F63: =_xll.EQNXTDZ($A$1,$B63,F$5,$B$1) -> 33099.34 | G63: =_xll.EQNXTDZ($A$1,$B63,G$5,$B$1) -> 0 | H63: =_xll.EQNXTDZ($A$1,$B63,H$5,$B$1) -> 34342.24 | I63: =_xll.EQNXTDZ($A$1,$B63,I$5,$B$1) -> 0 | J63: =_xll.EQNXTDZ($A$1,$B63,J$5,$B$1) -> 31969.94 | ... BV63: =_xll.EQNXTDZ($A$1,$B63,BV$5,$B$1) -> 0
A64: Other Long Term Liabilities | B64: QTRB_OTHER_LT_LIABILITIES | C64: =_xll.EQNXTDZ($A$1,$B64,C$5,$B$1) -> 0 | D64: =_xll.EQNXTDZ($A$1,$B64,D$5,$B$1) -> 99.86 | E64: =_xll.EQNXTDZ($A$1,$B64,E$5,$B$1) -> 0 | F64: =_xll.EQNXTDZ($A$1,$B64,F$5,$B$1) -> 949.11 | G64: =_xll.EQNXTDZ($A$1,$B64,G$5,$B$1) -> 0 | H64: =_xll.EQNXTDZ($A$1,$B64,H$5,$B$1) -> 993.27 | I64: =_xll.EQNXTDZ($A$1,$B64,I$5,$B$1) -> 0 | J64: =_xll.EQNXTDZ($A$1,$B64,J$5,$B$1) -> 974.57 | ... BV64: =_xll.EQNXTDZ($A$1,$B64,BV$5,$B$1) -> 0
A65: Long Term Trade Payables | B65: QTRB_LT_TRADE_PAYABLE | C65: =_xll.EQNXTDZ($A$1,$B65,C$5,$B$1) -> 0 | D65: =_xll.EQNXTDZ($A$1,$B65,D$5,$B$1) -> 0 | E65: =_xll.EQNXTDZ($A$1,$B65,E$5,$B$1) -> 0 | F65: =_xll.EQNXTDZ($A$1,$B65,F$5,$B$1) -> 0 | G65: =_xll.EQNXTDZ($A$1,$B65,G$5,$B$1) -> 0 | H65: =_xll.EQNXTDZ($A$1,$B65,H$5,$B$1) -> 0 | I65: =_xll.EQNXTDZ($A$1,$B65,I$5,$B$1) -> 0 | J65: =_xll.EQNXTDZ($A$1,$B65,J$5,$B$1) -> 0 | ... BV65: =_xll.EQNXTDZ($A$1,$B65,BV$5,$B$1) -> 0
A66: Lont Term Provisions | B66: QTRB_LT_PROVISIONS | C66: =_xll.EQNXTDZ($A$1,$B66,C$5,$B$1) -> 0 | D66: =_xll.EQNXTDZ($A$1,$B66,D$5,$B$1) -> 529.38 | E66: =_xll.EQNXTDZ($A$1,$B66,E$5,$B$1) -> 0 | F66: =_xll.EQNXTDZ($A$1,$B66,F$5,$B$1) -> 1164.59 | G66: =_xll.EQNXTDZ($A$1,$B66,G$5,$B$1) -> 0 | H66: =_xll.EQNXTDZ($A$1,$B66,H$5,$B$1) -> 1273.11 | I66: =_xll.EQNXTDZ($A$1,$B66,I$5,$B$1) -> 0 | J66: =_xll.EQNXTDZ($A$1,$B66,J$5,$B$1) -> 914.77 | ... BV66: =_xll.EQNXTDZ($A$1,$B66,BV$5,$B$1) -> 0
... A97: Total Assets | B97: QTRB_TOTAL_APPLICATIONS | C97: =_xll.EQNXTDZ($A$1,$B97,C$5,$B$1) -> 0 | D97: =_xll.EQNXTDZ($A$1,$B97,D$5,$B$1) -> 22971.3 | E97: =_xll.EQNXTDZ($A$1,$B97,E$5,$B$1) -> 0 | F97: =_xll.EQNXTDZ($A$1,$B97,F$5,$B$1) -> 49613.43 | G97: =_xll.EQNXTDZ($A$1,$B97,G$5,$B$1) -> 0 | H97: =_xll.EQNXTDZ($A$1,$B97,H$5,$B$1) -> 51821.47 | I97: =_xll.EQNXTDZ($A$1,$B97,I$5,$B$1) -> 0 | J97: =_xll.EQNXTDZ($A$1,$B97,J$5,$B$1) -> 48533.66 | ... BV97: =_xll.EQNXTDZ($A$1,$B97,BV$5,$B$1) -> 0

Sheet Annual Raw
A1: 100400 | B1: X | C1: 200103 | D1: 200203 | E1: 200303 | F1: 200403 | G1: 200503 | H1: 200603 | I1: 200703 | J1: 200803 | K1: 200903 | L1: 201003 | M1: 201103 | N1: 201203 | O1: 201303 | P1: 201403 | Q1: 201503 | R1: 201603 | S1: 201703 | T1: 201803 | U1: 201903 | V1: 202003 | W1: 202103 | X1: 202203 | Y1: 202303 | Z1: 202403 | AA1: 202503 | AB1: 202603 | AC1: 202703 | AD1: 202803 | AE1: 202903 | AF1: 203003
A3: Field Description | B3: Field Name
A4: Company Name | B4: CD_COMPNAME | C4: =_xll.EQNXTDZ(A1,B4,"L") -> Tata Power Company Ltd.
A5: Year End | B5: PL_YEAR_END | C5: =_xll.EQNXTDZ($A$1,$B5,C$1,$B$1) -> 200103 | D5: =_xll.EQNXTDZ($A$1,$B5,D$1,$B$1) -> 200203 | E5: =_xll.EQNXTDZ($A$1,$B5,E$1,$B$1) -> 200303 | F5: =_xll.EQNXTDZ($A$1,$B5,F$1,$B$1) -> 200403 | G5: =_xll.EQNXTDZ($A$1,$B5,G$1,$B$1) -> 200503 | H5: =_xll.EQNXTDZ($A$1,$B5,H$1,$B$1) -> 200603 | I5: =_xll.EQNXTDZ($A$1,$B5,I$1,$B$1) -> 200703 | J5: =_xll.EQNXTDZ($A$1,$B5,J$1,$B$1) -> 200803 | ... AF5: =_xll.EQNXTDZ($A$1,$B5,AF$1,$B$1) -> 0
A6: Sales Turnover | B6: PL_TOTAL_GROSS_SALES | C6: =_xll.EQNXTDZ($A$1,$B6,C$1,$B$1) -> 3374.8175 | D6: =_xll.EQNXTDZ($A$1,$B6,D$1,$B$1) -> 3861.06 | E6: =_xll.EQNXTDZ($A$1,$B6,E$1,$B$1) -> 4805.45 | F6: =_xll.EQNXTDZ($A$1,$B6,F$1,$B$1) -> 4996.38 | G6: =_xll.EQNXTDZ($A$1,$B6,G$1,$B$1) -> 4900.58 | H6: =_xll.EQNXTDZ($A$1,$B6,H$1,$B$1) -> 5623.21 | I6: =_xll.EQNXTDZ($A$1,$B6,I$1,$B$1) -> 6484.23 | J6: =_xll.EQNXTDZ($A$1,$B6,J$1,$B$1) -> 10904.19 | ... AF6: =_xll.EQNXTDZ($A$1,$B6,AF$1,$B$1) -> 0
A7: Less: Inter divisional transfers | B7: PL_INTER_DIV_TRF | C7: =_xll.EQNXTDZ($A$1,$B7,C$1,$B$1) -> 0 | D7: =_xll.EQNXTDZ($A$1,$B7,D$1,$B$1) -> 0 | E7: =_xll.EQNXTDZ($A$1,$B7,E$1,$B$1) -> 0 | F7: =_xll.EQNXTDZ($A$1,$B7,F$1,$B$1) -> 0 | G7: =_xll.EQNXTDZ($A$1,$B7,G$1,$B$1) -> 0 | H7: =_xll.EQNXTDZ($A$1,$B7,H$1,$B$1) -> 0 | I7: =_xll.EQNXTDZ($A$1,$B7,I$1,$B$1) -> 0 | J7: =_xll.EQNXTDZ($A$1,$B7,J$1,$B$1) -> 0 | ... AF7: =_xll.EQNXTDZ($A$1,$B7,AF$1,$B$1) -> 0
A8: Less: Sales Returns | B8: PL_SALES_RETURN | C8: =_xll.EQNXTDZ($A$1,$B8,C$1,$B$1) -> 0 | D8: =_xll.EQNXTDZ($A$1,$B8,D$1,$B$1) -> 0 | E8: =_xll.EQNXTDZ($A$1,$B8,E$1,$B$1) -> 0 | F8: =_xll.EQNXTDZ($A$1,$B8,F$1,$B$1) -> 0 | G8: =_xll.EQNXTDZ($A$1,$B8,G$1,$B$1) -> 0 | H8: =_xll.EQNXTDZ($A$1,$B8,H$1,$B$1) -> 0 | I8: =_xll.EQNXTDZ($A$1,$B8,I$1,$B$1) -> 0 | J8: =_xll.EQNXTDZ($A$1,$B8,J$1,$B$1) -> 0 | ... AF8: =_xll.EQNXTDZ($A$1,$B8,AF$1,$B$1) -> 0
A9: Less: Excise | B9: PL_EXCISE | C9: =_xll.EQNXTDZ($A$1,$B9,C$1,$B$1) -> 0.355909 | D9: =_xll.EQNXTDZ($A$1,$B9,D$1,$B$1) -> 0 | E9: =_xll.EQNXTDZ($A$1,$B9,E$1,$B$1) -> 0 | F9: =_xll.EQNXTDZ($A$1,$B9,F$1,$B$1) -> 2.66 | G9: =_xll.EQNXTDZ($A$1,$B9,G$1,$B$1) -> 0.29 | H9: =_xll.EQNXTDZ($A$1,$B9,H$1,$B$1) -> 1.95 | I9: =_xll.EQNXTDZ($A$1,$B9,I$1,$B$1) -> 8.59 | J9: =_xll.EQNXTDZ($A$1,$B9,J$1,$B$1) -> 13.33 | ... AF9: =_xll.EQNXTDZ($A$1,$B9,AF$1,$B$1) -> 0
A10: Net Sales | B10: PL_NET_SALES | C10: =_xll.EQNXTDZ($A$1,$B10,C$1,$B$1) -> 3374.4616 | D10: =_xll.EQNXTDZ($A$1,$B10,D$1,$B$1) -> 3861.06 | E10: =_xll.EQNXTDZ($A$1,$B10,E$1,$B$1) -> 4805.45 | F10: =_xll.EQNXTDZ($A$1,$B10,F$1,$B$1) -> 4993.72 | G10: =_xll.EQNXTDZ($A$1,$B10,G$1,$B$1) -> 4900.29 | H10: =_xll.EQNXTDZ($A$1,$B10,H$1,$B$1) -> 5621.26 | I10: =_xll.EQNXTDZ($A$1,$B10,I$1,$B$1) -> 6475.64 | J10: =_xll.EQNXTDZ($A$1,$B10,J$1,$B$1) -> 10890.86 | ... AF10: =_xll.EQNXTDZ($A$1,$B10,AF$1,$B$1) -> 0
A11: Increase/Decrease in Stock | B11: PL_INC_DEC_INVENTORY | C11: =_xll.EQNXTDZ($A$1,$B11,C$1,$B$1) -> -7.9388933 | D11: =_xll.EQNXTDZ($A$1,$B11,D$1,$B$1) -> 1.81 | E11: =_xll.EQNXTDZ($A$1,$B11,E$1,$B$1) -> 19.2 | F11: =_xll.EQNXTDZ($A$1,$B11,F$1,$B$1) -> 0.58 | G11: =_xll.EQNXTDZ($A$1,$B11,G$1,$B$1) -> 1.88 | H11: =_xll.EQNXTDZ($A$1,$B11,H$1,$B$1) -> -28.48 | I11: =_xll.EQNXTDZ($A$1,$B11,I$1,$B$1) -> -7.71 | J11: =_xll.EQNXTDZ($A$1,$B11,J$1,$B$1) -> 17.26 | ... AF11: =_xll.EQNXTDZ($A$1,$B11,AF$1,$B$1) -> 0
A12: Raw Material Consumed | B12: PL_RAW_MATRS_CONSUMED | C12: =_xll.EQNXTDZ($A$1,$B12,C$1,$B$1) -> 0 | D12: =_xll.EQNXTDZ($A$1,$B12,D$1,$B$1) -> 0 | E12: =_xll.EQNXTDZ($A$1,$B12,E$1,$B$1) -> 0 | F12: =_xll.EQNXTDZ($A$1,$B12,F$1,$B$1) -> 0 | G12: =_xll.EQNXTDZ($A$1,$B12,G$1,$B$1) -> 0 | H12: =_xll.EQNXTDZ($A$1,$B12,H$1,$B$1) -> 0 | I12: =_xll.EQNXTDZ($A$1,$B12,I$1,$B$1) -> 0 | J12: =_xll.EQNXTDZ($A$1,$B12,J$1,$B$1) -> 0 | ... AF12: =_xll.EQNXTDZ($A$1,$B12,AF$1,$B$1) -> 0
A13: Power & Fuel Cost | B13: PL_POWER_FUEL | C13: =_xll.EQNXTDZ($A$1,$B13,C$1,$B$1) -> 2107.8016 | D13: =_xll.EQNXTDZ($A$1,$B13,D$1,$B$1) -> 2188.79 | E13: =_xll.EQNXTDZ($A$1,$B13,E$1,$B$1) -> 2783.68 | F13: =_xll.EQNXTDZ($A$1,$B13,F$1,$B$1) -> 2698.83 | G13: =_xll.EQNXTDZ($A$1,$B13,G$1,$B$1) -> 3011.47 | H13: =_xll.EQNXTDZ($A$1,$B13,H$1,$B$1) -> 3770.73 | I13: =_xll.EQNXTDZ($A$1,$B13,I$1,$B$1) -> 4626 | J13: =_xll.EQNXTDZ($A$1,$B13,J$1,$B$1) -> 6512.76 | ... AF13: =_xll.EQNXTDZ($A$1,$B13,AF$1,$B$1) -> 0
A14: Employee Cost | B14: PL_EMPLOYEES | C14: =_xll.EQNXTDZ($A$1,$B14,C$1,$B$1) -> 133.60525 | D14: =_xll.EQNXTDZ($A$1,$B14,D$1,$B$1) -> 137.15 | E14: =_xll.EQNXTDZ($A$1,$B14,E$1,$B$1) -> 181.63 | F14: =_xll.EQNXTDZ($A$1,$B14,F$1,$B$1) -> 245.5 | G14: =_xll.EQNXTDZ($A$1,$B14,G$1,$B$1) -> 209.4 | H14: =_xll.EQNXTDZ($A$1,$B14,H$1,$B$1) -> 234.95 | I14: =_xll.EQNXTDZ($A$1,$B14,I$1,$B$1) -> 275.21 | J14: =_xll.EQNXTDZ($A$1,$B14,J$1,$B$1) -> 448.32 | ... AF14: =_xll.EQNXTDZ($A$1,$B14,AF$1,$B$1) -> 0
A15: Operating & Manufacturing Expenses | B15: PL_GEN_OTHER_MFG_EXPS | C15: =_xll.EQNXTDZ($A$1,$B15,C$1,$B$1) -> 151.80271 | D15: =_xll.EQNXTDZ($A$1,$B15,D$1,$B$1) -> 195.58 | E15: =_xll.EQNXTDZ($A$1,$B15,E$1,$B$1) -> 190.96 | F15: =_xll.EQNXTDZ($A$1,$B15,F$1,$B$1) -> 322.6 | G15: =_xll.EQNXTDZ($A$1,$B15,G$1,$B$1) -> 237.45 | H15: =_xll.EQNXTDZ($A$1,$B15,H$1,$B$1) -> 470.94 | I15: =_xll.EQNXTDZ($A$1,$B15,I$1,$B$1) -> 333.98 | J15: =_xll.EQNXTDZ($A$1,$B15,J$1,$B$1) -> 1298.52 | ... AF15: =_xll.EQNXTDZ($A$1,$B15,AF$1,$B$1) -> 0
A16: Cost of Software development | B16: PL_COST_SW | C16: =_xll.EQNXTDZ($A$1,$B16,C$1,$B$1) -> 0 | D16: =_xll.EQNXTDZ($A$1,$B16,D$1,$B$1) -> 0 | E16: =_xll.EQNXTDZ($A$1,$B16,E$1,$B$1) -> 0 | F16: =_xll.EQNXTDZ($A$1,$B16,F$1,$B$1) -> 0 | G16: =_xll.EQNXTDZ($A$1,$B16,G$1,$B$1) -> 0 | H16: =_xll.EQNXTDZ($A$1,$B16,H$1,$B$1) -> 0 | I16: =_xll.EQNXTDZ($A$1,$B16,I$1,$B$1) -> 0 | J16: =_xll.EQNXTDZ($A$1,$B16,J$1,$B$1) -> 0 | ... AF16: =_xll.EQNXTDZ($A$1,$B16,AF$1,$B$1) -> 0
... A36: Profit After Tax from Discontinued Operations | B36: PL_PAT_DIS_OP | C36: =_xll.EQNXTDZ($A$1,$B36,C$1,$B$1) -> 0 | D36: =_xll.EQNXTDZ($A$1,$B36,D$1,$B$1) -> 0 | E36: =_xll.EQNXTDZ($A$1,$B36,E$1,$B$1) -> 0 | F36: =_xll.EQNXTDZ($A$1,$B36,F$1,$B$1) -> 0 | G36: =_xll.EQNXTDZ($A$1,$B36,G$1,$B$1) -> 0 | H36: =_xll.EQNXTDZ($A$1,$B36,H$1,$B$1) -> 0 | I36: =_xll.EQNXTDZ($A$1,$B36,I$1,$B$1) -> 0 | J36: =_xll.EQNXTDZ($A$1,$B36,J$1,$B$1) -> 0 | ... AF36: =_xll.EQNXTDZ($A$1,$B36,AF$1,$B$1) -> 0
A39: Field Description | B39: Field Name
A40: Year End | B40: BS_YEAR_END | C40: =_xll.EQNXTDZ($A$1,$B40,C$1,$B$1) -> 200103 | D40: =_xll.EQNXTDZ($A$1,$B40,D$1,$B$1) -> 200203 | E40: =_xll.EQNXTDZ($A$1,$B40,E$1,$B$1) -> 200303 | F40: =_xll.EQNXTDZ($A$1,$B40,F$1,$B$1) -> 200403 | G40: =_xll.EQNXTDZ($A$1,$B40,G$1,$B$1) -> 200503 | H40: =_xll.EQNXTDZ($A$1,$B40,H$1,$B$1) -> 200603 | I40: =_xll.EQNXTDZ($A$1,$B40,I$1,$B$1) -> 200703 | J40: =_xll.EQNXTDZ($A$1,$B40,J$1,$B$1) -> 200803 | ... AF40: =_xll.EQNXTDZ($A$1,$B40,AF$1,$B$1) -> 0
A41: Share Capital | B41: BS_SHARE_CAPITAL | C41: =_xll.EQNXTDZ($A$1,$B41,C$1,$B$1) -> 197.91345 | D41: =_xll.EQNXTDZ($A$1,$B41,D$1,$B$1) -> 197.87 | E41: =_xll.EQNXTDZ($A$1,$B41,E$1,$B$1) -> 197.87 | F41: =_xll.EQNXTDZ($A$1,$B41,F$1,$B$1) -> 197.88 | G41: =_xll.EQNXTDZ($A$1,$B41,G$1,$B$1) -> 197.88 | H41: =_xll.EQNXTDZ($A$1,$B41,H$1,$B$1) -> 197.88 | I41: =_xll.EQNXTDZ($A$1,$B41,I$1,$B$1) -> 197.88 | J41: =_xll.EQNXTDZ($A$1,$B41,J$1,$B$1) -> 220.68 | ... AF41: =_xll.EQNXTDZ($A$1,$B41,AF$1,$B$1) -> 0
A42: Share Warrants & Outstandings | B42: BS_SHAREWROUTST | C42: =_xll.EQNXTDZ($A$1,$B42,C$1,$B$1) -> 0 | D42: =_xll.EQNXTDZ($A$1,$B42,D$1,$B$1) -> 0 | E42: =_xll.EQNXTDZ($A$1,$B42,E$1,$B$1) -> 0 | F42: =_xll.EQNXTDZ($A$1,$B42,F$1,$B$1) -> 0 | G42: =_xll.EQNXTDZ($A$1,$B42,G$1,$B$1) -> 0 | H42: =_xll.EQNXTDZ($A$1,$B42,H$1,$B$1) -> 0 | I42: =_xll.EQNXTDZ($A$1,$B42,I$1,$B$1) -> 0 | J42: =_xll.EQNXTDZ($A$1,$B42,J$1,$B$1) -> 60.99 | ... AF42: =_xll.EQNXTDZ($A$1,$B42,AF$1,$B$1) -> 0
A43: Total Reserves | B43: BS_RESERVE | C43: =_xll.EQNXTDZ($A$1,$B43,C$1,$B$1) -> 3670.1513 | D43: =_xll.EQNXTDZ($A$1,$B43,D$1,$B$1) -> 4027.96 | E43: =_xll.EQNXTDZ($A$1,$B43,E$1,$B$1) -> 4270.37 | F43: =_xll.EQNXTDZ($A$1,$B43,F$1,$B$1) -> 4592.28 | G43: =_xll.EQNXTDZ($A$1,$B43,G$1,$B$1) -> 4723.34 | H43: =_xll.EQNXTDZ($A$1,$B43,H$1,$B$1) -> 5284.03 | I43: =_xll.EQNXTDZ($A$1,$B43,I$1,$B$1) -> 5825.76 | J43: =_xll.EQNXTDZ($A$1,$B43,J$1,$B$1) -> 8063.15 | ... AF43: =_xll.EQNXTDZ($A$1,$B43,AF$1,$B$1) -> 0
A44: Shareholder's Funds | B44: BS_SHAREHODERS_FUNDS | C44: =_xll.EQNXTDZ($A$1,$B44,C$1,$B$1) -> 3868.0647 | D44: =_xll.EQNXTDZ($A$1,$B44,D$1,$B$1) -> 4225.83 | E44: =_xll.EQNXTDZ($A$1,$B44,E$1,$B$1) -> 4468.24 | F44: =_xll.EQNXTDZ($A$1,$B44,F$1,$B$1) -> 4790.16 | G44: =_xll.EQNXTDZ($A$1,$B44,G$1,$B$1) -> 4921.22 | H44: =_xll.EQNXTDZ($A$1,$B44,H$1,$B$1) -> 5481.91 | I44: =_xll.EQNXTDZ($A$1,$B44,I$1,$B$1) -> 6023.64 | J44: =_xll.EQNXTDZ($A$1,$B44,J$1,$B$1) -> 8344.82 | ... AF44: =_xll.EQNXTDZ($A$1,$B44,AF$1,$B$1) -> 0
A45: Minority Interest | B45: BS_MINORITY_INTEREST | C45: =_xll.EQNXTDZ($A$1,$B45,C$1,$B$1) -> 0 | D45: =_xll.EQNXTDZ($A$1,$B45,D$1,$B$1) -> 9.57 | E45: =_xll.EQNXTDZ($A$1,$B45,E$1,$B$1) -> 10 | F45: =_xll.EQNXTDZ($A$1,$B45,F$1,$B$1) -> 10.1 | G45: =_xll.EQNXTDZ($A$1,$B45,G$1,$B$1) -> 95.6 | H45: =_xll.EQNXTDZ($A$1,$B45,H$1,$B$1) -> 206.75 | I45: =_xll.EQNXTDZ($A$1,$B45,I$1,$B$1) -> 249.62 | J45: =_xll.EQNXTDZ($A$1,$B45,J$1,$B$1) -> 806.17 | ... AF45: =_xll.EQNXTDZ($A$1,$B45,AF$1,$B$1) -> 0
A46: Long-Term Borrowings | B46: BS_LTRM_BORROWING | C46: =_xll.EQNXTDZ($A$1,$B46,C$1,$B$1) -> 0 | D46: =_xll.EQNXTDZ($A$1,$B46,D$1,$B$1) -> 0 | E46: =_xll.EQNXTDZ($A$1,$B46,E$1,$B$1) -> 0 | F46: =_xll.EQNXTDZ($A$1,$B46,F$1,$B$1) -> 0 | G46: =_xll.EQNXTDZ($A$1,$B46,G$1,$B$1) -> 0 | H46: =_xll.EQNXTDZ($A$1,$B46,H$1,$B$1) -> 0 | I46: =_xll.EQNXTDZ($A$1,$B46,I$1,$B$1) -> 0 | J46: =_xll.EQNXTDZ($A$1,$B46,J$1,$B$1) -> 0 | ... AF46: =_xll.EQNXTDZ($A$1,$B46,AF$1,$B$1) -> 0
A47: Secured Loans | B47: BS_SECURED_LOANS | C47: =_xll.EQNXTDZ($A$1,$B47,C$1,$B$1) -> 1337.9599 | D47: =_xll.EQNXTDZ($A$1,$B47,D$1,$B$1) -> 1516.3 | E47: =_xll.EQNXTDZ($A$1,$B47,E$1,$B$1) -> 1691.54 | F47: =_xll.EQNXTDZ($A$1,$B47,F$1,$B$1) -> 1090.93 | G47: =_xll.EQNXTDZ($A$1,$B47,G$1,$B$1) -> 1949.47 | H47: =_xll.EQNXTDZ($A$1,$B47,H$1,$B$1) -> 2363.93 | I47: =_xll.EQNXTDZ($A$1,$B47,I$1,$B$1) -> 2822.83 | J47: =_xll.EQNXTDZ($A$1,$B47,J$1,$B$1) -> 8208.08 | ... AF47: =_xll.EQNXTDZ($A$1,$B47,AF$1,$B$1) -> 0
A48: Unsecured Loans | B48: BS_UNSECURED_LOANS_NF | C48: =_xll.EQNXTDZ($A$1,$B48,C$1,$B$1) -> 1259.9256 | D48: =_xll.EQNXTDZ($A$1,$B48,D$1,$B$1) -> 1290.45 | E48: =_xll.EQNXTDZ($A$1,$B48,E$1,$B$1) -> 1059.15 | F48: =_xll.EQNXTDZ($A$1,$B48,F$1,$B$1) -> 1003.36 | G48: =_xll.EQNXTDZ($A$1,$B48,G$1,$B$1) -> 1806.3 | H48: =_xll.EQNXTDZ($A$1,$B48,H$1,$B$1) -> 1864.54 | I48: =_xll.EQNXTDZ($A$1,$B48,I$1,$B$1) -> 2355.61 | J48: =_xll.EQNXTDZ($A$1,$B48,J$1,$B$1) -> 952.08 | ... AF48: =_xll.EQNXTDZ($A$1,$B48,AF$1,$B$1) -> 0
A49: Deferred Tax Assets / Liabilities | B49: BS_NET_DEF_TAX_NF | C49: =_xll.EQNXTDZ($A$1,$B49,C$1,$B$1) -> 0 | D49: =_xll.EQNXTDZ($A$1,$B49,D$1,$B$1) -> 130.57 | E49: =_xll.EQNXTDZ($A$1,$B49,E$1,$B$1) -> -21.22 | F49: =_xll.EQNXTDZ($A$1,$B49,F$1,$B$1) -> -17.66 | G49: =_xll.EQNXTDZ($A$1,$B49,G$1,$B$1) -> 43.96 | H49: =_xll.EQNXTDZ($A$1,$B49,H$1,$B$1) -> 33.62 | I49: =_xll.EQNXTDZ($A$1,$B49,I$1,$B$1) -> 45.82 | J49: =_xll.EQNXTDZ($A$1,$B49,J$1,$B$1) -> 282.02 | ... AF49: =_xll.EQNXTDZ($A$1,$B49,AF$1,$B$1) -> 0
A50: Other Long Term Liabilities | B50: BS_OTH_LT_LIAB | C50: =_xll.EQNXTDZ($A$1,$B50,C$1,$B$1) -> 0 | D50: =_xll.EQNXTDZ($A$1,$B50,D$1,$B$1) -> 0 | E50: =_xll.EQNXTDZ($A$1,$B50,E$1,$B$1) -> 0 | F50: =_xll.EQNXTDZ($A$1,$B50,F$1,$B$1) -> 0 | G50: =_xll.EQNXTDZ($A$1,$B50,G$1,$B$1) -> 0 | H50: =_xll.EQNXTDZ($A$1,$B50,H$1,$B$1) -> 0 | I50: =_xll.EQNXTDZ($A$1,$B50,I$1,$B$1) -> 0 | J50: =_xll.EQNXTDZ($A$1,$B50,J$1,$B$1) -> 0 | ... AF50: =_xll.EQNXTDZ($A$1,$B50,AF$1,$B$1) -> 0
A51: Long Term Trade Payables | B51: BS_LT_TRADE_PAYABLES | C51: =_xll.EQNXTDZ($A$1,$B51,C$1,$B$1) -> 0 | D51: =_xll.EQNXTDZ($A$1,$B51,D$1,$B$1) -> 0 | E51: =_xll.EQNXTDZ($A$1,$B51,E$1,$B$1) -> 0 | F51: =_xll.EQNXTDZ($A$1,$B51,F$1,$B$1) -> 0 | G51: =_xll.EQNXTDZ($A$1,$B51,G$1,$B$1) -> 0 | H51: =_xll.EQNXTDZ($A$1,$B51,H$1,$B$1) -> 0 | I51: =_xll.EQNXTDZ($A$1,$B51,I$1,$B$1) -> 0 | J51: =_xll.EQNXTDZ($A$1,$B51,J$1,$B$1) -> 0 | ... AF51: =_xll.EQNXTDZ($A$1,$B51,AF$1,$B$1) -> 0
... A99: Estimated Capital Contracts Remaining | B99: BS_ESTIMATED_CAPITAL_CONTRACT | C99: =_xll.EQNXTDZ($A$1,$B99,C$1,$B$1) -> 0 | D99: =_xll.EQNXTDZ($A$1,$B99,D$1,$B$1) -> 0 | E99: =_xll.EQNXTDZ($A$1,$B99,E$1,$B$1) -> 0 | F99: =_xll.EQNXTDZ($A$1,$B99,F$1,$B$1) -> 0 | G99: =_xll.EQNXTDZ($A$1,$B99,G$1,$B$1) -> 0 | H99: =_xll.EQNXTDZ($A$1,$B99,H$1,$B$1) -> 0 | I99: =_xll.EQNXTDZ($A$1,$B99,I$1,$B$1) -> 0 | J99: =_xll.EQNXTDZ($A$1,$B99,J$1,$B$1) -> 0 | ... AF99: =_xll.EQNXTDZ($A$1,$B99,AF$1,$B$1) -> 0
A103: Field Description | B103: Field Name
A104: Equity Paid Up | B104: BS_EQUITY_PAIDUP | C104: =_xll.EQNXTDZ($A$1,$B104,C$1,$B$1) -> 197.84458 | D104: =_xll.EQNXTDZ($A$1,$B104,D$1,$B$1) -> 197.81 | E104: =_xll.EQNXTDZ($A$1,$B104,E$1,$B$1) -> 197.81 | F104: =_xll.EQNXTDZ($A$1,$B104,F$1,$B$1) -> 197.82 | G104: =_xll.EQNXTDZ($A$1,$B104,G$1,$B$1) -> 197.82 | H104: =_xll.EQNXTDZ($A$1,$B104,H$1,$B$1) -> 197.82 | I104: =_xll.EQNXTDZ($A$1,$B104,I$1,$B$1) -> 197.82 | J104: =_xll.EQNXTDZ($A$1,$B104,J$1,$B$1) -> 220.62 | ... AF104: =_xll.EQNXTDZ($A$1,$B104,AF$1,$B$1) -> 0
A105: Face Value | B105: BS_FACE_VALUE | C105: =_xll.EQNXTDZ($A$1,$B105,C$1,$B$1) -> 10 | D105: =_xll.EQNXTDZ($A$1,$B105,D$1,$B$1) -> 10 | E105: =_xll.EQNXTDZ($A$1,$B105,E$1,$B$1) -> 10 | F105: =_xll.EQNXTDZ($A$1,$B105,F$1,$B$1) -> 10 | G105: =_xll.EQNXTDZ($A$1,$B105,G$1,$B$1) -> 10 | H105: =_xll.EQNXTDZ($A$1,$B105,H$1,$B$1) -> 10 | I105: =_xll.EQNXTDZ($A$1,$B105,I$1,$B$1) -> 10 | J105: =_xll.EQNXTDZ($A$1,$B105,J$1,$B$1) -> 10 | ... AF105: =_xll.EQNXTDZ($A$1,$B105,AF$1,$B$1) -> 0
A106: Close Price (Unit Curr.) | B106: FH_YEAR_PRICE | C106: =_xll.EQNXTDZ($A$1,$B106,C$1,$B$1) -> 9.5681419 | D106: =_xll.EQNXTDZ($A$1,$B106,D$1,$B$1) -> 10.952941 | E106: =_xll.EQNXTDZ($A$1,$B106,E$1,$B$1) -> 10.91434 | F106: =_xll.EQNXTDZ($A$1,$B106,F$1,$B$1) -> 36.37631 | G106: =_xll.EQNXTDZ($A$1,$B106,G$1,$B$1) -> 34.489702 | H106: =_xll.EQNXTDZ($A$1,$B106,H$1,$B$1) -> 55.9179 | I106: =_xll.EQNXTDZ($A$1,$B106,I$1,$B$1) -> 49.162783 | J106: =_xll.EQNXTDZ($A$1,$B106,J$1,$B$1) -> 113.09032 | ... AF106: =_xll.EQNXTDZ($A$1,$B106,AF$1,$B$1) -> 0
A107: High Price (Unit Curr.) | B107: FH_HIGH | C107: =_xll.EQNXTDZ($A$1,$B107,C$1,$B$1) -> 17.437854 | D107: =_xll.EQNXTDZ($A$1,$B107,D$1,$B$1) -> 14.92881 | E107: =_xll.EQNXTDZ($A$1,$B107,E$1,$B$1) -> 13.341358 | F107: =_xll.EQNXTDZ($A$1,$B107,F$1,$B$1) -> 41.30272 | G107: =_xll.EQNXTDZ($A$1,$B107,G$1,$B$1) -> 41.013215 | H107: =_xll.EQNXTDZ($A$1,$B107,H$1,$B$1) -> 58.436594 | I107: =_xll.EQNXTDZ($A$1,$B107,I$1,$B$1) -> 61.761077 | J107: =_xll.EQNXTDZ($A$1,$B107,J$1,$B$1) -> 158.35926 | ... AF107: =_xll.EQNXTDZ($A$1,$B107,AF$1,$B$1) -> 0
A108: Low Price (Unit Curr.) | B108: FH_LOW | C108: =_xll.EQNXTDZ($A$1,$B108,C$1,$B$1) -> 4.2701995 | D108: =_xll.EQNXTDZ($A$1,$B108,D$1,$B$1) -> 8.6851515 | E108: =_xll.EQNXTDZ($A$1,$B108,E$1,$B$1) -> 8.8781549 | F108: =_xll.EQNXTDZ($A$1,$B108,F$1,$B$1) -> 10.899865 | G108: =_xll.EQNXTDZ($A$1,$B108,G$1,$B$1) -> 20.516258 | H108: =_xll.EQNXTDZ($A$1,$B108,H$1,$B$1) -> 32.067509 | I108: =_xll.EQNXTDZ($A$1,$B108,I$1,$B$1) -> 37.635656 | J108: =_xll.EQNXTDZ($A$1,$B108,J$1,$B$1) -> 47.382326 | ... AF108: =_xll.EQNXTDZ($A$1,$B108,AF$1,$B$1) -> 0
A109: Market Capitalization | B109: FH_MCAP | C109: =_xll.EQNXTDZ($A$1,$B109,C$1,$B$1) -> 1961.629 | D109: =_xll.EQNXTDZ($A$1,$B109,D$1,$B$1) -> 2245.1435 | E109: =_xll.EQNXTDZ($A$1,$B109,E$1,$B$1) -> 2237.2311 | F109: =_xll.EQNXTDZ($A$1,$B109,F$1,$B$1) -> 7456.8249 | G109: =_xll.EQNXTDZ($A$1,$B109,G$1,$B$1) -> 7070.0868 | H109: =_xll.EQNXTDZ($A$1,$B109,H$1,$B$1) -> 11462.68 | I109: =_xll.EQNXTDZ($A$1,$B109,I$1,$B$1) -> 10077.94 | J109: =_xll.EQNXTDZ($A$1,$B109,J$1,$B$1) -> 25854.458 | ... AF109: =_xll.EQNXTDZ($A$1,$B109,AF$1,$B$1) -> 0
A110: Adj DPS(Rs) | B110: FR_ADJ_DPS | C110: =_xll.EQNXTDZ($A$1,$B110,C$1,$B$1) -> 0.48262548 | D110: =_xll.EQNXTDZ($A$1,$B110,D$1,$B$1) -> 0.48262548 | E110: =_xll.EQNXTDZ($A$1,$B110,E$1,$B$1) -> 0.62741313 | F110: =_xll.EQNXTDZ($A$1,$B110,F$1,$B$1) -> 0.67567568 | G110: =_xll.EQNXTDZ($A$1,$B110,G$1,$B$1) -> 0.72393822 | H110: =_xll.EQNXTDZ($A$1,$B110,H$1,$B$1) -> 0.82046332 | I110: =_xll.EQNXTDZ($A$1,$B110,I$1,$B$1) -> 0.91698842 | J110: =_xll.EQNXTDZ($A$1,$B110,J$1,$B$1) -> 1.0135135 | ... AF110: =_xll.EQNXTDZ($A$1,$B110,AF$1,$B$1) -> 0
A111: Date End | B111: SHP_DATE_END | C111: =_xll.EQNXTDZ($A$1,$B111,C$5) -> 200103 | D111: =_xll.EQNXTDZ($A$1,$B111,D$5) -> 200203 | E111: =_xll.EQNXTDZ($A$1,$B111,E$5) -> 200303 | F111: =_xll.EQNXTDZ($A$1,$B111,F$5) -> 200403 | G111: =_xll.EQNXTDZ($A$1,$B111,G$5) -> 200503 | H111: =_xll.EQNXTDZ($A$1,$B111,H$5) -> 200603 | I111: =_xll.EQNXTDZ($A$1,$B111,I$5) -> 200703 | J111: =_xll.EQNXTDZ($A$1,$B111,J$5) -> 200803 | ... AF111: =_xll.EQNXTDZ($A$1,$B111,AF$5) -> 0
A112: Total of Promoter and Promoter Group | B112: SHP_TPFTOTALPROMOTER | C112: =_xll.EQNXTDZ($A$1,$B112,C$5) -> 32.05 | D112: =_xll.EQNXTDZ($A$1,$B112,D$5) -> 32.55 | E112: =_xll.EQNXTDZ($A$1,$B112,E$5) -> 32.54 | F112: =_xll.EQNXTDZ($A$1,$B112,F$5) -> 32.5 | G112: =_xll.EQNXTDZ($A$1,$B112,G$5) -> 32.46 | H112: =_xll.EQNXTDZ($A$1,$B112,H$5) -> 32.28 | I112: =_xll.EQNXTDZ($A$1,$B112,I$5) -> 32.25 | J112: =_xll.EQNXTDZ($A$1,$B112,J$5) -> 33.44 | ... AF112: =_xll.EQNXTDZ($A$1,$B112,AF$5) -> 0
A113: Total of Promoter and Promoter Group Pledged | B113: SHP_PSHFTOTALPROMOTER | C113: =_xll.EQNXTDZ($A$1,$B113,C$5) -> 0 | D113: =_xll.EQNXTDZ($A$1,$B113,D$5) -> 0 | E113: =_xll.EQNXTDZ($A$1,$B113,E$5) -> 0 | F113: =_xll.EQNXTDZ($A$1,$B113,F$5) -> 0 | G113: =_xll.EQNXTDZ($A$1,$B113,G$5) -> 0 | H113: =_xll.EQNXTDZ($A$1,$B113,H$5) -> 0 | I113: =_xll.EQNXTDZ($A$1,$B113,I$5) -> 0 | J113: =_xll.EQNXTDZ($A$1,$B113,J$5) -> 0 | ... AF113: =_xll.EQNXTDZ($A$1,$B113,AF$5) -> 0

Sheet QTR Share Price
A1: ='QTR Raw'!A1 -> 100400 | C1: 201206 | D1: 201207 | E1: 201208 | F1: 201209 | G1: 201210 | H1: 201211 | I1: 201212 | J1: 201301 | K1: 201302 | L1: 201303 | M1: 201304 | N1: 201305 | O1: 201306 | P1: 201307 | Q1: 201308 | R1: 201309 | S1: 201310 | T1: 201311 | U1: 201312 | V1: 201401 | W1: 201402 | X1: 201403 | Y1: 201404 | Z1: 201405 | AA1: 201406 | AB1: 201407 | AC1: 201408 | AD1: 201409 | AE1: 201410 | AF1: 201411 | AG1: 201412 | AH1: 201501 | AI1: 201502 | AJ1: 201503 | AK1: 201504 | AL1: 201505 | AM1: 201506 | AN1: 201507 | AO1: 201508 | AP1: 201509 | AQ1: 201510 | AR1: 201511 | AS1: 201512 | AT1: 201601 | AU1: 201602 | AV1: 201603 | AW1: 201604 | AX1: 201605 | AY1: 201606 | AZ1: 201607 | BA1: 201608 | BB1: 201609 | BC1: 201610 | BD1: 201611 | BE1: 201612 | BF1: 201701 | BG1: 201702 | BH1: 201703 | BI1: 201704 | BJ1: 201705 | BK1: 201706 | BL1: 201707 | BM1: 201708 | BN1: 201709 | BO1: 201710 | BP1: 201711 | BQ1: 201712 | BR1: 201801 | BS1: 201802 | BT1: 201803 | BU1: 201804 | BV1: 201805 | BW1: 201806 | BX1: 201807 | BY1: 201808 | BZ1: 201809 | CA1: 201810 | CB1: 201811 | CC1: 201812 | CD1: 201901 | CE1: 201902 | CF1: 201903 | CG1: 201904 | CH1: 201905 | CI1: 201906 | CJ1: 201907 | CK1: 201908 | CL1: 201909 | CM1: 201910 | CN1: 201911 | CO1: 201912 | CP1: 202001 | CQ1: 202002 | CR1: 202003 | CS1: 202004 | CT1: 202005 | CU1: 202006 | CV1: 202007 | CW1: 202008 | CX1: 202009 | CY1: 202010 | CZ1: 202011 | DA1: 202012 | DB1: 202101 | DC1: 202102 | DD1: 202103 | DE1: 202104 | DF1: 202105 | DG1: 202106 | DH1: 202107 | DI1: 202108 | DJ1: 202109 | DK1: 202110 | DL1: 202111 | DM1: 202112 | DN1: 202201 | DO1: 202202 | DP1: 202203 | DQ1: 202204 | DR1: 202205 | DS1: 202206 | DT1: 202207 | DU1: 202208 | DV1: 202209 | DW1: 202210 | DX1: 202211 | DY1: 202212 | DZ1: 202301 | EA1: 202302 | EB1: 202303 | EC1: 202304 | ED1: 202305 | EE1: 202306 | EF1: 202307 | EG1: 202308 | EH1: 202309 | EI1: 202310 | EJ1: 202311 | EK1: 202312 | EL1: 202401 | EM1: 202402 | EN1: 202403 | EO1: 202404 | EP1: 202405 | EQ1: 202406 | ER1: 202407 | ES1: 202408 | ET1: 202409 | EU1: 202410 | EV1: 202411 | EW1: 202412 | EX1: 202501 | EY1: 202502 | EZ1: 202503 | FA1: 202504 | FB1: 202505 | FC1: 202506 | FD1: 202507 | FE1: 202508 | FF1: 202509 | FG1: 202510 | FH1: 202511 | FI1: 202512 | FJ1: 202601 | FK1: 202602 | FL1: 202603 | FM1: 202604 | FN1: 202605 | FO1: 202606 | FP1: 202607 | FQ1: 202608 | FR1: 202609 | FS1: 202610 | FT1: 202611 | FU1: 202612 | FV1: 202701 | FW1: 202702 | FX1: 202703 | FY1: 202704 | FZ1: 202705 | GA1: 202706 | GB1: 202707 | GC1: 202708 | GD1: 202709 | GE1: 202710 | GF1: 202711 | GG1: 202712 | GH1: 202801 | GI1: 202802 | GJ1: 202803 | GK1: 202804 | GL1: 202805 | GM1: 202806 | GN1: 202807 | GO1: 202808 | GP1: 202809 | GQ1: 202810 | GR1: 202811 | GS1: 202812 | GT1: 202901 | GU1: 202902 | GV1: 202903 | GW1: 202904 | GX1: 202905 | GY1: 202906 | GZ1: 202907 | HA1: 202908 | HB1: 202909 | HC1: 202910 | HD1: 202911 | HE1: 202912 | HF1: 203001 | HG1: 203002 | HH1: 203003 | HM1: 201206 | HN1: 201207 | HO1: 201208 | HP1: 201209 | HQ1: 201212 | HR1: 201303 | HS1: 201306 | HT1: 201309 | HU1: 201312 | HV1: 201403 | HW1: 201406 | HX1: 201409 | HY1: 201412 | HZ1: 201503 | IA1: 201506 | IB1: 201509 | IC1: 201512 | ID1: 201603 | IE1: 201606 | IF1: 201609 | IG1: 201612 | IH1: 201703 | II1: 201706 | IJ1: 201709 | IK1: 201712 | IL1: 201803 | IM1: 201806 | IN1: 201809 | IO1: 201812 | IP1: 201903 | IQ1: 201906 | IR1: 201909 | IS1: 201912 | IT1: 202003 | IU1: 202006 | IV1: 202009 | IW1: 202012 | IX1: 202103 | IY1: 202106 | IZ1: 202109 | JA1: 202112 | JB1: 202203 | JC1: 202206 | JD1: 202209 | JE1: 202212 | JF1: 202303 | JG1: 202306 | JH1: 202309 | JI1: 202312 | JJ1: 202403 | JK1: 202406 | JL1: 202409 | JM1: 202412 | JN1: 202503 | JO1: 202506 | JP1: 202509 | JQ1: 202512 | JR1: 202603 | JS1: 202606 | JT1: 202609 | JU1: 202612 | JV1: 202703 | JW1: 202706 | JX1: 202709 | JY1: 202712 | JZ1: 202803 | KA1: 202806 | KB1: 202809 | KC1: 202812 | KD1: 202903 | KE1: 202906 | KF1: 202909 | KG1: 202912 | KH1: 203003
FF2: 45901 | FG2: =+EOMONTH(FF2,1) -> 45961 | FH2: =+EOMONTH(FG2,1) -> 45991 | FI2: =+EOMONTH(FH2,1) -> 46022 | FJ2: =+EOMONTH(FI2,1) -> 46053 | FK2: =+EOMONTH(FJ2,1) -> 46081 | FL2: =+EOMONTH(FK2,1) -> 46112 | FM2: =+EOMONTH(FL2,1) -> 46142 | FN2: =+EOMONTH(FM2,1) -> 46173 | ... HH2: =+EOMONTH(HG2,1) -> 47573
A4: Field Description | B4: Field Name
A5: MonthEnd | B5: NMONTH_MONTHEND | C5: {=_xll.EQNXTDZ($A$1,$B5,C$1)} -> 201206 | D5: {=_xll.EQNXTDZ($A$1,$B5,D$1)} -> 201207 | E5: {=_xll.EQNXTDZ($A$1,$B5,E$1)} -> 201208 | F5: {=_xll.EQNXTDZ($A$1,$B5,F$1)} -> 201209 | G5: {=_xll.EQNXTDZ($A$1,$B5,G$1)} -> 201210 | H5: {=_xll.EQNXTDZ($A$1,$B5,H$1)} -> 201211 | I5: {=_xll.EQNXTDZ($A$1,$B5,I$1)} -> 201212 | J5: {=_xll.EQNXTDZ($A$1,$B5,J$1)} -> 201301 | ... HH5: {=_xll.EQNXTDZ($A$1,$B5,HH$1)} -> 0
A6: Open | B6: NMONTH_OPEN | C6: {=_xll.EQNXTDZ($A$1,$B6,C$1)} -> 90.132572 | D6: {=_xll.EQNXTDZ($A$1,$B6,D$1)} -> 102.29178 | E6: {=_xll.EQNXTDZ($A$1,$B6,E$1)} -> 95.247161 | F6: {=_xll.EQNXTDZ($A$1,$B6,F$1)} -> 96.501683 | G6: {=_xll.EQNXTDZ($A$1,$B6,G$1)} -> 102.48479 | H6: {=_xll.EQNXTDZ($A$1,$B6,H$1)} -> 102.77429 | I6: {=_xll.EQNXTDZ($A$1,$B6,I$1)} -> 104.22182 | J6: {=_xll.EQNXTDZ($A$1,$B6,J$1)} -> 107.30987 | ... HH6: {=_xll.EQNXTDZ($A$1,$B6,HH$1)} -> 0
A7: High | B7: NMONTH_HIGH | C7: {=_xll.EQNXTDZ($A$1,$B7,C$1)} -> 101.80928 | D7: {=_xll.EQNXTDZ($A$1,$B7,D$1)} -> 102.48479 | E7: {=_xll.EQNXTDZ($A$1,$B7,E$1)} -> 99.396734 | F7: {=_xll.EQNXTDZ($A$1,$B7,F$1)} -> 106.73086 | G7: {=_xll.EQNXTDZ($A$1,$B7,G$1)} -> 103.93231 | H7: {=_xll.EQNXTDZ($A$1,$B7,H$1)} -> 104.70433 | I7: {=_xll.EQNXTDZ($A$1,$B7,I$1)} -> 109.19165 | J7: {=_xll.EQNXTDZ($A$1,$B7,J$1)} -> 108.61264 | ... HH7: {=_xll.EQNXTDZ($A$1,$B7,HH$1)} -> 0 | HP7: =+MAX(D7:F7) -> 106.73086 | HQ7: =+MAX(G7:I7) -> 109.19165 | HR7: =+MAX(J7:L7) -> 108.61264 | HS7: =+MAX(M7:O7) -> 97.852707 | HT7: =+MAX(P7:R7) -> 91.869602 | HU7: =+MAX(S7:U7) -> 89.360559 | HV7: =+MAX(V7:X7) -> 88.733298 | HW7: =+MAX(Y7:AA7) -> 115.6 | HX7: =+MAX(AB7:AD7) -> 112.2 | HY7: =+MAX(AE7:AG7) -> 94.9 | HZ7: =+MAX(AH7:AJ7) -> 92.45 | IA7: =+MAX(AK7:AM7) -> 82.35 | IB7: =+MAX(AN7:AP7) -> 76.85 | IC7: =+MAX(AQ7:AS7) -> 72.5 | ID7: =+MAX(AT7:AV7) -> 70.7 | IE7: =+MAX(AW7:AY7) -> 77.4 | IF7: =+MAX(AZ7:BB7) -> 80.35 | IG7: =+MAX(BC7:BE7) -> 84.4 | IH7: =+MAX(BF7:BH7) -> 91.15 | II7: =+MAX(BI7:BK7) -> 90.7 | IJ7: =+MAX(BL7:BN7) -> 89.05 | IK7: =+MAX(BO7:BQ7) -> 97.1 | IL7: =+MAX(BR7:BT7) -> 101.8 | IM7: =+MAX(BU7:BW7) -> 89.55 | IN7: =+MAX(BX7:BZ7) -> 79 | IO7: =+MAX(CA7:CC7) -> 86.1 | IP7: =+MAX(CD7:CF7) -> 77.95 | IQ7: =+MAX(CG7:CI7) -> 77 | IR7: =+MAX(CJ7:CL7) -> 74.15 | IS7: =+MAX(CM7:CO7) -> 62.85 | IT7: =+MAX(CP7:CR7) -> 62.1 | IU7: =+MAX(CS7:CU7) -> 47.4 | IV7: =+MAX(CV7:CX7) -> 63.4 | IW7: =+MAX(CY7:DA7) -> 78.8 | IX7: =+MAX(DB7:DD7) -> 114.5 | IY7: =+MAX(DE7:DG7) -> 132.7 | IZ7: =+MAX(DH7:DJ7) -> 161.2 | JA7: =+MAX(DK7:DM7) -> 267.85 | JB7: =+MAX(DN7:DP7) -> 257.9 | JC7: =+MAX(DQ7:DS7) -> 298.05 | JD7: =+MAX(DT7:DV7) -> 251.15 | JE7: =+MAX(DW7:DY7) -> 234.5 | JF7: =+MAX(DZ7:EB7) -> 215.4 | JG7: =+MAX(EC7:EE7) -> 226.35 | JH7: =+MAX(EF7:EH7) -> 276.5 | JI7: =+MAX(EI7:EK7) -> 346.9 | JJ7: =+MAX(EL7:EN7) -> 433.3 | JK7: =MAX(EO7:EQ7) -> 464.2 | JL7: =MAX(ER7:ET7) -> 494.85 | JM7: =MAX(EU7:EW7) -> 491.2 | JN7: =MAX(EX7:EZ7) -> 402.95 | JO7: =MAX(FA7:FC7) -> 416.8 | JP7: =MAX(FD7:FF7) -> 416.75 | JQ7: =MAX(FG7:FI7) -> 413.25 | JR7: =MAX(FJ7:FL7) -> 418.45 | JS7: =MAX(FM7:FO7) -> 464.9 | JT7: =MAX(FP7:FR7) -> 0 | JU7: =MAX(FS7:FU7) -> 0 | JV7: =MAX(FV7:FX7) -> 0 | JW7: =MAX(FY7:GA7) -> 0 | JX7: =MAX(GB7:GD7) -> 0 | JY7: =MAX(GE7:GG7) -> 0 | JZ7: =MAX(GH7:GJ7) -> 0 | KA7: =MAX(GK7:GM7) -> 0 | KB7: =MAX(GN7:GP7) -> 0 | KC7: =MAX(GQ7:GS7) -> 0 | KD7: =MAX(GT7:GV7) -> 0 | KE7: =MAX(GW7:GY7) -> 0 | KF7: =MAX(GZ7:HB7) -> 0 | KG7: =MAX(HC7:HE7) -> 0 | KH7: =MAX(HF7:HH7) -> 0
A8: Low | B8: NMONTH_LOW | C8: {=_xll.EQNXTDZ($A$1,$B8,C$1)} -> 85.645244 | D8: {=_xll.EQNXTDZ($A$1,$B8,D$1)} -> 88.829799 | E8: {=_xll.EQNXTDZ($A$1,$B8,E$1)} -> 91.580097 | F8: {=_xll.EQNXTDZ($A$1,$B8,F$1)} -> 87.237522 | G8: {=_xll.EQNXTDZ($A$1,$B8,G$1)} -> 81.640424 | H8: {=_xll.EQNXTDZ($A$1,$B8,H$1)} -> 92.88287 | I8: {=_xll.EQNXTDZ($A$1,$B8,I$1)} -> 100.55475 | J8: {=_xll.EQNXTDZ($A$1,$B8,J$1)} -> 96.88769 | ... HH8: {=_xll.EQNXTDZ($A$1,$B8,HH$1)} -> 0 | HP8: =+MIN(D8:F8) -> 87.237522 | HQ8: =+MIN(G8:I8) -> 81.640424 | HR8: =+MIN(J8:L8) -> 89.601813 | HS8: =+MIN(M8:O8) -> 74.4993 | HT8: =+MIN(P8:R8) -> 65.717646 | HU8: =+MIN(S8:U8) -> 73.872039 | HV8: =+MIN(V8:X8) -> 68.902202 | HW8: =+MIN(Y8:AA8) -> 75.65 | HX8: =+MIN(AB8:AD8) -> 81.95 | HY8: =+MIN(AE8:AG8) -> 76.55 | HZ8: =+MIN(AH8:AJ8) -> 73.55 | IA8: =+MIN(AK8:AM8) -> 68.35 | IB8: =+MIN(AN8:AP8) -> 55.2 | IC8: =+MIN(AQ8:AS8) -> 61 | ID8: =+MIN(AT8:AV8) -> 55 | IE8: =+MIN(AW8:AY8) -> 60.55 | IF8: =+MIN(AZ8:BB8) -> 69.8 | IG8: =+MIN(BC8:BE8) -> 67 | IH8: =+MIN(BF8:BH8) -> 75.05 | II8: =+MIN(BI8:BK8) -> 76.65 | IJ8: =+MIN(BL8:BN8) -> 75.8 | IK8: =+MIN(BO8:BQ8) -> 77.1 | IL8: =+MIN(BR8:BT8) -> 77 | IM8: =+MIN(BU8:BW8) -> 71 | IN8: =+MIN(BX8:BZ8) -> 65.5 | IO8: =+MIN(CA8:CC8) -> 59.8 | IP8: =+MIN(CD8:CF8) -> 64.05 | IQ8: =+MIN(CG8:CI8) -> 60.85 | IR8: =+MIN(CJ8:CL8) -> 50.35 | IS8: =+MIN(CM8:CO8) -> 51.05 | IT8: =+MIN(CP8:CR8) -> 31.2 | IU8: =+MIN(CS8:CU8) -> 27 | IV8: =+MIN(CV8:CX8) -> 44.05 | IW8: =+MIN(CY8:DA8) -> 51.65 | IX8: =+MIN(DB8:DD8) -> 74.45 | IY8: =+MIN(DE8:DG8) -> 89.9 | IZ8: =+MIN(DH8:DJ8) -> 118.4 | JA8: =+MIN(DK8:DM8) -> 156.6 | JB8: =+MIN(DN8:DP8) -> 203.25 | JC8: =+MIN(DQ8:DS8) -> 190 | JD8: =+MIN(DT8:DV8) -> 200.6 | JE8: =+MIN(DW8:DY8) -> 194.6 | JF8: =+MIN(DZ8:EB8) -> 182.35 | JG8: =+MIN(EC8:EE8) -> 192.05 | JH8: =+MIN(EF8:EH8) -> 216.75 | JI8: =+MIN(EI8:EK8) -> 230.8 | JJ8: =+MIN(EL8:EN8) -> 319.6 | JK8: =MIN(EO8:EQ8) -> 371.65 | JL8: =MIN(ER8:ET8) -> 400 | JM8: =MIN(EU8:EW8) -> 385.5 | JN8: =MIN(EX8:EZ8) -> 326.35 | JO8: =MIN(FA8:FC8) -> 335 | JP8: =MIN(FD8:FF8) -> 368.5 | JQ8: =MIN(FG8:FI8) -> 369.8 | JR8: =MIN(FJ8:FL8) -> 342.5 | JS8: =MIN(FM8:FO8) -> 368 | JT8: =MIN(FP8:FR8) -> 0 | JU8: =MIN(FS8:FU8) -> 0 | JV8: =MIN(FV8:FX8) -> 0 | JW8: =MIN(FY8:GA8) -> 0 | JX8: =MIN(GB8:GD8) -> 0 | JY8: =MIN(GE8:GG8) -> 0 | JZ8: =MIN(GH8:GJ8) -> 0 | KA8: =MIN(GK8:GM8) -> 0 | KB8: =MIN(GN8:GP8) -> 0 | KC8: =MIN(GQ8:GS8) -> 0 | KD8: =MIN(GT8:GV8) -> 0 | KE8: =MIN(GW8:GY8) -> 0 | KF8: =MIN(GZ8:HB8) -> 0 | KG8: =MIN(HC8:HE8) -> 0 | KH8: =MIN(HF8:HH8) -> 0
A9: Close | B9: NMONTH_CLOSE | C9: {=_xll.EQNXTDZ($A$1,$B9,C$1)} -> 101.03726 | D9: {=_xll.EQNXTDZ($A$1,$B9,D$1)} -> 94.812904 | E9: {=_xll.EQNXTDZ($A$1,$B9,E$1)} -> 96.019175 | F9: {=_xll.EQNXTDZ($A$1,$B9,F$1)} -> 103.20855 | G9: {=_xll.EQNXTDZ($A$1,$B9,G$1)} -> 102.34004 | H9: {=_xll.EQNXTDZ($A$1,$B9,H$1)} -> 104.02881 | I9: {=_xll.EQNXTDZ($A$1,$B9,I$1)} -> 106.48961 | J9: {=_xll.EQNXTDZ($A$1,$B9,J$1)} -> 97.563202 | ... HH9: {=_xll.EQNXTDZ($A$1,$B9,HH$1)} -> 0 | HP9: =+F9 -> 103.20855 | HQ9: =+I9 -> 106.48961 | HR9: =+L9 -> 93.124124 | HS9: =+O9 -> 83.280953 | HT9: =+R9 -> 78.311116 | HU9: =+U9 -> 88.154288 | HV9: =+X9 -> 85.15 | HW9: =+AA9 -> 107.8 | HX9: =+AD9 -> 83.05 | HY9: =+AG9 -> 82.15 | HZ9: =+AJ9 -> 77.1 | IA9: =+AM9 -> 74.15 | IB9: =+AP9 -> 64.95 | IC9: =+AS9 -> 67.9 | ID9: =+AV9 -> 64.65 | IE9: =+AY9 -> 73.35 | IF9: =+BB9 -> 75.4 | IG9: =+BE9 -> 75.9 | IH9: =+BH9 -> 90.35 | II9: =+BK9 -> 80.55 | IJ9: =+BN9 -> 77.8 | IK9: =+BQ9 -> 93.5 | IL9: =+BT9 -> 79 | IM9: =+BW9 -> 73.25 | IN9: =+BZ9 -> 65.85 | IO9: =+CC9 -> 76.8 | IP9: =+CF9 -> 73.8 | IQ9: =+CI9 -> 69 | IR9: =+CL9 -> 62.5 | IS9: =+CO9 -> 56.5 | IT9: =+CR9 -> 32.85 | IU9: =+CU9 -> 44.85 | IV9: =+CX9 -> 53.3 | IW9: =+DA9 -> 75.65 | IX9: =+DD9 -> 103.25 | IY9: =+DG9 -> 122.1 | IZ9: =+DJ9 -> 158.75 | JA9: =+DM9 -> 220.95 | JB9: =+DP9 -> 238.65 | JC9: =+DS9 -> 202.2 | JD9: =+DV9 -> 216.5 | JE9: =+DY9 -> 207.7 | JF9: =+EB9 -> 190.25 | JG9: =+EE9 -> 221.85 | JH9: =+EH9 -> 262.3 | JI9: =+EK9 -> 332.15 | JJ9: =+EN9 -> 394.2 | JK9: =EQ9 -> 440.6 | JL9: =ET9 -> 482.6 | JM9: =EW9 -> 392.4 | JN9: =EZ9 -> 375.4 | JO9: =FC9 -> 405.45 | JP9: =FF9 -> 388.65 | JQ9: =FI9 -> 379.6 | JR9: =FL9 -> 378.75 | JS9: =FO9 -> 402.25 | JT9: =FR9 -> 0 | JU9: =FU9 -> 0 | JV9: =FX9 -> 0 | JW9: =GA9 -> 0 | JX9: =GD9 -> 0 | JY9: =GG9 -> 0 | JZ9: =GJ9 -> 0 | KA9: =GM9 -> 0 | KB9: =GP9 -> 0 | KC9: =GS9 -> 0 | KD9: =GV9 -> 0 | KE9: =GY9 -> 0 | KF9: =HB9 -> 0 | KG9: =HE9 -> 0 | KH9: =HH9 -> 0
A11: Field Description | B11: Field Name | C11: {=_xll.EQNXTDZ($A$1,$B11,C$1)} -> 0 | D11: {=_xll.EQNXTDZ($A$1,$B11,D$1)} -> 0 | E11: {=_xll.EQNXTDZ($A$1,$B11,E$1)} -> 0 | F11: {=_xll.EQNXTDZ($A$1,$B11,F$1)} -> 0 | G11: {=_xll.EQNXTDZ($A$1,$B11,G$1)} -> 0 | H11: {=_xll.EQNXTDZ($A$1,$B11,H$1)} -> 0 | I11: {=_xll.EQNXTDZ($A$1,$B11,I$1)} -> 0 | J11: {=_xll.EQNXTDZ($A$1,$B11,J$1)} -> 0 | ... HH11: {=_xll.EQNXTDZ($A$1,$B11,HH$1)} -> 0
A12: Month End | B12: BMONTH_MONTHEND | C12: {=_xll.EQNXTDZ($A$1,$B12,C$1)} -> 201206 | D12: {=_xll.EQNXTDZ($A$1,$B12,D$1)} -> 201207 | E12: {=_xll.EQNXTDZ($A$1,$B12,E$1)} -> 201208 | F12: {=_xll.EQNXTDZ($A$1,$B12,F$1)} -> 201209 | G12: {=_xll.EQNXTDZ($A$1,$B12,G$1)} -> 201210 | H12: {=_xll.EQNXTDZ($A$1,$B12,H$1)} -> 201211 | I12: {=_xll.EQNXTDZ($A$1,$B12,I$1)} -> 201212 | J12: {=_xll.EQNXTDZ($A$1,$B12,J$1)} -> 201301 | ... HH12: {=_xll.EQNXTDZ($A$1,$B12,HH$1)} -> 0
A13: Open | B13: BMONTH_OPEN | C13: {=_xll.EQNXTDZ($A$1,$B13,C$1)} -> 89.746565 | D13: {=_xll.EQNXTDZ($A$1,$B13,D$1)} -> 102.48479 | E13: {=_xll.EQNXTDZ($A$1,$B13,E$1)} -> 94.57165 | F13: {=_xll.EQNXTDZ($A$1,$B13,F$1)} -> 96.501683 | G13: {=_xll.EQNXTDZ($A$1,$B13,G$1)} -> 102.29178 | H13: {=_xll.EQNXTDZ($A$1,$B13,H$1)} -> 102.05053 | I13: {=_xll.EQNXTDZ($A$1,$B13,I$1)} -> 104.22182 | J13: {=_xll.EQNXTDZ($A$1,$B13,J$1)} -> 106.92387 | ... HH13: {=_xll.EQNXTDZ($A$1,$B13,HH$1)} -> 0
A14: High | B14: BMONTH_HIGH | C14: {=_xll.EQNXTDZ($A$1,$B14,C$1)} -> 102.19528 | D14: {=_xll.EQNXTDZ($A$1,$B14,D$1)} -> 102.67779 | E14: {=_xll.EQNXTDZ($A$1,$B14,E$1)} -> 99.396734 | F14: {=_xll.EQNXTDZ($A$1,$B14,F$1)} -> 106.68261 | G14: {=_xll.EQNXTDZ($A$1,$B14,G$1)} -> 103.73931 | H14: {=_xll.EQNXTDZ($A$1,$B14,H$1)} -> 104.46307 | I14: {=_xll.EQNXTDZ($A$1,$B14,I$1)} -> 109.23991 | J14: {=_xll.EQNXTDZ($A$1,$B14,J$1)} -> 108.56439 | ... HH14: {=_xll.EQNXTDZ($A$1,$B14,HH$1)} -> 0 | HP14: =+MAX(D14:F14) -> 106.68261 | HQ14: =+MAX(G14:I14) -> 109.23991 | HR14: =+MAX(J14:L14) -> 108.56439 | HS14: =+MAX(M14:O14) -> 97.804456 | HT14: =+MAX(P14:R14) -> 91.821352 | HU14: =+MAX(S14:U14) -> 89.215806 | HV14: =+MAX(V14:X14) -> 88.588545 | HW14: =+MAX(Y14:AA14) -> 115.25 | HX14: =+MAX(AB14:AD14) -> 112.1 | HY14: =+MAX(AE14:AG14) -> 94.9 | HZ14: =+MAX(AH14:AJ14) -> 92.4 | IA14: =+MAX(AK14:AM14) -> 82.15 | IB14: =+MAX(AN14:AP14) -> 76.75 | IC14: =+MAX(AQ14:AS14) -> 72.45 | ID14: =+MAX(AT14:AV14) -> 70.75 | IE14: =+MAX(AW14:AY14) -> 77.95 | IF14: =+MAX(AZ14:BB14) -> 80.35 | IG14: =+MAX(BC14:BE14) -> 84.45 | IH14: =+MAX(BF14:BH14) -> 91.1 | II14: =+MAX(BI14:BK14) -> 91.25 | IJ14: =+MAX(BL14:BN14) -> 87.3 | IK14: =+MAX(BO14:BQ14) -> 97.05 | IL14: =+MAX(BR14:BT14) -> 101.75 | IM14: =+MAX(BU14:BW14) -> 89.5 | IN14: =+MAX(BX14:BZ14) -> 78.95 | IO14: =+MAX(CA14:CC14) -> 86.15 | IP14: =+MAX(CD14:CF14) -> 77.9 | IQ14: =+MAX(CG14:CI14) -> 76.9 | IR14: =+MAX(CJ14:CL14) -> 74.05 | IS14: =+MAX(CM14:CO14) -> 62.95 | IT14: =+MAX(CP14:CR14) -> 62.1 | IU14: =+MAX(CS14:CU14) -> 47.35 | IV14: =+MAX(CV14:CX14) -> 63.45 | IW14: =+MAX(CY14:DA14) -> 79 | IX14: =+MAX(DB14:DD14) -> 114.95 | IY14: =+MAX(DE14:DG14) -> 132.5 | IZ14: =+MAX(DH14:DJ14) -> 161.15 | JA14: =+MAX(DK14:DM14) -> 269.7 | JB14: =+MAX(DN14:DP14) -> 257.85 | JC14: =+MAX(DQ14:DS14) -> 298 | JD14: =+MAX(DT14:DV14) -> 251 | JE14: =+MAX(DW14:DY14) -> 234.5 | JF14: =+MAX(DZ14:EB14) -> 215.45 | JG14: =+MAX(EC14:EE14) -> 226.25 | JH14: =+MAX(EF14:EH14) -> 276.5 | JI14: =+MAX(EI14:EK14) -> 346.9 | JJ14: =+MAX(EL14:EN14) -> 433.2 | JK14: =MAX(EO14:EQ14) -> 464.3 | JL14: =MAX(ER14:ET14) -> 494.85 | JM14: =MAX(EU14:EW14) -> 491.25 | JN14: =MAX(EX14:EZ14) -> 402.9 | JO14: =MAX(FA14:FC14) -> 416.7 | JP14: =MAX(FD14:FF14) -> 416.7 | JQ14: =MAX(FG14:FI14) -> 413.2 | JR14: =MAX(FJ14:FL14) -> 418.4 | JS14: =MAX(FM14:FO14) -> 464.8 | JT14: =MAX(FP14:FR14) -> 0 | JU14: =MAX(FS14:FU14) -> 0 | JV14: =MAX(FV14:FX14) -> 0 | JW14: =MAX(FY14:GA14) -> 0 | JX14: =MAX(GB14:GD14) -> 0 | JY14: =MAX(GE14:GG14) -> 0 | JZ14: =MAX(GH14:GJ14) -> 0 | KA14: =MAX(GK14:GM14) -> 0 | KB14: =MAX(GN14:GP14) -> 0 | KC14: =MAX(GQ14:GS14) -> 0 | KD14: =MAX(GT14:GV14) -> 0 | KE14: =MAX(GW14:GY14) -> 0 | KF14: =MAX(GZ14:HB14) -> 0 | KG14: =MAX(HC14:HE14) -> 0 | KH14: =MAX(HF14:HH14) -> 0
A15: Low | B15: BMONTH_LOW | C15: {=_xll.EQNXTDZ($A$1,$B15,C$1)} -> 85.500491 | D15: {=_xll.EQNXTDZ($A$1,$B15,D$1)} -> 89.312308 | E15: {=_xll.EQNXTDZ($A$1,$B15,E$1)} -> 91.676599 | F15: {=_xll.EQNXTDZ($A$1,$B15,F$1)} -> 90.759833 | G15: {=_xll.EQNXTDZ($A$1,$B15,G$1)} -> 96.30868 | H15: {=_xll.EQNXTDZ($A$1,$B15,H$1)} -> 92.979372 | I15: {=_xll.EQNXTDZ($A$1,$B15,I$1)} -> 100.55475 | J15: {=_xll.EQNXTDZ($A$1,$B15,J$1)} -> 97.032443 | ... HH15: {=_xll.EQNXTDZ($A$1,$B15,HH$1)} -> 0 | HP15: =+MIN(D15:F15) -> 89.312308 | HQ15: =+MIN(G15:I15) -> 92.979372 | HR15: =+MIN(J15:L15) -> 89.650064 | HS15: =+MIN(M15:O15) -> 74.54755 | HT15: =+MIN(P15:R15) -> 65.862399 | HU15: =+MIN(S15:U15) -> 73.920289 | HV15: =+MIN(V15:X15) -> 68.950453 | HW15: =+MIN(Y15:AA15) -> 75.85 | HX15: =+MIN(AB15:AD15) -> 82 | HY15: =+MIN(AE15:AG15) -> 76.8 | HZ15: =+MIN(AH15:AJ15) -> 73.6 | IA15: =+MIN(AK15:AM15) -> 68.4 | IB15: =+MIN(AN15:AP15) -> 55.55 | IC15: =+MIN(AQ15:AS15) -> 61 | ID15: =+MIN(AT15:AV15) -> 55 | IE15: =+MIN(AW15:AY15) -> 60.6 | IF15: =+MIN(AZ15:BB15) -> 69.7 | IG15: =+MIN(BC15:BE15) -> 67.1 | IH15: =+MIN(BF15:BH15) -> 75.1 | II15: =+MIN(BI15:BK15) -> 76.7 | IJ15: =+MIN(BL15:BN15) -> 75.9 | IK15: =+MIN(BO15:BQ15) -> 77.1 | IL15: =+MIN(BR15:BT15) -> 77 | IM15: =+MIN(BU15:BW15) -> 71 | IN15: =+MIN(BX15:BZ15) -> 65.55 | IO15: =+MIN(CA15:CC15) -> 59.9 | IP15: =+MIN(CD15:CF15) -> 64.1 | IQ15: =+MIN(CG15:CI15) -> 60.9 | IR15: =+MIN(CJ15:CL15) -> 50.4 | IS15: =+MIN(CM15:CO15) -> 51.05 | IT15: =+MIN(CP15:CR15) -> 31.3 | IU15: =+MIN(CS15:CU15) -> 27 | IV15: =+MIN(CV15:CX15) -> 44.05 | IW15: =+MIN(CY15:DA15) -> 51.65 | IX15: =+MIN(DB15:DD15) -> 74.5 | IY15: =+MIN(DE15:DG15) -> 89.95 | IZ15: =+MIN(DH15:DJ15) -> 118.4 | JA15: =+MIN(DK15:DM15) -> 156.6 | JB15: =+MIN(DN15:DP15) -> 203.3 | JC15: =+MIN(DQ15:DS15) -> 190 | JD15: =+MIN(DT15:DV15) -> 200.55 | JE15: =+MIN(DW15:DY15) -> 194.45 | JF15: =+MIN(DZ15:EB15) -> 182.45 | JG15: =+MIN(EC15:EE15) -> 192.05 | JH15: =+MIN(EF15:EH15) -> 216.95 | JI15: =+MIN(EI15:EK15) -> 230.75 | JJ15: =+MIN(EL15:EN15) -> 319.8 | JK15: =MIN(EO15:EQ15) -> 377.2 | JL15: =MIN(ER15:ET15) -> 400 | JM15: =MIN(EU15:EW15) -> 385.45 | JN15: =MIN(EX15:EZ15) -> 326.25 | JO15: =MIN(FA15:FC15) -> 332.1 | JP15: =MIN(FD15:FF15) -> 368.65 | JQ15: =MIN(FG15:FI15) -> 369.75 | JR15: =MIN(FJ15:FL15) -> 342.35 | JS15: =MIN(FM15:FO15) -> 367.85 | JT15: =MIN(FP15:FR15) -> 0 | JU15: =MIN(FS15:FU15) -> 0 | JV15: =MIN(FV15:FX15) -> 0 | JW15: =MIN(FY15:GA15) -> 0 | JX15: =MIN(GB15:GD15) -> 0 | JY15: =MIN(GE15:GG15) -> 0 | JZ15: =MIN(GH15:GJ15) -> 0 | KA15: =MIN(GK15:GM15) -> 0 | KB15: =MIN(GN15:GP15) -> 0 | KC15: =MIN(GQ15:GS15) -> 0 | KD15: =MIN(GT15:GV15) -> 0 | KE15: =MIN(GW15:GY15) -> 0 | KF15: =MIN(GZ15:HB15) -> 0 | KG15: =MIN(HC15:HE15) -> 0 | KH15: =MIN(HF15:HH15) -> 0
A16: Close | B16: BMONTH_CLOSE | C16: {=_xll.EQNXTDZ($A$1,$B16,C$1)} -> 101.03726 | D16: {=_xll.EQNXTDZ($A$1,$B16,D$1)} -> 94.6199 | E16: {=_xll.EQNXTDZ($A$1,$B16,E$1)} -> 96.115677 | F16: {=_xll.EQNXTDZ($A$1,$B16,F$1)} -> 103.20855 | G16: {=_xll.EQNXTDZ($A$1,$B16,G$1)} -> 102.24353 | H16: {=_xll.EQNXTDZ($A$1,$B16,H$1)} -> 103.78756 | I16: {=_xll.EQNXTDZ($A$1,$B16,I$1)} -> 106.48961 | J16: {=_xll.EQNXTDZ($A$1,$B16,J$1)} -> 97.659703 | ... HH16: {=_xll.EQNXTDZ($A$1,$B16,HH$1)} -> 0 | HP16: =+F16 -> 103.20855 | HQ16: =+I16 -> 106.48961 | HR16: =+L16 -> 93.027623 | HS16: =+O16 -> 83.039698 | HT16: =+R16 -> 78.262865 | HU16: =+U16 -> 88.154288 | HV16: =+X16 -> 84.8 | HW16: =+AA16 -> 107.75 | HX16: =+AD16 -> 83 | HY16: =+AG16 -> 82.15 | HZ16: =+AJ16 -> 77.1 | IA16: =+AM16 -> 74.05 | IB16: =+AP16 -> 65.05 | IC16: =+AS16 -> 67.9 | ID16: =+AV16 -> 64.65 | IE16: =+AY16 -> 73.45 | IF16: =+BB16 -> 75.3 | IG16: =+BE16 -> 75.7 | IH16: =+BH16 -> 90.5 | II16: =+BK16 -> 80.55 | IJ16: =+BN16 -> 77.75 | IK16: =+BQ16 -> 93.85 | IL16: =+BT16 -> 79.35 | IM16: =+BW16 -> 73.05 | IN16: =+BZ16 -> 65.95 | IO16: =+CC16 -> 76.75 | IP16: =+CF16 -> 73.8 | IQ16: =+CI16 -> 69 | IR16: =+CL16 -> 62.5 | IS16: =+CO16 -> 56.5 | IT16: =+CR16 -> 32.85 | IU16: =+CU16 -> 44.9 | IV16: =+CX16 -> 53.15 | IW16: =+DA16 -> 75.65 | IX16: =+DD16 -> 103.2 | IY16: =+DG16 -> 122.1 | IZ16: =+DJ16 -> 158.7 | JA16: =+DM16 -> 220.9 | JB16: =+DP16 -> 238.85 | JC16: =+DS16 -> 202.35 | JD16: =+DV16 -> 216.5 | JE16: =+DY16 -> 207.7 | JF16: =+EB16 -> 190.2 | JG16: =+EE16 -> 221.8 | JH16: =+EH16 -> 262.2 | JI16: =+EK16 -> 332.05 | JJ16: =+EN16 -> 394.15 | JK16: =EQ16 -> 440.5 | JL16: =ET16 -> 482.7 | JM16: =EW16 -> 392.4 | JN16: =EZ16 -> 375.4 | JO16: =FC16 -> 405.6 | JP16: =FF16 -> 388.75 | JQ16: =FI16 -> 379.55 | JR16: =FL16 -> 378.7 | JS16: =FO16 -> 402.1 | JT16: =FR16 -> 0 | JU16: =FU16 -> 0 | JV16: =FX16 -> 0 | JW16: =GA16 -> 0 | JX16: =GD16 -> 0 | JY16: =GG16 -> 0 | JZ16: =GJ16 -> 0 | KA16: =GM16 -> 0 | KB16: =GP16 -> 0 | KC16: =GS16 -> 0 | KD16: =GV16 -> 0 | KE16: =GY16 -> 0 | KF16: =HB16 -> 0 | KG16: =HE16 -> 0 | KH16: =HH16 -> 0
A19: High | HP19: =+IF(HP14=0,HP7,HP14) -> 106.68261 | HQ19: =+IF(HQ14=0,HQ7,HQ14) -> 109.23991 | HR19: =+IF(HR14=0,HR7,HR14) -> 108.56439 | HS19: =+IF(HS14=0,HS7,HS14) -> 97.804456 | HT19: =+IF(HT14=0,HT7,HT14) -> 91.821352 | HU19: =+IF(HU14=0,HU7,HU14) -> 89.215806 | HV19: =+IF(HV14=0,HV7,HV14) -> 88.588545 | HW19: =+IF(HW14=0,HW7,HW14) -> 115.25 | ... KH19: =+IF(KH14=0,KH7,KH14) -> 0
A20: Low | HP20: =+IF(HP15=0,HP8,HP15) -> 89.312308 | HQ20: =+IF(HQ15=0,HQ8,HQ15) -> 92.979372 | HR20: =+IF(HR15=0,HR8,HR15) -> 89.650064 | HS20: =+IF(HS15=0,HS8,HS15) -> 74.54755 | HT20: =+IF(HT15=0,HT8,HT15) -> 65.862399 | HU20: =+IF(HU15=0,HU8,HU15) -> 73.920289 | HV20: =+IF(HV15=0,HV8,HV15) -> 68.950453 | HW20: =+IF(HW15=0,HW8,HW15) -> 75.85 | ... KH20: =+IF(KH15=0,KH8,KH15) -> 0
A21: Close | HP21: =+IF(HP16=0,HP9,HP16) -> 103.20855 | HQ21: =+IF(HQ16=0,HQ9,HQ16) -> 106.48961 | HR21: =+IF(HR16=0,HR9,HR16) -> 93.027623 | HS21: =+IF(HS16=0,HS9,HS16) -> 83.039698 | HT21: =+IF(HT16=0,HT9,HT16) -> 78.262865 | HU21: =+IF(HU16=0,HU9,HU16) -> 88.154288 | HV21: =+IF(HV16=0,HV9,HV16) -> 84.8 | HW21: =+IF(HW16=0,HW9,HW16) -> 107.75 | ... KH21: =+IF(KH16=0,KH9,KH16) -> 0

Sheet QTR No. of Shares
A1: ='QTR Raw'!A1 -> 100400 | C1: 201206 | D1: 201209 | E1: 201212 | F1: 201303 | G1: 201306 | H1: 201309 | I1: 201312 | J1: 201403 | K1: 201406 | L1: 201409 | M1: 201412 | N1: 201503 | O1: 201506 | P1: 201509 | Q1: 201512 | R1: 201603 | S1: 201606 | T1: 201609 | U1: 201612 | V1: 201703 | W1: 201706 | X1: 201709 | Y1: 201712 | Z1: 201803 | AA1: 201806 | AB1: 201809 | AC1: 201812 | AD1: 201903 | AE1: 201906 | AF1: 201909 | AG1: 201912 | AH1: 202003 | AI1: 202006 | AJ1: 202009 | AK1: 202012 | AL1: 202103 | AM1: 202106 | AN1: 202109 | AO1: 202112 | AP1: 202203 | AQ1: 202206 | AR1: 202209 | AS1: 202212 | AT1: 202303 | AU1: 202306 | AV1: 202309 | AW1: 202312 | AX1: 202403 | AY1: 202406
A4: Field Description | B4: Field Name
A5: Date End | B5: SHP_DATE_END | C5: {=_xll.EQNXTDZ($A$1,$B5,C$1)} -> 201206 | D5: {=_xll.EQNXTDZ($A$1,$B5,D$1)} -> 201209 | E5: {=_xll.EQNXTDZ($A$1,$B5,E$1)} -> 201212 | F5: {=_xll.EQNXTDZ($A$1,$B5,F$1)} -> 201303 | G5: {=_xll.EQNXTDZ($A$1,$B5,G$1)} -> 201306 | H5: {=_xll.EQNXTDZ($A$1,$B5,H$1)} -> 201309 | I5: {=_xll.EQNXTDZ($A$1,$B5,I$1)} -> 201312 | J5: {=_xll.EQNXTDZ($A$1,$B5,J$1)} -> 201403 | ... AY5: {=_xll.EQNXTDZ($A$1,$B5,AY$1)} -> 202406
A6: Grand Total | B6: SHP_NSGRANDTOTAL | C6: {=_xll.EQNXTDZ($A$1,$B6,C$1)} -> 2373072360 | D6: {=_xll.EQNXTDZ($A$1,$B6,D$1)} -> 2373072360 | E6: {=_xll.EQNXTDZ($A$1,$B6,E$1)} -> 2373072360 | F6: {=_xll.EQNXTDZ($A$1,$B6,F$1)} -> 2373072360 | G6: {=_xll.EQNXTDZ($A$1,$B6,G$1)} -> 2373072360 | H6: {=_xll.EQNXTDZ($A$1,$B6,H$1)} -> 2373072360 | I6: {=_xll.EQNXTDZ($A$1,$B6,I$1)} -> 2373072360 | J6: {=_xll.EQNXTDZ($A$1,$B6,J$1)} -> 2373072360 | ... AY6: {=_xll.EQNXTDZ($A$1,$B6,AY$1)} -> 3195339547
B7: In Crs. | C7: =+C6/10^7 -> 237.30724 | D7: =+D6/10^7 -> 237.30724 | E7: =+E6/10^7 -> 237.30724 | F7: =+F6/10^7 -> 237.30724 | G7: =+G6/10^7 -> 237.30724 | H7: =+H6/10^7 -> 237.30724 | I7: =+I6/10^7 -> 237.30724 | J7: =+J6/10^7 -> 237.30724 | ... AY7: =+AY6/10^7 -> 319.53395

Sheet Share price Daily
A1: =_xll.EQNXTH(B1,"[ADJC];[ADJH];[ADJL];[ADJO];[UCLS];[VOLUME]","2015-Jan-01","Y","All traded days","Asc") -> EQNXTH | B1: =+'Annual Raw'!A1 -> 100400 | L1: =_xll.EQNXTH(B1,"[NADJC];[NADJH];[NADJLOW];[NADJOPEN];[NUCLOSE];[NVOLUME]","2015-Jan-01","Y","All traded days","Asc") -> EQNXTH
A2: Tata Power Company Ltd. | L2: Tata Power Company Ltd.
A3: DATE | B3: ADJHIGH | C3: ADJCLOSE | D3: ADJLOW | E3: ADJOPEN | F3: CLOSE | G3: VOLUME | L3: DATE | M3: ADJCLOSE | N3: ADJHIGH | O3: ADJLOW | P3: ADJOPEN | Q3: CLOSE | R3: VOLUME
A4: 42005 | B4: 82.6 | C4: 82.15 | D4: 81.85 | E4: 81.85 | F4: 82.15 | G4: 188996 | L4: 42005 | M4: 82.15 | N4: 82.65 | O4: 81.95 | P4: 82.2 | Q4: 82.15 | R4: 938370
A5: 42006 | B5: 83.7 | C5: 83.35 | D5: 81.8 | E5: 81.8 | F5: 83.35 | G5: 280751 | L5: 42006 | M5: 83.35 | N5: 83.75 | O5: 82.25 | P5: 82.25 | Q5: 83.35 | R5: 2387959
A6: 42009 | B6: 84.8 | C6: 83 | D6: 82.8 | E6: 84 | F6: 83 | G6: 418334 | L6: 42009 | M6: 82.85 | N6: 84.6 | O6: 82.7 | P6: 84.1 | Q6: 82.85 | R6: 1932062
A7: 42010 | B7: 82.3 | C7: 79.75 | D7: 79.55 | E7: 82.2 | F7: 79.75 | G7: 771722 | L7: 42010 | M7: 79.65 | N7: 82.3 | O7: 79.5 | P7: 82 | Q7: 79.65 | R7: 3509161
A8: 42011 | B8: 80.2 | C8: 78.45 | D8: 78.2 | E8: 79.05 | F8: 78.45 | G8: 366086 | L8: 42011 | M8: 78.25 | N8: 80.2 | O8: 78 | P8: 79.5 | Q8: 78.25 | R8: 6050723
A9: 42012 | B9: 80.35 | C9: 79.95 | D9: 79 | E9: 79 | F9: 79.95 | G9: 193075 | L9: 42012 | M9: 80 | N9: 80.4 | O9: 78.8 | P9: 78.8 | Q9: 80 | R9: 2131875
A10: 42013 | B10: 81 | C10: 79.8 | D10: 79 | E10: 80.4 | F10: 79.8 | G10: 218873 | L10: 42013 | M10: 79.8 | N10: 80.8 | O10: 79 | P10: 80.8 | Q10: 79.8 | R10: 1628211
A11: 42016 | B11: 80.5 | C11: 80.25 | D11: 79.2 | E11: 79.45 | F11: 80.25 | G11: 153187 | L11: 42016 | M11: 80.3 | N11: 80.55 | O11: 79.1 | P11: 79.65 | Q11: 80.3 | R11: 1152593
A12: 42017 | B12: 80.5 | C12: 79.15 | D12: 78.85 | E12: 80.5 | F12: 79.15 | G12: 179604 | L12: 42017 | M12: 79.1 | N12: 80.5 | O12: 78.8 | P12: 80.1 | Q12: 79.1 | R12: 1239610
A13: 42018 | B13: 79.4 | C13: 78.8 | D13: 78.25 | E13: 79 | F13: 78.8 | G13: 169680 | L13: 42018 | M13: 78.85 | N13: 79.5 | O13: 78.2 | P13: 79.2 | Q13: 78.85 | R13: 1698726
A14: 42019 | B14: 82.25 | C14: 81.6 | D14: 79.35 | E14: 79.35 | F14: 81.6 | G14: 514587 | L14: 42019 | M14: 81.7 | N14: 82.5 | O14: 79.8 | P14: 80 | Q14: 81.7 | R14: 3779466
A15: 42020 | B15: 82.6 | C15: 82.45 | D15: 81.1 | E15: 81.2 | F15: 82.45 | G15: 252917 | L15: 42020 | M15: 82.7 | N15: 83 | O15: 81.1 | P15: 81.4 | Q15: 82.7 | R15: 3751660
... A2841: 46190 | B2841: 403.15 | C2841: 401.15 | D2841: 399.6 | E2841: 402.25 | F2841: 401.15 | G2841: 239661 | L2841: 46190 | M2841: 401.5 | N2841: 403.45 | O2841: 399.35 | P2841: 402.25 | Q2841: 401.5 | R2841: 5958070

Sheet Sheet2
J19: 219.3 | K19: 186.25 | L19: 186.75
J20: 192.9 | K20: 135.5 | L20: 146.9 | N20: 219.3 | O20: 192.9 | P20: 186 | Q20: 178.7 | R20: 207 | S20: 255.15 | T20: 348.25 | U20: 374 | V20: 495.9 | W20: 659.9 | X20: 613.4 | Y20: 607.9 | Z20: 555.95 | AA20: 497.8 | AB20: 459.9 | AC20: 374 | AD20: 362 | AE20: 341.5 | AF20: 384.2 | AG20: 433.8 | AH20: 460 | AI20: 474.4 | AJ20: 414.4 | AK20: 318.7 | AL20: 303.25 | AM20: 332.7 | AN20: 295 | AO20: 247 | AP20: 214.4 | AQ20: 179.5 | AR20: 97.9 | AS20: 119.1 | AT20: 130.65 | AU20: 148.55 | AV20: 153.8 | AW20: 152.9 | AX20: 136 | AY20: 141.15 | AZ20: 128.1 | BA20: 142.5 | BB20: 143.55 | BC20: 124.5 | BD20: 241 | BE20: 450 | BF20: 503.35
J21: 186 | K21: 145.4 | L21: 169.1 | N21: 186.25 | O21: 135.5 | P21: 145.4 | Q21: 108.95 | R21: 137 | S21: 170 | T21: 243.15 | U21: 307.5 | V21: 325.1 | W21: 463 | X21: 467.05 | Y21: 436.5 | Z21: 467 | AA21: 348.2 | AB21: 325 | AC21: 313.1 | AD21: 285 | AE21: 277.85 | AF21: 327 | AG21: 317 | AH21: 370.7 | AI21: 360 | AJ21: 271.15 | AK21: 233.15 | AL21: 218.8 | AM21: 262 | AN21: 223.6 | AO21: 137.6 | AP21: 142 | AQ21: 59.3 | AR21: 58 | AS21: 72.8 | AT21: 80 | AU21: 107.25 | AV21: 106 | AW21: 125.1 | AX21: 112.25 | AY21: 81.45 | AZ21: 88 | BA21: 90.35 | BB21: 106.05 | BC21: 98.55 | BD21: 119.25 | BE21: 210 | BF21: 349
J22: 178.7 | K22: 108.95 | L22: 139.75 | N22: 186.75 | O22: 146.9 | P22: 169.1 | Q22: 139.75 | R22: 202.15 | S22: 249.05 | T22: 346.4 | U22: 349.2 | V22: 469.9 | W22: 584.8 | X22: 536.15 | Y22: 513.35 | Z22: 474 | AA22: 438.55 | AB22: 355.4 | AC22: 334.95 | AD22: 298.8 | AE22: 328.35 | AF22: 343 | AG22: 389.9 | AH22: 443.05 | AI22: 407.5 | AJ22: 290.1 | AK22: 235.75 | AL22: 292.65 | AM22: 276.1 | AN22: 237.05 | AO22: 190.1 | AP22: 147.2 | AQ22: 71.9 | AR22: 75.2 | AS22: 90.1 | AT22: 117.2 | AU22: 116.3 | AV22: 140.5 | AW22: 128.6 | AX22: 133.65 | AY22: 91.65 | AZ22: 97.65 | BA22: 125 | BB22: 115.35 | BC22: 119.25 | BD22: 219.3 | BE22: 442.65 | BF22: 503.35
J23: 207 | K23: 137 | L23: 202.15
J24: 255.15 | K24: 170 | L24: 249.05
J25: 348.25 | K25: 243.15 | L25: 346.4
J26: 374 | K26: 307.5 | L26: 349.2
J27: 495.9 | K27: 325.1 | L27: 469.9
J28: 659.9 | K28: 463 | L28: 584.8
J29: 613.4 | K29: 467.05 | L29: 536.15
J30: 607.9 | K30: 436.5 | L30: 513.35
J31: 555.95 | K31: 467 | L31: 474
J32: 497.8 | K32: 348.2 | L32: 438.55
J33: 459.9 | K33: 325 | L33: 355.4
J34: 374 | K34: 313.1 | L34: 334.95
... J63: 503.35 | K63: 349 | L63: 503.35
