Workbook

Sheet Template
A1: =+'Annual Raw'!C4 -> Tata Motors Ltd. | B1: 36951 | C1: =EOMONTH(B1,12) -> 37346 | D1: =EOMONTH(C1,12) -> 37711 | E1: =EOMONTH(D1,12) -> 38077 | F1: =EOMONTH(E1,12) -> 38442 | G1: =EOMONTH(F1,12) -> 38807 | H1: =EOMONTH(G1,12) -> 39172 | I1: =EOMONTH(H1,12) -> 39538 | J1: =EOMONTH(I1,12) -> 39903 | ... AE1: =EOMONTH(AD1,12) -> 47573 | AH1: QTR | AI1: 41061 | AJ1: 41153 | AK1: 41244 | AL1: 41334 | AM1: 41426 | AN1: 41518 | AO1: 41609 | AP1: 41699 | AQ1: 41791 | AR1: 41883 | AS1: 41974 | AT1: 42064 | AU1: 42156 | AV1: 42248 | AW1: 42339 | AX1: 42430 | AY1: 42522 | AZ1: 42614 | BA1: 42705 | BB1: 42795 | BC1: 42887 | BD1: 42979 | BE1: 43070 | BF1: 43160 | BG1: 43252 | BH1: 43344 | BI1: 43435 | BJ1: 43525 | BK1: 43617 | BL1: 43709 | BM1: 43800 | BN1: 43891 | BO1: 43983 | BP1: 44075 | BQ1: =EOMONTH(BP1,3) -> 44196 | BR1: =EOMONTH(BQ1,3) -> 44286 | BS1: =EOMONTH(BR1,3) -> 44377 | BT1: =EOMONTH(BS1,3) -> 44469 | BU1: =EOMONTH(BT1,3) -> 44561 | BV1: =EOMONTH(BU1,3) -> 44651 | BW1: =EOMONTH(BV1,3) -> 44742 | BX1: =EOMONTH(BW1,3) -> 44834 | ... DB1: =EOMONTH(DA1,3) -> 47573 | DE1: HISTORICAL ESTIMATES | DF1: 46112
A2: Presentation Data (Start)
A4: Vahan Data | X4: =+SUM(BW4:BZ4) -> 382995 | Y4: =+SUM(CA4:CD4) -> 369972 | Z4: =+SUM(CE4:CH4) -> 350232 | BW4: =+'Monthly Nos Vahan'!$E$21 -> 97144 | BX4: =+'Monthly Nos Vahan'!$E$24 -> 90110 | BY4: =+'Monthly Nos Vahan'!$E$27 -> 90519 | BZ4: =+'Monthly Nos Vahan'!$E$30 -> 105222 | CA4: =+'Monthly Nos Vahan'!$E$33 -> 89546 | CB4: =+'Monthly Nos Vahan'!$E$36 -> 88114 | CC4: =+'Monthly Nos Vahan'!$E$39 -> 92136 | CD4: =+'Monthly Nos Vahan'!$E$42 -> 100176 | CE4: =+'Monthly Nos Vahan'!$E$45 -> 91641 | CF4: =+'Monthly Nos Vahan'!$E$48 -> 81058 | CG4: =+'Monthly Nos Vahan'!$E$51 -> 85315 | CH4: =+'Monthly Nos Vahan'!$E$54 -> 92218 | CI4: =+'Monthly Nos Vahan'!$E$57 -> 85244 | CJ4: =+'Monthly Nos Vahan'!$E$60 -> 77120 | CK4: ='Monthly Nos Vahan'!E63 -> 99958 | CL4: ='Monthly Nos Vahan'!E66 -> 112511
A5: Volume YoY% | Y5: =+Y4/X4-1 -> -0.034003055 | Z5: =+Z4/Y4-1 -> -0.053355389 | CA5: =+CA4/BW4-1 -> -0.078213786 | CB5: =+CB4/BX4-1 -> -0.022150705 | CC5: =+CC4/BY4-1 -> 0.017863653 | CD5: =+CD4/BZ4-1 -> -0.047955751 | CE5: =+CE4/CA4-1 -> 0.023395797 | CF5: =+CF4/CB4-1 -> -0.080078081 | CG5: =+CG4/CC4-1 -> -0.074031866 | CH5: =+CH4/CD4-1 -> -0.079440185 | ... CL5: =+CL4/CH4-1 -> 0.22005465
A7: Co. reported Volume TTM | N7: =N12 -> 580711 | O7: =O12 -> 420181 | P7: =P12 -> 364573 | Q7: =Q12 -> 378798 | R7: =R12 -> 385029 | S7: =S12 -> 449281 | T7: =T12 -> 519777 | U7: =U12 -> 339953 | ... Z7: =Z12 -> 376903 | AL7: =SUM(AI12:AL12) -> 580711 | AM7: =SUM(AJ12:AM12) -> 570574 | AN7: =SUM(AK12:AN12) -> 536663 | AO7: =SUM(AL12:AO12) -> 483154 | AP7: =SUM(AM12:AP12) -> 420181 | AQ7: =SUM(AN12:AQ12) -> 388189 | AR7: =SUM(AO12:AR12) -> 366855 | AS7: =SUM(AP12:AS12) -> 361344 | ... CL7: =SUM(CI12:CL12) -> 427306
A8: Vahan Volume TTM | N8: =N4 -> 0 | O8: =O4 -> 0 | P8: =P4 -> 0 | Q8: =Q4 -> 0 | R8: =R4 -> 0 | S8: =S4 -> 0 | T8: =T4 -> 0 | U8: =U4 -> 0 | ... Z8: =Z4 -> 350232 | BZ8: =SUM(BW4:BZ4) -> 382995 | CA8: =SUM(BX4:CA4) -> 375397 | CB8: =SUM(BY4:CB4) -> 373401 | CC8: =SUM(BZ4:CC4) -> 375018 | CD8: =SUM(CA4:CD4) -> 369972 | CE8: =SUM(CB4:CE4) -> 372067 | CF8: =SUM(CC4:CF4) -> 365011 | CG8: =SUM(CD4:CG4) -> 358190 | ... CL8: =SUM(CI4:CL4) -> 374833
A9: Co. reported Volume TTM Growth YoY | O9: =O7/N7-1 -> -0.27643699 | P9: =P7/O7-1 -> -0.13234297 | Q9: =Q7/P7-1 -> 0.039018249 | R9: =R7/Q7-1 -> 0.0164494 | S9: =S7/R7-1 -> 0.16687574 | T9: =T7/S7-1 -> 0.15690848 | U9: =U7/T7-1 -> -0.34596375 | V9: =V7/U7-1 -> -0.20032181 | ... Z9: =Z7/Y7-1 -> -0.047852063 | AP9: =AP7/AL7-1 -> -0.27643699 | AQ9: =AQ7/AM7-1 -> -0.31965179 | AR9: =AR7/AN7-1 -> -0.31641458 | AS9: =AS7/AO7-1 -> -0.25211423 | AT9: =AT7/AP7-1 -> -0.13234297 | AU9: =AU7/AQ7-1 -> -0.063481964 | AV9: =AV7/AR7-1 -> -0.014948685 | AW9: =AW7/AS7-1 -> -0.00095200142 | ... CL9: =CL7/CH7-1 -> 0.13372937
A10: Vahan Volume TTM Growth YoY | Y10: =Y8/X8-1 -> -0.034003055 | Z10: =Z8/Y8-1 -> -0.053355389 | CD10: =CD8/BZ8-1 -> -0.034003055 | CE10: =CE8/CA8-1 -> -0.008870609 | CF10: =CF8/CB8-1 -> -0.022469142 | CG10: =CG8/CC8-1 -> -0.044872513 | CH10: =CH8/CD8-1 -> -0.053355389 | CI10: =CI8/CE8-1 -> -0.075878807 | CJ10: =CJ8/CF8-1 -> -0.068803406 | CK10: =CK8/CG8-1 -> -0.010190123 | CL10: =CL8/CH8-1 -> 0.070242011
A12: Monthly Volume | N12: =+SUM(AI12:AL12) -> 580711 | O12: =+SUM(AM12:AP12) -> 420181 | P12: =+SUM(AQ12:AT12) -> 364573 | Q12: =+SUM(AU12:AX12) -> 378798 | R12: =+SUM(AY12:BB12) -> 385029 | S12: =+SUM(BC12:BF12) -> 449281 | T12: =+SUM(BG12:BJ12) -> 519777 | U12: =+SUM(BK12:BN12) -> 339953 | V12: =+SUM(BO12:BR12) -> 271853 | W12: =+SUM(BS12:BV12) -> 356972 | X12: =+SUM(BW12:BZ12) -> 413539 | Y12: =+SUM(CA12:CD12) -> 395845 | Z12: =+SUM(CE12:CH12) -> 376903 | AA12: =SUM(CI12:CL12) -> 427306 | AB12: =+SUM(CM12:CP12) -> 477140.16 | AC12: =+SUM(CQ12:CT12) -> 532952.23 | AD12: =+SUM(CU12:CX12) -> 595479.24 | AE12: =+SUM(CY12:DB12) -> 665551.41 | AI12: =+'Monthly Nos Company'!$K$6 -> 126634 | AJ12: =+'Monthly Nos Company'!$K$9 -> 148667 | AK12: =+'Monthly Nos Company'!$K$12 -> 148965 | AL12: =+'Monthly Nos Company'!$K$15 -> 156445 | AM12: =+'Monthly Nos Company'!$K$18 -> 116497 | AN12: =+'Monthly Nos Company'!$K$21 -> 114756 | AO12: =+'Monthly Nos Company'!$K$24 -> 95456 | AP12: =+'Monthly Nos Company'!$K$27 -> 93472 | AQ12: =+'Monthly Nos Company'!$K$30 -> 84505 | AR12: =+'Monthly Nos Company'!$K$33 -> 93422 | AS12: =+'Monthly Nos Company'!$K$36 -> 89945 | AT12: =+'Monthly Nos Company'!$K$39 -> 96701 | AU12: =+'Monthly Nos Company'!$K$42 -> 83478 | AV12: =+'Monthly Nos Company'!$K$45 -> 91247 | AW12: =+'Monthly Nos Company'!$K$48 -> 89574 | AX12: =+'Monthly Nos Company'!$K$51 -> 114499 | AY12: =+'Monthly Nos Company'!$K$54 -> 91444 | AZ12: =+'Monthly Nos Company'!$K$57 -> 92180 | BA12: =+'Monthly Nos Company'!$K$60 -> 91693 | BB12: =+'Monthly Nos Company'!$K$63 -> 109712 | BC12: =+'Monthly Nos Company'!$K$66 -> 74520 | BD12: =+'Monthly Nos Company'!$K$69 -> 106091 | BE12: =+'Monthly Nos Company'!$K$72 -> 123091 | BF12: =+'Monthly Nos Company'!$K$75 -> 145579 | BG12: =+'Monthly Nos Company'!$K$78 -> 123215 | BH12: =+'Monthly Nos Company'!$K$81 -> 136184 | BI12: =+'Monthly Nos Company'!$K$84 -> 121785 | BJ12: =+'Monthly Nos Company'!$K$87 -> 138593 | BK12: =+'Monthly Nos Company'!$K$90 -> 99610 | BL12: =+'Monthly Nos Company'!$K$93 -> 78602 | BM12: =+'Monthly Nos Company'!$K$96 -> 92672 | BN12: =+'Monthly Nos Company'!$K$99 -> 69069 | BO12: =+'Monthly Nos Company'!$K$102 -> 19666 | BP12: =+'Monthly Nos Company'!$K$105 -> 55487 | BQ12: =+'Monthly Nos Company'!$K$108 -> 89323 | BR12: =+'Monthly Nos Company'!$K$111 -> 107377 | BS12: =+'Monthly Nos Company'!$K$114 -> 50145 | BT12: =+'Monthly Nos Company'!$K$117 -> 86887 | BU12: =+'Monthly Nos Company'!$K$120 -> 100070 | BV12: =+'Monthly Nos Company'!$K$123 -> 119870 | BW12: =+'Monthly Nos Company'!$K$126 -> 100921 | BX12: =+'Monthly Nos Company'!$K$129 -> 100536 | BY12: =+'Monthly Nos Company'!$K$132 -> 95914 | BZ12: =+'Monthly Nos Company'!$K$135 -> 116168 | CA12: =+'Monthly Nos Company'!$K$138 -> 85795 | CB12: =+'Monthly Nos Company'!$K$141 -> 104085 | CC12: =+'Monthly Nos Company'!$K$144 -> 96526 | CD12: =+'Monthly Nos Company'!$K$147 -> 109439 | CE12: =+'Monthly Nos Company'!$K$150 -> 91209 | CF12: =+'Monthly Nos Company'!$K$153 -> 84281 | CG12: =+'Monthly Nos Company'!$K$156 -> 95770 | CH12: =+'Monthly Nos Company'!$K$159 -> 105643 | CI12: =+'Monthly Nos Company'!$K$162 -> 85606 | CJ12: =+'Monthly Nos Company'!$K$165 -> 94681 | CK12: =+'Monthly Nos Company'!$K$168 -> 114554 | CL12: =+'Monthly Nos Company'!$K$171 -> 132465 | CM12: =+'Monthly Nos Company'!$K$174 -> 95538 | CN12: =+'Monthly Nos Company'!$K$177 -> 105843.18 | CO12: =+'Monthly Nos Company'!$K$180 -> 128026.56 | CP12: =+'Monthly Nos Company'!$K$183 -> 147732.42 | CQ12: =+'Monthly Nos Company'!$K$186 -> 106655.2 | CR12: =+'Monthly Nos Company'!$K$189 -> 118358.75 | CS12: =+'Monthly Nos Company'!$K$192 -> 143128.78 | CT12: =+'Monthly Nos Company'!$K$195 -> 164809.51 | CU12: =+'Monthly Nos Company'!$K$198 -> 119102.99 | CV12: =+'Monthly Nos Company'!$K$201 -> 132396.25 | CW12: =+'Monthly Nos Company'!$K$204 -> 160063.16 | CX12: =+'Monthly Nos Company'!$K$207 -> 183916.85 | CY12: =+'Monthly Nos Company'!$K$210 -> 133045.08 | CZ12: =+'Monthly Nos Company'!$K$213 -> 148145.73 | DA12: =+'Monthly Nos Company'!$K$216 -> 179057.98 | DB12: =+'Monthly Nos Company'!$K$219 -> 205302.62
A13: Volume YoY% | O13: =+O12/N12-1 -> -0.27643699 | P13: =+P12/O12-1 -> -0.13234297 | Q13: =+Q12/P12-1 -> 0.039018249 | R13: =+R12/Q12-1 -> 0.0164494 | S13: =+S12/R12-1 -> 0.16687574 | T13: =+T12/S12-1 -> 0.15690848 | U13: =+U12/T12-1 -> -0.34596375 | V13: =+V12/U12-1 -> -0.20032181 | ... AE13: =+AE12/AD12-1 -> 0.11767356 | AM13: =+AM12/AI12-1 -> -0.080049592 | AN13: =+AN12/AJ12-1 -> -0.22810039 | AO13: =+AO12/AK12-1 -> -0.35920518 | AP13: =+AP12/AL12-1 -> -0.40252485 | AQ13: =+AQ12/AM12-1 -> -0.27461651 | AR13: =+AR12/AN12-1 -> -0.18590749 | AS13: =+AS12/AO12-1 -> -0.057733406 | AT13: =+AT12/AP12-1 -> 0.034545104 | ... DB13: =+DB12/CX12-1 -> 0.11627954
A15: Unit Matrix
A16: Realisation | N16: =+N32*10^7/N12 -> 823222.94 | O16: =+O32*10^7/O12 -> 865397.76 | P16: =+P32*10^7/P12 -> 1043984 | Q16: =+Q32*10^7/Q12 -> 1262029.6 | R16: =+R32*10^7/R12 -> 1289159.8 | S16: =+S32*10^7/S12 -> 1316443.2 | T16: =+T32*10^7/T12 -> 1339817.7 | U16: =+U32*10^7/U12 -> 1305197.5 | ... AE16: =+AE32*10^7/AE12 -> 1774090 | AI16: =+AI32*10^7/AI12 -> 835984.81 | AJ16: =+AJ32*10^7/AJ12 -> 839550.14 | AK16: =+AK32*10^7/AK12 -> 713596.48 | AL16: =+AL32*10^7/AL12 -> 707455.66 | AM16: =+AM32*10^7/AM12 -> 781522.27 | AN16: =+AN32*10^7/AN12 -> 772809.26 | AO16: =+AO32*10^7/AO12 -> 813953.03 | AP16: =+AP32*10^7/AP12 -> 914229.93 | ... CL16: =+CL32*10^7/CL12 -> 1865851.4 | CM16: =+AVERAGE(CI16:CL16) -> 1827462.8 | CN16: =+AVERAGE(CJ16:CM16) -> 1826358.3 | CO16: =+AVERAGE(CK16:CN16) -> 1830164.3 | CP16: =+AVERAGE(CL16:CO16) -> 1837459.2 | CQ16: =+AVERAGE(CM16:CP16)*0.98 -> 1793753.9 | CR16: =+AVERAGE(CN16:CQ16)*0.98 -> 1785495.2 | CS16: =+AVERAGE(CO16:CR16)*0.98 -> 1775483.8 | CT16: =+AVERAGE(CP16:CS16)*0.98 -> 1762087.1 | CU16: =+AVERAGE(CQ16:CT16) -> 1779205 | CV16: =+AVERAGE(CR16:CU16) -> 1775567.8 | CW16: =+AVERAGE(CS16:CV16) -> 1773085.9 | CX16: =+AVERAGE(CT16:CW16) -> 1772486.4 | CY16: =+AVERAGE(CU16:CX16) -> 1775086.3 | CZ16: =+AVERAGE(CV16:CY16) -> 1774056.6 | DA16: =+AVERAGE(CW16:CZ16) -> 1773678.8 | DB16: =+AVERAGE(CX16:DA16) -> 1773827 | DF16: 1834268.4
A17: RM | N17: =+N16-N18 -> 567668.43 | O17: =+O16-O18 -> 616743.97 | P17: =+P16-P18 -> 741734.85 | Q17: =+Q16-Q18 -> 768468.15 | R17: =+R16-R18 -> 814106.99 | S17: =+S16-S18 -> 950071.56 | T17: =+T16-T18 -> 973797.99 | U17: =+U16-U18 -> 958206.28 | ... AE17: =+AE16-AE18 -> 1217393.6 | AI17: =+AI16-AI18 -> 586951.37 | AJ17: =+AJ16-AJ18 -> 623870.8 | AK17: =+AK16-AK18 -> 537531.63 | AL17: =+AL16-AL18 -> 527347.63 | AM17: =+AM16-AM18 -> 567435.21 | AN17: =+AN16-AN18 -> 573697.24 | AO17: =+AO16-AO18 -> 624667.91 | AP17: =+AP16-AP18 -> 722955.54 | ... DB17: =+DB16-DB18 -> 1198966.3 | DF17: 1276624.2
A18: Delta | N18: =+N38*10^7/N12 -> 255554.52 | O18: =+O38*10^7/O12 -> 248653.79 | P18: =+P38*10^7/P12 -> 302249.17 | Q18: =+Q38*10^7/Q12 -> 493561.48 | R18: =+R38*10^7/R12 -> 475052.79 | S18: =+S38*10^7/S12 -> 366371.6 | T18: =+T38*10^7/T12 -> 366019.66 | U18: =+U38*10^7/U12 -> 346991.2 | ... AE18: =+AE38*10^7/AE12 -> 556696.37 | AI18: =+AI38*10^7/AI12 -> 249033.43 | AJ18: =+AJ38*10^7/AJ12 -> 215679.34 | AK18: =+AK38*10^7/AK12 -> 176064.85 | AL18: =+AL38*10^7/AL12 -> 180108.03 | AM18: =+AM38*10^7/AM12 -> 214087.06 | AN18: =+AN38*10^7/AN12 -> 199112.03 | AO18: =+AO38*10^7/AO12 -> 189285.12 | AP18: =+AP38*10^7/AP12 -> 191274.39 | ... CL18: =+CL38*10^7/CL12 -> 578718.91 | CM18: =+AVERAGE(CI18:CL18) -> 579845.43 | CN18: =+AVERAGE(CJ18:CM18) -> 574087.22 | CO18: =+AVERAGE(CK18:CN18) -> 571962.06 | CP18: =+AVERAGE(CL18:CO18) -> 576153.4 | CQ18: =+AVERAGE(CM18:CP18) -> 575512.03 | CR18: =+AVERAGE(CN18:CQ18) -> 574428.68 | CS18: =+AVERAGE(CO18:CR18) -> 574514.04 | CT18: =+AVERAGE(CP18:CS18) -> 575152.04 | ... DB18: =+AVERAGE(CX18:DA18) -> 574860.69 | DF18: 557644.24
A19: Delta Margin % | N19: =+N18/N16 -> 0.31043172 | O19: =+O18/O16 -> 0.2873289 | P19: =+P18/P16 -> 0.28951513 | Q19: =+Q18/Q16 -> 0.39108549 | R19: =+R18/R16 -> 0.36849799 | S19: =+S18/S16 -> 0.27830416 | T19: =+T18/T16 -> 0.27318617 | U19: =+U18/U16 -> 0.26585341 | ... AE19: =+AE18/AE16 -> 0.31379263 | AI19: =+AI18/AI16 -> 0.2978923 | AJ19: =+AJ18/AJ16 -> 0.2568987 | AK19: =+AK18/AK16 -> 0.24672886 | AL19: =+AL18/AL16 -> 0.2545856 | AM19: =+AM18/AM16 -> 0.27393597 | AN19: =+AN18/AN16 -> 0.25764705 | AO19: =+AO18/AO16 -> 0.23255042 | AP19: =+AP18/AP16 -> 0.20921913 | ... DB19: =+DB18/DB16 -> 0.32407934 | DF19: 0.30401452
A20: Employee Cost | N20: =+N45*10^7/N12 -> 48853.905 | O20: =+O45*10^7/O12 -> 68486.914 | P20: =+P45*10^7/P12 -> 84796.735 | Q20: =+Q45*10^7/Q12 -> 84186.559 | R20: =+R45*10^7/R12 -> 97767.96 | S20: =+S45*10^7/S12 -> 88290.624 | T20: =+T45*10^7/T12 -> 82210.256 | U20: =+U45*10^7/U12 -> 128968.12 | ... AE20: =+AE45*10^7/AE12 -> 91699.396 | AI20: =+AI45*10^7/AI12 -> 55819.132 | AJ20: =+AJ45*10^7/AJ12 -> 50393.833 | AK20: =+AK45*10^7/AK12 -> 49100.795 | AL20: =+AL45*10^7/AL12 -> 41517.466 | AM20: =+AM45*10^7/AM12 -> 64163.884 | AN20: =+AN45*10^7/AN12 -> 60716.651 | AO20: =+AO45*10^7/AO12 -> 75472.469 | AP20: =+AP45*10^7/AP12 -> 76280.597 | ... CL20: =+CL45*10^7/CL12 -> 89080.134 | CM20: =+CI20 -> 135971.78 | CN20: =+CJ20 -> 122516.66 | CO20: =+CK20 -> 100563.93 | CP20: =+CL20 -> 89080.134 | CQ20: =+CM20 -> 135971.78 | CR20: =+CN20 -> 122516.66 | CS20: =+CO20 -> 100563.93 | CT20: =+CP20 -> 89080.134 | ... DB20: =+CX20 -> 89080.134 | DF20: 105070.85
A21: Employee cost % | N21: =+N20/N16 -> 0.059344683 | O21: =+O20/O16 -> 0.079139232 | P21: =+P20/P16 -> 0.081224169 | Q21: =+Q20/Q16 -> 0.066707276 | R21: =+R20/R16 -> 0.075838513 | S21: =+S20/S16 -> 0.067067555 | T21: =+T20/T16 -> 0.061359287 | U21: =+U20/U16 -> 0.098811194 | ... AE21: =+AE20/AE16 -> 0.051688132 | AI21: =+AI20/AI16 -> 0.06677051 | AJ21: =+AJ20/AJ16 -> 0.060024805 | AK21: =+AK20/AK16 -> 0.068807508 | AL21: =+AL20/AL16 -> 0.058685609 | AM21: =+AM20/AM16 -> 0.082101159 | AN21: =+AN20/AN16 -> 0.078566153 | AO21: =+AO20/AO16 -> 0.092723372 | AP21: =+AP20/AP16 -> 0.083436994 | ... DB21: =+DB20/DB16 -> 0.050219177 | DF21: 0.057282157
A22: Other Cost | N22: =+N18-N20-N23 -> 124771.36 | O22: =+O18-O20-O23 -> 152477.55 | P22: =+P18-P20-P23 -> 203141.76 | Q22: =+Q18-Q20-Q23 -> 200648.37 | R22: =+R18-R20-R23 -> 203850.36 | S22: =+S18-S20-S23 -> 197074.21 | T22: =+T18-T20-T23 -> 176212.3 | U22: =+U18-U20-U23 -> 217133.84 | ... AE22: =+AE18-AE20-AE23 -> 461154.61 | AI22: =+AI18-AI20-AI23 -> 137951.89 | AJ22: =+AJ18-AJ20-AJ23 -> 121329.55 | AK22: =+AK18-AK20-AK23 -> 117212.77 | AL22: =+AL18-AL20-AL23 -> 124566.46 | AM22: =+AM18-AM20-AM23 -> 140893.76 | AN22: =+AN18-AN20-AN23 -> 131309.04 | AO22: =+AO18-AO20-AO23 -> 161906.01 | AP22: =+AP18-AP20-AP23 -> 183251.67 | ... DB22: =+DB18-DB20-DB23 -> 236129.71 | DF22: 321225.36
A23: EBITDA | N23: =+N52*10^7/N12 -> 81929.254 | O23: =+O52*10^7/O12 -> 27689.32 | P23: =+P52*10^7/P12 -> 14310.678 | Q23: =+Q52*10^7/Q12 -> 208726.55 | R23: =+R52*10^7/R12 -> 173434.47 | S23: =+S52*10^7/S12 -> 81006.764 | T23: =+T52*10^7/T12 -> 107597.1 | U23: =+U52*10^7/U12 -> 889.24057 | ... AE23: =+AE52*10^7/AE12 -> 3842.3563 | AI23: =+AI52*10^7/AI12 -> 55262.41 | AJ23: =+AJ52*10^7/AJ12 -> 43955.955 | AK23: =+AK52*10^7/AK12 -> 9751.2839 | AL23: =+AL52*10^7/AL12 -> 14024.098 | AM23: =+AM52*10^7/AM12 -> 9029.4171 | AN23: =+AN52*10^7/AN12 -> 7086.3397 | AO23: =+AO52*10^7/AO12 -> -48093.362 | AP23: =+AP52*10^7/AP12 -> -68257.874 | ... CL23: =+CL52*10^7/CL12 -> 249650.85 | CM23: =+CI23 -> 220778.92 | CN23: =+CJ23 -> 219368.19 | CO23: =+CK23 -> 227490.96 | CP23: =+CL23 -> 249650.85 | CQ23: =+CM23 -> 220778.92 | CR23: =+CN23 -> 219368.19 | CS23: =+CO23 -> 227490.96 | CT23: =+CP23 -> 249650.85 | ... DB23: =+CX23 -> 249650.85 | DF23: 131348.03
A24: EBITDA margin % | N24: =+N23/N16 -> 0.099522559 | O24: =+O23/O16 -> 0.031996062 | P24: =+P23/P16 -> 0.013707756 | Q24: =+Q23/Q16 -> 0.16538958 | R24: =+R23/R16 -> 0.13453295 | S24: =+S23/S16 -> 0.06153457 | T24: =+T23/T16 -> 0.080307275 | U24: =+U23/U16 -> 0.0006813073 | ... AE24: =+AE23/AE16 -> 0.0021658182 | AI24: =+AI23/AI16 -> 0.066104562 | AJ24: =+AJ23/AJ16 -> 0.052356558 | AK24: =+AK23/AK16 -> 0.013664983 | AL24: =+AL23/AL16 -> 0.019823289 | AM24: =+AM23/AM16 -> 0.011553627 | AN24: =+AN23/AN16 -> 0.0091695843 | AO24: =+AO23/AO16 -> -0.059086165 | AP24: =+AP23/AP16 -> -0.074661605 | ... CK24: =+CK23/CK16 -> 0.12631477 | CL24: s | CM24: =+CM23/CM16 -> 0.12081172 | CN24: =+CN23/CN16 -> 0.12011236 | CO24: =+CO23/CO16 -> 0.12430084 | CP24: =+CP23/CP16 -> 0.13586743 | CQ24: =+CQ23/CQ16 -> 0.12308205 | CR24: =+CR23/CR16 -> 0.12286126 | CS24: =+CS23/CS16 -> 0.128129 | CT24: =+CT23/CT16 -> 0.14167907 | ... DB24: =+DB23/DB16 -> 0.14074137 | DF24: 0.071607857
A27: Presentation Data (End)
A28: Profit & Loss- Annual (Start)
A29: Gross Revenue | B29: ='Annual Raw'!C6 -> 0 | C29: ='Annual Raw'!D6 -> 0 | D29: ='Annual Raw'!E6 -> 0 | E29: 15018.59 | F29: 19940.72 | G29: 22912.09 | H29: 30710.67 | I29: 31933.41 | J29: 27426.12 | K29: 37134.35 | L29: 50611.05 | M29: 57401.682 | N29: 47412.782 | O29: 35981.23 | P29: 37656.599 | Q29: 47383.61 | R29: 49054.49 | S29: 58689.81 | T29: 69202.76 | U29: 43928.17 | V29: 47031.47 | W29: 46880.97 | X29: 65298.84 | Y29: 72746 | Z29: 68869 | AA29: 68869 | AB29: =+SUM(CM29:CP29) -> 87366.164 | AC29: =+SUM(CQ29:CT29) -> 94717.369 | AD29: =+SUM(CU29:CX29) -> 105678.3 | AE29: =+SUM(CY29:DB29) -> 118074.81 | AI29: 11581.7 | AJ29: 13714.36 | AK29: 11584.57 | AL29: 12046.42 | AM29: 10013.05 | AN29: 9657.43 | AO29: 8458.27 | AP29: 9248.11 | AQ29: 8256.46 | AR29: 9377.22 | AS29: 9681.92 | AT29: 11804.5 | AU29: 10262.76 | AV29: 11601 | AW29: 10892.22 | AX29: 14147.98 | AY29: 11434.91 | AZ29: 11365.86 | BA29: 11207.2 | BB29: 15080.56 | BC29: 10366.19 | BD29: 13310.37 | BE29: 15962.39 | BF29: 19173.46 | BG29: 16674.99 | BH29: 17758.69 | BI29: 16207.67 | BJ29: 18561.41 | BK29: 13351.91 | BL29: 10000.48 | BM29: 10842.91 | BN29: 9732.87 | BO29: 2686.87 | BP29: 9668.1 | BQ29: 14630.6 | BR29: 20045.9 | BS29: 11904.19 | BT29: 10996.02 | BU29: 12352.78 | BV29: 17338.27 | BW29: 14874.44 | BX29: 14946.78 | BY29: 15793.98 | BZ29: 20142.13 | CA29: 15832.57 | CB29: 18541.7 | CC29: 18668.56 | CD29: 20260.24 | CE29: 16862 | CF29: 15518 | CG29: 17040 | CH29: 19999 | CI29: 15682 | CJ29: ='QTR Raw'!BD6+'QTR Raw'!BD8 -> 16861 | CK29: ='QTR Raw'!BE6+'QTR Raw'!BE8 -> 20404 | CL29: ='QTR Raw'!BF6+'QTR Raw'!BF8 -> 24452 | CM29: =+CM12*CM16/10^7 -> 17459.214 | CN29: =+CN12*CN16/10^7 -> 19330.757 | CO29: =+CO12*CO16/10^7 -> 23430.964 | CP29: =+CP12*CP16/10^7 -> 27145.229 | CQ29: =+CQ12*CQ16/10^7 -> 19131.317 | CR29: =+CR12*CR16/10^7 -> 21132.898 | CS29: =+CS12*CS16/10^7 -> 25412.283 | CT29: =+CT12*CT16/10^7 -> 29040.871 | ... DB29: =+DB12*DB16/10^7 -> 36417.133 | DF29: 24297.637
A30: Other operating income | E30: 103.88 | F30: 105.68 | G30: 132.04 | H30: 208.27 | I30: 208.91 | J30: 255.96 | K30: 219.27 | L30: 233.04 | M30: 301.16 | N30: 392.68 | O30: 381.14 | P30: 404.24 | Q30: 421.82 | R30: 581.9 | S30: 455.48 | T30: 437.88 | U30: 442.41 | V30: 472.08 | W30: 382.71 | X30: 458.49 | Y30: 557 | Z30: 550 | AA30: 550 | AI30: 75.77 | AJ30: 84.97 | AK30: 101.43 | AL30: 130.51 | AM30: 68.89 | AN30: 107.35 | AO30: 98.27 | AP30: 106.63 | AQ30: 91.87 | AR30: 94.23 | AS30: 112.51 | AT30: 108.09 | AU30: 137.59 | AV30: 192.9 | AW30: 163.05 | AX30: 0 | AY30: 0 | AZ30: 0 | BA30: 0 | BB30: 0 | BC30: 0 | BD30: 0 | BE30: 0 | BF30: 0 | BG30: 0 | BH30: 0 | BI30: 0 | BJ30: 0 | BK30: 0 | BL30: 0 | BM30: 0 | BN30: 0 | BO30: 0 | BP30: 0 | BQ30: 0 | BR30: 0 | BS30: 0 | BT30: 0 | BU30: 0 | BV30: 0 | BW30: 0 | BX30: 0 | BY30: 0 | BZ30: 0 | CA30: 0 | CB30: 0 | CC30: 0 | CD30: 0 | CE30: 0 | CF30: 0 | CG30: 0 | CH30: 0 | CI30: 0 | CJ30: 0 | CK30: 0 | CL30: 0
A31: Less: Exise Duty | B31: ='Annual Raw'!C7+'Annual Raw'!C8+'Annual Raw'!C9 -> 0 | C31: ='Annual Raw'!D7+'Annual Raw'!D8+'Annual Raw'!D9 -> 0 | D31: ='Annual Raw'!E7+'Annual Raw'!E8+'Annual Raw'!E9 -> 0 | E31: ='Annual Raw'!F7+'Annual Raw'!F8+'Annual Raw'!F9 -> 0 | F31: ='Annual Raw'!G7+'Annual Raw'!G8+'Annual Raw'!G9 -> 0 | G31: ='Annual Raw'!H7+'Annual Raw'!H8+'Annual Raw'!H9 -> 0 | H31: ='Annual Raw'!I7+'Annual Raw'!I8+'Annual Raw'!I9 -> 0 | I31: ='Annual Raw'!J7+'Annual Raw'!J8+'Annual Raw'!J9 -> 0 | ... AA31: ='Annual Raw'!AB7+'Annual Raw'!AB8+'Annual Raw'!AB9 -> 0 | AI31: 1071.06 | AJ31: 1317.99 | AK31: 1055.91 | AL31: 1109.14 | AM31: 977.44 | AN31: 896.33 | AO31: 786.87 | AP31: 809.25 | AQ31: 643.57 | AR31: 719.37 | AS31: 738.35 | AT31: 1128.31 | AU31: 1076.15 | AV31: 1100.21 | AW31: 1013.48 | AX31: 1348.3 | AY31: 1145.19 | AZ31: 1083.69 | BA31: 1001.78 | BB31: 1506.42 | BC31: 1278.37 | BD31: -487.7 | BE31: 0 | BF31: 0 | BG31: 0 | BH31: 0 | BI31: 0 | BJ31: 0 | BK31: 0 | BL31: 0 | BM31: 0 | BN31: 0 | BO31: 0 | BP31: 0 | BQ31: 0 | BR31: 0 | BS31: 0 | BT31: 0 | BU31: 0 | BV31: 0 | BW31: 0 | BX31: 0 | BY31: 0 | BZ31: 0 | CA31: 0 | CB31: 0 | CC31: 0 | CD31: 0 | CE31: 0 | CF31: 0 | CG31: 0 | CH31: 0 | CI31: 0 | CJ31: ='QTR Raw'!BD21+'QTR Raw'!BD20+'QTR Raw'!BD19+'QTR Raw'!BD13+'QTR Raw'!BD7 -> -287 | CK31: ='QTR Raw'!BE21+'QTR Raw'!BE20+'QTR Raw'!BE19+'QTR Raw'!BE13+'QTR Raw'!BE7 -> -227 | CL31: ='QTR Raw'!BF21+'QTR Raw'!BF20+'QTR Raw'!BF19+'QTR Raw'!BF13+'QTR Raw'!BF7 -> -264
A32: Net Revenue | B32: =+B29-B31 -> 0 | C32: =+C29-C31 -> 0 | D32: =+D29-D31 -> 0 | E32: =+E29-E31+E30 -> 15122.47 | F32: =+F29-F31+F30 -> 20046.4 | G32: =+G29-G31+G30 -> 23044.13 | H32: =+H29-H31+H30 -> 30918.94 | I32: =+I29-I31+I30 -> 32142.32 | J32: =+J29-J31+J30 -> 27682.08 | K32: =+K29-K31+K30 -> 37353.62 | L32: =+L29-L31+L30 -> 50844.09 | ... AE32: =+AE29-AE31+AE30 -> 118074.81 | AI32: =+AI29-AI31+AI30 -> 10586.41 | AJ32: =+AJ29-AJ31+AJ30 -> 12481.34 | AK32: =+AK29-AK31+AK30 -> 10630.09 | AL32: =+AL29-AL31+AL30 -> 11067.79 | AM32: =+AM29-AM31+AM30 -> 9104.5 | AN32: =+AN29-AN31+AN30 -> 8868.45 | AO32: =+AO29-AO31+AO30 -> 7769.67 | AP32: =+AP29-AP31+AP30 -> 8545.49 | ... CL32: =+CL29-CL31+CL30 -> 24716 | CM32: =+CM29-CM31 -> 17459.214 | CN32: =+CN29-CN31 -> 19330.757 | CO32: =+CO29-CO31 -> 23430.964 | CP32: =+CP29-CP31 -> 27145.229 | CQ32: =+CQ29-CQ31 -> 19131.317 | CR32: =+CR29-CR31 -> 21132.898 | CS32: =+CS29-CS31 -> 25412.283 | CT32: =+CT29-CT31 -> 29040.871 | ... DB32: =+DB29-DB31 -> 36417.133 | DF32: 24297.637
A33: Net Revenue YOY% | C33: =C32/B32-1 -> #DIV/0! | D33: =D32/C32-1 -> #DIV/0! | F33: =F32/E32-1 -> 0.32560356 | G33: =G32/F32-1 -> 0.14953957 | H33: =H32/G32-1 -> 0.34172737 | I33: =I32/H32-1 -> 0.039567333 | J33: =J32/I32-1 -> -0.13876534 | K33: =K32/J32-1 -> 0.34937909 | L33: =L32/K32-1 -> 0.36115563 | M33: =M32/L32-1 -> 0.13489772 | ... AE33: =AE32/AD32-1 -> 0.1173042 | AM33: =+AM32/AI32-1 -> -0.1399823 | AN33: =+AN32/AJ32-1 -> -0.28946331 | AO33: =+AO32/AK32-1 -> -0.26908709 | AP33: =+AP32/AL32-1 -> -0.22789554 | AQ33: =+AQ32/AM32-1 -> -0.15374156 | AR33: =+AR32/AN32-1 -> -0.013121797 | AS33: =+AS32/AO32-1 -> 0.16556816 | AT33: =+AT32/AP32-1 -> 0.26198498 | ... CI33: =+CI32/CE32-1 -> -0.069979836 | CJ33: =+IF(CF32<0,1-CJ32/CF32,CJ32/CF32-1) -> 0.10503931 | CK33: =+IF(CG32<0,1-CK32/CG32,CK32/CG32-1) -> 0.21073944 | CL33: =+IF(CH32<0,1-CL32/CH32,CL32/CH32-1) -> 0.23586179 | CM33: =+AVERAGE(CI33:CL33) -> 0.12041518 | CN33: =+AVERAGE(CJ33:CM33) -> 0.16801393 | CO33: =+AVERAGE(CK33:CN33) -> 0.18375758 | CP33: =+AVERAGE(CL33:CO33) -> 0.17701212 | CQ33: =+AVERAGE(CM33:CP33) -> 0.1622997 | CR33: =+AVERAGE(CN33:CQ33) -> 0.17277083 | CS33: =+AVERAGE(CO33:CR33) -> 0.17396006 | CT33: =+AVERAGE(CP33:CS33) -> 0.17151068 | ... DB33: =+AVERAGE(CX33:DA33) -> 0.17153161 | DF33: 0.058226172
A34: Net Revenue QOQ% | AJ34: =+AJ32/AI32-1 -> 0.17899647 | AK34: =+AK32/AJ32-1 -> -0.14832141 | AL34: =+AL32/AK32-1 -> 0.041175569 | AM34: =+AM32/AL32-1 -> -0.17738772 | AN34: =+AN32/AM32-1 -> -0.02592674 | AO34: =+AO32/AN32-1 -> -0.12389764 | AP34: =+AP32/AO32-1 -> 0.099852375 | AQ34: =+AQ32/AP32-1 -> -0.09838289 | ... CI34: =+CI32/CH32-1 -> -0.21586079 | CJ34: =+IF(CI32<0,1-CJ32/CI32,CJ32/CI32-1) -> 0.093482974 | CK34: =+IF(CJ32<0,1-CK32/CJ32,CK32/CJ32-1) -> 0.20311407 | CL34: =+IF(CK32<0,1-CL32/CK32,CL32/CK32-1) -> 0.19800301 | CM34: =+CM32/CL32-1 -> -0.29360681 | CN34: =+CN32/CM32-1 -> 0.10719512 | CO34: =+CO32/CN32-1 -> 0.21210794 | CP34: =+CP32/CO32-1 -> 0.15851953 | CQ34: =+CQ32/CP32-1 -> -0.29522358 | CR34: =+CR32/CQ32-1 -> 0.10462326 | CS34: =+CS32/CR32-1 -> 0.2024987 | CT34: =+CT32/CS32-1 -> 0.14278875 | ... DB34: =+DB32/DA32-1 -> 0.14666639 | DF34: 0.17772462
A35: Increase/Decrease in Stock | B35: ='Annual Raw'!C11 -> 0 | C35: ='Annual Raw'!D11 -> 0 | D35: ='Annual Raw'!E11 -> 0 | E35: 141.98 | F35: -144 | G35: -256.91 | H35: -349.68 | I35: 40.48 | J35: 238.04 | K35: -606.63 | L35: -354.22 | M35: -623.84 | N35: -143.6 | O35: 371.72 | P35: -878.82 | Q35: 10.05 | R35: -252.14 | S35: 842.05 | T35: 144.69 | U35: 722.68 | V35: -69.02 | W35: -403.87 | X35: 484.69 | Y35: -600 | Z35: 284 | AA35: 284 | AB35: =+SUM(CM35:CP35) -> 0 | AC35: =+SUM(CQ35:CT35) -> 0 | AD35: =+SUM(CU35:CX35) -> 0 | AE35: =+SUM(CY35:DB35) -> 0 | AI35: -982.01 | AJ35: 89.36 | AK35: 348.41 | AL35: 400.64 | AM35: -426.13 | AN35: 44.92 | AO35: 415.82 | AP35: 337.11 | AQ35: -541.8 | AR35: -128.28 | AS35: -31.57 | AT35: -177.17 | AU35: -418.81 | AV35: 37.43 | AW35: 408.97 | AX35: -17.54 | AY35: -836.16 | AZ35: -105.23 | BA35: -99.14 | BB35: 789.89 | BC35: -482.6 | BD35: 663.73 | BE35: 153.73 | BF35: 507.19 | BG35: -1090.68 | BH35: -119.6 | BI35: -149.62 | BJ35: 1504.59 | BK35: -1458.96 | BL35: 644.83 | BM35: 1063.21 | BN35: 473.6 | BO35: 309.56 | BP35: -174.86 | BQ35: -591.5 | BR35: 387.78 | BS35: -1401.54 | BT35: -26.29 | BU35: -188.35 | BV35: 870.43 | BW35: -919.23 | BX35: 349.83 | BY35: -65.26 | BZ35: 1119.34 | CA35: -1395.71 | CB35: -9.06 | CC35: -861.33 | CD35: 1665.66 | CE35: -601 | CF35: 222 | CG35: 229 | CH35: 555 | CI35: -1175 | CJ35: ='QTR Raw'!BD10 -> 263 | CK35: ='QTR Raw'!BE10 -> 317 | CL35: ='QTR Raw'!BF10 -> 164 | DF35: -431
A36: Purchase of Finished Goods | B36: 0 | C36: 0 | D36: 0 | E36: 467.98 | F36: 665.12 | G36: 998.74 | H36: 1459.2 | I36: 1598.11 | J36: 2180.32 | K36: 4513.23 | L36: 7363.13 | M36: 0 | N36: 0 | O36: 5049.82 | P36: 5765.24 | Q36: 4101.97 | R36: 3945.97 | S36: 4762.41 | T36: 6722.32 | U36: 5679.98 | V36: 5490.67 | W36: 5030 | X36: 6561.32 | Y36: 7764 | Z36: 7367 | AA36: 7367 | AB36: =+SUM(CM36:CP36) -> 0 | AC36: =+SUM(CQ36:CT36) -> 0 | AD36: =+SUM(CU36:CX36) -> 0 | AE36: =+SUM(CY36:DB36) -> 0 | AI36: 8414.81 | AJ36: 9185.54 | AK36: 7658.93 | AL36: 7849.45 | AM36: 7036.58 | AN36: 6538.6 | AO36: 5547.01 | AP36: 6420.5 | AQ36: 6243.26 | AR36: 6772.3 | AS36: 7022.76 | AT36: 7882.15 | AU36: 6781.98 | AV36: 7314.29 | AW36: 6630.5 | AX36: 8372.6 | AY36: 7722.68 | AZ36: 7527.7 | BA36: 7578.25 | BB36: 8771.3 | BC36: 6901.31 | BD36: 9645.37 | BE36: 11629.71 | BF36: 13666.47 | BG36: 13166.95 | BH36: 13029.6 | BI36: 11970.03 | BJ36: 12304.51 | BK36: 11052.99 | BL36: 6834.85 | BM36: 6978.51 | BN36: 6985.48 | BO36: 1630.44 | BP36: 7425.18 | BQ36: 11471.09 | BR36: 14974.57 | BS36: 10536.15 | BT36: 8439.31 | BU36: 9842.37 | BV36: 12642.26 | BW36: 12181.8 | BX36: 11187.41 | BY36: 11698.98 | BZ36: 13719.94 | CA36: 12832.74 | CB36: 13333.45 | CC36: 13950.07 | CD36: 12672.93 | CE36: 12157 | CF36: 10307 | CG36: 11489 | CH36: 13158 | CI36: =(99330+17630)/10 -> 11696 | CJ36: ='QTR Raw'!BD12 -> 1744 | CK36: ='QTR Raw'!BE12 -> 1954 | CL36: ='QTR Raw'!BF12 -> 2488 | DF36: 17882
A37: Raw Material Consumed | B37: ='Annual Raw'!C12 -> 0 | C37: ='Annual Raw'!D12 -> 0 | D37: ='Annual Raw'!E12 -> 0 | E37: 7873.41 | F37: 11264.36 | G37: 13265.12 | H37: 17915.73 | I37: 18592.08 | J37: 16187.68 | K37: 20392.6 | L37: 27058.47 | M37: 40328.77 | N37: 33108.73 | O37: 20492.87 | P37: 22155.23 | Q37: 24997.4 | R37: 27651.65 | S37: 37080.45 | T37: 43748.77 | U37: 26171.85 | V37: 30010.61 | W37: 31693.11 | X37: 42226.81 | Y37: 45025 | Z37: 39865 | AA37: 39865 | AB37: =+SUM(CM37:CP37) -> 59914.564 | AC37: =+SUM(CQ37:CT37) -> 64989.366 | AD37: =+SUM(CU37:CX37) -> 72516.398 | AE37: =+SUM(CY37:DB37) -> 81023.803 | AI37: =('QTR Raw'!C11)/10 -> 0 | AJ37: =('QTR Raw'!D11)/10 -> 0 | AK37: =('QTR Raw'!E11)/10 -> 0 | AL37: =('QTR Raw'!F11)/10 -> 0 | AM37: =('QTR Raw'!G11)/10 -> 0 | AN37: =('QTR Raw'!H11)/10 -> 0 | AO37: =('QTR Raw'!I11)/10 -> 0 | AP37: =('QTR Raw'!J11)/10 -> 0 | ... CE37: =('QTR Raw'!AY11)/10 -> 0 | CF37: 0 | CG37: =('QTR Raw'!BA11)/10 -> 974.1 | CH37: =('QTR Raw'!BB11)/10 -> 1110.4 | CI37: =('QTR Raw'!BC11)/10 -> 0 | CJ37: ='QTR Raw'!BD11 -> 9625 | CK37: ='QTR Raw'!BE11 -> 12000 | CL37: ='QTR Raw'!BF11 -> 14398 | CM37: =+CM32-CM38 -> 11919.357 | CN37: =+CN32-CN38 -> 13254.083 | CO37: =+CO32-CO38 -> 16108.244 | CP37: =+CP32-CP38 -> 18632.879 | CQ37: =+CQ32-CQ38 -> 13115.647 | CR37: =+CR32-CR38 -> 14502.968 | CS37: =+CS32-CS38 -> 17443.783 | CT37: =+CT32-CT38 -> 19926.968 | ... DB37: =+DB32-DB38 -> 24989.58 | DF37: 16562.707
A38: Gross Profit | B38: =B32-B35-B37-B36 -> 0 | C38: =C32-C35-C37-C36 -> 0 | D38: =D32-D35-D37-D36 -> 0 | E38: =E32-E35-E37-E36 -> 6639.1 | F38: =F32-F35-F37-F36 -> 8260.92 | G38: =G32-G35-G37-G36 -> 9037.18 | H38: =H32-H35-H37-H36 -> 11893.69 | I38: =I32-I35-I37-I36 -> 11911.65 | ... AE38: =AE32-AE35-AE37-AE36 -> 37051.005 | AH38: 10 | AI38: =AI32-AI35-AI37-AI36 -> 3153.61 | AJ38: =AJ32-AJ35-AJ37-AJ36 -> 3206.44 | AK38: =AK32-AK35-AK37-AK36 -> 2622.75 | AL38: =AL32-AL35-AL37-AL36 -> 2817.7 | AM38: =AM32-AM35-AM37-AM36 -> 2494.05 | AN38: =AN32-AN35-AN37-AN36 -> 2284.93 | AO38: =AO32-AO35-AO37-AO36 -> 1806.84 | AP38: =AP32-AP35-AP37-AP36 -> 1787.88 | ... CL38: =CL32-CL35-CL37-CL36 -> 7666 | CM38: =+CM39*CM32 -> 5539.8567 | CN38: =+CN39*CN32 -> 6076.6733 | CO38: =+CO39*CO32 -> 7322.7195 | CP38: =+CP39*CP32 -> 8512.3501 | CQ38: =+CQ39*CQ32 -> 6015.6707 | CR38: =+CR39*CR32 -> 6629.9305 | CS38: =+CS39*CS32 -> 7968.4993 | CT38: =+CT39*CT32 -> 9113.9029 | ... DB38: =+DB39*DB32 -> 11427.553 | DF38: 7734.9295
A39: GP% | B39: =B38/B32 -> #DIV/0! | C39: =C38/C32 -> #DIV/0! | D39: =D38/D32 -> #DIV/0! | E39: =E38/E32 -> 0.4390222 | F39: =F38/F32 -> 0.41208995 | G39: =G38/G32 -> 0.39216842 | H39: =H38/H32 -> 0.38467328 | I39: =I38/I32 -> 0.37059086 | ... AE39: =AE38/AE32 -> 0.31379263 | AI39: =AI38/AI32 -> 0.2978923 | AJ39: =AJ38/AJ32 -> 0.2568987 | AK39: =AK38/AK32 -> 0.24672886 | AL39: =AL38/AL32 -> 0.2545856 | AM39: =AM38/AM32 -> 0.27393597 | AN39: =AN38/AN32 -> 0.25764705 | AO39: =AO38/AO32 -> 0.23255042 | AP39: =AP38/AP32 -> 0.20921913 | ... CL39: =CL38/CL32 -> 0.31016346 | CM39: =AVERAGE(CI39:CL39) -> 0.31730275 | CN39: =AVERAGE(CJ39:CM39) -> 0.31435258 | CO39: =AVERAGE(CK39:CN39) -> 0.31252319 | CP39: =AVERAGE(CL39:CO39) -> 0.31358549 | CQ39: =AVERAGE(CM39:CP39) -> 0.314441 | CR39: =AVERAGE(CN39:CQ39) -> 0.31372557 | CS39: =AVERAGE(CO39:CR39) -> 0.31356881 | CT39: =AVERAGE(CP39:CS39) -> 0.31383022 | ... DB39: =AVERAGE(CX39:DA39) -> 0.31379606 | DF39: 0.31834082
A40: GP YOY% | C40: =+C38/B38-1 -> #DIV/0! | D40: =+D38/C38-1 -> #DIV/0! | F40: =+F38/E38-1 -> 0.24428311 | G40: =+G38/F38-1 -> 0.093967742 | H40: =+H38/G38-1 -> 0.31608422 | I40: =+I38/H38-1 -> 0.0015100444 | J40: =+J38/I38-1 -> -0.2380535 | K40: =+K38/J38-1 -> 0.43833875 | L40: =+L38/K38-1 -> 0.28513638 | M40: =+M38/L38-1 -> 0.072791484 | ... AE40: =+AE38/AD38-1 -> 0.11727625 | AM40: =+IF(AI38<0,1-AM38/AI38,AM38/AI38-1) -> -0.20914444 | AN40: =+IF(AJ38<0,1-AN38/AJ38,AN38/AJ38-1) -> -0.2873935 | AO40: =+IF(AK38<0,1-AO38/AK38,AO38/AK38-1) -> -0.31108951 | AP40: =+IF(AL38<0,1-AP38/AL38,AP38/AL38-1) -> -0.36548249 | AQ40: =+IF(AM38<0,1-AQ38/AM38,AQ38/AM38-1) -> -0.19676831 | AR40: =+IF(AN38<0,1-AR38/AN38,AR38/AN38-1) -> -0.077407185 | AS40: =+IF(AO38<0,1-AS38/AO38,AS38/AO38-1) -> 0.1428184 | AT40: =+IF(AP38<0,1-AT38/AP38,AT38/AP38-1) -> 0.72231917 | ... CL40: =+IF(CH38<0,1-CL38/CH38,CL38/CH38-1) -> 0.48118093 | CM40: =+CM38/CI38-1 -> 0.073407615 | CN40: =+CN38/CJ38-1 -> 0.10164491 | CO40: =+CO38/CK38-1 -> 0.15137098 | CP40: =+CP38/CL38-1 -> 0.11040309 | CQ40: =+CQ38/CM38-1 -> 0.085889222 | CR40: =+CR38/CN38-1 -> 0.091046064 | CS40: =+CS38/CO38-1 -> 0.088188525 | CT40: =+CT38/CP38-1 -> 0.070668234 | ... DB40: =+DB38/CX38-1 -> 0.1170771 | DF40: 0.23050104
A41: GP QOQ% | AJ41: =+IF(AI38<0,1-AJ38/AI38,AJ38/AI38-1) -> 0.01675223 | AK41: =+IF(AJ38<0,1-AK38/AJ38,AK38/AJ38-1) -> -0.18203678 | AL41: =+IF(AK38<0,1-AL38/AK38,AL38/AK38-1) -> 0.074330378 | AM41: =+IF(AL38<0,1-AM38/AL38,AM38/AL38-1) -> -0.11486319 | AN41: =+IF(AM38<0,1-AN38/AM38,AN38/AM38-1) -> -0.083847557 | AO41: =+IF(AN38<0,1-AO38/AN38,AO38/AN38-1) -> -0.20923617 | AP41: =+IF(AO38<0,1-AP38/AO38,AP38/AO38-1) -> -0.010493458 | AQ41: =+IF(AP38<0,1-AQ38/AP38,AQ38/AP38-1) -> 0.12048907 | ... CL41: =+IF(CK38<0,1-CL38/CK38,CL38/CK38-1) -> 0.20534591 | CM41: =+CM38/CL38-1 -> -0.27734716 | CN41: =+CN38/CM38-1 -> 0.096900809 | CO41: =+CO38/CN38-1 -> 0.205054 | CP41: =+CP38/CO38-1 -> 0.16245749 | CQ41: =+CQ38/CP38-1 -> -0.29330084 | CR41: =+CR38/CQ38-1 -> 0.10210994 | CS41: =+CS38/CR38-1 -> 0.20189786 | CT41: =+CT38/CS38-1 -> 0.14374144 | ... DB41: =+DB38/DA38-1 -> 0.14669194 | DF41: 0.21618389
A42: Power & Fuel Cost | B42: ='Annual Raw'!C13 -> 0 | C42: ='Annual Raw'!D13 -> 0 | D42: ='Annual Raw'!E13 -> 0 | E42: 214.52 | F42: 237.81 | G42: 258.51 | H42: 327.41 | I42: 325.19 | J42: 304.94 | K42: 362.62 | L42: 471.28 | M42: 550.89 | N42: 484.66 | O42: 392.09 | P42: 395.88 | Q42: 402.36 | R42: 483.48 | S42: 545.11 | T42: 598.62 | U42: 428.85 | V42: 371.78 | W42: 344.78 | X42: 420.98 | Y42: 424 | Z42: 419 | AA42: 419 | AB42: =+SUM(CM42:CP42) -> 0 | AC42: =+SUM(CQ42:CT42) -> 0 | AD42: =+SUM(CU42:CX42) -> 0 | AE42: =+SUM(CY42:DB42) -> 0 | DF42: 0
A43: Selling and Distribution Expenses | B43: ='Annual Raw'!C18 -> 0 | C43: ='Annual Raw'!D18 -> 0 | D43: ='Annual Raw'!E18 -> 0 | E43: 455.56 | F43: 598.75 | G43: 759.54 | H43: 1068.56 | I43: 1173.8 | J43: 1224.15 | K43: 1578.14 | L43: 2283.19 | M43: 2913.1746 | N43: 2567.6283 | O43: 2168.6634 | P43: 2521.2651 | Q43: 2674.8469 | R43: 2878.46 | S43: 3189.51 | T43: 3601.22 | U43: 2462.16 | V43: 966.194 | W43: 2064.8 | X43: 2578.25 | Y43: 2999 | Z43: 3686 | AA43: 3686 | AB43: =+SUM(CM43:CP43) -> 0 | AC43: =+SUM(CQ43:CT43) -> 0 | AD43: =+SUM(CU43:CX43) -> 0 | AE43: =+SUM(CY43:DB43) -> 0 | DF43: 0
A44: Other Manufacturing Expenses | B44: ='Annual Raw'!C15+'Annual Raw'!C16 -> 0 | C44: ='Annual Raw'!D15+'Annual Raw'!D16 -> 0 | D44: ='Annual Raw'!E15+'Annual Raw'!E16 -> 0 | E44: 236.73 | F44: 315.8 | G44: 369.16 | H44: 504.63 | I44: 465.4 | J44: 402.43 | K44: 451.91 | L44: 625.45 | M44: 753.02 | N44: 655.67 | O44: 497.9 | P44: 447.36 | Q44: 470.94 | R44: 653.61 | S44: 639.35 | T44: 617.67 | U44: 461.37 | V44: 417.57 | W44: 406.36 | X44: 424.32 | Y44: 494 | Z44: 441 | AA44: 441 | AB44: =+SUM(CM44:CP44) -> 11342.614 | AC44: =+SUM(CQ44:CT44) -> 12045.624 | AD44: =+SUM(CU44:CX44) -> 13491.849 | AE44: =+SUM(CY44:DB44) -> 15346.105 | AI44: 1890.94 | AJ44: 1962.24 | AK44: 1920.43 | AL44: 2000.04 | AM44: 1789.32 | AN44: 1675.88 | AO44: 1685.01 | AP44: 1836.76 | AQ44: 1730.62 | AR44: 1824.08 | AS44: 2031.12 | AT44: 2218.64 | AU44: 1843.68 | AV44: 1965.18 | AW44: 1836.43 | AX44: 2571.36 | AY44: 2081.35 | AZ44: 1887.49 | BA44: 1960.04 | BB44: 2669.67 | BC44: 1924.38 | BD44: 1806.02 | BE44: 2119.06 | BF44: 3387.46 | BG44: 2410.69 | BH44: 2548.51 | BI44: 2134.94 | BJ44: 2586.32 | BK44: 2051.94 | BL44: 1928.47 | BM44: 1890.01 | BN44: 1850.33 | BO44: 661.73 | BP44: 1283.21 | BQ44: 1738.42 | BR44: 2118.54 | BS44: 1495.12 | BT44: 1548.94 | BU44: 1589.72 | BV44: 1832.57 | BW44: 1923.4 | BX44: 1846.41 | BY44: 1842.19 | BZ44: 2207.74 | CA44: 2039.3 | CB44: 2192.86 | CC44: 2355.53 | CD44: 2373.29 | CE44: 2292 | CF44: 2220 | CG44: 2248 | CH44: 2728 | CI44: 2212 | CJ44: ='QTR Raw'!BD14 -> 2279 | CK44: ='QTR Raw'!BE14 -> 2602 | CL44: ='QTR Raw'!BF14 -> 3179 | CM44: =CM50-CM45 -> 2104.3056 | CN44: =CN50-CN45 -> 2386.8657 | CO44: =CO50-CO45 -> 3089.6098 | CP44: =CP50-CP45 -> 3761.8325 | CQ44: =CQ50-CQ45 -> 2214.3683 | CR44: =CR50-CR45 -> 2556.2668 | CS44: =CS50-CS45 -> 3327.613 | CT44: =CT50-CT45 -> 3947.3759 | ... DB44: =DB50-DB45 -> 5069.3911 | DF44: 3553.3759
A45: Employee Cost | B45: ='Annual Raw'!C14 -> 0 | C45: ='Annual Raw'!D14 -> 0 | D45: ='Annual Raw'!E14 -> 0 | E45: 882.49 | F45: 1039.34 | G45: 1143.13 | H45: 1324.83 | I45: 1544.57 | J45: 1551.39 | K45: 1836.13 | L45: 2294.02 | M45: 2691.45 | N45: 2837 | O45: 2877.69 | P45: 3091.46 | Q45: 3188.97 | R45: 3764.35 | S45: 3966.73 | T45: 4273.1 | U45: 4384.31 | V45: 4212.99 | W45: 3601.51 | X45: 4021.63 | Y45: 4308 | Z45: 4513 | AA45: 4513 | AB45: =+SUM(CM45:CP45) -> 4981.92 | AC45: =+SUM(CQ45:CT45) -> 5330.6544 | AD45: =+SUM(CU45:CX45) -> 5703.8002 | AE45: =+SUM(CY45:DB45) -> 6103.0662 | AI45: 706.86 | AJ45: 749.19 | AK45: 731.43 | AL45: 649.52 | AM45: 747.49 | AN45: 696.76 | AO45: 720.43 | AP45: 713.01 | AQ45: 739.5 | AR45: 751 | AS45: 764.71 | AT45: 836.2 | AU45: 808.25 | AV45: 769.49 | AW45: 824.98 | AX45: 785.36 | AY45: 898.94 | AZ45: 881.7 | BA45: 845.35 | BB45: 983.94 | BC45: 937.65 | BD45: 941.97 | BE45: 983.51 | BF45: 1103.6 | BG45: 1032.92 | BH45: 1045.4 | BI45: 1060.11 | BJ45: 1134.67 | BK45: 1149.34 | BL45: 1067.09 | BM45: 1018.27 | BN45: 1149.61 | BO45: 966.74 | BP45: 1058.6 | BQ45: 1105.89 | BR45: 1081.76 | BS45: 1180.41 | BT45: 886.25 | BU45: 918.1 | BV45: 875.6 | BW45: 1062.85 | BX45: 964.43 | BY45: 972.28 | BZ45: 1022.07 | CA45: 1064.47 | CB45: 1085.96 | CC45: 1110.48 | CD45: 1047.27 | CE45: 1151 | CF45: 1141 | CG45: 1111 | CH45: 1110 | CI45: 1164 | CJ45: ='QTR Raw'!BD16 -> 1160 | CK45: ='QTR Raw'!BE16 -> 1152 | CL45: ='QTR Raw'!BF16 -> 1180 | CM45: =CI45*107% -> 1245.48 | CN45: =CJ45*107% -> 1241.2 | CO45: =CK45*107% -> 1232.64 | CP45: =CL45*107% -> 1262.6 | CQ45: =CM45*107% -> 1332.6636 | CR45: =CN45*107% -> 1328.084 | CS45: =CO45*107% -> 1318.9248 | CT45: =CP45*107% -> 1350.982 | ... DB45: =CX45*107% -> 1546.7393 | DF45: 1187.7
A46: General and Administration Expenses | B46: ='Annual Raw'!C17 -> 0 | C46: ='Annual Raw'!D17 -> 0 | D46: ='Annual Raw'!E17 -> 0 | E46: 388.59 | F46: 555.66 | G46: 625.7 | H46: 823.79 | I46: 851.43 | J46: 810.6 | K46: 1212.9 | L46: 1676.07 | M46: 2057.51 | N46: 1743.64 | O46: 1416.7 | P46: 1450.57 | Q46: 1507.21 | R46: 1004.45 | S46: 1240.88 | T46: 1567.89 | U46: 1051.13 | V46: 953.49 | W46: 1039.05 | X46: 1292.71 | Y46: 1610 | Z46: 1229 | AA46: 1229 | AB46: =+SUM(CM44:CP44) -> 11342.614 | AC46: =+SUM(CQ44:CT44) -> 12045.624 | AD46: =+SUM(CU44:CX44) -> 13491.849 | AE46: =+SUM(CY44:DB44) -> 15346.105 | DF46: 0
A47: Product Development Expenditure | E47: 51.64 | F47: 67.12 | G47: 73.78 | H47: 85.02 | I47: 64.35 | J47: 51.17 | K47: 144.03 | L47: 106.17 | M47: 234.25 | N47: 425.76 | O47: 428.74 | P47: 437.47 | Q47: 418.27 | R47: 454.48 | S47: 474.98 | T47: 571.76 | U47: 830.24 | V47: 907.64 | W47: 593.9 | X47: 899.06 | Y47: 1105 | Z47: 1033 | AA47: 1033 | AI47: 74.56 | AJ47: 79.92 | AK47: 88.52 | AL47: 182.7 | AM47: 101.32 | AN47: 96.25 | AO47: 121.24 | AP47: 109.93 | AQ47: 79.6 | AR47: 119.92 | AS47: 97.66 | AT47: 140.29 | AU47: 94.41 | AV47: 97.67 | AW47: 107.38 | AX47: 118.81 | AY47: 116.17 | AZ47: 69.89 | BA47: 76.95 | BB47: 191.47 | BC47: 75.24 | BD47: 111.19 | BE47: 136.65 | BF47: 151.9 | BG47: 105.5 | BH47: 103.12 | BI47: 120.22 | BJ47: 242.92 | BK47: 120.06 | BL47: 345.37 | BM47: 205.8 | BN47: 297.37 | BO47: 138.19 | BP47: 176.25 | BQ47: 237.03 | BR47: 356.13 | BS47: 208.53 | BT47: 116.08 | BU47: 122.83 | BV47: 262.63 | BW47: 177.67 | BX47: 200.19 | BY47: 214.83 | BZ47: 306.37 | CA47: 224.85 | CB47: 222.57 | CC47: 279.55 | CD47: 377.83 | CE47: 225 | CF47: 274 | CG47: 268 | CH47: 266 | CI47: 173
A48: Other Fixed Cost | E48: 825.05 | F48: 968.59 | G48: 1146.67 | H48: 1620.53 | I48: 1960.99 | J48: 1862.82 | K48: 2400.33 | L48: 2669.44 | M48: 2130.9154 | N48: 2322.0517 | O48: 2511.8336 | P48: 3272.2049 | Q48: 3161.2931 | R48: 3315.9 | S48: 3619.42 | T48: 3295.06 | U48: 3317.24 | V48: 3092.876 | W48: 2163.72 | X48: 3103.48 | Y48: 3434 | Z48: 3713 | AA48: 3713
A49: Miscellaneous Expenses (Expenses Capitalised) | B49: ='Annual Raw'!C19-'Annual Raw'!C20 -> 0 | C49: ='Annual Raw'!D19-'Annual Raw'!D20 -> 0 | D49: ='Annual Raw'!E19-'Annual Raw'!E20 -> 0 | E49: -144.89 | F49: -282.43 | G49: -308.85 | H49: -577.05 | I49: -744.23 | J49: -885.08 | K49: -726.46 | L49: -817.68 | M49: -907.13 | N49: -953.8 | O49: -1009.11 | P49: -1118.75 | Q49: -1034.4 | R49: -941.55 | S49: -855.08 | T49: -1093.11 | U49: -1169.46 | V49: -817.63 | W49: -905.42 | X49: -1066.73 | Y49: -1130 | Z49: -1213 | AA49: -1213 | AB49: =+SUM(CM49:CP49) -> 0 | AC49: =+SUM(CQ49:CT49) -> 0 | AD49: =+SUM(CU49:CX49) -> 0 | AE49: =+SUM(CY49:DB49) -> 0 | AI49: -218.56 | AJ49: -238.39 | AK49: -262.89 | AL49: -233.96 | AM49: -249.27 | AN49: -265.28 | AO49: -260.76 | AP49: -233.8 | AQ49: -252.21 | AR49: -324.69 | AS49: -266.99 | AT49: -274.86 | AU49: -256.01 | AV49: -267.58 | AW49: -263.9 | AX49: -246.91 | AY49: -246.77 | AZ49: -245.29 | BA49: -218.06 | BB49: -231.43 | BC49: -209.02 | BD49: -177.77 | BE49: -221.81 | BF49: -246.46 | BG49: -286.4 | BH49: -246.43 | BI49: -237.31 | BJ49: -322.97 | BK49: -301.91 | BL49: -306.44 | BM49: -260.28 | BN49: -300.83 | BO49: -177.7 | BP49: -201.99 | BQ49: -180.02 | BR49: -257.82 | BS49: -203.93 | BT49: -209.66 | BU49: -233.09 | BV49: -261.85 | BW49: -243.87 | BX49: -252.78 | BY49: -235 | BZ49: -313.59 | CA49: -261.41 | CB49: -264.09 | CC49: -299.06 | CD49: -305.17 | CE49: -278 | CF49: -299 | CG49: -320 | CH49: -316 | CI49: -278 | DF49: -278
A50: Total Cost | B50: =+#REF!+#REF! -> #REF! | C50: =+#REF!+#REF! -> #REF! | D50: =+#REF!+#REF! -> #REF! | E50: =+SUM(E42:E49) -> 2909.69 | F50: =+SUM(F42:F49) -> 3500.64 | G50: =+SUM(G42:G49) -> 4067.64 | H50: =+SUM(H42:H49) -> 5177.72 | I50: =+SUM(I42:I49) -> 5641.5 | J50: =+SUM(J42:J49) -> 5322.42 | K50: =+SUM(K42:K49) -> 7259.6 | L50: =+SUM(L42:L49) -> 9307.94 | ... AE50: =+SUM(AE42:AE49) -> 36795.276 | AI50: =+SUM(AI42:AI49) -> 2453.8 | AJ50: =+SUM(AJ42:AJ49) -> 2552.96 | AK50: =+SUM(AK42:AK49) -> 2477.49 | AL50: =+SUM(AL42:AL49) -> 2598.3 | AM50: =+SUM(AM42:AM49) -> 2388.86 | AN50: =+SUM(AN42:AN49) -> 2203.61 | AO50: =+SUM(AO42:AO49) -> 2265.92 | AP50: =+SUM(AP42:AP49) -> 2425.9 | ... CL50: =+SUM(CL42:CL49) -> 4359 | CM50: =CM51*CM32 -> 3349.7856 | CN50: =CN51*CN32 -> 3628.0657 | CO50: =CO51*CO32 -> 4322.2498 | CP50: =CP51*CP32 -> 5024.4325 | CQ50: =CQ51*CQ32 -> 3547.0319 | CR50: =CR51*CR32 -> 3884.3508 | CS50: =CS51*CS32 -> 4646.5378 | CT50: =CT51*CT32 -> 5298.3579 | ... DB50: =DB51*DB32 -> 6616.1304 | DF50: 4741.0759
A51: Cost % | B51: =B50/B32 -> #REF! | C51: =C50/C32 -> #REF! | D51: =D50/D32 -> #REF! | E51: =E50/E32 -> 0.19240838 | F51: =F50/F32 -> 0.17462687 | G51: =G50/G32 -> 0.17651523 | H51: =H50/H32 -> 0.16746111 | I51: =I50/I32 -> 0.17551627 | ... AE51: =AE50/AE32 -> 0.31162682 | AI51: =AI50/AI32 -> 0.23178774 | AJ51: =AJ50/AJ32 -> 0.20454214 | AK51: =AK50/AK32 -> 0.23306388 | AL51: =AL50/AL32 -> 0.23476231 | AM51: =AM50/AM32 -> 0.26238234 | AN51: =AN50/AN32 -> 0.24847747 | AO51: =AO50/AO32 -> 0.29163658 | AP51: =AP50/AP32 -> 0.28388074 | ... CL51: =CL50/CL32 -> 0.17636349 | CM51: =AVERAGE(CI51:CL51) -> 0.19186348 | CN51: =AVERAGE(CJ51:CM51) -> 0.18768358 | CO51: =AVERAGE(CK51:CN51) -> 0.18446744 | CP51: =AVERAGE(CL51:CO51) -> 0.1850945 | CQ51: =AVERAGE(CM51:CP51)*0.99 -> 0.18540448 | CR51: =AVERAGE(CN51:CQ51)*0.99 -> 0.18380587 | CS51: =AVERAGE(CO51:CR51)*0.99 -> 0.18284614 | CT51: =AVERAGE(CP51:CS51)*0.99 -> 0.18244487 | CU51: =AVERAGE(CQ51:CT51)*0.99 -> 0.18178909 | CV51: =AVERAGE(CR51:CU51)*0.99 -> 0.18089428 | CW51: =AVERAGE(CS51:CV51) -> 0.18199359 | CX51: =AVERAGE(CT51:CW51) -> 0.18178046 | CY51: =AVERAGE(CU51:CX51) -> 0.18161435 | CZ51: =AVERAGE(CV51:CY51) -> 0.18157067 | DA51: =AVERAGE(CW51:CZ51) -> 0.18173977 | DB51: =AVERAGE(CX51:DA51) -> 0.18167631 | DF51: 0.19512498
A52: EBITDA | B52: =B38-B50 -> #REF! | C52: =C38-C50 -> #REF! | D52: =D38-D50 -> #REF! | E52: =E38-E50 -> 3729.41 | F52: =F38-F50 -> 4760.28 | G52: =G38-G50 -> 4969.54 | H52: =H38-H50 -> 6715.97 | I52: =I38-I50 -> 6270.15 | ... AE52: =AE38-AE50 -> 255.72857 | AI52: =AI38-AI50 -> 699.81 | AJ52: =AJ38-AJ50 -> 653.48 | AK52: =AK38-AK50 -> 145.26 | AL52: =AL38-AL50 -> 219.4 | AM52: =AM38-AM50 -> 105.19 | AN52: =AN38-AN50 -> 81.32 | AO52: =AO38-AO50 -> -459.08 | AP52: =AP38-AP50 -> -638.02 | ... DB52: =DB38-DB50 -> 4811.4223 | DF52: 2993.8537
A53: EBITDA Margins | B53: =B52/B32 -> #REF! | C53: =C52/C32 -> #REF! | D53: =D52/D32 -> #REF! | E53: =E52/E32 -> 0.24661381 | F53: =F52/F32 -> 0.23746309 | G53: =G52/G32 -> 0.21565318 | H53: =H52/H32 -> 0.21721217 | I53: =I52/I32 -> 0.19507459 | ... AE53: =AE52/AE32 -> 0.0021658182 | AI53: =AI52/AI32 -> 0.066104562 | AJ53: =AJ52/AJ32 -> 0.052356558 | AK53: =AK52/AK32 -> 0.013664983 | AL53: =AL52/AL32 -> 0.019823289 | AM53: =AM52/AM32 -> 0.011553627 | AN53: =AN52/AN32 -> 0.0091695843 | AO53: =AO52/AO32 -> -0.059086165 | AP53: =AP52/AP32 -> -0.074661605 | ... DB53: =DB52/DB32 -> 0.13211974 | DF53: 0.12321584
A54: EBITDA YOY% | C54: =+C52/B52-1 -> #REF! | D54: =+D52/C52-1 -> #REF! | F54: =+F52/E52-1 -> 0.27641638 | G54: =+G52/F52-1 -> 0.043959599 | H54: =+H52/G52-1 -> 0.35142689 | I54: =+I52/H52-1 -> -0.066382071 | J54: =+J52/I52-1 -> -0.40135084 | K54: =+K52/J52-1 -> 0.54379506 | L54: =+L52/K52-1 -> 0.28887006 | M54: =+M52/L52-1 -> 0.01406679 | ... AE54: =+AE52/AD52-1 -> -0.46094689 | AM54: =+IF(AI52<0,1-AM52/AI52,AM52/AI52-1) -> -0.84968777 | AN54: =+IF(AJ52<0,1-AN52/AJ52,AN52/AJ52-1) -> -0.87555855 | AO54: =+IF(AK52<0,1-AO52/AK52,AO52/AK52-1) -> -4.160402 | AP54: =+IF(AL52<0,1-AP52/AL52,AP52/AL52-1) -> -3.9080219 | AQ54: =+IF(AM52<0,1-AQ52/AM52,AQ52/AM52-1) -> -3.7969389 | AR54: =+IF(AN52<0,1-AR52/AN52,AR52/AN52-1) -> -4.2249139 | AS54: =+IF(AO52<0,1-AS52/AO52,AS52/AO52-1) -> -0.22333798 | AT54: =+IF(AP52<0,1-AT52/AP52,AT52/AP52-1) -> 1.2492555 | ... CL54: =+IF(CH52<0,1-CL52/CH52,CL52/CH52-1) -> 1.3832517 | CM54: =+CM52/CI52-1 -> 0.15876775 | CN54: =+CN52/CJ52-1 -> 0.17891557 | CO54: =+CO52/CK52-1 -> 0.15136979 | CP54: =+CP52/CL52-1 -> 0.054707455 | CQ54: =+CQ52/CM52-1 -> 0.12719574 | CR54: =+CR52/CN52-1 -> 0.121282 | CS54: =+CS52/CO52-1 -> 0.10714717 | CT54: =+CT52/CP52-1 -> 0.0939321 | ... DB54: =+DB52/CX52-1 -> 0.11789395 | DF54: 0.19850027
A55: EBITDA QOQ% | AJ55: =+IF(AI52<0,1-AJ52/AI52,AJ52/AI52-1) -> -0.066203684 | AK55: =+IF(AJ52<0,1-AK52/AJ52,AK52/AJ52-1) -> -0.77771317 | AL55: =+IF(AK52<0,1-AL52/AK52,AL52/AK52-1) -> 0.51039515 | AM55: =+IF(AL52<0,1-AM52/AL52,AM52/AL52-1) -> -0.52055606 | AN55: =+IF(AM52<0,1-AN52/AM52,AN52/AM52-1) -> -0.22692271 | AO55: =+IF(AN52<0,1-AO52/AN52,AO52/AN52-1) -> -6.6453517 | AP55: =+IF(AO52<0,1-AP52/AO52,AP52/AO52-1) -> -0.38977956 | AQ55: =+IF(AP52<0,1-AQ52/AP52,AQ52/AP52-1) -> 0.53887025 | ... CL55: =+IF(CK52<0,1-CL52/CK52,CL52/CK52-1) -> 0.26899463 | CM55: =+CM52/CL52-1 -> -0.33774688 | CN55: =+CN52/CM52-1 -> 0.1180494 | CO55: =+CO52/CN52-1 -> 0.22537789 | CP55: =+CP52/CO52-1 -> 0.1624572 | CQ55: =+CQ52/CP52-1 -> -0.29223133 | CR55: =+CR52/CQ52-1 -> 0.11218365 | CS55: =+CS52/CR52-1 -> 0.20993084 | CT55: =+CT52/CS52-1 -> 0.14858194 | ... DB55: =+DB52/DA52-1 -> 0.14727812 | DF55: 0.14883103
A56: Depreciation | B56: ='Annual Raw'!C27 -> 0 | C56: ='Annual Raw'!D27 -> 0 | D56: ='Annual Raw'!E27 -> 0 | E56: 382.6 | F56: 450.16 | G56: 520.94 | H56: 586.29 | I56: 652.31 | J56: 874.54 | K56: 1033.87 | L56: 1360.77 | M56: 1606.74 | N56: 1817.62 | O56: 2070.3 | P56: 2603.22 | Q56: 2329.22 | R56: 3037.12 | S56: 3101.89 | T56: 3098.64 | U56: 3375.29 | V56: 3681.61 | W56: 1760.57 | X56: 1766.86 | Y56: 2017 | Z56: 2008 | AA56: 2008 | AB56: =+SUM(CM56:CP56) -> 1899.193 | AC56: =+SUM(CQ56:CT56) -> 1902.083 | AD56: =+SUM(CU56:CX56) -> 1904.5717 | AE56: =+SUM(CY56:DB56) -> 1906.7146 | AI56: 429.36 | AJ56: 447.15 | AK56: 482.38 | AL56: 458.73 | AM56: 499.78 | AN56: 519.05 | AO56: 512.18 | AP56: 539.29 | AQ56: 540.82 | AR56: 613.47 | AS56: 625.6 | AT56: 823.33 | AU56: 580.3 | AV56: 591.96 | AW56: 590.98 | AX56: 565.98 | AY56: 712.24 | AZ56: 718.57 | BA56: 728.96 | BB56: 819.25 | BC56: 689.83 | BD56: 767.39 | BE56: 788.5 | BF56: 856.17 | BG56: 705.15 | BH56: 754.05 | BI56: 766.83 | BJ56: 872.61 | BK56: 777.05 | BL56: 760.65 | BM56: 853.46 | BN56: 984.13 | BO56: 859.89 | BP56: 909.92 | BQ56: 947.64 | BR56: 964.16 | BS56: 959.39 | BT56: 432.68 | BU56: 452.15 | BV56: 457.86 | BW56: 422.98 | BX56: 446.13 | BY56: 430.18 | BZ56: 467.57 | CA56: 495.91 | CB56: 509 | CC56: 513.13 | CD56: 498.8 | CE56: 477 | CF56: 484 | CG56: 497 | CH56: 542 | CI56: 423 | CJ56: ='QTR Raw'!BD28 -> 412 | CK56: ='QTR Raw'!BE28 -> 417 | CL56: ='QTR Raw'!BF28 -> 449 | CM56: =CM57*CL165 -> 474.50302 | CN56: =CN57*CM165 -> 474.70474 | CO56: =CO57*CN165 -> 474.89905 | CP56: =CP57*CO165 -> 475.08622 | CQ56: =CQ57*CP165 -> 475.26654 | CR56: =CR57*CQ165 -> 475.44023 | CS56: =CS57*CR165 -> 475.60755 | CT56: =CT57*CS165 -> 475.76873 | ... DB56: =DB57*DA165 -> 476.86252 | DF56: 403.25709
A57: Depreciation % of Net Block | E57: =+E56/E165 -> 0.12918213 | F57: =+F56/F165 -> 0.14256081 | G57: =+G56/G165 -> 0.14591993 | H57: =+H56/H165 -> 0.15105662 | I57: =+I56/I165 -> 0.12108269 | J57: =+J56/J165 -> 0.11438968 | K57: =+K56/K165 -> 0.092277771 | L57: =+L56/L165 -> 0.10314818 | ... AA57: =+AA56/AA165 -> 0.14226001 | AI57: =+AI56/AH165 -> #DIV/0! | AJ57: =+AJ56/AI165 -> #DIV/0! | AK57: =+AK56/AJ165 -> #DIV/0! | AL57: =+AL56/AK165 -> #DIV/0! | AM57: =+AM56/AL165 -> #DIV/0! | AN57: =+AN56/AM165 -> #DIV/0! | AO57: =+AO56/AN165 -> #DIV/0! | AP57: =+AP56/AO165 -> #DIV/0! | ... CL57: =+CL56/CK165 -> 0.036694998 | CM57: =CL57 -> 0.036694998 | CN57: =CM57 -> 0.036694998 | CO57: =CN57 -> 0.036694998 | CP57: =CO57 -> 0.036694998 | CQ57: =CP57 -> 0.036694998 | CR57: =CQ57 -> 0.036694998 | CS57: =CR57 -> 0.036694998 | CT57: =CS57 -> 0.036694998 | ... DB57: =DA57 -> 0.036694998 | DF57: 0.032956611
A58: EBIT | B58: =B52-B56 -> #REF! | C58: =C52-C56 -> #REF! | D58: =D52-D56 -> #REF! | E58: =E52-E56 -> 3346.81 | F58: =F52-F56 -> 4310.12 | G58: =G52-G56 -> 4448.6 | H58: =H52-H56 -> 6129.68 | I58: =I52-I56 -> 5617.84 | ... AE58: =AE52-AE56 -> -1650.986 | AI58: =AI52-AI56 -> 270.45 | AJ58: =AJ52-AJ56 -> 206.33 | AK58: =AK52-AK56 -> -337.12 | AL58: =AL52-AL56 -> -239.33 | AM58: =AM52-AM56 -> -394.59 | AN58: =AN52-AN56 -> -437.73 | AO58: =AO52-AO56 -> -971.26 | AP58: =AP52-AP56 -> -1177.31 | ... DB58: =DB52-DB56 -> 4334.5598 | DF58: 2590.5966
A59: Other Income | B59: ='Annual Raw'!C23 -> 0 | C59: ='Annual Raw'!D23 -> 0 | D59: ='Annual Raw'!E23 -> 0 | E59: 35.93 | F59: 93.55 | G59: 17.94 | H59: 37.79 | I59: 211.69 | J59: 4.48 | K59: 0.21 | L59: 22.98 | M59: 574.08 | N59: 2088.2 | O59: 2230.35 | P59: 182.93 | Q59: 1402.31 | R59: 981.06 | S59: 2492.48 | T59: 2554.66 | U59: 1383.05 | V59: 842.96 | W59: 659.91 | X59: 820.94 | Y59: 1150 | Z59: 2796 | AA59: 2796 | AB59: =+SUM(CM59:CP59) -> 0 | AC59: =+SUM(CQ59:CT59) -> 0 | AD59: =+SUM(CU59:CX59) -> 0 | AE59: =+SUM(CY59:DB59) -> 0 | AI59: 447.07 | AJ59: 1439.31 | AK59: 111.8 | AL59: 90.02 | AM59: 1620.55 | AN59: 76.19 | AO59: 40.15 | AP59: 148.24 | AQ59: 1597.19 | AR59: 142.71 | AS59: 44.95 | AT59: 83.07 | AU59: 582.67 | AV59: 214.95 | AW59: 493.9 | AX59: 110.79 | AY59: 624.55 | AZ59: 146.02 | BA59: 93.95 | BB59: 115.29 | BC59: 640.97 | BD59: 222.27 | BE59: 223.76 | BF59: 1282.88 | BG59: 1521.59 | BH59: 343.87 | BI59: 269.4 | BJ59: 419.8 | BK59: 401.2 | BL59: 361.42 | BM59: 351.51 | BN59: 268.92 | BO59: 134.33 | BP59: 241.98 | BQ59: 206.65 | BR59: 260 | BS59: 245.81 | BT59: 201.3 | BU59: 138.74 | BV59: 195.32 | BW59: 210.77 | BX59: 195.06 | BY59: 173.18 | BZ59: 241.93 | CA59: 299.08 | CB59: 579.81 | CC59: 146.82 | CD59: 124.16 | CE59: 1989 | CF59: 176 | CG59: 306 | CH59: 207 | CI59: 245 | CJ59: ='QTR Raw'!BD23 -> 278 | CK59: ='QTR Raw'!BE23 -> 272 | CL59: ='QTR Raw'!BF23 -> 240 | DF59: 1035
A60: Interest | B60: ='Annual Raw'!C25 -> 0 | C60: ='Annual Raw'!D25 -> 0 | D60: ='Annual Raw'!E25 -> 0 | E60: 161.26 | F60: 154.15 | G60: 226.35 | H60: 313.07 | I60: 282.37 | J60: 673.68 | K60: 1103.84 | L60: 1383.7 | M60: 1218.62 | N60: 1387.76 | O60: 1337.52 | P60: 1611.68 | Q60: 1592 | R60: 1569.01 | S60: 1744.43 | T60: 1793.57 | U60: 1973 | V60: 2358.64 | W60: 2121.73 | X60: 2047.51 | Y60: 1706 | Z60: 1122 | AA60: 1122 | AB60: =+SUM(CM60:CP60) -> 959.07535 | AC60: =+SUM(CQ60:CT60) -> 1117.0786 | AD60: =+SUM(CU60:CX60) -> 1075.1895 | AE60: =+SUM(CY60:DB60) -> 1586.6013 | AI60: 319.23 | AJ60: 366.77 | AK60: 367.81 | AL60: 333.95 | AM60: 318.51 | AN60: 339.96 | AO60: 356.49 | AP60: 323.12 | AQ60: 343.68 | AR60: 347.19 | AS60: 418.41 | AT60: 470.91 | AU60: 434.98 | AV60: 367.16 | AW60: 357.16 | AX60: 433.59 | AY60: 349.13 | AZ60: 372.77 | BA60: 413.73 | BB60: 449.28 | BC60: 362.72 | BD60: 439.2 | BE60: 496.08 | BF60: 446.43 | BG60: 493.23 | BH60: 443.12 | BI60: 468.08 | BJ60: 389.14 | BK60: 439.49 | BL60: 497.92 | BM60: 478.54 | BN60: 557.05 | BO60: 552.8 | BP60: 634.67 | BQ60: 656.22 | BR60: 514.86 | BS60: 621.1 | BT60: 530.94 | BU60: 535.55 | BV60: 491.75 | BW60: 528.8 | BX60: 549.35 | BY60: 503.43 | BZ60: 465.93 | CA60: 411.74 | CB60: 471.48 | CC60: 411.95 | CD60: 410.57 | CE60: 344 | CF60: 211 | CG60: 265 | CH60: 252 | CI60: 174 | CJ60: ='QTR Raw'!BD25 -> 186 | CK60: ='QTR Raw'!BE25 -> 143 | CL60: ='QTR Raw'!BF25 -> 126 | CM60: =CM61*CL200 -> 230.535 | CN60: =CN61*CM200 -> 102.37889 | CO60: =CO61*CN200 -> 218.00357 | CP60: =CP61*CO200 -> 408.15789 | CQ60: =CQ61*CP200 -> 278.08555 | CR60: =CR61*CQ200 -> 209.21321 | CS60: =CS61*CR200 -> 267.61079 | CT60: =CT61*CS200 -> 362.16901 | ... DB60: =DB61*DA200 -> 460.17276 | DF60: -59.703062
A61: Interest % of Debt | E61: =+E60/E159 -> 0.12800749 | F61: =+F60/F159 -> 0.061773168 | G61: =+G60/G159 -> 0.077072636 | H61: =+H60/H159 -> 0.078089066 | I61: =+I60/I159 -> 0.044959653 | J61: =+J60/J159 -> 0.050539848 | K61: =+K60/K159 -> 0.067172767 | L61: =+L60/L159 -> 0.094526714 | ... AA61: =+AA60/AA159 -> 0.10163964 | AI61: =(AI60-AI59)/AH200 -> #DIV/0! | AJ61: =(AJ60-AJ59)/AI200 -> #DIV/0! | AK61: =(AK60-AK59)/AJ200 -> #DIV/0! | AL61: =(AL60-AL59)/AK200 -> 0.53202905 | AM61: =(AM60-AM59)/AL200 -> #DIV/0! | AN61: =(AN60-AN59)/AM200 -> -0.37506754 | AO61: =(AO60-AO59)/AN200 -> #DIV/0! | AP61: =(AP60-AP59)/AO200 -> -0.13974748 | ... CL61: =(CL60-CL59)/CK200 -> -0.054267245 | CM61: -0.045 | CN61: =+CM61 -> -0.045 | CO61: =+CN61 -> -0.045 | CP61: =+CO61 -> -0.045 | CQ61: -0.021 | CR61: =+CQ61 -> -0.021 | CS61: =+CR61 -> -0.021 | CT61: =+CS61 -> -0.021 | CU61: -0.012 | CV61: =+CU61 -> -0.012 | CW61: =+CV61 -> -0.012 | CX61: =+CW61 -> -0.012 | CY61: =+CX61 -> -0.012 | CZ61: =+CY61 -> -0.012 | DA61: =+CZ61 -> -0.012 | DB61: =+DA61 -> -0.012 | DF61: -0.028420357
A62: PBT | B62: =B58+B59-B60 -> #REF! | C62: =C58+C59-C60 -> #REF! | D62: =D58+D59-D60 -> #REF! | E62: =E58+E59-E60 -> 3221.48 | F62: =F58+F59-F60 -> 4249.52 | G62: =G58+G59-G60 -> 4240.19 | H62: =H58+H59-H60 -> 5854.4 | I62: =I58+I59-I60 -> 5547.16 | ... AE62: =AE58+AE59-AE60 -> -3237.5873 | AI62: =AI58+AI59-AI60 -> 398.29 | AJ62: =AJ58+AJ59-AJ60 -> 1278.87 | AK62: =AK58+AK59-AK60 -> -593.13 | AL62: =AL58+AL59-AL60 -> -483.26 | AM62: =AM58+AM59-AM60 -> 907.45 | AN62: =AN58+AN59-AN60 -> -701.5 | AO62: =AO58+AO59-AO60 -> -1287.6 | AP62: =AP58+AP59-AP60 -> -1352.19 | ... DB62: =DB58+DB59-DB60 -> 3874.387 | DF62: 2650.2996
A63: Tax | B63: ='Annual Raw'!C30 -> 0 | C63: ='Annual Raw'!D30 -> 0 | D63: ='Annual Raw'!E30 -> 0 | E63: 482 | F63: 414.95 | G63: 524.5 | H63: 659.72 | I63: 547.55 | J63: 12.5 | K63: 589.46 | L63: 384.7 | M63: 98.8 | N63: -126.88 | O63: -1360.32 | P63: 764.23 | Q63: -4.8 | R63: 76.33 | S63: 87.93 | T63: 378.33 | U63: 162.29 | V63: 82.87 | W63: 99.18 | X63: -1473.33 | Y63: -51 | Z63: 1900 | AA63: 1900 | AB63: =+SUM(CM63:CP63) -> 1687.0216 | AC63: =+SUM(CQ63:CT63) -> 1980.27 | AD63: =+SUM(CU63:CX63) -> 2339.1235 | AE63: =+SUM(CY63:DB63) -> 2579.9923 | AI63: 32 | AJ63: 157 | AK63: -142.79 | AL63: -173.09 | AM63: 50 | AN63: -180 | AO63: -630 | AP63: -600.32 | AQ63: 0 | AR63: 738.26 | AS63: 18.14 | AT63: 7.83 | AU63: 42.16 | AV63: 16.74 | AW63: -2.43 | AX63: -61.27 | AY63: 12.12 | AZ63: 21.84 | BA63: 14.33 | BB63: 18.94 | BC63: 0.21 | BD63: 33.77 | BE63: 27.74 | BF63: 26.21 | BG63: 276.5 | BH63: 41.21 | BI63: -98.7 | BJ63: 159.32 | BK63: 49.43 | BL63: 11.98 | BM63: 15.66 | BN63: 85.22 | BO63: 0.38 | BP63: 0.4 | BQ63: 37.5 | BR63: 44.59 | BS63: 6.59 | BT63: 3.8 | BU63: 53.84 | BV63: 40.74 | BW63: 41.35 | BX63: 41 | BY63: 54.03 | BZ63: -1609.71 | CA63: 85.85 | CB63: 147.62 | CC63: 296.07 | CD63: -580.8 | CE63: 845 | CF63: 446 | CG63: 125 | CH63: 253 | CI63: 214 | CJ63: ='QTR Raw'!BD29 -> 412 | CK63: ='QTR Raw'!BE29 -> 212 | CL63: ='QTR Raw'!BF29 -> 786 | CM63: =+CM62*CM64 -> 281.68895 | CN63: =+CN62*CN64 -> 379.59492 | CO63: =+CO62*CO64 -> 449.03871 | CP63: =+CP62*CP64 -> 576.69898 | CQ63: =+CQ62*CQ64 -> 353.64304 | CR63: =+CR62*CR64 -> 433.56807 | CS63: =+CS62*CS64 -> 547.46786 | CT63: =+CT62*CT64 -> 645.59099 | ... DB63: =+DB62*DB64 -> 825.82367 | DF63: 395.87653
A64: Tax Rate % | B64: =B63/B62 -> #REF! | C64: =C63/C62 -> #REF! | D64: =D63/D62 -> #REF! | E64: =E63/E62 -> 0.14962067 | F64: =F63/F62 -> 0.097646322 | G64: =G63/G62 -> 0.12369729 | H64: =H63/H62 -> 0.11268789 | I64: =I63/I62 -> 0.098708168 | ... AE64: =AE63/AE62 -> -0.79688733 | AI64: =AI63/AI62 -> 0.080343468 | AJ64: =AJ63/AJ62 -> 0.12276463 | AK64: =AK63/AK62 -> 0.2407398 | AL64: =AL63/AL62 -> 0.35817158 | AM64: =AM63/AM62 -> 0.055099455 | AN64: =AN63/AN62 -> 0.25659301 | AO64: =AO63/AO62 -> 0.48928239 | AP64: =AP63/AP62 -> 0.44396128 | ... CL64: =CL63/CL62 -> 0.26446837 | CM64: =AVERAGE(CI64:CL64)*1.04 -> 0.18968531 | CN64: =AVERAGE(CJ64:CM64)*1.04 -> 0.20282663 | CO64: =AVERAGE(CK64:CN64)*1.04 -> 0.194594 | CP64: =AVERAGE(CL64:CO64)*1.04 -> 0.22140932 | CQ64: =AVERAGE(CM64:CP64)*1.02 -> 0.20617139 | CR64: =AVERAGE(CN64:CQ64)*1.02 -> 0.21037534 | CS64: =AVERAGE(CO64:CR64)*1.02 -> 0.21230027 | CT64: =AVERAGE(CP64:CS64)*1.02 -> 0.21681536 | CU64: =AVERAGE(CQ64:CT64) -> 0.21141559 | CV64: =AVERAGE(CR64:CU64) -> 0.21272664 | CW64: =AVERAGE(CS64:CV64) -> 0.21331447 | CX64: =AVERAGE(CT64:CW64) -> 0.21356802 | CY64: =AVERAGE(CU64:CX64) -> 0.21275618 | CZ64: =AVERAGE(CV64:CY64) -> 0.21309133 | DA64: =AVERAGE(CW64:CZ64) -> 0.2131825 | DB64: =AVERAGE(CX64:DA64) -> 0.2131495 | DF64: 0.14937048
A65: PAT | B65: =B62-B63 -> #REF! | C65: =C62-C63 -> #REF! | D65: =D62-D63 -> #REF! | E65: =E62-E63 -> 2739.48 | F65: =F62-F63 -> 3834.57 | G65: =G62-G63 -> 3715.69 | H65: =H62-H63 -> 5194.68 | I65: =I62-I63 -> 4999.61 | ... AE65: =AE62-AE63 -> -5817.5796 | AI65: =AI62-AI63 -> 366.29 | AJ65: =AJ62-AJ63 -> 1121.87 | AK65: =AK62-AK63 -> -450.34 | AL65: =AL62-AL63 -> -310.17 | AM65: =AM62-AM63 -> 857.45 | AN65: =AN62-AN63 -> -521.5 | AO65: =AO62-AO63 -> -657.6 | AP65: =AP62-AP63 -> -751.87 | ... DB65: =DB62-DB63 -> 3048.5633 | DF65: 2254.4231
A66: PAT % | B66: =+B65/B32 -> #REF! | C66: =+C65/C32 -> #REF! | D66: =+D65/D32 -> #REF! | E66: =+E65/E32 -> 0.18115295 | F66: =+F65/F32 -> 0.19128472 | G66: =+G65/G32 -> 0.16124236 | H66: =+H65/H32 -> 0.16800964 | I66: =+I65/I32 -> 0.15554602 | ... AE66: =+AE65/AE32 -> -0.049270287 | AI66: =+AI65/AI32 -> 0.03460002 | AJ66: =+AJ65/AJ32 -> 0.089883779 | AK66: =+AK65/AK32 -> -0.042364646 | AL66: =+AL65/AL32 -> -0.028024565 | AM66: =+AM65/AM32 -> 0.094178703 | AN66: =+AN65/AN32 -> -0.058803962 | AO66: =+AO65/AO32 -> -0.084636799 | AP66: =+AP65/AP32 -> -0.087984422 | ... DB66: =+DB65/DB32 -> 0.083712338 | DF66: 0.092783637
A67: PAT YOY% | C67: =+C65/B65-1 -> #REF! | D67: =+D65/C65-1 -> #REF! | F67: =+F65/E65-1 -> 0.39974375 | G67: =+G65/F65-1 -> -0.031002172 | H67: =+H65/G65-1 -> 0.39803913 | I67: =+I65/H65-1 -> -0.03755188 | J67: =+J65/I65-1 -> -0.56048972 | K67: =+K65/J65-1 -> 0.3961445 | L67: =+L65/K65-1 -> 0.42202708 | M67: =+M65/L65-1 -> 0.19739962 | ... V67: =+V65/U65-1 -> -0.19122837 | W67: =W65/V65-1 -> -0.49126677 | X67: =X65/W65-1 -> -2.9519821 | Y67: =Y65/X65-1 -> 0.62518119 | Z67: =Z65/Y65-1 -> 0.093492895 | AA67: =AA65/Z65-1 -> 0 | AB67: =+AB65/AA65-1 -> -1.8140967 | AC67: =+AC65/AB65-1 -> -0.014179651 | AD67: =+AD65/AC65-1 -> 0.032205413 | AE67: =+AE65/AD65-1 -> 0.20086739 | AM67: =+IF(AI65<0,1-AM65/AI65,AM65/AI65-1) -> 1.3409047 | AN67: =+IF(AJ65<0,1-AN65/AJ65,AN65/AJ65-1) -> -1.4648489 | AO67: =+IF(AK65<0,1-AO65/AK65,AO65/AK65-1) -> -0.46023005 | AP67: =+IF(AL65<0,1-AP65/AL65,AP65/AL65-1) -> -1.4240578 | AQ67: =+IF(AM65<0,1-AQ65/AM65,AQ65/AM65-1) -> -0.51194822 | AR67: =+IF(AN65<0,1-AR65/AN65,AR65/AN65-1) -> -2.4869799 | AS67: =+IF(AO65<0,1-AS65/AO65,AS65/AO65-1) -> -1.4008668 | AT67: =+IF(AP65<0,1-AT65/AP65,AT65/AP65-1) -> -0.40977829 | ... CL67: =+IF(CH65<0,1-CL65/CH65,CL65/CH65-1) -> 2.9919649 | CM67: =+CM65/CI65-1 -> -0.091129846 | CN67: =+CN65/CJ65-1 -> 0.10924096 | CO67: =+CO65/CK65-1 -> -0.11750791 | CP67: =+CP65/CL65-1 -> -0.072289819 | CQ67: =+CQ65/CM65-1 -> 0.1315497 | CR67: =+CR65/CN65-1 -> 0.090774467 | CS67: =+CS65/CO65-1 -> 0.09294825 | CT67: =+CT65/CP65-1 -> 0.14992387 | ... DB67: =+DB65/CX65-1 -> 0.10705947 | DF67: 0.35972443
A68: PAT QOQ% | AJ68: =+IF(AI65<0,1-AJ65/AI65,AJ65/AI65-1) -> 2.0627918 | AK68: =+IF(AJ65<0,1-AK65/AJ65,AK65/AJ65-1) -> -1.4014191 | AL68: =+IF(AK65<0,1-AL65/AK65,AL65/AK65-1) -> 0.31125372 | AM68: =+IF(AL65<0,1-AM65/AL65,AM65/AL65-1) -> 3.7644518 | AN68: =+IF(AM65<0,1-AN65/AM65,AN65/AM65-1) -> -1.6081987 | AO68: =+IF(AN65<0,1-AO65/AN65,AO65/AN65-1) -> -0.26097795 | AP68: =+IF(AO65<0,1-AP65/AO65,AP65/AO65-1) -> -0.14335462 | AQ68: =+IF(AP65<0,1-AQ65/AP65,AQ65/AP65-1) -> 1.5565856 | ... CL68: =+IF(CK65<0,1-CL65/CK65,CL65/CK65-1) -> 0.037986705 | CM68: =+CM65/CL65-1 -> -0.44952238 | CN68: =+CN65/CM65-1 -> 0.23981919 | CO68: =+CO65/CN65-1 -> 0.24572163 | CP68: =+CP65/CO65-1 -> 0.091172196 | CQ68: =+CQ65/CP65-1 -> -0.32856963 | CR68: =+CR65/CQ65-1 -> 0.19514249 | CS68: =+CS65/CR65-1 -> 0.24820421 | CT68: =+CT65/CS65-1 -> 0.14805523 | ... DB68: =+DB65/DA65-1 -> 0.16484027 | DF68: 0.070476311
A69: Minority Interest | B69: ='Annual Raw'!C32 -> 0 | C69: ='Annual Raw'!D32 -> 0 | D69: ='Annual Raw'!E32 -> 0 | E69: ='Annual Raw'!F32 -> 0 | F69: ='Annual Raw'!G32 -> 0 | G69: ='Annual Raw'!H32 -> 0 | H69: ='Annual Raw'!I32 -> 0 | I69: ='Annual Raw'!J32 -> 0 | ... AA69: ='Annual Raw'!AB32 -> 0 | AB69: =+SUM(CM69:CP69) -> 0 | AC69: =+SUM(CQ69:CT69) -> 0 | AD69: =+SUM(CU69:CX69) -> 0 | AE69: =+SUM(CY69:DB69) -> 0 | AI69: ='QTR Raw'!C34 -> 0 | AJ69: ='QTR Raw'!D34 -> 0 | AK69: ='QTR Raw'!E34 -> 0 | AL69: ='QTR Raw'!F34 -> 0 | AM69: ='QTR Raw'!G34 -> 0 | AN69: ='QTR Raw'!H34 -> 0 | AO69: ='QTR Raw'!I34 -> 0 | AP69: ='QTR Raw'!J34 -> 0 | ... CL69: ='QTR Raw'!BF34 -> 0 | CM69: =+CL69 -> 0 | CN69: =+CM69 -> 0 | CO69: =+CN69 -> 0 | CP69: =+CO69 -> 0 | CQ69: =+CP69 -> 0 | CR69: =+CQ69 -> 0 | CS69: =+CR69 -> 0 | CT69: =+CS69 -> 0 | ... DB69: =+DA69 -> 0 | DF69: 0
A70: Share of Associate | B70: ='Annual Raw'!C33+'Annual Raw'!C28 -> 0 | C70: ='Annual Raw'!D33+'Annual Raw'!D28 -> 0 | D70: ='Annual Raw'!E33+'Annual Raw'!E28 -> 0 | E70: ='Annual Raw'!F33+'Annual Raw'!F28 -> 0 | F70: ='Annual Raw'!G33+'Annual Raw'!G28 -> 0 | G70: ='Annual Raw'!H33+'Annual Raw'!H28 -> 0 | H70: ='Annual Raw'!I33+'Annual Raw'!I28 -> 0 | I70: ='Annual Raw'!J33+'Annual Raw'!J28 -> 0 | ... AA70: ='Annual Raw'!AB33+'Annual Raw'!AB28 -> 0 | AB70: =+SUM(CM70:CP70) -> 0 | AC70: =+SUM(CQ70:CT70) -> 0 | AD70: =+SUM(CU70:CX70) -> 0 | AE70: =+SUM(CY70:DB70) -> 0 | AI70: ='QTR Raw'!C35 -> 0 | AJ70: ='QTR Raw'!D35 -> 0 | AK70: ='QTR Raw'!E35 -> 0 | AL70: ='QTR Raw'!F35 -> 0 | AM70: ='QTR Raw'!G35 -> 0 | AN70: ='QTR Raw'!H35 -> 0 | AO70: ='QTR Raw'!I35 -> 0 | AP70: ='QTR Raw'!J35 -> 0 | ... CL70: ='QTR Raw'!BF35 -> 0 | CM70: =+CL70 -> 0 | CN70: =+CM70 -> 0 | CO70: =+CN70 -> 0 | CP70: =+CO70 -> 0 | CQ70: =+CP70 -> 0 | CR70: =+CQ70 -> 0 | CS70: =+CR70 -> 0 | CT70: =+CS70 -> 0 | ... DB70: =+DA70 -> 0 | DF70: 0
A71: Foreign Exchange Gain/loss | E71: 40.95 | F71: -29.04 | G71: -21.7 | H71: 130.48 | I71: 160.73 | J71: -65.3 | K71: -69.6 | L71: -147.12 | M71: -455.24 | N71: -438.12 | O71: -273.06 | P71: -320.5 | Q71: -222.91 | R71: 252.78 | S71: -17.14 | T71: -215.22 | U71: -239 | V71: -1.67 | W71: -136.81 | X71: -279.76 | Y71: -255 | Z71: -71 | AA71: -71 | AI71: -160.95 | AJ71: -254.85 | AK71: -8.15 | AL71: -14.17 | AM71: -154.19 | AN71: -282.03 | AO71: -11.87 | AP71: -26.97 | AQ71: -24.78 | AR71: -27.04 | AS71: -247.52 | AT71: -21.16 | AU71: -21.76 | AV71: -205.53 | AW71: -19.2 | AX71: 9.69 | AY71: -78.82 | AZ71: 120.15 | BA71: -44.15 | BB71: 255.27 | BC71: 7.79 | BD71: -72.82 | BE71: 143.34 | BF71: -95.38 | BG71: -195.07 | BH71: -301.23 | BI71: 203.32 | BJ71: 77.76 | BK71: 37.15 | BL71: 69.18 | BM71: 13.14 | BN71: -220.11 | BO71: -20.93 | BP71: 35.21 | BQ71: 5.28 | BR71: -21.23 | BS71: -44.02 | BT71: -17.79 | BU71: -33.8 | BV71: -49.8 | BW71: -89.06 | BX71: -98.42 | BY71: -66.68 | BZ71: -25.6 | CA71: -49.96 | CB71: -36.08 | CC71: -157.84 | CD71: -11.09 | CE71: -11 | CF71: -12 | CG71: -6 | CH71: -46 | CI71: 97
A72: Exceptional Income / Expenses | B72: ='Annual Raw'!C29+'Annual Raw'!C31+'Annual Raw'!C34+'Annual Raw'!C36 -> 0 | C72: ='Annual Raw'!D29+'Annual Raw'!D31+'Annual Raw'!D34+'Annual Raw'!D36 -> 0 | D72: ='Annual Raw'!E29+'Annual Raw'!E31+'Annual Raw'!E34+'Annual Raw'!E36 -> 0 | E72: 52.86 | F72: 13.85 | G72: -169.95 | H72: 104.92 | I72: -326.39 | J72: -571.01 | K72: -950.86 | L72: 0 | M72: 130 | N72: -12.25 | O72: 266.8 | P72: 83.25 | Q72: 271.84 | R72: 338.71 | S72: 966.66 | T72: 203.07 | U72: 2510.92 | V72: -1392.08 | W72: -83.41 | X72: 282.82 | Y72: -2809 | Z72: 325 | AA72: 325 | AB72: =+SUM(CM72:CP72) -> 0 | AC72: =+SUM(CQ72:CT72) -> 0 | AD72: =+SUM(CU72:CX72) -> 0 | AE72: =+SUM(CY72:DB72) -> 0 | AI72: 0 | AJ72: 0 | AK72: 0 | AL72: -12.25 | AM72: 0 | AN72: 0 | AO72: -1920.87 | AP72: 37.77 | AQ72: 0 | AR72: 0.13 | AS72: 296.39 | AT72: 83.12 | AU72: -315.67 | AV72: 99.56 | AW72: 163.24 | AX72: 0.23 | AY72: 0 | AZ72: 49.66 | BA72: 0.75 | BB72: 288.3 | BC72: 0 | BD72: 0 | BE72: 4.73 | BF72: 961.93 | BG72: 0 | BH72: 93.21 | BI72: 28.19 | BJ72: 81.67 | BK72: 7.93 | BL72: -71.67 | BM72: 3.89 | BN72: 2570.77 | BO72: 48.88 | BP72: 46.36 | BQ72: 58.3 | BR72: -1545.62 | BS72: 24.89 | BT72: 33.16 | BU72: 0.09 | BV72: -141.55 | BW72: 1.43 | BX72: 4.04 | BY72: 0.11 | BZ72: 277.24 | CA72: 647.95 | CB72: 126.02 | CC72: -3668.9 | CD72: 86.5 | CE72: 38 | CF72: 33 | CG72: 24 | CH72: 230 | CI72: 10 | CJ72: ='QTR Raw'!BD26+'QTR Raw'!BD31+'QTR Raw'!BD32+'QTR Raw'!BD33+'QTR Raw'!BD36+'QTR Raw'!BD37+'QTR Raw'!BD39 -> -2366 | CK72: ='QTR Raw'!BE26+'QTR Raw'!BE31+'QTR Raw'!BE32+'QTR Raw'!BE33+'QTR Raw'!BE36+'QTR Raw'!BE37+'QTR Raw'!BE39 -> -1545 | CL72: ='QTR Raw'!BF26+'QTR Raw'!BF31+'QTR Raw'!BF32+'QTR Raw'!BF33+'QTR Raw'!BF36+'QTR Raw'!BF37+'QTR Raw'!BF39 -> 220 | DF72: -3681
A73: Consolidated Net Profit | B73: =B65+B69+B70+B72 -> #REF! | C73: =C65+C69+C70+C72 -> #REF! | D73: =D65+D69+D70+D72 -> #REF! | E73: =E65+E69+E70-E72+E71 -> 2727.57 | F73: =F65+F69+F70-F72+F71 -> 3791.68 | G73: =G65+G69+G70-G72+G71 -> 3863.94 | H73: =H65+H69+H70-H72+H71 -> 5220.24 | I73: =I65+I69+I70-I72+I71 -> 5486.73 | J73: =J65+J69+J70-J72+J71 -> 2703.09 | K73: =K65+K69+K70-K72+K71 -> 3949.12 | L73: =L65+L69+L70-L72+L71 -> 4215.46 | ... AE73: =AE65+AE69+AE70-AE72+AE71 -> -5817.5796 | AI73: =AI65+AI69+AI70-AI72+AI71 -> 205.34 | AJ73: =AJ65+AJ69+AJ70-AJ72+AJ71 -> 867.02 | AK73: =AK65+AK69+AK70-AK72+AK71 -> -458.49 | AL73: =AL65+AL69+AL70-AL72+AL71 -> -312.09 | AM73: =AM65+AM69+AM70-AM72+AM71 -> 703.26 | AN73: =AN65+AN69+AN70-AN72+AN71 -> -803.53 | AO73: =AO65+AO69+AO70-AO72+AO71 -> 1251.4 | AP73: =AP65+AP69+AP70-AP72+AP71 -> -816.61 | ... CI73: =CI65+CI69+CI70-CI72+CI71 -> 1411 | CJ73: =CJ65+CJ69+CJ70+CJ72+CJ71 -> -1021 | CK73: =CK65+CK69+CK70+CK72+CK71 -> 561 | CL73: =CL65+CL69+CL70+CL72+CL71 -> 2406 | CM73: =CM65+CM69+CM70-CM72+CM71 -> 1203.3441 | CN73: =CN65+CN69+CN70+CN72 -> 1491.9291 | CO73: =CO65+CO69+CO70+CO72 -> 1858.5283 | CP73: =CP65+CP69+CP70+CP72 -> 2027.9745 | CQ73: =CQ65+CQ69+CQ70+CQ72 -> 1361.6436 | CR73: =CR65+CR69+CR70+CR72 -> 1627.3582 | CS73: =CS65+CS69+CS70+CS72 -> 2031.2753 | CT73: =CT65+CT69+CT70+CT72 -> 2332.0162 | CU73: =CU65+CU69+CU70+CU72 -> 1627.1324 | ... DB73: =DB65+DB69+DB70+DB72 -> 3048.5633 | DF73: 2254.4231
A74: Profit & Loss- Annual (End)
A75: Rat
A76: Ace - PAT | B76: ='Annual Raw'!C35 -> 0 | C76: ='Annual Raw'!D35 -> 0 | D76: ='Annual Raw'!E35 -> 0 | E76: 2727.57 | F76: 3791.68 | G76: 3863.94 | H76: 5220.24 | I76: 5486.73 | J76: 2703.09 | K76: 3949.12 | L76: 4215.46 | M76: 4638.5116 | N76: 3341.5519 | O76: 806.44262 | P76: -4678.2213 | Q76: 4897.66 | R76: 2890.4 | S76: 213.91 | T76: 2458.48 | U76: -6847.22 | V76: -1923.37 | W76: -1739.23 | X76: 2728.13 | Y76: 7902 | Z76: 5452 | AA76: 5452 | AB76: =+AB73 -> -4760.8377 | AC76: =+AC73 -> -4693.3307 | AD76: =+AD73 -> -4844.4813 | AE76: =+AE73 -> -5817.5796 | AI76: 205.34 | AJ76: 867.02 | AK76: -458.49 | AL76: -312.09 | AM76: 703.26 | AN76: -803.53 | AO76: 1251.4 | AP76: -816.61 | AQ76: 393.7 | AR76: -1845.63 | AS76: -2122.72 | AT76: -1164.25 | AU76: 289.84 | AV76: -288.79 | AW76: -136.82 | AX76: 397.95 | AY76: 25.75 | AZ76: -630.76 | BA76: -1045.94 | BB76: -805.91 | BC76: -463.14 | BD76: -283.35 | BE76: 211.59 | BF76: -499.94 | BG76: 1187.65 | BH76: 109.14 | BI76: 617.62 | BJ76: 106.19 | BK76: -97.1 | BL76: -1281.97 | BM76: -1039.51 | BN76: -4871.05 | BO76: -2190.64 | BP76: -1212.45 | BQ76: -638.04 | BR76: 1645.72 | BS76: -1320.73 | BT76: -575.68 | BU76: -635.49 | BV76: 413.35 | BW76: -181.03 | BX76: -292.59 | BY76: 484.71 | BZ76: 2695.56 | CA76: -64 | CB76: 1269.62 | CC76: 4570.05 | CD76: 2126.43 | CE76: 2190 | CF76: 643 | CG76: 1404 | CH76: 1382 | CI76: 1411 | CJ76: ='QTR Raw'!BD42 -> -1021 | CK76: ='QTR Raw'!BE42 -> 561 | CL76: ='QTR Raw'!BF42 -> 2406 | DF76: 10037
A77: Checksum - PAT | B77: =B76-B73 -> #REF! | C77: =C76-C73 -> #REF! | D77: =D76-D73 -> #REF! | E77: =E76-E73 -> 0 | F77: =F76-F73 -> 0 | G77: =G76-G73 -> 0 | H77: =H76-H73 -> 0 | I77: =I76-I73 -> 0 | ... AE77: =AE76-AE73 -> 0 | AI77: =AI76-AI73 -> -1.1937118e-12 | AJ77: =AJ76-AJ73 -> 1.7053026e-12 | AK77: =AK76-AK73 -> -2.5579538e-12 | AL77: =AL76-AL73 -> -1.4210855e-12 | AM77: =AM76-AM73 -> 4.0927262e-12 | AN77: =AN76-AN73 -> -1.5916157e-12 | AO77: =AO76-AO73 -> 0 | AP77: =AP76-AP73 -> -1.2505552e-12 | ... CL77: =CL76-CL73 -> 0 | DF77: 0
A78: Ratios (Start)
A79: ROE (%) | B79: =(B73-B72)/B150 -> #REF! | C79: =(C73-C72)/C150 -> #REF! | D79: =(D73-D72)/D150 -> #REF! | E79: =(E73-E72)/E150 -> 0.7442982 | F79: =(F73-F72)/F150 -> 0.91886929 | G79: =(G73-G72)/G150 -> 0.72852429 | H79: =(H73-H72)/H150 -> 0.74461516 | I79: =(I73-I72)/I150 -> 0.74151668 | ... AE79: =(AE73-AE72)/AE150 -> -0.12783371 | AL79: =(SUM(AI73:AL73)-SUM(AI72:AL72))/AL150 -> #DIV/0! | AM79: =(SUM(AJ73:AM73)-SUM(AJ72:AM72))/AM150 -> 1.1545517 | AN79: =(SUM(AK73:AN73)-SUM(AK72:AN72))/AN150 -> #DIV/0! | AO79: =(SUM(AL73:AO73)-SUM(AL72:AO72))/AO150 -> 2.2152469 | AP79: =(SUM(AM73:AP73)-SUM(AM72:AP72))/AP150 -> #DIV/0! | AQ79: =(SUM(AN73:AQ73)-SUM(AN72:AQ72))/AQ150 -> 4.8464821 | AR79: =(SUM(AO73:AR73)-SUM(AO72:AR72))/AR150 -> #DIV/0! | AS79: =(SUM(AP73:AS73)-SUM(AP72:AS72))/AS150 -> 2.2261768 | ... DB79: =(SUM(CY73:DB73)-SUM(CY72:DB72))/DB150 -> 0.2093769 | DF79: 0.53595266
A80: ROCE (%) | B80: =+B58/B160 -> #REF! | C80: =+C58/C160 -> #REF! | D80: =+D58/D160 -> #REF! | E80: =+E58/E160 -> 0.68958476 | F80: =+F58/F160 -> 0.65237535 | G80: =+G58/G160 -> 0.52497607 | H80: =+H58/H160 -> 0.56344719 | I80: =+I58/I160 -> 0.39786346 | ... AE80: =+AE58/AE160 -> -0.034084548 | AL80: =+SUM(AI58:AL58)/AL160 -> #DIV/0! | AM80: =+SUM(AJ58:AM58)/AM160 -> -1.0873788 | AN80: =+SUM(AK58:AN58)/AN160 -> #DIV/0! | AO80: =+SUM(AL58:AO58)/AO160 -> -1.6324996 | AP80: =+SUM(AM58:AP58)/AP160 -> #DIV/0! | AQ80: =+SUM(AN58:AQ58)/AQ160 -> -8.6901956 | AR80: =+SUM(AO58:AR58)/AR160 -> #DIV/0! | AS80: =+SUM(AP58:AS58)/AS160 -> 1.919834 | ... DB80: =+SUM(CY58:DB58)/DB160 -> 0.28273524 | DF80: 0.41901485
A81: Ratios (End)
A82: Checksum Of qtr to Annual
A83: Revenue - Checksum Of qtr to Annual | N83: =N32-SUM(AI32:AL32) -> 3039.8319 | O83: =O32-SUM(AM32:AP32) -> 2074.2596 | P83: =P32-SUM(AQ32:AT32) -> 1763.6387 | Q83: =Q32-SUM(AU32:AX32) -> 4946.07 | R83: =R32-SUM(AY32:BB32) -> 5284.94 | S83: =S32-SUM(BC32:BF32) -> 1123.55 | T83: =T32-SUM(BG32:BJ32) -> 437.88 | U83: =U32-SUM(BK32:BN32) -> 442.41 | V83: =V32-SUM(BO32:BR32) -> 472.08 | W83: =W32-SUM(BS32:BV32) -> -5327.58 | X83: =X32-SUM(BW32:BZ32) -> 0 | Y83: =Y32-SUM(CA32:CD32) -> -0.07 | Z83: =Z32-SUM(CE32:CH32) -> 0 | AA83: =AA32-SUM(CF32:CI32) -> 1180 | AB83: =AB32-SUM(CM32:CP32) -> 0 | AC83: =AC32-SUM(CQ32:CT32) -> 0 | AD83: =AD32-SUM(CU32:CX32) -> 0 | AE83: =AE32-SUM(CY32:DB32) -> 0 | DF83: -778
A84: GP - Checksum Of qtr to Annual | N84: =N38-SUM(AI38:AL38) -> 3039.8319 | O84: =O38-SUM(AM38:AP38) -> 2074.2596 | P84: =P38-SUM(AQ38:AT38) -> 1763.6387 | Q84: =Q38-SUM(AU38:AX38) -> 4946.07 | R84: =R38-SUM(AY38:BB38) -> 5288.75 | S84: =S38-SUM(BC38:BF38) -> 1123.55 | T84: =T38-SUM(BG38:BJ38) -> 437.88 | U84: =U38-SUM(BK38:BN38) -> 442.41 | V84: =V38-SUM(BO38:BR38) -> 472.08 | W84: =W38-SUM(BS38:BV38) -> -932.48 | X84: =X38-SUM(BW38:BZ38) -> -0.01 | Y84: =Y38-SUM(CA38:CD38) -> -0.32 | Z84: =Z38-SUM(CE38:CH38) -> 2084.5 | AA84: =AA38-SUM(CF38:CI38) -> 2229.5 | AB84: =AB38-SUM(CM38:CP38) -> 0 | AC84: =AC38-SUM(CQ38:CT38) -> 0 | AD84: =AD38-SUM(CU38:CX38) -> 0 | AE84: =AE38-SUM(CY38:DB38) -> 0 | DF84: -778
A85: EBITDA - Checksum Of qtr to Annual | N85: =N52-SUM(AI52:AL52) -> 3039.7719 | O85: =O52-SUM(AM52:AP52) -> 2074.0426 | P85: =P52-SUM(AQ52:AT52) -> 1480.7687 | Q85: =Q52-SUM(AU52:AX52) -> 4945.18 | R85: =R52-SUM(AY52:BB52) -> 5396.98 | S85: =S52-SUM(BC52:BF52) -> 1126.22 | T85: =T52-SUM(BG52:BJ52) -> 437.88 | U85: =U52-SUM(BK52:BN52) -> 580.77 | V85: =V52-SUM(BO52:BR52) -> 472.13 | W85: =W52-SUM(BS52:BV52) -> -112.93 | X85: =X52-SUM(BW52:BZ52) -> 21.48 | Y85: =Y52-SUM(CA52:CD52) -> -0.09 | Z85: =Z52-SUM(CE52:CH52) -> 2084.5 | AA85: =AA52-SUM(CF52:CI52) -> 2110.5 | AB85: =AB52-SUM(CM52:CP52) -> -11342.614 | AC85: =AC52-SUM(CQ52:CT52) -> -12045.624 | AD85: =AD52-SUM(CU52:CX52) -> -13491.849 | AE85: =AE52-SUM(CY52:DB52) -> -15346.105 | DF85: -605
A86: PAT - Checksum Of qtr to Annual | N86: =N73-SUM(AI73:AL73) -> 3039.7719 | O86: =O73-SUM(AM73:AP73) -> 471.92262 | P86: =P73-SUM(AQ73:AT73) -> 60.678674 | Q86: =Q73-SUM(AU73:AX73) -> 4635.48 | R86: =R73-SUM(AY73:BB73) -> 5347.26 | S86: =S73-SUM(BC73:BF73) -> 1248.75 | T86: =T73-SUM(BG73:BJ73) -> 437.88 | U86: =U73-SUM(BK73:BN73) -> 442.41 | V86: =V73-SUM(BO73:BR73) -> 472.04 | W86: =W65-SUM(BS65:BV65) -> 370.72 | X86: =X65-SUM(BW65:BZ65) -> 21.48 | Y86: =Y65-SUM(CA65:CD65) -> -0.64 | Z86: =Z65-SUM(CE65:CH65) -> 1913.5 | AA86: =AA65-SUM(CF65:CI65) -> 2828.5 | AB86: =AB65-SUM(CM65:CP65) -> -11342.614 | AC86: =AC65-SUM(CQ65:CT65) -> -12045.624 | AD86: =AD65-SUM(CU65:CX65) -> -13491.849 | AE86: =AE65-SUM(CY65:DB65) -> -15346.105 | DF86: -605
A87: Valuation (Start)
A88: Eq | B88: ='Annual Raw'!C104 -> 0 | C88: ='Annual Raw'!D104 -> 0 | D88: ='Annual Raw'!E104 -> 0 | E88: ='Annual Raw'!F104 -> 0 | F88: ='Annual Raw'!G104 -> 0 | G88: ='Annual Raw'!H104 -> 0 | H88: ='Annual Raw'!I104 -> 0 | I88: ='Annual Raw'!J104 -> 0 | ... AA88: ='Annual Raw'!AB104 -> 736 | AB88: =AA88 -> 736 | AC88: =AB88 -> 736 | AD88: =AC88 -> 736 | AE88: =AD88 -> 736 | AI88: =+AJ88 -> 736.466 | AJ88: =+AK88 -> 736.466 | AK88: =+AL88 -> 736.466 | AL88: =+AM88 -> 736.466 | AM88: =+AN88 -> 736.466 | AN88: =+AO88 -> 736.466 | AO88: =+AP88 -> 736.466 | AP88: =+AQ88 -> 736.466 | ... CI88: =+CJ88 -> 736.466 | CJ88: ='QTR Raw'!BD45 -> 736.466 | CK88: ='QTR Raw'!BE45 -> 736 | CL88: ='QTR Raw'!BF45 -> 736 | CM88: =+CL88 -> 736 | CN88: =+CM88 -> 736 | CO88: =+CN88 -> 736 | CP88: =+CO88 -> 736 | CQ88: =+CP88 -> 736 | CR88: =+CQ88 -> 736 | CS88: =+CR88 -> 736 | CT88: =+CS88 -> 736 | ... DB88: =+DA88 -> 736 | DF88: 736
A89: FV | B89: ='Annual Raw'!C105 -> 0 | C89: ='Annual Raw'!D105 -> 0 | D89: ='Annual Raw'!E105 -> 0 | E89: ='Annual Raw'!F105 -> 0 | F89: ='Annual Raw'!G105 -> 0 | G89: ='Annual Raw'!H105 -> 0 | H89: ='Annual Raw'!I105 -> 0 | I89: ='Annual Raw'!J105 -> 0 | ... AA89: ='Annual Raw'!AB105 -> 2 | AB89: =AA89 -> 2 | AC89: =AB89 -> 2 | AD89: =AC89 -> 2 | AE89: =AD89 -> 2 | AI89: =+AJ89 -> 2 | AJ89: =+AK89 -> 2 | AK89: =+AL89 -> 2 | AL89: =+AM89 -> 2 | AM89: =+AN89 -> 2 | AN89: =+AO89 -> 2 | AO89: =+AP89 -> 2 | AP89: =+AQ89 -> 2 | ... CI89: =+CJ89 -> 2 | CJ89: ='QTR Raw'!BD46 -> 2 | CK89: ='QTR Raw'!BE46 -> 2 | CL89: ='QTR Raw'!BF46 -> 2 | CM89: =+CL89 -> 2 | CN89: =+CM89 -> 2 | CO89: =+CN89 -> 2 | CP89: =+CO89 -> 2 | CQ89: =+CP89 -> 2 | CR89: =+CQ89 -> 2 | CS89: =+CR89 -> 2 | CT89: =+CS89 -> 2 | ... DB89: =+DA89 -> 2 | DF89: 2
A90: No of share | B90: =B88/B89 -> #DIV/0! | C90: =C88/C89 -> #DIV/0! | D90: =D88/D89 -> #DIV/0! | E90: =E88/E89 -> #DIV/0! | F90: =F88/F89 -> #DIV/0! | G90: =G88/G89 -> #DIV/0! | H90: =H88/H89 -> #DIV/0! | I90: =I88/I89 -> #DIV/0! | ... AE90: =AE88/AE89 -> 368 | AI90: =AI88/AI89 -> 368.233 | AJ90: =AJ88/AJ89 -> 368.233 | AK90: =AK88/AK89 -> 368.233 | AL90: =AL88/AL89 -> 368.233 | AM90: =AM88/AM89 -> 368.233 | AN90: =AN88/AN89 -> 368.233 | AO90: =AO88/AO89 -> 368.233 | AP90: =AP88/AP89 -> 368.233 | ... DB90: =DB88/DB89 -> 368 | DF90: 368
A91: EPS | B91: =(B73-B72)/B90 -> #REF! | C91: =(C73-C72)/C90 -> #REF! | D91: =(D73-D72)/D90 -> #REF! | E91: =(E73-E72)/E90 -> #DIV/0! | F91: =(F73-F72)/F90 -> #DIV/0! | G91: =(G73-G72)/G90 -> #DIV/0! | H91: =(H73-H72)/H90 -> #DIV/0! | I91: =(I73-I72)/I90 -> #DIV/0! | ... AE91: =(AE73-AE72)/AE90 -> -15.80864 | AI91: =(AI73-AI72)/AI90 -> 0.55763606 | AJ91: =(AJ73-AJ72)/AJ90 -> 2.3545418 | AK91: =(AK73-AK72)/AK90 -> -1.2451084 | AL91: =(AL73-AL72)/AL90 -> -0.81426705 | AM91: =(AM73-AM72)/AM90 -> 1.9098234 | AN91: =(AN73-AN72)/AN90 -> -2.1821238 | AO91: =(AO73-AO72)/AO90 -> 8.6148444 | AP91: =(AP73-AP72)/AP90 -> -2.3202157 | ... DB91: =(DB73-DB72)/DB90 -> 8.2841395 | DF91: 6.1261498
A92: DPS | B92: ='Annual Raw'!C110 -> 0 | C92: ='Annual Raw'!D110 -> 0 | D92: ='Annual Raw'!E110 -> 0 | E92: ='Annual Raw'!F110 -> 0 | F92: ='Annual Raw'!G110 -> 0 | G92: ='Annual Raw'!H110 -> 0 | H92: ='Annual Raw'!I110 -> 0 | I92: ='Annual Raw'!J110 -> 0 | ... AA92: ='Annual Raw'!AB110 -> 4
A93: DPS % of EPS | B93: =B92/B91 -> #REF! | C93: =C92/C91 -> #REF! | D93: =D92/D91 -> #REF! | E93: =E92/E91 -> #DIV/0! | F93: =F92/F91 -> #DIV/0! | G93: =G92/G91 -> #DIV/0! | H93: =H92/H91 -> #DIV/0! | I93: =I92/I91 -> #DIV/0! | ... AE93: =AE92/AE91 -> 0 | DF93: 0
A94: EPS TTM | B94: =+B91 -> #REF! | C94: =+C91 -> #REF! | D94: =+D91 -> #REF! | E94: =+E91 -> #DIV/0! | F94: =+F91 -> #DIV/0! | G94: =+G91 -> #DIV/0! | H94: =+H91 -> #DIV/0! | I94: =+I91 -> #DIV/0! | ... AE94: =+AE91 -> -15.80864 | AL94: =SUM(AI91:AL91) -> 0.85280244 | AM94: =SUM(AJ91:AM91) -> 2.2049898 | AN94: =SUM(AK91:AN91) -> -2.3316759 | AO94: =SUM(AL91:AO91) -> 7.5282769 | AP94: =SUM(AM91:AP91) -> 6.0223283 | AQ94: =SUM(AN91:AQ91) -> 5.1816649 | AR94: =SUM(AO91:AR91) -> 2.3513102 | AS94: =SUM(AP91:AS91) -> -12.833043 | ... DB94: =SUM(CY91:DB91) -> 25.892732 | DF94: 19.306211
A95: EPS Growth YoY % | C95: =+C94/B94-1 -> #REF! | D95: =+D94/C94-1 -> #REF! | E95: =+E94/D94-1 -> #DIV/0! | F95: =+F94/E94-1 -> #DIV/0! | G95: =+G94/F94-1 -> #DIV/0! | H95: =+H94/G94-1 -> #DIV/0! | I95: =+I94/H94-1 -> #DIV/0! | J95: =+J94/I94-1 -> #DIV/0! | ... AA95: =+AA94/Z94-1 -> -0.99986413 | AP95: =+IF(AL94<0,1-AP94/AL94,AP94/AL94-1) -> 6.0618094 | AQ95: =+IF(AM94<0,1-AQ94/AM94,AQ94/AM94-1) -> 1.3499723 | AR95: =+IF(AN94<0,1-AR94/AN94,AR94/AN94-1) -> 2.0084207 | AS95: =+IF(AO94<0,1-AS94/AO94,AS94/AO94-1) -> -2.7046455 | AT95: =+IF(AP94<0,1-AT94/AP94,AT94/AP94-1) -> -3.3081231 | AU95: =+IF(AQ94<0,1-AU94/AQ94,AU94/AQ94-1) -> -3.5715806 | AV95: =+IF(AR94<0,1-AV94/AR94,AV94/AR94-1) -> -4.9838305 | AW95: =+IF(AS94<0,1-AW94/AS94,AW94/AS94-1) -> 0.71849414 | ... DB95: =+IF(CX94<0,1-DB94/CX94,DB94/CX94-1) -> 0.10189895 | DF95: 0.64568252
A96: Bloomberg Estimate | CP96: 18.5 | CT96: 21.7 | CX96: 23.1
A97: Estimate deviation | CP97: =CP94/CP96-1 -> -0.033229146 | CT97: =CT94/CT96-1 -> -0.079306084 | CX97: =CX94/CX96-1 -> 0.017241634
A98: Promoter Share holding % | B98: ='Annual Raw'!C112 -> 0 | C98: ='Annual Raw'!D112 -> 0 | D98: ='Annual Raw'!E112 -> 0 | E98: ='Annual Raw'!F112 -> 0 | F98: ='Annual Raw'!G112 -> 0 | G98: ='Annual Raw'!H112 -> 0 | H98: ='Annual Raw'!I112 -> 0 | I98: ='Annual Raw'!J112 -> 0 | ... AA98: ='Annual Raw'!AB112 -> 42.56 | AI98: ='QTR Raw'!C49 -> 0 | AJ98: ='QTR Raw'!D49 -> 0 | AK98: ='QTR Raw'!E49 -> 0 | AL98: ='QTR Raw'!F49 -> 0 | AM98: ='QTR Raw'!G49 -> 0 | AN98: ='QTR Raw'!H49 -> 0 | AO98: ='QTR Raw'!I49 -> 0 | AP98: ='QTR Raw'!J49 -> 0 | ... CL98: ='QTR Raw'!BF49 -> 42.56
A99: Pledge Share % | B99: ='Annual Raw'!C113 -> 0 | C99: ='Annual Raw'!D113 -> 0 | D99: ='Annual Raw'!E113 -> 0 | E99: ='Annual Raw'!F113 -> 0 | F99: ='Annual Raw'!G113 -> 0 | G99: ='Annual Raw'!H113 -> 0 | H99: ='Annual Raw'!I113 -> 0 | I99: ='Annual Raw'!J113 -> 0 | ... AA99: ='Annual Raw'!AB113 -> 0 | AI99: ='QTR Raw'!C50 -> 0 | AJ99: ='QTR Raw'!D50 -> 0 | AK99: ='QTR Raw'!E50 -> 0 | AL99: ='QTR Raw'!F50 -> 0 | AM99: ='QTR Raw'!G50 -> 0 | AN99: ='QTR Raw'!H50 -> 0 | AO99: ='QTR Raw'!I50 -> 0 | AP99: ='QTR Raw'!J50 -> 0 | ... CL99: ='QTR Raw'!BF50 -> 0
A101: Share Price
A102: Share Price - Close | B102: ='Annual Raw'!C106 -> 0 | C102: ='Annual Raw'!D106 -> 0 | D102: ='Annual Raw'!E106 -> 0 | E102: ='Annual Raw'!F106 -> 0 | F102: ='Annual Raw'!G106 -> 0 | G102: ='Annual Raw'!H106 -> 0 | H102: ='Annual Raw'!I106 -> 0 | I102: ='Annual Raw'!J106 -> 0 | ... AA102: ='Annual Raw'!AB106 -> 394.6 | AB102: =+CP102 -> 374 | AC102: =+CT102 -> 374 | AD102: =+CX102 -> 374 | AE102: =+DB102 -> 374 | AJ102: ='QTR Share Price'!HP21 -> 0 | AK102: ='QTR Share Price'!HQ21 -> 0 | AL102: ='QTR Share Price'!HR21 -> 0 | AM102: ='QTR Share Price'!HS21 -> 0 | AN102: ='QTR Share Price'!HT21 -> 0 | AO102: ='QTR Share Price'!HU21 -> 0 | AP102: ='QTR Share Price'!HV21 -> 0 | AQ102: ='QTR Share Price'!HW21 -> 0 | ... CL102: ='QTR Share Price'!JR21 -> 394.6 | CM102: 374 | CN102: =+CM102 -> 374 | CO102: =+CN102 -> 374 | CP102: =+CO102 -> 374 | CQ102: =+CP102 -> 374 | CR102: =+CQ102 -> 374 | CS102: =+CR102 -> 374 | CT102: =+CS102 -> 374 | CU102: =+CT102 -> 374 | ... DB102: =+DA102 -> 374 | DF102: 356.95
A103: Share Price - High | B103: ='Annual Raw'!C107 -> 0 | C103: ='Annual Raw'!D107 -> 0 | D103: ='Annual Raw'!E107 -> 0 | E103: ='Annual Raw'!F107 -> 0 | F103: ='Annual Raw'!G107 -> 0 | G103: ='Annual Raw'!H107 -> 0 | H103: ='Annual Raw'!I107 -> 0 | I103: ='Annual Raw'!J107 -> 0 | ... AA103: ='Annual Raw'!AB107 -> 508.95 | AB103: =+MAX(CM103:CP103) -> 505.40649 | AC103: =+MAX(CQ103:CT103) -> 531.80928 | AD103: =+MAX(CU103:CX103) -> 625.48516 | AE103: =+MAX(CY103:DB103) -> 689.22145 | AJ103: ='QTR Share Price'!HP19 -> 0 | AK103: ='QTR Share Price'!HQ19 -> 0 | AL103: ='QTR Share Price'!HR19 -> 0 | AM103: ='QTR Share Price'!HS19 -> 0 | AN103: ='QTR Share Price'!HT19 -> 0 | AO103: ='QTR Share Price'!HU19 -> 0 | AP103: ='QTR Share Price'!HV19 -> 0 | AQ103: ='QTR Share Price'!HW19 -> 0 | ... CL103: ='QTR Share Price'!JR19 -> 508.95 | CM103: =+CM94*CM111 -> 494.71719 | CN103: =+CN94*CN111 -> 505.40649 | CO103: =+CO94*CO111 -> 487.50626 | CP103: =+CP94*CP111 -> 476.07589 | CQ103: =+CQ94*CQ111 -> 487.52608 | CR103: =+CR94*CR111 -> 497.32199 | CS103: =+CS94*CS111 -> 509.8172 | CT103: =+CT94*CT111 -> 531.80928 | ... DB103: =+DB94*DB111 -> 689.22145 | DF103: 368
A104: Share Price - Low | B104: ='Annual Raw'!C108 -> 0 | C104: ='Annual Raw'!D108 -> 0 | D104: ='Annual Raw'!E108 -> 0 | E104: ='Annual Raw'!F108 -> 0 | F104: ='Annual Raw'!G108 -> 0 | G104: ='Annual Raw'!H108 -> 0 | H104: ='Annual Raw'!I108 -> 0 | I104: ='Annual Raw'!J108 -> 0 | ... AA104: ='Annual Raw'!AB108 -> 306 | AB104: =+MIN(CM104:CP104) -> 363.92047 | AC104: =+MIN(CQ104:CT104) -> 372.67319 | AD104: =+MIN(CU104:CX104) -> 421.20346 | AE104: =+MIN(CY104:DB104) -> 486.40821 | AJ104: =+'QTR Share Price'!HP20 -> 0 | AK104: =+'QTR Share Price'!HQ20 -> 0 | AL104: =+'QTR Share Price'!HR20 -> 0 | AM104: =+'QTR Share Price'!HS20 -> 0 | AN104: =+'QTR Share Price'!HT20 -> 0 | AO104: =+'QTR Share Price'!HU20 -> 0 | AP104: =+'QTR Share Price'!HV20 -> 0 | AQ104: =+'QTR Share Price'!HW20 -> 0 | ... CL104: =+'QTR Share Price'!JR20 -> 389.05 | CM104: =+CM112*CM94 -> 378.1702 | CN104: =+CN112*CN94 -> 386.34128 | CO104: =+CO112*CO94 -> 372.65804 | CP104: =+CP112*CP94 -> 363.92047 | CQ104: =+CQ112*CQ94 -> 372.67319 | CR104: =+CR112*CR94 -> 380.16135 | CS104: =+CS112*CS94 -> 389.7129 | CT104: =+CT112*CT94 -> 406.52402 | ... DB104: =+DB112*DB94 -> 526.85255 | DF104: 306.3
A106: Upside (%) | AB106: =+AB103/AB102-1 -> 0.35135424 | AC106: =+AC103/AC102-1 -> 0.42194995 | AD106: =+AD103/AD102-1 -> 0.67242023 | AE106: =+AE103/AE102-1 -> 0.8428381 | CM106: =+CM103/CM102-1 -> 0.32277323 | CN106: =+CN103/CN102-1 -> 0.35135424 | CO106: =+CO103/CO102-1 -> 0.30349267 | CP106: =+CP103/CP102-1 -> 0.27293018 | CQ106: =+CQ103/CQ102-1 -> 0.30354566 | CR106: =+CR103/CR102-1 -> 0.32973795 | CS106: =+CS103/CS102-1 -> 0.36314759 | CT106: =+CT103/CT102-1 -> 0.42194995 | ... DB106: =+DB103/DB102-1 -> 0.8428381 | DF106: 0.030956717
A107: Downside (%) | AB107: =+AB104/AB102-1 -> -0.026950615 | AC107: =+AC104/AC102-1 -> -0.0035476185 | AD107: =+AD104/AD102-1 -> 0.12621247 | AE107: =+AE104/AE102-1 -> 0.30055672 | CM107: =+CM104/CM102-1 -> 0.01115026 | CN107: =+CN104/CN102-1 -> 0.032998068 | CO107: =+CO104/CO102-1 -> -0.0035881272 | CP107: =+CP104/CP102-1 -> -0.026950615 | CQ107: =+CQ104/CQ102-1 -> -0.0035476185 | CR107: =+CR104/CR102-1 -> 0.016474207 | CS107: =+CS104/CS102-1 -> 0.042013108 | CT107: =+CT104/CT102-1 -> 0.086962627 | ... DB107: =+DB104/DB102-1 -> 0.40869665 | DF107: -0.14189662
A109: PE
...

Sheet Monthly Nos Company
A1: Monthly Volume
A3: Month | B3: M& HCV | C3: LCV | D3: CV Export | E3: CV | G3: 3M Rolling' | H3: M& HCV | I3: LCV | J3: CV Export | K3: CV | M3: 3M YoY% | N3: M& HCV | O3: LCV | P3: CV Export | Q3: CV | S3: 12M Rolling | T3: M& HCV | U3: LCV | V3: CV Export | W3: CV | Y3: 12M YoY% | Z3: M& HCV | AA3: LCV | AB3: CV Export | AC3: CV
A4: 41000 | B4: 9829 | C4: 24818 | D4: 2213 | E4: =+C4+B4+D4 -> 36860
A5: =+EOMONTH(A4,1) -> 41060 | B5: 12451 | C5: 27174 | D5: 3752 | E5: =+C5+B5+D5 -> 43377
A6: =+EOMONTH(A5,1) -> 41090 | B6: 12663 | C6: 28363 | D6: 5371 | E6: =+C6+B6+D6 -> 46397 | H6: =+SUM(B4:B6) -> 34943 | I6: =+SUM(C4:C6) -> 80355 | J6: =+SUM(D4:D6) -> 11336 | K6: =+H6+I6+J6 -> 126634
A7: =+EOMONTH(A6,1) -> 41121 | B7: 12786 | C7: 29601 | D7: 4196 | E7: =+C7+B7+D7 -> 46583 | H7: =+SUM(B5:B7) -> 37900 | I7: =+SUM(C5:C7) -> 85138 | J7: =+SUM(D5:D7) -> 13319 | K7: =+H7+I7+J7 -> 136357
A8: =+EOMONTH(A7,1) -> 41152 | B8: 14681 | C8: 30461 | D8: 3603 | E8: =+C8+B8+D8 -> 48745 | H8: =+SUM(B6:B8) -> 40130 | I8: =+SUM(C6:C8) -> 88425 | J8: =+SUM(D6:D8) -> 13170 | K8: =+H8+I8+J8 -> 141725
A9: =+EOMONTH(A8,1) -> 41182 | B9: 15287 | C9: 33393 | D9: 4659 | E9: =+C9+B9+D9 -> 53339 | H9: =+SUM(B7:B9) -> 42754 | I9: =+SUM(C7:C9) -> 93455 | J9: =+SUM(D7:D9) -> 12458 | K9: =+H9+I9+J9 -> 148667
A10: =+EOMONTH(A9,1) -> 41213 | B10: 12120 | C10: 34905 | D10: 3378 | E10: =+C10+B10+D10 -> 50403 | H10: =+SUM(B8:B10) -> 42088 | I10: =+SUM(C8:C10) -> 98759 | J10: =+SUM(D8:D10) -> 11640 | K10: =+H10+I10+J10 -> 152487
A11: =+EOMONTH(A10,1) -> 41243 | B11: 9495 | C11: 34828 | D11: 3300 | E11: =+C11+B11+D11 -> 47623 | H11: =+SUM(B9:B11) -> 36902 | I11: =+SUM(C9:C11) -> 103126 | J11: =+SUM(D9:D11) -> 11337 | K11: =+H11+I11+J11 -> 151365
A12: =+EOMONTH(A11,1) -> 41274 | B12: 9866 | C12: 37649 | D12: 3424 | E12: =+C12+B12+D12 -> 50939 | H12: =+SUM(B10:B12) -> 31481 | I12: =+SUM(C10:C12) -> 107382 | J12: =+SUM(D10:D12) -> 10102 | K12: =+H12+I12+J12 -> 148965
A13: =+EOMONTH(A12,1) -> 41305 | B13: 8722 | C13: 33849 | D13: 3381 | E13: =+C13+B13+D13 -> 45952 | H13: =+SUM(B11:B13) -> 28083 | I13: =+SUM(C11:C13) -> 106326 | J13: =+SUM(D11:D13) -> 10105 | K13: =+H13+I13+J13 -> 144514
A14: =+EOMONTH(A13,1) -> 41333 | B14: 10629 | C14: 36760 | D14: 3432 | E14: =+C14+B14+D14 -> 50821 | H14: =+SUM(B12:B14) -> 29217 | I14: =+SUM(C12:C14) -> 108258 | J14: =+SUM(D12:D14) -> 10237 | K14: =+H14+I14+J14 -> 147712
A15: =+EOMONTH(A14,1) -> 41364 | B15: 14852 | C15: 41961 | D15: 2859 | E15: =+C15+B15+D15 -> 59672 | H15: =+SUM(B13:B15) -> 34203 | I15: =+SUM(C13:C15) -> 112570 | J15: =+SUM(D13:D15) -> 9672 | K15: =+H15+I15+J15 -> 156445 | T15: =+SUM(B4:B15) -> 143381 | U15: =+SUM(C4:C15) -> 393762 | V15: =+SUM(D4:D15) -> 43568 | W15: =+SUM(E4:E15) -> 580711
A16: =+EOMONTH(A15,1) -> 41394 | B16: 10002 | C16: 26023 | D16: 2737 | E16: =+C16+B16+D16 -> 38762 | H16: =+SUM(B14:B16) -> 35483 | I16: =+SUM(C14:C16) -> 104744 | J16: =+SUM(D14:D16) -> 9028 | K16: =+H16+I16+J16 -> 149255 | T16: =+SUM(B5:B16) -> 143554 | U16: =+SUM(C5:C16) -> 394967 | V16: =+SUM(D5:D16) -> 44092 | W16: =+SUM(E5:E16) -> 582613
A17: =+EOMONTH(A16,1) -> 41425 | B17: 10123 | C17: 24173 | D17: 3076 | E17: =+C17+B17+D17 -> 37372 | H17: =+SUM(B15:B17) -> 34977 | I17: =+SUM(C15:C17) -> 92157 | J17: =+SUM(D15:D17) -> 8672 | K17: =+H17+I17+J17 -> 135806 | T17: =+SUM(B6:B17) -> 141226 | U17: =+SUM(C6:C17) -> 391966 | V17: =+SUM(D6:D17) -> 43416 | W17: =+SUM(E6:E17) -> 576608
A18: =+EOMONTH(A17,1) -> 41455 | B18: 11130 | C18: 25778 | D18: 3455 | E18: =+C18+B18+D18 -> 40363 | H18: =+SUM(B16:B18) -> 31255 | I18: =+SUM(C16:C18) -> 75974 | J18: =+SUM(D16:D18) -> 9268 | K18: =+H18+I18+J18 -> 116497 | N18: =+H18/H6-1 -> -0.10554331 | O18: =+I18/I6-1 -> -0.054520565 | P18: =+J18/J6-1 -> -0.18242766 | Q18: =+K18/K6-1 -> -0.080049592 | T18: =+SUM(B7:B18) -> 139693 | U18: =+SUM(C7:C18) -> 389381 | V18: =+SUM(D7:D18) -> 41500 | W18: =+SUM(E7:E18) -> 570574
A19: =+EOMONTH(A18,1) -> 41486 | B19: 9758 | C19: 26609 | D19: 3579 | E19: =+C19+B19+D19 -> 39946 | H19: =+SUM(B17:B19) -> 31011 | I19: =+SUM(C17:C19) -> 76560 | J19: =+SUM(D17:D19) -> 10110 | K19: =+H19+I19+J19 -> 117681 | N19: =+H19/H7-1 -> -0.18176781 | O19: =+I19/I7-1 -> -0.10075407 | P19: =+J19/J7-1 -> -0.240934 | Q19: =+K19/K7-1 -> -0.136964 | T19: =+SUM(B8:B19) -> 136665 | U19: =+SUM(C8:C19) -> 386389 | V19: =+SUM(D8:D19) -> 40883 | W19: =+SUM(E8:E19) -> 563937
A20: =+EOMONTH(A19,1) -> 41517 | B20: 8249 | C20: 24904 | D20: 3879 | E20: =+C20+B20+D20 -> 37032 | H20: =+SUM(B18:B20) -> 29137 | I20: =+SUM(C18:C20) -> 77291 | J20: =+SUM(D18:D20) -> 10913 | K20: =+H20+I20+J20 -> 117341 | N20: =+H20/H8-1 -> -0.27393471 | O20: =+I20/I8-1 -> -0.12591462 | P20: =+J20/J8-1 -> -0.17137434 | Q20: =+K20/K8-1 -> -0.17205151 | T20: =+SUM(B9:B20) -> 130233 | U20: =+SUM(C9:C20) -> 380832 | V20: =+SUM(D9:D20) -> 41159 | W20: =+SUM(E9:E20) -> 552224
A21: =+EOMONTH(A20,1) -> 41547 | B21: 8815 | C21: 24304 | D21: 4659 | E21: =+C21+B21+D21 -> 37778 | H21: =+SUM(B19:B21) -> 26822 | I21: =+SUM(C19:C21) -> 75817 | J21: =+SUM(D19:D21) -> 12117 | K21: =+H21+I21+J21 -> 114756 | N21: =+H21/H9-1 -> -0.3726435 | O21: =+I21/I9-1 -> -0.18873255 | P21: =+J21/J9-1 -> -0.02737197 | Q21: =+K21/K9-1 -> -0.22810039 | T21: =+SUM(B10:B21) -> 123761 | U21: =+SUM(C10:C21) -> 371743 | V21: =+SUM(D10:D21) -> 41159 | W21: =+SUM(E10:E21) -> 536663
A22: =+EOMONTH(A21,1) -> 41578 | B22: 7935 | C22: 24858 | D22: 4188 | E22: =+C22+B22+D22 -> 36981 | H22: =+SUM(B20:B22) -> 24999 | I22: =+SUM(C20:C22) -> 74066 | J22: =+SUM(D20:D22) -> 12726 | K22: =+H22+I22+J22 -> 111791 | N22: =+H22/H10-1 -> -0.40603022 | O22: =+I22/I10-1 -> -0.25003291 | P22: =+J22/J10-1 -> 0.093298969 | Q22: =+K22/K10-1 -> -0.26688177 | T22: =+SUM(B11:B22) -> 119576 | U22: =+SUM(C11:C22) -> 361696 | V22: =+SUM(D11:D22) -> 41969 | W22: =+SUM(E11:E22) -> 523241
A23: =+EOMONTH(A22,1) -> 41608 | B23: 6823 | C23: 19993 | D23: 3300 | E23: =+C23+B23+D23 -> 30116 | H23: =+SUM(B21:B23) -> 23573 | I23: =+SUM(C21:C23) -> 69155 | J23: =+SUM(D21:D23) -> 12147 | K23: =+H23+I23+J23 -> 104875 | N23: =+H23/H11-1 -> -0.36119993 | O23: =+I23/I11-1 -> -0.32941256 | P23: =+J23/J11-1 -> 0.071447473 | Q23: =+K23/K11-1 -> -0.30713837 | T23: =+SUM(B12:B23) -> 116904 | U23: =+SUM(C12:C23) -> 346861 | V23: =+SUM(D12:D23) -> 41969 | W23: =+SUM(E12:E23) -> 505734
A24: =+EOMONTH(A23,1) -> 41639 | B24: 7659 | C24: 18079 | D24: 2621 | E24: =+C24+B24+D24 -> 28359 | H24: =+SUM(B22:B24) -> 22417 | I24: =+SUM(C22:C24) -> 62930 | J24: =+SUM(D22:D24) -> 10109 | K24: =+H24+I24+J24 -> 95456 | N24: =+H24/H12-1 -> -0.2879197 | O24: =+I24/I12-1 -> -0.41396137 | P24: =+J24/J12-1 -> 0.00069293209 | Q24: =+K24/K12-1 -> -0.35920518 | T24: =+SUM(B13:B24) -> 114697 | U24: =+SUM(C13:C24) -> 327291 | V24: =+SUM(D13:D24) -> 41166 | W24: =+SUM(E13:E24) -> 483154
A25: =+EOMONTH(A24,1) -> 41670 | B25: 8166 | C25: 17517 | D25: 3387 | E25: =+C25+B25+D25 -> 29070 | H25: =+SUM(B23:B25) -> 22648 | I25: =+SUM(C23:C25) -> 55589 | J25: =+SUM(D23:D25) -> 9308 | K25: =+H25+I25+J25 -> 87545 | N25: =+H25/H13-1 -> -0.19353345 | O25: =+I25/I13-1 -> -0.47718338 | P25: =+J25/J13-1 -> -0.078871846 | Q25: =+K25/K13-1 -> -0.39421094 | T25: =+SUM(B14:B25) -> 114141 | U25: =+SUM(C14:C25) -> 310959 | V25: =+SUM(D14:D25) -> 41172 | W25: =+SUM(E14:E25) -> 466272
A26: =+EOMONTH(A25,1) -> 41698 | B26: 9109 | C26: 14881 | D26: 4197 | E26: =+C26+B26+D26 -> 28187 | H26: =+SUM(B24:B26) -> 24934 | I26: =+SUM(C24:C26) -> 50477 | J26: =+SUM(D24:D26) -> 10205 | K26: =+H26+I26+J26 -> 85616 | N26: =+H26/H14-1 -> -0.14659274 | O26: =+I26/I14-1 -> -0.53373423 | P26: =+J26/J14-1 -> -0.0031259158 | Q26: =+K26/K14-1 -> -0.42038562 | T26: =+SUM(B15:B26) -> 112621 | U26: =+SUM(C15:C26) -> 289080 | V26: =+SUM(D15:D26) -> 41937 | W26: =+SUM(E15:E26) -> 443638
A27: =+EOMONTH(A26,1) -> 41729 | B27: 12418 | C27: 20938 | D27: 2859 | E27: =+C27+B27+D27 -> 36215 | H27: =+SUM(B25:B27) -> 29693 | I27: =+SUM(C25:C27) -> 53336 | J27: =+SUM(D25:D27) -> 10443 | K27: =+H27+I27+J27 -> 93472 | N27: =+H27/H15-1 -> -0.13185978 | O27: =+I27/I15-1 -> -0.52619703 | P27: =+J27/J15-1 -> 0.07971464 | Q27: =+K27/K15-1 -> -0.40252485 | T27: =+SUM(B16:B27) -> 110187 | U27: =+SUM(C16:C27) -> 268057 | V27: =+SUM(D16:D27) -> 41937 | W27: =+SUM(E16:E27) -> 420181 | Z27: =+T27/T15-1 -> -0.23150906 | AA27: =+U27/U15-1 -> -0.31924106 | AB27: =+V27/V15-1 -> -0.037435733 | AC27: =+W27/W15-1 -> -0.27643699
A28: =+EOMONTH(A27,1) -> 41759 | B28: 8425 | C28: 14804 | D28: 2828 | E28: =+C28+B28+D28 -> 26057 | H28: =+SUM(B26:B28) -> 29952 | I28: =+SUM(C26:C28) -> 50623 | J28: =+SUM(D26:D28) -> 9884 | K28: =+H28+I28+J28 -> 90459 | N28: =+H28/H16-1 -> -0.15587746 | O28: =+I28/I16-1 -> -0.51669785 | P28: =+J28/J16-1 -> 0.094816128 | Q28: =+K28/K16-1 -> -0.39392985 | T28: =+SUM(B17:B28) -> 108610 | U28: =+SUM(C17:C28) -> 256838 | V28: =+SUM(D17:D28) -> 42028 | W28: =+SUM(E17:E28) -> 407476 | Z28: =+T28/T16-1 -> -0.24342059 | AA28: =+U28/U16-1 -> -0.34972289 | AB28: =+V28/V16-1 -> -0.046811213 | AC28: =+W28/W16-1 -> -0.30060606
A29: =+EOMONTH(A28,1) -> 41790 | B29: 9113 | C29: 15991 | D29: 3005 | E29: =+C29+B29+D29 -> 28109 | H29: =+SUM(B27:B29) -> 29956 | I29: =+SUM(C27:C29) -> 51733 | J29: =+SUM(D27:D29) -> 8692 | K29: =+H29+I29+J29 -> 90381 | N29: =+H29/H17-1 -> -0.14355148 | O29: =+I29/I17-1 -> -0.43864275 | P29: =+J29/J17-1 -> 0.0023062731 | Q29: =+K29/K17-1 -> -0.33448449 | T29: =+SUM(B18:B29) -> 107600 | U29: =+SUM(C18:C29) -> 248656 | V29: =+SUM(D18:D29) -> 41957 | W29: =+SUM(E18:E29) -> 398213 | Z29: =+T29/T17-1 -> -0.23810063 | AA29: =+U29/U17-1 -> -0.36561845 | AB29: =+V29/V17-1 -> -0.033605123 | AC29: =+W29/W17-1 -> -0.30938697
A30: =+EOMONTH(A29,1) -> 41820 | B30: 9620 | C30: 17212 | D30: 3507 | E30: =+C30+B30+D30 -> 30339 | H30: =+SUM(B28:B30) -> 27158 | I30: =+SUM(C28:C30) -> 48007 | J30: =+SUM(D28:D30) -> 9340 | K30: =+H30+I30+J30 -> 84505 | N30: =+H30/H18-1 -> -0.13108303 | O30: =+I30/I18-1 -> -0.36811278 | P30: =+J30/J18-1 -> 0.0077686664 | Q30: =+K30/K18-1 -> -0.27461651 | T30: =+SUM(B19:B30) -> 106090 | U30: =+SUM(C19:C30) -> 240090 | V30: =+SUM(D19:D30) -> 42009 | W30: =+SUM(E19:E30) -> 388189 | Z30: =+T30/T18-1 -> -0.24054892 | AA30: =+U30/U18-1 -> -0.38340597 | AB30: =+V30/V18-1 -> 0.01226506 | AC30: =+W30/W18-1 -> -0.31965179
A31: =+EOMONTH(A30,1) -> 41851 | B31: 9725 | C31: 16364 | D31: 3996 | E31: =+C31+B31+D31 -> 30085 | H31: =+SUM(B29:B31) -> 28458 | I31: =+SUM(C29:C31) -> 49567 | J31: =+SUM(D29:D31) -> 10508 | K31: =+H31+I31+J31 -> 88533 | N31: =+H31/H19-1 -> -0.082325626 | O31: =+I31/I19-1 -> -0.35257315 | P31: =+J31/J19-1 -> 0.039366963 | Q31: =+K31/K19-1 -> -0.24768654 | T31: =+SUM(B20:B31) -> 106057 | U31: =+SUM(C20:C31) -> 229845 | V31: =+SUM(D20:D31) -> 42426 | W31: =+SUM(E20:E31) -> 378328 | Z31: =+T31/T19-1 -> -0.22396371 | AA31: =+U31/U19-1 -> -0.40514611 | AB31: =+V31/V19-1 -> 0.037741849 | AC31: =+W31/W19-1 -> -0.32913074
A32: =+EOMONTH(A31,1) -> 41882 | B32: 9141 | C32: 16287 | D32: 4117 | E32: =+C32+B32+D32 -> 29545 | H32: =+SUM(B30:B32) -> 28486 | I32: =+SUM(C30:C32) -> 49863 | J32: =+SUM(D30:D32) -> 11620 | K32: =+H32+I32+J32 -> 89969 | N32: =+H32/H20-1 -> -0.022342726 | O32: =+I32/I20-1 -> -0.35486667 | P32: =+J32/J20-1 -> 0.064785119 | Q32: =+K32/K20-1 -> -0.23326885 | T32: =+SUM(B21:B32) -> 106949 | U32: =+SUM(C21:C32) -> 221228 | V32: =+SUM(D21:D32) -> 42664 | W32: =+SUM(E21:E32) -> 370841 | Z32: =+T32/T20-1 -> -0.17878725 | AA32: =+U32/U20-1 -> -0.41909293 | AB32: =+V32/V20-1 -> 0.036565514 | AC32: =+W32/W20-1 -> -0.3284591
A33: =+EOMONTH(A32,1) -> 41912 | B33: 10404 | C33: 18539 | D33: 4849 | E33: =+C33+B33+D33 -> 33792 | H33: =+SUM(B31:B33) -> 29270 | I33: =+SUM(C31:C33) -> 51190 | J33: =+SUM(D31:D33) -> 12962 | K33: =+H33+I33+J33 -> 93422 | N33: =+H33/H21-1 -> 0.091268362 | O33: =+I33/I21-1 -> -0.32482161 | P33: =+J33/J21-1 -> 0.069736734 | Q33: =+K33/K21-1 -> -0.18590749 | T33: =+SUM(B22:B33) -> 108538 | U33: =+SUM(C22:C33) -> 215463 | V33: =+SUM(D22:D33) -> 42854 | W33: =+SUM(E22:E33) -> 366855 | Z33: =+T33/T21-1 -> -0.12300321 | AA33: =+U33/U21-1 -> -0.42039796 | AB33: =+V33/V21-1 -> 0.041181759 | AC33: =+W33/W21-1 -> -0.31641458
A34: =+EOMONTH(A33,1) -> 41943 | B34: 10352 | C34: 16897 | D34: 3780 | E34: =+C34+B34+D34 -> 31029 | H34: =+SUM(B32:B34) -> 29897 | I34: =+SUM(C32:C34) -> 51723 | J34: =+SUM(D32:D34) -> 12746 | K34: =+H34+I34+J34 -> 94366 | N34: =+H34/H22-1 -> 0.19592784 | O34: =+I34/I22-1 -> -0.30166338 | P34: =+J34/J22-1 -> 0.0015715857 | Q34: =+K34/K22-1 -> -0.15587122 | T34: =+SUM(B23:B34) -> 110955 | U34: =+SUM(C23:C34) -> 207502 | V34: =+SUM(D23:D34) -> 42446 | W34: =+SUM(E23:E34) -> 360903 | Z34: =+T34/T22-1 -> -0.072096407 | AA34: =+U34/U22-1 -> -0.42630828 | AB34: =+V34/V22-1 -> 0.011365532 | AC34: =+W34/W22-1 -> -0.31025474
A35: =+EOMONTH(A34,1) -> 41973 | B35: 9452 | C35: 15954 | D35: 3959 | E35: =+C35+B35+D35 -> 29365 | H35: =+SUM(B33:B35) -> 30208 | I35: =+SUM(C33:C35) -> 51390 | J35: =+SUM(D33:D35) -> 12588 | K35: =+H35+I35+J35 -> 94186 | N35: =+H35/H23-1 -> 0.28146608 | O35: =+I35/I23-1 -> -0.2568867 | P35: =+J35/J23-1 -> 0.036305261 | Q35: =+K35/K23-1 -> -0.10192133 | T35: =+SUM(B24:B35) -> 113584 | U35: =+SUM(C24:C35) -> 203463 | V35: =+SUM(D24:D35) -> 43105 | W35: =+SUM(E24:E35) -> 360152 | Z35: =+T35/T23-1 -> -0.02839937 | AA35: =+U35/U23-1 -> -0.41341633 | AB35: =+V35/V23-1 -> 0.027067598 | AC35: =+W35/W23-1 -> -0.28786279
A36: =+EOMONTH(A35,1) -> 42004 | B36: 12438 | C36: 13298 | D36: 3815 | E36: =+C36+B36+D36 -> 29551 | H36: =+SUM(B34:B36) -> 32242 | I36: =+SUM(C34:C36) -> 46149 | J36: =+SUM(D34:D36) -> 11554 | K36: =+H36+I36+J36 -> 89945 | N36: =+H36/H24-1 -> 0.43828345 | O36: =+I36/I24-1 -> -0.26666137 | P36: =+J36/J24-1 -> 0.14294193 | Q36: =+K36/K24-1 -> -0.057733406 | T36: =+SUM(B25:B36) -> 118363 | U36: =+SUM(C25:C36) -> 198682 | V36: =+SUM(D25:D36) -> 44299 | W36: =+SUM(E25:E36) -> 361344 | Z36: =+T36/T24-1 -> 0.031962475 | AA36: =+U36/U24-1 -> -0.39295 | AB36: =+V36/V24-1 -> 0.076106496 | AC36: =+W36/W24-1 -> -0.25211423
A37: =+EOMONTH(A36,1) -> 42035 | B37: 11273 | C37: 14301 | D37: 3714 | E37: =+C37+B37+D37 -> 29288 | H37: =+SUM(B35:B37) -> 33163 | I37: =+SUM(C35:C37) -> 43553 | J37: =+SUM(D35:D37) -> 11488 | K37: =+H37+I37+J37 -> 88204 | N37: =+H37/H25-1 -> 0.46427941 | O37: =+I37/I25-1 -> -0.21651766 | P37: =+J37/J25-1 -> 0.23420713 | Q37: =+K37/K25-1 -> 0.0075275573 | T37: =+SUM(B26:B37) -> 121470 | U37: =+SUM(C26:C37) -> 195466 | V37: =+SUM(D26:D37) -> 44626 | W37: =+SUM(E26:E37) -> 361562 | Z37: =+T37/T25-1 -> 0.064210056 | AA37: =+U37/U25-1 -> -0.37140909 | AB37: =+V37/V25-1 -> 0.083891965 | AC37: =+W37/W25-1 -> -0.22456849
A38: =+EOMONTH(A37,1) -> 42063 | B38: 12190 | C38: 14357 | D38: 3726 | E38: =+C38+B38+D38 -> 30273 | H38: =+SUM(B36:B38) -> 35901 | I38: =+SUM(C36:C38) -> 41956 | J38: =+SUM(D36:D38) -> 11255 | K38: =+H38+I38+J38 -> 89112 | N38: =+H38/H26-1 -> 0.43984118 | O38: =+I38/I26-1 -> -0.16880956 | P38: =+J38/J26-1 -> 0.10289074 | Q38: =+K38/K26-1 -> 0.040833489 | T38: =+SUM(B27:B38) -> 124551 | U38: =+SUM(C27:C38) -> 194942 | V38: =+SUM(D27:D38) -> 44155 | W38: =+SUM(E27:E38) -> 363648 | Z38: =+T38/T26-1 -> 0.10593051 | AA38: =+U38/U26-1 -> -0.32564688 | AB38: =+V38/V26-1 -> 0.052888857 | AC38: =+W38/W26-1 -> -0.18030466
... A99: =+EOMONTH(A98,1) -> 43921 | B99: 2819 | C99: 2517 | D99: 1787 | E99: =+C99+B99+D99 -> 7123 | H99: =+SUM(B97:B99) -> 23849 | I99: =+SUM(C97:C99) -> 38407 | J99: =+SUM(D97:D99) -> 6813 | K99: =+H99+I99+J99 -> 69069 | N99: =+H99/H87-1 -> -0.55017164 | O99: =+I99/I87-1 -> -0.48167991 | P99: =+J99/J87-1 -> -0.40632625 | Q99: =+K99/K87-1 -> -0.5016415 | T99: =+SUM(B88:B99) -> 111752 | U99: =+SUM(C88:C99) -> 198409 | V99: =+SUM(D88:D99) -> 29792 | W99: =+SUM(E88:E99) -> 339953 | Z99: =+T99/T87-1 -> -0.42626258 | AA99: =+U99/U87-1 -> -0.27564957 | AB99: =+V99/V87-1 -> -0.41681511 | AC99: =+W99/W87-1 -> -0.34596375
A100: =+EOMONTH(A99,1) -> 43951 | B100: 3000 | C100: 3000 | E100: =+C100+B100+D100 -> 6000 | H100: =+SUM(B98:B100) -> 15924 | I100: =+SUM(C98:C100) -> 20984 | J100: =+SUM(D98:D100) -> 4301 | K100: =+H100+I100+J100 -> 41209 | N100: =+H100/H88-1 -> -0.67901633 | O100: =+I100/I88-1 -> -0.69853607 | P100: =+J100/J88-1 -> -0.55600289 | Q100: =+K100/K88-1 -> -0.68031248 | T100: =+SUM(B89:B100) -> 102581 | U100: =+SUM(C89:C100) -> 184391 | V100: =+SUM(D89:D100) -> 28495 | W100: =+SUM(E89:E100) -> 315467 | Z100: =+T100/T88-1 -> -0.46117764 | AA100: =+U100/U88-1 -> -0.32015485 | AB100: =+V100/V88-1 -> -0.42401763 | AC100: =+W100/W88-1 -> -0.38274076
A101: =+EOMONTH(A100,1) -> 43982 | B101: 3000 | C101: 3000 | E101: =+C101+B101+D101 -> 6000 | H101: =+SUM(B99:B101) -> 8819 | I101: =+SUM(C99:C101) -> 8517 | J101: =+SUM(D99:D101) -> 1787 | K101: =+H101+I101+J101 -> 19123 | N101: =+H101/H89-1 -> -0.80143201 | O101: =+I101/I89-1 -> -0.86901356 | P101: =+J101/J89-1 -> -0.78700834 | Q101: =+K101/K89-1 -> -0.83769998 | T101: =+SUM(B90:B101) -> 94472 | U101: =+SUM(C90:C101) -> 169171 | V101: =+SUM(D90:D101) -> 27021 | W101: =+SUM(E90:E101) -> 290664 | Z101: =+T101/T89-1 -> -0.49120794 | AA101: =+U101/U89-1 -> -0.36982071 | AB101: =+V101/V89-1 -> -0.42904535 | AC101: =+W101/W89-1 -> -0.4203576
A102: =+EOMONTH(A101,1) -> 44012 | B102: 2862 | C102: 5106 | D102: =+I101-H101 -> -302 | E102: =+C102+B102+D102 -> 7666 | H102: =+SUM(B100:B102) -> 8862 | I102: =+SUM(C100:C102) -> 11106 | J102: =+SUM(D100:D102) -> -302 | K102: =+H102+I102+J102 -> 19666 | N102: =+H102/H90-1 -> -0.75717887 | O102: =+I102/I90-1 -> -0.80766833 | P102: =+J102/J90-1 -> -1.0562384 | Q102: =+K102/K90-1 -> -0.80257002 | T102: =+SUM(B91:B102) -> 84118 | U102: =+SUM(C91:C102) -> 151771 | V102: =+SUM(D91:D102) -> 24120 | W102: =+SUM(E91:E102) -> 260009 | Z102: =+T102/T90-1 -> -0.5424789 | AA102: =+U102/U90-1 -> -0.43249175 | AB102: =+V102/V90-1 -> -0.46259079 | AC102: =+W102/W90-1 -> -0.47597003
A103: =+EOMONTH(A102,1) -> 44043 | B103: 3725 | C103: 8287 | D103: 676 | E103: =+C103+B103+D103 -> 12688 | H103: =+SUM(B101:B103) -> 9587 | I103: =+SUM(C101:C103) -> 16393 | J103: =+SUM(D101:D103) -> 374 | K103: =+H103+I103+J103 -> 26354 | N103: =+H103/H91-1 -> -0.70483374 | O103: =+I103/I91-1 -> -0.70207546 | P103: =+J103/J91-1 -> -0.94864754 | Q103: =+K103/K91-1 -> -0.72196609 | T103: =+SUM(B92:B103) -> 79688 | U103: =+SUM(C92:C103) -> 145760 | V103: =+SUM(D92:D103) -> 21586 | W103: =+SUM(E92:E103) -> 247034 | Z103: =+T103/T91-1 -> -0.55425036 | AA103: =+U103/U91-1 -> -0.43971432 | AB103: =+V103/V91-1 -> -0.50068238 | AC103: =+W103/W91-1 -> -0.48764821
A104: =+EOMONTH(A103,1) -> 44074 | B104: 5467 | C104: 11370 | D104: 1052 | E104: =+C104+B104+D104 -> 17889 | H104: =+SUM(B102:B104) -> 12054 | I104: =+SUM(C102:C104) -> 24763 | J104: =+SUM(D102:D104) -> 1426 | K104: =+H104+I104+J104 -> 38243 | N104: =+H104/H92-1 -> -0.58848832 | O104: =+I104/I92-1 -> -0.51164533 | P104: =+J104/J92-1 -> -0.83877897 | Q104: =+K104/K92-1 -> -0.56954887 | T104: =+SUM(B93:B104) -> 77234 | U104: =+SUM(C93:C104) -> 143227 | V104: =+SUM(D93:D104) -> 19602 | W104: =+SUM(E93:E104) -> 240063 | Z104: =+T104/T92-1 -> -0.54616289 | AA104: =+U104/U92-1 -> -0.42871673 | AB104: =+V104/V92-1 -> -0.52235678 | AC104: =+W104/W92-1 -> -0.48030438
A105: =+EOMONTH(A104,1) -> 44104 | B105: 8723 | C105: 14522 | D105: 1665 | E105: =+C105+B105+D105 -> 24910 | H105: =+SUM(B103:B105) -> 17915 | I105: =+SUM(C103:C105) -> 34179 | J105: =+SUM(D103:D105) -> 3393 | K105: =+H105+I105+J105 -> 55487 | N105: =+H105/H93-1 -> -0.24875246 | O105: =+I105/I93-1 -> -0.23552305 | P105: =+J105/J93-1 -> -0.66225363 | Q105: =+K105/K93-1 -> -0.29407649 | T105: =+SUM(B94:B105) -> 78186 | U105: =+SUM(C94:C105) -> 141241 | V105: =+SUM(D94:D105) -> 17467 | W105: =+SUM(E94:E105) -> 236894 | Z105: =+T105/T93-1 -> -0.50674405 | AA105: =+U105/U93-1 -> -0.41269736 | AB105: =+V105/V93-1 -> -0.55879158 | AC105: =+W105/W93-1 -> -0.45987369
A106: =+EOMONTH(A105,1) -> 44135 | B106: 9319 | C106: 16733 | D106: 2420 | E106: =+C106+B106+D106 -> 28472 | H106: =+SUM(B104:B106) -> 23509 | I106: =+SUM(C104:C106) -> 42625 | J106: =+SUM(D104:D106) -> 5137 | K106: =+H106+I106+J106 -> 71271 | N106: =+H106/H94-1 -> 0.0037144565 | O106: =+I106/I94-1 -> -0.12409584 | P106: =+J106/J94-1 -> -0.41987578 | Q106: =+K106/K94-1 -> -0.11946974 | T106: =+SUM(B95:B106) -> 79775 | U106: =+SUM(C95:C106) -> 139721 | V106: =+SUM(D95:D106) -> 17868 | W106: =+SUM(E95:E106) -> 237364 | Z106: =+T106/T94-1 -> -0.46643793 | AA106: =+U106/U94-1 -> -0.40808727 | AB106: =+V106/V94-1 -> -0.51987102 | AC106: =+W106/W94-1 -> -0.43856246
A107: =+EOMONTH(A106,1) -> 44165 | B107: 10409 | C107: 15809 | D107: 1764 | E107: =+C107+B107+D107 -> 27982 | H107: =+SUM(B105:B107) -> 28451 | I107: =+SUM(C105:C107) -> 47064 | J107: =+SUM(D105:D107) -> 5849 | K107: =+H107+I107+J107 -> 81364 | N107: =+H107/H95-1 -> 0.16712475 | O107: =+I107/I95-1 -> -0.12098913 | P107: =+J107/J95-1 -> -0.33154286 | Q107: =+K107/K95-1 -> -0.061209891 | T107: =+SUM(B96:B107) -> 81308 | U107: =+SUM(C96:C107) -> 136749 | V107: =+SUM(D96:D107) -> 16701 | W107: =+SUM(E96:E107) -> 234758 | Z107: =+T107/T95-1 -> -0.44058619 | AA107: =+U107/U95-1 -> -0.41656996 | AB107: =+V107/V95-1 -> -0.53188329 | AC107: =+W107/W95-1 -> -0.43487639
A108: =+EOMONTH(A107,1) -> 44196 | B108: 13747 | C108: 16138 | D108: 2984 | E108: =+C108+B108+D108 -> 32869 | H108: =+SUM(B106:B108) -> 33475 | I108: =+SUM(C106:C108) -> 48680 | J108: =+SUM(D106:D108) -> 7168 | K108: =+H108+I108+J108 -> 89323 | N108: =+H108/H96-1 -> 0.21462264 | O108: =+I108/I96-1 -> -0.15411215 | P108: =+J108/J96-1 -> -0.052227952 | Q108: =+K108/K96-1 -> -0.036138208 | T108: =+SUM(B97:B108) -> 84101 | U108: =+SUM(C97:C108) -> 132372 | V108: =+SUM(D97:D108) -> 17072 | W108: =+SUM(E97:E108) -> 233545 | Z108: =+T108/T96-1 -> -0.40320463 | AA108: =+U108/U96-1 -> -0.43455175 | AB108: =+V108/V96-1 -> -0.50451313 | AC108: =+W108/W96-1 -> -0.42965051
A109: =+EOMONTH(A108,1) -> 44227 | B109: 14378 | C109: 16386 | D109: 2145 | E109: =+C109+B109+D109 -> 32909 | H109: =+SUM(B107:B109) -> 38534 | I109: =+SUM(C107:C109) -> 48333 | J109: =+SUM(D107:D109) -> 6893 | K109: =+H109+I109+J109 -> 93760 | N109: =+H109/H97-1 -> 0.25293448 | O109: =+I109/I97-1 -> -0.19065959 | P109: =+J109/J97-1 -> -0.14436445 | Q109: =+K109/K97-1 -> -0.048411651 | T109: =+SUM(B98:B109) -> 87554 | U109: =+SUM(C98:C109) -> 128335 | V109: =+SUM(D98:D109) -> 16705 | W109: =+SUM(E98:E109) -> 232594 | Z109: =+T109/T97-1 -> -0.357482 | AA109: =+U109/U97-1 -> -0.4492391 | AB109: =+V109/V97-1 -> -0.5069508 | AC109: =+W109/W97-1 -> -0.42307559
A110: =+EOMONTH(A109,1) -> 44255 | B110: 15535 | C110: 15606 | D110: 2718 | E110: =+C110+B110+D110 -> 33859 | H110: =+SUM(B108:B110) -> 43660 | I110: =+SUM(C108:C110) -> 48130 | J110: =+SUM(D108:D110) -> 7847 | K110: =+H110+I110+J110 -> 99637 | N110: =+H110/H98-1 -> 0.36505753 | O110: =+I110/I98-1 -> -0.14670685 | P110: =+J110/J98-1 -> 0.027228695 | Q110: =+K110/K98-1 -> 0.037582788 | T110: =+SUM(B99:B110) -> 92984 | U110: =+SUM(C99:C110) -> 128474 | V110: =+SUM(D99:D110) -> 16909 | W110: =+SUM(E99:E110) -> 238367 | Z110: =+T110/T98-1 -> -0.28510141 | AA110: =+U110/U98-1 -> -0.43071483 | AB110: =+V110/V98-1 -> -0.49711516 | AC110: =+W110/W98-1 -> -0.38780736
A111: =+EOMONTH(A110,1) -> 44286 | B111: 19702 | C111: 17253 | D111: 3654 | E111: =+C111+B111+D111 -> 40609 | H111: =+SUM(B109:B111) -> 49615 | I111: =+SUM(C109:C111) -> 49245 | J111: =+SUM(D109:D111) -> 8517 | K111: =+H111+I111+J111 -> 107377 | N111: =+H111/H99-1 -> 1.0803807 | O111: =+I111/I99-1 -> 0.28218814 | P111: =+J111/J99-1 -> 0.25011008 | Q111: =+K111/K99-1 -> 0.55463377 | T111: =+SUM(B100:B111) -> 109867 | U111: =+SUM(C100:C111) -> 143210 | V111: =+SUM(D100:D111) -> 18776 | W111: =+SUM(E100:E111) -> 271853 | Z111: =+T111/T99-1 -> -0.016867707 | AA111: =+U111/U99-1 -> -0.27820815 | AB111: =+V111/V99-1 -> -0.36976369 | AC111: =+W111/W99-1 -> -0.20032181
A112: =+EOMONTH(A111,1) -> 44316 | B112: 7505 | C112: 6930 | D112: 2209 | E112: =+C112+B112+D112 -> 16644 | H112: =+SUM(B110:B112) -> 42742 | I112: =+SUM(C110:C112) -> 39789 | J112: =+SUM(D110:D112) -> 8581 | K112: =+H112+I112+J112 -> 91112 | N112: =+H112/H100-1 -> 1.6841246 | O112: =+I112/I100-1 -> 0.89615898 | P112: =+J112/J100-1 -> 0.99511741 | Q112: =+K112/K100-1 -> 1.2109733 | T112: =+SUM(B101:B112) -> 114372 | U112: =+SUM(C101:C112) -> 147140 | V112: =+SUM(D101:D112) -> 20985 | W112: =+SUM(E101:E112) -> 282497 | Z112: =+T112/T100-1 -> 0.11494331 | AA112: =+U112/U100-1 -> -0.20202179 | AB112: =+V112/V100-1 -> -0.26355501 | AC112: =+W112/W100-1 -> -0.10451172
A113: =+EOMONTH(A112,1) -> 44347 | B113: 4238 | C113: 5133 | D113: 2030 | E113: =+C113+B113+D113 -> 11401 | H113: =+SUM(B111:B113) -> 31445 | I113: =+SUM(C111:C113) -> 29316 | J113: =+SUM(D111:D113) -> 7893 | K113: =+H113+I113+J113 -> 68654 | N113: =+H113/H101-1 -> 2.565597 | O113: =+I113/I101-1 -> 2.4420571 | P113: =+J113/J101-1 -> 3.4168998 | Q113: =+K113/K101-1 -> 2.5901271 | T113: =+SUM(B102:B113) -> 115610 | U113: =+SUM(C102:C113) -> 149273 | V113: =+SUM(D102:D113) -> 23015 | W113: =+SUM(E102:E113) -> 287898 | Z113: =+T113/T101-1 -> 0.22374884 | AA113: =+U113/U101-1 -> -0.11762063 | AB113: =+V113/V101-1 -> -0.14825506 | AC113: =+W113/W101-1 -> -0.0095161423
A114: =+EOMONTH(A113,1) -> 44377 | B114: 8971 | C114: 10623 | D114: 2506 | E114: =+C114+B114+D114 -> 22100 | H114: =+SUM(B112:B114) -> 20714 | I114: =+SUM(C112:C114) -> 22686 | J114: =+SUM(D112:D114) -> 6745 | K114: =+H114+I114+J114 -> 50145 | N114: =+H114/H102-1 -> 1.3373956 | O114: =+I114/I102-1 -> 1.0426796 | P114: =+J114/J102-1 -> -23.334437 | Q114: =+K114/K102-1 -> 1.5498322 | T114: =+SUM(B103:B114) -> 121719 | U114: =+SUM(C103:C114) -> 154790 | V114: =+SUM(D103:D114) -> 25823 | W114: =+SUM(E103:E114) -> 302332 | Z114: =+T114/T102-1 -> 0.44700302 | AA114: =+U114/U102-1 -> 0.019891811 | AB114: =+V114/V102-1 -> 0.070605307 | AC114: =+W114/W102-1 -> 0.16277513
... A167: =+EOMONTH(A166,1) -> 45991 | B167: 19426 | C167: 13327 | D167: 1763 | E167: =+C167+B167+D167 -> 34516 | H167: =+SUM(B165:B167) -> 58554 | I167: =+SUM(C165:C167) -> 42455 | J167: =+SUM(D165:D167) -> 6899 | K167: =+H167+I167+J167 -> 107908 | N167: =+H167/H155-1 -> 0.13785464 | O167: =+I167/I155-1 -> 0.17727802 | P167: =+J167/J155-1 -> 0.5661748 | Q167: =+K167/K155-1 -> 0.17384446 | T167: =+SUM(B156:B167) -> 227411 | U167: =+SUM(C156:C167) -> 139216 | V167: =+SUM(D156:D167) -> 25224 | W167: =+SUM(E156:E167) -> 391851 | Z167: =+T167/T155-1 -> 0.041979574 | AA167: =+U167/U155-1 -> -0.045013651 | AB167: =+V167/V155-1 -> 0.48577487 | AC167: =+W167/W155-1 -> 0.028469517
A168: =+EOMONTH(A167,1) -> 46022 | B168: =12483+7959+4167 -> 24609 | C168: 15448 | D168: 2451 | E168: =+C168+B168+D168 -> 42508 | H168: =+SUM(B166:B168) -> 64125 | I168: =+SUM(C166:C168) -> 43793 | J168: =+SUM(D166:D168) -> 6636 | K168: =+H168+I168+J168 -> 114554 | N168: =+H168/H156-1 -> 0.2092668 | O168: =+I168/I156-1 -> 0.14545407 | P168: =+J168/J156-1 -> 0.4713969 | Q168: =+K168/K156-1 -> 0.19613658 | T168: =+SUM(B157:B168) -> 232669 | U168: =+SUM(C157:C168) -> 141646 | V168: =+SUM(D157:D168) -> 26169 | W168: =+SUM(E157:E168) -> 400484 | Z168: =+T168/T156-1 -> 0.068926704 | AA168: =+U168/U156-1 -> -0.030233736 | AB168: =+V168/V156-1 -> 0.54198338 | AC168: =+W168/W156-1 -> 0.051970192
A169: =+EOMONTH(A168,1) -> 46053 | B169: =12691+7071+4562 -> 24324 | C169: 14520 | D169: 2705 | E169: =+C169+B169+D169 -> 41549 | H169: =+SUM(B167:B169) -> 68359 | I169: =+SUM(C167:C169) -> 43295 | J169: =+SUM(D167:D169) -> 6919 | K169: =+H169+I169+J169 -> 118573 | N169: =+H169/H157-1 -> 0.28487115 | O169: =+I169/I157-1 -> 0.22191804 | P169: =+J169/J157-1 -> 0.42249178 | Q169: =+K169/K157-1 -> 0.26817399 | T169: =+SUM(B158:B169) -> 238123 | U169: =+SUM(C158:C169) -> 144953 | V169: =+SUM(D158:D169) -> 26969 | W169: =+SUM(E158:E169) -> 410045 | Z169: =+T169/T157-1 -> 0.087245166 | AA169: =+U169/U157-1 -> 0.005549659 | AB169: =+V169/V157-1 -> 0.54754117 | AC169: =+W169/W157-1 -> 0.077378841
A170: =+EOMONTH(A169,1) -> 46081 | B170: =13559+7577+5548 -> 26684 | C170: 14209 | D170: 2047 | E170: =+C170+B170+D170 -> 42940 | H170: =+SUM(B168:B170) -> 75617 | I170: =+SUM(C168:C170) -> 44177 | J170: =+SUM(D168:D170) -> 7203 | K170: =+H170+I170+J170 -> 126997 | N170: =+H170/H158-1 -> 0.30104955 | O170: =+I170/I158-1 -> 0.25756497 | P170: =+J170/J158-1 -> 0.39945599 | Q170: =+K170/K158-1 -> 0.29067239 | T170: =+SUM(B159:B170) -> 244908 | U170: =+SUM(C159:C170) -> 148264 | V170: =+SUM(D159:D170) -> 27280 | W170: =+SUM(E159:E170) -> 420452 | Z170: =+T170/T158-1 -> 0.11805632 | AA170: =+U170/U158-1 -> 0.048914043 | AB170: =+V170/V158-1 -> 0.54604704 | AC170: =+W170/W158-1 -> 0.11218036
A171: =+EOMONTH(A170,1) -> 46112 | B171: 30934 | C171: 14891 | D171: 2151 | E171: =+C171+B171+D171 -> 47976 | H171: =+SUM(B169:B171) -> 81942 | I171: =+SUM(C169:C171) -> 43620 | J171: =+SUM(D169:D171) -> 6903 | K171: =+H171+I171+J171 -> 132465 | N171: =+H171/H159-1 -> 0.26270533 | O171: =+I171/I159-1 -> 0.25093203 | P171: =+J171/J159-1 -> 0.17417928 | Q171: =+K171/K159-1 -> 0.25389283 | T171: =+SUM(B160:B171) -> 249717 | U171: =+SUM(C160:C171) -> 150396 | V171: =+SUM(D160:D171) -> 27193 | W171: =+SUM(E160:E171) -> 427306 | Z171: =+T171/T159-1 -> 0.13596539 | AA171: =+U171/U159-1 -> 0.083997636 | AB171: =+V171/V159-1 -> 0.48328151 | AC171: =+W171/W159-1 -> 0.13372937
A172: =+EOMONTH(A171,1) -> 46142 | B172: =8969+5454+5743 -> 20166 | C172: 12799 | D172: 1868 | E172: =+C172+B172+D172 -> 34833 | H172: =+SUM(B170:B172) -> 77784 | I172: =+SUM(C170:C172) -> 41899 | J172: =+SUM(D170:D172) -> 6066 | K172: =+H172+I172+J172 -> 125749 | N172: =+H172/H160-1 -> 0.24142554 | O172: =+I172/I160-1 -> 0.27787605 | P172: =+J172/J160-1 -> 0.11692138 | Q172: =+K172/K160-1 -> 0.24657005 | T172: =+SUM(B161:B172) -> 253250 | U172: =+SUM(C161:C172) -> 154064 | V172: =+SUM(D161:D172) -> 27604 | W172: =+SUM(E161:E172) -> 434918 | Z172: =+T172/T160-1 -> 0.15235157 | AA172: =+U172/U160-1 -> 0.1324072 | AB172: =+V172/V160-1 -> 0.47080136 | AC172: =+W172/W160-1 -> 0.16106315
A173: =+EOMONTH(A172,1) -> 46173 | B173: =7877+5331+5757 -> 18965 | C173: 11819 | D173: 2066 | E173: =+C173+B173+D173 -> 32850 | H173: =+SUM(B171:B173) -> 70065 | I173: =+SUM(C171:C173) -> 39509 | J173: =+SUM(D171:D173) -> 6085 | K173: =+H173+I173+J173 -> 115659 | N173: =+H173/H161-1 -> 0.17625827 | O173: =+I173/I161-1 -> 0.27637785 | P173: =+J173/J161-1 -> 0.019262982 | Q173: =+K173/K161-1 -> 0.19866307 | T173: =+SUM(B162:B173) -> 255407 | U173: =+SUM(C162:C173) -> 156819 | V173: =+SUM(D162:D173) -> 27395 | W173: =+SUM(E162:E173) -> 439621 | Z173: =+T173/T161-1 -> 0.16391948 | AA173: =+U173/U161-1 -> 0.17224187 | AB173: =+V173/V161-1 -> 0.38163204 | AC173: =+W173/W161-1 -> 0.17847588
A174: =+EOMONTH(A173,1) -> 46203 | H174: =+H162*(1+N174) -> 56453.1 | I174: =+I162*(1+O174) -> 32206.14 | J174: =+J162*(1+P174) -> 6878.76 | K174: =+H174+I174+J174 -> 95538 | N174: 0.1 | O174: 0.14 | P174: 0.14 | Q174: =+K174/K162-1 -> 0.11601991
A175: =+EOMONTH(A174,1) -> 46234 | H175: =+H163*(1+N175) -> 56364 | I175: =+I163*(1+O175) -> 33060 | J175: =+J163*(1+P175) -> 8095.14 | K175: =+H175+I175+J175 -> 97519.14 | N175: 0.1 | O175: 0.14 | P175: 0.14 | Q175: =+K175/K163-1 -> 0.11653336
A176: =+EOMONTH(A175,1) -> 46265 | H176: =+H164*(1+N176) -> 56288.1 | I176: =+I164*(1+O176) -> 34972.92 | J176: =+J164*(1+P176) -> 8217.12 | K176: =+H176+I176+J176 -> 99478.14 | N176: 0.1 | O176: 0.14 | P176: 0.14 | Q176: =+K176/K164-1 -> 0.11701652
A177: =+EOMONTH(A176,1) -> 46295 | H177: =+H165*(1+N177) -> 57561.9 | I177: =+I165*(1+O177) -> 39594.48 | J177: =+J165*(1+P177) -> 8686.8 | K177: =+H177+I177+J177 -> 105843.18 | N177: 0.1 | O177: 0.14 | P177: 0.14 | Q177: =+K177/K165-1 -> 0.1178925
A178: =+EOMONTH(A177,1) -> 46326 | H178: =+H166*(1+N178) -> 61453.7 | I178: =+I166*(1+O178) -> 45451.8 | J178: =+J166*(1+P178) -> 8570.52 | K178: =+H178+I178+J178 -> 115476.02 | N178: 0.1 | O178: 0.14 | P178: 0.14 | Q178: =+K178/K166-1 -> 0.11835766
A179: =+EOMONTH(A178,1) -> 46356 | H179: =+H167*(1+N179) -> 64409.4 | I179: =+I167*(1+O179) -> 48398.7 | J179: =+J167*(1+P179) -> 7864.86 | K179: =+H179+I179+J179 -> 120672.96 | N179: 0.1 | O179: 0.14 | P179: 0.14 | Q179: =+K179/K167-1 -> 0.11829484
A180: =+EOMONTH(A179,1) -> 46387 | H180: =+H168*(1+N180) -> 70537.5 | I180: =+I168*(1+O180) -> 49924.02 | J180: =+J168*(1+P180) -> 7565.04 | K180: =+H180+I180+J180 -> 128026.56 | N180: 0.1 | O180: 0.14 | P180: 0.14 | Q180: =+K180/K168-1 -> 0.11760881
A181: =+EOMONTH(A180,1) -> 46418 | H181: =+H169*(1+N181) -> 75194.9 | I181: =+I169*(1+O181) -> 49356.3 | J181: =+J169*(1+P181) -> 7887.66 | K181: =+H181+I181+J181 -> 132438.86 | N181: 0.1 | O181: 0.14 | P181: 0.14 | Q181: =+K181/K169-1 -> 0.11693944
A182: =+EOMONTH(A181,1) -> 46446 | H182: =+H170*(1+N182) -> 83178.7 | I182: =+I170*(1+O182) -> 50361.78 | J182: =+J170*(1+P182) -> 8211.42 | K182: =+H182+I182+J182 -> 141751.9 | N182: 0.1 | O182: 0.14 | P182: 0.14 | Q182: =+K182/K170-1 -> 0.11618306
A183: =+EOMONTH(A182,1) -> 46477 | H183: =+H171*(1+N183) -> 90136.2 | I183: =+I171*(1+O183) -> 49726.8 | J183: =+J171*(1+P183) -> 7869.42 | K183: =+H183+I183+J183 -> 147732.42 | N183: 0.1 | O183: 0.14 | P183: 0.14 | Q183: =+K183/K171-1 -> 0.11525626
A184: =+EOMONTH(A183,1) -> 46507 | H184: =+H172*(1+N184) -> 85562.4 | I184: =+I172*(1+O184) -> 47764.86 | J184: =+J172*(1+P184) -> 6915.24 | K184: =+H184+I184+J184 -> 140242.5 | N184: 0.1 | O184: 0.14 | P184: 0.14 | Q184: =+K184/K172-1 -> 0.11525738
A185: =+EOMONTH(A184,1) -> 46538 | H185: =+H173*(1+N185) -> 77071.5 | I185: =+I173*(1+O185) -> 45040.26 | J185: =+J173*(1+P185) -> 6936.9 | K185: =+H185+I185+J185 -> 129048.66 | N185: 0.1 | O185: 0.14 | P185: 0.14 | Q185: =+K185/K173-1 -> 0.11576842
... A219: =+EOMONTH(A218,1) -> 47573 | H219: =+H207*(1+N219) -> 119971.28 | I219: =+I207*(1+O219) -> 73672.442 | J219: =+J207*(1+P219) -> 11658.892 | K219: =+H219+I219+J219 -> 205302.62 | N219: 0.1 | O219: 0.14 | P219: 0.14 | Q219: =+K219/K207-1 -> 0.11627954
A223: 46022 | H223: 58330.8 | I223: 43584.48 | J223: 43584.48 | K223: 101915.28 | N223: 0.1 | O223: 0.14 | P223: 0.14 | Q223: 0.1167574
A229: 46173 | H229: 65522.6 | I229: 35287.56 | J229: 6805.8 | K229: 107615.96 | N229: 0.1 | O229: 0.14 | P229: 0.14 | Q229: 0.11530687

Sheet Monthly Nos Vahan
A1: Vahan Registrations
A3: Month | B3: Registrations | C3: YoY% | E3: 3M Rolling | F3: QoQ% | G3: YoY% | I3: 12M Rolling | J3: YoY%
A4: 44197
A5: =+EOMONTH(A4,1) -> 44255
A6: =+EOMONTH(A5,1) -> 44286
A7: =+EOMONTH(A6,1) -> 44316
A8: =+EOMONTH(A7,1) -> 44347
A9: =+EOMONTH(A8,1) -> 44377
A10: =+EOMONTH(A9,1) -> 44408
A11: =+EOMONTH(A10,1) -> 44439
A12: =+EOMONTH(A11,1) -> 44469
A13: =+EOMONTH(A12,1) -> 44500
A14: =+EOMONTH(A13,1) -> 44530
A15: =+EOMONTH(A14,1) -> 44561
A16: =+EOMONTH(A15,1) -> 44592
A17: =+EOMONTH(A16,1) -> 44620 | B17: 35748
A18: =+EOMONTH(A17,1) -> 44651 | B18: 38458
A19: =+EOMONTH(A18,1) -> 44681 | B19: 36650 | E19: =+SUM(B17:B19) -> 110856
A20: =+EOMONTH(A19,1) -> 44712 | B20: 30256 | E20: =+SUM(B18:B20) -> 105364 | F20: =+E20/E19-1 -> -0.049541748
A21: =+EOMONTH(A20,1) -> 44742 | B21: 30238 | E21: =+SUM(B19:B21) -> 97144 | F21: =+E21/E20-1 -> -0.078015261
A22: =+EOMONTH(A21,1) -> 44773 | B22: 29389 | E22: =+SUM(B20:B22) -> 89883 | F22: =+E22/E21-1 -> -0.074744709
A23: =+EOMONTH(A22,1) -> 44804 | B23: 29910 | E23: =+SUM(B21:B23) -> 89537 | F23: =+E23/E22-1 -> -0.0038494487
A24: =+EOMONTH(A23,1) -> 44834 | B24: 30811 | E24: =+SUM(B22:B24) -> 90110 | F24: =+E24/E23-1 -> 0.006399589
A25: =+EOMONTH(A24,1) -> 44865 | B25: 29402 | E25: =+SUM(B23:B25) -> 90123 | F25: =+E25/E24-1 -> 0.00014426812
A26: =+EOMONTH(A25,1) -> 44895 | B26: 32717 | E26: =+SUM(B24:B26) -> 92930 | F26: =+E26/E25-1 -> 0.031146322
A27: =+EOMONTH(A26,1) -> 44926 | B27: 28400 | E27: =+SUM(B25:B27) -> 90519 | F27: =+E27/E26-1 -> -0.025944259
A28: =+EOMONTH(A27,1) -> 44957 | B28: 34438 | E28: =+SUM(B26:B28) -> 95555 | F28: =+E28/E27-1 -> 0.055634729 | I28: =+SUM(B17:B28) -> 386417
A29: =+EOMONTH(A28,1) -> 44985 | B29: 32587 | C29: =+B29/B17-1 -> -0.088424527 | E29: =+SUM(B27:B29) -> 95425 | F29: =+E29/E28-1 -> -0.001360473 | I29: =+SUM(B18:B29) -> 383256
A30: =+EOMONTH(A29,1) -> 45016 | B30: 38197 | C30: =+B30/B18-1 -> -0.0067866244 | E30: =+SUM(B28:B30) -> 105222 | F30: =+E30/E29-1 -> 0.10266702 | I30: =+SUM(B19:B30) -> 382995
A31: =+EOMONTH(A30,1) -> 45046 | B31: 34453 | C31: =+B31/B19-1 -> -0.05994543 | E31: =+SUM(B29:B31) -> 105237 | F31: =+E31/E30-1 -> 0.00014255574 | G31: =+E31/E19-1 -> -0.050687378 | I31: =+SUM(B20:B31) -> 380798
A32: =+EOMONTH(A31,1) -> 45077 | B32: 27485 | C32: =+B32/B20-1 -> -0.09158514 | E32: =+SUM(B30:B32) -> 100135 | F32: =+E32/E31-1 -> -0.048481048 | G32: =+E32/E20-1 -> -0.049627956 | I32: =+SUM(B21:B32) -> 378027
A33: =+EOMONTH(A32,1) -> 45107 | B33: 27608 | C33: =+B33/B21-1 -> -0.086976652 | E33: =+SUM(B31:B33) -> 89546 | F33: =+E33/E32-1 -> -0.10574724 | G33: =+E33/E21-1 -> -0.078213786 | I33: =+SUM(B22:B33) -> 375397
A34: =+EOMONTH(A33,1) -> 45138 | B34: 28446 | C34: =+B34/B22-1 -> -0.032086835 | E34: =+SUM(B32:B34) -> 83539 | F34: =+E34/E33-1 -> -0.06708284 | G34: =+E34/E22-1 -> -0.070580644 | I34: =+SUM(B23:B34) -> 374454
A35: =+EOMONTH(A34,1) -> 45169 | B35: 29189 | C35: =+B35/B23-1 -> -0.02410565 | E35: =+SUM(B33:B35) -> 85243 | F35: =+E35/E34-1 -> 0.020397659 | G35: =+E35/E23-1 -> -0.047957827 | I35: =+SUM(B24:B35) -> 373733
A36: =+EOMONTH(A35,1) -> 45199 | B36: 30479 | C36: =+B36/B24-1 -> -0.010775372 | E36: =+SUM(B34:B36) -> 88114 | F36: =+E36/E35-1 -> 0.033680185 | G36: =+E36/E24-1 -> -0.022150705 | I36: =+SUM(B25:B36) -> 373401
A37: =+EOMONTH(A36,1) -> 45230 | B37: 33554 | C37: =+B37/B25-1 -> 0.14121488 | E37: =+SUM(B35:B37) -> 93222 | F37: =+E37/E36-1 -> 0.057970357 | G37: =+E37/E25-1 -> 0.034386339 | I37: =+SUM(B26:B37) -> 377553
A38: =+EOMONTH(A37,1) -> 45260 | B38: 31152 | C38: =+B38/B26-1 -> -0.047834459 | E38: =+SUM(B36:B38) -> 95185 | F38: =+E38/E37-1 -> 0.021057261 | G38: =+E38/E26-1 -> 0.024265576 | I38: =+SUM(B27:B38) -> 375988
A39: =+EOMONTH(A38,1) -> 45291 | B39: 27430 | C39: =+B39/B27-1 -> -0.03415493 | E39: =+SUM(B37:B39) -> 92136 | F39: =+E39/E38-1 -> -0.032032358 | G39: =+E39/E27-1 -> 0.017863653 | I39: =+SUM(B28:B39) -> 375018
A40: =+EOMONTH(A39,1) -> 45322 | B40: 32592 | C40: =+B40/B28-1 -> -0.053603577 | E40: =+SUM(B38:B40) -> 91174 | F40: =+E40/E39-1 -> -0.010441087 | G40: =+E40/E28-1 -> -0.045847941 | I40: =+SUM(B29:B40) -> 373172 | J40: =+I40/I28-1 -> -0.034276442
A41: =+EOMONTH(A40,1) -> 45351 | B41: 33348 | C41: =+B41/B29-1 -> 0.023352871 | E41: =+SUM(B39:B41) -> 93370 | F41: =+E41/E40-1 -> 0.024085814 | G41: =+E41/E29-1 -> -0.021535237 | I41: =+SUM(B30:B41) -> 373933 | J41: =+I41/I29-1 -> -0.024325777
A42: =+EOMONTH(A41,1) -> 45382 | B42: 34236 | C42: =+B42/B30-1 -> -0.10369924 | E42: =+SUM(B40:B42) -> 100176 | F42: =+E42/E41-1 -> 0.072892792 | G42: =+E42/E30-1 -> -0.047955751 | I42: =+SUM(B31:B42) -> 369972 | J42: =+I42/I30-1 -> -0.034003055
A43: =+EOMONTH(A42,1) -> 45412 | B43: 33649 | C43: =+B43/B31-1 -> -0.023336139 | E43: =+SUM(B41:B43) -> 101233 | F43: =+E43/E42-1 -> 0.010551429 | G43: =+E43/E31-1 -> -0.038047455 | I43: =+SUM(B32:B43) -> 369168 | J43: =+I43/I31-1 -> -0.030541127
A44: =+EOMONTH(A43,1) -> 45443 | B44: 30784 | C44: =+B44/B32-1 -> 0.12002911 | E44: =+SUM(B42:B44) -> 98669 | F44: =+E44/E43-1 -> -0.025327709 | G44: =+E44/E32-1 -> -0.014640236 | I44: =+SUM(B33:B44) -> 372467 | J44: =+I44/I32-1 -> -0.014707944
A45: =+EOMONTH(A44,1) -> 45473 | B45: 27208 | C45: =+B45/B33-1 -> -0.014488554 | E45: =+SUM(B43:B45) -> 91641 | F45: =+E45/E44-1 -> -0.071228045 | G45: =+E45/E33-1 -> 0.023395797 | I45: =+SUM(B34:B45) -> 372067 | J45: =+I45/I33-1 -> -0.008870609
A46: =+EOMONTH(A45,1) -> 45504 | B46: 29210 | C46: =+B46/B34-1 -> 0.026857906 | E46: =+SUM(B44:B46) -> 87202 | F46: =+E46/E45-1 -> -0.048439017 | G46: =+E46/E34-1 -> 0.043847784 | I46: =+SUM(B35:B46) -> 372831 | J46: =+I46/I34-1 -> -0.0043343108
A47: =+EOMONTH(A46,1) -> 45535 | B47: 26113 | C47: =+B47/B35-1 -> -0.10538216 | E47: =+SUM(B45:B47) -> 82531 | F47: =+E47/E46-1 -> -0.053565285 | G47: =+E47/E35-1 -> -0.031814929 | I47: =+SUM(B36:B47) -> 369755 | J47: =+I47/I35-1 -> -0.010643962
A48: =+EOMONTH(A47,1) -> 45565 | B48: 25735 | C48: =+B48/B36-1 -> -0.15564815 | E48: =+SUM(B46:B48) -> 81058 | F48: =+E48/E47-1 -> -0.017847839 | G48: =+E48/E36-1 -> -0.080078081 | I48: =+SUM(B37:B48) -> 365011 | J48: =+I48/I36-1 -> -0.022469142
A49: =+EOMONTH(A48,1) -> 45596 | B49: 31700 | C49: =+B49/B37-1 -> -0.055254217 | E49: =+SUM(B47:B49) -> 83548 | F49: =+E49/E48-1 -> 0.030718745 | G49: =+E49/E37-1 -> -0.10377379 | I49: =+SUM(B38:B49) -> 363157 | J49: =+I49/I37-1 -> -0.038129746
A50: =+EOMONTH(A49,1) -> 45626 | B50: 28561 | C50: =+B50/B38-1 -> -0.08317283 | E50: =+SUM(B48:B50) -> 85996 | F50: =+E50/E49-1 -> 0.029300522 | G50: =+E50/E38-1 -> -0.09653832 | I50: =+SUM(B39:B50) -> 360566 | J50: =+I50/I38-1 -> -0.041017267
A51: =+EOMONTH(A50,1) -> 45657 | B51: 25054 | C51: =+B51/B39-1 -> -0.086620489 | E51: =+SUM(B49:B51) -> 85315 | F51: =+E51/E50-1 -> -0.007918973 | G51: =+E51/E39-1 -> -0.074031866 | I51: =+SUM(B40:B51) -> 358190 | J51: =+I51/I39-1 -> -0.044872513
... A68: =+EOMONTH(A67,1) -> 46173 | B68: 30908 | C68: =+B68/B56-1 -> 0.12519568 | E68: =+SUM(B66:B68) -> 107589 | F68: =+E68/E67-1 -> -0.054594823 | G68: =+E68/E56-1 -> 0.17861838 | I68: =+SUM(B57:B68) -> 384985 | J68: =+I68/I56-1 -> 0.11500977
A69: =+EOMONTH(A68,1) -> 46203
A70: =+EOMONTH(A69,1) -> 46234
A71: =+EOMONTH(A70,1) -> 46265
A72: =+EOMONTH(A71,1) -> 46295
A73: =+EOMONTH(A72,1) -> 46326
A74: =+EOMONTH(A73,1) -> 46356
A75: =+EOMONTH(A74,1) -> 46387
A76: =+EOMONTH(A75,1) -> 46418
A77: =+EOMONTH(A76,1) -> 46446
A78: =+EOMONTH(A77,1) -> 46477
A79: =+EOMONTH(A78,1) -> 46507
A80: =+EOMONTH(A79,1) -> 46538

Sheet QTR Raw
A1: ='Annual Raw'!A1 -> 322918 | C1: 0 | D1: 0 | E1: 0 | F1: 0 | G1: 201306 | H1: 201309 | I1: 201312 | J1: 201403 | K1: 201406 | L1: 201409 | M1: 201412 | N1: 201503 | O1: 201506 | P1: 201509 | Q1: 201512 | R1: 201603 | S1: 201606 | T1: 201609 | U1: 201612 | V1: 201703 | W1: 201706 | X1: 201709 | Y1: 201712 | Z1: 201803 | AA1: 201806 | AB1: 201809 | AC1: 201812 | AD1: 201903 | AE1: 201906 | AF1: 201909 | AG1: 201912 | AH1: 202003 | AI1: 202006 | AJ1: 202009 | AK1: 202012 | AL1: 202103 | AM1: 202106 | AN1: 202109 | AO1: 202112 | AP1: 202203 | AQ1: 202206 | AR1: 202209 | AS1: 202212 | AT1: 202303 | AU1: 202306 | AV1: 202309 | AW1: 202312 | AX1: 202403 | AY1: 202406 | AZ1: 202409 | BA1: 202412 | BB1: 202503 | BC1: 202506 | BD1: 202509 | BE1: 202512 | BF1: 202603 | BG1: 202606 | BH1: 202609 | BI1: 202612 | BJ1: 202703 | BK1: 202706 | BL1: 202709 | BM1: 202712 | BN1: 202803 | BO1: 202806 | BP1: 202809 | BQ1: 202812 | BR1: 202903 | BS1: 202906 | BT1: 202909 | BU1: 202912 | BV1: 203003
A3: Field Description | B3: Field Name
A4: Company Name | B4: CD_COMPNAME | C4: =_xll.EQNXTDZ(A1,B4,C1) -> Tata Motors Ltd.
A5: Date End | B5: QTR_DATE_END | C5: =_xll.EQNXTDZ($A$1,$B5,C$1,$B$1) -> 0 | D5: =_xll.EQNXTDZ($A$1,$B5,D$1,$B$1) -> 0 | E5: =_xll.EQNXTDZ($A$1,$B5,E$1,$B$1) -> 0 | F5: =_xll.EQNXTDZ($A$1,$B5,F$1,$B$1) -> 0 | G5: =_xll.EQNXTDZ($A$1,$B5,G$1,$B$1) -> 0 | H5: =_xll.EQNXTDZ($A$1,$B5,H$1,$B$1) -> 0 | I5: =_xll.EQNXTDZ($A$1,$B5,I$1,$B$1) -> 0 | J5: =_xll.EQNXTDZ($A$1,$B5,J$1,$B$1) -> 0 | ... BV5: =_xll.EQNXTDZ($A$1,$B5,BV$1,$B$1) -> 0
A6: Gross Sales | B6: QTR_GROSS_SALE | C6: =_xll.EQNXTDZ($A$1,$B6,C$1,$B$1) -> 0 | D6: =_xll.EQNXTDZ($A$1,$B6,D$1,$B$1) -> 0 | E6: =_xll.EQNXTDZ($A$1,$B6,E$1,$B$1) -> 0 | F6: =_xll.EQNXTDZ($A$1,$B6,F$1,$B$1) -> 0 | G6: =_xll.EQNXTDZ($A$1,$B6,G$1,$B$1) -> 0 | H6: =_xll.EQNXTDZ($A$1,$B6,H$1,$B$1) -> 0 | I6: =_xll.EQNXTDZ($A$1,$B6,I$1,$B$1) -> 0 | J6: =_xll.EQNXTDZ($A$1,$B6,J$1,$B$1) -> 0 | ... BV6: =_xll.EQNXTDZ($A$1,$B6,BV$1,$B$1) -> 0
A7: Less: Excise Duty | B7: QTR_EXCISE_DUTY | C7: =_xll.EQNXTDZ($A$1,$B7,C$1,$B$1) -> 0 | D7: =_xll.EQNXTDZ($A$1,$B7,D$1,$B$1) -> 0 | E7: =_xll.EQNXTDZ($A$1,$B7,E$1,$B$1) -> 0 | F7: =_xll.EQNXTDZ($A$1,$B7,F$1,$B$1) -> 0 | G7: =_xll.EQNXTDZ($A$1,$B7,G$1,$B$1) -> 0 | H7: =_xll.EQNXTDZ($A$1,$B7,H$1,$B$1) -> 0 | I7: =_xll.EQNXTDZ($A$1,$B7,I$1,$B$1) -> 0 | J7: =_xll.EQNXTDZ($A$1,$B7,J$1,$B$1) -> 0 | ... BV7: =_xll.EQNXTDZ($A$1,$B7,BV$1,$B$1) -> 0
A8: Other operating income | B8: QTR_JOB_WORKS | C8: =_xll.EQNXTDZ($A$1,$B8,C$1,$B$1) -> 0 | D8: =_xll.EQNXTDZ($A$1,$B8,D$1,$B$1) -> 0 | E8: =_xll.EQNXTDZ($A$1,$B8,E$1,$B$1) -> 0 | F8: =_xll.EQNXTDZ($A$1,$B8,F$1,$B$1) -> 0 | G8: =_xll.EQNXTDZ($A$1,$B8,G$1,$B$1) -> 0 | H8: =_xll.EQNXTDZ($A$1,$B8,H$1,$B$1) -> 0 | I8: =_xll.EQNXTDZ($A$1,$B8,I$1,$B$1) -> 0 | J8: =_xll.EQNXTDZ($A$1,$B8,J$1,$B$1) -> 0 | ... BV8: =_xll.EQNXTDZ($A$1,$B8,BV$1,$B$1) -> 0
A9: Net Sales & Other Operating Income | B9: QTR_NET_SALES | C9: =_xll.EQNXTDZ($A$1,$B9,C$1,$B$1) -> 0 | D9: =_xll.EQNXTDZ($A$1,$B9,D$1,$B$1) -> 0 | E9: =_xll.EQNXTDZ($A$1,$B9,E$1,$B$1) -> 0 | F9: =_xll.EQNXTDZ($A$1,$B9,F$1,$B$1) -> 0 | G9: =_xll.EQNXTDZ($A$1,$B9,G$1,$B$1) -> 0 | H9: =_xll.EQNXTDZ($A$1,$B9,H$1,$B$1) -> 0 | I9: =_xll.EQNXTDZ($A$1,$B9,I$1,$B$1) -> 0 | J9: =_xll.EQNXTDZ($A$1,$B9,J$1,$B$1) -> 0 | ... BV9: =_xll.EQNXTDZ($A$1,$B9,BV$1,$B$1) -> 0
A10: (Increase) / Decrease In Stocks | B10: QTR_INC_DEC_INVENTORY | C10: =_xll.EQNXTDZ($A$1,$B10,C$1,$B$1) -> 0 | D10: =_xll.EQNXTDZ($A$1,$B10,D$1,$B$1) -> 0 | E10: =_xll.EQNXTDZ($A$1,$B10,E$1,$B$1) -> 0 | F10: =_xll.EQNXTDZ($A$1,$B10,F$1,$B$1) -> 0 | G10: =_xll.EQNXTDZ($A$1,$B10,G$1,$B$1) -> 0 | H10: =_xll.EQNXTDZ($A$1,$B10,H$1,$B$1) -> 0 | I10: =_xll.EQNXTDZ($A$1,$B10,I$1,$B$1) -> 0 | J10: =_xll.EQNXTDZ($A$1,$B10,J$1,$B$1) -> 0 | ... BV10: =_xll.EQNXTDZ($A$1,$B10,BV$1,$B$1) -> 0
A11: Cost of Services & Raw Materials | B11: QTR_RAW_MATERIAL_COST | C11: =_xll.EQNXTDZ($A$1,$B11,C$1,$B$1) -> 0 | D11: =_xll.EQNXTDZ($A$1,$B11,D$1,$B$1) -> 0 | E11: =_xll.EQNXTDZ($A$1,$B11,E$1,$B$1) -> 0 | F11: =_xll.EQNXTDZ($A$1,$B11,F$1,$B$1) -> 0 | G11: =_xll.EQNXTDZ($A$1,$B11,G$1,$B$1) -> 0 | H11: =_xll.EQNXTDZ($A$1,$B11,H$1,$B$1) -> 0 | I11: =_xll.EQNXTDZ($A$1,$B11,I$1,$B$1) -> 0 | J11: =_xll.EQNXTDZ($A$1,$B11,J$1,$B$1) -> 0 | ... BV11: =_xll.EQNXTDZ($A$1,$B11,BV$1,$B$1) -> 0
A12: Purchase of Finished Goods | B12: QTR_PURCHASE_FIN_GOOD | C12: =_xll.EQNXTDZ($A$1,$B12,C$1,$B$1) -> 0 | D12: =_xll.EQNXTDZ($A$1,$B12,D$1,$B$1) -> 0 | E12: =_xll.EQNXTDZ($A$1,$B12,E$1,$B$1) -> 0 | F12: =_xll.EQNXTDZ($A$1,$B12,F$1,$B$1) -> 0 | G12: =_xll.EQNXTDZ($A$1,$B12,G$1,$B$1) -> 0 | H12: =_xll.EQNXTDZ($A$1,$B12,H$1,$B$1) -> 0 | I12: =_xll.EQNXTDZ($A$1,$B12,I$1,$B$1) -> 0 | J12: =_xll.EQNXTDZ($A$1,$B12,J$1,$B$1) -> 0 | ... BV12: =_xll.EQNXTDZ($A$1,$B12,BV$1,$B$1) -> 0
A13: Excise Duty | B13: QTR_EXCISE | C13: =_xll.EQNXTDZ($A$1,$B13,C$1,$B$1) -> 0 | D13: =_xll.EQNXTDZ($A$1,$B13,D$1,$B$1) -> 0 | E13: =_xll.EQNXTDZ($A$1,$B13,E$1,$B$1) -> 0 | F13: =_xll.EQNXTDZ($A$1,$B13,F$1,$B$1) -> 0 | G13: =_xll.EQNXTDZ($A$1,$B13,G$1,$B$1) -> 0 | H13: =_xll.EQNXTDZ($A$1,$B13,H$1,$B$1) -> 0 | I13: =_xll.EQNXTDZ($A$1,$B13,I$1,$B$1) -> 0 | J13: =_xll.EQNXTDZ($A$1,$B13,J$1,$B$1) -> 0 | ... BV13: =_xll.EQNXTDZ($A$1,$B13,BV$1,$B$1) -> 0
A14: Operating & Manufacturing Expenses | B14: QTR_MFG_EXPS | C14: =_xll.EQNXTDZ($A$1,$B14,C$1,$B$1) -> 0 | D14: =_xll.EQNXTDZ($A$1,$B14,D$1,$B$1) -> 0 | E14: =_xll.EQNXTDZ($A$1,$B14,E$1,$B$1) -> 0 | F14: =_xll.EQNXTDZ($A$1,$B14,F$1,$B$1) -> 0 | G14: =_xll.EQNXTDZ($A$1,$B14,G$1,$B$1) -> 0 | H14: =_xll.EQNXTDZ($A$1,$B14,H$1,$B$1) -> 0 | I14: =_xll.EQNXTDZ($A$1,$B14,I$1,$B$1) -> 0 | J14: =_xll.EQNXTDZ($A$1,$B14,J$1,$B$1) -> 0 | ... BV14: =_xll.EQNXTDZ($A$1,$B14,BV$1,$B$1) -> 0
A15: Electricity Power & Fuel Cost | B15: QTR_ELECTRICITY_POWER_FUEL | C15: =_xll.EQNXTDZ($A$1,$B15,C$1,$B$1) -> 0 | D15: =_xll.EQNXTDZ($A$1,$B15,D$1,$B$1) -> 0 | E15: =_xll.EQNXTDZ($A$1,$B15,E$1,$B$1) -> 0 | F15: =_xll.EQNXTDZ($A$1,$B15,F$1,$B$1) -> 0 | G15: =_xll.EQNXTDZ($A$1,$B15,G$1,$B$1) -> 0 | H15: =_xll.EQNXTDZ($A$1,$B15,H$1,$B$1) -> 0 | I15: =_xll.EQNXTDZ($A$1,$B15,I$1,$B$1) -> 0 | J15: =_xll.EQNXTDZ($A$1,$B15,J$1,$B$1) -> 0 | ... BV15: =_xll.EQNXTDZ($A$1,$B15,BV$1,$B$1) -> 0
A16: Employee Cost | B16: QTR_EXPLOYEE_COST | C16: =_xll.EQNXTDZ($A$1,$B16,C$1,$B$1) -> 0 | D16: =_xll.EQNXTDZ($A$1,$B16,D$1,$B$1) -> 0 | E16: =_xll.EQNXTDZ($A$1,$B16,E$1,$B$1) -> 0 | F16: =_xll.EQNXTDZ($A$1,$B16,F$1,$B$1) -> 0 | G16: =_xll.EQNXTDZ($A$1,$B16,G$1,$B$1) -> 0 | H16: =_xll.EQNXTDZ($A$1,$B16,H$1,$B$1) -> 0 | I16: =_xll.EQNXTDZ($A$1,$B16,I$1,$B$1) -> 0 | J16: =_xll.EQNXTDZ($A$1,$B16,J$1,$B$1) -> 0 | ... BV16: =_xll.EQNXTDZ($A$1,$B16,BV$1,$B$1) -> 0
... A42: Consolidated PAT(after extra items) | B42: QTR_CONS_PAT_EXITM | C42: =_xll.EQNXTDZ($A$1,$B42,C$1,$B$1) -> 0 | D42: =_xll.EQNXTDZ($A$1,$B42,D$1,$B$1) -> 0 | E42: =_xll.EQNXTDZ($A$1,$B42,E$1,$B$1) -> 0 | F42: =_xll.EQNXTDZ($A$1,$B42,F$1,$B$1) -> 0 | G42: =_xll.EQNXTDZ($A$1,$B42,G$1,$B$1) -> 0 | H42: =_xll.EQNXTDZ($A$1,$B42,H$1,$B$1) -> 0 | I42: =_xll.EQNXTDZ($A$1,$B42,I$1,$B$1) -> 0 | J42: =_xll.EQNXTDZ($A$1,$B42,J$1,$B$1) -> 0 | ... BV42: =_xll.EQNXTDZ($A$1,$B42,BV$1,$B$1) -> 0
A44: Field Description | B44: Field Name
A45: Equity Capital | B45: QTR_EQUITY_CAP | C45: =_xll.EQNXTDZ($A$1,$B45,C$1,$B$1) -> 0 | D45: =_xll.EQNXTDZ($A$1,$B45,D$1,$B$1) -> 0 | E45: =_xll.EQNXTDZ($A$1,$B45,E$1,$B$1) -> 0 | F45: =_xll.EQNXTDZ($A$1,$B45,F$1,$B$1) -> 0 | G45: =_xll.EQNXTDZ($A$1,$B45,G$1,$B$1) -> 0 | H45: =_xll.EQNXTDZ($A$1,$B45,H$1,$B$1) -> 0 | I45: =_xll.EQNXTDZ($A$1,$B45,I$1,$B$1) -> 0 | J45: =_xll.EQNXTDZ($A$1,$B45,J$1,$B$1) -> 0 | ... BV45: =_xll.EQNXTDZ($A$1,$B45,BV$1,$B$1) -> 0
A46: Face Value | B46: QTR_FV | C46: =_xll.EQNXTDZ($A$1,$B46,C$1,$B$1) -> 0 | D46: =_xll.EQNXTDZ($A$1,$B46,D$1,$B$1) -> 0 | E46: =_xll.EQNXTDZ($A$1,$B46,E$1,$B$1) -> 0 | F46: =_xll.EQNXTDZ($A$1,$B46,F$1,$B$1) -> 0 | G46: =_xll.EQNXTDZ($A$1,$B46,G$1,$B$1) -> 0 | H46: =_xll.EQNXTDZ($A$1,$B46,H$1,$B$1) -> 0 | I46: =_xll.EQNXTDZ($A$1,$B46,I$1,$B$1) -> 0 | J46: =_xll.EQNXTDZ($A$1,$B46,J$1,$B$1) -> 0 | ... BV46: =_xll.EQNXTDZ($A$1,$B46,BV$1,$B$1) -> 0
A47: Month End | B47: BMONTH_MONTHEND | C47: =_xll.EQNXTDZ($A$1,$B47,C$5) -> 0 | D47: =_xll.EQNXTDZ($A$1,$B47,D$5) -> 0 | E47: =_xll.EQNXTDZ($A$1,$B47,E$5) -> 0 | F47: =_xll.EQNXTDZ($A$1,$B47,F$5) -> 0 | G47: =_xll.EQNXTDZ($A$1,$B47,G$5) -> 0 | H47: =_xll.EQNXTDZ($A$1,$B47,H$5) -> 0 | I47: =_xll.EQNXTDZ($A$1,$B47,I$5) -> 0 | J47: =_xll.EQNXTDZ($A$1,$B47,J$5) -> 0 | ... BV47: =_xll.EQNXTDZ($A$1,$B47,BV$5) -> 0
A48: Close | B48: BMONTH_CLOSE | C48: =_xll.EQNXTDZ($A$1,$B48,C$5) -> 0 | D48: =_xll.EQNXTDZ($A$1,$B48,D$5) -> 0 | E48: =_xll.EQNXTDZ($A$1,$B48,E$5) -> 0 | F48: =_xll.EQNXTDZ($A$1,$B48,F$5) -> 0 | G48: =_xll.EQNXTDZ($A$1,$B48,G$5) -> 0 | H48: =_xll.EQNXTDZ($A$1,$B48,H$5) -> 0 | I48: =_xll.EQNXTDZ($A$1,$B48,I$5) -> 0 | J48: =_xll.EQNXTDZ($A$1,$B48,J$5) -> 0 | ... BV48: =_xll.EQNXTDZ($A$1,$B48,BV$5) -> 0
A49: Total of Promoter and Promoter Group | B49: SHP_TPFTOTALPROMOTER | C49: =_xll.EQNXTDZ($A$1,$B49,C$5) -> 0 | D49: =_xll.EQNXTDZ($A$1,$B49,D$5) -> 0 | E49: =_xll.EQNXTDZ($A$1,$B49,E$5) -> 0 | F49: =_xll.EQNXTDZ($A$1,$B49,F$5) -> 0 | G49: =_xll.EQNXTDZ($A$1,$B49,G$5) -> 0 | H49: =_xll.EQNXTDZ($A$1,$B49,H$5) -> 0 | I49: =_xll.EQNXTDZ($A$1,$B49,I$5) -> 0 | J49: =_xll.EQNXTDZ($A$1,$B49,J$5) -> 0 | ... BV49: =_xll.EQNXTDZ($A$1,$B49,BV$5) -> 0
A50: Total of Promoter and Promoter Group Pledged | B50: SHP_PSHFTOTALPROMOTER | C50: =_xll.EQNXTDZ($A$1,$B50,C$5) -> 0 | D50: =_xll.EQNXTDZ($A$1,$B50,D$5) -> 0 | E50: =_xll.EQNXTDZ($A$1,$B50,E$5) -> 0 | F50: =_xll.EQNXTDZ($A$1,$B50,F$5) -> 0 | G50: =_xll.EQNXTDZ($A$1,$B50,G$5) -> 0 | H50: =_xll.EQNXTDZ($A$1,$B50,H$5) -> 0 | I50: =_xll.EQNXTDZ($A$1,$B50,I$5) -> 0 | J50: =_xll.EQNXTDZ($A$1,$B50,J$5) -> 0 | ... BV50: =_xll.EQNXTDZ($A$1,$B50,BV$5) -> 0
A54: Field Description | B54: Field Name | C54: =_xll.EQNXTDZ($A$1,$B54,C$5) -> 0 | D54: =_xll.EQNXTDZ($A$1,$B54,D$5) -> 0 | E54: =_xll.EQNXTDZ($A$1,$B54,E$5) -> 0 | F54: =_xll.EQNXTDZ($A$1,$B54,F$5) -> 0 | G54: =_xll.EQNXTDZ($A$1,$B54,G$5) -> 0 | H54: =_xll.EQNXTDZ($A$1,$B54,H$5) -> 0 | I54: =_xll.EQNXTDZ($A$1,$B54,I$5) -> 0 | J54: =_xll.EQNXTDZ($A$1,$B54,J$5) -> 0 | ... BV54: =_xll.EQNXTDZ($A$1,$B54,BV$5) -> 0
A55: Year End | B55: QTRB_DATE_END | C55: =_xll.EQNXTDZ($A$1,$B55,C$5,$B$1) -> 0 | D55: =_xll.EQNXTDZ($A$1,$B55,D$5,$B$1) -> 0 | E55: =_xll.EQNXTDZ($A$1,$B55,E$5,$B$1) -> 0 | F55: =_xll.EQNXTDZ($A$1,$B55,F$5,$B$1) -> 0 | G55: =_xll.EQNXTDZ($A$1,$B55,G$5,$B$1) -> 0 | H55: =_xll.EQNXTDZ($A$1,$B55,H$5,$B$1) -> 0 | I55: =_xll.EQNXTDZ($A$1,$B55,I$5,$B$1) -> 0 | J55: =_xll.EQNXTDZ($A$1,$B55,J$5,$B$1) -> 0 | ... BV55: =_xll.EQNXTDZ($A$1,$B55,BV$5,$B$1) -> 0
A56: Share Capital | B56: QTRB_SHARE_CAPITAL | C56: =_xll.EQNXTDZ($A$1,$B56,C$5,$B$1) -> 0 | D56: =_xll.EQNXTDZ($A$1,$B56,D$5,$B$1) -> 0 | E56: =_xll.EQNXTDZ($A$1,$B56,E$5,$B$1) -> 0 | F56: =_xll.EQNXTDZ($A$1,$B56,F$5,$B$1) -> 0 | G56: =_xll.EQNXTDZ($A$1,$B56,G$5,$B$1) -> 0 | H56: =_xll.EQNXTDZ($A$1,$B56,H$5,$B$1) -> 0 | I56: =_xll.EQNXTDZ($A$1,$B56,I$5,$B$1) -> 0 | J56: =_xll.EQNXTDZ($A$1,$B56,J$5,$B$1) -> 0 | ... BV56: =_xll.EQNXTDZ($A$1,$B56,BV$5,$B$1) -> 0
A57: Share Warrants & outstandings | B57: QTRB_SHAREWARNDOUT | C57: =_xll.EQNXTDZ($A$1,$B57,C$5,$B$1) -> 0 | D57: =_xll.EQNXTDZ($A$1,$B57,D$5,$B$1) -> 0 | E57: =_xll.EQNXTDZ($A$1,$B57,E$5,$B$1) -> 0 | F57: =_xll.EQNXTDZ($A$1,$B57,F$5,$B$1) -> 0 | G57: =_xll.EQNXTDZ($A$1,$B57,G$5,$B$1) -> 0 | H57: =_xll.EQNXTDZ($A$1,$B57,H$5,$B$1) -> 0 | I57: =_xll.EQNXTDZ($A$1,$B57,I$5,$B$1) -> 0 | J57: =_xll.EQNXTDZ($A$1,$B57,J$5,$B$1) -> 0 | ... BV57: =_xll.EQNXTDZ($A$1,$B57,BV$5,$B$1) -> 0
A58: Reserves & Surplus | B58: QTRB_RESERVE | C58: =_xll.EQNXTDZ($A$1,$B58,C$5,$B$1) -> 0 | D58: =_xll.EQNXTDZ($A$1,$B58,D$5,$B$1) -> 0 | E58: =_xll.EQNXTDZ($A$1,$B58,E$5,$B$1) -> 0 | F58: =_xll.EQNXTDZ($A$1,$B58,F$5,$B$1) -> 0 | G58: =_xll.EQNXTDZ($A$1,$B58,G$5,$B$1) -> 0 | H58: =_xll.EQNXTDZ($A$1,$B58,H$5,$B$1) -> 0 | I58: =_xll.EQNXTDZ($A$1,$B58,I$5,$B$1) -> 0 | J58: =_xll.EQNXTDZ($A$1,$B58,J$5,$B$1) -> 0 | ... BV58: =_xll.EQNXTDZ($A$1,$B58,BV$5,$B$1) -> 0
A59: Shareholder's Funds | B59: QTRB_SHAREHODERS_FUNDS | C59: =_xll.EQNXTDZ($A$1,$B59,C$5,$B$1) -> 0 | D59: =_xll.EQNXTDZ($A$1,$B59,D$5,$B$1) -> 0 | E59: =_xll.EQNXTDZ($A$1,$B59,E$5,$B$1) -> 0 | F59: =_xll.EQNXTDZ($A$1,$B59,F$5,$B$1) -> 0 | G59: =_xll.EQNXTDZ($A$1,$B59,G$5,$B$1) -> 0 | H59: =_xll.EQNXTDZ($A$1,$B59,H$5,$B$1) -> 0 | I59: =_xll.EQNXTDZ($A$1,$B59,I$5,$B$1) -> 0 | J59: =_xll.EQNXTDZ($A$1,$B59,J$5,$B$1) -> 0 | ... BV59: =_xll.EQNXTDZ($A$1,$B59,BV$5,$B$1) -> 0
A60: Minority Interest | B60: QTRB_MINORITY_INTEREST_BS | C60: =_xll.EQNXTDZ($A$1,$B60,C$5,$B$1) -> 0 | D60: =_xll.EQNXTDZ($A$1,$B60,D$5,$B$1) -> 0 | E60: =_xll.EQNXTDZ($A$1,$B60,E$5,$B$1) -> 0 | F60: =_xll.EQNXTDZ($A$1,$B60,F$5,$B$1) -> 0 | G60: =_xll.EQNXTDZ($A$1,$B60,G$5,$B$1) -> 0 | H60: =_xll.EQNXTDZ($A$1,$B60,H$5,$B$1) -> 0 | I60: =_xll.EQNXTDZ($A$1,$B60,I$5,$B$1) -> 0 | J60: =_xll.EQNXTDZ($A$1,$B60,J$5,$B$1) -> 0 | ... BV60: =_xll.EQNXTDZ($A$1,$B60,BV$5,$B$1) -> 0
A61: Long Term Borrowings | B61: QTRB_TOTAL_DEBTS | C61: =_xll.EQNXTDZ($A$1,$B61,C$5,$B$1) -> 0 | D61: =_xll.EQNXTDZ($A$1,$B61,D$5,$B$1) -> 0 | E61: =_xll.EQNXTDZ($A$1,$B61,E$5,$B$1) -> 0 | F61: =_xll.EQNXTDZ($A$1,$B61,F$5,$B$1) -> 0 | G61: =_xll.EQNXTDZ($A$1,$B61,G$5,$B$1) -> 0 | H61: =_xll.EQNXTDZ($A$1,$B61,H$5,$B$1) -> 0 | I61: =_xll.EQNXTDZ($A$1,$B61,I$5,$B$1) -> 0 | J61: =_xll.EQNXTDZ($A$1,$B61,J$5,$B$1) -> 0 | ... BV61: =_xll.EQNXTDZ($A$1,$B61,BV$5,$B$1) -> 0
A62: Secured Loans | B62: QTRB_SECURED_LOANS | C62: =_xll.EQNXTDZ($A$1,$B62,C$5,$B$1) -> 0 | D62: =_xll.EQNXTDZ($A$1,$B62,D$5,$B$1) -> 0 | E62: =_xll.EQNXTDZ($A$1,$B62,E$5,$B$1) -> 0 | F62: =_xll.EQNXTDZ($A$1,$B62,F$5,$B$1) -> 0 | G62: =_xll.EQNXTDZ($A$1,$B62,G$5,$B$1) -> 0 | H62: =_xll.EQNXTDZ($A$1,$B62,H$5,$B$1) -> 0 | I62: =_xll.EQNXTDZ($A$1,$B62,I$5,$B$1) -> 0 | J62: =_xll.EQNXTDZ($A$1,$B62,J$5,$B$1) -> 0 | ... BV62: =_xll.EQNXTDZ($A$1,$B62,BV$5,$B$1) -> 0
A63: Unsecured Loans | B63: QTRB_UNSECURED_LOANS_NF | C63: =_xll.EQNXTDZ($A$1,$B63,C$5,$B$1) -> 0 | D63: =_xll.EQNXTDZ($A$1,$B63,D$5,$B$1) -> 0 | E63: =_xll.EQNXTDZ($A$1,$B63,E$5,$B$1) -> 0 | F63: =_xll.EQNXTDZ($A$1,$B63,F$5,$B$1) -> 0 | G63: =_xll.EQNXTDZ($A$1,$B63,G$5,$B$1) -> 0 | H63: =_xll.EQNXTDZ($A$1,$B63,H$5,$B$1) -> 0 | I63: =_xll.EQNXTDZ($A$1,$B63,I$5,$B$1) -> 0 | J63: =_xll.EQNXTDZ($A$1,$B63,J$5,$B$1) -> 0 | ... BV63: =_xll.EQNXTDZ($A$1,$B63,BV$5,$B$1) -> 0
A64: Other Long Term Liabilities | B64: QTRB_OTHER_LT_LIABILITIES | C64: =_xll.EQNXTDZ($A$1,$B64,C$5,$B$1) -> 0 | D64: =_xll.EQNXTDZ($A$1,$B64,D$5,$B$1) -> 0 | E64: =_xll.EQNXTDZ($A$1,$B64,E$5,$B$1) -> 0 | F64: =_xll.EQNXTDZ($A$1,$B64,F$5,$B$1) -> 0 | G64: =_xll.EQNXTDZ($A$1,$B64,G$5,$B$1) -> 0 | H64: =_xll.EQNXTDZ($A$1,$B64,H$5,$B$1) -> 0 | I64: =_xll.EQNXTDZ($A$1,$B64,I$5,$B$1) -> 0 | J64: =_xll.EQNXTDZ($A$1,$B64,J$5,$B$1) -> 0 | ... BV64: =_xll.EQNXTDZ($A$1,$B64,BV$5,$B$1) -> 0
A65: Long Term Trade Payables | B65: QTRB_LT_TRADE_PAYABLE | C65: =_xll.EQNXTDZ($A$1,$B65,C$5,$B$1) -> 0 | D65: =_xll.EQNXTDZ($A$1,$B65,D$5,$B$1) -> 0 | E65: =_xll.EQNXTDZ($A$1,$B65,E$5,$B$1) -> 0 | F65: =_xll.EQNXTDZ($A$1,$B65,F$5,$B$1) -> 0 | G65: =_xll.EQNXTDZ($A$1,$B65,G$5,$B$1) -> 0 | H65: =_xll.EQNXTDZ($A$1,$B65,H$5,$B$1) -> 0 | I65: =_xll.EQNXTDZ($A$1,$B65,I$5,$B$1) -> 0 | J65: =_xll.EQNXTDZ($A$1,$B65,J$5,$B$1) -> 0 | ... BV65: =_xll.EQNXTDZ($A$1,$B65,BV$5,$B$1) -> 0
A66: Lont Term Provisions | B66: QTRB_LT_PROVISIONS | C66: =_xll.EQNXTDZ($A$1,$B66,C$5,$B$1) -> 0 | D66: =_xll.EQNXTDZ($A$1,$B66,D$5,$B$1) -> 0 | E66: =_xll.EQNXTDZ($A$1,$B66,E$5,$B$1) -> 0 | F66: =_xll.EQNXTDZ($A$1,$B66,F$5,$B$1) -> 0 | G66: =_xll.EQNXTDZ($A$1,$B66,G$5,$B$1) -> 0 | H66: =_xll.EQNXTDZ($A$1,$B66,H$5,$B$1) -> 0 | I66: =_xll.EQNXTDZ($A$1,$B66,I$5,$B$1) -> 0 | J66: =_xll.EQNXTDZ($A$1,$B66,J$5,$B$1) -> 0 | ... BV66: =_xll.EQNXTDZ($A$1,$B66,BV$5,$B$1) -> 0
... A97: Total Assets | B97: QTRB_TOTAL_APPLICATIONS | C97: =_xll.EQNXTDZ($A$1,$B97,C$5,$B$1) -> 0 | D97: =_xll.EQNXTDZ($A$1,$B97,D$5,$B$1) -> 0 | E97: =_xll.EQNXTDZ($A$1,$B97,E$5,$B$1) -> 0 | F97: =_xll.EQNXTDZ($A$1,$B97,F$5,$B$1) -> 0 | G97: =_xll.EQNXTDZ($A$1,$B97,G$5,$B$1) -> 0 | H97: =_xll.EQNXTDZ($A$1,$B97,H$5,$B$1) -> 0 | I97: =_xll.EQNXTDZ($A$1,$B97,I$5,$B$1) -> 0 | J97: =_xll.EQNXTDZ($A$1,$B97,J$5,$B$1) -> 0 | ... BV97: =_xll.EQNXTDZ($A$1,$B97,BV$5,$B$1) -> 0

Sheet Annual Raw
A1: 322918 | C1: 200103 | D1: 200203 | E1: 200303 | F1: 200403 | G1: 200503 | H1: 200603 | I1: 200703 | J1: 200803 | K1: 200903 | L1: 201003 | M1: 201103 | N1: 201203 | O1: 201303 | P1: 201403 | Q1: 201503 | R1: 201603 | S1: 201703 | T1: 201803 | U1: 201903 | V1: 202003 | W1: 202103 | X1: 202203 | Y1: 202303 | Z1: 202403 | AA1: 202503 | AB1: 202603 | AC1: 202703 | AD1: 202803 | AE1: 202903 | AF1: 203003
A3: Field Description | B3: Field Name
A4: Company Name | B4: CD_COMPNAME | C4: =_xll.EQNXTDZ(A1,B4,"L") -> Tata Motors Ltd.
A5: Year End | B5: PL_YEAR_END | C5: =_xll.EQNXTDZ($A$1,$B5,C$1,$B$1) -> 0 | D5: =_xll.EQNXTDZ($A$1,$B5,D$1,$B$1) -> 0 | E5: =_xll.EQNXTDZ($A$1,$B5,E$1,$B$1) -> 0 | F5: =_xll.EQNXTDZ($A$1,$B5,F$1,$B$1) -> 0 | G5: =_xll.EQNXTDZ($A$1,$B5,G$1,$B$1) -> 0 | H5: =_xll.EQNXTDZ($A$1,$B5,H$1,$B$1) -> 0 | I5: =_xll.EQNXTDZ($A$1,$B5,I$1,$B$1) -> 0 | J5: =_xll.EQNXTDZ($A$1,$B5,J$1,$B$1) -> 0 | ... AF5: =_xll.EQNXTDZ($A$1,$B5,AF$1,$B$1) -> 0
A6: Sales Turnover | B6: PL_TOTAL_GROSS_SALES | C6: =_xll.EQNXTDZ($A$1,$B6,C$1,$B$1) -> 0 | D6: =_xll.EQNXTDZ($A$1,$B6,D$1,$B$1) -> 0 | E6: =_xll.EQNXTDZ($A$1,$B6,E$1,$B$1) -> 0 | F6: =_xll.EQNXTDZ($A$1,$B6,F$1,$B$1) -> 0 | G6: =_xll.EQNXTDZ($A$1,$B6,G$1,$B$1) -> 0 | H6: =_xll.EQNXTDZ($A$1,$B6,H$1,$B$1) -> 0 | I6: =_xll.EQNXTDZ($A$1,$B6,I$1,$B$1) -> 0 | J6: =_xll.EQNXTDZ($A$1,$B6,J$1,$B$1) -> 0 | ... AF6: =_xll.EQNXTDZ($A$1,$B6,AF$1,$B$1) -> 0
A7: Less: Inter divisional transfers | B7: PL_INTER_DIV_TRF | C7: =_xll.EQNXTDZ($A$1,$B7,C$1,$B$1) -> 0 | D7: =_xll.EQNXTDZ($A$1,$B7,D$1,$B$1) -> 0 | E7: =_xll.EQNXTDZ($A$1,$B7,E$1,$B$1) -> 0 | F7: =_xll.EQNXTDZ($A$1,$B7,F$1,$B$1) -> 0 | G7: =_xll.EQNXTDZ($A$1,$B7,G$1,$B$1) -> 0 | H7: =_xll.EQNXTDZ($A$1,$B7,H$1,$B$1) -> 0 | I7: =_xll.EQNXTDZ($A$1,$B7,I$1,$B$1) -> 0 | J7: =_xll.EQNXTDZ($A$1,$B7,J$1,$B$1) -> 0 | ... AF7: =_xll.EQNXTDZ($A$1,$B7,AF$1,$B$1) -> 0
A8: Less: Sales Returns | B8: PL_SALES_RETURN | C8: =_xll.EQNXTDZ($A$1,$B8,C$1,$B$1) -> 0 | D8: =_xll.EQNXTDZ($A$1,$B8,D$1,$B$1) -> 0 | E8: =_xll.EQNXTDZ($A$1,$B8,E$1,$B$1) -> 0 | F8: =_xll.EQNXTDZ($A$1,$B8,F$1,$B$1) -> 0 | G8: =_xll.EQNXTDZ($A$1,$B8,G$1,$B$1) -> 0 | H8: =_xll.EQNXTDZ($A$1,$B8,H$1,$B$1) -> 0 | I8: =_xll.EQNXTDZ($A$1,$B8,I$1,$B$1) -> 0 | J8: =_xll.EQNXTDZ($A$1,$B8,J$1,$B$1) -> 0 | ... AF8: =_xll.EQNXTDZ($A$1,$B8,AF$1,$B$1) -> 0
A9: Less: Excise | B9: PL_EXCISE | C9: =_xll.EQNXTDZ($A$1,$B9,C$1,$B$1) -> 0 | D9: =_xll.EQNXTDZ($A$1,$B9,D$1,$B$1) -> 0 | E9: =_xll.EQNXTDZ($A$1,$B9,E$1,$B$1) -> 0 | F9: =_xll.EQNXTDZ($A$1,$B9,F$1,$B$1) -> 0 | G9: =_xll.EQNXTDZ($A$1,$B9,G$1,$B$1) -> 0 | H9: =_xll.EQNXTDZ($A$1,$B9,H$1,$B$1) -> 0 | I9: =_xll.EQNXTDZ($A$1,$B9,I$1,$B$1) -> 0 | J9: =_xll.EQNXTDZ($A$1,$B9,J$1,$B$1) -> 0 | ... AF9: =_xll.EQNXTDZ($A$1,$B9,AF$1,$B$1) -> 0
A10: Net Sales | B10: PL_NET_SALES | C10: =_xll.EQNXTDZ($A$1,$B10,C$1,$B$1) -> 0 | D10: =_xll.EQNXTDZ($A$1,$B10,D$1,$B$1) -> 0 | E10: =_xll.EQNXTDZ($A$1,$B10,E$1,$B$1) -> 0 | F10: =_xll.EQNXTDZ($A$1,$B10,F$1,$B$1) -> 0 | G10: =_xll.EQNXTDZ($A$1,$B10,G$1,$B$1) -> 0 | H10: =_xll.EQNXTDZ($A$1,$B10,H$1,$B$1) -> 0 | I10: =_xll.EQNXTDZ($A$1,$B10,I$1,$B$1) -> 0 | J10: =_xll.EQNXTDZ($A$1,$B10,J$1,$B$1) -> 0 | ... AF10: =_xll.EQNXTDZ($A$1,$B10,AF$1,$B$1) -> 0
A11: Increase/Decrease in Stock | B11: PL_INC_DEC_INVENTORY | C11: =_xll.EQNXTDZ($A$1,$B11,C$1,$B$1) -> 0 | D11: =_xll.EQNXTDZ($A$1,$B11,D$1,$B$1) -> 0 | E11: =_xll.EQNXTDZ($A$1,$B11,E$1,$B$1) -> 0 | F11: =_xll.EQNXTDZ($A$1,$B11,F$1,$B$1) -> 0 | G11: =_xll.EQNXTDZ($A$1,$B11,G$1,$B$1) -> 0 | H11: =_xll.EQNXTDZ($A$1,$B11,H$1,$B$1) -> 0 | I11: =_xll.EQNXTDZ($A$1,$B11,I$1,$B$1) -> 0 | J11: =_xll.EQNXTDZ($A$1,$B11,J$1,$B$1) -> 0 | ... AF11: =_xll.EQNXTDZ($A$1,$B11,AF$1,$B$1) -> 0
A12: Raw Material Consumed | B12: PL_RAW_MATRS_CONSUMED | C12: =_xll.EQNXTDZ($A$1,$B12,C$1,$B$1) -> 0 | D12: =_xll.EQNXTDZ($A$1,$B12,D$1,$B$1) -> 0 | E12: =_xll.EQNXTDZ($A$1,$B12,E$1,$B$1) -> 0 | F12: =_xll.EQNXTDZ($A$1,$B12,F$1,$B$1) -> 0 | G12: =_xll.EQNXTDZ($A$1,$B12,G$1,$B$1) -> 0 | H12: =_xll.EQNXTDZ($A$1,$B12,H$1,$B$1) -> 0 | I12: =_xll.EQNXTDZ($A$1,$B12,I$1,$B$1) -> 0 | J12: =_xll.EQNXTDZ($A$1,$B12,J$1,$B$1) -> 0 | ... AF12: =_xll.EQNXTDZ($A$1,$B12,AF$1,$B$1) -> 0
A13: Power & Fuel Cost | B13: PL_POWER_FUEL | C13: =_xll.EQNXTDZ($A$1,$B13,C$1,$B$1) -> 0 | D13: =_xll.EQNXTDZ($A$1,$B13,D$1,$B$1) -> 0 | E13: =_xll.EQNXTDZ($A$1,$B13,E$1,$B$1) -> 0 | F13: =_xll.EQNXTDZ($A$1,$B13,F$1,$B$1) -> 0 | G13: =_xll.EQNXTDZ($A$1,$B13,G$1,$B$1) -> 0 | H13: =_xll.EQNXTDZ($A$1,$B13,H$1,$B$1) -> 0 | I13: =_xll.EQNXTDZ($A$1,$B13,I$1,$B$1) -> 0 | J13: =_xll.EQNXTDZ($A$1,$B13,J$1,$B$1) -> 0 | ... AF13: =_xll.EQNXTDZ($A$1,$B13,AF$1,$B$1) -> 0
A14: Employee Cost | B14: PL_EMPLOYEES | C14: =_xll.EQNXTDZ($A$1,$B14,C$1,$B$1) -> 0 | D14: =_xll.EQNXTDZ($A$1,$B14,D$1,$B$1) -> 0 | E14: =_xll.EQNXTDZ($A$1,$B14,E$1,$B$1) -> 0 | F14: =_xll.EQNXTDZ($A$1,$B14,F$1,$B$1) -> 0 | G14: =_xll.EQNXTDZ($A$1,$B14,G$1,$B$1) -> 0 | H14: =_xll.EQNXTDZ($A$1,$B14,H$1,$B$1) -> 0 | I14: =_xll.EQNXTDZ($A$1,$B14,I$1,$B$1) -> 0 | J14: =_xll.EQNXTDZ($A$1,$B14,J$1,$B$1) -> 0 | ... AF14: =_xll.EQNXTDZ($A$1,$B14,AF$1,$B$1) -> 0
A15: Operating & Manufacturing Expenses | B15: PL_GEN_OTHER_MFG_EXPS | C15: =_xll.EQNXTDZ($A$1,$B15,C$1,$B$1) -> 0 | D15: =_xll.EQNXTDZ($A$1,$B15,D$1,$B$1) -> 0 | E15: =_xll.EQNXTDZ($A$1,$B15,E$1,$B$1) -> 0 | F15: =_xll.EQNXTDZ($A$1,$B15,F$1,$B$1) -> 0 | G15: =_xll.EQNXTDZ($A$1,$B15,G$1,$B$1) -> 0 | H15: =_xll.EQNXTDZ($A$1,$B15,H$1,$B$1) -> 0 | I15: =_xll.EQNXTDZ($A$1,$B15,I$1,$B$1) -> 0 | J15: =_xll.EQNXTDZ($A$1,$B15,J$1,$B$1) -> 0 | ... AF15: =_xll.EQNXTDZ($A$1,$B15,AF$1,$B$1) -> 0
A16: Cost of Software development | B16: PL_COST_SW | C16: =_xll.EQNXTDZ($A$1,$B16,C$1,$B$1) -> 0 | D16: =_xll.EQNXTDZ($A$1,$B16,D$1,$B$1) -> 0 | E16: =_xll.EQNXTDZ($A$1,$B16,E$1,$B$1) -> 0 | F16: =_xll.EQNXTDZ($A$1,$B16,F$1,$B$1) -> 0 | G16: =_xll.EQNXTDZ($A$1,$B16,G$1,$B$1) -> 0 | H16: =_xll.EQNXTDZ($A$1,$B16,H$1,$B$1) -> 0 | I16: =_xll.EQNXTDZ($A$1,$B16,I$1,$B$1) -> 0 | J16: =_xll.EQNXTDZ($A$1,$B16,J$1,$B$1) -> 0 | ... AF16: =_xll.EQNXTDZ($A$1,$B16,AF$1,$B$1) -> 0
... A36: Profit After Tax from Discontinued Operations | B36: PL_PAT_DIS_OP | C36: =_xll.EQNXTDZ($A$1,$B36,C$1,$B$1) -> 0 | D36: =_xll.EQNXTDZ($A$1,$B36,D$1,$B$1) -> 0 | E36: =_xll.EQNXTDZ($A$1,$B36,E$1,$B$1) -> 0 | F36: =_xll.EQNXTDZ($A$1,$B36,F$1,$B$1) -> 0 | G36: =_xll.EQNXTDZ($A$1,$B36,G$1,$B$1) -> 0 | H36: =_xll.EQNXTDZ($A$1,$B36,H$1,$B$1) -> 0 | I36: =_xll.EQNXTDZ($A$1,$B36,I$1,$B$1) -> 0 | J36: =_xll.EQNXTDZ($A$1,$B36,J$1,$B$1) -> 0 | ... AF36: =_xll.EQNXTDZ($A$1,$B36,AF$1,$B$1) -> 0
A39: Field Description | B39: Field Name
A40: Year End | B40: BS_YEAR_END | C40: =_xll.EQNXTDZ($A$1,$B40,C$1,$B$1) -> 0 | D40: =_xll.EQNXTDZ($A$1,$B40,D$1,$B$1) -> 0 | E40: =_xll.EQNXTDZ($A$1,$B40,E$1,$B$1) -> 0 | F40: =_xll.EQNXTDZ($A$1,$B40,F$1,$B$1) -> 0 | G40: =_xll.EQNXTDZ($A$1,$B40,G$1,$B$1) -> 0 | H40: =_xll.EQNXTDZ($A$1,$B40,H$1,$B$1) -> 0 | I40: =_xll.EQNXTDZ($A$1,$B40,I$1,$B$1) -> 0 | J40: =_xll.EQNXTDZ($A$1,$B40,J$1,$B$1) -> 0 | ... AF40: =_xll.EQNXTDZ($A$1,$B40,AF$1,$B$1) -> 0
A41: Share Capital | B41: BS_SHARE_CAPITAL | C41: =_xll.EQNXTDZ($A$1,$B41,C$1,$B$1) -> 0 | D41: =_xll.EQNXTDZ($A$1,$B41,D$1,$B$1) -> 0 | E41: =_xll.EQNXTDZ($A$1,$B41,E$1,$B$1) -> 0 | F41: =_xll.EQNXTDZ($A$1,$B41,F$1,$B$1) -> 0 | G41: =_xll.EQNXTDZ($A$1,$B41,G$1,$B$1) -> 0 | H41: =_xll.EQNXTDZ($A$1,$B41,H$1,$B$1) -> 0 | I41: =_xll.EQNXTDZ($A$1,$B41,I$1,$B$1) -> 0 | J41: =_xll.EQNXTDZ($A$1,$B41,J$1,$B$1) -> 0 | ... AF41: =_xll.EQNXTDZ($A$1,$B41,AF$1,$B$1) -> 0
A42: Share Warrants & Outstandings | B42: BS_SHAREWROUTST | C42: =_xll.EQNXTDZ($A$1,$B42,C$1,$B$1) -> 0 | D42: =_xll.EQNXTDZ($A$1,$B42,D$1,$B$1) -> 0 | E42: =_xll.EQNXTDZ($A$1,$B42,E$1,$B$1) -> 0 | F42: =_xll.EQNXTDZ($A$1,$B42,F$1,$B$1) -> 0 | G42: =_xll.EQNXTDZ($A$1,$B42,G$1,$B$1) -> 0 | H42: =_xll.EQNXTDZ($A$1,$B42,H$1,$B$1) -> 0 | I42: =_xll.EQNXTDZ($A$1,$B42,I$1,$B$1) -> 0 | J42: =_xll.EQNXTDZ($A$1,$B42,J$1,$B$1) -> 0 | ... AF42: =_xll.EQNXTDZ($A$1,$B42,AF$1,$B$1) -> 0
A43: Total Reserves | B43: BS_RESERVE | C43: =_xll.EQNXTDZ($A$1,$B43,C$1,$B$1) -> 0 | D43: =_xll.EQNXTDZ($A$1,$B43,D$1,$B$1) -> 0 | E43: =_xll.EQNXTDZ($A$1,$B43,E$1,$B$1) -> 0 | F43: =_xll.EQNXTDZ($A$1,$B43,F$1,$B$1) -> 0 | G43: =_xll.EQNXTDZ($A$1,$B43,G$1,$B$1) -> 0 | H43: =_xll.EQNXTDZ($A$1,$B43,H$1,$B$1) -> 0 | I43: =_xll.EQNXTDZ($A$1,$B43,I$1,$B$1) -> 0 | J43: =_xll.EQNXTDZ($A$1,$B43,J$1,$B$1) -> 0 | ... AF43: =_xll.EQNXTDZ($A$1,$B43,AF$1,$B$1) -> 0
A44: Shareholder's Funds | B44: BS_SHAREHODERS_FUNDS | C44: =_xll.EQNXTDZ($A$1,$B44,C$1,$B$1) -> 0 | D44: =_xll.EQNXTDZ($A$1,$B44,D$1,$B$1) -> 0 | E44: =_xll.EQNXTDZ($A$1,$B44,E$1,$B$1) -> 0 | F44: =_xll.EQNXTDZ($A$1,$B44,F$1,$B$1) -> 0 | G44: =_xll.EQNXTDZ($A$1,$B44,G$1,$B$1) -> 0 | H44: =_xll.EQNXTDZ($A$1,$B44,H$1,$B$1) -> 0 | I44: =_xll.EQNXTDZ($A$1,$B44,I$1,$B$1) -> 0 | J44: =_xll.EQNXTDZ($A$1,$B44,J$1,$B$1) -> 0 | ... AF44: =_xll.EQNXTDZ($A$1,$B44,AF$1,$B$1) -> 0
A45: Minority Interest | B45: BS_MINORITY_INTEREST | C45: =_xll.EQNXTDZ($A$1,$B45,C$1,$B$1) -> 0 | D45: =_xll.EQNXTDZ($A$1,$B45,D$1,$B$1) -> 0 | E45: =_xll.EQNXTDZ($A$1,$B45,E$1,$B$1) -> 0 | F45: =_xll.EQNXTDZ($A$1,$B45,F$1,$B$1) -> 0 | G45: =_xll.EQNXTDZ($A$1,$B45,G$1,$B$1) -> 0 | H45: =_xll.EQNXTDZ($A$1,$B45,H$1,$B$1) -> 0 | I45: =_xll.EQNXTDZ($A$1,$B45,I$1,$B$1) -> 0 | J45: =_xll.EQNXTDZ($A$1,$B45,J$1,$B$1) -> 0 | ... AF45: =_xll.EQNXTDZ($A$1,$B45,AF$1,$B$1) -> 0
A46: Long-Term Borrowings | B46: BS_LTRM_BORROWING | C46: =_xll.EQNXTDZ($A$1,$B46,C$1,$B$1) -> 0 | D46: =_xll.EQNXTDZ($A$1,$B46,D$1,$B$1) -> 0 | E46: =_xll.EQNXTDZ($A$1,$B46,E$1,$B$1) -> 0 | F46: =_xll.EQNXTDZ($A$1,$B46,F$1,$B$1) -> 0 | G46: =_xll.EQNXTDZ($A$1,$B46,G$1,$B$1) -> 0 | H46: =_xll.EQNXTDZ($A$1,$B46,H$1,$B$1) -> 0 | I46: =_xll.EQNXTDZ($A$1,$B46,I$1,$B$1) -> 0 | J46: =_xll.EQNXTDZ($A$1,$B46,J$1,$B$1) -> 0 | ... AF46: =_xll.EQNXTDZ($A$1,$B46,AF$1,$B$1) -> 0
A47: Secured Loans | B47: BS_SECURED_LOANS | C47: =_xll.EQNXTDZ($A$1,$B47,C$1,$B$1) -> 0 | D47: =_xll.EQNXTDZ($A$1,$B47,D$1,$B$1) -> 0 | E47: =_xll.EQNXTDZ($A$1,$B47,E$1,$B$1) -> 0 | F47: =_xll.EQNXTDZ($A$1,$B47,F$1,$B$1) -> 0 | G47: =_xll.EQNXTDZ($A$1,$B47,G$1,$B$1) -> 0 | H47: =_xll.EQNXTDZ($A$1,$B47,H$1,$B$1) -> 0 | I47: =_xll.EQNXTDZ($A$1,$B47,I$1,$B$1) -> 0 | J47: =_xll.EQNXTDZ($A$1,$B47,J$1,$B$1) -> 0 | ... AF47: =_xll.EQNXTDZ($A$1,$B47,AF$1,$B$1) -> 0
A48: Unsecured Loans | B48: BS_UNSECURED_LOANS_NF | C48: =_xll.EQNXTDZ($A$1,$B48,C$1,$B$1) -> 0 | D48: =_xll.EQNXTDZ($A$1,$B48,D$1,$B$1) -> 0 | E48: =_xll.EQNXTDZ($A$1,$B48,E$1,$B$1) -> 0 | F48: =_xll.EQNXTDZ($A$1,$B48,F$1,$B$1) -> 0 | G48: =_xll.EQNXTDZ($A$1,$B48,G$1,$B$1) -> 0 | H48: =_xll.EQNXTDZ($A$1,$B48,H$1,$B$1) -> 0 | I48: =_xll.EQNXTDZ($A$1,$B48,I$1,$B$1) -> 0 | J48: =_xll.EQNXTDZ($A$1,$B48,J$1,$B$1) -> 0 | ... AF48: =_xll.EQNXTDZ($A$1,$B48,AF$1,$B$1) -> 0
A49: Deferred Tax Assets / Liabilities | B49: BS_NET_DEF_TAX_NF | C49: =_xll.EQNXTDZ($A$1,$B49,C$1,$B$1) -> 0 | D49: =_xll.EQNXTDZ($A$1,$B49,D$1,$B$1) -> 0 | E49: =_xll.EQNXTDZ($A$1,$B49,E$1,$B$1) -> 0 | F49: =_xll.EQNXTDZ($A$1,$B49,F$1,$B$1) -> 0 | G49: =_xll.EQNXTDZ($A$1,$B49,G$1,$B$1) -> 0 | H49: =_xll.EQNXTDZ($A$1,$B49,H$1,$B$1) -> 0 | I49: =_xll.EQNXTDZ($A$1,$B49,I$1,$B$1) -> 0 | J49: =_xll.EQNXTDZ($A$1,$B49,J$1,$B$1) -> 0 | ... AF49: =_xll.EQNXTDZ($A$1,$B49,AF$1,$B$1) -> 0
A50: Other Long Term Liabilities | B50: BS_OTH_LT_LIAB | C50: =_xll.EQNXTDZ($A$1,$B50,C$1,$B$1) -> 0 | D50: =_xll.EQNXTDZ($A$1,$B50,D$1,$B$1) -> 0 | E50: =_xll.EQNXTDZ($A$1,$B50,E$1,$B$1) -> 0 | F50: =_xll.EQNXTDZ($A$1,$B50,F$1,$B$1) -> 0 | G50: =_xll.EQNXTDZ($A$1,$B50,G$1,$B$1) -> 0 | H50: =_xll.EQNXTDZ($A$1,$B50,H$1,$B$1) -> 0 | I50: =_xll.EQNXTDZ($A$1,$B50,I$1,$B$1) -> 0 | J50: =_xll.EQNXTDZ($A$1,$B50,J$1,$B$1) -> 0 | ... AF50: =_xll.EQNXTDZ($A$1,$B50,AF$1,$B$1) -> 0
A51: Long Term Trade Payables | B51: BS_LT_TRADE_PAYABLES | C51: =_xll.EQNXTDZ($A$1,$B51,C$1,$B$1) -> 0 | D51: =_xll.EQNXTDZ($A$1,$B51,D$1,$B$1) -> 0 | E51: =_xll.EQNXTDZ($A$1,$B51,E$1,$B$1) -> 0 | F51: =_xll.EQNXTDZ($A$1,$B51,F$1,$B$1) -> 0 | G51: =_xll.EQNXTDZ($A$1,$B51,G$1,$B$1) -> 0 | H51: =_xll.EQNXTDZ($A$1,$B51,H$1,$B$1) -> 0 | I51: =_xll.EQNXTDZ($A$1,$B51,I$1,$B$1) -> 0 | J51: =_xll.EQNXTDZ($A$1,$B51,J$1,$B$1) -> 0 | ... AF51: =_xll.EQNXTDZ($A$1,$B51,AF$1,$B$1) -> 0
... A99: Estimated Capital Contracts Remaining | B99: BS_ESTIMATED_CAPITAL_CONTRACT | C99: =_xll.EQNXTDZ($A$1,$B99,C$1,$B$1) -> 0 | D99: =_xll.EQNXTDZ($A$1,$B99,D$1,$B$1) -> 0 | E99: =_xll.EQNXTDZ($A$1,$B99,E$1,$B$1) -> 0 | F99: =_xll.EQNXTDZ($A$1,$B99,F$1,$B$1) -> 0 | G99: =_xll.EQNXTDZ($A$1,$B99,G$1,$B$1) -> 0 | H99: =_xll.EQNXTDZ($A$1,$B99,H$1,$B$1) -> 0 | I99: =_xll.EQNXTDZ($A$1,$B99,I$1,$B$1) -> 0 | J99: =_xll.EQNXTDZ($A$1,$B99,J$1,$B$1) -> 0 | ... AF99: =_xll.EQNXTDZ($A$1,$B99,AF$1,$B$1) -> 0
A103: Field Description | B103: Field Name
A104: Equity Paid Up | B104: BS_EQUITY_PAIDUP | C104: =_xll.EQNXTDZ($A$1,$B104,C$1,$B$1) -> 0 | D104: =_xll.EQNXTDZ($A$1,$B104,D$1,$B$1) -> 0 | E104: =_xll.EQNXTDZ($A$1,$B104,E$1,$B$1) -> 0 | F104: =_xll.EQNXTDZ($A$1,$B104,F$1,$B$1) -> 0 | G104: =_xll.EQNXTDZ($A$1,$B104,G$1,$B$1) -> 0 | H104: =_xll.EQNXTDZ($A$1,$B104,H$1,$B$1) -> 0 | I104: =_xll.EQNXTDZ($A$1,$B104,I$1,$B$1) -> 0 | J104: =_xll.EQNXTDZ($A$1,$B104,J$1,$B$1) -> 0 | ... AF104: =_xll.EQNXTDZ($A$1,$B104,AF$1,$B$1) -> 0
A105: Face Value | B105: BS_FACE_VALUE | C105: =_xll.EQNXTDZ($A$1,$B105,C$1,$B$1) -> 0 | D105: =_xll.EQNXTDZ($A$1,$B105,D$1,$B$1) -> 0 | E105: =_xll.EQNXTDZ($A$1,$B105,E$1,$B$1) -> 0 | F105: =_xll.EQNXTDZ($A$1,$B105,F$1,$B$1) -> 0 | G105: =_xll.EQNXTDZ($A$1,$B105,G$1,$B$1) -> 0 | H105: =_xll.EQNXTDZ($A$1,$B105,H$1,$B$1) -> 0 | I105: =_xll.EQNXTDZ($A$1,$B105,I$1,$B$1) -> 0 | J105: =_xll.EQNXTDZ($A$1,$B105,J$1,$B$1) -> 0 | ... AF105: =_xll.EQNXTDZ($A$1,$B105,AF$1,$B$1) -> 0
A106: Close Price (Unit Curr.) | B106: FH_YEAR_PRICE | C106: =_xll.EQNXTDZ($A$1,$B106,C$1,$B$1) -> 0 | D106: =_xll.EQNXTDZ($A$1,$B106,D$1,$B$1) -> 0 | E106: =_xll.EQNXTDZ($A$1,$B106,E$1,$B$1) -> 0 | F106: =_xll.EQNXTDZ($A$1,$B106,F$1,$B$1) -> 0 | G106: =_xll.EQNXTDZ($A$1,$B106,G$1,$B$1) -> 0 | H106: =_xll.EQNXTDZ($A$1,$B106,H$1,$B$1) -> 0 | I106: =_xll.EQNXTDZ($A$1,$B106,I$1,$B$1) -> 0 | J106: =_xll.EQNXTDZ($A$1,$B106,J$1,$B$1) -> 0 | ... AF106: =_xll.EQNXTDZ($A$1,$B106,AF$1,$B$1) -> 0
A107: High Price (Unit Curr.) | B107: FH_HIGH | C107: =_xll.EQNXTDZ($A$1,$B107,C$1,$B$1) -> 0 | D107: =_xll.EQNXTDZ($A$1,$B107,D$1,$B$1) -> 0 | E107: =_xll.EQNXTDZ($A$1,$B107,E$1,$B$1) -> 0 | F107: =_xll.EQNXTDZ($A$1,$B107,F$1,$B$1) -> 0 | G107: =_xll.EQNXTDZ($A$1,$B107,G$1,$B$1) -> 0 | H107: =_xll.EQNXTDZ($A$1,$B107,H$1,$B$1) -> 0 | I107: =_xll.EQNXTDZ($A$1,$B107,I$1,$B$1) -> 0 | J107: =_xll.EQNXTDZ($A$1,$B107,J$1,$B$1) -> 0 | ... AF107: =_xll.EQNXTDZ($A$1,$B107,AF$1,$B$1) -> 0
A108: Low Price (Unit Curr.) | B108: FH_LOW | C108: =_xll.EQNXTDZ($A$1,$B108,C$1,$B$1) -> 0 | D108: =_xll.EQNXTDZ($A$1,$B108,D$1,$B$1) -> 0 | E108: =_xll.EQNXTDZ($A$1,$B108,E$1,$B$1) -> 0 | F108: =_xll.EQNXTDZ($A$1,$B108,F$1,$B$1) -> 0 | G108: =_xll.EQNXTDZ($A$1,$B108,G$1,$B$1) -> 0 | H108: =_xll.EQNXTDZ($A$1,$B108,H$1,$B$1) -> 0 | I108: =_xll.EQNXTDZ($A$1,$B108,I$1,$B$1) -> 0 | J108: =_xll.EQNXTDZ($A$1,$B108,J$1,$B$1) -> 0 | ... AF108: =_xll.EQNXTDZ($A$1,$B108,AF$1,$B$1) -> 0
A109: Market Capitalization | B109: FH_MCAP | C109: =_xll.EQNXTDZ($A$1,$B109,C$1,$B$1) -> 0 | D109: =_xll.EQNXTDZ($A$1,$B109,D$1,$B$1) -> 0 | E109: =_xll.EQNXTDZ($A$1,$B109,E$1,$B$1) -> 0 | F109: =_xll.EQNXTDZ($A$1,$B109,F$1,$B$1) -> 0 | G109: =_xll.EQNXTDZ($A$1,$B109,G$1,$B$1) -> 0 | H109: =_xll.EQNXTDZ($A$1,$B109,H$1,$B$1) -> 0 | I109: =_xll.EQNXTDZ($A$1,$B109,I$1,$B$1) -> 0 | J109: =_xll.EQNXTDZ($A$1,$B109,J$1,$B$1) -> 0 | ... AF109: =_xll.EQNXTDZ($A$1,$B109,AF$1,$B$1) -> 0
A110: Adj DPS(Rs) | B110: FR_ADJ_DPS | C110: =_xll.EQNXTDZ($A$1,$B110,C$1,$B$1) -> 0 | D110: =_xll.EQNXTDZ($A$1,$B110,D$1,$B$1) -> 0 | E110: =_xll.EQNXTDZ($A$1,$B110,E$1,$B$1) -> 0 | F110: =_xll.EQNXTDZ($A$1,$B110,F$1,$B$1) -> 0 | G110: =_xll.EQNXTDZ($A$1,$B110,G$1,$B$1) -> 0 | H110: =_xll.EQNXTDZ($A$1,$B110,H$1,$B$1) -> 0 | I110: =_xll.EQNXTDZ($A$1,$B110,I$1,$B$1) -> 0 | J110: =_xll.EQNXTDZ($A$1,$B110,J$1,$B$1) -> 0 | ... AF110: =_xll.EQNXTDZ($A$1,$B110,AF$1,$B$1) -> 0
A111: Date End | B111: SHP_DATE_END | C111: =_xll.EQNXTDZ($A$1,$B111,C$5) -> 0 | D111: =_xll.EQNXTDZ($A$1,$B111,D$5) -> 0 | E111: =_xll.EQNXTDZ($A$1,$B111,E$5) -> 0 | F111: =_xll.EQNXTDZ($A$1,$B111,F$5) -> 0 | G111: =_xll.EQNXTDZ($A$1,$B111,G$5) -> 0 | H111: =_xll.EQNXTDZ($A$1,$B111,H$5) -> 0 | I111: =_xll.EQNXTDZ($A$1,$B111,I$5) -> 0 | J111: =_xll.EQNXTDZ($A$1,$B111,J$5) -> 0 | ... AF111: =_xll.EQNXTDZ($A$1,$B111,AF$5) -> 0
A112: Total of Promoter and Promoter Group | B112: SHP_TPFTOTALPROMOTER | C112: =_xll.EQNXTDZ($A$1,$B112,C$5) -> 0 | D112: =_xll.EQNXTDZ($A$1,$B112,D$5) -> 0 | E112: =_xll.EQNXTDZ($A$1,$B112,E$5) -> 0 | F112: =_xll.EQNXTDZ($A$1,$B112,F$5) -> 0 | G112: =_xll.EQNXTDZ($A$1,$B112,G$5) -> 0 | H112: =_xll.EQNXTDZ($A$1,$B112,H$5) -> 0 | I112: =_xll.EQNXTDZ($A$1,$B112,I$5) -> 0 | J112: =_xll.EQNXTDZ($A$1,$B112,J$5) -> 0 | ... AF112: =_xll.EQNXTDZ($A$1,$B112,AF$5) -> 0
A113: Total of Promoter and Promoter Group Pledged | B113: SHP_PSHFTOTALPROMOTER | C113: =_xll.EQNXTDZ($A$1,$B113,C$5) -> 0 | D113: =_xll.EQNXTDZ($A$1,$B113,D$5) -> 0 | E113: =_xll.EQNXTDZ($A$1,$B113,E$5) -> 0 | F113: =_xll.EQNXTDZ($A$1,$B113,F$5) -> 0 | G113: =_xll.EQNXTDZ($A$1,$B113,G$5) -> 0 | H113: =_xll.EQNXTDZ($A$1,$B113,H$5) -> 0 | I113: =_xll.EQNXTDZ($A$1,$B113,I$5) -> 0 | J113: =_xll.EQNXTDZ($A$1,$B113,J$5) -> 0 | ... AF113: =_xll.EQNXTDZ($A$1,$B113,AF$5) -> 0

Sheet QTR Share Price
A1: ='QTR Raw'!A1 -> 322918 | C1: 201206 | D1: 201207 | E1: 201208 | F1: 201209 | G1: 201210 | H1: 201211 | I1: 201212 | J1: 201301 | K1: 201302 | L1: 201303 | M1: 201304 | N1: 201305 | O1: 201306 | P1: 201307 | Q1: 201308 | R1: 201309 | S1: 201310 | T1: 201311 | U1: 201312 | V1: 201401 | W1: 201402 | X1: 201403 | Y1: 201404 | Z1: 201405 | AA1: 201406 | AB1: 201407 | AC1: 201408 | AD1: 201409 | AE1: 201410 | AF1: 201411 | AG1: 201412 | AH1: 201501 | AI1: 201502 | AJ1: 201503 | AK1: 201504 | AL1: 201505 | AM1: 201506 | AN1: 201507 | AO1: 201508 | AP1: 201509 | AQ1: 201510 | AR1: 201511 | AS1: 201512 | AT1: 201601 | AU1: 201602 | AV1: 201603 | AW1: 201604 | AX1: 201605 | AY1: 201606 | AZ1: 201607 | BA1: 201608 | BB1: 201609 | BC1: 201610 | BD1: 201611 | BE1: 201612 | BF1: 201701 | BG1: 201702 | BH1: 201703 | BI1: 201704 | BJ1: 201705 | BK1: 201706 | BL1: 201707 | BM1: 201708 | BN1: 201709 | BO1: 201710 | BP1: 201711 | BQ1: 201712 | BR1: 201801 | BS1: 201802 | BT1: 201803 | BU1: 201804 | BV1: 201805 | BW1: 201806 | BX1: 201807 | BY1: 201808 | BZ1: 201809 | CA1: 201810 | CB1: 201811 | CC1: 201812 | CD1: 201901 | CE1: 201902 | CF1: 201903 | CG1: 201904 | CH1: 201905 | CI1: 201906 | CJ1: 201907 | CK1: 201908 | CL1: 201909 | CM1: 201910 | CN1: 201911 | CO1: 201912 | CP1: 202001 | CQ1: 202002 | CR1: 202003 | CS1: 202004 | CT1: 202005 | CU1: 202006 | CV1: 202007 | CW1: 202008 | CX1: 202009 | CY1: 202010 | CZ1: 202011 | DA1: 202012 | DB1: 202101 | DC1: 202102 | DD1: 202103 | DE1: 202104 | DF1: 202105 | DG1: 202106 | DH1: 202107 | DI1: 202108 | DJ1: 202109 | DK1: 202110 | DL1: 202111 | DM1: 202112 | DN1: 202201 | DO1: 202202 | DP1: 202203 | DQ1: 202204 | DR1: 202205 | DS1: 202206 | DT1: 202207 | DU1: 202208 | DV1: 202209 | DW1: 202210 | DX1: 202211 | DY1: 202212 | DZ1: 202301 | EA1: 202302 | EB1: 202303 | EC1: 202304 | ED1: 202305 | EE1: 202306 | EF1: 202307 | EG1: 202308 | EH1: 202309 | EI1: 202310 | EJ1: 202311 | EK1: 202312 | EL1: 202401 | EM1: 202402 | EN1: 202403 | EO1: 202404 | EP1: 202405 | EQ1: 202406 | ER1: 202407 | ES1: 202408 | ET1: 202409 | EU1: 202410 | EV1: 202411 | EW1: 202412 | EX1: 202501 | EY1: 202502 | EZ1: 202503 | FA1: 202504 | FB1: 202505 | FC1: 202506 | FD1: 202507 | FE1: 202508 | FF1: 202509 | FG1: 202510 | FH1: 202511 | FI1: 202512 | FJ1: 202601 | FK1: 202602 | FL1: 202603 | FM1: 202604 | FN1: 202605 | FO1: 202606 | FP1: 202607 | FQ1: 202608 | FR1: 202609 | FS1: 202610 | FT1: 202611 | FU1: 202612 | FV1: 202701 | FW1: 202702 | FX1: 202703 | FY1: 202704 | FZ1: 202705 | GA1: 202706 | GB1: 202707 | GC1: 202708 | GD1: 202709 | GE1: 202710 | GF1: 202711 | GG1: 202712 | GH1: 202801 | GI1: 202802 | GJ1: 202803 | GK1: 202804 | GL1: 202805 | GM1: 202806 | GN1: 202807 | GO1: 202808 | GP1: 202809 | GQ1: 202810 | GR1: 202811 | GS1: 202812 | GT1: 202901 | GU1: 202902 | GV1: 202903 | GW1: 202904 | GX1: 202905 | GY1: 202906 | GZ1: 202907 | HA1: 202908 | HB1: 202909 | HC1: 202910 | HD1: 202911 | HE1: 202912 | HF1: 203001 | HG1: 203002 | HH1: 203003 | HM1: 201206 | HN1: 201207 | HO1: 201208 | HP1: 201209 | HQ1: 201212 | HR1: 201303 | HS1: 201306 | HT1: 201309 | HU1: 201312 | HV1: 201403 | HW1: 201406 | HX1: 201409 | HY1: 201412 | HZ1: 201503 | IA1: 201506 | IB1: 201509 | IC1: 201512 | ID1: 201603 | IE1: 201606 | IF1: 201609 | IG1: 201612 | IH1: 201703 | II1: 201706 | IJ1: 201709 | IK1: 201712 | IL1: 201803 | IM1: 201806 | IN1: 201809 | IO1: 201812 | IP1: 201903 | IQ1: 201906 | IR1: 201909 | IS1: 201912 | IT1: 202003 | IU1: 202006 | IV1: 202009 | IW1: 202012 | IX1: 202103 | IY1: 202106 | IZ1: 202109 | JA1: 202112 | JB1: 202203 | JC1: 202206 | JD1: 202209 | JE1: 202212 | JF1: 202303 | JG1: 202306 | JH1: 202309 | JI1: 202312 | JJ1: 202403 | JK1: 202406 | JL1: 202409 | JM1: 202412 | JN1: 202503 | JO1: 202506 | JP1: 202509 | JQ1: 202512 | JR1: 202603
FF2: 45901 | FG2: =+EOMONTH(FF2,1) -> 45961 | FH2: =+EOMONTH(FG2,1) -> 45991 | FI2: =+EOMONTH(FH2,1) -> 46022 | FJ2: =+EOMONTH(FI2,1) -> 46053 | FK2: =+EOMONTH(FJ2,1) -> 46081 | FL2: =+EOMONTH(FK2,1) -> 46112 | FM2: =+EOMONTH(FL2,1) -> 46142 | FN2: =+EOMONTH(FM2,1) -> 46173 | ... HH2: =+EOMONTH(HG2,1) -> 47573
A4: Field Description | B4: Field Name
A5: MonthEnd | B5: NMONTH_MONTHEND | C5: {=_xll.EQNXTDZ($A$1,$B5,C$1)} -> 0 | D5: {=_xll.EQNXTDZ($A$1,$B5,D$1)} -> 0 | E5: {=_xll.EQNXTDZ($A$1,$B5,E$1)} -> 0 | F5: {=_xll.EQNXTDZ($A$1,$B5,F$1)} -> 0 | G5: {=_xll.EQNXTDZ($A$1,$B5,G$1)} -> 0 | H5: {=_xll.EQNXTDZ($A$1,$B5,H$1)} -> 0 | I5: {=_xll.EQNXTDZ($A$1,$B5,I$1)} -> 0 | J5: {=_xll.EQNXTDZ($A$1,$B5,J$1)} -> 0 | ... HH5: {=_xll.EQNXTDZ($A$1,$B5,HH$1)} -> 0
A6: Open | B6: NMONTH_OPEN | C6: {=_xll.EQNXTDZ($A$1,$B6,C$1)} -> 0 | D6: {=_xll.EQNXTDZ($A$1,$B6,D$1)} -> 0 | E6: {=_xll.EQNXTDZ($A$1,$B6,E$1)} -> 0 | F6: {=_xll.EQNXTDZ($A$1,$B6,F$1)} -> 0 | G6: {=_xll.EQNXTDZ($A$1,$B6,G$1)} -> 0 | H6: {=_xll.EQNXTDZ($A$1,$B6,H$1)} -> 0 | I6: {=_xll.EQNXTDZ($A$1,$B6,I$1)} -> 0 | J6: {=_xll.EQNXTDZ($A$1,$B6,J$1)} -> 0 | ... HH6: {=_xll.EQNXTDZ($A$1,$B6,HH$1)} -> 0
A7: High | B7: NMONTH_HIGH | C7: {=_xll.EQNXTDZ($A$1,$B7,C$1)} -> 0 | D7: {=_xll.EQNXTDZ($A$1,$B7,D$1)} -> 0 | E7: {=_xll.EQNXTDZ($A$1,$B7,E$1)} -> 0 | F7: {=_xll.EQNXTDZ($A$1,$B7,F$1)} -> 0 | G7: {=_xll.EQNXTDZ($A$1,$B7,G$1)} -> 0 | H7: {=_xll.EQNXTDZ($A$1,$B7,H$1)} -> 0 | I7: {=_xll.EQNXTDZ($A$1,$B7,I$1)} -> 0 | J7: {=_xll.EQNXTDZ($A$1,$B7,J$1)} -> 0 | ... HH7: {=_xll.EQNXTDZ($A$1,$B7,HH$1)} -> 0 | HP7: =+MAX(D7:F7) -> 0 | HQ7: =+MAX(G7:I7) -> 0 | HR7: =+MAX(J7:L7) -> 0 | HS7: =+MAX(M7:O7) -> 0 | HT7: =+MAX(P7:R7) -> 0 | HU7: =+MAX(S7:U7) -> 0 | HV7: =+MAX(V7:X7) -> 0 | HW7: =+MAX(Y7:AA7) -> 0 | HX7: =+MAX(AB7:AD7) -> 0 | HY7: =+MAX(AE7:AG7) -> 0 | HZ7: =+MAX(AH7:AJ7) -> 0 | IA7: =+MAX(AK7:AM7) -> 0 | IB7: =+MAX(AN7:AP7) -> 0 | IC7: =+MAX(AQ7:AS7) -> 0 | ID7: =+MAX(AT7:AV7) -> 0 | IE7: =+MAX(AW7:AY7) -> 0 | IF7: =+MAX(AZ7:BB7) -> 0 | IG7: =+MAX(BC7:BE7) -> 0 | IH7: =+MAX(BF7:BH7) -> 0 | II7: =+MAX(BI7:BK7) -> 0 | IJ7: =+MAX(BL7:BN7) -> 0 | IK7: =+MAX(BO7:BQ7) -> 0 | IL7: =+MAX(BR7:BT7) -> 0 | IM7: =+MAX(BU7:BW7) -> 0 | IN7: =+MAX(BX7:BZ7) -> 0 | IO7: =+MAX(CA7:CC7) -> 0 | IP7: =+MAX(CD7:CF7) -> 0 | IQ7: =+MAX(CG7:CI7) -> 0 | IR7: =+MAX(CJ7:CL7) -> 0 | IS7: =+MAX(CM7:CO7) -> 0 | IT7: =+MAX(CP7:CR7) -> 0 | IU7: =+MAX(CS7:CU7) -> 0 | IV7: =+MAX(CV7:CX7) -> 0 | IW7: =+MAX(CY7:DA7) -> 0 | IX7: =+MAX(DB7:DD7) -> 0 | IY7: =+MAX(DE7:DG7) -> 0 | IZ7: =+MAX(DH7:DJ7) -> 0 | JA7: =+MAX(DK7:DM7) -> 0 | JB7: =+MAX(DN7:DP7) -> 0 | JC7: =+MAX(DQ7:DS7) -> 0 | JD7: =+MAX(DT7:DV7) -> 0 | JE7: =+MAX(DW7:DY7) -> 0 | JF7: =+MAX(DZ7:EB7) -> 0 | JG7: =+MAX(EC7:EE7) -> 0 | JH7: =+MAX(EF7:EH7) -> 0 | JI7: =+MAX(EI7:EK7) -> 0 | JJ7: =+MAX(EL7:EN7) -> 0 | JK7: =MAX(EO7:EQ7) -> 0 | JL7: =MAX(ER7:ET7) -> 0 | JM7: =MAX(EU7:EW7) -> 0 | JN7: =MAX(EX7:EZ7) -> 0 | JO7: =MAX(FA7:FC7) -> 0 | JP7: =MAX(FD7:FF7) -> 0 | JQ7: =MAX(FG7:FI7) -> 432.3 | JR7: =MAX(FJ7:FL7) -> 509
A8: Low | B8: NMONTH_LOW | C8: {=_xll.EQNXTDZ($A$1,$B8,C$1)} -> 0 | D8: {=_xll.EQNXTDZ($A$1,$B8,D$1)} -> 0 | E8: {=_xll.EQNXTDZ($A$1,$B8,E$1)} -> 0 | F8: {=_xll.EQNXTDZ($A$1,$B8,F$1)} -> 0 | G8: {=_xll.EQNXTDZ($A$1,$B8,G$1)} -> 0 | H8: {=_xll.EQNXTDZ($A$1,$B8,H$1)} -> 0 | I8: {=_xll.EQNXTDZ($A$1,$B8,I$1)} -> 0 | J8: {=_xll.EQNXTDZ($A$1,$B8,J$1)} -> 0 | ... HH8: {=_xll.EQNXTDZ($A$1,$B8,HH$1)} -> 0 | HP8: =+MIN(D8:F8) -> 0 | HQ8: =+MIN(G8:I8) -> 0 | HR8: =+MIN(J8:L8) -> 0 | HS8: =+MIN(M8:O8) -> 0 | HT8: =+MIN(P8:R8) -> 0 | HU8: =+MIN(S8:U8) -> 0 | HV8: =+MIN(V8:X8) -> 0 | HW8: =+MIN(Y8:AA8) -> 0 | HX8: =+MIN(AB8:AD8) -> 0 | HY8: =+MIN(AE8:AG8) -> 0 | HZ8: =+MIN(AH8:AJ8) -> 0 | IA8: =+MIN(AK8:AM8) -> 0 | IB8: =+MIN(AN8:AP8) -> 0 | IC8: =+MIN(AQ8:AS8) -> 0 | ID8: =+MIN(AT8:AV8) -> 0 | IE8: =+MIN(AW8:AY8) -> 0 | IF8: =+MIN(AZ8:BB8) -> 0 | IG8: =+MIN(BC8:BE8) -> 0 | IH8: =+MIN(BF8:BH8) -> 0 | II8: =+MIN(BI8:BK8) -> 0 | IJ8: =+MIN(BL8:BN8) -> 0 | IK8: =+MIN(BO8:BQ8) -> 0 | IL8: =+MIN(BR8:BT8) -> 0 | IM8: =+MIN(BU8:BW8) -> 0 | IN8: =+MIN(BX8:BZ8) -> 0 | IO8: =+MIN(CA8:CC8) -> 0 | IP8: =+MIN(CD8:CF8) -> 0 | IQ8: =+MIN(CG8:CI8) -> 0 | IR8: =+MIN(CJ8:CL8) -> 0 | IS8: =+MIN(CM8:CO8) -> 0 | IT8: =+MIN(CP8:CR8) -> 0 | IU8: =+MIN(CS8:CU8) -> 0 | IV8: =+MIN(CV8:CX8) -> 0 | IW8: =+MIN(CY8:DA8) -> 0 | IX8: =+MIN(DB8:DD8) -> 0 | IY8: =+MIN(DE8:DG8) -> 0 | IZ8: =+MIN(DH8:DJ8) -> 0 | JA8: =+MIN(DK8:DM8) -> 0 | JB8: =+MIN(DN8:DP8) -> 0 | JC8: =+MIN(DQ8:DS8) -> 0 | JD8: =+MIN(DT8:DV8) -> 0 | JE8: =+MIN(DW8:DY8) -> 0 | JF8: =+MIN(DZ8:EB8) -> 0 | JG8: =+MIN(EC8:EE8) -> 0 | JH8: =+MIN(EF8:EH8) -> 0 | JI8: =+MIN(EI8:EK8) -> 0 | JJ8: =+MIN(EL8:EN8) -> 0 | JK8: =MIN(EO8:EQ8) -> 0 | JL8: =MIN(ER8:ET8) -> 0 | JM8: =MIN(EU8:EW8) -> 0 | JN8: =MIN(EX8:EZ8) -> 0 | JO8: =MIN(FA8:FC8) -> 0 | JP8: =MIN(FD8:FF8) -> 0 | JQ8: =MIN(FG8:FI8) -> 0 | JR8: =MIN(FJ8:FL8) -> 388.75
A9: Close | B9: NMONTH_CLOSE | C9: {=_xll.EQNXTDZ($A$1,$B9,C$1)} -> 0 | D9: {=_xll.EQNXTDZ($A$1,$B9,D$1)} -> 0 | E9: {=_xll.EQNXTDZ($A$1,$B9,E$1)} -> 0 | F9: {=_xll.EQNXTDZ($A$1,$B9,F$1)} -> 0 | G9: {=_xll.EQNXTDZ($A$1,$B9,G$1)} -> 0 | H9: {=_xll.EQNXTDZ($A$1,$B9,H$1)} -> 0 | I9: {=_xll.EQNXTDZ($A$1,$B9,I$1)} -> 0 | J9: {=_xll.EQNXTDZ($A$1,$B9,J$1)} -> 0 | ... HH9: {=_xll.EQNXTDZ($A$1,$B9,HH$1)} -> 0 | HP9: =+F9 -> 0 | HQ9: =+I9 -> 0 | HR9: =+L9 -> 0 | HS9: =+O9 -> 0 | HT9: =+R9 -> 0 | HU9: =+U9 -> 0 | HV9: =+X9 -> 0 | HW9: =+AA9 -> 0 | HX9: =+AD9 -> 0 | HY9: =+AG9 -> 0 | HZ9: =+AJ9 -> 0 | IA9: =+AM9 -> 0 | IB9: =+AP9 -> 0 | IC9: =+AS9 -> 0 | ID9: =+AV9 -> 0 | IE9: =+AY9 -> 0 | IF9: =+BB9 -> 0 | IG9: =+BE9 -> 0 | IH9: =+BH9 -> 0 | II9: =+BK9 -> 0 | IJ9: =+BN9 -> 0 | IK9: =+BQ9 -> 0 | IL9: =+BT9 -> 0 | IM9: =+BW9 -> 0 | IN9: =+BZ9 -> 0 | IO9: =+CC9 -> 0 | IP9: =+CF9 -> 0 | IQ9: =+CI9 -> 0 | IR9: =+CL9 -> 0 | IS9: =+CO9 -> 0 | IT9: =+CR9 -> 0 | IU9: =+CU9 -> 0 | IV9: =+CX9 -> 0 | IW9: =+DA9 -> 0 | IX9: =+DD9 -> 0 | IY9: =+DG9 -> 0 | IZ9: =+DJ9 -> 0 | JA9: =+DM9 -> 0 | JB9: =+DP9 -> 0 | JC9: =+DS9 -> 0 | JD9: =+DV9 -> 0 | JE9: =+DY9 -> 0 | JF9: =+EB9 -> 0 | JG9: =+EE9 -> 0 | JH9: =+EH9 -> 0 | JI9: =+EK9 -> 0 | JJ9: =+EN9 -> 0 | JK9: =EQ9 -> 0 | JL9: =ET9 -> 0 | JM9: =EW9 -> 0 | JN9: =EZ9 -> 0 | JO9: =FC9 -> 0 | JP9: =FF9 -> 0 | JQ9: =FI9 -> 415.5 | JR9: =FL9 -> 394.8
A11: Field Description | B11: Field Name | C11: {=_xll.EQNXTDZ($A$1,$B11,C$1)} -> 0 | D11: {=_xll.EQNXTDZ($A$1,$B11,D$1)} -> 0 | E11: {=_xll.EQNXTDZ($A$1,$B11,E$1)} -> 0 | F11: {=_xll.EQNXTDZ($A$1,$B11,F$1)} -> 0 | G11: {=_xll.EQNXTDZ($A$1,$B11,G$1)} -> 0 | H11: {=_xll.EQNXTDZ($A$1,$B11,H$1)} -> 0 | I11: {=_xll.EQNXTDZ($A$1,$B11,I$1)} -> 0 | J11: {=_xll.EQNXTDZ($A$1,$B11,J$1)} -> 0 | ... HH11: {=_xll.EQNXTDZ($A$1,$B11,HH$1)} -> 0
A12: Month End | B12: BMONTH_MONTHEND | C12: {=_xll.EQNXTDZ($A$1,$B12,C$1)} -> 0 | D12: {=_xll.EQNXTDZ($A$1,$B12,D$1)} -> 0 | E12: {=_xll.EQNXTDZ($A$1,$B12,E$1)} -> 0 | F12: {=_xll.EQNXTDZ($A$1,$B12,F$1)} -> 0 | G12: {=_xll.EQNXTDZ($A$1,$B12,G$1)} -> 0 | H12: {=_xll.EQNXTDZ($A$1,$B12,H$1)} -> 0 | I12: {=_xll.EQNXTDZ($A$1,$B12,I$1)} -> 0 | J12: {=_xll.EQNXTDZ($A$1,$B12,J$1)} -> 0 | ... HH12: {=_xll.EQNXTDZ($A$1,$B12,HH$1)} -> 0
A13: Open | B13: BMONTH_OPEN | C13: {=_xll.EQNXTDZ($A$1,$B13,C$1)} -> 0 | D13: {=_xll.EQNXTDZ($A$1,$B13,D$1)} -> 0 | E13: {=_xll.EQNXTDZ($A$1,$B13,E$1)} -> 0 | F13: {=_xll.EQNXTDZ($A$1,$B13,F$1)} -> 0 | G13: {=_xll.EQNXTDZ($A$1,$B13,G$1)} -> 0 | H13: {=_xll.EQNXTDZ($A$1,$B13,H$1)} -> 0 | I13: {=_xll.EQNXTDZ($A$1,$B13,I$1)} -> 0 | J13: {=_xll.EQNXTDZ($A$1,$B13,J$1)} -> 0 | ... HH13: {=_xll.EQNXTDZ($A$1,$B13,HH$1)} -> 0
A14: High | B14: BMONTH_HIGH | C14: {=_xll.EQNXTDZ($A$1,$B14,C$1)} -> 0 | D14: {=_xll.EQNXTDZ($A$1,$B14,D$1)} -> 0 | E14: {=_xll.EQNXTDZ($A$1,$B14,E$1)} -> 0 | F14: {=_xll.EQNXTDZ($A$1,$B14,F$1)} -> 0 | G14: {=_xll.EQNXTDZ($A$1,$B14,G$1)} -> 0 | H14: {=_xll.EQNXTDZ($A$1,$B14,H$1)} -> 0 | I14: {=_xll.EQNXTDZ($A$1,$B14,I$1)} -> 0 | J14: {=_xll.EQNXTDZ($A$1,$B14,J$1)} -> 0 | ... HH14: {=_xll.EQNXTDZ($A$1,$B14,HH$1)} -> 0 | HP14: =+MAX(D14:F14) -> 0 | HQ14: =+MAX(G14:I14) -> 0 | HR14: =+MAX(J14:L14) -> 0 | HS14: =+MAX(M14:O14) -> 0 | HT14: =+MAX(P14:R14) -> 0 | HU14: =+MAX(S14:U14) -> 0 | HV14: =+MAX(V14:X14) -> 0 | HW14: =+MAX(Y14:AA14) -> 0 | HX14: =+MAX(AB14:AD14) -> 0 | HY14: =+MAX(AE14:AG14) -> 0 | HZ14: =+MAX(AH14:AJ14) -> 0 | IA14: =+MAX(AK14:AM14) -> 0 | IB14: =+MAX(AN14:AP14) -> 0 | IC14: =+MAX(AQ14:AS14) -> 0 | ID14: =+MAX(AT14:AV14) -> 0 | IE14: =+MAX(AW14:AY14) -> 0 | IF14: =+MAX(AZ14:BB14) -> 0 | IG14: =+MAX(BC14:BE14) -> 0 | IH14: =+MAX(BF14:BH14) -> 0 | II14: =+MAX(BI14:BK14) -> 0 | IJ14: =+MAX(BL14:BN14) -> 0 | IK14: =+MAX(BO14:BQ14) -> 0 | IL14: =+MAX(BR14:BT14) -> 0 | IM14: =+MAX(BU14:BW14) -> 0 | IN14: =+MAX(BX14:BZ14) -> 0 | IO14: =+MAX(CA14:CC14) -> 0 | IP14: =+MAX(CD14:CF14) -> 0 | IQ14: =+MAX(CG14:CI14) -> 0 | IR14: =+MAX(CJ14:CL14) -> 0 | IS14: =+MAX(CM14:CO14) -> 0 | IT14: =+MAX(CP14:CR14) -> 0 | IU14: =+MAX(CS14:CU14) -> 0 | IV14: =+MAX(CV14:CX14) -> 0 | IW14: =+MAX(CY14:DA14) -> 0 | IX14: =+MAX(DB14:DD14) -> 0 | IY14: =+MAX(DE14:DG14) -> 0 | IZ14: =+MAX(DH14:DJ14) -> 0 | JA14: =+MAX(DK14:DM14) -> 0 | JB14: =+MAX(DN14:DP14) -> 0 | JC14: =+MAX(DQ14:DS14) -> 0 | JD14: =+MAX(DT14:DV14) -> 0 | JE14: =+MAX(DW14:DY14) -> 0 | JF14: =+MAX(DZ14:EB14) -> 0 | JG14: =+MAX(EC14:EE14) -> 0 | JH14: =+MAX(EF14:EH14) -> 0 | JI14: =+MAX(EI14:EK14) -> 0 | JJ14: =+MAX(EL14:EN14) -> 0 | JK14: =MAX(EO14:EQ14) -> 0 | JL14: =MAX(ER14:ET14) -> 0 | JM14: =MAX(EU14:EW14) -> 0 | JN14: =MAX(EX14:EZ14) -> 0 | JO14: =MAX(FA14:FC14) -> 0 | JP14: =MAX(FD14:FF14) -> 0 | JQ14: =MAX(FG14:FI14) -> 433.65 | JR14: =MAX(FJ14:FL14) -> 508.95
A15: Low | B15: BMONTH_LOW | C15: {=_xll.EQNXTDZ($A$1,$B15,C$1)} -> 0 | D15: {=_xll.EQNXTDZ($A$1,$B15,D$1)} -> 0 | E15: {=_xll.EQNXTDZ($A$1,$B15,E$1)} -> 0 | F15: {=_xll.EQNXTDZ($A$1,$B15,F$1)} -> 0 | G15: {=_xll.EQNXTDZ($A$1,$B15,G$1)} -> 0 | H15: {=_xll.EQNXTDZ($A$1,$B15,H$1)} -> 0 | I15: {=_xll.EQNXTDZ($A$1,$B15,I$1)} -> 0 | J15: {=_xll.EQNXTDZ($A$1,$B15,J$1)} -> 0 | ... HH15: {=_xll.EQNXTDZ($A$1,$B15,HH$1)} -> 0 | HP15: =+MIN(D15:F15) -> 0 | HQ15: =+MIN(G15:I15) -> 0 | HR15: =+MIN(J15:L15) -> 0 | HS15: =+MIN(M15:O15) -> 0 | HT15: =+MIN(P15:R15) -> 0 | HU15: =+MIN(S15:U15) -> 0 | HV15: =+MIN(V15:X15) -> 0 | HW15: =+MIN(Y15:AA15) -> 0 | HX15: =+MIN(AB15:AD15) -> 0 | HY15: =+MIN(AE15:AG15) -> 0 | HZ15: =+MIN(AH15:AJ15) -> 0 | IA15: =+MIN(AK15:AM15) -> 0 | IB15: =+MIN(AN15:AP15) -> 0 | IC15: =+MIN(AQ15:AS15) -> 0 | ID15: =+MIN(AT15:AV15) -> 0 | IE15: =+MIN(AW15:AY15) -> 0 | IF15: =+MIN(AZ15:BB15) -> 0 | IG15: =+MIN(BC15:BE15) -> 0 | IH15: =+MIN(BF15:BH15) -> 0 | II15: =+MIN(BI15:BK15) -> 0 | IJ15: =+MIN(BL15:BN15) -> 0 | IK15: =+MIN(BO15:BQ15) -> 0 | IL15: =+MIN(BR15:BT15) -> 0 | IM15: =+MIN(BU15:BW15) -> 0 | IN15: =+MIN(BX15:BZ15) -> 0 | IO15: =+MIN(CA15:CC15) -> 0 | IP15: =+MIN(CD15:CF15) -> 0 | IQ15: =+MIN(CG15:CI15) -> 0 | IR15: =+MIN(CJ15:CL15) -> 0 | IS15: =+MIN(CM15:CO15) -> 0 | IT15: =+MIN(CP15:CR15) -> 0 | IU15: =+MIN(CS15:CU15) -> 0 | IV15: =+MIN(CV15:CX15) -> 0 | IW15: =+MIN(CY15:DA15) -> 0 | IX15: =+MIN(DB15:DD15) -> 0 | IY15: =+MIN(DE15:DG15) -> 0 | IZ15: =+MIN(DH15:DJ15) -> 0 | JA15: =+MIN(DK15:DM15) -> 0 | JB15: =+MIN(DN15:DP15) -> 0 | JC15: =+MIN(DQ15:DS15) -> 0 | JD15: =+MIN(DT15:DV15) -> 0 | JE15: =+MIN(DW15:DY15) -> 0 | JF15: =+MIN(DZ15:EB15) -> 0 | JG15: =+MIN(EC15:EE15) -> 0 | JH15: =+MIN(EF15:EH15) -> 0 | JI15: =+MIN(EI15:EK15) -> 0 | JJ15: =+MIN(EL15:EN15) -> 0 | JK15: =MIN(EO15:EQ15) -> 0 | JL15: =MIN(ER15:ET15) -> 0 | JM15: =MIN(EU15:EW15) -> 0 | JN15: =MIN(EX15:EZ15) -> 0 | JO15: =MIN(FA15:FC15) -> 0 | JP15: =MIN(FD15:FF15) -> 0 | JQ15: =MIN(FG15:FI15) -> 0 | JR15: =MIN(FJ15:FL15) -> 389.05
A16: Close | B16: BMONTH_CLOSE | C16: {=_xll.EQNXTDZ($A$1,$B16,C$1)} -> 0 | D16: {=_xll.EQNXTDZ($A$1,$B16,D$1)} -> 0 | E16: {=_xll.EQNXTDZ($A$1,$B16,E$1)} -> 0 | F16: {=_xll.EQNXTDZ($A$1,$B16,F$1)} -> 0 | G16: {=_xll.EQNXTDZ($A$1,$B16,G$1)} -> 0 | H16: {=_xll.EQNXTDZ($A$1,$B16,H$1)} -> 0 | I16: {=_xll.EQNXTDZ($A$1,$B16,I$1)} -> 0 | J16: {=_xll.EQNXTDZ($A$1,$B16,J$1)} -> 0 | ... HH16: {=_xll.EQNXTDZ($A$1,$B16,HH$1)} -> 0 | HP16: =+F16 -> 0 | HQ16: =+I16 -> 0 | HR16: =+L16 -> 0 | HS16: =+O16 -> 0 | HT16: =+R16 -> 0 | HU16: =+U16 -> 0 | HV16: =+X16 -> 0 | HW16: =+AA16 -> 0 | HX16: =+AD16 -> 0 | HY16: =+AG16 -> 0 | HZ16: =+AJ16 -> 0 | IA16: =+AM16 -> 0 | IB16: =+AP16 -> 0 | IC16: =+AS16 -> 0 | ID16: =+AV16 -> 0 | IE16: =+AY16 -> 0 | IF16: =+BB16 -> 0 | IG16: =+BE16 -> 0 | IH16: =+BH16 -> 0 | II16: =+BK16 -> 0 | IJ16: =+BN16 -> 0 | IK16: =+BQ16 -> 0 | IL16: =+BT16 -> 0 | IM16: =+BW16 -> 0 | IN16: =+BZ16 -> 0 | IO16: =+CC16 -> 0 | IP16: =+CF16 -> 0 | IQ16: =+CI16 -> 0 | IR16: =+CL16 -> 0 | IS16: =+CO16 -> 0 | IT16: =+CR16 -> 0 | IU16: =+CU16 -> 0 | IV16: =+CX16 -> 0 | IW16: =+DA16 -> 0 | IX16: =+DD16 -> 0 | IY16: =+DG16 -> 0 | IZ16: =+DJ16 -> 0 | JA16: =+DM16 -> 0 | JB16: =+DP16 -> 0 | JC16: =+DS16 -> 0 | JD16: =+DV16 -> 0 | JE16: =+DY16 -> 0 | JF16: =+EB16 -> 0 | JG16: =+EE16 -> 0 | JH16: =+EH16 -> 0 | JI16: =+EK16 -> 0 | JJ16: =+EN16 -> 0 | JK16: =EQ16 -> 0 | JL16: =ET16 -> 0 | JM16: =EW16 -> 0 | JN16: =EZ16 -> 0 | JO16: =FC16 -> 0 | JP16: =FF16 -> 0 | JQ16: =FI16 -> 415.45 | JR16: =FL16 -> 394.6
A19: High | HP19: =+IF(HP14=0,HP7,HP14) -> 0 | HQ19: =+IF(HQ14=0,HQ7,HQ14) -> 0 | HR19: =+IF(HR14=0,HR7,HR14) -> 0 | HS19: =+IF(HS14=0,HS7,HS14) -> 0 | HT19: =+IF(HT14=0,HT7,HT14) -> 0 | HU19: =+IF(HU14=0,HU7,HU14) -> 0 | HV19: =+IF(HV14=0,HV7,HV14) -> 0 | HW19: =+IF(HW14=0,HW7,HW14) -> 0 | ... JR19: =+IF(JR14=0,JR7,JR14) -> 508.95
A20: Low | HP20: =+IF(HP15=0,HP8,HP15) -> 0 | HQ20: =+IF(HQ15=0,HQ8,HQ15) -> 0 | HR20: =+IF(HR15=0,HR8,HR15) -> 0 | HS20: =+IF(HS15=0,HS8,HS15) -> 0 | HT20: =+IF(HT15=0,HT8,HT15) -> 0 | HU20: =+IF(HU15=0,HU8,HU15) -> 0 | HV20: =+IF(HV15=0,HV8,HV15) -> 0 | HW20: =+IF(HW15=0,HW8,HW15) -> 0 | ... JR20: =+IF(JR15=0,JR8,JR15) -> 389.05
A21: Close | HP21: =+IF(HP16=0,HP9,HP16) -> 0 | HQ21: =+IF(HQ16=0,HQ9,HQ16) -> 0 | HR21: =+IF(HR16=0,HR9,HR16) -> 0 | HS21: =+IF(HS16=0,HS9,HS16) -> 0 | HT21: =+IF(HT16=0,HT9,HT16) -> 0 | HU21: =+IF(HU16=0,HU9,HU16) -> 0 | HV21: =+IF(HV16=0,HV9,HV16) -> 0 | HW21: =+IF(HW16=0,HW9,HW16) -> 0 | ... JR21: =+IF(JR16=0,JR9,JR16) -> 394.6

Sheet QTR No. of Shares
A1: ='QTR Raw'!A1 -> 322918 | C1: 201206 | D1: 201209 | E1: 201212 | F1: 201303 | G1: 201306 | H1: 201309 | I1: 201312 | J1: 201403 | K1: 201406 | L1: 201409 | M1: 201412 | N1: 201503 | O1: 201506 | P1: 201509 | Q1: 201512 | R1: 201603 | S1: 201606 | T1: 201609 | U1: 201612 | V1: 201703 | W1: 201706 | X1: 201709 | Y1: 201712 | Z1: 201803 | AA1: 201806 | AB1: 201809 | AC1: 201812 | AD1: 201903 | AE1: 201906 | AF1: 201909 | AG1: 201912 | AH1: 202003 | AI1: 202006 | AJ1: 202009 | AK1: 202012 | AL1: 202103 | AM1: 202106 | AN1: 202109 | AO1: 202112 | AP1: 202203 | AQ1: 202206 | AR1: 202209 | AS1: 202212 | AT1: 202303 | AU1: 202306 | AV1: 202309 | AW1: 202312 | AX1: 202403 | AY1: 202406
A4: Field Description | B4: Field Name
A5: Date End | B5: SHP_DATE_END | C5: {=_xll.EQNXTDZ($A$1,$B5,C$1)} -> 0 | D5: {=_xll.EQNXTDZ($A$1,$B5,D$1)} -> 0 | E5: {=_xll.EQNXTDZ($A$1,$B5,E$1)} -> 0 | F5: {=_xll.EQNXTDZ($A$1,$B5,F$1)} -> 0 | G5: {=_xll.EQNXTDZ($A$1,$B5,G$1)} -> 0 | H5: {=_xll.EQNXTDZ($A$1,$B5,H$1)} -> 0 | I5: {=_xll.EQNXTDZ($A$1,$B5,I$1)} -> 0 | J5: {=_xll.EQNXTDZ($A$1,$B5,J$1)} -> 0 | ... AY5: {=_xll.EQNXTDZ($A$1,$B5,AY$1)} -> 0
A6: Grand Total | B6: SHP_NSGRANDTOTAL | C6: {=_xll.EQNXTDZ($A$1,$B6,C$1)} -> 0 | D6: {=_xll.EQNXTDZ($A$1,$B6,D$1)} -> 0 | E6: {=_xll.EQNXTDZ($A$1,$B6,E$1)} -> 0 | F6: {=_xll.EQNXTDZ($A$1,$B6,F$1)} -> 0 | G6: {=_xll.EQNXTDZ($A$1,$B6,G$1)} -> 0 | H6: {=_xll.EQNXTDZ($A$1,$B6,H$1)} -> 0 | I6: {=_xll.EQNXTDZ($A$1,$B6,I$1)} -> 0 | J6: {=_xll.EQNXTDZ($A$1,$B6,J$1)} -> 0 | ... AY6: {=_xll.EQNXTDZ($A$1,$B6,AY$1)} -> 0
B7: In Crs. | C7: =+C6/10^7 -> 0 | D7: =+D6/10^7 -> 0 | E7: =+E6/10^7 -> 0 | F7: =+F6/10^7 -> 0 | G7: =+G6/10^7 -> 0 | H7: =+H6/10^7 -> 0 | I7: =+I6/10^7 -> 0 | J7: =+J6/10^7 -> 0 | ... AY7: =+AY6/10^7 -> 0

Sheet Sheet2
J19: 219.3 | K19: 186.25 | L19: 186.75
J20: 192.9 | K20: 135.5 | L20: 146.9 | N20: 219.3 | O20: 192.9 | P20: 186 | Q20: 178.7 | R20: 207 | S20: 255.15 | T20: 348.25 | U20: 374 | V20: 495.9 | W20: 659.9 | X20: 613.4 | Y20: 607.9 | Z20: 555.95 | AA20: 497.8 | AB20: 459.9 | AC20: 374 | AD20: 362 | AE20: 341.5 | AF20: 384.2 | AG20: 433.8 | AH20: 460 | AI20: 474.4 | AJ20: 414.4 | AK20: 318.7 | AL20: 303.25 | AM20: 332.7 | AN20: 295 | AO20: 247 | AP20: 214.4 | AQ20: 179.5 | AR20: 97.9 | AS20: 119.1 | AT20: 130.65 | AU20: 148.55 | AV20: 153.8 | AW20: 152.9 | AX20: 136 | AY20: 141.15 | AZ20: 128.1 | BA20: 142.5 | BB20: 143.55 | BC20: 124.5 | BD20: 241 | BE20: 450 | BF20: 503.35
J21: 186 | K21: 145.4 | L21: 169.1 | N21: 186.25 | O21: 135.5 | P21: 145.4 | Q21: 108.95 | R21: 137 | S21: 170 | T21: 243.15 | U21: 307.5 | V21: 325.1 | W21: 463 | X21: 467.05 | Y21: 436.5 | Z21: 467 | AA21: 348.2 | AB21: 325 | AC21: 313.1 | AD21: 285 | AE21: 277.85 | AF21: 327 | AG21: 317 | AH21: 370.7 | AI21: 360 | AJ21: 271.15 | AK21: 233.15 | AL21: 218.8 | AM21: 262 | AN21: 223.6 | AO21: 137.6 | AP21: 142 | AQ21: 59.3 | AR21: 58 | AS21: 72.8 | AT21: 80 | AU21: 107.25 | AV21: 106 | AW21: 125.1 | AX21: 112.25 | AY21: 81.45 | AZ21: 88 | BA21: 90.35 | BB21: 106.05 | BC21: 98.55 | BD21: 119.25 | BE21: 210 | BF21: 349
J22: 178.7 | K22: 108.95 | L22: 139.75 | N22: 186.75 | O22: 146.9 | P22: 169.1 | Q22: 139.75 | R22: 202.15 | S22: 249.05 | T22: 346.4 | U22: 349.2 | V22: 469.9 | W22: 584.8 | X22: 536.15 | Y22: 513.35 | Z22: 474 | AA22: 438.55 | AB22: 355.4 | AC22: 334.95 | AD22: 298.8 | AE22: 328.35 | AF22: 343 | AG22: 389.9 | AH22: 443.05 | AI22: 407.5 | AJ22: 290.1 | AK22: 235.75 | AL22: 292.65 | AM22: 276.1 | AN22: 237.05 | AO22: 190.1 | AP22: 147.2 | AQ22: 71.9 | AR22: 75.2 | AS22: 90.1 | AT22: 117.2 | AU22: 116.3 | AV22: 140.5 | AW22: 128.6 | AX22: 133.65 | AY22: 91.65 | AZ22: 97.65 | BA22: 125 | BB22: 115.35 | BC22: 119.25 | BD22: 219.3 | BE22: 442.65 | BF22: 503.35
J23: 207 | K23: 137 | L23: 202.15
J24: 255.15 | K24: 170 | L24: 249.05
J25: 348.25 | K25: 243.15 | L25: 346.4
J26: 374 | K26: 307.5 | L26: 349.2
J27: 495.9 | K27: 325.1 | L27: 469.9
J28: 659.9 | K28: 463 | L28: 584.8
J29: 613.4 | K29: 467.05 | L29: 536.15
J30: 607.9 | K30: 436.5 | L30: 513.35
J31: 555.95 | K31: 467 | L31: 474
J32: 497.8 | K32: 348.2 | L32: 438.55
J33: 459.9 | K33: 325 | L33: 355.4
J34: 374 | K34: 313.1 | L34: 334.95
... J63: 503.35 | K63: 349 | L63: 503.35
