Workbook

Sheet Template
A1: =+'Annual Raw'!C4 -> Thyrocare Technologies Ltd. | B1: 36951 | C1: =EOMONTH(B1,12) -> 37346 | D1: =EOMONTH(C1,12) -> 37711 | E1: =EOMONTH(D1,12) -> 38077 | F1: =EOMONTH(E1,12) -> 38442 | G1: =EOMONTH(F1,12) -> 38807 | H1: =EOMONTH(G1,12) -> 39172 | I1: =EOMONTH(H1,12) -> 39538 | J1: =EOMONTH(I1,12) -> 39903 | ... AE1: =EOMONTH(AD1,12) -> 47573 | AH1: QTR | AI1: 41061 | AJ1: 41153 | AK1: 41244 | AL1: 41334 | AM1: 41426 | AN1: 41518 | AO1: 41609 | AP1: 41699 | AQ1: 41791 | AR1: 41883 | AS1: 41974 | AT1: 42064 | AU1: 42156 | AV1: 42248 | AW1: 42339 | AX1: 42430 | AY1: 42522 | AZ1: 42614 | BA1: 42705 | BB1: 42795 | BC1: 42887 | BD1: 42979 | BE1: 43070 | BF1: 43160 | BG1: 43252 | BH1: 43344 | BI1: 43435 | BJ1: 43525 | BK1: 43617 | BL1: 43709 | BM1: 43800 | BN1: 43891 | BO1: 43983 | BP1: 44075 | BQ1: =EOMONTH(BP1,3) -> 44196 | BR1: =EOMONTH(BQ1,3) -> 44286 | BS1: =EOMONTH(BR1,3) -> 44377 | BT1: =EOMONTH(BS1,3) -> 44469 | BU1: =EOMONTH(BT1,3) -> 44561 | BV1: =EOMONTH(BU1,3) -> 44651 | BW1: =EOMONTH(BV1,3) -> 44742 | BX1: =EOMONTH(BW1,3) -> 44834 | ... DB1: =EOMONTH(DA1,3) -> 47573 | DE1: HISTORICAL ESTIMATES | DF1: 46112
A2: Presentation Data (Start)
A4: Revenue Breakup
A5: Pathology | Q5: =SUM(AU5:AX5) -> 214.29 | R5: =SUM(AY5:BB5) -> 273.2 | S5: =SUM(BC5:BF5) -> 328.96 | T5: =SUM(BG5:BJ5) -> 368.11 | U5: =SUM(BK5:BN5) -> 397.06 | V5: =SUM(BO5:BR5) -> 472.87 | W5: =SUM(BS5:BV5) -> 555.43 | X5: =SUM(BW5:BZ5) -> 481.21 | Y5: =SUM(CA5:CD5) -> 522.23 | Z5: =SUM(CE5:CH5) -> 629.69 | AA5: =SUM(CI5:CL5) -> 775.8 | AB5: =+SUM(CM5:CP5) -> 919.51997 | AC5: =+SUM(CQ5:CT5) -> 1097.3551 | AD5: =+SUM(CU5:CX5) -> 1309.5836 | AE5: =+SUM(CY5:DB5) -> 1562.8571 | AU5: 50.64 | AV5: 55.58 | AW5: 50.29 | AX5: 57.78 | AY5: 62 | AZ5: 70.1 | BA5: 62.63 | BB5: 78.47 | BC5: 81.5 | BD5: 81.04 | BE5: 77.02 | BF5: 89.4 | BG5: 88.87 | BH5: 95.18 | BI5: 87.42 | BJ5: 96.64 | BK5: 99.97 | BL5: 106.99 | BM5: 97.25 | BN5: 92.85 | BO5: 54.1 | BP5: 148.25 | BQ5: 131.84 | BR5: 138.68 | BS5: 156.94 | BT5: 167.13 | BU5: 109.3 | BV5: 122.06 | BW5: 118.43 | BX5: 123.83 | BY5: 115.74 | BZ5: 123.21 | CA5: 121.94 | CB5: 136.75 | CC5: 122.43 | CD5: 141.11 | CE5: 143.21 | CF5: 161.92 | CG5: 151.87 | CH5: 172.69 | CI5: 178.9 | CJ5: 202.3 | CK5: 183.1 | CL5: 211.5 | CM5: =CM22 -> 212.4527 | CN5: =CN22 -> 240.12261 | CO5: =CO22 -> 216.72788 | CP5: =CP22 -> 250.21678 | CQ5: =CQ22 -> 253.54105 | CR5: =CR22 -> 286.56232 | CS5: =CS22 -> 258.64305 | CT5: =CT22 -> 298.60871 | ... DB5: =DB22 -> 425.27959
A6: Radiology | Q6: =SUM(AU6:AX6) -> 26.68 | R6: =SUM(AY6:BB6) -> 33.61 | S6: =SUM(BC6:BF6) -> 27.37 | T6: =SUM(BG6:BJ6) -> 34.8 | U6: =SUM(BK6:BN6) -> 37.03 | V6: =SUM(BO6:BR6) -> 21.76 | W6: =SUM(BS6:BV6) -> 33.38 | X6: =SUM(BW6:BZ6) -> 45.46 | Y6: =SUM(CA6:CD6) -> 49.65 | Z6: =SUM(CE6:CH6) -> 57.67 | AA6: =SUM(CI6:CL6) -> 53.16 | AB6: =+SUM(CM6:CP6) -> 49.6 | AC6: =+SUM(CQ6:CT6) -> 49.6 | AD6: =+SUM(CU6:CX6) -> 49.6 | AE6: =+SUM(CY6:DB6) -> 49.6 | AU6: 6.36 | AV6: 6.68 | AW6: 6.37 | AX6: 7.27 | AY6: 7.36 | AZ6: 8.62 | BA6: 8.42 | BB6: 9.21 | BC6: 6.26 | BD6: 7 | BE6: 6.85 | BF6: 7.26 | BG6: 8.28 | BH6: 8.7 | BI6: 8.87 | BJ6: 8.95 | BK6: 10 | BL6: 9.51 | BM6: 8.65 | BN6: 8.87 | BO6: 2.17 | BP6: 5 | BQ6: 6.43 | BR6: 8.16 | BS6: 7.7 | BT6: 9.08 | BU6: 8.1 | BV6: 8.5 | BW6: 9.36 | BX6: 11.14 | BY6: 12.29 | BZ6: 12.67 | CA6: 12.95 | CB6: 11.25 | CC6: 12.31 | CD6: 13.14 | CE6: 13.7 | CF6: 15.44 | CG6: 14.06 | CH6: 14.47 | CI6: 14.13 | CJ6: 14.23 | CK6: 12.4 | CL6: 12.4 | CM6: =CL6 -> 12.4 | CN6: =CM6 -> 12.4 | CO6: =CN6 -> 12.4 | CP6: =CO6 -> 12.4 | CQ6: =CP6 -> 12.4 | CR6: =CQ6 -> 12.4 | CS6: =CR6 -> 12.4 | CT6: =CS6 -> 12.4 | ... DB6: =DA6 -> 12.4
A7: Total Revenue | Q7: =+SUM(Q5:Q6) -> 240.97 | R7: =+SUM(R5:R6) -> 306.81 | S7: =+SUM(S5:S6) -> 356.33 | T7: =+SUM(T5:T6) -> 402.91 | U7: =+SUM(U5:U6) -> 434.09 | V7: =+SUM(V5:V6) -> 494.63 | W7: =+SUM(W5:W6) -> 588.81 | X7: =+SUM(X5:X6) -> 526.67 | ... AE7: =+SUM(AE5:AE6) -> 1612.4571 | AU7: =+SUM(AU5:AU6) -> 57 | AV7: =+SUM(AV5:AV6) -> 62.26 | AW7: =+SUM(AW5:AW6) -> 56.66 | AX7: =+SUM(AX5:AX6) -> 65.05 | AY7: =+SUM(AY5:AY6) -> 69.36 | AZ7: =+SUM(AZ5:AZ6) -> 78.72 | BA7: =+SUM(BA5:BA6) -> 71.05 | BB7: =+SUM(BB5:BB6) -> 87.68 | ... DB7: =+SUM(DB5:DB6) -> 437.67959
A8: Checksum | Q8: =+Q7-Q41 -> 0.005 | R8: =+R7-R41 -> 2.423 | S8: =+S7-S41 -> 0.01 | T8: =+T7-T41 -> 0 | U8: =+U7-U41 -> -0.17 | V8: =+V7-V41 -> 0.01 | W8: =+W7-W41 -> -0.05 | X8: =+X7-X41 -> 0 | ... Z8: =+Z7-Z41 -> 0.01 | AU8: =+AU7-AU41 -> 0.005 | AV8: =+AV7-AV41 -> -0.005 | AW8: =+AW7-AW41 -> 0.008 | AX8: =+AX7-AX41 -> -0.005 | AY8: =+AY7-AY41 -> 0.615 | AZ8: =+AZ7-AZ41 -> 0.572 | BA8: =+BA7-BA41 -> 0.672 | BB8: =+BB7-BB41 -> 0.564 | ... DB8: =+DB7-DB41 -> 0
A10: EBITDA Breakup
A11: Pathology | Q11: =SUM(AU11:AX11) -> 0 | R11: =SUM(AY11:BB11) -> 0 | S11: =SUM(BC11:BF11) -> 0 | U11: =SUM(BK11:BN11) -> 167.08 | V11: =SUM(BO11:BR11) -> 171.07 | W11: =SUM(BS11:BV11) -> 230.54 | X11: =SUM(BW11:BZ11) -> 142.53 | Y11: =SUM(CA11:CD11) -> 157.3 | Z11: =SUM(CE11:CH11) -> 203.8 | AA11: =SUM(CI11:CL11) -> 267.4 | AB11: =+SUM(CM11:CP11) -> 0 | AC11: =+SUM(CQ11:CT11) -> 0 | AD11: =+SUM(CU11:CX11) -> 0 | AE11: =+SUM(CY11:DB11) -> 0 | BK11: 44.02 | BL11: 50.92 | BM11: 42.84 | BN11: 29.3 | BO11: 9.51 | BP11: 61.7 | BQ11: 49.17 | BR11: 50.69 | BS11: 70.47 | BT11: 87 | BU11: 36 | BV11: 37.07 | BW11: 34.08 | BX11: 37.53 | BY11: 32.27 | BZ11: 38.65 | CA11: 40.3 | CB11: 41.5 | CC11: 34.3 | CD11: 41.2 | CE11: 43.5 | CF11: 50.7 | CG11: 47.1 | CH11: 62.5 | CI11: 61.7 | CJ11: 72.6 | CK11: 60.7 | CL11: 72.4
A12: Radiology (incl.ESOP cost) | Q12: =SUM(AU12:AX12) -> 0 | R12: =SUM(AY12:BB12) -> 0 | S12: =SUM(BC12:BF12) -> 0 | U12: =SUM(BK12:BN12) -> 4.76 | V12: =SUM(BO12:BR12) -> 0.05 | W12: =SUM(BS12:BV12) -> 3.32 | X12: =SUM(BW12:BZ12) -> 5.81 | Y12: =SUM(CA12:CD12) -> 4.5 | Z12: =SUM(CE12:CH12) -> 6.2 | AA12: =SUM(CI12:CL12) -> 8.7 | AB12: =+SUM(CM12:CP12) -> 0 | AC12: =+SUM(CQ12:CT12) -> 0 | AD12: =+SUM(CU12:CX12) -> 0 | AE12: =+SUM(CY12:DB12) -> 0 | BK12: 1.32 | BL12: 1.25 | BM12: 0.87 | BN12: 1.32 | BO12: -1.14 | BP12: -0.2 | BQ12: 0.65 | BR12: 0.74 | BS12: 0.6 | BT12: 1.6 | BU12: 0.7 | BV12: 0.42 | BW12: 0.42 | BX12: 1.64 | BY12: 2.11 | BZ12: 1.64 | CA12: 1.4 | CB12: 1.1 | CC12: 1 | CD12: 1 | CE12: 1.3 | CF12: -0.2 | CG12: 2.3 | CH12: 2.8 | CI12: 1.7 | CJ12: 2.8 | CK12: 1.5 | CL12: 2.7
A13: ESOP Cost(b/f) | BV13: 0.1 | BW13: 1.42 | BX13: -7.59 | BY13: -6.52 | BZ13: -15.6 | CA13: -7.19 | CB13: -5.08 | CC13: -3.71 | CD13: -8.39 | CE13: -2.16 | CF13: -2.21 | CG13: -7.67 | CH13: -7.6 | CI13: -5.63 | CJ13: -4.05 | CK13: -4.37 | CL13: 0
A14: Total EBITDA | Q14: =+Q11+Q12 -> 0 | R14: =+R11+R12 -> 0 | S14: =+S11+S12 -> 0 | U14: =+U11+U12 -> 171.84 | V14: =+V11+V12 -> 171.12 | W14: =+W11+W12 -> 233.86 | X14: =+X11+X12 -> 148.34 | Y14: =+Y11+Y12 -> 161.8 | Z14: =+Z11+Z12 -> 210 | AA14: =+AA11+AA12 -> 276.1 | AB14: =+AB11+AB12 -> 0 | ... AE14: =+AE11+AE12 -> 0 | BK14: =+BK11+BK12 -> 45.34 | BL14: =+BL11+BL12 -> 52.17 | BM14: =+BM11+BM12 -> 43.71 | BN14: =+BN11+BN12 -> 30.62 | BO14: =+BO11+BO12 -> 8.37 | BP14: =+BP11+BP12 -> 61.5 | BQ14: =+BQ11+BQ12 -> 49.82 | BR14: =+BR11+BR12 -> 51.43 | ... BU14: =+BU11+BU12 -> 36.7 | BV14: =+BV11+BV12+BV13 -> 37.59 | BW14: =+BW11+BW12+BW13 -> 35.92 | BX14: =+BX11+BX12+BX13 -> 31.58 | BY14: =+BY11+BY12+BY13 -> 27.86 | BZ14: =+BZ11+BZ12+BZ13 -> 24.69 | CA14: =+CA11+CA12+CA13 -> 34.51 | CB14: =+CB11+CB12+CB13 -> 37.52 | CC14: =+CC11+CC12+CC13 -> 31.59 | ... CL14: =+CL11+CL12+CL13 -> 75.1
A15: Checksum | Q15: =+Q14-Q70 -> -94.049 | R15: =+R14-R70 -> -115.379 | S15: =+S14-S70 -> -144.72 | U15: =+U14-U70 -> -1.73 | V15: =+V14-V70 -> -0.14 | W15: =+W14-W70 -> -1.87 | X15: =+X14-X70 -> 25.81 | Y15: =+Y14-Y70 -> 23.04 | Z15: =+Z14-Z70 -> 19.44 | BK15: =+BK14-BK70 -> -0.27 | BL15: =+BL14-BL70 -> 0.01 | BM15: =+BM14-BM70 -> -0.07 | BN15: =+BN14-BN70 -> -0.35 | BO15: =+BO14-BO70 -> -0.09 | BP15: =+BP14-BP70 -> -0.4 | BQ15: =+BQ14-BQ70 -> 0.2 | BR15: =+BR14-BR70 -> -0.1 | ... CL15: =+CL14-CL70 -> 0.01
A17: Pathology- Revenue Breakup
A18: Franchise | Q18: =SUM(AU18:AX18) -> 0 | R18: =SUM(AY18:BB18) -> 0 | S18: =SUM(BC18:BF18) -> 0 | T18: =SUM(BG18:BJ18) -> 0 | U18: =SUM(BK18:BN18) -> 0 | V18: =SUM(BO18:BR18) -> 0 | W18: =SUM(BS18:BV18) -> 247 | X18: =SUM(BW18:BZ18) -> 280 | Y18: =SUM(CA18:CD18) -> 325.2 | Z18: =SUM(CE18:CH18) -> 399 | AA18: =SUM(CI18:CL18) -> 477.7 | AB18: =+SUM(CM18:CP18) -> 919.51997 | AC18: =+SUM(CQ18:CT18) -> 1097.3551 | AD18: =+SUM(CU18:CX18) -> 1309.5836 | AE18: =+SUM(CY18:DB18) -> 1562.8571 | BS18: 60 | BT18: 65 | BU18: 60 | BV18: 62 | BW18: 68 | BX18: 72 | BY18: 67 | BZ18: 73 | CA18: 79.4 | CB18: 86.3 | CC18: 76 | CD18: 83.5 | CE18: 88.5 | CF18: 104.9 | CG18: 100.2 | CH18: 105.4 | CI18: 112.5 | CJ18: 125.4 | CK18: 112.2 | CL18: 127.6 | CM18: =CM32*CM28/10 -> 212.4527 | CN18: =CN32*CN28/10 -> 240.12261 | CO18: =CO32*CO28/10 -> 216.72788 | CP18: =CP32*CP28/10 -> 250.21678 | CQ18: =CQ32*CQ28/10 -> 253.54105 | CR18: =CR32*CR28/10 -> 286.56232 | CS18: =CS32*CS28/10 -> 258.64305 | CT18: =CT32*CT28/10 -> 298.60871 | ... DB18: =DB32*DB28/10 -> 425.27959
A19: Partnerships (Includes B2G) | Q19: =SUM(AU19:AX19) -> 0 | R19: =SUM(AY19:BB19) -> 0 | S19: =SUM(BC19:BF19) -> 0 | T19: =SUM(BG19:BJ19) -> 0 | U19: =SUM(BK19:BN19) -> 0 | V19: =SUM(BO19:BR19) -> 0 | W19: =SUM(BS19:BV19) -> 104 | X19: =SUM(BW19:BZ19) -> 149 | Y19: =SUM(CA19:CD19) -> 151.2 | Z19: =SUM(CE19:CH19) -> 191.8 | AA19: =SUM(CI19:CL19) -> 253.6 | AB19: =+SUM(CM19:CP19) -> 0 | AC19: =+SUM(CQ19:CT19) -> 0 | AD19: =+SUM(CU19:CX19) -> 0 | AE19: =+SUM(CY19:DB19) -> 0 | BS19: 20 | BT19: 28 | BU19: 25 | BV19: 31 | BW19: 38 | BX19: 38 | BY19: 35 | BZ19: 38 | CA19: 32.3 | CB19: 36.9 | CC19: 35.2 | CD19: 46.8 | CE19: 41.5 | CF19: 48.9 | CG19: 43.2 | CH19: 58.2 | CI19: 56.3 | CJ19: 65.6 | CK19: 60.1 | CL19: 71.6
A20: D2C | Q20: =SUM(AU20:AX20) -> 0 | R20: =SUM(AY20:BB20) -> 0 | S20: =SUM(BC20:BF20) -> 0 | T20: =SUM(BG20:BJ20) -> 0 | U20: =SUM(BK20:BN20) -> 0 | V20: =SUM(BO20:BR20) -> 0 | W20: =SUM(BS20:BV20) -> 25 | X20: =SUM(BW20:BZ20) -> 28 | Y20: =SUM(CA20:CD20) -> 31.6 | Z20: =SUM(CE20:CH20) -> 38 | AA20: =SUM(CI20:CL20) -> 43 | AB20: =+SUM(CM20:CP20) -> 0 | AC20: =+SUM(CQ20:CT20) -> 0 | AD20: =+SUM(CU20:CX20) -> 0 | AE20: =+SUM(CY20:DB20) -> 0 | BS20: 4 | BT20: 7 | BU20: 6 | BV20: 8 | BW20: 6 | BX20: 7 | BY20: 7 | BZ20: 8 | CA20: 7.4 | CB20: 8.3 | CC20: 7.4 | CD20: 8.5 | CE20: 8.6 | CF20: 10 | CG20: 9.1 | CH20: 10.3 | CI20: 10.1 | CJ20: 11.2 | CK20: 10.2 | CL20: 11.5
A21: Covid Materials & Others | Q21: =SUM(AU21:AX21) -> 0 | R21: =SUM(AY21:BB21) -> 0 | S21: =SUM(BC21:BF21) -> 0 | T21: =SUM(BG21:BJ21) -> 0 | U21: =SUM(BK21:BN21) -> 0 | V21: =SUM(BO21:BR21) -> 0 | W21: =SUM(BS21:BV21) -> 185.49 | X21: =SUM(BW21:BZ21) -> 29.46 | Y21: =SUM(CA21:CD21) -> 16 | Z21: =SUM(CE21:CH21) -> 5 | AA21: =SUM(CI21:CL21) -> 0 | AB21: =+SUM(CM21:CP21) -> 0 | AC21: =+SUM(CQ21:CT21) -> 0 | AD21: =+SUM(CU21:CX21) -> 0 | AE21: =+SUM(CY21:DB21) -> 0 | BS21: 75.26 | BT21: 68.7 | BU21: 19.2 | BV21: 22.33 | BW21: 7.24 | BX21: 8.23 | BY21: 8.17 | BZ21: 5.82 | CA21: 4.51 | CB21: 4.79 | CC21: 4.3 | CD21: 2.4 | CE21: 5
A22: Total Pathology Revenue | Q22: =+SUM(Q18:Q21) -> 0 | R22: =+SUM(R18:R21) -> 0 | S22: =+SUM(S18:S21) -> 0 | T22: =+SUM(T18:T21) -> 0 | U22: =+SUM(U18:U21) -> 0 | V22: =+SUM(V18:V21) -> 0 | W22: =+SUM(W18:W21) -> 561.49 | X22: =+SUM(X18:X21) -> 486.46 | ... AE22: =+SUM(AE18:AE21) -> 1562.8571 | BS22: =+SUM(BS18:BS21) -> 159.26 | BT22: =+SUM(BT18:BT21) -> 168.7 | BU22: =+SUM(BU18:BU21) -> 110.2 | BV22: =+SUM(BV18:BV21) -> 123.33 | BW22: =+SUM(BW18:BW21) -> 119.24 | BX22: =+SUM(BX18:BX21) -> 125.23 | BY22: =+SUM(BY18:BY21) -> 117.17 | BZ22: =+SUM(BZ18:BZ21) -> 124.82 | ... DB22: =+SUM(DB18:DB21) -> 425.27959
A23: Checksum | W23: =+W22-W5 -> 6.06 | X23: =+X22-X5 -> 5.25 | Y23: =+Y22-Y5 -> 1.77 | Z23: =+Z22-Z5 -> 4.11 | AA23: =+AA22-AA5 -> -1.5 | AB23: =+AB22-AB5 -> 0 | AC23: =+AC22-AC5 -> 0 | AD23: =+AD22-AD5 -> 0 | AE23: =+AE22-AE5 -> 0 | BS23: =+BS22-BS5 -> 2.32 | BT23: =+BT22-BT5 -> 1.57 | BU23: =+BU22-BU5 -> 0.9 | BV23: =+BV22-BV5 -> 1.27 | BW23: =+BW22-BW5 -> 0.81 | BX23: =+BX22-BX5 -> 1.4 | BY23: =+BY22-BY5 -> 1.43 | BZ23: =+BZ22-BZ5 -> 1.61 | ... DB23: =+DB22-DB5 -> 0
A25: Key Metrics
A26: Franchisees | X26: =+BZ26 -> 9481 | Y26: =+CD26 -> 9696 | Z26: =+CH26 -> 11249 | AA26: =CL26 -> 10800 | AB26: =CP26 -> 12636 | AC26: =CT26 -> 14784.12 | AD26: =CX26 -> 17297.42 | AE26: =DB26 -> 20237.982 | BY26: 7171 | BZ26: 9481 | CA26: 7633 | CB26: 7451 | CC26: 7284 | CD26: 9696 | CE26: 8145 | CF26: 8446 | CG26: 9158 | CH26: 11249 | CI26: 9551 | CJ26: 10159 | CK26: 10278 | CL26: 10800 | CM26: =CI26+(CI26*CM27) -> 11174.67 | CN26: =CJ26+(CJ26*CN27) -> 11886.03 | CO26: =CK26+(CK26*CO27) -> 12025.26 | CP26: =CL26+(CL26*CP27) -> 12636 | CQ26: =CM26+(CM26*CQ27) -> 13074.364 | CR26: =CN26+(CN26*CR27) -> 13906.655 | CS26: =CO26+(CO26*CS27) -> 14069.554 | CT26: =CP26+(CP26*CT27) -> 14784.12 | ... DB26: =CX26+(CX26*DB27) -> 20237.982
A27: YOY% | Y27: =Y26/X26-1 -> 0.022676933 | Z27: =Z26/Y26-1 -> 0.16016914 | AA27: =AA26/Z26-1 -> -0.039914659 | AB27: =AB26/AA26-1 -> 0.17 | AC27: =AC26/AB26-1 -> 0.17 | AD27: =AD26/AC26-1 -> 0.17 | AE27: =AE26/AD26-1 -> 0.17 | CC27: =CC26/BY26-1 -> 0.015757914 | CD27: =CD26/BZ26-1 -> 0.022676933 | CE27: =CE26/CA26-1 -> 0.067077165 | CF27: =CF26/CB26-1 -> 0.13353912 | CG27: =CG26/CC26-1 -> 0.25727622 | CH27: =CH26/CD26-1 -> 0.16016914 | CI27: =CI26/CE26-1 -> 0.17262124 | CJ27: =CJ26/CF26-1 -> 0.2028179 | ... CL27: =CL26/CH26-1 -> -0.039914659 | CM27: 0.17 | CN27: 0.17 | CO27: 0.17 | CP27: 0.17 | CQ27: 0.17 | CR27: 0.17 | CS27: 0.17 | CT27: 0.17 | CU27: 0.17 | CV27: 0.17 | CW27: 0.17 | CX27: 0.17 | CY27: 0.17 | CZ27: 0.17 | DA27: 0.17 | DB27: 0.17
A28: No. Of Tests Performed(mn) | X28: =SUM(BW28:BZ28) -> 141.4 | Y28: =SUM(CA28:CD28) -> 147 | Z28: =SUM(CE28:CH28) -> 167.9 | AA28: =SUM(CI28:CL28) -> 208.8 | AB28: =+SUM(CM28:CP28) -> 244.296 | AC28: =+SUM(CQ28:CT28) -> 285.82632 | AD28: =+SUM(CU28:CX28) -> 334.41679 | AE28: =+SUM(CY28:DB28) -> 391.26765 | BW28: 35 | BX28: 36.2 | BY28: 33.9 | BZ28: 36.3 | CA28: 35.086207 | CB28: 38.2 | CC28: 34.2 | CD28: 39.513793 | CE28: 40.7 | CF28: 44 | CG28: 39 | CH28: 44.2 | CI28: 46.9 | CJ28: 53.3 | CK28: 49.6 | CL28: 59 | CM28: =CM29*3*CM26/10^6 -> 54.873 | CN28: =CN29*3*CN26/10^6 -> 62.361 | CO28: =CO29*3*CO26/10^6 -> 58.032 | CP28: =CP29*3*CP26/10^6 -> 69.03 | CQ28: =CQ29*3*CQ26/10^6 -> 64.20141 | CR28: =CR29*3*CR26/10^6 -> 72.96237 | CS28: =CS29*3*CS26/10^6 -> 67.89744 | CT28: =CT29*3*CT26/10^6 -> 80.7651 | ... DB28: =DB29*3*DB26/10^6 -> 110.55935
A29: Test Per Franchisee per month | X29: =X28/X26*1000000/12 -> 1242.8366 | Y29: =Y28/Y26*1000000/12 -> 1263.4076 | Z29: =Z28/Z26*1000000/12 -> 1243.8143 | AA29: =AA28/AA26*1000000/12 -> 1611.1111 | AB29: =AB28/AB26*1000000/12 -> 1611.1111 | AC29: =AC28/AC26*1000000/12 -> 1611.1111 | AD29: =AD28/AD26*1000000/12 -> 1611.1111 | AE29: =AE28/AE26*1000000/12 -> 1611.1111 | BY29: =BY28*1000000/BY26/3 -> 1575.7914 | BZ29: =BZ28*1000000/BZ26/3 -> 1276.2367 | CA29: =CA28*1000000/CA26/3 -> 1532.2157 | CB29: =CB28*1000000/CB26/3 -> 1708.9429 | CC29: =CC28*1000000/CC26/3 -> 1565.0741 | CD29: =CD28*1000000/CD26/3 -> 1358.4225 | CE29: =CE28*1000000/CE26/3 -> 1665.6435 | CF29: =CF28*1000000/CF26/3 -> 1736.5222 | ... CL29: =CL28*1000000/CL26/3 -> 1820.9877 | CM29: =CI29+(CI29*CM30) -> 1636.8269 | CN29: =CJ29+(CJ29*CN30) -> 1748.8598 | CO29: =CK29+(CK29*CO30) -> 1608.6139 | CP29: =CL29+(CL29*CP30) -> 1820.9877 | CQ29: =CM29+(CM29*CQ30) -> 1636.8269 | CR29: =CN29+(CN29*CR30) -> 1748.8598 | CS29: =CO29+(CO29*CS30) -> 1608.6139 | CT29: =CP29+(CP29*CT30) -> 1820.9877 | ... DB29: =CX29+(CX29*DB30) -> 1820.9877
A30: YOY% | Y30: =Y29/X29-1 -> 0.016551686 | Z30: =Z29/Y29-1 -> -0.015508317 | AA30: =AA29/Z29-1 -> 0.29529879 | AB30: =AB29/AA29-1 -> 0 | AC30: =AC29/AB29-1 -> 0 | AD30: =AD29/AC29-1 -> 0 | AE30: =AE29/AD29-1 -> 0 | CC30: =CC29/BY29-1 -> -0.0068011838 | CD30: =CD29/BZ29-1 -> 0.064396986 | CE30: =CE29/CA29-1 -> 0.087081645 | CF30: =CF29/CB29-1 -> 0.016138251 | CG30: =CG29/CC29-1 -> -0.092998931 | CH30: =CH29/CD29-1 -> -0.035833056 | CI30: =CI29/CE29-1 -> -0.017300631 | CJ30: =CJ29/CF29-1 -> 0.0071047616 | ... CL30: =CL29/CH29-1 -> 0.39033643 | CM30: 0 | CN30: 0 | CO30: 0 | CP30: 0 | CQ30: 0 | CR30: 0 | CS30: 0 | CT30: 0 | CU30: 0 | CV30: 0 | CW30: 0 | CX30: 0 | CY30: 0 | CZ30: 0 | DA30: 0 | DB30: 0
A31: No. Of Patients(mn) | X31: =SUM(BW31:BZ31) -> 15.4 | Y31: =SUM(CA31:CD31) -> 15.1 | Z31: =SUM(CE31:CH31) -> 16.7 | BW31: 3.7 | BX31: 4 | BY31: 3.7 | BZ31: 4 | CA31: 3.7614679 | CB31: 4 | CC31: 3.5 | CD31: 3.8385321 | CE31: 4.1 | CF31: 4.4 | CG31: 3.9 | CH31: 4.3 | CI31: 4.6 | CJ31: 5 | CK31: 4.5 | CL31: 5.1
A32: Revenue Per Test (Pathology) | X32: =+X22*10^7/X28/10^6 -> 34.403112 | Y32: =+Y22*10^7/Y28/10^6 -> 35.646259 | Z32: =+Z22*10^7/Z28/10^6 -> 37.74866 | AA32: =+AA22*10^7/AA28/10^6 -> 37.083333 | AB32: =+AB22*10^7/AB28/10^6 -> 37.639583 | AC32: =+AC22*10^7/AC28/10^6 -> 38.392375 | AD32: =+AD22*10^7/AD28/10^6 -> 39.160223 | AE32: =+AE22*10^7/AE28/10^6 -> 39.943427 | BW32: =+BW22*10^7/BW28/10^6 -> 34.068571 | BX32: =+BX22*10^7/BX28/10^6 -> 34.593923 | BY32: =+BY22*10^7/BY28/10^6 -> 34.563422 | BZ32: =+BZ22*10^7/BZ28/10^6 -> 34.385675 | CA32: =+CA22*10^7/CA28/10^6 -> 35.230369 | CB32: =+CB22*10^7/CB28/10^6 -> 35.67801 | CC32: =+CC22*10^7/CC28/10^6 -> 35.935673 | CD32: =+CD22*10^7/CD28/10^6 -> 35.734357 | ... CL32: =+CL22*10^7/CL28/10^6 -> 35.711864 | CM32: =CI32+(CI32*CM33) -> 38.717164 | CN32: =CJ32+(CJ32*CN33) -> 38.505253 | CO32: =CK32+(CK32*CO33) -> 37.34627 | CP32: =CL32+(CL32*CP33) -> 36.247542 | CQ32: =CM32+(CM32*CQ33) -> 39.491507 | CR32: =CN32+(CN32*CR33) -> 39.275358 | CS32: =CO32+(CO32*CS33) -> 38.093196 | CT32: =CP32+(CP32*CT33) -> 36.972493 | ... DB32: =CX32+(CX32*DB33) -> 38.466182
A33: YOY% | Y33: =Y32/X32-1 -> 0.036134719 | Z33: =Z32/Y32-1 -> 0.058979582 | AA33: =AA32/Z32-1 -> -0.017625171 | AB33: =AB32/AA32-1 -> 0.015 | AC33: =AC32/AB32-1 -> 0.02 | AD33: =AD32/AC32-1 -> 0.02 | AE33: =AE32/AD32-1 -> 0.02 | CC33: =CC32/BY32-1 -> 0.039702397 | CD33: =CD32/BZ32-1 -> 0.039222215 | CE33: =CE32/CA32-1 -> 0.0014812996 | CF33: =CF32/CB32-1 -> 0.043423449 | CG33: =CG32/CC32-1 -> 0.088126682 | CH33: =CH32/CD32-1 -> 0.10101019 | CI33: =CI32/CE32-1 -> 0.081128876 | CJ33: =CJ32/CF32-1 -> 0.019043496 | ... CL33: =CL32/CH32-1 -> -0.09231489 | CM33: 0.015 | CN33: 0.015 | CO33: 0.015 | CP33: 0.015 | CQ33: 0.02 | CR33: 0.02 | CS33: 0.02 | CT33: 0.02 | CU33: 0.02 | CV33: 0.02 | CW33: 0.02 | CX33: 0.02 | CY33: 0.02 | CZ33: 0.02 | DA33: 0.02 | DB33: 0.02
A39: Presentation Data (End)
A40: Profit & Loss- Annual (Start)
A41: Gross Revenue | B41: ='Annual Raw'!C6 -> 0 | C41: ='Annual Raw'!D6 -> 0 | D41: ='Annual Raw'!E6 -> 0 | E41: ='Annual Raw'!F6 -> 0 | F41: ='Annual Raw'!G6 -> 0 | G41: ='Annual Raw'!H6 -> 0 | H41: ='Annual Raw'!I6 -> 33.754414 | I41: ='Annual Raw'!J6 -> 44.410636 | ... AA41: ='Annual Raw'!AB6 -> 829.04 | AB41: =+SUM(CM41:CP41) -> 969.11997 | AC41: =+SUM(CQ41:CT41) -> 1146.9551 | AD41: =+SUM(CU41:CX41) -> 1359.1836 | AE41: =+SUM(CY41:DB41) -> 1612.4571 | AI41: ='QTR Raw'!C6+'QTR Raw'!C8 -> 0 | AJ41: ='QTR Raw'!D6+'QTR Raw'!D8 -> 0 | AK41: ='QTR Raw'!E6+'QTR Raw'!E8 -> 0 | AL41: ='QTR Raw'!F6+'QTR Raw'!F8 -> 0 | AM41: ='QTR Raw'!G6+'QTR Raw'!G8 -> 0 | AN41: ='QTR Raw'!H6+'QTR Raw'!H8 -> 0 | AO41: ='QTR Raw'!I6+'QTR Raw'!I8 -> 0 | AP41: ='QTR Raw'!J6+'QTR Raw'!J8 -> 0 | ... CL41: ='QTR Raw'!BF6+'QTR Raw'!BF8 -> 223.95 | CM41: =CM7 -> 224.8527 | CN41: =CN7 -> 252.52261 | CO41: =CO7 -> 229.12788 | CP41: =CP7 -> 262.61678 | CQ41: =CQ7 -> 265.94105 | CR41: =CR7 -> 298.96232 | CS41: =CS7 -> 271.04305 | CT41: =CT7 -> 311.00871 | ... DB41: =DB7 -> 437.67959 | DF41: 219.93226
A42: Less: Exise Duty | B42: ='Annual Raw'!C7+'Annual Raw'!C8+'Annual Raw'!C9 -> 0 | C42: ='Annual Raw'!D7+'Annual Raw'!D8+'Annual Raw'!D9 -> 0 | D42: ='Annual Raw'!E7+'Annual Raw'!E8+'Annual Raw'!E9 -> 0 | E42: ='Annual Raw'!F7+'Annual Raw'!F8+'Annual Raw'!F9 -> 0 | F42: ='Annual Raw'!G7+'Annual Raw'!G8+'Annual Raw'!G9 -> 0 | G42: ='Annual Raw'!H7+'Annual Raw'!H8+'Annual Raw'!H9 -> 0 | H42: ='Annual Raw'!I7+'Annual Raw'!I8+'Annual Raw'!I9 -> 0 | I42: ='Annual Raw'!J7+'Annual Raw'!J8+'Annual Raw'!J9 -> 0 | ... AA42: ='Annual Raw'!AB7+'Annual Raw'!AB8+'Annual Raw'!AB9 -> 0 | AB42: =+SUM(CM42:CP42) -> 0 | AC42: =+SUM(CQ42:CT42) -> 0 | AD42: =+SUM(CU42:CX42) -> 0 | AE42: =+SUM(CY42:DB42) -> 0 | AI42: =+'QTR Raw'!C20+'QTR Raw'!C19+'QTR Raw'!C13+'QTR Raw'!C7 -> 0 | AJ42: =+'QTR Raw'!D20+'QTR Raw'!D19+'QTR Raw'!D13+'QTR Raw'!D7 -> 0 | AK42: =+'QTR Raw'!E20+'QTR Raw'!E19+'QTR Raw'!E13+'QTR Raw'!E7 -> 0 | AL42: =+'QTR Raw'!F20+'QTR Raw'!F19+'QTR Raw'!F13+'QTR Raw'!F7 -> 0 | AM42: =+'QTR Raw'!G20+'QTR Raw'!G19+'QTR Raw'!G13+'QTR Raw'!G7 -> 0 | AN42: =+'QTR Raw'!H20+'QTR Raw'!H19+'QTR Raw'!H13+'QTR Raw'!H7 -> 0 | AO42: =+'QTR Raw'!I20+'QTR Raw'!I19+'QTR Raw'!I13+'QTR Raw'!I7 -> 0 | AP42: =+'QTR Raw'!J20+'QTR Raw'!J19+'QTR Raw'!J13+'QTR Raw'!J7 -> 0 | ... CL42: =+'QTR Raw'!BF20+'QTR Raw'!BF19+'QTR Raw'!BF13+'QTR Raw'!BF7 -> 0 | DF42: 0
A43: Net Revenue | B43: =+B41-B42 -> 0 | C43: =+C41-C42 -> 0 | D43: =+D41-D42 -> 0 | E43: =+E41-E42 -> 0 | F43: =+F41-F42 -> 0 | G43: =+G41-G42 -> 0 | H43: =+H41-H42 -> 33.754414 | I43: =+I41-I42 -> 44.410636 | ... AE43: =+AE41-AE42 -> 1612.4571 | AI43: =+AI41-AI42 -> 0 | AJ43: =+AJ41-AJ42 -> 0 | AK43: =+AK41-AK42 -> 0 | AL43: =+AL41-AL42 -> 0 | AM43: =+AM41-AM42 -> 0 | AN43: =+AN41-AN42 -> 0 | AO43: =+AO41-AO42 -> 0 | AP43: =+AP41-AP42 -> 0 | ... DB43: =+DB41-DB42 -> 437.67959 | DF43: 219.93226
A44: Net Revenue YOY% | C44: =C43/B43-1 -> #DIV/0! | D44: =D43/C43-1 -> #DIV/0! | E44: =E43/D43-1 -> #DIV/0! | F44: =F43/E43-1 -> #DIV/0! | G44: =G43/F43-1 -> #DIV/0! | H44: =H43/G43-1 -> #DIV/0! | I44: =I43/H43-1 -> 0.31569863 | J44: =J43/I43-1 -> 0.019539038 | ... AE44: =AE43/AD43-1 -> 0.18634235 | AM44: =+IF(AI43<0,1-AM43/AI43,AM43/AI43-1) -> #DIV/0! | AN44: =+IF(AJ43<0,1-AN43/AJ43,AN43/AJ43-1) -> #DIV/0! | AO44: =+IF(AK43<0,1-AO43/AK43,AO43/AK43-1) -> #DIV/0! | AP44: =+IF(AL43<0,1-AP43/AL43,AP43/AL43-1) -> #DIV/0! | AQ44: =+IF(AM43<0,1-AQ43/AM43,AQ43/AM43-1) -> #DIV/0! | AR44: =+IF(AN43<0,1-AR43/AN43,AR43/AN43-1) -> #DIV/0! | AS44: =+IF(AO43<0,1-AS43/AO43,AS43/AO43-1) -> #DIV/0! | AT44: =+IF(AP43<0,1-AT43/AP43,AT43/AP43-1) -> #DIV/0! | ... DB44: =+IF(CX43<0,1-DB43/CX43,DB43/CX43-1) -> 0.18689669 | DF44: 0.17510291
A45: Net Revenue QOQ% | AJ45: =+IF(AI43<0,1-AJ43/AI43,AJ43/AI43-1) -> #DIV/0! | AK45: =+IF(AJ43<0,1-AK43/AJ43,AK43/AJ43-1) -> #DIV/0! | AL45: =+IF(AK43<0,1-AL43/AK43,AL43/AK43-1) -> #DIV/0! | AM45: =+IF(AL43<0,1-AM43/AL43,AM43/AL43-1) -> #DIV/0! | AN45: =+IF(AM43<0,1-AN43/AM43,AN43/AM43-1) -> #DIV/0! | AO45: =+IF(AN43<0,1-AO43/AN43,AO43/AN43-1) -> #DIV/0! | AP45: =+IF(AO43<0,1-AP43/AO43,AP43/AO43-1) -> #DIV/0! | AQ45: =+IF(AP43<0,1-AQ43/AP43,AQ43/AP43-1) -> #DIV/0! | ... DB45: =+IF(DA43<0,1-DB43/DA43,DB43/DA43-1) -> 0.14948837 | DF45: 0.12480059
A46: Increase/Decrease in Stock | B46: ='Annual Raw'!C11 -> 0 | C46: ='Annual Raw'!D11 -> 0 | D46: ='Annual Raw'!E11 -> 0 | E46: ='Annual Raw'!F11 -> 0 | F46: ='Annual Raw'!G11 -> 0 | G46: ='Annual Raw'!H11 -> 0 | H46: ='Annual Raw'!I11 -> 0 | I46: ='Annual Raw'!J11 -> 0 | ... AA46: ='Annual Raw'!AB11 -> -0.24 | AB46: =+SUM(CM46:CP46) -> 0 | AC46: =+SUM(CQ46:CT46) -> 0 | AD46: =+SUM(CU46:CX46) -> 0 | AE46: =+SUM(CY46:DB46) -> 0 | AI46: ='QTR Raw'!C10 -> 0 | AJ46: ='QTR Raw'!D10 -> 0 | AK46: ='QTR Raw'!E10 -> 0 | AL46: ='QTR Raw'!F10 -> 0 | AM46: ='QTR Raw'!G10 -> 0 | AN46: ='QTR Raw'!H10 -> 0 | AO46: ='QTR Raw'!I10 -> 0 | AP46: ='QTR Raw'!J10 -> 0 | ... CL46: ='QTR Raw'!BF10 -> -0.51 | DF46: -0.23
A47: Purchase of Finished Goods | B47: 0 | C47: 0 | D47: 0 | E47: 0 | F47: 0 | G47: 0 | H47: 0 | I47: 0 | J47: 0 | K47: 0 | L47: 0 | M47: 0 | N47: 0 | O47: 0 | P47: 0 | Q47: 0 | R47: 0 | S47: 0 | T47: 0 | U47: 0 | V47: 0 | W47: 0 | X47: 0 | Y47: 0 | Z47: 0 | AA47: 0 | AB47: =+SUM(CM47:CP47) -> 0 | AC47: =+SUM(CQ47:CT47) -> 0 | AD47: =+SUM(CU47:CX47) -> 0 | AE47: =+SUM(CY47:DB47) -> 0 | AI47: ='QTR Raw'!C12 -> 0 | AJ47: ='QTR Raw'!D12 -> 0 | AK47: ='QTR Raw'!E12 -> 0 | AL47: ='QTR Raw'!F12 -> 0 | AM47: ='QTR Raw'!G12 -> 0 | AN47: ='QTR Raw'!H12 -> 0 | AO47: ='QTR Raw'!I12 -> 0 | AP47: ='QTR Raw'!J12 -> 0 | ... CL47: ='QTR Raw'!BF12 -> 0.77 | DF47: 1.09
A48: Raw Material Consumed | B48: ='Annual Raw'!C12 -> 0 | C48: ='Annual Raw'!D12 -> 0 | D48: ='Annual Raw'!E12 -> 0 | E48: ='Annual Raw'!F12 -> 0 | F48: ='Annual Raw'!G12 -> 0 | G48: ='Annual Raw'!H12 -> 0 | H48: ='Annual Raw'!I12 -> 11.50973 | I48: ='Annual Raw'!J12 -> 11.1301 | ... AA48: ='Annual Raw'!AB12 -> 219.8 | AB48: =+SUM(CM48:CP48) -> 251.15758 | AC48: =+SUM(CQ48:CT48) -> 296.05356 | AD48: =+SUM(CU48:CX48) -> 350.62471 | AE48: =+SUM(CY48:DB48) -> 415.93349 | AI48: ='QTR Raw'!C11 -> 0 | AJ48: ='QTR Raw'!D11 -> 0 | AK48: ='QTR Raw'!E11 -> 0 | AL48: ='QTR Raw'!F11 -> 0 | AM48: ='QTR Raw'!G11 -> 0 | AN48: ='QTR Raw'!H11 -> 0 | AO48: ='QTR Raw'!I11 -> 0 | AP48: ='QTR Raw'!J11 -> 0 | ... CL48: ='QTR Raw'!BF11 -> 56.42 | CM48: =+CM43-CM49 -> 59.589106 | CN48: =+CN43-CN49 -> 65.458679 | CO48: =+CO43-CO49 -> 58.354313 | CP48: =+CP43-CP49 -> 67.755483 | CQ48: =+CQ43-CQ49 -> 68.939532 | CR48: =+CR43-CR49 -> 77.067192 | CS48: =+CS43-CS49 -> 69.772739 | CT48: =+CT43-CT49 -> 80.274097 | ... DB48: =+DB43-DB49 -> 112.90375 | DF48: 58.902422
A49: Gross Profit | B49: =B43-B46-B48-B47 -> 0 | C49: =C43-C46-C48-C47 -> 0 | D49: =D43-D46-D48-D47 -> 0 | E49: =E43-E46-E48-E47 -> 0 | F49: =F43-F46-F48-F47 -> 0 | G49: =G43-G46-G48-G47 -> 0 | H49: =H43-H46-H48-H47 -> 22.244684 | I49: =I43-I46-I48-I47 -> 33.280536 | ... AE49: =AE43-AE46-AE48-AE47 -> 1196.5236 | AI49: =AI43-AI46-AI48-AI47 -> 0 | AJ49: =AJ43-AJ46-AJ48-AJ47 -> 0 | AK49: =AK43-AK46-AK48-AK47 -> 0 | AL49: =AL43-AL46-AL48-AL47 -> 0 | AM49: =AM43-AM46-AM48-AM47 -> 0 | AN49: =AN43-AN46-AN48-AN47 -> 0 | AO49: =AO43-AO46-AO48-AO47 -> 0 | AP49: =AP43-AP46-AP48-AP47 -> 0 | ... CL49: =CL43-CL46-CL48-CL47 -> 167.27 | CM49: =+CM50*CM43 -> 165.26359 | CN49: =+CN50*CN43 -> 187.06393 | CO49: =+CO50*CO43 -> 170.77356 | CP49: =+CP50*CP43 -> 194.8613 | CQ49: =+CQ50*CQ43 -> 197.00151 | CR49: =+CR50*CR43 -> 221.89513 | CS49: =+CS50*CS43 -> 201.27031 | CT49: =+CT50*CT43 -> 230.73461 | ... DB49: =+DB50*DB43 -> 324.77584 | DF49: 161.02984
A50: GP% | B50: =B49/B43 -> #DIV/0! | C50: =C49/C43 -> #DIV/0! | D50: =D49/D43 -> #DIV/0! | E50: =E49/E43 -> #DIV/0! | F50: =F49/F43 -> #DIV/0! | G50: =G49/G43 -> #DIV/0! | H50: =H49/H43 -> 0.65901556 | I50: =I49/I43 -> 0.74938212 | ... AE50: =AE49/AE43 -> 0.74204989 | AI50: =AI49/AI43 -> #DIV/0! | AJ50: =AJ49/AJ43 -> #DIV/0! | AK50: =AK49/AK43 -> #DIV/0! | AL50: =AL49/AL43 -> #DIV/0! | AM50: =AM49/AM43 -> #DIV/0! | AN50: =AN49/AN43 -> #DIV/0! | AO50: =AO49/AO43 -> #DIV/0! | AP50: =AP49/AP43 -> #DIV/0! | ... CL50: =CL49/CL43 -> 0.74690779 | CM50: =AVERAGE(CI50:CL50) -> 0.73498603 | CN50: =AVERAGE(CJ50:CM50) -> 0.74078092 | CO50: =AVERAGE(CK50:CN50) -> 0.74531989 | CP50: =AVERAGE(CL50:CO50) -> 0.74199866 | CQ50: =AVERAGE(CM50:CP50) -> 0.74077137 | CR50: =AVERAGE(CN50:CQ50) -> 0.74221771 | CS50: =AVERAGE(CO50:CR50) -> 0.74257691 | CT50: =AVERAGE(CP50:CS50) -> 0.74189116 | ... DB50: =AVERAGE(CX50:DA50) -> 0.74204018 | DF50: 0.73217925
A51: GP YOY% | C51: =+IF(B49<0,1-C49/B49,C49/B49-1) -> #DIV/0! | D51: =+IF(C49<0,1-D49/C49,D49/C49-1) -> #DIV/0! | E51: =+IF(D49<0,1-E49/D49,E49/D49-1) -> #DIV/0! | F51: =+IF(E49<0,1-F49/E49,F49/E49-1) -> #DIV/0! | G51: =+IF(F49<0,1-G49/F49,G49/F49-1) -> #DIV/0! | H51: =+IF(G49<0,1-H49/G49,H49/G49-1) -> #DIV/0! | I51: =+IF(H49<0,1-I49/H49,I49/H49-1) -> 0.4961119 | J51: =+IF(I49<0,1-J49/I49,J49/I49-1) -> -0.12389549 | ... AE51: =+IF(AD49<0,1-AE49/AD49,AE49/AD49-1) -> 0.18636957 | AM51: =+IF(AI49<0,1-AM49/AI49,AM49/AI49-1) -> #DIV/0! | AN51: =+IF(AJ49<0,1-AN49/AJ49,AN49/AJ49-1) -> #DIV/0! | AO51: =+IF(AK49<0,1-AO49/AK49,AO49/AK49-1) -> #DIV/0! | AP51: =+IF(AL49<0,1-AP49/AL49,AP49/AL49-1) -> #DIV/0! | AQ51: =+IF(AM49<0,1-AQ49/AM49,AQ49/AM49-1) -> #DIV/0! | AR51: =+IF(AN49<0,1-AR49/AN49,AR49/AN49-1) -> #DIV/0! | AS51: =+IF(AO49<0,1-AS49/AO49,AS49/AO49-1) -> #DIV/0! | AT51: =+IF(AP49<0,1-AT49/AP49,AT49/AP49-1) -> #DIV/0! | ... CL51: =+IF(CH49<0,1-CL49/CH49,CL49/CH49-1) -> 0.21483042 | CM51: =+CM49/CI49-1 -> 0.20279177 | CN51: =+CN49/CJ49-1 -> 0.19552586 | CO51: =+CO49/CK49-1 -> 0.15130831 | CP51: =+CP49/CL49-1 -> 0.16495069 | CQ51: =+CQ49/CM49-1 -> 0.19204427 | CR51: =+CR49/CN49-1 -> 0.18619944 | CS51: =+CS49/CO49-1 -> 0.17858001 | CT51: =+CT49/CP49-1 -> 0.18409665 | ... DB51: =+DB49/CX49-1 -> 0.18695679 | DF51: 0.16951004
A52: GP QOQ% | AJ52: =+IF(AI49<0,1-AJ49/AI49,AJ49/AI49-1) -> #DIV/0! | AK52: =+IF(AJ49<0,1-AK49/AJ49,AK49/AJ49-1) -> #DIV/0! | AL52: =+IF(AK49<0,1-AL49/AK49,AL49/AK49-1) -> #DIV/0! | AM52: =+IF(AL49<0,1-AM49/AL49,AM49/AL49-1) -> #DIV/0! | AN52: =+IF(AM49<0,1-AN49/AM49,AN49/AM49-1) -> #DIV/0! | AO52: =+IF(AN49<0,1-AO49/AN49,AO49/AN49-1) -> #DIV/0! | AP52: =+IF(AO49<0,1-AP49/AO49,AP49/AO49-1) -> #DIV/0! | AQ52: =+IF(AP49<0,1-AQ49/AP49,AQ49/AP49-1) -> #DIV/0! | ... CL52: =+IF(CK49<0,1-CL49/CK49,CL49/CK49-1) -> 0.12768826 | CM52: =+CM49/CL49-1 -> -0.011995045 | CN52: =+CN49/CM49-1 -> 0.13191256 | CO52: =+CO49/CN49-1 -> -0.0870845 | CP52: =+CP49/CO49-1 -> 0.14105075 | CQ52: =+CQ49/CP49-1 -> 0.010983259 | CR52: =+CR49/CQ49-1 -> 0.12636256 | CS52: =+CS49/CR49-1 -> -0.092948519 | CT52: =+CT49/CS49-1 -> 0.14639172 | ... DB52: =+DB49/DA49-1 -> 0.14946442 | DF52: 0.085618809
A53: Employee Cost | B53: ='Annual Raw'!C14 -> 0 | C53: ='Annual Raw'!D14 -> 0 | D53: ='Annual Raw'!E14 -> 0 | E53: ='Annual Raw'!F14 -> 0 | F53: ='Annual Raw'!G14 -> 0 | G53: ='Annual Raw'!H14 -> 0 | H53: ='Annual Raw'!I14 -> 1.5794924 | I53: ='Annual Raw'!J14 -> 1.7314282 | ... AA53: ='Annual Raw'!AB14 -> 138.06 | AB53: =+SUM(CM53:CP53) -> 147.7242 | AC53: =+SUM(CQ53:CT53) -> 158.06489 | AD53: =+SUM(CU53:CX53) -> 169.12944 | AE53: =+SUM(CY53:DB53) -> 180.9685 | AI53: ='QTR Raw'!C16 -> 0 | AJ53: ='QTR Raw'!D16 -> 0 | AK53: ='QTR Raw'!E16 -> 0 | AL53: ='QTR Raw'!F16 -> 0 | AM53: ='QTR Raw'!G16 -> 0 | AN53: ='QTR Raw'!H16 -> 0 | AO53: ='QTR Raw'!I16 -> 0 | AP53: ='QTR Raw'!J16 -> 0 | ... CL53: ='QTR Raw'!BF16 -> 36.07 | CM53: =CI53*107% -> 35.31 | CN53: =CJ53*107% -> 35.5561 | CO53: =CK53*107% -> 38.2632 | CP53: =CL53*107% -> 38.5949 | CQ53: =CM53*107% -> 37.7817 | CR53: =CN53*107% -> 38.045027 | CS53: =CO53*107% -> 40.941624 | CT53: =CP53*107% -> 41.296543 | ... DB53: =CX53*107% -> 47.280412 | DF53: 35.8129
A54: Healthcare Service Operation Cost | Y54: 33.73 | Z54: 45.34 | AA54: 45.34 | AB54: =+SUM(CM54:CP54) -> 0 | AC54: =+SUM(CQ54:CT54) -> 0 | AD54: =+SUM(CU54:CX54) -> 0 | AE54: =+SUM(CY54:DB54) -> 0 | DF54: 0
A55: Professional and legal fees | P55: 1.52 | Q55: 2.61 | R55: 3.57 | S55: 6.76 | T55: 10.85 | U55: 11.41 | V55: 9.2 | W55: 11.38 | X55: 16.93 | Y55: 25.57 | Z55: 28.6 | AA55: 28.6 | AB55: =+SUM(CM55:CP55) -> 0 | AC55: =+SUM(CQ55:CT55) -> 0 | AD55: =+SUM(CU55:CX55) -> 0 | AE55: =+SUM(CY55:DB55) -> 0 | DF55: 0
A56: Repairs & Maintenance | P56: 1.71 | Q56: 2.58 | R56: 3.2 | S56: 3.54 | T56: 6.59 | U56: 8.44 | V56: 8.46 | W56: 11.1 | X56: 15.04 | Y56: 21.85 | Z56: 24.07 | AA56: 24.07 | AB56: =+SUM(CM56:CP56) -> 0 | AC56: =+SUM(CQ56:CT56) -> 0 | AD56: =+SUM(CU56:CX56) -> 0 | AE56: =+SUM(CY56:DB56) -> 0 | DF56: 0
A57: Business Promotion | P57: 4.83 | Q57: 6.18 | R57: 6.9 | S57: 10.28 | T57: 11.37 | U57: 5.75 | V57: 5.66 | W57: 5.3 | X57: 6.44 | Y57: 16.74 | Z57: 19.41 | AA57: 19.41 | AB57: =+SUM(CM57:CP57) -> 0 | AC57: =+SUM(CQ57:CT57) -> 0 | AD57: =+SUM(CU57:CX57) -> 0 | AE57: =+SUM(CY57:DB57) -> 0 | DF57: 0
A58: Sales Incentive | P58: 4.96 | Q58: 4.07 | R58: 7.02 | S58: 9.59 | T58: 12.61 | U58: 17.76 | V58: 18.23 | W58: 16 | X58: 12.75 | Y58: 13.75 | Z58: 17.57 | AA58: 17.57 | AB58: =+SUM(CM58:CP58) -> 0 | AC58: =+SUM(CQ58:CT58) -> 0 | AD58: =+SUM(CU58:CX58) -> 0 | AE58: =+SUM(CY58:DB58) -> 0 | DF58: 0
A59: Power & Fuel Cost | B59: ='Annual Raw'!C13 -> 0 | C59: ='Annual Raw'!D13 -> 0 | D59: ='Annual Raw'!E13 -> 0 | E59: ='Annual Raw'!F13 -> 0 | F59: ='Annual Raw'!G13 -> 0 | G59: ='Annual Raw'!H13 -> 0 | H59: ='Annual Raw'!I13 -> 0.3917144 | I59: ='Annual Raw'!J13 -> 0.3645711 | ... AA59: ='Annual Raw'!AB13 -> 11.26 | AB59: =+SUM(CM59:CP59) -> 0 | AC59: =+SUM(CQ59:CT59) -> 0 | AD59: =+SUM(CU59:CX59) -> 0 | AE59: =+SUM(CY59:DB59) -> 0 | AI59: ='QTR Raw'!C15 -> 0 | AJ59: ='QTR Raw'!D15 -> 0 | AK59: ='QTR Raw'!E15 -> 0 | AL59: ='QTR Raw'!F15 -> 0 | AM59: ='QTR Raw'!G15 -> 0 | AN59: ='QTR Raw'!H15 -> 0 | AO59: ='QTR Raw'!I15 -> 0 | AP59: ='QTR Raw'!J15 -> 0 | ... CL59: ='QTR Raw'!BF15 -> 0 | DF59: 0
A60: Selling and Distribution Expenses | B60: ='Annual Raw'!C18+'Annual Raw'!C17 -> 0 | C60: ='Annual Raw'!D18+'Annual Raw'!D17 -> 0 | D60: ='Annual Raw'!E18+'Annual Raw'!E17 -> 0 | E60: ='Annual Raw'!F18+'Annual Raw'!F17 -> 0 | F60: ='Annual Raw'!G18+'Annual Raw'!G17 -> 0 | G60: ='Annual Raw'!H18+'Annual Raw'!H17 -> 0 | H60: ='Annual Raw'!I18+'Annual Raw'!I17 -> 18.443396 | I60: ='Annual Raw'!J18+'Annual Raw'!J17 -> 4.9117987 | ... O60: ='Annual Raw'!P18+'Annual Raw'!P17 -> 19.981 | P60: =(((((('Annual Raw'!Q18+'Annual Raw'!Q17)-1.52)-4.83)-4.96)-6.47)-3.2)-2.35 -> 3.891 | Q60: =(((((('Annual Raw'!R18+'Annual Raw'!R17)-2.61)-6.18)-4.07)-8.72)-7.87)-3.38 -> 4.773 | R60: =(((((('Annual Raw'!S18+'Annual Raw'!S17)-3.57)-6.9)-7.02)-12.76)-18.61)-4.01 -> 5.553 | S60: =(((((('Annual Raw'!T18+'Annual Raw'!T17)-6.76)-10.28)-9.59)-14.13)-14.76)-4.28 -> 3.9 | T60: =(((((('Annual Raw'!U18+'Annual Raw'!U17)-10.85)-11.37)-12.61)-15.06)-15.41)-5.31 -> 3.72 | U60: =(((((('Annual Raw'!V18+'Annual Raw'!V17)-11.41)-5.75)-17.76)-22.57)-2.19)-3.88 -> 3.51 | V60: =(((((('Annual Raw'!W18+'Annual Raw'!W17)-9.2)-5.66)-18.23)-34.36)-2.97)-3.6 -> 2.49 | W60: =(((((('Annual Raw'!X18+'Annual Raw'!X17)-11.38)-5.3)-16)-37.4)-4.5)-5.1 -> 4.01 | X60: =(((((('Annual Raw'!Y18+'Annual Raw'!Y17)-16.93)-6.44)-12.75)-39.21)-6.78)-5.14 -> 4.65 | Y60: =(((((('Annual Raw'!Z18+'Annual Raw'!Z17)-25.57)-16.74)-13.75)-0)-5.54)-5.35 -> 6.28 | Z60: =(((((('Annual Raw'!AA18+'Annual Raw'!AA17)-28.6)-19.41)-17.57)-0.35)-3.16)-5.75 -> 7.84 | AA60: =(((((('Annual Raw'!AB18+'Annual Raw'!AB17)-28.6)-19.41)-17.57)-0.35)-3.16)-5.75 -> 23.97 | AB60: =+SUM(CM60:CP60) -> 0 | AC60: =+SUM(CQ60:CT60) -> 0 | AD60: =+SUM(CU60:CX60) -> 0 | AE60: =+SUM(CY60:DB60) -> 0 | AI60: ='QTR Raw'!C18 -> 0 | AJ60: ='QTR Raw'!D18 -> 0 | AK60: ='QTR Raw'!E18 -> 0 | AL60: ='QTR Raw'!F18 -> 0 | AM60: ='QTR Raw'!G18 -> 0 | AN60: ='QTR Raw'!H18 -> 0 | AO60: ='QTR Raw'!I18 -> 0 | AP60: ='QTR Raw'!J18 -> 0 | ... CL60: ='QTR Raw'!BF18 -> 0 | DF60: 0
A61: Outlab Processing Charges | P61: 2.48 | Q61: 3.21 | R61: 3.51 | S61: 1.8 | T61: 1.7 | U61: 1.47 | V61: 1.2 | W61: 2.8 | X61: 3.41 | Y61: 4.06 | Z61: 6.21 | AA61: 6.21 | AB61: =+SUM(CM61:CP61) -> 0 | AC61: =+SUM(CQ61:CT61) -> 0 | AD61: =+SUM(CU61:CX61) -> 0 | AE61: =+SUM(CY61:DB61) -> 0 | DF61: 0
A62: Communication , Postage courier services | P62: 2.35 | Q62: 3.38 | R62: 4.01 | S62: 4.28 | T62: 5.31 | U62: 3.88 | V62: 3.6 | W62: 5.1 | X62: 5.14 | Y62: 5.35 | Z62: 5.75 | AA62: 5.75 | AB62: =+SUM(CM62:CP62) -> 0 | AC62: =+SUM(CQ62:CT62) -> 0 | AD62: =+SUM(CU62:CX62) -> 0 | AE62: =+SUM(CY62:DB62) -> 0 | DF62: 0
A63: Miscellaneous Expenses | B63: ='Annual Raw'!C19-'Annual Raw'!C20 -> 0 | C63: ='Annual Raw'!D19-'Annual Raw'!D20 -> 0 | D63: ='Annual Raw'!E19-'Annual Raw'!E20 -> 0 | E63: ='Annual Raw'!F19-'Annual Raw'!F20 -> 0 | F63: ='Annual Raw'!G19-'Annual Raw'!G20 -> 0 | G63: ='Annual Raw'!H19-'Annual Raw'!H20 -> 0 | H63: ='Annual Raw'!I19-'Annual Raw'!I20 -> 0.0194409 | I63: ='Annual Raw'!J19-'Annual Raw'!J20 -> 0.069335 | ... AA63: ='Annual Raw'!AB19-'Annual Raw'!AB20 -> 18.24 | AB63: =+SUM(CM63:CP63) -> 0 | AC63: =+SUM(CQ63:CT63) -> 0 | AD63: =+SUM(CU63:CX63) -> 0 | AE63: =+SUM(CY63:DB63) -> 0 | AI63: =+'QTR Raw'!C21 -> 0 | AJ63: =+'QTR Raw'!D21 -> 0 | AK63: =+'QTR Raw'!E21 -> 0 | AL63: =+'QTR Raw'!F21 -> 0 | AM63: =+'QTR Raw'!G21 -> 0 | AN63: =+'QTR Raw'!H21 -> 0 | AO63: =+'QTR Raw'!I21 -> 0 | AP63: =+'QTR Raw'!J21 -> 0 | ... CL63: =+'QTR Raw'!BF21 -> 0 | DF63: 0
A64: Freight & Forwarding | P64: 0.02 | Q64: 0.02 | R64: 0.14 | W64: 0.82 | X64: 0.99 | Y64: 2.17 | Z64: 3.32 | AA64: 3.32 | AB64: =+SUM(CM64:CP64) -> 0 | AC64: =+SUM(CQ64:CT64) -> 0 | AD64: =+SUM(CU64:CX64) -> 0 | AE64: =+SUM(CY64:DB64) -> 0 | DF64: 0
A65: Rent, Rates & Taxes | P65: 3.2 | Q65: 7.87 | R65: 18.61 | S65: 14.76 | T65: 15.41 | U65: 2.19 | V65: 2.97 | W65: 4.5 | X65: 6.78 | Y65: 5.54 | Z65: 3.16 | AA65: 3.16 | AB65: =+SUM(CM65:CP65) -> 0 | AC65: =+SUM(CQ65:CT65) -> 0 | AD65: =+SUM(CU65:CX65) -> 0 | AE65: =+SUM(CY65:DB65) -> 0 | DF65: 0
A66: Healthcare service Operation Costs | P66: 6.47 | Q66: 8.72 | R66: 12.76 | S66: 14.13 | T66: 15.06 | U66: 22.57 | V66: 34.36 | W66: 37.4 | X66: 39.21 | Z66: 0.35 | AA66: 0.35 | AB66: =+SUM(CM66:CP66) -> 0 | AC66: =+SUM(CQ66:CT66) -> 0 | AD66: =+SUM(CU66:CX66) -> 0 | AE66: =+SUM(CY66:DB66) -> 0 | DF66: 0
A67: Other Manufacturing Expenses | B67: ='Annual Raw'!C15+'Annual Raw'!C16 -> 0 | C67: ='Annual Raw'!D15+'Annual Raw'!D16 -> 0 | D67: ='Annual Raw'!E15+'Annual Raw'!E16 -> 0 | E67: ='Annual Raw'!F15+'Annual Raw'!F16 -> 0 | F67: ='Annual Raw'!G15+'Annual Raw'!G16 -> 0 | G67: ='Annual Raw'!H15+'Annual Raw'!H16 -> 0 | H67: ='Annual Raw'!I15+'Annual Raw'!I16 -> 0.3454323 | I67: ='Annual Raw'!J15+'Annual Raw'!J16 -> 0.4266916 | ... O67: ='Annual Raw'!P15+'Annual Raw'!P16 -> 3.651 | P67: =((('Annual Raw'!Q15+'Annual Raw'!Q16)-0.02)-1.71)-2.48 -> -0.001 | Q67: =((('Annual Raw'!R15+'Annual Raw'!R16)-0.02)-2.58)-3.21 -> -0.001 | R67: =((('Annual Raw'!S15+'Annual Raw'!S16)-0.14)-3.2)-3.51 -> -0.006 | S67: =((('Annual Raw'!T15+'Annual Raw'!T16)-0)-3.54)-1.8 -> 0 | T67: =((('Annual Raw'!U15+'Annual Raw'!U16)-0)-6.59)-1.7 -> 0 | U67: =((('Annual Raw'!V15+'Annual Raw'!V16)-0)-8.44)-1.47 -> 0 | V67: =((('Annual Raw'!W15+'Annual Raw'!W16)-0)-8.46)-1.2 -> 0 | W67: =((('Annual Raw'!X15+'Annual Raw'!X16)-0.82)-11.1)-2.8 -> 0 | X67: =((('Annual Raw'!Y15+'Annual Raw'!Y16)-0.99)-15.04)-3.41 -> 3.5527137e-15 | Y67: =(((('Annual Raw'!Z15+'Annual Raw'!Z16)-33.73)-2.17)-21.85)-4.06 -> 0 | Z67: =(((('Annual Raw'!AA15+'Annual Raw'!AA16)-45.34)-3.32)-24.07)-6.21 -> 0.08 | AA67: =(((('Annual Raw'!AB15+'Annual Raw'!AB16)-45.34)-3.32)-24.07)-6.21 -> 18.24 | AB67: =+SUM(CM67:CP67) -> 256.10344 | AC67: =+SUM(CQ67:CT67) -> 312.98783 | AD67: =+SUM(CU67:CX67) -> 388.35508 | AE67: =+SUM(CY67:DB67) -> 480.18421 | AI67: ='QTR Raw'!C14 -> 0 | AJ67: ='QTR Raw'!D14 -> 0 | AK67: ='QTR Raw'!E14 -> 0 | AL67: ='QTR Raw'!F14 -> 0 | AM67: ='QTR Raw'!G14 -> 0 | AN67: ='QTR Raw'!H14 -> 0 | AO67: ='QTR Raw'!I14 -> 0 | AP67: ='QTR Raw'!J14 -> 0 | ... CL67: ='QTR Raw'!BF14 -> 56.11 | CM67: =+CM68-CM53 -> 58.188779 | CN67: =+CN68-CN53 -> 69.654435 | CO67: =+CO68-CO53 -> 58.534483 | CP67: =+CP68-CP53 -> 69.725743 | CQ67: =+CQ68-CQ53 -> 71.966487 | CR67: =+CR68-CR53 -> 85.09772 | CS67: =+CS68-CS53 -> 70.38335 | CT67: =+CT68-CT53 -> 85.540277 | ... DB67: =+DB68-DB53 -> 132.15346 | DF67: 57.431173
A68: Total Cost | B68: =+SUM(B53:B67) -> 0 | C68: =+SUM(C53:C67) -> 0 | D68: =+SUM(D53:D67) -> 0 | E68: =+SUM(E53:E67) -> 0 | F68: =+SUM(F53:F67) -> 0 | G68: =+SUM(G53:G67) -> 0 | H68: =+SUM(H53:H67) -> 20.779476 | I68: =+SUM(I53:I67) -> 7.5038246 | ... AE68: =+SUM(AE53:AE67) -> 661.15271 | AI68: =+SUM(AI53:AI67) -> 0 | AJ68: =+SUM(AJ53:AJ67) -> 0 | AK68: =+SUM(AK53:AK67) -> 0 | AL68: =+SUM(AL53:AL67) -> 0 | AM68: =+SUM(AM53:AM67) -> 0 | AN68: =+SUM(AN53:AN67) -> 0 | AO68: =+SUM(AO53:AO67) -> 0 | AP68: =+SUM(AP53:AP67) -> 0 | ... CL68: =+SUM(CL53:CL67) -> 92.18 | CM68: =CM69*CM43 -> 93.498779 | CN68: =CN69*CN43 -> 105.21053 | CO68: =CO69*CO43 -> 96.797683 | CP68: =CP69*CP43 -> 108.32064 | CQ68: =CQ69*CQ43 -> 109.74819 | CR68: =CR69*CR43 -> 123.14275 | CS68: =CS69*CS43 -> 111.32497 | CT68: =CT69*CT43 -> 126.83682 | ... DB68: =DB69*DB43 -> 179.43387 | DF68: 93.244073
A69: Cost % | B69: =B68/B43 -> #DIV/0! | C69: =C68/C43 -> #DIV/0! | D69: =D68/D43 -> #DIV/0! | E69: =E68/E43 -> #DIV/0! | F69: =F68/F43 -> #DIV/0! | G69: =G68/G43 -> #DIV/0! | H69: =H68/H43 -> 0.61560765 | I69: =I68/I43 -> 0.16896458 | ... AE69: =AE68/AE43 -> 0.4100281 | AI69: =AI68/AI43 -> #DIV/0! | AJ69: =AJ68/AJ43 -> #DIV/0! | AK69: =AK68/AK43 -> #DIV/0! | AL69: =AL68/AL43 -> #DIV/0! | AM69: =AM68/AM43 -> #DIV/0! | AN69: =AN68/AN43 -> #DIV/0! | AO69: =AO68/AO43 -> #DIV/0! | AP69: =AP68/AP43 -> #DIV/0! | ... CL69: =CL68/CL43 -> 0.41160973 | CM69: =AVERAGE(CI69:CL69)*0.99 -> 0.41582236 | CN69: =AVERAGE(CJ69:CM69)*0.99 -> 0.41663808 | CO69: =AVERAGE(CK69:CN69)*0.99 -> 0.4224614 | CP69: =AVERAGE(CL69:CO69)*0.99 -> 0.41246657 | CQ69: =AVERAGE(CM69:CP69)*0.99 -> 0.41267863 | CR69: =AVERAGE(CN69:CQ69)*0.99 -> 0.41190056 | CS69: =AVERAGE(CO69:CR69)*0.99 -> 0.41072802 | CT69: =AVERAGE(CP69:CS69)*0.99 -> 0.40782401 | CU69: =AVERAGE(CQ69:CT69) -> 0.4107828 | CV69: =AVERAGE(CR69:CU69) -> 0.41030885 | CW69: =AVERAGE(CS69:CV69) -> 0.40991092 | CX69: =AVERAGE(CT69:CW69) -> 0.40970665 | CY69: =AVERAGE(CU69:CX69) -> 0.4101773 | CZ69: =AVERAGE(CV69:CY69) -> 0.41002593 | DA69: =AVERAGE(CW69:CZ69) -> 0.4099552 | DB69: =AVERAGE(CX69:DA69) -> 0.40996627 | DF69: 0.42396724
A70: EBITDA | B70: =B49-B68 -> 0 | C70: =C49-C68 -> 0 | D70: =D49-D68 -> 0 | E70: =E49-E68 -> 0 | F70: =F49-F68 -> 0 | G70: =G49-G68 -> 0 | H70: =H49-H68 -> 1.4652085 | I70: =I49-I68 -> 25.776712 | ... AE70: =AE49-AE68 -> 535.37088 | AI70: =AI49-AI68 -> 0 | AJ70: =AJ49-AJ68 -> 0 | AK70: =AK49-AK68 -> 0 | AL70: =AL49-AL68 -> 0 | AM70: =AM49-AM68 -> 0 | AN70: =AN49-AN68 -> 0 | AO70: =AO49-AO68 -> 0 | AP70: =AP49-AP68 -> 0 | ... DB70: =DB49-DB68 -> 145.34197 | DF70: 67.785765
A71: EBITDA Margins | B71: =B70/B43 -> #DIV/0! | C71: =C70/C43 -> #DIV/0! | D71: =D70/D43 -> #DIV/0! | E71: =E70/E43 -> #DIV/0! | F71: =F70/F43 -> #DIV/0! | G71: =G70/G43 -> #DIV/0! | H71: =H70/H43 -> 0.043407908 | I71: =I70/I43 -> 0.58041753 | ... AE71: =AE70/AE43 -> 0.33202179 | AI71: =AI70/AI43 -> #DIV/0! | AJ71: =AJ70/AJ43 -> #DIV/0! | AK71: =AK70/AK43 -> #DIV/0! | AL71: =AL70/AL43 -> #DIV/0! | AM71: =AM70/AM43 -> #DIV/0! | AN71: =AN70/AN43 -> #DIV/0! | AO71: =AO70/AO43 -> #DIV/0! | AP71: =AP70/AP43 -> #DIV/0! | ... DB71: =DB70/DB43 -> 0.33207391 | DF71: 0.30821201
A72: EBITDA YOY% | C72: =+IF(B70<0,1-C70/B70,C70/B70-1) -> #DIV/0! | D72: =+IF(C70<0,1-D70/C70,D70/C70-1) -> #DIV/0! | E72: =+IF(D70<0,1-E70/D70,E70/D70-1) -> #DIV/0! | F72: =+IF(E70<0,1-F70/E70,F70/E70-1) -> #DIV/0! | G72: =+IF(F70<0,1-G70/F70,G70/F70-1) -> #DIV/0! | H72: =+IF(G70<0,1-H70/G70,H70/G70-1) -> #DIV/0! | I72: =+IF(H70<0,1-I70/H70,I70/H70-1) -> 16.592521 | J72: =+IF(I70<0,1-J70/I70,J70/I70-1) -> -0.53222838 | ... AE72: =+IF(AD70<0,1-AE70/AD70,AE70/AD70-1) -> 0.18687937 | AM72: =+IF(AI70<0,1-AM70/AI70,AM70/AI70-1) -> #DIV/0! | AN72: =+IF(AJ70<0,1-AN70/AJ70,AN70/AJ70-1) -> #DIV/0! | AO72: =+IF(AK70<0,1-AO70/AK70,AO70/AK70-1) -> #DIV/0! | AP72: =+IF(AL70<0,1-AP70/AL70,AP70/AL70-1) -> #DIV/0! | AQ72: =+IF(AM70<0,1-AQ70/AM70,AQ70/AM70-1) -> #DIV/0! | AR72: =+IF(AN70<0,1-AR70/AN70,AR70/AN70-1) -> #DIV/0! | AS72: =+IF(AO70<0,1-AS70/AO70,AS70/AO70-1) -> #DIV/0! | AT72: =+IF(AP70<0,1-AT70/AP70,AT70/AP70-1) -> #DIV/0! | ... CL72: =+IF(CH70<0,1-CL70/CH70,CL70/CH70-1) -> 0.30138648 | CM72: =+CM70/CI70-1 -> 0.24225047 | CN72: =+CN70/CJ70-1 -> 0.14720948 | CO72: =+CO70/CK70-1 -> 0.27919556 | CP72: =+CP70/CL70-1 -> 0.15249245 | CQ72: =+CQ70/CM70-1 -> 0.21582329 | CR72: =+CR70/CN70-1 -> 0.20645431 | CS72: =+CS70/CO70-1 -> 0.21587379 | CT72: =+CT70/CP70-1 -> 0.20056626 | ... DB72: =+DB70/CX70-1 -> 0.18610357 | DF72: 0.17479662
A73: EBITDA QOQ% | AJ73: =+IF(AI70<0,1-AJ70/AI70,AJ70/AI70-1) -> #DIV/0! | AK73: =+IF(AJ70<0,1-AK70/AJ70,AK70/AJ70-1) -> #DIV/0! | AL73: =+IF(AK70<0,1-AL70/AK70,AL70/AK70-1) -> #DIV/0! | AM73: =+IF(AL70<0,1-AM70/AL70,AM70/AL70-1) -> #DIV/0! | AN73: =+IF(AM70<0,1-AN70/AM70,AN70/AM70-1) -> #DIV/0! | AO73: =+IF(AN70<0,1-AO70/AN70,AO70/AN70-1) -> #DIV/0! | AP73: =+IF(AO70<0,1-AP70/AO70,AP70/AO70-1) -> #DIV/0! | AQ73: =+IF(AP70<0,1-AQ70/AP70,AQ70/AP70-1) -> #DIV/0! | ... CI73: =+IF(CH70<0,1-CI70/CH70,CI70/CH70-1) -> 0.0012131716 | CJ73: =+IF(CI70>1,CJ70/CI70-1,1-CJ70/CI70) -> 0.23507011 | CK73: =+IF(CJ70>1,CK70/CJ70-1,1-CK70/CJ70) -> -0.18948844 | CL73: =+IF(CK70>1,CL70/CK70-1,1-CL70/CK70) -> 0.29846101 | CM73: =+CM70/CL70-1 -> -0.044282734 | CN73: =+CN70/CM70-1 -> 0.14057846 | CO73: =+CO70/CN70-1 -> -0.096239343 | CP73: =+CP70/CO70-1 -> 0.16984968 | CQ73: =+CQ70/CP70-1 -> 0.0082350727 | CR73: =+CR70/CQ70-1 -> 0.13178931 | CS73: =+CS70/CR70-1 -> -0.089183166 | CT73: =+CT70/CS70-1 -> 0.15512157 | ... DB73: =+DB70/DA70-1 -> 0.14939655 | DF73: 0.17215571
A74: Depreciation | B74: ='Annual Raw'!C27 -> 0 | C74: ='Annual Raw'!D27 -> 0 | D74: ='Annual Raw'!E27 -> 0 | E74: ='Annual Raw'!F27 -> 0 | F74: ='Annual Raw'!G27 -> 0 | G74: ='Annual Raw'!H27 -> 0 | H74: ='Annual Raw'!I27 -> 0.9496698 | I74: ='Annual Raw'!J27 -> 1.2822612 | ... AA74: ='Annual Raw'!AB27 -> 58.58 | AB74: =+SUM(CM74:CP74) -> 61.318821 | AC74: =+SUM(CQ74:CT74) -> 60.851677 | AD74: =+SUM(CU74:CX74) -> 60.550002 | AE74: =+SUM(CY74:DB74) -> 60.355184 | AI74: ='QTR Raw'!C28 -> 0 | AJ74: ='QTR Raw'!D28 -> 0 | AK74: ='QTR Raw'!E28 -> 0 | AL74: ='QTR Raw'!F28 -> 0 | AM74: ='QTR Raw'!G28 -> 0 | AN74: ='QTR Raw'!H28 -> 0 | AO74: ='QTR Raw'!I28 -> 0 | AP74: ='QTR Raw'!J28 -> 0 | ... CL74: ='QTR Raw'!BF28 -> 14.03 | CM74: =CM75*CL176 -> 15.385571 | CN74: =CN75*CM176 -> 15.345642 | CO74: =CO75*CN176 -> 15.309848 | CP74: =CP75*CO176 -> 15.277761 | CQ74: =CQ75*CP176 -> 15.248996 | CR74: =CR75*CQ176 -> 15.223211 | CS74: =CS75*CR176 -> 15.200096 | CT74: =CT75*CS176 -> 15.179374 | ... DB74: =DB75*DA176 -> 15.074806 | DF74: 18.652106
A75: Depreciation % of Net Block | B75: =+B74/B176 -> #DIV/0! | C75: =+C74/C176 -> #DIV/0! | D75: =+D74/D176 -> #DIV/0! | E75: =+E74/E176 -> #DIV/0! | F75: =+F74/F176 -> #DIV/0! | G75: =+G74/G176 -> #DIV/0! | H75: =+H74/H176 -> 0.068733365 | I75: =+I74/I176 -> 0.073112209 | ... AE75: =+AE74/AE176 -> 0.41482847 | AI75: =+AI74/AH176 -> #DIV/0! | AJ75: =+AJ74/AI176 -> #DIV/0! | AK75: =+AK74/AJ176 -> #DIV/0! | AL75: =+AL74/AK176 -> #DIV/0! | AM75: =+AM74/AL176 -> #DIV/0! | AN75: =+AN74/AM176 -> #DIV/0! | AO75: =+AO74/AN176 -> #DIV/0! | AP75: =+AP74/AO176 -> #DIV/0! | ... CL75: =+CL74/CK176 -> 0.10355772 | CM75: =CL75 -> 0.10355772 | CN75: =CM75 -> 0.10355772 | CO75: =CN75 -> 0.10355772 | CP75: =CO75 -> 0.10355772 | CQ75: =CP75 -> 0.10355772 | CR75: =CQ75 -> 0.10355772 | CS75: =CR75 -> 0.10355772 | CT75: =CS75 -> 0.10355772 | ... DB75: =DA75 -> 0.10355772 | DF75: 0.13767424
A76: EBIT | B76: =B70-B74 -> 0 | C76: =C70-C74 -> 0 | D76: =D70-D74 -> 0 | E76: =E70-E74 -> 0 | F76: =F70-F74 -> 0 | G76: =G70-G74 -> 0 | H76: =H70-H74 -> 0.5155387 | I76: =I70-I74 -> 24.494451 | ... AE76: =AE70-AE74 -> 475.0157 | AI76: =AI70-AI74 -> 0 | AJ76: =AJ70-AJ74 -> 0 | AK76: =AK70-AK74 -> 0 | AL76: =AL70-AL74 -> 0 | AM76: =AM70-AM74 -> 0 | AN76: =AN70-AN74 -> 0 | AO76: =AO70-AO74 -> 0 | AP76: =AP70-AP74 -> 0 | ... DB76: =DB70-DB74 -> 130.26717 | DF76: 49.133659
A77: Other Income | B77: ='Annual Raw'!C23 -> 0 | C77: ='Annual Raw'!D23 -> 0 | D77: ='Annual Raw'!E23 -> 0 | E77: ='Annual Raw'!F23 -> 0 | F77: ='Annual Raw'!G23 -> 0 | G77: ='Annual Raw'!H23 -> 0 | H77: ='Annual Raw'!I23 -> 2.8232943 | I77: ='Annual Raw'!J23 -> 6.6917268 | ... AA77: ='Annual Raw'!AB23 -> 34.27 | AB77: =+SUM(CM77:CP77) -> 0 | AC77: =+SUM(CQ77:CT77) -> 0 | AD77: =+SUM(CU77:CX77) -> 0 | AE77: =+SUM(CY77:DB77) -> 0 | AI77: ='QTR Raw'!C23 -> 0 | AJ77: ='QTR Raw'!D23 -> 0 | AK77: ='QTR Raw'!E23 -> 0 | AL77: ='QTR Raw'!F23 -> 0 | AM77: ='QTR Raw'!G23 -> 0 | AN77: ='QTR Raw'!H23 -> 0 | AO77: ='QTR Raw'!I23 -> 0 | AP77: ='QTR Raw'!J23 -> 0 | ... CL77: ='QTR Raw'!BF23 -> 4.31 | DF77: 16.99
A78: Interest | B78: ='Annual Raw'!C25 -> 0 | C78: ='Annual Raw'!D25 -> 0 | D78: ='Annual Raw'!E25 -> 0 | E78: ='Annual Raw'!F25 -> 0 | F78: ='Annual Raw'!G25 -> 0 | G78: ='Annual Raw'!H25 -> 0 | H78: ='Annual Raw'!I25 -> 0.0542012 | I78: ='Annual Raw'!J25 -> 0.0624122 | ... AA78: ='Annual Raw'!AB25 -> 3.96 | AB78: =+SUM(CM78:CP78) -> -12.988802 | AC78: =+SUM(CQ78:CT78) -> -19.642469 | AD78: =+SUM(CU78:CX78) -> -29.979455 | AE78: =+SUM(CY78:DB78) -> -42.802844 | AI78: ='QTR Raw'!C25 -> 0 | AJ78: ='QTR Raw'!D25 -> 0 | AK78: ='QTR Raw'!E25 -> 0 | AL78: ='QTR Raw'!F25 -> 0 | AM78: ='QTR Raw'!G25 -> 0 | AN78: ='QTR Raw'!H25 -> 0 | AO78: ='QTR Raw'!I25 -> 0 | AP78: ='QTR Raw'!J25 -> 0 | ... CL78: ='QTR Raw'!BF25 -> 1.52 | CM78: =CM79*CL219 -> -2.4856481 | CN78: =CN79*CM219 -> -2.9751659 | CO78: =CO79*CN219 -> -3.4654591 | CP78: =CP79*CO219 -> -4.062529 | CQ78: =CQ79*CP219 -> -4.0494527 | CR78: =CR79*CQ219 -> -4.6024907 | CS78: =CS79*CR219 -> -5.1587066 | CT78: =CT79*CS219 -> -5.8318186 | ... DB78: =DB79*DA219 -> -12.117799 | DF78: -3.6983397
A79: Interest % of Debt | B79: =+B78/B170 -> #DIV/0! | C79: =+C78/C170 -> #DIV/0! | D79: =+D78/D170 -> #DIV/0! | E79: =+E78/E170 -> #DIV/0! | F79: =+F78/F170 -> #DIV/0! | G79: =+G78/G170 -> #DIV/0! | H79: =+H78/H170 -> 0.002168048 | I79: =+I78/I170 -> 0.002496488 | ... AE79: =+AE78/AE170 -> #DIV/0! | AI79: =(AI78-AI77)/AH219 -> #DIV/0! | AJ79: =(AJ78-AJ77)/AI219 -> #DIV/0! | AK79: =(AK78-AK77)/AJ219 -> #DIV/0! | AL79: =(AL78-AL77)/AK219 -> #DIV/0! | AM79: =(AM78-AM77)/AL219 -> #DIV/0! | AN79: =(AN78-AN77)/AM219 -> #DIV/0! | AO79: =(AO78-AO77)/AN219 -> #DIV/0! | AP79: =(AP78-AP77)/AO219 -> #DIV/0! | ... CL79: =(CL78-CL77)/CK219 -> 0.011315889 | CM79: =+CL79 -> 0.011315889 | CN79: =+CM79 -> 0.011315889 | CO79: =+CN79 -> 0.011315889 | CP79: =+CO79 -> 0.011315889 | CQ79: 0.01 | CR79: =+CQ79 -> 0.01 | CS79: =+CR79 -> 0.01 | CT79: =+CS79 -> 0.01 | CU79: =+CT79 -> 0.01 | CV79: =+CU79 -> 0.01 | CW79: =+CV79 -> 0.01 | CX79: =+CW79 -> 0.01 | CY79: =+CX79 -> 0.01 | ... DB79: =+DA79 -> 0.01 | DF79: 0.015
A80: PBT | B80: =B76+B77-B78 -> 0 | C80: =C76+C77-C78 -> 0 | D80: =D76+D77-D78 -> 0 | E80: =E76+E77-E78 -> 0 | F80: =F76+F77-F78 -> 0 | G80: =G76+G77-G78 -> 0 | H80: =H76+H77-H78 -> 3.2846318 | I80: =I76+I77-I78 -> 31.123765 | ... AE80: =AE76+AE77-AE78 -> 517.81854 | AI80: =AI76+AI77-AI78 -> 0 | AJ80: =AJ76+AJ77-AJ78 -> 0 | AK80: =AK76+AK77-AK78 -> 0 | AL80: =AL76+AL77-AL78 -> 0 | AM80: =AM76+AM77-AM78 -> 0 | AN80: =AN76+AN77-AN78 -> 0 | AO80: =AO76+AO77-AO78 -> 0 | AP80: =AP76+AP77-AP78 -> 0 | ... DB80: =DB76+DB77-DB78 -> 142.38497 | DF80: 52.831998
A81: Tax | B81: ='Annual Raw'!C30 -> 0 | C81: ='Annual Raw'!D30 -> 0 | D81: ='Annual Raw'!E30 -> 0 | E81: ='Annual Raw'!F30 -> 0 | F81: ='Annual Raw'!G30 -> 0 | G81: ='Annual Raw'!H30 -> 0 | H81: ='Annual Raw'!I30 -> 0.9733351 | I81: ='Annual Raw'!J30 -> 9.2206065 | ... AA81: ='Annual Raw'!AB30 -> 50.03 | AB81: =+SUM(CM81:CP81) -> 66.451181 | AC81: =+SUM(CQ81:CT81) -> 84.659907 | AD81: =+SUM(CU81:CX81) -> 105.12596 | AE81: =+SUM(CY81:DB81) -> 129.45464 | AI81: ='QTR Raw'!C29 -> 0 | AJ81: ='QTR Raw'!D29 -> 0 | AK81: ='QTR Raw'!E29 -> 0 | AL81: ='QTR Raw'!F29 -> 0 | AM81: ='QTR Raw'!G29 -> 0 | AN81: ='QTR Raw'!H29 -> 0 | AO81: ='QTR Raw'!I29 -> 0 | AP81: ='QTR Raw'!J29 -> 0 | ... CL81: ='QTR Raw'!BF29 -> 15.73 | CM81: =+CM80*CM82 -> 14.716222 | CN81: =+CN80*CN82 -> 17.37073 | CO81: =+CO80*CO82 -> 15.532873 | CP81: =+CP80*CP82 -> 18.831357 | CQ81: =+CQ80*CQ82 -> 19.013446 | CR81: =+CR80*CR82 -> 22.032916 | CS81: =+CS80*CS82 -> 19.975986 | CT81: =+CT80*CT82 -> 23.63756 | ... DB81: =+DB80*DB82 -> 35.596242 | DF81: 13.208
A82: Tax Rate % | B82: =B81/B80 -> #DIV/0! | C82: =C81/C80 -> #DIV/0! | D82: =D81/D80 -> #DIV/0! | E82: =E81/E80 -> #DIV/0! | F82: =F81/F80 -> #DIV/0! | G82: =G81/G80 -> #DIV/0! | H82: =H81/H80 -> 0.29633005 | I82: =I81/I80 -> 0.29625614 | ... AE82: =AE81/AE80 -> 0.25 | AI82: =AI81/AI80 -> #DIV/0! | AJ82: =AJ81/AJ80 -> #DIV/0! | AK82: =AK81/AK80 -> #DIV/0! | AL82: =AL81/AL80 -> #DIV/0! | AM82: =AM81/AM80 -> #DIV/0! | AN82: =AN81/AN80 -> #DIV/0! | AO82: =AO81/AO80 -> #DIV/0! | AP82: =AP81/AP80 -> #DIV/0! | ... CL82: =CL81/CL80 -> 0.24635865 | CM82: 0.25 | CN82: 0.25 | CO82: 0.25 | CP82: 0.25 | CQ82: 0.25 | CR82: 0.25 | CS82: 0.25 | CT82: 0.25 | CU82: 0.25 | CV82: 0.25 | CW82: 0.25 | CX82: 0.25 | CY82: 0.25 | CZ82: 0.25 | DA82: 0.25 | DB82: 0.25 | DF82: 0.25
A83: PAT | B83: =B80-B81 -> 0 | C83: =C80-C81 -> 0 | D83: =D80-D81 -> 0 | E83: =E80-E81 -> 0 | F83: =F80-F81 -> 0 | G83: =G80-G81 -> 0 | H83: =H80-H81 -> 2.3112967 | I83: =I80-I81 -> 21.903159 | ... AE83: =AE80-AE81 -> 388.36391 | AI83: =AI80-AI81 -> 0 | AJ83: =AJ80-AJ81 -> 0 | AK83: =AK80-AK81 -> 0 | AL83: =AL80-AL81 -> 0 | AM83: =AM80-AM81 -> 0 | AN83: =AN80-AN81 -> 0 | AO83: =AO80-AO81 -> 0 | AP83: =AP80-AP81 -> 0 | ... DB83: =DB80-DB81 -> 106.78872 | DF83: 39.623999
A84: PAT % | B84: =+B83/B43 -> #DIV/0! | C84: =+C83/C43 -> #DIV/0! | D84: =+D83/D43 -> #DIV/0! | E84: =+E83/E43 -> #DIV/0! | F84: =+F83/F43 -> #DIV/0! | G84: =+G83/G43 -> #DIV/0! | H84: =+H83/H43 -> 0.06847391 | I84: =+I83/I43 -> 0.49319624 | ... AE84: =+AE83/AE43 -> 0.24085224 | AI84: =+AI83/AI43 -> #DIV/0! | AJ84: =+AJ83/AJ43 -> #DIV/0! | AK84: =+AK83/AK43 -> #DIV/0! | AL84: =+AL83/AL43 -> #DIV/0! | AM84: =+AM83/AM43 -> #DIV/0! | AN84: =+AN83/AN43 -> #DIV/0! | AO84: =+AO83/AO43 -> #DIV/0! | AP84: =+AP83/AP43 -> #DIV/0! | ... DB84: =+DB83/DB43 -> 0.24398836 | DF84: 0.18016456
A85: PAT YOY% | C85: =+IF(B83<0,1-C83/B83,C83/B83-1) -> #DIV/0! | D85: =+IF(C83<0,1-D83/C83,D83/C83-1) -> #DIV/0! | E85: =+IF(D83<0,1-E83/D83,E83/D83-1) -> #DIV/0! | F85: =+IF(E83<0,1-F83/E83,F83/E83-1) -> #DIV/0! | G85: =+IF(F83<0,1-G83/F83,G83/F83-1) -> #DIV/0! | H85: =+IF(G83<0,1-H83/G83,H83/G83-1) -> #DIV/0! | I85: =+IF(H83<0,1-I83/H83,I83/H83-1) -> 8.4765673 | J85: =+IF(I83<0,1-J83/I83,J83/I83-1) -> -0.65012607 | ... AE85: =+IF(AD83<0,1-AE83/AD83,AE83/AD83-1) -> 0.23142406 | AM85: =+IF(AI83<0,1-AM83/AI83,AM83/AI83-1) -> #DIV/0! | AN85: =+IF(AJ83<0,1-AN83/AJ83,AN83/AJ83-1) -> #DIV/0! | AO85: =+IF(AK83<0,1-AO83/AK83,AO83/AK83-1) -> #DIV/0! | AP85: =+IF(AL83<0,1-AP83/AL83,AP83/AL83-1) -> #DIV/0! | AQ85: =+IF(AM83<0,1-AQ83/AM83,AQ83/AM83-1) -> #DIV/0! | AR85: =+IF(AN83<0,1-AR83/AN83,AR83/AN83-1) -> #DIV/0! | AS85: =+IF(AO83<0,1-AS83/AO83,AS83/AO83-1) -> #DIV/0! | AT85: =+IF(AP83<0,1-AT83/AP83,AT83/AP83-1) -> #DIV/0! | ... CL85: =+IF(CH83<0,1-CL83/CH83,CL83/CH83-1) -> 1.1675676 | CM85: =+CM83/CI83-1 -> 0.16058531 | CN85: =+CN83/CJ83-1 -> 0.096406274 | CO85: =+CO83/CK83-1 -> 0.37337512 | CP85: =+CP83/CL83-1 -> 0.17402473 | CQ85: =+CQ83/CM83-1 -> 0.29200593 | CR85: =+CR83/CN83-1 -> 0.26839319 | CS85: =+CS83/CO83-1 -> 0.28604582 | CT85: =+CT83/CP83-1 -> 0.25522341 | ... DB85: =+DB83/CX83-1 -> 0.22677255 | DF85: 0.78486481
A86: PAT QOQ% | AJ86: =+IF(AI83<0,1-AJ83/AI83,AJ83/AI83-1) -> #DIV/0! | AK86: =+IF(AJ83<0,1-AK83/AJ83,AK83/AJ83-1) -> #DIV/0! | AL86: =+IF(AK83<0,1-AL83/AK83,AL83/AK83-1) -> #DIV/0! | AM86: =+IF(AL83<0,1-AM83/AL83,AM83/AL83-1) -> #DIV/0! | AN86: =+IF(AM83<0,1-AN83/AM83,AN83/AM83-1) -> #DIV/0! | AO86: =+IF(AN83<0,1-AO83/AN83,AO83/AN83-1) -> #DIV/0! | AP86: =+IF(AO83<0,1-AP83/AO83,AP83/AO83-1) -> #DIV/0! | AQ86: =+IF(AP83<0,1-AQ83/AP83,AQ83/AP83-1) -> #DIV/0! | ... CL86: =+IF(CK83<0,1-CL83/CK83,CL83/CK83-1) -> 0.41821397 | CM86: =+CM83/CL83-1 -> -0.082529815 | CN86: =+CN83/CM83-1 -> 0.18037974 | CO86: =+CO83/CN83-1 -> -0.10580197 | CP86: =+CP83/CO83-1 -> 0.21235506 | CQ86: =+CQ83/CP83-1 -> 0.0096694661 | CR86: =+CR83/CQ83-1 -> 0.15880708 | CS86: =+CS83/CR83-1 -> -0.093357129 | CT86: =+CT83/CS83-1 -> 0.18329878 | ... DB86: =+DB83/DA83-1 -> 0.16271385 | DF86: 0.16781606
A87: Minority Interest | B87: ='Annual Raw'!C32 -> 0 | C87: ='Annual Raw'!D32 -> 0 | D87: ='Annual Raw'!E32 -> 0 | E87: ='Annual Raw'!F32 -> 0 | F87: ='Annual Raw'!G32 -> 0 | G87: ='Annual Raw'!H32 -> 0 | H87: ='Annual Raw'!I32 -> 0 | I87: ='Annual Raw'!J32 -> 0 | ... AA87: ='Annual Raw'!AB32 -> 0.19 | AB87: =+SUM(CM87:CP87) -> -6.36 | AC87: =+SUM(CQ87:CT87) -> -6.36 | AD87: =+SUM(CU87:CX87) -> -6.36 | AE87: =+SUM(CY87:DB87) -> -6.36 | AI87: ='QTR Raw'!C34 -> 0 | AJ87: ='QTR Raw'!D34 -> 0 | AK87: ='QTR Raw'!E34 -> 0 | AL87: ='QTR Raw'!F34 -> 0 | AM87: ='QTR Raw'!G34 -> 0 | AN87: ='QTR Raw'!H34 -> 0 | AO87: ='QTR Raw'!I34 -> 0 | AP87: ='QTR Raw'!J34 -> 0 | ... CL87: ='QTR Raw'!BF34 -> -1.59 | CM87: =+CL87 -> -1.59 | CN87: =+CM87 -> -1.59 | CO87: =+CN87 -> -1.59 | CP87: =+CO87 -> -1.59 | CQ87: =+CP87 -> -1.59 | CR87: =+CQ87 -> -1.59 | CS87: =+CR87 -> -1.59 | CT87: =+CS87 -> -1.59 | ... DB87: =+DA87 -> -1.59 | DF87: 0.96
A88: Share of Associate | B88: ='Annual Raw'!C33+'Annual Raw'!C28 -> 0 | C88: ='Annual Raw'!D33+'Annual Raw'!D28 -> 0 | D88: ='Annual Raw'!E33+'Annual Raw'!E28 -> 0 | E88: ='Annual Raw'!F33+'Annual Raw'!F28 -> 0 | F88: ='Annual Raw'!G33+'Annual Raw'!G28 -> 0 | G88: ='Annual Raw'!H33+'Annual Raw'!H28 -> 0 | H88: ='Annual Raw'!I33+'Annual Raw'!I28 -> 0 | I88: ='Annual Raw'!J33+'Annual Raw'!J28 -> 0 | ... AA88: ='Annual Raw'!AB33+'Annual Raw'!AB28 -> 1.39 | AB88: =+SUM(CM88:CP88) -> 2.32 | AC88: =+SUM(CQ88:CT88) -> 2.32 | AD88: =+SUM(CU88:CX88) -> 2.32 | AE88: =+SUM(CY88:DB88) -> 2.32 | AI88: ='QTR Raw'!C35 -> 0 | AJ88: ='QTR Raw'!D35 -> 0 | AK88: ='QTR Raw'!E35 -> 0 | AL88: ='QTR Raw'!F35 -> 0 | AM88: ='QTR Raw'!G35 -> 0 | AN88: ='QTR Raw'!H35 -> 0 | AO88: ='QTR Raw'!I35 -> 0 | AP88: ='QTR Raw'!J35 -> 0 | ... CL88: ='QTR Raw'!BF35 -> 0.58 | CM88: =+CL88 -> 0.58 | CN88: =+CM88 -> 0.58 | CO88: =+CN88 -> 0.58 | CP88: =+CO88 -> 0.58 | CQ88: =+CP88 -> 0.58 | CR88: =+CQ88 -> 0.58 | CS88: =+CR88 -> 0.58 | CT88: =+CS88 -> 0.58 | ... DB88: =+DA88 -> 0.58 | DF88: 0.28
A89: Exceptional Income / Expenses | B89: ='Annual Raw'!C29+'Annual Raw'!C31+'Annual Raw'!C34+'Annual Raw'!C36 -> 0 | C89: ='Annual Raw'!D29+'Annual Raw'!D31+'Annual Raw'!D34+'Annual Raw'!D36 -> 0 | D89: ='Annual Raw'!E29+'Annual Raw'!E31+'Annual Raw'!E34+'Annual Raw'!E36 -> 0 | E89: ='Annual Raw'!F29+'Annual Raw'!F31+'Annual Raw'!F34+'Annual Raw'!F36 -> 0 | F89: ='Annual Raw'!G29+'Annual Raw'!G31+'Annual Raw'!G34+'Annual Raw'!G36 -> 0 | G89: ='Annual Raw'!H29+'Annual Raw'!H31+'Annual Raw'!H34+'Annual Raw'!H36 -> 0 | H89: ='Annual Raw'!I29+'Annual Raw'!I31+'Annual Raw'!I34+'Annual Raw'!I36 -> 0 | I89: ='Annual Raw'!J29+'Annual Raw'!J31+'Annual Raw'!J34+'Annual Raw'!J36 -> 0 | ... AA89: ='Annual Raw'!AB29+'Annual Raw'!AB31+'Annual Raw'!AB34+'Annual Raw'!AB36 -> -5.79 | AB89: =+SUM(CM89:CP89) -> 0 | AC89: =+SUM(CQ89:CT89) -> 0 | AD89: =+SUM(CU89:CX89) -> 0 | AE89: =+SUM(CY89:DB89) -> 0 | AI89: ='QTR Raw'!C26+'QTR Raw'!C31+'QTR Raw'!C32+'QTR Raw'!C33+'QTR Raw'!C36+'QTR Raw'!C37+'QTR Raw'!C39 -> 0 | AJ89: ='QTR Raw'!D26+'QTR Raw'!D31+'QTR Raw'!D32+'QTR Raw'!D33+'QTR Raw'!D36+'QTR Raw'!D37+'QTR Raw'!D39 -> 0 | AK89: ='QTR Raw'!E26+'QTR Raw'!E31+'QTR Raw'!E32+'QTR Raw'!E33+'QTR Raw'!E36+'QTR Raw'!E37+'QTR Raw'!E39 -> 0 | AL89: ='QTR Raw'!F26+'QTR Raw'!F31+'QTR Raw'!F32+'QTR Raw'!F33+'QTR Raw'!F36+'QTR Raw'!F37+'QTR Raw'!F39 -> 0 | AM89: ='QTR Raw'!G26+'QTR Raw'!G31+'QTR Raw'!G32+'QTR Raw'!G33+'QTR Raw'!G36+'QTR Raw'!G37+'QTR Raw'!G39 -> 0 | AN89: ='QTR Raw'!H26+'QTR Raw'!H31+'QTR Raw'!H32+'QTR Raw'!H33+'QTR Raw'!H36+'QTR Raw'!H37+'QTR Raw'!H39 -> 0 | AO89: ='QTR Raw'!I26+'QTR Raw'!I31+'QTR Raw'!I32+'QTR Raw'!I33+'QTR Raw'!I36+'QTR Raw'!I37+'QTR Raw'!I39 -> 0 | AP89: ='QTR Raw'!J26+'QTR Raw'!J31+'QTR Raw'!J32+'QTR Raw'!J33+'QTR Raw'!J36+'QTR Raw'!J37+'QTR Raw'!J39 -> 0 | ... CL89: ='QTR Raw'!BF26+'QTR Raw'!BF31+'QTR Raw'!BF32+'QTR Raw'!BF33+'QTR Raw'!BF36+'QTR Raw'!BF37+'QTR Raw'!BF39 -> 0 | DF89: -6.16
A90: Consolidated Net Profit | B90: =B83+B87+B88+B89 -> 0 | C90: =C83+C87+C88+C89 -> 0 | D90: =D83+D87+D88+D89 -> 0 | E90: =E83+E87+E88+E89 -> 0 | F90: =F83+F87+F88+F89 -> 0 | G90: =G83+G87+G88+G89 -> 0 | H90: =H83+H87+H88+H89 -> 2.3112967 | I90: =I83+I87+I88+I89 -> 21.903159 | ... AE90: =AE83+AE87+AE88+AE89 -> 384.32391 | AI90: =AI83+AI87+AI88+AI89 -> 0 | AJ90: =AJ83+AJ87+AJ88+AJ89 -> 0 | AK90: =AK83+AK87+AK88+AK89 -> 0 | AL90: =AL83+AL87+AL88+AL89 -> 0 | AM90: =AM83+AM87+AM88+AM89 -> 0 | AN90: =AN83+AN87+AN88+AN89 -> 0 | AO90: =AO83+AO87+AO88+AO89 -> 0 | AP90: =AP83+AP87+AP88+AP89 -> 0 | ... DB90: =DB83+DB87+DB88+DB89 -> 105.77872 | DF90: 40.863999
A91: Profit & Loss- Annual (End)
A93: Ace - PAT | B93: ='Annual Raw'!C35 -> 0 | C93: ='Annual Raw'!D35 -> 0 | D93: ='Annual Raw'!E35 -> 0 | E93: ='Annual Raw'!F35 -> 0 | F93: ='Annual Raw'!G35 -> 0 | G93: ='Annual Raw'!H35 -> 0 | H93: ='Annual Raw'!I35 -> 2.3112967 | I93: ='Annual Raw'!J35 -> 21.903159 | ... AA93: ='Annual Raw'!AB35 -> 163.42 | AB93: =+AB90 -> 195.31354 | AC93: =+AC90 -> 249.93972 | AD93: =+AD90 -> 311.33788 | AE93: =+AE90 -> 384.32391 | AI93: ='QTR Raw'!C42 -> 0 | AJ93: ='QTR Raw'!D42 -> 0 | AK93: ='QTR Raw'!E42 -> 0 | AL93: ='QTR Raw'!F42 -> 0 | AM93: ='QTR Raw'!G42 -> 0 | AN93: ='QTR Raw'!H42 -> 0 | AO93: ='QTR Raw'!I42 -> 0 | AP93: ='QTR Raw'!J42 -> 0 | ... CL93: ='QTR Raw'!BF42 -> 47.11 | DF93: 163.04
A94: Checksum - PAT | B94: =B93-B90 -> 0 | C94: =C93-C90 -> 0 | D94: =D93-D90 -> 0 | E94: =E93-E90 -> 0 | F94: =F93-F90 -> 0 | G94: =G93-G90 -> 0 | H94: =H93-H90 -> 4.4408921e-15 | I94: =I93-I90 -> 0 | ... AE94: =AE93-AE90 -> 0 | AI94: =AI93-AI90 -> 0 | AJ94: =AJ93-AJ90 -> 0 | AK94: =AK93-AK90 -> 0 | AL94: =AL93-AL90 -> 0 | AM94: =AM93-AM90 -> 0 | AN94: =AN93-AN90 -> 0 | AO94: =AO93-AO90 -> 0 | AP94: =AP93-AP90 -> 0 | ... CL94: =CL93-CL90 -> 5.6843419e-14 | DF94: 0
A95: Ratios (Start)
A96: ROE (%) | B96: =(B90-B89)/B162 -> #DIV/0! | C96: =(C90-C89)/C162 -> #DIV/0! | D96: =(D90-D89)/D162 -> #DIV/0! | E96: =(E90-E89)/E162 -> #DIV/0! | F96: =(F90-F89)/F162 -> #DIV/0! | G96: =(G90-G89)/G162 -> #DIV/0! | H96: =(H90-H89)/H162 -> 0.085835571 | I96: =(I90-I89)/I162 -> 0.71616136 | ... AE96: =(AE90-AE89)/AE162 -> 0.22261385 | AL96: =(SUM(AI90:AL90)-SUM(AI89:AL89))/AL162 -> #DIV/0! | AM96: =(SUM(AJ90:AM90)-SUM(AJ89:AM89))/AM162 -> #DIV/0! | AN96: =(SUM(AK90:AN90)-SUM(AK89:AN89))/AN162 -> #DIV/0! | AO96: =(SUM(AL90:AO90)-SUM(AL89:AO89))/AO162 -> #DIV/0! | AP96: =(SUM(AM90:AP90)-SUM(AM89:AP89))/AP162 -> #DIV/0! | AQ96: =(SUM(AN90:AQ90)-SUM(AN89:AQ89))/AQ162 -> #DIV/0! | AR96: =(SUM(AO90:AR90)-SUM(AO89:AR89))/AR162 -> #DIV/0! | AS96: =(SUM(AP90:AS90)-SUM(AP89:AS89))/AS162 -> #DIV/0! | ... DB96: =(SUM(CY90:DB90)-SUM(CY89:DB89))/DB162 -> 0.22261385 | DF96: 0.26975387
A97: ROCE (%) | B97: =+B76/B171 -> #DIV/0! | C97: =+C76/C171 -> #DIV/0! | D97: =+D76/D171 -> #DIV/0! | E97: =+E76/E171 -> #DIV/0! | F97: =+F76/F171 -> #DIV/0! | G97: =+G76/G171 -> #DIV/0! | H97: =+H76/H171 -> 0.0099281383 | I97: =+I76/I171 -> 0.4406736 | ... AE97: =+AE76/AE171 -> 0.27506286 | AL97: =+SUM(AI76:AL76)/AL171 -> #DIV/0! | AM97: =+SUM(AJ76:AM76)/AM171 -> #DIV/0! | AN97: =+SUM(AK76:AN76)/AN171 -> #DIV/0! | AO97: =+SUM(AL76:AO76)/AO171 -> #DIV/0! | AP97: =+SUM(AM76:AP76)/AP171 -> #DIV/0! | AQ97: =+SUM(AN76:AQ76)/AQ171 -> #DIV/0! | AR97: =+SUM(AO76:AR76)/AR171 -> #DIV/0! | AS97: =+SUM(AP76:AS76)/AS171 -> #DIV/0! | ... DB97: =+SUM(CY76:DB76)/DB171 -> 0.27506286 | DF97: 0.31711711
A98: Ratios (End)
A99: Checksum Of qtr to Annual
A100: Revenue - Checksum Of qtr to Annual | N100: =N43-SUM(AI43:AL43) -> 134.261 | O100: =O43-SUM(AM43:AP43) -> 149.978 | P100: =P43-SUM(AQ43:AT43) -> 182.958 | Q100: =Q43-SUM(AU43:AX43) -> -0.002 | R100: =R43-SUM(AY43:BB43) -> 0 | S100: =S43-SUM(BC43:BF43) -> -0.006 | T100: =T43-SUM(BG43:BJ43) -> 0 | U100: =U43-SUM(BK43:BN43) -> 1.06 | V100: =V43-SUM(BO43:BR43) -> -0.01 | W100: =W43-SUM(BS43:BV43) -> 0.04 | X100: =X43-SUM(BW43:BZ43) -> 0 | Y100: =Y43-SUM(CA43:CD43) -> 0 | Z100: =Z43-SUM(CE43:CH43) -> 0 | AA100: =AA43-SUM(CF43:CI43) -> 105.57 | AB100: =AB43-SUM(CM43:CP43) -> 0 | AC100: =AC43-SUM(CQ43:CT43) -> 0 | AD100: =AD43-SUM(CU43:CX43) -> 0 | AE100: =AE43-SUM(CY43:DB43) -> 0 | DF100: 0
A101: GP - Checksum Of qtr to Annual | N101: =N49-SUM(AI49:AL49) -> 98.67 | O101: =O49-SUM(AM49:AP49) -> 107.468 | P101: =P49-SUM(AQ49:AT49) -> 127.129 | Q101: =Q49-SUM(AU49:AX49) -> -0.004 | R101: =R49-SUM(AY49:BB49) -> -0.001 | S101: =S49-SUM(BC49:BF49) -> 0.014 | T101: =T49-SUM(BG49:BJ49) -> 0 | U101: =U49-SUM(BK49:BN49) -> 1.06 | V101: =V49-SUM(BO49:BR49) -> 0 | W101: =W49-SUM(BS49:BV49) -> 0.07 | X101: =X49-SUM(BW49:BZ49) -> 0 | Y101: =Y49-SUM(CA49:CD49) -> 0 | Z101: =Z49-SUM(CE49:CH49) -> 0 | AA101: =AA49-SUM(CF49:CI49) -> 87.26 | AB101: =AB49-SUM(CM49:CP49) -> 0 | AC101: =AC49-SUM(CQ49:CT49) -> 0 | AD101: =AD49-SUM(CU49:CX49) -> 0 | AE101: =AE49-SUM(CY49:DB49) -> 0 | DF101: 0
A102: EBITDA - Checksum Of qtr to Annual | N102: =N70-SUM(AI70:AL70) -> 63.561 | O102: =O70-SUM(AM70:AP70) -> 68.841 | P102: =P70-SUM(AQ70:AT70) -> 72.672 | Q102: =Q70-SUM(AU70:AX70) -> 0.989 | R102: =R70-SUM(AY70:BB70) -> 0.195 | S102: =S70-SUM(BC70:BF70) -> 0.004 | T102: =T70-SUM(BG70:BJ70) -> 0 | U102: =U70-SUM(BK70:BN70) -> 1.05 | V102: =V70-SUM(BO70:BR70) -> -0.25 | W102: =W70-SUM(BS70:BV70) -> 0.82 | X102: =X70-SUM(BW70:BZ70) -> 2.48 | Y102: =Y70-SUM(CA70:CD70) -> 1.33 | Z102: =Z70-SUM(CE70:CH70) -> 0.2 | AA102: =AA70-SUM(CF70:CI70) -> 40.44 | AB102: =AB70-SUM(CM70:CP70) -> 0 | AC102: =AC70-SUM(CQ70:CT70) -> 0 | AD102: =AD70-SUM(CU70:CX70) -> 0 | AE102: =AE70-SUM(CY70:DB70) -> 0 | DF102: 0
A103: PAT - Checksum Of qtr to Annual | N103: =N90-SUM(AI90:AL90) -> 56.819 | O103: =O90-SUM(AM90:AP90) -> 46.156 | P103: =P90-SUM(AQ90:AT90) -> 45.217 | Q103: =Q90-SUM(AU90:AX90) -> -1.281 | R103: =R90-SUM(AY90:BB90) -> 0.046 | S103: =S90-SUM(BC90:BF90) -> 0.184 | T103: =T90-SUM(BG90:BJ90) -> 0.11 | U103: =U90-SUM(BK90:BN90) -> 0.11 | V103: =V90-SUM(BO90:BR90) -> -1.66 | W103: =W83-SUM(BS83:BV83) -> 0.11 | X103: =X83-SUM(BW83:BZ83) -> -1.0658141e-13 | Y103: =Y83-SUM(CA83:CD83) -> -0.01 | Z103: =Z83-SUM(CE83:CH83) -> -0.13 | AA103: =AA83-SUM(CF83:CI83) -> 61.57 | AB103: =AB83-SUM(CM83:CP83) -> 0 | AC103: =AC83-SUM(CQ83:CT83) -> 0 | AD103: =AD83-SUM(CU83:CX83) -> 0 | AE103: =AE83-SUM(CY83:DB83) -> 0 | DF103: 0
A104: Valuation (Start)
A105: Eq | B105: ='Annual Raw'!C104 -> 0 | C105: ='Annual Raw'!D104 -> 0 | D105: ='Annual Raw'!E104 -> 0 | E105: =+F105 -> 0 | F105: =+G105 -> 0 | G105: =+H105 -> 0 | H105: =+I105 -> 0 | I105: =+J105 -> 0 | J105: =+K105 -> 0 | K105: =+L105 -> 0 | L105: =+M105 -> 0 | ... AA105: =+AB105 -> 0 | AB105: =AA105 -> 0 | AC105: =AB105 -> 0 | AD105: =AC105 -> 0 | AE105: =AD105 -> 0 | AI105: =+AJ105 -> 159.16 | AJ105: =+AK105 -> 159.16 | AK105: =+AL105 -> 159.16 | AL105: =+AM105 -> 159.16 | AM105: =+AN105 -> 159.16 | AN105: =+AO105 -> 159.16 | AO105: =+AP105 -> 159.16 | AP105: =+AQ105 -> 159.16 | ... CK105: =+CL105 -> 159.16 | CL105: =+'QTR Raw'!BF45 -> 159.16 | CM105: =+CL105 -> 159.16 | CN105: =+CM105 -> 159.16 | CO105: =+CN105 -> 159.16 | CP105: =+CO105 -> 159.16 | CQ105: =+CP105 -> 159.16 | CR105: =+CQ105 -> 159.16 | CS105: =+CR105 -> 159.16 | CT105: =+CS105 -> 159.16 | ... DB105: =+DA105 -> 159.16 | DF105: 159.16
A106: FV | B106: ='Annual Raw'!C105 -> 0 | C106: ='Annual Raw'!D105 -> 0 | D106: ='Annual Raw'!E105 -> 0 | E106: =+F106 -> 0 | F106: =+G106 -> 0 | G106: =+H106 -> 0 | H106: =+I106 -> 0 | I106: =+J106 -> 0 | J106: =+K106 -> 0 | K106: =+L106 -> 0 | L106: =+M106 -> 0 | ... AA106: =+AB106 -> 0 | AB106: =AA106 -> 0 | AC106: =AB106 -> 0 | AD106: =AC106 -> 0 | AE106: =AD106 -> 0 | AI106: =+AJ106 -> 10 | AJ106: =+AK106 -> 10 | AK106: =+AL106 -> 10 | AL106: =+AM106 -> 10 | AM106: =+AN106 -> 10 | AN106: =+AO106 -> 10 | AO106: =+AP106 -> 10 | AP106: =+AQ106 -> 10 | ... CK106: =+CL106 -> 10 | CL106: ='QTR Raw'!BF46 -> 10 | CM106: =+CL106 -> 10 | CN106: =+CM106 -> 10 | CO106: =+CN106 -> 10 | CP106: =+CO106 -> 10 | CQ106: =+CP106 -> 10 | CR106: =+CQ106 -> 10 | CS106: =+CR106 -> 10 | CT106: =+CS106 -> 10 | ... DB106: =+DA106 -> 10 | DF106: 10
A107: No of share | B107: =B105/B106 -> #DIV/0! | C107: =C105/C106 -> #DIV/0! | D107: =D105/D106 -> #DIV/0! | E107: =E105/E106 -> #DIV/0! | F107: =F105/F106 -> #DIV/0! | G107: =G105/G106 -> #DIV/0! | H107: =H105/H106 -> #DIV/0! | I107: =I105/I106 -> #DIV/0! | ... AE107: =AE105/AE106 -> #DIV/0! | AI107: =AI105/AI106 -> 15.916 | AJ107: =AJ105/AJ106 -> 15.916 | AK107: =AK105/AK106 -> 15.916 | AL107: =AL105/AL106 -> 15.916 | AM107: =AM105/AM106 -> 15.916 | AN107: =AN105/AN106 -> 15.916 | AO107: =AO105/AO106 -> 15.916 | AP107: =AP105/AP106 -> 15.916 | ... DB107: =DB105/DB106 -> 15.916 | DF107: 15.916
A108: EPS | B108: =(B90-B89)/B107 -> #DIV/0! | C108: =(C90-C89)/C107 -> #DIV/0! | D108: =(D90-D89)/D107 -> #DIV/0! | E108: =(E90-E89)/E107 -> #DIV/0! | F108: =(F90-F89)/F107 -> #DIV/0! | G108: =(G90-G89)/G107 -> #DIV/0! | H108: =(H90-H89)/H107 -> #DIV/0! | I108: =(I90-I89)/I107 -> #DIV/0! | ... AE108: =(AE90-AE89)/AE107 -> #DIV/0! | AI108: =(AI90-AI89)/AI107 -> 0 | AJ108: =(AJ90-AJ89)/AJ107 -> 0 | AK108: =(AK90-AK89)/AK107 -> 0 | AL108: =(AL90-AL89)/AL107 -> 0 | AM108: =(AM90-AM89)/AM107 -> 0 | AN108: =(AN90-AN89)/AN107 -> 0 | AO108: =(AO90-AO89)/AO107 -> 0 | AP108: =(AP90-AP89)/AP107 -> 0 | ... DB108: =(DB90-DB89)/DB107 -> 6.6460621 | DF108: 2.5674792
A109: DPS | B109: ='Annual Raw'!C110 -> 0 | C109: ='Annual Raw'!D110 -> 0 | D109: ='Annual Raw'!E110 -> 0 | E109: ='Annual Raw'!F110 -> 0 | F109: ='Annual Raw'!G110 -> 0 | G109: ='Annual Raw'!H110 -> 0 | H109: ='Annual Raw'!I110 -> 0 | I109: ='Annual Raw'!J110 -> 1.25 | ... AA109: ='Annual Raw'!AB110 -> 14
A110: DPS % of EPS | B110: =B109/B108 -> #DIV/0! | C110: =C109/C108 -> #DIV/0! | D110: =D109/D108 -> #DIV/0! | E110: =E109/E108 -> #DIV/0! | F110: =F109/F108 -> #DIV/0! | G110: =G109/G108 -> #DIV/0! | H110: =H109/H108 -> #DIV/0! | I110: =I109/I108 -> #DIV/0! | ... AE110: =AE109/AE108 -> #DIV/0! | DF110: 0
...

Sheet QTR Raw
A1: ='Annual Raw'!A1 -> 218764 | B1: X | C1: 201206 | D1: 201209 | E1: 201212 | F1: 201303 | G1: 201306 | H1: 201309 | I1: 201312 | J1: 201403 | K1: 201406 | L1: 201409 | M1: 201412 | N1: 201503 | O1: 201506 | P1: 201509 | Q1: 201512 | R1: 201603 | S1: 201606 | T1: 201609 | U1: 201612 | V1: 201703 | W1: 201706 | X1: 201709 | Y1: 201712 | Z1: 201803 | AA1: 201806 | AB1: 201809 | AC1: 201812 | AD1: 201903 | AE1: 201906 | AF1: 201909 | AG1: 201912 | AH1: 202003 | AI1: 202006 | AJ1: 202009 | AK1: 202012 | AL1: 202103 | AM1: 202106 | AN1: 202109 | AO1: 202112 | AP1: 202203 | AQ1: 202206 | AR1: 202209 | AS1: 202212 | AT1: 202303 | AU1: 202306 | AV1: 202309 | AW1: 202312 | AX1: 202403 | AY1: 202406 | AZ1: 202409 | BA1: 202412 | BB1: 202503 | BC1: 202506 | BD1: 202509 | BE1: 202512 | BF1: 202603 | BG1: 202606 | BH1: 202609 | BI1: 202612 | BJ1: 202703 | BK1: 202706 | BL1: 202709 | BM1: 202712 | BN1: 202803 | BO1: 202806 | BP1: 202809 | BQ1: 202812 | BR1: 202903 | BS1: 202906 | BT1: 202909 | BU1: 202912 | BV1: 203003
A3: Field Description | B3: Field Name
A4: Company Name | B4: CD_COMPNAME | C4: =_xll.EQNXTDZ(A1,B4,C1) -> Thyrocare Technologies Ltd.
A5: Date End | B5: QTR_DATE_END | C5: =_xll.EQNXTDZ($A$1,$B5,C$1,$B$1) -> 0 | D5: =_xll.EQNXTDZ($A$1,$B5,D$1,$B$1) -> 0 | E5: =_xll.EQNXTDZ($A$1,$B5,E$1,$B$1) -> 0 | F5: =_xll.EQNXTDZ($A$1,$B5,F$1,$B$1) -> 0 | G5: =_xll.EQNXTDZ($A$1,$B5,G$1,$B$1) -> 0 | H5: =_xll.EQNXTDZ($A$1,$B5,H$1,$B$1) -> 0 | I5: =_xll.EQNXTDZ($A$1,$B5,I$1,$B$1) -> 0 | J5: =_xll.EQNXTDZ($A$1,$B5,J$1,$B$1) -> 0 | ... BV5: =_xll.EQNXTDZ($A$1,$B5,BV$1,$B$1) -> 0
A6: Gross Sales | B6: QTR_GROSS_SALE | C6: =_xll.EQNXTDZ($A$1,$B6,C$1,$B$1) -> 0 | D6: =_xll.EQNXTDZ($A$1,$B6,D$1,$B$1) -> 0 | E6: =_xll.EQNXTDZ($A$1,$B6,E$1,$B$1) -> 0 | F6: =_xll.EQNXTDZ($A$1,$B6,F$1,$B$1) -> 0 | G6: =_xll.EQNXTDZ($A$1,$B6,G$1,$B$1) -> 0 | H6: =_xll.EQNXTDZ($A$1,$B6,H$1,$B$1) -> 0 | I6: =_xll.EQNXTDZ($A$1,$B6,I$1,$B$1) -> 0 | J6: =_xll.EQNXTDZ($A$1,$B6,J$1,$B$1) -> 0 | ... BV6: =_xll.EQNXTDZ($A$1,$B6,BV$1,$B$1) -> 0
A7: Less: Excise Duty | B7: QTR_EXCISE_DUTY | C7: =_xll.EQNXTDZ($A$1,$B7,C$1,$B$1) -> 0 | D7: =_xll.EQNXTDZ($A$1,$B7,D$1,$B$1) -> 0 | E7: =_xll.EQNXTDZ($A$1,$B7,E$1,$B$1) -> 0 | F7: =_xll.EQNXTDZ($A$1,$B7,F$1,$B$1) -> 0 | G7: =_xll.EQNXTDZ($A$1,$B7,G$1,$B$1) -> 0 | H7: =_xll.EQNXTDZ($A$1,$B7,H$1,$B$1) -> 0 | I7: =_xll.EQNXTDZ($A$1,$B7,I$1,$B$1) -> 0 | J7: =_xll.EQNXTDZ($A$1,$B7,J$1,$B$1) -> 0 | ... BV7: =_xll.EQNXTDZ($A$1,$B7,BV$1,$B$1) -> 0
A8: Other operating income | B8: QTR_JOB_WORKS | C8: =_xll.EQNXTDZ($A$1,$B8,C$1,$B$1) -> 0 | D8: =_xll.EQNXTDZ($A$1,$B8,D$1,$B$1) -> 0 | E8: =_xll.EQNXTDZ($A$1,$B8,E$1,$B$1) -> 0 | F8: =_xll.EQNXTDZ($A$1,$B8,F$1,$B$1) -> 0 | G8: =_xll.EQNXTDZ($A$1,$B8,G$1,$B$1) -> 0 | H8: =_xll.EQNXTDZ($A$1,$B8,H$1,$B$1) -> 0 | I8: =_xll.EQNXTDZ($A$1,$B8,I$1,$B$1) -> 0 | J8: =_xll.EQNXTDZ($A$1,$B8,J$1,$B$1) -> 0 | ... BV8: =_xll.EQNXTDZ($A$1,$B8,BV$1,$B$1) -> 0
A9: Net Sales & Other Operating Income | B9: QTR_NET_SALES | C9: =_xll.EQNXTDZ($A$1,$B9,C$1,$B$1) -> 0 | D9: =_xll.EQNXTDZ($A$1,$B9,D$1,$B$1) -> 0 | E9: =_xll.EQNXTDZ($A$1,$B9,E$1,$B$1) -> 0 | F9: =_xll.EQNXTDZ($A$1,$B9,F$1,$B$1) -> 0 | G9: =_xll.EQNXTDZ($A$1,$B9,G$1,$B$1) -> 0 | H9: =_xll.EQNXTDZ($A$1,$B9,H$1,$B$1) -> 0 | I9: =_xll.EQNXTDZ($A$1,$B9,I$1,$B$1) -> 0 | J9: =_xll.EQNXTDZ($A$1,$B9,J$1,$B$1) -> 0 | ... BV9: =_xll.EQNXTDZ($A$1,$B9,BV$1,$B$1) -> 0
A10: (Increase) / Decrease In Stocks | B10: QTR_INC_DEC_INVENTORY | C10: =_xll.EQNXTDZ($A$1,$B10,C$1,$B$1) -> 0 | D10: =_xll.EQNXTDZ($A$1,$B10,D$1,$B$1) -> 0 | E10: =_xll.EQNXTDZ($A$1,$B10,E$1,$B$1) -> 0 | F10: =_xll.EQNXTDZ($A$1,$B10,F$1,$B$1) -> 0 | G10: =_xll.EQNXTDZ($A$1,$B10,G$1,$B$1) -> 0 | H10: =_xll.EQNXTDZ($A$1,$B10,H$1,$B$1) -> 0 | I10: =_xll.EQNXTDZ($A$1,$B10,I$1,$B$1) -> 0 | J10: =_xll.EQNXTDZ($A$1,$B10,J$1,$B$1) -> 0 | ... BV10: =_xll.EQNXTDZ($A$1,$B10,BV$1,$B$1) -> 0
A11: Cost of Services & Raw Materials | B11: QTR_RAW_MATERIAL_COST | C11: =_xll.EQNXTDZ($A$1,$B11,C$1,$B$1) -> 0 | D11: =_xll.EQNXTDZ($A$1,$B11,D$1,$B$1) -> 0 | E11: =_xll.EQNXTDZ($A$1,$B11,E$1,$B$1) -> 0 | F11: =_xll.EQNXTDZ($A$1,$B11,F$1,$B$1) -> 0 | G11: =_xll.EQNXTDZ($A$1,$B11,G$1,$B$1) -> 0 | H11: =_xll.EQNXTDZ($A$1,$B11,H$1,$B$1) -> 0 | I11: =_xll.EQNXTDZ($A$1,$B11,I$1,$B$1) -> 0 | J11: =_xll.EQNXTDZ($A$1,$B11,J$1,$B$1) -> 0 | ... BV11: =_xll.EQNXTDZ($A$1,$B11,BV$1,$B$1) -> 0
A12: Purchase of Finished Goods | B12: QTR_PURCHASE_FIN_GOOD | C12: =_xll.EQNXTDZ($A$1,$B12,C$1,$B$1) -> 0 | D12: =_xll.EQNXTDZ($A$1,$B12,D$1,$B$1) -> 0 | E12: =_xll.EQNXTDZ($A$1,$B12,E$1,$B$1) -> 0 | F12: =_xll.EQNXTDZ($A$1,$B12,F$1,$B$1) -> 0 | G12: =_xll.EQNXTDZ($A$1,$B12,G$1,$B$1) -> 0 | H12: =_xll.EQNXTDZ($A$1,$B12,H$1,$B$1) -> 0 | I12: =_xll.EQNXTDZ($A$1,$B12,I$1,$B$1) -> 0 | J12: =_xll.EQNXTDZ($A$1,$B12,J$1,$B$1) -> 0 | ... BV12: =_xll.EQNXTDZ($A$1,$B12,BV$1,$B$1) -> 0
A13: Excise Duty | B13: QTR_EXCISE | C13: =_xll.EQNXTDZ($A$1,$B13,C$1,$B$1) -> 0 | D13: =_xll.EQNXTDZ($A$1,$B13,D$1,$B$1) -> 0 | E13: =_xll.EQNXTDZ($A$1,$B13,E$1,$B$1) -> 0 | F13: =_xll.EQNXTDZ($A$1,$B13,F$1,$B$1) -> 0 | G13: =_xll.EQNXTDZ($A$1,$B13,G$1,$B$1) -> 0 | H13: =_xll.EQNXTDZ($A$1,$B13,H$1,$B$1) -> 0 | I13: =_xll.EQNXTDZ($A$1,$B13,I$1,$B$1) -> 0 | J13: =_xll.EQNXTDZ($A$1,$B13,J$1,$B$1) -> 0 | ... BV13: =_xll.EQNXTDZ($A$1,$B13,BV$1,$B$1) -> 0
A14: Operating & Manufacturing Expenses | B14: QTR_MFG_EXPS | C14: =_xll.EQNXTDZ($A$1,$B14,C$1,$B$1) -> 0 | D14: =_xll.EQNXTDZ($A$1,$B14,D$1,$B$1) -> 0 | E14: =_xll.EQNXTDZ($A$1,$B14,E$1,$B$1) -> 0 | F14: =_xll.EQNXTDZ($A$1,$B14,F$1,$B$1) -> 0 | G14: =_xll.EQNXTDZ($A$1,$B14,G$1,$B$1) -> 0 | H14: =_xll.EQNXTDZ($A$1,$B14,H$1,$B$1) -> 0 | I14: =_xll.EQNXTDZ($A$1,$B14,I$1,$B$1) -> 0 | J14: =_xll.EQNXTDZ($A$1,$B14,J$1,$B$1) -> 0 | ... BV14: =_xll.EQNXTDZ($A$1,$B14,BV$1,$B$1) -> 0
A15: Electricity Power & Fuel Cost | B15: QTR_ELECTRICITY_POWER_FUEL | C15: =_xll.EQNXTDZ($A$1,$B15,C$1,$B$1) -> 0 | D15: =_xll.EQNXTDZ($A$1,$B15,D$1,$B$1) -> 0 | E15: =_xll.EQNXTDZ($A$1,$B15,E$1,$B$1) -> 0 | F15: =_xll.EQNXTDZ($A$1,$B15,F$1,$B$1) -> 0 | G15: =_xll.EQNXTDZ($A$1,$B15,G$1,$B$1) -> 0 | H15: =_xll.EQNXTDZ($A$1,$B15,H$1,$B$1) -> 0 | I15: =_xll.EQNXTDZ($A$1,$B15,I$1,$B$1) -> 0 | J15: =_xll.EQNXTDZ($A$1,$B15,J$1,$B$1) -> 0 | ... BV15: =_xll.EQNXTDZ($A$1,$B15,BV$1,$B$1) -> 0
A16: Employee Cost | B16: QTR_EXPLOYEE_COST | C16: =_xll.EQNXTDZ($A$1,$B16,C$1,$B$1) -> 0 | D16: =_xll.EQNXTDZ($A$1,$B16,D$1,$B$1) -> 0 | E16: =_xll.EQNXTDZ($A$1,$B16,E$1,$B$1) -> 0 | F16: =_xll.EQNXTDZ($A$1,$B16,F$1,$B$1) -> 0 | G16: =_xll.EQNXTDZ($A$1,$B16,G$1,$B$1) -> 0 | H16: =_xll.EQNXTDZ($A$1,$B16,H$1,$B$1) -> 0 | I16: =_xll.EQNXTDZ($A$1,$B16,I$1,$B$1) -> 0 | J16: =_xll.EQNXTDZ($A$1,$B16,J$1,$B$1) -> 0 | ... BV16: =_xll.EQNXTDZ($A$1,$B16,BV$1,$B$1) -> 0
... A42: Consolidated PAT(after extra items) | B42: QTR_CONS_PAT_EXITM | C42: =_xll.EQNXTDZ($A$1,$B42,C$1,$B$1) -> 0 | D42: =_xll.EQNXTDZ($A$1,$B42,D$1,$B$1) -> 0 | E42: =_xll.EQNXTDZ($A$1,$B42,E$1,$B$1) -> 0 | F42: =_xll.EQNXTDZ($A$1,$B42,F$1,$B$1) -> 0 | G42: =_xll.EQNXTDZ($A$1,$B42,G$1,$B$1) -> 0 | H42: =_xll.EQNXTDZ($A$1,$B42,H$1,$B$1) -> 0 | I42: =_xll.EQNXTDZ($A$1,$B42,I$1,$B$1) -> 0 | J42: =_xll.EQNXTDZ($A$1,$B42,J$1,$B$1) -> 0 | ... BV42: =_xll.EQNXTDZ($A$1,$B42,BV$1,$B$1) -> 0
A44: Field Description | B44: Field Name
A45: Equity Capital | B45: QTR_EQUITY_CAP | C45: =_xll.EQNXTDZ($A$1,$B45,C$1,$B$1) -> 0 | D45: =_xll.EQNXTDZ($A$1,$B45,D$1,$B$1) -> 0 | E45: =_xll.EQNXTDZ($A$1,$B45,E$1,$B$1) -> 0 | F45: =_xll.EQNXTDZ($A$1,$B45,F$1,$B$1) -> 0 | G45: =_xll.EQNXTDZ($A$1,$B45,G$1,$B$1) -> 0 | H45: =_xll.EQNXTDZ($A$1,$B45,H$1,$B$1) -> 0 | I45: =_xll.EQNXTDZ($A$1,$B45,I$1,$B$1) -> 0 | J45: =_xll.EQNXTDZ($A$1,$B45,J$1,$B$1) -> 0 | ... BV45: =_xll.EQNXTDZ($A$1,$B45,BV$1,$B$1) -> 0
A46: Face Value | B46: QTR_FV | C46: =_xll.EQNXTDZ($A$1,$B46,C$1,$B$1) -> 0 | D46: =_xll.EQNXTDZ($A$1,$B46,D$1,$B$1) -> 0 | E46: =_xll.EQNXTDZ($A$1,$B46,E$1,$B$1) -> 0 | F46: =_xll.EQNXTDZ($A$1,$B46,F$1,$B$1) -> 0 | G46: =_xll.EQNXTDZ($A$1,$B46,G$1,$B$1) -> 0 | H46: =_xll.EQNXTDZ($A$1,$B46,H$1,$B$1) -> 0 | I46: =_xll.EQNXTDZ($A$1,$B46,I$1,$B$1) -> 0 | J46: =_xll.EQNXTDZ($A$1,$B46,J$1,$B$1) -> 0 | ... BV46: =_xll.EQNXTDZ($A$1,$B46,BV$1,$B$1) -> 0
A47: Month End | B47: BMONTH_MONTHEND | C47: =_xll.EQNXTDZ($A$1,$B47,C$5) -> 0 | D47: =_xll.EQNXTDZ($A$1,$B47,D$5) -> 0 | E47: =_xll.EQNXTDZ($A$1,$B47,E$5) -> 0 | F47: =_xll.EQNXTDZ($A$1,$B47,F$5) -> 0 | G47: =_xll.EQNXTDZ($A$1,$B47,G$5) -> 0 | H47: =_xll.EQNXTDZ($A$1,$B47,H$5) -> 0 | I47: =_xll.EQNXTDZ($A$1,$B47,I$5) -> 0 | J47: =_xll.EQNXTDZ($A$1,$B47,J$5) -> 0 | ... BV47: =_xll.EQNXTDZ($A$1,$B47,BV$5) -> 0
A48: Close | B48: BMONTH_CLOSE | C48: =_xll.EQNXTDZ($A$1,$B48,C$5) -> 0 | D48: =_xll.EQNXTDZ($A$1,$B48,D$5) -> 0 | E48: =_xll.EQNXTDZ($A$1,$B48,E$5) -> 0 | F48: =_xll.EQNXTDZ($A$1,$B48,F$5) -> 0 | G48: =_xll.EQNXTDZ($A$1,$B48,G$5) -> 0 | H48: =_xll.EQNXTDZ($A$1,$B48,H$5) -> 0 | I48: =_xll.EQNXTDZ($A$1,$B48,I$5) -> 0 | J48: =_xll.EQNXTDZ($A$1,$B48,J$5) -> 0 | ... BV48: =_xll.EQNXTDZ($A$1,$B48,BV$5) -> 0
A49: Total of Promoter and Promoter Group | B49: SHP_TPFTOTALPROMOTER | C49: =_xll.EQNXTDZ($A$1,$B49,C$5) -> 0 | D49: =_xll.EQNXTDZ($A$1,$B49,D$5) -> 0 | E49: =_xll.EQNXTDZ($A$1,$B49,E$5) -> 0 | F49: =_xll.EQNXTDZ($A$1,$B49,F$5) -> 0 | G49: =_xll.EQNXTDZ($A$1,$B49,G$5) -> 0 | H49: =_xll.EQNXTDZ($A$1,$B49,H$5) -> 0 | I49: =_xll.EQNXTDZ($A$1,$B49,I$5) -> 0 | J49: =_xll.EQNXTDZ($A$1,$B49,J$5) -> 0 | ... BV49: =_xll.EQNXTDZ($A$1,$B49,BV$5) -> 0
A50: Total of Promoter and Promoter Group Pledged | B50: SHP_PSHFTOTALPROMOTER | C50: =_xll.EQNXTDZ($A$1,$B50,C$5) -> 0 | D50: =_xll.EQNXTDZ($A$1,$B50,D$5) -> 0 | E50: =_xll.EQNXTDZ($A$1,$B50,E$5) -> 0 | F50: =_xll.EQNXTDZ($A$1,$B50,F$5) -> 0 | G50: =_xll.EQNXTDZ($A$1,$B50,G$5) -> 0 | H50: =_xll.EQNXTDZ($A$1,$B50,H$5) -> 0 | I50: =_xll.EQNXTDZ($A$1,$B50,I$5) -> 0 | J50: =_xll.EQNXTDZ($A$1,$B50,J$5) -> 0 | ... BV50: =_xll.EQNXTDZ($A$1,$B50,BV$5) -> 0
A54: Field Description | B54: Field Name | C54: =_xll.EQNXTDZ($A$1,$B54,C$5) -> 0 | D54: =_xll.EQNXTDZ($A$1,$B54,D$5) -> 0 | E54: =_xll.EQNXTDZ($A$1,$B54,E$5) -> 0 | F54: =_xll.EQNXTDZ($A$1,$B54,F$5) -> 0 | G54: =_xll.EQNXTDZ($A$1,$B54,G$5) -> 0 | H54: =_xll.EQNXTDZ($A$1,$B54,H$5) -> 0 | I54: =_xll.EQNXTDZ($A$1,$B54,I$5) -> 0 | J54: =_xll.EQNXTDZ($A$1,$B54,J$5) -> 0 | ... BV54: =_xll.EQNXTDZ($A$1,$B54,BV$5) -> 0
A55: Year End | B55: QTRB_DATE_END | C55: =_xll.EQNXTDZ($A$1,$B55,C$5,$B$1) -> 0 | D55: =_xll.EQNXTDZ($A$1,$B55,D$5,$B$1) -> 0 | E55: =_xll.EQNXTDZ($A$1,$B55,E$5,$B$1) -> 0 | F55: =_xll.EQNXTDZ($A$1,$B55,F$5,$B$1) -> 0 | G55: =_xll.EQNXTDZ($A$1,$B55,G$5,$B$1) -> 0 | H55: =_xll.EQNXTDZ($A$1,$B55,H$5,$B$1) -> 0 | I55: =_xll.EQNXTDZ($A$1,$B55,I$5,$B$1) -> 0 | J55: =_xll.EQNXTDZ($A$1,$B55,J$5,$B$1) -> 0 | ... BV55: =_xll.EQNXTDZ($A$1,$B55,BV$5,$B$1) -> 0
A56: Share Capital | B56: QTRB_SHARE_CAPITAL | C56: =_xll.EQNXTDZ($A$1,$B56,C$5,$B$1) -> 0 | D56: =_xll.EQNXTDZ($A$1,$B56,D$5,$B$1) -> 0 | E56: =_xll.EQNXTDZ($A$1,$B56,E$5,$B$1) -> 0 | F56: =_xll.EQNXTDZ($A$1,$B56,F$5,$B$1) -> 0 | G56: =_xll.EQNXTDZ($A$1,$B56,G$5,$B$1) -> 0 | H56: =_xll.EQNXTDZ($A$1,$B56,H$5,$B$1) -> 0 | I56: =_xll.EQNXTDZ($A$1,$B56,I$5,$B$1) -> 0 | J56: =_xll.EQNXTDZ($A$1,$B56,J$5,$B$1) -> 0 | ... BV56: =_xll.EQNXTDZ($A$1,$B56,BV$5,$B$1) -> 0
A57: Share Warrants & outstandings | B57: QTRB_SHAREWARNDOUT | C57: =_xll.EQNXTDZ($A$1,$B57,C$5,$B$1) -> 0 | D57: =_xll.EQNXTDZ($A$1,$B57,D$5,$B$1) -> 0 | E57: =_xll.EQNXTDZ($A$1,$B57,E$5,$B$1) -> 0 | F57: =_xll.EQNXTDZ($A$1,$B57,F$5,$B$1) -> 0 | G57: =_xll.EQNXTDZ($A$1,$B57,G$5,$B$1) -> 0 | H57: =_xll.EQNXTDZ($A$1,$B57,H$5,$B$1) -> 0 | I57: =_xll.EQNXTDZ($A$1,$B57,I$5,$B$1) -> 0 | J57: =_xll.EQNXTDZ($A$1,$B57,J$5,$B$1) -> 0 | ... BV57: =_xll.EQNXTDZ($A$1,$B57,BV$5,$B$1) -> 0
A58: Reserves & Surplus | B58: QTRB_RESERVE | C58: =_xll.EQNXTDZ($A$1,$B58,C$5,$B$1) -> 0 | D58: =_xll.EQNXTDZ($A$1,$B58,D$5,$B$1) -> 0 | E58: =_xll.EQNXTDZ($A$1,$B58,E$5,$B$1) -> 0 | F58: =_xll.EQNXTDZ($A$1,$B58,F$5,$B$1) -> 0 | G58: =_xll.EQNXTDZ($A$1,$B58,G$5,$B$1) -> 0 | H58: =_xll.EQNXTDZ($A$1,$B58,H$5,$B$1) -> 0 | I58: =_xll.EQNXTDZ($A$1,$B58,I$5,$B$1) -> 0 | J58: =_xll.EQNXTDZ($A$1,$B58,J$5,$B$1) -> 0 | ... BV58: =_xll.EQNXTDZ($A$1,$B58,BV$5,$B$1) -> 0
A59: Shareholder's Funds | B59: QTRB_SHAREHODERS_FUNDS | C59: =_xll.EQNXTDZ($A$1,$B59,C$5,$B$1) -> 0 | D59: =_xll.EQNXTDZ($A$1,$B59,D$5,$B$1) -> 0 | E59: =_xll.EQNXTDZ($A$1,$B59,E$5,$B$1) -> 0 | F59: =_xll.EQNXTDZ($A$1,$B59,F$5,$B$1) -> 0 | G59: =_xll.EQNXTDZ($A$1,$B59,G$5,$B$1) -> 0 | H59: =_xll.EQNXTDZ($A$1,$B59,H$5,$B$1) -> 0 | I59: =_xll.EQNXTDZ($A$1,$B59,I$5,$B$1) -> 0 | J59: =_xll.EQNXTDZ($A$1,$B59,J$5,$B$1) -> 0 | ... BV59: =_xll.EQNXTDZ($A$1,$B59,BV$5,$B$1) -> 0
A60: Minority Interest | B60: QTRB_MINORITY_INTEREST_BS | C60: =_xll.EQNXTDZ($A$1,$B60,C$5,$B$1) -> 0 | D60: =_xll.EQNXTDZ($A$1,$B60,D$5,$B$1) -> 0 | E60: =_xll.EQNXTDZ($A$1,$B60,E$5,$B$1) -> 0 | F60: =_xll.EQNXTDZ($A$1,$B60,F$5,$B$1) -> 0 | G60: =_xll.EQNXTDZ($A$1,$B60,G$5,$B$1) -> 0 | H60: =_xll.EQNXTDZ($A$1,$B60,H$5,$B$1) -> 0 | I60: =_xll.EQNXTDZ($A$1,$B60,I$5,$B$1) -> 0 | J60: =_xll.EQNXTDZ($A$1,$B60,J$5,$B$1) -> 0 | ... BV60: =_xll.EQNXTDZ($A$1,$B60,BV$5,$B$1) -> 0
A61: Long Term Borrowings | B61: QTRB_TOTAL_DEBTS | C61: =_xll.EQNXTDZ($A$1,$B61,C$5,$B$1) -> 0 | D61: =_xll.EQNXTDZ($A$1,$B61,D$5,$B$1) -> 0 | E61: =_xll.EQNXTDZ($A$1,$B61,E$5,$B$1) -> 0 | F61: =_xll.EQNXTDZ($A$1,$B61,F$5,$B$1) -> 0 | G61: =_xll.EQNXTDZ($A$1,$B61,G$5,$B$1) -> 0 | H61: =_xll.EQNXTDZ($A$1,$B61,H$5,$B$1) -> 0 | I61: =_xll.EQNXTDZ($A$1,$B61,I$5,$B$1) -> 0 | J61: =_xll.EQNXTDZ($A$1,$B61,J$5,$B$1) -> 0 | ... BV61: =_xll.EQNXTDZ($A$1,$B61,BV$5,$B$1) -> 0
A62: Secured Loans | B62: QTRB_SECURED_LOANS | C62: =_xll.EQNXTDZ($A$1,$B62,C$5,$B$1) -> 0 | D62: =_xll.EQNXTDZ($A$1,$B62,D$5,$B$1) -> 0 | E62: =_xll.EQNXTDZ($A$1,$B62,E$5,$B$1) -> 0 | F62: =_xll.EQNXTDZ($A$1,$B62,F$5,$B$1) -> 0 | G62: =_xll.EQNXTDZ($A$1,$B62,G$5,$B$1) -> 0 | H62: =_xll.EQNXTDZ($A$1,$B62,H$5,$B$1) -> 0 | I62: =_xll.EQNXTDZ($A$1,$B62,I$5,$B$1) -> 0 | J62: =_xll.EQNXTDZ($A$1,$B62,J$5,$B$1) -> 0 | ... BV62: =_xll.EQNXTDZ($A$1,$B62,BV$5,$B$1) -> 0
A63: Unsecured Loans | B63: QTRB_UNSECURED_LOANS_NF | C63: =_xll.EQNXTDZ($A$1,$B63,C$5,$B$1) -> 0 | D63: =_xll.EQNXTDZ($A$1,$B63,D$5,$B$1) -> 0 | E63: =_xll.EQNXTDZ($A$1,$B63,E$5,$B$1) -> 0 | F63: =_xll.EQNXTDZ($A$1,$B63,F$5,$B$1) -> 0 | G63: =_xll.EQNXTDZ($A$1,$B63,G$5,$B$1) -> 0 | H63: =_xll.EQNXTDZ($A$1,$B63,H$5,$B$1) -> 0 | I63: =_xll.EQNXTDZ($A$1,$B63,I$5,$B$1) -> 0 | J63: =_xll.EQNXTDZ($A$1,$B63,J$5,$B$1) -> 0 | ... BV63: =_xll.EQNXTDZ($A$1,$B63,BV$5,$B$1) -> 0
A64: Other Long Term Liabilities | B64: QTRB_OTHER_LT_LIABILITIES | C64: =_xll.EQNXTDZ($A$1,$B64,C$5,$B$1) -> 0 | D64: =_xll.EQNXTDZ($A$1,$B64,D$5,$B$1) -> 0 | E64: =_xll.EQNXTDZ($A$1,$B64,E$5,$B$1) -> 0 | F64: =_xll.EQNXTDZ($A$1,$B64,F$5,$B$1) -> 0 | G64: =_xll.EQNXTDZ($A$1,$B64,G$5,$B$1) -> 0 | H64: =_xll.EQNXTDZ($A$1,$B64,H$5,$B$1) -> 0 | I64: =_xll.EQNXTDZ($A$1,$B64,I$5,$B$1) -> 0 | J64: =_xll.EQNXTDZ($A$1,$B64,J$5,$B$1) -> 0 | ... BV64: =_xll.EQNXTDZ($A$1,$B64,BV$5,$B$1) -> 0
A65: Long Term Trade Payables | B65: QTRB_LT_TRADE_PAYABLE | C65: =_xll.EQNXTDZ($A$1,$B65,C$5,$B$1) -> 0 | D65: =_xll.EQNXTDZ($A$1,$B65,D$5,$B$1) -> 0 | E65: =_xll.EQNXTDZ($A$1,$B65,E$5,$B$1) -> 0 | F65: =_xll.EQNXTDZ($A$1,$B65,F$5,$B$1) -> 0 | G65: =_xll.EQNXTDZ($A$1,$B65,G$5,$B$1) -> 0 | H65: =_xll.EQNXTDZ($A$1,$B65,H$5,$B$1) -> 0 | I65: =_xll.EQNXTDZ($A$1,$B65,I$5,$B$1) -> 0 | J65: =_xll.EQNXTDZ($A$1,$B65,J$5,$B$1) -> 0 | ... BV65: =_xll.EQNXTDZ($A$1,$B65,BV$5,$B$1) -> 0
A66: Lont Term Provisions | B66: QTRB_LT_PROVISIONS | C66: =_xll.EQNXTDZ($A$1,$B66,C$5,$B$1) -> 0 | D66: =_xll.EQNXTDZ($A$1,$B66,D$5,$B$1) -> 0 | E66: =_xll.EQNXTDZ($A$1,$B66,E$5,$B$1) -> 0 | F66: =_xll.EQNXTDZ($A$1,$B66,F$5,$B$1) -> 0 | G66: =_xll.EQNXTDZ($A$1,$B66,G$5,$B$1) -> 0 | H66: =_xll.EQNXTDZ($A$1,$B66,H$5,$B$1) -> 0 | I66: =_xll.EQNXTDZ($A$1,$B66,I$5,$B$1) -> 0 | J66: =_xll.EQNXTDZ($A$1,$B66,J$5,$B$1) -> 0 | ... BV66: =_xll.EQNXTDZ($A$1,$B66,BV$5,$B$1) -> 0
... A97: Total Assets | B97: QTRB_TOTAL_APPLICATIONS | C97: =_xll.EQNXTDZ($A$1,$B97,C$5,$B$1) -> 0 | D97: =_xll.EQNXTDZ($A$1,$B97,D$5,$B$1) -> 0 | E97: =_xll.EQNXTDZ($A$1,$B97,E$5,$B$1) -> 0 | F97: =_xll.EQNXTDZ($A$1,$B97,F$5,$B$1) -> 0 | G97: =_xll.EQNXTDZ($A$1,$B97,G$5,$B$1) -> 0 | H97: =_xll.EQNXTDZ($A$1,$B97,H$5,$B$1) -> 0 | I97: =_xll.EQNXTDZ($A$1,$B97,I$5,$B$1) -> 0 | J97: =_xll.EQNXTDZ($A$1,$B97,J$5,$B$1) -> 0 | ... BV97: =_xll.EQNXTDZ($A$1,$B97,BV$5,$B$1) -> 0

Sheet Annual Raw
A1: 218764 | B1: X | C1: 200103 | D1: 200203 | E1: 200303 | F1: 200403 | G1: 200503 | H1: 200603 | I1: 200703 | J1: 200803 | K1: 200903 | L1: 201003 | M1: 201103 | N1: 201203 | O1: 201303 | P1: 201403 | Q1: 201503 | R1: 201603 | S1: 201703 | T1: 201803 | U1: 201903 | V1: 202003 | W1: 202103 | X1: 202203 | Y1: 202303 | Z1: 202403 | AA1: 202503 | AB1: 202603 | AC1: 202703 | AD1: 202803 | AE1: 202903 | AF1: 203003
A3: Field Description | B3: Field Name
A4: Company Name | B4: CD_COMPNAME | C4: =_xll.EQNXTDZ(A1,B4,"L") -> Thyrocare Technologies Ltd.
A5: Year End | B5: PL_YEAR_END | C5: =_xll.EQNXTDZ($A$1,$B5,C$1,$B$1) -> 0 | D5: =_xll.EQNXTDZ($A$1,$B5,D$1,$B$1) -> 0 | E5: =_xll.EQNXTDZ($A$1,$B5,E$1,$B$1) -> 0 | F5: =_xll.EQNXTDZ($A$1,$B5,F$1,$B$1) -> 0 | G5: =_xll.EQNXTDZ($A$1,$B5,G$1,$B$1) -> 0 | H5: =_xll.EQNXTDZ($A$1,$B5,H$1,$B$1) -> 0 | I5: =_xll.EQNXTDZ($A$1,$B5,I$1,$B$1) -> 200703 | J5: =_xll.EQNXTDZ($A$1,$B5,J$1,$B$1) -> 200803 | ... AF5: =_xll.EQNXTDZ($A$1,$B5,AF$1,$B$1) -> 0
A6: Sales Turnover | B6: PL_TOTAL_GROSS_SALES | C6: =_xll.EQNXTDZ($A$1,$B6,C$1,$B$1) -> 0 | D6: =_xll.EQNXTDZ($A$1,$B6,D$1,$B$1) -> 0 | E6: =_xll.EQNXTDZ($A$1,$B6,E$1,$B$1) -> 0 | F6: =_xll.EQNXTDZ($A$1,$B6,F$1,$B$1) -> 0 | G6: =_xll.EQNXTDZ($A$1,$B6,G$1,$B$1) -> 0 | H6: =_xll.EQNXTDZ($A$1,$B6,H$1,$B$1) -> 0 | I6: =_xll.EQNXTDZ($A$1,$B6,I$1,$B$1) -> 33.754414 | J6: =_xll.EQNXTDZ($A$1,$B6,J$1,$B$1) -> 44.410636 | ... AF6: =_xll.EQNXTDZ($A$1,$B6,AF$1,$B$1) -> 0
A7: Less: Inter divisional transfers | B7: PL_INTER_DIV_TRF | C7: =_xll.EQNXTDZ($A$1,$B7,C$1,$B$1) -> 0 | D7: =_xll.EQNXTDZ($A$1,$B7,D$1,$B$1) -> 0 | E7: =_xll.EQNXTDZ($A$1,$B7,E$1,$B$1) -> 0 | F7: =_xll.EQNXTDZ($A$1,$B7,F$1,$B$1) -> 0 | G7: =_xll.EQNXTDZ($A$1,$B7,G$1,$B$1) -> 0 | H7: =_xll.EQNXTDZ($A$1,$B7,H$1,$B$1) -> 0 | I7: =_xll.EQNXTDZ($A$1,$B7,I$1,$B$1) -> 0 | J7: =_xll.EQNXTDZ($A$1,$B7,J$1,$B$1) -> 0 | ... AF7: =_xll.EQNXTDZ($A$1,$B7,AF$1,$B$1) -> 0
A8: Less: Sales Returns | B8: PL_SALES_RETURN | C8: =_xll.EQNXTDZ($A$1,$B8,C$1,$B$1) -> 0 | D8: =_xll.EQNXTDZ($A$1,$B8,D$1,$B$1) -> 0 | E8: =_xll.EQNXTDZ($A$1,$B8,E$1,$B$1) -> 0 | F8: =_xll.EQNXTDZ($A$1,$B8,F$1,$B$1) -> 0 | G8: =_xll.EQNXTDZ($A$1,$B8,G$1,$B$1) -> 0 | H8: =_xll.EQNXTDZ($A$1,$B8,H$1,$B$1) -> 0 | I8: =_xll.EQNXTDZ($A$1,$B8,I$1,$B$1) -> 0 | J8: =_xll.EQNXTDZ($A$1,$B8,J$1,$B$1) -> 0 | ... AF8: =_xll.EQNXTDZ($A$1,$B8,AF$1,$B$1) -> 0
A9: Less: Excise | B9: PL_EXCISE | C9: =_xll.EQNXTDZ($A$1,$B9,C$1,$B$1) -> 0 | D9: =_xll.EQNXTDZ($A$1,$B9,D$1,$B$1) -> 0 | E9: =_xll.EQNXTDZ($A$1,$B9,E$1,$B$1) -> 0 | F9: =_xll.EQNXTDZ($A$1,$B9,F$1,$B$1) -> 0 | G9: =_xll.EQNXTDZ($A$1,$B9,G$1,$B$1) -> 0 | H9: =_xll.EQNXTDZ($A$1,$B9,H$1,$B$1) -> 0 | I9: =_xll.EQNXTDZ($A$1,$B9,I$1,$B$1) -> 0 | J9: =_xll.EQNXTDZ($A$1,$B9,J$1,$B$1) -> 0 | ... AF9: =_xll.EQNXTDZ($A$1,$B9,AF$1,$B$1) -> 0
A10: Net Sales | B10: PL_NET_SALES | C10: =_xll.EQNXTDZ($A$1,$B10,C$1,$B$1) -> 0 | D10: =_xll.EQNXTDZ($A$1,$B10,D$1,$B$1) -> 0 | E10: =_xll.EQNXTDZ($A$1,$B10,E$1,$B$1) -> 0 | F10: =_xll.EQNXTDZ($A$1,$B10,F$1,$B$1) -> 0 | G10: =_xll.EQNXTDZ($A$1,$B10,G$1,$B$1) -> 0 | H10: =_xll.EQNXTDZ($A$1,$B10,H$1,$B$1) -> 0 | I10: =_xll.EQNXTDZ($A$1,$B10,I$1,$B$1) -> 33.754414 | J10: =_xll.EQNXTDZ($A$1,$B10,J$1,$B$1) -> 44.410636 | ... AF10: =_xll.EQNXTDZ($A$1,$B10,AF$1,$B$1) -> 0
A11: Increase/Decrease in Stock | B11: PL_INC_DEC_INVENTORY | C11: =_xll.EQNXTDZ($A$1,$B11,C$1,$B$1) -> 0 | D11: =_xll.EQNXTDZ($A$1,$B11,D$1,$B$1) -> 0 | E11: =_xll.EQNXTDZ($A$1,$B11,E$1,$B$1) -> 0 | F11: =_xll.EQNXTDZ($A$1,$B11,F$1,$B$1) -> 0 | G11: =_xll.EQNXTDZ($A$1,$B11,G$1,$B$1) -> 0 | H11: =_xll.EQNXTDZ($A$1,$B11,H$1,$B$1) -> 0 | I11: =_xll.EQNXTDZ($A$1,$B11,I$1,$B$1) -> 0 | J11: =_xll.EQNXTDZ($A$1,$B11,J$1,$B$1) -> 0 | ... AF11: =_xll.EQNXTDZ($A$1,$B11,AF$1,$B$1) -> 0
A12: Raw Material Consumed | B12: PL_RAW_MATRS_CONSUMED | C12: =_xll.EQNXTDZ($A$1,$B12,C$1,$B$1) -> 0 | D12: =_xll.EQNXTDZ($A$1,$B12,D$1,$B$1) -> 0 | E12: =_xll.EQNXTDZ($A$1,$B12,E$1,$B$1) -> 0 | F12: =_xll.EQNXTDZ($A$1,$B12,F$1,$B$1) -> 0 | G12: =_xll.EQNXTDZ($A$1,$B12,G$1,$B$1) -> 0 | H12: =_xll.EQNXTDZ($A$1,$B12,H$1,$B$1) -> 0 | I12: =_xll.EQNXTDZ($A$1,$B12,I$1,$B$1) -> 11.50973 | J12: =_xll.EQNXTDZ($A$1,$B12,J$1,$B$1) -> 11.1301 | ... AF12: =_xll.EQNXTDZ($A$1,$B12,AF$1,$B$1) -> 0
A13: Power & Fuel Cost | B13: PL_POWER_FUEL | C13: =_xll.EQNXTDZ($A$1,$B13,C$1,$B$1) -> 0 | D13: =_xll.EQNXTDZ($A$1,$B13,D$1,$B$1) -> 0 | E13: =_xll.EQNXTDZ($A$1,$B13,E$1,$B$1) -> 0 | F13: =_xll.EQNXTDZ($A$1,$B13,F$1,$B$1) -> 0 | G13: =_xll.EQNXTDZ($A$1,$B13,G$1,$B$1) -> 0 | H13: =_xll.EQNXTDZ($A$1,$B13,H$1,$B$1) -> 0 | I13: =_xll.EQNXTDZ($A$1,$B13,I$1,$B$1) -> 0.3917144 | J13: =_xll.EQNXTDZ($A$1,$B13,J$1,$B$1) -> 0.3645711 | ... AF13: =_xll.EQNXTDZ($A$1,$B13,AF$1,$B$1) -> 0
A14: Employee Cost | B14: PL_EMPLOYEES | C14: =_xll.EQNXTDZ($A$1,$B14,C$1,$B$1) -> 0 | D14: =_xll.EQNXTDZ($A$1,$B14,D$1,$B$1) -> 0 | E14: =_xll.EQNXTDZ($A$1,$B14,E$1,$B$1) -> 0 | F14: =_xll.EQNXTDZ($A$1,$B14,F$1,$B$1) -> 0 | G14: =_xll.EQNXTDZ($A$1,$B14,G$1,$B$1) -> 0 | H14: =_xll.EQNXTDZ($A$1,$B14,H$1,$B$1) -> 0 | I14: =_xll.EQNXTDZ($A$1,$B14,I$1,$B$1) -> 1.5794924 | J14: =_xll.EQNXTDZ($A$1,$B14,J$1,$B$1) -> 1.7314282 | ... AF14: =_xll.EQNXTDZ($A$1,$B14,AF$1,$B$1) -> 0
A15: Operating & Manufacturing Expenses | B15: PL_GEN_OTHER_MFG_EXPS | C15: =_xll.EQNXTDZ($A$1,$B15,C$1,$B$1) -> 0 | D15: =_xll.EQNXTDZ($A$1,$B15,D$1,$B$1) -> 0 | E15: =_xll.EQNXTDZ($A$1,$B15,E$1,$B$1) -> 0 | F15: =_xll.EQNXTDZ($A$1,$B15,F$1,$B$1) -> 0 | G15: =_xll.EQNXTDZ($A$1,$B15,G$1,$B$1) -> 0 | H15: =_xll.EQNXTDZ($A$1,$B15,H$1,$B$1) -> 0 | I15: =_xll.EQNXTDZ($A$1,$B15,I$1,$B$1) -> 0.3454323 | J15: =_xll.EQNXTDZ($A$1,$B15,J$1,$B$1) -> 0.4266916 | ... AF15: =_xll.EQNXTDZ($A$1,$B15,AF$1,$B$1) -> 0
A16: Cost of Software development | B16: PL_COST_SW | C16: =_xll.EQNXTDZ($A$1,$B16,C$1,$B$1) -> 0 | D16: =_xll.EQNXTDZ($A$1,$B16,D$1,$B$1) -> 0 | E16: =_xll.EQNXTDZ($A$1,$B16,E$1,$B$1) -> 0 | F16: =_xll.EQNXTDZ($A$1,$B16,F$1,$B$1) -> 0 | G16: =_xll.EQNXTDZ($A$1,$B16,G$1,$B$1) -> 0 | H16: =_xll.EQNXTDZ($A$1,$B16,H$1,$B$1) -> 0 | I16: =_xll.EQNXTDZ($A$1,$B16,I$1,$B$1) -> 0 | J16: =_xll.EQNXTDZ($A$1,$B16,J$1,$B$1) -> 0 | ... AF16: =_xll.EQNXTDZ($A$1,$B16,AF$1,$B$1) -> 0
... A36: Profit After Tax from Discontinued Operations | B36: PL_PAT_DIS_OP | C36: =_xll.EQNXTDZ($A$1,$B36,C$1,$B$1) -> 0 | D36: =_xll.EQNXTDZ($A$1,$B36,D$1,$B$1) -> 0 | E36: =_xll.EQNXTDZ($A$1,$B36,E$1,$B$1) -> 0 | F36: =_xll.EQNXTDZ($A$1,$B36,F$1,$B$1) -> 0 | G36: =_xll.EQNXTDZ($A$1,$B36,G$1,$B$1) -> 0 | H36: =_xll.EQNXTDZ($A$1,$B36,H$1,$B$1) -> 0 | I36: =_xll.EQNXTDZ($A$1,$B36,I$1,$B$1) -> 0 | J36: =_xll.EQNXTDZ($A$1,$B36,J$1,$B$1) -> 0 | ... AF36: =_xll.EQNXTDZ($A$1,$B36,AF$1,$B$1) -> 0
A39: Field Description | B39: Field Name
A40: Year End | B40: BS_YEAR_END | C40: =_xll.EQNXTDZ($A$1,$B40,C$1,$B$1) -> 0 | D40: =_xll.EQNXTDZ($A$1,$B40,D$1,$B$1) -> 0 | E40: =_xll.EQNXTDZ($A$1,$B40,E$1,$B$1) -> 0 | F40: =_xll.EQNXTDZ($A$1,$B40,F$1,$B$1) -> 0 | G40: =_xll.EQNXTDZ($A$1,$B40,G$1,$B$1) -> 0 | H40: =_xll.EQNXTDZ($A$1,$B40,H$1,$B$1) -> 0 | I40: =_xll.EQNXTDZ($A$1,$B40,I$1,$B$1) -> 200703 | J40: =_xll.EQNXTDZ($A$1,$B40,J$1,$B$1) -> 200803 | ... AF40: =_xll.EQNXTDZ($A$1,$B40,AF$1,$B$1) -> 0
A41: Share Capital | B41: BS_SHARE_CAPITAL | C41: =_xll.EQNXTDZ($A$1,$B41,C$1,$B$1) -> 0 | D41: =_xll.EQNXTDZ($A$1,$B41,D$1,$B$1) -> 0 | E41: =_xll.EQNXTDZ($A$1,$B41,E$1,$B$1) -> 0 | F41: =_xll.EQNXTDZ($A$1,$B41,F$1,$B$1) -> 0 | G41: =_xll.EQNXTDZ($A$1,$B41,G$1,$B$1) -> 0 | H41: =_xll.EQNXTDZ($A$1,$B41,H$1,$B$1) -> 0 | I41: =_xll.EQNXTDZ($A$1,$B41,I$1,$B$1) -> 10.407425 | J41: =_xll.EQNXTDZ($A$1,$B41,J$1,$B$1) -> 10.407425 | ... AF41: =_xll.EQNXTDZ($A$1,$B41,AF$1,$B$1) -> 0
A42: Share Warrants & Outstandings | B42: BS_SHAREWROUTST | C42: =_xll.EQNXTDZ($A$1,$B42,C$1,$B$1) -> 0 | D42: =_xll.EQNXTDZ($A$1,$B42,D$1,$B$1) -> 0 | E42: =_xll.EQNXTDZ($A$1,$B42,E$1,$B$1) -> 0 | F42: =_xll.EQNXTDZ($A$1,$B42,F$1,$B$1) -> 0 | G42: =_xll.EQNXTDZ($A$1,$B42,G$1,$B$1) -> 0 | H42: =_xll.EQNXTDZ($A$1,$B42,H$1,$B$1) -> 0 | I42: =_xll.EQNXTDZ($A$1,$B42,I$1,$B$1) -> 0 | J42: =_xll.EQNXTDZ($A$1,$B42,J$1,$B$1) -> 0 | ... AF42: =_xll.EQNXTDZ($A$1,$B42,AF$1,$B$1) -> 0
A43: Total Reserves | B43: BS_RESERVE | C43: =_xll.EQNXTDZ($A$1,$B43,C$1,$B$1) -> 0 | D43: =_xll.EQNXTDZ($A$1,$B43,D$1,$B$1) -> 0 | E43: =_xll.EQNXTDZ($A$1,$B43,E$1,$B$1) -> 0 | F43: =_xll.EQNXTDZ($A$1,$B43,F$1,$B$1) -> 0 | G43: =_xll.EQNXTDZ($A$1,$B43,G$1,$B$1) -> 0 | H43: =_xll.EQNXTDZ($A$1,$B43,H$1,$B$1) -> 0 | I43: =_xll.EQNXTDZ($A$1,$B43,I$1,$B$1) -> 16.519602 | J43: =_xll.EQNXTDZ($A$1,$B43,J$1,$B$1) -> 20.176686 | ... AF43: =_xll.EQNXTDZ($A$1,$B43,AF$1,$B$1) -> 0
A44: Shareholder's Funds | B44: BS_SHAREHODERS_FUNDS | C44: =_xll.EQNXTDZ($A$1,$B44,C$1,$B$1) -> 0 | D44: =_xll.EQNXTDZ($A$1,$B44,D$1,$B$1) -> 0 | E44: =_xll.EQNXTDZ($A$1,$B44,E$1,$B$1) -> 0 | F44: =_xll.EQNXTDZ($A$1,$B44,F$1,$B$1) -> 0 | G44: =_xll.EQNXTDZ($A$1,$B44,G$1,$B$1) -> 0 | H44: =_xll.EQNXTDZ($A$1,$B44,H$1,$B$1) -> 0 | I44: =_xll.EQNXTDZ($A$1,$B44,I$1,$B$1) -> 26.927027 | J44: =_xll.EQNXTDZ($A$1,$B44,J$1,$B$1) -> 30.584111 | ... AF44: =_xll.EQNXTDZ($A$1,$B44,AF$1,$B$1) -> 0
A45: Minority Interest | B45: BS_MINORITY_INTEREST | C45: =_xll.EQNXTDZ($A$1,$B45,C$1,$B$1) -> 0 | D45: =_xll.EQNXTDZ($A$1,$B45,D$1,$B$1) -> 0 | E45: =_xll.EQNXTDZ($A$1,$B45,E$1,$B$1) -> 0 | F45: =_xll.EQNXTDZ($A$1,$B45,F$1,$B$1) -> 0 | G45: =_xll.EQNXTDZ($A$1,$B45,G$1,$B$1) -> 0 | H45: =_xll.EQNXTDZ($A$1,$B45,H$1,$B$1) -> 0 | I45: =_xll.EQNXTDZ($A$1,$B45,I$1,$B$1) -> 0 | J45: =_xll.EQNXTDZ($A$1,$B45,J$1,$B$1) -> 0 | ... AF45: =_xll.EQNXTDZ($A$1,$B45,AF$1,$B$1) -> 0
A46: Long-Term Borrowings | B46: BS_LTRM_BORROWING | C46: =_xll.EQNXTDZ($A$1,$B46,C$1,$B$1) -> 0 | D46: =_xll.EQNXTDZ($A$1,$B46,D$1,$B$1) -> 0 | E46: =_xll.EQNXTDZ($A$1,$B46,E$1,$B$1) -> 0 | F46: =_xll.EQNXTDZ($A$1,$B46,F$1,$B$1) -> 0 | G46: =_xll.EQNXTDZ($A$1,$B46,G$1,$B$1) -> 0 | H46: =_xll.EQNXTDZ($A$1,$B46,H$1,$B$1) -> 0 | I46: =_xll.EQNXTDZ($A$1,$B46,I$1,$B$1) -> 0 | J46: =_xll.EQNXTDZ($A$1,$B46,J$1,$B$1) -> 0 | ... AF46: =_xll.EQNXTDZ($A$1,$B46,AF$1,$B$1) -> 0
A47: Secured Loans | B47: BS_SECURED_LOANS | C47: =_xll.EQNXTDZ($A$1,$B47,C$1,$B$1) -> 0 | D47: =_xll.EQNXTDZ($A$1,$B47,D$1,$B$1) -> 0 | E47: =_xll.EQNXTDZ($A$1,$B47,E$1,$B$1) -> 0 | F47: =_xll.EQNXTDZ($A$1,$B47,F$1,$B$1) -> 0 | G47: =_xll.EQNXTDZ($A$1,$B47,G$1,$B$1) -> 0 | H47: =_xll.EQNXTDZ($A$1,$B47,H$1,$B$1) -> 0 | I47: =_xll.EQNXTDZ($A$1,$B47,I$1,$B$1) -> 0 | J47: =_xll.EQNXTDZ($A$1,$B47,J$1,$B$1) -> 0 | ... AF47: =_xll.EQNXTDZ($A$1,$B47,AF$1,$B$1) -> 0
A48: Unsecured Loans | B48: BS_UNSECURED_LOANS_NF | C48: =_xll.EQNXTDZ($A$1,$B48,C$1,$B$1) -> 0 | D48: =_xll.EQNXTDZ($A$1,$B48,D$1,$B$1) -> 0 | E48: =_xll.EQNXTDZ($A$1,$B48,E$1,$B$1) -> 0 | F48: =_xll.EQNXTDZ($A$1,$B48,F$1,$B$1) -> 0 | G48: =_xll.EQNXTDZ($A$1,$B48,G$1,$B$1) -> 0 | H48: =_xll.EQNXTDZ($A$1,$B48,H$1,$B$1) -> 0 | I48: =_xll.EQNXTDZ($A$1,$B48,I$1,$B$1) -> 25 | J48: =_xll.EQNXTDZ($A$1,$B48,J$1,$B$1) -> 25 | ... AF48: =_xll.EQNXTDZ($A$1,$B48,AF$1,$B$1) -> 0
A49: Deferred Tax Assets / Liabilities | B49: BS_NET_DEF_TAX_NF | C49: =_xll.EQNXTDZ($A$1,$B49,C$1,$B$1) -> 0 | D49: =_xll.EQNXTDZ($A$1,$B49,D$1,$B$1) -> 0 | E49: =_xll.EQNXTDZ($A$1,$B49,E$1,$B$1) -> 0 | F49: =_xll.EQNXTDZ($A$1,$B49,F$1,$B$1) -> 0 | G49: =_xll.EQNXTDZ($A$1,$B49,G$1,$B$1) -> 0 | H49: =_xll.EQNXTDZ($A$1,$B49,H$1,$B$1) -> 0 | I49: =_xll.EQNXTDZ($A$1,$B49,I$1,$B$1) -> 0.3283898 | J49: =_xll.EQNXTDZ($A$1,$B49,J$1,$B$1) -> 0.2511328 | ... AF49: =_xll.EQNXTDZ($A$1,$B49,AF$1,$B$1) -> 0
A50: Other Long Term Liabilities | B50: BS_OTH_LT_LIAB | C50: =_xll.EQNXTDZ($A$1,$B50,C$1,$B$1) -> 0 | D50: =_xll.EQNXTDZ($A$1,$B50,D$1,$B$1) -> 0 | E50: =_xll.EQNXTDZ($A$1,$B50,E$1,$B$1) -> 0 | F50: =_xll.EQNXTDZ($A$1,$B50,F$1,$B$1) -> 0 | G50: =_xll.EQNXTDZ($A$1,$B50,G$1,$B$1) -> 0 | H50: =_xll.EQNXTDZ($A$1,$B50,H$1,$B$1) -> 0 | I50: =_xll.EQNXTDZ($A$1,$B50,I$1,$B$1) -> 0 | J50: =_xll.EQNXTDZ($A$1,$B50,J$1,$B$1) -> 0 | ... AF50: =_xll.EQNXTDZ($A$1,$B50,AF$1,$B$1) -> 0
A51: Long Term Trade Payables | B51: BS_LT_TRADE_PAYABLES | C51: =_xll.EQNXTDZ($A$1,$B51,C$1,$B$1) -> 0 | D51: =_xll.EQNXTDZ($A$1,$B51,D$1,$B$1) -> 0 | E51: =_xll.EQNXTDZ($A$1,$B51,E$1,$B$1) -> 0 | F51: =_xll.EQNXTDZ($A$1,$B51,F$1,$B$1) -> 0 | G51: =_xll.EQNXTDZ($A$1,$B51,G$1,$B$1) -> 0 | H51: =_xll.EQNXTDZ($A$1,$B51,H$1,$B$1) -> 0 | I51: =_xll.EQNXTDZ($A$1,$B51,I$1,$B$1) -> 0 | J51: =_xll.EQNXTDZ($A$1,$B51,J$1,$B$1) -> 0 | ... AF51: =_xll.EQNXTDZ($A$1,$B51,AF$1,$B$1) -> 0
... A99: Estimated Capital Contracts Remaining | B99: BS_ESTIMATED_CAPITAL_CONTRACT | C99: =_xll.EQNXTDZ($A$1,$B99,C$1,$B$1) -> 0 | D99: =_xll.EQNXTDZ($A$1,$B99,D$1,$B$1) -> 0 | E99: =_xll.EQNXTDZ($A$1,$B99,E$1,$B$1) -> 0 | F99: =_xll.EQNXTDZ($A$1,$B99,F$1,$B$1) -> 0 | G99: =_xll.EQNXTDZ($A$1,$B99,G$1,$B$1) -> 0 | H99: =_xll.EQNXTDZ($A$1,$B99,H$1,$B$1) -> 0 | I99: =_xll.EQNXTDZ($A$1,$B99,I$1,$B$1) -> 0 | J99: =_xll.EQNXTDZ($A$1,$B99,J$1,$B$1) -> 0 | ... AF99: =_xll.EQNXTDZ($A$1,$B99,AF$1,$B$1) -> 0
A103: Field Description | B103: Field Name
A104: Equity Paid Up | B104: BS_EQUITY_PAIDUP | C104: =_xll.EQNXTDZ($A$1,$B104,C$1,$B$1) -> 0 | D104: =_xll.EQNXTDZ($A$1,$B104,D$1,$B$1) -> 0 | E104: =_xll.EQNXTDZ($A$1,$B104,E$1,$B$1) -> 0 | F104: =_xll.EQNXTDZ($A$1,$B104,F$1,$B$1) -> 0 | G104: =_xll.EQNXTDZ($A$1,$B104,G$1,$B$1) -> 0 | H104: =_xll.EQNXTDZ($A$1,$B104,H$1,$B$1) -> 0 | I104: =_xll.EQNXTDZ($A$1,$B104,I$1,$B$1) -> 10.407425 | J104: =_xll.EQNXTDZ($A$1,$B104,J$1,$B$1) -> 10.407425 | ... AF104: =_xll.EQNXTDZ($A$1,$B104,AF$1,$B$1) -> 0
A105: Face Value | B105: BS_FACE_VALUE | C105: =_xll.EQNXTDZ($A$1,$B105,C$1,$B$1) -> 0 | D105: =_xll.EQNXTDZ($A$1,$B105,D$1,$B$1) -> 0 | E105: =_xll.EQNXTDZ($A$1,$B105,E$1,$B$1) -> 0 | F105: =_xll.EQNXTDZ($A$1,$B105,F$1,$B$1) -> 0 | G105: =_xll.EQNXTDZ($A$1,$B105,G$1,$B$1) -> 0 | H105: =_xll.EQNXTDZ($A$1,$B105,H$1,$B$1) -> 0 | I105: =_xll.EQNXTDZ($A$1,$B105,I$1,$B$1) -> 10 | J105: =_xll.EQNXTDZ($A$1,$B105,J$1,$B$1) -> 10 | ... AF105: =_xll.EQNXTDZ($A$1,$B105,AF$1,$B$1) -> 0
A106: Close Price (Unit Curr.) | B106: FH_YEAR_PRICE | C106: =_xll.EQNXTDZ($A$1,$B106,C$1,$B$1) -> 0 | D106: =_xll.EQNXTDZ($A$1,$B106,D$1,$B$1) -> 0 | E106: =_xll.EQNXTDZ($A$1,$B106,E$1,$B$1) -> 0 | F106: =_xll.EQNXTDZ($A$1,$B106,F$1,$B$1) -> 0 | G106: =_xll.EQNXTDZ($A$1,$B106,G$1,$B$1) -> 0 | H106: =_xll.EQNXTDZ($A$1,$B106,H$1,$B$1) -> 0 | I106: =_xll.EQNXTDZ($A$1,$B106,I$1,$B$1) -> 0 | J106: =_xll.EQNXTDZ($A$1,$B106,J$1,$B$1) -> 0 | ... AF106: =_xll.EQNXTDZ($A$1,$B106,AF$1,$B$1) -> 0
A107: High Price (Unit Curr.) | B107: FH_HIGH | C107: =_xll.EQNXTDZ($A$1,$B107,C$1,$B$1) -> 0 | D107: =_xll.EQNXTDZ($A$1,$B107,D$1,$B$1) -> 0 | E107: =_xll.EQNXTDZ($A$1,$B107,E$1,$B$1) -> 0 | F107: =_xll.EQNXTDZ($A$1,$B107,F$1,$B$1) -> 0 | G107: =_xll.EQNXTDZ($A$1,$B107,G$1,$B$1) -> 0 | H107: =_xll.EQNXTDZ($A$1,$B107,H$1,$B$1) -> 0 | I107: =_xll.EQNXTDZ($A$1,$B107,I$1,$B$1) -> 0 | J107: =_xll.EQNXTDZ($A$1,$B107,J$1,$B$1) -> 0 | ... AF107: =_xll.EQNXTDZ($A$1,$B107,AF$1,$B$1) -> 0
A108: Low Price (Unit Curr.) | B108: FH_LOW | C108: =_xll.EQNXTDZ($A$1,$B108,C$1,$B$1) -> 0 | D108: =_xll.EQNXTDZ($A$1,$B108,D$1,$B$1) -> 0 | E108: =_xll.EQNXTDZ($A$1,$B108,E$1,$B$1) -> 0 | F108: =_xll.EQNXTDZ($A$1,$B108,F$1,$B$1) -> 0 | G108: =_xll.EQNXTDZ($A$1,$B108,G$1,$B$1) -> 0 | H108: =_xll.EQNXTDZ($A$1,$B108,H$1,$B$1) -> 0 | I108: =_xll.EQNXTDZ($A$1,$B108,I$1,$B$1) -> 0 | J108: =_xll.EQNXTDZ($A$1,$B108,J$1,$B$1) -> 0 | ... AF108: =_xll.EQNXTDZ($A$1,$B108,AF$1,$B$1) -> 0
A109: Market Capitalization | B109: FH_MCAP | C109: =_xll.EQNXTDZ($A$1,$B109,C$1,$B$1) -> 0 | D109: =_xll.EQNXTDZ($A$1,$B109,D$1,$B$1) -> 0 | E109: =_xll.EQNXTDZ($A$1,$B109,E$1,$B$1) -> 0 | F109: =_xll.EQNXTDZ($A$1,$B109,F$1,$B$1) -> 0 | G109: =_xll.EQNXTDZ($A$1,$B109,G$1,$B$1) -> 0 | H109: =_xll.EQNXTDZ($A$1,$B109,H$1,$B$1) -> 0 | I109: =_xll.EQNXTDZ($A$1,$B109,I$1,$B$1) -> 0 | J109: =_xll.EQNXTDZ($A$1,$B109,J$1,$B$1) -> 0 | ... AF109: =_xll.EQNXTDZ($A$1,$B109,AF$1,$B$1) -> 0
A110: Adj DPS(Rs) | B110: FR_ADJ_DPS | C110: =_xll.EQNXTDZ($A$1,$B110,C$1,$B$1) -> 0 | D110: =_xll.EQNXTDZ($A$1,$B110,D$1,$B$1) -> 0 | E110: =_xll.EQNXTDZ($A$1,$B110,E$1,$B$1) -> 0 | F110: =_xll.EQNXTDZ($A$1,$B110,F$1,$B$1) -> 0 | G110: =_xll.EQNXTDZ($A$1,$B110,G$1,$B$1) -> 0 | H110: =_xll.EQNXTDZ($A$1,$B110,H$1,$B$1) -> 0 | I110: =_xll.EQNXTDZ($A$1,$B110,I$1,$B$1) -> 0 | J110: =_xll.EQNXTDZ($A$1,$B110,J$1,$B$1) -> 1.25 | ... AF110: =_xll.EQNXTDZ($A$1,$B110,AF$1,$B$1) -> 0
A111: Date End | B111: SHP_DATE_END | C111: =_xll.EQNXTDZ($A$1,$B111,C$5) -> 0 | D111: =_xll.EQNXTDZ($A$1,$B111,D$5) -> 0 | E111: =_xll.EQNXTDZ($A$1,$B111,E$5) -> 0 | F111: =_xll.EQNXTDZ($A$1,$B111,F$5) -> 0 | G111: =_xll.EQNXTDZ($A$1,$B111,G$5) -> 0 | H111: =_xll.EQNXTDZ($A$1,$B111,H$5) -> 0 | I111: =_xll.EQNXTDZ($A$1,$B111,I$5) -> 0 | J111: =_xll.EQNXTDZ($A$1,$B111,J$5) -> 0 | ... AF111: =_xll.EQNXTDZ($A$1,$B111,AF$5) -> 0
A112: Total of Promoter and Promoter Group | B112: SHP_TPFTOTALPROMOTER | C112: =_xll.EQNXTDZ($A$1,$B112,C$5) -> 0 | D112: =_xll.EQNXTDZ($A$1,$B112,D$5) -> 0 | E112: =_xll.EQNXTDZ($A$1,$B112,E$5) -> 0 | F112: =_xll.EQNXTDZ($A$1,$B112,F$5) -> 0 | G112: =_xll.EQNXTDZ($A$1,$B112,G$5) -> 0 | H112: =_xll.EQNXTDZ($A$1,$B112,H$5) -> 0 | I112: =_xll.EQNXTDZ($A$1,$B112,I$5) -> 0 | J112: =_xll.EQNXTDZ($A$1,$B112,J$5) -> 0 | ... AF112: =_xll.EQNXTDZ($A$1,$B112,AF$5) -> 0
A113: Total of Promoter and Promoter Group Pledged | B113: SHP_PSHFTOTALPROMOTER | C113: =_xll.EQNXTDZ($A$1,$B113,C$5) -> 0 | D113: =_xll.EQNXTDZ($A$1,$B113,D$5) -> 0 | E113: =_xll.EQNXTDZ($A$1,$B113,E$5) -> 0 | F113: =_xll.EQNXTDZ($A$1,$B113,F$5) -> 0 | G113: =_xll.EQNXTDZ($A$1,$B113,G$5) -> 0 | H113: =_xll.EQNXTDZ($A$1,$B113,H$5) -> 0 | I113: =_xll.EQNXTDZ($A$1,$B113,I$5) -> 0 | J113: =_xll.EQNXTDZ($A$1,$B113,J$5) -> 0 | ... AF113: =_xll.EQNXTDZ($A$1,$B113,AF$5) -> 0

Sheet QTR Share Price
A1: ='QTR Raw'!A1 -> 218764 | C1: 201206 | D1: 201207 | E1: 201208 | F1: 201209 | G1: 201210 | H1: 201211 | I1: 201212 | J1: 201301 | K1: 201302 | L1: 201303 | M1: 201304 | N1: 201305 | O1: 201306 | P1: 201307 | Q1: 201308 | R1: 201309 | S1: 201310 | T1: 201311 | U1: 201312 | V1: 201401 | W1: 201402 | X1: 201403 | Y1: 201404 | Z1: 201405 | AA1: 201406 | AB1: 201407 | AC1: 201408 | AD1: 201409 | AE1: 201410 | AF1: 201411 | AG1: 201412 | AH1: 201501 | AI1: 201502 | AJ1: 201503 | AK1: 201504 | AL1: 201505 | AM1: 201506 | AN1: 201507 | AO1: 201508 | AP1: 201509 | AQ1: 201510 | AR1: 201511 | AS1: 201512 | AT1: 201601 | AU1: 201602 | AV1: 201603 | AW1: 201604 | AX1: 201605 | AY1: 201606 | AZ1: 201607 | BA1: 201608 | BB1: 201609 | BC1: 201610 | BD1: 201611 | BE1: 201612 | BF1: 201701 | BG1: 201702 | BH1: 201703 | BI1: 201704 | BJ1: 201705 | BK1: 201706 | BL1: 201707 | BM1: 201708 | BN1: 201709 | BO1: 201710 | BP1: 201711 | BQ1: 201712 | BR1: 201801 | BS1: 201802 | BT1: 201803 | BU1: 201804 | BV1: 201805 | BW1: 201806 | BX1: 201807 | BY1: 201808 | BZ1: 201809 | CA1: 201810 | CB1: 201811 | CC1: 201812 | CD1: 201901 | CE1: 201902 | CF1: 201903 | CG1: 201904 | CH1: 201905 | CI1: 201906 | CJ1: 201907 | CK1: 201908 | CL1: 201909 | CM1: 201910 | CN1: 201911 | CO1: 201912 | CP1: 202001 | CQ1: 202002 | CR1: 202003 | CS1: 202004 | CT1: 202005 | CU1: 202006 | CV1: 202007 | CW1: 202008 | CX1: 202009 | CY1: 202010 | CZ1: 202011 | DA1: 202012 | DB1: 202101 | DC1: 202102 | DD1: 202103 | DE1: 202104 | DF1: 202105 | DG1: 202106 | DH1: 202107 | DI1: 202108 | DJ1: 202109 | DK1: 202110 | DL1: 202111 | DM1: 202112 | DN1: 202201 | DO1: 202202 | DP1: 202203 | DQ1: 202204 | DR1: 202205 | DS1: 202206 | DT1: 202207 | DU1: 202208 | DV1: 202209 | DW1: 202210 | DX1: 202211 | DY1: 202212 | DZ1: 202301 | EA1: 202302 | EB1: 202303 | EC1: 202304 | ED1: 202305 | EE1: 202306 | EF1: 202307 | EG1: 202308 | EH1: 202309 | EI1: 202310 | EJ1: 202311 | EK1: 202312 | EL1: 202401 | EM1: 202402 | EN1: 202403 | EO1: 202404 | EP1: 202405 | EQ1: 202406 | ER1: 202407 | ES1: 202408 | ET1: 202409 | EU1: 202410 | EV1: 202411 | EW1: 202412 | EX1: 202501 | EY1: 202502 | EZ1: 202503 | FA1: 202504 | FB1: 202505 | FC1: 202506 | FD1: 202507 | FE1: 202508 | FF1: 202509 | FG1: 202510 | FH1: 202511 | FI1: 202512 | FJ1: 202601 | FK1: 202602 | FL1: 202603 | FM1: 202604 | FN1: 202605 | FO1: 202606 | FP1: 202607 | FQ1: 202608 | FR1: 202609 | FS1: 202610 | FT1: 202611 | FU1: 202612 | FV1: 202701 | FW1: 202702 | FX1: 202703 | FY1: 202704 | FZ1: 202705 | GA1: 202706 | GB1: 202707 | GC1: 202708 | GD1: 202709 | GE1: 202710 | GF1: 202711 | GG1: 202712 | GH1: 202801 | GI1: 202802 | GJ1: 202803 | GK1: 202804 | GL1: 202805 | GM1: 202806 | GN1: 202807 | GO1: 202808 | GP1: 202809 | GQ1: 202810 | GR1: 202811 | GS1: 202812 | GT1: 202901 | GU1: 202902 | GV1: 202903 | GW1: 202904 | GX1: 202905 | GY1: 202906 | GZ1: 202907 | HA1: 202908 | HB1: 202909 | HC1: 202910 | HD1: 202911 | HE1: 202912 | HF1: 203001 | HG1: 203002 | HH1: 203003 | HM1: 201206 | HN1: 201207 | HO1: 201208 | HP1: 201209 | HQ1: 201212 | HR1: 201303 | HS1: 201306 | HT1: 201309 | HU1: 201312 | HV1: 201403 | HW1: 201406 | HX1: 201409 | HY1: 201412 | HZ1: 201503 | IA1: 201506 | IB1: 201509 | IC1: 201512 | ID1: 201603 | IE1: 201606 | IF1: 201609 | IG1: 201612 | IH1: 201703 | II1: 201706 | IJ1: 201709 | IK1: 201712 | IL1: 201803 | IM1: 201806 | IN1: 201809 | IO1: 201812 | IP1: 201903 | IQ1: 201906 | IR1: 201909 | IS1: 201912 | IT1: 202003 | IU1: 202006 | IV1: 202009 | IW1: 202012 | IX1: 202103 | IY1: 202106 | IZ1: 202109 | JA1: 202112 | JB1: 202203 | JC1: 202206 | JD1: 202209 | JE1: 202212 | JF1: 202303 | JG1: 202306 | JH1: 202309 | JI1: 202312 | JJ1: 202403 | JK1: 202406 | JL1: 202409 | JM1: 202412 | JN1: 202503 | JO1: 202506 | JP1: 202509 | JQ1: 202512 | JR1: 202603 | JS1: 202606 | JT1: 202609 | JU1: 202612 | JV1: 202703 | JW1: 202706 | JX1: 202709 | JY1: 202712 | JZ1: 202803 | KA1: 202806 | KB1: 202809 | KC1: 202812 | KD1: 202903 | KE1: 202906 | KF1: 202909 | KG1: 202912 | KH1: 203003
FF2: 45901 | FG2: =+EOMONTH(FF2,1) -> 45961 | FH2: =+EOMONTH(FG2,1) -> 45991 | FI2: =+EOMONTH(FH2,1) -> 46022 | FJ2: =+EOMONTH(FI2,1) -> 46053 | FK2: =+EOMONTH(FJ2,1) -> 46081 | FL2: =+EOMONTH(FK2,1) -> 46112 | FM2: =+EOMONTH(FL2,1) -> 46142 | FN2: =+EOMONTH(FM2,1) -> 46173 | ... HH2: =+EOMONTH(HG2,1) -> 47573
A4: Field Description | B4: Field Name
A5: MonthEnd | B5: NMONTH_MONTHEND | C5: {=_xll.EQNXTDZ($A$1,$B5,C$1)} -> 0 | D5: {=_xll.EQNXTDZ($A$1,$B5,D$1)} -> 0 | E5: {=_xll.EQNXTDZ($A$1,$B5,E$1)} -> 0 | F5: {=_xll.EQNXTDZ($A$1,$B5,F$1)} -> 0 | G5: {=_xll.EQNXTDZ($A$1,$B5,G$1)} -> 0 | H5: {=_xll.EQNXTDZ($A$1,$B5,H$1)} -> 0 | I5: {=_xll.EQNXTDZ($A$1,$B5,I$1)} -> 0 | J5: {=_xll.EQNXTDZ($A$1,$B5,J$1)} -> 0 | ... HH5: {=_xll.EQNXTDZ($A$1,$B5,HH$1)} -> 0
A6: Open | B6: NMONTH_OPEN | C6: {=_xll.EQNXTDZ($A$1,$B6,C$1)} -> 0 | D6: {=_xll.EQNXTDZ($A$1,$B6,D$1)} -> 0 | E6: {=_xll.EQNXTDZ($A$1,$B6,E$1)} -> 0 | F6: {=_xll.EQNXTDZ($A$1,$B6,F$1)} -> 0 | G6: {=_xll.EQNXTDZ($A$1,$B6,G$1)} -> 0 | H6: {=_xll.EQNXTDZ($A$1,$B6,H$1)} -> 0 | I6: {=_xll.EQNXTDZ($A$1,$B6,I$1)} -> 0 | J6: {=_xll.EQNXTDZ($A$1,$B6,J$1)} -> 0 | ... HH6: {=_xll.EQNXTDZ($A$1,$B6,HH$1)} -> 0
A7: High | B7: NMONTH_HIGH | C7: {=_xll.EQNXTDZ($A$1,$B7,C$1)} -> 0 | D7: {=_xll.EQNXTDZ($A$1,$B7,D$1)} -> 0 | E7: {=_xll.EQNXTDZ($A$1,$B7,E$1)} -> 0 | F7: {=_xll.EQNXTDZ($A$1,$B7,F$1)} -> 0 | G7: {=_xll.EQNXTDZ($A$1,$B7,G$1)} -> 0 | H7: {=_xll.EQNXTDZ($A$1,$B7,H$1)} -> 0 | I7: {=_xll.EQNXTDZ($A$1,$B7,I$1)} -> 0 | J7: {=_xll.EQNXTDZ($A$1,$B7,J$1)} -> 0 | ... HH7: {=_xll.EQNXTDZ($A$1,$B7,HH$1)} -> 0 | HP7: =+MAX(D7:F7) -> 0 | HQ7: =+MAX(G7:I7) -> 0 | HR7: =+MAX(J7:L7) -> 0 | HS7: =+MAX(M7:O7) -> 0 | HT7: =+MAX(P7:R7) -> 0 | HU7: =+MAX(S7:U7) -> 0 | HV7: =+MAX(V7:X7) -> 0 | HW7: =+MAX(Y7:AA7) -> 0 | HX7: =+MAX(AB7:AD7) -> 0 | HY7: =+MAX(AE7:AG7) -> 0 | HZ7: =+MAX(AH7:AJ7) -> 0 | IA7: =+MAX(AK7:AM7) -> 0 | IB7: =+MAX(AN7:AP7) -> 0 | IC7: =+MAX(AQ7:AS7) -> 0 | ID7: =+MAX(AT7:AV7) -> 0 | IE7: =+MAX(AW7:AY7) -> 223.3 | IF7: =+MAX(AZ7:BB7) -> 222.93333 | IG7: =+MAX(BC7:BE7) -> 240.21667 | IH7: =+MAX(BF7:BH7) -> 248.23333 | II7: =+MAX(BI7:BK7) -> 260 | IJ7: =+MAX(BL7:BN7) -> 290.33333 | IK7: =+MAX(BO7:BQ7) -> 236.66667 | IL7: =+MAX(BR7:BT7) -> 241.33333 | IM7: =+MAX(BU7:BW7) -> 237 | IN7: =+MAX(BX7:BZ7) -> 231.6 | IO7: =+MAX(CA7:CC7) -> 225.66667 | IP7: =+MAX(CD7:CF7) -> 201.56667 | IQ7: =+MAX(CG7:CI7) -> 181.33333 | IR7: =+MAX(CJ7:CL7) -> 178.33333 | IS7: =+MAX(CM7:CO7) -> 201.5 | IT7: =+MAX(CP7:CR7) -> 241 | IU7: =+MAX(CS7:CU7) -> 194.23333 | IV7: =+MAX(CV7:CX7) -> 282.3 | IW7: =+MAX(CY7:DA7) -> 404 | IX7: =+MAX(DB7:DD7) -> 335.3 | IY7: =+MAX(DE7:DG7) -> 488.33333 | IZ7: =+MAX(DH7:DJ7) -> 458.3 | JA7: =+MAX(DK7:DM7) -> 432.66667 | JB7: =+MAX(DN7:DP7) -> 377.33333 | JC7: =+MAX(DQ7:DS7) -> 301.43333 | JD7: =+MAX(DT7:DV7) -> 247.33333 | JE7: =+MAX(DW7:DY7) -> 256.08333 | JF7: =+MAX(DZ7:EB7) -> 206.96667 | JG7: =+MAX(EC7:EE7) -> 178.9 | JH7: =+MAX(EF7:EH7) -> 203.16667 | JI7: =+MAX(EI7:EK7) -> 229.98333 | JJ7: =+MAX(EL7:EN7) -> 240.88333 | JK7: =MAX(EO7:EQ7) -> 227.36667 | JL7: =MAX(ER7:ET7) -> 310.45 | JM7: =MAX(EU7:EW7) -> 350.05 | JN7: =MAX(EX7:EZ7) -> 351.66667 | JO7: =MAX(FA7:FC7) -> 357.73333 | JP7: =MAX(FD7:FF7) -> 478.33333 | JQ7: =MAX(FG7:FI7) -> 536.66667 | JR7: =MAX(FJ7:FL7) -> 508 | JS7: =MAX(FM7:FO7) -> 578.25 | JT7: =MAX(FP7:FR7) -> 0 | JU7: =MAX(FS7:FU7) -> 0 | JV7: =MAX(FV7:FX7) -> 0 | JW7: =MAX(FY7:GA7) -> 0 | JX7: =MAX(GB7:GD7) -> 0 | JY7: =MAX(GE7:GG7) -> 0 | JZ7: =MAX(GH7:GJ7) -> 0 | KA7: =MAX(GK7:GM7) -> 0 | KB7: =MAX(GN7:GP7) -> 0 | KC7: =MAX(GQ7:GS7) -> 0 | KD7: =MAX(GT7:GV7) -> 0 | KE7: =MAX(GW7:GY7) -> 0 | KF7: =MAX(GZ7:HB7) -> 0 | KG7: =MAX(HC7:HE7) -> 0 | KH7: =MAX(HF7:HH7) -> 0
A8: Low | B8: NMONTH_LOW | C8: {=_xll.EQNXTDZ($A$1,$B8,C$1)} -> 0 | D8: {=_xll.EQNXTDZ($A$1,$B8,D$1)} -> 0 | E8: {=_xll.EQNXTDZ($A$1,$B8,E$1)} -> 0 | F8: {=_xll.EQNXTDZ($A$1,$B8,F$1)} -> 0 | G8: {=_xll.EQNXTDZ($A$1,$B8,G$1)} -> 0 | H8: {=_xll.EQNXTDZ($A$1,$B8,H$1)} -> 0 | I8: {=_xll.EQNXTDZ($A$1,$B8,I$1)} -> 0 | J8: {=_xll.EQNXTDZ($A$1,$B8,J$1)} -> 0 | ... HH8: {=_xll.EQNXTDZ($A$1,$B8,HH$1)} -> 0 | HP8: =+MIN(D8:F8) -> 0 | HQ8: =+MIN(G8:I8) -> 0 | HR8: =+MIN(J8:L8) -> 0 | HS8: =+MIN(M8:O8) -> 0 | HT8: =+MIN(P8:R8) -> 0 | HU8: =+MIN(S8:U8) -> 0 | HV8: =+MIN(V8:X8) -> 0 | HW8: =+MIN(Y8:AA8) -> 0 | HX8: =+MIN(AB8:AD8) -> 0 | HY8: =+MIN(AE8:AG8) -> 0 | HZ8: =+MIN(AH8:AJ8) -> 0 | IA8: =+MIN(AK8:AM8) -> 0 | IB8: =+MIN(AN8:AP8) -> 0 | IC8: =+MIN(AQ8:AS8) -> 0 | ID8: =+MIN(AT8:AV8) -> 0 | IE8: =+MIN(AW8:AY8) -> 0 | IF8: =+MIN(AZ8:BB8) -> 178.66667 | IG8: =+MIN(BC8:BE8) -> 180.03333 | IH8: =+MIN(BF8:BH8) -> 222.28333 | II8: =+MIN(BI8:BK8) -> 228.46667 | IJ8: =+MIN(BL8:BN8) -> 221.16667 | IK8: =+MIN(BO8:BQ8) -> 213.76667 | IL8: =+MIN(BR8:BT8) -> 188.5 | IM8: =+MIN(BU8:BW8) -> 190.7 | IN8: =+MIN(BX8:BZ8) -> 187.33333 | IO8: =+MIN(CA8:CC8) -> 174.66667 | IP8: =+MIN(CD8:CF8) -> 161.66667 | IQ8: =+MIN(CG8:CI8) -> 141.68333 | IR8: =+MIN(CJ8:CL8) -> 135.71667 | IS8: =+MIN(CM8:CO8) -> 162.68333 | IT8: =+MIN(CP8:CR8) -> 136.53333 | IU8: =+MIN(CS8:CU8) -> 160.66667 | IV8: =+MIN(CV8:CX8) -> 167.33333 | IW8: =+MIN(CY8:DA8) -> 251 | IX8: =+MIN(DB8:DD8) -> 277 | IY8: =+MIN(DE8:DG8) -> 301 | IZ8: =+MIN(DH8:DJ8) -> 386.03333 | JA8: =+MIN(DK8:DM8) -> 315 | JB8: =+MIN(DN8:DP8) -> 247.35 | JC8: =+MIN(DQ8:DS8) -> 206.66667 | JD8: =+MIN(DT8:DV8) -> 200.3 | JE8: =+MIN(DW8:DY8) -> 200 | JF8: =+MIN(DZ8:EB8) -> 138.46667 | JG8: =+MIN(EC8:EE8) -> 143.2 | JH8: =+MIN(EF8:EH8) -> 172.33333 | JI8: =+MIN(EI8:EK8) -> 168.93333 | JJ8: =+MIN(EL8:EN8) -> 184.7 | JK8: =MIN(EO8:EQ8) -> 190.46667 | JL8: =MIN(ER8:ET8) -> 207 | JM8: =MIN(EU8:EW8) -> 258.31667 | JN8: =MIN(EX8:EZ8) -> 219.33333 | JO8: =MIN(FA8:FC8) -> 219.56667 | JP8: =MIN(FD8:FF8) -> 323.01667 | JQ8: =MIN(FG8:FI8) -> 376.66667 | JR8: =MIN(FJ8:FL8) -> 342.55 | JS8: =MIN(FM8:FO8) -> 352.9 | JT8: =MIN(FP8:FR8) -> 0 | JU8: =MIN(FS8:FU8) -> 0 | JV8: =MIN(FV8:FX8) -> 0 | JW8: =MIN(FY8:GA8) -> 0 | JX8: =MIN(GB8:GD8) -> 0 | JY8: =MIN(GE8:GG8) -> 0 | JZ8: =MIN(GH8:GJ8) -> 0 | KA8: =MIN(GK8:GM8) -> 0 | KB8: =MIN(GN8:GP8) -> 0 | KC8: =MIN(GQ8:GS8) -> 0 | KD8: =MIN(GT8:GV8) -> 0 | KE8: =MIN(GW8:GY8) -> 0 | KF8: =MIN(GZ8:HB8) -> 0 | KG8: =MIN(HC8:HE8) -> 0 | KH8: =MIN(HF8:HH8) -> 0
A9: Close | B9: NMONTH_CLOSE | C9: {=_xll.EQNXTDZ($A$1,$B9,C$1)} -> 0 | D9: {=_xll.EQNXTDZ($A$1,$B9,D$1)} -> 0 | E9: {=_xll.EQNXTDZ($A$1,$B9,E$1)} -> 0 | F9: {=_xll.EQNXTDZ($A$1,$B9,F$1)} -> 0 | G9: {=_xll.EQNXTDZ($A$1,$B9,G$1)} -> 0 | H9: {=_xll.EQNXTDZ($A$1,$B9,H$1)} -> 0 | I9: {=_xll.EQNXTDZ($A$1,$B9,I$1)} -> 0 | J9: {=_xll.EQNXTDZ($A$1,$B9,J$1)} -> 0 | ... HH9: {=_xll.EQNXTDZ($A$1,$B9,HH$1)} -> 0 | HP9: =+F9 -> 0 | HQ9: =+I9 -> 0 | HR9: =+L9 -> 0 | HS9: =+O9 -> 0 | HT9: =+R9 -> 0 | HU9: =+U9 -> 0 | HV9: =+X9 -> 0 | HW9: =+AA9 -> 0 | HX9: =+AD9 -> 0 | HY9: =+AG9 -> 0 | HZ9: =+AJ9 -> 0 | IA9: =+AM9 -> 0 | IB9: =+AP9 -> 0 | IC9: =+AS9 -> 0 | ID9: =+AV9 -> 0 | IE9: =+AY9 -> 190.46667 | IF9: =+BB9 -> 204.36667 | IG9: =+BE9 -> 231.08333 | IH9: =+BH9 -> 239.26667 | II9: =+BK9 -> 242.46667 | IJ9: =+BN9 -> 227.43333 | IK9: =+BQ9 -> 233.03333 | IL9: =+BT9 -> 198.95 | IM9: =+BW9 -> 191.61667 | IN9: =+BZ9 -> 214.06667 | IO9: =+CC9 -> 179.85 | IP9: =+CF9 -> 177.96667 | IQ9: =+CI9 -> 157.35 | IR9: =+CL9 -> 171.93333 | IS9: =+CO9 -> 183.05 | IT9: =+CR9 -> 165.51667 | IU9: =+CU9 -> 169.5 | IV9: =+CX9 -> 252.75 | IW9: =+DA9 -> 304.33333 | IX9: =+DD9 -> 300.86667 | IY9: =+DG9 -> 437.56667 | IZ9: =+DJ9 -> 388.73333 | JA9: =+DM9 -> 369.18333 | JB9: =+DP9 -> 258.43333 | JC9: =+DS9 -> 207.01667 | JD9: =+DV9 -> 233.43333 | JE9: =+DY9 -> 206.21667 | JF9: =+EB9 -> 143.28333 | JG9: =+EE9 -> 172.65 | JH9: =+EH9 -> 189.43333 | JI9: =+EK9 -> 214.51667 | JJ9: =+EN9 -> 196.65 | JK9: =EQ9 -> 212.43333 | JL9: =ET9 -> 270.68333 | JM9: =EW9 -> 303.93333 | JN9: =EZ9 -> 226.55 | JO9: =FC9 -> 330.16667 | JP9: =FF9 -> 386.86667 | JQ9: =FI9 -> 445.7 | JR9: =FL9 -> 349.55 | JS9: =FO9 -> 533.6 | JT9: =FR9 -> 0 | JU9: =FU9 -> 0 | JV9: =FX9 -> 0 | JW9: =GA9 -> 0 | JX9: =GD9 -> 0 | JY9: =GG9 -> 0 | JZ9: =GJ9 -> 0 | KA9: =GM9 -> 0 | KB9: =GP9 -> 0 | KC9: =GS9 -> 0 | KD9: =GV9 -> 0 | KE9: =GY9 -> 0 | KF9: =HB9 -> 0 | KG9: =HE9 -> 0 | KH9: =HH9 -> 0
A11: Field Description | B11: Field Name | C11: {=_xll.EQNXTDZ($A$1,$B11,C$1)} -> 0 | D11: {=_xll.EQNXTDZ($A$1,$B11,D$1)} -> 0 | E11: {=_xll.EQNXTDZ($A$1,$B11,E$1)} -> 0 | F11: {=_xll.EQNXTDZ($A$1,$B11,F$1)} -> 0 | G11: {=_xll.EQNXTDZ($A$1,$B11,G$1)} -> 0 | H11: {=_xll.EQNXTDZ($A$1,$B11,H$1)} -> 0 | I11: {=_xll.EQNXTDZ($A$1,$B11,I$1)} -> 0 | J11: {=_xll.EQNXTDZ($A$1,$B11,J$1)} -> 0 | ... HH11: {=_xll.EQNXTDZ($A$1,$B11,HH$1)} -> 0
A12: Month End | B12: BMONTH_MONTHEND | C12: {=_xll.EQNXTDZ($A$1,$B12,C$1)} -> 0 | D12: {=_xll.EQNXTDZ($A$1,$B12,D$1)} -> 0 | E12: {=_xll.EQNXTDZ($A$1,$B12,E$1)} -> 0 | F12: {=_xll.EQNXTDZ($A$1,$B12,F$1)} -> 0 | G12: {=_xll.EQNXTDZ($A$1,$B12,G$1)} -> 0 | H12: {=_xll.EQNXTDZ($A$1,$B12,H$1)} -> 0 | I12: {=_xll.EQNXTDZ($A$1,$B12,I$1)} -> 0 | J12: {=_xll.EQNXTDZ($A$1,$B12,J$1)} -> 0 | ... HH12: {=_xll.EQNXTDZ($A$1,$B12,HH$1)} -> 0
A13: Open | B13: BMONTH_OPEN | C13: {=_xll.EQNXTDZ($A$1,$B13,C$1)} -> 0 | D13: {=_xll.EQNXTDZ($A$1,$B13,D$1)} -> 0 | E13: {=_xll.EQNXTDZ($A$1,$B13,E$1)} -> 0 | F13: {=_xll.EQNXTDZ($A$1,$B13,F$1)} -> 0 | G13: {=_xll.EQNXTDZ($A$1,$B13,G$1)} -> 0 | H13: {=_xll.EQNXTDZ($A$1,$B13,H$1)} -> 0 | I13: {=_xll.EQNXTDZ($A$1,$B13,I$1)} -> 0 | J13: {=_xll.EQNXTDZ($A$1,$B13,J$1)} -> 0 | ... HH13: {=_xll.EQNXTDZ($A$1,$B13,HH$1)} -> 0
A14: High | B14: BMONTH_HIGH | C14: {=_xll.EQNXTDZ($A$1,$B14,C$1)} -> 0 | D14: {=_xll.EQNXTDZ($A$1,$B14,D$1)} -> 0 | E14: {=_xll.EQNXTDZ($A$1,$B14,E$1)} -> 0 | F14: {=_xll.EQNXTDZ($A$1,$B14,F$1)} -> 0 | G14: {=_xll.EQNXTDZ($A$1,$B14,G$1)} -> 0 | H14: {=_xll.EQNXTDZ($A$1,$B14,H$1)} -> 0 | I14: {=_xll.EQNXTDZ($A$1,$B14,I$1)} -> 0 | J14: {=_xll.EQNXTDZ($A$1,$B14,J$1)} -> 0 | ... HH14: {=_xll.EQNXTDZ($A$1,$B14,HH$1)} -> 0 | HP14: =+MAX(D14:F14) -> 0 | HQ14: =+MAX(G14:I14) -> 0 | HR14: =+MAX(J14:L14) -> 0 | HS14: =+MAX(M14:O14) -> 0 | HT14: =+MAX(P14:R14) -> 0 | HU14: =+MAX(S14:U14) -> 0 | HV14: =+MAX(V14:X14) -> 0 | HW14: =+MAX(Y14:AA14) -> 0 | HX14: =+MAX(AB14:AD14) -> 0 | HY14: =+MAX(AE14:AG14) -> 0 | HZ14: =+MAX(AH14:AJ14) -> 0 | IA14: =+MAX(AK14:AM14) -> 0 | IB14: =+MAX(AN14:AP14) -> 0 | IC14: =+MAX(AQ14:AS14) -> 0 | ID14: =+MAX(AT14:AV14) -> 0 | IE14: =+MAX(AW14:AY14) -> 222.9 | IF14: =+MAX(AZ14:BB14) -> 222.65 | IG14: =+MAX(BC14:BE14) -> 239.95 | IH14: =+MAX(BF14:BH14) -> 247.58333 | II14: =+MAX(BI14:BK14) -> 259.96667 | IJ14: =+MAX(BL14:BN14) -> 257.65 | IK14: =+MAX(BO14:BQ14) -> 237.33333 | IL14: =+MAX(BR14:BT14) -> 241.66667 | IM14: =+MAX(BU14:BW14) -> 241.66667 | IN14: =+MAX(BX14:BZ14) -> 232.33333 | IO14: =+MAX(CA14:CC14) -> 225.98333 | IP14: =+MAX(CD14:CF14) -> 201.36667 | IQ14: =+MAX(CG14:CI14) -> 181.66667 | IR14: =+MAX(CJ14:CL14) -> 178.3 | IS14: =+MAX(CM14:CO14) -> 201.51667 | IT14: =+MAX(CP14:CR14) -> 229.81667 | IU14: =+MAX(CS14:CU14) -> 193.96667 | IV14: =+MAX(CV14:CX14) -> 281.75 | IW14: =+MAX(CY14:DA14) -> 404 | IX14: =+MAX(DB14:DD14) -> 335.36667 | IY14: =+MAX(DE14:DG14) -> 488.63333 | IZ14: =+MAX(DH14:DJ14) -> 461.53333 | JA14: =+MAX(DK14:DM14) -> 432.33333 | JB14: =+MAX(DN14:DP14) -> 376.66667 | JC14: =+MAX(DQ14:DS14) -> 305.65 | JD14: =+MAX(DT14:DV14) -> 246.45 | JE14: =+MAX(DW14:DY14) -> 256.33333 | JF14: =+MAX(DZ14:EB14) -> 207.05 | JG14: =+MAX(EC14:EE14) -> 178.65 | JH14: =+MAX(EF14:EH14) -> 203.35 | JI14: =+MAX(EI14:EK14) -> 229.4 | JJ14: =+MAX(EL14:EN14) -> 240.66667 | JK14: =MAX(EO14:EQ14) -> 227.23333 | JL14: =MAX(ER14:ET14) -> 310 | JM14: =MAX(EU14:EW14) -> 350.21667 | JN14: =MAX(EX14:EZ14) -> 351.01667 | JO14: =MAX(FA14:FC14) -> 357.48333 | JP14: =MAX(FD14:FF14) -> 478.1 | JQ14: =MAX(FG14:FI14) -> 537.96667 | JR14: =MAX(FJ14:FL14) -> 507.75 | JS14: =MAX(FM14:FO14) -> 578.05 | JT14: =MAX(FP14:FR14) -> 0 | JU14: =MAX(FS14:FU14) -> 0 | JV14: =MAX(FV14:FX14) -> 0 | JW14: =MAX(FY14:GA14) -> 0 | JX14: =MAX(GB14:GD14) -> 0 | JY14: =MAX(GE14:GG14) -> 0 | JZ14: =MAX(GH14:GJ14) -> 0 | KA14: =MAX(GK14:GM14) -> 0 | KB14: =MAX(GN14:GP14) -> 0 | KC14: =MAX(GQ14:GS14) -> 0 | KD14: =MAX(GT14:GV14) -> 0 | KE14: =MAX(GW14:GY14) -> 0 | KF14: =MAX(GZ14:HB14) -> 0 | KG14: =MAX(HC14:HE14) -> 0 | KH14: =MAX(HF14:HH14) -> 0
A15: Low | B15: BMONTH_LOW | C15: {=_xll.EQNXTDZ($A$1,$B15,C$1)} -> 0 | D15: {=_xll.EQNXTDZ($A$1,$B15,D$1)} -> 0 | E15: {=_xll.EQNXTDZ($A$1,$B15,E$1)} -> 0 | F15: {=_xll.EQNXTDZ($A$1,$B15,F$1)} -> 0 | G15: {=_xll.EQNXTDZ($A$1,$B15,G$1)} -> 0 | H15: {=_xll.EQNXTDZ($A$1,$B15,H$1)} -> 0 | I15: {=_xll.EQNXTDZ($A$1,$B15,I$1)} -> 0 | J15: {=_xll.EQNXTDZ($A$1,$B15,J$1)} -> 0 | ... HH15: {=_xll.EQNXTDZ($A$1,$B15,HH$1)} -> 0 | HP15: =+MIN(D15:F15) -> 0 | HQ15: =+MIN(G15:I15) -> 0 | HR15: =+MIN(J15:L15) -> 0 | HS15: =+MIN(M15:O15) -> 0 | HT15: =+MIN(P15:R15) -> 0 | HU15: =+MIN(S15:U15) -> 0 | HV15: =+MIN(V15:X15) -> 0 | HW15: =+MIN(Y15:AA15) -> 0 | HX15: =+MIN(AB15:AD15) -> 0 | HY15: =+MIN(AE15:AG15) -> 0 | HZ15: =+MIN(AH15:AJ15) -> 0 | IA15: =+MIN(AK15:AM15) -> 0 | IB15: =+MIN(AN15:AP15) -> 0 | IC15: =+MIN(AQ15:AS15) -> 0 | ID15: =+MIN(AT15:AV15) -> 0 | IE15: =+MIN(AW15:AY15) -> 0 | IF15: =+MIN(AZ15:BB15) -> 178.75 | IG15: =+MIN(BC15:BE15) -> 190.36667 | IH15: =+MIN(BF15:BH15) -> 221.86667 | II15: =+MIN(BI15:BK15) -> 228.2 | IJ15: =+MIN(BL15:BN15) -> 220 | IK15: =+MIN(BO15:BQ15) -> 203.7 | IL15: =+MIN(BR15:BT15) -> 190 | IM15: =+MIN(BU15:BW15) -> 191.66667 | IN15: =+MIN(BX15:BZ15) -> 182.56667 | IO15: =+MIN(CA15:CC15) -> 173.28333 | IP15: =+MIN(CD15:CF15) -> 160.66667 | IQ15: =+MIN(CG15:CI15) -> 141.75 | IR15: =+MIN(CJ15:CL15) -> 135.55 | IS15: =+MIN(CM15:CO15) -> 162.4 | IT15: =+MIN(CP15:CR15) -> 136.66667 | IU15: =+MIN(CS15:CU15) -> 161.76667 | IV15: =+MIN(CV15:CX15) -> 161.76667 | IW15: =+MIN(CY15:DA15) -> 250.86667 | IX15: =+MIN(DB15:DD15) -> 277.33333 | IY15: =+MIN(DE15:DG15) -> 300.91667 | IZ15: =+MIN(DH15:DJ15) -> 386.33333 | JA15: =+MIN(DK15:DM15) -> 315.56667 | JB15: =+MIN(DN15:DP15) -> 247.41667 | JC15: =+MIN(DQ15:DS15) -> 206.75 | JD15: =+MIN(DT15:DV15) -> 200 | JE15: =+MIN(DW15:DY15) -> 200.03333 | JF15: =+MIN(DZ15:EB15) -> 138.66667 | JG15: =+MIN(EC15:EE15) -> 143.23333 | JH15: =+MIN(EF15:EH15) -> 170.81667 | JI15: =+MIN(EI15:EK15) -> 170.33333 | JJ15: =+MIN(EL15:EN15) -> 185.28333 | JK15: =MIN(EO15:EQ15) -> 190.25 | JL15: =MIN(ER15:ET15) -> 206.95 | JM15: =MIN(EU15:EW15) -> 258.2 | JN15: =MIN(EX15:EZ15) -> 219.33333 | JO15: =MIN(FA15:FC15) -> 220.01667 | JP15: =MIN(FD15:FF15) -> 322.88333 | JQ15: =MIN(FG15:FI15) -> 376.71667 | JR15: =MIN(FJ15:FL15) -> 342.55 | JS15: =MIN(FM15:FO15) -> 350.4 | JT15: =MIN(FP15:FR15) -> 0 | JU15: =MIN(FS15:FU15) -> 0 | JV15: =MIN(FV15:FX15) -> 0 | JW15: =MIN(FY15:GA15) -> 0 | JX15: =MIN(GB15:GD15) -> 0 | JY15: =MIN(GE15:GG15) -> 0 | JZ15: =MIN(GH15:GJ15) -> 0 | KA15: =MIN(GK15:GM15) -> 0 | KB15: =MIN(GN15:GP15) -> 0 | KC15: =MIN(GQ15:GS15) -> 0 | KD15: =MIN(GT15:GV15) -> 0 | KE15: =MIN(GW15:GY15) -> 0 | KF15: =MIN(GZ15:HB15) -> 0 | KG15: =MIN(HC15:HE15) -> 0 | KH15: =MIN(HF15:HH15) -> 0
A16: Close | B16: BMONTH_CLOSE | C16: {=_xll.EQNXTDZ($A$1,$B16,C$1)} -> 0 | D16: {=_xll.EQNXTDZ($A$1,$B16,D$1)} -> 0 | E16: {=_xll.EQNXTDZ($A$1,$B16,E$1)} -> 0 | F16: {=_xll.EQNXTDZ($A$1,$B16,F$1)} -> 0 | G16: {=_xll.EQNXTDZ($A$1,$B16,G$1)} -> 0 | H16: {=_xll.EQNXTDZ($A$1,$B16,H$1)} -> 0 | I16: {=_xll.EQNXTDZ($A$1,$B16,I$1)} -> 0 | J16: {=_xll.EQNXTDZ($A$1,$B16,J$1)} -> 0 | ... HH16: {=_xll.EQNXTDZ($A$1,$B16,HH$1)} -> 0 | HP16: =+F16 -> 0 | HQ16: =+I16 -> 0 | HR16: =+L16 -> 0 | HS16: =+O16 -> 0 | HT16: =+R16 -> 0 | HU16: =+U16 -> 0 | HV16: =+X16 -> 0 | HW16: =+AA16 -> 0 | HX16: =+AD16 -> 0 | HY16: =+AG16 -> 0 | HZ16: =+AJ16 -> 0 | IA16: =+AM16 -> 0 | IB16: =+AP16 -> 0 | IC16: =+AS16 -> 0 | ID16: =+AV16 -> 0 | IE16: =+AY16 -> 190.56667 | IF16: =+BB16 -> 204.85 | IG16: =+BE16 -> 230.15 | IH16: =+BH16 -> 238.56667 | II16: =+BK16 -> 242.91667 | IJ16: =+BN16 -> 229.41667 | IK16: =+BQ16 -> 229.93333 | IL16: =+BT16 -> 200.38333 | IM16: =+BW16 -> 192.2 | IN16: =+BZ16 -> 214.98333 | IO16: =+CC16 -> 175.71667 | IP16: =+CF16 -> 176.83333 | IQ16: =+CI16 -> 157.21667 | IR16: =+CL16 -> 171.78333 | IS16: =+CO16 -> 182.3 | IT16: =+CR16 -> 165.18333 | IU16: =+CU16 -> 168.66667 | IV16: =+CX16 -> 252.8 | IW16: =+DA16 -> 304.46667 | IX16: =+DD16 -> 300.98333 | IY16: =+DG16 -> 437.85 | IZ16: =+DJ16 -> 388.65 | JA16: =+DM16 -> 368.51667 | JB16: =+DP16 -> 257.91667 | JC16: =+DS16 -> 207.08333 | JD16: =+DV16 -> 233.16667 | JE16: =+DY16 -> 205.96667 | JF16: =+EB16 -> 143.23333 | JG16: =+EE16 -> 172.63333 | JH16: =+EH16 -> 189.78333 | JI16: =+EK16 -> 214.5 | JJ16: =+EN16 -> 197.4 | JK16: =EQ16 -> 211.38333 | JL16: =ET16 -> 270.56667 | JM16: =EW16 -> 304.83333 | JN16: =EZ16 -> 226.73333 | JO16: =FC16 -> 330.05 | JP16: =FF16 -> 386.71667 | JQ16: =FI16 -> 446 | JR16: =FL16 -> 349.75 | JS16: =FO16 -> 533.1 | JT16: =FR16 -> 0 | JU16: =FU16 -> 0 | JV16: =FX16 -> 0 | JW16: =GA16 -> 0 | JX16: =GD16 -> 0 | JY16: =GG16 -> 0 | JZ16: =GJ16 -> 0 | KA16: =GM16 -> 0 | KB16: =GP16 -> 0 | KC16: =GS16 -> 0 | KD16: =GV16 -> 0 | KE16: =GY16 -> 0 | KF16: =HB16 -> 0 | KG16: =HE16 -> 0 | KH16: =HH16 -> 0
A19: High | HP19: =+IF(HP14=0,HP7,HP14) -> 0 | HQ19: =+IF(HQ14=0,HQ7,HQ14) -> 0 | HR19: =+IF(HR14=0,HR7,HR14) -> 0 | HS19: =+IF(HS14=0,HS7,HS14) -> 0 | HT19: =+IF(HT14=0,HT7,HT14) -> 0 | HU19: =+IF(HU14=0,HU7,HU14) -> 0 | HV19: =+IF(HV14=0,HV7,HV14) -> 0 | HW19: =+IF(HW14=0,HW7,HW14) -> 0 | ... KH19: =+IF(KH14=0,KH7,KH14) -> 0
A20: Low | HP20: =+IF(HP15=0,HP8,HP15) -> 0 | HQ20: =+IF(HQ15=0,HQ8,HQ15) -> 0 | HR20: =+IF(HR15=0,HR8,HR15) -> 0 | HS20: =+IF(HS15=0,HS8,HS15) -> 0 | HT20: =+IF(HT15=0,HT8,HT15) -> 0 | HU20: =+IF(HU15=0,HU8,HU15) -> 0 | HV20: =+IF(HV15=0,HV8,HV15) -> 0 | HW20: =+IF(HW15=0,HW8,HW15) -> 0 | ... KH20: =+IF(KH15=0,KH8,KH15) -> 0
A21: Close | HP21: =+IF(HP16=0,HP9,HP16) -> 0 | HQ21: =+IF(HQ16=0,HQ9,HQ16) -> 0 | HR21: =+IF(HR16=0,HR9,HR16) -> 0 | HS21: =+IF(HS16=0,HS9,HS16) -> 0 | HT21: =+IF(HT16=0,HT9,HT16) -> 0 | HU21: =+IF(HU16=0,HU9,HU16) -> 0 | HV21: =+IF(HV16=0,HV9,HV16) -> 0 | HW21: =+IF(HW16=0,HW9,HW16) -> 0 | ... KH21: =+IF(KH16=0,KH9,KH16) -> 0

Sheet QTR No. of Shares
A1: ='QTR Raw'!A1 -> 218764 | C1: 201206 | D1: 201209 | E1: 201212 | F1: 201303 | G1: 201306 | H1: 201309 | I1: 201312 | J1: 201403 | K1: 201406 | L1: 201409 | M1: 201412 | N1: 201503 | O1: 201506 | P1: 201509 | Q1: 201512 | R1: 201603 | S1: 201606 | T1: 201609 | U1: 201612 | V1: 201703 | W1: 201706 | X1: 201709 | Y1: 201712 | Z1: 201803 | AA1: 201806 | AB1: 201809 | AC1: 201812 | AD1: 201903 | AE1: 201906 | AF1: 201909 | AG1: 201912 | AH1: 202003 | AI1: 202006 | AJ1: 202009 | AK1: 202012 | AL1: 202103 | AM1: 202106 | AN1: 202109 | AO1: 202112 | AP1: 202203 | AQ1: 202206 | AR1: 202209 | AS1: 202212 | AT1: 202303 | AU1: 202306 | AV1: 202309 | AW1: 202312 | AX1: 202403 | AY1: 202406
A4: Field Description | B4: Field Name
A5: Date End | B5: SHP_DATE_END | C5: {=_xll.EQNXTDZ($A$1,$B5,C$1)} -> 0 | D5: {=_xll.EQNXTDZ($A$1,$B5,D$1)} -> 0 | E5: {=_xll.EQNXTDZ($A$1,$B5,E$1)} -> 0 | F5: {=_xll.EQNXTDZ($A$1,$B5,F$1)} -> 201303 | G5: {=_xll.EQNXTDZ($A$1,$B5,G$1)} -> 0 | H5: {=_xll.EQNXTDZ($A$1,$B5,H$1)} -> 201309 | I5: {=_xll.EQNXTDZ($A$1,$B5,I$1)} -> 0 | J5: {=_xll.EQNXTDZ($A$1,$B5,J$1)} -> 0 | ... AY5: {=_xll.EQNXTDZ($A$1,$B5,AY$1)} -> 202406
A6: Grand Total | B6: SHP_NSGRANDTOTAL | C6: {=_xll.EQNXTDZ($A$1,$B6,C$1)} -> 0 | D6: {=_xll.EQNXTDZ($A$1,$B6,D$1)} -> 0 | E6: {=_xll.EQNXTDZ($A$1,$B6,E$1)} -> 0 | F6: {=_xll.EQNXTDZ($A$1,$B6,F$1)} -> 10917519 | G6: {=_xll.EQNXTDZ($A$1,$B6,G$1)} -> 0 | H6: {=_xll.EQNXTDZ($A$1,$B6,H$1)} -> 10917519 | I6: {=_xll.EQNXTDZ($A$1,$B6,I$1)} -> 0 | J6: {=_xll.EQNXTDZ($A$1,$B6,J$1)} -> 0 | ... AY6: {=_xll.EQNXTDZ($A$1,$B6,AY$1)} -> 52952676
B7: In Crs. | C7: =+C6/10^7 -> 0 | D7: =+D6/10^7 -> 0 | E7: =+E6/10^7 -> 0 | F7: =+F6/10^7 -> 1.0917519 | G7: =+G6/10^7 -> 0 | H7: =+H6/10^7 -> 1.0917519 | I7: =+I6/10^7 -> 0 | J7: =+J6/10^7 -> 0 | ... AY7: =+AY6/10^7 -> 5.2952676

Sheet Share price Daily
A1: =_xll.EQNXTH(B1,"[ADJC];[ADJH];[ADJL];[ADJO];[UCLS];[VOLUME]","2015-Jan-01","Y","All traded days","Asc") -> EQNXTH | B1: =+'Annual Raw'!A1 -> 218764 | L1: =_xll.EQNXTH(B1,"[NADJC];[NADJH];[NADJLOW];[NADJOPEN];[NUCLOSE];[NVOLUME]","2015-Jan-01","Y","All traded days","Asc") -> EQNXTH
A2: Thyrocare Technologies Ltd. | L2: Thyrocare Technologies Ltd.
A3: DATE | B3: ADJHIGH | C3: ADJCLOSE | D3: ADJLOW | E3: ADJOPEN | F3: CLOSE | G3: VOLUME | L3: DATE | M3: ADJCLOSE | N3: ADJHIGH | O3: ADJLOW | P3: ADJOPEN | Q3: CLOSE | R3: VOLUME
A4: 42499 | B4: 221.8 | C4: 206.03333 | D4: 202 | E4: 220.66667 | F4: 618.1 | G4: 2678027 | L4: 42499 | M4: 206.26667 | N4: 221.66667 | O4: 201.93333 | P4: 221.66667 | Q4: 618.8 | R4: 12860078
A5: 42500 | B5: 205.81667 | C5: 200.85 | D5: 198.33333 | E5: 205.26667 | F5: 602.55 | G5: 703865 | L5: 42500 | M5: 200.86667 | N5: 206.25 | O5: 198.25 | P5: 205.3 | Q5: 602.6 | R5: 2902129
A6: 42501 | B6: 209.9 | C6: 208.93333 | D6: 195 | E6: 196.7 | F6: 626.8 | G6: 765305 | L6: 42501 | M6: 209.08333 | N6: 209.96667 | O6: 195.15 | P6: 196.7 | Q6: 627.25 | R6: 2734316
A7: 42502 | B7: 211.46667 | C7: 209.88333 | D7: 207.58333 | E7: 209.9 | F7: 629.65 | G7: 233671 | L7: 42502 | M7: 209.83333 | N7: 211.43333 | O7: 207.36667 | P7: 209.46667 | Q7: 629.5 | R7: 849875
A8: 42503 | B8: 211.3 | C8: 207.56667 | D8: 206 | E8: 209.33333 | F8: 622.7 | G8: 169821 | L8: 42503 | M8: 208.46667 | N8: 211.25 | O8: 206 | P8: 209 | Q8: 625.4 | R8: 616134
A9: 42506 | B9: 214.16667 | C9: 209.93333 | D9: 205.1 | E9: 208.1 | F9: 629.8 | G9: 238292 | L9: 42506 | M9: 210.01667 | N9: 214.16667 | O9: 205.05 | P9: 208 | Q9: 630.05 | R9: 615793
A10: 42507 | B10: 211.83333 | C10: 208.36667 | D10: 207.7 | E10: 210 | F10: 625.1 | G10: 123810 | L10: 42507 | M10: 208.56667 | N10: 211.9 | O10: 208.05 | P10: 210.01667 | Q10: 625.7 | R10: 341194
A11: 42508 | B11: 210 | C11: 208.31667 | D11: 207.33333 | E11: 208.31667 | F11: 624.95 | G11: 56193 | L11: 42508 | M11: 208.45 | N11: 210 | O11: 207.66667 | P11: 208.33333 | Q11: 625.35 | R11: 168022
A12: 42509 | B12: 209.4 | C12: 202.33333 | D12: 201 | E12: 208.85 | F12: 607 | G12: 43076 | L12: 42509 | M12: 202.18333 | N12: 209.55 | O12: 200.35 | P12: 208.48333 | Q12: 606.55 | R12: 167565
A13: 42510 | B13: 205.1 | C13: 201.16667 | D13: 200.38333 | E13: 202.73333 | F13: 603.5 | G13: 49201 | L13: 42510 | M13: 201.11667 | N13: 205.16667 | O13: 200.5 | P13: 202.7 | Q13: 603.35 | R13: 157728
A14: 42513 | B14: 206.26667 | C14: 202.25 | D14: 200 | E14: 201.33333 | F14: 606.75 | G14: 68409 | L14: 42513 | M14: 202.66667 | N14: 206.33333 | O14: 199.98333 | P14: 201.8 | Q14: 608 | R14: 187330
A15: 42514 | B15: 204.91667 | C15: 202.26667 | D15: 201 | E15: 202.66667 | F15: 606.8 | G15: 40922 | L15: 42514 | M15: 203.08333 | N15: 204.98333 | O15: 201 | P15: 203 | Q15: 609.25 | R15: 130537
... A2722: 46010 | B2722: 939 | C2722: 932.5 | D2722: 906.25 | E2722: 910.9 | F2722: 932.5 | G2722: 8862 | L2722: 46010 | M2722: 936.6 | N2722: 938.9 | O2722: 905 | P2722: 905 | Q2722: 936.6 | R2722: 296202

Sheet Sheet2
J19: 219.3 | K19: 186.25 | L19: 186.75
J20: 192.9 | K20: 135.5 | L20: 146.9 | N20: 219.3 | O20: 192.9 | P20: 186 | Q20: 178.7 | R20: 207 | S20: 255.15 | T20: 348.25 | U20: 374 | V20: 495.9 | W20: 659.9 | X20: 613.4 | Y20: 607.9 | Z20: 555.95 | AA20: 497.8 | AB20: 459.9 | AC20: 374 | AD20: 362 | AE20: 341.5 | AF20: 384.2 | AG20: 433.8 | AH20: 460 | AI20: 474.4 | AJ20: 414.4 | AK20: 318.7 | AL20: 303.25 | AM20: 332.7 | AN20: 295 | AO20: 247 | AP20: 214.4 | AQ20: 179.5 | AR20: 97.9 | AS20: 119.1 | AT20: 130.65 | AU20: 148.55 | AV20: 153.8 | AW20: 152.9 | AX20: 136 | AY20: 141.15 | AZ20: 128.1 | BA20: 142.5 | BB20: 143.55 | BC20: 124.5 | BD20: 241 | BE20: 450 | BF20: 503.35
J21: 186 | K21: 145.4 | L21: 169.1 | N21: 186.25 | O21: 135.5 | P21: 145.4 | Q21: 108.95 | R21: 137 | S21: 170 | T21: 243.15 | U21: 307.5 | V21: 325.1 | W21: 463 | X21: 467.05 | Y21: 436.5 | Z21: 467 | AA21: 348.2 | AB21: 325 | AC21: 313.1 | AD21: 285 | AE21: 277.85 | AF21: 327 | AG21: 317 | AH21: 370.7 | AI21: 360 | AJ21: 271.15 | AK21: 233.15 | AL21: 218.8 | AM21: 262 | AN21: 223.6 | AO21: 137.6 | AP21: 142 | AQ21: 59.3 | AR21: 58 | AS21: 72.8 | AT21: 80 | AU21: 107.25 | AV21: 106 | AW21: 125.1 | AX21: 112.25 | AY21: 81.45 | AZ21: 88 | BA21: 90.35 | BB21: 106.05 | BC21: 98.55 | BD21: 119.25 | BE21: 210 | BF21: 349
J22: 178.7 | K22: 108.95 | L22: 139.75 | N22: 186.75 | O22: 146.9 | P22: 169.1 | Q22: 139.75 | R22: 202.15 | S22: 249.05 | T22: 346.4 | U22: 349.2 | V22: 469.9 | W22: 584.8 | X22: 536.15 | Y22: 513.35 | Z22: 474 | AA22: 438.55 | AB22: 355.4 | AC22: 334.95 | AD22: 298.8 | AE22: 328.35 | AF22: 343 | AG22: 389.9 | AH22: 443.05 | AI22: 407.5 | AJ22: 290.1 | AK22: 235.75 | AL22: 292.65 | AM22: 276.1 | AN22: 237.05 | AO22: 190.1 | AP22: 147.2 | AQ22: 71.9 | AR22: 75.2 | AS22: 90.1 | AT22: 117.2 | AU22: 116.3 | AV22: 140.5 | AW22: 128.6 | AX22: 133.65 | AY22: 91.65 | AZ22: 97.65 | BA22: 125 | BB22: 115.35 | BC22: 119.25 | BD22: 219.3 | BE22: 442.65 | BF22: 503.35
J23: 207 | K23: 137 | L23: 202.15
J24: 255.15 | K24: 170 | L24: 249.05
J25: 348.25 | K25: 243.15 | L25: 346.4
J26: 374 | K26: 307.5 | L26: 349.2
J27: 495.9 | K27: 325.1 | L27: 469.9
J28: 659.9 | K28: 463 | L28: 584.8
J29: 613.4 | K29: 467.05 | L29: 536.15
J30: 607.9 | K30: 436.5 | L30: 513.35
J31: 555.95 | K31: 467 | L31: 474
J32: 497.8 | K32: 348.2 | L32: 438.55
J33: 459.9 | K33: 325 | L33: 355.4
J34: 374 | K34: 313.1 | L34: 334.95
... J63: 503.35 | K63: 349 | L63: 503.35
