Workbook

Sheet Template
A1: =+'Annual Raw'!C4 -> Voltas Ltd. | B1: 36951 | C1: =EOMONTH(B1,12) -> 37346 | D1: =EOMONTH(C1,12) -> 37711 | E1: =EOMONTH(D1,12) -> 38077 | F1: =EOMONTH(E1,12) -> 38442 | G1: =EOMONTH(F1,12) -> 38807 | H1: =EOMONTH(G1,12) -> 39172 | I1: =EOMONTH(H1,12) -> 39538 | J1: =EOMONTH(I1,12) -> 39903 | ... AE1: =EOMONTH(AD1,12) -> 47573 | AH1: QTR | AI1: 41061 | AJ1: 41153 | AK1: 41244 | AL1: 41334 | AM1: 41426 | AN1: 41518 | AO1: 41609 | AP1: 41699 | AQ1: 41791 | AR1: 41883 | AS1: 41974 | AT1: 42064 | AU1: 42156 | AV1: 42248 | AW1: 42339 | AX1: 42430 | AY1: 42522 | AZ1: 42614 | BA1: 42705 | BB1: 42795 | BC1: 42887 | BD1: 42979 | BE1: 43070 | BF1: 43160 | BG1: 43252 | BH1: 43344 | BI1: 43435 | BJ1: 43525 | BK1: 43617 | BL1: 43709 | BM1: 43800 | BN1: 43891 | BO1: 43983 | BP1: 44075 | BQ1: =EOMONTH(BP1,3) -> 44196 | BR1: =EOMONTH(BQ1,3) -> 44286 | BS1: =EOMONTH(BR1,3) -> 44377 | BT1: =EOMONTH(BS1,3) -> 44469 | BU1: =EOMONTH(BT1,3) -> 44561 | BV1: =EOMONTH(BU1,3) -> 44651 | BW1: =EOMONTH(BV1,3) -> 44742 | BX1: =EOMONTH(BW1,3) -> 44834 | ... DB1: =EOMONTH(DA1,3) -> 47573 | DE1: HISTORICAL ESTIMATES | DF1: 46112
A2: Presentation Data (Start)
A4: Revenue - Electro Mechanical Projects & Services | O4: =+SUM(AM4:AP4) -> 2692.42 | P4: =+SUM(AQ4:AT4) -> 2208.54 | Q4: =+SUM(AU4:AX4) -> 2717.15 | R4: =+SUM(AY4:BB4) -> 2655.03 | S4: =+SUM(BC4:BF4) -> 2845.21 | T4: =+SUM(BG4:BJ4) -> 3619.08 | U4: =+SUM(BK4:BN4) -> 3246.14 | V4: =+SUM(BO4:BR4) -> 3566.38 | W4: =+SUM(BS4:BV4) -> 2470.49 | X4: =+SUM(BW4:BZ4) -> 2402.91 | Y4: =+SUM(CA4:CD4) -> 3683.03 | Z4: =+SUM(CE4:CH4) -> 4156.79 | AA4: =+SUM(CI4:CL4) -> 2862.18 | AB4: =+SUM(CM4:CP4) -> 0 | AC4: =+SUM(CQ4:CT4) -> 0 | AD4: =+SUM(CU4:CX4) -> 0 | AE4: =+SUM(CY4:DB4) -> 0 | AL4: 883.35 | AM4: 692.95 | AN4: 670.88 | AO4: 642.91 | AP4: 685.68 | AQ4: 622.24 | AR4: 525.32 | AS4: 461.31 | AT4: 599.67 | AU4: 555.93 | AV4: 620.8 | AW4: 721.87 | AX4: 818.55 | AY4: 580.21 | AZ4: 543.24 | BA4: 702.58 | BB4: 829 | BC4: 660.83 | BD4: 557.47 | BE4: 753.37 | BF4: 873.54 | BG4: 866.37 | BH4: 901.48 | BI4: 875.23 | BJ4: 976 | BK4: 824.12 | BL4: 809.33 | BM4: 808.13 | BN4: 804.56 | BO4: 518.09 | BP4: 927.8 | BQ4: 1016.66 | BR4: 1103.83 | BS4: 688.42 | BT4: 536.48 | BU4: 553.78 | BV4: 691.81 | BW4: 454.69 | BX4: 554.04 | BY4: 648.39 | BZ4: 745.79 | CA4: 679.06 | CB4: 924.19 | CC4: 981.88 | CD4: 1097.9 | CE4: 949.13 | CF4: 879.91 | CG4: 1190.23 | CH4: 1137.52 | CI4: 921.83 | CJ4: 966.17 | CK4: 974.18
A5: Revenue - Engineering Product Services | O5: =+SUM(AM5:AP5) -> 448.22 | P5: =+SUM(AQ5:AT5) -> 360.06 | Q5: =+SUM(AU5:AX5) -> 370.19 | R5: =+SUM(AY5:BB5) -> 331.81 | S5: =+SUM(BC5:BF5) -> 309.93 | T5: =+SUM(BG5:BJ5) -> 311.65 | U5: =+SUM(BK5:BN5) -> 331.66 | V5: =+SUM(BO5:BR5) -> 359.49 | W5: =+SUM(BS5:BV5) -> 488.66 | X5: =+SUM(BW5:BZ5) -> 521.96 | Y5: =+SUM(CA5:CD5) -> 587.91 | Z5: =+SUM(CE5:CH5) -> 568.25 | AA5: =+SUM(CI5:CL5) -> 431.06 | AB5: =+SUM(CM5:CP5) -> 0 | AC5: =+SUM(CQ5:CT5) -> 0 | AD5: =+SUM(CU5:CX5) -> 0 | AE5: =+SUM(CY5:DB5) -> 0 | AL5: 103.9 | AM5: 111.17 | AN5: 126.46 | AO5: 111.83 | AP5: 98.76 | AQ5: 110.89 | AR5: 87.17 | AS5: 80.95 | AT5: 81.05 | AU5: 70 | AV5: 96.12 | AW5: 111.41 | AX5: 92.66 | AY5: 69.14 | AZ5: 75.1 | BA5: 80.74 | BB5: 106.83 | BC5: 90.35 | BD5: 66.62 | BE5: 69.52 | BF5: 83.44 | BG5: 77.16 | BH5: 72.86 | BI5: 83.16 | BJ5: 78.47 | BK5: 73.96 | BL5: 80.3 | BM5: 82.6 | BN5: 94.8 | BO5: 47.61 | BP5: 93.29 | BQ5: 120.91 | BR5: 97.68 | BS5: 115.06 | BT5: 125.42 | BU5: 124.68 | BV5: 123.5 | BW5: 124.33 | BX5: 137.37 | BY5: 117.91 | BZ5: 142.35 | CA5: 142.31 | CB5: 134.44 | CC5: 154.8 | CD5: 156.36 | CE5: 160.78 | CF5: 145.71 | CG5: 129.67 | CH5: 132.09 | CI5: 135.44 | CJ5: 139.05 | CK5: 156.57
A6: Revenue - Unitary Cooling Products | O6: =+SUM(AM6:AP6) -> 2052.42 | P6: =+SUM(AQ6:AT6) -> 2510.49 | Q6: =+SUM(AU6:AX6) -> 2556.63 | R6: =+SUM(AY6:BB6) -> 3046.86 | S6: =+SUM(BC6:BF6) -> 3226.09 | T6: =+SUM(BG6:BJ6) -> 3155.56 | U6: =+SUM(BK6:BN6) -> 4073.7 | V6: =+SUM(BO6:BR6) -> 3555.04 | W6: =+SUM(BS6:BV6) -> 4881.92 | X6: =+SUM(BW6:BZ6) -> 6474.5 | Y6: =+SUM(CA6:CD6) -> 8153.5 | Z6: =+SUM(CE6:CH6) -> 10613.92 | AA6: =+SUM(CI6:CL6) -> 6007.19 | AB6: =+SUM(CM6:CP6) -> 0 | AC6: =+SUM(CQ6:CT6) -> 0 | AD6: =+SUM(CU6:CX6) -> 0 | AE6: =+SUM(CY6:DB6) -> 0 | AL6: 585.51 | AM6: 786.74 | AN6: 264.31 | AO6: 347.04 | AP6: 654.33 | AQ6: 1001.38 | AR6: 344.87 | AS6: 383.51 | AT6: 780.73 | AU6: 948.95 | AV6: 314.1 | AW6: 434.53 | AX6: 859.05 | AY6: 1195.62 | AZ6: 354.16 | BA6: 411.07 | BB6: 1086.01 | BC6: 1211.66 | BD6: 407.77 | BE6: 542.17 | BF6: 1064.49 | BG6: 1191.06 | BH6: 441.01 | BI6: 525.92 | BJ6: 997.57 | BK6: 1748.78 | BL6: 525.55 | BM6: 600.51 | BN6: 1198.86 | BO6: 707.11 | BP6: 571.65 | BQ6: 839.61 | BR6: 1436.67 | BS6: 963.11 | BT6: 1006.8 | BU6: 1093.6 | BV6: 1818.41 | BW6: 2162.2 | BX6: 1047.71 | BY6: 1215.97 | BZ6: 2048.62 | CA6: 2513.97 | CB6: 1208.8 | CC6: 1475.61 | CD6: 2955.12 | CE6: 3802.17 | CF6: 1582.19 | CG6: 1771.13 | CH6: 3458.43 | CI6: 2867.86 | CJ6: 1215.13 | CK6: 1924.2
A7: Revenue - Others | O7: =+SUM(AM7:AP7) -> 52.04 | P7: =+SUM(AQ7:AT7) -> 66.12 | Q7: =+SUM(AU7:AX7) -> 188.45 | R7: =+SUM(AY7:BB7) -> 0 | S7: =+SUM(BC7:BF7) -> 0 | T7: =+SUM(BG7:BJ7) -> 0 | U7: =+SUM(BK7:BN7) -> 0 | V7: =+SUM(BO7:BR7) -> 0 | W7: =+SUM(BS7:BV7) -> 0 | X7: =+SUM(BW7:BZ7) -> 0 | Y7: =+SUM(CA7:CD7) -> 0 | Z7: =+SUM(CE7:CH7) -> 0 | AA7: =+SUM(CI7:CL7) -> 0 | AB7: =+SUM(CM7:CP7) -> 0 | AC7: =+SUM(CQ7:CT7) -> 0 | AD7: =+SUM(CU7:CX7) -> 0 | AE7: =+SUM(CY7:DB7) -> 0 | AL7: 19.82 | AM7: 11.16 | AN7: 15.05 | AO7: 13.36 | AP7: 12.47 | AQ7: 18.11 | AR7: 11.68 | AS7: 13.39 | AT7: 22.94 | AU7: 20.53 | AV7: 28.88 | AW7: 33.44 | AX7: 105.6
A8: Revenue - Other operating income | O8: =+SUM(AM8:AP8) -> 22.38 | P8: =+SUM(AQ8:AT8) -> 38.8 | Q8: =+SUM(AU8:AX8) -> 26.84 | R8: =+SUM(AY8:BB8) -> 62.24 | S8: =+SUM(BC8:BF8) -> 47.59 | T8: =+SUM(BG8:BJ8) -> 39.48 | U8: =+SUM(BK8:BN8) -> 30.93 | V8: =+SUM(BO8:BR8) -> 99.23 | W8: =+SUM(BS8:BV8) -> 93.38 | X8: =+SUM(BW8:BZ8) -> 99.4 | Y8: =+SUM(CA8:CD8) -> 73.85 | Z8: =+SUM(CE8:CH8) -> 92.34 | AA8: =+SUM(CI8:CL8) -> 77.21 | AB8: =+SUM(CM8:CP8) -> 0 | AC8: =+SUM(CQ8:CT8) -> 0 | AD8: =+SUM(CU8:CX8) -> 0 | AE8: =+SUM(CY8:DB8) -> 0 | AL8: 4.89 | AM8: 1.52 | AN8: 4 | AO8: 4.41 | AP8: 12.45 | AQ8: 5.03 | AR8: 15.73 | AS8: 12.16 | AT8: 5.88 | AU8: 3.1 | AV8: 3.02 | AW8: 6.77 | AX8: 13.95 | AY8: 10.37 | AZ8: 9.17 | BA8: 5.95 | BB8: 36.75 | BC8: 5.74 | BD8: 5.05 | BE8: 9.72 | BF8: 27.08 | BG8: 13.68 | BH8: 6.66 | BI8: 7.93 | BJ8: 11.21 | BK8: 7.33 | BL8: 6.92 | BM8: 5.44 | BN8: 11.24 | BO8: 26.18 | BP8: 24.99 | BQ8: 24.24 | BR8: 23.82 | BS8: 18.61 | BT8: 20.38 | BU8: 21.53 | BV8: 32.86 | BW8: 26.78 | BX8: 29.24 | BY8: 23.34 | BZ8: 20.04 | CA8: 24.52 | CB8: 25.32 | CC8: 13.43 | CD8: 10.58 | CE8: 17.11 | CF8: 17.96 | CG8: 17.75 | CH8: 39.52 | CI8: 26.29 | CJ8: 32.92 | CK8: 18
A9: Less: Inter-segment Revenue | O9: =+SUM(AM9:AP9) -> 1.44 | P9: =+SUM(AQ9:AT9) -> 0.92 | Q9: =+SUM(AU9:AX9) -> 112.6 | R9: =+SUM(AY9:BB9) -> 0.92 | S9: =+SUM(BC9:BF9) -> 0.95 | T9: =+SUM(BG9:BJ9) -> 1.7 | U9: =+SUM(BK9:BN9) -> 24.35 | V9: =+SUM(BO9:BR9) -> 24.36 | W9: =+SUM(BS9:BV9) -> 0 | X9: =+SUM(BW9:BZ9) -> 0 | Y9: =+SUM(CA9:CD9) -> 17.08 | Z9: =+SUM(CE9:CH9) -> 19.5 | AA9: =+SUM(CI9:CL9) -> 20.98 | AB9: =+SUM(CM9:CP9) -> 0 | AC9: =+SUM(CQ9:CT9) -> 0 | AD9: =+SUM(CU9:CX9) -> 0 | AE9: =+SUM(CY9:DB9) -> 0 | AL9: 0.36 | AM9: 0.24 | AN9: 0.17 | AO9: 0.15 | AP9: 0.88 | AQ9: 0.31 | AR9: 0.12 | AS9: 0.19 | AT9: 0.3 | AU9: 34.24 | AV9: 16.24 | AW9: 35.67 | AX9: 26.45 | AY9: 0.16 | AZ9: 0.21 | BA9: 0.22 | BB9: 0.33 | BC9: 0.47 | BD9: 0.2 | BE9: 0.11 | BF9: 0.17 | BG9: 0.18 | BH9: 0.65 | BI9: 0.46 | BJ9: 0.41 | BK9: 0.19 | BL9: 0.16 | BM9: 4.17 | BN9: 19.83 | BO9: 2.05 | BP9: 5.19 | BQ9: 6.78 | BR9: 10.34 | BS9: 0 | BT9: 0 | BU9: 0 | BV9: 0 | BW9: 0 | BX9: 0 | BY9: 0 | BZ9: 0 | CA9: 0 | CB9: 0 | CC9: 0 | CD9: 17.08 | CE9: 8.17 | CF9: 7.66 | CG9: 3.67 | CI9: 12.84 | CJ9: 5.96 | CK9: 2.18
A10: Net Revenue | O10: =+SUM(O4:O8)-O9 -> 5266.04 | P10: =+SUM(P4:P8)-P9 -> 5183.09 | Q10: =+SUM(Q4:Q8)-Q9 -> 5746.66 | R10: =+SUM(R4:R8)-R9 -> 6095.02 | S10: =+SUM(S4:S8)-S9 -> 6427.87 | T10: =+SUM(T4:T8)-T9 -> 7124.07 | U10: =+SUM(U4:U8)-U9 -> 7658.08 | V10: =+SUM(V4:V8)-V9 -> 7555.78 | ... AE10: =+SUM(AE4:AE8)-AE9 -> 0 | AL10: =+SUM(AL4:AL8)-AL9 -> 1597.11 | AM10: =+SUM(AM4:AM8)-AM9 -> 1603.3 | AN10: =+SUM(AN4:AN8)-AN9 -> 1080.53 | AO10: =+SUM(AO4:AO8)-AO9 -> 1119.4 | AP10: =+SUM(AP4:AP8)-AP9 -> 1462.81 | AQ10: =+SUM(AQ4:AQ8)-AQ9 -> 1757.34 | AR10: =+SUM(AR4:AR8)-AR9 -> 984.65 | AS10: =+SUM(AS4:AS8)-AS9 -> 951.13 | ... CK10: =+SUM(CK4:CK8)-CK9 -> 3070.77
O11: =+O10-O24 -> -36.8148 | P11: =+P10-P24 -> -21.7067 | Q11: =+Q10-Q24 -> 0.0071 | R11: =+R10-R24 -> 0 | S11: =+S10-S24 -> 0 | T11: =+T10-T24 -> 0 | U11: =+U10-U24 -> 0 | V11: =+V10-V24 -> 0 | ... Z11: =+Z10-Z24 -> -0.99 | AL11: =+AL10-AL24 -> 0 | AM11: =+AM10-AM24 -> 0 | AN11: =+AN10-AN24 -> 0 | AO11: =+AO10-AO24 -> 0 | AP11: =+AP10-AP24 -> 0 | AQ11: =+AQ10-AQ24 -> 0 | AR11: =+AR10-AR24 -> 0 | AS11: =+AS10-AS24 -> 0 | ... CK11: =+CK10-CK24 -> 0
A13: Revenue YoY% - Electro Mechanical Projects & Services | P13: =+P4/O4-1 -> -0.17971936 | Q13: =+Q4/P4-1 -> 0.23029241 | R13: =+R4/Q4-1 -> -0.02286219 | S13: =+S4/R4-1 -> 0.071630076 | T13: =+T4/S4-1 -> 0.27199047 | U13: =+U4/T4-1 -> -0.10304829 | V13: =+V4/U4-1 -> 0.098652553 | W13: =+W4/V4-1 -> -0.30728358 | ... AE13: =+AE4/AD4-1 -> #DIV/0! | AP13: =+AP4/AL4-1 -> -0.22377314 | AQ13: =+AQ4/AM4-1 -> -0.10204199 | AR13: =+AR4/AN4-1 -> -0.21696876 | AS13: =+AS4/AO4-1 -> -0.28246566 | AT13: =+AT4/AP4-1 -> -0.12543752 | AU13: =+AU4/AQ4-1 -> -0.1065666 | AV13: =+AV4/AR4-1 -> 0.18175588 | AW13: =+AW4/AS4-1 -> 0.56482626 | ... CK13: =+CK4/CG4-1 -> -0.18151954
A14: Revenue YoY% - Engineering Product Services | P14: =+P5/O5-1 -> -0.19668913 | Q14: =+Q5/P5-1 -> 0.0281342 | R14: =+R5/Q5-1 -> -0.10367649 | S14: =+S5/R5-1 -> -0.065941352 | T14: =+T5/S5-1 -> 0.0055496402 | U14: =+U5/T5-1 -> 0.064206642 | V14: =+V5/U5-1 -> 0.083911234 | W14: =+W5/V5-1 -> 0.35931458 | ... AE14: =+AE5/AD5-1 -> #DIV/0! | AP14: =+AP5/AL5-1 -> -0.049470645 | AQ14: =+AQ5/AM5-1 -> -0.0025186651 | AR14: =+AR5/AN5-1 -> -0.31069113 | AS14: =+AS5/AO5-1 -> -0.27613342 | AT14: =+AT5/AP5-1 -> -0.17932361 | AU14: =+AU5/AQ5-1 -> -0.3687438 | AV14: =+AV5/AR5-1 -> 0.10267294 | AW14: =+AW5/AS5-1 -> 0.37628166 | ... CK14: =+CK5/CG5-1 -> 0.20744968
A15: Revenue YoY% - Unitary Cooling Products | P15: =+P6/O6-1 -> 0.22318531 | Q15: =+Q6/P6-1 -> 0.018378882 | R15: =+R6/Q6-1 -> 0.19174851 | S15: =+S6/R6-1 -> 0.058824495 | T15: =+T6/S6-1 -> -0.021862378 | U15: =+U6/T6-1 -> 0.29095945 | V15: =+V6/U6-1 -> -0.12731914 | W15: =+W6/V6-1 -> 0.37323912 | ... AE15: =+AE6/AD6-1 -> #DIV/0! | AP15: =+AP6/AL6-1 -> 0.11753856 | AQ15: =+AQ6/AM6-1 -> 0.27282203 | AR15: =+AR6/AN6-1 -> 0.30479361 | AS15: =+AS6/AO6-1 -> 0.10508875 | AT15: =+AT6/AP6-1 -> 0.1931747 | AU15: =+AU6/AQ6-1 -> -0.052357746 | AV15: =+AV6/AR6-1 -> -0.089222026 | AW15: =+AW6/AS6-1 -> 0.13303434 | ... CK15: =+CK6/CG6-1 -> 0.086425051
A16: Revenue YoY% - Others | P16: =+P7/O7-1 -> 0.27056111 | Q16: =+Q7/P7-1 -> 1.850121 | R16: =+R7/Q7-1 -> -1 | AP16: =+AP7/AL7-1 -> -0.37083754 | AQ16: =+AQ7/AM7-1 -> 0.62275986 | AR16: =+AR7/AN7-1 -> -0.22392027 | AS16: =+AS7/AO7-1 -> 0.002245509 | AT16: =+AT7/AP7-1 -> 0.83961508 | AU16: =+AU7/AQ7-1 -> 0.13362783 | AV16: =+AV7/AR7-1 -> 1.4726027 | AW16: =+AW7/AS7-1 -> 1.4973861 | ... BB16: =+BB7/AX7-1 -> -1
A17: Revenue YoY% - Other operating income | P17: =+P8/O8-1 -> 0.7336908 | Q17: =+Q8/P8-1 -> -0.30824742 | R17: =+R8/Q8-1 -> 1.318927 | S17: =+S8/R8-1 -> -0.23537918 | T17: =+T8/S8-1 -> -0.17041395 | U17: =+U8/T8-1 -> -0.21656535 | V17: =+V8/U8-1 -> 2.2082121 | W17: =+W8/V8-1 -> -0.058953945 | ... AE17: =+AE8/AD8-1 -> #DIV/0! | AP17: =+AP8/AL8-1 -> 1.5460123 | AQ17: =+AQ8/AM8-1 -> 2.3092105 | AR17: =+AR8/AN8-1 -> 2.9325 | AS17: =+AS8/AO8-1 -> 1.7573696 | AT17: =+AT8/AP8-1 -> -0.52771084 | AU17: =+AU8/AQ8-1 -> -0.38369781 | AV17: =+AV8/AR8-1 -> -0.80801017 | AW17: =+AW8/AS8-1 -> -0.44325658 | ... CK17: =+CK8/CG8-1 -> 0.014084507
A18: Inter-segment Revenue YoY% | P18: =+P9/O9-1 -> -0.36111111 | Q18: =+Q9/P9-1 -> 121.3913 | R18: =+R9/Q9-1 -> -0.99182948 | S18: =+S9/R9-1 -> 0.032608696 | T18: =+T9/S9-1 -> 0.78947368 | U18: =+U9/T9-1 -> 13.323529 | V18: =+V9/U9-1 -> 0.00041067762 | W18: =+W9/V9-1 -> -1 | ... AE18: =+AE9/AD9-1 -> #DIV/0! | AP18: =+AP9/AL9-1 -> 1.4444444 | AQ18: =+AQ9/AM9-1 -> 0.29166667 | AR18: =+AR9/AN9-1 -> -0.29411765 | AS18: =+AS9/AO9-1 -> 0.26666667 | AT18: =+AT9/AP9-1 -> -0.65909091 | AU18: =+AU9/AQ9-1 -> 109.45161 | AV18: =+AV9/AR9-1 -> 134.33333 | AW18: =+AW9/AS9-1 -> 186.73684 | ... BV18: =+BV9/BR9-1 -> -1 | CH18: =+CH9/CD9-1 -> -1 | CI18: =+CI9/CE9-1 -> 0.57160343 | CJ18: =+CJ9/CF9-1 -> -0.22193211 | CK18: =+CK9/CG9-1 -> -0.40599455
A19: Net Revenue YoY% | P19: =+P10/O10-1 -> -0.015751874 | Q19: =+Q10/P10-1 -> 0.10873244 | R19: =+R10/Q10-1 -> 0.06061956 | S19: =+S10/R10-1 -> 0.054610157 | T19: =+T10/S10-1 -> 0.1083096 | U19: =+U10/T10-1 -> 0.074958556 | V19: =+V10/U10-1 -> -0.01335844 | W19: =+W10/V10-1 -> 0.050116599 | ... AE19: =+AE10/AD10-1 -> #DIV/0! | AP19: =+AP10/AL10-1 -> -0.084089386 | AQ19: =+AQ10/AM10-1 -> 0.096076842 | AR19: =+AR10/AN10-1 -> -0.088734232 | AS19: =+AS10/AO10-1 -> -0.1503216 | AT19: =+AT10/AP10-1 -> 0.018567005 | AU19: =+AU10/AQ10-1 -> -0.10986491 | AV19: =+AV10/AR10-1 -> 0.062997004 | AW19: =+AW10/AS10-1 -> 0.3377246 | ... CK19: =+CK10/CG10-1 -> -0.01105919
A22: Presentation Data (End)
A23: Profit & Loss- Annual (Start)
A24: Gross Revenue | B24: ='Annual Raw'!C6 -> 853.7166 | C24: ='Annual Raw'!D6 -> 956.7624 | D24: ='Annual Raw'!E6 -> 1342.1175 | E24: ='Annual Raw'!F6 -> 1437.5206 | F24: ='Annual Raw'!G6 -> 1550.7879 | G24: ='Annual Raw'!H6 -> 2022.7089 | H24: ='Annual Raw'!I6 -> 2598.301 | I24: ='Annual Raw'!J6 -> 3264.3878 | ... AA24: ='Annual Raw'!AB6 -> 14244.5 | AB24: =+SUM(CM24:CP24) -> 17093.4 | AC24: =+SUM(CQ24:CT24) -> 19657.41 | AD24: =+SUM(CU24:CX24) -> 22606.021 | AE24: =+SUM(CY24:DB24) -> 25996.925 | AI24: ='QTR Raw'!C6+'QTR Raw'!C8 -> 1616.82 | AJ24: ='QTR Raw'!D6+'QTR Raw'!D8 -> 1164.49 | AK24: ='QTR Raw'!E6+'QTR Raw'!E8 -> 1152.54 | AL24: ='QTR Raw'!F6+'QTR Raw'!F8 -> 1597.11 | AM24: ='QTR Raw'!G6+'QTR Raw'!G8 -> 1603.3 | AN24: ='QTR Raw'!H6+'QTR Raw'!H8 -> 1080.53 | AO24: ='QTR Raw'!I6+'QTR Raw'!I8 -> 1119.4 | AP24: ='QTR Raw'!J6+'QTR Raw'!J8 -> 1462.81 | ... CL24: ='QTR Raw'!BF6+'QTR Raw'!BF8 -> 4887.83 | CM24: =+CI26+(CM27*CI26) -> 4726.296 | CN24: =+CJ26+(CN27*CJ26) -> 2816.784 | CO24: =+CK26+(CO27*CK26) -> 3684.924 | CP24: =+CL26+(CP27*CL26) -> 5865.396 | CQ24: =+CM26+(CQ27*CM26) -> 5435.2404 | CR24: =+CN26+(CR27*CN26) -> 3239.3016 | CS24: =+CO26+(CS27*CO26) -> 4237.6626 | CT24: =+CP26+(CT27*CP26) -> 6745.2054 | ... DB24: =+CX26+(DB27*CX26) -> 8920.5341 | DF24: 5268.1538
A25: Less: Exise Duty | B25: ='Annual Raw'!C7+'Annual Raw'!C8+'Annual Raw'!C9 -> 89.1636 | C25: ='Annual Raw'!D7+'Annual Raw'!D8+'Annual Raw'!D9 -> 75.602 | D25: ='Annual Raw'!E7+'Annual Raw'!E8+'Annual Raw'!E9 -> 86.575 | E25: ='Annual Raw'!F7+'Annual Raw'!F8+'Annual Raw'!F9 -> 77.567 | F25: ='Annual Raw'!G7+'Annual Raw'!G8+'Annual Raw'!G9 -> 73.7203 | G25: ='Annual Raw'!H7+'Annual Raw'!H8+'Annual Raw'!H9 -> 68.2717 | H25: ='Annual Raw'!I7+'Annual Raw'!I8+'Annual Raw'!I9 -> 71.564 | I25: ='Annual Raw'!J7+'Annual Raw'!J8+'Annual Raw'!J9 -> 61.4611 | ... AA25: ='Annual Raw'!AB7+'Annual Raw'!AB8+'Annual Raw'!AB9 -> 0 | AB25: =+SUM(CM25:CP25) -> 0 | AC25: =+SUM(CQ25:CT25) -> 0 | AD25: =+SUM(CU25:CX25) -> 0 | AE25: =+SUM(CY25:DB25) -> 0 | AI25: =+'QTR Raw'!C20+'QTR Raw'!C19+'QTR Raw'!C13+'QTR Raw'!C7 -> 0 | AJ25: =+'QTR Raw'!D20+'QTR Raw'!D19+'QTR Raw'!D13+'QTR Raw'!D7 -> 0 | AK25: =+'QTR Raw'!E20+'QTR Raw'!E19+'QTR Raw'!E13+'QTR Raw'!E7 -> 0 | AL25: =+'QTR Raw'!F20+'QTR Raw'!F19+'QTR Raw'!F13+'QTR Raw'!F7 -> 0 | AM25: =+'QTR Raw'!G20+'QTR Raw'!G19+'QTR Raw'!G13+'QTR Raw'!G7 -> 0 | AN25: =+'QTR Raw'!H20+'QTR Raw'!H19+'QTR Raw'!H13+'QTR Raw'!H7 -> 0 | AO25: =+'QTR Raw'!I20+'QTR Raw'!I19+'QTR Raw'!I13+'QTR Raw'!I7 -> 0 | AP25: =+'QTR Raw'!J20+'QTR Raw'!J19+'QTR Raw'!J13+'QTR Raw'!J7 -> 0 | ... CL25: =+'QTR Raw'!BF20+'QTR Raw'!BF19+'QTR Raw'!BF13+'QTR Raw'!BF7 -> 0 | DF25: 0
A26: Net Revenue | B26: =+B24-B25 -> 764.553 | C26: =+C24-C25 -> 881.1604 | D26: =+D24-D25 -> 1255.5425 | E26: =+E24-E25 -> 1359.9536 | F26: =+F24-F25 -> 1477.0676 | G26: =+G24-G25 -> 1954.4372 | H26: =+H24-H25 -> 2526.737 | I26: =+I24-I25 -> 3202.9267 | ... AE26: =+AE24-AE25 -> 25996.925 | AI26: =+AI24-AI25 -> 1616.82 | AJ26: =+AJ24-AJ25 -> 1164.49 | AK26: =+AK24-AK25 -> 1152.54 | AL26: =+AL24-AL25 -> 1597.11 | AM26: =+AM24-AM25 -> 1603.3 | AN26: =+AN24-AN25 -> 1080.53 | AO26: =+AO24-AO25 -> 1119.4 | AP26: =+AP24-AP25 -> 1462.81 | ... DB26: =+DB24-DB25 -> 8920.5341 | DF26: 5268.1538
A27: Net Revenue YOY% | C27: =C26/B26-1 -> 0.15251709 | D27: =D26/C26-1 -> 0.42487395 | E27: =E26/D26-1 -> 0.083160148 | F27: =F26/E26-1 -> 0.086116173 | G27: =G26/F26-1 -> 0.32318737 | H27: =H26/G26-1 -> 0.29282077 | I27: =I26/H26-1 -> 0.2676138 | J27: =J26/I26-1 -> 0.35060781 | ... AE27: =AE26/AD26-1 -> 0.15 | AM27: =+IF(AI26<0,1-AM26/AI26,AM26/AI26-1) -> -0.0083620935 | AN27: =+IF(AJ26<0,1-AN26/AJ26,AN26/AJ26-1) -> -0.072100233 | AO27: =+IF(AK26<0,1-AO26/AK26,AO26/AK26-1) -> -0.028753883 | AP27: =+IF(AL26<0,1-AP26/AL26,AP26/AL26-1) -> -0.084089386 | AQ27: =+IF(AM26<0,1-AQ26/AM26,AQ26/AM26-1) -> 0.096076842 | AR27: =+IF(AN26<0,1-AR26/AN26,AR26/AN26-1) -> -0.088734232 | AS27: =+IF(AO26<0,1-AS26/AO26,AS26/AO26-1) -> -0.1503216 | AT27: =+IF(AP26<0,1-AT26/AP26,AT26/AP26-1) -> 0.018567005 | ... CL27: =+IF(CH26<0,1-CL26/CH26,CL26/CH26-1) -> 0.025226741 | CM27: 0.2 | CN27: 0.2 | CO27: 0.2 | CP27: 0.2 | CQ27: 0.15 | CR27: 0.15 | CS27: 0.15 | CT27: 0.15 | CU27: =+AVERAGE(CQ27:CT27) -> 0.15 | CV27: =+AVERAGE(CR27:CU27) -> 0.15 | CW27: =+AVERAGE(CS27:CV27) -> 0.15 | CX27: =+AVERAGE(CT27:CW27) -> 0.15 | CY27: =+AVERAGE(CU27:CX27) -> 0.15 | CZ27: =+AVERAGE(CV27:CY27) -> 0.15 | DA27: =+AVERAGE(CW27:CZ27) -> 0.15 | DB27: =+AVERAGE(CX27:DA27) -> 0.15 | DF27: 0.105
A28: Net Revenue QOQ% | AJ28: =+IF(AI26<0,1-AJ26/AI26,AJ26/AI26-1) -> -0.27976522 | AK28: =+IF(AJ26<0,1-AK26/AJ26,AK26/AJ26-1) -> -0.010262003 | AL28: =+IF(AK26<0,1-AL26/AK26,AL26/AK26-1) -> 0.38573065 | AM28: =+IF(AL26<0,1-AM26/AL26,AM26/AL26-1) -> 0.0038757506 | AN28: =+IF(AM26<0,1-AN26/AM26,AN26/AM26-1) -> -0.32605875 | AO28: =+IF(AN26<0,1-AO26/AN26,AO26/AN26-1) -> 0.035973087 | AP28: =+IF(AO26<0,1-AP26/AO26,AP26/AO26-1) -> 0.30678042 | AQ28: =+IF(AP26<0,1-AQ26/AP26,AQ26/AP26-1) -> 0.20134536 | ... CL28: =+IF(CK26<0,1-CL26/CK26,CL26/CK26-1) -> 0.59172781 | CM28: =+CM26/CL26-1 -> -0.033048203 | CN28: =+CN26/CM26-1 -> -0.40401871 | CO28: =+CO26/CN26-1 -> 0.30820255 | CP28: =+CP26/CO26-1 -> 0.59172781 | CQ28: =+CQ26/CP26-1 -> -0.073337862 | CR28: =+CR26/CQ26-1 -> -0.40401871 | CS28: =+CS26/CR26-1 -> 0.30820255 | CT28: =+CT26/CS26-1 -> 0.59172781 | ... DB28: =+DB26/DA26-1 -> 0.59172781 | DF28: 0.71558072
A29: Increase/Decrease in Stock | B29: ='Annual Raw'!C11 -> 29.476 | C29: ='Annual Raw'!D11 -> 65.8875 | D29: ='Annual Raw'!E11 -> 40.0038 | E29: ='Annual Raw'!F11 -> 10.4407 | F29: ='Annual Raw'!G11 -> -346.5813 | G29: ='Annual Raw'!H11 -> -608.1094 | H29: ='Annual Raw'!I11 -> 0 | I29: ='Annual Raw'!J11 -> 0 | ... AA29: ='Annual Raw'!AB11 -> -269.75 | AB29: =+SUM(CM29:CP29) -> 0 | AC29: =+SUM(CQ29:CT29) -> 0 | AD29: =+SUM(CU29:CX29) -> 0 | AE29: =+SUM(CY29:DB29) -> 0 | AI29: ='QTR Raw'!C10 -> 37.85 | AJ29: ='QTR Raw'!D10 -> -21.29 | AK29: ='QTR Raw'!E10 -> -67.99 | AL29: ='QTR Raw'!F10 -> -84.79 | AM29: ='QTR Raw'!G10 -> 192.03 | AN29: ='QTR Raw'!H10 -> -63.66 | AO29: ='QTR Raw'!I10 -> -82.12 | AP29: ='QTR Raw'!J10 -> 71.7 | ... CL29: ='QTR Raw'!BF10 -> 88.31 | DF29: -269.75
A30: Purchase of Finished Goods | B30: 0 | C30: 0 | D30: 0 | E30: 0 | F30: 0 | G30: 0 | H30: 0 | I30: 0 | J30: 0 | K30: 0 | L30: 0 | M30: 0 | N30: 0 | O30: 0 | P30: 0 | Q30: 0 | R30: 0 | S30: 0 | T30: 0 | U30: 0 | V30: 0 | W30: 0 | X30: 0 | Y30: 0 | Z30: 0 | AA30: 0 | AB30: =+SUM(CM30:CP30) -> 0 | AC30: =+SUM(CQ30:CT30) -> 0 | AD30: =+SUM(CU30:CX30) -> 0 | AE30: =+SUM(CY30:DB30) -> 0 | AI30: ='QTR Raw'!C12 -> 176.4 | AJ30: ='QTR Raw'!D12 -> 89.98 | AK30: ='QTR Raw'!E12 -> 101.68 | AL30: ='QTR Raw'!F12 -> 218.44 | AM30: ='QTR Raw'!G12 -> 131.3 | AN30: ='QTR Raw'!H12 -> 161.37 | AO30: ='QTR Raw'!I12 -> 175.73 | AP30: ='QTR Raw'!J12 -> 104.81 | ... CL30: ='QTR Raw'!BF12 -> 1158.04 | DF30: 3083.26
A31: Raw Material Consumed | B31: ='Annual Raw'!C12 -> 632.75 | C31: ='Annual Raw'!D12 -> 612.7476 | D31: ='Annual Raw'!E12 -> 974.4928 | E31: ='Annual Raw'!F12 -> 991.7907 | F31: ='Annual Raw'!G12 -> 1434.6836 | G31: ='Annual Raw'!H12 -> 2065.1993 | H31: ='Annual Raw'!I12 -> 1878.1579 | I31: ='Annual Raw'!J12 -> 2338.4082 | ... AA31: ='Annual Raw'!AB12 -> 11339.53 | AB31: =+SUM(CM31:CP31) -> 12949.998 | AC31: =+SUM(CQ31:CT31) -> 14878.298 | AD31: =+SUM(CU31:CX31) -> 17107.062 | AE31: =+SUM(CY31:DB31) -> 19672.536 | AI31: ='QTR Raw'!C11 -> 990.66 | AJ31: ='QTR Raw'!D11 -> 779.77 | AK31: ='QTR Raw'!E11 -> 847.57 | AL31: ='QTR Raw'!F11 -> 1098.75 | AM31: ='QTR Raw'!G11 -> 900.11 | AN31: ='QTR Raw'!H11 -> 673.43 | AO31: ='QTR Raw'!I11 -> 679.11 | AP31: ='QTR Raw'!J11 -> 910.44 | ... CL31: ='QTR Raw'!BF11 -> 2635.2 | CM31: =+CM26-CM32 -> 3598.6735 | CN31: =+CN26-CN32 -> 2129.5928 | CO31: =+CO26-CO32 -> 2790.1422 | CP31: =+CP26-CP32 -> 4431.5896 | CQ31: =+CQ26-CQ32 -> 4117.4365 | CR31: =+CR26-CR32 -> 2450.7806 | CS31: =+CS26-CS32 -> 3206.6894 | CT31: =+CT26-CT32 -> 5103.3911 | ... DB31: =+DB26-DB32 -> 6750.363 | DF31: 3999.4552
A32: Gross Profit | B32: =B26-B29-B31-B30 -> 102.327 | C32: =C26-C29-C31-C30 -> 202.5253 | D32: =D26-D29-D31-D30 -> 241.0459 | E32: =E26-E29-E31-E30 -> 357.7222 | F32: =F26-F29-F31-F30 -> 388.9653 | G32: =G26-G29-G31-G30 -> 497.3473 | H32: =H26-H29-H31-H30 -> 648.5791 | I32: =I26-I29-I31-I30 -> 864.5185 | ... AE32: =AE26-AE29-AE31-AE30 -> 6324.3886 | AI32: =AI26-AI29-AI31-AI30 -> 411.91 | AJ32: =AJ26-AJ29-AJ31-AJ30 -> 316.03 | AK32: =AK26-AK29-AK31-AK30 -> 271.28 | AL32: =AL26-AL29-AL31-AL30 -> 364.71 | AM32: =AM26-AM29-AM31-AM30 -> 379.86 | AN32: =AN26-AN29-AN31-AN30 -> 309.39 | AO32: =AO26-AO29-AO31-AO30 -> 346.68 | AP32: =AP26-AP29-AP31-AP30 -> 375.86 | ... CL32: =CL26-CL29-CL31-CL30 -> 1006.28 | CM32: =+CM33*CM26 -> 1127.6225 | CN32: =+CN33*CN26 -> 687.19122 | CO32: =+CO33*CO26 -> 894.78178 | CP32: =+CP33*CP26 -> 1433.8064 | CQ32: =+CQ33*CQ26 -> 1317.8039 | CR32: =+CR33*CR26 -> 788.52101 | CS32: =+CS33*CS26 -> 1030.9732 | CT32: =+CT33*CT26 -> 1641.8143 | ... DB32: =+DB33*DB26 -> 2170.1711 | DF32: 1268.6986
A33: GP% | B33: =B32/B26 -> 0.13383899 | C33: =C32/C26 -> 0.22983931 | D33: =D32/D26 -> 0.19198546 | E33: =E32/E26 -> 0.26304 | F33: =F32/F26 -> 0.26333615 | G33: =G32/G26 -> 0.25447085 | H33: =H32/H26 -> 0.25668643 | I33: =I32/I26 -> 0.26991517 | ... AE33: =AE32/AE26 -> 0.24327449 | AI33: =AI32/AI26 -> 0.25476553 | AJ33: =AJ32/AJ26 -> 0.27138919 | AK33: =AK32/AK26 -> 0.23537578 | AL33: =AL32/AL26 -> 0.22835622 | AM33: =AM32/AM26 -> 0.23692384 | AN33: =AN32/AN26 -> 0.28633171 | AO33: =AO32/AO26 -> 0.30970163 | AP33: =AP32/AP26 -> 0.25694383 | ... CL33: =CL32/CL26 -> 0.20587459 | CM33: =AVERAGE(CI33:CL33)*1.05 -> 0.23858483 | CN33: =AVERAGE(CJ33:CM33)*1.05 -> 0.24396305 | CO33: =AVERAGE(CK33:CN33)*1.05 -> 0.24282232 | CP33: =AVERAGE(CL33:CO33)*1.05 -> 0.24445176 | CQ33: =AVERAGE(CM33:CP33) -> 0.24245549 | CR33: =AVERAGE(CN33:CQ33) -> 0.24342315 | CS33: =AVERAGE(CO33:CR33) -> 0.24328818 | CT33: =AVERAGE(CP33:CS33) -> 0.24340464 | CU33: =AVERAGE(CQ33:CT33) -> 0.24314287 | CV33: =AVERAGE(CR33:CU33) -> 0.24331471 | CW33: =AVERAGE(CS33:CV33) -> 0.2432876 | CX33: =AVERAGE(CT33:CW33) -> 0.24328745 | ... DB33: =AVERAGE(CX33:DA33) -> 0.24327816 | DF33: 0.24082413
A34: GP YOY% | C34: =+IF(B32<0,1-C32/B32,C32/B32-1) -> 0.97919708 | D34: =+IF(C32<0,1-D32/C32,D32/C32-1) -> 0.19020142 | E34: =+IF(D32<0,1-E32/D32,E32/D32-1) -> 0.48404184 | F34: =+IF(E32<0,1-F32/E32,F32/E32-1) -> 0.087339002 | G34: =+IF(F32<0,1-G32/F32,G32/F32-1) -> 0.27864182 | H34: =+IF(G32<0,1-H32/G32,H32/G32-1) -> 0.30407685 | I34: =+IF(H32<0,1-I32/H32,I32/H32-1) -> 0.33294227 | J34: =+IF(I32<0,1-J32/I32,J32/I32-1) -> 0.3387422 | ... AE34: =+IF(AD32<0,1-AE32/AD32,AE32/AD32-1) -> 0.15010633 | AM34: =+IF(AI32<0,1-AM32/AI32,AM32/AI32-1) -> -0.077808259 | AN34: =+IF(AJ32<0,1-AN32/AJ32,AN32/AJ32-1) -> -0.021010664 | AO34: =+IF(AK32<0,1-AO32/AK32,AO32/AK32-1) -> 0.27794161 | AP34: =+IF(AL32<0,1-AP32/AL32,AP32/AL32-1) -> 0.030572235 | AQ34: =+IF(AM32<0,1-AQ32/AM32,AQ32/AM32-1) -> 0.2426157 | AR34: =+IF(AN32<0,1-AR32/AN32,AR32/AN32-1) -> 0.10714632 | AS34: =+IF(AO32<0,1-AS32/AO32,AS32/AO32-1) -> -0.096775124 | AT34: =+IF(AP32<0,1-AT32/AP32,AT32/AP32-1) -> 0.21840579 | ... CL34: =+IF(CH32<0,1-CL32/CH32,CL32/CH32-1) -> -0.015564621 | CM34: =+CM32/CI32-1 -> 0.31273068 | CN34: =+CN32/CJ32-1 -> 0.17899876 | CO34: =+CO32/CK32-1 -> 0.231481 | CP34: =+CP32/CL32-1 -> 0.42485825 | CQ34: =+CQ32/CM32-1 -> 0.16865692 | CR34: =+CR32/CN32-1 -> 0.14745501 | CS34: =+CS32/CO32-1 -> 0.15220631 | CT34: =+CT32/CP32-1 -> 0.14507396 | ... DB34: =+DB32/CX32-1 -> 0.14995607 | DF34: 0.2411573
A35: GP QOQ% | AJ35: =+IF(AI32<0,1-AJ32/AI32,AJ32/AI32-1) -> -0.23276929 | AK35: =+IF(AJ32<0,1-AK32/AJ32,AK32/AJ32-1) -> -0.14160048 | AL35: =+IF(AK32<0,1-AL32/AK32,AL32/AK32-1) -> 0.34440431 | AM35: =+IF(AL32<0,1-AM32/AL32,AM32/AL32-1) -> 0.041539854 | AN35: =+IF(AM32<0,1-AN32/AM32,AN32/AM32-1) -> -0.18551572 | AO35: =+IF(AN32<0,1-AO32/AN32,AO32/AN32-1) -> 0.12052749 | AP35: =+IF(AO32<0,1-AP32/AO32,AP32/AO32-1) -> 0.08416984 | AQ35: =+IF(AP32<0,1-AQ32/AP32,AQ32/AP32-1) -> 0.25583994 | ... CL35: =+IF(CK32<0,1-CL32/CK32,CL32/CK32-1) -> 0.38493511 | CM35: =+CM32/CL32-1 -> 0.12058525 | CN35: =+CN32/CM32-1 -> -0.39058399 | CO35: =+CO32/CN32-1 -> 0.30208558 | CP35: =+CP32/CO32-1 -> 0.60240898 | CQ35: =+CQ32/CP32-1 -> -0.08090527 | CR35: =+CR32/CQ32-1 -> -0.40164009 | CS35: =+CS32/CR32-1 -> 0.30747717 | CT35: =+CT32/CS32-1 -> 0.59248979 | ... DB35: =+DB32/DA32-1 -> 0.59171546 | DF35: 0.74609969
A36: Employee Cost | B36: ='Annual Raw'!C14 -> 100.3037 | C36: ='Annual Raw'!D14 -> 110.8011 | D36: ='Annual Raw'!E14 -> 134.5882 | E36: ='Annual Raw'!F14 -> 135.1971 | F36: ='Annual Raw'!G14 -> 153.6958 | G36: ='Annual Raw'!H14 -> 190.9696 | H36: ='Annual Raw'!I14 -> 258.6337 | I36: ='Annual Raw'!J14 -> 297.6833 | ... AA36: ='Annual Raw'!AB14 -> 938.59 | AB36: =+SUM(CM36:CP36) -> 1004.2913 | AC36: =+SUM(CQ36:CT36) -> 1074.5917 | AD36: =+SUM(CU36:CX36) -> 1149.8131 | AE36: =+SUM(CY36:DB36) -> 1230.3 | AI36: ='QTR Raw'!C16 -> 164.49 | AJ36: ='QTR Raw'!D16 -> 162.99 | AK36: ='QTR Raw'!E16 -> 147.26 | AL36: ='QTR Raw'!F16 -> 157.79 | AM36: ='QTR Raw'!G16 -> 164.86 | AN36: ='QTR Raw'!H16 -> 152.65 | AO36: ='QTR Raw'!I16 -> 146.47 | AP36: ='QTR Raw'!J16 -> 130.71 | ... CL36: ='QTR Raw'!BF16 -> 242.68 | CM36: =CI36*107% -> 246.6457 | CN36: =CJ36*107% -> 257.6132 | CO36: =CK36*107% -> 240.3648 | CP36: =CL36*107% -> 259.6676 | CQ36: =CM36*107% -> 263.9109 | CR36: =CN36*107% -> 275.64612 | CS36: =CO36*107% -> 257.19034 | CT36: =CP36*107% -> 277.84433 | ... DB36: =CX36*107% -> 318.10398 | DF36: 233.795
A37: General and Administration Expenses | B37: ='Annual Raw'!C17 -> -68.082 | C37: ='Annual Raw'!D17 -> 19.8816 | D37: ='Annual Raw'!E17 -> 12.0623 | E37: ='Annual Raw'!F17 -> 115.5002 | F37: ='Annual Raw'!G17 -> 122.9156 | G37: ='Annual Raw'!H17 -> 138.0629 | H37: ='Annual Raw'!I17 -> 184.709 | I37: ='Annual Raw'!J17 -> 209.0765 | ... AA37: ='Annual Raw'!AB17 -> 674.14 | AB37: =+SUM(CM37:CP37) -> 0 | AC37: =+SUM(CQ37:CT37) -> 0 | AD37: =+SUM(CU37:CX37) -> 0 | AE37: =+SUM(CY37:DB37) -> 0 | AI37: ='QTR Raw'!C17 -> 0 | AJ37: ='QTR Raw'!D17 -> 0 | AK37: ='QTR Raw'!E17 -> 0 | AL37: ='QTR Raw'!F17 -> 0 | AM37: ='QTR Raw'!G17 -> 0 | AN37: ='QTR Raw'!H17 -> 0 | AO37: ='QTR Raw'!I17 -> 0 | AP37: ='QTR Raw'!J17 -> 0 | ... CL37: ='QTR Raw'!BF17 -> 0 | DF37: 0
A38: Miscellaneous Expenses | B38: ='Annual Raw'!C19-'Annual Raw'!C20 -> 6.9943 | C38: ='Annual Raw'!D19-'Annual Raw'!D20 -> 9.6995 | D38: ='Annual Raw'!E19-'Annual Raw'!E20 -> 10.1377 | E38: ='Annual Raw'!F19-'Annual Raw'!F20 -> 17.7687 | F38: ='Annual Raw'!G19-'Annual Raw'!G20 -> 15.1924 | G38: ='Annual Raw'!H19-'Annual Raw'!H20 -> 7.6245 | H38: ='Annual Raw'!I19-'Annual Raw'!I20 -> 15.9955 | I38: ='Annual Raw'!J19-'Annual Raw'!J20 -> 12.1042 | ... AA38: ='Annual Raw'!AB19-'Annual Raw'!AB20 -> 191.46 | AB38: =+SUM(CM38:CP38) -> 0 | AC38: =+SUM(CQ38:CT38) -> 0 | AD38: =+SUM(CU38:CX38) -> 0 | AE38: =+SUM(CY38:DB38) -> 0 | AI38: =+'QTR Raw'!C21 -> 0 | AJ38: =+'QTR Raw'!D21 -> 0 | AK38: =+'QTR Raw'!E21 -> 0 | AL38: =+'QTR Raw'!F21 -> 0 | AM38: =+'QTR Raw'!G21 -> 0 | AN38: =+'QTR Raw'!H21 -> 0 | AO38: =+'QTR Raw'!I21 -> 0 | AP38: =+'QTR Raw'!J21 -> 0 | ... CL38: =+'QTR Raw'!BF21 -> 0 | DF38: 0
A39: Other Manufacturing Expenses | B39: ='Annual Raw'!C15+'Annual Raw'!C16 -> 7.5553 | C39: ='Annual Raw'!D15+'Annual Raw'!D16 -> 8.841 | D39: ='Annual Raw'!E15+'Annual Raw'!E16 -> 7.32 | E39: ='Annual Raw'!F15+'Annual Raw'!F16 -> 7.5075 | F39: ='Annual Raw'!G15+'Annual Raw'!G16 -> 6.7282 | G39: ='Annual Raw'!H15+'Annual Raw'!H16 -> 7.0118 | H39: ='Annual Raw'!I15+'Annual Raw'!I16 -> 10.0716 | I39: ='Annual Raw'!J15+'Annual Raw'!J16 -> 12.8489 | ... AA39: ='Annual Raw'!AB15+'Annual Raw'!AB16 -> 117.42 | AB39: =+SUM(CM39:CP39) -> 2089.7031 | AC39: =+SUM(CQ39:CT39) -> 2404.2659 | AD39: =+SUM(CU39:CX39) -> 2847.4853 | AE39: =+SUM(CY39:DB39) -> 3364.969 | AI39: ='QTR Raw'!C14 -> 153.51 | AJ39: ='QTR Raw'!D14 -> 109.06 | AK39: ='QTR Raw'!E14 -> 99.76 | AL39: ='QTR Raw'!F14 -> 125.13 | AM39: ='QTR Raw'!G14 -> 164.53 | AN39: ='QTR Raw'!H14 -> 114.47 | AO39: ='QTR Raw'!I14 -> 132.71 | AP39: ='QTR Raw'!J14 -> 139.78 | ... CL39: ='QTR Raw'!BF14 -> 542.93 | CM39: =CM42-CM36-CM37-CM38-CM40-CM41 -> 621.0338 | CN39: =CN42-CN36-CN37-CN38-CN40-CN41 -> 267.1634 | CO39: =CO42-CO36-CO37-CO38-CO40-CO41 -> 416.51385 | CP39: =CP42-CP36-CP37-CP38-CP40-CP41 -> 784.99204 | CQ39: =CQ42-CQ36-CQ37-CQ38-CQ40-CQ41 -> 703.19574 | CR39: =CR42-CR36-CR37-CR38-CR40-CR41 -> 302.08067 | CS39: =CS42-CS36-CS37-CS38-CS40-CS41 -> 490.25072 | CT39: =CT42-CT36-CT37-CT38-CT40-CT41 -> 908.73882 | ... DB39: =DB42-DB36-DB37-DB38-DB40-DB41 -> 1258.4958 | DF39: 669.67049
A40: Power & Fuel Cost | B40: ='Annual Raw'!C13 -> 6.6359 | C40: ='Annual Raw'!D13 -> 5.844 | D40: ='Annual Raw'!E13 -> 5.1779 | E40: ='Annual Raw'!F13 -> 4.9364 | F40: ='Annual Raw'!G13 -> 4.3908 | G40: ='Annual Raw'!H13 -> 4.1447 | H40: ='Annual Raw'!I13 -> 4.258 | I40: ='Annual Raw'!J13 -> 4.0643 | ... AA40: ='Annual Raw'!AB13 -> 30.29 | AB40: =+SUM(CM40:CP40) -> 0 | AC40: =+SUM(CQ40:CT40) -> 0 | AD40: =+SUM(CU40:CX40) -> 0 | AE40: =+SUM(CY40:DB40) -> 0 | AI40: ='QTR Raw'!C15 -> 0 | AJ40: ='QTR Raw'!D15 -> 0 | AK40: ='QTR Raw'!E15 -> 0 | AL40: ='QTR Raw'!F15 -> 0 | AM40: ='QTR Raw'!G15 -> 0 | AN40: ='QTR Raw'!H15 -> 0 | AO40: ='QTR Raw'!I15 -> 0 | AP40: ='QTR Raw'!J15 -> 0 | ... CL40: ='QTR Raw'!BF15 -> 0 | DF40: 0
A41: Selling and Distribution Expenses | B41: ='Annual Raw'!C18 -> 21.4302 | C41: ='Annual Raw'!D18 -> 25.2276 | D41: ='Annual Raw'!E18 -> 36.8914 | E41: ='Annual Raw'!F18 -> 35.8005 | F41: ='Annual Raw'!G18 -> 33.266 | G41: ='Annual Raw'!H18 -> 37.9538 | H41: ='Annual Raw'!I18 -> 46.844 | I41: ='Annual Raw'!J18 -> 75.7394 | ... AA41: ='Annual Raw'!AB18 -> 620.72 | AB41: =+SUM(CM41:CP41) -> 0 | AC41: =+SUM(CQ41:CT41) -> 0 | AD41: =+SUM(CU41:CX41) -> 0 | AE41: =+SUM(CY41:DB41) -> 0 | AI41: ='QTR Raw'!C18 -> 0 | AJ41: ='QTR Raw'!D18 -> 0 | AK41: ='QTR Raw'!E18 -> 0 | AL41: ='QTR Raw'!F18 -> 0 | AM41: ='QTR Raw'!G18 -> 0 | AN41: ='QTR Raw'!H18 -> 0 | AO41: ='QTR Raw'!I18 -> 0 | AP41: ='QTR Raw'!J18 -> 0 | ... CL41: ='QTR Raw'!BF18 -> 0 | DF41: 0
A42: Total Cost | B42: =+SUM(B36:B41) -> 74.8374 | C42: =+SUM(C36:C41) -> 180.2948 | D42: =+SUM(D36:D41) -> 206.1775 | E42: =+SUM(E36:E41) -> 316.7104 | F42: =+SUM(F36:F41) -> 336.1888 | G42: =+SUM(G36:G41) -> 385.7673 | H42: =+SUM(H36:H41) -> 520.5118 | I42: =+SUM(I36:I41) -> 611.5166 | ... AE42: =+SUM(AE36:AE41) -> 4595.269 | AI42: =+SUM(AI36:AI41) -> 318 | AJ42: =+SUM(AJ36:AJ41) -> 272.05 | AK42: =+SUM(AK36:AK41) -> 247.02 | AL42: =+SUM(AL36:AL41) -> 282.92 | AM42: =+SUM(AM36:AM41) -> 329.39 | AN42: =+SUM(AN36:AN41) -> 267.12 | AO42: =+SUM(AO36:AO41) -> 279.18 | AP42: =+SUM(AP36:AP41) -> 270.49 | ... CL42: =+SUM(CL36:CL41) -> 785.61 | CM42: =CM43*CM26 -> 867.6795 | CN42: =CN43*CN26 -> 524.7766 | CO42: =CO43*CO26 -> 656.87865 | CP42: =CP43*CP26 -> 1044.6596 | CQ42: =CQ43*CQ26 -> 967.10664 | CR42: =CR43*CR26 -> 577.7268 | CS42: =CS43*CS26 -> 747.44105 | CT42: =CT43*CT26 -> 1186.5831 | ... DB42: =DB43*DB26 -> 1576.5998 | DF42: 903.46549
A43: Cost % | B43: =B42/B26 -> 0.097883862 | C43: =C42/C26 -> 0.20461065 | D43: =D42/D26 -> 0.16421388 | E43: =E42/E26 -> 0.23288324 | F43: =F42/F26 -> 0.22760556 | G43: =G42/G26 -> 0.19738025 | H43: =H42/H26 -> 0.20600157 | I43: =I42/I26 -> 0.19092432 | ... AE43: =AE42/AE26 -> 0.17676202 | AI43: =AI42/AI26 -> 0.19668238 | AJ43: =AJ42/AJ26 -> 0.23362159 | AK43: =AK42/AK26 -> 0.21432662 | AL43: =AL42/AL26 -> 0.17714497 | AM43: =AM42/AM26 -> 0.20544502 | AN43: =AN42/AN26 -> 0.24721202 | AO43: =AO42/AO26 -> 0.24940147 | AP43: =AP42/AP26 -> 0.18491123 | ... CL43: =CL42/CL26 -> 0.16072777 | CM43: =AVERAGE(CI43:CL43)*1.005 -> 0.18358552 | CN43: =AVERAGE(CJ43:CM43)*1.005 -> 0.18630346 | CO43: =AVERAGE(CK43:CN43)*1.005 -> 0.17826111 | CP43: =AVERAGE(CL43:CO43)*1.005 -> 0.17810556 | CQ43: =AVERAGE(CM43:CP43)*0.98 -> 0.17793263 | CR43: =AVERAGE(CN43:CQ43)*0.99 -> 0.17834918 | CS43: =AVERAGE(CO43:CR43)*0.99 -> 0.1763805 | CT43: =AVERAGE(CP43:CS43)*0.99 -> 0.17591505 | CU43: =AVERAGE(CQ43:CT43) -> 0.17714434 | CV43: =AVERAGE(CR43:CU43) -> 0.17694727 | CW43: =AVERAGE(CS43:CV43) -> 0.17659679 | CX43: =AVERAGE(CT43:CW43) -> 0.17665086 | CY43: =AVERAGE(CU43:CX43) -> 0.17683482 | CZ43: =AVERAGE(CV43:CY43) -> 0.17675744 | DA43: =AVERAGE(CW43:CZ43) -> 0.17670998 | DB43: =AVERAGE(CX43:DA43) -> 0.17673827 | DF43: 0.17149566
A44: EBITDA | B44: =B32-B42 -> 27.4896 | C44: =C32-C42 -> 22.2305 | D44: =D32-D42 -> 34.8684 | E44: =E32-E42 -> 41.0118 | F44: =F32-F42 -> 52.7765 | G44: =G32-G42 -> 111.58 | H44: =H32-H42 -> 128.0673 | I44: =I32-I42 -> 253.0019 | ... AE44: =AE32-AE42 -> 1729.1196 | AI44: =AI32-AI42 -> 93.91 | AJ44: =AJ32-AJ42 -> 43.98 | AK44: =AK32-AK42 -> 24.26 | AL44: =AL32-AL42 -> 81.79 | AM44: =AM32-AM42 -> 50.47 | AN44: =AN32-AN42 -> 42.27 | AO44: =AO32-AO42 -> 67.5 | AP44: =AP32-AP42 -> 105.37 | ... DB44: =DB32-DB42 -> 593.57134 | DF44: 365.23308
A45: EBITDA Margins | B45: =B44/B26 -> 0.035955127 | C45: =C44/C26 -> 0.025228664 | D45: =D44/D26 -> 0.027771581 | E45: =E44/E26 -> 0.030156764 | F45: =F44/F26 -> 0.035730592 | G45: =G44/G26 -> 0.057090604 | H45: =H44/H26 -> 0.050684856 | I45: =I44/I26 -> 0.078990849 | ... AE45: =AE44/AE26 -> 0.066512465 | AI45: =AI44/AI26 -> 0.058083151 | AJ45: =AJ44/AJ26 -> 0.037767606 | AK45: =AK44/AK26 -> 0.021049161 | AL45: =AL44/AL26 -> 0.05121125 | AM45: =AM44/AM26 -> 0.031478825 | AN45: =AN44/AN26 -> 0.039119691 | AO45: =AO44/AO26 -> 0.060300161 | AP45: =AP44/AP26 -> 0.072032595 | ... DB45: =DB44/DB26 -> 0.066539887 | DF45: 0.069328478
A46: EBITDA YOY% | C46: =+IF(B44<0,1-C44/B44,C44/B44-1) -> -0.19131235 | D46: =+IF(C44<0,1-D44/C44,D44/C44-1) -> 0.56849374 | E46: =+IF(D44<0,1-E44/D44,E44/D44-1) -> 0.17618818 | F46: =+IF(E44<0,1-F44/E44,F44/E44-1) -> 0.28686134 | G46: =+IF(F44<0,1-G44/F44,G44/F44-1) -> 1.1141986 | H46: =+IF(G44<0,1-H44/G44,H44/G44-1) -> 0.14776214 | I46: =+IF(H44<0,1-I44/H44,I44/H44-1) -> 0.97553864 | J46: =+IF(I44<0,1-J44/I44,J44/I44-1) -> 0.11878646 | ... AE46: =+IF(AD44<0,1-AE44/AD44,AE44/AD44-1) -> 0.1514709 | AM46: =+IF(AI44<0,1-AM44/AI44,AM44/AI44-1) -> -0.46257055 | AN46: =+IF(AJ44<0,1-AN44/AJ44,AN44/AJ44-1) -> -0.03888131 | AO46: =+IF(AK44<0,1-AO44/AK44,AO44/AK44-1) -> 1.7823578 | AP46: =+IF(AL44<0,1-AP44/AL44,AP44/AL44-1) -> 0.2882993 | AQ46: =+IF(AM44<0,1-AQ44/AM44,AQ44/AM44-1) -> 1.6132356 | AR46: =+IF(AN44<0,1-AR44/AN44,AR44/AN44-1) -> 0.83912941 | AS46: =+IF(AO44<0,1-AS44/AO44,AS44/AO44-1) -> -0.14962963 | AT46: =+IF(AP44<0,1-AT44/AP44,AT44/AP44-1) -> 0.35721742 | ... CL46: =+IF(CH44<0,1-CL44/CH44,CL44/CH44-1) -> -0.33688924 | CM46: =+CM44/CI44-1 -> 0.45601873 | CN46: =+CN44/CJ44-1 -> 1.3066982 | CO46: =+CO44/CK44-1 -> 0.34188692 | CP46: =+CP44/CL44-1 -> 0.76347809 | CQ46: =+CQ44/CM44-1 -> 0.34913112 | CR46: =+CR44/CN44-1 -> 0.29787708 | CS46: =+CS44/CO44-1 -> 0.19179667 | CT46: =+CT44/CP44-1 -> 0.16981889 | ... DB46: =+DB44/CX44-1 -> 0.1483311 | DF46: 0.09752114
A47: EBITDA QOQ% | AJ47: =+IF(AI44<0,1-AJ44/AI44,AJ44/AI44-1) -> -0.53167927 | AK47: =+IF(AJ44<0,1-AK44/AJ44,AK44/AJ44-1) -> -0.44838563 | AL47: =+IF(AK44<0,1-AL44/AK44,AL44/AK44-1) -> 2.3713932 | AM47: =+IF(AL44<0,1-AM44/AL44,AM44/AL44-1) -> -0.3829319 | AN47: =+IF(AM44<0,1-AN44/AM44,AN44/AM44-1) -> -0.16247276 | AO47: =+IF(AN44<0,1-AO44/AN44,AO44/AN44-1) -> 0.59687722 | AP47: =+IF(AO44<0,1-AP44/AO44,AP44/AO44-1) -> 0.56103704 | AQ47: =+IF(AP44<0,1-AQ44/AP44,AQ44/AP44-1) -> 0.25168454 | ... CI47: =+IF(CH44<0,1-CI44/CH44,CI44/CH44-1) -> -0.46351944 | CJ47: =+IF(CI44>1,CJ44/CI44-1,1-CJ44/CI44) -> -0.6056125 | CK47: =+IF(CJ44>1,CK44/CJ44-1,1-CK44/CJ44) -> 1.5179662 | CL47: =+IF(CK44>1,CL44/CK44-1,1-CL44/CK44) -> 0.24468385 | CM47: =+CM44/CL44-1 -> 0.17797174 | CN47: =+CN44/CM44-1 -> -0.37519147 | CO47: =+CO44/CN44-1 -> 0.46478891 | CP47: =+CP44/CO44-1 -> 0.63573597 | CQ47: =+CQ44/CP44-1 -> -0.098804603 | CR47: =+CR44/CQ44-1 -> -0.3989282 | CS47: =+CS44/CR44-1 -> 0.34506616 | CT47: =+CT44/CS44-1 -> 0.60557155 | ... DB47: =+DB44/DA44-1 -> 0.59100609 | DF47: 1.0600885
A48: Depreciation | B48: ='Annual Raw'!C27 -> 14.792 | C48: ='Annual Raw'!D27 -> 15.2251 | D48: ='Annual Raw'!E27 -> 17.6584 | E48: ='Annual Raw'!F27 -> 15.9524 | F48: ='Annual Raw'!G27 -> 13.269 | G48: ='Annual Raw'!H27 -> 14.0906 | H48: ='Annual Raw'!I27 -> 15.5668 | I48: ='Annual Raw'!J27 -> 16.6926 | ... AA48: ='Annual Raw'!AB27 -> 84.1 | AB48: =+SUM(CM48:CP48) -> 90.927358 | AC48: =+SUM(CQ48:CT48) -> 82.122007 | AD48: =+SUM(CU48:CX48) -> 74.16936 | AE48: =+SUM(CY48:DB48) -> 66.986844 | AI48: ='QTR Raw'!C28 -> 7.3 | AJ48: ='QTR Raw'!D28 -> 7.59 | AK48: ='QTR Raw'!E28 -> 6.95 | AL48: ='QTR Raw'!F28 -> 6 | AM48: ='QTR Raw'!G28 -> 6.05 | AN48: ='QTR Raw'!H28 -> 5.95 | AO48: ='QTR Raw'!I28 -> 5.96 | AP48: ='QTR Raw'!J28 -> 6.88 | ... CL48: ='QTR Raw'!BF28 -> 20.59 | CM48: =CM49*CL150 -> 23.607322 | CN48: =CN49*CM150 -> 23.013781 | CO48: =CO49*CN150 -> 22.435163 | CP48: =CP49*CO150 -> 21.871092 | CQ48: =CQ49*CP150 -> 21.321203 | CR48: =CR49*CQ150 -> 20.78514 | CS48: =CS49*CR150 -> 20.262555 | CT48: =CT49*CS150 -> 19.753108 | ... DB48: =DB49*DA150 -> 16.112592 | DF48: 20.113563
A49: Depreciation % of Net Block | B49: =+B48/B150 -> 0.11052077 | C49: =+C48/C150 -> 0.11511997 | D49: =+D48/D150 -> 0.12083406 | E49: =+E48/E150 -> 0.11028054 | F49: =+F48/F150 -> 0.13132553 | G49: =+G48/G150 -> 0.094521539 | H49: =+H48/H150 -> 0.10571645 | I49: =+I48/I150 -> 0.09811956 | ... AE49: =+AE48/AE150 -> 0.10722279 | AI49: =+AI48/AH150 -> #DIV/0! | AJ49: =+AJ48/AI150 -> #DIV/0! | AK49: =+AK48/AJ150 -> 0.032735151 | AL49: =+AL48/AK150 -> 0.028260562 | AM49: =+AM48/AL150 -> 0.028672986 | AN49: =+AN48/AM150 -> 0.028199052 | AO49: =+AO48/AN150 -> 0.029032101 | AP49: =+AP48/AO150 -> 0.033513566 | ... CL49: =+CL48/CK150 -> 0.025142257 | CM49: =CL49 -> 0.025142257 | CN49: =CM49 -> 0.025142257 | CO49: =CN49 -> 0.025142257 | CP49: =CO49 -> 0.025142257 | CQ49: =CP49 -> 0.025142257 | CR49: =CQ49 -> 0.025142257 | CS49: =CR49 -> 0.025142257 | CT49: =CS49 -> 0.025142257 | ... DB49: =DA49 -> 0.025142257 | DF49: 0.024560484
A50: EBIT | B50: =B44-B48 -> 12.6976 | C50: =C44-C48 -> 7.0054 | D50: =D44-D48 -> 17.21 | E50: =E44-E48 -> 25.0594 | F50: =F44-F48 -> 39.5075 | G50: =G44-G48 -> 97.4894 | H50: =H44-H48 -> 112.5005 | I50: =I44-I48 -> 236.3093 | ... AE50: =AE44-AE48 -> 1662.1327 | AI50: =AI44-AI48 -> 86.61 | AJ50: =AJ44-AJ48 -> 36.39 | AK50: =AK44-AK48 -> 17.31 | AL50: =AL44-AL48 -> 75.79 | AM50: =AM44-AM48 -> 44.42 | AN50: =AN44-AN48 -> 36.32 | AO50: =AO44-AO48 -> 61.54 | AP50: =AP44-AP48 -> 98.49 | ... DB50: =DB44-DB48 -> 577.45875 | DF50: 345.11952
A51: Other Income | B51: ='Annual Raw'!C23 -> 19.0685 | C51: ='Annual Raw'!D23 -> 26.7028 | D51: ='Annual Raw'!E23 -> 21.1738 | E51: ='Annual Raw'!F23 -> 23.2862 | F51: ='Annual Raw'!G23 -> 24.355 | G51: ='Annual Raw'!H23 -> 31.1923 | H51: ='Annual Raw'!I23 -> 70.1808 | I51: ='Annual Raw'!J23 -> 48.3372 | ... AA51: ='Annual Raw'!AB23 -> 282.95 | AB51: =+SUM(CM51:CP51) -> 0 | AC51: =+SUM(CQ51:CT51) -> 0 | AD51: =+SUM(CU51:CX51) -> 0 | AE51: =+SUM(CY51:DB51) -> 0 | AI51: ='QTR Raw'!C23 -> 34.94 | AJ51: ='QTR Raw'!D23 -> 18.26 | AK51: ='QTR Raw'!E23 -> 24.3 | AL51: ='QTR Raw'!F23 -> 12.63 | AM51: ='QTR Raw'!G23 -> 22.11 | AN51: ='QTR Raw'!H23 -> 30.25 | AO51: ='QTR Raw'!I23 -> 17.04 | AP51: ='QTR Raw'!J23 -> 30.78 | ... CL51: ='QTR Raw'!BF23 -> 42.63 | DF51: 238.15
A52: Interest | B52: ='Annual Raw'!C25 -> 14.5763 | C52: ='Annual Raw'!D25 -> 12.21 | D52: ='Annual Raw'!E25 -> 9.7595 | E52: ='Annual Raw'!F25 -> 8.2192 | F52: ='Annual Raw'!G25 -> 8.7386 | G52: ='Annual Raw'!H25 -> 6.4469 | H52: ='Annual Raw'!I25 -> 9.8649 | I52: ='Annual Raw'!J25 -> 8.975 | ... AA52: ='Annual Raw'!AB25 -> 86.78 | AB52: =+SUM(CM52:CP52) -> 61.499042 | AC52: =+SUM(CQ52:CT52) -> 108.73146 | AD52: =+SUM(CU52:CX52) -> 151.1211 | AE52: =+SUM(CY52:DB52) -> 199.42741 | AI52: ='QTR Raw'!C25 -> 12.09 | AJ52: ='QTR Raw'!D25 -> 8.53 | AK52: ='QTR Raw'!E25 -> 7.15 | AL52: ='QTR Raw'!F25 -> 10.71 | AM52: ='QTR Raw'!G25 -> 6.97 | AN52: ='QTR Raw'!H25 -> 4.56 | AO52: ='QTR Raw'!I25 -> 4.56 | AP52: ='QTR Raw'!J25 -> 6.46 | ... CL52: ='QTR Raw'!BF25 -> 22.2 | CM52: =CM53*CL184 -> 1.8322 | CN52: =CN53*CM184 -> 6.9241344 | CO52: =CO53*CN184 -> 29.914365 | CP52: =CP53*CO184 -> 22.828343 | CQ52: =CQ53*CP184 -> 4.25364 | CR52: =CR53*CQ184 -> 15.962608 | CS52: =CS53*CR184 -> 49.372294 | CT52: =CT53*CS184 -> 39.142914 | ... DB52: =DB53*DA184 -> 65.669994 | DF52: -58.086787
A53: Interest % of Debt | B53: =+B52/B144 -> 0.10839888 | C53: =+C52/C144 -> 0.12392806 | D53: =+D52/D144 -> 0.089582064 | E53: =+E52/E144 -> 0.079869941 | F53: =+F52/F144 -> 0.069090438 | G53: =+G52/G144 -> 0.07157385 | H53: =+H52/H144 -> 0.088409976 | I53: =+I52/I144 -> 0.12170977 | ... AE53: =+AE52/AE144 -> 0.20636115 | AI53: =(AI52-AI51)/AH184 -> #DIV/0! | AJ53: =(AJ52-AJ51)/AI184 -> #DIV/0! | AK53: =(AK52-AK51)/AJ184 -> 0.10398351 | AL53: =(AL52-AL51)/AK184 -> 0.0073178952 | AM53: =(AM52-AM51)/AL184 -> 0.042452962 | AN53: =(AN52-AN51)/AM184 -> 0.065042446 | AO53: =(AO52-AO51)/AN184 -> 0.022762092 | AP53: =(AP52-AP51)/AO184 -> 0.04123756 | ... CL53: =(CL52-CL51)/CK184 -> -0.010551453 | CM53: -0.02 | CN53: =+CM53 -> -0.02 | CO53: =+CN53 -> -0.02 | CP53: =+CO53 -> -0.02 | CQ53: -0.025 | CR53: =+CQ53 -> -0.025 | CS53: =+CR53 -> -0.025 | CT53: =+CS53 -> -0.025 | CU53: =+CT53 -> -0.025 | CV53: =+CU53 -> -0.025 | CW53: =+CV53 -> -0.025 | CX53: =+CW53 -> -0.025 | CY53: =+CX53 -> -0.025 | ... DB53: =+DA53 -> -0.025 | DF53: -0.03
A54: PBT | B54: =B50+B51-B52 -> 17.1898 | C54: =C50+C51-C52 -> 21.4982 | D54: =D50+D51-D52 -> 28.6243 | E54: =E50+E51-E52 -> 40.1264 | F54: =F50+F51-F52 -> 55.1239 | G54: =G50+G51-G52 -> 122.2348 | H54: =H50+H51-H52 -> 172.8164 | I54: =I50+I51-I52 -> 275.6715 | ... AE54: =AE50+AE51-AE52 -> 1462.7053 | AI54: =AI50+AI51-AI52 -> 109.46 | AJ54: =AJ50+AJ51-AJ52 -> 46.12 | AK54: =AK50+AK51-AK52 -> 34.46 | AL54: =AL50+AL51-AL52 -> 77.71 | AM54: =AM50+AM51-AM52 -> 59.56 | AN54: =AN50+AN51-AN52 -> 62.01 | AO54: =AO50+AO51-AO52 -> 74.02 | AP54: =AP50+AP51-AP52 -> 122.81 | ... DB54: =DB50+DB51-DB52 -> 511.78875 | DF54: 403.20631
A55: Tax | B55: ='Annual Raw'!C30 -> 0.1437 | C55: ='Annual Raw'!D30 -> 1.1987 | D55: ='Annual Raw'!E30 -> 4.155 | E55: ='Annual Raw'!F30 -> 8.1565 | F55: ='Annual Raw'!G30 -> 8.0124 | G55: ='Annual Raw'!H30 -> 22.3577 | H55: ='Annual Raw'!I30 -> 40.7439 | I55: ='Annual Raw'!J30 -> 99.6639 | ... AA55: ='Annual Raw'!AB30 -> 187.11 | AB55: =+SUM(CM55:CP55) -> 233.34485 | AC55: =+SUM(CQ55:CT55) -> 287.8352 | AD55: =+SUM(CU55:CX55) -> 331.48617 | AE55: =+SUM(CY55:DB55) -> 380.03916 | AI55: ='QTR Raw'!C29 -> 31.6 | AJ55: ='QTR Raw'!D29 -> 17.69 | AK55: ='QTR Raw'!E29 -> 18.07 | AL55: ='QTR Raw'!F29 -> 5.4 | AM55: ='QTR Raw'!G29 -> 18.95 | AN55: ='QTR Raw'!H29 -> 19.63 | AO55: ='QTR Raw'!I29 -> 16.35 | AP55: ='QTR Raw'!J29 -> 39.2 | ... CL55: ='QTR Raw'!BF29 -> 71.07 | CM55: =+CM54*CM56 -> 59.977995 | CN55: =+CN54*CN56 -> 33.355386 | CO55: =+CO54*CO56 -> 46.822432 | CP55: =+CP54*CP56 -> 93.189033 | CQ55: =+CQ54*CQ56 -> 83.754338 | CR55: =+CR54*CR56 -> 44.916056 | CS55: =+CS54*CS56 -> 55.536495 | CT55: =+CT54*CT56 -> 103.62831 | ... DB55: =+DB54*DB56 -> 132.99955 | DF55: 99.518533
A56: Tax Rate % | B56: =B55/B54 -> 0.0083596086 | C56: =C55/C54 -> 0.055758156 | D56: =D55/D54 -> 0.14515639 | E56: =E55/E54 -> 0.20327017 | F56: =F55/F54 -> 0.14535256 | G56: =G55/G54 -> 0.18290781 | H56: =H55/H54 -> 0.23576408 | I56: =I55/I54 -> 0.36153139 | ... AE56: =AE55/AE54 -> 0.25981937 | AI56: =AI55/AI54 -> 0.28868993 | AJ56: =AJ55/AJ54 -> 0.38356461 | AK56: =AK55/AK54 -> 0.52437609 | AL56: =AL55/AL54 -> 0.069489126 | AM56: =AM55/AM54 -> 0.31816655 | AN56: =AN55/AN54 -> 0.31656184 | AO56: =AO55/AO54 -> 0.22088625 | AP56: =AP55/AP54 -> 0.31919225 | ... CL56: =CL55/CL54 -> 0.32229831 | CM56: =AVERAGE(CI56:CL56) -> 0.25576588 | CN56: =AVERAGE(CJ56:CM56) -> 0.25178303 | CO56: =AVERAGE(CK56:CN56) -> 0.25233911 | CP56: =AVERAGE(CL56:CO56) -> 0.27054658 | CQ56: =AVERAGE(CM56:CP56) -> 0.25760865 | CR56: =AVERAGE(CN56:CQ56) -> 0.25806934 | CS56: =AVERAGE(CO56:CR56) -> 0.25964092 | CT56: =AVERAGE(CP56:CS56) -> 0.26146637 | ... DB56: =AVERAGE(CX56:DA56) -> 0.25987197 | DF56: 0.2468179
A57: PAT | B57: =B54-B55 -> 17.0461 | C57: =C54-C55 -> 20.2995 | D57: =D54-D55 -> 24.4693 | E57: =E54-E55 -> 31.9699 | F57: =F54-F55 -> 47.1115 | G57: =G54-G55 -> 99.8771 | H57: =H54-H55 -> 132.0725 | I57: =I54-I55 -> 176.0076 | ... AE57: =AE54-AE55 -> 1082.6661 | AI57: =AI54-AI55 -> 77.86 | AJ57: =AJ54-AJ55 -> 28.43 | AK57: =AK54-AK55 -> 16.39 | AL57: =AL54-AL55 -> 72.31 | AM57: =AM54-AM55 -> 40.61 | AN57: =AN54-AN55 -> 42.38 | AO57: =AO54-AO55 -> 57.67 | AP57: =AP54-AP55 -> 83.61 | ... DB57: =DB54-DB55 -> 378.7892 | DF57: 303.68778
A58: PAT % | B58: =+B57/B26 -> 0.022295511 | C58: =+C57/C26 -> 0.023037236 | D58: =+D57/D26 -> 0.019489026 | E58: =+E57/E26 -> 0.023508081 | F58: =+F57/F26 -> 0.03189529 | G58: =+G57/G26 -> 0.051102742 | H58: =+H57/H26 -> 0.052269983 | I58: =+I57/I26 -> 0.054952116 | ... AE58: =+AE57/AE26 -> 0.041645931 | AI58: =+AI57/AI26 -> 0.048156257 | AJ58: =+AJ57/AJ26 -> 0.024414121 | AK58: =+AK57/AK26 -> 0.014220765 | AL58: =+AL57/AL26 -> 0.045275529 | AM58: =+AM57/AM26 -> 0.025329009 | AN58: =+AN57/AN26 -> 0.039221493 | AO58: =+AO57/AO26 -> 0.051518671 | AP58: =+AP57/AP26 -> 0.057157115 | ... DB58: =+DB57/DB26 -> 0.042462615 | DF58: 0.057645959
A59: PAT YOY% | C59: =+IF(B57<0,1-C57/B57,C57/B57-1) -> 0.19085891 | D59: =+IF(C57<0,1-D57/C57,D57/C57-1) -> 0.20541393 | E59: =+IF(D57<0,1-E57/D57,E57/D57-1) -> 0.30653104 | F59: =+IF(E57<0,1-F57/E57,F57/E57-1) -> 0.4736205 | G59: =+IF(F57<0,1-G57/F57,G57/F57-1) -> 1.1200153 | H59: =+IF(G57<0,1-H57/G57,H57/G57-1) -> 0.32235017 | I59: =+IF(H57<0,1-I57/H57,I57/H57-1) -> 0.33265896 | J59: =+IF(I57<0,1-J57/I57,J57/I57-1) -> 0.29770703 | ... AE59: =+IF(AD57<0,1-AE57/AD57,AE57/AD57-1) -> 0.14581801 | AM59: =+IF(AI57<0,1-AM57/AI57,AM57/AI57-1) -> -0.47842281 | AN59: =+IF(AJ57<0,1-AN57/AJ57,AN57/AJ57-1) -> 0.49067886 | AO59: =+IF(AK57<0,1-AO57/AK57,AO57/AK57-1) -> 2.5186089 | AP59: =+IF(AL57<0,1-AP57/AL57,AP57/AL57-1) -> 0.15627161 | AQ59: =+IF(AM57<0,1-AQ57/AM57,AQ57/AM57-1) -> 1.7040138 | AR59: =+IF(AN57<0,1-AR57/AN57,AR57/AN57-1) -> 0.1833412 | AS59: =+IF(AO57<0,1-AS57/AO57,AS57/AO57-1) -> 0.071267557 | AT59: =+IF(AP57<0,1-AT57/AP57,AT57/AP57-1) -> 0.41251047 | ... CL59: =+IF(CH57<0,1-CL57/CH57,CL57/CH57-1) -> -0.44167974 | CM59: =+CM57/CI57-1 -> 0.048264206 | CN59: =+CN57/CJ57-1 -> 0.45723784 | CO59: =+CO57/CK57-1 -> -0.030597634 | CP59: =+CP57/CL57-1 -> 0.68133192 | CQ59: =+CQ57/CM57-1 -> 0.38299579 | CR59: =+CR57/CN57-1 -> 0.30275111 | CS59: =+CS57/CO57-1 -> 0.14149411 | CT59: =+CT57/CP57-1 -> 0.16496411 | ... DB59: =+DB57/CX57-1 -> 0.1439358 | DF59: 0.13460277
A60: PAT QOQ% | AJ60: =+IF(AI57<0,1-AJ57/AI57,AJ57/AI57-1) -> -0.63485744 | AK60: =+IF(AJ57<0,1-AK57/AJ57,AK57/AJ57-1) -> -0.42349631 | AL60: =+IF(AK57<0,1-AL57/AK57,AL57/AK57-1) -> 3.4118365 | AM60: =+IF(AL57<0,1-AM57/AL57,AM57/AL57-1) -> -0.43839026 | AN60: =+IF(AM57<0,1-AN57/AM57,AN57/AM57-1) -> 0.043585324 | AO60: =+IF(AN57<0,1-AO57/AN57,AO57/AN57-1) -> 0.36078339 | AP60: =+IF(AO57<0,1-AP57/AO57,AP57/AO57-1) -> 0.44980059 | AQ60: =+IF(AP57<0,1-AQ57/AP57,AQ57/AP57-1) -> 0.31335965 | ... CL60: =+IF(CK57<0,1-CL57/CK57,CL57/CK57-1) -> 0.04423171 | CM60: =+CM57/CL57-1 -> 0.16786341 | CN60: =+CN57/CM57-1 -> -0.43205255 | CO60: =+CO57/CN57-1 -> 0.39960985 | CP60: =+CP57/CO57-1 -> 0.81111597 | CQ60: =+CQ57/CP57-1 -> -0.039362687 | CR60: =+CR57/CQ57-1 -> -0.4650062 | CS60: =+CS57/CR57-1 -> 0.2263635 | CT60: =+CT57/CS57-1 -> 0.84835391 | ... DB60: =+DB57/DA57-1 -> 0.84594191 | DF60: 1.1220584
A61: Minority Interest | B61: ='Annual Raw'!C32 -> 0 | C61: ='Annual Raw'!D32 -> 0 | D61: ='Annual Raw'!E32 -> 0.1324 | E61: ='Annual Raw'!F32 -> 0.0497 | F61: ='Annual Raw'!G32 -> -0.0177 | G61: ='Annual Raw'!H32 -> -0.0335 | H61: ='Annual Raw'!I32 -> -0.1753 | I61: ='Annual Raw'!J32 -> -0.1174 | ... AA61: ='Annual Raw'!AB32 -> 5.88 | AB61: =+SUM(CM61:CP61) -> 11 | AC61: =+SUM(CQ61:CT61) -> 11 | AD61: =+SUM(CU61:CX61) -> 11 | AE61: =+SUM(CY61:DB61) -> 11 | AI61: ='QTR Raw'!C34 -> 0.15 | AJ61: ='QTR Raw'!D34 -> -0.04 | AK61: ='QTR Raw'!E34 -> 0.67 | AL61: ='QTR Raw'!F34 -> -0.07 | AM61: ='QTR Raw'!G34 -> 0.22 | AN61: ='QTR Raw'!H34 -> -0.1 | AO61: ='QTR Raw'!I34 -> 0 | AP61: ='QTR Raw'!J34 -> -0.57 | ... CL61: ='QTR Raw'!BF34 -> 2.75 | CM61: =+CL61 -> 2.75 | CN61: =+CM61 -> 2.75 | CO61: =+CN61 -> 2.75 | CP61: =+CO61 -> 2.75 | CQ61: =+CP61 -> 2.75 | CR61: =+CQ61 -> 2.75 | CS61: =+CR61 -> 2.75 | CT61: =+CS61 -> 2.75 | ... DB61: =+DA61 -> 2.75 | DF61: 0.49
A62: Share of Associate | B62: ='Annual Raw'!C33+'Annual Raw'!C28 -> 0 | C62: ='Annual Raw'!D33+'Annual Raw'!D28 -> 0 | D62: ='Annual Raw'!E33+'Annual Raw'!E28 -> -0.1596 | E62: ='Annual Raw'!F33+'Annual Raw'!F28 -> 0 | F62: ='Annual Raw'!G33+'Annual Raw'!G28 -> 0 | G62: ='Annual Raw'!H33+'Annual Raw'!H28 -> 0 | H62: ='Annual Raw'!I33+'Annual Raw'!I28 -> 0.0432 | I62: ='Annual Raw'!J33+'Annual Raw'!J28 -> 0.2015 | ... AA62: ='Annual Raw'!AB33+'Annual Raw'!AB28 -> -130.57 | AB62: =+SUM(CM62:CP62) -> -144.04 | AC62: =+SUM(CQ62:CT62) -> -144.04 | AD62: =+SUM(CU62:CX62) -> -144.04 | AE62: =+SUM(CY62:DB62) -> -144.04 | AI62: ='QTR Raw'!C35 -> 0 | AJ62: ='QTR Raw'!D35 -> 0 | AK62: ='QTR Raw'!E35 -> 0 | AL62: ='QTR Raw'!F35 -> 0 | AM62: ='QTR Raw'!G35 -> 0 | AN62: ='QTR Raw'!H35 -> 0 | AO62: ='QTR Raw'!I35 -> 0 | AP62: ='QTR Raw'!J35 -> 0 | ... CL62: ='QTR Raw'!BF35 -> -36.01 | CM62: =+CL62 -> -36.01 | CN62: =+CM62 -> -36.01 | CO62: =+CN62 -> -36.01 | CP62: =+CO62 -> -36.01 | CQ62: =+CP62 -> -36.01 | CR62: =+CQ62 -> -36.01 | CS62: =+CR62 -> -36.01 | CT62: =+CS62 -> -36.01 | ... DB62: =+DA62 -> -36.01 | DF62: -32.16
A63: Exceptional Income / Expenses | B63: ='Annual Raw'!C29+'Annual Raw'!C31+'Annual Raw'!C34+'Annual Raw'!C36 -> -11.466 | C63: ='Annual Raw'!D29+'Annual Raw'!D31+'Annual Raw'!D34+'Annual Raw'!D36 -> 5.5109 | D63: ='Annual Raw'!E29+'Annual Raw'!E31+'Annual Raw'!E34+'Annual Raw'!E36 -> 5.2744 | E63: ='Annual Raw'!F29+'Annual Raw'!F31+'Annual Raw'!F34+'Annual Raw'!F36 -> 8.3426 | F63: ='Annual Raw'!G29+'Annual Raw'!G31+'Annual Raw'!G34+'Annual Raw'!G36 -> 5.1571 | G63: ='Annual Raw'!H29+'Annual Raw'!H31+'Annual Raw'!H34+'Annual Raw'!H36 -> -26.191 | H63: ='Annual Raw'!I29+'Annual Raw'!I31+'Annual Raw'!I34+'Annual Raw'!I36 -> 69.6393 | I63: ='Annual Raw'!J29+'Annual Raw'!J31+'Annual Raw'!J34+'Annual Raw'!J36 -> 31.5886 | ... AA63: ='Annual Raw'!AB29+'Annual Raw'!AB31+'Annual Raw'!AB34+'Annual Raw'!AB36 -> -26.49 | AB63: =+SUM(CM63:CP63) -> 0 | AC63: =+SUM(CQ63:CT63) -> 0 | AD63: =+SUM(CU63:CX63) -> 0 | AE63: =+SUM(CY63:DB63) -> 0 | AI63: ='QTR Raw'!C26+'QTR Raw'!C31+'QTR Raw'!C32+'QTR Raw'!C33+'QTR Raw'!C36+'QTR Raw'!C37+'QTR Raw'!C39 -> 1.11 | AJ63: ='QTR Raw'!D26+'QTR Raw'!D31+'QTR Raw'!D32+'QTR Raw'!D33+'QTR Raw'!D36+'QTR Raw'!D37+'QTR Raw'!D39 -> 14.54 | AK63: ='QTR Raw'!E26+'QTR Raw'!E31+'QTR Raw'!E32+'QTR Raw'!E33+'QTR Raw'!E36+'QTR Raw'!E37+'QTR Raw'!E39 -> 59.75 | AL63: ='QTR Raw'!F26+'QTR Raw'!F31+'QTR Raw'!F32+'QTR Raw'!F33+'QTR Raw'!F36+'QTR Raw'!F37+'QTR Raw'!F39 -> -63.32 | AM63: ='QTR Raw'!G26+'QTR Raw'!G31+'QTR Raw'!G32+'QTR Raw'!G33+'QTR Raw'!G36+'QTR Raw'!G37+'QTR Raw'!G39 -> -0.08 | AN63: ='QTR Raw'!H26+'QTR Raw'!H31+'QTR Raw'!H32+'QTR Raw'!H33+'QTR Raw'!H36+'QTR Raw'!H37+'QTR Raw'!H39 -> 0 | AO63: ='QTR Raw'!I26+'QTR Raw'!I31+'QTR Raw'!I32+'QTR Raw'!I33+'QTR Raw'!I36+'QTR Raw'!I37+'QTR Raw'!I39 -> 4.25 | AP63: ='QTR Raw'!J26+'QTR Raw'!J31+'QTR Raw'!J32+'QTR Raw'!J33+'QTR Raw'!J36+'QTR Raw'!J37+'QTR Raw'!J39 -> 17.37 | ... CL63: ='QTR Raw'!BF26+'QTR Raw'!BF31+'QTR Raw'!BF32+'QTR Raw'!BF33+'QTR Raw'!BF36+'QTR Raw'!BF37+'QTR Raw'!BF39 -> 0 | DF63: -26.49
A64: Consolidated Net Profit | B64: =B57+B61+B62+B63 -> 5.5801 | C64: =C57+C61+C62+C63 -> 25.8104 | D64: =D57+D61+D62+D63 -> 29.7165 | E64: =E57+E61+E62+E63 -> 40.3622 | F64: =F57+F61+F62+F63 -> 52.2509 | G64: =G57+G61+G62+G63 -> 73.6526 | H64: =H57+H61+H62+H63 -> 201.5797 | I64: =I57+I61+I62+I63 -> 207.6803 | ... AE64: =AE57+AE61+AE62+AE63 -> 949.62614 | AI64: =AI57+AI61+AI62+AI63 -> 79.12 | AJ64: =AJ57+AJ61+AJ62+AJ63 -> 42.93 | AK64: =AK57+AK61+AK62+AK63 -> 76.81 | AL64: =AL57+AL61+AL62+AL63 -> 8.92 | AM64: =AM57+AM61+AM62+AM63 -> 40.75 | AN64: =AN57+AN61+AN62+AN63 -> 42.28 | AO64: =AO57+AO61+AO62+AO63 -> 61.92 | AP64: =AP57+AP61+AP62+AP63 -> 100.41 | ... DB64: =DB57+DB61+DB62+DB63 -> 345.5292 | DF64: 272.01778
A65: Profit & Loss- Annual (End)
A67: Ace - PAT | B67: ='Annual Raw'!C35 -> 5.5801 | C67: ='Annual Raw'!D35 -> 25.8104 | D67: ='Annual Raw'!E35 -> 29.7165 | E67: ='Annual Raw'!F35 -> 40.3622 | F67: ='Annual Raw'!G35 -> 52.2509 | G67: ='Annual Raw'!H35 -> 73.6526 | H67: ='Annual Raw'!I35 -> 201.5797 | I67: ='Annual Raw'!J35 -> 207.6803 | ... AA67: ='Annual Raw'!AB35 -> 375.88 | AB67: =+AB64 -> 530.59624 | AC67: =+AC64 -> 688.5261 | AD67: =+AD64 -> 811.8449 | AE67: =+AE64 -> 949.62614 | AI67: ='QTR Raw'!C42 -> 79.12 | AJ67: ='QTR Raw'!D42 -> 42.93 | AK67: ='QTR Raw'!E42 -> 76.81 | AL67: ='QTR Raw'!F42 -> 8.92 | AM67: ='QTR Raw'!G42 -> 40.75 | AN67: ='QTR Raw'!H42 -> 42.28 | AO67: ='QTR Raw'!I42 -> 61.92 | AP67: ='QTR Raw'!J42 -> 100.41 | ... CL67: ='QTR Raw'!BF42 -> 116.18 | DF67: 375.88
A68: Checksum - PAT | B68: =B67-B64 -> 1.7763568e-14 | C68: =C67-C64 -> 1.1013412e-13 | D68: =D67-D64 -> -9.2370556e-14 | E68: =E67-E64 -> 7.1054274e-14 | F68: =F67-F64 -> 0 | G68: =G67-G64 -> 1.4210855e-13 | H68: =H67-H64 -> 0 | I68: =I67-I64 -> 0 | ... AE68: =AE67-AE64 -> 0 | AI68: =AI67-AI64 -> 0 | AJ68: =AJ67-AJ64 -> 0 | AK68: =AK67-AK64 -> 0 | AL68: =AL67-AL64 -> -1.2256862e-13 | AM68: =AM67-AM64 -> 0 | AN68: =AN67-AN64 -> -9.2370556e-14 | AO68: =AO67-AO64 -> 6.3948846e-14 | AP68: =AP67-AP64 -> 1.4210855e-13 | ... CL68: =CL67-CL64 -> 1.4210855e-13 | DF68: 0
A69: Ratios (Start)
A70: ROE (%) | B70: =(B64-B63)/B136 -> 0.10992328 | C70: =(C64-C63)/C136 -> 0.097624023 | D70: =(D64-D63)/D136 -> 0.13110724 | E70: =(E64-E63)/E136 -> 0.1490694 | F70: =(F64-F63)/F136 -> 0.21451076 | G70: =(G64-G63)/G136 -> 0.36793156 | H70: =(H64-H63)/H136 -> 0.3113712 | I70: =(I64-I63)/I136 -> 0.30506691 | ... AE70: =(AE64-AE63)/AE136 -> 0.10149044 | AL70: =(SUM(AI64:AL64)-SUM(AI63:AL63))/AL136 -> 0.12038484 | AM70: =(SUM(AJ64:AM64)-SUM(AJ63:AM63))/AM136 -> 0.095128933 | AN70: =(SUM(AK64:AN64)-SUM(AK63:AN63))/AN136 -> 0.09956745 | AO70: =(SUM(AL64:AO64)-SUM(AL63:AO63))/AO136 -> 0.11877269 | AP70: =(SUM(AM64:AP64)-SUM(AM63:AP63))/AP136 -> 0.12302399 | AQ70: =(SUM(AN64:AQ64)-SUM(AN63:AQ63))/AQ136 -> 0.15117901 | AR70: =(SUM(AO64:AR64)-SUM(AO63:AR63))/AR136 -> 0.15177973 | AS70: =(SUM(AP64:AS64)-SUM(AP63:AS63))/AS136 -> 0.14644086 | ... DB70: =(SUM(CY64:DB64)-SUM(CY63:DB63))/DB136 -> 0.10149044 | DF70: 0.082993054
A71: ROCE (%) | B71: =+B50/B145 -> 0.043854117 | C71: =+C50/C145 -> 0.02280034 | D71: =+D50/D145 -> 0.05819102 | E71: =+E50/E145 -> 0.078811224 | F71: =+F50/F145 -> 0.11409687 | G71: =+G50/G145 -> 0.26952976 | H71: =+H50/H145 -> 0.2099836 | I71: =+I50/I145 -> 0.36270894 | ... AE71: =+AE50/AE145 -> 0.16065395 | AL71: =+SUM(AI50:AL50)/AL145 -> 0.11381651 | AM71: =+SUM(AJ50:AM50)/AM145 -> 0.089671139 | AN71: =+SUM(AK50:AN50)/AN145 -> 0.087511138 | AO71: =+SUM(AL50:AO50)/AO145 -> 0.10645818 | AP71: =+SUM(AM50:AP50)/AP145 -> 0.11486954 | AQ71: =+SUM(AN50:AQ50)/AQ145 -> 0.14611205 | AR71: =+SUM(AO50:AR50)/AR145 -> 0.1630472 | AS71: =+SUM(AP50:AS50)/AS145 -> 0.15057863 | ... DB71: =+SUM(CY50:DB50)/DB145 -> 0.16065395 | DF71: 0.083495885
A72: Ratios (End)
A73: Checksum Of qtr to Annual
A74: Revenue - Checksum Of qtr to Annual | N74: =N26-SUM(AI26:AL26) -> 9.9999999e-05 | O74: =O26-SUM(AM26:AP26) -> 0.0049 | P74: =P26-SUM(AQ26:AT26) -> -0.0034 | Q74: =Q26-SUM(AU26:AX26) -> -0.0049 | R74: =R26-SUM(AY26:BB26) -> 0 | S74: =S26-SUM(BC26:BF26) -> 0 | T74: =T26-SUM(BG26:BJ26) -> 0 | U74: =U26-SUM(BK26:BN26) -> 0 | V74: =V26-SUM(BO26:BR26) -> 0 | W74: =W26-SUM(BS26:BV26) -> 0 | X74: =X26-SUM(BW26:BZ26) -> 0 | Y74: =Y26-SUM(CA26:CD26) -> 0 | Z74: =Z26-SUM(CE26:CH26) -> -0.01 | AA74: =AA26-SUM(CF26:CI26) -> -185.86 | AB74: =AB26-SUM(CM26:CP26) -> 0 | AC74: =AC26-SUM(CQ26:CT26) -> 0 | AD74: =AD26-SUM(CU26:CX26) -> 0 | AE74: =AE26-SUM(CY26:DB26) -> 0 | DF74: 0
A75: GP - Checksum Of qtr to Annual | N75: =N32-SUM(AI32:AL32) -> 0.0055 | O75: =O32-SUM(AM32:AP32) -> -0.0032 | P75: =P32-SUM(AQ32:AT32) -> 0.0002 | Q75: =Q32-SUM(AU32:AX32) -> -0.0089 | R75: =R32-SUM(AY32:BB32) -> 0 | S75: =S32-SUM(BC32:BF32) -> 0 | T75: =T32-SUM(BG32:BJ32) -> 0 | U75: =U32-SUM(BK32:BN32) -> 0 | V75: =V32-SUM(BO32:BR32) -> 0 | W75: =W32-SUM(BS32:BV32) -> 0 | X75: =X32-SUM(BW32:BZ32) -> 0 | Y75: =Y32-SUM(CA32:CD32) -> 0 | Z75: =Z32-SUM(CE32:CH32) -> -0.01 | AA75: =AA32-SUM(CF32:CI32) -> -107.89 | AB75: =AB32-SUM(CM32:CP32) -> 0 | AC75: =AC32-SUM(CQ32:CT32) -> 0 | AD75: =AD32-SUM(CU32:CX32) -> 0 | AE75: =AE32-SUM(CY32:DB32) -> 0 | DF75: 0
A76: EBITDA - Checksum Of qtr to Annual | N76: =N44-SUM(AI44:AL44) -> -5.9291 | O76: =O44-SUM(AM44:AP44) -> 0.0016 | P76: =P44-SUM(AQ44:AT44) -> -0.0022 | Q76: =Q44-SUM(AU44:AX44) -> 0.0016 | R76: =R44-SUM(AY44:BB44) -> -11.45 | S76: =S44-SUM(BC44:BF44) -> -10.99 | T76: =T44-SUM(BG44:BJ44) -> -11.17 | U76: =U44-SUM(BK44:BN44) -> -0.71 | V76: =V44-SUM(BO44:BR44) -> 0 | W76: =W44-SUM(BS44:BV44) -> 0 | X76: =X44-SUM(BW44:BZ44) -> 9.094947e-13 | Y76: =Y44-SUM(CA44:CD44) -> -1.74 | Z76: =Z44-SUM(CE44:CH44) -> 2.2737368e-12 | AA76: =AA44-SUM(CF44:CI44) -> -268.81 | AB76: =AB44-SUM(CM44:CP44) -> 0 | AC76: =AC44-SUM(CQ44:CT44) -> 0 | AD76: =AD44-SUM(CU44:CX44) -> -2.7284841e-12 | AE76: =AE44-SUM(CY44:DB44) -> 0 | DF76: 0
A77: PAT - Checksum Of qtr to Annual | N77: =N64-SUM(AI64:AL64) -> 7.9177 | O77: =O64-SUM(AM64:AP64) -> -0.0029 | P77: =P64-SUM(AQ64:AT64) -> 0.0069 | Q77: =Q64-SUM(AU64:AX64) -> 0.9832 | R77: =R64-SUM(AY64:BB64) -> 0 | S77: =S64-SUM(BC64:BF64) -> 0 | T77: =T64-SUM(BG64:BJ64) -> 0 | U77: =U64-SUM(BK64:BN64) -> 9.094947e-13 | V77: =V64-SUM(BO64:BR64) -> 0 | W77: =W57-SUM(BS57:BV57) -> 0 | X77: =X57-SUM(BW57:BZ57) -> 8.5265128e-13 | Y77: =Y57-SUM(CA57:CD57) -> -1.8758328e-12 | Z77: =Z57-SUM(CE57:CH57) -> 2.5011104e-12 | AA77: =AA57-SUM(CF57:CI57) -> -235.36 | AB77: =AB57-SUM(CM57:CP57) -> 1.5916157e-12 | AC77: =AC57-SUM(CQ57:CT57) -> 1.4779289e-12 | AD77: =AD57-SUM(CU57:CX57) -> -2.9558578e-12 | AE77: =AE57-SUM(CY57:DB57) -> 0 | DF77: 0
A78: Valuation (Start)
A79: Eq | B79: ='Annual Raw'!C104 -> 33.0539 | C79: ='Annual Raw'!D104 -> 33.0539 | D79: ='Annual Raw'!E104 -> 33.0539 | E79: =+F79 -> 0 | F79: =+G79 -> 0 | G79: =+H79 -> 0 | H79: =+I79 -> 0 | I79: =+J79 -> 0 | J79: =+K79 -> 0 | K79: =+L79 -> 0 | L79: =+M79 -> 0 | ... AA79: =+AB79 -> 0 | AB79: =AA79 -> 0 | AC79: =AB79 -> 0 | AD79: =AC79 -> 0 | AE79: =AD79 -> 0 | AI79: =+AJ79 -> 33.08 | AJ79: =+AK79 -> 33.08 | AK79: =+AL79 -> 33.08 | AL79: =+AM79 -> 33.08 | AM79: =+AN79 -> 33.08 | AN79: =+AO79 -> 33.08 | AO79: =+AP79 -> 33.08 | AP79: =+AQ79 -> 33.08 | ... CI79: =+CJ79 -> 33.08 | CJ79: ='QTR Raw'!BD45 -> 33.08 | CK79: ='QTR Raw'!BE45 -> 33.08 | CL79: ='QTR Raw'!BF45 -> 33.08 | CM79: =+CL79 -> 33.08 | CN79: =+CM79 -> 33.08 | CO79: =+CN79 -> 33.08 | CP79: =+CO79 -> 33.08 | CQ79: =+CP79 -> 33.08 | CR79: =+CQ79 -> 33.08 | CS79: =+CR79 -> 33.08 | CT79: =+CS79 -> 33.08 | ... DB79: =+DA79 -> 33.08 | DF79: 33.08
A80: FV | B80: ='Annual Raw'!C105 -> 10 | C80: ='Annual Raw'!D105 -> 10 | D80: ='Annual Raw'!E105 -> 10 | E80: =+F80 -> 0 | F80: =+G80 -> 0 | G80: =+H80 -> 0 | H80: =+I80 -> 0 | I80: =+J80 -> 0 | J80: =+K80 -> 0 | K80: =+L80 -> 0 | L80: =+M80 -> 0 | ... AA80: =+AB80 -> 0 | AB80: =AA80 -> 0 | AC80: =AB80 -> 0 | AD80: =AC80 -> 0 | AE80: =AD80 -> 0 | AI80: =AJ80 -> 1 | AJ80: =AK80 -> 1 | AK80: =AL80 -> 1 | AL80: =AM80 -> 1 | AM80: =AN80 -> 1 | AN80: =AO80 -> 1 | AO80: =AP80 -> 1 | AP80: =AQ80 -> 1 | ... CI80: =CJ80 -> 1 | CJ80: ='QTR Raw'!BD46 -> 1 | CK80: ='QTR Raw'!BE46 -> 1 | CL80: ='QTR Raw'!BF46 -> 1 | CM80: =+CL80 -> 1 | CN80: =+CM80 -> 1 | CO80: =+CN80 -> 1 | CP80: =+CO80 -> 1 | CQ80: =+CP80 -> 1 | CR80: =+CQ80 -> 1 | CS80: =+CR80 -> 1 | CT80: =+CS80 -> 1 | ... DB80: =+DA80 -> 1 | DF80: 1
A81: No of share | B81: =B79/B80 -> 3.30539 | C81: =C79/C80 -> 3.30539 | D81: =D79/D80 -> 3.30539 | E81: =E79/E80 -> #DIV/0! | F81: =F79/F80 -> #DIV/0! | G81: =G79/G80 -> #DIV/0! | H81: =H79/H80 -> #DIV/0! | I81: =I79/I80 -> #DIV/0! | ... AE81: =AE79/AE80 -> #DIV/0! | AI81: =AI79/AI80 -> 33.08 | AJ81: =AJ79/AJ80 -> 33.08 | AK81: =AK79/AK80 -> 33.08 | AL81: =AL79/AL80 -> 33.08 | AM81: =AM79/AM80 -> 33.08 | AN81: =AN79/AN80 -> 33.08 | AO81: =AO79/AO80 -> 33.08 | AP81: =AP79/AP80 -> 33.08 | ... DB81: =DB79/DB80 -> 33.08 | DF81: 33.08
A82: EPS | B82: =(B64-B63)/B81 -> 5.1570616 | C82: =(C64-C63)/C81 -> 6.1413328 | D82: =(D64-D63)/D81 -> 7.3946191 | E82: =(E64-E63)/E81 -> #DIV/0! | F82: =(F64-F63)/F81 -> #DIV/0! | G82: =(G64-G63)/G81 -> #DIV/0! | H82: =(H64-H63)/H81 -> #DIV/0! | I82: =(I64-I63)/I81 -> #DIV/0! | ... AE82: =(AE64-AE63)/AE81 -> #DIV/0! | AI82: =(AI64-AI63)/AI81 -> 2.3582225 | AJ82: =(AJ64-AJ63)/AJ81 -> 0.85822249 | AK82: =(AK64-AK63)/AK81 -> 0.51571947 | AL82: =(AL64-AL63)/AL81 -> 2.1837969 | AM82: =(AM64-AM63)/AM81 -> 1.2342805 | AN82: =(AN64-AN63)/AN81 -> 1.2781137 | AO82: =(AO64-AO63)/AO81 -> 1.7433495 | AP82: =(AP64-AP63)/AP81 -> 2.5102781 | ... DB82: =(DB64-DB63)/DB81 -> 10.44526 | DF82: 8.2230283
A83: DPS | B83: ='Annual Raw'!C110 -> 0.12 | C83: ='Annual Raw'!D110 -> 0.18 | D83: ='Annual Raw'!E110 -> 0.25 | E83: ='Annual Raw'!F110 -> 0.3 | F83: ='Annual Raw'!G110 -> 0.5 | G83: ='Annual Raw'!H110 -> 0.6 | H83: ='Annual Raw'!I110 -> 1 | I83: ='Annual Raw'!J110 -> 1.35 | ... AA83: ='Annual Raw'!AB110 -> 4
A84: DPS % of EPS | B84: =B83/B82 -> 0.023269064 | C84: =C83/C82 -> 0.029309599 | D84: =D83/D82 -> 0.033808368 | E84: =E83/E82 -> #DIV/0! | F84: =F83/F82 -> #DIV/0! | G84: =G83/G82 -> #DIV/0! | H84: =H83/H82 -> #DIV/0! | I84: =I83/I82 -> #DIV/0! | ... AE84: =AE83/AE82 -> #DIV/0! | DF84: 0
A85: EPS TTM | B85: =+B82 -> 5.1570616 | C85: =+C82 -> 6.1413328 | D85: =+D82 -> 7.3946191 | E85: =+E82 -> #DIV/0! | F85: =+F82 -> #DIV/0! | G85: =+G82 -> #DIV/0! | H85: =+H82 -> #DIV/0! | I85: =+I82 -> #DIV/0! | ... AE85: =+AE82 -> #DIV/0! | AL85: =SUM(AI82:AL82) -> 5.9159613 | AM85: =SUM(AJ82:AM82) -> 4.7920193 | AN85: =SUM(AK82:AN82) -> 5.2119105 | AO85: =SUM(AL82:AO82) -> 6.4395405 | AP85: =SUM(AM82:AP82) -> 6.7660218 | AQ85: =SUM(AN82:AQ82) -> 8.8125756 | AR85: =SUM(AO82:AR82) -> 9.0438331 | AS85: =SUM(AP82:AS82) -> 9.2010278 | ... DB85: =SUM(CY82:DB82) -> 28.706957 | DF85: 16.874479
A86: EPS Growth YoY % | C86: =+C85/B85-1 -> 0.19085891 | D86: =+D85/C85-1 -> 0.20407399 | E86: =+E85/D85-1 -> #DIV/0! | F86: =+F85/E85-1 -> #DIV/0! | G86: =+G85/F85-1 -> #DIV/0! | H86: =+H85/G85-1 -> #DIV/0! | I86: =+I85/H85-1 -> #DIV/0! | J86: =+J85/I85-1 -> #DIV/0! | ... AE86: =+AE85/AD85-1 -> #DIV/0! | AP86: =+IF(AL85<0,1-AP85/AL85,AP85/AL85-1) -> 0.14368932 | AQ86: =+IF(AM85<0,1-AQ85/AM85,AQ85/AM85-1) -> 0.83901085 | AR86: =+IF(AN85<0,1-AR85/AN85,AR85/AN85-1) -> 0.73522417 | AS86: =+IF(AO85<0,1-AS85/AO85,AS85/AO85-1) -> 0.42883297 | AT86: =+IF(AP85<0,1-AT85/AP85,AT85/AP85-1) -> 0.51076758 | AU86: =+IF(AQ85<0,1-AU85/AQ85,AU85/AQ85-1) -> 0.13937294 | AV86: =+IF(AR85<0,1-AV85/AR85,AV85/AR85-1) -> 0.16816526 | AW86: =+IF(AS85<0,1-AW85/AS85,AW85/AS85-1) -> 0.12120117 | ... DB86: =+IF(CX85<0,1-DB85/CX85,DB85/CX85-1) -> 0.16971374 | DF86: -0.33654899
A87: Bloomberg Estimate | CP87: 29.3 | CT87: 37.3 | DF87: 17
A88: Estimate deviation | CP88: =+CP85/CP87-1 -> -0.45256691 | CT88: =+CT85/CT87-1 -> -0.44198474 | DF88: -0.0073835683
A89: Promoter Share holding % | B89: ='Annual Raw'!C112 -> 20.04 | C89: ='Annual Raw'!D112 -> 24.85 | D89: ='Annual Raw'!E112 -> 25.69 | E89: ='Annual Raw'!F112 -> 27.74 | F89: ='Annual Raw'!G112 -> 27.74 | G89: ='Annual Raw'!H112 -> 27.56 | H89: ='Annual Raw'!I112 -> 27.61 | I89: ='Annual Raw'!J112 -> 27.55 | ... AA89: ='Annual Raw'!AB112 -> 30.3 | AI89: ='QTR Raw'!C49 -> 30.15 | AJ89: ='QTR Raw'!D49 -> 30.15 | AK89: ='QTR Raw'!E49 -> 30.15 | AL89: ='QTR Raw'!F49 -> 30.15 | AM89: ='QTR Raw'!G49 -> 30.15 | AN89: ='QTR Raw'!H49 -> 30.15 | AO89: ='QTR Raw'!I49 -> 30.3 | AP89: ='QTR Raw'!J49 -> 30.3 | ... CL89: ='QTR Raw'!BF49 -> 30.3
A90: Pledge Share % | B90: ='Annual Raw'!C113 -> 0 | C90: ='Annual Raw'!D113 -> 0 | D90: ='Annual Raw'!E113 -> 0 | E90: ='Annual Raw'!F113 -> 0 | F90: ='Annual Raw'!G113 -> 0 | G90: ='Annual Raw'!H113 -> 0 | H90: ='Annual Raw'!I113 -> 0 | I90: ='Annual Raw'!J113 -> 0 | ... AA90: ='Annual Raw'!AB113 -> 0 | AI90: ='QTR Raw'!C50 -> 0 | AJ90: ='QTR Raw'!D50 -> 0 | AK90: ='QTR Raw'!E50 -> 0 | AL90: ='QTR Raw'!F50 -> 0 | AM90: ='QTR Raw'!G50 -> 0 | AN90: ='QTR Raw'!H50 -> 0 | AO90: ='QTR Raw'!I50 -> 0 | AP90: ='QTR Raw'!J50 -> 0 | ... CL90: ='QTR Raw'!BF50 -> 0
A92: Share Price
A93: Share Price - Close | B93: ='Annual Raw'!C106 -> 4 | C93: ='Annual Raw'!D106 -> 4.88 | D93: ='Annual Raw'!E106 -> 5.16 | E93: ='Annual Raw'!F106 -> 11.54 | F93: ='Annual Raw'!G106 -> 22.84 | G93: ='Annual Raw'!H106 -> 100.475 | H93: ='Annual Raw'!I106 -> 84.8 | I93: ='Annual Raw'!J106 -> 177.95 | ... AA93: ='Annual Raw'!AB106 -> 1270.25 | AB93: =+CP93 -> 1389 | AC93: =+CT93 -> 1389 | AD93: =+CX93 -> 1389 | AE93: =+DB93 -> 1389 | AJ93: ='QTR Share Price'!HP21 -> 124.6 | AK93: ='QTR Share Price'!HQ21 -> 105.85 | AL93: ='QTR Share Price'!HR21 -> 75.45 | AM93: ='QTR Share Price'!HS21 -> 80.95 | AN93: ='QTR Share Price'!HT21 -> 73.95 | AO93: ='QTR Share Price'!HU21 -> 115.8 | AP93: ='QTR Share Price'!HV21 -> 160.95 | AQ93: ='QTR Share Price'!HW21 -> 218.2 | ... CL93: ='QTR Share Price'!JR21 -> 1270.25 | CM93: 1389 | CN93: =+CM93 -> 1389 | CO93: =+CN93 -> 1389 | CP93: =+CO93 -> 1389 | CQ93: =+CP93 -> 1389 | CR93: =+CQ93 -> 1389 | CS93: =+CR93 -> 1389 | CT93: =+CS93 -> 1389 | CU93: =+CT93 -> 1389 | ... DB93: =+DA93 -> 1389 | DF93: 1270.25
A94: Share Price - High | B94: ='Annual Raw'!C107 -> 6 | C94: ='Annual Raw'!D107 -> 5.65 | D94: ='Annual Raw'!E107 -> 6.55 | E94: ='Annual Raw'!F107 -> 15.9 | F94: ='Annual Raw'!G107 -> 24.79 | G94: ='Annual Raw'!H107 -> 108.84 | H94: ='Annual Raw'!I107 -> 120.5 | I94: ='Annual Raw'!J107 -> 266.9 | ... AA94: ='Annual Raw'!AB107 -> 1582 | AB94: =+MAX(CM94:CP94) -> 2086.1477 | AC94: =+MAX(CQ94:CT94) -> 2707.0813 | AD94: =+MAX(CU94:CX94) -> 3191.9344 | AE94: =+MAX(CY94:DB94) -> 3733.6495 | AJ94: ='QTR Share Price'!HP19 -> 138.5 | AK94: ='QTR Share Price'!HQ19 -> 127.25 | AL94: ='QTR Share Price'!HR19 -> 110.65 | AM94: ='QTR Share Price'!HS19 -> 96.75 | AN94: ='QTR Share Price'!HT19 -> 86.7 | AO94: ='QTR Share Price'!HU19 -> 124.5 | AP94: ='QTR Share Price'!HV19 -> 164.35 | AQ94: ='QTR Share Price'!HW19 -> 233.05 | ... CL94: ='QTR Share Price'!JR19 -> 1582 | CM94: =+CM85*CM102 -> 1585.167 | CN94: =+CN85*CN102 -> 1709.2961 | CO94: =+CO85*CO102 -> 1685.8284 | CP94: =+CP85*CP102 -> 2086.1477 | CQ94: =+CQ85*CQ102 -> 2348.9528 | CR94: =+CR85*CR102 -> 2466.9397 | CS94: =+CS85*CS102 -> 2544.1177 | CT94: =+CT85*CT102 -> 2707.0813 | ... DB94: =+DB85*DB102 -> 3733.6495 | DF94: 1582
A95: Share Price - Low | B95: ='Annual Raw'!C108 -> 2.6 | C95: ='Annual Raw'!D108 -> 3.105 | D95: ='Annual Raw'!E108 -> 4.16 | E95: ='Annual Raw'!F108 -> 5 | F95: ='Annual Raw'!G108 -> 9.73 | G95: ='Annual Raw'!H108 -> 21.835 | H95: ='Annual Raw'!I108 -> 63.51 | I95: ='Annual Raw'!J108 -> 79.4 | ... AA95: ='Annual Raw'!AB108 -> 1172.2 | AB95: =+MIN(CM95:CP95) -> 1224.9473 | AC95: =+MIN(CQ95:CT95) -> 1815.1674 | AD95: =+MIN(CU95:CX95) -> 2218.2865 | AE95: =+MIN(CY95:DB95) -> 2598.0163 | AJ95: =+'QTR Share Price'!HP20 -> 98.55 | AK95: =+'QTR Share Price'!HQ20 -> 100.9 | AL95: =+'QTR Share Price'!HR20 -> 73.25 | AM95: =+'QTR Share Price'!HS20 -> 75.1 | AN95: =+'QTR Share Price'!HT20 -> 62.7 | AO95: =+'QTR Share Price'!HU20 -> 74 | AP95: =+'QTR Share Price'!HV20 -> 97.05 | AQ95: =+'QTR Share Price'!HW20 -> 148.5 | ... CL95: =+'QTR Share Price'!JR20 -> 1222.5 | CM95: =+CM103*CM85 -> 1224.9473 | CN95: =+CN103*CN85 -> 1320.8688 | CO95: =+CO103*CO85 -> 1302.7341 | CP95: =+CP103*CP85 -> 1612.0832 | CQ95: =+CQ103*CQ85 -> 1815.1674 | CR95: =+CR103*CR85 -> 1906.3425 | CS95: =+CS103*CS85 -> 1965.9822 | CT95: =+CT103*CT85 -> 2091.9133 | ... DB95: =+DB103*DB85 -> 2885.2001 | DF95: 1222.5
A97: Upside (%) | AB97: =+AB94/AB93-1 -> 0.5019062 | AC97: =+AC94/AC93-1 -> 0.9489426 | AD97: =+AD94/AD93-1 -> 1.2980089 | AE97: =+AE94/AE93-1 -> 1.6880126 | CM97: =+CM94/CM93-1 -> 0.14122895 | CN97: =+CN94/CN93-1 -> 0.23059476 | CO97: =+CO94/CO93-1 -> 0.21369939 | CP97: =+CP94/CP93-1 -> 0.5019062 | CQ97: =+CQ94/CQ93-1 -> 0.69111074 | CR97: =+CR94/CR93-1 -> 0.77605449 | CS97: =+CS94/CS93-1 -> 0.83161818 | CT97: =+CT94/CT93-1 -> 0.9489426 | ... DB97: =+DB94/DB93-1 -> 1.6880126 | DF97: 0.24542413
A98: Downside (%) | AB98: =+AB95/AB93-1 -> -0.11810847 | AC98: =+AC95/AC93-1 -> 0.30681598 | AD98: =+AD95/AD93-1 -> 0.59703852 | AE98: =+AE95/AE93-1 -> 0.87042211 | CM98: =+CM95/CM93-1 -> -0.11810847 | CN98: =+CN95/CN93-1 -> -0.049050513 | CO98: =+CO95/CO93-1 -> -0.06210651 | CP98: =+CP95/CP93-1 -> 0.16060703 | CQ98: =+CQ95/CQ93-1 -> 0.30681598 | CR98: =+CR95/CR93-1 -> 0.37245677 | CS98: =+CS95/CS93-1 -> 0.41539395 | CT98: =+CT95/CT93-1 -> 0.5060571 | ... DB98: =+DB95/DB93-1 -> 1.0771779 | DF98: -0.07718953
A100: PE
A101: PE - Close | B101: =+B93/B85 -> 0.77563548 | C101: =+C93/C85 -> 0.79461579 | D101: =+D93/D85 -> 0.69780471 | E101: =+E93/E85 -> #DIV/0! | F101: =+F93/F85 -> #DIV/0! | G101: =+G93/G85 -> #DIV/0! | H101: =+H93/H85 -> #DIV/0! | I101: =+I93/I85 -> #DIV/0! | ... AE101: =+AE93/AE85 -> #DIV/0! | AL101: =+AL93/AL85 -> 12.753633 | AM101: =+AM93/AM85 -> 16.89267 | AN101: =+AN93/AN85 -> 14.188655 | AO101: =+AO93/AO85 -> 17.98265 | AP101: =+AP93/AP85 -> 23.787981 | AQ101: =+AQ93/AQ85 -> 24.760071 | AR101: =+AR93/AR85 -> 26.736451 | AS101: =+AS93/AS85 -> 26.312278 | ... DB101: =+DB93/DB85 -> 48.385484 | DF101: 75.276397
A102: PE - High | B102: =+B94/B85 -> 1.1634532 | C102: =+C94/C85 -> 0.91999574 | D102: =+D94/D85 -> 0.88577923 | E102: =+E94/E85 -> #DIV/0! | F102: =+F94/F85 -> #DIV/0! | G102: =+G94/G85 -> #DIV/0! | H102: =+H94/H85 -> #DIV/0! | I102: =+I94/I85 -> #DIV/0! | ... AE102: =+AE94/AE85 -> #DIV/0! | AL102: =+AL94/AL85 -> 18.703638 | AM102: =+AM94/AM85 -> 20.189818 | AN102: =+AN94/AN85 -> 16.634975 | AO102: =+AO94/AO85 -> 19.333678 | AP102: =+AP94/AP85 -> 24.290492 | AQ102: =+AQ94/AQ85 -> 26.445163 | AR102: =+AR94/AR85 -> 29.931999 | AS102: =+AS94/AS85 -> 31.137826 | ... CL102: =+CL94/CL85 -> 130.06079 | CM102: =+CL102 -> 130.06079 | CN102: =+CM102 -> 130.06079 | CO102: =+CN102 -> 130.06079 | CP102: =+CO102 -> 130.06079 | CQ102: =+CP102 -> 130.06079 | CR102: =+CQ102 -> 130.06079 | CS102: =+CR102 -> 130.06079 | CT102: =+CS102 -> 130.06079 | ... DB102: =+DA102 -> 130.06079 | DF102: 93.751041
A103: PE - Low | B103: =+B95/B85 -> 0.50416306 | C103: =+C95/C85 -> 0.50559058 | D103: =+D95/D85 -> 0.56257124 | E103: =+E95/E85 -> #DIV/0! | F103: =+F95/F85 -> #DIV/0! | G103: =+G95/G85 -> #DIV/0! | H103: =+H95/H85 -> #DIV/0! | I103: =+I95/I85 -> #DIV/0! | ... AE103: =+AE95/AE85 -> #DIV/0! | AL103: =+AL95/AL85 -> 12.381758 | AM103: =+AM95/AM85 -> 15.67189 | AN103: =+AN95/AN85 -> 12.030137 | AO103: =+AO95/AO85 -> 11.491503 | AP103: =+AP95/AP85 -> 14.343732 | AQ103: =+AQ95/AQ85 -> 16.850919 | AR103: =+AR95/AR85 -> 20.151853 | AS103: =+AS95/AS85 -> 23.812557 | ... CL103: =+CL95/CL85 -> 100.50526 | CM103: =+CL103 -> 100.50526 | CN103: =+CM103 -> 100.50526 | CO103: =+CN103 -> 100.50526 | CP103: =+CO103 -> 100.50526 | CQ103: =+CP103 -> 100.50526 | CR103: =+CQ103 -> 100.50526 | CS103: =+CR103 -> 100.50526 | CT103: =+CS103 -> 100.50526 | ... DB103: =+DA103 -> 100.50526 | DF103: 72.44668
A105: PE - 1Yr Fwd | B105: =+B94/C85 -> 0.97698663 | C105: =+C94/D85 -> 0.76406911 | D105: =+D94/E85 -> #DIV/0! | E105: =+E94/F85 -> #DIV/0! | F105: =+F94/G85 -> #DIV/0! | G105: =+G94/H85 -> #DIV/0! | H105: =+H94/I85 -> #DIV/0! | I105: =+I94/J85 -> #DIV/0! | ... AD105: =+AD94/AE85 -> #DIV/0! | AL105: =+AL94/AP85 -> 16.353775 | AM105: =+AM94/AQ85 -> 10.978629 | AN105: =+AN94/AR85 -> 9.586643 | AO105: =+AO94/AS85 -> 13.531097 | AP105: =+AP94/AT85 -> 16.078246 | AQ105: =+AQ94/AU85 -> 23.210278 | AR105: =+AR94/AV85 -> 25.623086 | AS105: =+AS94/AW85 -> 27.771846 | ... CL105: =+CL94/CP85 -> 98.629723 | DF105: 54.462804
A106: Correlation | AO106: =+CORREL(AL85:AO85,AL102:AO102) -> 0.039510756 | AP106: =+CORREL(AM85:AP85,AM102:AP102) -> 0.60958187 | AQ106: =+CORREL(AN85:AQ85,AN102:AQ102) -> 0.91182198 | AR106: =+CORREL(AO85:AR85,AO102:AR102) -> 0.89126969 | AS106: =+CORREL(AP85:AS85,AP102:AS102) -> 0.85481351 | AT106: =+CORREL(AQ85:AT85,AQ102:AT102) -> 0.32940693 | AU106: =+CORREL(AR85:AU85,AR102:AU102) -> 0.32397085 | AV106: =+CORREL(AS85:AV85,AS102:AV102) -> -0.025575611 | ... CL106: =+CORREL(CI85:CL85,CI102:CL102) -> -0.97531207 | DF106: -0.93190693
A108: BVPS | E108: =+E$136/E$81 -> #DIV/0! | F108: =+F$136/F$81 -> #DIV/0! | G108: =+G$136/G$81 -> #DIV/0! | H108: =+H$136/H$81 -> #DIV/0! | I108: =+I$136/I$81 -> #DIV/0! | J108: =+J$136/J$81 -> #DIV/0! | K108: =+K$136/K$81 -> #DIV/0! | L108: =+L$136/L$81 -> #DIV/0! | ... AE108: =+AE$136/AE$81 -> #DIV/0! | AL108: =+AL$136/AL$81 -> 49.14208 | AM108: =+AM$136/AM$81 -> 50.373942 | AN108: =+AN$136/AN$81 -> 52.345526 | AO108: =+AO$136/AO$81 -> 54.217352 | AP108: =+AP$136/AP$81 -> 54.997582 | AQ108: =+AQ$136/AQ$81 -> 58.292322 | AR108: =+AR$136/AR$81 -> 59.585248 | AS108: =+AS$136/AS$81 -> 62.831016 | ... DB108: =+DB$136/DB$81 -> 282.85379 | DF108: 203.324
A109: PB
A110: PB - Close | E110: =+E93/E$108 -> #DIV/0! | F110: =+F93/F$108 -> #DIV/0! | G110: =+G93/G$108 -> #DIV/0! | H110: =+H93/H$108 -> #DIV/0! | I110: =+I93/I$108 -> #DIV/0! | J110: =+J93/J$108 -> #DIV/0! | K110: =+K93/K$108 -> #DIV/0! | L110: =+L93/L$108 -> #DIV/0! | ... AE110: =+AE93/AE$108 -> #DIV/0! | AL110: =+AL93/AL$108 -> 1.5353441 | AM110: =+AM93/AM$108 -> 1.6069816 | AN110: =+AN93/AN$108 -> 1.4127282 | AO110: =+AO93/AO$108 -> 2.1358476 | AP110: =+AP93/AP$108 -> 2.9264923 | AQ110: =+AQ93/AQ$108 -> 3.7432031 | AR110: =+AR93/AR$108 -> 4.0580514 | AS110: =+AS93/AS$108 -> 3.8531925 | ... DB110: =+DB93/DB$108 -> 4.9106643 | DF110: 6.247418
...

Sheet QTR Raw
A1: ='Annual Raw'!A1 -> 100575 | B1: X | C1: 201206 | D1: 201209 | E1: 201212 | F1: 201303 | G1: 201306 | H1: 201309 | I1: 201312 | J1: 201403 | K1: 201406 | L1: 201409 | M1: 201412 | N1: 201503 | O1: 201506 | P1: 201509 | Q1: 201512 | R1: 201603 | S1: 201606 | T1: 201609 | U1: 201612 | V1: 201703 | W1: 201706 | X1: 201709 | Y1: 201712 | Z1: 201803 | AA1: 201806 | AB1: 201809 | AC1: 201812 | AD1: 201903 | AE1: 201906 | AF1: 201909 | AG1: 201912 | AH1: 202003 | AI1: 202006 | AJ1: 202009 | AK1: 202012 | AL1: 202103 | AM1: 202106 | AN1: 202109 | AO1: 202112 | AP1: 202203 | AQ1: 202206 | AR1: 202209 | AS1: 202212 | AT1: 202303 | AU1: 202306 | AV1: 202309 | AW1: 202312 | AX1: 202403 | AY1: 202406 | AZ1: 202409 | BA1: 202412 | BB1: 202503 | BC1: 202506 | BD1: 202509 | BE1: 202512 | BF1: 202603 | BG1: 202606 | BH1: 202609 | BI1: 202612 | BJ1: 202703 | BK1: 202706 | BL1: 202709 | BM1: 202712 | BN1: 202803 | BO1: 202806 | BP1: 202809 | BQ1: 202812 | BR1: 202903 | BS1: 202906 | BT1: 202909 | BU1: 202912 | BV1: 203003
A3: Field Description | B3: Field Name
A4: Company Name | B4: CD_COMPNAME | C4: =_xll.EQNXTDZ(A1,B4,C1) -> Voltas Ltd.
A5: Date End | B5: QTR_DATE_END | C5: =_xll.EQNXTDZ($A$1,$B5,C$1,$B$1) -> 201206 | D5: =_xll.EQNXTDZ($A$1,$B5,D$1,$B$1) -> 201209 | E5: =_xll.EQNXTDZ($A$1,$B5,E$1,$B$1) -> 201212 | F5: =_xll.EQNXTDZ($A$1,$B5,F$1,$B$1) -> 201303 | G5: =_xll.EQNXTDZ($A$1,$B5,G$1,$B$1) -> 201306 | H5: =_xll.EQNXTDZ($A$1,$B5,H$1,$B$1) -> 201309 | I5: =_xll.EQNXTDZ($A$1,$B5,I$1,$B$1) -> 201312 | J5: =_xll.EQNXTDZ($A$1,$B5,J$1,$B$1) -> 201403 | ... BV5: =_xll.EQNXTDZ($A$1,$B5,BV$1,$B$1) -> 0
A6: Gross Sales | B6: QTR_GROSS_SALE | C6: =_xll.EQNXTDZ($A$1,$B6,C$1,$B$1) -> 1611.57 | D6: =_xll.EQNXTDZ($A$1,$B6,D$1,$B$1) -> 1160.1 | E6: =_xll.EQNXTDZ($A$1,$B6,E$1,$B$1) -> 1150.17 | F6: =_xll.EQNXTDZ($A$1,$B6,F$1,$B$1) -> 1592.22 | G6: =_xll.EQNXTDZ($A$1,$B6,G$1,$B$1) -> 1601.78 | H6: =_xll.EQNXTDZ($A$1,$B6,H$1,$B$1) -> 1076.53 | I6: =_xll.EQNXTDZ($A$1,$B6,I$1,$B$1) -> 1114.99 | J6: =_xll.EQNXTDZ($A$1,$B6,J$1,$B$1) -> 1450.36 | ... BV6: =_xll.EQNXTDZ($A$1,$B6,BV$1,$B$1) -> 0
A7: Less: Excise Duty | B7: QTR_EXCISE_DUTY | C7: =_xll.EQNXTDZ($A$1,$B7,C$1,$B$1) -> 0 | D7: =_xll.EQNXTDZ($A$1,$B7,D$1,$B$1) -> 0 | E7: =_xll.EQNXTDZ($A$1,$B7,E$1,$B$1) -> 0 | F7: =_xll.EQNXTDZ($A$1,$B7,F$1,$B$1) -> 0 | G7: =_xll.EQNXTDZ($A$1,$B7,G$1,$B$1) -> 0 | H7: =_xll.EQNXTDZ($A$1,$B7,H$1,$B$1) -> 0 | I7: =_xll.EQNXTDZ($A$1,$B7,I$1,$B$1) -> 0 | J7: =_xll.EQNXTDZ($A$1,$B7,J$1,$B$1) -> 0 | ... BV7: =_xll.EQNXTDZ($A$1,$B7,BV$1,$B$1) -> 0
A8: Other operating income | B8: QTR_JOB_WORKS | C8: =_xll.EQNXTDZ($A$1,$B8,C$1,$B$1) -> 5.25 | D8: =_xll.EQNXTDZ($A$1,$B8,D$1,$B$1) -> 4.39 | E8: =_xll.EQNXTDZ($A$1,$B8,E$1,$B$1) -> 2.37 | F8: =_xll.EQNXTDZ($A$1,$B8,F$1,$B$1) -> 4.89 | G8: =_xll.EQNXTDZ($A$1,$B8,G$1,$B$1) -> 1.52 | H8: =_xll.EQNXTDZ($A$1,$B8,H$1,$B$1) -> 4 | I8: =_xll.EQNXTDZ($A$1,$B8,I$1,$B$1) -> 4.41 | J8: =_xll.EQNXTDZ($A$1,$B8,J$1,$B$1) -> 12.45 | ... BV8: =_xll.EQNXTDZ($A$1,$B8,BV$1,$B$1) -> 0
A9: Net Sales & Other Operating Income | B9: QTR_NET_SALES | C9: =_xll.EQNXTDZ($A$1,$B9,C$1,$B$1) -> 1616.82 | D9: =_xll.EQNXTDZ($A$1,$B9,D$1,$B$1) -> 1164.49 | E9: =_xll.EQNXTDZ($A$1,$B9,E$1,$B$1) -> 1152.54 | F9: =_xll.EQNXTDZ($A$1,$B9,F$1,$B$1) -> 1597.11 | G9: =_xll.EQNXTDZ($A$1,$B9,G$1,$B$1) -> 1603.3 | H9: =_xll.EQNXTDZ($A$1,$B9,H$1,$B$1) -> 1080.53 | I9: =_xll.EQNXTDZ($A$1,$B9,I$1,$B$1) -> 1119.4 | J9: =_xll.EQNXTDZ($A$1,$B9,J$1,$B$1) -> 1462.81 | ... BV9: =_xll.EQNXTDZ($A$1,$B9,BV$1,$B$1) -> 0
A10: (Increase) / Decrease In Stocks | B10: QTR_INC_DEC_INVENTORY | C10: =_xll.EQNXTDZ($A$1,$B10,C$1,$B$1) -> 37.85 | D10: =_xll.EQNXTDZ($A$1,$B10,D$1,$B$1) -> -21.29 | E10: =_xll.EQNXTDZ($A$1,$B10,E$1,$B$1) -> -67.99 | F10: =_xll.EQNXTDZ($A$1,$B10,F$1,$B$1) -> -84.79 | G10: =_xll.EQNXTDZ($A$1,$B10,G$1,$B$1) -> 192.03 | H10: =_xll.EQNXTDZ($A$1,$B10,H$1,$B$1) -> -63.66 | I10: =_xll.EQNXTDZ($A$1,$B10,I$1,$B$1) -> -82.12 | J10: =_xll.EQNXTDZ($A$1,$B10,J$1,$B$1) -> 71.7 | ... BV10: =_xll.EQNXTDZ($A$1,$B10,BV$1,$B$1) -> 0
A11: Cost of Services & Raw Materials | B11: QTR_RAW_MATERIAL_COST | C11: =_xll.EQNXTDZ($A$1,$B11,C$1,$B$1) -> 990.66 | D11: =_xll.EQNXTDZ($A$1,$B11,D$1,$B$1) -> 779.77 | E11: =_xll.EQNXTDZ($A$1,$B11,E$1,$B$1) -> 847.57 | F11: =_xll.EQNXTDZ($A$1,$B11,F$1,$B$1) -> 1098.75 | G11: =_xll.EQNXTDZ($A$1,$B11,G$1,$B$1) -> 900.11 | H11: =_xll.EQNXTDZ($A$1,$B11,H$1,$B$1) -> 673.43 | I11: =_xll.EQNXTDZ($A$1,$B11,I$1,$B$1) -> 679.11 | J11: =_xll.EQNXTDZ($A$1,$B11,J$1,$B$1) -> 910.44 | ... BV11: =_xll.EQNXTDZ($A$1,$B11,BV$1,$B$1) -> 0
A12: Purchase of Finished Goods | B12: QTR_PURCHASE_FIN_GOOD | C12: =_xll.EQNXTDZ($A$1,$B12,C$1,$B$1) -> 176.4 | D12: =_xll.EQNXTDZ($A$1,$B12,D$1,$B$1) -> 89.98 | E12: =_xll.EQNXTDZ($A$1,$B12,E$1,$B$1) -> 101.68 | F12: =_xll.EQNXTDZ($A$1,$B12,F$1,$B$1) -> 218.44 | G12: =_xll.EQNXTDZ($A$1,$B12,G$1,$B$1) -> 131.3 | H12: =_xll.EQNXTDZ($A$1,$B12,H$1,$B$1) -> 161.37 | I12: =_xll.EQNXTDZ($A$1,$B12,I$1,$B$1) -> 175.73 | J12: =_xll.EQNXTDZ($A$1,$B12,J$1,$B$1) -> 104.81 | ... BV12: =_xll.EQNXTDZ($A$1,$B12,BV$1,$B$1) -> 0
A13: Excise Duty | B13: QTR_EXCISE | C13: =_xll.EQNXTDZ($A$1,$B13,C$1,$B$1) -> 0 | D13: =_xll.EQNXTDZ($A$1,$B13,D$1,$B$1) -> 0 | E13: =_xll.EQNXTDZ($A$1,$B13,E$1,$B$1) -> 0 | F13: =_xll.EQNXTDZ($A$1,$B13,F$1,$B$1) -> 0 | G13: =_xll.EQNXTDZ($A$1,$B13,G$1,$B$1) -> 0 | H13: =_xll.EQNXTDZ($A$1,$B13,H$1,$B$1) -> 0 | I13: =_xll.EQNXTDZ($A$1,$B13,I$1,$B$1) -> 0 | J13: =_xll.EQNXTDZ($A$1,$B13,J$1,$B$1) -> 0 | ... BV13: =_xll.EQNXTDZ($A$1,$B13,BV$1,$B$1) -> 0
A14: Operating & Manufacturing Expenses | B14: QTR_MFG_EXPS | C14: =_xll.EQNXTDZ($A$1,$B14,C$1,$B$1) -> 153.51 | D14: =_xll.EQNXTDZ($A$1,$B14,D$1,$B$1) -> 109.06 | E14: =_xll.EQNXTDZ($A$1,$B14,E$1,$B$1) -> 99.76 | F14: =_xll.EQNXTDZ($A$1,$B14,F$1,$B$1) -> 125.13 | G14: =_xll.EQNXTDZ($A$1,$B14,G$1,$B$1) -> 164.53 | H14: =_xll.EQNXTDZ($A$1,$B14,H$1,$B$1) -> 114.47 | I14: =_xll.EQNXTDZ($A$1,$B14,I$1,$B$1) -> 132.71 | J14: =_xll.EQNXTDZ($A$1,$B14,J$1,$B$1) -> 139.78 | ... BV14: =_xll.EQNXTDZ($A$1,$B14,BV$1,$B$1) -> 0
A15: Electricity Power & Fuel Cost | B15: QTR_ELECTRICITY_POWER_FUEL | C15: =_xll.EQNXTDZ($A$1,$B15,C$1,$B$1) -> 0 | D15: =_xll.EQNXTDZ($A$1,$B15,D$1,$B$1) -> 0 | E15: =_xll.EQNXTDZ($A$1,$B15,E$1,$B$1) -> 0 | F15: =_xll.EQNXTDZ($A$1,$B15,F$1,$B$1) -> 0 | G15: =_xll.EQNXTDZ($A$1,$B15,G$1,$B$1) -> 0 | H15: =_xll.EQNXTDZ($A$1,$B15,H$1,$B$1) -> 0 | I15: =_xll.EQNXTDZ($A$1,$B15,I$1,$B$1) -> 0 | J15: =_xll.EQNXTDZ($A$1,$B15,J$1,$B$1) -> 0 | ... BV15: =_xll.EQNXTDZ($A$1,$B15,BV$1,$B$1) -> 0
A16: Employee Cost | B16: QTR_EXPLOYEE_COST | C16: =_xll.EQNXTDZ($A$1,$B16,C$1,$B$1) -> 164.49 | D16: =_xll.EQNXTDZ($A$1,$B16,D$1,$B$1) -> 162.99 | E16: =_xll.EQNXTDZ($A$1,$B16,E$1,$B$1) -> 147.26 | F16: =_xll.EQNXTDZ($A$1,$B16,F$1,$B$1) -> 157.79 | G16: =_xll.EQNXTDZ($A$1,$B16,G$1,$B$1) -> 164.86 | H16: =_xll.EQNXTDZ($A$1,$B16,H$1,$B$1) -> 152.65 | I16: =_xll.EQNXTDZ($A$1,$B16,I$1,$B$1) -> 146.47 | J16: =_xll.EQNXTDZ($A$1,$B16,J$1,$B$1) -> 130.71 | ... BV16: =_xll.EQNXTDZ($A$1,$B16,BV$1,$B$1) -> 0
... A42: Consolidated PAT(after extra items) | B42: QTR_CONS_PAT_EXITM | C42: =_xll.EQNXTDZ($A$1,$B42,C$1,$B$1) -> 79.12 | D42: =_xll.EQNXTDZ($A$1,$B42,D$1,$B$1) -> 42.93 | E42: =_xll.EQNXTDZ($A$1,$B42,E$1,$B$1) -> 76.81 | F42: =_xll.EQNXTDZ($A$1,$B42,F$1,$B$1) -> 8.92 | G42: =_xll.EQNXTDZ($A$1,$B42,G$1,$B$1) -> 40.75 | H42: =_xll.EQNXTDZ($A$1,$B42,H$1,$B$1) -> 42.28 | I42: =_xll.EQNXTDZ($A$1,$B42,I$1,$B$1) -> 61.92 | J42: =_xll.EQNXTDZ($A$1,$B42,J$1,$B$1) -> 100.41 | ... BV42: =_xll.EQNXTDZ($A$1,$B42,BV$1,$B$1) -> 0
A44: Field Description | B44: Field Name
A45: Equity Capital | B45: QTR_EQUITY_CAP | C45: =_xll.EQNXTDZ($A$1,$B45,C$1,$B$1) -> 33.07 | D45: =_xll.EQNXTDZ($A$1,$B45,D$1,$B$1) -> 33.07 | E45: =_xll.EQNXTDZ($A$1,$B45,E$1,$B$1) -> 33.07 | F45: =_xll.EQNXTDZ($A$1,$B45,F$1,$B$1) -> 33.07 | G45: =_xll.EQNXTDZ($A$1,$B45,G$1,$B$1) -> 33.07 | H45: =_xll.EQNXTDZ($A$1,$B45,H$1,$B$1) -> 33.07 | I45: =_xll.EQNXTDZ($A$1,$B45,I$1,$B$1) -> 33.07 | J45: =_xll.EQNXTDZ($A$1,$B45,J$1,$B$1) -> 33.07 | ... BV45: =_xll.EQNXTDZ($A$1,$B45,BV$1,$B$1) -> 0
A46: Face Value | B46: QTR_FV | C46: =_xll.EQNXTDZ($A$1,$B46,C$1,$B$1) -> 1 | D46: =_xll.EQNXTDZ($A$1,$B46,D$1,$B$1) -> 1 | E46: =_xll.EQNXTDZ($A$1,$B46,E$1,$B$1) -> 1 | F46: =_xll.EQNXTDZ($A$1,$B46,F$1,$B$1) -> 1 | G46: =_xll.EQNXTDZ($A$1,$B46,G$1,$B$1) -> 1 | H46: =_xll.EQNXTDZ($A$1,$B46,H$1,$B$1) -> 1 | I46: =_xll.EQNXTDZ($A$1,$B46,I$1,$B$1) -> 1 | J46: =_xll.EQNXTDZ($A$1,$B46,J$1,$B$1) -> 1 | ... BV46: =_xll.EQNXTDZ($A$1,$B46,BV$1,$B$1) -> 0
A47: Month End | B47: BMONTH_MONTHEND | C47: =_xll.EQNXTDZ($A$1,$B47,C$5) -> 201206 | D47: =_xll.EQNXTDZ($A$1,$B47,D$5) -> 201209 | E47: =_xll.EQNXTDZ($A$1,$B47,E$5) -> 201212 | F47: =_xll.EQNXTDZ($A$1,$B47,F$5) -> 201303 | G47: =_xll.EQNXTDZ($A$1,$B47,G$5) -> 201306 | H47: =_xll.EQNXTDZ($A$1,$B47,H$5) -> 201309 | I47: =_xll.EQNXTDZ($A$1,$B47,I$5) -> 201312 | J47: =_xll.EQNXTDZ($A$1,$B47,J$5) -> 201403 | ... BV47: =_xll.EQNXTDZ($A$1,$B47,BV$5) -> 0
A48: Close | B48: BMONTH_CLOSE | C48: =_xll.EQNXTDZ($A$1,$B48,C$5) -> 104.65 | D48: =_xll.EQNXTDZ($A$1,$B48,D$5) -> 124.6 | E48: =_xll.EQNXTDZ($A$1,$B48,E$5) -> 105.85 | F48: =_xll.EQNXTDZ($A$1,$B48,F$5) -> 75.45 | G48: =_xll.EQNXTDZ($A$1,$B48,G$5) -> 80.95 | H48: =_xll.EQNXTDZ($A$1,$B48,H$5) -> 73.95 | I48: =_xll.EQNXTDZ($A$1,$B48,I$5) -> 115.8 | J48: =_xll.EQNXTDZ($A$1,$B48,J$5) -> 160.95 | ... BV48: =_xll.EQNXTDZ($A$1,$B48,BV$5) -> 0
A49: Total of Promoter and Promoter Group | B49: SHP_TPFTOTALPROMOTER | C49: =_xll.EQNXTDZ($A$1,$B49,C$5) -> 30.15 | D49: =_xll.EQNXTDZ($A$1,$B49,D$5) -> 30.15 | E49: =_xll.EQNXTDZ($A$1,$B49,E$5) -> 30.15 | F49: =_xll.EQNXTDZ($A$1,$B49,F$5) -> 30.15 | G49: =_xll.EQNXTDZ($A$1,$B49,G$5) -> 30.15 | H49: =_xll.EQNXTDZ($A$1,$B49,H$5) -> 30.15 | I49: =_xll.EQNXTDZ($A$1,$B49,I$5) -> 30.3 | J49: =_xll.EQNXTDZ($A$1,$B49,J$5) -> 30.3 | ... BV49: =_xll.EQNXTDZ($A$1,$B49,BV$5) -> 0
A50: Total of Promoter and Promoter Group Pledged | B50: SHP_PSHFTOTALPROMOTER | C50: =_xll.EQNXTDZ($A$1,$B50,C$5) -> 0 | D50: =_xll.EQNXTDZ($A$1,$B50,D$5) -> 0 | E50: =_xll.EQNXTDZ($A$1,$B50,E$5) -> 0 | F50: =_xll.EQNXTDZ($A$1,$B50,F$5) -> 0 | G50: =_xll.EQNXTDZ($A$1,$B50,G$5) -> 0 | H50: =_xll.EQNXTDZ($A$1,$B50,H$5) -> 0 | I50: =_xll.EQNXTDZ($A$1,$B50,I$5) -> 0 | J50: =_xll.EQNXTDZ($A$1,$B50,J$5) -> 0 | ... BV50: =_xll.EQNXTDZ($A$1,$B50,BV$5) -> 0
A54: Field Description | B54: Field Name | C54: =_xll.EQNXTDZ($A$1,$B54,C$5) -> 0 | D54: =_xll.EQNXTDZ($A$1,$B54,D$5) -> 0 | E54: =_xll.EQNXTDZ($A$1,$B54,E$5) -> 0 | F54: =_xll.EQNXTDZ($A$1,$B54,F$5) -> 0 | G54: =_xll.EQNXTDZ($A$1,$B54,G$5) -> 0 | H54: =_xll.EQNXTDZ($A$1,$B54,H$5) -> 0 | I54: =_xll.EQNXTDZ($A$1,$B54,I$5) -> 0 | J54: =_xll.EQNXTDZ($A$1,$B54,J$5) -> 0 | ... BV54: =_xll.EQNXTDZ($A$1,$B54,BV$5) -> 0
A55: Year End | B55: QTRB_DATE_END | C55: =_xll.EQNXTDZ($A$1,$B55,C$5,$B$1) -> 0 | D55: =_xll.EQNXTDZ($A$1,$B55,D$5,$B$1) -> 201209 | E55: =_xll.EQNXTDZ($A$1,$B55,E$5,$B$1) -> 0 | F55: =_xll.EQNXTDZ($A$1,$B55,F$5,$B$1) -> 201303 | G55: =_xll.EQNXTDZ($A$1,$B55,G$5,$B$1) -> 0 | H55: =_xll.EQNXTDZ($A$1,$B55,H$5,$B$1) -> 201309 | I55: =_xll.EQNXTDZ($A$1,$B55,I$5,$B$1) -> 0 | J55: =_xll.EQNXTDZ($A$1,$B55,J$5,$B$1) -> 201403 | ... BV55: =_xll.EQNXTDZ($A$1,$B55,BV$5,$B$1) -> 0
A56: Share Capital | B56: QTRB_SHARE_CAPITAL | C56: =_xll.EQNXTDZ($A$1,$B56,C$5,$B$1) -> 0 | D56: =_xll.EQNXTDZ($A$1,$B56,D$5,$B$1) -> 33.07 | E56: =_xll.EQNXTDZ($A$1,$B56,E$5,$B$1) -> 0 | F56: =_xll.EQNXTDZ($A$1,$B56,F$5,$B$1) -> 33.07 | G56: =_xll.EQNXTDZ($A$1,$B56,G$5,$B$1) -> 0 | H56: =_xll.EQNXTDZ($A$1,$B56,H$5,$B$1) -> 33.07 | I56: =_xll.EQNXTDZ($A$1,$B56,I$5,$B$1) -> 0 | J56: =_xll.EQNXTDZ($A$1,$B56,J$5,$B$1) -> 33.07 | ... BV56: =_xll.EQNXTDZ($A$1,$B56,BV$5,$B$1) -> 0
A57: Share Warrants & outstandings | B57: QTRB_SHAREWARNDOUT | C57: =_xll.EQNXTDZ($A$1,$B57,C$5,$B$1) -> 0 | D57: =_xll.EQNXTDZ($A$1,$B57,D$5,$B$1) -> 0 | E57: =_xll.EQNXTDZ($A$1,$B57,E$5,$B$1) -> 0 | F57: =_xll.EQNXTDZ($A$1,$B57,F$5,$B$1) -> 0 | G57: =_xll.EQNXTDZ($A$1,$B57,G$5,$B$1) -> 0 | H57: =_xll.EQNXTDZ($A$1,$B57,H$5,$B$1) -> 0 | I57: =_xll.EQNXTDZ($A$1,$B57,I$5,$B$1) -> 0 | J57: =_xll.EQNXTDZ($A$1,$B57,J$5,$B$1) -> 0 | ... BV57: =_xll.EQNXTDZ($A$1,$B57,BV$5,$B$1) -> 0
A58: Reserves & Surplus | B58: QTRB_RESERVE | C58: =_xll.EQNXTDZ($A$1,$B58,C$5,$B$1) -> 0 | D58: =_xll.EQNXTDZ($A$1,$B58,D$5,$B$1) -> 1569.59 | E58: =_xll.EQNXTDZ($A$1,$B58,E$5,$B$1) -> 0 | F58: =_xll.EQNXTDZ($A$1,$B58,F$5,$B$1) -> 1592.55 | G58: =_xll.EQNXTDZ($A$1,$B58,G$5,$B$1) -> 0 | H58: =_xll.EQNXTDZ($A$1,$B58,H$5,$B$1) -> 1698.52 | I58: =_xll.EQNXTDZ($A$1,$B58,I$5,$B$1) -> 0 | J58: =_xll.EQNXTDZ($A$1,$B58,J$5,$B$1) -> 1786.25 | ... BV58: =_xll.EQNXTDZ($A$1,$B58,BV$5,$B$1) -> 0
A59: Shareholder's Funds | B59: QTRB_SHAREHODERS_FUNDS | C59: =_xll.EQNXTDZ($A$1,$B59,C$5,$B$1) -> 0 | D59: =_xll.EQNXTDZ($A$1,$B59,D$5,$B$1) -> 1602.66 | E59: =_xll.EQNXTDZ($A$1,$B59,E$5,$B$1) -> 0 | F59: =_xll.EQNXTDZ($A$1,$B59,F$5,$B$1) -> 1625.62 | G59: =_xll.EQNXTDZ($A$1,$B59,G$5,$B$1) -> 0 | H59: =_xll.EQNXTDZ($A$1,$B59,H$5,$B$1) -> 1731.59 | I59: =_xll.EQNXTDZ($A$1,$B59,I$5,$B$1) -> 0 | J59: =_xll.EQNXTDZ($A$1,$B59,J$5,$B$1) -> 1819.32 | ... BV59: =_xll.EQNXTDZ($A$1,$B59,BV$5,$B$1) -> 0
A60: Minority Interest | B60: QTRB_MINORITY_INTEREST_BS | C60: =_xll.EQNXTDZ($A$1,$B60,C$5,$B$1) -> 0 | D60: =_xll.EQNXTDZ($A$1,$B60,D$5,$B$1) -> 12.82 | E60: =_xll.EQNXTDZ($A$1,$B60,E$5,$B$1) -> 0 | F60: =_xll.EQNXTDZ($A$1,$B60,F$5,$B$1) -> 11.81 | G60: =_xll.EQNXTDZ($A$1,$B60,G$5,$B$1) -> 0 | H60: =_xll.EQNXTDZ($A$1,$B60,H$5,$B$1) -> 12.71 | I60: =_xll.EQNXTDZ($A$1,$B60,I$5,$B$1) -> 0 | J60: =_xll.EQNXTDZ($A$1,$B60,J$5,$B$1) -> 13.82 | ... BV60: =_xll.EQNXTDZ($A$1,$B60,BV$5,$B$1) -> 0
A61: Long Term Borrowings | B61: QTRB_TOTAL_DEBTS | C61: =_xll.EQNXTDZ($A$1,$B61,C$5,$B$1) -> 0 | D61: =_xll.EQNXTDZ($A$1,$B61,D$5,$B$1) -> 7.45 | E61: =_xll.EQNXTDZ($A$1,$B61,E$5,$B$1) -> 0 | F61: =_xll.EQNXTDZ($A$1,$B61,F$5,$B$1) -> 6.02 | G61: =_xll.EQNXTDZ($A$1,$B61,G$5,$B$1) -> 0 | H61: =_xll.EQNXTDZ($A$1,$B61,H$5,$B$1) -> 5.6 | I61: =_xll.EQNXTDZ($A$1,$B61,I$5,$B$1) -> 0 | J61: =_xll.EQNXTDZ($A$1,$B61,J$5,$B$1) -> 5.37 | ... BV61: =_xll.EQNXTDZ($A$1,$B61,BV$5,$B$1) -> 0
A62: Secured Loans | B62: QTRB_SECURED_LOANS | C62: =_xll.EQNXTDZ($A$1,$B62,C$5,$B$1) -> 0 | D62: =_xll.EQNXTDZ($A$1,$B62,D$5,$B$1) -> 0 | E62: =_xll.EQNXTDZ($A$1,$B62,E$5,$B$1) -> 0 | F62: =_xll.EQNXTDZ($A$1,$B62,F$5,$B$1) -> 0 | G62: =_xll.EQNXTDZ($A$1,$B62,G$5,$B$1) -> 0 | H62: =_xll.EQNXTDZ($A$1,$B62,H$5,$B$1) -> 0 | I62: =_xll.EQNXTDZ($A$1,$B62,I$5,$B$1) -> 0 | J62: =_xll.EQNXTDZ($A$1,$B62,J$5,$B$1) -> 0 | ... BV62: =_xll.EQNXTDZ($A$1,$B62,BV$5,$B$1) -> 0
A63: Unsecured Loans | B63: QTRB_UNSECURED_LOANS_NF | C63: =_xll.EQNXTDZ($A$1,$B63,C$5,$B$1) -> 0 | D63: =_xll.EQNXTDZ($A$1,$B63,D$5,$B$1) -> 7.45 | E63: =_xll.EQNXTDZ($A$1,$B63,E$5,$B$1) -> 0 | F63: =_xll.EQNXTDZ($A$1,$B63,F$5,$B$1) -> 6.02 | G63: =_xll.EQNXTDZ($A$1,$B63,G$5,$B$1) -> 0 | H63: =_xll.EQNXTDZ($A$1,$B63,H$5,$B$1) -> 5.6 | I63: =_xll.EQNXTDZ($A$1,$B63,I$5,$B$1) -> 0 | J63: =_xll.EQNXTDZ($A$1,$B63,J$5,$B$1) -> 5.37 | ... BV63: =_xll.EQNXTDZ($A$1,$B63,BV$5,$B$1) -> 0
A64: Other Long Term Liabilities | B64: QTRB_OTHER_LT_LIABILITIES | C64: =_xll.EQNXTDZ($A$1,$B64,C$5,$B$1) -> 0 | D64: =_xll.EQNXTDZ($A$1,$B64,D$5,$B$1) -> 32.84 | E64: =_xll.EQNXTDZ($A$1,$B64,E$5,$B$1) -> 0 | F64: =_xll.EQNXTDZ($A$1,$B64,F$5,$B$1) -> 27.96 | G64: =_xll.EQNXTDZ($A$1,$B64,G$5,$B$1) -> 0 | H64: =_xll.EQNXTDZ($A$1,$B64,H$5,$B$1) -> 36.78 | I64: =_xll.EQNXTDZ($A$1,$B64,I$5,$B$1) -> 0 | J64: =_xll.EQNXTDZ($A$1,$B64,J$5,$B$1) -> 29.87 | ... BV64: =_xll.EQNXTDZ($A$1,$B64,BV$5,$B$1) -> 0
A65: Long Term Trade Payables | B65: QTRB_LT_TRADE_PAYABLE | C65: =_xll.EQNXTDZ($A$1,$B65,C$5,$B$1) -> 0 | D65: =_xll.EQNXTDZ($A$1,$B65,D$5,$B$1) -> 0 | E65: =_xll.EQNXTDZ($A$1,$B65,E$5,$B$1) -> 0 | F65: =_xll.EQNXTDZ($A$1,$B65,F$5,$B$1) -> 0 | G65: =_xll.EQNXTDZ($A$1,$B65,G$5,$B$1) -> 0 | H65: =_xll.EQNXTDZ($A$1,$B65,H$5,$B$1) -> 0 | I65: =_xll.EQNXTDZ($A$1,$B65,I$5,$B$1) -> 0 | J65: =_xll.EQNXTDZ($A$1,$B65,J$5,$B$1) -> 0 | ... BV65: =_xll.EQNXTDZ($A$1,$B65,BV$5,$B$1) -> 0
A66: Lont Term Provisions | B66: QTRB_LT_PROVISIONS | C66: =_xll.EQNXTDZ($A$1,$B66,C$5,$B$1) -> 0 | D66: =_xll.EQNXTDZ($A$1,$B66,D$5,$B$1) -> 90.44 | E66: =_xll.EQNXTDZ($A$1,$B66,E$5,$B$1) -> 0 | F66: =_xll.EQNXTDZ($A$1,$B66,F$5,$B$1) -> 89.83 | G66: =_xll.EQNXTDZ($A$1,$B66,G$5,$B$1) -> 0 | H66: =_xll.EQNXTDZ($A$1,$B66,H$5,$B$1) -> 95.37 | I66: =_xll.EQNXTDZ($A$1,$B66,I$5,$B$1) -> 0 | J66: =_xll.EQNXTDZ($A$1,$B66,J$5,$B$1) -> 90.23 | ... BV66: =_xll.EQNXTDZ($A$1,$B66,BV$5,$B$1) -> 0
... A97: Total Assets | B97: QTRB_TOTAL_APPLICATIONS | C97: =_xll.EQNXTDZ($A$1,$B97,C$5,$B$1) -> 0 | D97: =_xll.EQNXTDZ($A$1,$B97,D$5,$B$1) -> 1746.21 | E97: =_xll.EQNXTDZ($A$1,$B97,E$5,$B$1) -> 0 | F97: =_xll.EQNXTDZ($A$1,$B97,F$5,$B$1) -> 1761.24 | G97: =_xll.EQNXTDZ($A$1,$B97,G$5,$B$1) -> 0 | H97: =_xll.EQNXTDZ($A$1,$B97,H$5,$B$1) -> 1882.05 | I97: =_xll.EQNXTDZ($A$1,$B97,I$5,$B$1) -> 0 | J97: =_xll.EQNXTDZ($A$1,$B97,J$5,$B$1) -> 1958.61 | ... BV97: =_xll.EQNXTDZ($A$1,$B97,BV$5,$B$1) -> 0

Sheet Annual Raw
A1: 100575 | B1: X | C1: 200103 | D1: 200203 | E1: 200303 | F1: 200403 | G1: 200503 | H1: 200603 | I1: 200703 | J1: 200803 | K1: 200903 | L1: 201003 | M1: 201103 | N1: 201203 | O1: 201303 | P1: 201403 | Q1: 201503 | R1: 201603 | S1: 201703 | T1: 201803 | U1: 201903 | V1: 202003 | W1: 202103 | X1: 202203 | Y1: 202303 | Z1: 202403 | AA1: 202503 | AB1: 202603 | AC1: 202703 | AD1: 202803 | AE1: 202903 | AF1: 203003
A3: Field Description | B3: Field Name
A4: Company Name | B4: CD_COMPNAME | C4: =_xll.EQNXTDZ(A1,B4,"L") -> Voltas Ltd.
A5: Year End | B5: PL_YEAR_END | C5: =_xll.EQNXTDZ($A$1,$B5,C$1,$B$1) -> 200103 | D5: =_xll.EQNXTDZ($A$1,$B5,D$1,$B$1) -> 200203 | E5: =_xll.EQNXTDZ($A$1,$B5,E$1,$B$1) -> 200303 | F5: =_xll.EQNXTDZ($A$1,$B5,F$1,$B$1) -> 200403 | G5: =_xll.EQNXTDZ($A$1,$B5,G$1,$B$1) -> 200503 | H5: =_xll.EQNXTDZ($A$1,$B5,H$1,$B$1) -> 200603 | I5: =_xll.EQNXTDZ($A$1,$B5,I$1,$B$1) -> 200703 | J5: =_xll.EQNXTDZ($A$1,$B5,J$1,$B$1) -> 200803 | ... AF5: =_xll.EQNXTDZ($A$1,$B5,AF$1,$B$1) -> 0
A6: Sales Turnover | B6: PL_TOTAL_GROSS_SALES | C6: =_xll.EQNXTDZ($A$1,$B6,C$1,$B$1) -> 853.7166 | D6: =_xll.EQNXTDZ($A$1,$B6,D$1,$B$1) -> 956.7624 | E6: =_xll.EQNXTDZ($A$1,$B6,E$1,$B$1) -> 1342.1175 | F6: =_xll.EQNXTDZ($A$1,$B6,F$1,$B$1) -> 1437.5206 | G6: =_xll.EQNXTDZ($A$1,$B6,G$1,$B$1) -> 1550.7879 | H6: =_xll.EQNXTDZ($A$1,$B6,H$1,$B$1) -> 2022.7089 | I6: =_xll.EQNXTDZ($A$1,$B6,I$1,$B$1) -> 2598.301 | J6: =_xll.EQNXTDZ($A$1,$B6,J$1,$B$1) -> 3264.3878 | ... AF6: =_xll.EQNXTDZ($A$1,$B6,AF$1,$B$1) -> 0
A7: Less: Inter divisional transfers | B7: PL_INTER_DIV_TRF | C7: =_xll.EQNXTDZ($A$1,$B7,C$1,$B$1) -> 0 | D7: =_xll.EQNXTDZ($A$1,$B7,D$1,$B$1) -> 0 | E7: =_xll.EQNXTDZ($A$1,$B7,E$1,$B$1) -> 0 | F7: =_xll.EQNXTDZ($A$1,$B7,F$1,$B$1) -> 0 | G7: =_xll.EQNXTDZ($A$1,$B7,G$1,$B$1) -> 0 | H7: =_xll.EQNXTDZ($A$1,$B7,H$1,$B$1) -> 0 | I7: =_xll.EQNXTDZ($A$1,$B7,I$1,$B$1) -> 0 | J7: =_xll.EQNXTDZ($A$1,$B7,J$1,$B$1) -> 0 | ... AF7: =_xll.EQNXTDZ($A$1,$B7,AF$1,$B$1) -> 0
A8: Less: Sales Returns | B8: PL_SALES_RETURN | C8: =_xll.EQNXTDZ($A$1,$B8,C$1,$B$1) -> 0 | D8: =_xll.EQNXTDZ($A$1,$B8,D$1,$B$1) -> 0 | E8: =_xll.EQNXTDZ($A$1,$B8,E$1,$B$1) -> 0 | F8: =_xll.EQNXTDZ($A$1,$B8,F$1,$B$1) -> 0 | G8: =_xll.EQNXTDZ($A$1,$B8,G$1,$B$1) -> 0 | H8: =_xll.EQNXTDZ($A$1,$B8,H$1,$B$1) -> 0 | I8: =_xll.EQNXTDZ($A$1,$B8,I$1,$B$1) -> 0 | J8: =_xll.EQNXTDZ($A$1,$B8,J$1,$B$1) -> 0 | ... AF8: =_xll.EQNXTDZ($A$1,$B8,AF$1,$B$1) -> 0
A9: Less: Excise | B9: PL_EXCISE | C9: =_xll.EQNXTDZ($A$1,$B9,C$1,$B$1) -> 89.1636 | D9: =_xll.EQNXTDZ($A$1,$B9,D$1,$B$1) -> 75.602 | E9: =_xll.EQNXTDZ($A$1,$B9,E$1,$B$1) -> 86.575 | F9: =_xll.EQNXTDZ($A$1,$B9,F$1,$B$1) -> 77.567 | G9: =_xll.EQNXTDZ($A$1,$B9,G$1,$B$1) -> 73.7203 | H9: =_xll.EQNXTDZ($A$1,$B9,H$1,$B$1) -> 68.2717 | I9: =_xll.EQNXTDZ($A$1,$B9,I$1,$B$1) -> 71.564 | J9: =_xll.EQNXTDZ($A$1,$B9,J$1,$B$1) -> 61.4611 | ... AF9: =_xll.EQNXTDZ($A$1,$B9,AF$1,$B$1) -> 0
A10: Net Sales | B10: PL_NET_SALES | C10: =_xll.EQNXTDZ($A$1,$B10,C$1,$B$1) -> 764.553 | D10: =_xll.EQNXTDZ($A$1,$B10,D$1,$B$1) -> 881.1604 | E10: =_xll.EQNXTDZ($A$1,$B10,E$1,$B$1) -> 1255.5425 | F10: =_xll.EQNXTDZ($A$1,$B10,F$1,$B$1) -> 1359.9536 | G10: =_xll.EQNXTDZ($A$1,$B10,G$1,$B$1) -> 1477.0676 | H10: =_xll.EQNXTDZ($A$1,$B10,H$1,$B$1) -> 1954.4372 | I10: =_xll.EQNXTDZ($A$1,$B10,I$1,$B$1) -> 2526.737 | J10: =_xll.EQNXTDZ($A$1,$B10,J$1,$B$1) -> 3202.9267 | ... AF10: =_xll.EQNXTDZ($A$1,$B10,AF$1,$B$1) -> 0
A11: Increase/Decrease in Stock | B11: PL_INC_DEC_INVENTORY | C11: =_xll.EQNXTDZ($A$1,$B11,C$1,$B$1) -> 29.476 | D11: =_xll.EQNXTDZ($A$1,$B11,D$1,$B$1) -> 65.8875 | E11: =_xll.EQNXTDZ($A$1,$B11,E$1,$B$1) -> 40.0038 | F11: =_xll.EQNXTDZ($A$1,$B11,F$1,$B$1) -> 10.4407 | G11: =_xll.EQNXTDZ($A$1,$B11,G$1,$B$1) -> -346.5813 | H11: =_xll.EQNXTDZ($A$1,$B11,H$1,$B$1) -> -608.1094 | I11: =_xll.EQNXTDZ($A$1,$B11,I$1,$B$1) -> 0 | J11: =_xll.EQNXTDZ($A$1,$B11,J$1,$B$1) -> 0 | ... AF11: =_xll.EQNXTDZ($A$1,$B11,AF$1,$B$1) -> 0
A12: Raw Material Consumed | B12: PL_RAW_MATRS_CONSUMED | C12: =_xll.EQNXTDZ($A$1,$B12,C$1,$B$1) -> 632.75 | D12: =_xll.EQNXTDZ($A$1,$B12,D$1,$B$1) -> 612.7476 | E12: =_xll.EQNXTDZ($A$1,$B12,E$1,$B$1) -> 974.4928 | F12: =_xll.EQNXTDZ($A$1,$B12,F$1,$B$1) -> 991.7907 | G12: =_xll.EQNXTDZ($A$1,$B12,G$1,$B$1) -> 1434.6836 | H12: =_xll.EQNXTDZ($A$1,$B12,H$1,$B$1) -> 2065.1993 | I12: =_xll.EQNXTDZ($A$1,$B12,I$1,$B$1) -> 1878.1579 | J12: =_xll.EQNXTDZ($A$1,$B12,J$1,$B$1) -> 2338.4082 | ... AF12: =_xll.EQNXTDZ($A$1,$B12,AF$1,$B$1) -> 0
A13: Power & Fuel Cost | B13: PL_POWER_FUEL | C13: =_xll.EQNXTDZ($A$1,$B13,C$1,$B$1) -> 6.6359 | D13: =_xll.EQNXTDZ($A$1,$B13,D$1,$B$1) -> 5.844 | E13: =_xll.EQNXTDZ($A$1,$B13,E$1,$B$1) -> 5.1779 | F13: =_xll.EQNXTDZ($A$1,$B13,F$1,$B$1) -> 4.9364 | G13: =_xll.EQNXTDZ($A$1,$B13,G$1,$B$1) -> 4.3908 | H13: =_xll.EQNXTDZ($A$1,$B13,H$1,$B$1) -> 4.1447 | I13: =_xll.EQNXTDZ($A$1,$B13,I$1,$B$1) -> 4.258 | J13: =_xll.EQNXTDZ($A$1,$B13,J$1,$B$1) -> 4.0643 | ... AF13: =_xll.EQNXTDZ($A$1,$B13,AF$1,$B$1) -> 0
A14: Employee Cost | B14: PL_EMPLOYEES | C14: =_xll.EQNXTDZ($A$1,$B14,C$1,$B$1) -> 100.3037 | D14: =_xll.EQNXTDZ($A$1,$B14,D$1,$B$1) -> 110.8011 | E14: =_xll.EQNXTDZ($A$1,$B14,E$1,$B$1) -> 134.5882 | F14: =_xll.EQNXTDZ($A$1,$B14,F$1,$B$1) -> 135.1971 | G14: =_xll.EQNXTDZ($A$1,$B14,G$1,$B$1) -> 153.6958 | H14: =_xll.EQNXTDZ($A$1,$B14,H$1,$B$1) -> 190.9696 | I14: =_xll.EQNXTDZ($A$1,$B14,I$1,$B$1) -> 258.6337 | J14: =_xll.EQNXTDZ($A$1,$B14,J$1,$B$1) -> 297.6833 | ... AF14: =_xll.EQNXTDZ($A$1,$B14,AF$1,$B$1) -> 0
A15: Operating & Manufacturing Expenses | B15: PL_GEN_OTHER_MFG_EXPS | C15: =_xll.EQNXTDZ($A$1,$B15,C$1,$B$1) -> 7.5553 | D15: =_xll.EQNXTDZ($A$1,$B15,D$1,$B$1) -> 8.841 | E15: =_xll.EQNXTDZ($A$1,$B15,E$1,$B$1) -> 7.32 | F15: =_xll.EQNXTDZ($A$1,$B15,F$1,$B$1) -> 7.5075 | G15: =_xll.EQNXTDZ($A$1,$B15,G$1,$B$1) -> 6.7282 | H15: =_xll.EQNXTDZ($A$1,$B15,H$1,$B$1) -> 7.0118 | I15: =_xll.EQNXTDZ($A$1,$B15,I$1,$B$1) -> 10.0716 | J15: =_xll.EQNXTDZ($A$1,$B15,J$1,$B$1) -> 12.8489 | ... AF15: =_xll.EQNXTDZ($A$1,$B15,AF$1,$B$1) -> 0
A16: Cost of Software development | B16: PL_COST_SW | C16: =_xll.EQNXTDZ($A$1,$B16,C$1,$B$1) -> 0 | D16: =_xll.EQNXTDZ($A$1,$B16,D$1,$B$1) -> 0 | E16: =_xll.EQNXTDZ($A$1,$B16,E$1,$B$1) -> 0 | F16: =_xll.EQNXTDZ($A$1,$B16,F$1,$B$1) -> 0 | G16: =_xll.EQNXTDZ($A$1,$B16,G$1,$B$1) -> 0 | H16: =_xll.EQNXTDZ($A$1,$B16,H$1,$B$1) -> 0 | I16: =_xll.EQNXTDZ($A$1,$B16,I$1,$B$1) -> 0 | J16: =_xll.EQNXTDZ($A$1,$B16,J$1,$B$1) -> 0 | ... AF16: =_xll.EQNXTDZ($A$1,$B16,AF$1,$B$1) -> 0
... A36: Profit After Tax from Discontinued Operations | B36: PL_PAT_DIS_OP | C36: =_xll.EQNXTDZ($A$1,$B36,C$1,$B$1) -> 0 | D36: =_xll.EQNXTDZ($A$1,$B36,D$1,$B$1) -> 0 | E36: =_xll.EQNXTDZ($A$1,$B36,E$1,$B$1) -> 0 | F36: =_xll.EQNXTDZ($A$1,$B36,F$1,$B$1) -> 0 | G36: =_xll.EQNXTDZ($A$1,$B36,G$1,$B$1) -> 0 | H36: =_xll.EQNXTDZ($A$1,$B36,H$1,$B$1) -> 0 | I36: =_xll.EQNXTDZ($A$1,$B36,I$1,$B$1) -> 0 | J36: =_xll.EQNXTDZ($A$1,$B36,J$1,$B$1) -> 0 | ... AF36: =_xll.EQNXTDZ($A$1,$B36,AF$1,$B$1) -> 0
A39: Field Description | B39: Field Name
A40: Year End | B40: BS_YEAR_END | C40: =_xll.EQNXTDZ($A$1,$B40,C$1,$B$1) -> 200103 | D40: =_xll.EQNXTDZ($A$1,$B40,D$1,$B$1) -> 200203 | E40: =_xll.EQNXTDZ($A$1,$B40,E$1,$B$1) -> 200303 | F40: =_xll.EQNXTDZ($A$1,$B40,F$1,$B$1) -> 200403 | G40: =_xll.EQNXTDZ($A$1,$B40,G$1,$B$1) -> 200503 | H40: =_xll.EQNXTDZ($A$1,$B40,H$1,$B$1) -> 200603 | I40: =_xll.EQNXTDZ($A$1,$B40,I$1,$B$1) -> 200703 | J40: =_xll.EQNXTDZ($A$1,$B40,J$1,$B$1) -> 200803 | ... AF40: =_xll.EQNXTDZ($A$1,$B40,AF$1,$B$1) -> 0
A41: Share Capital | B41: BS_SHARE_CAPITAL | C41: =_xll.EQNXTDZ($A$1,$B41,C$1,$B$1) -> 33.0539 | D41: =_xll.EQNXTDZ($A$1,$B41,D$1,$B$1) -> 33.0539 | E41: =_xll.EQNXTDZ($A$1,$B41,E$1,$B$1) -> 33.0539 | F41: =_xll.EQNXTDZ($A$1,$B41,F$1,$B$1) -> 33.0553 | G41: =_xll.EQNXTDZ($A$1,$B41,G$1,$B$1) -> 33.0553 | H41: =_xll.EQNXTDZ($A$1,$B41,H$1,$B$1) -> 33.0626 | I41: =_xll.EQNXTDZ($A$1,$B41,I$1,$B$1) -> 33.0683 | J41: =_xll.EQNXTDZ($A$1,$B41,J$1,$B$1) -> 33.0695 | ... AF41: =_xll.EQNXTDZ($A$1,$B41,AF$1,$B$1) -> 0
A42: Share Warrants & Outstandings | B42: BS_SHAREWROUTST | C42: =_xll.EQNXTDZ($A$1,$B42,C$1,$B$1) -> 0 | D42: =_xll.EQNXTDZ($A$1,$B42,D$1,$B$1) -> 0 | E42: =_xll.EQNXTDZ($A$1,$B42,E$1,$B$1) -> 0 | F42: =_xll.EQNXTDZ($A$1,$B42,F$1,$B$1) -> 0 | G42: =_xll.EQNXTDZ($A$1,$B42,G$1,$B$1) -> 0 | H42: =_xll.EQNXTDZ($A$1,$B42,H$1,$B$1) -> 0 | I42: =_xll.EQNXTDZ($A$1,$B42,I$1,$B$1) -> 0 | J42: =_xll.EQNXTDZ($A$1,$B42,J$1,$B$1) -> 0 | ... AF42: =_xll.EQNXTDZ($A$1,$B42,AF$1,$B$1) -> 0
A43: Total Reserves | B43: BS_RESERVE | C43: =_xll.EQNXTDZ($A$1,$B43,C$1,$B$1) -> 122.0188 | D43: =_xll.EQNXTDZ($A$1,$B43,D$1,$B$1) -> 174.8816 | E43: =_xll.EQNXTDZ($A$1,$B43,E$1,$B$1) -> 153.3744 | F43: =_xll.EQNXTDZ($A$1,$B43,F$1,$B$1) -> 181.7413 | G43: =_xll.EQNXTDZ($A$1,$B43,G$1,$B$1) -> 186.4852 | H43: =_xll.EQNXTDZ($A$1,$B43,H$1,$B$1) -> 238.302 | I43: =_xll.EQNXTDZ($A$1,$B43,I$1,$B$1) -> 390.6716 | J43: =_xll.EQNXTDZ($A$1,$B43,J$1,$B$1) -> 544.1537 | ... AF43: =_xll.EQNXTDZ($A$1,$B43,AF$1,$B$1) -> 0
A44: Shareholder's Funds | B44: BS_SHAREHODERS_FUNDS | C44: =_xll.EQNXTDZ($A$1,$B44,C$1,$B$1) -> 155.0727 | D44: =_xll.EQNXTDZ($A$1,$B44,D$1,$B$1) -> 207.9355 | E44: =_xll.EQNXTDZ($A$1,$B44,E$1,$B$1) -> 186.4283 | F44: =_xll.EQNXTDZ($A$1,$B44,F$1,$B$1) -> 214.7966 | G44: =_xll.EQNXTDZ($A$1,$B44,G$1,$B$1) -> 219.5405 | H44: =_xll.EQNXTDZ($A$1,$B44,H$1,$B$1) -> 271.3646 | I44: =_xll.EQNXTDZ($A$1,$B44,I$1,$B$1) -> 423.7399 | J44: =_xll.EQNXTDZ($A$1,$B44,J$1,$B$1) -> 577.2232 | ... AF44: =_xll.EQNXTDZ($A$1,$B44,AF$1,$B$1) -> 0
A45: Minority Interest | B45: BS_MINORITY_INTEREST | C45: =_xll.EQNXTDZ($A$1,$B45,C$1,$B$1) -> 0 | D45: =_xll.EQNXTDZ($A$1,$B45,D$1,$B$1) -> 0.7894 | E45: =_xll.EQNXTDZ($A$1,$B45,E$1,$B$1) -> 0.377 | F45: =_xll.EQNXTDZ($A$1,$B45,F$1,$B$1) -> 0.2635 | G45: =_xll.EQNXTDZ($A$1,$B45,G$1,$B$1) -> 0.2417 | H45: =_xll.EQNXTDZ($A$1,$B45,H$1,$B$1) -> 0.2638 | I45: =_xll.EQNXTDZ($A$1,$B45,I$1,$B$1) -> 0.4373 | J45: =_xll.EQNXTDZ($A$1,$B45,J$1,$B$1) -> 0.548 | ... AF45: =_xll.EQNXTDZ($A$1,$B45,AF$1,$B$1) -> 0
A46: Long-Term Borrowings | B46: BS_LTRM_BORROWING | C46: =_xll.EQNXTDZ($A$1,$B46,C$1,$B$1) -> 0 | D46: =_xll.EQNXTDZ($A$1,$B46,D$1,$B$1) -> 0 | E46: =_xll.EQNXTDZ($A$1,$B46,E$1,$B$1) -> 0 | F46: =_xll.EQNXTDZ($A$1,$B46,F$1,$B$1) -> 0 | G46: =_xll.EQNXTDZ($A$1,$B46,G$1,$B$1) -> 0 | H46: =_xll.EQNXTDZ($A$1,$B46,H$1,$B$1) -> 0 | I46: =_xll.EQNXTDZ($A$1,$B46,I$1,$B$1) -> 0 | J46: =_xll.EQNXTDZ($A$1,$B46,J$1,$B$1) -> 0 | ... AF46: =_xll.EQNXTDZ($A$1,$B46,AF$1,$B$1) -> 0
A47: Secured Loans | B47: BS_SECURED_LOANS | C47: =_xll.EQNXTDZ($A$1,$B47,C$1,$B$1) -> 67.1332 | D47: =_xll.EQNXTDZ($A$1,$B47,D$1,$B$1) -> 22.0743 | E47: =_xll.EQNXTDZ($A$1,$B47,E$1,$B$1) -> 72.8393 | F47: =_xll.EQNXTDZ($A$1,$B47,F$1,$B$1) -> 71.1421 | G47: =_xll.EQNXTDZ($A$1,$B47,G$1,$B$1) -> 94.2632 | H47: =_xll.EQNXTDZ($A$1,$B47,H$1,$B$1) -> 64.7867 | I47: =_xll.EQNXTDZ($A$1,$B47,I$1,$B$1) -> 111.3028 | J47: =_xll.EQNXTDZ($A$1,$B47,J$1,$B$1) -> 73.741 | ... AF47: =_xll.EQNXTDZ($A$1,$B47,AF$1,$B$1) -> 0
A48: Unsecured Loans | B48: BS_UNSECURED_LOANS_NF | C48: =_xll.EQNXTDZ($A$1,$B48,C$1,$B$1) -> 67.3359 | D48: =_xll.EQNXTDZ($A$1,$B48,D$1,$B$1) -> 76.4506 | E48: =_xll.EQNXTDZ($A$1,$B48,E$1,$B$1) -> 36.1055 | F48: =_xll.EQNXTDZ($A$1,$B48,F$1,$B$1) -> 31.7652 | G48: =_xll.EQNXTDZ($A$1,$B48,G$1,$B$1) -> 32.2174 | H48: =_xll.EQNXTDZ($A$1,$B48,H$1,$B$1) -> 25.2867 | I48: =_xll.EQNXTDZ($A$1,$B48,I$1,$B$1) -> 0.2785 | J48: =_xll.EQNXTDZ($A$1,$B48,J$1,$B$1) -> 0 | ... AF48: =_xll.EQNXTDZ($A$1,$B48,AF$1,$B$1) -> 0
A49: Deferred Tax Assets / Liabilities | B49: BS_NET_DEF_TAX_NF | C49: =_xll.EQNXTDZ($A$1,$B49,C$1,$B$1) -> 0 | D49: =_xll.EQNXTDZ($A$1,$B49,D$1,$B$1) -> -11.69 | E49: =_xll.EQNXTDZ($A$1,$B49,E$1,$B$1) -> -13.6536 | F49: =_xll.EQNXTDZ($A$1,$B49,F$1,$B$1) -> -10.2225 | G49: =_xll.EQNXTDZ($A$1,$B49,G$1,$B$1) -> -21.1635 | H49: =_xll.EQNXTDZ($A$1,$B49,H$1,$B$1) -> -25.63 | I49: =_xll.EQNXTDZ($A$1,$B49,I$1,$B$1) -> -27.8976 | J49: =_xll.EQNXTDZ($A$1,$B49,J$1,$B$1) -> -18.9312 | ... AF49: =_xll.EQNXTDZ($A$1,$B49,AF$1,$B$1) -> 0
A50: Other Long Term Liabilities | B50: BS_OTH_LT_LIAB | C50: =_xll.EQNXTDZ($A$1,$B50,C$1,$B$1) -> 0 | D50: =_xll.EQNXTDZ($A$1,$B50,D$1,$B$1) -> 0 | E50: =_xll.EQNXTDZ($A$1,$B50,E$1,$B$1) -> 0 | F50: =_xll.EQNXTDZ($A$1,$B50,F$1,$B$1) -> 0 | G50: =_xll.EQNXTDZ($A$1,$B50,G$1,$B$1) -> 0 | H50: =_xll.EQNXTDZ($A$1,$B50,H$1,$B$1) -> 0 | I50: =_xll.EQNXTDZ($A$1,$B50,I$1,$B$1) -> 0 | J50: =_xll.EQNXTDZ($A$1,$B50,J$1,$B$1) -> 0 | ... AF50: =_xll.EQNXTDZ($A$1,$B50,AF$1,$B$1) -> 0
A51: Long Term Trade Payables | B51: BS_LT_TRADE_PAYABLES | C51: =_xll.EQNXTDZ($A$1,$B51,C$1,$B$1) -> 0 | D51: =_xll.EQNXTDZ($A$1,$B51,D$1,$B$1) -> 0 | E51: =_xll.EQNXTDZ($A$1,$B51,E$1,$B$1) -> 0 | F51: =_xll.EQNXTDZ($A$1,$B51,F$1,$B$1) -> 0 | G51: =_xll.EQNXTDZ($A$1,$B51,G$1,$B$1) -> 0 | H51: =_xll.EQNXTDZ($A$1,$B51,H$1,$B$1) -> 0 | I51: =_xll.EQNXTDZ($A$1,$B51,I$1,$B$1) -> 0 | J51: =_xll.EQNXTDZ($A$1,$B51,J$1,$B$1) -> 0 | ... AF51: =_xll.EQNXTDZ($A$1,$B51,AF$1,$B$1) -> 0
... A99: Estimated Capital Contracts Remaining | B99: BS_ESTIMATED_CAPITAL_CONTRACT | C99: =_xll.EQNXTDZ($A$1,$B99,C$1,$B$1) -> 0 | D99: =_xll.EQNXTDZ($A$1,$B99,D$1,$B$1) -> 0 | E99: =_xll.EQNXTDZ($A$1,$B99,E$1,$B$1) -> 0 | F99: =_xll.EQNXTDZ($A$1,$B99,F$1,$B$1) -> 0 | G99: =_xll.EQNXTDZ($A$1,$B99,G$1,$B$1) -> 0 | H99: =_xll.EQNXTDZ($A$1,$B99,H$1,$B$1) -> 0 | I99: =_xll.EQNXTDZ($A$1,$B99,I$1,$B$1) -> 0 | J99: =_xll.EQNXTDZ($A$1,$B99,J$1,$B$1) -> 0 | ... AF99: =_xll.EQNXTDZ($A$1,$B99,AF$1,$B$1) -> 0
A103: Field Description | B103: Field Name
A104: Equity Paid Up | B104: BS_EQUITY_PAIDUP | C104: =_xll.EQNXTDZ($A$1,$B104,C$1,$B$1) -> 33.0539 | D104: =_xll.EQNXTDZ($A$1,$B104,D$1,$B$1) -> 33.0539 | E104: =_xll.EQNXTDZ($A$1,$B104,E$1,$B$1) -> 33.0539 | F104: =_xll.EQNXTDZ($A$1,$B104,F$1,$B$1) -> 33.0553 | G104: =_xll.EQNXTDZ($A$1,$B104,G$1,$B$1) -> 33.0553 | H104: =_xll.EQNXTDZ($A$1,$B104,H$1,$B$1) -> 33.0626 | I104: =_xll.EQNXTDZ($A$1,$B104,I$1,$B$1) -> 33.0683 | J104: =_xll.EQNXTDZ($A$1,$B104,J$1,$B$1) -> 33.0695 | ... AF104: =_xll.EQNXTDZ($A$1,$B104,AF$1,$B$1) -> 0
A105: Face Value | B105: BS_FACE_VALUE | C105: =_xll.EQNXTDZ($A$1,$B105,C$1,$B$1) -> 10 | D105: =_xll.EQNXTDZ($A$1,$B105,D$1,$B$1) -> 10 | E105: =_xll.EQNXTDZ($A$1,$B105,E$1,$B$1) -> 10 | F105: =_xll.EQNXTDZ($A$1,$B105,F$1,$B$1) -> 10 | G105: =_xll.EQNXTDZ($A$1,$B105,G$1,$B$1) -> 10 | H105: =_xll.EQNXTDZ($A$1,$B105,H$1,$B$1) -> 10 | I105: =_xll.EQNXTDZ($A$1,$B105,I$1,$B$1) -> 1 | J105: =_xll.EQNXTDZ($A$1,$B105,J$1,$B$1) -> 1 | ... AF105: =_xll.EQNXTDZ($A$1,$B105,AF$1,$B$1) -> 0
A106: Close Price (Unit Curr.) | B106: FH_YEAR_PRICE | C106: =_xll.EQNXTDZ($A$1,$B106,C$1,$B$1) -> 4 | D106: =_xll.EQNXTDZ($A$1,$B106,D$1,$B$1) -> 4.88 | E106: =_xll.EQNXTDZ($A$1,$B106,E$1,$B$1) -> 5.16 | F106: =_xll.EQNXTDZ($A$1,$B106,F$1,$B$1) -> 11.54 | G106: =_xll.EQNXTDZ($A$1,$B106,G$1,$B$1) -> 22.84 | H106: =_xll.EQNXTDZ($A$1,$B106,H$1,$B$1) -> 100.475 | I106: =_xll.EQNXTDZ($A$1,$B106,I$1,$B$1) -> 84.8 | J106: =_xll.EQNXTDZ($A$1,$B106,J$1,$B$1) -> 177.95 | ... AF106: =_xll.EQNXTDZ($A$1,$B106,AF$1,$B$1) -> 0
A107: High Price (Unit Curr.) | B107: FH_HIGH | C107: =_xll.EQNXTDZ($A$1,$B107,C$1,$B$1) -> 6 | D107: =_xll.EQNXTDZ($A$1,$B107,D$1,$B$1) -> 5.65 | E107: =_xll.EQNXTDZ($A$1,$B107,E$1,$B$1) -> 6.55 | F107: =_xll.EQNXTDZ($A$1,$B107,F$1,$B$1) -> 15.9 | G107: =_xll.EQNXTDZ($A$1,$B107,G$1,$B$1) -> 24.79 | H107: =_xll.EQNXTDZ($A$1,$B107,H$1,$B$1) -> 108.84 | I107: =_xll.EQNXTDZ($A$1,$B107,I$1,$B$1) -> 120.5 | J107: =_xll.EQNXTDZ($A$1,$B107,J$1,$B$1) -> 266.9 | ... AF107: =_xll.EQNXTDZ($A$1,$B107,AF$1,$B$1) -> 0
A108: Low Price (Unit Curr.) | B108: FH_LOW | C108: =_xll.EQNXTDZ($A$1,$B108,C$1,$B$1) -> 2.6 | D108: =_xll.EQNXTDZ($A$1,$B108,D$1,$B$1) -> 3.105 | E108: =_xll.EQNXTDZ($A$1,$B108,E$1,$B$1) -> 4.16 | F108: =_xll.EQNXTDZ($A$1,$B108,F$1,$B$1) -> 5 | G108: =_xll.EQNXTDZ($A$1,$B108,G$1,$B$1) -> 9.73 | H108: =_xll.EQNXTDZ($A$1,$B108,H$1,$B$1) -> 21.835 | I108: =_xll.EQNXTDZ($A$1,$B108,I$1,$B$1) -> 63.51 | J108: =_xll.EQNXTDZ($A$1,$B108,J$1,$B$1) -> 79.4 | ... AF108: =_xll.EQNXTDZ($A$1,$B108,AF$1,$B$1) -> 0
A109: Market Capitalization | B109: FH_MCAP | C109: =_xll.EQNXTDZ($A$1,$B109,C$1,$B$1) -> 132.2156 | D109: =_xll.EQNXTDZ($A$1,$B109,D$1,$B$1) -> 161.30303 | E109: =_xll.EQNXTDZ($A$1,$B109,E$1,$B$1) -> 170.55812 | F109: =_xll.EQNXTDZ($A$1,$B109,F$1,$B$1) -> 381.45816 | G109: =_xll.EQNXTDZ($A$1,$B109,G$1,$B$1) -> 754.98305 | H109: =_xll.EQNXTDZ($A$1,$B109,H$1,$B$1) -> 3321.9647 | I109: =_xll.EQNXTDZ($A$1,$B109,I$1,$B$1) -> 2804.1918 | J109: =_xll.EQNXTDZ($A$1,$B109,J$1,$B$1) -> 5884.7175 | ... AF109: =_xll.EQNXTDZ($A$1,$B109,AF$1,$B$1) -> 0
A110: Adj DPS(Rs) | B110: FR_ADJ_DPS | C110: =_xll.EQNXTDZ($A$1,$B110,C$1,$B$1) -> 0.12 | D110: =_xll.EQNXTDZ($A$1,$B110,D$1,$B$1) -> 0.18 | E110: =_xll.EQNXTDZ($A$1,$B110,E$1,$B$1) -> 0.25 | F110: =_xll.EQNXTDZ($A$1,$B110,F$1,$B$1) -> 0.3 | G110: =_xll.EQNXTDZ($A$1,$B110,G$1,$B$1) -> 0.5 | H110: =_xll.EQNXTDZ($A$1,$B110,H$1,$B$1) -> 0.6 | I110: =_xll.EQNXTDZ($A$1,$B110,I$1,$B$1) -> 1 | J110: =_xll.EQNXTDZ($A$1,$B110,J$1,$B$1) -> 1.35 | ... AF110: =_xll.EQNXTDZ($A$1,$B110,AF$1,$B$1) -> 0
A111: Date End | B111: SHP_DATE_END | C111: =_xll.EQNXTDZ($A$1,$B111,C$5) -> 200103 | D111: =_xll.EQNXTDZ($A$1,$B111,D$5) -> 200203 | E111: =_xll.EQNXTDZ($A$1,$B111,E$5) -> 200303 | F111: =_xll.EQNXTDZ($A$1,$B111,F$5) -> 200403 | G111: =_xll.EQNXTDZ($A$1,$B111,G$5) -> 200503 | H111: =_xll.EQNXTDZ($A$1,$B111,H$5) -> 200603 | I111: =_xll.EQNXTDZ($A$1,$B111,I$5) -> 200703 | J111: =_xll.EQNXTDZ($A$1,$B111,J$5) -> 200803 | ... AF111: =_xll.EQNXTDZ($A$1,$B111,AF$5) -> 0
A112: Total of Promoter and Promoter Group | B112: SHP_TPFTOTALPROMOTER | C112: =_xll.EQNXTDZ($A$1,$B112,C$5) -> 20.04 | D112: =_xll.EQNXTDZ($A$1,$B112,D$5) -> 24.85 | E112: =_xll.EQNXTDZ($A$1,$B112,E$5) -> 25.69 | F112: =_xll.EQNXTDZ($A$1,$B112,F$5) -> 27.74 | G112: =_xll.EQNXTDZ($A$1,$B112,G$5) -> 27.74 | H112: =_xll.EQNXTDZ($A$1,$B112,H$5) -> 27.56 | I112: =_xll.EQNXTDZ($A$1,$B112,I$5) -> 27.61 | J112: =_xll.EQNXTDZ($A$1,$B112,J$5) -> 27.55 | ... AF112: =_xll.EQNXTDZ($A$1,$B112,AF$5) -> 0
A113: Total of Promoter and Promoter Group Pledged | B113: SHP_PSHFTOTALPROMOTER | C113: =_xll.EQNXTDZ($A$1,$B113,C$5) -> 0 | D113: =_xll.EQNXTDZ($A$1,$B113,D$5) -> 0 | E113: =_xll.EQNXTDZ($A$1,$B113,E$5) -> 0 | F113: =_xll.EQNXTDZ($A$1,$B113,F$5) -> 0 | G113: =_xll.EQNXTDZ($A$1,$B113,G$5) -> 0 | H113: =_xll.EQNXTDZ($A$1,$B113,H$5) -> 0 | I113: =_xll.EQNXTDZ($A$1,$B113,I$5) -> 0 | J113: =_xll.EQNXTDZ($A$1,$B113,J$5) -> 0 | ... AF113: =_xll.EQNXTDZ($A$1,$B113,AF$5) -> 0

Sheet QTR Share Price
A1: ='QTR Raw'!A1 -> 100575 | C1: 201206 | D1: 201207 | E1: 201208 | F1: 201209 | G1: 201210 | H1: 201211 | I1: 201212 | J1: 201301 | K1: 201302 | L1: 201303 | M1: 201304 | N1: 201305 | O1: 201306 | P1: 201307 | Q1: 201308 | R1: 201309 | S1: 201310 | T1: 201311 | U1: 201312 | V1: 201401 | W1: 201402 | X1: 201403 | Y1: 201404 | Z1: 201405 | AA1: 201406 | AB1: 201407 | AC1: 201408 | AD1: 201409 | AE1: 201410 | AF1: 201411 | AG1: 201412 | AH1: 201501 | AI1: 201502 | AJ1: 201503 | AK1: 201504 | AL1: 201505 | AM1: 201506 | AN1: 201507 | AO1: 201508 | AP1: 201509 | AQ1: 201510 | AR1: 201511 | AS1: 201512 | AT1: 201601 | AU1: 201602 | AV1: 201603 | AW1: 201604 | AX1: 201605 | AY1: 201606 | AZ1: 201607 | BA1: 201608 | BB1: 201609 | BC1: 201610 | BD1: 201611 | BE1: 201612 | BF1: 201701 | BG1: 201702 | BH1: 201703 | BI1: 201704 | BJ1: 201705 | BK1: 201706 | BL1: 201707 | BM1: 201708 | BN1: 201709 | BO1: 201710 | BP1: 201711 | BQ1: 201712 | BR1: 201801 | BS1: 201802 | BT1: 201803 | BU1: 201804 | BV1: 201805 | BW1: 201806 | BX1: 201807 | BY1: 201808 | BZ1: 201809 | CA1: 201810 | CB1: 201811 | CC1: 201812 | CD1: 201901 | CE1: 201902 | CF1: 201903 | CG1: 201904 | CH1: 201905 | CI1: 201906 | CJ1: 201907 | CK1: 201908 | CL1: 201909 | CM1: 201910 | CN1: 201911 | CO1: 201912 | CP1: 202001 | CQ1: 202002 | CR1: 202003 | CS1: 202004 | CT1: 202005 | CU1: 202006 | CV1: 202007 | CW1: 202008 | CX1: 202009 | CY1: 202010 | CZ1: 202011 | DA1: 202012 | DB1: 202101 | DC1: 202102 | DD1: 202103 | DE1: 202104 | DF1: 202105 | DG1: 202106 | DH1: 202107 | DI1: 202108 | DJ1: 202109 | DK1: 202110 | DL1: 202111 | DM1: 202112 | DN1: 202201 | DO1: 202202 | DP1: 202203 | DQ1: 202204 | DR1: 202205 | DS1: 202206 | DT1: 202207 | DU1: 202208 | DV1: 202209 | DW1: 202210 | DX1: 202211 | DY1: 202212 | DZ1: 202301 | EA1: 202302 | EB1: 202303 | EC1: 202304 | ED1: 202305 | EE1: 202306 | EF1: 202307 | EG1: 202308 | EH1: 202309 | EI1: 202310 | EJ1: 202311 | EK1: 202312 | EL1: 202401 | EM1: 202402 | EN1: 202403 | EO1: 202404 | EP1: 202405 | EQ1: 202406 | ER1: 202407 | ES1: 202408 | ET1: 202409 | EU1: 202410 | EV1: 202411 | EW1: 202412 | EX1: 202501 | EY1: 202502 | EZ1: 202503 | FA1: 202504 | FB1: 202505 | FC1: 202506 | FD1: 202507 | FE1: 202508 | FF1: 202509 | FG1: 202510 | FH1: 202511 | FI1: 202512 | FJ1: 202601 | FK1: 202602 | FL1: 202603 | FM1: 202604 | FN1: 202605 | FO1: 202606 | FP1: 202607 | FQ1: 202608 | FR1: 202609 | FS1: 202610 | FT1: 202611 | FU1: 202612 | FV1: 202701 | FW1: 202702 | FX1: 202703 | FY1: 202704 | FZ1: 202705 | GA1: 202706 | GB1: 202707 | GC1: 202708 | GD1: 202709 | GE1: 202710 | GF1: 202711 | GG1: 202712 | GH1: 202801 | GI1: 202802 | GJ1: 202803 | GK1: 202804 | GL1: 202805 | GM1: 202806 | GN1: 202807 | GO1: 202808 | GP1: 202809 | GQ1: 202810 | GR1: 202811 | GS1: 202812 | GT1: 202901 | GU1: 202902 | GV1: 202903 | GW1: 202904 | GX1: 202905 | GY1: 202906 | GZ1: 202907 | HA1: 202908 | HB1: 202909 | HC1: 202910 | HD1: 202911 | HE1: 202912 | HF1: 203001 | HG1: 203002 | HH1: 203003 | HM1: 201206 | HN1: 201207 | HO1: 201208 | HP1: 201209 | HQ1: 201212 | HR1: 201303 | HS1: 201306 | HT1: 201309 | HU1: 201312 | HV1: 201403 | HW1: 201406 | HX1: 201409 | HY1: 201412 | HZ1: 201503 | IA1: 201506 | IB1: 201509 | IC1: 201512 | ID1: 201603 | IE1: 201606 | IF1: 201609 | IG1: 201612 | IH1: 201703 | II1: 201706 | IJ1: 201709 | IK1: 201712 | IL1: 201803 | IM1: 201806 | IN1: 201809 | IO1: 201812 | IP1: 201903 | IQ1: 201906 | IR1: 201909 | IS1: 201912 | IT1: 202003 | IU1: 202006 | IV1: 202009 | IW1: 202012 | IX1: 202103 | IY1: 202106 | IZ1: 202109 | JA1: 202112 | JB1: 202203 | JC1: 202206 | JD1: 202209 | JE1: 202212 | JF1: 202303 | JG1: 202306 | JH1: 202309 | JI1: 202312 | JJ1: 202403 | JK1: 202406 | JL1: 202409 | JM1: 202412 | JN1: 202503 | JO1: 202506 | JP1: 202509 | JQ1: 202512 | JR1: 202603 | JS1: 202606 | JT1: 202609 | JU1: 202612 | JV1: 202703 | JW1: 202706 | JX1: 202709 | JY1: 202712 | JZ1: 202803 | KA1: 202806 | KB1: 202809 | KC1: 202812 | KD1: 202903 | KE1: 202906 | KF1: 202909 | KG1: 202912 | KH1: 203003
FF2: 45901 | FG2: =+EOMONTH(FF2,1) -> 45961 | FH2: =+EOMONTH(FG2,1) -> 45991 | FI2: =+EOMONTH(FH2,1) -> 46022 | FJ2: =+EOMONTH(FI2,1) -> 46053 | FK2: =+EOMONTH(FJ2,1) -> 46081 | FL2: =+EOMONTH(FK2,1) -> 46112 | FM2: =+EOMONTH(FL2,1) -> 46142 | FN2: =+EOMONTH(FM2,1) -> 46173 | ... HH2: =+EOMONTH(HG2,1) -> 47573
A4: Field Description | B4: Field Name
A5: MonthEnd | B5: NMONTH_MONTHEND | C5: {=_xll.EQNXTDZ($A$1,$B5,C$1)} -> 201206 | D5: {=_xll.EQNXTDZ($A$1,$B5,D$1)} -> 201207 | E5: {=_xll.EQNXTDZ($A$1,$B5,E$1)} -> 201208 | F5: {=_xll.EQNXTDZ($A$1,$B5,F$1)} -> 201209 | G5: {=_xll.EQNXTDZ($A$1,$B5,G$1)} -> 201210 | H5: {=_xll.EQNXTDZ($A$1,$B5,H$1)} -> 201211 | I5: {=_xll.EQNXTDZ($A$1,$B5,I$1)} -> 201212 | J5: {=_xll.EQNXTDZ($A$1,$B5,J$1)} -> 201301 | ... HH5: {=_xll.EQNXTDZ($A$1,$B5,HH$1)} -> 0
A6: Open | B6: NMONTH_OPEN | C6: {=_xll.EQNXTDZ($A$1,$B6,C$1)} -> 99.55 | D6: {=_xll.EQNXTDZ($A$1,$B6,D$1)} -> 105 | E6: {=_xll.EQNXTDZ($A$1,$B6,E$1)} -> 101 | F6: {=_xll.EQNXTDZ($A$1,$B6,F$1)} -> 110.9 | G6: {=_xll.EQNXTDZ($A$1,$B6,G$1)} -> 123.95 | H6: {=_xll.EQNXTDZ($A$1,$B6,H$1)} -> 110.8 | I6: {=_xll.EQNXTDZ($A$1,$B6,I$1)} -> 105.15 | J6: {=_xll.EQNXTDZ($A$1,$B6,J$1)} -> 106 | ... HH6: {=_xll.EQNXTDZ($A$1,$B6,HH$1)} -> 0
A7: High | B7: NMONTH_HIGH | C7: {=_xll.EQNXTDZ($A$1,$B7,C$1)} -> 111.4 | D7: {=_xll.EQNXTDZ($A$1,$B7,D$1)} -> 117.7 | E7: {=_xll.EQNXTDZ($A$1,$B7,E$1)} -> 119.9 | F7: {=_xll.EQNXTDZ($A$1,$B7,F$1)} -> 136.3 | G7: {=_xll.EQNXTDZ($A$1,$B7,G$1)} -> 127.3 | H7: {=_xll.EQNXTDZ($A$1,$B7,H$1)} -> 119 | I7: {=_xll.EQNXTDZ($A$1,$B7,I$1)} -> 116.75 | J7: {=_xll.EQNXTDZ($A$1,$B7,J$1)} -> 110.55 | ... HH7: {=_xll.EQNXTDZ($A$1,$B7,HH$1)} -> 0 | HP7: =+MAX(D7:F7) -> 136.3 | HQ7: =+MAX(G7:I7) -> 127.3 | HR7: =+MAX(J7:L7) -> 110.55 | HS7: =+MAX(M7:O7) -> 96.7 | HT7: =+MAX(P7:R7) -> 86.9 | HU7: =+MAX(S7:U7) -> 124.7 | HV7: =+MAX(V7:X7) -> 164.2 | HW7: =+MAX(Y7:AA7) -> 233.45 | HX7: =+MAX(AB7:AD7) -> 271.2 | HY7: =+MAX(AE7:AG7) -> 286.45 | HZ7: =+MAX(AH7:AJ7) -> 301.4 | IA7: =+MAX(AK7:AM7) -> 359.9 | IB7: =+MAX(AN7:AP7) -> 330.4 | IC7: =+MAX(AQ7:AS7) -> 327 | ID7: =+MAX(AT7:AV7) -> 324.5 | IE7: =+MAX(AW7:AY7) -> 349 | IF7: =+MAX(AZ7:BB7) -> 401.8 | IG7: =+MAX(BC7:BE7) -> 406.4 | IH7: =+MAX(BF7:BH7) -> 424.75 | II7: =+MAX(BI7:BK7) -> 514 | IJ7: =+MAX(BL7:BN7) -> 565 | IK7: =+MAX(BO7:BQ7) -> 675.3 | IL7: =+MAX(BR7:BT7) -> 660.8 | IM7: =+MAX(BU7:BW7) -> 664.7 | IN7: =+MAX(BX7:BZ7) -> 636.9 | IO7: =+MAX(CA7:CC7) -> 590.5 | IP7: =+MAX(CD7:CF7) -> 633.7 | IQ7: =+MAX(CG7:CI7) -> 658.85 | IR7: =+MAX(CJ7:CL7) -> 705 | IS7: =+MAX(CM7:CO7) -> 725.4 | IT7: =+MAX(CP7:CR7) -> 741 | IU7: =+MAX(CS7:CU7) -> 587.5 | IV7: =+MAX(CV7:CX7) -> 713.5 | IW7: =+MAX(CY7:DA7) -> 844.95 | IX7: =+MAX(DB7:DD7) -> 1132 | IY7: =+MAX(DE7:DG7) -> 1125 | IZ7: =+MAX(DH7:DJ7) -> 1265 | JA7: =+MAX(DK7:DM7) -> 1356.9 | JB7: =+MAX(DN7:DP7) -> 1340 | JC7: =+MAX(DQ7:DS7) -> 1347.65 | JD7: =+MAX(DT7:DV7) -> 1064.95 | JE7: =+MAX(DW7:DY7) -> 936 | JF7: =+MAX(DZ7:EB7) -> 934 | JG7: =+MAX(EC7:EE7) -> 869.9 | JH7: =+MAX(EF7:EH7) -> 914.5 | JI7: =+MAX(EI7:EK7) -> 992.8 | JJ7: =+MAX(EL7:EN7) -> 1139.6 | JK7: =MAX(EO7:EQ7) -> 1560 | JL7: =MAX(ER7:ET7) -> 1944.9 | JM7: =MAX(EU7:EW7) -> 1902 | JN7: =MAX(EX7:EZ7) -> 1859.4 | JO7: =MAX(FA7:FC7) -> 1430 | JP7: =MAX(FD7:FF7) -> 1470 | JQ7: =MAX(FG7:FI7) -> 1463.8 | JR7: =MAX(FJ7:FL7) -> 1582.5 | JS7: =MAX(FM7:FO7) -> 1537.9 | JT7: =MAX(FP7:FR7) -> 0 | JU7: =MAX(FS7:FU7) -> 0 | JV7: =MAX(FV7:FX7) -> 0 | JW7: =MAX(FY7:GA7) -> 0 | JX7: =MAX(GB7:GD7) -> 0 | JY7: =MAX(GE7:GG7) -> 0 | JZ7: =MAX(GH7:GJ7) -> 0 | KA7: =MAX(GK7:GM7) -> 0 | KB7: =MAX(GN7:GP7) -> 0 | KC7: =MAX(GQ7:GS7) -> 0 | KD7: =MAX(GT7:GV7) -> 0 | KE7: =MAX(GW7:GY7) -> 0 | KF7: =MAX(GZ7:HB7) -> 0 | KG7: =MAX(HC7:HE7) -> 0 | KH7: =MAX(HF7:HH7) -> 0
A8: Low | B8: NMONTH_LOW | C8: {=_xll.EQNXTDZ($A$1,$B8,C$1)} -> 90.95 | D8: {=_xll.EQNXTDZ($A$1,$B8,D$1)} -> 98.5 | E8: {=_xll.EQNXTDZ($A$1,$B8,E$1)} -> 101 | F8: {=_xll.EQNXTDZ($A$1,$B8,F$1)} -> 105.05 | G8: {=_xll.EQNXTDZ($A$1,$B8,G$1)} -> 107.1 | H8: {=_xll.EQNXTDZ($A$1,$B8,H$1)} -> 100.85 | I8: {=_xll.EQNXTDZ($A$1,$B8,I$1)} -> 102.45 | J8: {=_xll.EQNXTDZ($A$1,$B8,J$1)} -> 94.5 | ... HH8: {=_xll.EQNXTDZ($A$1,$B8,HH$1)} -> 0 | HP8: =+MIN(D8:F8) -> 98.5 | HQ8: =+MIN(G8:I8) -> 100.85 | HR8: =+MIN(J8:L8) -> 73.15 | HS8: =+MIN(M8:O8) -> 75 | HT8: =+MIN(P8:R8) -> 62.5 | HU8: =+MIN(S8:U8) -> 74 | HV8: =+MIN(V8:X8) -> 96.85 | HW8: =+MIN(Y8:AA8) -> 148.3 | HX8: =+MIN(AB8:AD8) -> 180 | HY8: =+MIN(AE8:AG8) -> 218.85 | HZ8: =+MIN(AH8:AJ8) -> 227 | IA8: =+MIN(AK8:AM8) -> 258.25 | IB8: =+MIN(AN8:AP8) -> 243 | IC8: =+MIN(AQ8:AS8) -> 252 | ID8: =+MIN(AT8:AV8) -> 211 | IE8: =+MIN(AW8:AY8) -> 266.7 | IF8: =+MIN(AZ8:BB8) -> 311.7 | IG8: =+MIN(BC8:BE8) -> 287.15 | IH8: =+MIN(BF8:BH8) -> 320.4 | II8: =+MIN(BI8:BK8) -> 401.3 | IJ8: =+MIN(BL8:BN8) -> 453.75 | IK8: =+MIN(BO8:BQ8) -> 506.65 | IL8: =+MIN(BR8:BT8) -> 552 | IM8: =+MIN(BU8:BW8) -> 493.05 | IN8: =+MIN(BX8:BZ8) -> 511 | IO8: =+MIN(CA8:CC8) -> 472.25 | IP8: =+MIN(CD8:CF8) -> 501.05 | IQ8: =+MIN(CG8:CI8) -> 537.7 | IR8: =+MIN(CJ8:CL8) -> 557.4 | IS8: =+MIN(CM8:CO8) -> 639 | IT8: =+MIN(CP8:CR8) -> 448.75 | IU8: =+MIN(CS8:CU8) -> 427.45 | IV8: =+MIN(CV8:CX8) -> 529.6 | IW8: =+MIN(CY8:DA8) -> 656.35 | IX8: =+MIN(DB8:DD8) -> 820.05 | IY8: =+MIN(DE8:DG8) -> 918 | IZ8: =+MIN(DH8:DJ8) -> 955 | JA8: =+MIN(DK8:DM8) -> 1131.25 | JB8: =+MIN(DN8:DP8) -> 1100 | JC8: =+MIN(DQ8:DS8) -> 922.55 | JD8: =+MIN(DT8:DV8) -> 868 | JE8: =+MIN(DW8:DY8) -> 770 | JF8: =+MIN(DZ8:EB8) -> 737.2 | JG8: =+MIN(EC8:EE8) -> 747.6 | JH8: =+MIN(EF8:EH8) -> 745 | JI8: =+MIN(EI8:EK8) -> 806.7 | JJ8: =+MIN(EL8:EN8) -> 968 | JK8: =MIN(EO8:EQ8) -> 1101.2 | JL8: =MIN(ER8:ET8) -> 1416.5 | JM8: =MIN(EU8:EW8) -> 1617.7 | JN8: =MIN(EX8:EZ8) -> 1135 | JO8: =MIN(FA8:FC8) -> 1190 | JP8: =MIN(FD8:FF8) -> 1192 | JQ8: =MIN(FG8:FI8) -> 1288.1 | JR8: =MIN(FJ8:FL8) -> 1223 | JS8: =MIN(FM8:FO8) -> 1186.8 | JT8: =MIN(FP8:FR8) -> 0 | JU8: =MIN(FS8:FU8) -> 0 | JV8: =MIN(FV8:FX8) -> 0 | JW8: =MIN(FY8:GA8) -> 0 | JX8: =MIN(GB8:GD8) -> 0 | JY8: =MIN(GE8:GG8) -> 0 | JZ8: =MIN(GH8:GJ8) -> 0 | KA8: =MIN(GK8:GM8) -> 0 | KB8: =MIN(GN8:GP8) -> 0 | KC8: =MIN(GQ8:GS8) -> 0 | KD8: =MIN(GT8:GV8) -> 0 | KE8: =MIN(GW8:GY8) -> 0 | KF8: =MIN(GZ8:HB8) -> 0 | KG8: =MIN(HC8:HE8) -> 0 | KH8: =MIN(HF8:HH8) -> 0
A9: Close | B9: NMONTH_CLOSE | C9: {=_xll.EQNXTDZ($A$1,$B9,C$1)} -> 104.7 | D9: {=_xll.EQNXTDZ($A$1,$B9,D$1)} -> 106.3 | E9: {=_xll.EQNXTDZ($A$1,$B9,E$1)} -> 110.2 | F9: {=_xll.EQNXTDZ($A$1,$B9,F$1)} -> 124.95 | G9: {=_xll.EQNXTDZ($A$1,$B9,G$1)} -> 110.8 | H9: {=_xll.EQNXTDZ($A$1,$B9,H$1)} -> 108.3 | I9: {=_xll.EQNXTDZ($A$1,$B9,I$1)} -> 105.9 | J9: {=_xll.EQNXTDZ($A$1,$B9,J$1)} -> 97.7 | ... HH9: {=_xll.EQNXTDZ($A$1,$B9,HH$1)} -> 0 | HP9: =+F9 -> 124.95 | HQ9: =+I9 -> 105.9 | HR9: =+L9 -> 75.35 | HS9: =+O9 -> 80.95 | HT9: =+R9 -> 73.9 | HU9: =+U9 -> 116.05 | HV9: =+X9 -> 160.9 | HW9: =+AA9 -> 218.05 | HX9: =+AD9 -> 241.6 | HY9: =+AG9 -> 242.5 | HZ9: =+AJ9 -> 279.85 | IA9: =+AM9 -> 315.3 | IB9: =+AP9 -> 268.3 | IC9: =+AS9 -> 324.3 | ID9: =+AV9 -> 278.1 | IE9: =+AY9 -> 322.25 | IF9: =+BB9 -> 379.1 | IG9: =+BE9 -> 328.25 | IH9: =+BH9 -> 412.1 | II9: =+BK9 -> 457.25 | IJ9: =+BN9 -> 506.05 | IK9: =+BQ9 -> 655.9 | IL9: =+BT9 -> 620.9 | IM9: =+BW9 -> 523.8 | IN9: =+BZ9 -> 532.2 | IO9: =+CC9 -> 553.5 | IP9: =+CF9 -> 629.45 | IQ9: =+CI9 -> 643.4 | IR9: =+CL9 -> 679.55 | IS9: =+CO9 -> 659.3 | IT9: =+CR9 -> 476.9 | IU9: =+CU9 -> 546.45 | IV9: =+CX9 -> 680.35 | IW9: =+DA9 -> 825.65 | IX9: =+DD9 -> 1001.95 | IY9: =+DG9 -> 1022.45 | IZ9: =+DJ9 -> 1218.05 | JA9: =+DM9 -> 1219.15 | JB9: =+DP9 -> 1245.4 | JC9: =+DS9 -> 972.4 | JD9: =+DV9 -> 906.45 | JE9: =+DY9 -> 799.85 | JF9: =+EB9 -> 818.25 | JG9: =+EE9 -> 759.75 | JH9: =+EH9 -> 863.3 | JI9: =+EK9 -> 978.35 | JJ9: =+EN9 -> 1103.55 | JK9: =EQ9 -> 1472.2 | JL9: =ET9 -> 1845.1 | JM9: =EW9 -> 1789.95 | JN9: =EZ9 -> 1458.7 | JO9: =FC9 -> 1314.1 | JP9: =FF9 -> 1353.5 | JQ9: =FI9 -> 1361.2 | JR9: =FL9 -> 1272.8 | JS9: =FO9 -> 1327.6 | JT9: =FR9 -> 0 | JU9: =FU9 -> 0 | JV9: =FX9 -> 0 | JW9: =GA9 -> 0 | JX9: =GD9 -> 0 | JY9: =GG9 -> 0 | JZ9: =GJ9 -> 0 | KA9: =GM9 -> 0 | KB9: =GP9 -> 0 | KC9: =GS9 -> 0 | KD9: =GV9 -> 0 | KE9: =GY9 -> 0 | KF9: =HB9 -> 0 | KG9: =HE9 -> 0 | KH9: =HH9 -> 0
A11: Field Description | B11: Field Name | C11: {=_xll.EQNXTDZ($A$1,$B11,C$1)} -> 0 | D11: {=_xll.EQNXTDZ($A$1,$B11,D$1)} -> 0 | E11: {=_xll.EQNXTDZ($A$1,$B11,E$1)} -> 0 | F11: {=_xll.EQNXTDZ($A$1,$B11,F$1)} -> 0 | G11: {=_xll.EQNXTDZ($A$1,$B11,G$1)} -> 0 | H11: {=_xll.EQNXTDZ($A$1,$B11,H$1)} -> 0 | I11: {=_xll.EQNXTDZ($A$1,$B11,I$1)} -> 0 | J11: {=_xll.EQNXTDZ($A$1,$B11,J$1)} -> 0 | ... HH11: {=_xll.EQNXTDZ($A$1,$B11,HH$1)} -> 0
A12: Month End | B12: BMONTH_MONTHEND | C12: {=_xll.EQNXTDZ($A$1,$B12,C$1)} -> 201206 | D12: {=_xll.EQNXTDZ($A$1,$B12,D$1)} -> 201207 | E12: {=_xll.EQNXTDZ($A$1,$B12,E$1)} -> 201208 | F12: {=_xll.EQNXTDZ($A$1,$B12,F$1)} -> 201209 | G12: {=_xll.EQNXTDZ($A$1,$B12,G$1)} -> 201210 | H12: {=_xll.EQNXTDZ($A$1,$B12,H$1)} -> 201211 | I12: {=_xll.EQNXTDZ($A$1,$B12,I$1)} -> 201212 | J12: {=_xll.EQNXTDZ($A$1,$B12,J$1)} -> 201301 | ... HH12: {=_xll.EQNXTDZ($A$1,$B12,HH$1)} -> 0
A13: Open | B13: BMONTH_OPEN | C13: {=_xll.EQNXTDZ($A$1,$B13,C$1)} -> 99.1 | D13: {=_xll.EQNXTDZ($A$1,$B13,D$1)} -> 105.3 | E13: {=_xll.EQNXTDZ($A$1,$B13,E$1)} -> 103 | F13: {=_xll.EQNXTDZ($A$1,$B13,F$1)} -> 110.55 | G13: {=_xll.EQNXTDZ($A$1,$B13,G$1)} -> 123.9 | H13: {=_xll.EQNXTDZ($A$1,$B13,H$1)} -> 110.5 | I13: {=_xll.EQNXTDZ($A$1,$B13,I$1)} -> 108.75 | J13: {=_xll.EQNXTDZ($A$1,$B13,J$1)} -> 106.65 | ... HH13: {=_xll.EQNXTDZ($A$1,$B13,HH$1)} -> 0
A14: High | B14: BMONTH_HIGH | C14: {=_xll.EQNXTDZ($A$1,$B14,C$1)} -> 111.4 | D14: {=_xll.EQNXTDZ($A$1,$B14,D$1)} -> 117.7 | E14: {=_xll.EQNXTDZ($A$1,$B14,E$1)} -> 117.75 | F14: {=_xll.EQNXTDZ($A$1,$B14,F$1)} -> 138.5 | G14: {=_xll.EQNXTDZ($A$1,$B14,G$1)} -> 127.25 | H14: {=_xll.EQNXTDZ($A$1,$B14,H$1)} -> 119 | I14: {=_xll.EQNXTDZ($A$1,$B14,I$1)} -> 116.75 | J14: {=_xll.EQNXTDZ($A$1,$B14,J$1)} -> 110.65 | ... HH14: {=_xll.EQNXTDZ($A$1,$B14,HH$1)} -> 0 | HP14: =+MAX(D14:F14) -> 138.5 | HQ14: =+MAX(G14:I14) -> 127.25 | HR14: =+MAX(J14:L14) -> 110.65 | HS14: =+MAX(M14:O14) -> 96.75 | HT14: =+MAX(P14:R14) -> 86.7 | HU14: =+MAX(S14:U14) -> 124.5 | HV14: =+MAX(V14:X14) -> 164.35 | HW14: =+MAX(Y14:AA14) -> 233.05 | HX14: =+MAX(AB14:AD14) -> 270.7 | HY14: =+MAX(AE14:AG14) -> 286.5 | HZ14: =+MAX(AH14:AJ14) -> 301.45 | IA14: =+MAX(AK14:AM14) -> 360 | IB14: =+MAX(AN14:AP14) -> 330.35 | IC14: =+MAX(AQ14:AS14) -> 325 | ID14: =+MAX(AT14:AV14) -> 324.5 | IE14: =+MAX(AW14:AY14) -> 349.1 | IF14: =+MAX(AZ14:BB14) -> 402 | IG14: =+MAX(BC14:BE14) -> 406 | IH14: =+MAX(BF14:BH14) -> 424.9 | II14: =+MAX(BI14:BK14) -> 514.65 | IJ14: =+MAX(BL14:BN14) -> 564.95 | IK14: =+MAX(BO14:BQ14) -> 675 | IL14: =+MAX(BR14:BT14) -> 664 | IM14: =+MAX(BU14:BW14) -> 664.6 | IN14: =+MAX(BX14:BZ14) -> 637.25 | IO14: =+MAX(CA14:CC14) -> 589.95 | IP14: =+MAX(CD14:CF14) -> 634.95 | IQ14: =+MAX(CG14:CI14) -> 658.6 | IR14: =+MAX(CJ14:CL14) -> 704.25 | IS14: =+MAX(CM14:CO14) -> 725.45 | IT14: =+MAX(CP14:CR14) -> 740.5 | IU14: =+MAX(CS14:CU14) -> 587.15 | IV14: =+MAX(CV14:CX14) -> 713.7 | IW14: =+MAX(CY14:DA14) -> 844.95 | IX14: =+MAX(DB14:DD14) -> 1131.2 | IY14: =+MAX(DE14:DG14) -> 1124.9 | IZ14: =+MAX(DH14:DJ14) -> 1265 | JA14: =+MAX(DK14:DM14) -> 1356.9 | JB14: =+MAX(DN14:DP14) -> 1339.85 | JC14: =+MAX(DQ14:DS14) -> 1347.75 | JD14: =+MAX(DT14:DV14) -> 1063.45 | JE14: =+MAX(DW14:DY14) -> 935.65 | JF14: =+MAX(DZ14:EB14) -> 933.5 | JG14: =+MAX(EC14:EE14) -> 870.8 | JH14: =+MAX(EF14:EH14) -> 914.1 | JI14: =+MAX(EI14:EK14) -> 993 | JJ14: =+MAX(EL14:EN14) -> 1139 | JK14: =MAX(EO14:EQ14) -> 1550.5 | JL14: =MAX(ER14:ET14) -> 1946.2 | JM14: =MAX(EU14:EW14) -> 1901 | JN14: =MAX(EX14:EZ14) -> 1859.65 | JO14: =MAX(FA14:FC14) -> 1455 | JP14: =MAX(FD14:FF14) -> 1469.9 | JQ14: =MAX(FG14:FI14) -> 1463.45 | JR14: =MAX(FJ14:FL14) -> 1582 | JS14: =MAX(FM14:FO14) -> 1537.6 | JT14: =MAX(FP14:FR14) -> 0 | JU14: =MAX(FS14:FU14) -> 0 | JV14: =MAX(FV14:FX14) -> 0 | JW14: =MAX(FY14:GA14) -> 0 | JX14: =MAX(GB14:GD14) -> 0 | JY14: =MAX(GE14:GG14) -> 0 | JZ14: =MAX(GH14:GJ14) -> 0 | KA14: =MAX(GK14:GM14) -> 0 | KB14: =MAX(GN14:GP14) -> 0 | KC14: =MAX(GQ14:GS14) -> 0 | KD14: =MAX(GT14:GV14) -> 0 | KE14: =MAX(GW14:GY14) -> 0 | KF14: =MAX(GZ14:HB14) -> 0 | KG14: =MAX(HC14:HE14) -> 0 | KH14: =MAX(HF14:HH14) -> 0
A15: Low | B15: BMONTH_LOW | C15: {=_xll.EQNXTDZ($A$1,$B15,C$1)} -> 93.05 | D15: {=_xll.EQNXTDZ($A$1,$B15,D$1)} -> 98.55 | E15: {=_xll.EQNXTDZ($A$1,$B15,E$1)} -> 100.3 | F15: {=_xll.EQNXTDZ($A$1,$B15,F$1)} -> 105.7 | G15: {=_xll.EQNXTDZ($A$1,$B15,G$1)} -> 107.15 | H15: {=_xll.EQNXTDZ($A$1,$B15,H$1)} -> 100.9 | I15: {=_xll.EQNXTDZ($A$1,$B15,I$1)} -> 102.6 | J15: {=_xll.EQNXTDZ($A$1,$B15,J$1)} -> 94.6 | ... HH15: {=_xll.EQNXTDZ($A$1,$B15,HH$1)} -> 0 | HP15: =+MIN(D15:F15) -> 98.55 | HQ15: =+MIN(G15:I15) -> 100.9 | HR15: =+MIN(J15:L15) -> 73.25 | HS15: =+MIN(M15:O15) -> 75.1 | HT15: =+MIN(P15:R15) -> 62.7 | HU15: =+MIN(S15:U15) -> 74 | HV15: =+MIN(V15:X15) -> 97.05 | HW15: =+MIN(Y15:AA15) -> 148.5 | HX15: =+MIN(AB15:AD15) -> 182.25 | HY15: =+MIN(AE15:AG15) -> 219.1 | HZ15: =+MIN(AH15:AJ15) -> 227 | IA15: =+MIN(AK15:AM15) -> 258.8 | IB15: =+MIN(AN15:AP15) -> 243.2 | IC15: =+MIN(AQ15:AS15) -> 252.25 | ID15: =+MIN(AT15:AV15) -> 211.2 | IE15: =+MIN(AW15:AY15) -> 266.8 | IF15: =+MIN(AZ15:BB15) -> 312 | IG15: =+MIN(BC15:BE15) -> 287 | IH15: =+MIN(BF15:BH15) -> 321.1 | II15: =+MIN(BI15:BK15) -> 401.25 | IJ15: =+MIN(BL15:BN15) -> 445.15 | IK15: =+MIN(BO15:BQ15) -> 508 | IL15: =+MIN(BR15:BT15) -> 551.85 | IM15: =+MIN(BU15:BW15) -> 493.45 | IN15: =+MIN(BX15:BZ15) -> 510.8 | IO15: =+MIN(CA15:CC15) -> 471 | IP15: =+MIN(CD15:CF15) -> 501.65 | IQ15: =+MIN(CG15:CI15) -> 537 | IR15: =+MIN(CJ15:CL15) -> 557.2 | IS15: =+MIN(CM15:CO15) -> 638.95 | IT15: =+MIN(CP15:CR15) -> 449.2 | IU15: =+MIN(CS15:CU15) -> 428 | IV15: =+MIN(CV15:CX15) -> 529.4 | IW15: =+MIN(CY15:DA15) -> 656.55 | IX15: =+MIN(DB15:DD15) -> 822.3 | IY15: =+MIN(DE15:DG15) -> 918 | IZ15: =+MIN(DH15:DJ15) -> 955.2 | JA15: =+MIN(DK15:DM15) -> 1131.55 | JB15: =+MIN(DN15:DP15) -> 1100.3 | JC15: =+MIN(DQ15:DS15) -> 923.5 | JD15: =+MIN(DT15:DV15) -> 868.7 | JE15: =+MIN(DW15:DY15) -> 770.55 | JF15: =+MIN(DZ15:EB15) -> 737.6 | JG15: =+MIN(EC15:EE15) -> 747.9 | JH15: =+MIN(EF15:EH15) -> 745 | JI15: =+MIN(EI15:EK15) -> 806.9 | JJ15: =+MIN(EL15:EN15) -> 968.05 | JK15: =MIN(EO15:EQ15) -> 1103 | JL15: =MIN(ER15:ET15) -> 1403.45 | JM15: =MIN(EU15:EW15) -> 1617.5 | JN15: =MIN(EX15:EZ15) -> 1135.55 | JO15: =MIN(FA15:FC15) -> 1172.2 | JP15: =MIN(FD15:FF15) -> 1202.2 | JQ15: =MIN(FG15:FI15) -> 1288 | JR15: =MIN(FJ15:FL15) -> 1222.5 | JS15: =MIN(FM15:FO15) -> 1187.5 | JT15: =MIN(FP15:FR15) -> 0 | JU15: =MIN(FS15:FU15) -> 0 | JV15: =MIN(FV15:FX15) -> 0 | JW15: =MIN(FY15:GA15) -> 0 | JX15: =MIN(GB15:GD15) -> 0 | JY15: =MIN(GE15:GG15) -> 0 | JZ15: =MIN(GH15:GJ15) -> 0 | KA15: =MIN(GK15:GM15) -> 0 | KB15: =MIN(GN15:GP15) -> 0 | KC15: =MIN(GQ15:GS15) -> 0 | KD15: =MIN(GT15:GV15) -> 0 | KE15: =MIN(GW15:GY15) -> 0 | KF15: =MIN(GZ15:HB15) -> 0 | KG15: =MIN(HC15:HE15) -> 0 | KH15: =MIN(HF15:HH15) -> 0
A16: Close | B16: BMONTH_CLOSE | C16: {=_xll.EQNXTDZ($A$1,$B16,C$1)} -> 104.65 | D16: {=_xll.EQNXTDZ($A$1,$B16,D$1)} -> 106.05 | E16: {=_xll.EQNXTDZ($A$1,$B16,E$1)} -> 110.5 | F16: {=_xll.EQNXTDZ($A$1,$B16,F$1)} -> 124.6 | G16: {=_xll.EQNXTDZ($A$1,$B16,G$1)} -> 110.75 | H16: {=_xll.EQNXTDZ($A$1,$B16,H$1)} -> 108.2 | I16: {=_xll.EQNXTDZ($A$1,$B16,I$1)} -> 105.85 | J16: {=_xll.EQNXTDZ($A$1,$B16,J$1)} -> 97.8 | ... HH16: {=_xll.EQNXTDZ($A$1,$B16,HH$1)} -> 0 | HP16: =+F16 -> 124.6 | HQ16: =+I16 -> 105.85 | HR16: =+L16 -> 75.45 | HS16: =+O16 -> 80.95 | HT16: =+R16 -> 73.95 | HU16: =+U16 -> 115.8 | HV16: =+X16 -> 160.95 | HW16: =+AA16 -> 218.2 | HX16: =+AD16 -> 241.8 | HY16: =+AG16 -> 242.1 | HZ16: =+AJ16 -> 279.35 | IA16: =+AM16 -> 314.6 | IB16: =+AP16 -> 268.3 | IC16: =+AS16 -> 323.7 | ID16: =+AV16 -> 276.95 | IE16: =+AY16 -> 321.3 | IF16: =+BB16 -> 379.5 | IG16: =+BE16 -> 328.25 | IH16: =+BH16 -> 412.15 | II16: =+BK16 -> 457.85 | IJ16: =+BN16 -> 504.7 | IK16: =+BQ16 -> 655.7 | IL16: =+BT16 -> 620.6 | IM16: =+BW16 -> 521.65 | IN16: =+BZ16 -> 529.15 | IO16: =+CC16 -> 552.45 | IP16: =+CF16 -> 630.45 | IQ16: =+CI16 -> 643.55 | IR16: =+CL16 -> 679.85 | IS16: =+CO16 -> 659.3 | IT16: =+CR16 -> 478.85 | IU16: =+CU16 -> 546.15 | IV16: =+CX16 -> 680.8 | IW16: =+DA16 -> 826 | IX16: =+DD16 -> 1001.85 | IY16: =+DG16 -> 1022.35 | IZ16: =+DJ16 -> 1219.1 | JA16: =+DM16 -> 1219.35 | JB16: =+DP16 -> 1244.5 | JC16: =+DS16 -> 972.85 | JD16: =+DV16 -> 906.4 | JE16: =+DY16 -> 803.4 | JF16: =+EB16 -> 818.25 | JG16: =+EE16 -> 759.8 | JH16: =+EH16 -> 863 | JI16: =+EK16 -> 978.45 | JJ16: =+EN16 -> 1103.55 | JK16: =EQ16 -> 1471.9 | JL16: =ET16 -> 1845.75 | JM16: =EW16 -> 1792.1 | JN16: =EZ16 -> 1458.5 | JO16: =FC16 -> 1314.3 | JP16: =FF16 -> 1351.95 | JQ16: =FI16 -> 1360.6 | JR16: =FL16 -> 1270.25 | JS16: =FO16 -> 1327.35 | JT16: =FR16 -> 0 | JU16: =FU16 -> 0 | JV16: =FX16 -> 0 | JW16: =GA16 -> 0 | JX16: =GD16 -> 0 | JY16: =GG16 -> 0 | JZ16: =GJ16 -> 0 | KA16: =GM16 -> 0 | KB16: =GP16 -> 0 | KC16: =GS16 -> 0 | KD16: =GV16 -> 0 | KE16: =GY16 -> 0 | KF16: =HB16 -> 0 | KG16: =HE16 -> 0 | KH16: =HH16 -> 0
A19: High | HP19: =+IF(HP14=0,HP7,HP14) -> 138.5 | HQ19: =+IF(HQ14=0,HQ7,HQ14) -> 127.25 | HR19: =+IF(HR14=0,HR7,HR14) -> 110.65 | HS19: =+IF(HS14=0,HS7,HS14) -> 96.75 | HT19: =+IF(HT14=0,HT7,HT14) -> 86.7 | HU19: =+IF(HU14=0,HU7,HU14) -> 124.5 | HV19: =+IF(HV14=0,HV7,HV14) -> 164.35 | HW19: =+IF(HW14=0,HW7,HW14) -> 233.05 | ... KH19: =+IF(KH14=0,KH7,KH14) -> 0
A20: Low | HP20: =+IF(HP15=0,HP8,HP15) -> 98.55 | HQ20: =+IF(HQ15=0,HQ8,HQ15) -> 100.9 | HR20: =+IF(HR15=0,HR8,HR15) -> 73.25 | HS20: =+IF(HS15=0,HS8,HS15) -> 75.1 | HT20: =+IF(HT15=0,HT8,HT15) -> 62.7 | HU20: =+IF(HU15=0,HU8,HU15) -> 74 | HV20: =+IF(HV15=0,HV8,HV15) -> 97.05 | HW20: =+IF(HW15=0,HW8,HW15) -> 148.5 | ... KH20: =+IF(KH15=0,KH8,KH15) -> 0
A21: Close | HP21: =+IF(HP16=0,HP9,HP16) -> 124.6 | HQ21: =+IF(HQ16=0,HQ9,HQ16) -> 105.85 | HR21: =+IF(HR16=0,HR9,HR16) -> 75.45 | HS21: =+IF(HS16=0,HS9,HS16) -> 80.95 | HT21: =+IF(HT16=0,HT9,HT16) -> 73.95 | HU21: =+IF(HU16=0,HU9,HU16) -> 115.8 | HV21: =+IF(HV16=0,HV9,HV16) -> 160.95 | HW21: =+IF(HW16=0,HW9,HW16) -> 218.2 | ... KH21: =+IF(KH16=0,KH9,KH16) -> 0

Sheet QTR No. of Shares
A1: ='QTR Raw'!A1 -> 100575 | C1: 201206 | D1: 201209 | E1: 201212 | F1: 201303 | G1: 201306 | H1: 201309 | I1: 201312 | J1: 201403 | K1: 201406 | L1: 201409 | M1: 201412 | N1: 201503 | O1: 201506 | P1: 201509 | Q1: 201512 | R1: 201603 | S1: 201606 | T1: 201609 | U1: 201612 | V1: 201703 | W1: 201706 | X1: 201709 | Y1: 201712 | Z1: 201803 | AA1: 201806 | AB1: 201809 | AC1: 201812 | AD1: 201903 | AE1: 201906 | AF1: 201909 | AG1: 201912 | AH1: 202003 | AI1: 202006 | AJ1: 202009 | AK1: 202012 | AL1: 202103 | AM1: 202106 | AN1: 202109 | AO1: 202112 | AP1: 202203 | AQ1: 202206 | AR1: 202209 | AS1: 202212 | AT1: 202303 | AU1: 202306 | AV1: 202309 | AW1: 202312 | AX1: 202403 | AY1: 202406
A4: Field Description | B4: Field Name
A5: Date End | B5: SHP_DATE_END | C5: {=_xll.EQNXTDZ($A$1,$B5,C$1)} -> 201206 | D5: {=_xll.EQNXTDZ($A$1,$B5,D$1)} -> 201209 | E5: {=_xll.EQNXTDZ($A$1,$B5,E$1)} -> 201212 | F5: {=_xll.EQNXTDZ($A$1,$B5,F$1)} -> 201303 | G5: {=_xll.EQNXTDZ($A$1,$B5,G$1)} -> 201306 | H5: {=_xll.EQNXTDZ($A$1,$B5,H$1)} -> 201309 | I5: {=_xll.EQNXTDZ($A$1,$B5,I$1)} -> 201312 | J5: {=_xll.EQNXTDZ($A$1,$B5,J$1)} -> 201403 | ... AY5: {=_xll.EQNXTDZ($A$1,$B5,AY$1)} -> 202406
A6: Grand Total | B6: SHP_NSGRANDTOTAL | C6: {=_xll.EQNXTDZ($A$1,$B6,C$1)} -> 330884740 | D6: {=_xll.EQNXTDZ($A$1,$B6,D$1)} -> 330884740 | E6: {=_xll.EQNXTDZ($A$1,$B6,E$1)} -> 330884740 | F6: {=_xll.EQNXTDZ($A$1,$B6,F$1)} -> 330884740 | G6: {=_xll.EQNXTDZ($A$1,$B6,G$1)} -> 330884740 | H6: {=_xll.EQNXTDZ($A$1,$B6,H$1)} -> 330884740 | I6: {=_xll.EQNXTDZ($A$1,$B6,I$1)} -> 330884740 | J6: {=_xll.EQNXTDZ($A$1,$B6,J$1)} -> 330884740 | ... AY6: {=_xll.EQNXTDZ($A$1,$B6,AY$1)} -> 330884740
B7: In Crs. | C7: =+C6/10^7 -> 33.088474 | D7: =+D6/10^7 -> 33.088474 | E7: =+E6/10^7 -> 33.088474 | F7: =+F6/10^7 -> 33.088474 | G7: =+G6/10^7 -> 33.088474 | H7: =+H6/10^7 -> 33.088474 | I7: =+I6/10^7 -> 33.088474 | J7: =+J6/10^7 -> 33.088474 | ... AY7: =+AY6/10^7 -> 33.088474

Sheet Share price Daily
A1: =_xll.EQNXTH(B1,"[ADJC];[ADJH];[ADJL];[ADJO];[UCLS];[VOLUME]","2015-Jan-01","Y","All traded days","Asc") -> EQNXTH | B1: =+'Annual Raw'!A1 -> 100575 | L1: =_xll.EQNXTH(B1,"[NADJC];[NADJH];[NADJLOW];[NADJOPEN];[NUCLOSE];[NVOLUME]","2015-Jan-01","Y","All traded days","Asc") -> EQNXTH
A2: Voltas Ltd. | L2: Voltas Ltd.
A3: DATE | B3: ADJHIGH | C3: ADJCLOSE | D3: ADJLOW | E3: ADJOPEN | F3: CLOSE | G3: VOLUME | L3: DATE | M3: ADJCLOSE | N3: ADJHIGH | O3: ADJLOW | P3: ADJOPEN | Q3: CLOSE | R3: VOLUME
A4: 42005 | B4: 243.5 | C4: 240.9 | D4: 240 | E4: 242.95 | F4: 240.9 | G4: 131445 | L4: 42005 | M4: 240.8 | N4: 243.35 | O4: 239.65 | P4: 242.5 | Q4: 240.8 | R4: 856386
A5: 42006 | B5: 248 | C5: 245.55 | D5: 240.9 | E5: 241.5 | F5: 245.55 | G5: 253180 | L5: 42006 | M5: 245.65 | N5: 248.4 | O5: 239.2 | P5: 239.2 | Q5: 245.65 | R5: 2630409
A6: 42009 | B6: 251.1 | C6: 245.8 | D6: 244.05 | E6: 246 | F6: 245.8 | G6: 153355 | L6: 42009 | M6: 245.85 | N6: 251.2 | O6: 244.1 | P6: 246 | Q6: 245.85 | R6: 1975993
A7: 42010 | B7: 245 | C7: 236.85 | D7: 235.05 | E7: 245 | F7: 236.85 | G7: 200913 | L7: 42010 | M7: 237.35 | N7: 244.4 | O7: 235.2 | P7: 244.4 | Q7: 237.35 | R7: 1951719
A8: 42011 | B8: 238.85 | C8: 229.95 | D8: 227 | E8: 236.75 | F8: 229.95 | G8: 255234 | L8: 42011 | M8: 229.45 | N8: 238.85 | O8: 227 | P8: 236.3 | Q8: 229.45 | R8: 2337628
A9: 42012 | B9: 245 | C9: 243 | D9: 233 | E9: 233 | F9: 243 | G9: 191668 | L9: 42012 | M9: 243.35 | N9: 244.7 | O9: 233.65 | P9: 233.8 | Q9: 243.35 | R9: 2362344
A10: 42013 | B10: 247 | C10: 246.05 | D10: 242.2 | E10: 245.5 | F10: 246.05 | G10: 180297 | L10: 42013 | M10: 246 | N10: 246.9 | O10: 242.1 | P10: 246.8 | Q10: 246 | R10: 1946824
A11: 42016 | B11: 248.2 | C11: 245.85 | D11: 243.25 | E11: 247 | F11: 245.85 | G11: 176083 | L11: 42016 | M11: 245.9 | N11: 248.25 | O11: 243.1 | P11: 246 | Q11: 245.9 | R11: 1292914
A12: 42017 | B12: 247.35 | C12: 242.25 | D12: 240 | E12: 247.35 | F12: 242.25 | G12: 142675 | L12: 42017 | M12: 242.05 | N12: 247.3 | O12: 239.75 | P12: 245 | Q12: 242.05 | R12: 2700501
A13: 42018 | B13: 248.3 | C13: 247.65 | D13: 241.85 | E13: 242.55 | F13: 247.65 | G13: 172931 | L13: 42018 | M13: 247.75 | N13: 248.5 | O13: 241.6 | P13: 242 | Q13: 247.75 | R13: 4226479
A14: 42019 | B14: 254.85 | C14: 253.15 | D14: 245.65 | E14: 250 | F14: 253.15 | G14: 321277 | L14: 42019 | M14: 253.45 | N14: 254.9 | O14: 245.35 | P14: 249.1 | Q14: 253.45 | R14: 4586490
A15: 42020 | B15: 257.55 | C15: 254.75 | D15: 249.5 | E15: 254 | F15: 254.75 | G15: 201568 | L15: 42020 | M15: 255.5 | N15: 257.8 | O15: 249 | P15: 252.2 | Q15: 255.5 | R15: 4723648
... A2841: 46190 | B2841: 1381 | C2841: 1351 | D2841: 1326.6 | E2841: 1326.95 | F2841: 1351 | G2841: 76100 | L2841: 46190 | M2841: 1352.9 | N2841: 1381.8 | O2841: 1325.3 | P2841: 1326.3 | Q2841: 1352.9 | R2841: 1952284

Sheet Sheet2
J19: 219.3 | K19: 186.25 | L19: 186.75
J20: 192.9 | K20: 135.5 | L20: 146.9 | N20: 219.3 | O20: 192.9 | P20: 186 | Q20: 178.7 | R20: 207 | S20: 255.15 | T20: 348.25 | U20: 374 | V20: 495.9 | W20: 659.9 | X20: 613.4 | Y20: 607.9 | Z20: 555.95 | AA20: 497.8 | AB20: 459.9 | AC20: 374 | AD20: 362 | AE20: 341.5 | AF20: 384.2 | AG20: 433.8 | AH20: 460 | AI20: 474.4 | AJ20: 414.4 | AK20: 318.7 | AL20: 303.25 | AM20: 332.7 | AN20: 295 | AO20: 247 | AP20: 214.4 | AQ20: 179.5 | AR20: 97.9 | AS20: 119.1 | AT20: 130.65 | AU20: 148.55 | AV20: 153.8 | AW20: 152.9 | AX20: 136 | AY20: 141.15 | AZ20: 128.1 | BA20: 142.5 | BB20: 143.55 | BC20: 124.5 | BD20: 241 | BE20: 450 | BF20: 503.35
J21: 186 | K21: 145.4 | L21: 169.1 | N21: 186.25 | O21: 135.5 | P21: 145.4 | Q21: 108.95 | R21: 137 | S21: 170 | T21: 243.15 | U21: 307.5 | V21: 325.1 | W21: 463 | X21: 467.05 | Y21: 436.5 | Z21: 467 | AA21: 348.2 | AB21: 325 | AC21: 313.1 | AD21: 285 | AE21: 277.85 | AF21: 327 | AG21: 317 | AH21: 370.7 | AI21: 360 | AJ21: 271.15 | AK21: 233.15 | AL21: 218.8 | AM21: 262 | AN21: 223.6 | AO21: 137.6 | AP21: 142 | AQ21: 59.3 | AR21: 58 | AS21: 72.8 | AT21: 80 | AU21: 107.25 | AV21: 106 | AW21: 125.1 | AX21: 112.25 | AY21: 81.45 | AZ21: 88 | BA21: 90.35 | BB21: 106.05 | BC21: 98.55 | BD21: 119.25 | BE21: 210 | BF21: 349
J22: 178.7 | K22: 108.95 | L22: 139.75 | N22: 186.75 | O22: 146.9 | P22: 169.1 | Q22: 139.75 | R22: 202.15 | S22: 249.05 | T22: 346.4 | U22: 349.2 | V22: 469.9 | W22: 584.8 | X22: 536.15 | Y22: 513.35 | Z22: 474 | AA22: 438.55 | AB22: 355.4 | AC22: 334.95 | AD22: 298.8 | AE22: 328.35 | AF22: 343 | AG22: 389.9 | AH22: 443.05 | AI22: 407.5 | AJ22: 290.1 | AK22: 235.75 | AL22: 292.65 | AM22: 276.1 | AN22: 237.05 | AO22: 190.1 | AP22: 147.2 | AQ22: 71.9 | AR22: 75.2 | AS22: 90.1 | AT22: 117.2 | AU22: 116.3 | AV22: 140.5 | AW22: 128.6 | AX22: 133.65 | AY22: 91.65 | AZ22: 97.65 | BA22: 125 | BB22: 115.35 | BC22: 119.25 | BD22: 219.3 | BE22: 442.65 | BF22: 503.35
J23: 207 | K23: 137 | L23: 202.15
J24: 255.15 | K24: 170 | L24: 249.05
J25: 348.25 | K25: 243.15 | L25: 346.4
J26: 374 | K26: 307.5 | L26: 349.2
J27: 495.9 | K27: 325.1 | L27: 469.9
J28: 659.9 | K28: 463 | L28: 584.8
J29: 613.4 | K29: 467.05 | L29: 536.15
J30: 607.9 | K30: 436.5 | L30: 513.35
J31: 555.95 | K31: 467 | L31: 474
J32: 497.8 | K32: 348.2 | L32: 438.55
J33: 459.9 | K33: 325 | L33: 355.4
J34: 374 | K34: 313.1 | L34: 334.95
... J63: 503.35 | K63: 349 | L63: 503.35
