Workbook

Sheet Template
A1: =+'Annual Raw'!C4 -> Varun Beverages Ltd. | B1: 36951 | C1: =EOMONTH(B1,12) -> 37346 | D1: 37591 | E1: =EOMONTH(D1,12) -> 37986 | F1: =EOMONTH(E1,12) -> 38352 | G1: =EOMONTH(F1,12) -> 38717 | H1: =EOMONTH(G1,12) -> 39082 | I1: =EOMONTH(H1,12) -> 39447 | J1: =EOMONTH(I1,12) -> 39813 | K1: =EOMONTH(J1,12) -> 40178 | L1: =EOMONTH(K1,12) -> 40543 | ... AE1: =EOMONTH(AD1,12) -> 47483 | AH1: QTR | AI1: 41061 | AJ1: 41153 | AK1: 41244 | AL1: 41334 | AM1: 41426 | AN1: 41518 | AO1: 41609 | AP1: 41699 | AQ1: 41791 | AR1: 41883 | AS1: 41974 | AT1: 42064 | AU1: 42156 | AV1: 42248 | AW1: 42339 | AX1: 42430 | AY1: 42522 | AZ1: 42614 | BA1: 42705 | BB1: 42795 | BC1: 42887 | BD1: 42979 | BE1: 43070 | BF1: 43160 | BG1: 43252 | BH1: 43344 | BI1: 43435 | BJ1: 43525 | BK1: 43617 | BL1: 43709 | BM1: 43800 | BN1: 43891 | BO1: 43983 | BP1: 44075 | BQ1: =EOMONTH(BP1,3) -> 44196 | BR1: =EOMONTH(BQ1,3) -> 44286 | BS1: =EOMONTH(BR1,3) -> 44377 | BT1: =EOMONTH(BS1,3) -> 44469 | BU1: =EOMONTH(BT1,3) -> 44561 | BV1: =EOMONTH(BU1,3) -> 44651 | BW1: =EOMONTH(BV1,3) -> 44742 | BX1: =EOMONTH(BW1,3) -> 44834 | ... DA1: =EOMONTH(CZ1,3) -> 47483 | DD1: HISTORICAL ESTIMATES
A2: Presentation Data (Start)
A4: Volume
A5: Volume Mn Units - CSD | S5: =SUM(BB5:BE5) -> 220 | T5: =SUM(BF5:BI5) -> 257 | U5: =SUM(BJ5:BM5) -> 347 | V5: =SUM(BN5:BQ5) -> 309 | W5: =SUM(BR5:BU5) -> 400 | X5: =SUM(BV5:BY5) -> 562 | Y5: =SUM(BZ5:CC5) -> 657 | Z5: =SUM(CD5:CG5) -> 833 | AA5: =SUM(CH5:CK5) -> 897 | AB5: =SUM(CL5:CO5) -> 977.5159 | AC5: =SUM(CP5:CS5) -> 1060.1004 | AD5: =SUM(CT5:CW5) -> 1143.3609 | AE5: =SUM(CX5:DA5) -> 1233.5061 | BB5: 51 | BC5: 92 | BD5: 53 | BE5: 24 | BF5: 60 | BG5: 107 | BH5: 59 | BI5: 31 | BJ5: 64 | BK5: 145 | BL5: 86 | BM5: 52 | BN5: 76 | BO5: 89 | BP5: 89 | BQ5: 55 | BR5: 106 | BS5: 118 | BT5: 108 | BU5: 68 | BV5: 126 | BW5: 218 | BX5: 133 | BY5: 85 | BZ5: 160 | CA5: 232 | CB5: 159 | CC5: 106 | CD5: 169 | CE5: 306 | CF5: 200 | CG5: 158 | CH5: 234 | CI5: 291 | CJ5: 202 | CK5: 170 | CL5: 268 | CM5: =+CI5*(1+CM11) -> 305.58287 | CN5: =+CJ5*(1+CN11) -> 217.62963 | CO5: =+CK5*(1+CO11) -> 186.3034 | CP5: =+CL5*(1+CP11) -> 295.17237 | CQ5: =+CM5*(1+CQ11) -> 328.40967 | CR5: =+CN5*(1+CR11) -> 235.11705 | CS5: =+CO5*(1+CS11) -> 201.40131 | CT5: =+CP5*(1+CT11) -> 318.0839 | ... DA5: =+CW5*(1+DA11) -> 234.48356
A6: Volume Mn Units - Juice | S6: =SUM(BB6:BE6) -> 14 | T6: =SUM(BF6:BI6) -> 22 | U6: =SUM(BJ6:BM6) -> 23 | V6: =SUM(BN6:BQ6) -> 26 | W6: =SUM(BR6:BU6) -> 36 | X6: =SUM(BV6:BY6) -> 57 | Y6: =SUM(BZ6:CC6) -> 58 | Z6: =SUM(CD6:CG6) -> 69.3 | AA6: =SUM(CH6:CK6) -> 72 | AB6: =SUM(CL6:CO6) -> 84.464503 | AC6: =SUM(CP6:CS6) -> 99.771826 | AD6: =SUM(CT6:CW6) -> 116.72322 | AE6: =SUM(CX6:DA6) -> 136.015 | BB6: 3 | BC6: 7 | BD6: 3 | BE6: 1 | BF6: 5 | BG6: 10 | BH6: 4 | BI6: 3 | BJ6: 6 | BK6: 5 | BL6: 7 | BM6: 5 | BN6: 8 | BO6: 8 | BP6: 6 | BQ6: 4 | BR6: 11 | BS6: 11 | BT6: 8 | BU6: 6 | BV6: 13 | BW6: 26 | BX6: 11 | BY6: 7 | BZ6: 16 | CA6: 23 | CB6: 11 | CC6: 8 | CD6: 18 | CE6: 32 | CF6: 11.3 | CG6: 8 | CH6: 22 | CI6: 28 | CJ6: 12 | CK6: 10 | CL6: 27 | CM6: =+CI6*(1+CM12) -> 31.189491 | CN6: =+CJ6*(1+CN12) -> 14.155329 | CO6: =+CK6*(1+CO12) -> 12.119683 | CP6: =+CL6*(1+CP12) -> 32.440759 | CQ6: =+CM6*(1+CQ12) -> 36.371462 | CR6: =+CN6*(1+CR12) -> 16.680921 | CS6: =+CO6*(1+CS12) -> 14.278684 | CT6: =+CP6*(1+CT12) -> 37.961864 | ... DA6: =+CW6*(1+DA12) -> 19.407676
A7: Volume Mn Units - Water | S7: =SUM(BB7:BE7) -> 44 | T7: =SUM(BF7:BI7) -> 61 | U7: =SUM(BJ7:BM7) -> 111 | V7: =SUM(BN7:BQ7) -> 90 | W7: =SUM(BR7:BU7) -> 132 | X7: =SUM(BV7:BY7) -> 182 | Y7: =SUM(BZ7:CC7) -> 199 | Z7: =SUM(CD7:CG7) -> 221 | AA7: =SUM(CH7:CK7) -> 244 | AB7: =SUM(CL7:CO7) -> 288.28631 | AC7: =SUM(CP7:CS7) -> 339.71225 | AD7: =SUM(CT7:CW7) -> 399.71925 | AE7: =SUM(CX7:DA7) -> 475.15727 | BB7: 13 | BC7: 13 | BD7: 10 | BE7: 8 | BF7: 15 | BG7: 19 | BH7: 15 | BI7: 12 | BJ7: 20 | BK7: 35 | BL7: 31 | BM7: 25 | BN7: 30 | BO7: 8 | BP7: 24 | BQ7: 28 | BR7: 34 | BS7: 23 | BT7: 37 | BU7: 38 | BV7: 41 | BW7: 55 | BX7: 46 | BY7: 40 | BZ7: 48 | CA7: 59 | CB7: 50 | CC7: 42 | CD7: 53 | CE7: 63 | CF7: 56 | CG7: 49 | CH7: 56 | CI7: 71 | CJ7: 60 | CK7: 57 | CL7: 68 | CM7: =+CI7*(1+CM13) -> 82.245692 | CN7: =+CJ7*(1+CN13) -> 70.021599 | CO7: =+CK7*(1+CO13) -> 68.019018 | CP7: =+CL7*(1+CP13) -> 81.707446 | CQ7: =+CM7*(1+CQ13) -> 96.16771 | CR7: =+CN7*(1+CR13) -> 82.05349 | CS7: =+CO7*(1+CS13) -> 79.783602 | CT7: =+CP7*(1+CT13) -> 95.448723 | ... DA7: =+CW7*(1+DA13) -> 112.48104
A8: Total Volume Mn Units | S8: =SUM(S5:S7) -> 278 | T8: =SUM(T5:T7) -> 340 | U8: =SUM(U5:U7) -> 481 | V8: =SUM(V5:V7) -> 425 | W8: =SUM(W5:W7) -> 568 | X8: =SUM(X5:X7) -> 801 | Y8: =SUM(Y5:Y7) -> 914 | Z8: =SUM(Z5:Z7) -> 1123.3 | ... AE8: =SUM(AE5:AE7) -> 1844.6784 | BB8: =SUM(BB5:BB7) -> 67 | BC8: =SUM(BC5:BC7) -> 112 | BD8: =SUM(BD5:BD7) -> 66 | BE8: =SUM(BE5:BE7) -> 33 | BF8: =SUM(BF5:BF7) -> 80 | BG8: =SUM(BG5:BG7) -> 136 | BH8: =SUM(BH5:BH7) -> 78 | BI8: =SUM(BI5:BI7) -> 46 | ... DA8: =SUM(DA5:DA7) -> 366.37228
A10: Volume Growth % Y-o-Y
A11: Volume Growth YoY% - CSD | T11: =T5/S5-1 -> 0.16818182 | U11: =U5/T5-1 -> 0.35019455 | V11: =V5/U5-1 -> -0.10951009 | W11: =W5/V5-1 -> 0.29449838 | X11: =X5/W5-1 -> 0.405 | Y11: =Y5/X5-1 -> 0.16903915 | Z11: =Z5/Y5-1 -> 0.26788432 | AA11: =AA5/Z5-1 -> 0.076830732 | ... AE11: =AE5/AD5-1 -> 0.078842281 | BF11: =BF5/BB5-1 -> 0.17647059 | BG11: =BG5/BC5-1 -> 0.16304348 | BH11: =BH5/BD5-1 -> 0.11320755 | BI11: =BI5/BE5-1 -> 0.29166667 | BJ11: =BJ5/BF5-1 -> 0.066666667 | BK11: =BK5/BG5-1 -> 0.35514019 | BL11: =BL5/BH5-1 -> 0.45762712 | BM11: =BM5/BI5-1 -> 0.67741935 | ... CL11: =CL5/CH5-1 -> 0.14529915 | CM11: =+AVERAGE(CI11:CL11)*1.1 -> 0.050112949 | CN11: =+AVERAGE(CJ11:CM11)*1.1 -> 0.077374402 | CO11: =+AVERAGE(CK11:CN11)*1.1 -> 0.095902362 | CP11: =+AVERAGE(CL11:CO11)*1.1 -> 0.10138944 | CQ11: =+AVERAGE(CM11:CP11)*0.92 -> 0.074699204 | CR11: =+AVERAGE(CN11:CQ11)*0.92 -> 0.080354043 | CS11: =+AVERAGE(CO11:CR11)*0.92 -> 0.08103936 | CT11: =+AVERAGE(CP11:CS11)*0.92 -> 0.07762087 | CU11: =+AVERAGE(CQ11:CT11) -> 0.078428369 | CV11: =+AVERAGE(CR11:CU11) -> 0.079360661 | CW11: =+AVERAGE(CS11:CV11) -> 0.079112315 | CX11: =+AVERAGE(CT11:CW11) -> 0.078630554 | CY11: =+AVERAGE(CU11:CX11) -> 0.078882975 | CZ11: =+AVERAGE(CV11:CY11) -> 0.078996626 | DA11: =+AVERAGE(CW11:CZ11) -> 0.078905617
A12: Volume Growth YoY% - Juice | T12: =T6/S6-1 -> 0.57142857 | U12: =U6/T6-1 -> 0.045454545 | V12: =V6/U6-1 -> 0.13043478 | W12: =W6/V6-1 -> 0.38461538 | X12: =X6/W6-1 -> 0.58333333 | Y12: =Y6/X6-1 -> 0.01754386 | Z12: =Z6/Y6-1 -> 0.19482759 | AA12: =AA6/Z6-1 -> 0.038961039 | ... AE12: =AE6/AD6-1 -> 0.16527795 | BF12: =BF6/BB6-1 -> 0.66666667 | BG12: =BG6/BC6-1 -> 0.42857143 | BH12: =BH6/BD6-1 -> 0.33333333 | BI12: =BI6/BE6-1 -> 2 | BJ12: =BJ6/BF6-1 -> 0.2 | BK12: =BK6/BG6-1 -> -0.5 | BL12: =BL6/BH6-1 -> 0.75 | BM12: =BM6/BI6-1 -> 0.66666667 | ... CL12: =CL6/CH6-1 -> 0.22727273 | CM12: =+AVERAGE(CI12:CL12)*1.1 -> 0.1139104 | CN12: =+AVERAGE(CJ12:CM12)*1.1 -> 0.17961076 | CO12: =+AVERAGE(CK12:CN12)*1.1 -> 0.21196832 | CP12: =+AVERAGE(CL12:CO12)*1.1 -> 0.20150961 | CQ12: =+AVERAGE(CM12:CP12)*0.94 -> 0.16614478 | CR12: =+AVERAGE(CN12:CQ12)*0.94 -> 0.17841986 | CS12: =+AVERAGE(CO12:CR12)*0.94 -> 0.17814 | CT12: =+AVERAGE(CP12:CS12)*0.94 -> 0.17019035 | CU12: =+AVERAGE(CQ12:CT12)*0.98 -> 0.16975928 | CV12: =+AVERAGE(CR12:CU12)*0.98 -> 0.17064483 | CW12: =+AVERAGE(CS12:CV12)*0.98 -> 0.16873994 | CX12: =+AVERAGE(CT12:CW12)*0.98 -> 0.16643693 | CY12: =+AVERAGE(CU12:CX12)*0.98 -> 0.16551734 | CZ12: =+AVERAGE(CV12:CY12)*0.98 -> 0.16447806 | DA12: =+AVERAGE(CW12:CZ12)*0.98 -> 0.16296721
A13: Volume Growth YoY% - Water | T13: =T7/S7-1 -> 0.38636364 | U13: =U7/T7-1 -> 0.81967213 | V13: =V7/U7-1 -> -0.18918919 | W13: =W7/V7-1 -> 0.46666667 | X13: =X7/W7-1 -> 0.37878788 | Y13: =Y7/X7-1 -> 0.093406593 | Z13: =Z7/Y7-1 -> 0.11055276 | AA13: =AA7/Z7-1 -> 0.1040724 | ... AE13: =AE7/AD7-1 -> 0.18872751 | BF13: =BF7/BB7-1 -> 0.15384615 | BG13: =BG7/BC7-1 -> 0.46153846 | BH13: =BH7/BD7-1 -> 0.5 | BI13: =BI7/BE7-1 -> 0.5 | BJ13: =BJ7/BF7-1 -> 0.33333333 | BK13: =BK7/BG7-1 -> 0.84210526 | BL13: =BL7/BH7-1 -> 1.0666667 | BM13: =BM7/BI7-1 -> 1.0833333 | ... CL13: =CL7/CH7-1 -> 0.21428571 | CM13: =+AVERAGE(CI13:CL13)*1.1 -> 0.15839002 | CN13: =+AVERAGE(CJ13:CM13)*1.1 -> 0.16702664 | CO13: =+AVERAGE(CK13:CN13)*1.1 -> 0.19331611 | CP13: =+AVERAGE(CL13:CO13)*1.1 -> 0.20158009 | CQ13: =+AVERAGE(CM13:CP13)*0.94 -> 0.16927352 | CR13: =+AVERAGE(CN13:CQ13)*0.94 -> 0.17183115 | CS13: =+AVERAGE(CO13:CR13)*0.94 -> 0.1729602 | CT13: =+AVERAGE(CP13:CS13)*0.94 -> 0.16817657 | CU13: =+AVERAGE(CQ13:CT13)*1.04 -> 0.17738277 | CV13: =+AVERAGE(CR13:CU13)*1.04 -> 0.17949118 | CW13: =+AVERAGE(CS13:CV13)*1.04 -> 0.18148279 | CX13: =+AVERAGE(CT13:CW13)*1.04 -> 0.18369866 | CY13: =+AVERAGE(CU13:CX13)*1.04 -> 0.1877344 | CZ13: =+AVERAGE(CV13:CY13)*1.04 -> 0.19042583 | DA13: =+AVERAGE(CW13:CZ13)*1.04 -> 0.19326884
A14: Total Volume Growth YoY% | T14: =T8/S8-1 -> 0.22302158 | U14: =U8/T8-1 -> 0.41470588 | V14: =V8/U8-1 -> -0.11642412 | W14: =W8/V8-1 -> 0.33647059 | X14: =X8/W8-1 -> 0.41021127 | Y14: =Y8/X8-1 -> 0.14107366 | Z14: =Z8/Y8-1 -> 0.22899344 | AA14: =AA8/Z8-1 -> 0.079854002 | ... AE14: =AE8/AD8-1 -> 0.11138366 | BF14: =BF8/BB8-1 -> 0.19402985 | BG14: =BG8/BC8-1 -> 0.21428571 | BH14: =BH8/BD8-1 -> 0.18181818 | BI14: =BI8/BE8-1 -> 0.39393939 | BJ14: =BJ8/BF8-1 -> 0.125 | BK14: =BK8/BG8-1 -> 0.36029412 | BL14: =BL8/BH8-1 -> 0.58974359 | BM14: =BM8/BI8-1 -> 0.7826087 | ... CL14: =CL8/CH8-1 -> 0.16346154
A16: Unit Metrics
A17: Realisation | S17: =+S30/S8 -> 14.401223 | T17: =+T30/T8 -> 15.015456 | U17: =+U30/U8 -> 14.822407 | V17: =+V30/V8 -> 15.176805 | W17: =+W30/W8 -> 15.533856 | X17: =+X30/X8 -> 16.44587 | Y17: =+Y30/Y8 -> 17.552058 | Z17: =+Z30/Z8 -> 17.811493 | ... AE17: =+AE30/AE8 -> 20.233643 | BB17: =+BB30/BB8 -> 13.122343 | BC17: =+BC30/BC8 -> 14.583884 | BD17: =+BD30/BD8 -> 14.597697 | BE17: =+BE30/BE8 -> 15.984848 | BF17: =+BF30/BF8 -> 13.684625 | BG17: =+BG30/BG8 -> 15.140669 | BH17: =+BH30/BH8 -> 14.945346 | BI17: =+BI30/BI8 -> 17.07863 | ... CL17: =+CL30/CL8 -> 18.110716 | CM17: =+CI17*1.04 -> 18.712989 | CN17: =+CJ17*1.04 -> 18.585825 | CO17: =+CK17*1.04 -> 18.449789 | CP17: =+CL17*1.05 -> 19.016252 | CQ17: =+CM17*1.05 -> 19.648639 | CR17: =+CN17*1.04 -> 19.329258 | CS17: =+CO17*1.04 -> 19.18778 | CT17: =+CP17*0.97 -> 18.445765 | CU17: =+CQ17*0.97 -> 19.05918 | CV17: =+CR17*0.97 -> 18.74938 | CW17: =+CS17*0.97 -> 18.612147 | CX17: =+CT17*1.08 -> 19.921426 | CY17: =+CU17*1.08 -> 20.583914 | CZ17: =+CV17*1.08 -> 20.24933 | DA17: =+CW17*1.08 -> 20.101119
A18: RM | S18: =S17-S19 -> 6.5109928 | T18: =T17-T19 -> 6.6002912 | U18: =U17-U19 -> 6.6931975 | V18: =V17-V19 -> 6.5033812 | W18: =W17-W19 -> 7.1032746 | X18: =X17-X19 -> 7.8166742 | Y18: =Y17-Y19 -> 8.101628 | Z18: =Z17-Z19 -> 7.9272892 | ... AE18: =AE17-AE19 -> 9.0063499 | BB18: =BB17-BB19 -> 5.9717313 | BC18: =BC17-BC19 -> 6.9906518 | BD18: =BD17-BD19 -> 6.594303 | BE18: =BE17-BE19 -> 5.811303 | BF18: =BF17-BF19 -> 6.14495 | BG18: =BG17-BG19 -> 7.0503309 | BH18: =BH17-BH19 -> 6.7524872 | BI18: =BI17-BI19 -> 5.8035652 | ... CL18: =CL17-CL19 -> 8.1147245
A19: GP | S19: =+S36/S8 -> 7.8902302 | T19: =+T36/T8 -> 8.4151647 | U19: =+U36/U8 -> 8.12921 | V19: =+V36/V8 -> 8.6734235 | W19: =+W36/W8 -> 8.430581 | X19: =+X36/X8 -> 8.629196 | Y19: =+Y36/Y8 -> 9.45043 | Z19: =+Z36/Z8 -> 9.8842037 | ... AE19: =+AE36/AE8 -> 11.227293 | BB19: =+BB36/BB8 -> 7.1506119 | BC19: =+BC36/BC8 -> 7.5932321 | BD19: =+BD36/BD8 -> 8.0033939 | BE19: =+BE36/BE8 -> 10.173545 | BF19: =+BF36/BF8 -> 7.539675 | BG19: =+BG36/BG8 -> 8.0903382 | BH19: =+BH36/BH8 -> 8.192859 | BI19: =+BI36/BI8 -> 11.275065 | ... CL19: =+CL36/CL8 -> 9.9959917
A20: VC | S20: =+S42/S8 -> 1.5667878 | T20: =+T42/T8 -> 1.8364618 | U20: =+U42/U8 -> 1.7132308 | V20: =+V42/V8 -> 2.0541671 | W20: =+W42/W8 -> 1.8911162 | X20: =+X42/X8 -> 1.9125655 | Y20: =+Y42/Y8 -> 2.0002407 | Z20: =+Z42/Z8 -> 2.1126876 | ... AE20: =+AE42/AE8 -> 4.9048081 | BB20: =+BB42/BB8 -> 3.4605522 | BC20: =+BC42/BC8 -> 2.2573571 | BD20: =+BD42/BD8 -> 3.3761061 | BE20: =+BE42/BE8 -> 5.9801212 | BF20: =+BF42/BF8 -> 3.6482375 | BG20: =+BG42/BG8 -> 2.7526691 | BH20: =+BH42/BH8 -> 3.5793333 | BI20: =+BI42/BI8 -> 7.0914783 | ... CL20: =+CL42/CL8 -> 4.0780854
A21: Contribution | S21: =+S19-S20 -> 6.3234424 | T21: =+T19-T20 -> 6.5787029 | U21: =+U19-U20 -> 6.4159792 | V21: =+V19-V20 -> 6.6192565 | W21: =+W19-W20 -> 6.5394648 | X21: =+X19-X20 -> 6.7166305 | Y21: =+Y19-Y20 -> 7.4501893 | Z21: =+Z19-Z20 -> 7.7715161 | ... AE21: =+AE19-AE20 -> 6.3224854 | BB21: =+BB19-BB20 -> 3.6900597 | BC21: =+BC19-BC20 -> 5.335875 | BD21: =+BD19-BD20 -> 4.6272879 | BE21: =+BE19-BE20 -> 4.1934242 | BF21: =+BF19-BF20 -> 3.8914375 | BG21: =+BG19-BG20 -> 5.3376691 | BH21: =+BH19-BH20 -> 4.6135256 | BI21: =+BI19-BI20 -> 4.183587 | ... CL21: =+CL19-CL20 -> 5.9179063
A22: FC | S22: =+S43/S8 -> 1.6649065 | T22: =+T43/T8 -> 1.7145618 | U22: =+U43/U8 -> 1.6856861 | V22: =+V43/V8 -> 2.0934965 | W22: =+W43/W8 -> 1.774118 | X22: =+X43/X8 -> 1.5189039 | Y22: =+Y43/Y8 -> 1.5826991 | Z22: =+Z43/Z8 -> 1.6781145 | ... AE22: =+AE43/AE8 -> 1.6116015 | BB22: =+BB43/BB8 -> 1.6417612 | BC22: =+BC43/BC8 -> 1.0456964 | BD22: =+BD43/BD8 -> 1.8175758 | BE22: =+BE43/BE8 -> 3.5081212 | BF22: =+BF43/BF8 -> 1.7327625 | BG22: =+BG43/BG8 -> 1.1107721 | BH22: =+BH43/BH8 -> 1.9053077 | BI22: =+BI43/BI8 -> 3.144587 | ... CL22: =+CL43/CL8 -> 1.7059862
A23: EBITDA | S23: =S21-S22 -> 4.658536 | T23: =T21-T22 -> 4.8641412 | U23: =U21-U22 -> 4.7302931 | V23: =V21-V22 -> 4.52576 | W23: =W21-W22 -> 4.7653468 | X23: =X21-X22 -> 5.1977266 | Y23: =Y21-Y22 -> 5.8674902 | Z23: =Z21-Z22 -> 6.0934016 | ... AE23: =AE21-AE22 -> 4.7108839 | BB23: =BB21-BB22 -> 2.0482985 | BC23: =BC21-BC22 -> 4.2901786 | BD23: =BD21-BD22 -> 2.8097121 | BE23: =BE21-BE22 -> 0.68530303 | BF23: =BF21-BF22 -> 2.158675 | BG23: =BG21-BG22 -> 4.2268971 | BH23: =BH21-BH22 -> 2.7082179 | BI23: =BI21-BI22 -> 1.039 | ... CL23: =CL21-CL22 -> 4.2119201
A26: Presentation Data (End)
A27: Profit & Loss- Annual (Start)
A28: Gross Revenue | B28: ='Annual Raw'!C6 -> 0 | C28: ='Annual Raw'!D6 -> 0 | D28: ='Annual Raw'!E6 -> 0 | E28: ='Annual Raw'!F6 -> 0 | F28: ='Annual Raw'!G6 -> 340.68526 | G28: ='Annual Raw'!H6 -> 367.68239 | H28: ='Annual Raw'!I6 -> 373.99352 | I28: ='Annual Raw'!J6 -> 425.89375 | ... Z28: ='Annual Raw'!AA6 -> 21234.143 | AA28: =SUM(CH28:CK28) -> 22225.584 | AB28: =+SUM(CL28:CO28) -> 25087.742 | AC28: =+SUM(CP28:CS28) -> 28963.152 | AD28: =+SUM(CT28:CW28) -> 31096.131 | AE28: =+SUM(CX28:DA28) -> 37324.564 | AI28: ='QTR Raw'!C6+'QTR Raw'!C8 -> 0 | AJ28: ='QTR Raw'!D6+'QTR Raw'!D8 -> 0 | AK28: ='QTR Raw'!E6+'QTR Raw'!E8 -> 0 | AL28: ='QTR Raw'!F6+'QTR Raw'!F8 -> 0 | AM28: ='QTR Raw'!G6+'QTR Raw'!G8 -> 0 | AN28: ='QTR Raw'!H6+'QTR Raw'!H8 -> 0 | AO28: ='QTR Raw'!I6+'QTR Raw'!I8 -> 0 | AP28: ='QTR Raw'!J6+'QTR Raw'!J8 -> 0 | ... CL28: ='QTR Raw'!BF6+'QTR Raw'!BF8 -> 6721.537 | CM28: =CM8*CM17 -> 7841.0803 | CN28: =CN8*CN17 -> 5609.3238 | CO28: =CO8*CO17 -> 4915.8005 | CP28: =CP8*CP17 -> 7783.7432 | CQ28: =CQ8*CQ17 -> 9057.0172 | CR28: =CR8*CR17 -> 6453.101 | CS28: =CS8*CS17 -> 5669.2905 | CT28: =CT8*CT17 -> 8328.1611 | ... DA28: =DA8*DA17 -> 7364.4926
A29: Less: Exise Duty | B29: ='Annual Raw'!C7+'Annual Raw'!C8+'Annual Raw'!C9 -> 0 | C29: ='Annual Raw'!D7+'Annual Raw'!D8+'Annual Raw'!D9 -> 0 | D29: ='Annual Raw'!E7+'Annual Raw'!E8+'Annual Raw'!E9 -> 0 | E29: ='Annual Raw'!F7+'Annual Raw'!F8+'Annual Raw'!F9 -> 0 | F29: ='Annual Raw'!G7+'Annual Raw'!G8+'Annual Raw'!G9 -> 57.193838 | G29: ='Annual Raw'!H7+'Annual Raw'!H8+'Annual Raw'!H9 -> 60.750738 | H29: ='Annual Raw'!I7+'Annual Raw'!I8+'Annual Raw'!I9 -> 46.140744 | I29: ='Annual Raw'!J7+'Annual Raw'!J8+'Annual Raw'!J9 -> 53.163081 | ... Z29: ='Annual Raw'!AA7+'Annual Raw'!AA8+'Annual Raw'!AA9 -> 1226.493 | AA29: =SUM(CH29:CK29) -> 540.205 | AB29: =+SUM(CL29:CO29) -> 147.347 | AC29: =+SUM(CP29:CS29) -> 0 | AD29: =+SUM(CT29:CW29) -> 0 | AE29: =+SUM(CX29:DA29) -> 0 | AI29: ='QTR Raw'!C21+'QTR Raw'!C20+'QTR Raw'!C19+'QTR Raw'!C13+'QTR Raw'!C7 -> 0 | AJ29: ='QTR Raw'!D21+'QTR Raw'!D20+'QTR Raw'!D19+'QTR Raw'!D13+'QTR Raw'!D7 -> 0 | AK29: ='QTR Raw'!E21+'QTR Raw'!E20+'QTR Raw'!E19+'QTR Raw'!E13+'QTR Raw'!E7 -> 0 | AL29: ='QTR Raw'!F21+'QTR Raw'!F20+'QTR Raw'!F19+'QTR Raw'!F13+'QTR Raw'!F7 -> 0 | AM29: ='QTR Raw'!G21+'QTR Raw'!G20+'QTR Raw'!G19+'QTR Raw'!G13+'QTR Raw'!G7 -> 0 | AN29: ='QTR Raw'!H21+'QTR Raw'!H20+'QTR Raw'!H19+'QTR Raw'!H13+'QTR Raw'!H7 -> 0 | AO29: ='QTR Raw'!I21+'QTR Raw'!I20+'QTR Raw'!I19+'QTR Raw'!I13+'QTR Raw'!I7 -> 0 | AP29: ='QTR Raw'!J21+'QTR Raw'!J20+'QTR Raw'!J19+'QTR Raw'!J13+'QTR Raw'!J7 -> 0 | ... CL29: ='QTR Raw'!BF21+'QTR Raw'!BF20+'QTR Raw'!BF19+'QTR Raw'!BF13+'QTR Raw'!BF7 -> 147.347
A30: Net Revenue | B30: =+B28-B29 -> 0 | C30: =+C28-C29 -> 0 | D30: =+D28-D29 -> 0 | E30: =+E28-E29 -> 0 | F30: =+F28-F29 -> 283.49143 | G30: =+G28-G29 -> 306.93166 | H30: =+H28-H29 -> 327.85278 | I30: =+I28-I29 -> 372.73067 | ... AE30: =+AE28-AE29 -> 37324.564 | AI30: =+AI28-AI29 -> 0 | AJ30: =+AJ28-AJ29 -> 0 | AK30: =+AK28-AK29 -> 0 | AL30: =+AL28-AL29 -> 0 | AM30: =+AM28-AM29 -> 0 | AN30: =+AN28-AN29 -> 0 | AO30: =+AO28-AO29 -> 0 | AP30: =+AP28-AP29 -> 0 | ... DA30: =+DA28-DA29 -> 7364.4926
A31: Net Revenue YOY% | C31: =C30/B30-1 -> #DIV/0! | D31: =D30/C30-1 -> #DIV/0! | E31: =E30/D30-1 -> #DIV/0! | F31: =F30/E30-1 -> #DIV/0! | G31: =G30/F30-1 -> 0.082684091 | H31: =H30/G30-1 -> 0.068162154 | I31: =I30/H30-1 -> 0.13688428 | J31: =J30/I30-1 -> 0.23371979 | ... AE31: =AE30/AD30-1 -> 0.20029609 | AM31: =+IF(AI30<0,1-AM30/AI30,AM30/AI30-1) -> #DIV/0! | AN31: =+IF(AJ30<0,1-AN30/AJ30,AN30/AJ30-1) -> #DIV/0! | AO31: =+IF(AK30<0,1-AO30/AK30,AO30/AK30-1) -> #DIV/0! | AP31: =+IF(AL30<0,1-AP30/AL30,AP30/AL30-1) -> #DIV/0! | AQ31: =+IF(AM30<0,1-AQ30/AM30,AQ30/AM30-1) -> #DIV/0! | AR31: =+IF(AN30<0,1-AR30/AN30,AR30/AN30-1) -> #DIV/0! | AS31: =+IF(AO30<0,1-AS30/AO30,AS30/AO30-1) -> #DIV/0! | AT31: =+IF(AP30<0,1-AT30/AP30,AT30/AP30-1) -> #DIV/0! | ... DA31: =+IF(CW30<0,1-DA30/CW30,DA30/CW30-1) -> 0.20529805
A32: Net Revenue QOQ% | AJ32: =+IF(AI30<0,1-AJ30/AI30,AJ30/AI30-1) -> #DIV/0! | AK32: =+IF(AJ30<0,1-AK30/AJ30,AK30/AJ30-1) -> #DIV/0! | AL32: =+IF(AK30<0,1-AL30/AK30,AL30/AK30-1) -> #DIV/0! | AM32: =+IF(AL30<0,1-AM30/AL30,AM30/AL30-1) -> #DIV/0! | AN32: =+IF(AM30<0,1-AN30/AM30,AN30/AM30-1) -> #DIV/0! | AO32: =+IF(AN30<0,1-AO30/AN30,AO30/AN30-1) -> #DIV/0! | AP32: =+IF(AO30<0,1-AP30/AO30,AP30/AO30-1) -> #DIV/0! | AQ32: =+IF(AP30<0,1-AQ30/AP30,AQ30/AP30-1) -> #DIV/0! | ... DA32: =+IF(CZ30<0,1-DA30/CZ30,DA30/CZ30-1) -> -0.11677086
A33: Increase/Decrease in Stock | B33: ='Annual Raw'!C11 -> 0 | C33: ='Annual Raw'!D11 -> 0 | D33: ='Annual Raw'!E11 -> 0 | E33: ='Annual Raw'!F11 -> 0 | F33: ='Annual Raw'!G11 -> -7.2403229 | G33: ='Annual Raw'!H11 -> 2.2733899 | H33: ='Annual Raw'!I11 -> -0.031626 | I33: ='Annual Raw'!J11 -> -2.1219878 | ... Z33: ='Annual Raw'!AA11 -> -74.94 | AA33: =SUM(CH33:CK33) -> 8.914 | AB33: =+SUM(CL33:CO33) -> -271.768 | AC33: =+SUM(CP33:CS33) -> 0 | AD33: =+SUM(CT33:CW33) -> 0 | AE33: =+SUM(CX33:DA33) -> 0 | AI33: ='QTR Raw'!C10 -> 0 | AJ33: ='QTR Raw'!D10 -> 0 | AK33: ='QTR Raw'!E10 -> 0 | AL33: ='QTR Raw'!F10 -> 0 | AM33: ='QTR Raw'!G10 -> 0 | AN33: ='QTR Raw'!H10 -> 0 | AO33: ='QTR Raw'!I10 -> 0 | AP33: ='QTR Raw'!J10 -> 0 | ... CL33: ='QTR Raw'!BF10 -> -271.768
A34: Purchase of Finished Goods | B34: 0 | C34: 0 | D34: 0 | E34: 0 | F34: 0 | G34: 0 | H34: 0 | I34: 0 | J34: 0 | K34: 0 | L34: 0 | M34: 0 | N34: 0 | O34: 0 | P34: 0 | Q34: 0 | R34: 0 | S34: 0 | T34: 0 | U34: 0 | V34: 0 | W34: 0 | X34: 0 | Y34: 0 | Z34: 0 | AA34: =SUM(CH34:CK34) -> 369.453 | AB34: =+SUM(CL34:CO34) -> 65.211 | AC34: =+SUM(CP34:CS34) -> 0 | AD34: =+SUM(CT34:CW34) -> 0 | AE34: =+SUM(CX34:DA34) -> 0 | AI34: ='QTR Raw'!C12 -> 0 | AJ34: ='QTR Raw'!D12 -> 0 | AK34: ='QTR Raw'!E12 -> 0 | AL34: ='QTR Raw'!F12 -> 0 | AM34: ='QTR Raw'!G12 -> 0 | AN34: ='QTR Raw'!H12 -> 0 | AO34: ='QTR Raw'!I12 -> 0 | AP34: ='QTR Raw'!J12 -> 0 | ... CL34: ='QTR Raw'!BF12 -> 65.211
A35: Raw Material Consumed | B35: ='Annual Raw'!C12 -> 0 | C35: ='Annual Raw'!D12 -> 0 | D35: ='Annual Raw'!E12 -> 0 | E35: ='Annual Raw'!F12 -> 0 | F35: ='Annual Raw'!G12 -> 146.19765 | G35: ='Annual Raw'!H12 -> 156.13787 | H35: ='Annual Raw'!I12 -> 175.91754 | I35: ='Annual Raw'!J12 -> 209.33044 | ... Z35: ='Annual Raw'!AA12 -> 8979.664 | AA35: =SUM(CH35:CK35) -> 9337.062 | AB35: =+SUM(CL35:CO35) -> 11321.696 | AC35: =+SUM(CP35:CS35) -> 12893.524 | AD35: =+SUM(CT35:CW35) -> 13841.444 | AE35: =+SUM(CX35:DA35) -> 16613.819 | AI35: ='QTR Raw'!C11 -> 0 | AJ35: ='QTR Raw'!D11 -> 0 | AK35: ='QTR Raw'!E11 -> 0 | AL35: ='QTR Raw'!F11 -> 0 | AM35: ='QTR Raw'!G11 -> 0 | AN35: ='QTR Raw'!H11 -> 0 | AO35: ='QTR Raw'!I11 -> 0 | AP35: ='QTR Raw'!J11 -> 0 | ... CL35: ='QTR Raw'!BF11 -> 3152.202 | CM35: =+CM30-CM36 -> 3492.8145 | CN35: =+CN30-CN36 -> 2485.6458 | CO35: =+CO30-CO36 -> 2191.0342 | CP35: =+CP30-CP36 -> 3468.3442 | CQ35: =+CQ30-CQ36 -> 4030.0987 | CR35: =+CR30-CR36 -> 2870.6589 | CS35: =+CS30-CS36 -> 2524.4218 | CT35: =+CT30-CT36 -> 3707.4631 | ... DA35: =+DA30-DA36 -> 3278.1227
A36: Gross Profit | B36: =B30-B33-B35-B34 -> 0 | C36: =C30-C33-C35-C34 -> 0 | D36: =D30-D33-D35-D34 -> 0 | E36: =E30-E33-E35-E34 -> 0 | F36: =F30-F33-F35-F34 -> 144.5341 | G36: =G30-G33-G35-G34 -> 148.52039 | H36: =H30-H33-H35-H34 -> 151.96687 | I36: =I30-I33-I35-I34 -> 165.52222 | ... AE36: =AE30-AE33-AE35-AE34 -> 20710.745 | AI36: =AI30-AI33-AI35-AI34 -> 0 | AJ36: =AJ30-AJ33-AJ35-AJ34 -> 0 | AK36: =AK30-AK33-AK35-AK34 -> 0 | AL36: =AL30-AL33-AL35-AL34 -> 0 | AM36: =AM30-AM33-AM35-AM34 -> 0 | AN36: =AN30-AN33-AN35-AN34 -> 0 | AO36: =AO30-AO33-AO35-AO34 -> 0 | AP36: =AP30-AP33-AP35-AP34 -> 0 | ... CL36: =CL30-CL33-CL35-CL34 -> 3628.545 | CM36: =+CM37*CM30 -> 4348.2658 | CN36: =+CN37*CN30 -> 3123.678 | CO36: =+CO37*CO30 -> 2724.7663 | CP36: =+CP37*CP30 -> 4315.399 | CQ36: =+CQ37*CQ30 -> 5026.9185 | CR36: =+CR37*CR30 -> 3582.4421 | CS36: =+CS37*CS30 -> 3144.8688 | CT36: =+CT37*CT30 -> 4620.698 | ... DA36: =+DA37*DA30 -> 4086.3699
A37: GP% | B37: =B36/B30 -> #DIV/0! | C37: =C36/C30 -> #DIV/0! | D37: =D36/D30 -> #DIV/0! | E37: =E36/E30 -> #DIV/0! | F37: =F36/F30 -> 0.50983587 | G37: =G36/G30 -> 0.4838875 | H37: =H36/H30 -> 0.46352167 | I37: =I36/I30 -> 0.44407995 | ... AE37: =AE36/AE30 -> 0.55488244 | AI37: =AI36/AI30 -> #DIV/0! | AJ37: =AJ36/AJ30 -> #DIV/0! | AK37: =AK36/AK30 -> #DIV/0! | AL37: =AL36/AL30 -> #DIV/0! | AM37: =AM36/AM30 -> #DIV/0! | AN37: =AN36/AN30 -> #DIV/0! | AO37: =AO36/AO30 -> #DIV/0! | AP37: =AP36/AP30 -> #DIV/0! | ... CL37: =CL36/CL30 -> 0.55193796 | CM37: =AVERAGE(CI37:CL37) -> 0.55454933 | CN37: =AVERAGE(CJ37:CM37) -> 0.55687247 | CO37: =AVERAGE(CK37:CN37) -> 0.55428741 | CP37: =AVERAGE(CL37:CO37) -> 0.55441179 | CQ37: =AVERAGE(CM37:CP37) -> 0.55503025 | CR37: =AVERAGE(CN37:CQ37) -> 0.55515048 | CS37: =AVERAGE(CO37:CR37) -> 0.55471998 | CT37: =AVERAGE(CP37:CS37) -> 0.55482813 | ... DA37: =AVERAGE(CW37:CZ37) -> 0.5548746
A38: GP YOY% | C38: =+IF(B36<0,1-C36/B36,C36/B36-1) -> #DIV/0! | D38: =+IF(C36<0,1-D36/C36,D36/C36-1) -> #DIV/0! | E38: =+IF(D36<0,1-E36/D36,E36/D36-1) -> #DIV/0! | F38: =+IF(E36<0,1-F36/E36,F36/E36-1) -> #DIV/0! | G38: =+IF(F36<0,1-G36/F36,G36/F36-1) -> 0.027580297 | H38: =+IF(G36<0,1-H36/G36,H36/G36-1) -> 0.023205412 | I38: =+IF(H36<0,1-I36/H36,I36/H36-1) -> 0.089199359 | J38: =+IF(I36<0,1-J36/I36,J36/I36-1) -> 0.21628057 | ... AE38: =+IF(AD36<0,1-AE36/AD36,AE36/AD36-1) -> 0.20029678 | AM38: =+IF(AI36<0,1-AM36/AI36,AM36/AI36-1) -> #DIV/0! | AN38: =+IF(AJ36<0,1-AN36/AJ36,AN36/AJ36-1) -> #DIV/0! | AO38: =+IF(AK36<0,1-AO36/AK36,AO36/AK36-1) -> #DIV/0! | AP38: =+IF(AL36<0,1-AP36/AL36,AP36/AL36-1) -> #DIV/0! | AQ38: =+IF(AM36<0,1-AQ36/AM36,AQ36/AM36-1) -> #DIV/0! | AR38: =+IF(AN36<0,1-AR36/AN36,AR36/AN36-1) -> #DIV/0! | AS38: =+IF(AO36<0,1-AS36/AO36,AS36/AO36-1) -> #DIV/0! | AT38: =+IF(AP36<0,1-AT36/AP36,AT36/AP36-1) -> #DIV/0! | ... CL38: =+IF(CH36<0,1-CL36/CH36,CL36/CH36-1) -> 0.19443643 | CM38: =+CM36/CI36-1 -> 0.13642449 | CN38: =+CN36/CJ36-1 -> 0.12466002 | CO38: =+CO36/CK36-1 -> 0.17024779 | CP38: =+CP36/CL36-1 -> 0.18929186 | CQ38: =+CQ36/CM36-1 -> 0.15607434 | CR38: =+CR36/CN36-1 -> 0.14686665 | CS38: =+CS36/CO36-1 -> 0.15417924 | CT38: =+CT36/CP36-1 -> 0.07074641 | ... DA38: =+DA36/CW36-1 -> 0.205358
A39: GP QOQ% | AJ39: =+IF(AI36<0,1-AJ36/AI36,AJ36/AI36-1) -> #DIV/0! | AK39: =+IF(AJ36<0,1-AK36/AJ36,AK36/AJ36-1) -> #DIV/0! | AL39: =+IF(AK36<0,1-AL36/AK36,AL36/AK36-1) -> #DIV/0! | AM39: =+IF(AL36<0,1-AM36/AL36,AM36/AL36-1) -> #DIV/0! | AN39: =+IF(AM36<0,1-AN36/AM36,AN36/AM36-1) -> #DIV/0! | AO39: =+IF(AN36<0,1-AO36/AN36,AO36/AN36-1) -> #DIV/0! | AP39: =+IF(AO36<0,1-AP36/AO36,AP36/AO36-1) -> #DIV/0! | AQ39: =+IF(AP36<0,1-AQ36/AP36,AQ36/AP36-1) -> #DIV/0! | ... CL39: =+IF(CK36<0,1-CL36/CK36,CL36/CK36-1) -> 0.55840767 | CM39: =+CM36/CL36-1 -> 0.1983497 | CN39: =+CN36/CM36-1 -> -0.28162672 | CO39: =+CO36/CN36-1 -> -0.12770575 | CP39: =+CP36/CO36-1 -> 0.58376847 | CQ39: =+CQ36/CP36-1 -> 0.16487919 | CR39: =+CR36/CQ36-1 -> -0.28734829 | CS39: =+CS36/CR36-1 -> -0.12214387 | CT39: =+CT36/CS36-1 -> 0.46928167 | ... DA39: =+DA36/CZ36-1 -> -0.1167814
A40: Power & Fuel Cost | B40: ='Annual Raw'!C13 -> 0 | C40: ='Annual Raw'!D13 -> 0 | D40: ='Annual Raw'!E13 -> 0 | E40: ='Annual Raw'!F13 -> 0 | F40: ='Annual Raw'!G13 -> 16.275857 | G40: ='Annual Raw'!H13 -> 17.007646 | H40: ='Annual Raw'!I13 -> 15.316662 | I40: ='Annual Raw'!J13 -> 14.83647 | ... Z40: ='Annual Raw'!AA13 -> 629.508 | AA40: =SUM(CH40:CK40) -> 0 | AB40: =+SUM(CL40:CO40) -> 0 | AC40: =+SUM(CP40:CS40) -> 0 | AD40: =+SUM(CT40:CW40) -> 0 | AE40: =+SUM(CX40:DA40) -> 0 | AI40: ='QTR Raw'!C15 -> 0 | AJ40: ='QTR Raw'!D15 -> 0 | AK40: ='QTR Raw'!E15 -> 0 | AL40: ='QTR Raw'!F15 -> 0 | AM40: ='QTR Raw'!G15 -> 0 | AN40: ='QTR Raw'!H15 -> 0 | AO40: ='QTR Raw'!I15 -> 0 | AP40: ='QTR Raw'!J15 -> 0 | ... CL40: ='QTR Raw'!BF15 -> 0
A41: Selling and Distribution Expenses | B41: =('Annual Raw'!C18) -> 0 | C41: =('Annual Raw'!D18) -> 0 | D41: =('Annual Raw'!E18) -> 0 | E41: =('Annual Raw'!F18) -> 0 | F41: =('Annual Raw'!G18) -> 2.9303384 | G41: =('Annual Raw'!H18) -> 4.3703567 | H41: =('Annual Raw'!I18) -> 2.9705899 | I41: =('Annual Raw'!J18) -> 4.6175069 | ... Z41: =('Annual Raw'!AA18) -> 669.552 | AA41: =SUM(CH41:CK41) -> 0 | AB41: =+SUM(CL41:CO41) -> 0 | AC41: =+SUM(CP41:CS41) -> 0 | AD41: =+SUM(CT41:CW41) -> 0 | AE41: =+SUM(CX41:DA41) -> 0 | AI41: ='QTR Raw'!C18 -> 0 | AJ41: ='QTR Raw'!D18 -> 0 | AK41: ='QTR Raw'!E18 -> 0 | AL41: ='QTR Raw'!F18 -> 0 | AM41: ='QTR Raw'!G18 -> 0 | AN41: ='QTR Raw'!H18 -> 0 | AO41: ='QTR Raw'!I18 -> 0 | AP41: ='QTR Raw'!J18 -> 0 | ... CL41: ='QTR Raw'!BF18 -> 0
A42: Other Manufacturing Expenses | B42: ='Annual Raw'!C15+'Annual Raw'!C16 -> 0 | C42: ='Annual Raw'!D15+'Annual Raw'!D16 -> 0 | D42: ='Annual Raw'!E15+'Annual Raw'!E16 -> 0 | E42: ='Annual Raw'!F15+'Annual Raw'!F16 -> 0 | F42: ='Annual Raw'!G15+'Annual Raw'!G16 -> 41.620309 | G42: ='Annual Raw'!H15+'Annual Raw'!H16 -> 43.679928 | H42: ='Annual Raw'!I15+'Annual Raw'!I16 -> 46.400612 | I42: ='Annual Raw'!J15+'Annual Raw'!J16 -> 51.546875 | ... Z42: ='Annual Raw'!AA15+'Annual Raw'!AA16 -> 2373.182 | AA42: =SUM(CH42:CK42) -> 4719.838 | AB42: =+SUM(CL42:CO42) -> 5675.9772 | AC42: =+SUM(CP42:CS42) -> 6582.8344 | AD42: =+SUM(CT42:CW42) -> 7225.6344 | AE42: =+SUM(CX42:DA42) -> 9047.7934 | AI42: ='QTR Raw'!C14 -> 0 | AJ42: ='QTR Raw'!D14 -> 0 | AK42: ='QTR Raw'!E14 -> 0 | AL42: ='QTR Raw'!F14 -> 0 | AM42: ='QTR Raw'!G14 -> 0 | AN42: ='QTR Raw'!H14 -> 0 | AO42: ='QTR Raw'!I14 -> 0 | AP42: ='QTR Raw'!J14 -> 0 | ... CL42: ='QTR Raw'!BF14 -> 1480.345 | CM42: =CM46-CM43 -> 1911.2194 | CN42: =CN46-CN43 -> 1275.2655 | CO42: =CO46-CO43 -> 1009.1473 | CP42: =CP46-CP43 -> 1798.5929 | CQ42: =CQ46-CQ43 -> 2227.55 | CR42: =CR46-CR43 -> 1396.807 | CS42: =CS46-CS43 -> 1159.8844 | CT42: =CT46-CT43 -> 1960.0268 | ... DA42: =DA46-DA43 -> 1603.3251
A43: Employee Cost | B43: ='Annual Raw'!C14 -> 0 | C43: ='Annual Raw'!D14 -> 0 | D43: ='Annual Raw'!E14 -> 0 | E43: ='Annual Raw'!F14 -> 0 | F43: ='Annual Raw'!G14 -> 15.354206 | G43: ='Annual Raw'!H14 -> 18.509317 | H43: ='Annual Raw'!I14 -> 20.416254 | I43: ='Annual Raw'!J14 -> 21.135453 | ... Z43: ='Annual Raw'!AA14 -> 1885.026 | AA43: =SUM(CH43:CK43) -> 2200.743 | AB43: =+SUM(CL43:CO43) -> 2426.7609 | AC43: =+SUM(CP43:CS43) -> 2596.6341 | AD43: =+SUM(CT43:CW43) -> 2778.3985 | AE43: =+SUM(CX43:DA43) -> 2972.8864 | AI43: ='QTR Raw'!C16 -> 0 | AJ43: ='QTR Raw'!D16 -> 0 | AK43: ='QTR Raw'!E16 -> 0 | AL43: ='QTR Raw'!F16 -> 0 | AM43: ='QTR Raw'!G16 -> 0 | AN43: ='QTR Raw'!H16 -> 0 | AO43: ='QTR Raw'!I16 -> 0 | AP43: ='QTR Raw'!J16 -> 0 | ... CL43: ='QTR Raw'!BF16 -> 619.273 | CM43: =CI43*107% -> 588.13406 | CN43: =CJ43*107% -> 592.0524 | CO43: =CK43*107% -> 627.30141 | CP43: =CL43*107% -> 662.62211 | CQ43: =CM43*107% -> 629.30344 | CR43: =CN43*107% -> 633.49607 | CS43: =CO43*107% -> 671.21251 | CT43: =CP43*107% -> 709.00566 | ... DA43: =CW43*107% -> 768.4712
A44: General and Administration Expenses | B44: ='Annual Raw'!C17 -> 0 | C44: ='Annual Raw'!D17 -> 0 | D44: ='Annual Raw'!E17 -> 0 | E44: ='Annual Raw'!F17 -> 0 | F44: ='Annual Raw'!G17 -> 6.838419 | G44: ='Annual Raw'!H17 -> 7.6012442 | H44: ='Annual Raw'!I17 -> 12.186069 | I44: ='Annual Raw'!J17 -> 13.76165 | ... Z44: ='Annual Raw'!AA17 -> 618.951 | AA44: =SUM(CH44:CK44) -> 0 | AB44: =+SUM(CL44:CO44) -> 0 | AC44: =+SUM(CP44:CS44) -> 0 | AD44: =+SUM(CT44:CW44) -> 0 | AE44: =+SUM(CX44:DA44) -> 0 | AI44: ='QTR Raw'!C17 -> 0 | AJ44: ='QTR Raw'!D17 -> 0 | AK44: ='QTR Raw'!E17 -> 0 | AL44: ='QTR Raw'!F17 -> 0 | AM44: ='QTR Raw'!G17 -> 0 | AN44: ='QTR Raw'!H17 -> 0 | AO44: ='QTR Raw'!I17 -> 0 | AP44: ='QTR Raw'!J17 -> 0 | ... CL44: ='QTR Raw'!BF17 -> 0
A45: Miscellaneous Expenses | B45: ='Annual Raw'!C19-'Annual Raw'!C20 -> 0 | C45: ='Annual Raw'!D19-'Annual Raw'!D20 -> 0 | D45: ='Annual Raw'!E19-'Annual Raw'!E20 -> 0 | E45: ='Annual Raw'!F19-'Annual Raw'!F20 -> 0 | F45: ='Annual Raw'!G19-'Annual Raw'!G20 -> 0.33951 | G45: ='Annual Raw'!H19-'Annual Raw'!H20 -> 2.0761435 | H45: ='Annual Raw'!I19-'Annual Raw'!I20 -> 0.178153 | I45: ='Annual Raw'!J19-'Annual Raw'!J20 -> 0.4061102 | ... Z45: ='Annual Raw'!AA19-'Annual Raw'!AA20 -> 183.164 | AA45: =SUM(CH45:CK45) -> 0 | AB45: =+SUM(CL45:CO45) -> 0 | AC45: =+SUM(CP45:CS45) -> 0 | AD45: =+SUM(CT45:CW45) -> 0 | AE45: =+SUM(CX45:DA45) -> 0
A46: Total Cost | B46: =+SUM(B40:B45) -> 0 | C46: =+SUM(C40:C45) -> 0 | D46: =+SUM(D40:D45) -> 0 | E46: =+SUM(E40:E45) -> 0 | F46: =+SUM(F40:F45) -> 83.35864 | G46: =+SUM(G40:G45) -> 93.244635 | H46: =+SUM(H40:H45) -> 97.46834 | I46: =+SUM(I40:I45) -> 106.30407 | ... AE46: =+SUM(AE40:AE45) -> 12020.68 | AI46: =+SUM(AI40:AI45) -> 0 | AJ46: =+SUM(AJ40:AJ45) -> 0 | AK46: =+SUM(AK40:AK45) -> 0 | AL46: =+SUM(AL40:AL45) -> 0 | AM46: =+SUM(AM40:AM45) -> 0 | AN46: =+SUM(AN40:AN45) -> 0 | AO46: =+SUM(AO40:AO45) -> 0 | AP46: =+SUM(AP40:AP45) -> 0 | ... CL46: =+SUM(CL40:CL45) -> 2099.618 | CM46: =CM47*CM30 -> 2499.3535 | CN46: =CN47*CN30 -> 1867.3179 | CO46: =CO47*CO30 -> 1636.4487 | CP46: =CP47*CP30 -> 2461.215 | CQ46: =CQ47*CQ30 -> 2856.8535 | CR46: =CR47*CR30 -> 2030.3031 | CS46: =CS47*CS30 -> 1831.097 | CT46: =CT47*CT30 -> 2669.0325 | ... DA46: =DA47*DA30 -> 2371.7963
A47: Cost % | B47: =B46/B30 -> #DIV/0! | C47: =C46/C30 -> #DIV/0! | D47: =D46/D30 -> #DIV/0! | E47: =E46/E30 -> #DIV/0! | F47: =F46/F30 -> 0.2940429 | G47: =G46/G30 -> 0.30379608 | H47: =H46/H30 -> 0.29729301 | I47: =I46/I30 -> 0.28520343 | ... AE47: =AE46/AE30 -> 0.32205814 | AI47: =AI46/AI30 -> #DIV/0! | AJ47: =AJ46/AJ30 -> #DIV/0! | AK47: =AK46/AK30 -> #DIV/0! | AL47: =AL46/AL30 -> #DIV/0! | AM47: =AM46/AM30 -> #DIV/0! | AN47: =AN46/AN30 -> #DIV/0! | AO47: =AO46/AO30 -> #DIV/0! | AP47: =AP46/AP30 -> #DIV/0! | ... CL47: =CL46/CL30 -> 0.31937288 | CM47: =AVERAGE(CI47:CL47)*0.97 -> 0.31875117 | CN47: =AVERAGE(CJ47:CM47)*0.97 -> 0.33289536 | CO47: =AVERAGE(CK47:CN47)*0.97 -> 0.33289566 | CP47: =AVERAGE(CL47:CO47)*0.97 -> 0.31619941 | CQ47: =AVERAGE(CM47:CP47)*0.97 -> 0.31542984 | CR47: =AVERAGE(CN47:CQ47)*0.97 -> 0.31462441 | CS47: =AVERAGE(CO47:CR47)*1.01 -> 0.3229852 | CT47: =AVERAGE(CP47:CS47)*1.01 -> 0.32048281 | CU47: =AVERAGE(CQ47:CT47)*1.01 -> 0.32156437 | CV47: =AVERAGE(CR47:CU47)*1.01 -> 0.32311334 | CW47: =AVERAGE(CS47:CV47) -> 0.32203643 | CX47: =AVERAGE(CT47:CW47) -> 0.32179924 | CY47: =AVERAGE(CU47:CX47) -> 0.32212835 | CZ47: =AVERAGE(CV47:CY47) -> 0.32226934 | DA47: =AVERAGE(CW47:CZ47) -> 0.32205834
A48: EBITDA | B48: =B36-B46 -> 0 | C48: =C36-C46 -> 0 | D48: =D36-D46 -> 0 | E48: =E36-E46 -> 0 | F48: =F36-F46 -> 61.175459 | G48: =G36-G46 -> 55.275757 | H48: =H36-H46 -> 54.498529 | I48: =I36-I46 -> 59.21815 | ... AE48: =AE36-AE46 -> 8690.0656 | AI48: =AI36-AI46 -> 0 | AJ48: =AJ36-AJ46 -> 0 | AK48: =AK36-AK46 -> 0 | AL48: =AL36-AL46 -> 0 | AM48: =AM36-AM46 -> 0 | AN48: =AN36-AN46 -> 0 | AO48: =AO36-AO46 -> 0 | AP48: =AP36-AP46 -> 0 | ... DA48: =DA36-DA46 -> 1714.5736
A49: EBITDA Margins | B49: =B48/B30 -> #DIV/0! | C49: =C48/C30 -> #DIV/0! | D49: =D48/D30 -> #DIV/0! | E49: =E48/E30 -> #DIV/0! | F49: =F48/F30 -> 0.21579298 | G49: =G48/G30 -> 0.18009142 | H49: =H48/H30 -> 0.16622866 | I49: =I48/I30 -> 0.15887652 | ... AE49: =AE48/AE30 -> 0.2328243 | AI49: =AI48/AI30 -> #DIV/0! | AJ49: =AJ48/AJ30 -> #DIV/0! | AK49: =AK48/AK30 -> #DIV/0! | AL49: =AL48/AL30 -> #DIV/0! | AM49: =AM48/AM30 -> #DIV/0! | AN49: =AN48/AN30 -> #DIV/0! | AO49: =AO48/AO30 -> #DIV/0! | AP49: =AP48/AP30 -> #DIV/0! | ... DA49: =DA48/DA30 -> 0.23281626
A50: EBITDA YOY% | C50: =+IF(B48<0,1-C48/B48,C48/B48-1) -> #DIV/0! | D50: =+IF(C48<0,1-D48/C48,D48/C48-1) -> #DIV/0! | E50: =+IF(D48<0,1-E48/D48,E48/D48-1) -> #DIV/0! | F50: =+IF(E48<0,1-F48/E48,F48/E48-1) -> #DIV/0! | G50: =+IF(F48<0,1-G48/F48,G48/F48-1) -> -0.096439035 | H50: =+IF(G48<0,1-H48/G48,H48/G48-1) -> -0.014060917 | I50: =+IF(H48<0,1-I48/H48,I48/H48-1) -> 0.086600901 | J50: =+IF(I48<0,1-J48/I48,J48/I48-1) -> 0.13687779 | ... AE50: =+IF(AD48<0,1-AE48/AD48,AE48/AD48-1) -> 0.19852157 | AM50: =+IF(AI48<0,1-AM48/AI48,AM48/AI48-1) -> #DIV/0! | AN50: =+IF(AJ48<0,1-AN48/AJ48,AN48/AJ48-1) -> #DIV/0! | AO50: =+IF(AK48<0,1-AO48/AK48,AO48/AK48-1) -> #DIV/0! | AP50: =+IF(AL48<0,1-AP48/AL48,AP48/AL48-1) -> #DIV/0! | AQ50: =+IF(AM48<0,1-AQ48/AM48,AQ48/AM48-1) -> #DIV/0! | AR50: =+IF(AN48<0,1-AR48/AN48,AR48/AN48-1) -> #DIV/0! | AS50: =+IF(AO48<0,1-AS48/AO48,AS48/AO48-1) -> #DIV/0! | AT50: =+IF(AP48<0,1-AT48/AP48,AT48/AP48-1) -> #DIV/0! | ... CL50: =+IF(CH48<0,1-CL48/CH48,CL48/CH48-1) -> 0.2096286 | CM50: =+CM48/CI48-1 -> -0.074976345 | CN50: =+CN48/CJ48-1 -> 0.094985525 | CO50: =+CO48/CK48-1 -> 0.7024755 | CP50: =+CP48/CL48-1 -> 0.2127355 | CQ50: =+CQ48/CM48-1 -> 0.17369821 | CR50: =+CR48/CN48-1 -> 0.23542524 | CS50: =+CS48/CO48-1 -> 0.20715837 | CT50: =+CT48/CP48-1 -> 0.052573788 | ... DA50: =+DA48/CW48-1 -> 0.2053275
A51: EBITDA QOQ% | AJ51: =+IF(AI48<0,1-AJ48/AI48,AJ48/AI48-1) -> #DIV/0! | AK51: =+IF(AJ48<0,1-AK48/AJ48,AK48/AJ48-1) -> #DIV/0! | AL51: =+IF(AK48<0,1-AL48/AK48,AL48/AK48-1) -> #DIV/0! | AM51: =+IF(AL48<0,1-AM48/AL48,AM48/AL48-1) -> #DIV/0! | AN51: =+IF(AM48<0,1-AN48/AM48,AN48/AM48-1) -> #DIV/0! | AO51: =+IF(AN48<0,1-AO48/AN48,AO48/AN48-1) -> #DIV/0! | AP51: =+IF(AO48<0,1-AP48/AO48,AP48/AO48-1) -> #DIV/0! | AQ51: =+IF(AP48<0,1-AQ48/AP48,AQ48/AP48-1) -> #DIV/0! | ... CI51: =+IF(CH48<0,1-CI48/CH48,CI48/CH48-1) -> 0.58135279 | CJ51: =+IF(CI48>1,CJ48/CI48-1,1-CJ48/CI48) -> -0.42595983 | CK51: =+IF(CJ48>1,CK48/CJ48-1,1-CK48/CJ48) -> -0.44285396 | CL51: =+IF(CK48>1,CL48/CK48-1,1-CL48/CK48) -> 1.3917288 | CM51: =+CM48/CL48-1 -> 0.2092875 | CN51: =+CN48/CM48-1 -> -0.32048691 | CO51: =+CO48/CN48-1 -> -0.1337534 | CP51: =+CP48/CO48-1 -> 0.70371582 | CQ51: =+CQ48/CP48-1 -> 0.1703612 | CR51: =+CR48/CQ48-1 -> -0.28475002 | CS51: =+CS48/CR48-1 -> -0.15357335 | CT51: =+CT48/CS48-1 -> 0.48554378 | ... DA51: =+DA48/CZ48-1 -> -0.11599482
A52: Depreciation | B52: ='Annual Raw'!C27 -> 0 | C52: ='Annual Raw'!D27 -> 0 | D52: ='Annual Raw'!E27 -> 0 | E52: ='Annual Raw'!F27 -> 0 | F52: ='Annual Raw'!G27 -> 18.074277 | G52: ='Annual Raw'!H27 -> 25.204787 | H52: ='Annual Raw'!I27 -> 26.143209 | I52: ='Annual Raw'!J27 -> 18.588624 | ... Z52: ='Annual Raw'!AA27 -> 947.386 | AA52: =SUM(CH52:CK52) -> 1216.463 | AB52: =+SUM(CL52:CO52) -> 1538.3506 | AC52: =+SUM(CP52:CS52) -> 1612.7288 | AD52: =+SUM(CT52:CW52) -> 1651.4613 | AE52: =+SUM(CX52:DA52) -> 1686.32 | AI52: ='QTR Raw'!C28 -> 0 | AJ52: ='QTR Raw'!D28 -> 0 | AK52: ='QTR Raw'!E28 -> 0 | AL52: ='QTR Raw'!F28 -> 0 | AM52: ='QTR Raw'!G28 -> 0 | AN52: ='QTR Raw'!H28 -> 0 | AO52: ='QTR Raw'!I28 -> 0 | AP52: ='QTR Raw'!J28 -> 0 | ... CL52: ='QTR Raw'!BF28 -> 356.794 | CM52: =CM53*CL154 -> 391.0439 | CN52: =CN53*CM154 -> 393.87676 | CO52: =CO53*CN154 -> 396.63596 | CP52: =CP53*CO154 -> 399.32343 | CQ52: =CQ53*CP154 -> 401.94102 | CR52: =CR53*CQ154 -> 404.49055 | CS52: =CS53*CR154 -> 406.9738 | CT52: =CT53*CS154 -> 409.39248 | ... DA52: =DA53*CZ154 -> 424.65109
A53: Depreciation % of Net Block | B53: =+B52/B154 -> #DIV/0! | C53: =+C52/C154 -> #DIV/0! | D53: =+D52/D154 -> #DIV/0! | E53: =+E52/E154 -> #DIV/0! | F53: =+F52/F154 -> 0.058970882 | G53: =+G52/G154 -> 0.085843575 | H53: =+H52/H154 -> 0.089156117 | I53: =+I52/I154 -> 0.060955592 | ... AE53: =+AE52/AE154 -> 0.10277373 | AI53: =+AI52/AH154 -> #DIV/0! | AJ53: =+AJ52/AI154 -> #DIV/0! | AK53: =+AK52/AJ154 -> #DIV/0! | AL53: =+AL52/AK154 -> #DIV/0! | AM53: =+AM52/AL154 -> #DIV/0! | AN53: =+AN52/AM154 -> #DIV/0! | AO53: =+AO52/AN154 -> #DIV/0! | AP53: =+AP52/AO154 -> #DIV/0! | ... CE53: =+CE52/CD154 -> 0.032989027 | CF53: =+CF52/CE151 -> 0.024929908 | CG53: =+CG52/CF154 -> 0.025335123 | CH53: =+CH52/CG154 -> 0.02080125 | CI53: =+CI52/CH154 -> 0.02336888 | CJ53: =+CJ52/CI154 -> 0.022113921 | CK53: =+CK52/CJ154 -> 0.023738604 | CL53: =+CL52/CK154 -> 0.023722769 | CM53: 0.026 | CN53: =CM53 -> 0.026 | CO53: =CN53 -> 0.026 | CP53: =CO53 -> 0.026 | CQ53: =CP53 -> 0.026 | CR53: =CQ53 -> 0.026 | CS53: =CR53 -> 0.026 | CT53: =CS53 -> 0.026 | CU53: =CT53 -> 0.026 | ... DA53: =CZ53 -> 0.026
A54: EBIT | B54: =B48-B52 -> 0 | C54: =C48-C52 -> 0 | D54: =D48-D52 -> 0 | E54: =E48-E52 -> 0 | F54: =F48-F52 -> 43.101182 | G54: =G48-G52 -> 30.07097 | H54: =H48-H52 -> 28.35532 | I54: =I48-I52 -> 40.629527 | ... AE54: =AE48-AE52 -> 7003.7457 | AI54: =AI48-AI52 -> 0 | AJ54: =AJ48-AJ52 -> 0 | AK54: =AK48-AK52 -> 0 | AL54: =AL48-AL52 -> 0 | AM54: =AM48-AM52 -> 0 | AN54: =AN48-AN52 -> 0 | AO54: =AO48-AO52 -> 0 | AP54: =AP48-AP52 -> 0 | ... DA54: =DA48-DA52 -> 1289.9225
A55: Other Income | B55: ='Annual Raw'!C23 -> 0 | C55: ='Annual Raw'!D23 -> 0 | D55: ='Annual Raw'!E23 -> 0 | E55: ='Annual Raw'!F23 -> 0 | F55: ='Annual Raw'!G23 -> 2.2789537 | G55: ='Annual Raw'!H23 -> 3.1997436 | H55: ='Annual Raw'!I23 -> 3.1739386 | I55: ='Annual Raw'!J23 -> 3.299421 | ... Z55: ='Annual Raw'!AA23 -> 121.268 | AA55: =SUM(CH55:CK55) -> 352.348 | AB55: =+SUM(CL55:CO55) -> 43.528 | AC55: =+SUM(CP55:CS55) -> 0 | AD55: =+SUM(CT55:CW55) -> 0 | AE55: =+SUM(CX55:DA55) -> 0 | AI55: ='QTR Raw'!C23 -> 0 | AJ55: ='QTR Raw'!D23 -> 0 | AK55: ='QTR Raw'!E23 -> 0 | AL55: ='QTR Raw'!F23 -> 0 | AM55: ='QTR Raw'!G23 -> 0 | AN55: ='QTR Raw'!H23 -> 0 | AO55: ='QTR Raw'!I23 -> 0 | AP55: ='QTR Raw'!J23 -> 0 | ... CL55: ='QTR Raw'!BF23 -> 43.528
A56: Interest | B56: ='Annual Raw'!C25 -> 0 | C56: ='Annual Raw'!D25 -> 0 | D56: ='Annual Raw'!E25 -> 0 | E56: ='Annual Raw'!F25 -> 0 | F56: ='Annual Raw'!G25 -> 14.002554 | G56: ='Annual Raw'!H25 -> 13.223031 | H56: ='Annual Raw'!I25 -> 12.519253 | I56: ='Annual Raw'!J25 -> 10.448867 | ... Z56: ='Annual Raw'!AA25 -> 482.858 | AA56: =SUM(CH56:CK56) -> 169.579 | AB56: =+SUM(CL56:CO56) -> -126.80142 | AC56: =+SUM(CP56:CS56) -> -446.79252 | AD56: =+SUM(CT56:CW56) -> -559.06457 | AE56: =+SUM(CX56:DA56) -> -805.07051 | AI56: ='QTR Raw'!C25 -> 0 | AJ56: ='QTR Raw'!D25 -> 0 | AK56: ='QTR Raw'!E25 -> 0 | AL56: ='QTR Raw'!F25 -> 0 | AM56: ='QTR Raw'!G25 -> 0 | AN56: ='QTR Raw'!H25 -> 0 | AO56: ='QTR Raw'!I25 -> 0 | AP56: ='QTR Raw'!J25 -> 0 | ... CL56: ='QTR Raw'!BF25 -> 48.525 | CM56: =CM57*CL188 -> -41.99498 | CN56: =CN57*CM188 -> -49.795461 | CO56: =CO57*CN188 -> -83.535982 | CP56: =CP57*CO188 -> -99.80347 | CQ56: =CQ57*CP188 -> -92.543093 | CR56: =CR57*CQ188 -> -105.84564 | CS56: =CS57*CR188 -> -148.60031 | CT56: =CT57*CS188 -> -127.70173 | ... DA56: =DA57*CZ188 -> -238.84337
A57: Interest % of Debt | B57: =+B56/B148 -> #DIV/0! | C57: =+C56/C148 -> #DIV/0! | D57: =+D56/D148 -> #DIV/0! | E57: =+E56/E148 -> #DIV/0! | F57: =+F56/F148 -> 0.082126156 | G57: =+G56/G148 -> 0.091246803 | H57: =+H56/H148 -> 0.093785772 | I57: =+I56/I148 -> 0.081561251 | ... AE57: =+AE56/AE148 -> -0.39773873 | AI57: =(AI56-AI55)/AH188 -> #DIV/0! | AJ57: =(AJ56-AJ55)/AI188 -> #DIV/0! | AK57: =(AK56-AK55)/AJ188 -> #DIV/0! | AL57: =(AL56-AL55)/AK188 -> #DIV/0! | AM57: =(AM56-AM55)/AL188 -> #DIV/0! | AN57: =(AN56-AN55)/AM188 -> #DIV/0! | AO57: =(AO56-AO55)/AN188 -> #DIV/0! | AP57: =(AP56-AP55)/AO188 -> #DIV/0! | ... CL57: =(CL56-CL55)/CK188 -> 0.19498205 | CM57: 0.02 | CN57: =+CM57 -> 0.02 | CO57: =+CN57 -> 0.02 | CP57: =+CO57 -> 0.02 | CQ57: =+CP57 -> 0.02 | CR57: =+CQ57 -> 0.02 | CS57: =+CR57 -> 0.02 | CT57: 0.015 | CU57: =+CT57 -> 0.015 | CV57: =+CU57 -> 0.015 | CW57: =+CV57 -> 0.015 | CX57: =+CW57 -> 0.015 | CY57: =+CX57 -> 0.015 | CZ57: =+CY57 -> 0.015 | DA57: =+CZ57 -> 0.015
A58: PBT | B58: =B54+B55-B56 -> 0 | C58: =C54+C55-C56 -> 0 | D58: =D54+D55-D56 -> 0 | E58: =E54+E55-E56 -> 0 | F58: =F54+F55-F56 -> 31.377582 | G58: =G54+G55-G56 -> 20.047682 | H58: =H54+H55-H56 -> 19.010006 | I58: =I54+I55-I56 -> 33.480081 | ... AE58: =AE54+AE55-AE56 -> 7808.8162 | AI58: =AI54+AI55-AI56 -> 0 | AJ58: =AJ54+AJ55-AJ56 -> 0 | AK58: =AK54+AK55-AK56 -> 0 | AL58: =AL54+AL55-AL56 -> 0 | AM58: =AM54+AM55-AM56 -> 0 | AN58: =AN54+AN55-AN56 -> 0 | AO58: =AO54+AO55-AO56 -> 0 | AP58: =AP54+AP55-AP56 -> 0 | ... DA58: =DA54+DA55-DA56 -> 1528.7659
A59: Tax | B59: ='Annual Raw'!C30 -> 0 | C59: ='Annual Raw'!D30 -> 0 | D59: ='Annual Raw'!E30 -> 0 | E59: ='Annual Raw'!F30 -> 0 | F59: ='Annual Raw'!G30 -> 13.206834 | G59: ='Annual Raw'!H30 -> 9.1863785 | H59: ='Annual Raw'!I30 -> 4.8914094 | I59: ='Annual Raw'!J30 -> 12.292801 | ... Z59: ='Annual Raw'!AA30 -> 798.804 | AA59: =SUM(CH59:CK59) -> 947.606 | AB59: =+SUM(CL59:CO59) -> 1057.785 | AC59: =+SUM(CP59:CS59) -> 1397.2853 | AD59: =+SUM(CT59:CW59) -> 1505.39 | AE59: =+SUM(CX59:DA59) -> 1909.4823 | AI59: ='QTR Raw'!C29 -> 0 | AJ59: ='QTR Raw'!D29 -> 0 | AK59: ='QTR Raw'!E29 -> 0 | AL59: ='QTR Raw'!F29 -> 0 | AM59: ='QTR Raw'!G29 -> 0 | AN59: ='QTR Raw'!H29 -> 0 | AO59: ='QTR Raw'!I29 -> 0 | AP59: ='QTR Raw'!J29 -> 0 | ... CL59: ='QTR Raw'!BF29 -> 284.476 | CM59: =+CM58*CM60 -> 359.77835 | CN59: =+CN58*CN60 -> 220.04286 | CO59: =+CO58*CO60 -> 193.48782 | CP59: =+CP58*CP60 -> 378.71831 | CQ59: =+CQ58*CQ60 -> 453.19728 | CR59: =+CR58*CR60 -> 306.4672 | CS59: =+CS58*CS60 -> 258.90251 | CT59: =+CT58*CT60 -> 407.87941 | ... DA59: =+DA58*DA60 -> 373.86631
A60: Tax Rate % | B60: =B59/B58 -> #DIV/0! | C60: =C59/C58 -> #DIV/0! | D60: =D59/D58 -> #DIV/0! | E60: =E59/E58 -> #DIV/0! | F60: =F59/F58 -> 0.4209003 | G60: =G59/G58 -> 0.45822647 | H60: =H59/H58 -> 0.25730709 | I60: =I59/I58 -> 0.3671676 | ... AE60: =AE59/AE58 -> 0.24452903 | AI60: =AI59/AI58 -> #DIV/0! | AJ60: =AJ59/AJ58 -> #DIV/0! | AK60: =AK59/AK58 -> #DIV/0! | AL60: =AL59/AL58 -> #DIV/0! | AM60: =AM59/AM58 -> #DIV/0! | AN60: =AN59/AN58 -> #DIV/0! | AO60: =AO59/AO58 -> #DIV/0! | AP60: =AP59/AP58 -> #DIV/0! | ... CL60: =CL59/CL58 -> 0.24373852 | CM60: =AVERAGE(CI60:CL60) -> 0.23987408 | CN60: =AVERAGE(CJ60:CM60) -> 0.24120132 | CO60: =AVERAGE(CK60:CN60) -> 0.24959159 | CP60: =AVERAGE(CL60:CO60) -> 0.24360138 | CQ60: =AVERAGE(CM60:CP60) -> 0.24356709 | CR60: =AVERAGE(CN60:CQ60) -> 0.24449035 | CS60: =AVERAGE(CO60:CR60) -> 0.2453126 | CT60: =AVERAGE(CP60:CS60) -> 0.24424285 | ... DA60: =AVERAGE(CW60:CZ60) -> 0.24455432
A61: PAT | B61: =B58-B59 -> 0 | C61: =C58-C59 -> 0 | D61: =D58-D59 -> 0 | E61: =E58-E59 -> 0 | F61: =F58-F59 -> 18.170748 | G61: =G58-G59 -> 10.861304 | H61: =H58-H59 -> 14.118597 | I61: =I58-I59 -> 21.18728 | ... AE61: =AE58-AE59 -> 5899.3339 | AI61: =AI58-AI59 -> 0 | AJ61: =AJ58-AJ59 -> 0 | AK61: =AK58-AK59 -> 0 | AL61: =AL58-AL59 -> 0 | AM61: =AM58-AM59 -> 0 | AN61: =AN58-AN59 -> 0 | AO61: =AO58-AO59 -> 0 | AP61: =AP58-AP59 -> 0 | ... DA61: =DA58-DA59 -> 1154.8996
A62: PAT % | B62: =+B61/B30 -> #DIV/0! | C62: =+C61/C30 -> #DIV/0! | D62: =+D61/D30 -> #DIV/0! | E62: =+E61/E30 -> #DIV/0! | F62: =+F61/F30 -> 0.064096288 | G62: =+G61/G30 -> 0.035386717 | H62: =+H61/H30 -> 0.043063831 | I62: =+I61/I30 -> 0.056843403 | ... AE62: =+AE61/AE30 -> 0.158055 | AI62: =+AI61/AI30 -> #DIV/0! | AJ62: =+AJ61/AJ30 -> #DIV/0! | AK62: =+AK61/AK30 -> #DIV/0! | AL62: =+AL61/AL30 -> #DIV/0! | AM62: =+AM61/AM30 -> #DIV/0! | AN62: =+AN61/AN30 -> #DIV/0! | AO62: =+AO61/AO30 -> #DIV/0! | AP62: =+AP61/AP30 -> #DIV/0! | ... DA62: =+DA61/DA30 -> 0.15681998
A63: PAT YOY% | C63: =+IF(B61<0,1-C61/B61,C61/B61-1) -> #DIV/0! | D63: =+IF(C61<0,1-D61/C61,D61/C61-1) -> #DIV/0! | E63: =+IF(D61<0,1-E61/D61,E61/D61-1) -> #DIV/0! | F63: =+IF(E61<0,1-F61/E61,F61/E61-1) -> #DIV/0! | G63: =+IF(F61<0,1-G61/F61,G61/F61-1) -> -0.40226437 | H63: =+IF(G61<0,1-H61/G61,H61/G61-1) -> 0.29989892 | I63: =+IF(H61<0,1-I61/H61,I61/H61-1) -> 0.50066471 | J63: =+IF(I61<0,1-J61/I61,J61/I61-1) -> 0.032020788 | ... AE63: =+IF(AD61<0,1-AE61/AD61,AE61/AD61-1) -> 0.26789207 | AM63: =+IF(AI61<0,1-AM61/AI61,AM61/AI61-1) -> #DIV/0! | AN63: =+IF(AJ61<0,1-AN61/AJ61,AN61/AJ61-1) -> #DIV/0! | AO63: =+IF(AK61<0,1-AO61/AK61,AO61/AK61-1) -> #DIV/0! | AP63: =+IF(AL61<0,1-AP61/AL61,AP61/AL61-1) -> #DIV/0! | AQ63: =+IF(AM61<0,1-AQ61/AM61,AQ61/AM61-1) -> #DIV/0! | AR63: =+IF(AN61<0,1-AR61/AN61,AR61/AN61-1) -> #DIV/0! | AS63: =+IF(AO61<0,1-AS61/AO61,AS61/AO61-1) -> #DIV/0! | AT63: =+IF(AP61<0,1-AT61/AP61,AT61/AP61-1) -> #DIV/0! | ... CL63: =+IF(CH61<0,1-CL61/CH61,CL61/CH61-1) -> 0.20592676 | CM63: =+CM61/CI61-1 -> -0.14064611 | CN63: =+CN61/CJ61-1 -> -0.073148189 | CO63: =+CO61/CK61-1 -> 1.2153627 | CP63: =+CP61/CL61-1 -> 0.33227491 | CQ63: =+CQ61/CM61-1 -> 0.23453059 | CR63: =+CR61/CN61-1 -> 0.36806947 | CS63: =+CS61/CO61-1 -> 0.36918497 | CT63: =+CT61/CP61-1 -> 0.073259839 | ... DA63: =+DA61/CW61-1 -> 0.29960892
A64: PAT QOQ% | AJ64: =+IF(AI61<0,1-AJ61/AI61,AJ61/AI61-1) -> #DIV/0! | AK64: =+IF(AJ61<0,1-AK61/AJ61,AK61/AJ61-1) -> #DIV/0! | AL64: =+IF(AK61<0,1-AL61/AK61,AL61/AK61-1) -> #DIV/0! | AM64: =+IF(AL61<0,1-AM61/AL61,AM61/AL61-1) -> #DIV/0! | AN64: =+IF(AM61<0,1-AN61/AM61,AN61/AM61-1) -> #DIV/0! | AO64: =+IF(AN61<0,1-AO61/AN61,AO61/AN61-1) -> #DIV/0! | AP64: =+IF(AO61<0,1-AP61/AO61,AP61/AO61-1) -> #DIV/0! | AQ64: =+IF(AP61<0,1-AQ61/AP61,AQ61/AP61-1) -> #DIV/0! | ... CL64: =+IF(CK61<0,1-CL61/CK61,CL61/CK61-1) -> 2.3613746 | CM64: =+CM61/CL61-1 -> 0.29164688 | CN64: =+CN61/CM61-1 -> -0.39282077 | CO64: =+CO61/CN61-1 -> -0.15963643 | CP64: =+CP61/CO61-1 -> 1.0214636 | CQ64: =+CQ61/CP61-1 -> 0.19688329 | CR64: =+CR61/CQ61-1 -> -0.32714233 | CS64: =+CS61/CR61-1 -> -0.15895121 | CT64: =+CT61/CS61-1 -> 0.58455996 | ... DA64: =+DA61/CZ61-1 -> -0.10748204
A65: Minority Interest | B65: ='Annual Raw'!C32 -> 0 | C65: ='Annual Raw'!D32 -> 0 | D65: ='Annual Raw'!E32 -> 0 | E65: ='Annual Raw'!F32 -> 0 | F65: ='Annual Raw'!G32 -> 0 | G65: ='Annual Raw'!H32 -> 0 | H65: ='Annual Raw'!I32 -> 0 | I65: ='Annual Raw'!J32 -> 0 | ... Z65: ='Annual Raw'!AA32 -> -39.652 | AA65: =SUM(CH65:CK65) -> -25.553 | AB65: =+SUM(CL65:CO65) -> -25.432 | AC65: =+SUM(CP65:CS65) -> -25.432 | AD65: =+SUM(CT65:CW65) -> -25.432 | AE65: =+SUM(CX65:DA65) -> -25.432 | AI65: ='QTR Raw'!C34 -> 0 | AJ65: ='QTR Raw'!D34 -> 0 | AK65: ='QTR Raw'!E34 -> 0 | AL65: ='QTR Raw'!F34 -> 0 | AM65: ='QTR Raw'!G34 -> 0 | AN65: ='QTR Raw'!H34 -> 0 | AO65: ='QTR Raw'!I34 -> 0 | AP65: ='QTR Raw'!J34 -> 0 | ... CL65: ='QTR Raw'!BF34 -> -6.358 | CM65: =+CL65 -> -6.358 | CN65: =+CM65 -> -6.358 | CO65: =+CN65 -> -6.358 | CP65: =+CO65 -> -6.358 | CQ65: =+CP65 -> -6.358 | CR65: =+CQ65 -> -6.358 | CS65: =+CR65 -> -6.358 | CT65: =+CS65 -> -6.358 | ... DA65: =+CZ65 -> -6.358
A66: Share of Associate | B66: ='Annual Raw'!C33+'Annual Raw'!C28 -> 0 | C66: ='Annual Raw'!D33+'Annual Raw'!D28 -> 0 | D66: ='Annual Raw'!E33+'Annual Raw'!E28 -> 0 | E66: ='Annual Raw'!F33+'Annual Raw'!F28 -> 0 | F66: ='Annual Raw'!G33+'Annual Raw'!G28 -> 0 | G66: ='Annual Raw'!H33+'Annual Raw'!H28 -> 0 | H66: ='Annual Raw'!I33+'Annual Raw'!I28 -> 0 | I66: ='Annual Raw'!J33+'Annual Raw'!J28 -> 0 | ... Z66: ='Annual Raw'!AA33+'Annual Raw'!AA28 -> -1.478 | AA66: =SUM(CH66:CK66) -> -6.027 | AB66: =+SUM(CL66:CO66) -> -15.788 | AC66: =+SUM(CP66:CS66) -> -15.788 | AD66: =+SUM(CT66:CW66) -> -15.788 | AE66: =+SUM(CX66:DA66) -> -15.788 | AI66: ='QTR Raw'!C35 -> 0 | AJ66: ='QTR Raw'!D35 -> 0 | AK66: ='QTR Raw'!E35 -> 0 | AL66: ='QTR Raw'!F35 -> 0 | AM66: ='QTR Raw'!G35 -> 0 | AN66: ='QTR Raw'!H35 -> 0 | AO66: ='QTR Raw'!I35 -> 0 | AP66: ='QTR Raw'!J35 -> 0 | ... CL66: ='QTR Raw'!BF35 -> -3.947 | CM66: =+CL66 -> -3.947 | CN66: =+CM66 -> -3.947 | CO66: =+CN66 -> -3.947 | CP66: =+CO66 -> -3.947 | CQ66: =+CP66 -> -3.947 | CR66: =+CQ66 -> -3.947 | CS66: =+CR66 -> -3.947 | CT66: =+CS66 -> -3.947 | ... DA66: =+CZ66 -> -3.947
A67: Exceptional Income / Expenses | B67: ='Annual Raw'!C29+'Annual Raw'!C31+'Annual Raw'!C34+'Annual Raw'!C36 -> 0 | C67: ='Annual Raw'!D29+'Annual Raw'!D31+'Annual Raw'!D34+'Annual Raw'!D36 -> 0 | D67: ='Annual Raw'!E29+'Annual Raw'!E31+'Annual Raw'!E34+'Annual Raw'!E36 -> 0 | E67: ='Annual Raw'!F29+'Annual Raw'!F31+'Annual Raw'!F34+'Annual Raw'!F36 -> 0 | F67: ='Annual Raw'!G29+'Annual Raw'!G31+'Annual Raw'!G34+'Annual Raw'!G36 -> 0 | G67: ='Annual Raw'!H29+'Annual Raw'!H31+'Annual Raw'!H34+'Annual Raw'!H36 -> 0 | H67: ='Annual Raw'!I29+'Annual Raw'!I31+'Annual Raw'!I34+'Annual Raw'!I36 -> 0 | I67: ='Annual Raw'!J29+'Annual Raw'!J31+'Annual Raw'!J34+'Annual Raw'!J36 -> 0 | ... Z67: ='Annual Raw'!AA29+'Annual Raw'!AA31+'Annual Raw'!AA34+'Annual Raw'!AA36 -> 0 | AA67: =SUM(CH67:CK67) -> 0 | AB67: =+SUM(CL67:CO67) -> 0 | AC67: =+SUM(CP67:CS67) -> 0 | AD67: =+SUM(CT67:CW67) -> 0 | AE67: =+SUM(CX67:DA67) -> 0 | AI67: ='QTR Raw'!C26+'QTR Raw'!C31+'QTR Raw'!C32+'QTR Raw'!C33+'QTR Raw'!C36+'QTR Raw'!C37+'QTR Raw'!C39 -> 0 | AJ67: ='QTR Raw'!D26+'QTR Raw'!D31+'QTR Raw'!D32+'QTR Raw'!D33+'QTR Raw'!D36+'QTR Raw'!D37+'QTR Raw'!D39 -> 0 | AK67: ='QTR Raw'!E26+'QTR Raw'!E31+'QTR Raw'!E32+'QTR Raw'!E33+'QTR Raw'!E36+'QTR Raw'!E37+'QTR Raw'!E39 -> 0 | AL67: ='QTR Raw'!F26+'QTR Raw'!F31+'QTR Raw'!F32+'QTR Raw'!F33+'QTR Raw'!F36+'QTR Raw'!F37+'QTR Raw'!F39 -> 0 | AM67: ='QTR Raw'!G26+'QTR Raw'!G31+'QTR Raw'!G32+'QTR Raw'!G33+'QTR Raw'!G36+'QTR Raw'!G37+'QTR Raw'!G39 -> 0 | AN67: ='QTR Raw'!H26+'QTR Raw'!H31+'QTR Raw'!H32+'QTR Raw'!H33+'QTR Raw'!H36+'QTR Raw'!H37+'QTR Raw'!H39 -> 0 | AO67: ='QTR Raw'!I26+'QTR Raw'!I31+'QTR Raw'!I32+'QTR Raw'!I33+'QTR Raw'!I36+'QTR Raw'!I37+'QTR Raw'!I39 -> 0 | AP67: ='QTR Raw'!J26+'QTR Raw'!J31+'QTR Raw'!J32+'QTR Raw'!J33+'QTR Raw'!J36+'QTR Raw'!J37+'QTR Raw'!J39 -> 0 | ... CL67: ='QTR Raw'!BF26+'QTR Raw'!BF31+'QTR Raw'!BF32+'QTR Raw'!BF33+'QTR Raw'!BF36+'QTR Raw'!BF37+'QTR Raw'!BF39 -> 0
A68: Consolidated Net Profit | B68: =B61+B65+B66+B67 -> 0 | C68: =C61+C65+C66+C67 -> 0 | D68: =D61+D65+D66+D67 -> 0 | E68: =E61+E65+E66+E67 -> 0 | F68: =F61+F65+F66+F67 -> 18.170748 | G68: =G61+G65+G66+G67 -> 10.861304 | H68: =H61+H65+H66+H67 -> 14.118597 | I68: =I61+I65+I66+I67 -> 21.18728 | ... AE68: =AE61+AE65+AE66+AE67 -> 5858.1139 | AI68: =AI61+AI65+AI66+AI67 -> 0 | AJ68: =AJ61+AJ65+AJ66+AJ67 -> 0 | AK68: =AK61+AK65+AK66+AK67 -> 0 | AL68: =AL61+AL65+AL66+AL67 -> 0 | AM68: =AM61+AM65+AM66+AM67 -> 0 | AN68: =AN61+AN65+AN66+AN67 -> 0 | AO68: =AO61+AO65+AO66+AO67 -> 0 | AP68: =AP61+AP65+AP66+AP67 -> 0 | ... DA68: =DA61+DA65+DA66+DA67 -> 1144.5946
A69: Profit & Loss- Annual (End)
A70: Rat
A71: Ace - PAT | B71: ='Annual Raw'!C35 -> 0 | C71: ='Annual Raw'!D35 -> 0 | D71: ='Annual Raw'!E35 -> 0 | E71: ='Annual Raw'!F35 -> 0 | F71: ='Annual Raw'!G35 -> 18.170748 | G71: ='Annual Raw'!H35 -> 10.861303 | H71: ='Annual Raw'!I35 -> 14.118597 | I71: ='Annual Raw'!J35 -> 21.18728 | ... Z71: ='Annual Raw'!AA35 -> 2594.633 | AA71: =+AA68 -> 3036.489 | AB71: =+AB68 -> 3255.4909 | AC71: =+AC68 -> 4285.7183 | AD71: =+AD68 -> 4611.6476 | AE71: =+AE68 -> 5858.1139 | AI71: ='QTR Raw'!C42 -> 0 | AJ71: ='QTR Raw'!D42 -> 0 | AK71: ='QTR Raw'!E42 -> 0 | AL71: ='QTR Raw'!F42 -> 0 | AM71: ='QTR Raw'!G42 -> 0 | AN71: ='QTR Raw'!H42 -> 0 | AO71: ='QTR Raw'!I42 -> 0 | AP71: ='QTR Raw'!J42 -> 0 | ... CL71: ='QTR Raw'!BF42 -> 872.355
A72: Checksum - PAT | B72: =B71-B68 -> 0 | C72: =C71-C68 -> 0 | D72: =D71-D68 -> 0 | E72: =E71-E68 -> 0 | F72: =F71-F68 -> 0 | G72: =G71-G68 -> -5.1514348e-14 | H72: =H71-H68 -> -3.375078e-14 | I72: =I71-I68 -> 0 | ... AE72: =AE71-AE68 -> 0 | AI72: =AI71-AI68 -> 0 | AJ72: =AJ71-AJ68 -> 0 | AK72: =AK71-AK68 -> 0 | AL72: =AL71-AL68 -> 0 | AM72: =AM71-AM68 -> 0 | AN72: =AN71-AN68 -> 0 | AO72: =AO71-AO68 -> 0 | AP72: =AP71-AP68 -> 0 | ... CL72: =CL71-CL68 -> 0
A73: Ratios (Start)
A74: ROE (%) | B74: =(B68-B67)/B140 -> #DIV/0! | C74: =(C68-C67)/C140 -> #DIV/0! | D74: =(D68-D67)/D140 -> #DIV/0! | E74: =(E68-E67)/E140 -> #DIV/0! | F74: =(F68-F67)/F140 -> 0.12258398 | G74: =(G68-G67)/G140 -> 0.068047015 | H74: =(H68-H67)/H140 -> 0.081586409 | I74: =(I68-I67)/I140 -> 0.10906992 | ... AE74: =(AE68-AE67)/AE140 -> 0.1558437 | AL74: =(SUM(AI68:AL68)-SUM(AI67:AL67))/AL140 -> #DIV/0! | AM74: =(SUM(AJ68:AM68)-SUM(AJ67:AM67))/AM140 -> #DIV/0! | AN74: =(SUM(AK68:AN68)-SUM(AK67:AN67))/AN140 -> #DIV/0! | AO74: =(SUM(AL68:AO68)-SUM(AL67:AO67))/AO140 -> #DIV/0! | AP74: =(SUM(AM68:AP68)-SUM(AM67:AP67))/AP140 -> #DIV/0! | AQ74: =(SUM(AN68:AQ68)-SUM(AN67:AQ67))/AQ140 -> #DIV/0! | AR74: =(SUM(AO68:AR68)-SUM(AO67:AR67))/AR140 -> #DIV/0! | AS74: =(SUM(AP68:AS68)-SUM(AP67:AS67))/AS140 -> #DIV/0! | ... DA74: =(SUM(CX68:DA68)-SUM(CX67:DA67))/DA140 -> 0.1558437
A75: ROCE (%) | B75: =+B54/B149 -> #DIV/0! | C75: =+C54/C149 -> #DIV/0! | D75: =+D54/D149 -> #DIV/0! | E75: =+E54/E149 -> #DIV/0! | F75: =+F54/F149 -> 0.13522722 | G75: =+G54/G149 -> 0.098745604 | H75: =+H54/H149 -> 0.092501629 | I75: =+I54/I149 -> 0.12603588 | ... AE75: =+AE54/AE149 -> 0.17607949 | AL75: =+SUM(AI54:AL54)/AL149 -> #DIV/0! | AM75: =+SUM(AJ54:AM54)/AM149 -> #DIV/0! | AN75: =+SUM(AK54:AN54)/AN149 -> #DIV/0! | AO75: =+SUM(AL54:AO54)/AO149 -> #DIV/0! | AP75: =+SUM(AM54:AP54)/AP149 -> #DIV/0! | AQ75: =+SUM(AN54:AQ54)/AQ149 -> #DIV/0! | AR75: =+SUM(AO54:AR54)/AR149 -> #DIV/0! | AS75: =+SUM(AP54:AS54)/AS149 -> #DIV/0! | ... DA75: =+SUM(CX54:DA54)/DA149 -> 0.17607949
A76: Ratios (End)
A77: Checksum Of qtr to Annual
A78: Revenue - Checksum Of qtr to Annual | N78: =N30-SUM(AI30:AL30) -> 1799.994 | R78: =R30-SUM(AX30:BA30) -> 0 | S78: =S30-SUM(BB30:BE30) -> 0 | T78: =T30-SUM(BF30:BI30) -> 0 | U78: =U30-SUM(BJ30:BM30) -> 0 | V78: =V30-SUM(BN30:BQ30) -> 0 | W78: =W30-SUM(BR30:BU30) -> 0 | X78: =X30-SUM(BV30:BY30) -> 0 | Y78: =Y30-SUM(BZ30:CC30) -> 0 | Z78: =Z30-SUM(CD30:CG30) -> 0 | AA78: =AA30-SUM(CH30:CK30) -> 0 | AB78: =AB30-SUM(CL30:CO30) -> 0 | AC78: =AC30-SUM(CP30:CS30) -> 0 | AD78: =AD30-SUM(CT30:CW30) -> 0 | AE78: =AE30-SUM(CX30:DA30) -> 0
A79: GP - Checksum Of qtr to Annual | N79: =N36-SUM(AI36:AL36) -> 772.21 | R79: =R36-SUM(AX36:BA36) -> 0 | S79: =S36-SUM(BB36:BE36) -> 0 | T79: =T36-SUM(BF36:BI36) -> 0 | U79: =U36-SUM(BJ36:BM36) -> 0 | V79: =V36-SUM(BN36:BQ36) -> 0 | W79: =W36-SUM(BR36:BU36) -> 0 | X79: =X36-SUM(BV36:BY36) -> 0 | Y79: =Y36-SUM(BZ36:CC36) -> 0 | Z79: =Z36-SUM(CD36:CG36) -> 0 | AA79: =AA36-SUM(CH36:CK36) -> 0 | AB79: =AB36-SUM(CL36:CO36) -> 0 | AC79: =AC36-SUM(CP36:CS36) -> 0 | AD79: =AD36-SUM(CT36:CW36) -> 0 | AE79: =AE36-SUM(CX36:DA36) -> 0
A80: EBITDA - Checksum Of qtr to Annual | N80: =N48-SUM(AI48:AL48) -> 228.456 | R80: =R48-SUM(AX48:BA48) -> 12.32 | S80: =S48-SUM(BB48:BE48) -> 12.533 | T80: =T48-SUM(BF48:BI48) -> 10.24 | U80: =U48-SUM(BJ48:BM48) -> 14.667 | V80: =V48-SUM(BN48:BQ48) -> 12.636 | W80: =W48-SUM(BR48:BU48) -> 22.268 | X80: =X48-SUM(BV48:BY48) -> 17.965 | Y80: =Y48-SUM(BZ48:CC48) -> 23.496 | Z80: =Z48-SUM(CD48:CG48) -> 32.472 | AA80: =AA48-SUM(CH48:CK48) -> -7.2759576e-12 | AB80: =AB48-SUM(CL48:CO48) -> 0 | AC80: =AC48-SUM(CP48:CS48) -> 0 | AD80: =AD48-SUM(CT48:CW48) -> 0 | AE80: =AE48-SUM(CX48:DA48) -> 0
A81: PAT - Checksum Of qtr to Annual | N81: =N68-SUM(AI68:AL68) -> 25.108 | R81: =R61-SUM(AX61:BA61) -> 3.0553338e-13 | S81: =S61-SUM(BB61:BE61) -> 7.9580786e-13 | T81: =T61-SUM(BF61:BI61) -> 0 | U81: =U61-SUM(BJ61:BM61) -> -1.0231815e-12 | V81: =V61-SUM(BN61:BQ61) -> 5.1159077e-13 | W81: =W61-SUM(BR61:BU61) -> -9.094947e-13 | X81: =X61-SUM(BV61:BY61) -> 0 | Y81: =Y61-SUM(BZ61:CC61) -> 0 | Z81: =Z61-SUM(CD61:CG61) -> 0 | AA81: =AA61-SUM(CH61:CK61) -> -5.9117156e-12 | AB81: =AB61-SUM(CL61:CO61) -> 0 | AC81: =AC61-SUM(CP61:CS61) -> 0 | AD81: =AD61-SUM(CT61:CW61) -> 0 | AE81: =AE61-SUM(CX61:DA61) -> 0
A82: Valuation (Start)
A83: Eq | B83: ='Annual Raw'!C104 -> 0 | C83: ='Annual Raw'!D104 -> 0 | D83: ='Annual Raw'!E104 -> 0 | E83: =+F83 -> 676.419 | F83: =+G83 -> 676.419 | G83: =+H83 -> 676.419 | H83: =+I83 -> 676.419 | I83: =+J83 -> 676.419 | J83: =+K83 -> 676.419 | K83: =+L83 -> 676.419 | L83: =+M83 -> 676.419 | ... Z83: =+AA83 -> 676.419 | AA83: =+CL83 -> 676.419 | AB83: =AA83 -> 676.419 | AC83: =AB83 -> 676.419 | AD83: =AC83 -> 676.419 | AE83: =AD83 -> 676.419 | AI83: =+AJ83 -> 676.392 | AJ83: =+AK83 -> 676.392 | AK83: =+AL83 -> 676.392 | AL83: =+AM83 -> 676.392 | AM83: =+AN83 -> 676.392 | AN83: =+AO83 -> 676.392 | AO83: =+AP83 -> 676.392 | AP83: =+AQ83 -> 676.392 | ... CI83: =+CJ83 -> 676.392 | CJ83: ='QTR Raw'!BD45 -> 676.392 | CK83: ='QTR Raw'!BE45 -> 676.398 | CL83: ='QTR Raw'!BF45 -> 676.419 | CM83: =+CL83 -> 676.419 | CN83: =+CM83 -> 676.419 | CO83: =+CN83 -> 676.419 | CP83: =+CO83 -> 676.419 | CQ83: =+CP83 -> 676.419 | CR83: =+CQ83 -> 676.419 | CS83: =+CR83 -> 676.419 | CT83: =+CS83 -> 676.419 | ... DA83: =+CZ83 -> 676.419
A84: FV | B84: ='Annual Raw'!C105 -> 0 | C84: ='Annual Raw'!D105 -> 0 | D84: ='Annual Raw'!E105 -> 0 | E84: =+F84 -> 2 | F84: =+G84 -> 2 | G84: =+H84 -> 2 | H84: =+I84 -> 2 | I84: =+J84 -> 2 | J84: =+K84 -> 2 | K84: =+L84 -> 2 | L84: =+M84 -> 2 | ... Z84: =+AA84 -> 2 | AA84: =+CL84 -> 2 | AB84: =AA84 -> 2 | AC84: =AB84 -> 2 | AD84: =AC84 -> 2 | AE84: =AD84 -> 2 | AI84: =AJ84 -> 2 | AJ84: =AK84 -> 2 | AK84: =AL84 -> 2 | AL84: =AM84 -> 2 | AM84: =AN84 -> 2 | AN84: =AO84 -> 2 | AO84: =AP84 -> 2 | AP84: =AQ84 -> 2 | ... CI84: =CJ84 -> 2 | CJ84: ='QTR Raw'!BD46 -> 2 | CK84: ='QTR Raw'!BE46 -> 2 | CL84: ='QTR Raw'!BF46 -> 2 | CM84: =+CL84 -> 2 | CN84: =+CM84 -> 2 | CO84: =+CN84 -> 2 | CP84: =+CO84 -> 2 | CQ84: =+CP84 -> 2 | CR84: =+CQ84 -> 2 | CS84: =+CR84 -> 2 | CT84: =+CS84 -> 2 | ... DA84: =+CZ84 -> 2
A85: No of share | B85: =B83/B84 -> #DIV/0! | C85: =C83/C84 -> #DIV/0! | D85: =D83/D84 -> #DIV/0! | E85: =E83/E84 -> 338.2095 | F85: =F83/F84 -> 338.2095 | G85: =G83/G84 -> 338.2095 | H85: =H83/H84 -> 338.2095 | I85: =I83/I84 -> 338.2095 | ... AE85: =AE83/AE84 -> 338.2095 | AI85: =AI83/AI84 -> 338.196 | AJ85: =AJ83/AJ84 -> 338.196 | AK85: =AK83/AK84 -> 338.196 | AL85: =AL83/AL84 -> 338.196 | AM85: =AM83/AM84 -> 338.196 | AN85: =AN83/AN84 -> 338.196 | AO85: =AO83/AO84 -> 338.196 | AP85: =AP83/AP84 -> 338.196 | ... DA85: =DA83/DA84 -> 338.2095
A86: EPS | B86: =(B68-B67)/B85 -> #DIV/0! | C86: =(C68-C67)/C85 -> #DIV/0! | D86: =(D68-D67)/D85 -> #DIV/0! | E86: =(E68-E67)/E85 -> 0 | F86: =(F68-F67)/F85 -> 0.053726309 | G86: =(G68-G67)/G85 -> 0.032114129 | H86: =(H68-H67)/H85 -> 0.041745122 | I86: =(I68-I67)/I85 -> 0.062645431 | ... AE86: =(AE68-AE67)/AE85 -> 17.320962 | AI86: =(AI68-AI67)/AI85 -> 0 | AJ86: =(AJ68-AJ67)/AJ85 -> 0 | AK86: =(AK68-AK67)/AK85 -> 0 | AL86: =(AL68-AL67)/AL85 -> 0 | AM86: =(AM68-AM67)/AM85 -> 0 | AN86: =(AN68-AN67)/AN85 -> 0 | AO86: =(AO68-AO67)/AO85 -> 0 | AP86: =(AP68-AP67)/AP85 -> 0 | ... DA86: =(DA68-DA67)/DA85 -> 3.3842769
A87: DPS | B87: ='Annual Raw'!C110 -> 0 | C87: ='Annual Raw'!D110 -> 0 | D87: ='Annual Raw'!E110 -> 0 | E87: ='Annual Raw'!F110 -> 0 | F87: ='Annual Raw'!G110 -> 0 | G87: ='Annual Raw'!H110 -> 0 | H87: ='Annual Raw'!I110 -> 0 | I87: ='Annual Raw'!J110 -> 0 | ... Z87: ='Annual Raw'!AA110 -> 1
A88: DPS % of EPS | B88: =B87/B86 -> #DIV/0! | C88: =C87/C86 -> #DIV/0! | D88: =D87/D86 -> #DIV/0! | E88: =E87/E86 -> #DIV/0! | F88: =F87/F86 -> 0 | G88: =G87/G86 -> 0 | H88: =H87/H86 -> 0 | I88: =I87/I86 -> 0 | ... AE88: =AE87/AE86 -> 0
A89: EPS TTM | B89: =+B86 -> #DIV/0! | C89: =+C86 -> #DIV/0! | D89: =+D86 -> #DIV/0! | E89: =+E86 -> 0 | F89: =+F86 -> 0.053726309 | G89: =+G86 -> 0.032114129 | H89: =+H86 -> 0.041745122 | I89: =+I86 -> 0.062645431 | ... AE89: =+AE86 -> 17.320962 | AL89: =SUM(AI86:AL86) -> 0 | AM89: =SUM(AJ86:AM86) -> 0 | AN89: =SUM(AK86:AN86) -> 0 | AO89: =SUM(AL86:AO86) -> 0 | AP89: =SUM(AM86:AP86) -> 0 | AQ89: =SUM(AN86:AQ86) -> 0 | AR89: =SUM(AO86:AR86) -> 0 | AS89: =SUM(AP86:AS86) -> 0 | ... DA89: =SUM(CX86:DA86) -> 17.320962
A90: EPS Growth YoY % | C90: =+C89/B89-1 -> #DIV/0! | D90: =+D89/C89-1 -> #DIV/0! | E90: =+E89/D89-1 -> #DIV/0! | F90: =+F89/E89-1 -> #DIV/0! | G90: =+G89/F89-1 -> -0.40226437 | H90: =+H89/G89-1 -> 0.29989892 | I90: =+I89/H89-1 -> 0.50066471 | J90: =+J89/I89-1 -> 0.032020788 | ... AE90: =+AE89/AD89-1 -> 0.27028655 | AP90: =+IF(AL89<0,1-AP89/AL89,AP89/AL89-1) -> #DIV/0! | AQ90: =+IF(AM89<0,1-AQ89/AM89,AQ89/AM89-1) -> #DIV/0! | AR90: =+IF(AN89<0,1-AR89/AN89,AR89/AN89-1) -> #DIV/0! | AS90: =+IF(AO89<0,1-AS89/AO89,AS89/AO89-1) -> #DIV/0! | AT90: =+IF(AP89<0,1-AT89/AP89,AT89/AP89-1) -> #DIV/0! | AU90: =+IF(AQ89<0,1-AU89/AQ89,AU89/AQ89-1) -> #DIV/0! | AV90: =+IF(AR89<0,1-AV89/AR89,AV89/AR89-1) -> #DIV/0! | AW90: =+IF(AS89<0,1-AW89/AS89,AW89/AS89-1) -> #DIV/0! | ... DA90: =+IF(CW89<0,1-DA89/CW89,DA89/CW89-1) -> 0.27028655
A91: Bloomberg Estimate | CO91: 10 | CS91: 11.8 | CW91: 13
A92: Estimate deviation | CO92: =CO89/CO91-1 -> -0.03743364 | CS92: =CS89/CS91-1 -> 0.073880145 | CW92: =CW89/CW91-1 -> 0.048882786
A93: Promoter Share holding % | B93: ='Annual Raw'!C112 -> 0 | C93: ='Annual Raw'!D112 -> 0 | D93: ='Annual Raw'!E112 -> 0 | E93: ='Annual Raw'!F112 -> 0 | F93: ='Annual Raw'!G112 -> 0 | G93: ='Annual Raw'!H112 -> 0 | H93: ='Annual Raw'!I112 -> 0 | I93: ='Annual Raw'!J112 -> 0 | ... Z93: ='Annual Raw'!AA112 -> 60.2 | AI93: ='QTR Raw'!C49 -> 0 | AJ93: ='QTR Raw'!D49 -> 0 | AK93: ='QTR Raw'!E49 -> 0 | AL93: ='QTR Raw'!F49 -> 0 | AM93: ='QTR Raw'!G49 -> 0 | AN93: ='QTR Raw'!H49 -> 0 | AO93: ='QTR Raw'!I49 -> 0 | AP93: ='QTR Raw'!J49 -> 0 | ... CL93: ='QTR Raw'!BF49 -> 59.44
A94: Pledge Share % | B94: ='Annual Raw'!C113 -> 0 | C94: ='Annual Raw'!D113 -> 0 | D94: ='Annual Raw'!E113 -> 0 | E94: ='Annual Raw'!F113 -> 0 | F94: ='Annual Raw'!G113 -> 0 | G94: ='Annual Raw'!H113 -> 0 | H94: ='Annual Raw'!I113 -> 0 | I94: ='Annual Raw'!J113 -> 0 | ... Z94: ='Annual Raw'!AA113 -> 0.04 | AI94: ='QTR Raw'!C50 -> 0 | AJ94: ='QTR Raw'!D50 -> 0 | AK94: ='QTR Raw'!E50 -> 0 | AL94: ='QTR Raw'!F50 -> 0 | AM94: ='QTR Raw'!G50 -> 0 | AN94: ='QTR Raw'!H50 -> 0 | AO94: ='QTR Raw'!I50 -> 0 | AP94: ='QTR Raw'!J50 -> 0 | ... CL94: ='QTR Raw'!BF50 -> 0
A96: Share Price
A97: Share Price - Close | B97: ='Annual Raw'!C106 -> 0 | C97: ='Annual Raw'!D106 -> 0 | D97: ='Annual Raw'!E106 -> 0 | E97: ='Annual Raw'!F106 -> 0 | F97: ='Annual Raw'!G106 -> 0 | G97: ='Annual Raw'!H106 -> 0 | H97: ='Annual Raw'!I106 -> 0 | I97: ='Annual Raw'!J106 -> 0 | ... Z97: ='Annual Raw'!AA106 -> 638.45 | AA97: =+CK97 -> 489.85 | AB97: =+CO97 -> 522 | AC97: =+CS97 -> 522 | AD97: =+CW97 -> 522 | AE97: =+DA97 -> 522 | AJ97: ='QTR Share Price'!HP21 -> 0 | AK97: ='QTR Share Price'!HQ21 -> 0 | AL97: ='QTR Share Price'!HR21 -> 0 | AM97: ='QTR Share Price'!HS21 -> 0 | AN97: ='QTR Share Price'!HT21 -> 0 | AO97: ='QTR Share Price'!HU21 -> 0 | AP97: ='QTR Share Price'!HV21 -> 0 | AQ97: ='QTR Share Price'!HW21 -> 0 | ... CL97: ='QTR Share Price'!JR21 -> 384.05 | CM97: 522 | CN97: =+CM97 -> 522 | CO97: =+CN97 -> 522 | CP97: =+CO97 -> 522 | CQ97: =+CP97 -> 522 | CR97: =+CQ97 -> 522 | CS97: =+CR97 -> 522 | CT97: =+CS97 -> 522 | CU97: =+CT97 -> 522 | ... DA97: =+CZ97 -> 522
A98: Share Price - High | B98: ='Annual Raw'!C107 -> 0 | C98: ='Annual Raw'!D107 -> 0 | D98: ='Annual Raw'!E107 -> 0 | E98: ='Annual Raw'!F107 -> 0 | F98: ='Annual Raw'!G107 -> 0 | G98: ='Annual Raw'!H107 -> 0 | H98: ='Annual Raw'!I107 -> 0 | I98: ='Annual Raw'!J107 -> 0 | ... Z98: ='Annual Raw'!AA107 -> 682.84 | AA98: =MAX(CH98:CK98) -> 663.7 | AB98: =+MAX(CL98:CO98) -> 523.49591 | AC98: =+MAX(CP98:CS98) -> 689.16059 | AD98: =+MAX(CT98:CW98) -> 741.57132 | AE98: =+MAX(CX98:DA98) -> 942.00807 | AJ98: ='QTR Share Price'!HP19 -> 0 | AK98: ='QTR Share Price'!HQ19 -> 0 | AL98: ='QTR Share Price'!HR19 -> 0 | AM98: ='QTR Share Price'!HS19 -> 0 | AN98: ='QTR Share Price'!HT19 -> 0 | AO98: ='QTR Share Price'!HU19 -> 0 | AP98: ='QTR Share Price'!HV19 -> 0 | AQ98: ='QTR Share Price'!HW19 -> 0 | ... CL98: ='QTR Share Price'!JR19 -> 511.75 | CM98: =+CM89*CM106 -> 481.63197 | CN98: =+CN89*CN106 -> 472.09812 | CO98: =+CO89*CO106 -> 523.49591 | CP98: =+CP89*CP106 -> 570.65743 | CQ98: =+CQ89*CQ106 -> 613.65398 | CR98: =+CR89*CR106 -> 654.62537 | CS98: =+CS89*CS106 -> 689.16059 | CT98: =+CT89*CT106 -> 703.01379 | ... DA98: =+DA89*DA106 -> 942.00807
A99: Share Price - Low | B99: ='Annual Raw'!C108 -> 0 | C99: ='Annual Raw'!D108 -> 0 | D99: ='Annual Raw'!E108 -> 0 | E99: ='Annual Raw'!F108 -> 0 | F99: ='Annual Raw'!G108 -> 0 | G99: ='Annual Raw'!H108 -> 0 | H99: ='Annual Raw'!I108 -> 0 | I99: ='Annual Raw'!J108 -> 0 | ... Z99: ='Annual Raw'!AA108 -> 478.48 | AA99: =MIN(CH99:CK99) -> 419.4 | AB99: =+MIN(CL99:CO99) -> 351.47901 | AC99: =+MIN(CP99:CS99) -> 424.85683 | AD99: =+MIN(CT99:CW99) -> 523.39668 | AE99: =+MIN(CX99:DA99) -> 590.33758 | AJ99: =+'QTR Share Price'!HP20 -> 0 | AK99: =+'QTR Share Price'!HQ20 -> 0 | AL99: =+'QTR Share Price'!HR20 -> 0 | AM99: =+'QTR Share Price'!HS20 -> 0 | AN99: =+'QTR Share Price'!HT20 -> 0 | AO99: =+'QTR Share Price'!HU20 -> 0 | AP99: =+'QTR Share Price'!HV20 -> 0 | AQ99: =+'QTR Share Price'!HW20 -> 0 | ... CL99: =+'QTR Share Price'!JR20 -> 381 | CM99: =+CM107*CM89 -> 358.577 | CN99: =+CN107*CN89 -> 351.47901 | CO99: =+CO107*CO89 -> 389.74488 | CP99: =+CP107*CP89 -> 424.85683 | CQ99: =+CQ107*CQ89 -> 456.86793 | CR99: =+CR107*CR89 -> 487.37131 | CS99: =+CS107*CS89 -> 513.08292 | CT99: =+CT107*CT89 -> 523.39668 | ... DA99: =+DA107*DA89 -> 701.32892
A101: Upside (%) | AA101: =+AA98/AA97-1 -> 0.35490456 | AB101: =+AB98/AB97-1 -> 0.0028657295 | AC101: =+AC98/AC97-1 -> 0.32023101 | AD101: =+AD98/AD97-1 -> 0.42063471 | AE101: =+AE98/AE97-1 -> 0.80461316 | CM101: =+CM98/CM97-1 -> -0.077333391 | CN101: =+CN98/CN97-1 -> -0.095597467 | CO101: =+CO98/CO97-1 -> 0.0028657295 | CP101: =+CP98/CP97-1 -> 0.093213472 | CQ101: =+CQ98/CQ97-1 -> 0.17558233 | CR101: =+CR98/CR97-1 -> 0.25407159 | CS101: =+CS98/CS97-1 -> 0.32023101 | CT101: =+CT98/CT97-1 -> 0.34676971 | ... DA101: =+DA98/DA97-1 -> 0.80461316
A102: Downside (%) | AA102: =+AA99/AA97-1 -> -0.14381954 | AB102: =+AB99/AB97-1 -> -0.32666856 | AC102: =+AC99/AC97-1 -> -0.18609803 | AD102: =+AD99/AD97-1 -> 0.0026756411 | AE102: =+AE99/AE97-1 -> 0.13091491 | CM102: =+CM99/CM97-1 -> -0.31307088 | CN102: =+CN99/CN97-1 -> -0.32666856 | CO102: =+CO99/CO97-1 -> -0.2533623 | CP102: =+CP99/CP97-1 -> -0.18609803 | CQ102: =+CQ99/CQ97-1 -> -0.12477407 | CR102: =+CR99/CR97-1 -> -0.066338491 | CS102: =+CS99/CS97-1 -> -0.017082528 | CT102: =+CT99/CT97-1 -> 0.0026756411 | ... DA102: =+DA99/DA97-1 -> 0.34354199
A104: PE
A105: PE - Close | B105: =+B97/B89 -> #DIV/0! | C105: =+C97/C89 -> #DIV/0! | D105: =+D97/D89 -> #DIV/0! | E105: =+E97/E89 -> #DIV/0! | F105: =+F97/F89 -> 0 | G105: =+G97/G89 -> 0 | H105: =+H97/H89 -> 0 | I105: =+I97/I89 -> 0 | ... AE105: =+AE97/AE89 -> 30.136894 | AL105: =+AL97/AL89 -> #DIV/0! | AM105: =+AM97/AM89 -> #DIV/0! | AN105: =+AN97/AN89 -> #DIV/0! | AO105: =+AO97/AO89 -> #DIV/0! | AP105: =+AP97/AP89 -> #DIV/0! | AQ105: =+AQ97/AQ89 -> #DIV/0! | AR105: =+AR97/AR89 -> #DIV/0! | AS105: =+AS97/AS89 -> #DIV/0! | ... DA105: =+DA97/DA89 -> 30.136894
A106: PE - High | B106: =+B98/B89 -> #DIV/0! | C106: =+C98/C89 -> #DIV/0! | D106: =+D98/D89 -> #DIV/0! | E106: =+E98/E89 -> #DIV/0! | F106: =+F98/F89 -> 0 | G106: =+G98/G89 -> 0 | H106: =+H98/H89 -> 0 | I106: =+I98/I89 -> 0 | ... AE106: =+AE98/AE89 -> 54.385436 | AL106: =+AL98/AL89 -> #DIV/0! | AM106: =+AM98/AM89 -> #DIV/0! | AN106: =+AN98/AN89 -> #DIV/0! | AO106: =+AO98/AO89 -> #DIV/0! | AP106: =+AP98/AP89 -> #DIV/0! | AQ106: =+AQ98/AQ89 -> #DIV/0! | AR106: =+AR98/AR89 -> #DIV/0! | AS106: =+AS98/AS89 -> #DIV/0! | ... CL106: =+CL98/CL89 -> 54.385436 | CM106: =+CL106 -> 54.385436 | CN106: =+CM106 -> 54.385436 | CO106: =+CN106 -> 54.385436 | CP106: =+CO106 -> 54.385436 | CQ106: =+CP106 -> 54.385436 | CR106: =+CQ106 -> 54.385436 | CS106: =+CR106 -> 54.385436 | CT106: =+CS106 -> 54.385436 | ... DA106: =+CZ106 -> 54.385436
A107: PE - Low | B107: =+B99/B89 -> #DIV/0! | C107: =+C99/C89 -> #DIV/0! | D107: =+D99/D89 -> #DIV/0! | E107: =+E99/E89 -> #DIV/0! | F107: =+F99/F89 -> 0 | G107: =+G99/G89 -> 0 | H107: =+H99/H89 -> 0 | I107: =+I99/I89 -> 0 | ... AE107: =+AE99/AE89 -> 34.082263 | AL107: =+AL99/AL89 -> #DIV/0! | AM107: =+AM99/AM89 -> #DIV/0! | AN107: =+AN99/AN89 -> #DIV/0! | AO107: =+AO99/AO89 -> #DIV/0! | AP107: =+AP99/AP89 -> #DIV/0! | AQ107: =+AQ99/AQ89 -> #DIV/0! | AR107: =+AR99/AR89 -> #DIV/0! | AS107: =+AS99/AS89 -> #DIV/0! | ... CL107: =+CL99/CL89 -> 40.490183 | CM107: =+CL107 -> 40.490183 | CN107: =+CM107 -> 40.490183 | CO107: =+CN107 -> 40.490183 | CP107: =+CO107 -> 40.490183 | CQ107: =+CP107 -> 40.490183 | CR107: =+CQ107 -> 40.490183 | CS107: =+CR107 -> 40.490183 | CT107: =+CS107 -> 40.490183 | ... DA107: =+CZ107 -> 40.490183
A109: PE - 1Yr Fwd | B109: =+B98/C89 -> #DIV/0! | C109: =+C98/D89 -> #DIV/0! | D109: =+D98/E89 -> #DIV/0! | E109: =+E98/F89 -> 0 | F109: =+F98/G89 -> 0 | G109: =+G98/H89 -> 0 | H109: =+H98/I89 -> 0 | I109: =+I98/J89 -> 0 | ... AD109: =+AD98/AE89 -> 42.813518 | AL109: =+AL98/AP89 -> #DIV/0! | AM109: =+AM98/AQ89 -> #DIV/0! | AN109: =+AN98/AR89 -> #DIV/0! | AO109: =+AO98/AS89 -> #DIV/0! | AP109: =+AP98/AT89 -> #DIV/0! | AQ109: =+AQ98/AU89 -> #DIV/0! | AR109: =+AR98/AV89 -> #DIV/0! | AS109: =+AS98/AW89 -> 0 | ... CL109: =+CL98/CP89 -> 48.771374
...

Sheet QTR Raw
A1: ='[1]Annual Raw'!A1 -> 209550 | B1: X | C1: 201206 | D1: 201209 | E1: 201212 | F1: 201303 | G1: 201306 | H1: 201309 | I1: 201312 | J1: 201403 | K1: 201406 | L1: 201409 | M1: 201412 | N1: 201503 | O1: 201506 | P1: 201509 | Q1: 201512 | R1: 201603 | S1: 201606 | T1: 201609 | U1: 201612 | V1: 201703 | W1: 201706 | X1: 201709 | Y1: 201712 | Z1: 201803 | AA1: 201806 | AB1: 201809 | AC1: 201812 | AD1: 201903 | AE1: 201906 | AF1: 201909 | AG1: 201912 | AH1: 202003 | AI1: 202006 | AJ1: 202009 | AK1: 202012 | AL1: 202103 | AM1: 202106 | AN1: 202109 | AO1: 202112 | AP1: 202203 | AQ1: 202206 | AR1: 202209 | AS1: 202212 | AT1: 202303 | AU1: 202306 | AV1: 202309 | AW1: 202312 | AX1: 202403 | AY1: 202406 | AZ1: 202409 | BA1: 202412 | BB1: 202503 | BC1: 202506 | BD1: 202509 | BE1: 202512 | BF1: 202603 | BG1: 202606 | BH1: 202609 | BI1: 202612 | BJ1: 202703 | BK1: 202706 | BL1: 202709 | BM1: 202712 | BN1: 202803 | BO1: 202806 | BP1: 202809 | BQ1: 202812 | BR1: 202903 | BS1: 202906 | BT1: 202909 | BU1: 202912
A3: Field Description | B3: Field Name
A4: Company Name | B4: CD_COMPNAME | C4: =_xll.EQNXTDZ(A1,B4,C1) -> Varun Beverages Ltd.
A5: Date End | B5: QTR_DATE_END | C5: =_xll.EQNXTDZ($A$1,$B5,C$1,$B$1) -> 0 | D5: =_xll.EQNXTDZ($A$1,$B5,D$1,$B$1) -> 0 | E5: =_xll.EQNXTDZ($A$1,$B5,E$1,$B$1) -> 0 | F5: =_xll.EQNXTDZ($A$1,$B5,F$1,$B$1) -> 0 | G5: =_xll.EQNXTDZ($A$1,$B5,G$1,$B$1) -> 0 | H5: =_xll.EQNXTDZ($A$1,$B5,H$1,$B$1) -> 0 | I5: =_xll.EQNXTDZ($A$1,$B5,I$1,$B$1) -> 0 | J5: =_xll.EQNXTDZ($A$1,$B5,J$1,$B$1) -> 0 | ... BU5: =_xll.EQNXTDZ($A$1,$B5,BU$1,$B$1) -> 0
A6: Gross Sales | B6: QTR_GROSS_SALE | C6: =_xll.EQNXTDZ($A$1,$B6,C$1,$B$1) -> 0 | D6: =_xll.EQNXTDZ($A$1,$B6,D$1,$B$1) -> 0 | E6: =_xll.EQNXTDZ($A$1,$B6,E$1,$B$1) -> 0 | F6: =_xll.EQNXTDZ($A$1,$B6,F$1,$B$1) -> 0 | G6: =_xll.EQNXTDZ($A$1,$B6,G$1,$B$1) -> 0 | H6: =_xll.EQNXTDZ($A$1,$B6,H$1,$B$1) -> 0 | I6: =_xll.EQNXTDZ($A$1,$B6,I$1,$B$1) -> 0 | J6: =_xll.EQNXTDZ($A$1,$B6,J$1,$B$1) -> 0 | ... BU6: =_xll.EQNXTDZ($A$1,$B6,BU$1,$B$1) -> 0
A7: Less: Excise Duty | B7: QTR_EXCISE_DUTY | C7: =_xll.EQNXTDZ($A$1,$B7,C$1,$B$1) -> 0 | D7: =_xll.EQNXTDZ($A$1,$B7,D$1,$B$1) -> 0 | E7: =_xll.EQNXTDZ($A$1,$B7,E$1,$B$1) -> 0 | F7: =_xll.EQNXTDZ($A$1,$B7,F$1,$B$1) -> 0 | G7: =_xll.EQNXTDZ($A$1,$B7,G$1,$B$1) -> 0 | H7: =_xll.EQNXTDZ($A$1,$B7,H$1,$B$1) -> 0 | I7: =_xll.EQNXTDZ($A$1,$B7,I$1,$B$1) -> 0 | J7: =_xll.EQNXTDZ($A$1,$B7,J$1,$B$1) -> 0 | ... BU7: =_xll.EQNXTDZ($A$1,$B7,BU$1,$B$1) -> 0
A8: Other operating income | B8: QTR_JOB_WORKS | C8: =_xll.EQNXTDZ($A$1,$B8,C$1,$B$1) -> 0 | D8: =_xll.EQNXTDZ($A$1,$B8,D$1,$B$1) -> 0 | E8: =_xll.EQNXTDZ($A$1,$B8,E$1,$B$1) -> 0 | F8: =_xll.EQNXTDZ($A$1,$B8,F$1,$B$1) -> 0 | G8: =_xll.EQNXTDZ($A$1,$B8,G$1,$B$1) -> 0 | H8: =_xll.EQNXTDZ($A$1,$B8,H$1,$B$1) -> 0 | I8: =_xll.EQNXTDZ($A$1,$B8,I$1,$B$1) -> 0 | J8: =_xll.EQNXTDZ($A$1,$B8,J$1,$B$1) -> 0 | ... BU8: =_xll.EQNXTDZ($A$1,$B8,BU$1,$B$1) -> 0
A9: Net Sales & Other Operating Income | B9: QTR_NET_SALES | C9: =_xll.EQNXTDZ($A$1,$B9,C$1,$B$1) -> 0 | D9: =_xll.EQNXTDZ($A$1,$B9,D$1,$B$1) -> 0 | E9: =_xll.EQNXTDZ($A$1,$B9,E$1,$B$1) -> 0 | F9: =_xll.EQNXTDZ($A$1,$B9,F$1,$B$1) -> 0 | G9: =_xll.EQNXTDZ($A$1,$B9,G$1,$B$1) -> 0 | H9: =_xll.EQNXTDZ($A$1,$B9,H$1,$B$1) -> 0 | I9: =_xll.EQNXTDZ($A$1,$B9,I$1,$B$1) -> 0 | J9: =_xll.EQNXTDZ($A$1,$B9,J$1,$B$1) -> 0 | ... BU9: =_xll.EQNXTDZ($A$1,$B9,BU$1,$B$1) -> 0
A10: (Increase) / Decrease In Stocks | B10: QTR_INC_DEC_INVENTORY | C10: =_xll.EQNXTDZ($A$1,$B10,C$1,$B$1) -> 0 | D10: =_xll.EQNXTDZ($A$1,$B10,D$1,$B$1) -> 0 | E10: =_xll.EQNXTDZ($A$1,$B10,E$1,$B$1) -> 0 | F10: =_xll.EQNXTDZ($A$1,$B10,F$1,$B$1) -> 0 | G10: =_xll.EQNXTDZ($A$1,$B10,G$1,$B$1) -> 0 | H10: =_xll.EQNXTDZ($A$1,$B10,H$1,$B$1) -> 0 | I10: =_xll.EQNXTDZ($A$1,$B10,I$1,$B$1) -> 0 | J10: =_xll.EQNXTDZ($A$1,$B10,J$1,$B$1) -> 0 | ... BU10: =_xll.EQNXTDZ($A$1,$B10,BU$1,$B$1) -> 0
A11: Cost of Services & Raw Materials | B11: QTR_RAW_MATERIAL_COST | C11: =_xll.EQNXTDZ($A$1,$B11,C$1,$B$1) -> 0 | D11: =_xll.EQNXTDZ($A$1,$B11,D$1,$B$1) -> 0 | E11: =_xll.EQNXTDZ($A$1,$B11,E$1,$B$1) -> 0 | F11: =_xll.EQNXTDZ($A$1,$B11,F$1,$B$1) -> 0 | G11: =_xll.EQNXTDZ($A$1,$B11,G$1,$B$1) -> 0 | H11: =_xll.EQNXTDZ($A$1,$B11,H$1,$B$1) -> 0 | I11: =_xll.EQNXTDZ($A$1,$B11,I$1,$B$1) -> 0 | J11: =_xll.EQNXTDZ($A$1,$B11,J$1,$B$1) -> 0 | ... BU11: =_xll.EQNXTDZ($A$1,$B11,BU$1,$B$1) -> 0
A12: Purchase of Finished Goods | B12: QTR_PURCHASE_FIN_GOOD | C12: =_xll.EQNXTDZ($A$1,$B12,C$1,$B$1) -> 0 | D12: =_xll.EQNXTDZ($A$1,$B12,D$1,$B$1) -> 0 | E12: =_xll.EQNXTDZ($A$1,$B12,E$1,$B$1) -> 0 | F12: =_xll.EQNXTDZ($A$1,$B12,F$1,$B$1) -> 0 | G12: =_xll.EQNXTDZ($A$1,$B12,G$1,$B$1) -> 0 | H12: =_xll.EQNXTDZ($A$1,$B12,H$1,$B$1) -> 0 | I12: =_xll.EQNXTDZ($A$1,$B12,I$1,$B$1) -> 0 | J12: =_xll.EQNXTDZ($A$1,$B12,J$1,$B$1) -> 0 | ... BU12: =_xll.EQNXTDZ($A$1,$B12,BU$1,$B$1) -> 0
A13: Excise Duty | B13: QTR_EXCISE | C13: =_xll.EQNXTDZ($A$1,$B13,C$1,$B$1) -> 0 | D13: =_xll.EQNXTDZ($A$1,$B13,D$1,$B$1) -> 0 | E13: =_xll.EQNXTDZ($A$1,$B13,E$1,$B$1) -> 0 | F13: =_xll.EQNXTDZ($A$1,$B13,F$1,$B$1) -> 0 | G13: =_xll.EQNXTDZ($A$1,$B13,G$1,$B$1) -> 0 | H13: =_xll.EQNXTDZ($A$1,$B13,H$1,$B$1) -> 0 | I13: =_xll.EQNXTDZ($A$1,$B13,I$1,$B$1) -> 0 | J13: =_xll.EQNXTDZ($A$1,$B13,J$1,$B$1) -> 0 | ... BU13: =_xll.EQNXTDZ($A$1,$B13,BU$1,$B$1) -> 0
A14: Operating & Manufacturing Expenses | B14: QTR_MFG_EXPS | C14: =_xll.EQNXTDZ($A$1,$B14,C$1,$B$1) -> 0 | D14: =_xll.EQNXTDZ($A$1,$B14,D$1,$B$1) -> 0 | E14: =_xll.EQNXTDZ($A$1,$B14,E$1,$B$1) -> 0 | F14: =_xll.EQNXTDZ($A$1,$B14,F$1,$B$1) -> 0 | G14: =_xll.EQNXTDZ($A$1,$B14,G$1,$B$1) -> 0 | H14: =_xll.EQNXTDZ($A$1,$B14,H$1,$B$1) -> 0 | I14: =_xll.EQNXTDZ($A$1,$B14,I$1,$B$1) -> 0 | J14: =_xll.EQNXTDZ($A$1,$B14,J$1,$B$1) -> 0 | ... BU14: =_xll.EQNXTDZ($A$1,$B14,BU$1,$B$1) -> 0
A15: Electricity Power & Fuel Cost | B15: QTR_ELECTRICITY_POWER_FUEL | C15: =_xll.EQNXTDZ($A$1,$B15,C$1,$B$1) -> 0 | D15: =_xll.EQNXTDZ($A$1,$B15,D$1,$B$1) -> 0 | E15: =_xll.EQNXTDZ($A$1,$B15,E$1,$B$1) -> 0 | F15: =_xll.EQNXTDZ($A$1,$B15,F$1,$B$1) -> 0 | G15: =_xll.EQNXTDZ($A$1,$B15,G$1,$B$1) -> 0 | H15: =_xll.EQNXTDZ($A$1,$B15,H$1,$B$1) -> 0 | I15: =_xll.EQNXTDZ($A$1,$B15,I$1,$B$1) -> 0 | J15: =_xll.EQNXTDZ($A$1,$B15,J$1,$B$1) -> 0 | ... BU15: =_xll.EQNXTDZ($A$1,$B15,BU$1,$B$1) -> 0
A16: Employee Cost | B16: QTR_EXPLOYEE_COST | C16: =_xll.EQNXTDZ($A$1,$B16,C$1,$B$1) -> 0 | D16: =_xll.EQNXTDZ($A$1,$B16,D$1,$B$1) -> 0 | E16: =_xll.EQNXTDZ($A$1,$B16,E$1,$B$1) -> 0 | F16: =_xll.EQNXTDZ($A$1,$B16,F$1,$B$1) -> 0 | G16: =_xll.EQNXTDZ($A$1,$B16,G$1,$B$1) -> 0 | H16: =_xll.EQNXTDZ($A$1,$B16,H$1,$B$1) -> 0 | I16: =_xll.EQNXTDZ($A$1,$B16,I$1,$B$1) -> 0 | J16: =_xll.EQNXTDZ($A$1,$B16,J$1,$B$1) -> 0 | ... BU16: =_xll.EQNXTDZ($A$1,$B16,BU$1,$B$1) -> 0
... A42: Consolidated PAT(after extra items) | B42: QTR_CONS_PAT_EXITM | C42: =_xll.EQNXTDZ($A$1,$B42,C$1,$B$1) -> 0 | D42: =_xll.EQNXTDZ($A$1,$B42,D$1,$B$1) -> 0 | E42: =_xll.EQNXTDZ($A$1,$B42,E$1,$B$1) -> 0 | F42: =_xll.EQNXTDZ($A$1,$B42,F$1,$B$1) -> 0 | G42: =_xll.EQNXTDZ($A$1,$B42,G$1,$B$1) -> 0 | H42: =_xll.EQNXTDZ($A$1,$B42,H$1,$B$1) -> 0 | I42: =_xll.EQNXTDZ($A$1,$B42,I$1,$B$1) -> 0 | J42: =_xll.EQNXTDZ($A$1,$B42,J$1,$B$1) -> 0 | ... BU42: =_xll.EQNXTDZ($A$1,$B42,BU$1,$B$1) -> 0
A44: Field Description | B44: Field Name
A45: Equity Capital | B45: QTR_EQUITY_CAP | C45: =_xll.EQNXTDZ($A$1,$B45,C$1,$B$1) -> 0 | D45: =_xll.EQNXTDZ($A$1,$B45,D$1,$B$1) -> 0 | E45: =_xll.EQNXTDZ($A$1,$B45,E$1,$B$1) -> 0 | F45: =_xll.EQNXTDZ($A$1,$B45,F$1,$B$1) -> 0 | G45: =_xll.EQNXTDZ($A$1,$B45,G$1,$B$1) -> 0 | H45: =_xll.EQNXTDZ($A$1,$B45,H$1,$B$1) -> 0 | I45: =_xll.EQNXTDZ($A$1,$B45,I$1,$B$1) -> 0 | J45: =_xll.EQNXTDZ($A$1,$B45,J$1,$B$1) -> 0 | ... BU45: =_xll.EQNXTDZ($A$1,$B45,BU$1,$B$1) -> 0
A46: Face Value | B46: QTR_FV | C46: =_xll.EQNXTDZ($A$1,$B46,C$1,$B$1) -> 0 | D46: =_xll.EQNXTDZ($A$1,$B46,D$1,$B$1) -> 0 | E46: =_xll.EQNXTDZ($A$1,$B46,E$1,$B$1) -> 0 | F46: =_xll.EQNXTDZ($A$1,$B46,F$1,$B$1) -> 0 | G46: =_xll.EQNXTDZ($A$1,$B46,G$1,$B$1) -> 0 | H46: =_xll.EQNXTDZ($A$1,$B46,H$1,$B$1) -> 0 | I46: =_xll.EQNXTDZ($A$1,$B46,I$1,$B$1) -> 0 | J46: =_xll.EQNXTDZ($A$1,$B46,J$1,$B$1) -> 0 | ... BU46: =_xll.EQNXTDZ($A$1,$B46,BU$1,$B$1) -> 0
A47: Month End | B47: BMONTH_MONTHEND | C47: =_xll.EQNXTDZ($A$1,$B47,C$5) -> 0 | D47: =_xll.EQNXTDZ($A$1,$B47,D$5) -> 0 | E47: =_xll.EQNXTDZ($A$1,$B47,E$5) -> 0 | F47: =_xll.EQNXTDZ($A$1,$B47,F$5) -> 0 | G47: =_xll.EQNXTDZ($A$1,$B47,G$5) -> 0 | H47: =_xll.EQNXTDZ($A$1,$B47,H$5) -> 0 | I47: =_xll.EQNXTDZ($A$1,$B47,I$5) -> 0 | J47: =_xll.EQNXTDZ($A$1,$B47,J$5) -> 0 | ... BU47: =_xll.EQNXTDZ($A$1,$B47,BU$5) -> 0
A48: Close | B48: BMONTH_CLOSE | C48: =_xll.EQNXTDZ($A$1,$B48,C$5) -> 0 | D48: =_xll.EQNXTDZ($A$1,$B48,D$5) -> 0 | E48: =_xll.EQNXTDZ($A$1,$B48,E$5) -> 0 | F48: =_xll.EQNXTDZ($A$1,$B48,F$5) -> 0 | G48: =_xll.EQNXTDZ($A$1,$B48,G$5) -> 0 | H48: =_xll.EQNXTDZ($A$1,$B48,H$5) -> 0 | I48: =_xll.EQNXTDZ($A$1,$B48,I$5) -> 0 | J48: =_xll.EQNXTDZ($A$1,$B48,J$5) -> 0 | ... BU48: =_xll.EQNXTDZ($A$1,$B48,BU$5) -> 0
A49: Total of Promoter and Promoter Group | B49: SHP_TPFTOTALPROMOTER | C49: =_xll.EQNXTDZ($A$1,$B49,C$5) -> 0 | D49: =_xll.EQNXTDZ($A$1,$B49,D$5) -> 0 | E49: =_xll.EQNXTDZ($A$1,$B49,E$5) -> 0 | F49: =_xll.EQNXTDZ($A$1,$B49,F$5) -> 0 | G49: =_xll.EQNXTDZ($A$1,$B49,G$5) -> 0 | H49: =_xll.EQNXTDZ($A$1,$B49,H$5) -> 0 | I49: =_xll.EQNXTDZ($A$1,$B49,I$5) -> 0 | J49: =_xll.EQNXTDZ($A$1,$B49,J$5) -> 0 | ... BU49: =_xll.EQNXTDZ($A$1,$B49,BU$5) -> 0
A50: Total of Promoter and Promoter Group Pledged | B50: SHP_PSHFTOTALPROMOTER | C50: =_xll.EQNXTDZ($A$1,$B50,C$5) -> 0 | D50: =_xll.EQNXTDZ($A$1,$B50,D$5) -> 0 | E50: =_xll.EQNXTDZ($A$1,$B50,E$5) -> 0 | F50: =_xll.EQNXTDZ($A$1,$B50,F$5) -> 0 | G50: =_xll.EQNXTDZ($A$1,$B50,G$5) -> 0 | H50: =_xll.EQNXTDZ($A$1,$B50,H$5) -> 0 | I50: =_xll.EQNXTDZ($A$1,$B50,I$5) -> 0 | J50: =_xll.EQNXTDZ($A$1,$B50,J$5) -> 0 | ... BU50: =_xll.EQNXTDZ($A$1,$B50,BU$5) -> 0
A54: Field Description | B54: Field Name | C54: =_xll.EQNXTDZ($A$1,$B54,C$5) -> 0 | D54: =_xll.EQNXTDZ($A$1,$B54,D$5) -> 0 | E54: =_xll.EQNXTDZ($A$1,$B54,E$5) -> 0 | F54: =_xll.EQNXTDZ($A$1,$B54,F$5) -> 0 | G54: =_xll.EQNXTDZ($A$1,$B54,G$5) -> 0 | H54: =_xll.EQNXTDZ($A$1,$B54,H$5) -> 0 | I54: =_xll.EQNXTDZ($A$1,$B54,I$5) -> 0 | J54: =_xll.EQNXTDZ($A$1,$B54,J$5) -> 0 | ... BU54: =_xll.EQNXTDZ($A$1,$B54,BU$5) -> 0
A55: Year End | B55: QTRB_DATE_END | C55: =_xll.EQNXTDZ($A$1,$B55,C$5,$B$1) -> 0 | D55: =_xll.EQNXTDZ($A$1,$B55,D$5,$B$1) -> 0 | E55: =_xll.EQNXTDZ($A$1,$B55,E$5,$B$1) -> 0 | F55: =_xll.EQNXTDZ($A$1,$B55,F$5,$B$1) -> 0 | G55: =_xll.EQNXTDZ($A$1,$B55,G$5,$B$1) -> 0 | H55: =_xll.EQNXTDZ($A$1,$B55,H$5,$B$1) -> 0 | I55: =_xll.EQNXTDZ($A$1,$B55,I$5,$B$1) -> 0 | J55: =_xll.EQNXTDZ($A$1,$B55,J$5,$B$1) -> 0 | ... BU55: =_xll.EQNXTDZ($A$1,$B55,BU$5,$B$1) -> 0
A56: Share Capital | B56: QTRB_SHARE_CAPITAL | C56: =_xll.EQNXTDZ($A$1,$B56,C$5,$B$1) -> 0 | D56: =_xll.EQNXTDZ($A$1,$B56,D$5,$B$1) -> 0 | E56: =_xll.EQNXTDZ($A$1,$B56,E$5,$B$1) -> 0 | F56: =_xll.EQNXTDZ($A$1,$B56,F$5,$B$1) -> 0 | G56: =_xll.EQNXTDZ($A$1,$B56,G$5,$B$1) -> 0 | H56: =_xll.EQNXTDZ($A$1,$B56,H$5,$B$1) -> 0 | I56: =_xll.EQNXTDZ($A$1,$B56,I$5,$B$1) -> 0 | J56: =_xll.EQNXTDZ($A$1,$B56,J$5,$B$1) -> 0 | ... BU56: =_xll.EQNXTDZ($A$1,$B56,BU$5,$B$1) -> 0
A57: Share Warrants & outstandings | B57: QTRB_SHAREWARNDOUT | C57: =_xll.EQNXTDZ($A$1,$B57,C$5,$B$1) -> 0 | D57: =_xll.EQNXTDZ($A$1,$B57,D$5,$B$1) -> 0 | E57: =_xll.EQNXTDZ($A$1,$B57,E$5,$B$1) -> 0 | F57: =_xll.EQNXTDZ($A$1,$B57,F$5,$B$1) -> 0 | G57: =_xll.EQNXTDZ($A$1,$B57,G$5,$B$1) -> 0 | H57: =_xll.EQNXTDZ($A$1,$B57,H$5,$B$1) -> 0 | I57: =_xll.EQNXTDZ($A$1,$B57,I$5,$B$1) -> 0 | J57: =_xll.EQNXTDZ($A$1,$B57,J$5,$B$1) -> 0 | ... BU57: =_xll.EQNXTDZ($A$1,$B57,BU$5,$B$1) -> 0
A58: Reserves & Surplus | B58: QTRB_RESERVE | C58: =_xll.EQNXTDZ($A$1,$B58,C$5,$B$1) -> 0 | D58: =_xll.EQNXTDZ($A$1,$B58,D$5,$B$1) -> 0 | E58: =_xll.EQNXTDZ($A$1,$B58,E$5,$B$1) -> 0 | F58: =_xll.EQNXTDZ($A$1,$B58,F$5,$B$1) -> 0 | G58: =_xll.EQNXTDZ($A$1,$B58,G$5,$B$1) -> 0 | H58: =_xll.EQNXTDZ($A$1,$B58,H$5,$B$1) -> 0 | I58: =_xll.EQNXTDZ($A$1,$B58,I$5,$B$1) -> 0 | J58: =_xll.EQNXTDZ($A$1,$B58,J$5,$B$1) -> 0 | ... BU58: =_xll.EQNXTDZ($A$1,$B58,BU$5,$B$1) -> 0
A59: Shareholder's Funds | B59: QTRB_SHAREHODERS_FUNDS | C59: =_xll.EQNXTDZ($A$1,$B59,C$5,$B$1) -> 0 | D59: =_xll.EQNXTDZ($A$1,$B59,D$5,$B$1) -> 0 | E59: =_xll.EQNXTDZ($A$1,$B59,E$5,$B$1) -> 0 | F59: =_xll.EQNXTDZ($A$1,$B59,F$5,$B$1) -> 0 | G59: =_xll.EQNXTDZ($A$1,$B59,G$5,$B$1) -> 0 | H59: =_xll.EQNXTDZ($A$1,$B59,H$5,$B$1) -> 0 | I59: =_xll.EQNXTDZ($A$1,$B59,I$5,$B$1) -> 0 | J59: =_xll.EQNXTDZ($A$1,$B59,J$5,$B$1) -> 0 | ... BU59: =_xll.EQNXTDZ($A$1,$B59,BU$5,$B$1) -> 0
A60: Minority Interest | B60: QTRB_MINORITY_INTEREST_BS | C60: =_xll.EQNXTDZ($A$1,$B60,C$5,$B$1) -> 0 | D60: =_xll.EQNXTDZ($A$1,$B60,D$5,$B$1) -> 0 | E60: =_xll.EQNXTDZ($A$1,$B60,E$5,$B$1) -> 0 | F60: =_xll.EQNXTDZ($A$1,$B60,F$5,$B$1) -> 0 | G60: =_xll.EQNXTDZ($A$1,$B60,G$5,$B$1) -> 0 | H60: =_xll.EQNXTDZ($A$1,$B60,H$5,$B$1) -> 0 | I60: =_xll.EQNXTDZ($A$1,$B60,I$5,$B$1) -> 0 | J60: =_xll.EQNXTDZ($A$1,$B60,J$5,$B$1) -> 0 | ... BU60: =_xll.EQNXTDZ($A$1,$B60,BU$5,$B$1) -> 0
A61: Long Term Borrowings | B61: QTRB_TOTAL_DEBTS | C61: =_xll.EQNXTDZ($A$1,$B61,C$5,$B$1) -> 0 | D61: =_xll.EQNXTDZ($A$1,$B61,D$5,$B$1) -> 0 | E61: =_xll.EQNXTDZ($A$1,$B61,E$5,$B$1) -> 0 | F61: =_xll.EQNXTDZ($A$1,$B61,F$5,$B$1) -> 0 | G61: =_xll.EQNXTDZ($A$1,$B61,G$5,$B$1) -> 0 | H61: =_xll.EQNXTDZ($A$1,$B61,H$5,$B$1) -> 0 | I61: =_xll.EQNXTDZ($A$1,$B61,I$5,$B$1) -> 0 | J61: =_xll.EQNXTDZ($A$1,$B61,J$5,$B$1) -> 0 | ... BU61: =_xll.EQNXTDZ($A$1,$B61,BU$5,$B$1) -> 0
A62: Secured Loans | B62: QTRB_SECURED_LOANS | C62: =_xll.EQNXTDZ($A$1,$B62,C$5,$B$1) -> 0 | D62: =_xll.EQNXTDZ($A$1,$B62,D$5,$B$1) -> 0 | E62: =_xll.EQNXTDZ($A$1,$B62,E$5,$B$1) -> 0 | F62: =_xll.EQNXTDZ($A$1,$B62,F$5,$B$1) -> 0 | G62: =_xll.EQNXTDZ($A$1,$B62,G$5,$B$1) -> 0 | H62: =_xll.EQNXTDZ($A$1,$B62,H$5,$B$1) -> 0 | I62: =_xll.EQNXTDZ($A$1,$B62,I$5,$B$1) -> 0 | J62: =_xll.EQNXTDZ($A$1,$B62,J$5,$B$1) -> 0 | ... BU62: =_xll.EQNXTDZ($A$1,$B62,BU$5,$B$1) -> 0
A63: Unsecured Loans | B63: QTRB_UNSECURED_LOANS_NF | C63: =_xll.EQNXTDZ($A$1,$B63,C$5,$B$1) -> 0 | D63: =_xll.EQNXTDZ($A$1,$B63,D$5,$B$1) -> 0 | E63: =_xll.EQNXTDZ($A$1,$B63,E$5,$B$1) -> 0 | F63: =_xll.EQNXTDZ($A$1,$B63,F$5,$B$1) -> 0 | G63: =_xll.EQNXTDZ($A$1,$B63,G$5,$B$1) -> 0 | H63: =_xll.EQNXTDZ($A$1,$B63,H$5,$B$1) -> 0 | I63: =_xll.EQNXTDZ($A$1,$B63,I$5,$B$1) -> 0 | J63: =_xll.EQNXTDZ($A$1,$B63,J$5,$B$1) -> 0 | ... BU63: =_xll.EQNXTDZ($A$1,$B63,BU$5,$B$1) -> 0
A64: Other Long Term Liabilities | B64: QTRB_OTHER_LT_LIABILITIES | C64: =_xll.EQNXTDZ($A$1,$B64,C$5,$B$1) -> 0 | D64: =_xll.EQNXTDZ($A$1,$B64,D$5,$B$1) -> 0 | E64: =_xll.EQNXTDZ($A$1,$B64,E$5,$B$1) -> 0 | F64: =_xll.EQNXTDZ($A$1,$B64,F$5,$B$1) -> 0 | G64: =_xll.EQNXTDZ($A$1,$B64,G$5,$B$1) -> 0 | H64: =_xll.EQNXTDZ($A$1,$B64,H$5,$B$1) -> 0 | I64: =_xll.EQNXTDZ($A$1,$B64,I$5,$B$1) -> 0 | J64: =_xll.EQNXTDZ($A$1,$B64,J$5,$B$1) -> 0 | ... BU64: =_xll.EQNXTDZ($A$1,$B64,BU$5,$B$1) -> 0
A65: Long Term Trade Payables | B65: QTRB_LT_TRADE_PAYABLE | C65: =_xll.EQNXTDZ($A$1,$B65,C$5,$B$1) -> 0 | D65: =_xll.EQNXTDZ($A$1,$B65,D$5,$B$1) -> 0 | E65: =_xll.EQNXTDZ($A$1,$B65,E$5,$B$1) -> 0 | F65: =_xll.EQNXTDZ($A$1,$B65,F$5,$B$1) -> 0 | G65: =_xll.EQNXTDZ($A$1,$B65,G$5,$B$1) -> 0 | H65: =_xll.EQNXTDZ($A$1,$B65,H$5,$B$1) -> 0 | I65: =_xll.EQNXTDZ($A$1,$B65,I$5,$B$1) -> 0 | J65: =_xll.EQNXTDZ($A$1,$B65,J$5,$B$1) -> 0 | ... BU65: =_xll.EQNXTDZ($A$1,$B65,BU$5,$B$1) -> 0
A66: Lont Term Provisions | B66: QTRB_LT_PROVISIONS | C66: =_xll.EQNXTDZ($A$1,$B66,C$5,$B$1) -> 0 | D66: =_xll.EQNXTDZ($A$1,$B66,D$5,$B$1) -> 0 | E66: =_xll.EQNXTDZ($A$1,$B66,E$5,$B$1) -> 0 | F66: =_xll.EQNXTDZ($A$1,$B66,F$5,$B$1) -> 0 | G66: =_xll.EQNXTDZ($A$1,$B66,G$5,$B$1) -> 0 | H66: =_xll.EQNXTDZ($A$1,$B66,H$5,$B$1) -> 0 | I66: =_xll.EQNXTDZ($A$1,$B66,I$5,$B$1) -> 0 | J66: =_xll.EQNXTDZ($A$1,$B66,J$5,$B$1) -> 0 | ... BU66: =_xll.EQNXTDZ($A$1,$B66,BU$5,$B$1) -> 0
... A97: Total Assets | B97: QTRB_TOTAL_APPLICATIONS | C97: =_xll.EQNXTDZ($A$1,$B97,C$5,$B$1) -> 0 | D97: =_xll.EQNXTDZ($A$1,$B97,D$5,$B$1) -> 0 | E97: =_xll.EQNXTDZ($A$1,$B97,E$5,$B$1) -> 0 | F97: =_xll.EQNXTDZ($A$1,$B97,F$5,$B$1) -> 0 | G97: =_xll.EQNXTDZ($A$1,$B97,G$5,$B$1) -> 0 | H97: =_xll.EQNXTDZ($A$1,$B97,H$5,$B$1) -> 0 | I97: =_xll.EQNXTDZ($A$1,$B97,I$5,$B$1) -> 0 | J97: =_xll.EQNXTDZ($A$1,$B97,J$5,$B$1) -> 0 | ... BU97: =_xll.EQNXTDZ($A$1,$B97,BU$5,$B$1) -> 0

Sheet Annual Raw
A1: 209550 | B1: X | C1: 200003 | D1: 200103 | E1: 200212 | F1: 200312 | G1: 200412 | H1: 200512 | I1: 200612 | J1: 200712 | K1: 200812 | L1: 200912 | M1: 201012 | N1: 201112 | O1: 201212 | P1: 201312 | Q1: 201412 | R1: 201512 | S1: 201612 | T1: 201712 | U1: 201812 | V1: 201912 | W1: 202012 | X1: 202112 | Y1: 202212 | Z1: 202312 | AA1: 202412 | AB1: 202512 | AC1: 202612 | AD1: 202712 | AE1: 202812 | AF1: 202912 | AG1: 203012
A3: Field Description | B3: Field Name
A4: Company Name | B4: CD_COMPNAME | C4: =_xll.EQNXTDZ(A1,B4,"L") -> Varun Beverages Ltd.
A5: Year End | B5: PL_YEAR_END | C5: =_xll.EQNXTDZ($A$1,$B5,C$1,$B$1) -> 0 | D5: =_xll.EQNXTDZ($A$1,$B5,D$1,$B$1) -> 0 | E5: =_xll.EQNXTDZ($A$1,$B5,E$1,$B$1) -> 0 | F5: =_xll.EQNXTDZ($A$1,$B5,F$1,$B$1) -> 0 | G5: =_xll.EQNXTDZ($A$1,$B5,G$1,$B$1) -> 200412 | H5: =_xll.EQNXTDZ($A$1,$B5,H$1,$B$1) -> 200512 | I5: =_xll.EQNXTDZ($A$1,$B5,I$1,$B$1) -> 200612 | J5: =_xll.EQNXTDZ($A$1,$B5,J$1,$B$1) -> 200712 | ... AG5: =_xll.EQNXTDZ($A$1,$B5,AG$1,$B$1) -> 0
A6: Sales Turnover | B6: PL_TOTAL_GROSS_SALES | C6: =_xll.EQNXTDZ($A$1,$B6,C$1,$B$1) -> 0 | D6: =_xll.EQNXTDZ($A$1,$B6,D$1,$B$1) -> 0 | E6: =_xll.EQNXTDZ($A$1,$B6,E$1,$B$1) -> 0 | F6: =_xll.EQNXTDZ($A$1,$B6,F$1,$B$1) -> 0 | G6: =_xll.EQNXTDZ($A$1,$B6,G$1,$B$1) -> 340.68526 | H6: =_xll.EQNXTDZ($A$1,$B6,H$1,$B$1) -> 367.68239 | I6: =_xll.EQNXTDZ($A$1,$B6,I$1,$B$1) -> 373.99352 | J6: =_xll.EQNXTDZ($A$1,$B6,J$1,$B$1) -> 425.89375 | ... AG6: =_xll.EQNXTDZ($A$1,$B6,AG$1,$B$1) -> 0
A7: Less: Inter divisional transfers | B7: PL_INTER_DIV_TRF | C7: =_xll.EQNXTDZ($A$1,$B7,C$1,$B$1) -> 0 | D7: =_xll.EQNXTDZ($A$1,$B7,D$1,$B$1) -> 0 | E7: =_xll.EQNXTDZ($A$1,$B7,E$1,$B$1) -> 0 | F7: =_xll.EQNXTDZ($A$1,$B7,F$1,$B$1) -> 0 | G7: =_xll.EQNXTDZ($A$1,$B7,G$1,$B$1) -> 0 | H7: =_xll.EQNXTDZ($A$1,$B7,H$1,$B$1) -> 0 | I7: =_xll.EQNXTDZ($A$1,$B7,I$1,$B$1) -> 0 | J7: =_xll.EQNXTDZ($A$1,$B7,J$1,$B$1) -> 0 | ... AG7: =_xll.EQNXTDZ($A$1,$B7,AG$1,$B$1) -> 0
A8: Less: Sales Returns | B8: PL_SALES_RETURN | C8: =_xll.EQNXTDZ($A$1,$B8,C$1,$B$1) -> 0 | D8: =_xll.EQNXTDZ($A$1,$B8,D$1,$B$1) -> 0 | E8: =_xll.EQNXTDZ($A$1,$B8,E$1,$B$1) -> 0 | F8: =_xll.EQNXTDZ($A$1,$B8,F$1,$B$1) -> 0 | G8: =_xll.EQNXTDZ($A$1,$B8,G$1,$B$1) -> 0 | H8: =_xll.EQNXTDZ($A$1,$B8,H$1,$B$1) -> 0 | I8: =_xll.EQNXTDZ($A$1,$B8,I$1,$B$1) -> 0 | J8: =_xll.EQNXTDZ($A$1,$B8,J$1,$B$1) -> 0 | ... AG8: =_xll.EQNXTDZ($A$1,$B8,AG$1,$B$1) -> 0
A9: Less: Excise | B9: PL_EXCISE | C9: =_xll.EQNXTDZ($A$1,$B9,C$1,$B$1) -> 0 | D9: =_xll.EQNXTDZ($A$1,$B9,D$1,$B$1) -> 0 | E9: =_xll.EQNXTDZ($A$1,$B9,E$1,$B$1) -> 0 | F9: =_xll.EQNXTDZ($A$1,$B9,F$1,$B$1) -> 0 | G9: =_xll.EQNXTDZ($A$1,$B9,G$1,$B$1) -> 57.193838 | H9: =_xll.EQNXTDZ($A$1,$B9,H$1,$B$1) -> 60.750738 | I9: =_xll.EQNXTDZ($A$1,$B9,I$1,$B$1) -> 46.140744 | J9: =_xll.EQNXTDZ($A$1,$B9,J$1,$B$1) -> 53.163081 | ... AG9: =_xll.EQNXTDZ($A$1,$B9,AG$1,$B$1) -> 0
A10: Net Sales | B10: PL_NET_SALES | C10: =_xll.EQNXTDZ($A$1,$B10,C$1,$B$1) -> 0 | D10: =_xll.EQNXTDZ($A$1,$B10,D$1,$B$1) -> 0 | E10: =_xll.EQNXTDZ($A$1,$B10,E$1,$B$1) -> 0 | F10: =_xll.EQNXTDZ($A$1,$B10,F$1,$B$1) -> 0 | G10: =_xll.EQNXTDZ($A$1,$B10,G$1,$B$1) -> 283.49143 | H10: =_xll.EQNXTDZ($A$1,$B10,H$1,$B$1) -> 306.93166 | I10: =_xll.EQNXTDZ($A$1,$B10,I$1,$B$1) -> 327.85278 | J10: =_xll.EQNXTDZ($A$1,$B10,J$1,$B$1) -> 372.73067 | ... AG10: =_xll.EQNXTDZ($A$1,$B10,AG$1,$B$1) -> 0
A11: Increase/Decrease in Stock | B11: PL_INC_DEC_INVENTORY | C11: =_xll.EQNXTDZ($A$1,$B11,C$1,$B$1) -> 0 | D11: =_xll.EQNXTDZ($A$1,$B11,D$1,$B$1) -> 0 | E11: =_xll.EQNXTDZ($A$1,$B11,E$1,$B$1) -> 0 | F11: =_xll.EQNXTDZ($A$1,$B11,F$1,$B$1) -> 0 | G11: =_xll.EQNXTDZ($A$1,$B11,G$1,$B$1) -> -7.2403229 | H11: =_xll.EQNXTDZ($A$1,$B11,H$1,$B$1) -> 2.2733899 | I11: =_xll.EQNXTDZ($A$1,$B11,I$1,$B$1) -> -0.031626 | J11: =_xll.EQNXTDZ($A$1,$B11,J$1,$B$1) -> -2.1219878 | ... AG11: =_xll.EQNXTDZ($A$1,$B11,AG$1,$B$1) -> 0
A12: Raw Material Consumed | B12: PL_RAW_MATRS_CONSUMED | C12: =_xll.EQNXTDZ($A$1,$B12,C$1,$B$1) -> 0 | D12: =_xll.EQNXTDZ($A$1,$B12,D$1,$B$1) -> 0 | E12: =_xll.EQNXTDZ($A$1,$B12,E$1,$B$1) -> 0 | F12: =_xll.EQNXTDZ($A$1,$B12,F$1,$B$1) -> 0 | G12: =_xll.EQNXTDZ($A$1,$B12,G$1,$B$1) -> 146.19765 | H12: =_xll.EQNXTDZ($A$1,$B12,H$1,$B$1) -> 156.13787 | I12: =_xll.EQNXTDZ($A$1,$B12,I$1,$B$1) -> 175.91754 | J12: =_xll.EQNXTDZ($A$1,$B12,J$1,$B$1) -> 209.33044 | ... AG12: =_xll.EQNXTDZ($A$1,$B12,AG$1,$B$1) -> 0
A13: Power & Fuel Cost | B13: PL_POWER_FUEL | C13: =_xll.EQNXTDZ($A$1,$B13,C$1,$B$1) -> 0 | D13: =_xll.EQNXTDZ($A$1,$B13,D$1,$B$1) -> 0 | E13: =_xll.EQNXTDZ($A$1,$B13,E$1,$B$1) -> 0 | F13: =_xll.EQNXTDZ($A$1,$B13,F$1,$B$1) -> 0 | G13: =_xll.EQNXTDZ($A$1,$B13,G$1,$B$1) -> 16.275857 | H13: =_xll.EQNXTDZ($A$1,$B13,H$1,$B$1) -> 17.007646 | I13: =_xll.EQNXTDZ($A$1,$B13,I$1,$B$1) -> 15.316662 | J13: =_xll.EQNXTDZ($A$1,$B13,J$1,$B$1) -> 14.83647 | ... AG13: =_xll.EQNXTDZ($A$1,$B13,AG$1,$B$1) -> 0
A14: Employee Cost | B14: PL_EMPLOYEES | C14: =_xll.EQNXTDZ($A$1,$B14,C$1,$B$1) -> 0 | D14: =_xll.EQNXTDZ($A$1,$B14,D$1,$B$1) -> 0 | E14: =_xll.EQNXTDZ($A$1,$B14,E$1,$B$1) -> 0 | F14: =_xll.EQNXTDZ($A$1,$B14,F$1,$B$1) -> 0 | G14: =_xll.EQNXTDZ($A$1,$B14,G$1,$B$1) -> 15.354206 | H14: =_xll.EQNXTDZ($A$1,$B14,H$1,$B$1) -> 18.509317 | I14: =_xll.EQNXTDZ($A$1,$B14,I$1,$B$1) -> 20.416254 | J14: =_xll.EQNXTDZ($A$1,$B14,J$1,$B$1) -> 21.135453 | ... AG14: =_xll.EQNXTDZ($A$1,$B14,AG$1,$B$1) -> 0
A15: Operating & Manufacturing Expenses | B15: PL_GEN_OTHER_MFG_EXPS | C15: =_xll.EQNXTDZ($A$1,$B15,C$1,$B$1) -> 0 | D15: =_xll.EQNXTDZ($A$1,$B15,D$1,$B$1) -> 0 | E15: =_xll.EQNXTDZ($A$1,$B15,E$1,$B$1) -> 0 | F15: =_xll.EQNXTDZ($A$1,$B15,F$1,$B$1) -> 0 | G15: =_xll.EQNXTDZ($A$1,$B15,G$1,$B$1) -> 41.620309 | H15: =_xll.EQNXTDZ($A$1,$B15,H$1,$B$1) -> 43.679928 | I15: =_xll.EQNXTDZ($A$1,$B15,I$1,$B$1) -> 46.400612 | J15: =_xll.EQNXTDZ($A$1,$B15,J$1,$B$1) -> 51.546875 | ... AG15: =_xll.EQNXTDZ($A$1,$B15,AG$1,$B$1) -> 0
A16: Cost of Software development | B16: PL_COST_SW | C16: =_xll.EQNXTDZ($A$1,$B16,C$1,$B$1) -> 0 | D16: =_xll.EQNXTDZ($A$1,$B16,D$1,$B$1) -> 0 | E16: =_xll.EQNXTDZ($A$1,$B16,E$1,$B$1) -> 0 | F16: =_xll.EQNXTDZ($A$1,$B16,F$1,$B$1) -> 0 | G16: =_xll.EQNXTDZ($A$1,$B16,G$1,$B$1) -> 0 | H16: =_xll.EQNXTDZ($A$1,$B16,H$1,$B$1) -> 0 | I16: =_xll.EQNXTDZ($A$1,$B16,I$1,$B$1) -> 0 | J16: =_xll.EQNXTDZ($A$1,$B16,J$1,$B$1) -> 0 | ... AG16: =_xll.EQNXTDZ($A$1,$B16,AG$1,$B$1) -> 0
... A36: Profit After Tax from Discontinued Operations | B36: PL_PAT_DIS_OP | C36: =_xll.EQNXTDZ($A$1,$B36,C$1,$B$1) -> 0 | D36: =_xll.EQNXTDZ($A$1,$B36,D$1,$B$1) -> 0 | E36: =_xll.EQNXTDZ($A$1,$B36,E$1,$B$1) -> 0 | F36: =_xll.EQNXTDZ($A$1,$B36,F$1,$B$1) -> 0 | G36: =_xll.EQNXTDZ($A$1,$B36,G$1,$B$1) -> 0 | H36: =_xll.EQNXTDZ($A$1,$B36,H$1,$B$1) -> 0 | I36: =_xll.EQNXTDZ($A$1,$B36,I$1,$B$1) -> 0 | J36: =_xll.EQNXTDZ($A$1,$B36,J$1,$B$1) -> 0 | ... AG36: =_xll.EQNXTDZ($A$1,$B36,AG$1,$B$1) -> 0
A39: Field Description | B39: Field Name
A40: Year End | B40: BS_YEAR_END | C40: =_xll.EQNXTDZ($A$1,$B40,C$1,$B$1) -> 0 | D40: =_xll.EQNXTDZ($A$1,$B40,D$1,$B$1) -> 0 | E40: =_xll.EQNXTDZ($A$1,$B40,E$1,$B$1) -> 0 | F40: =_xll.EQNXTDZ($A$1,$B40,F$1,$B$1) -> 0 | G40: =_xll.EQNXTDZ($A$1,$B40,G$1,$B$1) -> 200412 | H40: =_xll.EQNXTDZ($A$1,$B40,H$1,$B$1) -> 200512 | I40: =_xll.EQNXTDZ($A$1,$B40,I$1,$B$1) -> 200612 | J40: =_xll.EQNXTDZ($A$1,$B40,J$1,$B$1) -> 200712 | ... AG40: =_xll.EQNXTDZ($A$1,$B40,AG$1,$B$1) -> 0
A41: Share Capital | B41: BS_SHARE_CAPITAL | C41: =_xll.EQNXTDZ($A$1,$B41,C$1,$B$1) -> 0 | D41: =_xll.EQNXTDZ($A$1,$B41,D$1,$B$1) -> 0 | E41: =_xll.EQNXTDZ($A$1,$B41,E$1,$B$1) -> 0 | F41: =_xll.EQNXTDZ($A$1,$B41,F$1,$B$1) -> 0 | G41: =_xll.EQNXTDZ($A$1,$B41,G$1,$B$1) -> 85.37635 | H41: =_xll.EQNXTDZ($A$1,$B41,H$1,$B$1) -> 85.37635 | I41: =_xll.EQNXTDZ($A$1,$B41,I$1,$B$1) -> 85.37635 | J41: =_xll.EQNXTDZ($A$1,$B41,J$1,$B$1) -> 85.37635 | ... AG41: =_xll.EQNXTDZ($A$1,$B41,AG$1,$B$1) -> 0
A42: Share Warrants & Outstandings | B42: BS_SHAREWROUTST | C42: =_xll.EQNXTDZ($A$1,$B42,C$1,$B$1) -> 0 | D42: =_xll.EQNXTDZ($A$1,$B42,D$1,$B$1) -> 0 | E42: =_xll.EQNXTDZ($A$1,$B42,E$1,$B$1) -> 0 | F42: =_xll.EQNXTDZ($A$1,$B42,F$1,$B$1) -> 0 | G42: =_xll.EQNXTDZ($A$1,$B42,G$1,$B$1) -> 0 | H42: =_xll.EQNXTDZ($A$1,$B42,H$1,$B$1) -> 0 | I42: =_xll.EQNXTDZ($A$1,$B42,I$1,$B$1) -> 0 | J42: =_xll.EQNXTDZ($A$1,$B42,J$1,$B$1) -> 0 | ... AG42: =_xll.EQNXTDZ($A$1,$B42,AG$1,$B$1) -> 0
A43: Total Reserves | B43: BS_RESERVE | C43: =_xll.EQNXTDZ($A$1,$B43,C$1,$B$1) -> 0 | D43: =_xll.EQNXTDZ($A$1,$B43,D$1,$B$1) -> 0 | E43: =_xll.EQNXTDZ($A$1,$B43,E$1,$B$1) -> 0 | F43: =_xll.EQNXTDZ($A$1,$B43,F$1,$B$1) -> 0 | G43: =_xll.EQNXTDZ($A$1,$B43,G$1,$B$1) -> 62.854672 | H43: =_xll.EQNXTDZ($A$1,$B43,H$1,$B$1) -> 74.238345 | I43: =_xll.EQNXTDZ($A$1,$B43,I$1,$B$1) -> 87.674491 | J43: =_xll.EQNXTDZ($A$1,$B43,J$1,$B$1) -> 108.87775 | ... AG43: =_xll.EQNXTDZ($A$1,$B43,AG$1,$B$1) -> 0
A44: Shareholder's Funds | B44: BS_SHAREHODERS_FUNDS | C44: =_xll.EQNXTDZ($A$1,$B44,C$1,$B$1) -> 0 | D44: =_xll.EQNXTDZ($A$1,$B44,D$1,$B$1) -> 0 | E44: =_xll.EQNXTDZ($A$1,$B44,E$1,$B$1) -> 0 | F44: =_xll.EQNXTDZ($A$1,$B44,F$1,$B$1) -> 0 | G44: =_xll.EQNXTDZ($A$1,$B44,G$1,$B$1) -> 148.23102 | H44: =_xll.EQNXTDZ($A$1,$B44,H$1,$B$1) -> 159.61469 | I44: =_xll.EQNXTDZ($A$1,$B44,I$1,$B$1) -> 173.05084 | J44: =_xll.EQNXTDZ($A$1,$B44,J$1,$B$1) -> 194.2541 | ... AG44: =_xll.EQNXTDZ($A$1,$B44,AG$1,$B$1) -> 0
A45: Minority Interest | B45: BS_MINORITY_INTEREST | C45: =_xll.EQNXTDZ($A$1,$B45,C$1,$B$1) -> 0 | D45: =_xll.EQNXTDZ($A$1,$B45,D$1,$B$1) -> 0 | E45: =_xll.EQNXTDZ($A$1,$B45,E$1,$B$1) -> 0 | F45: =_xll.EQNXTDZ($A$1,$B45,F$1,$B$1) -> 0 | G45: =_xll.EQNXTDZ($A$1,$B45,G$1,$B$1) -> 0 | H45: =_xll.EQNXTDZ($A$1,$B45,H$1,$B$1) -> 0 | I45: =_xll.EQNXTDZ($A$1,$B45,I$1,$B$1) -> 0 | J45: =_xll.EQNXTDZ($A$1,$B45,J$1,$B$1) -> 0 | ... AG45: =_xll.EQNXTDZ($A$1,$B45,AG$1,$B$1) -> 0
A46: Long-Term Borrowings | B46: BS_LTRM_BORROWING | C46: =_xll.EQNXTDZ($A$1,$B46,C$1,$B$1) -> 0 | D46: =_xll.EQNXTDZ($A$1,$B46,D$1,$B$1) -> 0 | E46: =_xll.EQNXTDZ($A$1,$B46,E$1,$B$1) -> 0 | F46: =_xll.EQNXTDZ($A$1,$B46,F$1,$B$1) -> 0 | G46: =_xll.EQNXTDZ($A$1,$B46,G$1,$B$1) -> 0 | H46: =_xll.EQNXTDZ($A$1,$B46,H$1,$B$1) -> 0 | I46: =_xll.EQNXTDZ($A$1,$B46,I$1,$B$1) -> 0 | J46: =_xll.EQNXTDZ($A$1,$B46,J$1,$B$1) -> 0 | ... AG46: =_xll.EQNXTDZ($A$1,$B46,AG$1,$B$1) -> 0
A47: Secured Loans | B47: BS_SECURED_LOANS | C47: =_xll.EQNXTDZ($A$1,$B47,C$1,$B$1) -> 0 | D47: =_xll.EQNXTDZ($A$1,$B47,D$1,$B$1) -> 0 | E47: =_xll.EQNXTDZ($A$1,$B47,E$1,$B$1) -> 0 | F47: =_xll.EQNXTDZ($A$1,$B47,F$1,$B$1) -> 0 | G47: =_xll.EQNXTDZ($A$1,$B47,G$1,$B$1) -> 165.50054 | H47: =_xll.EQNXTDZ($A$1,$B47,H$1,$B$1) -> 139.91501 | I47: =_xll.EQNXTDZ($A$1,$B47,I$1,$B$1) -> 124.55949 | J47: =_xll.EQNXTDZ($A$1,$B47,J$1,$B$1) -> 105.7051 | ... AG47: =_xll.EQNXTDZ($A$1,$B47,AG$1,$B$1) -> 0
A48: Unsecured Loans | B48: BS_UNSECURED_LOANS_NF | C48: =_xll.EQNXTDZ($A$1,$B48,C$1,$B$1) -> 0 | D48: =_xll.EQNXTDZ($A$1,$B48,D$1,$B$1) -> 0 | E48: =_xll.EQNXTDZ($A$1,$B48,E$1,$B$1) -> 0 | F48: =_xll.EQNXTDZ($A$1,$B48,F$1,$B$1) -> 0 | G48: =_xll.EQNXTDZ($A$1,$B48,G$1,$B$1) -> 5 | H48: =_xll.EQNXTDZ($A$1,$B48,H$1,$B$1) -> 5 | I48: =_xll.EQNXTDZ($A$1,$B48,I$1,$B$1) -> 8.9282734 | J48: =_xll.EQNXTDZ($A$1,$B48,J$1,$B$1) -> 22.405578 | ... AG48: =_xll.EQNXTDZ($A$1,$B48,AG$1,$B$1) -> 0
A49: Deferred Tax Assets / Liabilities | B49: BS_NET_DEF_TAX_NF | C49: =_xll.EQNXTDZ($A$1,$B49,C$1,$B$1) -> 0 | D49: =_xll.EQNXTDZ($A$1,$B49,D$1,$B$1) -> 0 | E49: =_xll.EQNXTDZ($A$1,$B49,E$1,$B$1) -> 0 | F49: =_xll.EQNXTDZ($A$1,$B49,F$1,$B$1) -> 0 | G49: =_xll.EQNXTDZ($A$1,$B49,G$1,$B$1) -> 37.21096 | H49: =_xll.EQNXTDZ($A$1,$B49,H$1,$B$1) -> 44.297339 | I49: =_xll.EQNXTDZ($A$1,$B49,I$1,$B$1) -> 46.438748 | J49: =_xll.EQNXTDZ($A$1,$B49,J$1,$B$1) -> 50.766549 | ... AG49: =_xll.EQNXTDZ($A$1,$B49,AG$1,$B$1) -> 0
A50: Other Long Term Liabilities | B50: BS_OTH_LT_LIAB | C50: =_xll.EQNXTDZ($A$1,$B50,C$1,$B$1) -> 0 | D50: =_xll.EQNXTDZ($A$1,$B50,D$1,$B$1) -> 0 | E50: =_xll.EQNXTDZ($A$1,$B50,E$1,$B$1) -> 0 | F50: =_xll.EQNXTDZ($A$1,$B50,F$1,$B$1) -> 0 | G50: =_xll.EQNXTDZ($A$1,$B50,G$1,$B$1) -> 0 | H50: =_xll.EQNXTDZ($A$1,$B50,H$1,$B$1) -> 0 | I50: =_xll.EQNXTDZ($A$1,$B50,I$1,$B$1) -> 0 | J50: =_xll.EQNXTDZ($A$1,$B50,J$1,$B$1) -> 0 | ... AG50: =_xll.EQNXTDZ($A$1,$B50,AG$1,$B$1) -> 0
A51: Long Term Trade Payables | B51: BS_LT_TRADE_PAYABLES | C51: =_xll.EQNXTDZ($A$1,$B51,C$1,$B$1) -> 0 | D51: =_xll.EQNXTDZ($A$1,$B51,D$1,$B$1) -> 0 | E51: =_xll.EQNXTDZ($A$1,$B51,E$1,$B$1) -> 0 | F51: =_xll.EQNXTDZ($A$1,$B51,F$1,$B$1) -> 0 | G51: =_xll.EQNXTDZ($A$1,$B51,G$1,$B$1) -> 0 | H51: =_xll.EQNXTDZ($A$1,$B51,H$1,$B$1) -> 0 | I51: =_xll.EQNXTDZ($A$1,$B51,I$1,$B$1) -> 0 | J51: =_xll.EQNXTDZ($A$1,$B51,J$1,$B$1) -> 0 | ... AG51: =_xll.EQNXTDZ($A$1,$B51,AG$1,$B$1) -> 0
... A99: Estimated Capital Contracts Remaining | B99: BS_ESTIMATED_CAPITAL_CONTRACT | C99: =_xll.EQNXTDZ($A$1,$B99,C$1,$B$1) -> 0 | D99: =_xll.EQNXTDZ($A$1,$B99,D$1,$B$1) -> 0 | E99: =_xll.EQNXTDZ($A$1,$B99,E$1,$B$1) -> 0 | F99: =_xll.EQNXTDZ($A$1,$B99,F$1,$B$1) -> 0 | G99: =_xll.EQNXTDZ($A$1,$B99,G$1,$B$1) -> 0.0503 | H99: =_xll.EQNXTDZ($A$1,$B99,H$1,$B$1) -> 8.1224 | I99: =_xll.EQNXTDZ($A$1,$B99,I$1,$B$1) -> 1.0252 | J99: =_xll.EQNXTDZ($A$1,$B99,J$1,$B$1) -> 23.2936 | ... AG99: =_xll.EQNXTDZ($A$1,$B99,AG$1,$B$1) -> 0
A103: Field Description | B103: Field Name
A104: Equity Paid Up | B104: BS_EQUITY_PAIDUP | C104: =_xll.EQNXTDZ($A$1,$B104,C$1,$B$1) -> 0 | D104: =_xll.EQNXTDZ($A$1,$B104,D$1,$B$1) -> 0 | E104: =_xll.EQNXTDZ($A$1,$B104,E$1,$B$1) -> 0 | F104: =_xll.EQNXTDZ($A$1,$B104,F$1,$B$1) -> 0 | G104: =_xll.EQNXTDZ($A$1,$B104,G$1,$B$1) -> 8 | H104: =_xll.EQNXTDZ($A$1,$B104,H$1,$B$1) -> 8 | I104: =_xll.EQNXTDZ($A$1,$B104,I$1,$B$1) -> 8 | J104: =_xll.EQNXTDZ($A$1,$B104,J$1,$B$1) -> 8 | ... AG104: =_xll.EQNXTDZ($A$1,$B104,AG$1,$B$1) -> 0
A105: Face Value | B105: BS_FACE_VALUE | C105: =_xll.EQNXTDZ($A$1,$B105,C$1,$B$1) -> 0 | D105: =_xll.EQNXTDZ($A$1,$B105,D$1,$B$1) -> 0 | E105: =_xll.EQNXTDZ($A$1,$B105,E$1,$B$1) -> 0 | F105: =_xll.EQNXTDZ($A$1,$B105,F$1,$B$1) -> 0 | G105: =_xll.EQNXTDZ($A$1,$B105,G$1,$B$1) -> 10 | H105: =_xll.EQNXTDZ($A$1,$B105,H$1,$B$1) -> 10 | I105: =_xll.EQNXTDZ($A$1,$B105,I$1,$B$1) -> 10 | J105: =_xll.EQNXTDZ($A$1,$B105,J$1,$B$1) -> 10 | ... AG105: =_xll.EQNXTDZ($A$1,$B105,AG$1,$B$1) -> 0
A106: Close Price (Unit Curr.) | B106: FH_YEAR_PRICE | C106: =_xll.EQNXTDZ($A$1,$B106,C$1,$B$1) -> 0 | D106: =_xll.EQNXTDZ($A$1,$B106,D$1,$B$1) -> 0 | E106: =_xll.EQNXTDZ($A$1,$B106,E$1,$B$1) -> 0 | F106: =_xll.EQNXTDZ($A$1,$B106,F$1,$B$1) -> 0 | G106: =_xll.EQNXTDZ($A$1,$B106,G$1,$B$1) -> 0 | H106: =_xll.EQNXTDZ($A$1,$B106,H$1,$B$1) -> 0 | I106: =_xll.EQNXTDZ($A$1,$B106,I$1,$B$1) -> 0 | J106: =_xll.EQNXTDZ($A$1,$B106,J$1,$B$1) -> 0 | ... AG106: =_xll.EQNXTDZ($A$1,$B106,AG$1,$B$1) -> 0
A107: High Price (Unit Curr.) | B107: FH_HIGH | C107: =_xll.EQNXTDZ($A$1,$B107,C$1,$B$1) -> 0 | D107: =_xll.EQNXTDZ($A$1,$B107,D$1,$B$1) -> 0 | E107: =_xll.EQNXTDZ($A$1,$B107,E$1,$B$1) -> 0 | F107: =_xll.EQNXTDZ($A$1,$B107,F$1,$B$1) -> 0 | G107: =_xll.EQNXTDZ($A$1,$B107,G$1,$B$1) -> 0 | H107: =_xll.EQNXTDZ($A$1,$B107,H$1,$B$1) -> 0 | I107: =_xll.EQNXTDZ($A$1,$B107,I$1,$B$1) -> 0 | J107: =_xll.EQNXTDZ($A$1,$B107,J$1,$B$1) -> 0 | ... AG107: =_xll.EQNXTDZ($A$1,$B107,AG$1,$B$1) -> 0
A108: Low Price (Unit Curr.) | B108: FH_LOW | C108: =_xll.EQNXTDZ($A$1,$B108,C$1,$B$1) -> 0 | D108: =_xll.EQNXTDZ($A$1,$B108,D$1,$B$1) -> 0 | E108: =_xll.EQNXTDZ($A$1,$B108,E$1,$B$1) -> 0 | F108: =_xll.EQNXTDZ($A$1,$B108,F$1,$B$1) -> 0 | G108: =_xll.EQNXTDZ($A$1,$B108,G$1,$B$1) -> 0 | H108: =_xll.EQNXTDZ($A$1,$B108,H$1,$B$1) -> 0 | I108: =_xll.EQNXTDZ($A$1,$B108,I$1,$B$1) -> 0 | J108: =_xll.EQNXTDZ($A$1,$B108,J$1,$B$1) -> 0 | ... AG108: =_xll.EQNXTDZ($A$1,$B108,AG$1,$B$1) -> 0
A109: Market Capitalization | B109: FH_MCAP | C109: =_xll.EQNXTDZ($A$1,$B109,C$1,$B$1) -> 0 | D109: =_xll.EQNXTDZ($A$1,$B109,D$1,$B$1) -> 0 | E109: =_xll.EQNXTDZ($A$1,$B109,E$1,$B$1) -> 0 | F109: =_xll.EQNXTDZ($A$1,$B109,F$1,$B$1) -> 0 | G109: =_xll.EQNXTDZ($A$1,$B109,G$1,$B$1) -> 0 | H109: =_xll.EQNXTDZ($A$1,$B109,H$1,$B$1) -> 0 | I109: =_xll.EQNXTDZ($A$1,$B109,I$1,$B$1) -> 0 | J109: =_xll.EQNXTDZ($A$1,$B109,J$1,$B$1) -> 0 | ... AG109: =_xll.EQNXTDZ($A$1,$B109,AG$1,$B$1) -> 0
A110: Adj DPS(Rs) | B110: FR_ADJ_DPS | C110: =_xll.EQNXTDZ($A$1,$B110,C$1,$B$1) -> 0 | D110: =_xll.EQNXTDZ($A$1,$B110,D$1,$B$1) -> 0 | E110: =_xll.EQNXTDZ($A$1,$B110,E$1,$B$1) -> 0 | F110: =_xll.EQNXTDZ($A$1,$B110,F$1,$B$1) -> 0 | G110: =_xll.EQNXTDZ($A$1,$B110,G$1,$B$1) -> 0 | H110: =_xll.EQNXTDZ($A$1,$B110,H$1,$B$1) -> 0 | I110: =_xll.EQNXTDZ($A$1,$B110,I$1,$B$1) -> 0 | J110: =_xll.EQNXTDZ($A$1,$B110,J$1,$B$1) -> 0 | ... AG110: =_xll.EQNXTDZ($A$1,$B110,AG$1,$B$1) -> 0
A111: Date End | B111: SHP_DATE_END | C111: =_xll.EQNXTDZ($A$1,$B111,C$5) -> 0 | D111: =_xll.EQNXTDZ($A$1,$B111,D$5) -> 0 | E111: =_xll.EQNXTDZ($A$1,$B111,E$5) -> 0 | F111: =_xll.EQNXTDZ($A$1,$B111,F$5) -> 0 | G111: =_xll.EQNXTDZ($A$1,$B111,G$5) -> 0 | H111: =_xll.EQNXTDZ($A$1,$B111,H$5) -> 0 | I111: =_xll.EQNXTDZ($A$1,$B111,I$5) -> 0 | J111: =_xll.EQNXTDZ($A$1,$B111,J$5) -> 0 | ... AG111: =_xll.EQNXTDZ($A$1,$B111,AG$5) -> 0
A112: Total of Promoter and Promoter Group | B112: SHP_TPFTOTALPROMOTER | C112: =_xll.EQNXTDZ($A$1,$B112,C$5) -> 0 | D112: =_xll.EQNXTDZ($A$1,$B112,D$5) -> 0 | E112: =_xll.EQNXTDZ($A$1,$B112,E$5) -> 0 | F112: =_xll.EQNXTDZ($A$1,$B112,F$5) -> 0 | G112: =_xll.EQNXTDZ($A$1,$B112,G$5) -> 0 | H112: =_xll.EQNXTDZ($A$1,$B112,H$5) -> 0 | I112: =_xll.EQNXTDZ($A$1,$B112,I$5) -> 0 | J112: =_xll.EQNXTDZ($A$1,$B112,J$5) -> 0 | ... AG112: =_xll.EQNXTDZ($A$1,$B112,AG$5) -> 0
A113: Total of Promoter and Promoter Group Pledged | B113: SHP_PSHFTOTALPROMOTER | C113: =_xll.EQNXTDZ($A$1,$B113,C$5) -> 0 | D113: =_xll.EQNXTDZ($A$1,$B113,D$5) -> 0 | E113: =_xll.EQNXTDZ($A$1,$B113,E$5) -> 0 | F113: =_xll.EQNXTDZ($A$1,$B113,F$5) -> 0 | G113: =_xll.EQNXTDZ($A$1,$B113,G$5) -> 0 | H113: =_xll.EQNXTDZ($A$1,$B113,H$5) -> 0 | I113: =_xll.EQNXTDZ($A$1,$B113,I$5) -> 0 | J113: =_xll.EQNXTDZ($A$1,$B113,J$5) -> 0 | ... AG113: =_xll.EQNXTDZ($A$1,$B113,AG$5) -> 0

Sheet QTR Share Price
A1: ='QTR Raw'!A1 -> 209550 | C1: 201206 | D1: 201207 | E1: 201208 | F1: 201209 | G1: 201210 | H1: 201211 | I1: 201212 | J1: 201301 | K1: 201302 | L1: 201303 | M1: 201304 | N1: 201305 | O1: 201306 | P1: 201307 | Q1: 201308 | R1: 201309 | S1: 201310 | T1: 201311 | U1: 201312 | V1: 201401 | W1: 201402 | X1: 201403 | Y1: 201404 | Z1: 201405 | AA1: 201406 | AB1: 201407 | AC1: 201408 | AD1: 201409 | AE1: 201410 | AF1: 201411 | AG1: 201412 | AH1: 201501 | AI1: 201502 | AJ1: 201503 | AK1: 201504 | AL1: 201505 | AM1: 201506 | AN1: 201507 | AO1: 201508 | AP1: 201509 | AQ1: 201510 | AR1: 201511 | AS1: 201512 | AT1: 201601 | AU1: 201602 | AV1: 201603 | AW1: 201604 | AX1: 201605 | AY1: 201606 | AZ1: 201607 | BA1: 201608 | BB1: 201609 | BC1: 201610 | BD1: 201611 | BE1: 201612 | BF1: 201701 | BG1: 201702 | BH1: 201703 | BI1: 201704 | BJ1: 201705 | BK1: 201706 | BL1: 201707 | BM1: 201708 | BN1: 201709 | BO1: 201710 | BP1: 201711 | BQ1: 201712 | BR1: 201801 | BS1: 201802 | BT1: 201803 | BU1: 201804 | BV1: 201805 | BW1: 201806 | BX1: 201807 | BY1: 201808 | BZ1: 201809 | CA1: 201810 | CB1: 201811 | CC1: 201812 | CD1: 201901 | CE1: 201902 | CF1: 201903 | CG1: 201904 | CH1: 201905 | CI1: 201906 | CJ1: 201907 | CK1: 201908 | CL1: 201909 | CM1: 201910 | CN1: 201911 | CO1: 201912 | CP1: 202001 | CQ1: 202002 | CR1: 202003 | CS1: 202004 | CT1: 202005 | CU1: 202006 | CV1: 202007 | CW1: 202008 | CX1: 202009 | CY1: 202010 | CZ1: 202011 | DA1: 202012 | DB1: 202101 | DC1: 202102 | DD1: 202103 | DE1: 202104 | DF1: 202105 | DG1: 202106 | DH1: 202107 | DI1: 202108 | DJ1: 202109 | DK1: 202110 | DL1: 202111 | DM1: 202112 | DN1: 202201 | DO1: 202202 | DP1: 202203 | DQ1: 202204 | DR1: 202205 | DS1: 202206 | DT1: 202207 | DU1: 202208 | DV1: 202209 | DW1: 202210 | DX1: 202211 | DY1: 202212 | DZ1: 202301 | EA1: 202302 | EB1: 202303 | EC1: 202304 | ED1: 202305 | EE1: 202306 | EF1: 202307 | EG1: 202308 | EH1: 202309 | EI1: 202310 | EJ1: 202311 | EK1: 202312 | EL1: 202401 | EM1: 202402 | EN1: 202403 | EO1: 202404 | EP1: 202405 | EQ1: 202406 | ER1: 202407 | ES1: 202408 | ET1: 202409 | EU1: 202410 | EV1: 202411 | EW1: 202412 | EX1: 202501 | EY1: 202502 | EZ1: 202503 | FA1: 202504 | FB1: 202505 | FC1: 202506 | FD1: 202507 | FE1: 202508 | FF1: 202509 | FG1: 202510 | FH1: 202511 | FI1: 202512 | FJ1: 202601 | FK1: 202602 | FL1: 202603 | FM1: 202604 | FN1: 202605 | FO1: 202606 | FP1: 202607 | FQ1: 202608 | FR1: 202609 | FS1: 202610 | FT1: 202611 | FU1: 202612 | FV1: 202701 | FW1: 202702 | FX1: 202703 | FY1: 202704 | FZ1: 202705 | GA1: 202706 | GB1: 202707 | GC1: 202708 | GD1: 202709 | GE1: 202710 | GF1: 202711 | GG1: 202712 | GH1: 202801 | GI1: 202802 | GJ1: 202803 | GK1: 202804 | GL1: 202805 | GM1: 202806 | GN1: 202807 | GO1: 202808 | GP1: 202809 | GQ1: 202810 | GR1: 202811 | GS1: 202812 | GT1: 202901 | GU1: 202902 | GV1: 202903 | GW1: 202904 | GX1: 202905 | GY1: 202906 | GZ1: 202907 | HA1: 202908 | HB1: 202909 | HC1: 202910 | HD1: 202911 | HE1: 202912 | HF1: 203001 | HG1: 203002 | HH1: 203003 | HM1: 201206 | HN1: 201207 | HO1: 201208 | HP1: 201209 | HQ1: 201212 | HR1: 201303 | HS1: 201306 | HT1: 201309 | HU1: 201312 | HV1: 201403 | HW1: 201406 | HX1: 201409 | HY1: 201412 | HZ1: 201503 | IA1: 201506 | IB1: 201509 | IC1: 201512 | ID1: 201603 | IE1: 201606 | IF1: 201609 | IG1: 201612 | IH1: 201703 | II1: 201706 | IJ1: 201709 | IK1: 201712 | IL1: 201803 | IM1: 201806 | IN1: 201809 | IO1: 201812 | IP1: 201903 | IQ1: 201906 | IR1: 201909 | IS1: 201912 | IT1: 202003 | IU1: 202006 | IV1: 202009 | IW1: 202012 | IX1: 202103 | IY1: 202106 | IZ1: 202109 | JA1: 202112 | JB1: 202203 | JC1: 202206 | JD1: 202209 | JE1: 202212 | JF1: 202303 | JG1: 202306 | JH1: 202309 | JI1: 202312 | JJ1: 202403 | JK1: 202406 | JL1: 202409 | JM1: 202412 | JN1: 202503 | JO1: 202506 | JP1: 202509 | JQ1: 202512 | JR1: 202603 | JS1: 202606 | JT1: 202609 | JU1: 202612 | JV1: 202703 | JW1: 202706 | JX1: 202709 | JY1: 202712 | JZ1: 202803 | KA1: 202806 | KB1: 202809 | KC1: 202812 | KD1: 202903 | KE1: 202906 | KF1: 202909 | KG1: 202912 | KH1: 203003
A4: Field Description | B4: Field Name
A5: MonthEnd | B5: NMONTH_MONTHEND | C5: {=_xll.EQNXTDZ($A$1,$B5,C$1)} -> 0 | D5: {=_xll.EQNXTDZ($A$1,$B5,D$1)} -> 0 | E5: {=_xll.EQNXTDZ($A$1,$B5,E$1)} -> 0 | F5: {=_xll.EQNXTDZ($A$1,$B5,F$1)} -> 0 | G5: {=_xll.EQNXTDZ($A$1,$B5,G$1)} -> 0 | H5: {=_xll.EQNXTDZ($A$1,$B5,H$1)} -> 0 | I5: {=_xll.EQNXTDZ($A$1,$B5,I$1)} -> 0 | J5: {=_xll.EQNXTDZ($A$1,$B5,J$1)} -> 0 | ... HH5: {=_xll.EQNXTDZ($A$1,$B5,HH$1)} -> 0
A6: Open | B6: NMONTH_OPEN | C6: {=_xll.EQNXTDZ($A$1,$B6,C$1)} -> 0 | D6: {=_xll.EQNXTDZ($A$1,$B6,D$1)} -> 0 | E6: {=_xll.EQNXTDZ($A$1,$B6,E$1)} -> 0 | F6: {=_xll.EQNXTDZ($A$1,$B6,F$1)} -> 0 | G6: {=_xll.EQNXTDZ($A$1,$B6,G$1)} -> 0 | H6: {=_xll.EQNXTDZ($A$1,$B6,H$1)} -> 0 | I6: {=_xll.EQNXTDZ($A$1,$B6,I$1)} -> 0 | J6: {=_xll.EQNXTDZ($A$1,$B6,J$1)} -> 0 | ... HH6: {=_xll.EQNXTDZ($A$1,$B6,HH$1)} -> 0
A7: High | B7: NMONTH_HIGH | C7: {=_xll.EQNXTDZ($A$1,$B7,C$1)} -> 0 | D7: {=_xll.EQNXTDZ($A$1,$B7,D$1)} -> 0 | E7: {=_xll.EQNXTDZ($A$1,$B7,E$1)} -> 0 | F7: {=_xll.EQNXTDZ($A$1,$B7,F$1)} -> 0 | G7: {=_xll.EQNXTDZ($A$1,$B7,G$1)} -> 0 | H7: {=_xll.EQNXTDZ($A$1,$B7,H$1)} -> 0 | I7: {=_xll.EQNXTDZ($A$1,$B7,I$1)} -> 0 | J7: {=_xll.EQNXTDZ($A$1,$B7,J$1)} -> 0 | ... HH7: {=_xll.EQNXTDZ($A$1,$B7,HH$1)} -> 0 | HP7: =+MAX(D7:F7) -> 0 | HQ7: =+MAX(G7:I7) -> 0 | HR7: =+MAX(J7:L7) -> 0 | HS7: =+MAX(M7:O7) -> 0 | HT7: =+MAX(P7:R7) -> 0 | HU7: =+MAX(S7:U7) -> 0 | HV7: =+MAX(V7:X7) -> 0 | HW7: =+MAX(Y7:AA7) -> 0 | HX7: =+MAX(AB7:AD7) -> 0 | HY7: =+MAX(AE7:AG7) -> 0 | HZ7: =+MAX(AH7:AJ7) -> 0 | IA7: =+MAX(AK7:AM7) -> 0 | IB7: =+MAX(AN7:AP7) -> 0 | IC7: =+MAX(AQ7:AS7) -> 0 | ID7: =+MAX(AT7:AV7) -> 0 | IE7: =+MAX(AW7:AY7) -> 0 | IF7: =+MAX(AZ7:BB7) -> 0 | IG7: =+MAX(BC7:BE7) -> 27.955556 | IH7: =+MAX(BF7:BH7) -> 24.888889 | II7: =+MAX(BI7:BK7) -> 33.247407 | IJ7: =+MAX(BL7:BN7) -> 33.979259 | IK7: =+MAX(BO7:BQ7) -> 39.348148 | IL7: =+MAX(BR7:BT7) -> 44.965926 | IM7: =+MAX(BU7:BW7) -> 47.111111 | IN7: =+MAX(BX7:BZ7) -> 49.765926 | IO7: =+MAX(CA7:CC7) -> 50.077037 | IP7: =+MAX(CD7:CF7) -> 51.97037 | IQ7: =+MAX(CG7:CI7) -> 57.004444 | IR7: =+MAX(CJ7:CL7) -> 59.911111 | IS7: =+MAX(CM7:CO7) -> 70.133333 | IT7: =+MAX(CP7:CR7) -> 77.333333 | IU7: =+MAX(CS7:CU7) -> 65.693333 | IV7: =+MAX(CV7:CX7) -> 70.826667 | IW7: =+MAX(CY7:DA7) -> 88.866667 | IX7: =+MAX(DB7:DD7) -> 100.44444 | IY7: =+MAX(DE7:DG7) -> 122.45333 | IZ7: =+MAX(DH7:DJ7) -> 126.93333 | JA7: =+MAX(DK7:DM7) -> 135.46667 | JB7: =+MAX(DN7:DP7) -> 135.30667 | JC7: =+MAX(DQ7:DS7) -> 161.12 | JD7: =+MAX(DT7:DV7) -> 238.94 | JE7: =+MAX(DW7:DY7) -> 286.49 | JF7: =+MAX(DZ7:EB7) -> 278.99 | JG7: =+MAX(EC7:EE7) -> 349.4 | JH7: =+MAX(EF7:EH7) -> 391.6 | JI7: =+MAX(EI7:EK7) -> 552 | JJ7: =+MAX(EL7:EN7) -> 624.78 | JK7: =MAX(EO7:EQ7) -> 668.8 | JL7: =MAX(ER7:ET7) -> 681.12 | JM7: =MAX(EU7:EW7) -> 662 | JN7: =MAX(EX7:EZ7) -> 663.6 | JO7: =MAX(FA7:FC7) -> 568.5 | JP7: =MAX(FD7:FF7) -> 534.2 | JQ7: =MAX(FG7:FI7) -> 501.7 | JR7: =MAX(FJ7:FL7) -> 511.65 | JS7: =MAX(FM7:FO7) -> 529.4 | JT7: =MAX(FP7:FR7) -> 0 | JU7: =MAX(FS7:FU7) -> 0 | JV7: =MAX(FV7:FX7) -> 0 | JW7: =MAX(FY7:GA7) -> 0 | JX7: =MAX(GB7:GD7) -> 0 | JY7: =MAX(GE7:GG7) -> 0 | JZ7: =MAX(GH7:GJ7) -> 0 | KA7: =MAX(GK7:GM7) -> 0 | KB7: =MAX(GN7:GP7) -> 0 | KC7: =MAX(GQ7:GS7) -> 0 | KD7: =MAX(GT7:GV7) -> 0 | KE7: =MAX(GW7:GY7) -> 0 | KF7: =MAX(GZ7:HB7) -> 0 | KG7: =MAX(HC7:HE7) -> 0 | KH7: =MAX(HF7:HH7) -> 0
A8: Low | B8: NMONTH_LOW | C8: {=_xll.EQNXTDZ($A$1,$B8,C$1)} -> 0 | D8: {=_xll.EQNXTDZ($A$1,$B8,D$1)} -> 0 | E8: {=_xll.EQNXTDZ($A$1,$B8,E$1)} -> 0 | F8: {=_xll.EQNXTDZ($A$1,$B8,F$1)} -> 0 | G8: {=_xll.EQNXTDZ($A$1,$B8,G$1)} -> 0 | H8: {=_xll.EQNXTDZ($A$1,$B8,H$1)} -> 0 | I8: {=_xll.EQNXTDZ($A$1,$B8,I$1)} -> 0 | J8: {=_xll.EQNXTDZ($A$1,$B8,J$1)} -> 0 | ... HH8: {=_xll.EQNXTDZ($A$1,$B8,HH$1)} -> 0 | HP8: =+MIN(D8:F8) -> 0 | HQ8: =+MIN(G8:I8) -> 0 | HR8: =+MIN(J8:L8) -> 0 | HS8: =+MIN(M8:O8) -> 0 | HT8: =+MIN(P8:R8) -> 0 | HU8: =+MIN(S8:U8) -> 0 | HV8: =+MIN(V8:X8) -> 0 | HW8: =+MIN(Y8:AA8) -> 0 | HX8: =+MIN(AB8:AD8) -> 0 | HY8: =+MIN(AE8:AG8) -> 0 | HZ8: =+MIN(AH8:AJ8) -> 0 | IA8: =+MIN(AK8:AM8) -> 0 | IB8: =+MIN(AN8:AP8) -> 0 | IC8: =+MIN(AQ8:AS8) -> 0 | ID8: =+MIN(AT8:AV8) -> 0 | IE8: =+MIN(AW8:AY8) -> 0 | IF8: =+MIN(AZ8:BB8) -> 0 | IG8: =+MIN(BC8:BE8) -> 0 | IH8: =+MIN(BF8:BH8) -> 20.148148 | II8: =+MIN(BI8:BK8) -> 23.703704 | IJ8: =+MIN(BL8:BN8) -> 28.213333 | IK8: =+MIN(BO8:BQ8) -> 28.776296 | IL8: =+MIN(BR8:BT8) -> 34.957037 | IM8: =+MIN(BU8:BW8) -> 37.054815 | IN8: =+MIN(BX8:BZ8) -> 39.514074 | IO8: =+MIN(CA8:CC8) -> 40.462222 | IP8: =+MIN(CD8:CF8) -> 43.558519 | IQ8: =+MIN(CG8:CI8) -> 46.942222 | IR8: =+MIN(CJ8:CL8) -> 45.89037 | IS8: =+MIN(CM8:CO8) -> 52.373333 | IT8: =+MIN(CP8:CR8) -> 42.862222 | IU8: =+MIN(CS8:CU8) -> 44.444444 | IV8: =+MIN(CV8:CX8) -> 58.786667 | IW8: =+MIN(CY8:DA8) -> 57.453333 | IX8: =+MIN(DB8:DD8) -> 75.915556 | IY8: =+MIN(DE8:DG8) -> 77.64 | IZ8: =+MIN(DH8:DJ8) -> 94.533333 | JA8: =+MIN(DK8:DM8) -> 107.84 | JB8: =+MIN(DN8:DP8) -> 111.41333 | JC8: =+MIN(DQ8:DS8) -> 124.23333 | JD8: =+MIN(DT8:DV8) -> 156.11 | JE8: =+MIN(DW8:DY8) -> 193.02 | JF8: =+MIN(DZ8:EB8) -> 220 | JG8: =+MIN(EC8:EE8) -> 275 | JH8: =+MIN(EF8:EH8) -> 313.96 | JI8: =+MIN(EI8:EK8) -> 331.26 | JJ8: =+MIN(EL8:EN8) -> 478.56 | JK8: =MIN(EO8:EQ8) -> 528.02 | JL8: =MIN(ER8:ET8) -> 549.22 | JM8: =MIN(EU8:EW8) -> 536.85 | JN8: =MIN(EX8:EZ8) -> 419.55 | JO8: =MIN(FA8:FC8) -> 446.15 | JP8: =MIN(FD8:FF8) -> 441.05 | JQ8: =MIN(FG8:FI8) -> 431.65 | JR8: =MIN(FJ8:FL8) -> 381 | JS8: =MIN(FM8:FO8) -> 0 | JT8: =MIN(FP8:FR8) -> 0 | JU8: =MIN(FS8:FU8) -> 0 | JV8: =MIN(FV8:FX8) -> 0 | JW8: =MIN(FY8:GA8) -> 0 | JX8: =MIN(GB8:GD8) -> 0 | JY8: =MIN(GE8:GG8) -> 0 | JZ8: =MIN(GH8:GJ8) -> 0 | KA8: =MIN(GK8:GM8) -> 0 | KB8: =MIN(GN8:GP8) -> 0 | KC8: =MIN(GQ8:GS8) -> 0 | KD8: =MIN(GT8:GV8) -> 0 | KE8: =MIN(GW8:GY8) -> 0 | KF8: =MIN(GZ8:HB8) -> 0 | KG8: =MIN(HC8:HE8) -> 0 | KH8: =MIN(HF8:HH8) -> 0
A9: Close | B9: NMONTH_CLOSE | C9: {=_xll.EQNXTDZ($A$1,$B9,C$1)} -> 0 | D9: {=_xll.EQNXTDZ($A$1,$B9,D$1)} -> 0 | E9: {=_xll.EQNXTDZ($A$1,$B9,E$1)} -> 0 | F9: {=_xll.EQNXTDZ($A$1,$B9,F$1)} -> 0 | G9: {=_xll.EQNXTDZ($A$1,$B9,G$1)} -> 0 | H9: {=_xll.EQNXTDZ($A$1,$B9,H$1)} -> 0 | I9: {=_xll.EQNXTDZ($A$1,$B9,I$1)} -> 0 | J9: {=_xll.EQNXTDZ($A$1,$B9,J$1)} -> 0 | ... HH9: {=_xll.EQNXTDZ($A$1,$B9,HH$1)} -> 0 | HP9: =+F9 -> 0 | HQ9: =+I9 -> 0 | HR9: =+L9 -> 0 | HS9: =+O9 -> 0 | HT9: =+R9 -> 0 | HU9: =+U9 -> 0 | HV9: =+X9 -> 0 | HW9: =+AA9 -> 0 | HX9: =+AD9 -> 0 | HY9: =+AG9 -> 0 | HZ9: =+AJ9 -> 0 | IA9: =+AM9 -> 0 | IB9: =+AP9 -> 0 | IC9: =+AS9 -> 0 | ID9: =+AV9 -> 0 | IE9: =+AY9 -> 0 | IF9: =+BB9 -> 0 | IG9: =+BE9 -> 22.551111 | IH9: =+BH9 -> 23.997037 | II9: =+BK9 -> 31.694815 | IJ9: =+BN9 -> 30.254815 | IK9: =+BQ9 -> 38.711111 | IL9: =+BT9 -> 37.297778 | IM9: =+BW9 -> 44.657778 | IN9: =+BZ9 -> 43.783704 | IO9: =+CC9 -> 46.482963 | IP9: =+CF9 -> 51.357037 | IQ9: =+CI9 -> 56.106667 | IR9: =+CL9 -> 55.475556 | IS9: =+CO9 -> 62.986667 | IT9: =+CR9 -> 47.062222 | IU9: =+CU9 -> 60.528889 | IV9: =+CX9 -> 62.071111 | IW9: =+DA9 -> 81.426667 | IX9: =+DD9 -> 89.151111 | IY9: =+DG9 -> 97.28 | IZ9: =+DJ9 -> 119.68 | JA9: =+DM9 -> 118.44 | JB9: =+DP9 -> 125.50667 | JC9: =+DS9 -> 158.11 | JD9: =+DV9 -> 208.84 | JE9: =+DY9 -> 264.51 | JF9: =+EB9 -> 277.4 | JG9: =+EE9 -> 321.02 | JH9: =+EH9 -> 378.28 | JI9: =+EK9 -> 494.76 | JJ9: =+EN9 -> 559.44 | JK9: =EQ9 -> 651.8 | JL9: =ET9 -> 606.3 | JM9: =EW9 -> 638.5 | JN9: =EZ9 -> 539.65 | JO9: =FC9 -> 457.55 | JP9: =FF9 -> 443.7 | JQ9: =FI9 -> 489.85 | JR9: =FL9 -> 384.1 | JS9: =FO9 -> 0 | JT9: =FR9 -> 0 | JU9: =FU9 -> 0 | JV9: =FX9 -> 0 | JW9: =GA9 -> 0 | JX9: =GD9 -> 0 | JY9: =GG9 -> 0 | JZ9: =GJ9 -> 0 | KA9: =GM9 -> 0 | KB9: =GP9 -> 0 | KC9: =GS9 -> 0 | KD9: =GV9 -> 0 | KE9: =GY9 -> 0 | KF9: =HB9 -> 0 | KG9: =HE9 -> 0 | KH9: =HH9 -> 0
A11: Field Description | B11: Field Name | C11: {=_xll.EQNXTDZ($A$1,$B11,C$1)} -> 0 | D11: {=_xll.EQNXTDZ($A$1,$B11,D$1)} -> 0 | E11: {=_xll.EQNXTDZ($A$1,$B11,E$1)} -> 0 | F11: {=_xll.EQNXTDZ($A$1,$B11,F$1)} -> 0 | G11: {=_xll.EQNXTDZ($A$1,$B11,G$1)} -> 0 | H11: {=_xll.EQNXTDZ($A$1,$B11,H$1)} -> 0 | I11: {=_xll.EQNXTDZ($A$1,$B11,I$1)} -> 0 | J11: {=_xll.EQNXTDZ($A$1,$B11,J$1)} -> 0 | ... HH11: {=_xll.EQNXTDZ($A$1,$B11,HH$1)} -> 0
A12: Month End | B12: BMONTH_MONTHEND | C12: {=_xll.EQNXTDZ($A$1,$B12,C$1)} -> 0 | D12: {=_xll.EQNXTDZ($A$1,$B12,D$1)} -> 0 | E12: {=_xll.EQNXTDZ($A$1,$B12,E$1)} -> 0 | F12: {=_xll.EQNXTDZ($A$1,$B12,F$1)} -> 0 | G12: {=_xll.EQNXTDZ($A$1,$B12,G$1)} -> 0 | H12: {=_xll.EQNXTDZ($A$1,$B12,H$1)} -> 0 | I12: {=_xll.EQNXTDZ($A$1,$B12,I$1)} -> 0 | J12: {=_xll.EQNXTDZ($A$1,$B12,J$1)} -> 0 | ... HH12: {=_xll.EQNXTDZ($A$1,$B12,HH$1)} -> 0
A13: Open | B13: BMONTH_OPEN | C13: {=_xll.EQNXTDZ($A$1,$B13,C$1)} -> 0 | D13: {=_xll.EQNXTDZ($A$1,$B13,D$1)} -> 0 | E13: {=_xll.EQNXTDZ($A$1,$B13,E$1)} -> 0 | F13: {=_xll.EQNXTDZ($A$1,$B13,F$1)} -> 0 | G13: {=_xll.EQNXTDZ($A$1,$B13,G$1)} -> 0 | H13: {=_xll.EQNXTDZ($A$1,$B13,H$1)} -> 0 | I13: {=_xll.EQNXTDZ($A$1,$B13,I$1)} -> 0 | J13: {=_xll.EQNXTDZ($A$1,$B13,J$1)} -> 0 | ... HH13: {=_xll.EQNXTDZ($A$1,$B13,HH$1)} -> 0
A14: High | B14: BMONTH_HIGH | C14: {=_xll.EQNXTDZ($A$1,$B14,C$1)} -> 0 | D14: {=_xll.EQNXTDZ($A$1,$B14,D$1)} -> 0 | E14: {=_xll.EQNXTDZ($A$1,$B14,E$1)} -> 0 | F14: {=_xll.EQNXTDZ($A$1,$B14,F$1)} -> 0 | G14: {=_xll.EQNXTDZ($A$1,$B14,G$1)} -> 0 | H14: {=_xll.EQNXTDZ($A$1,$B14,H$1)} -> 0 | I14: {=_xll.EQNXTDZ($A$1,$B14,I$1)} -> 0 | J14: {=_xll.EQNXTDZ($A$1,$B14,J$1)} -> 0 | ... HH14: {=_xll.EQNXTDZ($A$1,$B14,HH$1)} -> 0 | HP14: =+MAX(D14:F14) -> 0 | HQ14: =+MAX(G14:I14) -> 0 | HR14: =+MAX(J14:L14) -> 0 | HS14: =+MAX(M14:O14) -> 0 | HT14: =+MAX(P14:R14) -> 0 | HU14: =+MAX(S14:U14) -> 0 | HV14: =+MAX(V14:X14) -> 0 | HW14: =+MAX(Y14:AA14) -> 0 | HX14: =+MAX(AB14:AD14) -> 0 | HY14: =+MAX(AE14:AG14) -> 0 | HZ14: =+MAX(AH14:AJ14) -> 0 | IA14: =+MAX(AK14:AM14) -> 0 | IB14: =+MAX(AN14:AP14) -> 0 | IC14: =+MAX(AQ14:AS14) -> 0 | ID14: =+MAX(AT14:AV14) -> 0 | IE14: =+MAX(AW14:AY14) -> 0 | IF14: =+MAX(AZ14:BB14) -> 0 | IG14: =+MAX(BC14:BE14) -> 27.911111 | IH14: =+MAX(BF14:BH14) -> 24.794074 | II14: =+MAX(BI14:BK14) -> 33.066667 | IJ14: =+MAX(BL14:BN14) -> 33.973333 | IK14: =+MAX(BO14:BQ14) -> 39.404444 | IL14: =+MAX(BR14:BT14) -> 45.128889 | IM14: =+MAX(BU14:BW14) -> 46.755556 | IN14: =+MAX(BX14:BZ14) -> 50.311111 | IO14: =+MAX(CA14:CC14) -> 49.860741 | IP14: =+MAX(CD14:CF14) -> 52.059259 | IQ14: =+MAX(CG14:CI14) -> 57.066667 | IR14: =+MAX(CJ14:CL14) -> 60.724444 | IS14: =+MAX(CM14:CO14) -> 70.111111 | IT14: =+MAX(CP14:CR14) -> 77.328889 | IU14: =+MAX(CS14:CU14) -> 65.635556 | IV14: =+MAX(CV14:CX14) -> 70.844444 | IW14: =+MAX(CY14:DA14) -> 88.808889 | IX14: =+MAX(DB14:DD14) -> 97.408889 | IY14: =+MAX(DE14:DG14) -> 122.48 | IZ14: =+MAX(DH14:DJ14) -> 127.25333 | JA14: =+MAX(DK14:DM14) -> 136 | JB14: =+MAX(DN14:DP14) -> 135.33333 | JC14: =+MAX(DQ14:DS14) -> 161.09 | JD14: =+MAX(DT14:DV14) -> 238.96 | JE14: =+MAX(DW14:DY14) -> 286.41 | JF14: =+MAX(DZ14:EB14) -> 278.94 | JG14: =+MAX(EC14:EE14) -> 349.43 | JH14: =+MAX(EF14:EH14) -> 391.66 | JI14: =+MAX(EI14:EK14) -> 552.18 | JJ14: =+MAX(EL14:EN14) -> 624.12 | JK14: =MAX(EO14:EQ14) -> 669.48 | JL14: =MAX(ER14:ET14) -> 682.84 | JM14: =MAX(EU14:EW14) -> 661.7 | JN14: =MAX(EX14:EZ14) -> 663.7 | JO14: =MAX(FA14:FC14) -> 568.5 | JP14: =MAX(FD14:FF14) -> 534 | JQ14: =MAX(FG14:FI14) -> 500.8 | JR14: =MAX(FJ14:FL14) -> 511.75 | JS14: =MAX(FM14:FO14) -> 529 | JT14: =MAX(FP14:FR14) -> 0 | JU14: =MAX(FS14:FU14) -> 0 | JV14: =MAX(FV14:FX14) -> 0 | JW14: =MAX(FY14:GA14) -> 0 | JX14: =MAX(GB14:GD14) -> 0 | JY14: =MAX(GE14:GG14) -> 0 | JZ14: =MAX(GH14:GJ14) -> 0 | KA14: =MAX(GK14:GM14) -> 0 | KB14: =MAX(GN14:GP14) -> 0 | KC14: =MAX(GQ14:GS14) -> 0 | KD14: =MAX(GT14:GV14) -> 0 | KE14: =MAX(GW14:GY14) -> 0 | KF14: =MAX(GZ14:HB14) -> 0 | KG14: =MAX(HC14:HE14) -> 0 | KH14: =MAX(HF14:HH14) -> 0
A15: Low | B15: BMONTH_LOW | C15: {=_xll.EQNXTDZ($A$1,$B15,C$1)} -> 0 | D15: {=_xll.EQNXTDZ($A$1,$B15,D$1)} -> 0 | E15: {=_xll.EQNXTDZ($A$1,$B15,E$1)} -> 0 | F15: {=_xll.EQNXTDZ($A$1,$B15,F$1)} -> 0 | G15: {=_xll.EQNXTDZ($A$1,$B15,G$1)} -> 0 | H15: {=_xll.EQNXTDZ($A$1,$B15,H$1)} -> 0 | I15: {=_xll.EQNXTDZ($A$1,$B15,I$1)} -> 0 | J15: {=_xll.EQNXTDZ($A$1,$B15,J$1)} -> 0 | ... HH15: {=_xll.EQNXTDZ($A$1,$B15,HH$1)} -> 0 | HP15: =+MIN(D15:F15) -> 0 | HQ15: =+MIN(G15:I15) -> 0 | HR15: =+MIN(J15:L15) -> 0 | HS15: =+MIN(M15:O15) -> 0 | HT15: =+MIN(P15:R15) -> 0 | HU15: =+MIN(S15:U15) -> 0 | HV15: =+MIN(V15:X15) -> 0 | HW15: =+MIN(Y15:AA15) -> 0 | HX15: =+MIN(AB15:AD15) -> 0 | HY15: =+MIN(AE15:AG15) -> 0 | HZ15: =+MIN(AH15:AJ15) -> 0 | IA15: =+MIN(AK15:AM15) -> 0 | IB15: =+MIN(AN15:AP15) -> 0 | IC15: =+MIN(AQ15:AS15) -> 0 | ID15: =+MIN(AT15:AV15) -> 0 | IE15: =+MIN(AW15:AY15) -> 0 | IF15: =+MIN(AZ15:BB15) -> 0 | IG15: =+MIN(BC15:BE15) -> 0 | IH15: =+MIN(BF15:BH15) -> 20.222222 | II15: =+MIN(BI15:BK15) -> 23.739259 | IJ15: =+MIN(BL15:BN15) -> 28.515556 | IK15: =+MIN(BO15:BQ15) -> 28.8 | IL15: =+MIN(BR15:BT15) -> 35.128889 | IM15: =+MIN(BU15:BW15) -> 37.137778 | IN15: =+MIN(BX15:BZ15) -> 39.70963 | IO15: =+MIN(CA15:CC15) -> 40.45037 | IP15: =+MIN(CD15:CF15) -> 44.145185 | IQ15: =+MIN(CG15:CI15) -> 47.17037 | IR15: =+MIN(CJ15:CL15) -> 51.222222 | IS15: =+MIN(CM15:CO15) -> 52.582222 | IT15: =+MIN(CP15:CR15) -> 43.115556 | IU15: =+MIN(CS15:CU15) -> 44.626667 | IV15: =+MIN(CV15:CX15) -> 58.844444 | IW15: =+MIN(CY15:DA15) -> 57.351111 | IX15: =+MIN(DB15:DD15) -> 76 | IY15: =+MIN(DE15:DG15) -> 77.688889 | IZ15: =+MIN(DH15:DJ15) -> 94.666667 | JA15: =+MIN(DK15:DM15) -> 107.76 | JB15: =+MIN(DN15:DP15) -> 111.44667 | JC15: =+MIN(DQ15:DS15) -> 124.22 | JD15: =+MIN(DT15:DV15) -> 156.09 | JE15: =+MIN(DW15:DY15) -> 192.67 | JF15: =+MIN(DZ15:EB15) -> 220 | JG15: =+MIN(EC15:EE15) -> 275 | JH15: =+MIN(EF15:EH15) -> 314 | JI15: =+MIN(EI15:EK15) -> 331.28 | JJ15: =+MIN(EL15:EN15) -> 478.48 | JK15: =MIN(EO15:EQ15) -> 528.4 | JL15: =MIN(ER15:ET15) -> 549.6 | JM15: =MIN(EU15:EW15) -> 537.8 | JN15: =MIN(EX15:EZ15) -> 419.4 | JO15: =MIN(FA15:FC15) -> 445.6 | JP15: =MIN(FD15:FF15) -> 441.1 | JQ15: =MIN(FG15:FI15) -> 431.3 | JR15: =MIN(FJ15:FL15) -> 381 | JS15: =MIN(FM15:FO15) -> 0 | JT15: =MIN(FP15:FR15) -> 0 | JU15: =MIN(FS15:FU15) -> 0 | JV15: =MIN(FV15:FX15) -> 0 | JW15: =MIN(FY15:GA15) -> 0 | JX15: =MIN(GB15:GD15) -> 0 | JY15: =MIN(GE15:GG15) -> 0 | JZ15: =MIN(GH15:GJ15) -> 0 | KA15: =MIN(GK15:GM15) -> 0 | KB15: =MIN(GN15:GP15) -> 0 | KC15: =MIN(GQ15:GS15) -> 0 | KD15: =MIN(GT15:GV15) -> 0 | KE15: =MIN(GW15:GY15) -> 0 | KF15: =MIN(GZ15:HB15) -> 0 | KG15: =MIN(HC15:HE15) -> 0 | KH15: =MIN(HF15:HH15) -> 0
A16: Close | B16: BMONTH_CLOSE | C16: {=_xll.EQNXTDZ($A$1,$B16,C$1)} -> 0 | D16: {=_xll.EQNXTDZ($A$1,$B16,D$1)} -> 0 | E16: {=_xll.EQNXTDZ($A$1,$B16,E$1)} -> 0 | F16: {=_xll.EQNXTDZ($A$1,$B16,F$1)} -> 0 | G16: {=_xll.EQNXTDZ($A$1,$B16,G$1)} -> 0 | H16: {=_xll.EQNXTDZ($A$1,$B16,H$1)} -> 0 | I16: {=_xll.EQNXTDZ($A$1,$B16,I$1)} -> 0 | J16: {=_xll.EQNXTDZ($A$1,$B16,J$1)} -> 0 | ... HH16: {=_xll.EQNXTDZ($A$1,$B16,HH$1)} -> 0 | HP16: =+F16 -> 0 | HQ16: =+I16 -> 0 | HR16: =+L16 -> 0 | HS16: =+O16 -> 0 | HT16: =+R16 -> 0 | HU16: =+U16 -> 0 | HV16: =+X16 -> 0 | HW16: =+AA16 -> 0 | HX16: =+AD16 -> 0 | HY16: =+AG16 -> 0 | HZ16: =+AJ16 -> 0 | IA16: =+AM16 -> 0 | IB16: =+AP16 -> 0 | IC16: =+AS16 -> 0 | ID16: =+AV16 -> 0 | IE16: =+AY16 -> 0 | IF16: =+BB16 -> 0 | IG16: =+BE16 -> 22.598519 | IH16: =+BH16 -> 23.985185 | II16: =+BK16 -> 31.617778 | IJ16: =+BN16 -> 29.973333 | IK16: =+BQ16 -> 38.598519 | IL16: =+BT16 -> 36.586667 | IM16: =+BW16 -> 44.637037 | IN16: =+BZ16 -> 43.84 | IO16: =+CC16 -> 46.645926 | IP16: =+CF16 -> 51.268148 | IQ16: =+CI16 -> 56.014815 | IR16: =+CL16 -> 55.577778 | IS16: =+CO16 -> 62.928889 | IT16: =+CR16 -> 47.16 | IU16: =+CU16 -> 60.684444 | IV16: =+CX16 -> 62.115556 | IW16: =+DA16 -> 81.373333 | IX16: =+DD16 -> 89.413333 | IY16: =+DG16 -> 97.226667 | IZ16: =+DJ16 -> 120.16667 | JA16: =+DM16 -> 118.20667 | JB16: =+DP16 -> 125.47333 | JC16: =+DS16 -> 158.12 | JD16: =+DV16 -> 208.8 | JE16: =+DY16 -> 264.5 | JF16: =+EB16 -> 277.45 | JG16: =+EE16 -> 320.2 | JH16: =+EH16 -> 378.44 | JI16: =+EK16 -> 494.62 | JJ16: =+EN16 -> 559.24 | JK16: =EQ16 -> 651.9 | JL16: =ET16 -> 606.2 | JM16: =EW16 -> 638.45 | JN16: =EZ16 -> 539.6 | JO16: =FC16 -> 457.55 | JP16: =FF16 -> 443.55 | JQ16: =FI16 -> 489.85 | JR16: =FL16 -> 384.05 | JS16: =FO16 -> 0 | JT16: =FR16 -> 0 | JU16: =FU16 -> 0 | JV16: =FX16 -> 0 | JW16: =GA16 -> 0 | JX16: =GD16 -> 0 | JY16: =GG16 -> 0 | JZ16: =GJ16 -> 0 | KA16: =GM16 -> 0 | KB16: =GP16 -> 0 | KC16: =GS16 -> 0 | KD16: =GV16 -> 0 | KE16: =GY16 -> 0 | KF16: =HB16 -> 0 | KG16: =HE16 -> 0 | KH16: =HH16 -> 0
A19: High | HP19: =+IF(HP14=0,HP7,HP14) -> 0 | HQ19: =+IF(HQ14=0,HQ7,HQ14) -> 0 | HR19: =+IF(HR14=0,HR7,HR14) -> 0 | HS19: =+IF(HS14=0,HS7,HS14) -> 0 | HT19: =+IF(HT14=0,HT7,HT14) -> 0 | HU19: =+IF(HU14=0,HU7,HU14) -> 0 | HV19: =+IF(HV14=0,HV7,HV14) -> 0 | HW19: =+IF(HW14=0,HW7,HW14) -> 0 | ... KH19: =+IF(KH14=0,KH7,KH14) -> 0
A20: Low | HP20: =+IF(HP15=0,HP8,HP15) -> 0 | HQ20: =+IF(HQ15=0,HQ8,HQ15) -> 0 | HR20: =+IF(HR15=0,HR8,HR15) -> 0 | HS20: =+IF(HS15=0,HS8,HS15) -> 0 | HT20: =+IF(HT15=0,HT8,HT15) -> 0 | HU20: =+IF(HU15=0,HU8,HU15) -> 0 | HV20: =+IF(HV15=0,HV8,HV15) -> 0 | HW20: =+IF(HW15=0,HW8,HW15) -> 0 | ... KH20: =+IF(KH15=0,KH8,KH15) -> 0
A21: Close | HP21: =+IF(HP16=0,HP9,HP16) -> 0 | HQ21: =+IF(HQ16=0,HQ9,HQ16) -> 0 | HR21: =+IF(HR16=0,HR9,HR16) -> 0 | HS21: =+IF(HS16=0,HS9,HS16) -> 0 | HT21: =+IF(HT16=0,HT9,HT16) -> 0 | HU21: =+IF(HU16=0,HU9,HU16) -> 0 | HV21: =+IF(HV16=0,HV9,HV16) -> 0 | HW21: =+IF(HW16=0,HW9,HW16) -> 0 | ... KH21: =+IF(KH16=0,KH9,KH16) -> 0

Sheet QTR No. of Shares
A1: ='QTR Raw'!A1 -> 209550 | C1: 201206 | D1: 201209 | E1: 201212 | F1: 201303 | G1: 201306 | H1: 201309 | I1: 201312 | J1: 201403 | K1: 201406 | L1: 201409 | M1: 201412 | N1: 201503 | O1: 201506 | P1: 201509 | Q1: 201512 | R1: 201603 | S1: 201606 | T1: 201609 | U1: 201612 | V1: 201703 | W1: 201706 | X1: 201709 | Y1: 201712 | Z1: 201803 | AA1: 201806 | AB1: 201809 | AC1: 201812 | AD1: 201903 | AE1: 201906 | AF1: 201909 | AG1: 201912 | AH1: 202003 | AI1: 202006 | AJ1: 202009 | AK1: 202012 | AL1: 202103 | AM1: 202106 | AN1: 202109 | AO1: 202112 | AP1: 202203 | AQ1: 202206 | AR1: 202209 | AS1: 202212 | AT1: 202303 | AU1: 202306 | AV1: 202309 | AW1: 202312 | AX1: 202403 | AY1: 202406
A4: Field Description | B4: Field Name
A5: Date End | B5: SHP_DATE_END | C5: {=_xll.EQNXTDZ($A$1,$B5,C$1)} -> 0 | D5: {=_xll.EQNXTDZ($A$1,$B5,D$1)} -> 0 | E5: {=_xll.EQNXTDZ($A$1,$B5,E$1)} -> 0 | F5: {=_xll.EQNXTDZ($A$1,$B5,F$1)} -> 0 | G5: {=_xll.EQNXTDZ($A$1,$B5,G$1)} -> 0 | H5: {=_xll.EQNXTDZ($A$1,$B5,H$1)} -> 0 | I5: {=_xll.EQNXTDZ($A$1,$B5,I$1)} -> 0 | J5: {=_xll.EQNXTDZ($A$1,$B5,J$1)} -> 0 | ... AY5: {=_xll.EQNXTDZ($A$1,$B5,AY$1)} -> 202406
A6: Grand Total | B6: SHP_NSGRANDTOTAL | C6: {=_xll.EQNXTDZ($A$1,$B6,C$1)} -> 0 | D6: {=_xll.EQNXTDZ($A$1,$B6,D$1)} -> 0 | E6: {=_xll.EQNXTDZ($A$1,$B6,E$1)} -> 0 | F6: {=_xll.EQNXTDZ($A$1,$B6,F$1)} -> 0 | G6: {=_xll.EQNXTDZ($A$1,$B6,G$1)} -> 0 | H6: {=_xll.EQNXTDZ($A$1,$B6,H$1)} -> 0 | I6: {=_xll.EQNXTDZ($A$1,$B6,I$1)} -> 0 | J6: {=_xll.EQNXTDZ($A$1,$B6,J$1)} -> 0 | ... AY6: {=_xll.EQNXTDZ($A$1,$B6,AY$1)} -> 1299440413
B7: In Crs. | C7: =+C6/10^7 -> 0 | D7: =+D6/10^7 -> 0 | E7: =+E6/10^7 -> 0 | F7: =+F6/10^7 -> 0 | G7: =+G6/10^7 -> 0 | H7: =+H6/10^7 -> 0 | I7: =+I6/10^7 -> 0 | J7: =+J6/10^7 -> 0 | ... AY7: =+AY6/10^7 -> 129.94404

Sheet Share price Daily
A1: =_xll.EQNXTH(B1,"[ADJC];[ADJH];[ADJL];[ADJO];[UCLS];[VOLUME]","2015-Jan-01","Y","All traded days","Asc") -> EQNXTH | B1: =+'Annual Raw'!A1 -> 209550 | L1: =_xll.EQNXTH(B1,"[NADJC];[NADJH];[NADJLOW];[NADJOPEN];[NUCLOSE];[NVOLUME]","2015-Jan-01","Y","All traded days","Asc") -> EQNXTH
A2: Varun Beverages Ltd. | L2: Varun Beverages Ltd.
A3: DATE | B3: ADJHIGH | C3: ADJCLOSE | D3: ADJLOW | E3: ADJOPEN | F3: CLOSE | G3: VOLUME | L3: DATE | M3: ADJCLOSE | N3: ADJHIGH | O3: ADJLOW | P3: ADJOPEN | Q3: CLOSE | R3: VOLUME
A4: 42682 | B4: 27.911111 | C4: 27.371852 | D4: 24.717037 | E4: 25.481481 | F4: 461.9 | G4: 5215325 | L4: 42682 | M4: 27.22963 | N4: 27.955556 | O4: 24.702222 | P4: 25.481481 | Q4: 459.5 | R4: 18118170
A5: 42683 | B5: 26.722963 | C5: 25.81037 | D5: 23.2 | E5: 23.2 | F5: 435.55 | G5: 328843 | L5: 42683 | M5: 25.739259 | N5: 26.666667 | O5: 23.288889 | P5: 23.288889 | Q5: 434.35 | R5: 811362
A6: 42684 | B6: 27.318519 | C6: 25.851852 | D6: 25.659259 | E6: 26.37037 | F6: 436.25 | G6: 199170 | L6: 42684 | M6: 25.857778 | N6: 27.312593 | O6: 25.674074 | P6: 26.42963 | Q6: 436.35 | R6: 459704
A7: 42685 | B7: 26.663704 | C7: 26.008889 | D7: 25.481481 | E7: 25.718519 | F7: 438.9 | G7: 132789 | L7: 42685 | M7: 26.112593 | N7: 26.666667 | O7: 25.478519 | P7: 25.718519 | Q7: 440.65 | R7: 324102
A8: 42689 | B8: 26.311111 | C8: 25.780741 | D8: 25.457778 | E8: 25.896296 | F8: 435.05 | G8: 66986 | L8: 42689 | M8: 25.961481 | N8: 26.352593 | O8: 25.481481 | P8: 25.955556 | Q8: 438.1 | R8: 359415
A9: 42690 | B9: 26.488889 | C9: 25.49037 | D9: 24.888889 | E9: 26.311111 | F9: 430.15 | G9: 32220 | L9: 42690 | M9: 25.819259 | N9: 26.488889 | O9: 25.540741 | P9: 26.074074 | Q9: 435.7 | R9: 79903
A10: 42691 | B10: 26.311111 | C10: 26.100741 | D10: 25.540741 | E10: 25.6 | F10: 440.45 | G10: 57157 | L10: 42691 | M10: 26.085926 | N10: 26.334815 | O10: 25.540741 | P10: 25.540741 | Q10: 440.2 | R10: 217069
A11: 42692 | B11: 26.305185 | C11: 25.822222 | D11: 25.6 | E11: 25.783704 | F11: 435.75 | G11: 27816 | L11: 42692 | M11: 26.103704 | N11: 26.37037 | O11: 25.777778 | P11: 26.065185 | Q11: 440.5 | R11: 84664
A12: 42695 | B12: 26.192593 | C12: 26.08 | D12: 25.688889 | E12: 25.908148 | F12: 440.1 | G12: 36474 | L12: 42695 | M12: 26.068148 | N12: 26.204444 | O12: 25.6 | P12: 25.6 | Q12: 439.9 | R12: 74176
A13: 42696 | B13: 26.216296 | C13: 26.10963 | D13: 25.837037 | E13: 25.837037 | F13: 440.6 | G13: 30697 | L13: 42696 | M13: 26.121481 | N13: 26.334815 | O13: 25.608889 | P13: 25.608889 | Q13: 440.8 | R13: 72366
A14: 42697 | B14: 26.37037 | C14: 26.198519 | D14: 25.659259 | E14: 26.074074 | F14: 442.1 | G14: 49884 | L14: 42697 | M14: 26.263704 | N14: 26.37037 | O14: 25.677037 | P14: 25.807407 | Q14: 443.2 | R14: 159354
A15: 42698 | B15: 26.180741 | C15: 26.014815 | D15: 25.777778 | E15: 26.074074 | F15: 439 | G15: 10490 | L15: 42698 | M15: 25.979259 | N15: 26.183704 | O15: 25.854815 | P15: 26.005926 | Q15: 438.4 | R15: 27508
... A2750: 46054 | B2750: 2375 | C2750: 2232.15 | D2750: 2068.4 | E2750: 2300.2 | F2750: 2232.15 | G2750: 1228545 | L2750: 46054 | M2750: 2233.3 | N2750: 2319.9 | O2750: 2068.5 | P2750: 2300 | Q2750: 2233.3 | R2750: 20999802

Sheet Sheet2
J19: 219.3 | K19: 186.25 | L19: 186.75
J20: 192.9 | K20: 135.5 | L20: 146.9 | N20: 219.3 | O20: 192.9 | P20: 186 | Q20: 178.7 | R20: 207 | S20: 255.15 | T20: 348.25 | U20: 374 | V20: 495.9 | W20: 659.9 | X20: 613.4 | Y20: 607.9 | Z20: 555.95 | AA20: 497.8 | AB20: 459.9 | AC20: 374 | AD20: 362 | AE20: 341.5 | AF20: 384.2 | AG20: 433.8 | AH20: 460 | AI20: 474.4 | AJ20: 414.4 | AK20: 318.7 | AL20: 303.25 | AM20: 332.7 | AN20: 295 | AO20: 247 | AP20: 214.4 | AQ20: 179.5 | AR20: 97.9 | AS20: 119.1 | AT20: 130.65 | AU20: 148.55 | AV20: 153.8 | AW20: 152.9 | AX20: 136 | AY20: 141.15 | AZ20: 128.1 | BA20: 142.5 | BB20: 143.55 | BC20: 124.5 | BD20: 241 | BE20: 450 | BF20: 503.35
J21: 186 | K21: 145.4 | L21: 169.1 | N21: 186.25 | O21: 135.5 | P21: 145.4 | Q21: 108.95 | R21: 137 | S21: 170 | T21: 243.15 | U21: 307.5 | V21: 325.1 | W21: 463 | X21: 467.05 | Y21: 436.5 | Z21: 467 | AA21: 348.2 | AB21: 325 | AC21: 313.1 | AD21: 285 | AE21: 277.85 | AF21: 327 | AG21: 317 | AH21: 370.7 | AI21: 360 | AJ21: 271.15 | AK21: 233.15 | AL21: 218.8 | AM21: 262 | AN21: 223.6 | AO21: 137.6 | AP21: 142 | AQ21: 59.3 | AR21: 58 | AS21: 72.8 | AT21: 80 | AU21: 107.25 | AV21: 106 | AW21: 125.1 | AX21: 112.25 | AY21: 81.45 | AZ21: 88 | BA21: 90.35 | BB21: 106.05 | BC21: 98.55 | BD21: 119.25 | BE21: 210 | BF21: 349
J22: 178.7 | K22: 108.95 | L22: 139.75 | N22: 186.75 | O22: 146.9 | P22: 169.1 | Q22: 139.75 | R22: 202.15 | S22: 249.05 | T22: 346.4 | U22: 349.2 | V22: 469.9 | W22: 584.8 | X22: 536.15 | Y22: 513.35 | Z22: 474 | AA22: 438.55 | AB22: 355.4 | AC22: 334.95 | AD22: 298.8 | AE22: 328.35 | AF22: 343 | AG22: 389.9 | AH22: 443.05 | AI22: 407.5 | AJ22: 290.1 | AK22: 235.75 | AL22: 292.65 | AM22: 276.1 | AN22: 237.05 | AO22: 190.1 | AP22: 147.2 | AQ22: 71.9 | AR22: 75.2 | AS22: 90.1 | AT22: 117.2 | AU22: 116.3 | AV22: 140.5 | AW22: 128.6 | AX22: 133.65 | AY22: 91.65 | AZ22: 97.65 | BA22: 125 | BB22: 115.35 | BC22: 119.25 | BD22: 219.3 | BE22: 442.65 | BF22: 503.35
J23: 207 | K23: 137 | L23: 202.15
J24: 255.15 | K24: 170 | L24: 249.05
J25: 348.25 | K25: 243.15 | L25: 346.4
J26: 374 | K26: 307.5 | L26: 349.2
J27: 495.9 | K27: 325.1 | L27: 469.9
J28: 659.9 | K28: 463 | L28: 584.8
J29: 613.4 | K29: 467.05 | L29: 536.15
J30: 607.9 | K30: 436.5 | L30: 513.35
J31: 555.95 | K31: 467 | L31: 474
J32: 497.8 | K32: 348.2 | L32: 438.55
J33: 459.9 | K33: 325 | L33: 355.4
J34: 374 | K34: 313.1 | L34: 334.95
... J63: 503.35 | K63: 349 | L63: 503.35
